Classfile /Users/mw/Projects/slang-braindump/.jar/jar8/assemble/slang-braindump/assemble/content/scala/collection/generic/DelegatedContext.class
  Last modified May 29, 2022; size 2296 bytes
  SHA-256 checksum b509590e362539f768f2ead4bb78c6a46113d07a40019179bc08c9e045d25441
  Compiled from "Signalling.scala"
public class scala.collection.generic.DelegatedContext implements scala.collection.generic.DelegatedSignalling
  minor version: 0
  major version: 52
  flags: (0x0021) ACC_PUBLIC, ACC_SUPER
  this_class: #2                          // scala/collection/generic/DelegatedContext
  super_class: #4                         // java/lang/Object
  interfaces: 1, fields: 1, methods: 10, attributes: 4
Constant pool:
   #1 = Utf8               scala/collection/generic/DelegatedContext
   #2 = Class              #1             // scala/collection/generic/DelegatedContext
   #3 = Utf8               java/lang/Object
   #4 = Class              #3             // java/lang/Object
   #5 = Utf8               scala/collection/generic/DelegatedSignalling
   #6 = Class              #5             // scala/collection/generic/DelegatedSignalling
   #7 = Utf8               Signalling.scala
   #8 = Utf8               Lscala/reflect/ScalaSignature;
   #9 = Utf8               bytes
  #10 = Utf8               \u0006\u0005\u001d2A!\u0002\u0004\u0001\u001b!Aa\u0003\u0001BA\u0002\u0013\u0005q\u0003\u0003\u0005\u001c\u0001\t\u0005\r\u0011\"\u0001\u001d\u0011!\u0011\u0003A!A!B\u0013A\u0002\"B\u0012\u0001\t\u0003!#\u0001\u0005#fY\u0016<\u0017\r^3e\u0007>tG/\u001a=u\u0015\t9\u0001\"A\u0004hK:,\'/[2\u000b\u0005%Q\u0011AC2pY2,7\r^5p]*\t1\"A\u0003tG\u0006d\u0017m\u0001\u0001\u0014\u0007\u0001q!\u0003\u0005\u0002\u0010!5\t!\"\u0003\u0002\u0012\u0015\t1\u0011I\\=SK\u001a\u0004\"a\u0005\u000b\u000e\u0003\u0019I!!\u0006\u0004\u0003\'\u0011+G.Z4bi\u0016$7+[4oC2d\u0017N\\4\u0002\u001dMLwM\\1m\t\u0016dWmZ1uKV\t\u0001\u0004\u0005\u0002\u00143%\u0011!D\u0002\u0002\u000b\'&<g.\u00197mS:<\u0017AE:jO:\fG\u000eR3mK\u001e\fG/Z0%KF$\"!\b\u0011\u0011\u0005=q\u0012BA\u0010\u000b\u0005\u0011)f.\u001b;\t\u000f\u0005\u0012\u0011\u0011!a\u00011\u0005\u0019\u0001\u0010J\u0019\u0002\u001fMLwM\\1m\t\u0016dWmZ1uK\u0002\na\u0001P5oSRtDCA\u0013\'!\t\u0019\u0002\u0001C\u0003\u0017\t\u0001\u0007\u0001\u0004
  #11 = Utf8               signalDelegate
  #12 = Utf8               Lscala/collection/generic/Signalling;
  #13 = Utf8               isAborted
  #14 = Utf8               ()Z
  #15 = Utf8               isAborted$
  #16 = Utf8               (Lscala/collection/generic/DelegatedSignalling;)Z
  #17 = NameAndType        #15:#16        // isAborted$:(Lscala/collection/generic/DelegatedSignalling;)Z
  #18 = InterfaceMethodref #6.#17         // scala/collection/generic/DelegatedSignalling.isAborted$:(Lscala/collection/generic/DelegatedSignalling;)Z
  #19 = Utf8               this
  #20 = Utf8               Lscala/collection/generic/DelegatedContext;
  #21 = Utf8               abort
  #22 = Utf8               ()V
  #23 = Utf8               abort$
  #24 = Utf8               (Lscala/collection/generic/DelegatedSignalling;)V
  #25 = NameAndType        #23:#24        // abort$:(Lscala/collection/generic/DelegatedSignalling;)V
  #26 = InterfaceMethodref #6.#25         // scala/collection/generic/DelegatedSignalling.abort$:(Lscala/collection/generic/DelegatedSignalling;)V
  #27 = Utf8               indexFlag
  #28 = Utf8               ()I
  #29 = Utf8               indexFlag$
  #30 = Utf8               (Lscala/collection/generic/DelegatedSignalling;)I
  #31 = NameAndType        #29:#30        // indexFlag$:(Lscala/collection/generic/DelegatedSignalling;)I
  #32 = InterfaceMethodref #6.#31         // scala/collection/generic/DelegatedSignalling.indexFlag$:(Lscala/collection/generic/DelegatedSignalling;)I
  #33 = Utf8               setIndexFlag
  #34 = Utf8               (I)V
  #35 = Utf8               f
  #36 = Utf8               setIndexFlag$
  #37 = Utf8               (Lscala/collection/generic/DelegatedSignalling;I)V
  #38 = NameAndType        #36:#37        // setIndexFlag$:(Lscala/collection/generic/DelegatedSignalling;I)V
  #39 = InterfaceMethodref #6.#38         // scala/collection/generic/DelegatedSignalling.setIndexFlag$:(Lscala/collection/generic/DelegatedSignalling;I)V
  #40 = Utf8               I
  #41 = Utf8               setIndexFlagIfGreater
  #42 = Utf8               setIndexFlagIfGreater$
  #43 = NameAndType        #42:#37        // setIndexFlagIfGreater$:(Lscala/collection/generic/DelegatedSignalling;I)V
  #44 = InterfaceMethodref #6.#43         // scala/collection/generic/DelegatedSignalling.setIndexFlagIfGreater$:(Lscala/collection/generic/DelegatedSignalling;I)V
  #45 = Utf8               setIndexFlagIfLesser
  #46 = Utf8               setIndexFlagIfLesser$
  #47 = NameAndType        #46:#37        // setIndexFlagIfLesser$:(Lscala/collection/generic/DelegatedSignalling;I)V
  #48 = InterfaceMethodref #6.#47         // scala/collection/generic/DelegatedSignalling.setIndexFlagIfLesser$:(Lscala/collection/generic/DelegatedSignalling;I)V
  #49 = Utf8               tag
  #50 = Utf8               tag$
  #51 = NameAndType        #50:#30        // tag$:(Lscala/collection/generic/DelegatedSignalling;)I
  #52 = InterfaceMethodref #6.#51         // scala/collection/generic/DelegatedSignalling.tag$:(Lscala/collection/generic/DelegatedSignalling;)I
  #53 = Utf8               ()Lscala/collection/generic/Signalling;
  #54 = NameAndType        #11:#12        // signalDelegate:Lscala/collection/generic/Signalling;
  #55 = Fieldref           #2.#54         // scala/collection/generic/DelegatedContext.signalDelegate:Lscala/collection/generic/Signalling;
  #56 = Utf8               signalDelegate_$eq
  #57 = Utf8               (Lscala/collection/generic/Signalling;)V
  #58 = Utf8               x$1
  #59 = Utf8               <init>
  #60 = NameAndType        #59:#22        // "<init>":()V
  #61 = Methodref          #4.#60         // java/lang/Object."<init>":()V
  #62 = Utf8               $init$
  #63 = NameAndType        #62:#24        // $init$:(Lscala/collection/generic/DelegatedSignalling;)V
  #64 = InterfaceMethodref #6.#63         // scala/collection/generic/DelegatedSignalling.$init$:(Lscala/collection/generic/DelegatedSignalling;)V
  #65 = Utf8               Code
  #66 = Utf8               LineNumberTable
  #67 = Utf8               LocalVariableTable
  #68 = Utf8               MethodParameters
  #69 = Utf8               SourceFile
  #70 = Utf8               RuntimeVisibleAnnotations
  #71 = Utf8               ScalaInlineInfo
  #72 = Utf8               ScalaSig
{
  private scala.collection.generic.Signalling signalDelegate;
    descriptor: Lscala/collection/generic/Signalling;
    flags: (0x0002) ACC_PRIVATE

  public boolean isAborted();
    descriptor: ()Z
    flags: (0x0001) ACC_PUBLIC
    Code:
      stack=1, locals=1, args_size=1
         0: aload_0
         1: invokestatic  #18                 // InterfaceMethod scala/collection/generic/DelegatedSignalling.isAborted$:(Lscala/collection/generic/DelegatedSignalling;)Z
         4: ireturn
      LineNumberTable:
        line 173: 0
      LocalVariableTable:
        Start  Length  Slot  Name   Signature
            0       5     0  this   Lscala/collection/generic/DelegatedContext;

  public void abort();
    descriptor: ()V
    flags: (0x0001) ACC_PUBLIC
    Code:
      stack=1, locals=1, args_size=1
         0: aload_0
         1: invokestatic  #26                 // InterfaceMethod scala/collection/generic/DelegatedSignalling.abort$:(Lscala/collection/generic/DelegatedSignalling;)V
         4: return
      LineNumberTable:
        line 173: 0
      LocalVariableTable:
        Start  Length  Slot  Name   Signature
            0       5     0  this   Lscala/collection/generic/DelegatedContext;

  public int indexFlag();
    descriptor: ()I
    flags: (0x0001) ACC_PUBLIC
    Code:
      stack=1, locals=1, args_size=1
         0: aload_0
         1: invokestatic  #32                 // InterfaceMethod scala/collection/generic/DelegatedSignalling.indexFlag$:(Lscala/collection/generic/DelegatedSignalling;)I
         4: ireturn
      LineNumberTable:
        line 173: 0
      LocalVariableTable:
        Start  Length  Slot  Name   Signature
            0       5     0  this   Lscala/collection/generic/DelegatedContext;

  public void setIndexFlag(int);
    descriptor: (I)V
    flags: (0x0001) ACC_PUBLIC
    Code:
      stack=2, locals=2, args_size=2
         0: aload_0
         1: iload_1
         2: invokestatic  #39                 // InterfaceMethod scala/collection/generic/DelegatedSignalling.setIndexFlag$:(Lscala/collection/generic/DelegatedSignalling;I)V
         5: return
      LineNumberTable:
        line 173: 0
      LocalVariableTable:
        Start  Length  Slot  Name   Signature
            0       6     0  this   Lscala/collection/generic/DelegatedContext;
            0       6     1     f   I
    MethodParameters:
      Name                           Flags
      f                              final

  public void setIndexFlagIfGreater(int);
    descriptor: (I)V
    flags: (0x0001) ACC_PUBLIC
    Code:
      stack=2, locals=2, args_size=2
         0: aload_0
         1: iload_1
         2: invokestatic  #44                 // InterfaceMethod scala/collection/generic/DelegatedSignalling.setIndexFlagIfGreater$:(Lscala/collection/generic/DelegatedSignalling;I)V
         5: return
      LineNumberTable:
        line 173: 0
      LocalVariableTable:
        Start  Length  Slot  Name   Signature
            0       6     0  this   Lscala/collection/generic/DelegatedContext;
            0       6     1     f   I
    MethodParameters:
      Name                           Flags
      f                              final

  public void setIndexFlagIfLesser(int);
    descriptor: (I)V
    flags: (0x0001) ACC_PUBLIC
    Code:
      stack=2, locals=2, args_size=2
         0: aload_0
         1: iload_1
         2: invokestatic  #48                 // InterfaceMethod scala/collection/generic/DelegatedSignalling.setIndexFlagIfLesser$:(Lscala/collection/generic/DelegatedSignalling;I)V
         5: return
      LineNumberTable:
        line 173: 0
      LocalVariableTable:
        Start  Length  Slot  Name   Signature
            0       6     0  this   Lscala/collection/generic/DelegatedContext;
            0       6     1     f   I
    MethodParameters:
      Name                           Flags
      f                              final

  public int tag();
    descriptor: ()I
    flags: (0x0001) ACC_PUBLIC
    Code:
      stack=1, locals=1, args_size=1
         0: aload_0
         1: invokestatic  #52                 // InterfaceMethod scala/collection/generic/DelegatedSignalling.tag$:(Lscala/collection/generic/DelegatedSignalling;)I
         4: ireturn
      LineNumberTable:
        line 173: 0
      LocalVariableTable:
        Start  Length  Slot  Name   Signature
            0       5     0  this   Lscala/collection/generic/DelegatedContext;

  public scala.collection.generic.Signalling signalDelegate();
    descriptor: ()Lscala/collection/generic/Signalling;
    flags: (0x0001) ACC_PUBLIC
    Code:
      stack=1, locals=1, args_size=1
         0: aload_0
         1: getfield      #55                 // Field signalDelegate:Lscala/collection/generic/Signalling;
         4: areturn
      LineNumberTable:
        line 173: 0
      LocalVariableTable:
        Start  Length  Slot  Name   Signature
            0       5     0  this   Lscala/collection/generic/DelegatedContext;

  public void signalDelegate_$eq(scala.collection.generic.Signalling);
    descriptor: (Lscala/collection/generic/Signalling;)V
    flags: (0x0001) ACC_PUBLIC
    Code:
      stack=2, locals=2, args_size=2
         0: aload_0
         1: aload_1
         2: putfield      #55                 // Field signalDelegate:Lscala/collection/generic/Signalling;
         5: return
      LineNumberTable:
        line 173: 0
      LocalVariableTable:
        Start  Length  Slot  Name   Signature
            0       6     0  this   Lscala/collection/generic/DelegatedContext;
            0       6     1   x$1   Lscala/collection/generic/Signalling;
    MethodParameters:
      Name                           Flags
      x$1                            final

  public scala.collection.generic.DelegatedContext(scala.collection.generic.Signalling);
    descriptor: (Lscala/collection/generic/Signalling;)V
    flags: (0x0001) ACC_PUBLIC
    Code:
      stack=2, locals=2, args_size=2
         0: aload_0
         1: aload_1
         2: putfield      #55                 // Field signalDelegate:Lscala/collection/generic/Signalling;
         5: aload_0
         6: invokespecial #61                 // Method java/lang/Object."<init>":()V
         9: aload_0
        10: invokestatic  #64                 // InterfaceMethod scala/collection/generic/DelegatedSignalling.$init$:(Lscala/collection/generic/DelegatedSignalling;)V
        13: return
      LineNumberTable:
        line 173: 0
      LocalVariableTable:
        Start  Length  Slot  Name   Signature
            0      14     0  this   Lscala/collection/generic/DelegatedContext;
            0      14     1 signalDelegate   Lscala/collection/generic/Signalling;
    MethodParameters:
      Name                           Flags
      signalDelegate                 final
}
SourceFile: "Signalling.scala"
RuntimeVisibleAnnotations:
  0: #8(#9=s#10)
    scala.reflect.ScalaSignature(
      bytes="\u0006\u0005\u001d2A!\u0002\u0004\u0001\u001b!Aa\u0003\u0001BA\u0002\u0013\u0005q\u0003\u0003\u0005\u001c\u0001\t\u0005\r\u0011\"\u0001\u001d\u0011!\u0011\u0003A!A!B\u0013A\u0002\"B\u0012\u0001\t\u0003!#\u0001\u0005#fY\u0016<\u0017\r^3e\u0007>tG/\u001a=u\u0015\t9\u0001\"A\u0004hK:,\'/[2\u000b\u0005%Q\u0011AC2pY2,7\r^5p]*\t1\"A\u0003tG\u0006d\u0017m\u0001\u0001\u0014\u0007\u0001q!\u0003\u0005\u0002\u0010!5\t!\"\u0003\u0002\u0012\u0015\t1\u0011I\\=SK\u001a\u0004\"a\u0005\u000b\u000e\u0003\u0019I!!\u0006\u0004\u0003\'\u0011+G.Z4bi\u0016$7+[4oC2d\u0017N\\4\u0002\u001dMLwM\\1m\t\u0016dWmZ1uKV\t\u0001\u0004\u0005\u0002\u00143%\u0011!D\u0002\u0002\u000b\'&<g.\u00197mS:<\u0017AE:jO:\fG\u000eR3mK\u001e\fG/Z0%KF$\"!\b\u0011\u0011\u0005=q\u0012BA\u0010\u000b\u0005\u0011)f.\u001b;\t\u000f\u0005\u0012\u0011\u0011!a\u00011\u0005\u0019\u0001\u0010J\u0019\u0002\u001fMLwM\\1m\t\u0016dWmZ1uK\u0002\na\u0001P5oSRtDCA\u0013\'!\t\u0019\u0002\u0001C\u0003\u0017\t\u0001\u0007\u0001\u0004"
    )
  ScalaInlineInfo: length = 0x36 (unknown attribute)
   01 00 00 0A 00 3B 00 39 00 00 15 00 16 00 00 1B
   00 1C 00 00 0D 00 0E 00 00 21 00 22 00 00 29 00
   22 00 00 2D 00 22 00 00 0B 00 35 00 00 38 00 39
   00 00 31 00 1C 00
  ScalaSig: length = 0x3 (unknown attribute)
   05 02 00
