Classfile /Users/mw/Projects/slang-braindump/.jar/jar8/assemble/slang-braindump/assemble/content/scala/collection/generic/IdleSignalling.class
  Last modified May 29, 2022; size 1089 bytes
  SHA-256 checksum 220e6a126825679a025543beb7ae27cb4638116abc671018e9b146bb8921892c
  Compiled from "Signalling.scala"
public final class scala.collection.generic.IdleSignalling
  minor version: 0
  major version: 52
  flags: (0x0031) ACC_PUBLIC, ACC_FINAL, ACC_SUPER
  this_class: #2                          // scala/collection/generic/IdleSignalling
  super_class: #4                         // java/lang/Object
  interfaces: 0, fields: 0, methods: 7, attributes: 3
Constant pool:
   #1 = Utf8               scala/collection/generic/IdleSignalling
   #2 = Class              #1             // scala/collection/generic/IdleSignalling
   #3 = Utf8               java/lang/Object
   #4 = Class              #3             // java/lang/Object
   #5 = Utf8               Signalling.scala
   #6 = Utf8               Lscala/reflect/ScalaSignature;
   #7 = Utf8               bytes
   #8 = Utf8               \u0006\u0005Q9Qa\u0001\u0003\t\u0002-1Q!\u0004\u0003\t\u00029AQAE\u0001\u0005\u0002M\ta\"\u00133mKNKwM\\1mY&twM\u0003\u0002\u0006\r\u00059q-\u001a8fe&\u001c\'BA\u0004\t\u0003)\u0019w\u000e\u001c7fGRLwN\u001c\u0006\u0002\u0013\u0005)1oY1mC\u000e\u0001\u0001C\u0001\u0007\u0002\u001b\u0005!!AD%eY\u0016\u001c\u0016n\u001a8bY2LgnZ\n\u0003\u0003=\u0001\"\u0001\u0004\t\n\u0005E!!!\u0005#fM\u0006,H\u000e^*jO:\fG\u000e\\5oO\u00061A(\u001b8jiz\"\u0012a\u0003
   #9 = Utf8               tag
  #10 = Utf8               ()I
  #11 = Utf8               scala/collection/generic/IdleSignalling$
  #12 = Class              #11            // scala/collection/generic/IdleSignalling$
  #13 = Utf8               MODULE$
  #14 = Utf8               Lscala/collection/generic/IdleSignalling$;
  #15 = NameAndType        #13:#14        // MODULE$:Lscala/collection/generic/IdleSignalling$;
  #16 = Fieldref           #12.#15        // scala/collection/generic/IdleSignalling$.MODULE$:Lscala/collection/generic/IdleSignalling$;
  #17 = NameAndType        #9:#10         // tag:()I
  #18 = Methodref          #12.#17        // scala/collection/generic/IdleSignalling$.tag:()I
  #19 = Utf8               setIndexFlagIfLesser
  #20 = Utf8               (I)V
  #21 = Utf8               f
  #22 = NameAndType        #19:#20        // setIndexFlagIfLesser:(I)V
  #23 = Methodref          #12.#22        // scala/collection/generic/IdleSignalling$.setIndexFlagIfLesser:(I)V
  #24 = Utf8               I
  #25 = Utf8               setIndexFlagIfGreater
  #26 = NameAndType        #25:#20        // setIndexFlagIfGreater:(I)V
  #27 = Methodref          #12.#26        // scala/collection/generic/IdleSignalling$.setIndexFlagIfGreater:(I)V
  #28 = Utf8               setIndexFlag
  #29 = NameAndType        #28:#20        // setIndexFlag:(I)V
  #30 = Methodref          #12.#29        // scala/collection/generic/IdleSignalling$.setIndexFlag:(I)V
  #31 = Utf8               indexFlag
  #32 = NameAndType        #31:#10        // indexFlag:()I
  #33 = Methodref          #12.#32        // scala/collection/generic/IdleSignalling$.indexFlag:()I
  #34 = Utf8               abort
  #35 = Utf8               ()V
  #36 = NameAndType        #34:#35        // abort:()V
  #37 = Methodref          #12.#36        // scala/collection/generic/IdleSignalling$.abort:()V
  #38 = Utf8               isAborted
  #39 = Utf8               ()Z
  #40 = NameAndType        #38:#39        // isAborted:()Z
  #41 = Methodref          #12.#40        // scala/collection/generic/IdleSignalling$.isAborted:()Z
  #42 = Utf8               Code
  #43 = Utf8               LocalVariableTable
  #44 = Utf8               MethodParameters
  #45 = Utf8               SourceFile
  #46 = Utf8               RuntimeVisibleAnnotations
  #47 = Utf8               ScalaSig
{
  public static int tag();
    descriptor: ()I
    flags: (0x0009) ACC_PUBLIC, ACC_STATIC
    Code:
      stack=1, locals=0, args_size=0
         0: getstatic     #16                 // Field scala/collection/generic/IdleSignalling$.MODULE$:Lscala/collection/generic/IdleSignalling$;
         3: invokevirtual #18                 // Method scala/collection/generic/IdleSignalling$.tag:()I
         6: ireturn

  public static void setIndexFlagIfLesser(int);
    descriptor: (I)V
    flags: (0x0009) ACC_PUBLIC, ACC_STATIC
    Code:
      stack=2, locals=1, args_size=1
         0: getstatic     #16                 // Field scala/collection/generic/IdleSignalling$.MODULE$:Lscala/collection/generic/IdleSignalling$;
         3: iload_0
         4: invokevirtual #23                 // Method scala/collection/generic/IdleSignalling$.setIndexFlagIfLesser:(I)V
         7: return
      LocalVariableTable:
        Start  Length  Slot  Name   Signature
            0       8     0     f   I
    MethodParameters:
      Name                           Flags
      f                              final

  public static void setIndexFlagIfGreater(int);
    descriptor: (I)V
    flags: (0x0009) ACC_PUBLIC, ACC_STATIC
    Code:
      stack=2, locals=1, args_size=1
         0: getstatic     #16                 // Field scala/collection/generic/IdleSignalling$.MODULE$:Lscala/collection/generic/IdleSignalling$;
         3: iload_0
         4: invokevirtual #27                 // Method scala/collection/generic/IdleSignalling$.setIndexFlagIfGreater:(I)V
         7: return
      LocalVariableTable:
        Start  Length  Slot  Name   Signature
            0       8     0     f   I
    MethodParameters:
      Name                           Flags
      f                              final

  public static void setIndexFlag(int);
    descriptor: (I)V
    flags: (0x0009) ACC_PUBLIC, ACC_STATIC
    Code:
      stack=2, locals=1, args_size=1
         0: getstatic     #16                 // Field scala/collection/generic/IdleSignalling$.MODULE$:Lscala/collection/generic/IdleSignalling$;
         3: iload_0
         4: invokevirtual #30                 // Method scala/collection/generic/IdleSignalling$.setIndexFlag:(I)V
         7: return
      LocalVariableTable:
        Start  Length  Slot  Name   Signature
            0       8     0     f   I
    MethodParameters:
      Name                           Flags
      f                              final

  public static int indexFlag();
    descriptor: ()I
    flags: (0x0009) ACC_PUBLIC, ACC_STATIC
    Code:
      stack=1, locals=0, args_size=0
         0: getstatic     #16                 // Field scala/collection/generic/IdleSignalling$.MODULE$:Lscala/collection/generic/IdleSignalling$;
         3: invokevirtual #33                 // Method scala/collection/generic/IdleSignalling$.indexFlag:()I
         6: ireturn

  public static void abort();
    descriptor: ()V
    flags: (0x0009) ACC_PUBLIC, ACC_STATIC
    Code:
      stack=1, locals=0, args_size=0
         0: getstatic     #16                 // Field scala/collection/generic/IdleSignalling$.MODULE$:Lscala/collection/generic/IdleSignalling$;
         3: invokevirtual #37                 // Method scala/collection/generic/IdleSignalling$.abort:()V
         6: return

  public static boolean isAborted();
    descriptor: ()Z
    flags: (0x0009) ACC_PUBLIC, ACC_STATIC
    Code:
      stack=1, locals=0, args_size=0
         0: getstatic     #16                 // Field scala/collection/generic/IdleSignalling$.MODULE$:Lscala/collection/generic/IdleSignalling$;
         3: invokevirtual #41                 // Method scala/collection/generic/IdleSignalling$.isAborted:()Z
         6: ireturn
}
SourceFile: "Signalling.scala"
RuntimeVisibleAnnotations:
  0: #6(#7=s#8)
    scala.reflect.ScalaSignature(
      bytes="\u0006\u0005Q9Qa\u0001\u0003\t\u0002-1Q!\u0004\u0003\t\u00029AQAE\u0001\u0005\u0002M\ta\"\u00133mKNKwM\\1mY&twM\u0003\u0002\u0006\r\u00059q-\u001a8fe&\u001c\'BA\u0004\t\u0003)\u0019w\u000e\u001c7fGRLwN\u001c\u0006\u0002\u0013\u0005)1oY1mC\u000e\u0001\u0001C\u0001\u0007\u0002\u001b\u0005!!AD%eY\u0016\u001c\u0016n\u001a8bY2LgnZ\n\u0003\u0003=\u0001\"\u0001\u0004\t\n\u0005E!!!\u0005#fM\u0006,H\u000e^*jO:\fG\u000e\\5oO\u00061A(\u001b8jiz\"\u0012a\u0003"
    )
  ScalaSig: length = 0x3 (unknown attribute)
   05 02 00
