Classfile /Users/mw/Projects/slang-braindump/.jar/jar8/assemble/slang-braindump/assemble/content/scala/collection/generic/IsIterableOnceLowPriority.class
  Last modified May 29, 2022; size 1626 bytes
  SHA-256 checksum dfc45955c5d10212f3e7a57c8b157b2e4aa2711b973ccab12ecbf9d031115ed6
  Compiled from "IsIterableOnce.scala"
public interface scala.collection.generic.IsIterableOnceLowPriority
  minor version: 0
  major version: 52
  flags: (0x0601) ACC_PUBLIC, ACC_INTERFACE, ACC_ABSTRACT
  this_class: #2                          // scala/collection/generic/IsIterableOnceLowPriority
  super_class: #4                         // java/lang/Object
  interfaces: 0, fields: 0, methods: 3, attributes: 4
Constant pool:
   #1 = Utf8               scala/collection/generic/IsIterableOnceLowPriority
   #2 = Class              #1             // scala/collection/generic/IsIterableOnceLowPriority
   #3 = Utf8               java/lang/Object
   #4 = Class              #3             // java/lang/Object
   #5 = Utf8               IsIterableOnce.scala
   #6 = Utf8               Lscala/reflect/ScalaSignature;
   #7 = Utf8               bytes
   #8 = Utf8               \u0006\u0005Q2qa\u0001\u0003\u0011\u0002\u0007\u00051\u0002C\u0003\u0011\u0001\u0011\u0005\u0011\u0003C\u0003\u0016\u0001\u0011\raCA\rJg&#XM]1cY\u0016|enY3M_^\u0004&/[8sSRL(BA\u0003\u0007\u0003\u001d9WM\\3sS\u000eT!a\u0002\u0005\u0002\u0015\r|G\u000e\\3di&|gNC\u0001\n\u0003\u0015\u00198-\u00197b\u0007\u0001\u0019\"\u0001\u0001\u0007\u0011\u00055qQ\"\u0001\u0005\n\u0005=A!AB!osJ+g-\u0001\u0004%S:LG\u000f\n\u000b\u0002%A\u0011QbE\u0005\u0003)!\u0011A!\u00168ji\u0006a\u0012n]%uKJ\f\'\r\\3MS.,\u0017j]%uKJ\f\'\r\\3P]\u000e,WCA\f\")\tAbF\u0005\u0002\u001a7\u0019!!\u0004\u0001\u0001\u0019\u00051a$/\u001a4j]\u0016lWM\u001c;?!\raRdH\u0007\u0002\t%\u0011a\u0004\u0002\u0002\u000f\u0013NLE/\u001a:bE2,wJ\\2f!\t\u0001\u0013\u0005\u0004\u0001\u0005\u000b\t\u0012!\u0019A\u0012\u0003\tI+\u0007O]\t\u0003I\u001d\u0002\"!D\u0013\n\u0005\u0019B!a\u0002(pi\"Lgn\u001a\t\u0003\u001b!J!!\u000b\u0005\u0003\u0007\u0005s\u00170\u0002\u0003,3\u0001a#!A!\u0011\u00055\u001adB\u0001\u0011/\u0011\u0015y#\u0001q\u00011\u00039I7/\u0013;fe\u0006\u0014G.\u001a\'jW\u0016\u00042\u0001H\u0019 \u0013\t\u0011DA\u0001\u0006Jg&#XM]1cY\u0016L!aK\u000f
   #9 = Utf8               isIterableLikeIsIterableOnce$
  #10 = Utf8               (Lscala/collection/generic/IsIterableOnceLowPriority;Lscala/collection/generic/IsIterable;)Lscala/collection/generic/IsIterableOnce;
  #11 = Utf8               $this
  #12 = Utf8               isIterableLike
  #13 = Utf8               isIterableLikeIsIterableOnce
  #14 = Utf8               (Lscala/collection/generic/IsIterable;)Lscala/collection/generic/IsIterableOnce;
  #15 = NameAndType        #13:#14        // isIterableLikeIsIterableOnce:(Lscala/collection/generic/IsIterable;)Lscala/collection/generic/IsIterableOnce;
  #16 = InterfaceMethodref #2.#15         // scala/collection/generic/IsIterableOnceLowPriority.isIterableLikeIsIterableOnce:(Lscala/collection/generic/IsIterable;)Lscala/collection/generic/IsIterableOnce;
  #17 = Utf8               Lscala/collection/generic/IsIterableOnceLowPriority;
  #18 = Utf8               Lscala/collection/generic/IsIterable;
  #19 = Utf8               <Repr:Ljava/lang/Object;>(Lscala/collection/generic/IsIterable<TRepr;>;)Lscala/collection/generic/IsIterableOnce<TRepr;>;
  #20 = Utf8               this
  #21 = Utf8               $init$
  #22 = Utf8               (Lscala/collection/generic/IsIterableOnceLowPriority;)V
  #23 = Utf8               Code
  #24 = Utf8               LineNumberTable
  #25 = Utf8               LocalVariableTable
  #26 = Utf8               MethodParameters
  #27 = Utf8               Signature
  #28 = Utf8               SourceFile
  #29 = Utf8               RuntimeVisibleAnnotations
  #30 = Utf8               ScalaInlineInfo
  #31 = Utf8               ScalaSig
{
  public static scala.collection.generic.IsIterableOnce isIterableLikeIsIterableOnce$(scala.collection.generic.IsIterableOnceLowPriority, scala.collection.generic.IsIterable);
    descriptor: (Lscala/collection/generic/IsIterableOnceLowPriority;Lscala/collection/generic/IsIterable;)Lscala/collection/generic/IsIterableOnce;
    flags: (0x1009) ACC_PUBLIC, ACC_STATIC, ACC_SYNTHETIC
    Code:
      stack=2, locals=2, args_size=2
         0: aload_0
         1: aload_1
         2: invokespecial #16                 // InterfaceMethod isIterableLikeIsIterableOnce:(Lscala/collection/generic/IsIterable;)Lscala/collection/generic/IsIterableOnce;
         5: areturn
      LineNumberTable:
        line 67: 0
      LocalVariableTable:
        Start  Length  Slot  Name   Signature
            0       6     0 $this   Lscala/collection/generic/IsIterableOnceLowPriority;
            0       6     1 isIterableLike   Lscala/collection/generic/IsIterable;
    MethodParameters:
      Name                           Flags
      $this                          final synthetic
      isIterableLike                 final

  public default <Repr extends java.lang.Object> scala.collection.generic.IsIterableOnce<Repr> isIterableLikeIsIterableOnce(scala.collection.generic.IsIterable<Repr>);
    descriptor: (Lscala/collection/generic/IsIterable;)Lscala/collection/generic/IsIterableOnce;
    flags: (0x0001) ACC_PUBLIC
    Code:
      stack=1, locals=2, args_size=2
         0: aload_1
         1: areturn
      LineNumberTable:
        line 69: 0
      LocalVariableTable:
        Start  Length  Slot  Name   Signature
            0       2     0  this   Lscala/collection/generic/IsIterableOnceLowPriority;
            0       2     1 isIterableLike   Lscala/collection/generic/IsIterable;
    Signature: #19                          // <Repr:Ljava/lang/Object;>(Lscala/collection/generic/IsIterable<TRepr;>;)Lscala/collection/generic/IsIterableOnce<TRepr;>;
    MethodParameters:
      Name                           Flags
      isIterableLike                 final

  public static void $init$(scala.collection.generic.IsIterableOnceLowPriority);
    descriptor: (Lscala/collection/generic/IsIterableOnceLowPriority;)V
    flags: (0x0009) ACC_PUBLIC, ACC_STATIC
    Code:
      stack=0, locals=1, args_size=1
         0: return
      LineNumberTable:
        line 64: 0
      LocalVariableTable:
        Start  Length  Slot  Name   Signature
            0       1     0 $this   Lscala/collection/generic/IsIterableOnceLowPriority;
    MethodParameters:
      Name                           Flags
      $this                          final synthetic
}
SourceFile: "IsIterableOnce.scala"
RuntimeVisibleAnnotations:
  0: #6(#7=s#8)
    scala.reflect.ScalaSignature(
      bytes="\u0006\u0005Q2qa\u0001\u0003\u0011\u0002\u0007\u00051\u0002C\u0003\u0011\u0001\u0011\u0005\u0011\u0003C\u0003\u0016\u0001\u0011\raCA\rJg&#XM]1cY\u0016|enY3M_^\u0004&/[8sSRL(BA\u0003\u0007\u0003\u001d9WM\\3sS\u000eT!a\u0002\u0005\u0002\u0015\r|G\u000e\\3di&|gNC\u0001\n\u0003\u0015\u00198-\u00197b\u0007\u0001\u0019\"\u0001\u0001\u0007\u0011\u00055qQ\"\u0001\u0005\n\u0005=A!AB!osJ+g-\u0001\u0004%S:LG\u000f\n\u000b\u0002%A\u0011QbE\u0005\u0003)!\u0011A!\u00168ji\u0006a\u0012n]%uKJ\f\'\r\\3MS.,\u0017j]%uKJ\f\'\r\\3P]\u000e,WCA\f\")\tAbF\u0005\u0002\u001a7\u0019!!\u0004\u0001\u0001\u0019\u00051a$/\u001a4j]\u0016lWM\u001c;?!\raRdH\u0007\u0002\t%\u0011a\u0004\u0002\u0002\u000f\u0013NLE/\u001a:bE2,wJ\\2f!\t\u0001\u0013\u0005\u0004\u0001\u0005\u000b\t\u0012!\u0019A\u0012\u0003\tI+\u0007O]\t\u0003I\u001d\u0002\"!D\u0013\n\u0005\u0019B!a\u0002(pi\"Lgn\u001a\t\u0003\u001b!J!!\u000b\u0005\u0003\u0007\u0005s\u00170\u0002\u0003,3\u0001a#!A!\u0011\u00055\u001adB\u0001\u0011/\u0011\u0015y#\u0001q\u00011\u00039I7/\u0013;fe\u0006\u0014G.\u001a\'jW\u0016\u00042\u0001H\u0019 \u0013\t\u0011DA\u0001\u0006Jg&#XM]1cY\u0016L!aK\u000f"
    )
  ScalaInlineInfo: length = 0x13 (unknown attribute)
   01 00 00 03 00 15 00 16 01 00 0D 00 0E 00 00 09
   00 0A 01
  ScalaSig: length = 0x3 (unknown attribute)
   05 02 00
