Classfile /Users/mw/Projects/slang-braindump/.jar/jar8/assemble/slang-braindump/assemble/content/scala/collection/generic/IsIterableOnce$.class
  Last modified May 29, 2022; size 1498 bytes
  SHA-256 checksum 682e46624b5bfbbfcb5328c1f55d0a44df9f9d3fa7a3acc99aaf2f115a341a72
  Compiled from "IsIterableOnce.scala"
public final class scala.collection.generic.IsIterableOnce$ implements scala.collection.generic.IsIterableOnceLowPriority
  minor version: 0
  major version: 52
  flags: (0x0031) ACC_PUBLIC, ACC_FINAL, ACC_SUPER
  this_class: #2                          // scala/collection/generic/IsIterableOnce$
  super_class: #4                         // java/lang/Object
  interfaces: 1, fields: 1, methods: 4, attributes: 4
Constant pool:
   #1 = Utf8               scala/collection/generic/IsIterableOnce$
   #2 = Class              #1             // scala/collection/generic/IsIterableOnce$
   #3 = Utf8               java/lang/Object
   #4 = Class              #3             // java/lang/Object
   #5 = Utf8               scala/collection/generic/IsIterableOnceLowPriority
   #6 = Class              #5             // scala/collection/generic/IsIterableOnceLowPriority
   #7 = Utf8               IsIterableOnce.scala
   #8 = Utf8               scala/collection/generic/IsIterableOnce$$anon$1
   #9 = Class              #8             // scala/collection/generic/IsIterableOnce$$anon$1
  #10 = Utf8               MODULE$
  #11 = Utf8               Lscala/collection/generic/IsIterableOnce$;
  #12 = Utf8               <clinit>
  #13 = Utf8               ()V
  #14 = Utf8               <init>
  #15 = NameAndType        #14:#13        // "<init>":()V
  #16 = Methodref          #2.#15         // scala/collection/generic/IsIterableOnce$."<init>":()V
  #17 = NameAndType        #10:#11        // MODULE$:Lscala/collection/generic/IsIterableOnce$;
  #18 = Fieldref           #2.#17         // scala/collection/generic/IsIterableOnce$.MODULE$:Lscala/collection/generic/IsIterableOnce$;
  #19 = Utf8               isIterableLikeIsIterableOnce
  #20 = Utf8               (Lscala/collection/generic/IsIterable;)Lscala/collection/generic/IsIterableOnce;
  #21 = Utf8               <Repr:Ljava/lang/Object;>(Lscala/collection/generic/IsIterable<TRepr;>;)Lscala/collection/generic/IsIterableOnce<TRepr;>;
  #22 = Utf8               isIterableLike
  #23 = Utf8               isIterableLikeIsIterableOnce$
  #24 = Utf8               (Lscala/collection/generic/IsIterableOnceLowPriority;Lscala/collection/generic/IsIterable;)Lscala/collection/generic/IsIterableOnce;
  #25 = NameAndType        #23:#24        // isIterableLikeIsIterableOnce$:(Lscala/collection/generic/IsIterableOnceLowPriority;Lscala/collection/generic/IsIterable;)Lscala/collection/generic/IsIterableOnce;
  #26 = InterfaceMethodref #6.#25         // scala/collection/generic/IsIterableOnceLowPriority.isIterableLikeIsIterableOnce$:(Lscala/collection/generic/IsIterableOnceLowPriority;Lscala/collection/generic/IsIterable;)Lscala/collection/generic/IsIterableOnce;
  #27 = Utf8               this
  #28 = Utf8               Lscala/collection/generic/IsIterable;
  #29 = Utf8               iterableOnceIsIterableOnce
  #30 = Utf8               ()Lscala/collection/generic/IsIterableOnce;
  #31 = Utf8               <CC0::Lscala/collection/IterableOnce<Ljava/lang/Object;>;A0:Ljava/lang/Object;>()Lscala/collection/generic/IsIterableOnce<TCC0;>;
  #32 = Methodref          #9.#15         // scala/collection/generic/IsIterableOnce$$anon$1."<init>":()V
  #33 = Methodref          #4.#15         // java/lang/Object."<init>":()V
  #34 = Utf8               Code
  #35 = Utf8               LineNumberTable
  #36 = Utf8               LocalVariableTable
  #37 = Utf8               Signature
  #38 = Utf8               MethodParameters
  #39 = Utf8               InnerClasses
  #40 = Utf8               SourceFile
  #41 = Utf8               ScalaInlineInfo
  #42 = Utf8               Scala
{
  public static final scala.collection.generic.IsIterableOnce$ MODULE$;
    descriptor: Lscala/collection/generic/IsIterableOnce$;
    flags: (0x0019) ACC_PUBLIC, ACC_STATIC, ACC_FINAL

  public static {};
    descriptor: ()V
    flags: (0x0009) ACC_PUBLIC, ACC_STATIC
    Code:
      stack=2, locals=0, args_size=0
         0: new           #2                  // class scala/collection/generic/IsIterableOnce$
         3: dup
         4: invokespecial #16                 // Method "<init>":()V
         7: putstatic     #18                 // Field MODULE$:Lscala/collection/generic/IsIterableOnce$;
        10: getstatic     #18                 // Field MODULE$:Lscala/collection/generic/IsIterableOnce$;
        13: pop
        14: return
      LineNumberTable:
        line 53: 0
        line 53: 14

  public <Repr extends java.lang.Object> scala.collection.generic.IsIterableOnce<Repr> isIterableLikeIsIterableOnce(scala.collection.generic.IsIterable<Repr>);
    descriptor: (Lscala/collection/generic/IsIterable;)Lscala/collection/generic/IsIterableOnce;
    flags: (0x0001) ACC_PUBLIC
    Code:
      stack=2, locals=2, args_size=2
         0: aload_0
         1: aload_1
         2: invokestatic  #26                 // InterfaceMethod scala/collection/generic/IsIterableOnceLowPriority.isIterableLikeIsIterableOnce$:(Lscala/collection/generic/IsIterableOnceLowPriority;Lscala/collection/generic/IsIterable;)Lscala/collection/generic/IsIterableOnce;
         5: areturn
      LineNumberTable:
        line 53: 0
      LocalVariableTable:
        Start  Length  Slot  Name   Signature
            0       6     0  this   Lscala/collection/generic/IsIterableOnce$;
            0       6     1 isIterableLike   Lscala/collection/generic/IsIterable;
    Signature: #21                          // <Repr:Ljava/lang/Object;>(Lscala/collection/generic/IsIterable<TRepr;>;)Lscala/collection/generic/IsIterableOnce<TRepr;>;
    MethodParameters:
      Name                           Flags
      isIterableLike                 final

  public <CC0 extends scala.collection.IterableOnce<java.lang.Object>, A0 extends java.lang.Object> scala.collection.generic.IsIterableOnce<CC0> iterableOnceIsIterableOnce();
    descriptor: ()Lscala/collection/generic/IsIterableOnce;
    flags: (0x0001) ACC_PUBLIC
    Code:
      stack=2, locals=1, args_size=1
         0: new           #9                  // class scala/collection/generic/IsIterableOnce$$anon$1
         3: dup
         4: invokespecial #32                 // Method scala/collection/generic/IsIterableOnce$$anon$1."<init>":()V
         7: areturn
      LineNumberTable:
        line 57: 0
      LocalVariableTable:
        Start  Length  Slot  Name   Signature
            0       8     0  this   Lscala/collection/generic/IsIterableOnce$;
    Signature: #31                          // <CC0::Lscala/collection/IterableOnce<Ljava/lang/Object;>;A0:Ljava/lang/Object;>()Lscala/collection/generic/IsIterableOnce<TCC0;>;

  private scala.collection.generic.IsIterableOnce$();
    descriptor: ()V
    flags: (0x0002) ACC_PRIVATE
    Code:
      stack=1, locals=1, args_size=1
         0: aload_0
         1: invokespecial #33                 // Method java/lang/Object."<init>":()V
         4: return
      LineNumberTable:
        line 53: 0
      LocalVariableTable:
        Start  Length  Slot  Name   Signature
            0       5     0  this   Lscala/collection/generic/IsIterableOnce$;
}
InnerClasses:
  public final #9;                        // class scala/collection/generic/IsIterableOnce$$anon$1
SourceFile: "IsIterableOnce.scala"
  ScalaInlineInfo: length = 0x13 (unknown attribute)
   01 01 00 03 00 0E 00 0D 01 00 13 00 14 01 00 1D
   00 1E 01
  Scala: length = 0x0 (unknown attribute)

