Classfile /Users/mw/Projects/slang-braindump/.jar/jar8/assemble/slang-braindump/assemble/content/scala/collection/generic/Subtractable.class
  Last modified May 29, 2022; size 4150 bytes
  SHA-256 checksum 9f0954c75daef499aa6100a4db4477ab700a3aa3d1bbf599c4c521e17ecd7424
  Compiled from "Subtractable.scala"
public interface scala.collection.generic.Subtractable<A extends java.lang.Object, Repr extends scala.collection.generic.Subtractable<A, Repr>>
  minor version: 0
  major version: 52
  flags: (0x0601) ACC_PUBLIC, ACC_INTERFACE, ACC_ABSTRACT
  this_class: #2                          // scala/collection/generic/Subtractable
  super_class: #5                         // java/lang/Object
  interfaces: 0, fields: 0, methods: 9, attributes: 8
Constant pool:
    #1 = Utf8               scala/collection/generic/Subtractable
    #2 = Class              #1            // scala/collection/generic/Subtractable
    #3 = Utf8               <A:Ljava/lang/Object;Repr::Lscala/collection/generic/Subtractable<TA;TRepr;>;>Ljava/lang/Object;
    #4 = Utf8               java/lang/Object
    #5 = Class              #4            // java/lang/Object
    #6 = Utf8               Subtractable.scala
    #7 = Utf8               Lscala/reflect/ScalaSignature;
    #8 = Utf8               bytes
    #9 = Utf8               \u0006\u000513qAB\u0004\u0011\u0002\u0007\u0005a\u0002C\u0003\u0015\u0001\u0011\u0005Q\u0003C\u0003\u001a\u0001\u0019E!\u0004C\u0003-\u0001\u0019\u0005Q\u0006C\u0003-\u0001\u0011\u0005\u0001\u0007C\u0003;\u0001\u0011\u00051H\u0001\u0007Tk\n$(/Y2uC\ndWM\u0003\u0002\t\u0013\u00059q-\u001a8fe&\u001c\'B\u0001\u0006\f\u0003)\u0019w\u000e\u001c7fGRLwN\u001c\u0006\u0002\u0019\u0005)1oY1mC\u000e\u0001QcA\b\';M\u0011\u0001\u0001\u0005\t\u0003#Ii\u0011aC\u0005\u0003\'-\u0011a!\u00118z%\u00164\u0017A\u0002\u0013j]&$H\u0005F\u0001\u0017!\t\tr#\u0003\u0002\u0019\u0017\t!QK\\5u\u0003\u0011\u0011X\r\u001d:\u0016\u0003m\u0001\"\u0001H\u000f\r\u0001\u00111a\u0004\u0001CC\u0002}\u0011AAU3qeF\u0011\u0001e\t\t\u0003#\u0005J!AI\u0006\u0003\u000f9{G\u000f[5oOB!A\u0005A\u0013\u001c\u001b\u00059\u0001C\u0001\u000f\'\t\u00159\u0003A1\u0001)\u0005\u0005\t\u0015C\u0001\u0011*!\t\t\"&\u0003\u0002,\u0017\t\u0019\u0011I\\=\u0002\r\u0011j\u0017N\\;t)\tYb\u0006C\u00030\u0007\u0001\u0007Q%\u0001\u0003fY\u0016lG\u0003B\u000e2gUBQA\r\u0003A\u0002\u0015\nQ!\u001a7f[FBQ\u0001\u000e\u0003A\u0002\u0015\nQ!\u001a7f[JBQA\u000e\u0003A\u0002]\nQ!\u001a7f[N\u00042!\u0005\u001d&\u0013\tI4B\u0001\u0006=e\u0016\u0004X-\u0019;fIz\nA\u0002J7j]V\u001cH%\\5okN$\"a\u0007\u001f\t\u000bu*\u0001\u0019\u0001 \u0002\u0005a\u001c\bcA AK5\t\u0011\"\u0003\u0002B\u0013\ta\u0011\n^3sC\ndWm\u00148dK\"2\u0001a\u0011$H\u0013*\u0003\"!\u0005#\n\u0005\u0015[!A\u00033faJ,7-\u0019;fI\u00069Q.Z:tC\u001e,\u0017%\u0001%\u0002\'N+(\r\u001e:bGR\f\'\r\\3!SN\u0004C-\u001a9sK\u000e\fG/\u001a3/AQC\u0017n\u001d\u0011jg\u0002rwn\u001e\u0011j[BdW-\\3oi\u0016$\u0007%Y:!a\u0006\u0014H\u000fI8gAM+Go\u00149tY\u0001j\u0015\r](qg2\u0002S\r^2/\u0003\u0015\u0019\u0018N\\2fC\u0005Y\u0015A\u0002\u001a/cMr\u0003\u0007
   #10 = Utf8               java/lang/invoke/MethodHandles$Lookup
   #11 = Class              #10           // java/lang/invoke/MethodHandles$Lookup
   #12 = Utf8               java/lang/invoke/MethodHandles
   #13 = Class              #12           // java/lang/invoke/MethodHandles
   #14 = Utf8               Lookup
   #15 = Utf8               repr
   #16 = Utf8               ()Lscala/collection/generic/Subtractable;
   #17 = Utf8               ()TRepr;
   #18 = Utf8               $minus
   #19 = Utf8               (Ljava/lang/Object;)Lscala/collection/generic/Subtractable;
   #20 = Utf8               (TA;)TRepr;
   #21 = Utf8               elem
   #22 = Utf8               $minus$
   #23 = Utf8               (Lscala/collection/generic/Subtractable;Ljava/lang/Object;Ljava/lang/Object;Lscala/collection/immutable/Seq;)Lscala/collection/generic/Subtractable;
   #24 = Utf8               $this
   #25 = Utf8               elem1
   #26 = Utf8               elem2
   #27 = Utf8               elems
   #28 = Utf8               (Ljava/lang/Object;Ljava/lang/Object;Lscala/collection/immutable/Seq;)Lscala/collection/generic/Subtractable;
   #29 = NameAndType        #18:#28       // $minus:(Ljava/lang/Object;Ljava/lang/Object;Lscala/collection/immutable/Seq;)Lscala/collection/generic/Subtractable;
   #30 = InterfaceMethodref #2.#29        // scala/collection/generic/Subtractable.$minus:(Ljava/lang/Object;Ljava/lang/Object;Lscala/collection/immutable/Seq;)Lscala/collection/generic/Subtractable;
   #31 = Utf8               Lscala/collection/generic/Subtractable;
   #32 = Utf8               Ljava/lang/Object;
   #33 = Utf8               Lscala/collection/immutable/Seq;
   #34 = Utf8               (TA;TA;Lscala/collection/immutable/Seq<TA;>;)TRepr;
   #35 = NameAndType        #18:#19       // $minus:(Ljava/lang/Object;)Lscala/collection/generic/Subtractable;
   #36 = InterfaceMethodref #2.#35        // scala/collection/generic/Subtractable.$minus:(Ljava/lang/Object;)Lscala/collection/generic/Subtractable;
   #37 = Utf8               $minus$minus
   #38 = Utf8               (Lscala/collection/IterableOnce;)Lscala/collection/generic/Subtractable;
   #39 = NameAndType        #37:#38       // $minus$minus:(Lscala/collection/IterableOnce;)Lscala/collection/generic/Subtractable;
   #40 = InterfaceMethodref #2.#39        // scala/collection/generic/Subtractable.$minus$minus:(Lscala/collection/IterableOnce;)Lscala/collection/generic/Subtractable;
   #41 = Utf8               this
   #42 = Utf8               $minus$minus$
   #43 = Utf8               (Lscala/collection/generic/Subtractable;Lscala/collection/IterableOnce;)Lscala/collection/generic/Subtractable;
   #44 = Utf8               xs
   #45 = Utf8               Lscala/collection/IterableOnce;
   #46 = Utf8               (Lscala/collection/IterableOnce<TA;>;)TRepr;
   #47 = NameAndType        #15:#16       // repr:()Lscala/collection/generic/Subtractable;
   #48 = InterfaceMethodref #2.#47        // scala/collection/generic/Subtractable.repr:()Lscala/collection/generic/Subtractable;
   #49 = Utf8               scala/collection/IterableOnce
   #50 = Class              #49           // scala/collection/IterableOnce
   #51 = Utf8               iterator
   #52 = Utf8               ()Lscala/collection/Iterator;
   #53 = NameAndType        #51:#52       // iterator:()Lscala/collection/Iterator;
   #54 = InterfaceMethodref #50.#53       // scala/collection/IterableOnce.iterator:()Lscala/collection/Iterator;
   #55 = Utf8               (Ljava/lang/Object;Ljava/lang/Object;)Ljava/lang/Object;
   #56 = MethodType         #55           //  (Ljava/lang/Object;Ljava/lang/Object;)Ljava/lang/Object;
   #57 = Utf8               $anonfun$$minus$minus$1
   #58 = Utf8               (Lscala/collection/generic/Subtractable;Ljava/lang/Object;)Lscala/collection/generic/Subtractable;
   #59 = NameAndType        #57:#58       // $anonfun$$minus$minus$1:(Lscala/collection/generic/Subtractable;Ljava/lang/Object;)Lscala/collection/generic/Subtractable;
   #60 = InterfaceMethodref #2.#59        // scala/collection/generic/Subtractable.$anonfun$$minus$minus$1:(Lscala/collection/generic/Subtractable;Ljava/lang/Object;)Lscala/collection/generic/Subtractable;
   #61 = MethodHandle       6:#60         // REF_invokeStatic scala/collection/generic/Subtractable.$anonfun$$minus$minus$1:(Lscala/collection/generic/Subtractable;Ljava/lang/Object;)Lscala/collection/generic/Subtractable;
   #62 = MethodType         #58           //  (Lscala/collection/generic/Subtractable;Ljava/lang/Object;)Lscala/collection/generic/Subtractable;
   #63 = Integer            5
   #64 = Integer            1
   #65 = Utf8               java/lang/invoke/LambdaMetafactory
   #66 = Class              #65           // java/lang/invoke/LambdaMetafactory
   #67 = Utf8               altMetafactory
   #68 = Utf8               (Ljava/lang/invoke/MethodHandles$Lookup;Ljava/lang/String;Ljava/lang/invoke/MethodType;[Ljava/lang/Object;)Ljava/lang/invoke/CallSite;
   #69 = NameAndType        #67:#68       // altMetafactory:(Ljava/lang/invoke/MethodHandles$Lookup;Ljava/lang/String;Ljava/lang/invoke/MethodType;[Ljava/lang/Object;)Ljava/lang/invoke/CallSite;
   #70 = Methodref          #66.#69       // java/lang/invoke/LambdaMetafactory.altMetafactory:(Ljava/lang/invoke/MethodHandles$Lookup;Ljava/lang/String;Ljava/lang/invoke/MethodType;[Ljava/lang/Object;)Ljava/lang/invoke/CallSite;
   #71 = MethodHandle       6:#70         // REF_invokeStatic java/lang/invoke/LambdaMetafactory.altMetafactory:(Ljava/lang/invoke/MethodHandles$Lookup;Ljava/lang/String;Ljava/lang/invoke/MethodType;[Ljava/lang/Object;)Ljava/lang/invoke/CallSite;
   #72 = Utf8               apply
   #73 = Utf8               ()Lscala/Function2;
   #74 = NameAndType        #72:#73       // apply:()Lscala/Function2;
   #75 = InvokeDynamic      #0:#74        // #0:apply:()Lscala/Function2;
   #76 = Utf8               scala/collection/IterableOnceOps
   #77 = Class              #76           // scala/collection/IterableOnceOps
   #78 = Utf8               foldLeft
   #79 = Utf8               (Ljava/lang/Object;Lscala/Function2;)Ljava/lang/Object;
   #80 = NameAndType        #78:#79       // foldLeft:(Ljava/lang/Object;Lscala/Function2;)Ljava/lang/Object;
   #81 = InterfaceMethodref #77.#80       // scala/collection/IterableOnceOps.foldLeft:(Ljava/lang/Object;Lscala/Function2;)Ljava/lang/Object;
   #82 = Utf8               $div$colon_op
   #83 = Utf8               Lscala/Function2;
   #84 = Utf8               scala/Function2
   #85 = Class              #84           // scala/Function2
   #86 = Utf8               scala/collection/Iterator
   #87 = Class              #86           // scala/collection/Iterator
   #88 = Utf8               x$1
   #89 = Utf8               x$2
   #90 = Utf8               $init$
   #91 = Utf8               (Lscala/collection/generic/Subtractable;)V
   #92 = Utf8               $deserializeLambda$
   #93 = Utf8               (Ljava/lang/invoke/SerializedLambda;)Ljava/lang/Object;
   #94 = Utf8               scala/runtime/LambdaDeserialize
   #95 = Class              #94           // scala/runtime/LambdaDeserialize
   #96 = Utf8               bootstrap
   #97 = Utf8               (Ljava/lang/invoke/MethodHandles$Lookup;Ljava/lang/String;Ljava/lang/invoke/MethodType;[Ljava/lang/invoke/MethodHandle;)Ljava/lang/invoke/CallSite;
   #98 = NameAndType        #96:#97       // bootstrap:(Ljava/lang/invoke/MethodHandles$Lookup;Ljava/lang/String;Ljava/lang/invoke/MethodType;[Ljava/lang/invoke/MethodHandle;)Ljava/lang/invoke/CallSite;
   #99 = Methodref          #95.#98       // scala/runtime/LambdaDeserialize.bootstrap:(Ljava/lang/invoke/MethodHandles$Lookup;Ljava/lang/String;Ljava/lang/invoke/MethodType;[Ljava/lang/invoke/MethodHandle;)Ljava/lang/invoke/CallSite;
  #100 = MethodHandle       6:#99         // REF_invokeStatic scala/runtime/LambdaDeserialize.bootstrap:(Ljava/lang/invoke/MethodHandles$Lookup;Ljava/lang/String;Ljava/lang/invoke/MethodType;[Ljava/lang/invoke/MethodHandle;)Ljava/lang/invoke/CallSite;
  #101 = Utf8               lambdaDeserialize
  #102 = NameAndType        #101:#93      // lambdaDeserialize:(Ljava/lang/invoke/SerializedLambda;)Ljava/lang/Object;
  #103 = InvokeDynamic      #1:#102       // #1:lambdaDeserialize:(Ljava/lang/invoke/SerializedLambda;)Ljava/lang/Object;
  #104 = Utf8               Signature
  #105 = Utf8               MethodParameters
  #106 = Utf8               Code
  #107 = Utf8               LineNumberTable
  #108 = Utf8               LocalVariableTable
  #109 = Utf8               StackMapTable
  #110 = Utf8               InnerClasses
  #111 = Utf8               SourceFile
  #112 = Utf8               Deprecated
  #113 = Utf8               RuntimeVisibleAnnotations
  #114 = Utf8               BootstrapMethods
  #115 = Utf8               ScalaInlineInfo
  #116 = Utf8               ScalaSig
{
  public abstract Repr repr();
    descriptor: ()Lscala/collection/generic/Subtractable;
    flags: (0x0401) ACC_PUBLIC, ACC_ABSTRACT
    Signature: #17                          // ()TRepr;

  public abstract Repr $minus(A);
    descriptor: (Ljava/lang/Object;)Lscala/collection/generic/Subtractable;
    flags: (0x0401) ACC_PUBLIC, ACC_ABSTRACT
    Signature: #20                          // (TA;)TRepr;
    MethodParameters:
      Name                           Flags
      elem                           final

  public static scala.collection.generic.Subtractable $minus$(scala.collection.generic.Subtractable, java.lang.Object, java.lang.Object, scala.collection.immutable.Seq);
    descriptor: (Lscala/collection/generic/Subtractable;Ljava/lang/Object;Ljava/lang/Object;Lscala/collection/immutable/Seq;)Lscala/collection/generic/Subtractable;
    flags: (0x1009) ACC_PUBLIC, ACC_STATIC, ACC_SYNTHETIC
    Code:
      stack=4, locals=4, args_size=4
         0: aload_0
         1: aload_1
         2: aload_2
         3: aload_3
         4: invokespecial #30                 // InterfaceMethod $minus:(Ljava/lang/Object;Ljava/lang/Object;Lscala/collection/immutable/Seq;)Lscala/collection/generic/Subtractable;
         7: areturn
      LineNumberTable:
        line 51: 0
      LocalVariableTable:
        Start  Length  Slot  Name   Signature
            0       8     0 $this   Lscala/collection/generic/Subtractable;
            0       8     1 elem1   Ljava/lang/Object;
            0       8     2 elem2   Ljava/lang/Object;
            0       8     3 elems   Lscala/collection/immutable/Seq;
    MethodParameters:
      Name                           Flags
      $this                          final synthetic
      elem1                          final
      elem2                          final
      elems                          final

  public default Repr $minus(A, A, scala.collection.immutable.Seq<A>);
    descriptor: (Ljava/lang/Object;Ljava/lang/Object;Lscala/collection/immutable/Seq;)Lscala/collection/generic/Subtractable;
    flags: (0x0001) ACC_PUBLIC
    Code:
      stack=2, locals=4, args_size=4
         0: aload_0
         1: aload_1
         2: invokeinterface #36,  2           // InterfaceMethod $minus:(Ljava/lang/Object;)Lscala/collection/generic/Subtractable;
         7: aload_2
         8: invokeinterface #36,  2           // InterfaceMethod $minus:(Ljava/lang/Object;)Lscala/collection/generic/Subtractable;
        13: aload_3
        14: invokeinterface #40,  2           // InterfaceMethod $minus$minus:(Lscala/collection/IterableOnce;)Lscala/collection/generic/Subtractable;
        19: areturn
      LineNumberTable:
        line 52: 0
      LocalVariableTable:
        Start  Length  Slot  Name   Signature
            0      20     0  this   Lscala/collection/generic/Subtractable;
            0      20     1 elem1   Ljava/lang/Object;
            0      20     2 elem2   Ljava/lang/Object;
            0      20     3 elems   Lscala/collection/immutable/Seq;
    Signature: #34                          // (TA;TA;Lscala/collection/immutable/Seq<TA;>;)TRepr;
    MethodParameters:
      Name                           Flags
      elem1                          final
      elem2                          final
      elems                          final

  public static scala.collection.generic.Subtractable $minus$minus$(scala.collection.generic.Subtractable, scala.collection.IterableOnce);
    descriptor: (Lscala/collection/generic/Subtractable;Lscala/collection/IterableOnce;)Lscala/collection/generic/Subtractable;
    flags: (0x1009) ACC_PUBLIC, ACC_STATIC, ACC_SYNTHETIC
    Code:
      stack=2, locals=2, args_size=2
         0: aload_0
         1: aload_1
         2: invokespecial #40                 // InterfaceMethod $minus$minus:(Lscala/collection/IterableOnce;)Lscala/collection/generic/Subtractable;
         5: areturn
      LineNumberTable:
        line 61: 0
      LocalVariableTable:
        Start  Length  Slot  Name   Signature
            0       6     0 $this   Lscala/collection/generic/Subtractable;
            0       6     1    xs   Lscala/collection/IterableOnce;
    MethodParameters:
      Name                           Flags
      $this                          final synthetic
      xs                             final

  public default Repr $minus$minus(scala.collection.IterableOnce<A>);
    descriptor: (Lscala/collection/IterableOnce;)Lscala/collection/generic/Subtractable;
    flags: (0x0001) ACC_PUBLIC
    Code:
      stack=3, locals=4, args_size=2
         0: aload_0
         1: invokeinterface #48,  1           // InterfaceMethod repr:()Lscala/collection/generic/Subtractable;
         6: astore_2
         7: aload_1
         8: invokeinterface #54,  1           // InterfaceMethod scala/collection/IterableOnce.iterator:()Lscala/collection/Iterator;
        13: invokedynamic #75,  0             // InvokeDynamic #0:apply:()Lscala/Function2;
        18: astore_3
        19: dup
        20: ifnonnull     25
        23: aconst_null
        24: athrow
        25: aload_2
        26: aload_3
        27: invokeinterface #81,  3           // InterfaceMethod scala/collection/IterableOnceOps.foldLeft:(Ljava/lang/Object;Lscala/Function2;)Ljava/lang/Object;
        32: checkcast     #2                  // class scala/collection/generic/Subtractable
        35: areturn
      StackMapTable: number_of_entries = 1
        frame_type = 255 /* full_frame */
          offset_delta = 25
          locals = [ class scala/collection/generic/Subtractable, class scala/collection/IterableOnce, class scala/collection/generic/Subtractable, class scala/Function2 ]
          stack = [ class scala/collection/Iterator ]
      LineNumberTable:
        line 61: 0
      LocalVariableTable:
        Start  Length  Slot  Name   Signature
            0      36     0  this   Lscala/collection/generic/Subtractable;
            0      36     1    xs   Lscala/collection/IterableOnce;
           25       7     3 $div$colon_op   Lscala/Function2;
    Signature: #46                          // (Lscala/collection/IterableOnce<TA;>;)TRepr;
    MethodParameters:
      Name                           Flags
      xs                             final

  public static scala.collection.generic.Subtractable $anonfun$$minus$minus$1(scala.collection.generic.Subtractable, java.lang.Object);
    descriptor: (Lscala/collection/generic/Subtractable;Ljava/lang/Object;)Lscala/collection/generic/Subtractable;
    flags: (0x1009) ACC_PUBLIC, ACC_STATIC, ACC_SYNTHETIC
    Code:
      stack=2, locals=2, args_size=2
         0: aload_0
         1: aload_1
         2: invokeinterface #36,  2           // InterfaceMethod $minus:(Ljava/lang/Object;)Lscala/collection/generic/Subtractable;
         7: areturn
      LineNumberTable:
        line 61: 0
      LocalVariableTable:
        Start  Length  Slot  Name   Signature
            0       8     0   x$1   Lscala/collection/generic/Subtractable;
            0       8     1   x$2   Ljava/lang/Object;
    MethodParameters:
      Name                           Flags
      x$1                            final
      x$2                            final

  public static void $init$(scala.collection.generic.Subtractable);
    descriptor: (Lscala/collection/generic/Subtractable;)V
    flags: (0x0009) ACC_PUBLIC, ACC_STATIC
    Code:
      stack=0, locals=1, args_size=1
         0: return
      LineNumberTable:
        line 27: 0
      LocalVariableTable:
        Start  Length  Slot  Name   Signature
            0       1     0 $this   Lscala/collection/generic/Subtractable;
    MethodParameters:
      Name                           Flags
      $this                          final synthetic

  private static java.lang.Object $deserializeLambda$(java.lang.invoke.SerializedLambda);
    descriptor: (Ljava/lang/invoke/SerializedLambda;)Ljava/lang/Object;
    flags: (0x100a) ACC_PRIVATE, ACC_STATIC, ACC_SYNTHETIC
    Code:
      stack=1, locals=1, args_size=1
         0: aload_0
         1: invokedynamic #103,  0            // InvokeDynamic #1:lambdaDeserialize:(Ljava/lang/invoke/SerializedLambda;)Ljava/lang/Object;
         6: areturn
}
InnerClasses:
  public static final #14= #11 of #13;    // Lookup=class java/lang/invoke/MethodHandles$Lookup of class java/lang/invoke/MethodHandles
Signature: #3                           // <A:Ljava/lang/Object;Repr::Lscala/collection/generic/Subtractable<TA;TRepr;>;>Ljava/lang/Object;
SourceFile: "Subtractable.scala"
Deprecated: true
RuntimeVisibleAnnotations:
  0: #7(#8=s#9)
    scala.reflect.ScalaSignature(
      bytes="\u0006\u000513qAB\u0004\u0011\u0002\u0007\u0005a\u0002C\u0003\u0015\u0001\u0011\u0005Q\u0003C\u0003\u001a\u0001\u0019E!\u0004C\u0003-\u0001\u0019\u0005Q\u0006C\u0003-\u0001\u0011\u0005\u0001\u0007C\u0003;\u0001\u0011\u00051H\u0001\u0007Tk\n$(/Y2uC\ndWM\u0003\u0002\t\u0013\u00059q-\u001a8fe&\u001c\'B\u0001\u0006\f\u0003)\u0019w\u000e\u001c7fGRLwN\u001c\u0006\u0002\u0019\u0005)1oY1mC\u000e\u0001QcA\b\';M\u0011\u0001\u0001\u0005\t\u0003#Ii\u0011aC\u0005\u0003\'-\u0011a!\u00118z%\u00164\u0017A\u0002\u0013j]&$H\u0005F\u0001\u0017!\t\tr#\u0003\u0002\u0019\u0017\t!QK\\5u\u0003\u0011\u0011X\r\u001d:\u0016\u0003m\u0001\"\u0001H\u000f\r\u0001\u00111a\u0004\u0001CC\u0002}\u0011AAU3qeF\u0011\u0001e\t\t\u0003#\u0005J!AI\u0006\u0003\u000f9{G\u000f[5oOB!A\u0005A\u0013\u001c\u001b\u00059\u0001C\u0001\u000f\'\t\u00159\u0003A1\u0001)\u0005\u0005\t\u0015C\u0001\u0011*!\t\t\"&\u0003\u0002,\u0017\t\u0019\u0011I\\=\u0002\r\u0011j\u0017N\\;t)\tYb\u0006C\u00030\u0007\u0001\u0007Q%\u0001\u0003fY\u0016lG\u0003B\u000e2gUBQA\r\u0003A\u0002\u0015\nQ!\u001a7f[FBQ\u0001\u000e\u0003A\u0002\u0015\nQ!\u001a7f[JBQA\u000e\u0003A\u0002]\nQ!\u001a7f[N\u00042!\u0005\u001d&\u0013\tI4B\u0001\u0006=e\u0016\u0004X-\u0019;fIz\nA\u0002J7j]V\u001cH%\\5okN$\"a\u0007\u001f\t\u000bu*\u0001\u0019\u0001 \u0002\u0005a\u001c\bcA AK5\t\u0011\"\u0003\u0002B\u0013\ta\u0011\n^3sC\ndWm\u00148dK\"2\u0001a\u0011$H\u0013*\u0003\"!\u0005#\n\u0005\u0015[!A\u00033faJ,7-\u0019;fI\u00069Q.Z:tC\u001e,\u0017%\u0001%\u0002\'N+(\r\u001e:bGR\f\'\r\\3!SN\u0004C-\u001a9sK\u000e\fG/\u001a3/AQC\u0017n\u001d\u0011jg\u0002rwn\u001e\u0011j[BdW-\\3oi\u0016$\u0007%Y:!a\u0006\u0014H\u000fI8gAM+Go\u00149tY\u0001j\u0015\r](qg2\u0002S\r^2/\u0003\u0015\u0019\u0018N\\2fC\u0005Y\u0015A\u0002\u001a/cMr\u0003\u0007"
    )
BootstrapMethods:
  0: #71 REF_invokeStatic java/lang/invoke/LambdaMetafactory.altMetafactory:(Ljava/lang/invoke/MethodHandles$Lookup;Ljava/lang/String;Ljava/lang/invoke/MethodType;[Ljava/lang/Object;)Ljava/lang/invoke/CallSite;
    Method arguments:
      #56 (Ljava/lang/Object;Ljava/lang/Object;)Ljava/lang/Object;
      #61 REF_invokeStatic scala/collection/generic/Subtractable.$anonfun$$minus$minus$1:(Lscala/collection/generic/Subtractable;Ljava/lang/Object;)Lscala/collection/generic/Subtractable;
      #62 (Lscala/collection/generic/Subtractable;Ljava/lang/Object;)Lscala/collection/generic/Subtractable;
      #63 5
      #64 1
      #62 (Lscala/collection/generic/Subtractable;Ljava/lang/Object;)Lscala/collection/generic/Subtractable;
  1: #100 REF_invokeStatic scala/runtime/LambdaDeserialize.bootstrap:(Ljava/lang/invoke/MethodHandles$Lookup;Ljava/lang/String;Ljava/lang/invoke/MethodType;[Ljava/lang/invoke/MethodHandle;)Ljava/lang/invoke/CallSite;
    Method arguments:
      #61 REF_invokeStatic scala/collection/generic/Subtractable.$anonfun$$minus$minus$1:(Lscala/collection/generic/Subtractable;Ljava/lang/Object;)Lscala/collection/generic/Subtractable;
  ScalaInlineInfo: length = 0x2C (unknown attribute)
   01 00 00 08 00 39 00 3A 01 00 5A 00 5B 01 00 12
   00 13 00 00 12 00 1C 00 00 16 00 17 01 00 25 00
   26 00 00 2A 00 2B 01 00 0F 00 10 00
  ScalaSig: length = 0x3 (unknown attribute)
   05 02 00
