Classfile /Users/mw/Projects/slang-braindump/.jar/jar8/assemble/slang-braindump/assemble/content/scala/collection/generic/VolatileAbort.class
  Last modified May 29, 2022; size 1485 bytes
  SHA-256 checksum 3b14eb6996194447c2f6e8bb4488409c72e7dc15781265781239b788dca6888d
  Compiled from "Signalling.scala"
public interface scala.collection.generic.VolatileAbort extends scala.collection.generic.Signalling
  minor version: 0
  major version: 52
  flags: (0x0601) ACC_PUBLIC, ACC_INTERFACE, ACC_ABSTRACT
  this_class: #2                          // scala/collection/generic/VolatileAbort
  super_class: #4                         // java/lang/Object
  interfaces: 1, fields: 0, methods: 7, attributes: 4
Constant pool:
   #1 = Utf8               scala/collection/generic/VolatileAbort
   #2 = Class              #1             // scala/collection/generic/VolatileAbort
   #3 = Utf8               java/lang/Object
   #4 = Class              #3             // java/lang/Object
   #5 = Utf8               scala/collection/generic/Signalling
   #6 = Class              #5             // scala/collection/generic/Signalling
   #7 = Utf8               Signalling.scala
   #8 = Utf8               Lscala/reflect/ScalaSignature;
   #9 = Utf8               bytes
  #10 = Utf8               \u0006\u0005-2qAB\u0004\u0011\u0002\u0007\u0005a\u0002C\u0003\u0018\u0001\u0011\u0005\u0001\u0004C\u0004\u001d\u0001\u0001\u0007I\u0011B\u000f\t\u000f\u0015\u0002\u0001\u0019!C\u0005M!)\u0011\u0006\u0001C!;!)!\u0006\u0001C!1\tiak\u001c7bi&dW-\u00112peRT!\u0001C\u0005\u0002\u000f\u001d,g.\u001a:jG*\u0011!bC\u0001\u000bG>dG.Z2uS>t\'\"\u0001\u0007\u0002\u000bM\u001c\u0017\r\\1\u0004\u0001M\u0019\u0001aD\n\u0011\u0005A\tR\"A\u0006\n\u0005IY!AB!osJ+g\r\u0005\u0002\u0015+5\tq!\u0003\u0002\u0017\u000f\tQ1+[4oC2d\u0017N\\4\u0002\r\u0011Jg.\u001b;%)\u0005I\u0002C\u0001\t\u001b\u0013\tY2B\u0001\u0003V]&$\u0018!C1c_J$h\r\\1h+\u0005q\u0002C\u0001\t \u0013\t\u00013BA\u0004C_>dW-\u00198)\u0005\t\u0011\u0003C\u0001\t$\u0013\t!3B\u0001\u0005w_2\fG/\u001b7f\u00035\t\'m\u001c:uM2\fwm\u0018\u0013fcR\u0011\u0011d\n\u0005\bQ\r\t\t\u00111\u0001\u001f\u0003\rAH%M\u0001\nSN\f%m\u001c:uK\u0012\fQ!\u00192peR\u0004
  #11 = Utf8               scala$collection$generic$VolatileAbort$$abortflag
  #12 = Utf8               ()Z
  #13 = Utf8               scala$collection$generic$VolatileAbort$$abortflag_$eq
  #14 = Utf8               (Z)V
  #15 = Utf8               x$1
  #16 = Utf8               isAborted$
  #17 = Utf8               (Lscala/collection/generic/VolatileAbort;)Z
  #18 = Utf8               $this
  #19 = Utf8               isAborted
  #20 = NameAndType        #19:#12        // isAborted:()Z
  #21 = InterfaceMethodref #2.#20         // scala/collection/generic/VolatileAbort.isAborted:()Z
  #22 = Utf8               Lscala/collection/generic/VolatileAbort;
  #23 = NameAndType        #11:#12        // scala$collection$generic$VolatileAbort$$abortflag:()Z
  #24 = InterfaceMethodref #2.#23         // scala/collection/generic/VolatileAbort.scala$collection$generic$VolatileAbort$$abortflag:()Z
  #25 = Utf8               this
  #26 = Utf8               abort$
  #27 = Utf8               (Lscala/collection/generic/VolatileAbort;)V
  #28 = Utf8               abort
  #29 = Utf8               ()V
  #30 = NameAndType        #28:#29        // abort:()V
  #31 = InterfaceMethodref #2.#30         // scala/collection/generic/VolatileAbort.abort:()V
  #32 = NameAndType        #13:#14        // scala$collection$generic$VolatileAbort$$abortflag_$eq:(Z)V
  #33 = InterfaceMethodref #2.#32         // scala/collection/generic/VolatileAbort.scala$collection$generic$VolatileAbort$$abortflag_$eq:(Z)V
  #34 = Utf8               $init$
  #35 = Utf8               MethodParameters
  #36 = Utf8               Code
  #37 = Utf8               LineNumberTable
  #38 = Utf8               LocalVariableTable
  #39 = Utf8               SourceFile
  #40 = Utf8               RuntimeVisibleAnnotations
  #41 = Utf8               ScalaInlineInfo
  #42 = Utf8               ScalaSig
{
  public abstract boolean scala$collection$generic$VolatileAbort$$abortflag();
    descriptor: ()Z
    flags: (0x0401) ACC_PUBLIC, ACC_ABSTRACT

  public abstract void scala$collection$generic$VolatileAbort$$abortflag_$eq(boolean);
    descriptor: (Z)V
    flags: (0x0401) ACC_PUBLIC, ACC_ABSTRACT
    MethodParameters:
      Name                           Flags
      x$1                            final

  public static boolean isAborted$(scala.collection.generic.VolatileAbort);
    descriptor: (Lscala/collection/generic/VolatileAbort;)Z
    flags: (0x1009) ACC_PUBLIC, ACC_STATIC, ACC_SYNTHETIC
    Code:
      stack=1, locals=1, args_size=1
         0: aload_0
         1: invokespecial #21                 // InterfaceMethod isAborted:()Z
         4: ireturn
      LineNumberTable:
        line 119: 0
      LocalVariableTable:
        Start  Length  Slot  Name   Signature
            0       5     0 $this   Lscala/collection/generic/VolatileAbort;
    MethodParameters:
      Name                           Flags
      $this                          final synthetic

  public default boolean isAborted();
    descriptor: ()Z
    flags: (0x0001) ACC_PUBLIC
    Code:
      stack=1, locals=1, args_size=1
         0: aload_0
         1: invokeinterface #24,  1           // InterfaceMethod scala$collection$generic$VolatileAbort$$abortflag:()Z
         6: ireturn
      LineNumberTable:
        line 119: 0
      LocalVariableTable:
        Start  Length  Slot  Name   Signature
            0       7     0  this   Lscala/collection/generic/VolatileAbort;

  public static void abort$(scala.collection.generic.VolatileAbort);
    descriptor: (Lscala/collection/generic/VolatileAbort;)V
    flags: (0x1009) ACC_PUBLIC, ACC_STATIC, ACC_SYNTHETIC
    Code:
      stack=1, locals=1, args_size=1
         0: aload_0
         1: invokespecial #31                 // InterfaceMethod abort:()V
         4: return
      LineNumberTable:
        line 120: 0
      LocalVariableTable:
        Start  Length  Slot  Name   Signature
            0       5     0 $this   Lscala/collection/generic/VolatileAbort;
    MethodParameters:
      Name                           Flags
      $this                          final synthetic

  public default void abort();
    descriptor: ()V
    flags: (0x0001) ACC_PUBLIC
    Code:
      stack=2, locals=1, args_size=1
         0: aload_0
         1: iconst_1
         2: invokeinterface #33,  2           // InterfaceMethod scala$collection$generic$VolatileAbort$$abortflag_$eq:(Z)V
         7: return
      LineNumberTable:
        line 120: 0
      LocalVariableTable:
        Start  Length  Slot  Name   Signature
            0       8     0  this   Lscala/collection/generic/VolatileAbort;

  public static void $init$(scala.collection.generic.VolatileAbort);
    descriptor: (Lscala/collection/generic/VolatileAbort;)V
    flags: (0x0009) ACC_PUBLIC, ACC_STATIC
    Code:
      stack=2, locals=1, args_size=1
         0: aload_0
         1: iconst_0
         2: invokeinterface #33,  2           // InterfaceMethod scala$collection$generic$VolatileAbort$$abortflag_$eq:(Z)V
         7: return
      LineNumberTable:
        line 118: 0
        line 117: 7
      LocalVariableTable:
        Start  Length  Slot  Name   Signature
            0       8     0 $this   Lscala/collection/generic/VolatileAbort;
    MethodParameters:
      Name                           Flags
      $this                          final synthetic
}
SourceFile: "Signalling.scala"
RuntimeVisibleAnnotations:
  0: #8(#9=s#10)
    scala.reflect.ScalaSignature(
      bytes="\u0006\u0005-2qAB\u0004\u0011\u0002\u0007\u0005a\u0002C\u0003\u0018\u0001\u0011\u0005\u0001\u0004C\u0004\u001d\u0001\u0001\u0007I\u0011B\u000f\t\u000f\u0015\u0002\u0001\u0019!C\u0005M!)\u0011\u0006\u0001C!;!)!\u0006\u0001C!1\tiak\u001c7bi&dW-\u00112peRT!\u0001C\u0005\u0002\u000f\u001d,g.\u001a:jG*\u0011!bC\u0001\u000bG>dG.Z2uS>t\'\"\u0001\u0007\u0002\u000bM\u001c\u0017\r\\1\u0004\u0001M\u0019\u0001aD\n\u0011\u0005A\tR\"A\u0006\n\u0005IY!AB!osJ+g\r\u0005\u0002\u0015+5\tq!\u0003\u0002\u0017\u000f\tQ1+[4oC2d\u0017N\\4\u0002\r\u0011Jg.\u001b;%)\u0005I\u0002C\u0001\t\u001b\u0013\tY2B\u0001\u0003V]&$\u0018!C1c_J$h\r\\1h+\u0005q\u0002C\u0001\t \u0013\t\u00013BA\u0004C_>dW-\u00198)\u0005\t\u0011\u0003C\u0001\t$\u0013\t!3B\u0001\u0005w_2\fG/\u001b7f\u00035\t\'m\u001c:uM2\fwm\u0018\u0013fcR\u0011\u0011d\n\u0005\bQ\r\t\t\u00111\u0001\u001f\u0003\rAH%M\u0001\nSN\f%m\u001c:uK\u0012\fQ!\u00192peR\u0004"
    )
  ScalaInlineInfo: length = 0x27 (unknown attribute)
   01 00 00 07 00 22 00 1B 01 00 1C 00 1D 00 00 1A
   00 1B 01 00 13 00 0C 00 00 10 00 11 01 00 0B 00
   0C 00 00 0D 00 0E 00
  ScalaSig: length = 0x3 (unknown attribute)
   05 02 00
