Classfile /Users/mw/Projects/slang-braindump/.jar/jar11/assemble/slang-braindump/assemble/content/com/zaxxer/nuprocess/osx/LibKevent$TimeSpec.class
  Last modified May 29, 2022; size 666 bytes
  SHA-256 checksum e2682a57838a0d615339c271600bb2802232e54643be1fe920b1d8832e1c735a
  Compiled from "LibKevent.java"
public class com.zaxxer.nuprocess.osx.LibKevent$TimeSpec extends com.sun.jna.Structure
  minor version: 0
  major version: 51
  flags: (0x0021) ACC_PUBLIC, ACC_SUPER
  this_class: #6                          // com/zaxxer/nuprocess/osx/LibKevent$TimeSpec
  super_class: #7                         // com/sun/jna/Structure
  interfaces: 0, fields: 2, methods: 2, attributes: 2
Constant pool:
   #1 = Methodref          #7.#24         // com/sun/jna/Structure."<init>":()V
   #2 = Class              #25            // java/lang/String
   #3 = String             #8             // tv_sec
   #4 = String             #10            // tv_nsec
   #5 = Methodref          #26.#27        // java/util/Arrays.asList:([Ljava/lang/Object;)Ljava/util/List;
   #6 = Class              #29            // com/zaxxer/nuprocess/osx/LibKevent$TimeSpec
   #7 = Class              #30            // com/sun/jna/Structure
   #8 = Utf8               tv_sec
   #9 = Utf8               J
  #10 = Utf8               tv_nsec
  #11 = Utf8               <init>
  #12 = Utf8               ()V
  #13 = Utf8               Code
  #14 = Utf8               LineNumberTable
  #15 = Utf8               LocalVariableTable
  #16 = Utf8               this
  #17 = Utf8               TimeSpec
  #18 = Utf8               InnerClasses
  #19 = Utf8               Lcom/zaxxer/nuprocess/osx/LibKevent$TimeSpec;
  #20 = Utf8               getFieldOrder
  #21 = Utf8               ()Ljava/util/List;
  #22 = Utf8               SourceFile
  #23 = Utf8               LibKevent.java
  #24 = NameAndType        #11:#12        // "<init>":()V
  #25 = Utf8               java/lang/String
  #26 = Class              #31            // java/util/Arrays
  #27 = NameAndType        #32:#33        // asList:([Ljava/lang/Object;)Ljava/util/List;
  #28 = Class              #34            // com/zaxxer/nuprocess/osx/LibKevent
  #29 = Utf8               com/zaxxer/nuprocess/osx/LibKevent$TimeSpec
  #30 = Utf8               com/sun/jna/Structure
  #31 = Utf8               java/util/Arrays
  #32 = Utf8               asList
  #33 = Utf8               ([Ljava/lang/Object;)Ljava/util/List;
  #34 = Utf8               com/zaxxer/nuprocess/osx/LibKevent
{
  public long tv_sec;
    descriptor: J
    flags: (0x0001) ACC_PUBLIC

  public long tv_nsec;
    descriptor: J
    flags: (0x0001) ACC_PUBLIC

  public com.zaxxer.nuprocess.osx.LibKevent$TimeSpec();
    descriptor: ()V
    flags: (0x0001) ACC_PUBLIC
    Code:
      stack=1, locals=1, args_size=1
         0: aload_0
         1: invokespecial #1                  // Method com/sun/jna/Structure."<init>":()V
         4: return
      LineNumberTable:
        line 41: 0
      LocalVariableTable:
        Start  Length  Slot  Name   Signature
            0       5     0  this   Lcom/zaxxer/nuprocess/osx/LibKevent$TimeSpec;

  protected java.util.List getFieldOrder();
    descriptor: ()Ljava/util/List;
    flags: (0x0004) ACC_PROTECTED
    Code:
      stack=4, locals=1, args_size=1
         0: iconst_2
         1: anewarray     #2                  // class java/lang/String
         4: dup
         5: iconst_0
         6: ldc           #3                  // String tv_sec
         8: aastore
         9: dup
        10: iconst_1
        11: ldc           #4                  // String tv_nsec
        13: aastore
        14: invokestatic  #5                  // Method java/util/Arrays.asList:([Ljava/lang/Object;)Ljava/util/List;
        17: areturn
      LineNumberTable:
        line 50: 0
      LocalVariableTable:
        Start  Length  Slot  Name   Signature
            0      18     0  this   Lcom/zaxxer/nuprocess/osx/LibKevent$TimeSpec;
}
SourceFile: "LibKevent.java"
InnerClasses:
  public static #17= #6 of #28;           // TimeSpec=class com/zaxxer/nuprocess/osx/LibKevent$TimeSpec of class com/zaxxer/nuprocess/osx/LibKevent
