Classfile /Users/mw/Projects/slang-braindump/.jar/jar11/assemble/slang-braindump/assemble/content/org/apache/commons/io/filefilter/EmptyFileFilter.class
  Last modified May 29, 2022; size 1136 bytes
  SHA-256 checksum ea35cd5dbf66424059d96d46581b0c998d4a2a886a4fc1fbfb13cc9eddf92744
  Compiled from "EmptyFileFilter.java"
public class org.apache.commons.io.filefilter.EmptyFileFilter extends org.apache.commons.io.filefilter.AbstractFileFilter implements java.io.Serializable
  minor version: 0
  major version: 52
  flags: (0x0021) ACC_PUBLIC, ACC_SUPER
  this_class: #5                          // org/apache/commons/io/filefilter/EmptyFileFilter
  super_class: #11                        // org/apache/commons/io/filefilter/AbstractFileFilter
  interfaces: 1, fields: 3, methods: 3, attributes: 1
Constant pool:
   #1 = Methodref          #11.#39        // org/apache/commons/io/filefilter/AbstractFileFilter."<init>":()V
   #2 = Methodref          #40.#41        // java/io/File.isDirectory:()Z
   #3 = Methodref          #40.#42        // java/io/File.listFiles:()[Ljava/io/File;
   #4 = Methodref          #40.#43        // java/io/File.length:()J
   #5 = Class              #44            // org/apache/commons/io/filefilter/EmptyFileFilter
   #6 = Methodref          #5.#39         // org/apache/commons/io/filefilter/EmptyFileFilter."<init>":()V
   #7 = Fieldref           #5.#45         // org/apache/commons/io/filefilter/EmptyFileFilter.EMPTY:Lorg/apache/commons/io/filefilter/IOFileFilter;
   #8 = Class              #46            // org/apache/commons/io/filefilter/NotFileFilter
   #9 = Methodref          #8.#47         // org/apache/commons/io/filefilter/NotFileFilter."<init>":(Lorg/apache/commons/io/filefilter/IOFileFilter;)V
  #10 = Fieldref           #5.#48         // org/apache/commons/io/filefilter/EmptyFileFilter.NOT_EMPTY:Lorg/apache/commons/io/filefilter/IOFileFilter;
  #11 = Class              #49            // org/apache/commons/io/filefilter/AbstractFileFilter
  #12 = Class              #50            // java/io/Serializable
  #13 = Utf8               serialVersionUID
  #14 = Utf8               J
  #15 = Utf8               ConstantValue
  #16 = Long               3631422087512832211l
  #18 = Utf8               EMPTY
  #19 = Utf8               Lorg/apache/commons/io/filefilter/IOFileFilter;
  #20 = Utf8               NOT_EMPTY
  #21 = Utf8               <init>
  #22 = Utf8               ()V
  #23 = Utf8               Code
  #24 = Utf8               LineNumberTable
  #25 = Utf8               LocalVariableTable
  #26 = Utf8               this
  #27 = Utf8               Lorg/apache/commons/io/filefilter/EmptyFileFilter;
  #28 = Utf8               accept
  #29 = Utf8               (Ljava/io/File;)Z
  #30 = Utf8               files
  #31 = Utf8               [Ljava/io/File;
  #32 = Utf8               file
  #33 = Utf8               Ljava/io/File;
  #34 = Utf8               StackMapTable
  #35 = Class              #31            // "[Ljava/io/File;"
  #36 = Utf8               <clinit>
  #37 = Utf8               SourceFile
  #38 = Utf8               EmptyFileFilter.java
  #39 = NameAndType        #21:#22        // "<init>":()V
  #40 = Class              #51            // java/io/File
  #41 = NameAndType        #52:#53        // isDirectory:()Z
  #42 = NameAndType        #54:#55        // listFiles:()[Ljava/io/File;
  #43 = NameAndType        #56:#57        // length:()J
  #44 = Utf8               org/apache/commons/io/filefilter/EmptyFileFilter
  #45 = NameAndType        #18:#19        // EMPTY:Lorg/apache/commons/io/filefilter/IOFileFilter;
  #46 = Utf8               org/apache/commons/io/filefilter/NotFileFilter
  #47 = NameAndType        #21:#58        // "<init>":(Lorg/apache/commons/io/filefilter/IOFileFilter;)V
  #48 = NameAndType        #20:#19        // NOT_EMPTY:Lorg/apache/commons/io/filefilter/IOFileFilter;
  #49 = Utf8               org/apache/commons/io/filefilter/AbstractFileFilter
  #50 = Utf8               java/io/Serializable
  #51 = Utf8               java/io/File
  #52 = Utf8               isDirectory
  #53 = Utf8               ()Z
  #54 = Utf8               listFiles
  #55 = Utf8               ()[Ljava/io/File;
  #56 = Utf8               length
  #57 = Utf8               ()J
  #58 = Utf8               (Lorg/apache/commons/io/filefilter/IOFileFilter;)V
{
  private static final long serialVersionUID;
    descriptor: J
    flags: (0x001a) ACC_PRIVATE, ACC_STATIC, ACC_FINAL
    ConstantValue: long 3631422087512832211l

  public static final org.apache.commons.io.filefilter.IOFileFilter EMPTY;
    descriptor: Lorg/apache/commons/io/filefilter/IOFileFilter;
    flags: (0x0019) ACC_PUBLIC, ACC_STATIC, ACC_FINAL

  public static final org.apache.commons.io.filefilter.IOFileFilter NOT_EMPTY;
    descriptor: Lorg/apache/commons/io/filefilter/IOFileFilter;
    flags: (0x0019) ACC_PUBLIC, ACC_STATIC, ACC_FINAL

  protected org.apache.commons.io.filefilter.EmptyFileFilter();
    descriptor: ()V
    flags: (0x0004) ACC_PROTECTED
    Code:
      stack=1, locals=1, args_size=1
         0: aload_0
         1: invokespecial #1                  // Method org/apache/commons/io/filefilter/AbstractFileFilter."<init>":()V
         4: return
      LineNumberTable:
        line 67: 0
        line 68: 4
      LocalVariableTable:
        Start  Length  Slot  Name   Signature
            0       5     0  this   Lorg/apache/commons/io/filefilter/EmptyFileFilter;

  public boolean accept(java.io.File);
    descriptor: (Ljava/io/File;)Z
    flags: (0x0001) ACC_PUBLIC
    Code:
      stack=4, locals=3, args_size=2
         0: aload_1
         1: invokevirtual #2                  // Method java/io/File.isDirectory:()Z
         4: ifeq          27
         7: aload_1
         8: invokevirtual #3                  // Method java/io/File.listFiles:()[Ljava/io/File;
        11: astore_2
        12: aload_2
        13: ifnull        21
        16: aload_2
        17: arraylength
        18: ifne          25
        21: iconst_1
        22: goto          26
        25: iconst_0
        26: ireturn
        27: aload_1
        28: invokevirtual #4                  // Method java/io/File.length:()J
        31: lconst_0
        32: lcmp
        33: ifne          40
        36: iconst_1
        37: goto          41
        40: iconst_0
        41: ireturn
      LineNumberTable:
        line 79: 0
        line 80: 7
        line 81: 12
        line 83: 27
      LocalVariableTable:
        Start  Length  Slot  Name   Signature
           12      15     2 files   [Ljava/io/File;
            0      42     0  this   Lorg/apache/commons/io/filefilter/EmptyFileFilter;
            0      42     1  file   Ljava/io/File;
      StackMapTable: number_of_entries = 6
        frame_type = 252 /* append */
          offset_delta = 21
          locals = [ class "[Ljava/io/File;" ]
        frame_type = 3 /* same */
        frame_type = 64 /* same_locals_1_stack_item */
          stack = [ int ]
        frame_type = 250 /* chop */
          offset_delta = 0
        frame_type = 12 /* same */
        frame_type = 64 /* same_locals_1_stack_item */
          stack = [ int ]

  static {};
    descriptor: ()V
    flags: (0x0008) ACC_STATIC
    Code:
      stack=3, locals=0, args_size=0
         0: new           #5                  // class org/apache/commons/io/filefilter/EmptyFileFilter
         3: dup
         4: invokespecial #6                  // Method "<init>":()V
         7: putstatic     #7                  // Field EMPTY:Lorg/apache/commons/io/filefilter/IOFileFilter;
        10: new           #8                  // class org/apache/commons/io/filefilter/NotFileFilter
        13: dup
        14: getstatic     #7                  // Field EMPTY:Lorg/apache/commons/io/filefilter/IOFileFilter;
        17: invokespecial #9                  // Method org/apache/commons/io/filefilter/NotFileFilter."<init>":(Lorg/apache/commons/io/filefilter/IOFileFilter;)V
        20: putstatic     #10                 // Field NOT_EMPTY:Lorg/apache/commons/io/filefilter/IOFileFilter;
        23: return
      LineNumberTable:
        line 59: 0
        line 62: 10
}
SourceFile: "EmptyFileFilter.java"
