Classfile /Users/mw/Projects/slang-braindump/.jar/jar11/assemble/slang-braindump/assemble/content/org/sireum/project/DependencyManager$.class
  Last modified May 29, 2022; size 7493 bytes
  SHA-256 checksum 3be5f979e7d892ecca27bb1a6dcf193b675f964d2e986f2018b70bf6e80ce819
  Compiled from "DependencyManager.scala"
public final class org.sireum.project.DependencyManager$
  minor version: 0
  major version: 52
  flags: (0x0031) ACC_PUBLIC, ACC_FINAL, ACC_SUPER
  this_class: #2                          // org/sireum/project/DependencyManager$
  super_class: #4                         // java/lang/Object
  interfaces: 0, fields: 15, methods: 20, attributes: 4
Constant pool:
    #1 = Utf8               org/sireum/project/DependencyManager$
    #2 = Class              #1            // org/sireum/project/DependencyManager$
    #3 = Utf8               java/lang/Object
    #4 = Class              #3            // java/lang/Object
    #5 = Utf8               DependencyManager.scala
    #6 = Utf8               org/sireum/$internal/PackageTrait$ISZ$
    #7 = Class              #6            // org/sireum/$internal/PackageTrait$ISZ$
    #8 = Utf8               org/sireum/$internal/PackageTrait
    #9 = Class              #8            // org/sireum/$internal/PackageTrait
   #10 = Utf8               ISZ$
   #11 = Utf8               org/sireum/CoursierClassifier$Default$
   #12 = Class              #11           // org/sireum/CoursierClassifier$Default$
   #13 = Utf8               org/sireum/CoursierClassifier
   #14 = Class              #13           // org/sireum/CoursierClassifier
   #15 = Utf8               Default$
   #16 = Utf8               org/sireum/CoursierClassifier$Javadoc$
   #17 = Class              #16           // org/sireum/CoursierClassifier$Javadoc$
   #18 = Utf8               Javadoc$
   #19 = Utf8               org/sireum/CoursierClassifier$Sources$
   #20 = Class              #19           // org/sireum/CoursierClassifier$Sources$
   #21 = Utf8               Sources$
   #22 = Utf8               org/sireum/CoursierClassifier$Type
   #23 = Class              #22           // org/sireum/CoursierClassifier$Type
   #24 = Utf8               Type
   #25 = Utf8               org/sireum/Os$Path
   #26 = Class              #25           // org/sireum/Os$Path
   #27 = Utf8               org/sireum/Os
   #28 = Class              #27           // org/sireum/Os
   #29 = Utf8               Path
   #30 = Utf8               MODULE$
   #31 = Utf8               Lorg/sireum/project/DependencyManager$;
   #32 = Utf8               javaKey
   #33 = Utf8               Ljava/lang/String;
   #34 = Utf8               jbrKey
   #35 = Utf8               scalacPluginKey
   #36 = Utf8               scalaKey
   #37 = Utf8               scalaJsKey
   #38 = Utf8               scalaTestKey
   #39 = Utf8               macrosKey
   #40 = Utf8               testKey
   #41 = Utf8               libraryKey
   #42 = Utf8               librarySharedKey
   #43 = Utf8               jarSuffix
   #44 = Utf8               sourceJarSuffix
   #45 = Utf8               docJarSuffix
   #46 = Utf8               ignoredLibraryNames
   #47 = Utf8               Lorg/sireum/HashSet;
   #48 = Utf8               Lorg/sireum/HashSet<Lorg/sireum/String;>;
   #49 = Utf8               <clinit>
   #50 = Utf8               ()V
   #51 = Utf8               <init>
   #52 = NameAndType        #51:#50       // "<init>":()V
   #53 = Methodref          #2.#52        // org/sireum/project/DependencyManager$."<init>":()V
   #54 = NameAndType        #30:#31       // MODULE$:Lorg/sireum/project/DependencyManager$;
   #55 = Fieldref           #2.#54        // org/sireum/project/DependencyManager$.MODULE$:Lorg/sireum/project/DependencyManager$;
   #56 = Utf8               org/sireum/String$
   #57 = Class              #56           // org/sireum/String$
   #58 = Utf8               Lorg/sireum/String$;
   #59 = NameAndType        #30:#58       // MODULE$:Lorg/sireum/String$;
   #60 = Fieldref           #57.#59       // org/sireum/String$.MODULE$:Lorg/sireum/String$;
   #61 = Utf8               org.sireum.version.zulu
   #62 = String             #61           // org.sireum.version.zulu
   #63 = Utf8               apply
   #64 = Utf8               (Ljava/lang/String;)Ljava/lang/String;
   #65 = NameAndType        #63:#64       // apply:(Ljava/lang/String;)Ljava/lang/String;
   #66 = Methodref          #57.#65       // org/sireum/String$.apply:(Ljava/lang/String;)Ljava/lang/String;
   #67 = NameAndType        #32:#33       // javaKey:Ljava/lang/String;
   #68 = Fieldref           #2.#67        // org/sireum/project/DependencyManager$.javaKey:Ljava/lang/String;
   #69 = Utf8               org.sireum.version.jbr
   #70 = String             #69           // org.sireum.version.jbr
   #71 = NameAndType        #34:#33       // jbrKey:Ljava/lang/String;
   #72 = Fieldref           #2.#71        // org/sireum/project/DependencyManager$.jbrKey:Ljava/lang/String;
   #73 = Utf8               org.sireum::scalac-plugin:
   #74 = String             #73           // org.sireum::scalac-plugin:
   #75 = NameAndType        #35:#33       // scalacPluginKey:Ljava/lang/String;
   #76 = Fieldref           #2.#75        // org/sireum/project/DependencyManager$.scalacPluginKey:Ljava/lang/String;
   #77 = Utf8               org.scala-lang:scala-library:
   #78 = String             #77           // org.scala-lang:scala-library:
   #79 = NameAndType        #36:#33       // scalaKey:Ljava/lang/String;
   #80 = Fieldref           #2.#79        // org/sireum/project/DependencyManager$.scalaKey:Ljava/lang/String;
   #81 = Utf8               org.scala-js:::scalajs-compiler:
   #82 = String             #81           // org.scala-js:::scalajs-compiler:
   #83 = NameAndType        #37:#33       // scalaJsKey:Ljava/lang/String;
   #84 = Fieldref           #2.#83        // org/sireum/project/DependencyManager$.scalaJsKey:Ljava/lang/String;
   #85 = Utf8               org.scalatest::scalatest::
   #86 = String             #85           // org.scalatest::scalatest::
   #87 = NameAndType        #38:#33       // scalaTestKey:Ljava/lang/String;
   #88 = Fieldref           #2.#87        // org/sireum/project/DependencyManager$.scalaTestKey:Ljava/lang/String;
   #89 = Utf8               org.sireum.kekinian::macros:
   #90 = String             #89           // org.sireum.kekinian::macros:
   #91 = NameAndType        #39:#33       // macrosKey:Ljava/lang/String;
   #92 = Fieldref           #2.#91        // org/sireum/project/DependencyManager$.macrosKey:Ljava/lang/String;
   #93 = Utf8               org.sireum.kekinian::test:
   #94 = String             #93           // org.sireum.kekinian::test:
   #95 = NameAndType        #40:#33       // testKey:Ljava/lang/String;
   #96 = Fieldref           #2.#95        // org/sireum/project/DependencyManager$.testKey:Ljava/lang/String;
   #97 = Utf8               org.sireum.kekinian::library:
   #98 = String             #97           // org.sireum.kekinian::library:
   #99 = NameAndType        #41:#33       // libraryKey:Ljava/lang/String;
  #100 = Fieldref           #2.#99        // org/sireum/project/DependencyManager$.libraryKey:Ljava/lang/String;
  #101 = Utf8               org.sireum.kekinian::library-shared:
  #102 = String             #101          // org.sireum.kekinian::library-shared:
  #103 = NameAndType        #42:#33       // librarySharedKey:Ljava/lang/String;
  #104 = Fieldref           #2.#103       // org/sireum/project/DependencyManager$.librarySharedKey:Ljava/lang/String;
  #105 = Utf8               .jar
  #106 = String             #105          // .jar
  #107 = NameAndType        #43:#33       // jarSuffix:Ljava/lang/String;
  #108 = Fieldref           #2.#107       // org/sireum/project/DependencyManager$.jarSuffix:Ljava/lang/String;
  #109 = Utf8               -sources.jar
  #110 = String             #109          // -sources.jar
  #111 = NameAndType        #44:#33       // sourceJarSuffix:Ljava/lang/String;
  #112 = Fieldref           #2.#111       // org/sireum/project/DependencyManager$.sourceJarSuffix:Ljava/lang/String;
  #113 = Utf8               -javadoc.jar
  #114 = String             #113          // -javadoc.jar
  #115 = NameAndType        #45:#33       // docJarSuffix:Ljava/lang/String;
  #116 = Fieldref           #2.#115       // org/sireum/project/DependencyManager$.docJarSuffix:Ljava/lang/String;
  #117 = Utf8               org/sireum/HashSet$
  #118 = Class              #117          // org/sireum/HashSet$
  #119 = Utf8               Lorg/sireum/HashSet$;
  #120 = NameAndType        #30:#119      // MODULE$:Lorg/sireum/HashSet$;
  #121 = Fieldref           #118.#120     // org/sireum/HashSet$.MODULE$:Lorg/sireum/HashSet$;
  #122 = Utf8               org/sireum/package$
  #123 = Class              #122          // org/sireum/package$
  #124 = Utf8               Lorg/sireum/package$;
  #125 = NameAndType        #30:#124      // MODULE$:Lorg/sireum/package$;
  #126 = Fieldref           #123.#125     // org/sireum/package$.MODULE$:Lorg/sireum/package$;
  #127 = Utf8               ISZ
  #128 = Utf8               ()Lorg/sireum/$internal/PackageTrait$ISZ$;
  #129 = NameAndType        #127:#128     // ISZ:()Lorg/sireum/$internal/PackageTrait$ISZ$;
  #130 = Methodref          #123.#129     // org/sireum/package$.ISZ:()Lorg/sireum/$internal/PackageTrait$ISZ$;
  #131 = Utf8               scala/runtime/ScalaRunTime$
  #132 = Class              #131          // scala/runtime/ScalaRunTime$
  #133 = Utf8               Lscala/runtime/ScalaRunTime$;
  #134 = NameAndType        #30:#133      // MODULE$:Lscala/runtime/ScalaRunTime$;
  #135 = Fieldref           #132.#134     // scala/runtime/ScalaRunTime$.MODULE$:Lscala/runtime/ScalaRunTime$;
  #136 = Utf8               org/sireum/String
  #137 = Class              #136          // org/sireum/String
  #138 = Utf8               org.scala-lang.scala-library
  #139 = String             #138          // org.scala-lang.scala-library
  #140 = Utf8               (Ljava/lang/String;)V
  #141 = NameAndType        #51:#140      // "<init>":(Ljava/lang/String;)V
  #142 = Methodref          #137.#141     // org/sireum/String."<init>":(Ljava/lang/String;)V
  #143 = Utf8               org.scala-lang.scala-reflect
  #144 = String             #143          // org.scala-lang.scala-reflect
  #145 = Utf8               org.scala-lang.scala-compiler
  #146 = String             #145          // org.scala-lang.scala-compiler
  #147 = Utf8               genericWrapArray
  #148 = Utf8               (Ljava/lang/Object;)Lscala/collection/immutable/ArraySeq;
  #149 = NameAndType        #147:#148     // genericWrapArray:(Ljava/lang/Object;)Lscala/collection/immutable/ArraySeq;
  #150 = Methodref          #132.#149     // scala/runtime/ScalaRunTime$.genericWrapArray:(Ljava/lang/Object;)Lscala/collection/immutable/ArraySeq;
  #151 = Utf8               (Lscala/collection/immutable/Seq;)Lorg/sireum/IS;
  #152 = NameAndType        #63:#151      // apply:(Lscala/collection/immutable/Seq;)Lorg/sireum/IS;
  #153 = Methodref          #7.#152       // org/sireum/$internal/PackageTrait$ISZ$.apply:(Lscala/collection/immutable/Seq;)Lorg/sireum/IS;
  #154 = Utf8               $plus$plus
  #155 = Utf8               (Lorg/sireum/IS;)Lorg/sireum/HashSet;
  #156 = NameAndType        #154:#155     // $plus$plus:(Lorg/sireum/IS;)Lorg/sireum/HashSet;
  #157 = Methodref          #118.#156     // org/sireum/HashSet$.$plus$plus:(Lorg/sireum/IS;)Lorg/sireum/HashSet;
  #158 = NameAndType        #46:#47       // ignoredLibraryNames:Lorg/sireum/HashSet;
  #159 = Fieldref           #2.#158       // org/sireum/project/DependencyManager$.ignoredLibraryNames:Lorg/sireum/HashSet;
  #160 = Utf8               ()Ljava/lang/String;
  #161 = Utf8               this
  #162 = Utf8               ()Lorg/sireum/HashSet;
  #163 = Utf8               ()Lorg/sireum/HashSet<Lorg/sireum/String;>;
  #164 = Utf8               buildClassifiers
  #165 = Utf8               (ZZ)Lorg/sireum/IS;
  #166 = Utf8               (ZZ)Lorg/sireum/IS<Lorg/sireum/Z;Lorg/sireum/CoursierClassifier$Type;>;
  #167 = Utf8               withSource
  #168 = Utf8               withDoc
  #169 = Utf8               Lorg/sireum/CoursierClassifier$Default$;
  #170 = NameAndType        #30:#169      // MODULE$:Lorg/sireum/CoursierClassifier$Default$;
  #171 = Fieldref           #12.#170      // org/sireum/CoursierClassifier$Default$.MODULE$:Lorg/sireum/CoursierClassifier$Default$;
  #172 = Utf8               [Ljava/lang/Object;
  #173 = Class              #172          // "[Ljava/lang/Object;"
  #174 = Utf8               wrapRefArray
  #175 = Utf8               ([Ljava/lang/Object;)Lscala/collection/immutable/ArraySeq;
  #176 = NameAndType        #174:#175     // wrapRefArray:([Ljava/lang/Object;)Lscala/collection/immutable/ArraySeq;
  #177 = Methodref          #132.#176     // scala/runtime/ScalaRunTime$.wrapRefArray:([Ljava/lang/Object;)Lscala/collection/immutable/ArraySeq;
  #178 = Utf8               org/sireum/B$
  #179 = Class              #178          // org/sireum/B$
  #180 = Utf8               Lorg/sireum/B$;
  #181 = NameAndType        #30:#180      // MODULE$:Lorg/sireum/B$;
  #182 = Fieldref           #179.#181     // org/sireum/B$.MODULE$:Lorg/sireum/B$;
  #183 = Utf8               $4B
  #184 = Utf8               (Z)Z
  #185 = NameAndType        #183:#184     // $4B:(Z)Z
  #186 = Methodref          #179.#185     // org/sireum/B$.$4B:(Z)Z
  #187 = Utf8               Lorg/sireum/CoursierClassifier$Sources$;
  #188 = NameAndType        #30:#187      // MODULE$:Lorg/sireum/CoursierClassifier$Sources$;
  #189 = Fieldref           #20.#188      // org/sireum/CoursierClassifier$Sources$.MODULE$:Lorg/sireum/CoursierClassifier$Sources$;
  #190 = Utf8               org/sireum/IS
  #191 = Class              #190          // org/sireum/IS
  #192 = Utf8               $colon$plus
  #193 = Utf8               (Ljava/lang/Object;)Lorg/sireum/IS;
  #194 = NameAndType        #192:#193     // $colon$plus:(Ljava/lang/Object;)Lorg/sireum/IS;
  #195 = Methodref          #191.#194     // org/sireum/IS.$colon$plus:(Ljava/lang/Object;)Lorg/sireum/IS;
  #196 = Utf8               Lorg/sireum/CoursierClassifier$Javadoc$;
  #197 = NameAndType        #30:#196      // MODULE$:Lorg/sireum/CoursierClassifier$Javadoc$;
  #198 = Fieldref           #17.#197      // org/sireum/CoursierClassifier$Javadoc$.MODULE$:Lorg/sireum/CoursierClassifier$Javadoc$;
  #199 = Utf8               classifiers
  #200 = Utf8               Lorg/sireum/IS;
  #201 = Utf8               Z
  #202 = Utf8               libName
  #203 = Utf8               (Lorg/sireum/CoursierFileInfo;)Ljava/lang/String;
  #204 = Utf8               cif
  #205 = Utf8               java/lang/StringBuilder
  #206 = Class              #205          // java/lang/StringBuilder
  #207 = Integer            1
  #208 = Utf8               (I)V
  #209 = NameAndType        #51:#208      // "<init>":(I)V
  #210 = Methodref          #206.#209     // java/lang/StringBuilder."<init>":(I)V
  #211 = Utf8               org/sireum/CoursierFileInfo
  #212 = Class              #211          // org/sireum/CoursierFileInfo
  #213 = Utf8               org
  #214 = NameAndType        #213:#160     // org:()Ljava/lang/String;
  #215 = Methodref          #212.#214     // org/sireum/CoursierFileInfo.org:()Ljava/lang/String;
  #216 = Utf8               append
  #217 = Utf8               (Ljava/lang/Object;)Ljava/lang/StringBuilder;
  #218 = NameAndType        #216:#217     // append:(Ljava/lang/Object;)Ljava/lang/StringBuilder;
  #219 = Methodref          #206.#218     // java/lang/StringBuilder.append:(Ljava/lang/Object;)Ljava/lang/StringBuilder;
  #220 = Utf8               .
  #221 = String             #220          // .
  #222 = Utf8               (Ljava/lang/String;)Ljava/lang/StringBuilder;
  #223 = NameAndType        #216:#222     // append:(Ljava/lang/String;)Ljava/lang/StringBuilder;
  #224 = Methodref          #206.#223     // java/lang/StringBuilder.append:(Ljava/lang/String;)Ljava/lang/StringBuilder;
  #225 = Utf8               module
  #226 = NameAndType        #225:#160     // module:()Ljava/lang/String;
  #227 = Methodref          #212.#226     // org/sireum/CoursierFileInfo.module:()Ljava/lang/String;
  #228 = Utf8               toString
  #229 = NameAndType        #228:#160     // toString:()Ljava/lang/String;
  #230 = Methodref          #206.#229     // java/lang/StringBuilder.toString:()Ljava/lang/String;
  #231 = Utf8               Lorg/sireum/CoursierFileInfo;
  #232 = Utf8               (Lorg/sireum/project/Project;Lorg/sireum/HashSMap;ZZZLorg/sireum/Os$Path;Lorg/sireum/Os$Path;Lorg/sireum/Os$Path;Lorg/sireum/Option;)Lorg/sireum/project/DependencyManager;
  #233 = Utf8               (Lorg/sireum/project/Project;Lorg/sireum/HashSMap<Lorg/sireum/String;Lorg/sireum/String;>;ZZZLorg/sireum/Os$Path;Lorg/sireum/Os$Path;Lorg/sireum/Os$Path;Lorg/sireum/Option<Lorg/sireum/Os$Path;>;)Lorg/sireum/project/DependencyManager;
  #234 = Utf8               project
  #235 = Utf8               versions
  #236 = Utf8               isJs
  #237 = Utf8               javaHome
  #238 = Utf8               scalaHome
  #239 = Utf8               sireumHome
  #240 = Utf8               cacheOpt
  #241 = Utf8               org/sireum/project/DependencyManager
  #242 = Class              #241          // org/sireum/project/DependencyManager
  #243 = Utf8               (Lorg/sireum/project/Project;Lorg/sireum/HashSMap;ZZZLorg/sireum/Os$Path;Lorg/sireum/Os$Path;Lorg/sireum/Os$Path;Lorg/sireum/Option;)V
  #244 = NameAndType        #51:#243      // "<init>":(Lorg/sireum/project/Project;Lorg/sireum/HashSMap;ZZZLorg/sireum/Os$Path;Lorg/sireum/Os$Path;Lorg/sireum/Os$Path;Lorg/sireum/Option;)V
  #245 = Methodref          #242.#244     // org/sireum/project/DependencyManager."<init>":(Lorg/sireum/project/Project;Lorg/sireum/HashSMap;ZZZLorg/sireum/Os$Path;Lorg/sireum/Os$Path;Lorg/sireum/Os$Path;Lorg/sireum/Option;)V
  #246 = Utf8               Lorg/sireum/project/Project;
  #247 = Utf8               Lorg/sireum/HashSMap;
  #248 = Utf8               Lorg/sireum/Os$Path;
  #249 = Utf8               Lorg/sireum/Option;
  #250 = Utf8               unapply
  #251 = Utf8               (Lorg/sireum/project/DependencyManager;)Lscala/Some;
  #252 = Utf8               (Lorg/sireum/project/DependencyManager;)Lscala/Some<Lscala/Tuple9<Lorg/sireum/project/Project;Lorg/sireum/HashSMap<Lorg/sireum/String;Lorg/sireum/String;>;Lorg/sireum/B;Lorg/sireum/B;Lorg/sireum/B;Lorg/sireum/Os$Path;Lorg/sireum/Os$Path;Lorg/sireum/Os$Path;Lorg/sireum/Option<Lorg/sireum/Os$Path;>;>;>;
  #253 = Utf8               o
  #254 = Utf8               scala/Some
  #255 = Class              #254          // scala/Some
  #256 = Utf8               scala/Tuple9
  #257 = Class              #256          // scala/Tuple9
  #258 = Utf8               org/sireum/helper$
  #259 = Class              #258          // org/sireum/helper$
  #260 = Utf8               Lorg/sireum/helper$;
  #261 = NameAndType        #30:#260      // MODULE$:Lorg/sireum/helper$;
  #262 = Fieldref           #259.#261     // org/sireum/helper$.MODULE$:Lorg/sireum/helper$;
  #263 = Utf8               ()Lorg/sireum/project/Project;
  #264 = NameAndType        #234:#263     // project:()Lorg/sireum/project/Project;
  #265 = Methodref          #242.#264     // org/sireum/project/DependencyManager.project:()Lorg/sireum/project/Project;
  #266 = Utf8               clone
  #267 = Utf8               (Ljava/lang/Object;)Ljava/lang/Object;
  #268 = NameAndType        #266:#267     // clone:(Ljava/lang/Object;)Ljava/lang/Object;
  #269 = Methodref          #259.#268     // org/sireum/helper$.clone:(Ljava/lang/Object;)Ljava/lang/Object;
  #270 = Utf8               ()Lorg/sireum/HashSMap;
  #271 = NameAndType        #235:#270     // versions:()Lorg/sireum/HashSMap;
  #272 = Methodref          #242.#271     // org/sireum/project/DependencyManager.versions:()Lorg/sireum/HashSMap;
  #273 = Utf8               org/sireum/B
  #274 = Class              #273          // org/sireum/B
  #275 = Utf8               ()Z
  #276 = NameAndType        #236:#275     // isJs:()Z
  #277 = Methodref          #242.#276     // org/sireum/project/DependencyManager.isJs:()Z
  #278 = Utf8               (Z)V
  #279 = NameAndType        #51:#278      // "<init>":(Z)V
  #280 = Methodref          #274.#279     // org/sireum/B."<init>":(Z)V
  #281 = NameAndType        #167:#275     // withSource:()Z
  #282 = Methodref          #242.#281     // org/sireum/project/DependencyManager.withSource:()Z
  #283 = NameAndType        #168:#275     // withDoc:()Z
  #284 = Methodref          #242.#283     // org/sireum/project/DependencyManager.withDoc:()Z
  #285 = Utf8               ()Lorg/sireum/Os$Path;
  #286 = NameAndType        #237:#285     // javaHome:()Lorg/sireum/Os$Path;
  #287 = Methodref          #242.#286     // org/sireum/project/DependencyManager.javaHome:()Lorg/sireum/Os$Path;
  #288 = NameAndType        #238:#285     // scalaHome:()Lorg/sireum/Os$Path;
  #289 = Methodref          #242.#288     // org/sireum/project/DependencyManager.scalaHome:()Lorg/sireum/Os$Path;
  #290 = NameAndType        #239:#285     // sireumHome:()Lorg/sireum/Os$Path;
  #291 = Methodref          #242.#290     // org/sireum/project/DependencyManager.sireumHome:()Lorg/sireum/Os$Path;
  #292 = Utf8               ()Lorg/sireum/Option;
  #293 = NameAndType        #240:#292     // cacheOpt:()Lorg/sireum/Option;
  #294 = Methodref          #242.#293     // org/sireum/project/DependencyManager.cacheOpt:()Lorg/sireum/Option;
  #295 = Utf8               (Ljava/lang/Object;Ljava/lang/Object;Ljava/lang/Object;Ljava/lang/Object;Ljava/lang/Object;Ljava/lang/Object;Ljava/lang/Object;Ljava/lang/Object;Ljava/lang/Object;)V
  #296 = NameAndType        #51:#295      // "<init>":(Ljava/lang/Object;Ljava/lang/Object;Ljava/lang/Object;Ljava/lang/Object;Ljava/lang/Object;Ljava/lang/Object;Ljava/lang/Object;Ljava/lang/Object;Ljava/lang/Object;)V
  #297 = Methodref          #257.#296     // scala/Tuple9."<init>":(Ljava/lang/Object;Ljava/lang/Object;Ljava/lang/Object;Ljava/lang/Object;Ljava/lang/Object;Ljava/lang/Object;Ljava/lang/Object;Ljava/lang/Object;Ljava/lang/Object;)V
  #298 = Utf8               (Ljava/lang/Object;)V
  #299 = NameAndType        #51:#298      // "<init>":(Ljava/lang/Object;)V
  #300 = Methodref          #255.#299     // scala/Some."<init>":(Ljava/lang/Object;)V
  #301 = Utf8               Lorg/sireum/project/DependencyManager;
  #302 = Methodref          #4.#52        // java/lang/Object."<init>":()V
  #303 = Utf8               Signature
  #304 = Utf8               Code
  #305 = Utf8               LineNumberTable
  #306 = Utf8               LocalVariableTable
  #307 = Utf8               StackMapTable
  #308 = Utf8               MethodParameters
  #309 = Utf8               InnerClasses
  #310 = Utf8               SourceFile
  #311 = Utf8               ScalaInlineInfo
  #312 = Utf8               Scala
{
  public static final org.sireum.project.DependencyManager$ MODULE$;
    descriptor: Lorg/sireum/project/DependencyManager$;
    flags: (0x0019) ACC_PUBLIC, ACC_STATIC, ACC_FINAL

  private static final java.lang.String javaKey;
    descriptor: Ljava/lang/String;
    flags: (0x001a) ACC_PRIVATE, ACC_STATIC, ACC_FINAL

  private static final java.lang.String jbrKey;
    descriptor: Ljava/lang/String;
    flags: (0x001a) ACC_PRIVATE, ACC_STATIC, ACC_FINAL

  private static final java.lang.String scalacPluginKey;
    descriptor: Ljava/lang/String;
    flags: (0x001a) ACC_PRIVATE, ACC_STATIC, ACC_FINAL

  private static final java.lang.String scalaKey;
    descriptor: Ljava/lang/String;
    flags: (0x001a) ACC_PRIVATE, ACC_STATIC, ACC_FINAL

  private static final java.lang.String scalaJsKey;
    descriptor: Ljava/lang/String;
    flags: (0x001a) ACC_PRIVATE, ACC_STATIC, ACC_FINAL

  private static final java.lang.String scalaTestKey;
    descriptor: Ljava/lang/String;
    flags: (0x001a) ACC_PRIVATE, ACC_STATIC, ACC_FINAL

  private static final java.lang.String macrosKey;
    descriptor: Ljava/lang/String;
    flags: (0x001a) ACC_PRIVATE, ACC_STATIC, ACC_FINAL

  private static final java.lang.String testKey;
    descriptor: Ljava/lang/String;
    flags: (0x001a) ACC_PRIVATE, ACC_STATIC, ACC_FINAL

  private static final java.lang.String libraryKey;
    descriptor: Ljava/lang/String;
    flags: (0x001a) ACC_PRIVATE, ACC_STATIC, ACC_FINAL

  private static final java.lang.String librarySharedKey;
    descriptor: Ljava/lang/String;
    flags: (0x001a) ACC_PRIVATE, ACC_STATIC, ACC_FINAL

  private static final java.lang.String jarSuffix;
    descriptor: Ljava/lang/String;
    flags: (0x001a) ACC_PRIVATE, ACC_STATIC, ACC_FINAL

  private static final java.lang.String sourceJarSuffix;
    descriptor: Ljava/lang/String;
    flags: (0x001a) ACC_PRIVATE, ACC_STATIC, ACC_FINAL

  private static final java.lang.String docJarSuffix;
    descriptor: Ljava/lang/String;
    flags: (0x001a) ACC_PRIVATE, ACC_STATIC, ACC_FINAL

  private static final org.sireum.HashSet<org.sireum.String> ignoredLibraryNames;
    descriptor: Lorg/sireum/HashSet;
    flags: (0x001a) ACC_PRIVATE, ACC_STATIC, ACC_FINAL
    Signature: #48                          // Lorg/sireum/HashSet<Lorg/sireum/String;>;

  public static {};
    descriptor: ()V
    flags: (0x0009) ACC_PUBLIC, ACC_STATIC
    Code:
      stack=10, locals=0, args_size=0
         0: new           #2                  // class org/sireum/project/DependencyManager$
         3: dup
         4: invokespecial #53                 // Method "<init>":()V
         7: putstatic     #55                 // Field MODULE$:Lorg/sireum/project/DependencyManager$;
        10: getstatic     #60                 // Field org/sireum/String$.MODULE$:Lorg/sireum/String$;
        13: ldc           #62                 // String org.sireum.version.zulu
        15: invokevirtual #66                 // Method org/sireum/String$.apply:(Ljava/lang/String;)Ljava/lang/String;
        18: putstatic     #68                 // Field javaKey:Ljava/lang/String;
        21: getstatic     #60                 // Field org/sireum/String$.MODULE$:Lorg/sireum/String$;
        24: ldc           #70                 // String org.sireum.version.jbr
        26: invokevirtual #66                 // Method org/sireum/String$.apply:(Ljava/lang/String;)Ljava/lang/String;
        29: putstatic     #72                 // Field jbrKey:Ljava/lang/String;
        32: getstatic     #60                 // Field org/sireum/String$.MODULE$:Lorg/sireum/String$;
        35: ldc           #74                 // String org.sireum::scalac-plugin:
        37: invokevirtual #66                 // Method org/sireum/String$.apply:(Ljava/lang/String;)Ljava/lang/String;
        40: putstatic     #76                 // Field scalacPluginKey:Ljava/lang/String;
        43: getstatic     #60                 // Field org/sireum/String$.MODULE$:Lorg/sireum/String$;
        46: ldc           #78                 // String org.scala-lang:scala-library:
        48: invokevirtual #66                 // Method org/sireum/String$.apply:(Ljava/lang/String;)Ljava/lang/String;
        51: putstatic     #80                 // Field scalaKey:Ljava/lang/String;
        54: getstatic     #60                 // Field org/sireum/String$.MODULE$:Lorg/sireum/String$;
        57: ldc           #82                 // String org.scala-js:::scalajs-compiler:
        59: invokevirtual #66                 // Method org/sireum/String$.apply:(Ljava/lang/String;)Ljava/lang/String;
        62: putstatic     #84                 // Field scalaJsKey:Ljava/lang/String;
        65: getstatic     #60                 // Field org/sireum/String$.MODULE$:Lorg/sireum/String$;
        68: ldc           #86                 // String org.scalatest::scalatest::
        70: invokevirtual #66                 // Method org/sireum/String$.apply:(Ljava/lang/String;)Ljava/lang/String;
        73: putstatic     #88                 // Field scalaTestKey:Ljava/lang/String;
        76: getstatic     #60                 // Field org/sireum/String$.MODULE$:Lorg/sireum/String$;
        79: ldc           #90                 // String org.sireum.kekinian::macros:
        81: invokevirtual #66                 // Method org/sireum/String$.apply:(Ljava/lang/String;)Ljava/lang/String;
        84: putstatic     #92                 // Field macrosKey:Ljava/lang/String;
        87: getstatic     #60                 // Field org/sireum/String$.MODULE$:Lorg/sireum/String$;
        90: ldc           #94                 // String org.sireum.kekinian::test:
        92: invokevirtual #66                 // Method org/sireum/String$.apply:(Ljava/lang/String;)Ljava/lang/String;
        95: putstatic     #96                 // Field testKey:Ljava/lang/String;
        98: getstatic     #60                 // Field org/sireum/String$.MODULE$:Lorg/sireum/String$;
       101: ldc           #98                 // String org.sireum.kekinian::library:
       103: invokevirtual #66                 // Method org/sireum/String$.apply:(Ljava/lang/String;)Ljava/lang/String;
       106: putstatic     #100                // Field libraryKey:Ljava/lang/String;
       109: getstatic     #60                 // Field org/sireum/String$.MODULE$:Lorg/sireum/String$;
       112: ldc           #102                // String org.sireum.kekinian::library-shared:
       114: invokevirtual #66                 // Method org/sireum/String$.apply:(Ljava/lang/String;)Ljava/lang/String;
       117: putstatic     #104                // Field librarySharedKey:Ljava/lang/String;
       120: getstatic     #60                 // Field org/sireum/String$.MODULE$:Lorg/sireum/String$;
       123: ldc           #106                // String .jar
       125: invokevirtual #66                 // Method org/sireum/String$.apply:(Ljava/lang/String;)Ljava/lang/String;
       128: putstatic     #108                // Field jarSuffix:Ljava/lang/String;
       131: getstatic     #60                 // Field org/sireum/String$.MODULE$:Lorg/sireum/String$;
       134: ldc           #110                // String -sources.jar
       136: invokevirtual #66                 // Method org/sireum/String$.apply:(Ljava/lang/String;)Ljava/lang/String;
       139: putstatic     #112                // Field sourceJarSuffix:Ljava/lang/String;
       142: getstatic     #60                 // Field org/sireum/String$.MODULE$:Lorg/sireum/String$;
       145: ldc           #114                // String -javadoc.jar
       147: invokevirtual #66                 // Method org/sireum/String$.apply:(Ljava/lang/String;)Ljava/lang/String;
       150: putstatic     #116                // Field docJarSuffix:Ljava/lang/String;
       153: getstatic     #121                // Field org/sireum/HashSet$.MODULE$:Lorg/sireum/HashSet$;
       156: getstatic     #126                // Field org/sireum/package$.MODULE$:Lorg/sireum/package$;
       159: invokevirtual #130                // Method org/sireum/package$.ISZ:()Lorg/sireum/$internal/PackageTrait$ISZ$;
       162: getstatic     #135                // Field scala/runtime/ScalaRunTime$.MODULE$:Lscala/runtime/ScalaRunTime$;
       165: iconst_3
       166: anewarray     #137                // class org/sireum/String
       169: dup
       170: iconst_0
       171: new           #137                // class org/sireum/String
       174: dup
       175: getstatic     #60                 // Field org/sireum/String$.MODULE$:Lorg/sireum/String$;
       178: ldc           #139                // String org.scala-lang.scala-library
       180: invokevirtual #66                 // Method org/sireum/String$.apply:(Ljava/lang/String;)Ljava/lang/String;
       183: invokespecial #142                // Method org/sireum/String."<init>":(Ljava/lang/String;)V
       186: aastore
       187: dup
       188: iconst_1
       189: new           #137                // class org/sireum/String
       192: dup
       193: getstatic     #60                 // Field org/sireum/String$.MODULE$:Lorg/sireum/String$;
       196: ldc           #144                // String org.scala-lang.scala-reflect
       198: invokevirtual #66                 // Method org/sireum/String$.apply:(Ljava/lang/String;)Ljava/lang/String;
       201: invokespecial #142                // Method org/sireum/String."<init>":(Ljava/lang/String;)V
       204: aastore
       205: dup
       206: iconst_2
       207: new           #137                // class org/sireum/String
       210: dup
       211: getstatic     #60                 // Field org/sireum/String$.MODULE$:Lorg/sireum/String$;
       214: ldc           #146                // String org.scala-lang.scala-compiler
       216: invokevirtual #66                 // Method org/sireum/String$.apply:(Ljava/lang/String;)Ljava/lang/String;
       219: invokespecial #142                // Method org/sireum/String."<init>":(Ljava/lang/String;)V
       222: aastore
       223: invokevirtual #150                // Method scala/runtime/ScalaRunTime$.genericWrapArray:(Ljava/lang/Object;)Lscala/collection/immutable/ArraySeq;
       226: invokevirtual #153                // Method org/sireum/$internal/PackageTrait$ISZ$.apply:(Lscala/collection/immutable/Seq;)Lorg/sireum/IS;
       229: invokevirtual #157                // Method org/sireum/HashSet$.$plus$plus:(Lorg/sireum/IS;)Lorg/sireum/HashSet;
       232: putstatic     #159                // Field ignoredLibraryNames:Lorg/sireum/HashSet;
       235: return
      LineNumberTable:
        line 31: 0
        line 40: 10
        line 41: 21
        line 42: 32
        line 43: 43
        line 44: 54
        line 45: 65
        line 46: 76
        line 47: 87
        line 48: 98
        line 49: 109
        line 51: 120
        line 52: 131
        line 53: 142
        line 55: 153
        line 56: 171
        line 55: 232
        line 31: 235

  public java.lang.String javaKey();
    descriptor: ()Ljava/lang/String;
    flags: (0x0001) ACC_PUBLIC
    Code:
      stack=1, locals=1, args_size=1
         0: getstatic     #68                 // Field javaKey:Ljava/lang/String;
         3: areturn
      LineNumberTable:
        line 40: 0
      LocalVariableTable:
        Start  Length  Slot  Name   Signature
            0       4     0  this   Lorg/sireum/project/DependencyManager$;

  public java.lang.String jbrKey();
    descriptor: ()Ljava/lang/String;
    flags: (0x0001) ACC_PUBLIC
    Code:
      stack=1, locals=1, args_size=1
         0: getstatic     #72                 // Field jbrKey:Ljava/lang/String;
         3: areturn
      LineNumberTable:
        line 41: 0
      LocalVariableTable:
        Start  Length  Slot  Name   Signature
            0       4     0  this   Lorg/sireum/project/DependencyManager$;

  public java.lang.String scalacPluginKey();
    descriptor: ()Ljava/lang/String;
    flags: (0x0001) ACC_PUBLIC
    Code:
      stack=1, locals=1, args_size=1
         0: getstatic     #76                 // Field scalacPluginKey:Ljava/lang/String;
         3: areturn
      LineNumberTable:
        line 42: 0
      LocalVariableTable:
        Start  Length  Slot  Name   Signature
            0       4     0  this   Lorg/sireum/project/DependencyManager$;

  public java.lang.String scalaKey();
    descriptor: ()Ljava/lang/String;
    flags: (0x0001) ACC_PUBLIC
    Code:
      stack=1, locals=1, args_size=1
         0: getstatic     #80                 // Field scalaKey:Ljava/lang/String;
         3: areturn
      LineNumberTable:
        line 43: 0
      LocalVariableTable:
        Start  Length  Slot  Name   Signature
            0       4     0  this   Lorg/sireum/project/DependencyManager$;

  public java.lang.String scalaJsKey();
    descriptor: ()Ljava/lang/String;
    flags: (0x0001) ACC_PUBLIC
    Code:
      stack=1, locals=1, args_size=1
         0: getstatic     #84                 // Field scalaJsKey:Ljava/lang/String;
         3: areturn
      LineNumberTable:
        line 44: 0
      LocalVariableTable:
        Start  Length  Slot  Name   Signature
            0       4     0  this   Lorg/sireum/project/DependencyManager$;

  public java.lang.String scalaTestKey();
    descriptor: ()Ljava/lang/String;
    flags: (0x0001) ACC_PUBLIC
    Code:
      stack=1, locals=1, args_size=1
         0: getstatic     #88                 // Field scalaTestKey:Ljava/lang/String;
         3: areturn
      LineNumberTable:
        line 45: 0
      LocalVariableTable:
        Start  Length  Slot  Name   Signature
            0       4     0  this   Lorg/sireum/project/DependencyManager$;

  public java.lang.String macrosKey();
    descriptor: ()Ljava/lang/String;
    flags: (0x0001) ACC_PUBLIC
    Code:
      stack=1, locals=1, args_size=1
         0: getstatic     #92                 // Field macrosKey:Ljava/lang/String;
         3: areturn
      LineNumberTable:
        line 46: 0
      LocalVariableTable:
        Start  Length  Slot  Name   Signature
            0       4     0  this   Lorg/sireum/project/DependencyManager$;

  public java.lang.String testKey();
    descriptor: ()Ljava/lang/String;
    flags: (0x0001) ACC_PUBLIC
    Code:
      stack=1, locals=1, args_size=1
         0: getstatic     #96                 // Field testKey:Ljava/lang/String;
         3: areturn
      LineNumberTable:
        line 47: 0
      LocalVariableTable:
        Start  Length  Slot  Name   Signature
            0       4     0  this   Lorg/sireum/project/DependencyManager$;

  public java.lang.String libraryKey();
    descriptor: ()Ljava/lang/String;
    flags: (0x0001) ACC_PUBLIC
    Code:
      stack=1, locals=1, args_size=1
         0: getstatic     #100                // Field libraryKey:Ljava/lang/String;
         3: areturn
      LineNumberTable:
        line 48: 0
      LocalVariableTable:
        Start  Length  Slot  Name   Signature
            0       4     0  this   Lorg/sireum/project/DependencyManager$;

  public java.lang.String librarySharedKey();
    descriptor: ()Ljava/lang/String;
    flags: (0x0001) ACC_PUBLIC
    Code:
      stack=1, locals=1, args_size=1
         0: getstatic     #104                // Field librarySharedKey:Ljava/lang/String;
         3: areturn
      LineNumberTable:
        line 49: 0
      LocalVariableTable:
        Start  Length  Slot  Name   Signature
            0       4     0  this   Lorg/sireum/project/DependencyManager$;

  public java.lang.String jarSuffix();
    descriptor: ()Ljava/lang/String;
    flags: (0x0001) ACC_PUBLIC
    Code:
      stack=1, locals=1, args_size=1
         0: getstatic     #108                // Field jarSuffix:Ljava/lang/String;
         3: areturn
      LineNumberTable:
        line 51: 0
      LocalVariableTable:
        Start  Length  Slot  Name   Signature
            0       4     0  this   Lorg/sireum/project/DependencyManager$;

  public java.lang.String sourceJarSuffix();
    descriptor: ()Ljava/lang/String;
    flags: (0x0001) ACC_PUBLIC
    Code:
      stack=1, locals=1, args_size=1
         0: getstatic     #112                // Field sourceJarSuffix:Ljava/lang/String;
         3: areturn
      LineNumberTable:
        line 52: 0
      LocalVariableTable:
        Start  Length  Slot  Name   Signature
            0       4     0  this   Lorg/sireum/project/DependencyManager$;

  public java.lang.String docJarSuffix();
    descriptor: ()Ljava/lang/String;
    flags: (0x0001) ACC_PUBLIC
    Code:
      stack=1, locals=1, args_size=1
         0: getstatic     #116                // Field docJarSuffix:Ljava/lang/String;
         3: areturn
      LineNumberTable:
        line 53: 0
      LocalVariableTable:
        Start  Length  Slot  Name   Signature
            0       4     0  this   Lorg/sireum/project/DependencyManager$;

  public org.sireum.HashSet<org.sireum.String> ignoredLibraryNames();
    descriptor: ()Lorg/sireum/HashSet;
    flags: (0x0001) ACC_PUBLIC
    Code:
      stack=1, locals=1, args_size=1
         0: getstatic     #159                // Field ignoredLibraryNames:Lorg/sireum/HashSet;
         3: areturn
      LineNumberTable:
        line 55: 0
      LocalVariableTable:
        Start  Length  Slot  Name   Signature
            0       4     0  this   Lorg/sireum/project/DependencyManager$;
    Signature: #163                         // ()Lorg/sireum/HashSet<Lorg/sireum/String;>;

  public org.sireum.IS<org.sireum.Z, org.sireum.CoursierClassifier$Type> buildClassifiers(boolean, boolean);
    descriptor: (ZZ)Lorg/sireum/IS;
    flags: (0x0001) ACC_PUBLIC
    Code:
      stack=6, locals=4, args_size=3
         0: getstatic     #126                // Field org/sireum/package$.MODULE$:Lorg/sireum/package$;
         3: invokevirtual #130                // Method org/sireum/package$.ISZ:()Lorg/sireum/$internal/PackageTrait$ISZ$;
         6: getstatic     #135                // Field scala/runtime/ScalaRunTime$.MODULE$:Lscala/runtime/ScalaRunTime$;
         9: iconst_1
        10: anewarray     #23                 // class org/sireum/CoursierClassifier$Type
        13: dup
        14: iconst_0
        15: getstatic     #171                // Field org/sireum/CoursierClassifier$Default$.MODULE$:Lorg/sireum/CoursierClassifier$Default$;
        18: aastore
        19: checkcast     #173                // class "[Ljava/lang/Object;"
        22: invokevirtual #177                // Method scala/runtime/ScalaRunTime$.wrapRefArray:([Ljava/lang/Object;)Lscala/collection/immutable/ArraySeq;
        25: invokevirtual #153                // Method org/sireum/$internal/PackageTrait$ISZ$.apply:(Lscala/collection/immutable/Seq;)Lorg/sireum/IS;
        28: astore_3
        29: getstatic     #182                // Field org/sireum/B$.MODULE$:Lorg/sireum/B$;
        32: iload_1
        33: invokevirtual #186                // Method org/sireum/B$.$4B:(Z)Z
        36: ifeq          50
        39: aload_3
        40: getstatic     #189                // Field org/sireum/CoursierClassifier$Sources$.MODULE$:Lorg/sireum/CoursierClassifier$Sources$;
        43: invokevirtual #195                // Method org/sireum/IS.$colon$plus:(Ljava/lang/Object;)Lorg/sireum/IS;
        46: astore_3
        47: goto          50
        50: getstatic     #182                // Field org/sireum/B$.MODULE$:Lorg/sireum/B$;
        53: iload_2
        54: invokevirtual #186                // Method org/sireum/B$.$4B:(Z)Z
        57: ifeq          71
        60: aload_3
        61: getstatic     #198                // Field org/sireum/CoursierClassifier$Javadoc$.MODULE$:Lorg/sireum/CoursierClassifier$Javadoc$;
        64: invokevirtual #195                // Method org/sireum/IS.$colon$plus:(Ljava/lang/Object;)Lorg/sireum/IS;
        67: astore_3
        68: goto          71
        71: aload_3
        72: areturn
      StackMapTable: number_of_entries = 2
        frame_type = 252 /* append */
          offset_delta = 50
          locals = [ class org/sireum/IS ]
        frame_type = 20 /* same */
      LineNumberTable:
        line 60: 0
        line 61: 29
        line 62: 39
        line 64: 50
        line 65: 60
        line 67: 71
      LocalVariableTable:
        Start  Length  Slot  Name   Signature
           29      44     3 classifiers   Lorg/sireum/IS;
            0      73     0  this   Lorg/sireum/project/DependencyManager$;
            0      73     1 withSource   Z
            0      73     2 withDoc   Z
    Signature: #166                         // (ZZ)Lorg/sireum/IS<Lorg/sireum/Z;Lorg/sireum/CoursierClassifier$Type;>;
    MethodParameters:
      Name                           Flags
      withSource                     final
      withDoc                        final

  public java.lang.String libName(org.sireum.CoursierFileInfo);
    descriptor: (Lorg/sireum/CoursierFileInfo;)Ljava/lang/String;
    flags: (0x0001) ACC_PUBLIC
    Code:
      stack=5, locals=2, args_size=2
         0: getstatic     #60                 // Field org/sireum/String$.MODULE$:Lorg/sireum/String$;
         3: new           #206                // class java/lang/StringBuilder
         6: dup
         7: ldc           #207                // int 1
         9: invokespecial #210                // Method java/lang/StringBuilder."<init>":(I)V
        12: new           #137                // class org/sireum/String
        15: dup
        16: aload_1
        17: invokevirtual #215                // Method org/sireum/CoursierFileInfo.org:()Ljava/lang/String;
        20: invokespecial #142                // Method org/sireum/String."<init>":(Ljava/lang/String;)V
        23: invokevirtual #219                // Method java/lang/StringBuilder.append:(Ljava/lang/Object;)Ljava/lang/StringBuilder;
        26: ldc           #221                // String .
        28: invokevirtual #224                // Method java/lang/StringBuilder.append:(Ljava/lang/String;)Ljava/lang/StringBuilder;
        31: new           #137                // class org/sireum/String
        34: dup
        35: aload_1
        36: invokevirtual #227                // Method org/sireum/CoursierFileInfo.module:()Ljava/lang/String;
        39: invokespecial #142                // Method org/sireum/String."<init>":(Ljava/lang/String;)V
        42: invokevirtual #219                // Method java/lang/StringBuilder.append:(Ljava/lang/Object;)Ljava/lang/StringBuilder;
        45: invokevirtual #230                // Method java/lang/StringBuilder.toString:()Ljava/lang/String;
        48: invokevirtual #66                 // Method org/sireum/String$.apply:(Ljava/lang/String;)Ljava/lang/String;
        51: areturn
      LineNumberTable:
        line 70: 0
      LocalVariableTable:
        Start  Length  Slot  Name   Signature
            0      52     0  this   Lorg/sireum/project/DependencyManager$;
            0      52     1   cif   Lorg/sireum/CoursierFileInfo;
    MethodParameters:
      Name                           Flags
      cif                            final

  public org.sireum.project.DependencyManager apply(org.sireum.project.Project, org.sireum.HashSMap<org.sireum.String, org.sireum.String>, boolean, boolean, boolean, org.sireum.Os$Path, org.sireum.Os$Path, org.sireum.Os$Path, org.sireum.Option<org.sireum.Os$Path>);
    descriptor: (Lorg/sireum/project/Project;Lorg/sireum/HashSMap;ZZZLorg/sireum/Os$Path;Lorg/sireum/Os$Path;Lorg/sireum/Os$Path;Lorg/sireum/Option;)Lorg/sireum/project/DependencyManager;
    flags: (0x0001) ACC_PUBLIC
    Code:
      stack=11, locals=10, args_size=10
         0: new           #242                // class org/sireum/project/DependencyManager
         3: dup
         4: aload_1
         5: aload_2
         6: iload_3
         7: iload         4
         9: iload         5
        11: aload         6
        13: aload         7
        15: aload         8
        17: aload         9
        19: invokespecial #245                // Method org/sireum/project/DependencyManager."<init>":(Lorg/sireum/project/Project;Lorg/sireum/HashSMap;ZZZLorg/sireum/Os$Path;Lorg/sireum/Os$Path;Lorg/sireum/Os$Path;Lorg/sireum/Option;)V
        22: areturn
      LineNumberTable:
        line 31: 0
      LocalVariableTable:
        Start  Length  Slot  Name   Signature
            0      23     0  this   Lorg/sireum/project/DependencyManager$;
            0      23     1 project   Lorg/sireum/project/Project;
            0      23     2 versions   Lorg/sireum/HashSMap;
            0      23     3  isJs   Z
            0      23     4 withSource   Z
            0      23     5 withDoc   Z
            0      23     6 javaHome   Lorg/sireum/Os$Path;
            0      23     7 scalaHome   Lorg/sireum/Os$Path;
            0      23     8 sireumHome   Lorg/sireum/Os$Path;
            0      23     9 cacheOpt   Lorg/sireum/Option;
    Signature: #233                         // (Lorg/sireum/project/Project;Lorg/sireum/HashSMap<Lorg/sireum/String;Lorg/sireum/String;>;ZZZLorg/sireum/Os$Path;Lorg/sireum/Os$Path;Lorg/sireum/Os$Path;Lorg/sireum/Option<Lorg/sireum/Os$Path;>;)Lorg/sireum/project/DependencyManager;
    MethodParameters:
      Name                           Flags
      project                        final
      versions                       final
      isJs                           final
      withSource                     final
      withDoc                        final
      javaHome                       final
      scalaHome                      final
      sireumHome                     final
      cacheOpt                       final

  public scala.Some<scala.Tuple9<org.sireum.project.Project, org.sireum.HashSMap<org.sireum.String, org.sireum.String>, org.sireum.B, org.sireum.B, org.sireum.B, org.sireum.Os$Path, org.sireum.Os$Path, org.sireum.Os$Path, org.sireum.Option<org.sireum.Os$Path>>> unapply(org.sireum.project.DependencyManager);
    descriptor: (Lorg/sireum/project/DependencyManager;)Lscala/Some;
    flags: (0x0001) ACC_PUBLIC
    Code:
      stack=14, locals=2, args_size=2
         0: new           #255                // class scala/Some
         3: dup
         4: new           #257                // class scala/Tuple9
         7: dup
         8: getstatic     #262                // Field org/sireum/helper$.MODULE$:Lorg/sireum/helper$;
        11: aload_1
        12: invokevirtual #265                // Method org/sireum/project/DependencyManager.project:()Lorg/sireum/project/Project;
        15: invokevirtual #269                // Method org/sireum/helper$.clone:(Ljava/lang/Object;)Ljava/lang/Object;
        18: getstatic     #262                // Field org/sireum/helper$.MODULE$:Lorg/sireum/helper$;
        21: aload_1
        22: invokevirtual #272                // Method org/sireum/project/DependencyManager.versions:()Lorg/sireum/HashSMap;
        25: invokevirtual #269                // Method org/sireum/helper$.clone:(Ljava/lang/Object;)Ljava/lang/Object;
        28: getstatic     #262                // Field org/sireum/helper$.MODULE$:Lorg/sireum/helper$;
        31: new           #274                // class org/sireum/B
        34: dup
        35: aload_1
        36: invokevirtual #277                // Method org/sireum/project/DependencyManager.isJs:()Z
        39: invokespecial #280                // Method org/sireum/B."<init>":(Z)V
        42: invokevirtual #269                // Method org/sireum/helper$.clone:(Ljava/lang/Object;)Ljava/lang/Object;
        45: getstatic     #262                // Field org/sireum/helper$.MODULE$:Lorg/sireum/helper$;
        48: new           #274                // class org/sireum/B
        51: dup
        52: aload_1
        53: invokevirtual #282                // Method org/sireum/project/DependencyManager.withSource:()Z
        56: invokespecial #280                // Method org/sireum/B."<init>":(Z)V
        59: invokevirtual #269                // Method org/sireum/helper$.clone:(Ljava/lang/Object;)Ljava/lang/Object;
        62: getstatic     #262                // Field org/sireum/helper$.MODULE$:Lorg/sireum/helper$;
        65: new           #274                // class org/sireum/B
        68: dup
        69: aload_1
        70: invokevirtual #284                // Method org/sireum/project/DependencyManager.withDoc:()Z
        73: invokespecial #280                // Method org/sireum/B."<init>":(Z)V
        76: invokevirtual #269                // Method org/sireum/helper$.clone:(Ljava/lang/Object;)Ljava/lang/Object;
        79: getstatic     #262                // Field org/sireum/helper$.MODULE$:Lorg/sireum/helper$;
        82: aload_1
        83: invokevirtual #287                // Method org/sireum/project/DependencyManager.javaHome:()Lorg/sireum/Os$Path;
        86: invokevirtual #269                // Method org/sireum/helper$.clone:(Ljava/lang/Object;)Ljava/lang/Object;
        89: getstatic     #262                // Field org/sireum/helper$.MODULE$:Lorg/sireum/helper$;
        92: aload_1
        93: invokevirtual #289                // Method org/sireum/project/DependencyManager.scalaHome:()Lorg/sireum/Os$Path;
        96: invokevirtual #269                // Method org/sireum/helper$.clone:(Ljava/lang/Object;)Ljava/lang/Object;
        99: getstatic     #262                // Field org/sireum/helper$.MODULE$:Lorg/sireum/helper$;
       102: aload_1
       103: invokevirtual #291                // Method org/sireum/project/DependencyManager.sireumHome:()Lorg/sireum/Os$Path;
       106: invokevirtual #269                // Method org/sireum/helper$.clone:(Ljava/lang/Object;)Ljava/lang/Object;
       109: getstatic     #262                // Field org/sireum/helper$.MODULE$:Lorg/sireum/helper$;
       112: aload_1
       113: invokevirtual #294                // Method org/sireum/project/DependencyManager.cacheOpt:()Lorg/sireum/Option;
       116: invokevirtual #269                // Method org/sireum/helper$.clone:(Ljava/lang/Object;)Ljava/lang/Object;
       119: invokespecial #297                // Method scala/Tuple9."<init>":(Ljava/lang/Object;Ljava/lang/Object;Ljava/lang/Object;Ljava/lang/Object;Ljava/lang/Object;Ljava/lang/Object;Ljava/lang/Object;Ljava/lang/Object;Ljava/lang/Object;)V
       122: invokespecial #300                // Method scala/Some."<init>":(Ljava/lang/Object;)V
       125: areturn
      LineNumberTable:
        line 31: 0
      LocalVariableTable:
        Start  Length  Slot  Name   Signature
            0     126     0  this   Lorg/sireum/project/DependencyManager$;
            0     126     1     o   Lorg/sireum/project/DependencyManager;
    Signature: #252                         // (Lorg/sireum/project/DependencyManager;)Lscala/Some<Lscala/Tuple9<Lorg/sireum/project/Project;Lorg/sireum/HashSMap<Lorg/sireum/String;Lorg/sireum/String;>;Lorg/sireum/B;Lorg/sireum/B;Lorg/sireum/B;Lorg/sireum/Os$Path;Lorg/sireum/Os$Path;Lorg/sireum/Os$Path;Lorg/sireum/Option<Lorg/sireum/Os$Path;>;>;>;
    MethodParameters:
      Name                           Flags
      o                              final

  private org.sireum.project.DependencyManager$();
    descriptor: ()V
    flags: (0x0002) ACC_PRIVATE
    Code:
      stack=1, locals=1, args_size=1
         0: aload_0
         1: invokespecial #302                // Method java/lang/Object."<init>":()V
         4: return
      LineNumberTable:
        line 31: 0
      LocalVariableTable:
        Start  Length  Slot  Name   Signature
            0       5     0  this   Lorg/sireum/project/DependencyManager$;
}
InnerClasses:
  public #10= #7 of #9;                   // ISZ$=class org/sireum/$internal/PackageTrait$ISZ$ of class org/sireum/$internal/PackageTrait
  public static final #15= #12 of #14;    // Default$=class org/sireum/CoursierClassifier$Default$ of class org/sireum/CoursierClassifier
  public static final #18= #17 of #14;    // Javadoc$=class org/sireum/CoursierClassifier$Javadoc$ of class org/sireum/CoursierClassifier
  public static final #21= #20 of #14;    // Sources$=class org/sireum/CoursierClassifier$Sources$ of class org/sireum/CoursierClassifier
  public static #24= #23 of #14;          // Type=class org/sireum/CoursierClassifier$Type of class org/sireum/CoursierClassifier
  public static #29= #26 of #28;          // Path=class org/sireum/Os$Path of class org/sireum/Os
SourceFile: "DependencyManager.scala"
  ScalaInlineInfo: length = 0x63 (unknown attribute)
   01 01 00 13 00 33 00 32 01 00 3F 00 E8 01 00 A4
   00 A5 01 00 2D 00 A0 01 00 2E 00 A2 01 00 2B 00
   A0 01 00 20 00 A0 01 00 22 00 A0 01 00 CA 00 CB
   01 00 29 00 A0 01 00 2A 00 A0 01 00 27 00 A0 01
   00 25 00 A0 01 00 24 00 A0 01 00 26 00 A0 01 00
   23 00 A0 01 00 2C 00 A0 01 00 28 00 A0 01 00 FA
   00 FB 01
  Scala: length = 0x0 (unknown attribute)

