Classfile /Users/mw/Projects/slang-braindump/.jar/jar11/assemble/slang-braindump/assemble/content/org/sireum/project/PublishInfo.class
  Last modified May 29, 2022; size 11252 bytes
  SHA-256 checksum 337c9cca714f0363caedebf873bbd11851ff8f96078d9ba166ce85b7d8fe7c08
  Compiled from "Project.scala"
public final class org.sireum.project.PublishInfo implements org.sireum.DatatypeSig
  minor version: 0
  major version: 52
  flags: (0x0031) ACC_PUBLIC, ACC_FINAL, ACC_SUPER
  this_class: #2                          // org/sireum/project/PublishInfo
  super_class: #4                         // java/lang/Object
  interfaces: 1, fields: 7, methods: 28, attributes: 5
Constant pool:
    #1 = Utf8               org/sireum/project/PublishInfo
    #2 = Class              #1            // org/sireum/project/PublishInfo
    #3 = Utf8               java/lang/Object
    #4 = Class              #3            // java/lang/Object
    #5 = Utf8               org/sireum/DatatypeSig
    #6 = Class              #5            // org/sireum/DatatypeSig
    #7 = Utf8               Project.scala
    #8 = Utf8               Lscala/reflect/ScalaSignature;
    #9 = Utf8               bytes
   #10 = Utf8               \u0006\u0005\t}c\u0001\u0002+V\u0005qC\u0001b\u001a\u0001\u0003\u0002\u0003\u0006I\u0001\u001b\u0005\tW\u0002\u0011\t\u0011)A\u0005Q\"AA\u000e\u0001B\u0001B\u0003%Q\u000e\u0003\u0006\u0003*\u0001\u0011\t\u0011)A\u0005\u00053Aq!!\u0003\u0001\t\u0003\u0011Y\u0003C\u0004\u00036\u0001\u0001\u000b\u0011\u00025\t\u000f\t5\u0001\u0001\"\u0001\u00022!9!q\u0007\u0001\u0005\u0002\u0005E\u0002bBA\u001b\u0001\u0001\u0006I\u0001\u001b\u0005\b\u0003o\u0001A\u0011AA\u0019\u0011\u001d\tI\u0004\u0001C\u0001\u0003cAqA!\u000f\u0001A\u0003%Q\u000eC\u0004\u0003\u0014\u0001!\tAa\u000f\t\u000f\tu\u0002\u0001\"\u0001\u0003<!A!q\b\u0001!\u0002\u0013\u0011I\u0002C\u0004\u0003\u0018\u0001!\tA!\u0011\t\u000f\t\r\u0003\u0001\"\u0001\u0003B!9\u0011\u0011\t\u0001\u0005B\u0005\r\u0003bBA*\u0001\u0011\u0005\u0013\u0011\u0007\u0005\u000b\u0003+\u0002\u0001R1A\u0005B\u0005]\u0003bBA0\u0001\u0011\u0005#Q\t\u0005\b\u00033\u0001A\u0011\u0001B%\u0011%\tY\bAI\u0001\n\u0003\ti\bC\u0005\u0002\u0014\u0002\t\n\u0011\"\u0001\u0002~!I\u0011Q\u0013\u0001\u0012\u0002\u0013\u0005!1\u000b\u0005\n\u0005/\u0002\u0011\u0013!C\u0001\u00053B!\"a&\u0001\u0011\u000b\u0007I\u0011IAM\u000f\u001d\t\u0019!\u0016E\u0001\u0003\u000b1a\u0001V+\t\u0002\u0005\u001d\u0001bBA\u0005;\u0011\u0005\u00111B\u0004\b\u0003\u001bi\u0002\u0012AA\b\r\u001d\t\u0019\"\bE\u0001\u0003+Aq!!\u0003!\t\u0003\t9\u0002C\u0004\u0002\u001a\u0001\"\t!a\u0007\t\u000f\u0005}\u0006\u0005\"\u0001\u0002B\u001a1\u00111C\u000f\u0003\u0003?A\u0011\"!\t%\u0005\u0003\u0005\u000b\u0011\u00025\t\u0011-$#\u0011!Q\u0001\n!D\u0011\"a\t%\u0005\u0003\u0005\u000b\u0011\u00025\t\u000f\u0005%A\u0005\"\u0001\u0002&!9\u0011Q\u0006\u0013!\u0002\u0013A\u0007bBA\u0018I\u0011\u0005\u0011\u0011\u0007\u0005\b\u0003g!C\u0011AA\u0019\u0011\u001d\t)\u0004\nQ\u0001\n!Dq!a\u000e%\t\u0003\t\t\u0004C\u0004\u0002:\u0011\"\t!!\r\t\u000f\u0005mB\u0005)A\u0005Q\"9\u0011Q\b\u0013\u0005\u0002\u0005E\u0002bBA I\u0011\u0005\u0011\u0011\u0007\u0005\b\u0003\u0003\"C\u0011IA\"\u0011\u001d\t\u0019\u0006\nC!\u0003cA!\"!\u0016%\u0011\u000b\u0007I\u0011IA,\u0011\u001d\ty\u0006\nC!\u0003CBq!!\u0007%\t\u0003\t\u0019\bC\u0005\u0002|\u0011\n\n\u0011\"\u0001\u0002~!I\u00111\u0013\u0013\u0012\u0002\u0013\u0005\u0011Q\u0010\u0005\n\u0003+#\u0013\u0013!C\u0001\u0003{B!\"a&%\u0011\u000b\u0007I\u0011IAM\u000f\u001d\t\t.\bE\u0001\u0003\'4q!!6\u001e\u0011\u0003\t9\u000eC\u0004\u0002\nq\"\t!!7\t\u000f\u0005eA\b\"\u0001\u0002\\\"9\u0011q\u0018\u001f\u0005\u0002\u0005}hABAk;\t\ty\u000eC\u0005\u0002b\u0002\u0013\t\u0011)A\u0005Q\"I\u0011\u0011\u0005!\u0003\u0002\u0003\u0006I\u0001\u001b\u0005\b\u0003\u0013\u0001E\u0011AAr\u0011\u001d\tI\u000f\u0011Q\u0001\n!Dq!a;A\t\u0003\t\t\u0004C\u0004\u0002n\u0002#\t!!\r\t\u000f\u00055\u0002\t)A\u0005Q\"9\u0011q\u0006!\u0005\u0002\u0005E\u0002bBA\u001a\u0001\u0012\u0005\u0011\u0011\u0007\u0005\b\u0003\u0003\u0002E\u0011IA\"\u0011\u001d\t\u0019\u0006\u0011C!\u0003cA!\"!\u0016A\u0011\u000b\u0007I\u0011IA,\u0011\u001d\ty\u0006\u0011C!\u0003_Dq!!\u0007A\t\u0003\t\u0019\u0010C\u0005\u0002|\u0001\u000b\n\u0011\"\u0001\u0002~!I\u00111\u0013!\u0012\u0002\u0013\u0005\u0011Q\u0010\u0005\u000b\u0003/\u0003\u0005R1A\u0005B\u0005e\u0005bBA\r;\u0011\u0005!q\u0001\u0005\b\u0003\u007fkB\u0011\u0001B\u000f\u0005-\u0001VO\u00197jg\"LeNZ8\u000b\u0005Y;\u0016a\u00029s_*,7\r\u001e\u0006\u00031f\u000baa]5sKVl\'\"\u0001.\u0002\u0007=\u0014xm\u0001\u0001\u0014\u0007\u0001i6\r\u0005\u0002_C6\tqLC\u0001a\u0003\u0015\u00198-\u00197b\u0013\t\u0011wL\u0001\u0004B]f\u0014VM\u001a\t\u0003I\u0016l\u0011aV\u0005\u0003M^\u00131\u0002R1uCRL\b/Z*jO\u0006iql\u00183fg\u000e\u0014\u0018\u000e\u001d;j_:\u0004\"\u0001Z5\n\u0005)<&AB*ue&tw-A\u0003`?V\u0014H.\u0001\u0006`?2L7-\u001a8tKN\u00042A\u001c=\u007f\u001d\tygO\u0004\u0002qk:\u0011\u0011\u000f^\u0007\u0002e*\u00111oW\u0001\u0007yI|w\u000e\u001e \n\u0003iK!\u0001W-\n\u0005]<\u0016a\u00029bG.\fw-Z\u0005\u0003sj\u00141!S*[\u0013\tYHP\u0001\u0007QC\u000e\\\u0017mZ3Ue\u0006LGO\u0003\u0002~/\u0006IA%\u001b8uKJt\u0017\r\u001c\t\u0003\u007f\u0012r1!!\u0001\u001d\u001b\u0005)\u0016a\u0003)vE2L7\u000f[%oM>\u00042!!\u0001\u001e\'\tiR,\u0001\u0004=S:LGO\u0010\u000b\u0003\u0003\u000b\tq\u0001T5dK:\u001cX\rE\u0002\u0002\u0012\u0001j\u0011!\b\u0002\b\u0019&\u001cWM\\:f\'\t\u0001S\f\u0006\u0002\u0002\u0010\u0005)\u0011\r\u001d9msRA\u0011QDA]\u0003w\u000bi\fE\u0002\u0002\u0012\u0011\u001a2\u0001J/d\u0003\u0019yvL\\1nK\u0006qql\u00183jgR\u0014\u0018NY;uS>tG\u0003CA\u000f\u0003O\tI#a\u000b\t\r\u0005\u0005\u0002\u00061\u0001i\u0011\u0015Y\u0007\u00061\u0001i\u0011\u0019\t\u0019\u0003\u000ba\u0001Q\u0006)qL\\1nK\u0006!a.Y7f+\u0005A\u0017aB4fi:\u000bW.Z\u0001\u0005?V\u0014H.A\u0002ve2\faaZ3u+Jd\u0017!D0eSN$(/\u001b2vi&|g.\u0001\u0007eSN$(/\u001b2vi&|g.A\bhKR$\u0015n\u001d;sS\n,H/[8o\u0003!!xn\u0015;sS:<GCAA#!\u0011\t9%!\u0015\u000e\u0005\u0005%#\u0002BA&\u0003\u001b\nA\u0001\\1oO*\u0011\u0011qJ\u0001\u0005U\u00064\u0018-C\u0002k\u0003\u0013\naa\u001d;sS:<\u0017\u0001\u00035bg\"\u001cu\u000eZ3\u0016\u0005\u0005e\u0003c\u00010\u0002\\%\u0019\u0011QL0\u0003\u0007%sG/\u0001\u0004fcV\fGn\u001d\u000b\u0005\u0003G\nI\u0007E\u0002_\u0003KJ1!a\u001a`\u0005\u001d\u0011un\u001c7fC:Dq!a\u001b6\u0001\u0004\ti\'A\u0001p!\rq\u0016qN\u0005\u0004\u0003cz&aA!osRA\u0011QDA;\u0003o\nI\b\u0003\u0005\u00020Y\u0002\n\u00111\u0001i\u0011!\t9D\u000eI\u0001\u0002\u0004A\u0007\u0002CA\u001fmA\u0005\t\u0019\u00015\u0002\u001f\u0005\u0004\b\u000f\\=%I\u00164\u0017-\u001e7uIE*\"!a +\u0007!\f\ti\u000b\u0002\u0002\u0004B!\u0011QQAH\u001b\t\t9I\u0003\u0003\u0002\n\u0006-\u0015!C;oG\",7m[3e\u0015\r\tiiX\u0001\u000bC:tw\u000e^1uS>t\u0017\u0002BAI\u0003\u000f\u0013\u0011#\u001e8dQ\u0016\u001c7.\u001a3WCJL\u0017M\\2f\u0003=\t\u0007\u000f\u001d7zI\u0011,g-Y;mi\u0012\u0012\u0014aD1qa2LH\u0005Z3gCVdG\u000fJ\u001a\u0002\u0011\u0011\u001awN\u001c;f]R,\"!a\'\u0011\r\u0005u\u0015QUAV\u001d\u0011\ty*a)\u000f\u0007E\f\t+C\u0001a\u0013\t9x,\u0003\u0003\u0002(\u0006%&aA*fc*\u0011qo\u0018\t\b=\u00065\u0016QIA7\u0013\r\tyk\u0018\u0002\u0007)V\u0004H.\u001a\u001a)\u0007\u0011\n\u0019\fE\u0002e\u0003kK1!a.X\u0005!!\u0017\r^1usB,\u0007BBA\u0018E\u0001\u0007\u0001\u000e\u0003\u0004\u00028\t\u0002\r\u0001\u001b\u0005\u0007\u0003{\u0011\u0003\u0019\u00015\u0002\u000fUt\u0017\r\u001d9msR!\u00111YAh!\u0015q\u0016QYAe\u0013\r\t9m\u0018\u0002\u0005\'>lW\r\u0005\u0004_\u0003\u0017D\u0007\u000e[\u0005\u0004\u0003\u001b|&A\u0002+va2,7\u0007C\u0004\u0002l\r\u0002\r!!\b\u0002\u0013\u0011+g/\u001a7pa\u0016\u0014\bcAA\ty\tIA)\u001a<fY>\u0004XM]\n\u0003yu#\"!a5\u0015\r\u0005u\u00171`A\u007f!\r\t\t\u0002Q\n\u0004\u0001v\u001b\u0017\u0001B0`S\u0012$b!!8\u0002f\u0006\u001d\bBBAq\u0007\u0002\u0007\u0001\u000e\u0003\u0004\u0002\"\r\u0003\r\u0001[\u0001\u0004?&$\u0017AA5e\u0003\u00159W\r^%e)\u0011\t\u0019\'!=\t\u000f\u0005-T\n1\u0001\u0002nQ1\u0011Q\\A{\u0003oD\u0001\"a;O!\u0003\u0005\r\u0001\u001b\u0005\t\u0003_q\u0005\u0013!a\u0001Q\"\u001a\u0001)a-\t\r\u0005-h\b1\u0001i\u0011\u0019\tyC\u0010a\u0001QR!!\u0011\u0001B\u0003!\u0015q\u0016Q\u0019B\u0002!\u0015q\u0016Q\u00165i\u0011\u001d\tYg\u0010a\u0001\u0003;$\"B!\u0003\u0003\f\t=!\u0011\u0003B\u000b!\r\t\t\u0001\u0001\u0005\u0007\u0005\u001b\u0011\u0006\u0019\u00015\u0002\u0017\u0011,7o\u0019:jaRLwN\u001c\u0005\u0007\u0003o\u0011\u0006\u0019\u00015\t\r\tM!\u000b1\u0001n\u0003!a\u0017nY3og\u0016\u001c\bb\u0002B\f%\u0002\u0007!\u0011D\u0001\u000bI\u00164X\r\\8qKJ\u001c\b\u0003\u00028y\u00057\u0001\"a !\u0015\t\t}!q\u0005\t\u0006=\u0006\u0015\'\u0011\u0005\t\t=\n\r\u0002\u000e[7\u0003\u001a%\u0019!QE0\u0003\rQ+\b\u000f\\35\u0011\u001d\tYg\u0015a\u0001\u0005\u0013\tAbX0eKZ,Gn\u001c9feN$\"B!\u0003\u0003.\t=\"\u0011\u0007B\u001a\u0011\u00159W\u00011\u0001i\u0011\u0015YW\u00011\u0001i\u0011\u0015aW\u00011\u0001n\u0011\u001d\u0011I#\u0002a\u0001\u00053\tAb\u00183fg\u000e\u0014\u0018\u000e\u001d;j_:\fabZ3u\t\u0016\u001c8M]5qi&|g.A\u0005`Y&\u001cWM\\:fgV\tQ.A\u0006hKRd\u0015nY3og\u0016\u001c\u0018aC0eKZ,Gn\u001c9feN,\"A!\u0007\u0002\u001b\u001d,G\u000fR3wK2|\u0007/\u001a:t)\u0011\t\u0019Ga\u0012\t\u000f\u0005-T\u00031\u0001\u0002nQQ!\u0011\u0002B&\u0005\u001b\u0012yE!\u0015\t\u0011\t5a\u0003%AA\u0002!D\u0001\"a\u000e\u0017!\u0003\u0005\r\u0001\u001b\u0005\t\u0005\'1\u0002\u0013!a\u0001[\"I!q\u0003\f\u0011\u0002\u0003\u0007!\u0011D\u000b\u0003\u0005+R3!\\AA\u0003=\t\u0007\u000f\u001d7zI\u0011,g-Y;mi\u0012\"TC\u0001B.U\u0011\u0011I\"!!)\u0007\u0001\t\u0019\f
   #11 = Utf8               org/sireum/project/PublishInfo$Developer
   #12 = Class              #11           // org/sireum/project/PublishInfo$Developer
   #13 = Utf8               Developer
   #14 = Utf8               org/sireum/project/PublishInfo$Developer$
   #15 = Class              #14           // org/sireum/project/PublishInfo$Developer$
   #16 = Utf8               Developer$
   #17 = Utf8               org/sireum/project/PublishInfo$License
   #18 = Class              #17           // org/sireum/project/PublishInfo$License
   #19 = Utf8               License
   #20 = Utf8               org/sireum/project/PublishInfo$License$
   #21 = Class              #20           // org/sireum/project/PublishInfo$License$
   #22 = Utf8               License$
   #23 = Utf8               hashCode
   #24 = Utf8               I
   #25 = Utf8               $content
   #26 = Utf8               Lscala/collection/immutable/Seq;
   #27 = Utf8               Lscala/collection/immutable/Seq<Lscala/Tuple2<Ljava/lang/String;Ljava/lang/Object;>;>;
   #28 = Utf8               _description
   #29 = Utf8               Ljava/lang/String;
   #30 = Utf8               _url
   #31 = Utf8               _licenses
   #32 = Utf8               Lorg/sireum/IS;
   #33 = Utf8               Lorg/sireum/IS<Lorg/sireum/Z;Lorg/sireum/project/PublishInfo$License;>;
   #34 = Utf8               _developers
   #35 = Utf8               Lorg/sireum/IS<Lorg/sireum/Z;Lorg/sireum/project/PublishInfo$Developer;>;
   #36 = Utf8               bitmap$0
   #37 = Utf8               B
   #38 = Utf8               unapply
   #39 = Utf8               (Lorg/sireum/project/PublishInfo;)Lscala/Some;
   #40 = Utf8               (Lorg/sireum/project/PublishInfo;)Lscala/Some<Lscala/Tuple4<Lorg/sireum/String;Lorg/sireum/String;Lorg/sireum/IS<Lorg/sireum/Z;Lorg/sireum/project/PublishInfo$License;>;Lorg/sireum/IS<Lorg/sireum/Z;Lorg/sireum/project/PublishInfo$Developer;>;>;>;
   #41 = Utf8               o
   #42 = Utf8               org/sireum/project/PublishInfo$
   #43 = Class              #42           // org/sireum/project/PublishInfo$
   #44 = Utf8               MODULE$
   #45 = Utf8               Lorg/sireum/project/PublishInfo$;
   #46 = NameAndType        #44:#45       // MODULE$:Lorg/sireum/project/PublishInfo$;
   #47 = Fieldref           #43.#46       // org/sireum/project/PublishInfo$.MODULE$:Lorg/sireum/project/PublishInfo$;
   #48 = NameAndType        #38:#39       // unapply:(Lorg/sireum/project/PublishInfo;)Lscala/Some;
   #49 = Methodref          #43.#48       // org/sireum/project/PublishInfo$.unapply:(Lorg/sireum/project/PublishInfo;)Lscala/Some;
   #50 = Utf8               Lorg/sireum/project/PublishInfo;
   #51 = Utf8               hash
   #52 = Utf8               ()Lorg/sireum/Z;
   #53 = Utf8               hash$
   #54 = Utf8               (Lorg/sireum/DatatypeSig;)Lorg/sireum/Z;
   #55 = NameAndType        #53:#54       // hash$:(Lorg/sireum/DatatypeSig;)Lorg/sireum/Z;
   #56 = InterfaceMethodref #6.#55        // org/sireum/DatatypeSig.hash$:(Lorg/sireum/DatatypeSig;)Lorg/sireum/Z;
   #57 = Utf8               this
   #58 = Utf8               $cannotMixImmutableAndMutable
   #59 = Utf8               ()Lscala/runtime/Nothing$;
   #60 = Utf8               org/sireum/Immutable
   #61 = Class              #60           // org/sireum/Immutable
   #62 = Utf8               $cannotMixImmutableAndMutable$
   #63 = Utf8               (Lorg/sireum/Immutable;)Lscala/runtime/Nothing$;
   #64 = NameAndType        #62:#63       // $cannotMixImmutableAndMutable$:(Lorg/sireum/Immutable;)Lscala/runtime/Nothing$;
   #65 = InterfaceMethodref #61.#64       // org/sireum/Immutable.$cannotMixImmutableAndMutable$:(Lorg/sireum/Immutable;)Lscala/runtime/Nothing$;
   #66 = Utf8               $hasEquals
   #67 = Utf8               ()Z
   #68 = Utf8               $hasEquals$
   #69 = Utf8               (Lorg/sireum/Immutable;)Z
   #70 = NameAndType        #68:#69       // $hasEquals$:(Lorg/sireum/Immutable;)Z
   #71 = InterfaceMethodref #61.#70       // org/sireum/Immutable.$hasEquals$:(Lorg/sireum/Immutable;)Z
   #72 = Utf8               $hasString
   #73 = Utf8               $hasString$
   #74 = NameAndType        #73:#69       // $hasString$:(Lorg/sireum/Immutable;)Z
   #75 = InterfaceMethodref #61.#74       // org/sireum/Immutable.$hasString$:(Lorg/sireum/Immutable;)Z
   #76 = Utf8               $clone
   #77 = Utf8               ()Lorg/sireum/$internal/ImmutableMarker;
   #78 = Utf8               org/sireum/$internal/ImmutableMarker
   #79 = Class              #78           // org/sireum/$internal/ImmutableMarker
   #80 = Utf8               $clone$
   #81 = Utf8               (Lorg/sireum/$internal/ImmutableMarker;)Lorg/sireum/$internal/ImmutableMarker;
   #82 = NameAndType        #80:#81       // $clone$:(Lorg/sireum/$internal/ImmutableMarker;)Lorg/sireum/$internal/ImmutableMarker;
   #83 = InterfaceMethodref #79.#82       // org/sireum/$internal/ImmutableMarker.$clone$:(Lorg/sireum/$internal/ImmutableMarker;)Lorg/sireum/$internal/ImmutableMarker;
   #84 = Utf8               description
   #85 = Utf8               ()Ljava/lang/String;
   #86 = NameAndType        #28:#29       // _description:Ljava/lang/String;
   #87 = Fieldref           #2.#86        // org/sireum/project/PublishInfo._description:Ljava/lang/String;
   #88 = Utf8               getDescription
   #89 = Utf8               url
   #90 = NameAndType        #30:#29       // _url:Ljava/lang/String;
   #91 = Fieldref           #2.#90        // org/sireum/project/PublishInfo._url:Ljava/lang/String;
   #92 = Utf8               getUrl
   #93 = Utf8               licenses
   #94 = Utf8               ()Lorg/sireum/IS;
   #95 = Utf8               ()Lorg/sireum/IS<Lorg/sireum/Z;Lorg/sireum/project/PublishInfo$License;>;
   #96 = NameAndType        #31:#32       // _licenses:Lorg/sireum/IS;
   #97 = Fieldref           #2.#96        // org/sireum/project/PublishInfo._licenses:Lorg/sireum/IS;
   #98 = Utf8               getLicenses
   #99 = Utf8               developers
  #100 = Utf8               ()Lorg/sireum/IS<Lorg/sireum/Z;Lorg/sireum/project/PublishInfo$Developer;>;
  #101 = NameAndType        #34:#32       // _developers:Lorg/sireum/IS;
  #102 = Fieldref           #2.#101       // org/sireum/project/PublishInfo._developers:Lorg/sireum/IS;
  #103 = Utf8               getDevelopers
  #104 = Utf8               toString
  #105 = NameAndType        #72:#67       // $hasString:()Z
  #106 = Methodref          #2.#105       // org/sireum/project/PublishInfo.$hasString:()Z
  #107 = Utf8               string$
  #108 = Utf8               (Lorg/sireum/DatatypeSig;)Ljava/lang/String;
  #109 = NameAndType        #107:#108     // string$:(Lorg/sireum/DatatypeSig;)Ljava/lang/String;
  #110 = InterfaceMethodref #6.#109       // org/sireum/DatatypeSig.string$:(Lorg/sireum/DatatypeSig;)Ljava/lang/String;
  #111 = Utf8               java/lang/StringBuilder
  #112 = Class              #111          // java/lang/StringBuilder
  #113 = Utf8               <init>
  #114 = Utf8               ()V
  #115 = NameAndType        #113:#114     // "<init>":()V
  #116 = Methodref          #112.#115     // java/lang/StringBuilder."<init>":()V
  #117 = Utf8               PublishInfo
  #118 = String             #117          // PublishInfo
  #119 = Utf8               append
  #120 = Utf8               (Ljava/lang/String;)Ljava/lang/StringBuilder;
  #121 = NameAndType        #119:#120     // append:(Ljava/lang/String;)Ljava/lang/StringBuilder;
  #122 = Methodref          #112.#121     // java/lang/StringBuilder.append:(Ljava/lang/String;)Ljava/lang/StringBuilder;
  #123 = Utf8               (C)Ljava/lang/StringBuilder;
  #124 = NameAndType        #119:#123     // append:(C)Ljava/lang/StringBuilder;
  #125 = Methodref          #112.#124     // java/lang/StringBuilder.append:(C)Ljava/lang/StringBuilder;
  #126 = Utf8               org/sireum/String$
  #127 = Class              #126          // org/sireum/String$
  #128 = Utf8               Lorg/sireum/String$;
  #129 = NameAndType        #44:#128      // MODULE$:Lorg/sireum/String$;
  #130 = Fieldref           #127.#129     // org/sireum/String$.MODULE$:Lorg/sireum/String$;
  #131 = Utf8               org/sireum/String
  #132 = Class              #131          // org/sireum/String
  #133 = NameAndType        #84:#85       // description:()Ljava/lang/String;
  #134 = Methodref          #2.#133       // org/sireum/project/PublishInfo.description:()Ljava/lang/String;
  #135 = Utf8               (Ljava/lang/String;)V
  #136 = NameAndType        #113:#135     // "<init>":(Ljava/lang/String;)V
  #137 = Methodref          #132.#136     // org/sireum/String."<init>":(Ljava/lang/String;)V
  #138 = Utf8               escape
  #139 = Utf8               (Ljava/lang/Object;)Ljava/lang/String;
  #140 = NameAndType        #138:#139     // escape:(Ljava/lang/Object;)Ljava/lang/String;
  #141 = Methodref          #127.#140     // org/sireum/String$.escape:(Ljava/lang/Object;)Ljava/lang/String;
  #142 = Utf8               ,
  #143 = String             #142          // ,
  #144 = NameAndType        #89:#85       // url:()Ljava/lang/String;
  #145 = Methodref          #2.#144       // org/sireum/project/PublishInfo.url:()Ljava/lang/String;
  #146 = NameAndType        #93:#94       // licenses:()Lorg/sireum/IS;
  #147 = Methodref          #2.#146       // org/sireum/project/PublishInfo.licenses:()Lorg/sireum/IS;
  #148 = NameAndType        #99:#94       // developers:()Lorg/sireum/IS;
  #149 = Methodref          #2.#148       // org/sireum/project/PublishInfo.developers:()Lorg/sireum/IS;
  #150 = NameAndType        #104:#85      // toString:()Ljava/lang/String;
  #151 = Methodref          #112.#150     // java/lang/StringBuilder.toString:()Ljava/lang/String;
  #152 = Utf8               sb
  #153 = Utf8               Ljava/lang/StringBuilder;
  #154 = Utf8               java/lang/String
  #155 = Class              #154          // java/lang/String
  #156 = Utf8               string
  #157 = Methodref          #2.#150       // org/sireum/project/PublishInfo.toString:()Ljava/lang/String;
  #158 = Utf8               apply
  #159 = Utf8               (Ljava/lang/String;)Ljava/lang/String;
  #160 = NameAndType        #158:#159     // apply:(Ljava/lang/String;)Ljava/lang/String;
  #161 = Methodref          #127.#160     // org/sireum/String$.apply:(Ljava/lang/String;)Ljava/lang/String;
  #162 = Utf8               hashCode$lzycompute
  #163 = Utf8               ()I
  #164 = NameAndType        #36:#37       // bitmap$0:B
  #165 = Fieldref           #2.#164       // org/sireum/project/PublishInfo.bitmap$0:B
  #166 = NameAndType        #66:#67       // $hasEquals:()Z
  #167 = Methodref          #2.#166       // org/sireum/project/PublishInfo.$hasEquals:()Z
  #168 = NameAndType        #23:#163      // hashCode:()I
  #169 = Methodref          #4.#168       // java/lang/Object.hashCode:()I
  #170 = Utf8               scala/package$
  #171 = Class              #170          // scala/package$
  #172 = Utf8               Lscala/package$;
  #173 = NameAndType        #44:#172      // MODULE$:Lscala/package$;
  #174 = Fieldref           #171.#173     // scala/package$.MODULE$:Lscala/package$;
  #175 = Utf8               Seq
  #176 = Utf8               ()Lscala/collection/immutable/Seq$;
  #177 = NameAndType        #175:#176     // Seq:()Lscala/collection/immutable/Seq$;
  #178 = Methodref          #171.#177     // scala/package$.Seq:()Lscala/collection/immutable/Seq$;
  #179 = Utf8               scala/runtime/ScalaRunTime$
  #180 = Class              #179          // scala/runtime/ScalaRunTime$
  #181 = Utf8               Lscala/runtime/ScalaRunTime$;
  #182 = NameAndType        #44:#181      // MODULE$:Lscala/runtime/ScalaRunTime$;
  #183 = Fieldref           #180.#182     // scala/runtime/ScalaRunTime$.MODULE$:Lscala/runtime/ScalaRunTime$;
  #184 = Utf8               getClass
  #185 = Utf8               ()Ljava/lang/Class;
  #186 = NameAndType        #184:#185     // getClass:()Ljava/lang/Class;
  #187 = Methodref          #2.#186       // org/sireum/project/PublishInfo.getClass:()Ljava/lang/Class;
  #188 = Utf8               java/lang/Class
  #189 = Class              #188          // java/lang/Class
  #190 = Utf8               getName
  #191 = NameAndType        #190:#85      // getName:()Ljava/lang/String;
  #192 = Methodref          #189.#191     // java/lang/Class.getName:()Ljava/lang/String;
  #193 = Utf8               genericWrapArray
  #194 = Utf8               (Ljava/lang/Object;)Lscala/collection/immutable/ArraySeq;
  #195 = NameAndType        #193:#194     // genericWrapArray:(Ljava/lang/Object;)Lscala/collection/immutable/ArraySeq;
  #196 = Methodref          #180.#195     // scala/runtime/ScalaRunTime$.genericWrapArray:(Ljava/lang/Object;)Lscala/collection/immutable/ArraySeq;
  #197 = Utf8               scala/collection/immutable/Seq$
  #198 = Class              #197          // scala/collection/immutable/Seq$
  #199 = Utf8               (Lscala/collection/immutable/Seq;)Lscala/collection/SeqOps;
  #200 = NameAndType        #158:#199     // apply:(Lscala/collection/immutable/Seq;)Lscala/collection/SeqOps;
  #201 = Methodref          #198.#200     // scala/collection/immutable/Seq$.apply:(Lscala/collection/immutable/Seq;)Lscala/collection/SeqOps;
  #202 = Utf8               scala/collection/Seq
  #203 = Class              #202          // scala/collection/Seq
  #204 = InterfaceMethodref #203.#168     // scala/collection/Seq.hashCode:()I
  #205 = NameAndType        #23:#24       // hashCode:I
  #206 = Fieldref           #2.#205       // org/sireum/project/PublishInfo.hashCode:I
  #207 = Utf8               java/lang/Throwable
  #208 = Class              #207          // java/lang/Throwable
  #209 = NameAndType        #162:#163     // hashCode$lzycompute:()I
  #210 = Methodref          #2.#209       // org/sireum/project/PublishInfo.hashCode$lzycompute:()I
  #211 = Utf8               equals
  #212 = Utf8               (Ljava/lang/Object;)Z
  #213 = NameAndType        #211:#212     // equals:(Ljava/lang/Object;)Z
  #214 = Methodref          #4.#213       // java/lang/Object.equals:(Ljava/lang/Object;)Z
  #215 = Methodref          #2.#168       // org/sireum/project/PublishInfo.hashCode:()I
  #216 = Utf8               Ljava/lang/Object;
  #217 = Utf8               org/sireum/IS
  #218 = Class              #217          // org/sireum/IS
  #219 = Utf8               (Ljava/lang/String;Ljava/lang/String;Lorg/sireum/IS;Lorg/sireum/IS;)Lorg/sireum/project/PublishInfo;
  #220 = Utf8               (Ljava/lang/String;Ljava/lang/String;Lorg/sireum/IS<Lorg/sireum/Z;Lorg/sireum/project/PublishInfo$License;>;Lorg/sireum/IS<Lorg/sireum/Z;Lorg/sireum/project/PublishInfo$Developer;>;)Lorg/sireum/project/PublishInfo;
  #221 = Utf8               (Ljava/lang/String;Ljava/lang/String;Lorg/sireum/IS;Lorg/sireum/IS;)V
  #222 = NameAndType        #113:#221     // "<init>":(Ljava/lang/String;Ljava/lang/String;Lorg/sireum/IS;Lorg/sireum/IS;)V
  #223 = Methodref          #2.#222       // org/sireum/project/PublishInfo."<init>":(Ljava/lang/String;Ljava/lang/String;Lorg/sireum/IS;Lorg/sireum/IS;)V
  #224 = Utf8               apply$default$1
  #225 = Utf8               apply$default$2
  #226 = Utf8               apply$default$3
  #227 = Utf8               apply$default$4
  #228 = Utf8               $content$lzycompute
  #229 = Utf8               ()Lscala/collection/immutable/Seq;
  #230 = Utf8               ()Lscala/collection/immutable/Seq<Lscala/Tuple2<Ljava/lang/String;Ljava/lang/Object;>;>;
  #231 = Utf8               scala/Tuple2
  #232 = Class              #231          // scala/Tuple2
  #233 = Utf8               type
  #234 = String             #233          // type
  #235 = Utf8               List
  #236 = Utf8               ()Lscala/collection/immutable/List$;
  #237 = NameAndType        #235:#236     // List:()Lscala/collection/immutable/List$;
  #238 = Methodref          #171.#237     // scala/package$.List:()Lscala/collection/immutable/List$;
  #239 = Utf8               org
  #240 = String             #239          // org
  #241 = Utf8               sireum
  #242 = String             #241          // sireum
  #243 = Utf8               project
  #244 = String             #243          // project
  #245 = Utf8               [Ljava/lang/Object;
  #246 = Class              #245          // "[Ljava/lang/Object;"
  #247 = Utf8               wrapRefArray
  #248 = Utf8               ([Ljava/lang/Object;)Lscala/collection/immutable/ArraySeq;
  #249 = NameAndType        #247:#248     // wrapRefArray:([Ljava/lang/Object;)Lscala/collection/immutable/ArraySeq;
  #250 = Methodref          #180.#249     // scala/runtime/ScalaRunTime$.wrapRefArray:([Ljava/lang/Object;)Lscala/collection/immutable/ArraySeq;
  #251 = Utf8               scala/collection/immutable/List$
  #252 = Class              #251          // scala/collection/immutable/List$
  #253 = Utf8               (Lscala/collection/immutable/Seq;)Ljava/lang/Object;
  #254 = NameAndType        #158:#253     // apply:(Lscala/collection/immutable/Seq;)Ljava/lang/Object;
  #255 = Methodref          #252.#254     // scala/collection/immutable/List$.apply:(Lscala/collection/immutable/Seq;)Ljava/lang/Object;
  #256 = Utf8               (Ljava/lang/Object;Ljava/lang/Object;)V
  #257 = NameAndType        #113:#256     // "<init>":(Ljava/lang/Object;Ljava/lang/Object;)V
  #258 = Methodref          #232.#257     // scala/Tuple2."<init>":(Ljava/lang/Object;Ljava/lang/Object;)V
  #259 = String             #84           // description
  #260 = String             #89           // url
  #261 = String             #93           // licenses
  #262 = String             #99           // developers
  #263 = Utf8               scala/collection/immutable/Seq
  #264 = Class              #263          // scala/collection/immutable/Seq
  #265 = NameAndType        #25:#26       // $content:Lscala/collection/immutable/Seq;
  #266 = Fieldref           #2.#265       // org/sireum/project/PublishInfo.$content:Lscala/collection/immutable/Seq;
  #267 = NameAndType        #228:#229     // $content$lzycompute:()Lscala/collection/immutable/Seq;
  #268 = Methodref          #2.#267       // org/sireum/project/PublishInfo.$content$lzycompute:()Lscala/collection/immutable/Seq;
  #269 = Utf8               ()Ljava/lang/Object;
  #270 = NameAndType        #76:#77       // $clone:()Lorg/sireum/$internal/ImmutableMarker;
  #271 = Methodref          #2.#270       // org/sireum/project/PublishInfo.$clone:()Lorg/sireum/$internal/ImmutableMarker;
  #272 = Utf8               (Ljava/lang/String;Ljava/lang/String;Lorg/sireum/IS<Lorg/sireum/Z;Lorg/sireum/project/PublishInfo$License;>;Lorg/sireum/IS<Lorg/sireum/Z;Lorg/sireum/project/PublishInfo$Developer;>;)V
  #273 = Utf8               __description
  #274 = Utf8               __url
  #275 = Utf8               __licenses
  #276 = Utf8               __developers
  #277 = Methodref          #4.#115       // java/lang/Object."<init>":()V
  #278 = Utf8               $init$
  #279 = Utf8               (Lorg/sireum/$internal/ImmutableMarker;)V
  #280 = NameAndType        #278:#279     // $init$:(Lorg/sireum/$internal/ImmutableMarker;)V
  #281 = InterfaceMethodref #79.#280      // org/sireum/$internal/ImmutableMarker.$init$:(Lorg/sireum/$internal/ImmutableMarker;)V
  #282 = Utf8               (Lorg/sireum/Immutable;)V
  #283 = NameAndType        #278:#282     // $init$:(Lorg/sireum/Immutable;)V
  #284 = InterfaceMethodref #61.#283      // org/sireum/Immutable.$init$:(Lorg/sireum/Immutable;)V
  #285 = Utf8               (Lorg/sireum/DatatypeSig;)V
  #286 = NameAndType        #278:#285     // $init$:(Lorg/sireum/DatatypeSig;)V
  #287 = InterfaceMethodref #6.#286       // org/sireum/DatatypeSig.$init$:(Lorg/sireum/DatatypeSig;)V
  #288 = Utf8               Signature
  #289 = Utf8               Code
  #290 = Utf8               LocalVariableTable
  #291 = Utf8               MethodParameters
  #292 = Utf8               LineNumberTable
  #293 = Utf8               StackMapTable
  #294 = Utf8               InnerClasses
  #295 = Utf8               SourceFile
  #296 = Utf8               RuntimeVisibleAnnotations
  #297 = Utf8               ScalaInlineInfo
  #298 = Utf8               ScalaSig
{
  private int hashCode;
    descriptor: I
    flags: (0x0002) ACC_PRIVATE

  private scala.collection.immutable.Seq<scala.Tuple2<java.lang.String, java.lang.Object>> $content;
    descriptor: Lscala/collection/immutable/Seq;
    flags: (0x0002) ACC_PRIVATE
    Signature: #27                          // Lscala/collection/immutable/Seq<Lscala/Tuple2<Ljava/lang/String;Ljava/lang/Object;>;>;

  private final java.lang.String _description;
    descriptor: Ljava/lang/String;
    flags: (0x0012) ACC_PRIVATE, ACC_FINAL

  private final java.lang.String _url;
    descriptor: Ljava/lang/String;
    flags: (0x0012) ACC_PRIVATE, ACC_FINAL

  private final org.sireum.IS<org.sireum.Z, org.sireum.project.PublishInfo$License> _licenses;
    descriptor: Lorg/sireum/IS;
    flags: (0x0012) ACC_PRIVATE, ACC_FINAL
    Signature: #33                          // Lorg/sireum/IS<Lorg/sireum/Z;Lorg/sireum/project/PublishInfo$License;>;

  private final org.sireum.IS<org.sireum.Z, org.sireum.project.PublishInfo$Developer> _developers;
    descriptor: Lorg/sireum/IS;
    flags: (0x0012) ACC_PRIVATE, ACC_FINAL
    Signature: #35                          // Lorg/sireum/IS<Lorg/sireum/Z;Lorg/sireum/project/PublishInfo$Developer;>;

  private volatile byte bitmap$0;
    descriptor: B
    flags: (0x0042) ACC_PRIVATE, ACC_VOLATILE

  public static scala.Some<scala.Tuple4<org.sireum.String, org.sireum.String, org.sireum.IS<org.sireum.Z, org.sireum.project.PublishInfo$License>, org.sireum.IS<org.sireum.Z, org.sireum.project.PublishInfo$Developer>>> unapply(org.sireum.project.PublishInfo);
    descriptor: (Lorg/sireum/project/PublishInfo;)Lscala/Some;
    flags: (0x0009) ACC_PUBLIC, ACC_STATIC
    Code:
      stack=2, locals=1, args_size=1
         0: getstatic     #47                 // Field org/sireum/project/PublishInfo$.MODULE$:Lorg/sireum/project/PublishInfo$;
         3: aload_0
         4: invokevirtual #49                 // Method org/sireum/project/PublishInfo$.unapply:(Lorg/sireum/project/PublishInfo;)Lscala/Some;
         7: areturn
      LocalVariableTable:
        Start  Length  Slot  Name   Signature
            0       8     0     o   Lorg/sireum/project/PublishInfo;
    Signature: #40                          // (Lorg/sireum/project/PublishInfo;)Lscala/Some<Lscala/Tuple4<Lorg/sireum/String;Lorg/sireum/String;Lorg/sireum/IS<Lorg/sireum/Z;Lorg/sireum/project/PublishInfo$License;>;Lorg/sireum/IS<Lorg/sireum/Z;Lorg/sireum/project/PublishInfo$Developer;>;>;>;
    MethodParameters:
      Name                           Flags
      o                              final

  public org.sireum.Z hash();
    descriptor: ()Lorg/sireum/Z;
    flags: (0x0001) ACC_PUBLIC
    Code:
      stack=1, locals=1, args_size=1
         0: aload_0
         1: invokestatic  #56                 // InterfaceMethod org/sireum/DatatypeSig.hash$:(Lorg/sireum/DatatypeSig;)Lorg/sireum/Z;
         4: areturn
      LineNumberTable:
        line 173: 0
      LocalVariableTable:
        Start  Length  Slot  Name   Signature
            0       5     0  this   Lorg/sireum/project/PublishInfo;

  public final scala.runtime.Nothing$ $cannotMixImmutableAndMutable();
    descriptor: ()Lscala/runtime/Nothing$;
    flags: (0x0011) ACC_PUBLIC, ACC_FINAL
    Code:
      stack=1, locals=1, args_size=1
         0: aload_0
         1: invokestatic  #65                 // InterfaceMethod org/sireum/Immutable.$cannotMixImmutableAndMutable$:(Lorg/sireum/Immutable;)Lscala/runtime/Nothing$;
         4: areturn
      LineNumberTable:
        line 173: 0
      LocalVariableTable:
        Start  Length  Slot  Name   Signature
            0       5     0  this   Lorg/sireum/project/PublishInfo;

  public boolean $hasEquals();
    descriptor: ()Z
    flags: (0x0001) ACC_PUBLIC
    Code:
      stack=1, locals=1, args_size=1
         0: aload_0
         1: invokestatic  #71                 // InterfaceMethod org/sireum/Immutable.$hasEquals$:(Lorg/sireum/Immutable;)Z
         4: ireturn
      LineNumberTable:
        line 173: 0
      LocalVariableTable:
        Start  Length  Slot  Name   Signature
            0       5     0  this   Lorg/sireum/project/PublishInfo;

  public boolean $hasString();
    descriptor: ()Z
    flags: (0x0001) ACC_PUBLIC
    Code:
      stack=1, locals=1, args_size=1
         0: aload_0
         1: invokestatic  #75                 // InterfaceMethod org/sireum/Immutable.$hasString$:(Lorg/sireum/Immutable;)Z
         4: ireturn
      LineNumberTable:
        line 173: 0
      LocalVariableTable:
        Start  Length  Slot  Name   Signature
            0       5     0  this   Lorg/sireum/project/PublishInfo;

  public org.sireum.$internal.ImmutableMarker $clone();
    descriptor: ()Lorg/sireum/$internal/ImmutableMarker;
    flags: (0x0001) ACC_PUBLIC
    Code:
      stack=1, locals=1, args_size=1
         0: aload_0
         1: invokestatic  #83                 // InterfaceMethod org/sireum/$internal/ImmutableMarker.$clone$:(Lorg/sireum/$internal/ImmutableMarker;)Lorg/sireum/$internal/ImmutableMarker;
         4: areturn
      LineNumberTable:
        line 173: 0
      LocalVariableTable:
        Start  Length  Slot  Name   Signature
            0       5     0  this   Lorg/sireum/project/PublishInfo;

  public java.lang.String description();
    descriptor: ()Ljava/lang/String;
    flags: (0x0001) ACC_PUBLIC
    Code:
      stack=1, locals=1, args_size=1
         0: aload_0
         1: getfield      #87                 // Field _description:Ljava/lang/String;
         4: areturn
      LineNumberTable:
        line 173: 0
      LocalVariableTable:
        Start  Length  Slot  Name   Signature
            0       5     0  this   Lorg/sireum/project/PublishInfo;

  public java.lang.String getDescription();
    descriptor: ()Ljava/lang/String;
    flags: (0x0001) ACC_PUBLIC
    Code:
      stack=1, locals=1, args_size=1
         0: aload_0
         1: getfield      #87                 // Field _description:Ljava/lang/String;
         4: areturn
      LineNumberTable:
        line 173: 0
      LocalVariableTable:
        Start  Length  Slot  Name   Signature
            0       5     0  this   Lorg/sireum/project/PublishInfo;

  public java.lang.String url();
    descriptor: ()Ljava/lang/String;
    flags: (0x0001) ACC_PUBLIC
    Code:
      stack=1, locals=1, args_size=1
         0: aload_0
         1: getfield      #91                 // Field _url:Ljava/lang/String;
         4: areturn
      LineNumberTable:
        line 173: 0
      LocalVariableTable:
        Start  Length  Slot  Name   Signature
            0       5     0  this   Lorg/sireum/project/PublishInfo;

  public java.lang.String getUrl();
    descriptor: ()Ljava/lang/String;
    flags: (0x0001) ACC_PUBLIC
    Code:
      stack=1, locals=1, args_size=1
         0: aload_0
         1: getfield      #91                 // Field _url:Ljava/lang/String;
         4: areturn
      LineNumberTable:
        line 173: 0
      LocalVariableTable:
        Start  Length  Slot  Name   Signature
            0       5     0  this   Lorg/sireum/project/PublishInfo;

  public org.sireum.IS<org.sireum.Z, org.sireum.project.PublishInfo$License> licenses();
    descriptor: ()Lorg/sireum/IS;
    flags: (0x0001) ACC_PUBLIC
    Code:
      stack=1, locals=1, args_size=1
         0: aload_0
         1: getfield      #97                 // Field _licenses:Lorg/sireum/IS;
         4: areturn
      LineNumberTable:
        line 173: 0
      LocalVariableTable:
        Start  Length  Slot  Name   Signature
            0       5     0  this   Lorg/sireum/project/PublishInfo;
    Signature: #95                          // ()Lorg/sireum/IS<Lorg/sireum/Z;Lorg/sireum/project/PublishInfo$License;>;

  public org.sireum.IS<org.sireum.Z, org.sireum.project.PublishInfo$License> getLicenses();
    descriptor: ()Lorg/sireum/IS;
    flags: (0x0001) ACC_PUBLIC
    Code:
      stack=1, locals=1, args_size=1
         0: aload_0
         1: getfield      #97                 // Field _licenses:Lorg/sireum/IS;
         4: areturn
      LineNumberTable:
        line 173: 0
      LocalVariableTable:
        Start  Length  Slot  Name   Signature
            0       5     0  this   Lorg/sireum/project/PublishInfo;
    Signature: #95                          // ()Lorg/sireum/IS<Lorg/sireum/Z;Lorg/sireum/project/PublishInfo$License;>;

  public org.sireum.IS<org.sireum.Z, org.sireum.project.PublishInfo$Developer> developers();
    descriptor: ()Lorg/sireum/IS;
    flags: (0x0001) ACC_PUBLIC
    Code:
      stack=1, locals=1, args_size=1
         0: aload_0
         1: getfield      #102                // Field _developers:Lorg/sireum/IS;
         4: areturn
      LineNumberTable:
        line 173: 0
      LocalVariableTable:
        Start  Length  Slot  Name   Signature
            0       5     0  this   Lorg/sireum/project/PublishInfo;
    Signature: #100                         // ()Lorg/sireum/IS<Lorg/sireum/Z;Lorg/sireum/project/PublishInfo$Developer;>;

  public org.sireum.IS<org.sireum.Z, org.sireum.project.PublishInfo$Developer> getDevelopers();
    descriptor: ()Lorg/sireum/IS;
    flags: (0x0001) ACC_PUBLIC
    Code:
      stack=1, locals=1, args_size=1
         0: aload_0
         1: getfield      #102                // Field _developers:Lorg/sireum/IS;
         4: areturn
      LineNumberTable:
        line 173: 0
      LocalVariableTable:
        Start  Length  Slot  Name   Signature
            0       5     0  this   Lorg/sireum/project/PublishInfo;
    Signature: #100                         // ()Lorg/sireum/IS<Lorg/sireum/Z;Lorg/sireum/project/PublishInfo$Developer;>;

  public java.lang.String toString();
    descriptor: ()Ljava/lang/String;
    flags: (0x0001) ACC_PUBLIC
    Code:
      stack=5, locals=2, args_size=1
         0: aload_0
         1: invokevirtual #106                // Method $hasString:()Z
         4: ifeq          14
         7: aload_0
         8: invokestatic  #110                // InterfaceMethod org/sireum/DatatypeSig.string$:(Lorg/sireum/DatatypeSig;)Ljava/lang/String;
        11: goto          142
        14: new           #112                // class java/lang/StringBuilder
        17: dup
        18: invokespecial #116                // Method java/lang/StringBuilder."<init>":()V
        21: astore_1
        22: aload_1
        23: ldc           #118                // String PublishInfo
        25: invokevirtual #122                // Method java/lang/StringBuilder.append:(Ljava/lang/String;)Ljava/lang/StringBuilder;
        28: pop
        29: aload_1
        30: bipush        40
        32: invokevirtual #125                // Method java/lang/StringBuilder.append:(C)Ljava/lang/StringBuilder;
        35: pop
        36: aload_1
        37: getstatic     #130                // Field org/sireum/String$.MODULE$:Lorg/sireum/String$;
        40: new           #132                // class org/sireum/String
        43: dup
        44: aload_0
        45: invokevirtual #134                // Method description:()Ljava/lang/String;
        48: invokespecial #137                // Method org/sireum/String."<init>":(Ljava/lang/String;)V
        51: invokevirtual #141                // Method org/sireum/String$.escape:(Ljava/lang/Object;)Ljava/lang/String;
        54: invokevirtual #122                // Method java/lang/StringBuilder.append:(Ljava/lang/String;)Ljava/lang/StringBuilder;
        57: pop
        58: aload_1
        59: ldc           #143                // String ,
        61: invokevirtual #122                // Method java/lang/StringBuilder.append:(Ljava/lang/String;)Ljava/lang/StringBuilder;
        64: pop
        65: aload_1
        66: getstatic     #130                // Field org/sireum/String$.MODULE$:Lorg/sireum/String$;
        69: new           #132                // class org/sireum/String
        72: dup
        73: aload_0
        74: invokevirtual #145                // Method url:()Ljava/lang/String;
        77: invokespecial #137                // Method org/sireum/String."<init>":(Ljava/lang/String;)V
        80: invokevirtual #141                // Method org/sireum/String$.escape:(Ljava/lang/Object;)Ljava/lang/String;
        83: invokevirtual #122                // Method java/lang/StringBuilder.append:(Ljava/lang/String;)Ljava/lang/StringBuilder;
        86: pop
        87: aload_1
        88: ldc           #143                // String ,
        90: invokevirtual #122                // Method java/lang/StringBuilder.append:(Ljava/lang/String;)Ljava/lang/StringBuilder;
        93: pop
        94: aload_1
        95: getstatic     #130                // Field org/sireum/String$.MODULE$:Lorg/sireum/String$;
        98: aload_0
        99: invokevirtual #147                // Method licenses:()Lorg/sireum/IS;
       102: invokevirtual #141                // Method org/sireum/String$.escape:(Ljava/lang/Object;)Ljava/lang/String;
       105: invokevirtual #122                // Method java/lang/StringBuilder.append:(Ljava/lang/String;)Ljava/lang/StringBuilder;
       108: pop
       109: aload_1
       110: ldc           #143                // String ,
       112: invokevirtual #122                // Method java/lang/StringBuilder.append:(Ljava/lang/String;)Ljava/lang/StringBuilder;
       115: pop
       116: aload_1
       117: getstatic     #130                // Field org/sireum/String$.MODULE$:Lorg/sireum/String$;
       120: aload_0
       121: invokevirtual #149                // Method developers:()Lorg/sireum/IS;
       124: invokevirtual #141                // Method org/sireum/String$.escape:(Ljava/lang/Object;)Ljava/lang/String;
       127: invokevirtual #122                // Method java/lang/StringBuilder.append:(Ljava/lang/String;)Ljava/lang/StringBuilder;
       130: pop
       131: aload_1
       132: bipush        41
       134: invokevirtual #125                // Method java/lang/StringBuilder.append:(C)Ljava/lang/StringBuilder;
       137: pop
       138: aload_1
       139: invokevirtual #151                // Method java/lang/StringBuilder.toString:()Ljava/lang/String;
       142: areturn
      StackMapTable: number_of_entries = 2
        frame_type = 14 /* same */
        frame_type = 247 /* same_locals_1_stack_item_frame_extended */
          offset_delta = 127
          stack = [ class java/lang/String ]
      LineNumberTable:
        line 173: 0
      LocalVariableTable:
        Start  Length  Slot  Name   Signature
           22     120     1    sb   Ljava/lang/StringBuilder;
            0     143     0  this   Lorg/sireum/project/PublishInfo;

  public java.lang.String string();
    descriptor: ()Ljava/lang/String;
    flags: (0x0001) ACC_PUBLIC
    Code:
      stack=2, locals=1, args_size=1
         0: aload_0
         1: invokevirtual #106                // Method $hasString:()Z
         4: ifeq          14
         7: aload_0
         8: invokestatic  #110                // InterfaceMethod org/sireum/DatatypeSig.string$:(Lorg/sireum/DatatypeSig;)Ljava/lang/String;
        11: goto          24
        14: getstatic     #130                // Field org/sireum/String$.MODULE$:Lorg/sireum/String$;
        17: aload_0
        18: invokevirtual #157                // Method toString:()Ljava/lang/String;
        21: invokevirtual #161                // Method org/sireum/String$.apply:(Ljava/lang/String;)Ljava/lang/String;
        24: areturn
      StackMapTable: number_of_entries = 2
        frame_type = 14 /* same */
        frame_type = 73 /* same_locals_1_stack_item */
          stack = [ class java/lang/String ]
      LineNumberTable:
        line 173: 0
      LocalVariableTable:
        Start  Length  Slot  Name   Signature
            0      25     0  this   Lorg/sireum/project/PublishInfo;

  private int hashCode$lzycompute();
    descriptor: ()I
    flags: (0x0002) ACC_PRIVATE
    Code:
      stack=9, locals=2, args_size=1
         0: aload_0
         1: dup
         2: astore_1
         3: monitorenter
         4: aload_0
         5: getfield      #165                // Field bitmap$0:B
         8: iconst_1
         9: iand
        10: i2b
        11: iconst_0
        12: if_icmpne     123
        15: aload_0
        16: aload_0
        17: invokevirtual #167                // Method $hasEquals:()Z
        20: ifeq          30
        23: aload_0
        24: invokespecial #169                // Method java/lang/Object.hashCode:()I
        27: goto          109
        30: getstatic     #174                // Field scala/package$.MODULE$:Lscala/package$;
        33: invokevirtual #178                // Method scala/package$.Seq:()Lscala/collection/immutable/Seq$;
        36: getstatic     #183                // Field scala/runtime/ScalaRunTime$.MODULE$:Lscala/runtime/ScalaRunTime$;
        39: iconst_5
        40: anewarray     #4                  // class java/lang/Object
        43: dup
        44: iconst_0
        45: aload_0
        46: invokevirtual #187                // Method getClass:()Ljava/lang/Class;
        49: invokevirtual #192                // Method java/lang/Class.getName:()Ljava/lang/String;
        52: aastore
        53: dup
        54: iconst_1
        55: new           #132                // class org/sireum/String
        58: dup
        59: aload_0
        60: invokevirtual #134                // Method description:()Ljava/lang/String;
        63: invokespecial #137                // Method org/sireum/String."<init>":(Ljava/lang/String;)V
        66: aastore
        67: dup
        68: iconst_2
        69: new           #132                // class org/sireum/String
        72: dup
        73: aload_0
        74: invokevirtual #145                // Method url:()Ljava/lang/String;
        77: invokespecial #137                // Method org/sireum/String."<init>":(Ljava/lang/String;)V
        80: aastore
        81: dup
        82: iconst_3
        83: aload_0
        84: invokevirtual #147                // Method licenses:()Lorg/sireum/IS;
        87: aastore
        88: dup
        89: iconst_4
        90: aload_0
        91: invokevirtual #149                // Method developers:()Lorg/sireum/IS;
        94: aastore
        95: invokevirtual #196                // Method scala/runtime/ScalaRunTime$.genericWrapArray:(Ljava/lang/Object;)Lscala/collection/immutable/ArraySeq;
        98: invokevirtual #201                // Method scala/collection/immutable/Seq$.apply:(Lscala/collection/immutable/Seq;)Lscala/collection/SeqOps;
       101: checkcast     #203                // class scala/collection/Seq
       104: invokeinterface #204,  1          // InterfaceMethod scala/collection/Seq.hashCode:()I
       109: putfield      #206                // Field hashCode:I
       112: aload_0
       113: aload_0
       114: getfield      #165                // Field bitmap$0:B
       117: iconst_1
       118: ior
       119: i2b
       120: putfield      #165                // Field bitmap$0:B
       123: aload_1
       124: monitorexit
       125: goto          131
       128: aload_1
       129: monitorexit
       130: athrow
       131: aload_0
       132: getfield      #206                // Field hashCode:I
       135: ireturn
      Exception table:
         from    to  target type
             4   123   128   any
      StackMapTable: number_of_entries = 5
        frame_type = 255 /* full_frame */
          offset_delta = 30
          locals = [ class org/sireum/project/PublishInfo, class org/sireum/project/PublishInfo ]
          stack = [ class org/sireum/project/PublishInfo ]
        frame_type = 255 /* full_frame */
          offset_delta = 78
          locals = [ class org/sireum/project/PublishInfo, class org/sireum/project/PublishInfo ]
          stack = [ class org/sireum/project/PublishInfo, int ]
        frame_type = 13 /* same */
        frame_type = 68 /* same_locals_1_stack_item */
          stack = [ class java/lang/Throwable ]
        frame_type = 2 /* same */
      LineNumberTable:
        line 173: 0
      LocalVariableTable:
        Start  Length  Slot  Name   Signature
            0     136     0  this   Lorg/sireum/project/PublishInfo;

  public int hashCode();
    descriptor: ()I
    flags: (0x0001) ACC_PUBLIC
    Code:
      stack=2, locals=1, args_size=1
         0: aload_0
         1: getfield      #165                // Field bitmap$0:B
         4: iconst_1
         5: iand
         6: i2b
         7: iconst_0
         8: if_icmpne     18
        11: aload_0
        12: invokespecial #210                // Method hashCode$lzycompute:()I
        15: goto          22
        18: aload_0
        19: getfield      #206                // Field hashCode:I
        22: ireturn
      StackMapTable: number_of_entries = 2
        frame_type = 18 /* same */
        frame_type = 67 /* same_locals_1_stack_item */
          stack = [ int ]
      LineNumberTable:
        line 173: 0
      LocalVariableTable:
        Start  Length  Slot  Name   Signature
            0      23     0  this   Lorg/sireum/project/PublishInfo;

  public boolean equals(java.lang.Object);
    descriptor: (Ljava/lang/Object;)Z
    flags: (0x0001) ACC_PUBLIC
    Code:
      stack=2, locals=9, args_size=2
         0: aload_0
         1: invokevirtual #167                // Method $hasEquals:()Z
         4: ifeq          15
         7: aload_0
         8: aload_1
         9: invokespecial #214                // Method java/lang/Object.equals:(Ljava/lang/Object;)Z
        12: goto          201
        15: aload_0
        16: aload_1
        17: if_acmpne     24
        20: iconst_1
        21: goto          201
        24: aload_1
        25: astore_3
        26: aload_3
        27: instanceof    #2                  // class org/sireum/project/PublishInfo
        30: ifeq          192
        33: aload_3
        34: checkcast     #2                  // class org/sireum/project/PublishInfo
        37: astore        4
        39: aload_0
        40: invokevirtual #215                // Method hashCode:()I
        43: aload         4
        45: invokevirtual #215                // Method hashCode:()I
        48: if_icmpeq     55
        51: iconst_0
        52: goto          188
        55: aload_0
        56: invokevirtual #134                // Method description:()Ljava/lang/String;
        59: aload         4
        61: invokevirtual #134                // Method description:()Ljava/lang/String;
        64: astore        5
        66: dup
        67: ifnonnull     79
        70: pop
        71: aload         5
        73: ifnull        87
        76: goto          187
        79: aload         5
        81: invokevirtual #214                // Method java/lang/Object.equals:(Ljava/lang/Object;)Z
        84: ifeq          187
        87: aload_0
        88: invokevirtual #145                // Method url:()Ljava/lang/String;
        91: aload         4
        93: invokevirtual #145                // Method url:()Ljava/lang/String;
        96: astore        6
        98: dup
        99: ifnonnull     111
       102: pop
       103: aload         6
       105: ifnull        119
       108: goto          187
       111: aload         6
       113: invokevirtual #214                // Method java/lang/Object.equals:(Ljava/lang/Object;)Z
       116: ifeq          187
       119: aload_0
       120: invokevirtual #147                // Method licenses:()Lorg/sireum/IS;
       123: aload         4
       125: invokevirtual #147                // Method licenses:()Lorg/sireum/IS;
       128: astore        7
       130: dup
       131: ifnonnull     143
       134: pop
       135: aload         7
       137: ifnull        151
       140: goto          187
       143: aload         7
       145: invokevirtual #214                // Method java/lang/Object.equals:(Ljava/lang/Object;)Z
       148: ifeq          187
       151: aload_0
       152: invokevirtual #149                // Method developers:()Lorg/sireum/IS;
       155: aload         4
       157: invokevirtual #149                // Method developers:()Lorg/sireum/IS;
       160: astore        8
       162: dup
       163: ifnonnull     175
       166: pop
       167: aload         8
       169: ifnull        183
       172: goto          187
       175: aload         8
       177: invokevirtual #214                // Method java/lang/Object.equals:(Ljava/lang/Object;)Z
       180: ifeq          187
       183: iconst_1
       184: goto          188
       187: iconst_0
       188: istore_2
       189: goto          200
       192: goto          195
       195: iconst_0
       196: istore_2
       197: goto          200
       200: iload_2
       201: ireturn
      StackMapTable: number_of_entries = 17
        frame_type = 15 /* same */
        frame_type = 8 /* same */
        frame_type = 254 /* append */
          offset_delta = 30
          locals = [ top, class java/lang/Object, class org/sireum/project/PublishInfo ]
        frame_type = 255 /* full_frame */
          offset_delta = 23
          locals = [ class org/sireum/project/PublishInfo, class java/lang/Object, top, class java/lang/Object, class org/sireum/project/PublishInfo, class java/lang/String ]
          stack = [ class java/lang/String ]
        frame_type = 7 /* same */
        frame_type = 255 /* full_frame */
          offset_delta = 23
          locals = [ class org/sireum/project/PublishInfo, class java/lang/Object, top, class java/lang/Object, class org/sireum/project/PublishInfo, class java/lang/String, class java/lang/String ]
          stack = [ class java/lang/String ]
        frame_type = 7 /* same */
        frame_type = 255 /* full_frame */
          offset_delta = 23
          locals = [ class org/sireum/project/PublishInfo, class java/lang/Object, top, class java/lang/Object, class org/sireum/project/PublishInfo, class java/lang/String, class java/lang/String, class org/sireum/IS ]
          stack = [ class org/sireum/IS ]
        frame_type = 7 /* same */
        frame_type = 255 /* full_frame */
          offset_delta = 23
          locals = [ class org/sireum/project/PublishInfo, class java/lang/Object, top, class java/lang/Object, class org/sireum/project/PublishInfo, class java/lang/String, class java/lang/String, class org/sireum/IS, class org/sireum/IS ]
          stack = [ class org/sireum/IS ]
        frame_type = 7 /* same */
        frame_type = 248 /* chop */
          offset_delta = 3
        frame_type = 255 /* full_frame */
          offset_delta = 0
          locals = [ class org/sireum/project/PublishInfo, class java/lang/Object, top, class java/lang/Object, class org/sireum/project/PublishInfo ]
          stack = [ int ]
        frame_type = 250 /* chop */
          offset_delta = 3
        frame_type = 2 /* same */
        frame_type = 255 /* full_frame */
          offset_delta = 4
          locals = [ class org/sireum/project/PublishInfo, class java/lang/Object, int, class java/lang/Object ]
          stack = []
        frame_type = 255 /* full_frame */
          offset_delta = 0
          locals = [ class org/sireum/project/PublishInfo, class java/lang/Object ]
          stack = [ int ]
      LineNumberTable:
        line 173: 0
      LocalVariableTable:
        Start  Length  Slot  Name   Signature
            0     202     0  this   Lorg/sireum/project/PublishInfo;
            0     202     1     o   Ljava/lang/Object;
    MethodParameters:
      Name                           Flags
      o                              final

  public org.sireum.project.PublishInfo apply(java.lang.String, java.lang.String, org.sireum.IS<org.sireum.Z, org.sireum.project.PublishInfo$License>, org.sireum.IS<org.sireum.Z, org.sireum.project.PublishInfo$Developer>);
    descriptor: (Ljava/lang/String;Ljava/lang/String;Lorg/sireum/IS;Lorg/sireum/IS;)Lorg/sireum/project/PublishInfo;
    flags: (0x0001) ACC_PUBLIC
    Code:
      stack=6, locals=5, args_size=5
         0: new           #2                  // class org/sireum/project/PublishInfo
         3: dup
         4: aload_1
         5: aload_2
         6: aload_3
         7: aload         4
         9: invokespecial #223                // Method "<init>":(Ljava/lang/String;Ljava/lang/String;Lorg/sireum/IS;Lorg/sireum/IS;)V
        12: areturn
      LineNumberTable:
        line 173: 0
      LocalVariableTable:
        Start  Length  Slot  Name   Signature
            0      13     0  this   Lorg/sireum/project/PublishInfo;
            0      13     1 description   Ljava/lang/String;
            0      13     2   url   Ljava/lang/String;
            0      13     3 licenses   Lorg/sireum/IS;
            0      13     4 developers   Lorg/sireum/IS;
    Signature: #220                         // (Ljava/lang/String;Ljava/lang/String;Lorg/sireum/IS<Lorg/sireum/Z;Lorg/sireum/project/PublishInfo$License;>;Lorg/sireum/IS<Lorg/sireum/Z;Lorg/sireum/project/PublishInfo$Developer;>;)Lorg/sireum/project/PublishInfo;
    MethodParameters:
      Name                           Flags
      description                    final
      url                            final
      licenses                       final
      developers                     final

  public java.lang.String apply$default$1();
    descriptor: ()Ljava/lang/String;
    flags: (0x0001) ACC_PUBLIC
    Code:
      stack=1, locals=1, args_size=1
         0: aload_0
         1: invokevirtual #134                // Method description:()Ljava/lang/String;
         4: areturn
      LineNumberTable:
        line 173: 0
      LocalVariableTable:
        Start  Length  Slot  Name   Signature
            0       5     0  this   Lorg/sireum/project/PublishInfo;

  public java.lang.String apply$default$2();
    descriptor: ()Ljava/lang/String;
    flags: (0x0001) ACC_PUBLIC
    Code:
      stack=1, locals=1, args_size=1
         0: aload_0
         1: invokevirtual #145                // Method url:()Ljava/lang/String;
         4: areturn
      LineNumberTable:
        line 173: 0
      LocalVariableTable:
        Start  Length  Slot  Name   Signature
            0       5     0  this   Lorg/sireum/project/PublishInfo;

  public org.sireum.IS<org.sireum.Z, org.sireum.project.PublishInfo$License> apply$default$3();
    descriptor: ()Lorg/sireum/IS;
    flags: (0x0001) ACC_PUBLIC
    Code:
      stack=1, locals=1, args_size=1
         0: aload_0
         1: invokevirtual #147                // Method licenses:()Lorg/sireum/IS;
         4: areturn
      LineNumberTable:
        line 173: 0
      LocalVariableTable:
        Start  Length  Slot  Name   Signature
            0       5     0  this   Lorg/sireum/project/PublishInfo;
    Signature: #95                          // ()Lorg/sireum/IS<Lorg/sireum/Z;Lorg/sireum/project/PublishInfo$License;>;

  public org.sireum.IS<org.sireum.Z, org.sireum.project.PublishInfo$Developer> apply$default$4();
    descriptor: ()Lorg/sireum/IS;
    flags: (0x0001) ACC_PUBLIC
    Code:
      stack=1, locals=1, args_size=1
         0: aload_0
         1: invokevirtual #149                // Method developers:()Lorg/sireum/IS;
         4: areturn
      LineNumberTable:
        line 173: 0
      LocalVariableTable:
        Start  Length  Slot  Name   Signature
            0       5     0  this   Lorg/sireum/project/PublishInfo;
    Signature: #100                         // ()Lorg/sireum/IS<Lorg/sireum/Z;Lorg/sireum/project/PublishInfo$Developer;>;

  private scala.collection.immutable.Seq<scala.Tuple2<java.lang.String, java.lang.Object>> $content$lzycompute();
    descriptor: ()Lscala/collection/immutable/Seq;
    flags: (0x0002) ACC_PRIVATE
    Code:
      stack=15, locals=2, args_size=1
         0: aload_0
         1: dup
         2: astore_1
         3: monitorenter
         4: aload_0
         5: getfield      #165                // Field bitmap$0:B
         8: iconst_2
         9: iand
        10: i2b
        11: iconst_0
        12: if_icmpne     191
        15: aload_0
        16: getstatic     #174                // Field scala/package$.MODULE$:Lscala/package$;
        19: invokevirtual #178                // Method scala/package$.Seq:()Lscala/collection/immutable/Seq$;
        22: getstatic     #183                // Field scala/runtime/ScalaRunTime$.MODULE$:Lscala/runtime/ScalaRunTime$;
        25: iconst_5
        26: anewarray     #232                // class scala/Tuple2
        29: dup
        30: iconst_0
        31: new           #232                // class scala/Tuple2
        34: dup
        35: ldc           #234                // String type
        37: getstatic     #174                // Field scala/package$.MODULE$:Lscala/package$;
        40: invokevirtual #238                // Method scala/package$.List:()Lscala/collection/immutable/List$;
        43: getstatic     #183                // Field scala/runtime/ScalaRunTime$.MODULE$:Lscala/runtime/ScalaRunTime$;
        46: iconst_4
        47: anewarray     #155                // class java/lang/String
        50: dup
        51: iconst_0
        52: ldc           #240                // String org
        54: aastore
        55: dup
        56: iconst_1
        57: ldc           #242                // String sireum
        59: aastore
        60: dup
        61: iconst_2
        62: ldc           #244                // String project
        64: aastore
        65: dup
        66: iconst_3
        67: ldc           #118                // String PublishInfo
        69: aastore
        70: checkcast     #246                // class "[Ljava/lang/Object;"
        73: invokevirtual #250                // Method scala/runtime/ScalaRunTime$.wrapRefArray:([Ljava/lang/Object;)Lscala/collection/immutable/ArraySeq;
        76: invokevirtual #255                // Method scala/collection/immutable/List$.apply:(Lscala/collection/immutable/Seq;)Ljava/lang/Object;
        79: invokespecial #258                // Method scala/Tuple2."<init>":(Ljava/lang/Object;Ljava/lang/Object;)V
        82: aastore
        83: dup
        84: iconst_1
        85: new           #232                // class scala/Tuple2
        88: dup
        89: ldc_w         #259                // String description
        92: new           #132                // class org/sireum/String
        95: dup
        96: aload_0
        97: invokevirtual #134                // Method description:()Ljava/lang/String;
       100: invokespecial #137                // Method org/sireum/String."<init>":(Ljava/lang/String;)V
       103: invokespecial #258                // Method scala/Tuple2."<init>":(Ljava/lang/Object;Ljava/lang/Object;)V
       106: aastore
       107: dup
       108: iconst_2
       109: new           #232                // class scala/Tuple2
       112: dup
       113: ldc_w         #260                // String url
       116: new           #132                // class org/sireum/String
       119: dup
       120: aload_0
       121: invokevirtual #145                // Method url:()Ljava/lang/String;
       124: invokespecial #137                // Method org/sireum/String."<init>":(Ljava/lang/String;)V
       127: invokespecial #258                // Method scala/Tuple2."<init>":(Ljava/lang/Object;Ljava/lang/Object;)V
       130: aastore
       131: dup
       132: iconst_3
       133: new           #232                // class scala/Tuple2
       136: dup
       137: ldc_w         #261                // String licenses
       140: aload_0
       141: invokevirtual #147                // Method licenses:()Lorg/sireum/IS;
       144: invokespecial #258                // Method scala/Tuple2."<init>":(Ljava/lang/Object;Ljava/lang/Object;)V
       147: aastore
       148: dup
       149: iconst_4
       150: new           #232                // class scala/Tuple2
       153: dup
       154: ldc_w         #262                // String developers
       157: aload_0
       158: invokevirtual #149                // Method developers:()Lorg/sireum/IS;
       161: invokespecial #258                // Method scala/Tuple2."<init>":(Ljava/lang/Object;Ljava/lang/Object;)V
       164: aastore
       165: checkcast     #246                // class "[Ljava/lang/Object;"
       168: invokevirtual #250                // Method scala/runtime/ScalaRunTime$.wrapRefArray:([Ljava/lang/Object;)Lscala/collection/immutable/ArraySeq;
       171: invokevirtual #201                // Method scala/collection/immutable/Seq$.apply:(Lscala/collection/immutable/Seq;)Lscala/collection/SeqOps;
       174: checkcast     #264                // class scala/collection/immutable/Seq
       177: putfield      #266                // Field $content:Lscala/collection/immutable/Seq;
       180: aload_0
       181: aload_0
       182: getfield      #165                // Field bitmap$0:B
       185: iconst_2
       186: ior
       187: i2b
       188: putfield      #165                // Field bitmap$0:B
       191: aload_1
       192: monitorexit
       193: goto          199
       196: aload_1
       197: monitorexit
       198: athrow
       199: aload_0
       200: getfield      #266                // Field $content:Lscala/collection/immutable/Seq;
       203: areturn
      Exception table:
         from    to  target type
             4   191   196   any
      StackMapTable: number_of_entries = 3
        frame_type = 252 /* append */
          offset_delta = 191
          locals = [ class org/sireum/project/PublishInfo ]
        frame_type = 68 /* same_locals_1_stack_item */
          stack = [ class java/lang/Throwable ]
        frame_type = 2 /* same */
      LineNumberTable:
        line 173: 0
      LocalVariableTable:
        Start  Length  Slot  Name   Signature
            0     204     0  this   Lorg/sireum/project/PublishInfo;
    Signature: #230                         // ()Lscala/collection/immutable/Seq<Lscala/Tuple2<Ljava/lang/String;Ljava/lang/Object;>;>;

  public scala.collection.immutable.Seq<scala.Tuple2<java.lang.String, java.lang.Object>> $content();
    descriptor: ()Lscala/collection/immutable/Seq;
    flags: (0x0001) ACC_PUBLIC
    Code:
      stack=2, locals=1, args_size=1
         0: aload_0
         1: getfield      #165                // Field bitmap$0:B
         4: iconst_2
         5: iand
         6: i2b
         7: iconst_0
         8: if_icmpne     18
        11: aload_0
        12: invokespecial #268                // Method $content$lzycompute:()Lscala/collection/immutable/Seq;
        15: goto          22
        18: aload_0
        19: getfield      #266                // Field $content:Lscala/collection/immutable/Seq;
        22: areturn
      StackMapTable: number_of_entries = 2
        frame_type = 18 /* same */
        frame_type = 67 /* same_locals_1_stack_item */
          stack = [ class scala/collection/immutable/Seq ]
      LineNumberTable:
        line 173: 0
      LocalVariableTable:
        Start  Length  Slot  Name   Signature
            0      23     0  this   Lorg/sireum/project/PublishInfo;
    Signature: #230                         // ()Lscala/collection/immutable/Seq<Lscala/Tuple2<Ljava/lang/String;Ljava/lang/Object;>;>;

  public java.lang.Object $clone();
    descriptor: ()Ljava/lang/Object;
    flags: (0x1041) ACC_PUBLIC, ACC_BRIDGE, ACC_SYNTHETIC
    Code:
      stack=1, locals=1, args_size=1
         0: aload_0
         1: invokevirtual #271                // Method $clone:()Lorg/sireum/$internal/ImmutableMarker;
         4: areturn
      LineNumberTable:
        line 173: 0
      LocalVariableTable:
        Start  Length  Slot  Name   Signature
            0       5     0  this   Lorg/sireum/project/PublishInfo;

  public org.sireum.project.PublishInfo(java.lang.String, java.lang.String, org.sireum.IS<org.sireum.Z, org.sireum.project.PublishInfo$License>, org.sireum.IS<org.sireum.Z, org.sireum.project.PublishInfo$Developer>);
    descriptor: (Ljava/lang/String;Ljava/lang/String;Lorg/sireum/IS;Lorg/sireum/IS;)V
    flags: (0x0001) ACC_PUBLIC
    Code:
      stack=2, locals=5, args_size=5
         0: aload_0
         1: invokespecial #277                // Method java/lang/Object."<init>":()V
         4: aload_0
         5: invokestatic  #281                // InterfaceMethod org/sireum/$internal/ImmutableMarker.$init$:(Lorg/sireum/$internal/ImmutableMarker;)V
         8: aload_0
         9: invokestatic  #284                // InterfaceMethod org/sireum/Immutable.$init$:(Lorg/sireum/Immutable;)V
        12: aload_0
        13: invokestatic  #287                // InterfaceMethod org/sireum/DatatypeSig.$init$:(Lorg/sireum/DatatypeSig;)V
        16: aload_0
        17: aload_1
        18: putfield      #87                 // Field _description:Ljava/lang/String;
        21: aload_0
        22: aload_2
        23: putfield      #91                 // Field _url:Ljava/lang/String;
        26: aload_0
        27: aload_3
        28: putfield      #97                 // Field _licenses:Lorg/sireum/IS;
        31: aload_0
        32: aload         4
        34: putfield      #102                // Field _developers:Lorg/sireum/IS;
        37: return
      LineNumberTable:
        line 173: 0
      LocalVariableTable:
        Start  Length  Slot  Name   Signature
            0      38     0  this   Lorg/sireum/project/PublishInfo;
            0      38     1 __description   Ljava/lang/String;
            0      38     2 __url   Ljava/lang/String;
            0      38     3 __licenses   Lorg/sireum/IS;
            0      38     4 __developers   Lorg/sireum/IS;
    Signature: #272                         // (Ljava/lang/String;Ljava/lang/String;Lorg/sireum/IS<Lorg/sireum/Z;Lorg/sireum/project/PublishInfo$License;>;Lorg/sireum/IS<Lorg/sireum/Z;Lorg/sireum/project/PublishInfo$Developer;>;)V
    MethodParameters:
      Name                           Flags
      __description                  final
      __url                          final
      __licenses                     final
      __developers                   final
}
InnerClasses:
  public static final #13= #12 of #2;     // Developer=class org/sireum/project/PublishInfo$Developer of class org/sireum/project/PublishInfo
  public static #16= #15 of #2;           // Developer$=class org/sireum/project/PublishInfo$Developer$ of class org/sireum/project/PublishInfo
  public static final #19= #18 of #2;     // License=class org/sireum/project/PublishInfo$License of class org/sireum/project/PublishInfo
  public static #22= #21 of #2;           // License$=class org/sireum/project/PublishInfo$License$ of class org/sireum/project/PublishInfo
SourceFile: "Project.scala"
RuntimeVisibleAnnotations:
  0: #8(#9=s#10)
    scala.reflect.ScalaSignature(
      bytes="\u0006\u0005\t}c\u0001\u0002+V\u0005qC\u0001b\u001a\u0001\u0003\u0002\u0003\u0006I\u0001\u001b\u0005\tW\u0002\u0011\t\u0011)A\u0005Q\"AA\u000e\u0001B\u0001B\u0003%Q\u000e\u0003\u0006\u0003*\u0001\u0011\t\u0011)A\u0005\u00053Aq!!\u0003\u0001\t\u0003\u0011Y\u0003C\u0004\u00036\u0001\u0001\u000b\u0011\u00025\t\u000f\t5\u0001\u0001\"\u0001\u00022!9!q\u0007\u0001\u0005\u0002\u0005E\u0002bBA\u001b\u0001\u0001\u0006I\u0001\u001b\u0005\b\u0003o\u0001A\u0011AA\u0019\u0011\u001d\tI\u0004\u0001C\u0001\u0003cAqA!\u000f\u0001A\u0003%Q\u000eC\u0004\u0003\u0014\u0001!\tAa\u000f\t\u000f\tu\u0002\u0001\"\u0001\u0003<!A!q\b\u0001!\u0002\u0013\u0011I\u0002C\u0004\u0003\u0018\u0001!\tA!\u0011\t\u000f\t\r\u0003\u0001\"\u0001\u0003B!9\u0011\u0011\t\u0001\u0005B\u0005\r\u0003bBA*\u0001\u0011\u0005\u0013\u0011\u0007\u0005\u000b\u0003+\u0002\u0001R1A\u0005B\u0005]\u0003bBA0\u0001\u0011\u0005#Q\t\u0005\b\u00033\u0001A\u0011\u0001B%\u0011%\tY\bAI\u0001\n\u0003\ti\bC\u0005\u0002\u0014\u0002\t\n\u0011\"\u0001\u0002~!I\u0011Q\u0013\u0001\u0012\u0002\u0013\u0005!1\u000b\u0005\n\u0005/\u0002\u0011\u0013!C\u0001\u00053B!\"a&\u0001\u0011\u000b\u0007I\u0011IAM\u000f\u001d\t\u0019!\u0016E\u0001\u0003\u000b1a\u0001V+\t\u0002\u0005\u001d\u0001bBA\u0005;\u0011\u0005\u00111B\u0004\b\u0003\u001bi\u0002\u0012AA\b\r\u001d\t\u0019\"\bE\u0001\u0003+Aq!!\u0003!\t\u0003\t9\u0002C\u0004\u0002\u001a\u0001\"\t!a\u0007\t\u000f\u0005}\u0006\u0005\"\u0001\u0002B\u001a1\u00111C\u000f\u0003\u0003?A\u0011\"!\t%\u0005\u0003\u0005\u000b\u0011\u00025\t\u0011-$#\u0011!Q\u0001\n!D\u0011\"a\t%\u0005\u0003\u0005\u000b\u0011\u00025\t\u000f\u0005%A\u0005\"\u0001\u0002&!9\u0011Q\u0006\u0013!\u0002\u0013A\u0007bBA\u0018I\u0011\u0005\u0011\u0011\u0007\u0005\b\u0003g!C\u0011AA\u0019\u0011\u001d\t)\u0004\nQ\u0001\n!Dq!a\u000e%\t\u0003\t\t\u0004C\u0004\u0002:\u0011\"\t!!\r\t\u000f\u0005mB\u0005)A\u0005Q\"9\u0011Q\b\u0013\u0005\u0002\u0005E\u0002bBA I\u0011\u0005\u0011\u0011\u0007\u0005\b\u0003\u0003\"C\u0011IA\"\u0011\u001d\t\u0019\u0006\nC!\u0003cA!\"!\u0016%\u0011\u000b\u0007I\u0011IA,\u0011\u001d\ty\u0006\nC!\u0003CBq!!\u0007%\t\u0003\t\u0019\bC\u0005\u0002|\u0011\n\n\u0011\"\u0001\u0002~!I\u00111\u0013\u0013\u0012\u0002\u0013\u0005\u0011Q\u0010\u0005\n\u0003+#\u0013\u0013!C\u0001\u0003{B!\"a&%\u0011\u000b\u0007I\u0011IAM\u000f\u001d\t\t.\bE\u0001\u0003\'4q!!6\u001e\u0011\u0003\t9\u000eC\u0004\u0002\nq\"\t!!7\t\u000f\u0005eA\b\"\u0001\u0002\\\"9\u0011q\u0018\u001f\u0005\u0002\u0005}hABAk;\t\ty\u000eC\u0005\u0002b\u0002\u0013\t\u0011)A\u0005Q\"I\u0011\u0011\u0005!\u0003\u0002\u0003\u0006I\u0001\u001b\u0005\b\u0003\u0013\u0001E\u0011AAr\u0011\u001d\tI\u000f\u0011Q\u0001\n!Dq!a;A\t\u0003\t\t\u0004C\u0004\u0002n\u0002#\t!!\r\t\u000f\u00055\u0002\t)A\u0005Q\"9\u0011q\u0006!\u0005\u0002\u0005E\u0002bBA\u001a\u0001\u0012\u0005\u0011\u0011\u0007\u0005\b\u0003\u0003\u0002E\u0011IA\"\u0011\u001d\t\u0019\u0006\u0011C!\u0003cA!\"!\u0016A\u0011\u000b\u0007I\u0011IA,\u0011\u001d\ty\u0006\u0011C!\u0003_Dq!!\u0007A\t\u0003\t\u0019\u0010C\u0005\u0002|\u0001\u000b\n\u0011\"\u0001\u0002~!I\u00111\u0013!\u0012\u0002\u0013\u0005\u0011Q\u0010\u0005\u000b\u0003/\u0003\u0005R1A\u0005B\u0005e\u0005bBA\r;\u0011\u0005!q\u0001\u0005\b\u0003\u007fkB\u0011\u0001B\u000f\u0005-\u0001VO\u00197jg\"LeNZ8\u000b\u0005Y;\u0016a\u00029s_*,7\r\u001e\u0006\u00031f\u000baa]5sKVl\'\"\u0001.\u0002\u0007=\u0014xm\u0001\u0001\u0014\u0007\u0001i6\r\u0005\u0002_C6\tqLC\u0001a\u0003\u0015\u00198-\u00197b\u0013\t\u0011wL\u0001\u0004B]f\u0014VM\u001a\t\u0003I\u0016l\u0011aV\u0005\u0003M^\u00131\u0002R1uCRL\b/Z*jO\u0006iql\u00183fg\u000e\u0014\u0018\u000e\u001d;j_:\u0004\"\u0001Z5\n\u0005)<&AB*ue&tw-A\u0003`?V\u0014H.\u0001\u0006`?2L7-\u001a8tKN\u00042A\u001c=\u007f\u001d\tygO\u0004\u0002qk:\u0011\u0011\u000f^\u0007\u0002e*\u00111oW\u0001\u0007yI|w\u000e\u001e \n\u0003iK!\u0001W-\n\u0005]<\u0016a\u00029bG.\fw-Z\u0005\u0003sj\u00141!S*[\u0013\tYHP\u0001\u0007QC\u000e\\\u0017mZ3Ue\u0006LGO\u0003\u0002~/\u0006IA%\u001b8uKJt\u0017\r\u001c\t\u0003\u007f\u0012r1!!\u0001\u001d\u001b\u0005)\u0016a\u0003)vE2L7\u000f[%oM>\u00042!!\u0001\u001e\'\tiR,\u0001\u0004=S:LGO\u0010\u000b\u0003\u0003\u000b\tq\u0001T5dK:\u001cX\rE\u0002\u0002\u0012\u0001j\u0011!\b\u0002\b\u0019&\u001cWM\\:f\'\t\u0001S\f\u0006\u0002\u0002\u0010\u0005)\u0011\r\u001d9msRA\u0011QDA]\u0003w\u000bi\fE\u0002\u0002\u0012\u0011\u001a2\u0001J/d\u0003\u0019yvL\\1nK\u0006qql\u00183jgR\u0014\u0018NY;uS>tG\u0003CA\u000f\u0003O\tI#a\u000b\t\r\u0005\u0005\u0002\u00061\u0001i\u0011\u0015Y\u0007\u00061\u0001i\u0011\u0019\t\u0019\u0003\u000ba\u0001Q\u0006)qL\\1nK\u0006!a.Y7f+\u0005A\u0017aB4fi:\u000bW.Z\u0001\u0005?V\u0014H.A\u0002ve2\faaZ3u+Jd\u0017!D0eSN$(/\u001b2vi&|g.\u0001\u0007eSN$(/\u001b2vi&|g.A\bhKR$\u0015n\u001d;sS\n,H/[8o\u0003!!xn\u0015;sS:<GCAA#!\u0011\t9%!\u0015\u000e\u0005\u0005%#\u0002BA&\u0003\u001b\nA\u0001\\1oO*\u0011\u0011qJ\u0001\u0005U\u00064\u0018-C\u0002k\u0003\u0013\naa\u001d;sS:<\u0017\u0001\u00035bg\"\u001cu\u000eZ3\u0016\u0005\u0005e\u0003c\u00010\u0002\\%\u0019\u0011QL0\u0003\u0007%sG/\u0001\u0004fcV\fGn\u001d\u000b\u0005\u0003G\nI\u0007E\u0002_\u0003KJ1!a\u001a`\u0005\u001d\u0011un\u001c7fC:Dq!a\u001b6\u0001\u0004\ti\'A\u0001p!\rq\u0016qN\u0005\u0004\u0003cz&aA!osRA\u0011QDA;\u0003o\nI\b\u0003\u0005\u00020Y\u0002\n\u00111\u0001i\u0011!\t9D\u000eI\u0001\u0002\u0004A\u0007\u0002CA\u001fmA\u0005\t\u0019\u00015\u0002\u001f\u0005\u0004\b\u000f\\=%I\u00164\u0017-\u001e7uIE*\"!a +\u0007!\f\ti\u000b\u0002\u0002\u0004B!\u0011QQAH\u001b\t\t9I\u0003\u0003\u0002\n\u0006-\u0015!C;oG\",7m[3e\u0015\r\tiiX\u0001\u000bC:tw\u000e^1uS>t\u0017\u0002BAI\u0003\u000f\u0013\u0011#\u001e8dQ\u0016\u001c7.\u001a3WCJL\u0017M\\2f\u0003=\t\u0007\u000f\u001d7zI\u0011,g-Y;mi\u0012\u0012\u0014aD1qa2LH\u0005Z3gCVdG\u000fJ\u001a\u0002\u0011\u0011\u001awN\u001c;f]R,\"!a\'\u0011\r\u0005u\u0015QUAV\u001d\u0011\ty*a)\u000f\u0007E\f\t+C\u0001a\u0013\t9x,\u0003\u0003\u0002(\u0006%&aA*fc*\u0011qo\u0018\t\b=\u00065\u0016QIA7\u0013\r\tyk\u0018\u0002\u0007)V\u0004H.\u001a\u001a)\u0007\u0011\n\u0019\fE\u0002e\u0003kK1!a.X\u0005!!\u0017\r^1usB,\u0007BBA\u0018E\u0001\u0007\u0001\u000e\u0003\u0004\u00028\t\u0002\r\u0001\u001b\u0005\u0007\u0003{\u0011\u0003\u0019\u00015\u0002\u000fUt\u0017\r\u001d9msR!\u00111YAh!\u0015q\u0016QYAe\u0013\r\t9m\u0018\u0002\u0005\'>lW\r\u0005\u0004_\u0003\u0017D\u0007\u000e[\u0005\u0004\u0003\u001b|&A\u0002+va2,7\u0007C\u0004\u0002l\r\u0002\r!!\b\u0002\u0013\u0011+g/\u001a7pa\u0016\u0014\bcAA\ty\tIA)\u001a<fY>\u0004XM]\n\u0003yu#\"!a5\u0015\r\u0005u\u00171`A\u007f!\r\t\t\u0002Q\n\u0004\u0001v\u001b\u0017\u0001B0`S\u0012$b!!8\u0002f\u0006\u001d\bBBAq\u0007\u0002\u0007\u0001\u000e\u0003\u0004\u0002\"\r\u0003\r\u0001[\u0001\u0004?&$\u0017AA5e\u0003\u00159W\r^%e)\u0011\t\u0019\'!=\t\u000f\u0005-T\n1\u0001\u0002nQ1\u0011Q\\A{\u0003oD\u0001\"a;O!\u0003\u0005\r\u0001\u001b\u0005\t\u0003_q\u0005\u0013!a\u0001Q\"\u001a\u0001)a-\t\r\u0005-h\b1\u0001i\u0011\u0019\tyC\u0010a\u0001QR!!\u0011\u0001B\u0003!\u0015q\u0016Q\u0019B\u0002!\u0015q\u0016Q\u00165i\u0011\u001d\tYg\u0010a\u0001\u0003;$\"B!\u0003\u0003\f\t=!\u0011\u0003B\u000b!\r\t\t\u0001\u0001\u0005\u0007\u0005\u001b\u0011\u0006\u0019\u00015\u0002\u0017\u0011,7o\u0019:jaRLwN\u001c\u0005\u0007\u0003o\u0011\u0006\u0019\u00015\t\r\tM!\u000b1\u0001n\u0003!a\u0017nY3og\u0016\u001c\bb\u0002B\f%\u0002\u0007!\u0011D\u0001\u000bI\u00164X\r\\8qKJ\u001c\b\u0003\u00028y\u00057\u0001\"a !\u0015\t\t}!q\u0005\t\u0006=\u0006\u0015\'\u0011\u0005\t\t=\n\r\u0002\u000e[7\u0003\u001a%\u0019!QE0\u0003\rQ+\b\u000f\\35\u0011\u001d\tYg\u0015a\u0001\u0005\u0013\tAbX0eKZ,Gn\u001c9feN$\"B!\u0003\u0003.\t=\"\u0011\u0007B\u001a\u0011\u00159W\u00011\u0001i\u0011\u0015YW\u00011\u0001i\u0011\u0015aW\u00011\u0001n\u0011\u001d\u0011I#\u0002a\u0001\u00053\tAb\u00183fg\u000e\u0014\u0018\u000e\u001d;j_:\fabZ3u\t\u0016\u001c8M]5qi&|g.A\u0005`Y&\u001cWM\\:fgV\tQ.A\u0006hKRd\u0015nY3og\u0016\u001c\u0018aC0eKZ,Gn\u001c9feN,\"A!\u0007\u0002\u001b\u001d,G\u000fR3wK2|\u0007/\u001a:t)\u0011\t\u0019Ga\u0012\t\u000f\u0005-T\u00031\u0001\u0002nQQ!\u0011\u0002B&\u0005\u001b\u0012yE!\u0015\t\u0011\t5a\u0003%AA\u0002!D\u0001\"a\u000e\u0017!\u0003\u0005\r\u0001\u001b\u0005\t\u0005\'1\u0002\u0013!a\u0001[\"I!q\u0003\f\u0011\u0002\u0003\u0007!\u0011D\u000b\u0003\u0005+R3!\\AA\u0003=\t\u0007\u000f\u001d7zI\u0011,g-Y;mi\u0012\"TC\u0001B.U\u0011\u0011I\"!!)\u0007\u0001\t\u0019\f"
    )
  ScalaInlineInfo: length = 0x8B (unknown attribute)
   01 01 00 1B 00 3A 00 3B 01 00 4C 01 0D 01 00 4C
   00 4D 01 00 19 00 E5 01 00 E4 00 E5 01 00 42 00
   43 01 00 48 00 43 01 00 71 00 DD 01 00 9E 00 DB
   01 00 E0 00 55 01 00 E1 00 55 01 00 E2 00 5E 01
   00 E3 00 5E 01 00 54 00 55 01 00 63 00 5E 01 00
   D3 00 D4 01 00 58 00 55 01 00 67 00 5E 01 00 62
   00 5E 01 00 5C 00 55 01 00 33 00 34 01 00 17 00
   A3 01 00 A2 00 A3 01 00 5D 00 5E 01 00 9C 00 55
   01 00 68 00 55 01 00 59 00 55 01
  ScalaSig: length = 0x3 (unknown attribute)
   05 02 00
