Classfile /Users/mw/Projects/slang-braindump/.jar/jar8/assemble/slang-braindump/assemble/content/org/sireum/ops/COps$.class
  Last modified May 29, 2022; size 4497 bytes
  SHA-256 checksum e684bb9bb3b9b10375c2c76772bcdd1bc9dd0f1187bf2948a66559931e70823c
  Compiled from "COps.scala"
public final class org.sireum.ops.COps$
  minor version: 0
  major version: 52
  flags: (0x0031) ACC_PUBLIC, ACC_FINAL, ACC_SUPER
  this_class: #2                          // org/sireum/ops/COps$
  super_class: #4                         // java/lang/Object
  interfaces: 0, fields: 1, methods: 7, attributes: 3
Constant pool:
    #1 = Utf8               org/sireum/ops/COps$
    #2 = Class              #1            // org/sireum/ops/COps$
    #3 = Utf8               java/lang/Object
    #4 = Class              #3            // java/lang/Object
    #5 = Utf8               COps.scala
    #6 = Utf8               MODULE$
    #7 = Utf8               Lorg/sireum/ops/COps$;
    #8 = Utf8               <clinit>
    #9 = Utf8               ()V
   #10 = Utf8               <init>
   #11 = NameAndType        #10:#9        // "<init>":()V
   #12 = Methodref          #2.#11        // org/sireum/ops/COps$."<init>":()V
   #13 = NameAndType        #6:#7         // MODULE$:Lorg/sireum/ops/COps$;
   #14 = Fieldref           #2.#13        // org/sireum/ops/COps$.MODULE$:Lorg/sireum/ops/COps$;
   #15 = Utf8               c2hex
   #16 = Utf8               (I)Lorg/sireum/Option;
   #17 = Utf8               (I)Lorg/sireum/Option<Lorg/sireum/C;>;
   #18 = Utf8               c
   #19 = Utf8               org/sireum/C$
   #20 = Class              #19           // org/sireum/C$
   #21 = Utf8               Lorg/sireum/C$;
   #22 = NameAndType        #6:#21        // MODULE$:Lorg/sireum/C$;
   #23 = Fieldref           #20.#22       // org/sireum/C$.MODULE$:Lorg/sireum/C$;
   #24 = Utf8               native$extension
   #25 = Utf8               (I)C
   #26 = NameAndType        #24:#25       // native$extension:(I)C
   #27 = Methodref          #20.#26       // org/sireum/C$.native$extension:(I)C
   #28 = Utf8               org/sireum/Some$
   #29 = Class              #28           // org/sireum/Some$
   #30 = Utf8               Lorg/sireum/Some$;
   #31 = NameAndType        #6:#30        // MODULE$:Lorg/sireum/Some$;
   #32 = Fieldref           #29.#31       // org/sireum/Some$.MODULE$:Lorg/sireum/Some$;
   #33 = Utf8               org/sireum/C
   #34 = Class              #33           // org/sireum/C
   #35 = Utf8               apply
   #36 = Utf8               (C)I
   #37 = NameAndType        #35:#36       // apply:(C)I
   #38 = Methodref          #20.#37       // org/sireum/C$.apply:(C)I
   #39 = Utf8               (I)V
   #40 = NameAndType        #10:#39       // "<init>":(I)V
   #41 = Methodref          #34.#40       // org/sireum/C."<init>":(I)V
   #42 = Utf8               (Ljava/lang/Object;)Lorg/sireum/Some;
   #43 = NameAndType        #35:#42       // apply:(Ljava/lang/Object;)Lorg/sireum/Some;
   #44 = Methodref          #29.#43       // org/sireum/Some$.apply:(Ljava/lang/Object;)Lorg/sireum/Some;
   #45 = Utf8               org/sireum/None$
   #46 = Class              #45           // org/sireum/None$
   #47 = Utf8               Lorg/sireum/None$;
   #48 = NameAndType        #6:#47        // MODULE$:Lorg/sireum/None$;
   #49 = Fieldref           #46.#48       // org/sireum/None$.MODULE$:Lorg/sireum/None$;
   #50 = Utf8               ()Lorg/sireum/None;
   #51 = NameAndType        #35:#50       // apply:()Lorg/sireum/None;
   #52 = Methodref          #46.#51       // org/sireum/None$.apply:()Lorg/sireum/None;
   #53 = Utf8               this
   #54 = Utf8               I
   #55 = Utf8               hex2c
   #56 = Utf8               (I)I
   #57 = Utf8               $amp$extension
   #58 = Utf8               (II)I
   #59 = NameAndType        #57:#58       // $amp$extension:(II)I
   #60 = Methodref          #20.#59       // org/sireum/C$.$amp$extension:(II)I
   #61 = Utf8               scala/MatchError
   #62 = Class              #61           // scala/MatchError
   #63 = Utf8               scala/runtime/BoxesRunTime
   #64 = Class              #63           // scala/runtime/BoxesRunTime
   #65 = Utf8               boxToCharacter
   #66 = Utf8               (C)Ljava/lang/Character;
   #67 = NameAndType        #65:#66       // boxToCharacter:(C)Ljava/lang/Character;
   #68 = Methodref          #64.#67       // scala/runtime/BoxesRunTime.boxToCharacter:(C)Ljava/lang/Character;
   #69 = Utf8               (Ljava/lang/Object;)V
   #70 = NameAndType        #10:#69       // "<init>":(Ljava/lang/Object;)V
   #71 = Methodref          #62.#70       // scala/MatchError."<init>":(Ljava/lang/Object;)V
   #72 = Utf8               r
   #73 = Utf8               fromUnicodeHex
   #74 = Utf8               (Lorg/sireum/IS;)Lorg/sireum/Option;
   #75 = Utf8               (Lorg/sireum/IS<Lorg/sireum/Z;Lorg/sireum/C;>;)Lorg/sireum/Option<Lorg/sireum/C;>;
   #76 = Utf8               hex
   #77 = Utf8               org/sireum/IS
   #78 = Class              #77           // org/sireum/IS
   #79 = Utf8               size
   #80 = Utf8               ()Lorg/sireum/Z;
   #81 = NameAndType        #79:#80       // size:()Lorg/sireum/Z;
   #82 = Methodref          #78.#81       // org/sireum/IS.size:()Lorg/sireum/Z;
   #83 = Utf8               org/sireum/Z$
   #84 = Class              #83           // org/sireum/Z$
   #85 = Utf8               Lorg/sireum/Z$;
   #86 = NameAndType        #6:#85        // MODULE$:Lorg/sireum/Z$;
   #87 = Fieldref           #84.#86       // org/sireum/Z$.MODULE$:Lorg/sireum/Z$;
   #88 = Utf8               (I)Lorg/sireum/Z;
   #89 = NameAndType        #35:#88       // apply:(I)Lorg/sireum/Z;
   #90 = Methodref          #84.#89       // org/sireum/Z$.apply:(I)Lorg/sireum/Z;
   #91 = Utf8               equals
   #92 = Utf8               (Ljava/lang/Object;)Z
   #93 = NameAndType        #91:#92       // equals:(Ljava/lang/Object;)Z
   #94 = Methodref          #4.#93        // java/lang/Object.equals:(Ljava/lang/Object;)Z
   #95 = Utf8               scala/Tuple4
   #96 = Class              #95           // scala/Tuple4
   #97 = Utf8               (Ljava/lang/Object;)Ljava/lang/Object;
   #98 = NameAndType        #35:#97       // apply:(Ljava/lang/Object;)Ljava/lang/Object;
   #99 = Methodref          #78.#98       // org/sireum/IS.apply:(Ljava/lang/Object;)Ljava/lang/Object;
  #100 = Utf8               value
  #101 = Utf8               ()I
  #102 = NameAndType        #100:#101     // value:()I
  #103 = Methodref          #34.#102      // org/sireum/C.value:()I
  #104 = NameAndType        #15:#16       // c2hex:(I)Lorg/sireum/Option;
  #105 = Methodref          #2.#104       // org/sireum/ops/COps$.c2hex:(I)Lorg/sireum/Option;
  #106 = Utf8               (Ljava/lang/Object;Ljava/lang/Object;Ljava/lang/Object;Ljava/lang/Object;)V
  #107 = NameAndType        #10:#106      // "<init>":(Ljava/lang/Object;Ljava/lang/Object;Ljava/lang/Object;Ljava/lang/Object;)V
  #108 = Methodref          #96.#107      // scala/Tuple4."<init>":(Ljava/lang/Object;Ljava/lang/Object;Ljava/lang/Object;Ljava/lang/Object;)V
  #109 = Utf8               _1
  #110 = Utf8               ()Ljava/lang/Object;
  #111 = NameAndType        #109:#110     // _1:()Ljava/lang/Object;
  #112 = Methodref          #96.#111      // scala/Tuple4._1:()Ljava/lang/Object;
  #113 = Utf8               org/sireum/Option
  #114 = Class              #113          // org/sireum/Option
  #115 = Utf8               _2
  #116 = NameAndType        #115:#110     // _2:()Ljava/lang/Object;
  #117 = Methodref          #96.#116      // scala/Tuple4._2:()Ljava/lang/Object;
  #118 = Utf8               _3
  #119 = NameAndType        #118:#110     // _3:()Ljava/lang/Object;
  #120 = Methodref          #96.#119      // scala/Tuple4._3:()Ljava/lang/Object;
  #121 = Utf8               _4
  #122 = NameAndType        #121:#110     // _4:()Ljava/lang/Object;
  #123 = Methodref          #96.#122      // scala/Tuple4._4:()Ljava/lang/Object;
  #124 = Utf8               org/sireum/Some
  #125 = Class              #124          // org/sireum/Some
  #126 = Utf8               unapply
  #127 = Utf8               (Lorg/sireum/Some;)Lscala/Some;
  #128 = NameAndType        #126:#127     // unapply:(Lorg/sireum/Some;)Lscala/Some;
  #129 = Methodref          #29.#128      // org/sireum/Some$.unapply:(Lorg/sireum/Some;)Lscala/Some;
  #130 = Utf8               scala/Some
  #131 = Class              #130          // scala/Some
  #132 = Utf8               isEmpty
  #133 = Utf8               ()Z
  #134 = NameAndType        #132:#133     // isEmpty:()Z
  #135 = Methodref          #131.#134     // scala/Some.isEmpty:()Z
  #136 = Utf8               get
  #137 = NameAndType        #136:#110     // get:()Ljava/lang/Object;
  #138 = Methodref          #131.#137     // scala/Some.get:()Ljava/lang/Object;
  #139 = Utf8               $less$less$extension
  #140 = NameAndType        #139:#58      // $less$less$extension:(II)I
  #141 = Methodref          #20.#140      // org/sireum/C$.$less$less$extension:(II)I
  #142 = Utf8               $bar$extension
  #143 = NameAndType        #142:#58      // $bar$extension:(II)I
  #144 = Methodref          #20.#143      // org/sireum/C$.$bar$extension:(II)I
  #145 = Utf8               c4
  #146 = Utf8               c3
  #147 = Utf8               c2
  #148 = Utf8               c1
  #149 = Utf8               Lorg/sireum/IS;
  #150 = Utf8               org/sireum/Z
  #151 = Class              #150          // org/sireum/Z
  #152 = Utf8               (I)Lorg/sireum/ops/COps;
  #153 = Utf8               org/sireum/ops/COps
  #154 = Class              #153          // org/sireum/ops/COps
  #155 = Methodref          #154.#40      // org/sireum/ops/COps."<init>":(I)V
  #156 = Utf8               (Lorg/sireum/ops/COps;)Lscala/Some;
  #157 = Utf8               (Lorg/sireum/ops/COps;)Lscala/Some<Lorg/sireum/C;>;
  #158 = Utf8               o
  #159 = NameAndType        #18:#101      // c:()I
  #160 = Methodref          #154.#159     // org/sireum/ops/COps.c:()I
  #161 = Methodref          #131.#70      // scala/Some."<init>":(Ljava/lang/Object;)V
  #162 = Utf8               Lorg/sireum/ops/COps;
  #163 = Methodref          #4.#11        // java/lang/Object."<init>":()V
  #164 = Utf8               Code
  #165 = Utf8               LineNumberTable
  #166 = Utf8               StackMapTable
  #167 = Utf8               LocalVariableTable
  #168 = Utf8               Signature
  #169 = Utf8               MethodParameters
  #170 = Utf8               SourceFile
  #171 = Utf8               ScalaInlineInfo
  #172 = Utf8               Scala
{
  public static final org.sireum.ops.COps$ MODULE$;
    descriptor: Lorg/sireum/ops/COps$;
    flags: (0x0019) ACC_PUBLIC, ACC_STATIC, ACC_FINAL

  public static {};
    descriptor: ()V
    flags: (0x0009) ACC_PUBLIC, ACC_STATIC
    Code:
      stack=2, locals=0, args_size=0
         0: new           #2                  // class org/sireum/ops/COps$
         3: dup
         4: invokespecial #12                 // Method "<init>":()V
         7: putstatic     #14                 // Field MODULE$:Lorg/sireum/ops/COps$;
        10: return
      LineNumberTable:
        line 81: 0

  public org.sireum.Option<org.sireum.C> c2hex(int);
    descriptor: (I)Lorg/sireum/Option;
    flags: (0x0001) ACC_PUBLIC
    Code:
      stack=5, locals=3, args_size=2
         0: getstatic     #23                 // Field org/sireum/C$.MODULE$:Lorg/sireum/C$;
         3: iload_1
         4: invokevirtual #27                 // Method org/sireum/C$.native$extension:(I)C
         7: istore_2
         8: iload_2
         9: lookupswitch  { // 22
                      48: 196
                      49: 217
                      50: 238
                      51: 259
                      52: 280
                      53: 301
                      54: 322
                      55: 344
                      56: 366
                      57: 388
                      65: 432
                      66: 476
                      67: 520
                      68: 564
                      69: 608
                      70: 652
                      97: 410
                      98: 454
                      99: 498
                     100: 542
                     101: 586
                     102: 630
                 default: 674
            }
       196: getstatic     #32                 // Field org/sireum/Some$.MODULE$:Lorg/sireum/Some$;
       199: new           #34                 // class org/sireum/C
       202: dup
       203: getstatic     #23                 // Field org/sireum/C$.MODULE$:Lorg/sireum/C$;
       206: iconst_0
       207: invokevirtual #38                 // Method org/sireum/C$.apply:(C)I
       210: invokespecial #41                 // Method org/sireum/C."<init>":(I)V
       213: invokevirtual #44                 // Method org/sireum/Some$.apply:(Ljava/lang/Object;)Lorg/sireum/Some;
       216: areturn
       217: getstatic     #32                 // Field org/sireum/Some$.MODULE$:Lorg/sireum/Some$;
       220: new           #34                 // class org/sireum/C
       223: dup
       224: getstatic     #23                 // Field org/sireum/C$.MODULE$:Lorg/sireum/C$;
       227: iconst_1
       228: invokevirtual #38                 // Method org/sireum/C$.apply:(C)I
       231: invokespecial #41                 // Method org/sireum/C."<init>":(I)V
       234: invokevirtual #44                 // Method org/sireum/Some$.apply:(Ljava/lang/Object;)Lorg/sireum/Some;
       237: areturn
       238: getstatic     #32                 // Field org/sireum/Some$.MODULE$:Lorg/sireum/Some$;
       241: new           #34                 // class org/sireum/C
       244: dup
       245: getstatic     #23                 // Field org/sireum/C$.MODULE$:Lorg/sireum/C$;
       248: iconst_2
       249: invokevirtual #38                 // Method org/sireum/C$.apply:(C)I
       252: invokespecial #41                 // Method org/sireum/C."<init>":(I)V
       255: invokevirtual #44                 // Method org/sireum/Some$.apply:(Ljava/lang/Object;)Lorg/sireum/Some;
       258: areturn
       259: getstatic     #32                 // Field org/sireum/Some$.MODULE$:Lorg/sireum/Some$;
       262: new           #34                 // class org/sireum/C
       265: dup
       266: getstatic     #23                 // Field org/sireum/C$.MODULE$:Lorg/sireum/C$;
       269: iconst_3
       270: invokevirtual #38                 // Method org/sireum/C$.apply:(C)I
       273: invokespecial #41                 // Method org/sireum/C."<init>":(I)V
       276: invokevirtual #44                 // Method org/sireum/Some$.apply:(Ljava/lang/Object;)Lorg/sireum/Some;
       279: areturn
       280: getstatic     #32                 // Field org/sireum/Some$.MODULE$:Lorg/sireum/Some$;
       283: new           #34                 // class org/sireum/C
       286: dup
       287: getstatic     #23                 // Field org/sireum/C$.MODULE$:Lorg/sireum/C$;
       290: iconst_4
       291: invokevirtual #38                 // Method org/sireum/C$.apply:(C)I
       294: invokespecial #41                 // Method org/sireum/C."<init>":(I)V
       297: invokevirtual #44                 // Method org/sireum/Some$.apply:(Ljava/lang/Object;)Lorg/sireum/Some;
       300: areturn
       301: getstatic     #32                 // Field org/sireum/Some$.MODULE$:Lorg/sireum/Some$;
       304: new           #34                 // class org/sireum/C
       307: dup
       308: getstatic     #23                 // Field org/sireum/C$.MODULE$:Lorg/sireum/C$;
       311: iconst_5
       312: invokevirtual #38                 // Method org/sireum/C$.apply:(C)I
       315: invokespecial #41                 // Method org/sireum/C."<init>":(I)V
       318: invokevirtual #44                 // Method org/sireum/Some$.apply:(Ljava/lang/Object;)Lorg/sireum/Some;
       321: areturn
       322: getstatic     #32                 // Field org/sireum/Some$.MODULE$:Lorg/sireum/Some$;
       325: new           #34                 // class org/sireum/C
       328: dup
       329: getstatic     #23                 // Field org/sireum/C$.MODULE$:Lorg/sireum/C$;
       332: bipush        6
       334: invokevirtual #38                 // Method org/sireum/C$.apply:(C)I
       337: invokespecial #41                 // Method org/sireum/C."<init>":(I)V
       340: invokevirtual #44                 // Method org/sireum/Some$.apply:(Ljava/lang/Object;)Lorg/sireum/Some;
       343: areturn
       344: getstatic     #32                 // Field org/sireum/Some$.MODULE$:Lorg/sireum/Some$;
       347: new           #34                 // class org/sireum/C
       350: dup
       351: getstatic     #23                 // Field org/sireum/C$.MODULE$:Lorg/sireum/C$;
       354: bipush        7
       356: invokevirtual #38                 // Method org/sireum/C$.apply:(C)I
       359: invokespecial #41                 // Method org/sireum/C."<init>":(I)V
       362: invokevirtual #44                 // Method org/sireum/Some$.apply:(Ljava/lang/Object;)Lorg/sireum/Some;
       365: areturn
       366: getstatic     #32                 // Field org/sireum/Some$.MODULE$:Lorg/sireum/Some$;
       369: new           #34                 // class org/sireum/C
       372: dup
       373: getstatic     #23                 // Field org/sireum/C$.MODULE$:Lorg/sireum/C$;
       376: bipush        8
       378: invokevirtual #38                 // Method org/sireum/C$.apply:(C)I
       381: invokespecial #41                 // Method org/sireum/C."<init>":(I)V
       384: invokevirtual #44                 // Method org/sireum/Some$.apply:(Ljava/lang/Object;)Lorg/sireum/Some;
       387: areturn
       388: getstatic     #32                 // Field org/sireum/Some$.MODULE$:Lorg/sireum/Some$;
       391: new           #34                 // class org/sireum/C
       394: dup
       395: getstatic     #23                 // Field org/sireum/C$.MODULE$:Lorg/sireum/C$;
       398: bipush        9
       400: invokevirtual #38                 // Method org/sireum/C$.apply:(C)I
       403: invokespecial #41                 // Method org/sireum/C."<init>":(I)V
       406: invokevirtual #44                 // Method org/sireum/Some$.apply:(Ljava/lang/Object;)Lorg/sireum/Some;
       409: areturn
       410: getstatic     #32                 // Field org/sireum/Some$.MODULE$:Lorg/sireum/Some$;
       413: new           #34                 // class org/sireum/C
       416: dup
       417: getstatic     #23                 // Field org/sireum/C$.MODULE$:Lorg/sireum/C$;
       420: bipush        10
       422: invokevirtual #38                 // Method org/sireum/C$.apply:(C)I
       425: invokespecial #41                 // Method org/sireum/C."<init>":(I)V
       428: invokevirtual #44                 // Method org/sireum/Some$.apply:(Ljava/lang/Object;)Lorg/sireum/Some;
       431: areturn
       432: getstatic     #32                 // Field org/sireum/Some$.MODULE$:Lorg/sireum/Some$;
       435: new           #34                 // class org/sireum/C
       438: dup
       439: getstatic     #23                 // Field org/sireum/C$.MODULE$:Lorg/sireum/C$;
       442: bipush        10
       444: invokevirtual #38                 // Method org/sireum/C$.apply:(C)I
       447: invokespecial #41                 // Method org/sireum/C."<init>":(I)V
       450: invokevirtual #44                 // Method org/sireum/Some$.apply:(Ljava/lang/Object;)Lorg/sireum/Some;
       453: areturn
       454: getstatic     #32                 // Field org/sireum/Some$.MODULE$:Lorg/sireum/Some$;
       457: new           #34                 // class org/sireum/C
       460: dup
       461: getstatic     #23                 // Field org/sireum/C$.MODULE$:Lorg/sireum/C$;
       464: bipush        11
       466: invokevirtual #38                 // Method org/sireum/C$.apply:(C)I
       469: invokespecial #41                 // Method org/sireum/C."<init>":(I)V
       472: invokevirtual #44                 // Method org/sireum/Some$.apply:(Ljava/lang/Object;)Lorg/sireum/Some;
       475: areturn
       476: getstatic     #32                 // Field org/sireum/Some$.MODULE$:Lorg/sireum/Some$;
       479: new           #34                 // class org/sireum/C
       482: dup
       483: getstatic     #23                 // Field org/sireum/C$.MODULE$:Lorg/sireum/C$;
       486: bipush        11
       488: invokevirtual #38                 // Method org/sireum/C$.apply:(C)I
       491: invokespecial #41                 // Method org/sireum/C."<init>":(I)V
       494: invokevirtual #44                 // Method org/sireum/Some$.apply:(Ljava/lang/Object;)Lorg/sireum/Some;
       497: areturn
       498: getstatic     #32                 // Field org/sireum/Some$.MODULE$:Lorg/sireum/Some$;
       501: new           #34                 // class org/sireum/C
       504: dup
       505: getstatic     #23                 // Field org/sireum/C$.MODULE$:Lorg/sireum/C$;
       508: bipush        12
       510: invokevirtual #38                 // Method org/sireum/C$.apply:(C)I
       513: invokespecial #41                 // Method org/sireum/C."<init>":(I)V
       516: invokevirtual #44                 // Method org/sireum/Some$.apply:(Ljava/lang/Object;)Lorg/sireum/Some;
       519: areturn
       520: getstatic     #32                 // Field org/sireum/Some$.MODULE$:Lorg/sireum/Some$;
       523: new           #34                 // class org/sireum/C
       526: dup
       527: getstatic     #23                 // Field org/sireum/C$.MODULE$:Lorg/sireum/C$;
       530: bipush        12
       532: invokevirtual #38                 // Method org/sireum/C$.apply:(C)I
       535: invokespecial #41                 // Method org/sireum/C."<init>":(I)V
       538: invokevirtual #44                 // Method org/sireum/Some$.apply:(Ljava/lang/Object;)Lorg/sireum/Some;
       541: areturn
       542: getstatic     #32                 // Field org/sireum/Some$.MODULE$:Lorg/sireum/Some$;
       545: new           #34                 // class org/sireum/C
       548: dup
       549: getstatic     #23                 // Field org/sireum/C$.MODULE$:Lorg/sireum/C$;
       552: bipush        13
       554: invokevirtual #38                 // Method org/sireum/C$.apply:(C)I
       557: invokespecial #41                 // Method org/sireum/C."<init>":(I)V
       560: invokevirtual #44                 // Method org/sireum/Some$.apply:(Ljava/lang/Object;)Lorg/sireum/Some;
       563: areturn
       564: getstatic     #32                 // Field org/sireum/Some$.MODULE$:Lorg/sireum/Some$;
       567: new           #34                 // class org/sireum/C
       570: dup
       571: getstatic     #23                 // Field org/sireum/C$.MODULE$:Lorg/sireum/C$;
       574: bipush        13
       576: invokevirtual #38                 // Method org/sireum/C$.apply:(C)I
       579: invokespecial #41                 // Method org/sireum/C."<init>":(I)V
       582: invokevirtual #44                 // Method org/sireum/Some$.apply:(Ljava/lang/Object;)Lorg/sireum/Some;
       585: areturn
       586: getstatic     #32                 // Field org/sireum/Some$.MODULE$:Lorg/sireum/Some$;
       589: new           #34                 // class org/sireum/C
       592: dup
       593: getstatic     #23                 // Field org/sireum/C$.MODULE$:Lorg/sireum/C$;
       596: bipush        14
       598: invokevirtual #38                 // Method org/sireum/C$.apply:(C)I
       601: invokespecial #41                 // Method org/sireum/C."<init>":(I)V
       604: invokevirtual #44                 // Method org/sireum/Some$.apply:(Ljava/lang/Object;)Lorg/sireum/Some;
       607: areturn
       608: getstatic     #32                 // Field org/sireum/Some$.MODULE$:Lorg/sireum/Some$;
       611: new           #34                 // class org/sireum/C
       614: dup
       615: getstatic     #23                 // Field org/sireum/C$.MODULE$:Lorg/sireum/C$;
       618: bipush        14
       620: invokevirtual #38                 // Method org/sireum/C$.apply:(C)I
       623: invokespecial #41                 // Method org/sireum/C."<init>":(I)V
       626: invokevirtual #44                 // Method org/sireum/Some$.apply:(Ljava/lang/Object;)Lorg/sireum/Some;
       629: areturn
       630: getstatic     #32                 // Field org/sireum/Some$.MODULE$:Lorg/sireum/Some$;
       633: new           #34                 // class org/sireum/C
       636: dup
       637: getstatic     #23                 // Field org/sireum/C$.MODULE$:Lorg/sireum/C$;
       640: bipush        15
       642: invokevirtual #38                 // Method org/sireum/C$.apply:(C)I
       645: invokespecial #41                 // Method org/sireum/C."<init>":(I)V
       648: invokevirtual #44                 // Method org/sireum/Some$.apply:(Ljava/lang/Object;)Lorg/sireum/Some;
       651: areturn
       652: getstatic     #32                 // Field org/sireum/Some$.MODULE$:Lorg/sireum/Some$;
       655: new           #34                 // class org/sireum/C
       658: dup
       659: getstatic     #23                 // Field org/sireum/C$.MODULE$:Lorg/sireum/C$;
       662: bipush        15
       664: invokevirtual #38                 // Method org/sireum/C$.apply:(C)I
       667: invokespecial #41                 // Method org/sireum/C."<init>":(I)V
       670: invokevirtual #44                 // Method org/sireum/Some$.apply:(Ljava/lang/Object;)Lorg/sireum/Some;
       673: areturn
       674: getstatic     #49                 // Field org/sireum/None$.MODULE$:Lorg/sireum/None$;
       677: invokevirtual #52                 // Method org/sireum/None$.apply:()Lorg/sireum/None;
       680: areturn
      StackMapTable: number_of_entries = 23
        frame_type = 252 /* append */
          offset_delta = 196
          locals = [ int ]
        frame_type = 20 /* same */
        frame_type = 20 /* same */
        frame_type = 20 /* same */
        frame_type = 20 /* same */
        frame_type = 20 /* same */
        frame_type = 20 /* same */
        frame_type = 21 /* same */
        frame_type = 21 /* same */
        frame_type = 21 /* same */
        frame_type = 21 /* same */
        frame_type = 21 /* same */
        frame_type = 21 /* same */
        frame_type = 21 /* same */
        frame_type = 21 /* same */
        frame_type = 21 /* same */
        frame_type = 21 /* same */
        frame_type = 21 /* same */
        frame_type = 21 /* same */
        frame_type = 21 /* same */
        frame_type = 21 /* same */
        frame_type = 21 /* same */
        frame_type = 21 /* same */
      LineNumberTable:
        line 83: 0
        line 84: 196
        line 85: 217
        line 86: 238
        line 87: 259
        line 88: 280
        line 89: 301
        line 90: 322
        line 91: 344
        line 92: 366
        line 93: 388
        line 94: 410
        line 95: 432
        line 96: 454
        line 97: 476
        line 98: 498
        line 99: 520
        line 100: 542
        line 101: 564
        line 102: 586
        line 103: 608
        line 104: 630
        line 105: 652
        line 106: 674
      LocalVariableTable:
        Start  Length  Slot  Name   Signature
            0     681     0  this   Lorg/sireum/ops/COps$;
            0     681     1     c   I
    Signature: #17                          // (I)Lorg/sireum/Option<Lorg/sireum/C;>;
    MethodParameters:
      Name                           Flags
      c                              final

  public int hex2c(int);
    descriptor: (I)I
    flags: (0x0001) ACC_PUBLIC
    Code:
      stack=5, locals=4, args_size=2
         0: getstatic     #23                 // Field org/sireum/C$.MODULE$:Lorg/sireum/C$;
         3: getstatic     #23                 // Field org/sireum/C$.MODULE$:Lorg/sireum/C$;
         6: iload_1
         7: getstatic     #23                 // Field org/sireum/C$.MODULE$:Lorg/sireum/C$;
        10: bipush        15
        12: invokevirtual #38                 // Method org/sireum/C$.apply:(C)I
        15: invokevirtual #60                 // Method org/sireum/C$.$amp$extension:(II)I
        18: invokevirtual #27                 // Method org/sireum/C$.native$extension:(I)C
        21: istore_3
        22: iload_3
        23: tableswitch   { // 0 to 15
                       0: 100
                       1: 111
                       2: 122
                       3: 133
                       4: 144
                       5: 155
                       6: 166
                       7: 177
                       8: 188
                       9: 199
                      10: 210
                      11: 221
                      12: 232
                      13: 243
                      14: 254
                      15: 265
                 default: 276
            }
       100: getstatic     #23                 // Field org/sireum/C$.MODULE$:Lorg/sireum/C$;
       103: bipush        48
       105: invokevirtual #38                 // Method org/sireum/C$.apply:(C)I
       108: goto          288
       111: getstatic     #23                 // Field org/sireum/C$.MODULE$:Lorg/sireum/C$;
       114: bipush        49
       116: invokevirtual #38                 // Method org/sireum/C$.apply:(C)I
       119: goto          288
       122: getstatic     #23                 // Field org/sireum/C$.MODULE$:Lorg/sireum/C$;
       125: bipush        50
       127: invokevirtual #38                 // Method org/sireum/C$.apply:(C)I
       130: goto          288
       133: getstatic     #23                 // Field org/sireum/C$.MODULE$:Lorg/sireum/C$;
       136: bipush        51
       138: invokevirtual #38                 // Method org/sireum/C$.apply:(C)I
       141: goto          288
       144: getstatic     #23                 // Field org/sireum/C$.MODULE$:Lorg/sireum/C$;
       147: bipush        52
       149: invokevirtual #38                 // Method org/sireum/C$.apply:(C)I
       152: goto          288
       155: getstatic     #23                 // Field org/sireum/C$.MODULE$:Lorg/sireum/C$;
       158: bipush        53
       160: invokevirtual #38                 // Method org/sireum/C$.apply:(C)I
       163: goto          288
       166: getstatic     #23                 // Field org/sireum/C$.MODULE$:Lorg/sireum/C$;
       169: bipush        54
       171: invokevirtual #38                 // Method org/sireum/C$.apply:(C)I
       174: goto          288
       177: getstatic     #23                 // Field org/sireum/C$.MODULE$:Lorg/sireum/C$;
       180: bipush        55
       182: invokevirtual #38                 // Method org/sireum/C$.apply:(C)I
       185: goto          288
       188: getstatic     #23                 // Field org/sireum/C$.MODULE$:Lorg/sireum/C$;
       191: bipush        56
       193: invokevirtual #38                 // Method org/sireum/C$.apply:(C)I
       196: goto          288
       199: getstatic     #23                 // Field org/sireum/C$.MODULE$:Lorg/sireum/C$;
       202: bipush        57
       204: invokevirtual #38                 // Method org/sireum/C$.apply:(C)I
       207: goto          288
       210: getstatic     #23                 // Field org/sireum/C$.MODULE$:Lorg/sireum/C$;
       213: bipush        65
       215: invokevirtual #38                 // Method org/sireum/C$.apply:(C)I
       218: goto          288
       221: getstatic     #23                 // Field org/sireum/C$.MODULE$:Lorg/sireum/C$;
       224: bipush        66
       226: invokevirtual #38                 // Method org/sireum/C$.apply:(C)I
       229: goto          288
       232: getstatic     #23                 // Field org/sireum/C$.MODULE$:Lorg/sireum/C$;
       235: bipush        67
       237: invokevirtual #38                 // Method org/sireum/C$.apply:(C)I
       240: goto          288
       243: getstatic     #23                 // Field org/sireum/C$.MODULE$:Lorg/sireum/C$;
       246: bipush        68
       248: invokevirtual #38                 // Method org/sireum/C$.apply:(C)I
       251: goto          288
       254: getstatic     #23                 // Field org/sireum/C$.MODULE$:Lorg/sireum/C$;
       257: bipush        69
       259: invokevirtual #38                 // Method org/sireum/C$.apply:(C)I
       262: goto          288
       265: getstatic     #23                 // Field org/sireum/C$.MODULE$:Lorg/sireum/C$;
       268: bipush        70
       270: invokevirtual #38                 // Method org/sireum/C$.apply:(C)I
       273: goto          288
       276: new           #62                 // class scala/MatchError
       279: dup
       280: iload_3
       281: invokestatic  #68                 // Method scala/runtime/BoxesRunTime.boxToCharacter:(C)Ljava/lang/Character;
       284: invokespecial #71                 // Method scala/MatchError."<init>":(Ljava/lang/Object;)V
       287: athrow
       288: istore_2
       289: iload_2
       290: ireturn
      StackMapTable: number_of_entries = 18
        frame_type = 253 /* append */
          offset_delta = 100
          locals = [ top, int ]
        frame_type = 10 /* same */
        frame_type = 10 /* same */
        frame_type = 10 /* same */
        frame_type = 10 /* same */
        frame_type = 10 /* same */
        frame_type = 10 /* same */
        frame_type = 10 /* same */
        frame_type = 10 /* same */
        frame_type = 10 /* same */
        frame_type = 10 /* same */
        frame_type = 10 /* same */
        frame_type = 10 /* same */
        frame_type = 10 /* same */
        frame_type = 10 /* same */
        frame_type = 10 /* same */
        frame_type = 10 /* same */
        frame_type = 75 /* same_locals_1_stack_item */
          stack = [ int ]
      LineNumberTable:
        line 111: 0
        line 112: 100
        line 113: 111
        line 114: 122
        line 115: 133
        line 116: 144
        line 117: 155
        line 118: 166
        line 119: 177
        line 120: 188
        line 121: 199
        line 122: 210
        line 123: 221
        line 124: 232
        line 125: 243
        line 126: 254
        line 127: 265
        line 111: 276
        line 129: 289
      LocalVariableTable:
        Start  Length  Slot  Name   Signature
          289       2     2     r   I
            0     291     0  this   Lorg/sireum/ops/COps$;
            0     291     1     c   I
    MethodParameters:
      Name                           Flags
      c                              final

  public org.sireum.Option<org.sireum.C> fromUnicodeHex(org.sireum.IS<org.sireum.Z, org.sireum.C>);
    descriptor: (Lorg/sireum/IS;)Lorg/sireum/Option;
    flags: (0x0001) ACC_PUBLIC
    Code:
      stack=11, locals=21, args_size=2
         0: aload_1
         1: invokevirtual #82                 // Method org/sireum/IS.size:()Lorg/sireum/Z;
         4: getstatic     #87                 // Field org/sireum/Z$.MODULE$:Lorg/sireum/Z$;
         7: iconst_4
         8: invokevirtual #90                 // Method org/sireum/Z$.apply:(I)Lorg/sireum/Z;
        11: astore_3
        12: dup
        13: ifnonnull     24
        16: pop
        17: aload_3
        18: ifnull        38
        21: goto          31
        24: aload_3
        25: invokevirtual #94                 // Method java/lang/Object.equals:(Ljava/lang/Object;)Z
        28: ifne          38
        31: getstatic     #49                 // Field org/sireum/None$.MODULE$:Lorg/sireum/None$;
        34: invokevirtual #52                 // Method org/sireum/None$.apply:()Lorg/sireum/None;
        37: areturn
        38: new           #96                 // class scala/Tuple4
        41: dup
        42: aload_0
        43: aload_1
        44: getstatic     #87                 // Field org/sireum/Z$.MODULE$:Lorg/sireum/Z$;
        47: iconst_0
        48: invokevirtual #90                 // Method org/sireum/Z$.apply:(I)Lorg/sireum/Z;
        51: invokevirtual #99                 // Method org/sireum/IS.apply:(Ljava/lang/Object;)Ljava/lang/Object;
        54: checkcast     #34                 // class org/sireum/C
        57: invokevirtual #103                // Method org/sireum/C.value:()I
        60: invokevirtual #105                // Method c2hex:(I)Lorg/sireum/Option;
        63: aload_0
        64: aload_1
        65: getstatic     #87                 // Field org/sireum/Z$.MODULE$:Lorg/sireum/Z$;
        68: iconst_1
        69: invokevirtual #90                 // Method org/sireum/Z$.apply:(I)Lorg/sireum/Z;
        72: invokevirtual #99                 // Method org/sireum/IS.apply:(Ljava/lang/Object;)Ljava/lang/Object;
        75: checkcast     #34                 // class org/sireum/C
        78: invokevirtual #103                // Method org/sireum/C.value:()I
        81: invokevirtual #105                // Method c2hex:(I)Lorg/sireum/Option;
        84: aload_0
        85: aload_1
        86: getstatic     #87                 // Field org/sireum/Z$.MODULE$:Lorg/sireum/Z$;
        89: iconst_2
        90: invokevirtual #90                 // Method org/sireum/Z$.apply:(I)Lorg/sireum/Z;
        93: invokevirtual #99                 // Method org/sireum/IS.apply:(Ljava/lang/Object;)Ljava/lang/Object;
        96: checkcast     #34                 // class org/sireum/C
        99: invokevirtual #103                // Method org/sireum/C.value:()I
       102: invokevirtual #105                // Method c2hex:(I)Lorg/sireum/Option;
       105: aload_0
       106: aload_1
       107: getstatic     #87                 // Field org/sireum/Z$.MODULE$:Lorg/sireum/Z$;
       110: iconst_3
       111: invokevirtual #90                 // Method org/sireum/Z$.apply:(I)Lorg/sireum/Z;
       114: invokevirtual #99                 // Method org/sireum/IS.apply:(Ljava/lang/Object;)Ljava/lang/Object;
       117: checkcast     #34                 // class org/sireum/C
       120: invokevirtual #103                // Method org/sireum/C.value:()I
       123: invokevirtual #105                // Method c2hex:(I)Lorg/sireum/Option;
       126: invokespecial #108                // Method scala/Tuple4."<init>":(Ljava/lang/Object;Ljava/lang/Object;Ljava/lang/Object;Ljava/lang/Object;)V
       129: astore        4
       131: aload         4
       133: ifnull        465
       136: aload         4
       138: invokevirtual #112                // Method scala/Tuple4._1:()Ljava/lang/Object;
       141: checkcast     #114                // class org/sireum/Option
       144: astore        5
       146: aload         4
       148: invokevirtual #117                // Method scala/Tuple4._2:()Ljava/lang/Object;
       151: checkcast     #114                // class org/sireum/Option
       154: astore        6
       156: aload         4
       158: invokevirtual #120                // Method scala/Tuple4._3:()Ljava/lang/Object;
       161: checkcast     #114                // class org/sireum/Option
       164: astore        7
       166: aload         4
       168: invokevirtual #123                // Method scala/Tuple4._4:()Ljava/lang/Object;
       171: checkcast     #114                // class org/sireum/Option
       174: astore        8
       176: aload         5
       178: instanceof    #125                // class org/sireum/Some
       181: ifeq          462
       184: aload         5
       186: checkcast     #125                // class org/sireum/Some
       189: astore        9
       191: getstatic     #32                 // Field org/sireum/Some$.MODULE$:Lorg/sireum/Some$;
       194: aload         9
       196: invokevirtual #129                // Method org/sireum/Some$.unapply:(Lorg/sireum/Some;)Lscala/Some;
       199: astore        10
       201: aload         10
       203: invokevirtual #135                // Method scala/Some.isEmpty:()Z
       206: ifne          459
       209: aload         10
       211: invokevirtual #138                // Method scala/Some.get:()Ljava/lang/Object;
       214: checkcast     #34                 // class org/sireum/C
       217: invokevirtual #103                // Method org/sireum/C.value:()I
       220: istore        11
       222: aload         6
       224: instanceof    #125                // class org/sireum/Some
       227: ifeq          456
       230: aload         6
       232: checkcast     #125                // class org/sireum/Some
       235: astore        12
       237: getstatic     #32                 // Field org/sireum/Some$.MODULE$:Lorg/sireum/Some$;
       240: aload         12
       242: invokevirtual #129                // Method org/sireum/Some$.unapply:(Lorg/sireum/Some;)Lscala/Some;
       245: astore        13
       247: aload         13
       249: invokevirtual #135                // Method scala/Some.isEmpty:()Z
       252: ifne          453
       255: aload         13
       257: invokevirtual #138                // Method scala/Some.get:()Ljava/lang/Object;
       260: checkcast     #34                 // class org/sireum/C
       263: invokevirtual #103                // Method org/sireum/C.value:()I
       266: istore        14
       268: aload         7
       270: instanceof    #125                // class org/sireum/Some
       273: ifeq          450
       276: aload         7
       278: checkcast     #125                // class org/sireum/Some
       281: astore        15
       283: getstatic     #32                 // Field org/sireum/Some$.MODULE$:Lorg/sireum/Some$;
       286: aload         15
       288: invokevirtual #129                // Method org/sireum/Some$.unapply:(Lorg/sireum/Some;)Lscala/Some;
       291: astore        16
       293: aload         16
       295: invokevirtual #135                // Method scala/Some.isEmpty:()Z
       298: ifne          447
       301: aload         16
       303: invokevirtual #138                // Method scala/Some.get:()Ljava/lang/Object;
       306: checkcast     #34                 // class org/sireum/C
       309: invokevirtual #103                // Method org/sireum/C.value:()I
       312: istore        17
       314: aload         8
       316: instanceof    #125                // class org/sireum/Some
       319: ifeq          444
       322: aload         8
       324: checkcast     #125                // class org/sireum/Some
       327: astore        18
       329: getstatic     #32                 // Field org/sireum/Some$.MODULE$:Lorg/sireum/Some$;
       332: aload         18
       334: invokevirtual #129                // Method org/sireum/Some$.unapply:(Lorg/sireum/Some;)Lscala/Some;
       337: astore        19
       339: aload         19
       341: invokevirtual #135                // Method scala/Some.isEmpty:()Z
       344: ifne          441
       347: aload         19
       349: invokevirtual #138                // Method scala/Some.get:()Ljava/lang/Object;
       352: checkcast     #34                 // class org/sireum/C
       355: invokevirtual #103                // Method org/sireum/C.value:()I
       358: istore        20
       360: getstatic     #32                 // Field org/sireum/Some$.MODULE$:Lorg/sireum/Some$;
       363: new           #34                 // class org/sireum/C
       366: dup
       367: getstatic     #23                 // Field org/sireum/C$.MODULE$:Lorg/sireum/C$;
       370: getstatic     #23                 // Field org/sireum/C$.MODULE$:Lorg/sireum/C$;
       373: getstatic     #23                 // Field org/sireum/C$.MODULE$:Lorg/sireum/C$;
       376: getstatic     #23                 // Field org/sireum/C$.MODULE$:Lorg/sireum/C$;
       379: iload         11
       381: getstatic     #23                 // Field org/sireum/C$.MODULE$:Lorg/sireum/C$;
       384: bipush        12
       386: invokevirtual #38                 // Method org/sireum/C$.apply:(C)I
       389: invokevirtual #141                // Method org/sireum/C$.$less$less$extension:(II)I
       392: getstatic     #23                 // Field org/sireum/C$.MODULE$:Lorg/sireum/C$;
       395: iload         14
       397: getstatic     #23                 // Field org/sireum/C$.MODULE$:Lorg/sireum/C$;
       400: bipush        8
       402: invokevirtual #38                 // Method org/sireum/C$.apply:(C)I
       405: invokevirtual #141                // Method org/sireum/C$.$less$less$extension:(II)I
       408: invokevirtual #144                // Method org/sireum/C$.$bar$extension:(II)I
       411: getstatic     #23                 // Field org/sireum/C$.MODULE$:Lorg/sireum/C$;
       414: iload         17
       416: getstatic     #23                 // Field org/sireum/C$.MODULE$:Lorg/sireum/C$;
       419: iconst_4
       420: invokevirtual #38                 // Method org/sireum/C$.apply:(C)I
       423: invokevirtual #141                // Method org/sireum/C$.$less$less$extension:(II)I
       426: invokevirtual #144                // Method org/sireum/C$.$bar$extension:(II)I
       429: iload         20
       431: invokevirtual #144                // Method org/sireum/C$.$bar$extension:(II)I
       434: invokespecial #41                 // Method org/sireum/C."<init>":(I)V
       437: invokevirtual #44                 // Method org/sireum/Some$.apply:(Ljava/lang/Object;)Lorg/sireum/Some;
       440: areturn
       441: goto          468
       444: goto          468
       447: goto          468
       450: goto          468
       453: goto          468
       456: goto          468
       459: goto          468
       462: goto          468
       465: goto          468
       468: getstatic     #49                 // Field org/sireum/None$.MODULE$:Lorg/sireum/None$;
       471: invokevirtual #52                 // Method org/sireum/None$.apply:()Lorg/sireum/None;
       474: areturn
      StackMapTable: number_of_entries = 13
        frame_type = 255 /* full_frame */
          offset_delta = 24
          locals = [ class org/sireum/ops/COps$, class org/sireum/IS, top, class org/sireum/Z ]
          stack = [ class org/sireum/Z ]
        frame_type = 6 /* same */
        frame_type = 6 /* same */
        frame_type = 255 /* full_frame */
          offset_delta = 402
          locals = [ class org/sireum/ops/COps$, class org/sireum/IS, top, class org/sireum/Z, class scala/Tuple4, class org/sireum/Option, class org/sireum/Option, class org/sireum/Option, class org/sireum/Option, class org/sireum/Some, class scala/Some, int, class org/sireum/Some, class scala/Some, int, class org/sireum/Some, class scala/Some, int, class org/sireum/Some, class scala/Some ]
          stack = []
        frame_type = 249 /* chop */
          offset_delta = 2
        frame_type = 250 /* chop */
          offset_delta = 2
        frame_type = 249 /* chop */
          offset_delta = 2
        frame_type = 250 /* chop */
          offset_delta = 2
        frame_type = 249 /* chop */
          offset_delta = 2
        frame_type = 250 /* chop */
          offset_delta = 2
        frame_type = 249 /* chop */
          offset_delta = 2
        frame_type = 255 /* full_frame */
          offset_delta = 2
          locals = [ class org/sireum/ops/COps$, class org/sireum/IS, top, class org/sireum/Z, class scala/Tuple4 ]
          stack = []
        frame_type = 2 /* same */
      LineNumberTable:
        line 133: 0
        line 134: 31
        line 136: 38
        line 137: 131
        line 136: 209
        line 137: 222
        line 136: 255
        line 137: 268
        line 136: 301
        line 137: 314
        line 136: 347
        line 138: 360
        line 137: 441
        line 139: 468
      LocalVariableTable:
        Start  Length  Slot  Name   Signature
          360      81    20    c4   I
          314     133    17    c3   I
          268     185    14    c2   I
          222     237    11    c1   I
            0     475     0  this   Lorg/sireum/ops/COps$;
            0     475     1   hex   Lorg/sireum/IS;
    Signature: #75                          // (Lorg/sireum/IS<Lorg/sireum/Z;Lorg/sireum/C;>;)Lorg/sireum/Option<Lorg/sireum/C;>;
    MethodParameters:
      Name                           Flags
      hex                            final

  public org.sireum.ops.COps apply(int);
    descriptor: (I)Lorg/sireum/ops/COps;
    flags: (0x0001) ACC_PUBLIC
    Code:
      stack=3, locals=2, args_size=2
         0: new           #154                // class org/sireum/ops/COps
         3: dup
         4: iload_1
         5: invokespecial #155                // Method org/sireum/ops/COps."<init>":(I)V
         8: areturn
      LineNumberTable:
        line 81: 0
      LocalVariableTable:
        Start  Length  Slot  Name   Signature
            0       9     0  this   Lorg/sireum/ops/COps$;
            0       9     1     c   I
    MethodParameters:
      Name                           Flags
      c                              final

  public scala.Some<org.sireum.C> unapply(org.sireum.ops.COps);
    descriptor: (Lorg/sireum/ops/COps;)Lscala/Some;
    flags: (0x0001) ACC_PUBLIC
    Code:
      stack=5, locals=2, args_size=2
         0: new           #131                // class scala/Some
         3: dup
         4: new           #34                 // class org/sireum/C
         7: dup
         8: aload_1
         9: invokevirtual #160                // Method org/sireum/ops/COps.c:()I
        12: invokespecial #41                 // Method org/sireum/C."<init>":(I)V
        15: invokespecial #161                // Method scala/Some."<init>":(Ljava/lang/Object;)V
        18: areturn
      LineNumberTable:
        line 81: 0
      LocalVariableTable:
        Start  Length  Slot  Name   Signature
            0      19     0  this   Lorg/sireum/ops/COps$;
            0      19     1     o   Lorg/sireum/ops/COps;
    Signature: #157                         // (Lorg/sireum/ops/COps;)Lscala/Some<Lorg/sireum/C;>;
    MethodParameters:
      Name                           Flags
      o                              final

  private org.sireum.ops.COps$();
    descriptor: ()V
    flags: (0x0002) ACC_PRIVATE
    Code:
      stack=1, locals=1, args_size=1
         0: aload_0
         1: invokespecial #163                // Method java/lang/Object."<init>":()V
         4: return
      LineNumberTable:
        line 81: 0
      LocalVariableTable:
        Start  Length  Slot  Name   Signature
            0       5     0  this   Lorg/sireum/ops/COps$;
}
SourceFile: "COps.scala"
  ScalaInlineInfo: length = 0x22 (unknown attribute)
   01 01 00 06 00 0A 00 09 01 00 23 00 98 01 00 0F
   00 10 01 00 49 00 4A 01 00 37 00 38 01 00 7E 00
   9C 01
  Scala: length = 0x0 (unknown attribute)

