Classfile /Users/mw/Projects/slang-braindump/.jar/jar8/assemble/slang-braindump/assemble/content/org/sireum/extension/Console_Ext.class
  Last modified May 29, 2022; size 618 bytes
  SHA-256 checksum 0727363e771b8193b4ab7552d0656f809f6a74953eaa7606bf850279cfda18bb
  Compiled from "Console_Ext.scala"
public final class org.sireum.extension.Console_Ext
  minor version: 0
  major version: 52
  flags: (0x0031) ACC_PUBLIC, ACC_FINAL, ACC_SUPER
  this_class: #2                          // org/sireum/extension/Console_Ext
  super_class: #4                         // java/lang/Object
  interfaces: 0, fields: 0, methods: 1, attributes: 3
Constant pool:
   #1 = Utf8               org/sireum/extension/Console_Ext
   #2 = Class              #1             // org/sireum/extension/Console_Ext
   #3 = Utf8               java/lang/Object
   #4 = Class              #3             // java/lang/Object
   #5 = Utf8               Console_Ext.scala
   #6 = Utf8               Lscala/reflect/ScalaSignature;
   #7 = Utf8               bytes
   #8 = Utf8               \u0006\u0005y9Q\u0001B\u0003\t\u000211QAD\u0003\t\u0002=AQAF\u0001\u0005\u0002]AQ\u0001G\u0001\u0005\u0002e\t1bQ8og>dWmX#yi*\u0011aaB\u0001\nKb$XM\\:j_:T!\u0001C\u0005\u0002\rML\'/Z;n\u0015\u0005Q\u0011aA8sO\u000e\u0001\u0001CA\u0007\u0002\u001b\u0005)!aC\"p]N|G.Z0FqR\u001c\"!\u0001\t\u0011\u0005E!R\"\u0001\n\u000b\u0003M\tQa]2bY\u0006L!!\u0006\n\u0003\r\u0005s\u0017PU3g\u0003\u0019a\u0014N\\5u}Q\tA\"\u0001\u0005sK\u0006$G*\u001b8f)\u0005Q\u0002CA\u000e\u001d\u001b\u00059\u0011BA\u000f\b\u0005\u0019\u0019FO]5oO\u0002
   #9 = Utf8               readLine
  #10 = Utf8               ()Ljava/lang/String;
  #11 = Utf8               org/sireum/extension/Console_Ext$
  #12 = Class              #11            // org/sireum/extension/Console_Ext$
  #13 = Utf8               MODULE$
  #14 = Utf8               Lorg/sireum/extension/Console_Ext$;
  #15 = NameAndType        #13:#14        // MODULE$:Lorg/sireum/extension/Console_Ext$;
  #16 = Fieldref           #12.#15        // org/sireum/extension/Console_Ext$.MODULE$:Lorg/sireum/extension/Console_Ext$;
  #17 = NameAndType        #9:#10         // readLine:()Ljava/lang/String;
  #18 = Methodref          #12.#17        // org/sireum/extension/Console_Ext$.readLine:()Ljava/lang/String;
  #19 = Utf8               Code
  #20 = Utf8               SourceFile
  #21 = Utf8               RuntimeVisibleAnnotations
  #22 = Utf8               ScalaSig
{
  public static java.lang.String readLine();
    descriptor: ()Ljava/lang/String;
    flags: (0x0009) ACC_PUBLIC, ACC_STATIC
    Code:
      stack=1, locals=0, args_size=0
         0: getstatic     #16                 // Field org/sireum/extension/Console_Ext$.MODULE$:Lorg/sireum/extension/Console_Ext$;
         3: invokevirtual #18                 // Method org/sireum/extension/Console_Ext$.readLine:()Ljava/lang/String;
         6: areturn
}
SourceFile: "Console_Ext.scala"
RuntimeVisibleAnnotations:
  0: #6(#7=s#8)
    scala.reflect.ScalaSignature(
      bytes="\u0006\u0005y9Q\u0001B\u0003\t\u000211QAD\u0003\t\u0002=AQAF\u0001\u0005\u0002]AQ\u0001G\u0001\u0005\u0002e\t1bQ8og>dWmX#yi*\u0011aaB\u0001\nKb$XM\\:j_:T!\u0001C\u0005\u0002\rML\'/Z;n\u0015\u0005Q\u0011aA8sO\u000e\u0001\u0001CA\u0007\u0002\u001b\u0005)!aC\"p]N|G.Z0FqR\u001c\"!\u0001\t\u0011\u0005E!R\"\u0001\n\u000b\u0003M\tQa]2bY\u0006L!!\u0006\n\u0003\r\u0005s\u0017PU3g\u0003\u0019a\u0014N\\5u}Q\tA\"\u0001\u0005sK\u0006$G*\u001b8f)\u0005Q\u0002CA\u000e\u001d\u001b\u00059\u0011BA\u000f\b\u0005\u0019\u0019FO]5oO\u0002"
    )
  ScalaSig: length = 0x3 (unknown attribute)
   05 02 00
