Classfile /Users/mw/Projects/slang-braindump/.jar/jar11/assemble/slang-braindump/assemble/content/coursier/cache/internal/ConsoleDim.class
  Last modified May 29, 2022; size 4800 bytes
  SHA-256 checksum 7aa7bde686903b1625ba77f4a7ee9bd45d22cf0ddfdb9bbd17d046f97f6603a5
  Compiled from "ConsoleDim.scala"
public final class coursier.cache.internal.ConsoleDim
  minor version: 0
  major version: 52
  flags: (0x0031) ACC_PUBLIC, ACC_FINAL, ACC_SUPER
  this_class: #2                          // coursier/cache/internal/ConsoleDim
  super_class: #4                         // java/lang/Object
  interfaces: 0, fields: 3, methods: 14, attributes: 6
Constant pool:
    #1 = Utf8               coursier/cache/internal/ConsoleDim
    #2 = Class              #1            // coursier/cache/internal/ConsoleDim
    #3 = Utf8               java/lang/Object
    #4 = Class              #3            // java/lang/Object
    #5 = Utf8               ConsoleDim.scala
    #6 = Utf8               Lscala/reflect/ScalaSignature;
    #7 = Utf8               bytes
    #8 = Utf8               \u0006\u0005}3A\u0001F\u000b\u00039!)1\u0005\u0001C\u0001I!9q\u0005\u0001a\u0001\n\u0013A\u0003b\u0002\u0017\u0001\u0001\u0004%I!\f\u0005\u0007g\u0001\u0001\u000b\u0015B\u0015\t\u000fQ\u0002!\u0019!C\u0005k!1a\b\u0001Q\u0001\nYBQa\u0010\u0001\u0005\n\u0001CQ!\u0011\u0001\u0005\n\tCQ!\u0013\u0001\u0005\u0002)CQa\u0013\u0001\u0005\u0002)Cq\u0001\u0014\u0001A\u0002\u0013%Q\nC\u0004R\u0001\u0001\u0007I\u0011\u0002*\t\rQ\u0003\u0001\u0015)\u0003O\u000f\u0015IV\u0003#\u0001[\r\u0015!R\u0003#\u0001\\\u0011\u0015\u0019s\u0002\"\u0001]\u0011!iv\u0002#b\u0001\n\u0003q\u0006\"B%\u0010\t\u0003Q\u0005\"B&\u0010\t\u0003Q%AC\"p]N|G.\u001a#j[*\u0011acF\u0001\tS:$XM\u001d8bY*\u0011\u0001$G\u0001\u0006G\u0006\u001c\u0007.\u001a\u0006\u00025\u0005A1m\\;sg&,\'o\u0001\u0001\u0014\u0005\u0001i\u0002C\u0001\u0010\"\u001b\u0005y\"\"\u0001\u0011\u0002\u000bM\u001c\u0017\r\\1\n\u0005\tz\"AB!osJ+g-\u0001\u0004=S:LGO\u0010\u000b\u0002KA\u0011a\u0005A\u0007\u0002+\u0005Y\u0011N\\5uS\u0006d\u0017N_3e+\u0005I\u0003C\u0001\u0010+\u0013\tYsDA\u0004C_>dW-\u00198\u0002\u001f%t\u0017\u000e^5bY&TX\rZ0%KF$\"AL\u0019\u0011\u0005yy\u0013B\u0001\u0019 \u0005\u0011)f.\u001b;\t\u000fI\u001a\u0011\u0011!a\u0001S\u0005\u0019\u0001\u0010J\u0019\u0002\u0019%t\u0017\u000e^5bY&TX\r\u001a\u0011\u0002\t1|7m[\u000b\u0002mA\u0011q\u0007P\u0007\u0002q)\u0011\u0011HO\u0001\u0005Y\u0006twMC\u0001<\u0003\u0011Q\u0017M^1\n\u0005uB$AB(cU\u0016\u001cG/A\u0003m_\u000e\\\u0007%A\u0003tKR,\b\u000fF\u0001/\u0003\u0011!\u0017.\\:\u0015\u0003\r\u0003BA\b#G\r&\u0011Qi\b\u0002\u0007)V\u0004H.\u001a\u001a\u0011\u0005y9\u0015B\u0001% \u0005\rIe\u000e^\u0001\u0006o&$G\u000f\u001b\u000b\u0002\r\u00061\u0001.Z5hQR\fq\u0001Z5ng>\u0003H/F\u0001O!\rqrjQ\u0005\u0003!~\u0011aa\u00149uS>t\u0017a\u00033j[N|\u0005\u000f^0%KF$\"AL*\t\u000fIb\u0011\u0011!a\u0001\u001d\u0006AA-[7t\u001fB$\b\u0005\u000b\u0002\u000e-B\u0011adV\u0005\u00031~\u0011\u0001B^8mCRLG.Z\u0001\u000b\u0007>t7o\u001c7f\t&l\u0007C\u0001\u0014\u0010\'\tyQ\u0004F\u0001[\u0003\r9W\r^\u000b\u0002K\u0001
    #9 = Utf8               coursier/cache/internal/ConsoleDim$$anon$1
   #10 = Class              #9            // coursier/cache/internal/ConsoleDim$$anon$1
   #11 = Utf8               java/lang/invoke/MethodHandles$Lookup
   #12 = Class              #11           // java/lang/invoke/MethodHandles$Lookup
   #13 = Utf8               java/lang/invoke/MethodHandles
   #14 = Class              #13           // java/lang/invoke/MethodHandles
   #15 = Utf8               Lookup
   #16 = Utf8               initialized
   #17 = Utf8               Z
   #18 = Utf8               coursier$cache$internal$ConsoleDim$$lock
   #19 = Utf8               Ljava/lang/Object;
   #20 = Utf8               coursier$cache$internal$ConsoleDim$$dimsOpt
   #21 = Utf8               Lscala/Option;
   #22 = Utf8               Lscala/Option<Lscala/Tuple2<Ljava/lang/Object;Ljava/lang/Object;>;>;
   #23 = Utf8               get
   #24 = Utf8               ()Lcoursier/cache/internal/ConsoleDim;
   #25 = Utf8               coursier/cache/internal/ConsoleDim$
   #26 = Class              #25           // coursier/cache/internal/ConsoleDim$
   #27 = Utf8               MODULE$
   #28 = Utf8               Lcoursier/cache/internal/ConsoleDim$;
   #29 = NameAndType        #27:#28       // MODULE$:Lcoursier/cache/internal/ConsoleDim$;
   #30 = Fieldref           #26.#29       // coursier/cache/internal/ConsoleDim$.MODULE$:Lcoursier/cache/internal/ConsoleDim$;
   #31 = NameAndType        #23:#24       // get:()Lcoursier/cache/internal/ConsoleDim;
   #32 = Methodref          #26.#31       // coursier/cache/internal/ConsoleDim$.get:()Lcoursier/cache/internal/ConsoleDim;
   #33 = Utf8               ()Lscala/Option;
   #34 = Utf8               ()Lscala/Option<Lscala/Tuple2<Ljava/lang/Object;Ljava/lang/Object;>;>;
   #35 = NameAndType        #20:#21       // coursier$cache$internal$ConsoleDim$$dimsOpt:Lscala/Option;
   #36 = Fieldref           #2.#35        // coursier/cache/internal/ConsoleDim.coursier$cache$internal$ConsoleDim$$dimsOpt:Lscala/Option;
   #37 = Utf8               this
   #38 = Utf8               Lcoursier/cache/internal/ConsoleDim;
   #39 = Utf8               coursier$cache$internal$ConsoleDim$$dimsOpt_$eq
   #40 = Utf8               (Lscala/Option;)V
   #41 = Utf8               (Lscala/Option<Lscala/Tuple2<Ljava/lang/Object;Ljava/lang/Object;>;>;)V
   #42 = Utf8               x$1
   #43 = Utf8               ()Z
   #44 = NameAndType        #16:#17       // initialized:Z
   #45 = Fieldref           #2.#44        // coursier/cache/internal/ConsoleDim.initialized:Z
   #46 = Utf8               initialized_$eq
   #47 = Utf8               (Z)V
   #48 = Utf8               ()Ljava/lang/Object;
   #49 = NameAndType        #18:#19       // coursier$cache$internal$ConsoleDim$$lock:Ljava/lang/Object;
   #50 = Fieldref           #2.#49        // coursier/cache/internal/ConsoleDim.coursier$cache$internal$ConsoleDim$$lock:Ljava/lang/Object;
   #51 = Utf8               setup
   #52 = Utf8               ()V
   #53 = Utf8               java/lang/IllegalArgumentException
   #54 = Class              #53           // java/lang/IllegalArgumentException
   #55 = Utf8               <init>
   #56 = Utf8               (Lcoursier/cache/internal/ConsoleDim;)V
   #57 = NameAndType        #55:#56       // "<init>":(Lcoursier/cache/internal/ConsoleDim;)V
   #58 = Methodref          #10.#57       // coursier/cache/internal/ConsoleDim$$anon$1."<init>":(Lcoursier/cache/internal/ConsoleDim;)V
   #59 = Utf8               coursier/cache/internal/SigWinch
   #60 = Class              #59           // coursier/cache/internal/SigWinch
   #61 = Utf8               addHandler
   #62 = Utf8               (Ljava/lang/Runnable;)V
   #63 = NameAndType        #61:#62       // addHandler:(Ljava/lang/Runnable;)V
   #64 = Methodref          #60.#63       // coursier/cache/internal/SigWinch.addHandler:(Ljava/lang/Runnable;)V
   #65 = NameAndType        #46:#47       // initialized_$eq:(Z)V
   #66 = Methodref          #2.#65        // coursier/cache/internal/ConsoleDim.initialized_$eq:(Z)V
   #67 = Utf8               dims
   #68 = Utf8               ()Lscala/Tuple2;
   #69 = Utf8               ()Lscala/Tuple2<Ljava/lang/Object;Ljava/lang/Object;>;
   #70 = NameAndType        #20:#33       // coursier$cache$internal$ConsoleDim$$dimsOpt:()Lscala/Option;
   #71 = Methodref          #2.#70        // coursier/cache/internal/ConsoleDim.coursier$cache$internal$ConsoleDim$$dimsOpt:()Lscala/Option;
   #72 = MethodType         #48           //  ()Ljava/lang/Object;
   #73 = Utf8               $anonfun$dims$1
   #74 = Utf8               (Lcoursier/cache/internal/ConsoleDim;)Lscala/Tuple2;
   #75 = NameAndType        #73:#74       // $anonfun$dims$1:(Lcoursier/cache/internal/ConsoleDim;)Lscala/Tuple2;
   #76 = Methodref          #2.#75        // coursier/cache/internal/ConsoleDim.$anonfun$dims$1:(Lcoursier/cache/internal/ConsoleDim;)Lscala/Tuple2;
   #77 = MethodHandle       6:#76         // REF_invokeStatic coursier/cache/internal/ConsoleDim.$anonfun$dims$1:(Lcoursier/cache/internal/ConsoleDim;)Lscala/Tuple2;
   #78 = MethodType         #68           //  ()Lscala/Tuple2;
   #79 = Integer            5
   #80 = Integer            1
   #81 = Utf8               java/lang/invoke/LambdaMetafactory
   #82 = Class              #81           // java/lang/invoke/LambdaMetafactory
   #83 = Utf8               altMetafactory
   #84 = Utf8               (Ljava/lang/invoke/MethodHandles$Lookup;Ljava/lang/String;Ljava/lang/invoke/MethodType;[Ljava/lang/Object;)Ljava/lang/invoke/CallSite;
   #85 = NameAndType        #83:#84       // altMetafactory:(Ljava/lang/invoke/MethodHandles$Lookup;Ljava/lang/String;Ljava/lang/invoke/MethodType;[Ljava/lang/Object;)Ljava/lang/invoke/CallSite;
   #86 = Methodref          #82.#85       // java/lang/invoke/LambdaMetafactory.altMetafactory:(Ljava/lang/invoke/MethodHandles$Lookup;Ljava/lang/String;Ljava/lang/invoke/MethodType;[Ljava/lang/Object;)Ljava/lang/invoke/CallSite;
   #87 = MethodHandle       6:#86         // REF_invokeStatic java/lang/invoke/LambdaMetafactory.altMetafactory:(Ljava/lang/invoke/MethodHandles$Lookup;Ljava/lang/String;Ljava/lang/invoke/MethodType;[Ljava/lang/Object;)Ljava/lang/invoke/CallSite;
   #88 = Utf8               apply
   #89 = Utf8               (Lcoursier/cache/internal/ConsoleDim;)Lscala/Function0;
   #90 = NameAndType        #88:#89       // apply:(Lcoursier/cache/internal/ConsoleDim;)Lscala/Function0;
   #91 = InvokeDynamic      #0:#90        // #0:apply:(Lcoursier/cache/internal/ConsoleDim;)Lscala/Function0;
   #92 = Utf8               scala/Option
   #93 = Class              #92           // scala/Option
   #94 = Utf8               getOrElse
   #95 = Utf8               (Lscala/Function0;)Ljava/lang/Object;
   #96 = NameAndType        #94:#95       // getOrElse:(Lscala/Function0;)Ljava/lang/Object;
   #97 = Methodref          #93.#96       // scala/Option.getOrElse:(Lscala/Function0;)Ljava/lang/Object;
   #98 = Utf8               scala/Tuple2
   #99 = Class              #98           // scala/Tuple2
  #100 = Utf8               width
  #101 = Utf8               ()I
  #102 = NameAndType        #67:#68       // dims:()Lscala/Tuple2;
  #103 = Methodref          #2.#102       // coursier/cache/internal/ConsoleDim.dims:()Lscala/Tuple2;
  #104 = Utf8               _1$mcI$sp
  #105 = NameAndType        #104:#101     // _1$mcI$sp:()I
  #106 = Methodref          #99.#105      // scala/Tuple2._1$mcI$sp:()I
  #107 = Utf8               height
  #108 = Utf8               _2$mcI$sp
  #109 = NameAndType        #108:#101     // _2$mcI$sp:()I
  #110 = Methodref          #99.#109      // scala/Tuple2._2$mcI$sp:()I
  #111 = Utf8               $anonfun$dims$2
  #112 = Utf8               $this
  #113 = NameAndType        #16:#43       // initialized:()Z
  #114 = Methodref          #2.#113       // coursier/cache/internal/ConsoleDim.initialized:()Z
  #115 = NameAndType        #51:#52       // setup:()V
  #116 = Methodref          #2.#115       // coursier/cache/internal/ConsoleDim.setup:()V
  #117 = Utf8               coursier/cache/internal/Terminal$
  #118 = Class              #117          // coursier/cache/internal/Terminal$
  #119 = Utf8               Lcoursier/cache/internal/Terminal$;
  #120 = NameAndType        #27:#119      // MODULE$:Lcoursier/cache/internal/Terminal$;
  #121 = Fieldref           #118.#120     // coursier/cache/internal/Terminal$.MODULE$:Lcoursier/cache/internal/Terminal$;
  #122 = Utf8               consoleDims
  #123 = NameAndType        #122:#68      // consoleDims:()Lscala/Tuple2;
  #124 = Methodref          #118.#123     // coursier/cache/internal/Terminal$.consoleDims:()Lscala/Tuple2;
  #125 = Utf8               scala/Some
  #126 = Class              #125          // scala/Some
  #127 = Utf8               (Ljava/lang/Object;)V
  #128 = NameAndType        #55:#127      // "<init>":(Ljava/lang/Object;)V
  #129 = Methodref          #126.#128     // scala/Some."<init>":(Ljava/lang/Object;)V
  #130 = NameAndType        #39:#40       // coursier$cache$internal$ConsoleDim$$dimsOpt_$eq:(Lscala/Option;)V
  #131 = Methodref          #2.#130       // coursier/cache/internal/ConsoleDim.coursier$cache$internal$ConsoleDim$$dimsOpt_$eq:(Lscala/Option;)V
  #132 = Utf8               Lscala/Tuple2;
  #133 = NameAndType        #18:#48       // coursier$cache$internal$ConsoleDim$$lock:()Ljava/lang/Object;
  #134 = Methodref          #2.#133       // coursier/cache/internal/ConsoleDim.coursier$cache$internal$ConsoleDim$$lock:()Ljava/lang/Object;
  #135 = NameAndType        #111:#74      // $anonfun$dims$2:(Lcoursier/cache/internal/ConsoleDim;)Lscala/Tuple2;
  #136 = Methodref          #2.#135       // coursier/cache/internal/ConsoleDim.$anonfun$dims$2:(Lcoursier/cache/internal/ConsoleDim;)Lscala/Tuple2;
  #137 = MethodHandle       6:#136        // REF_invokeStatic coursier/cache/internal/ConsoleDim.$anonfun$dims$2:(Lcoursier/cache/internal/ConsoleDim;)Lscala/Tuple2;
  #138 = InvokeDynamic      #1:#90        // #1:apply:(Lcoursier/cache/internal/ConsoleDim;)Lscala/Function0;
  #139 = Utf8               java/lang/Throwable
  #140 = Class              #139          // java/lang/Throwable
  #141 = NameAndType        #55:#52       // "<init>":()V
  #142 = Methodref          #4.#141       // java/lang/Object."<init>":()V
  #143 = Utf8               scala/None$
  #144 = Class              #143          // scala/None$
  #145 = Utf8               Lscala/None$;
  #146 = NameAndType        #27:#145      // MODULE$:Lscala/None$;
  #147 = Fieldref           #144.#146     // scala/None$.MODULE$:Lscala/None$;
  #148 = Utf8               $deserializeLambda$
  #149 = Utf8               (Ljava/lang/invoke/SerializedLambda;)Ljava/lang/Object;
  #150 = Utf8               scala/runtime/LambdaDeserialize
  #151 = Class              #150          // scala/runtime/LambdaDeserialize
  #152 = Utf8               bootstrap
  #153 = Utf8               (Ljava/lang/invoke/MethodHandles$Lookup;Ljava/lang/String;Ljava/lang/invoke/MethodType;[Ljava/lang/invoke/MethodHandle;)Ljava/lang/invoke/CallSite;
  #154 = NameAndType        #152:#153     // bootstrap:(Ljava/lang/invoke/MethodHandles$Lookup;Ljava/lang/String;Ljava/lang/invoke/MethodType;[Ljava/lang/invoke/MethodHandle;)Ljava/lang/invoke/CallSite;
  #155 = Methodref          #151.#154     // scala/runtime/LambdaDeserialize.bootstrap:(Ljava/lang/invoke/MethodHandles$Lookup;Ljava/lang/String;Ljava/lang/invoke/MethodType;[Ljava/lang/invoke/MethodHandle;)Ljava/lang/invoke/CallSite;
  #156 = MethodHandle       6:#155        // REF_invokeStatic scala/runtime/LambdaDeserialize.bootstrap:(Ljava/lang/invoke/MethodHandles$Lookup;Ljava/lang/String;Ljava/lang/invoke/MethodType;[Ljava/lang/invoke/MethodHandle;)Ljava/lang/invoke/CallSite;
  #157 = Utf8               lambdaDeserialize
  #158 = NameAndType        #157:#149     // lambdaDeserialize:(Ljava/lang/invoke/SerializedLambda;)Ljava/lang/Object;
  #159 = InvokeDynamic      #2:#158       // #2:lambdaDeserialize:(Ljava/lang/invoke/SerializedLambda;)Ljava/lang/Object;
  #160 = Utf8               Signature
  #161 = Utf8               Code
  #162 = Utf8               LineNumberTable
  #163 = Utf8               LocalVariableTable
  #164 = Utf8               MethodParameters
  #165 = Utf8               StackMapTable
  #166 = Utf8               InnerClasses
  #167 = Utf8               SourceFile
  #168 = Utf8               RuntimeVisibleAnnotations
  #169 = Utf8               BootstrapMethods
  #170 = Utf8               ScalaInlineInfo
  #171 = Utf8               ScalaSig
{
  private boolean initialized;
    descriptor: Z
    flags: (0x0002) ACC_PRIVATE

  private final java.lang.Object coursier$cache$internal$ConsoleDim$$lock;
    descriptor: Ljava/lang/Object;
    flags: (0x0012) ACC_PRIVATE, ACC_FINAL

  private volatile scala.Option<scala.Tuple2<java.lang.Object, java.lang.Object>> coursier$cache$internal$ConsoleDim$$dimsOpt;
    descriptor: Lscala/Option;
    flags: (0x0042) ACC_PRIVATE, ACC_VOLATILE
    Signature: #22                          // Lscala/Option<Lscala/Tuple2<Ljava/lang/Object;Ljava/lang/Object;>;>;

  public static coursier.cache.internal.ConsoleDim get();
    descriptor: ()Lcoursier/cache/internal/ConsoleDim;
    flags: (0x0009) ACC_PUBLIC, ACC_STATIC
    Code:
      stack=1, locals=0, args_size=0
         0: getstatic     #30                 // Field coursier/cache/internal/ConsoleDim$.MODULE$:Lcoursier/cache/internal/ConsoleDim$;
         3: invokevirtual #32                 // Method coursier/cache/internal/ConsoleDim$.get:()Lcoursier/cache/internal/ConsoleDim;
         6: areturn

  private scala.Option<scala.Tuple2<java.lang.Object, java.lang.Object>> coursier$cache$internal$ConsoleDim$$dimsOpt();
    descriptor: ()Lscala/Option;
    flags: (0x0002) ACC_PRIVATE
    Code:
      stack=1, locals=1, args_size=1
         0: aload_0
         1: getfield      #36                 // Field coursier$cache$internal$ConsoleDim$$dimsOpt:Lscala/Option;
         4: areturn
      LineNumberTable:
        line 5: 0
      LocalVariableTable:
        Start  Length  Slot  Name   Signature
            0       5     0  this   Lcoursier/cache/internal/ConsoleDim;
    Signature: #34                          // ()Lscala/Option<Lscala/Tuple2<Ljava/lang/Object;Ljava/lang/Object;>;>;

  public void coursier$cache$internal$ConsoleDim$$dimsOpt_$eq(scala.Option<scala.Tuple2<java.lang.Object, java.lang.Object>>);
    descriptor: (Lscala/Option;)V
    flags: (0x0001) ACC_PUBLIC
    Code:
      stack=2, locals=2, args_size=2
         0: aload_0
         1: aload_1
         2: putfield      #36                 // Field coursier$cache$internal$ConsoleDim$$dimsOpt:Lscala/Option;
         5: return
      LineNumberTable:
        line 5: 0
      LocalVariableTable:
        Start  Length  Slot  Name   Signature
            0       6     0  this   Lcoursier/cache/internal/ConsoleDim;
            0       6     1   x$1   Lscala/Option;
    Signature: #41                          // (Lscala/Option<Lscala/Tuple2<Ljava/lang/Object;Ljava/lang/Object;>;>;)V
    MethodParameters:
      Name                           Flags
      x$1                            final

  private boolean initialized();
    descriptor: ()Z
    flags: (0x0002) ACC_PRIVATE
    Code:
      stack=1, locals=1, args_size=1
         0: aload_0
         1: getfield      #45                 // Field initialized:Z
         4: ireturn
      LineNumberTable:
        line 6: 0
      LocalVariableTable:
        Start  Length  Slot  Name   Signature
            0       5     0  this   Lcoursier/cache/internal/ConsoleDim;

  private void initialized_$eq(boolean);
    descriptor: (Z)V
    flags: (0x0002) ACC_PRIVATE
    Code:
      stack=2, locals=2, args_size=2
         0: aload_0
         1: iload_1
         2: putfield      #45                 // Field initialized:Z
         5: return
      LineNumberTable:
        line 6: 0
      LocalVariableTable:
        Start  Length  Slot  Name   Signature
            0       6     0  this   Lcoursier/cache/internal/ConsoleDim;
            0       6     1   x$1   Z
    MethodParameters:
      Name                           Flags
      x$1                            final

  public java.lang.Object coursier$cache$internal$ConsoleDim$$lock();
    descriptor: ()Ljava/lang/Object;
    flags: (0x0001) ACC_PUBLIC
    Code:
      stack=1, locals=1, args_size=1
         0: aload_0
         1: getfield      #50                 // Field coursier$cache$internal$ConsoleDim$$lock:Ljava/lang/Object;
         4: areturn
      LineNumberTable:
        line 7: 0
      LocalVariableTable:
        Start  Length  Slot  Name   Signature
            0       5     0  this   Lcoursier/cache/internal/ConsoleDim;

  private void setup();
    descriptor: ()V
    flags: (0x0002) ACC_PRIVATE
    Code:
      stack=3, locals=1, args_size=1
         0: new           #10                 // class coursier/cache/internal/ConsoleDim$$anon$1
         3: dup
         4: aload_0
         5: invokespecial #58                 // Method coursier/cache/internal/ConsoleDim$$anon$1."<init>":(Lcoursier/cache/internal/ConsoleDim;)V
         8: invokestatic  #64                 // Method coursier/cache/internal/SigWinch.addHandler:(Ljava/lang/Runnable;)V
        11: goto          18
        14: pop
        15: goto          18
        18: aload_0
        19: iconst_1
        20: invokespecial #66                 // Method initialized_$eq:(Z)V
        23: return
      Exception table:
         from    to  target type
             0    11    14   Class java/lang/IllegalArgumentException
      StackMapTable: number_of_entries = 2
        frame_type = 78 /* same_locals_1_stack_item */
          stack = [ class java/lang/IllegalArgumentException ]
        frame_type = 3 /* same */
      LineNumberTable:
        line 15: 0
        line 23: 15
        line 27: 18
      LocalVariableTable:
        Start  Length  Slot  Name   Signature
            0      24     0  this   Lcoursier/cache/internal/ConsoleDim;

  private scala.Tuple2<java.lang.Object, java.lang.Object> dims();
    descriptor: ()Lscala/Tuple2;
    flags: (0x0002) ACC_PRIVATE
    Code:
      stack=2, locals=1, args_size=1
         0: aload_0
         1: invokespecial #71                 // Method coursier$cache$internal$ConsoleDim$$dimsOpt:()Lscala/Option;
         4: aload_0
         5: invokedynamic #91,  0             // InvokeDynamic #0:apply:(Lcoursier/cache/internal/ConsoleDim;)Lscala/Function0;
        10: invokevirtual #97                 // Method scala/Option.getOrElse:(Lscala/Function0;)Ljava/lang/Object;
        13: checkcast     #99                 // class scala/Tuple2
        16: areturn
      LineNumberTable:
        line 31: 0
        line 32: 4
      LocalVariableTable:
        Start  Length  Slot  Name   Signature
            0      17     0  this   Lcoursier/cache/internal/ConsoleDim;
    Signature: #69                          // ()Lscala/Tuple2<Ljava/lang/Object;Ljava/lang/Object;>;

  public int width();
    descriptor: ()I
    flags: (0x0001) ACC_PUBLIC
    Code:
      stack=1, locals=1, args_size=1
         0: aload_0
         1: invokespecial #103                // Method dims:()Lscala/Tuple2;
         4: invokevirtual #106                // Method scala/Tuple2._1$mcI$sp:()I
         7: ireturn
      LineNumberTable:
        line 44: 0
      LocalVariableTable:
        Start  Length  Slot  Name   Signature
            0       8     0  this   Lcoursier/cache/internal/ConsoleDim;

  public int height();
    descriptor: ()I
    flags: (0x0001) ACC_PUBLIC
    Code:
      stack=1, locals=1, args_size=1
         0: aload_0
         1: invokespecial #103                // Method dims:()Lscala/Tuple2;
         4: invokevirtual #110                // Method scala/Tuple2._2$mcI$sp:()I
         7: ireturn
      LineNumberTable:
        line 46: 0
      LocalVariableTable:
        Start  Length  Slot  Name   Signature
            0       8     0  this   Lcoursier/cache/internal/ConsoleDim;

  public static final scala.Tuple2 $anonfun$dims$2(coursier.cache.internal.ConsoleDim);
    descriptor: (Lcoursier/cache/internal/ConsoleDim;)Lscala/Tuple2;
    flags: (0x1019) ACC_PUBLIC, ACC_STATIC, ACC_FINAL, ACC_SYNTHETIC
    Code:
      stack=4, locals=2, args_size=1
         0: aload_0
         1: invokespecial #114                // Method initialized:()Z
         4: ifne          14
         7: aload_0
         8: invokespecial #116                // Method setup:()V
        11: goto          14
        14: getstatic     #121                // Field coursier/cache/internal/Terminal$.MODULE$:Lcoursier/cache/internal/Terminal$;
        17: invokevirtual #124                // Method coursier/cache/internal/Terminal$.consoleDims:()Lscala/Tuple2;
        20: astore_1
        21: aload_0
        22: new           #126                // class scala/Some
        25: dup
        26: aload_1
        27: invokespecial #129                // Method scala/Some."<init>":(Ljava/lang/Object;)V
        30: invokevirtual #131                // Method coursier$cache$internal$ConsoleDim$$dimsOpt_$eq:(Lscala/Option;)V
        33: aload_1
        34: areturn
      StackMapTable: number_of_entries = 1
        frame_type = 14 /* same */
      LineNumberTable:
        line 34: 0
        line 35: 7
        line 36: 14
        line 37: 21
        line 38: 33
      LocalVariableTable:
        Start  Length  Slot  Name   Signature
           21      13     1  dims   Lscala/Tuple2;
            0      35     0 $this   Lcoursier/cache/internal/ConsoleDim;
    MethodParameters:
      Name                           Flags
      $this                          final synthetic

  public static final scala.Tuple2 $anonfun$dims$1(coursier.cache.internal.ConsoleDim);
    descriptor: (Lcoursier/cache/internal/ConsoleDim;)Lscala/Tuple2;
    flags: (0x1019) ACC_PUBLIC, ACC_STATIC, ACC_FINAL, ACC_SYNTHETIC
    Code:
      stack=2, locals=3, args_size=1
         0: aload_0
         1: invokevirtual #134                // Method coursier$cache$internal$ConsoleDim$$lock:()Ljava/lang/Object;
         4: dup
         5: astore_1
         6: monitorenter
         7: aload_0
         8: invokespecial #71                 // Method coursier$cache$internal$ConsoleDim$$dimsOpt:()Lscala/Option;
        11: aload_0
        12: invokedynamic #138,  0            // InvokeDynamic #1:apply:(Lcoursier/cache/internal/ConsoleDim;)Lscala/Function0;
        17: invokevirtual #97                 // Method scala/Option.getOrElse:(Lscala/Function0;)Ljava/lang/Object;
        20: checkcast     #99                 // class scala/Tuple2
        23: astore_2
        24: aload_1
        25: monitorexit
        26: aload_2
        27: goto          33
        30: aload_1
        31: monitorexit
        32: athrow
        33: areturn
      Exception table:
         from    to  target type
             7    24    30   any
      StackMapTable: number_of_entries = 2
        frame_type = 255 /* full_frame */
          offset_delta = 30
          locals = [ class coursier/cache/internal/ConsoleDim, class java/lang/Object ]
          stack = [ class java/lang/Throwable ]
        frame_type = 255 /* full_frame */
          offset_delta = 2
          locals = [ class coursier/cache/internal/ConsoleDim, class java/lang/Object, class scala/Tuple2 ]
          stack = [ class scala/Tuple2 ]
      LineNumberTable:
        line 32: 0
        line 33: 7
        line 32: 33
      LocalVariableTable:
        Start  Length  Slot  Name   Signature
            0      34     0 $this   Lcoursier/cache/internal/ConsoleDim;
    MethodParameters:
      Name                           Flags
      $this                          final synthetic

  public coursier.cache.internal.ConsoleDim();
    descriptor: ()V
    flags: (0x0001) ACC_PUBLIC
    Code:
      stack=3, locals=1, args_size=1
         0: aload_0
         1: invokespecial #142                // Method java/lang/Object."<init>":()V
         4: aload_0
         5: getstatic     #147                // Field scala/None$.MODULE$:Lscala/None$;
         8: putfield      #36                 // Field coursier$cache$internal$ConsoleDim$$dimsOpt:Lscala/Option;
        11: aload_0
        12: iconst_0
        13: putfield      #45                 // Field initialized:Z
        16: aload_0
        17: new           #4                  // class java/lang/Object
        20: dup
        21: invokespecial #142                // Method java/lang/Object."<init>":()V
        24: putfield      #50                 // Field coursier$cache$internal$ConsoleDim$$lock:Ljava/lang/Object;
        27: return
      LineNumberTable:
        line 50: 0
        line 5: 4
        line 6: 11
        line 7: 16
        line 3: 27
      LocalVariableTable:
        Start  Length  Slot  Name   Signature
            0      28     0  this   Lcoursier/cache/internal/ConsoleDim;

  private static java.lang.Object $deserializeLambda$(java.lang.invoke.SerializedLambda);
    descriptor: (Ljava/lang/invoke/SerializedLambda;)Ljava/lang/Object;
    flags: (0x100a) ACC_PRIVATE, ACC_STATIC, ACC_SYNTHETIC
    Code:
      stack=1, locals=1, args_size=1
         0: aload_0
         1: invokedynamic #159,  0            // InvokeDynamic #2:lambdaDeserialize:(Ljava/lang/invoke/SerializedLambda;)Ljava/lang/Object;
         6: areturn
}
InnerClasses:
  public final #10;                       // class coursier/cache/internal/ConsoleDim$$anon$1
  public static final #15= #12 of #14;    // Lookup=class java/lang/invoke/MethodHandles$Lookup of class java/lang/invoke/MethodHandles
SourceFile: "ConsoleDim.scala"
RuntimeVisibleAnnotations:
  0: #6(#7=s#8)
    scala.reflect.ScalaSignature(
      bytes="\u0006\u0005}3A\u0001F\u000b\u00039!)1\u0005\u0001C\u0001I!9q\u0005\u0001a\u0001\n\u0013A\u0003b\u0002\u0017\u0001\u0001\u0004%I!\f\u0005\u0007g\u0001\u0001\u000b\u0015B\u0015\t\u000fQ\u0002!\u0019!C\u0005k!1a\b\u0001Q\u0001\nYBQa\u0010\u0001\u0005\n\u0001CQ!\u0011\u0001\u0005\n\tCQ!\u0013\u0001\u0005\u0002)CQa\u0013\u0001\u0005\u0002)Cq\u0001\u0014\u0001A\u0002\u0013%Q\nC\u0004R\u0001\u0001\u0007I\u0011\u0002*\t\rQ\u0003\u0001\u0015)\u0003O\u000f\u0015IV\u0003#\u0001[\r\u0015!R\u0003#\u0001\\\u0011\u0015\u0019s\u0002\"\u0001]\u0011!iv\u0002#b\u0001\n\u0003q\u0006\"B%\u0010\t\u0003Q\u0005\"B&\u0010\t\u0003Q%AC\"p]N|G.\u001a#j[*\u0011acF\u0001\tS:$XM\u001d8bY*\u0011\u0001$G\u0001\u0006G\u0006\u001c\u0007.\u001a\u0006\u00025\u0005A1m\\;sg&,\'o\u0001\u0001\u0014\u0005\u0001i\u0002C\u0001\u0010\"\u001b\u0005y\"\"\u0001\u0011\u0002\u000bM\u001c\u0017\r\\1\n\u0005\tz\"AB!osJ+g-\u0001\u0004=S:LGO\u0010\u000b\u0002KA\u0011a\u0005A\u0007\u0002+\u0005Y\u0011N\\5uS\u0006d\u0017N_3e+\u0005I\u0003C\u0001\u0010+\u0013\tYsDA\u0004C_>dW-\u00198\u0002\u001f%t\u0017\u000e^5bY&TX\rZ0%KF$\"AL\u0019\u0011\u0005yy\u0013B\u0001\u0019 \u0005\u0011)f.\u001b;\t\u000fI\u001a\u0011\u0011!a\u0001S\u0005\u0019\u0001\u0010J\u0019\u0002\u0019%t\u0017\u000e^5bY&TX\r\u001a\u0011\u0002\t1|7m[\u000b\u0002mA\u0011q\u0007P\u0007\u0002q)\u0011\u0011HO\u0001\u0005Y\u0006twMC\u0001<\u0003\u0011Q\u0017M^1\n\u0005uB$AB(cU\u0016\u001cG/A\u0003m_\u000e\\\u0007%A\u0003tKR,\b\u000fF\u0001/\u0003\u0011!\u0017.\\:\u0015\u0003\r\u0003BA\b#G\r&\u0011Qi\b\u0002\u0007)V\u0004H.\u001a\u001a\u0011\u0005y9\u0015B\u0001% \u0005\rIe\u000e^\u0001\u0006o&$G\u000f\u001b\u000b\u0002\r\u00061\u0001.Z5hQR\fq\u0001Z5ng>\u0003H/F\u0001O!\rqrjQ\u0005\u0003!~\u0011aa\u00149uS>t\u0017a\u00033j[N|\u0005\u000f^0%KF$\"AL*\t\u000fIb\u0011\u0011!a\u0001\u001d\u0006AA-[7t\u001fB$\b\u0005\u000b\u0002\u000e-B\u0011adV\u0005\u00031~\u0011\u0001B^8mCRLG.Z\u0001\u000b\u0007>t7o\u001c7f\t&l\u0007C\u0001\u0014\u0010\'\tyQ\u0004F\u0001[\u0003\r9W\r^\u000b\u0002K\u0001"
    )
BootstrapMethods:
  0: #87 REF_invokeStatic java/lang/invoke/LambdaMetafactory.altMetafactory:(Ljava/lang/invoke/MethodHandles$Lookup;Ljava/lang/String;Ljava/lang/invoke/MethodType;[Ljava/lang/Object;)Ljava/lang/invoke/CallSite;
    Method arguments:
      #72 ()Ljava/lang/Object;
      #77 REF_invokeStatic coursier/cache/internal/ConsoleDim.$anonfun$dims$1:(Lcoursier/cache/internal/ConsoleDim;)Lscala/Tuple2;
      #78 ()Lscala/Tuple2;
      #79 5
      #80 1
      #78 ()Lscala/Tuple2;
  1: #87 REF_invokeStatic java/lang/invoke/LambdaMetafactory.altMetafactory:(Ljava/lang/invoke/MethodHandles$Lookup;Ljava/lang/String;Ljava/lang/invoke/MethodType;[Ljava/lang/Object;)Ljava/lang/invoke/CallSite;
    Method arguments:
      #72 ()Ljava/lang/Object;
      #137 REF_invokeStatic coursier/cache/internal/ConsoleDim.$anonfun$dims$2:(Lcoursier/cache/internal/ConsoleDim;)Lscala/Tuple2;
      #78 ()Lscala/Tuple2;
      #79 5
      #80 1
      #78 ()Lscala/Tuple2;
  2: #156 REF_invokeStatic scala/runtime/LambdaDeserialize.bootstrap:(Ljava/lang/invoke/MethodHandles$Lookup;Ljava/lang/String;Ljava/lang/invoke/MethodType;[Ljava/lang/invoke/MethodHandle;)Ljava/lang/invoke/CallSite;
    Method arguments:
      #77 REF_invokeStatic coursier/cache/internal/ConsoleDim.$anonfun$dims$1:(Lcoursier/cache/internal/ConsoleDim;)Lscala/Tuple2;
      #137 REF_invokeStatic coursier/cache/internal/ConsoleDim.$anonfun$dims$2:(Lcoursier/cache/internal/ConsoleDim;)Lscala/Tuple2;
  ScalaInlineInfo: length = 0x40 (unknown attribute)
   01 01 00 0C 00 49 00 4A 01 00 6F 00 4A 01 00 37
   00 34 01 00 14 00 21 01 00 27 00 28 01 00 12 00
   30 01 00 43 00 44 01 00 6B 00 65 01 00 10 00 2B
   01 00 2E 00 2F 01 00 33 00 34 01 00 64 00 65 01

  ScalaSig: length = 0x3 (unknown attribute)
   05 02 00
