Classfile /Users/mw/Projects/slang-braindump/.jar/jar11/assemble/slang-braindump/assemble/content/coursier/cache/internal/Terminal$Ansi$.class
  Last modified May 29, 2022; size 2317 bytes
  SHA-256 checksum bbf8ea3a4387eca4bed4b63ca4f4a989c29bd9f8bd02e9b52cd8c3fe246fec45
  Compiled from "Terminal.scala"
public class coursier.cache.internal.Terminal$Ansi$
  minor version: 0
  major version: 52
  flags: (0x0021) ACC_PUBLIC, ACC_SUPER
  this_class: #2                          // coursier/cache/internal/Terminal$Ansi$
  super_class: #4                         // java/lang/Object
  interfaces: 0, fields: 1, methods: 9, attributes: 4
Constant pool:
   #1 = Utf8               coursier/cache/internal/Terminal$Ansi$
   #2 = Class              #1             // coursier/cache/internal/Terminal$Ansi$
   #3 = Utf8               java/lang/Object
   #4 = Class              #3             // java/lang/Object
   #5 = Utf8               Terminal.scala
   #6 = Utf8               coursier/cache/internal/Terminal$Ansi
   #7 = Class              #6             // coursier/cache/internal/Terminal$Ansi
   #8 = Utf8               coursier/cache/internal/Terminal
   #9 = Class              #8             // coursier/cache/internal/Terminal
  #10 = Utf8               Ansi
  #11 = Utf8
  #12 = Utf8               MODULE$
  #13 = Utf8               Lcoursier/cache/internal/Terminal$Ansi$;
  #14 = Utf8               <clinit>
  #15 = Utf8               ()V
  #16 = Utf8               <init>
  #17 = NameAndType        #16:#15        // "<init>":()V
  #18 = Methodref          #2.#17         // coursier/cache/internal/Terminal$Ansi$."<init>":()V
  #19 = NameAndType        #12:#13        // MODULE$:Lcoursier/cache/internal/Terminal$Ansi$;
  #20 = Fieldref           #2.#19         // coursier/cache/internal/Terminal$Ansi$.MODULE$:Lcoursier/cache/internal/Terminal$Ansi$;
  #21 = Utf8               control$extension
  #22 = Utf8               (Ljava/io/Writer;IC)V
  #23 = Utf8               $this
  #24 = Utf8               n
  #25 = Utf8               c
  #26 = Utf8               java/lang/StringBuilder
  #27 = Class              #26            // java/lang/StringBuilder
  #28 = Integer            2
  #29 = Utf8               (I)V
  #30 = NameAndType        #16:#29        // "<init>":(I)V
  #31 = Methodref          #27.#30        // java/lang/StringBuilder."<init>":(I)V
  #32 = Utf8               \u001b[
  #33 = String             #32            // \u001b[
  #34 = Utf8               append
  #35 = Utf8               (Ljava/lang/String;)Ljava/lang/StringBuilder;
  #36 = NameAndType        #34:#35        // append:(Ljava/lang/String;)Ljava/lang/StringBuilder;
  #37 = Methodref          #27.#36        // java/lang/StringBuilder.append:(Ljava/lang/String;)Ljava/lang/StringBuilder;
  #38 = Utf8               (I)Ljava/lang/StringBuilder;
  #39 = NameAndType        #34:#38        // append:(I)Ljava/lang/StringBuilder;
  #40 = Methodref          #27.#39        // java/lang/StringBuilder.append:(I)Ljava/lang/StringBuilder;
  #41 = Utf8               (C)Ljava/lang/StringBuilder;
  #42 = NameAndType        #34:#41        // append:(C)Ljava/lang/StringBuilder;
  #43 = Methodref          #27.#42        // java/lang/StringBuilder.append:(C)Ljava/lang/StringBuilder;
  #44 = Utf8               toString
  #45 = Utf8               ()Ljava/lang/String;
  #46 = NameAndType        #44:#45        // toString:()Ljava/lang/String;
  #47 = Methodref          #27.#46        // java/lang/StringBuilder.toString:()Ljava/lang/String;
  #48 = Utf8               java/io/Writer
  #49 = Class              #48            // java/io/Writer
  #50 = Utf8               write
  #51 = Utf8               (Ljava/lang/String;)V
  #52 = NameAndType        #50:#51        // write:(Ljava/lang/String;)V
  #53 = Methodref          #49.#52        // java/io/Writer.write:(Ljava/lang/String;)V
  #54 = Utf8               this
  #55 = Utf8               Ljava/io/Writer;
  #56 = Utf8               I
  #57 = Utf8               C
  #58 = Utf8               up$extension
  #59 = Utf8               (Ljava/io/Writer;I)V
  #60 = NameAndType        #21:#22        // control$extension:(Ljava/io/Writer;IC)V
  #61 = Methodref          #2.#60         // coursier/cache/internal/Terminal$Ansi$.control$extension:(Ljava/io/Writer;IC)V
  #62 = Utf8               down$extension
  #63 = Utf8               left$extension
  #64 = Utf8               clearLine$extension
  #65 = Utf8               hashCode$extension
  #66 = Utf8               (Ljava/io/Writer;)I
  #67 = Utf8               hashCode
  #68 = Utf8               ()I
  #69 = NameAndType        #67:#68        // hashCode:()I
  #70 = Methodref          #49.#69        // java/io/Writer.hashCode:()I
  #71 = Utf8               equals$extension
  #72 = Utf8               (Ljava/io/Writer;Ljava/lang/Object;)Z
  #73 = Utf8               x$1
  #74 = Utf8               output
  #75 = Utf8               ()Ljava/io/Writer;
  #76 = NameAndType        #74:#75        // output:()Ljava/io/Writer;
  #77 = Methodref          #7.#76         // coursier/cache/internal/Terminal$Ansi.output:()Ljava/io/Writer;
  #78 = Utf8               equals
  #79 = Utf8               (Ljava/lang/Object;)Z
  #80 = NameAndType        #78:#79        // equals:(Ljava/lang/Object;)Z
  #81 = Methodref          #4.#80         // java/lang/Object.equals:(Ljava/lang/Object;)Z
  #82 = Utf8               Ljava/lang/Object;
  #83 = Methodref          #4.#17         // java/lang/Object."<init>":()V
  #84 = Utf8               Code
  #85 = Utf8               LineNumberTable
  #86 = Utf8               LocalVariableTable
  #87 = Utf8               MethodParameters
  #88 = Utf8               StackMapTable
  #89 = Utf8               InnerClasses
  #90 = Utf8               SourceFile
  #91 = Utf8               ScalaInlineInfo
  #92 = Utf8               Scala
{
  public static final coursier.cache.internal.Terminal$Ansi$ MODULE$;
    descriptor: Lcoursier/cache/internal/Terminal$Ansi$;
    flags: (0x0019) ACC_PUBLIC, ACC_STATIC, ACC_FINAL

  public static {};
    descriptor: ()V
    flags: (0x0009) ACC_PUBLIC, ACC_STATIC
    Code:
      stack=2, locals=0, args_size=0
         0: new           #2                  // class coursier/cache/internal/Terminal$Ansi$
         3: dup
         4: invokespecial #18                 // Method "<init>":()V
         7: putstatic     #20                 // Field MODULE$:Lcoursier/cache/internal/Terminal$Ansi$;
        10: return
      LineNumberTable:
        line 82: 0

  public final void control$extension(java.io.Writer, int, char);
    descriptor: (Ljava/io/Writer;IC)V
    flags: (0x0011) ACC_PUBLIC, ACC_FINAL
    Code:
      stack=4, locals=4, args_size=4
         0: aload_1
         1: new           #27                 // class java/lang/StringBuilder
         4: dup
         5: ldc           #28                 // int 2
         7: invokespecial #31                 // Method java/lang/StringBuilder."<init>":(I)V
        10: ldc           #33                 // String \u001b[
        12: invokevirtual #37                 // Method java/lang/StringBuilder.append:(Ljava/lang/String;)Ljava/lang/StringBuilder;
        15: iload_2
        16: invokevirtual #40                 // Method java/lang/StringBuilder.append:(I)Ljava/lang/StringBuilder;
        19: iload_3
        20: invokevirtual #43                 // Method java/lang/StringBuilder.append:(C)Ljava/lang/StringBuilder;
        23: invokevirtual #47                 // Method java/lang/StringBuilder.toString:()Ljava/lang/String;
        26: invokevirtual #53                 // Method java/io/Writer.write:(Ljava/lang/String;)V
        29: return
      LineNumberTable:
        line 84: 0
      LocalVariableTable:
        Start  Length  Slot  Name   Signature
            0      30     0  this   Lcoursier/cache/internal/Terminal$Ansi$;
            0      30     1 $this   Ljava/io/Writer;
            0      30     2     n   I
            0      30     3     c   C
    MethodParameters:
      Name                           Flags
      $this                          final
      n                              final
      c                              final

  public final void up$extension(java.io.Writer, int);
    descriptor: (Ljava/io/Writer;I)V
    flags: (0x0011) ACC_PUBLIC, ACC_FINAL
    Code:
      stack=4, locals=3, args_size=3
         0: iload_2
         1: iconst_0
         2: if_icmple     16
         5: aload_0
         6: aload_1
         7: iload_2
         8: bipush        65
        10: invokevirtual #61                 // Method control$extension:(Ljava/io/Writer;IC)V
        13: goto          16
        16: return
      StackMapTable: number_of_entries = 1
        frame_type = 16 /* same */
      LineNumberTable:
        line 89: 0
      LocalVariableTable:
        Start  Length  Slot  Name   Signature
            0      17     0  this   Lcoursier/cache/internal/Terminal$Ansi$;
            0      17     1 $this   Ljava/io/Writer;
            0      17     2     n   I
    MethodParameters:
      Name                           Flags
      $this                          final
      n                              final

  public final void down$extension(java.io.Writer, int);
    descriptor: (Ljava/io/Writer;I)V
    flags: (0x0011) ACC_PUBLIC, ACC_FINAL
    Code:
      stack=4, locals=3, args_size=3
         0: iload_2
         1: iconst_0
         2: if_icmple     16
         5: aload_0
         6: aload_1
         7: iload_2
         8: bipush        66
        10: invokevirtual #61                 // Method control$extension:(Ljava/io/Writer;IC)V
        13: goto          16
        16: return
      StackMapTable: number_of_entries = 1
        frame_type = 16 /* same */
      LineNumberTable:
        line 93: 0
      LocalVariableTable:
        Start  Length  Slot  Name   Signature
            0      17     0  this   Lcoursier/cache/internal/Terminal$Ansi$;
            0      17     1 $this   Ljava/io/Writer;
            0      17     2     n   I
    MethodParameters:
      Name                           Flags
      $this                          final
      n                              final

  public final void left$extension(java.io.Writer, int);
    descriptor: (Ljava/io/Writer;I)V
    flags: (0x0011) ACC_PUBLIC, ACC_FINAL
    Code:
      stack=4, locals=3, args_size=3
         0: iload_2
         1: iconst_0
         2: if_icmple     16
         5: aload_0
         6: aload_1
         7: iload_2
         8: bipush        68
        10: invokevirtual #61                 // Method control$extension:(Ljava/io/Writer;IC)V
        13: goto          16
        16: return
      StackMapTable: number_of_entries = 1
        frame_type = 16 /* same */
      LineNumberTable:
        line 97: 0
      LocalVariableTable:
        Start  Length  Slot  Name   Signature
            0      17     0  this   Lcoursier/cache/internal/Terminal$Ansi$;
            0      17     1 $this   Ljava/io/Writer;
            0      17     2     n   I
    MethodParameters:
      Name                           Flags
      $this                          final
      n                              final

  public final void clearLine$extension(java.io.Writer, int);
    descriptor: (Ljava/io/Writer;I)V
    flags: (0x0011) ACC_PUBLIC, ACC_FINAL
    Code:
      stack=4, locals=3, args_size=3
         0: aload_0
         1: aload_1
         2: iload_2
         3: bipush        75
         5: invokevirtual #61                 // Method control$extension:(Ljava/io/Writer;IC)V
         8: return
      LineNumberTable:
        line 107: 2
      LocalVariableTable:
        Start  Length  Slot  Name   Signature
            0       9     0  this   Lcoursier/cache/internal/Terminal$Ansi$;
            0       9     1 $this   Ljava/io/Writer;
            0       9     2     n   I
    MethodParameters:
      Name                           Flags
      $this                          final
      n                              final

  public final int hashCode$extension(java.io.Writer);
    descriptor: (Ljava/io/Writer;)I
    flags: (0x0011) ACC_PUBLIC, ACC_FINAL
    Code:
      stack=1, locals=2, args_size=2
         0: aload_1
         1: invokevirtual #70                 // Method java/io/Writer.hashCode:()I
         4: ireturn
      LineNumberTable:
        line 82: 0
      LocalVariableTable:
        Start  Length  Slot  Name   Signature
            0       5     0  this   Lcoursier/cache/internal/Terminal$Ansi$;
            0       5     1 $this   Ljava/io/Writer;
    MethodParameters:
      Name                           Flags
      $this                          final

  public final boolean equals$extension(java.io.Writer, java.lang.Object);
    descriptor: (Ljava/io/Writer;Ljava/lang/Object;)Z
    flags: (0x0011) ACC_PUBLIC, ACC_FINAL
    Code:
      stack=2, locals=7, args_size=3
         0: aload_2
         1: astore        4
         3: aload         4
         5: instanceof    #7                  // class coursier/cache/internal/Terminal$Ansi
         8: ifeq          16
        11: iconst_1
        12: istore_3
        13: goto          24
        16: goto          19
        19: iconst_0
        20: istore_3
        21: goto          24
        24: iload_3
        25: ifeq          83
        28: aload_2
        29: ifnonnull     36
        32: aconst_null
        33: goto          43
        36: aload_2
        37: checkcast     #7                  // class coursier/cache/internal/Terminal$Ansi
        40: invokevirtual #77                 // Method coursier/cache/internal/Terminal$Ansi.output:()Ljava/io/Writer;
        43: astore        5
        45: aload_1
        46: aload         5
        48: astore        6
        50: dup
        51: ifnonnull     63
        54: pop
        55: aload         6
        57: ifnull        71
        60: goto          75
        63: aload         6
        65: invokevirtual #81                 // Method java/lang/Object.equals:(Ljava/lang/Object;)Z
        68: ifeq          75
        71: iconst_1
        72: goto          76
        75: iconst_0
        76: ifeq          83
        79: iconst_1
        80: goto          84
        83: iconst_0
        84: ireturn
      StackMapTable: number_of_entries = 11
        frame_type = 253 /* append */
          offset_delta = 16
          locals = [ top, class java/lang/Object ]
        frame_type = 2 /* same */
        frame_type = 255 /* full_frame */
          offset_delta = 4
          locals = [ class coursier/cache/internal/Terminal$Ansi$, class java/io/Writer, class java/lang/Object, int, class java/lang/Object ]
          stack = []
        frame_type = 11 /* same */
        frame_type = 70 /* same_locals_1_stack_item */
          stack = [ class java/io/Writer ]
        frame_type = 255 /* full_frame */
          offset_delta = 19
          locals = [ class coursier/cache/internal/Terminal$Ansi$, class java/io/Writer, class java/lang/Object, int, class java/lang/Object, class java/io/Writer, class java/io/Writer ]
          stack = [ class java/io/Writer ]
        frame_type = 7 /* same */
        frame_type = 3 /* same */
        frame_type = 64 /* same_locals_1_stack_item */
          stack = [ int ]
        frame_type = 249 /* chop */
          offset_delta = 6
        frame_type = 64 /* same_locals_1_stack_item */
          stack = [ int ]
      LineNumberTable:
        line 82: 0
      LocalVariableTable:
        Start  Length  Slot  Name   Signature
            0      85     0  this   Lcoursier/cache/internal/Terminal$Ansi$;
            0      85     1 $this   Ljava/io/Writer;
            0      85     2   x$1   Ljava/lang/Object;
    MethodParameters:
      Name                           Flags
      $this                          final
      x$1                            final

  public coursier.cache.internal.Terminal$Ansi$();
    descriptor: ()V
    flags: (0x0001) ACC_PUBLIC
    Code:
      stack=1, locals=1, args_size=1
         0: aload_0
         1: invokespecial #83                 // Method java/lang/Object."<init>":()V
         4: return
      LineNumberTable:
        line 82: 0
      LocalVariableTable:
        Start  Length  Slot  Name   Signature
            0       5     0  this   Lcoursier/cache/internal/Terminal$Ansi$;
}
InnerClasses:
  public static final #10= #7 of #9;      // Ansi=class coursier/cache/internal/Terminal$Ansi of class coursier/cache/internal/Terminal
  public static #11= #2 of #9;            // =class coursier/cache/internal/Terminal$Ansi$ of class coursier/cache/internal/Terminal
SourceFile: "Terminal.scala"
  ScalaInlineInfo: length = 0x2C (unknown attribute)
   01 01 00 08 00 10 00 0F 01 00 40 00 3B 01 00 15
   00 16 01 00 3E 00 3B 01 00 47 00 48 01 00 41 00
   42 01 00 3F 00 3B 01 00 3A 00 3B 01
  Scala: length = 0x0 (unknown attribute)

