Classfile /Users/mw/Projects/slang-braindump/.jar/jar8/assemble/slang-braindump/assemble/content/scala/util/ChainingSyntax.class
  Last modified May 29, 2022; size 1183 bytes
  SHA-256 checksum de9ff0e254e7653f885bc97fca6bae111b7c18bb66457712bdf7d5447ed83513
  Compiled from "ChainingOps.scala"
public interface scala.util.ChainingSyntax
  minor version: 0
  major version: 52
  flags: (0x0601) ACC_PUBLIC, ACC_INTERFACE, ACC_ABSTRACT
  this_class: #2                          // scala/util/ChainingSyntax
  super_class: #4                         // java/lang/Object
  interfaces: 0, fields: 0, methods: 3, attributes: 4
Constant pool:
   #1 = Utf8               scala/util/ChainingSyntax
   #2 = Class              #1             // scala/util/ChainingSyntax
   #3 = Utf8               java/lang/Object
   #4 = Class              #3             // java/lang/Object
   #5 = Utf8               ChainingOps.scala
   #6 = Utf8               Lscala/reflect/ScalaSignature;
   #7 = Utf8               bytes
   #8 = Utf8               \u0006\u0005-2qa\u0001\u0003\u0011\u0002\u0007\u0005\u0011\u0002C\u0003\u000f\u0001\u0011\u0005q\u0002C\u0003\u0014\u0001\u0011\u001dAC\u0001\bDQ\u0006Lg.\u001b8h\'ftG/\u0019=\u000b\u0005\u00151\u0011\u0001B;uS2T\u0011aB\u0001\u0006g\u000e\fG.Y\u0002\u0001\'\t\u0001!\u0002\u0005\u0002\f\u00195\ta!\u0003\u0002\u000e\r\t1\u0011I\\=SK\u001a\fa\u0001J5oSR$C#\u0001\t\u0011\u0005-\t\u0012B\u0001\n\u0007\u0005\u0011)f.\u001b;\u0002)M\u001c\u0017\r\\1Vi&d7\t[1j]&twm\u00149t+\t)B\u0004\u0006\u0002\u0017KA\u0019q\u0003\u0007\u000e\u000e\u0003\u0011I!!\u0007\u0003\u0003\u0017\rC\u0017-\u001b8j]\u001e|\u0005o\u001d\t\u00037qa\u0001\u0001B\u0003\u001e\u0005\t\u0007aDA\u0001B#\ty\"\u0005\u0005\u0002\fA%\u0011\u0011E\u0002\u0002\b\u001d>$\b.\u001b8h!\tY1%\u0003\u0002%\r\t\u0019\u0011I\\=\t\u000b\u0019\u0012\u0001\u0019\u0001\u000e\u0002\u0003\u0005D#A\u0001\u0015\u0011\u0005-I\u0013B\u0001\u0016\u0007\u0005\u0019Ig\u000e\\5oK\u0002
   #9 = Utf8               scalaUtilChainingOps$
  #10 = Utf8               (Lscala/util/ChainingSyntax;Ljava/lang/Object;)Ljava/lang/Object;
  #11 = Utf8               $this
  #12 = Utf8               a
  #13 = Utf8               scalaUtilChainingOps
  #14 = Utf8               (Ljava/lang/Object;)Ljava/lang/Object;
  #15 = NameAndType        #13:#14        // scalaUtilChainingOps:(Ljava/lang/Object;)Ljava/lang/Object;
  #16 = InterfaceMethodref #2.#15         // scala/util/ChainingSyntax.scalaUtilChainingOps:(Ljava/lang/Object;)Ljava/lang/Object;
  #17 = Utf8               Lscala/util/ChainingSyntax;
  #18 = Utf8               Ljava/lang/Object;
  #19 = Utf8               <A:Ljava/lang/Object;>(TA;)TA;
  #20 = Utf8               this
  #21 = Utf8               $init$
  #22 = Utf8               (Lscala/util/ChainingSyntax;)V
  #23 = Utf8               Code
  #24 = Utf8               LineNumberTable
  #25 = Utf8               LocalVariableTable
  #26 = Utf8               MethodParameters
  #27 = Utf8               Signature
  #28 = Utf8               SourceFile
  #29 = Utf8               RuntimeVisibleAnnotations
  #30 = Utf8               ScalaInlineInfo
  #31 = Utf8               ScalaSig
{
  public static java.lang.Object scalaUtilChainingOps$(scala.util.ChainingSyntax, java.lang.Object);
    descriptor: (Lscala/util/ChainingSyntax;Ljava/lang/Object;)Ljava/lang/Object;
    flags: (0x1009) ACC_PUBLIC, ACC_STATIC, ACC_SYNTHETIC
    Code:
      stack=2, locals=2, args_size=2
         0: aload_0
         1: aload_1
         2: invokespecial #16                 // InterfaceMethod scalaUtilChainingOps:(Ljava/lang/Object;)Ljava/lang/Object;
         5: areturn
      LineNumberTable:
        line 19: 0
      LocalVariableTable:
        Start  Length  Slot  Name   Signature
            0       6     0 $this   Lscala/util/ChainingSyntax;
            0       6     1     a   Ljava/lang/Object;
    MethodParameters:
      Name                           Flags
      $this                          final synthetic
      a                              final

  public default <A extends java.lang.Object> A scalaUtilChainingOps(A);
    descriptor: (Ljava/lang/Object;)Ljava/lang/Object;
    flags: (0x0001) ACC_PUBLIC
    Code:
      stack=1, locals=2, args_size=2
         0: aload_1
         1: areturn
      LineNumberTable:
        line 19: 0
      LocalVariableTable:
        Start  Length  Slot  Name   Signature
            0       2     0  this   Lscala/util/ChainingSyntax;
            0       2     1     a   Ljava/lang/Object;
    Signature: #19                          // <A:Ljava/lang/Object;>(TA;)TA;
    MethodParameters:
      Name                           Flags
      a                              final

  public static void $init$(scala.util.ChainingSyntax);
    descriptor: (Lscala/util/ChainingSyntax;)V
    flags: (0x0009) ACC_PUBLIC, ACC_STATIC
    Code:
      stack=0, locals=1, args_size=1
         0: return
      LineNumberTable:
        line 18: 0
      LocalVariableTable:
        Start  Length  Slot  Name   Signature
            0       1     0 $this   Lscala/util/ChainingSyntax;
    MethodParameters:
      Name                           Flags
      $this                          final synthetic
}
SourceFile: "ChainingOps.scala"
RuntimeVisibleAnnotations:
  0: #6(#7=s#8)
    scala.reflect.ScalaSignature(
      bytes="\u0006\u0005-2qa\u0001\u0003\u0011\u0002\u0007\u0005\u0011\u0002C\u0003\u000f\u0001\u0011\u0005q\u0002C\u0003\u0014\u0001\u0011\u001dAC\u0001\bDQ\u0006Lg.\u001b8h\'ftG/\u0019=\u000b\u0005\u00151\u0011\u0001B;uS2T\u0011aB\u0001\u0006g\u000e\fG.Y\u0002\u0001\'\t\u0001!\u0002\u0005\u0002\f\u00195\ta!\u0003\u0002\u000e\r\t1\u0011I\\=SK\u001a\fa\u0001J5oSR$C#\u0001\t\u0011\u0005-\t\u0012B\u0001\n\u0007\u0005\u0011)f.\u001b;\u0002)M\u001c\u0017\r\\1Vi&d7\t[1j]&twm\u00149t+\t)B\u0004\u0006\u0002\u0017KA\u0019q\u0003\u0007\u000e\u000e\u0003\u0011I!!\u0007\u0003\u0003\u0017\rC\u0017-\u001b8j]\u001e|\u0005o\u001d\t\u00037qa\u0001\u0001B\u0003\u001e\u0005\t\u0007aDA\u0001B#\ty\"\u0005\u0005\u0002\fA%\u0011\u0011E\u0002\u0002\b\u001d>$\b.\u001b8h!\tY1%\u0003\u0002%\r\t\u0019\u0011I\\=\t\u000b\u0019\u0012\u0001\u0019\u0001\u000e\u0002\u0003\u0005D#A\u0001\u0015\u0011\u0005-I\u0013B\u0001\u0016\u0007\u0005\u0019Ig\u000e\\5oK\u0002"
    )
  ScalaInlineInfo: length = 0x13 (unknown attribute)
   01 00 00 03 00 15 00 16 01 00 0D 00 0E 05 00 09
   00 0A 05
  ScalaSig: length = 0x3 (unknown attribute)
   05 02 00
