Classfile /Users/mw/Projects/slang-braindump/.jar/jar8/assemble/slang-braindump/assemble/content/scala/util/Right.class
  Last modified May 29, 2022; size 5011 bytes
  SHA-256 checksum ef8331425ed4b939843dda8c08be80d800bae7d5648a36210b8b3f44a7413f7d
  Compiled from "Either.scala"
public final class scala.util.Right<A extends java.lang.Object, B extends java.lang.Object> extends scala.util.Either<A, B>
  minor version: 0
  major version: 52
  flags: (0x0031) ACC_PUBLIC, ACC_FINAL, ACC_SUPER
  this_class: #2                          // scala/util/Right
  super_class: #5                         // scala/util/Either
  interfaces: 0, fields: 1, methods: 18, attributes: 6
Constant pool:
    #1 = Utf8               scala/util/Right
    #2 = Class              #1            // scala/util/Right
    #3 = Utf8               <A:Ljava/lang/Object;B:Ljava/lang/Object;>Lscala/util/Either<TA;TB;>;
    #4 = Utf8               scala/util/Either
    #5 = Class              #4            // scala/util/Either
    #6 = Utf8               Either.scala
    #7 = Utf8               Lscala/reflect/ScalaSignature;
    #8 = Utf8               bytes
    #9 = Utf8               \u0006\u0005\u0005}d\u0001B\r\u001b\u0005~A\u0001b\u0011\u0001\u0003\u0016\u0004%\t\u0001\u0012\u0005\t\u000b\u0002\u0011\t\u0012)A\u0005c!)a\t\u0001C\u0001\u000f\")!\n\u0001C\u0001\u0017\")q\n\u0001C\u0001\u0017\")\u0001\u000b\u0001C\u0001#\"9\u0001\fAA\u0001\n\u0003I\u0006bB1\u0001#\u0003%\tA\u0019\u0005\ba\u0002\t\t\u0011\"\u0011r\u0011\u001dQ\b!!A\u0005\u0002mD\u0001b \u0001\u0002\u0002\u0013\u0005\u0011\u0011\u0001\u0005\n\u0003\u000f\u0001\u0011\u0011!C!\u0003\u0013A\u0011\"a\u0006\u0001\u0003\u0003%\t!!\u0007\t\u0013\u0005u\u0001!!A\u0005B\u0005}\u0001\"CA\u0012\u0001\u0005\u0005I\u0011IA\u0013\u0011%\t9\u0003AA\u0001\n\u0003\nI\u0003C\u0005\u0002,\u0001\t\t\u0011\"\u0011\u0002.\u001dI\u0011\u0011\u0007\u000e\u0002\u0002#\u0005\u00111\u0007\u0004\t3i\t\t\u0011#\u0001\u00026!1ai\u0005C\u0001\u0003\u000fB\u0011\"a\n\u0014\u0003\u0003%)%!\u000b\t\u0013\u0005%3#!A\u0005\u0002\u0006-\u0003\"CA.\'\u0005\u0005I\u0011QA/\u0011%\t)hEA\u0001\n\u0013\t9HA\u0003SS\u001eDGO\u0003\u0002\u001c9\u0005!Q\u000f^5m\u0015\u0005i\u0012!B:dC2\f7\u0001A\u000b\u0004A\u001d\u00124\u0003\u0002\u0001\"i]\u0002BAI\u0012&c5\t!$\u0003\u0002%5\t1Q)\u001b;iKJ\u0004\"AJ\u0014\r\u0001\u00111\u0001\u0006\u0001CC\u0002%\u0012\u0011!Q\t\u0003U9\u0002\"a\u000b\u0017\u000e\u0003qI!!\f\u000f\u0003\u000f9{G\u000f[5oOB\u00111fL\u0005\u0003aq\u00111!\u00118z!\t1#\u0007\u0002\u00044\u0001\u0011\u0015\r!\u000b\u0002\u0002\u0005B\u00111&N\u0005\u0003mq\u0011q\u0001\u0015:pIV\u001cG\u000f\u0005\u00029\u0001:\u0011\u0011H\u0010\b\u0003uuj\u0011a\u000f\u0006\u0003yy\ta\u0001\u0010:p_Rt\u0014\"A\u000f\n\u0005}b\u0012a\u00029bG.\fw-Z\u0005\u0003\u0003\n\u0013AbU3sS\u0006d\u0017N_1cY\u0016T!a\u0010\u000f\u0002\u000bY\fG.^3\u0016\u0003E\naA^1mk\u0016\u0004\u0013A\u0002\u001fj]&$h\b\u0006\u0002I\u0013B!!\u0005A\u00132\u0011\u0015\u00195\u00011\u00012\u0003\u0019I7\u000fT3giV\tA\n\u0005\u0002,\u001b&\u0011a\n\b\u0002\b\u0005>|G.Z1o\u0003\u001dI7OU5hQR\f\u0001b^5uQ2+g\r^\u000b\u0003%V+\u0012a\u0015\t\u0005E\r\"\u0016\u0007\u0005\u0002\'+\u0012)aK\u0002b\u0001/\n\u0011\u0011)M\t\u0003K9\nAaY8qsV\u0019!,X0\u0015\u0005m\u0003\u0007\u0003\u0002\u0012\u00019z\u0003\"AJ/\u0005\u000b!:!\u0019A\u0015\u0011\u0005\u0019zF!B\u001a\b\u0005\u0004I\u0003bB\"\b!\u0003\u0005\rAX\u0001\u000fG>\u0004\u0018\u0010\n3fM\u0006,H\u000e\u001e\u00132+\r\u0019gn\\\u000b\u0002I*\u0012\u0011\'Z\u0016\u0002MB\u0011q\r\\\u0007\u0002Q*\u0011\u0011N[\u0001\nk:\u001c\u0007.Z2lK\u0012T!a\u001b\u000f\u0002\u0015\u0005tgn\u001c;bi&|g.\u0003\u0002nQ\n\tRO\\2iK\u000e\\W\r\u001a,be&\fgnY3\u0005\u000b!B!\u0019A\u0015\u0005\u000bMB!\u0019A\u0015\u0002\u001bA\u0014x\u000eZ;diB\u0013XMZ5y+\u0005\u0011\bCA:y\u001b\u0005!(BA;w\u0003\u0011a\u0017M\\4\u000b\u0003]\fAA[1wC&\u0011\u0011\u0010\u001e\u0002\u0007\'R\u0014\u0018N\\4\u0002\u0019A\u0014x\u000eZ;di\u0006\u0013\u0018\u000e^=\u0016\u0003q\u0004\"aK?\n\u0005yd\"aA%oi\u0006q\u0001O]8ek\u000e$X\t\\3nK:$Hc\u0001\u0018\u0002\u0004!A\u0011QA\u0006\u0002\u0002\u0003\u0007A0A\u0002yIE\nq\u0002\u001d:pIV\u001cG/\u0013;fe\u0006$xN]\u000b\u0003\u0003\u0017\u0001R!!\u0004\u0002\u00149j!!a\u0004\u000b\u0007\u0005EA$\u0001\u0006d_2dWm\u0019;j_:LA!!\u0006\u0002\u0010\tA\u0011\n^3sCR|\'/\u0001\u0005dC:,\u0015/^1m)\ra\u00151\u0004\u0005\t\u0003\u000bi\u0011\u0011!a\u0001]\u0005\u0011\u0002O]8ek\u000e$X\t\\3nK:$h*Y7f)\r\u0011\u0018\u0011\u0005\u0005\t\u0003\u000bq\u0011\u0011!a\u0001y\u0006A\u0001.Y:i\u0007>$W\rF\u0001}\u0003!!xn\u0015;sS:<G#\u0001:\u0002\r\u0015\fX/\u00197t)\ra\u0015q\u0006\u0005\t\u0003\u000b\t\u0012\u0011!a\u0001]\u0005)!+[4iiB\u0011!eE\n\u0006\'\u0005]\u0012Q\b\t\u0004W\u0005e\u0012bAA\u001e9\t1\u0011I\\=SK\u001a\u0004B!a\u0010\u0002F5\u0011\u0011\u0011\t\u0006\u0004\u0003\u00072\u0018AA5p\u0013\r\t\u0015\u0011\t\u000b\u0003\u0003g\tQ!\u00199qYf,b!!\u0014\u0002T\u0005]C\u0003BA(\u00033\u0002bA\t\u0001\u0002R\u0005U\u0003c\u0001\u0014\u0002T\u0011)\u0001F\u0006b\u0001SA\u0019a%a\u0016\u0005\u000bM2\"\u0019A\u0015\t\r\r3\u0002\u0019AA+\u0003\u001d)h.\u00199qYf,b!a\u0018\u0002t\u0005%D\u0003BA1\u0003W\u0002RaKA2\u0003OJ1!!\u001a\u001d\u0005\u0019y\u0005\u000f^5p]B\u0019a%!\u001b\u0005\u000bM:\"\u0019A\u0015\t\u0013\u00055t#!AA\u0002\u0005=\u0014a\u0001=%aA1!\u0005AA9\u0003O\u00022AJA:\t\u0015AsC1\u0001*\u000319(/\u001b;f%\u0016\u0004H.Y2f)\t\tI\bE\u0002t\u0003wJ1!! u\u0005\u0019y%M[3di\u0002
   #10 = Utf8               scala/runtime/ScalaRunTime$$anon$1
   #11 = Class              #10           // scala/runtime/ScalaRunTime$$anon$1
   #12 = Utf8               value
   #13 = Utf8               Ljava/lang/Object;
   #14 = Utf8               TB;
   #15 = Utf8               unapply
   #16 = Utf8               (Lscala/util/Right;)Lscala/Option;
   #17 = Utf8               <A:Ljava/lang/Object;B:Ljava/lang/Object;>(Lscala/util/Right<TA;TB;>;)Lscala/Option<TB;>;
   #18 = Utf8               x$0
   #19 = Utf8               scala/util/Right$
   #20 = Class              #19           // scala/util/Right$
   #21 = Utf8               MODULE$
   #22 = Utf8               Lscala/util/Right$;
   #23 = NameAndType        #21:#22       // MODULE$:Lscala/util/Right$;
   #24 = Fieldref           #20.#23       // scala/util/Right$.MODULE$:Lscala/util/Right$;
   #25 = NameAndType        #15:#16       // unapply:(Lscala/util/Right;)Lscala/Option;
   #26 = Methodref          #20.#25       // scala/util/Right$.unapply:(Lscala/util/Right;)Lscala/Option;
   #27 = Utf8               Lscala/util/Right;
   #28 = Utf8               apply
   #29 = Utf8               (Ljava/lang/Object;)Lscala/util/Right;
   #30 = Utf8               <A:Ljava/lang/Object;B:Ljava/lang/Object;>(TB;)Lscala/util/Right<TA;TB;>;
   #31 = Utf8               <init>
   #32 = Utf8               (Ljava/lang/Object;)V
   #33 = NameAndType        #31:#32       // "<init>":(Ljava/lang/Object;)V
   #34 = Methodref          #2.#33        // scala/util/Right."<init>":(Ljava/lang/Object;)V
   #35 = Utf8               ()Ljava/lang/Object;
   #36 = Utf8               ()TB;
   #37 = NameAndType        #12:#13       // value:Ljava/lang/Object;
   #38 = Fieldref           #2.#37        // scala/util/Right.value:Ljava/lang/Object;
   #39 = Utf8               this
   #40 = Utf8               isLeft
   #41 = Utf8               ()Z
   #42 = Utf8               isRight
   #43 = Utf8               withLeft
   #44 = Utf8               ()Lscala/util/Either;
   #45 = Utf8               <A1:Ljava/lang/Object;>()Lscala/util/Either<TA1;TB;>;
   #46 = Utf8               copy
   #47 = Utf8               copy$default$1
   #48 = Utf8               <A:Ljava/lang/Object;B:Ljava/lang/Object;>()TB;
   #49 = NameAndType        #12:#35       // value:()Ljava/lang/Object;
   #50 = Methodref          #2.#49        // scala/util/Right.value:()Ljava/lang/Object;
   #51 = Utf8               productPrefix
   #52 = Utf8               ()Ljava/lang/String;
   #53 = Utf8               Right
   #54 = String             #53           // Right
   #55 = Utf8               productArity
   #56 = Utf8               ()I
   #57 = Utf8               productElement
   #58 = Utf8               (I)Ljava/lang/Object;
   #59 = Utf8               x$1
   #60 = Utf8               scala/runtime/Statics
   #61 = Class              #60           // scala/runtime/Statics
   #62 = Utf8               ioobe
   #63 = NameAndType        #62:#58       // ioobe:(I)Ljava/lang/Object;
   #64 = Methodref          #61.#63       // scala/runtime/Statics.ioobe:(I)Ljava/lang/Object;
   #65 = Utf8               I
   #66 = Utf8               productIterator
   #67 = Utf8               ()Lscala/collection/Iterator;
   #68 = Utf8               ()Lscala/collection/Iterator<Ljava/lang/Object;>;
   #69 = Utf8               (Lscala/Product;)V
   #70 = NameAndType        #31:#69       // "<init>":(Lscala/Product;)V
   #71 = Methodref          #11.#70       // scala/runtime/ScalaRunTime$$anon$1."<init>":(Lscala/Product;)V
   #72 = Utf8               canEqual
   #73 = Utf8               (Ljava/lang/Object;)Z
   #74 = Utf8               productElementName
   #75 = Utf8               (I)Ljava/lang/String;
   #76 = String             #12           // value
   #77 = Utf8               java/lang/String
   #78 = Class              #77           // java/lang/String
   #79 = Utf8               hashCode
   #80 = Utf8               scala/util/hashing/MurmurHash3$
   #81 = Class              #80           // scala/util/hashing/MurmurHash3$
   #82 = Utf8               Lscala/util/hashing/MurmurHash3$;
   #83 = NameAndType        #21:#82       // MODULE$:Lscala/util/hashing/MurmurHash3$;
   #84 = Fieldref           #81.#83       // scala/util/hashing/MurmurHash3$.MODULE$:Lscala/util/hashing/MurmurHash3$;
   #85 = Utf8               productHash
   #86 = Utf8               (Lscala/Product;)I
   #87 = NameAndType        #85:#86       // productHash:(Lscala/Product;)I
   #88 = Methodref          #81.#87       // scala/util/hashing/MurmurHash3$.productHash:(Lscala/Product;)I
   #89 = Utf8               toString
   #90 = Utf8               scala/runtime/ScalaRunTime$
   #91 = Class              #90           // scala/runtime/ScalaRunTime$
   #92 = Utf8               Lscala/runtime/ScalaRunTime$;
   #93 = NameAndType        #21:#92       // MODULE$:Lscala/runtime/ScalaRunTime$;
   #94 = Fieldref           #91.#93       // scala/runtime/ScalaRunTime$.MODULE$:Lscala/runtime/ScalaRunTime$;
   #95 = Utf8               _toString
   #96 = Utf8               (Lscala/Product;)Ljava/lang/String;
   #97 = NameAndType        #95:#96       // _toString:(Lscala/Product;)Ljava/lang/String;
   #98 = Methodref          #91.#97       // scala/runtime/ScalaRunTime$._toString:(Lscala/Product;)Ljava/lang/String;
   #99 = Utf8               equals
  #100 = Utf8               scala/runtime/BoxesRunTime
  #101 = Class              #100          // scala/runtime/BoxesRunTime
  #102 = Utf8               (Ljava/lang/Object;Ljava/lang/Object;)Z
  #103 = NameAndType        #99:#102      // equals:(Ljava/lang/Object;Ljava/lang/Object;)Z
  #104 = Methodref          #101.#103     // scala/runtime/BoxesRunTime.equals:(Ljava/lang/Object;Ljava/lang/Object;)Z
  #105 = Utf8               (TB;)V
  #106 = Utf8               ()V
  #107 = NameAndType        #31:#106      // "<init>":()V
  #108 = Methodref          #5.#107       // scala/util/Either."<init>":()V
  #109 = Utf8               Signature
  #110 = Utf8               Code
  #111 = Utf8               LocalVariableTable
  #112 = Utf8               MethodParameters
  #113 = Utf8               LineNumberTable
  #114 = Utf8               StackMapTable
  #115 = Utf8               InnerClasses
  #116 = Utf8               SourceFile
  #117 = Utf8               RuntimeVisibleAnnotations
  #118 = Utf8               ScalaInlineInfo
  #119 = Utf8               ScalaSig
{
  private final B value;
    descriptor: Ljava/lang/Object;
    flags: (0x0012) ACC_PRIVATE, ACC_FINAL
    Signature: #14                          // TB;

  public static <A extends java.lang.Object, B extends java.lang.Object> scala.Option<B> unapply(scala.util.Right<A, B>);
    descriptor: (Lscala/util/Right;)Lscala/Option;
    flags: (0x0009) ACC_PUBLIC, ACC_STATIC
    Code:
      stack=2, locals=1, args_size=1
         0: getstatic     #24                 // Field scala/util/Right$.MODULE$:Lscala/util/Right$;
         3: aload_0
         4: invokevirtual #26                 // Method scala/util/Right$.unapply:(Lscala/util/Right;)Lscala/Option;
         7: areturn
      LocalVariableTable:
        Start  Length  Slot  Name   Signature
            0       8     0   x$0   Lscala/util/Right;
    Signature: #17                          // <A:Ljava/lang/Object;B:Ljava/lang/Object;>(Lscala/util/Right<TA;TB;>;)Lscala/Option<TB;>;
    MethodParameters:
      Name                           Flags
      x$0                            final

  public static <A extends java.lang.Object, B extends java.lang.Object> scala.util.Right<A, B> apply(B);
    descriptor: (Ljava/lang/Object;)Lscala/util/Right;
    flags: (0x0009) ACC_PUBLIC, ACC_STATIC
    Code:
      stack=3, locals=1, args_size=1
         0: getstatic     #24                 // Field scala/util/Right$.MODULE$:Lscala/util/Right$;
         3: pop
         4: new           #2                  // class scala/util/Right
         7: dup
         8: aload_0
         9: invokespecial #34                 // Method "<init>":(Ljava/lang/Object;)V
        12: areturn
      LineNumberTable:
        line 471: 4
      LocalVariableTable:
        Start  Length  Slot  Name   Signature
            0      13     0 value   Ljava/lang/Object;
    Signature: #30                          // <A:Ljava/lang/Object;B:Ljava/lang/Object;>(TB;)Lscala/util/Right<TA;TB;>;
    MethodParameters:
      Name                           Flags
      value                          final

  public B value();
    descriptor: ()Ljava/lang/Object;
    flags: (0x0001) ACC_PUBLIC
    Code:
      stack=1, locals=1, args_size=1
         0: aload_0
         1: getfield      #38                 // Field value:Ljava/lang/Object;
         4: areturn
      LineNumberTable:
        line 471: 0
      LocalVariableTable:
        Start  Length  Slot  Name   Signature
            0       5     0  this   Lscala/util/Right;
    Signature: #36                          // ()TB;

  public boolean isLeft();
    descriptor: ()Z
    flags: (0x0001) ACC_PUBLIC
    Code:
      stack=1, locals=1, args_size=1
         0: iconst_0
         1: ireturn
      LineNumberTable:
        line 472: 0
      LocalVariableTable:
        Start  Length  Slot  Name   Signature
            0       2     0  this   Lscala/util/Right;

  public boolean isRight();
    descriptor: ()Z
    flags: (0x0001) ACC_PUBLIC
    Code:
      stack=1, locals=1, args_size=1
         0: iconst_1
         1: ireturn
      LineNumberTable:
        line 473: 0
      LocalVariableTable:
        Start  Length  Slot  Name   Signature
            0       2     0  this   Lscala/util/Right;

  public <A1 extends java.lang.Object> scala.util.Either<A1, B> withLeft();
    descriptor: ()Lscala/util/Either;
    flags: (0x0001) ACC_PUBLIC
    Code:
      stack=1, locals=1, args_size=1
         0: aload_0
         1: areturn
      LineNumberTable:
        line 482: 0
      LocalVariableTable:
        Start  Length  Slot  Name   Signature
            0       2     0  this   Lscala/util/Right;
    Signature: #45                          // <A1:Ljava/lang/Object;>()Lscala/util/Either<TA1;TB;>;

  public <A extends java.lang.Object, B extends java.lang.Object> scala.util.Right<A, B> copy(B);
    descriptor: (Ljava/lang/Object;)Lscala/util/Right;
    flags: (0x0001) ACC_PUBLIC
    Code:
      stack=3, locals=2, args_size=2
         0: new           #2                  // class scala/util/Right
         3: dup
         4: aload_1
         5: invokespecial #34                 // Method "<init>":(Ljava/lang/Object;)V
         8: areturn
      LineNumberTable:
        line 471: 0
      LocalVariableTable:
        Start  Length  Slot  Name   Signature
            0       9     0  this   Lscala/util/Right;
            0       9     1 value   Ljava/lang/Object;
    Signature: #30                          // <A:Ljava/lang/Object;B:Ljava/lang/Object;>(TB;)Lscala/util/Right<TA;TB;>;
    MethodParameters:
      Name                           Flags
      value                          final

  public <A extends java.lang.Object, B extends java.lang.Object> B copy$default$1();
    descriptor: ()Ljava/lang/Object;
    flags: (0x0001) ACC_PUBLIC
    Code:
      stack=1, locals=1, args_size=1
         0: aload_0
         1: invokevirtual #50                 // Method value:()Ljava/lang/Object;
         4: areturn
      LineNumberTable:
        line 471: 0
      LocalVariableTable:
        Start  Length  Slot  Name   Signature
            0       5     0  this   Lscala/util/Right;
    Signature: #48                          // <A:Ljava/lang/Object;B:Ljava/lang/Object;>()TB;

  public java.lang.String productPrefix();
    descriptor: ()Ljava/lang/String;
    flags: (0x0001) ACC_PUBLIC
    Code:
      stack=1, locals=1, args_size=1
         0: ldc           #54                 // String Right
         2: areturn
      LineNumberTable:
        line 471: 0
      LocalVariableTable:
        Start  Length  Slot  Name   Signature
            0       3     0  this   Lscala/util/Right;

  public int productArity();
    descriptor: ()I
    flags: (0x0001) ACC_PUBLIC
    Code:
      stack=1, locals=1, args_size=1
         0: iconst_1
         1: ireturn
      LineNumberTable:
        line 471: 0
      LocalVariableTable:
        Start  Length  Slot  Name   Signature
            0       2     0  this   Lscala/util/Right;

  public java.lang.Object productElement(int);
    descriptor: (I)Ljava/lang/Object;
    flags: (0x0001) ACC_PUBLIC
    Code:
      stack=1, locals=2, args_size=2
         0: iload_1
         1: tableswitch   { // 0 to 0
                       0: 20
                 default: 25
            }
        20: aload_0
        21: invokevirtual #50                 // Method value:()Ljava/lang/Object;
        24: areturn
        25: iload_1
        26: invokestatic  #64                 // Method scala/runtime/Statics.ioobe:(I)Ljava/lang/Object;
        29: areturn
      StackMapTable: number_of_entries = 2
        frame_type = 20 /* same */
        frame_type = 4 /* same */
      LineNumberTable:
        line 471: 0
      LocalVariableTable:
        Start  Length  Slot  Name   Signature
            0      30     0  this   Lscala/util/Right;
            0      30     1   x$1   I
    MethodParameters:
      Name                           Flags
      x$1                            final

  public scala.collection.Iterator<java.lang.Object> productIterator();
    descriptor: ()Lscala/collection/Iterator;
    flags: (0x0001) ACC_PUBLIC
    Code:
      stack=3, locals=1, args_size=1
         0: new           #11                 // class scala/runtime/ScalaRunTime$$anon$1
         3: dup
         4: aload_0
         5: invokespecial #71                 // Method scala/runtime/ScalaRunTime$$anon$1."<init>":(Lscala/Product;)V
         8: areturn
      LineNumberTable:
        line 471: 0
      LocalVariableTable:
        Start  Length  Slot  Name   Signature
            0       9     0  this   Lscala/util/Right;
    Signature: #68                          // ()Lscala/collection/Iterator<Ljava/lang/Object;>;

  public boolean canEqual(java.lang.Object);
    descriptor: (Ljava/lang/Object;)Z
    flags: (0x0001) ACC_PUBLIC
    Code:
      stack=1, locals=2, args_size=2
         0: aload_1
         1: instanceof    #2                  // class scala/util/Right
         4: ireturn
      LineNumberTable:
        line 471: 0
      LocalVariableTable:
        Start  Length  Slot  Name   Signature
            0       5     0  this   Lscala/util/Right;
            0       5     1   x$1   Ljava/lang/Object;
    MethodParameters:
      Name                           Flags
      x$1                            final

  public java.lang.String productElementName(int);
    descriptor: (I)Ljava/lang/String;
    flags: (0x0001) ACC_PUBLIC
    Code:
      stack=1, locals=2, args_size=2
         0: iload_1
         1: tableswitch   { // 0 to 0
                       0: 20
                 default: 23
            }
        20: ldc           #76                 // String value
        22: areturn
        23: iload_1
        24: invokestatic  #64                 // Method scala/runtime/Statics.ioobe:(I)Ljava/lang/Object;
        27: checkcast     #78                 // class java/lang/String
        30: areturn
      StackMapTable: number_of_entries = 2
        frame_type = 20 /* same */
        frame_type = 2 /* same */
      LineNumberTable:
        line 471: 0
      LocalVariableTable:
        Start  Length  Slot  Name   Signature
            0      31     0  this   Lscala/util/Right;
            0      31     1   x$1   I
    MethodParameters:
      Name                           Flags
      x$1                            final

  public int hashCode();
    descriptor: ()I
    flags: (0x0001) ACC_PUBLIC
    Code:
      stack=2, locals=1, args_size=1
         0: getstatic     #84                 // Field scala/util/hashing/MurmurHash3$.MODULE$:Lscala/util/hashing/MurmurHash3$;
         3: aload_0
         4: invokevirtual #88                 // Method scala/util/hashing/MurmurHash3$.productHash:(Lscala/Product;)I
         7: ireturn
      LineNumberTable:
        line 471: 0
      LocalVariableTable:
        Start  Length  Slot  Name   Signature
            0       8     0  this   Lscala/util/Right;

  public java.lang.String toString();
    descriptor: ()Ljava/lang/String;
    flags: (0x0001) ACC_PUBLIC
    Code:
      stack=2, locals=1, args_size=1
         0: getstatic     #94                 // Field scala/runtime/ScalaRunTime$.MODULE$:Lscala/runtime/ScalaRunTime$;
         3: aload_0
         4: invokevirtual #98                 // Method scala/runtime/ScalaRunTime$._toString:(Lscala/Product;)Ljava/lang/String;
         7: areturn
      LineNumberTable:
        line 471: 0
      LocalVariableTable:
        Start  Length  Slot  Name   Signature
            0       8     0  this   Lscala/util/Right;

  public boolean equals(java.lang.Object);
    descriptor: (Ljava/lang/Object;)Z
    flags: (0x0001) ACC_PUBLIC
    Code:
      stack=2, locals=4, args_size=2
         0: aload_0
         1: aload_1
         2: if_acmpeq     50
         5: aload_1
         6: instanceof    #2                  // class scala/util/Right
         9: ifeq          17
        12: iconst_1
        13: istore_2
        14: goto          19
        17: iconst_0
        18: istore_2
        19: iload_2
        20: ifeq          52
        23: aload_1
        24: checkcast     #2                  // class scala/util/Right
        27: astore_3
        28: aload_0
        29: invokevirtual #50                 // Method value:()Ljava/lang/Object;
        32: aload_3
        33: invokevirtual #50                 // Method value:()Ljava/lang/Object;
        36: invokestatic  #104                // Method scala/runtime/BoxesRunTime.equals:(Ljava/lang/Object;Ljava/lang/Object;)Z
        39: ifeq          46
        42: iconst_1
        43: goto          47
        46: iconst_0
        47: ifeq          52
        50: iconst_1
        51: ireturn
        52: iconst_0
        53: ireturn
      StackMapTable: number_of_entries = 6
        frame_type = 17 /* same */
        frame_type = 252 /* append */
          offset_delta = 1
          locals = [ int ]
        frame_type = 252 /* append */
          offset_delta = 26
          locals = [ class scala/util/Right ]
        frame_type = 64 /* same_locals_1_stack_item */
          stack = [ int ]
        frame_type = 249 /* chop */
          offset_delta = 2
        frame_type = 252 /* append */
          offset_delta = 1
          locals = [ int ]
      LineNumberTable:
        line 471: 0
      LocalVariableTable:
        Start  Length  Slot  Name   Signature
            0      54     0  this   Lscala/util/Right;
            0      54     1   x$1   Ljava/lang/Object;
    MethodParameters:
      Name                           Flags
      x$1                            final

  public scala.util.Right(B);
    descriptor: (Ljava/lang/Object;)V
    flags: (0x0001) ACC_PUBLIC
    Code:
      stack=2, locals=2, args_size=2
         0: aload_0
         1: aload_1
         2: putfield      #38                 // Field value:Ljava/lang/Object;
         5: aload_0
         6: invokespecial #108                // Method scala/util/Either."<init>":()V
         9: return
      LineNumberTable:
        line 471: 0
      LocalVariableTable:
        Start  Length  Slot  Name   Signature
            0      10     0  this   Lscala/util/Right;
            0      10     1 value   Ljava/lang/Object;
    Signature: #105                         // (TB;)V
    MethodParameters:
      Name                           Flags
      value                          final
}
InnerClasses:
  public final #11;                       // class scala/runtime/ScalaRunTime$$anon$1
Signature: #3                           // <A:Ljava/lang/Object;B:Ljava/lang/Object;>Lscala/util/Either<TA;TB;>;
SourceFile: "Either.scala"
RuntimeVisibleAnnotations:
  0: #7(#8=s#9)
    scala.reflect.ScalaSignature(
      bytes="\u0006\u0005\u0005}d\u0001B\r\u001b\u0005~A\u0001b\u0011\u0001\u0003\u0016\u0004%\t\u0001\u0012\u0005\t\u000b\u0002\u0011\t\u0012)A\u0005c!)a\t\u0001C\u0001\u000f\")!\n\u0001C\u0001\u0017\")q\n\u0001C\u0001\u0017\")\u0001\u000b\u0001C\u0001#\"9\u0001\fAA\u0001\n\u0003I\u0006bB1\u0001#\u0003%\tA\u0019\u0005\ba\u0002\t\t\u0011\"\u0011r\u0011\u001dQ\b!!A\u0005\u0002mD\u0001b \u0001\u0002\u0002\u0013\u0005\u0011\u0011\u0001\u0005\n\u0003\u000f\u0001\u0011\u0011!C!\u0003\u0013A\u0011\"a\u0006\u0001\u0003\u0003%\t!!\u0007\t\u0013\u0005u\u0001!!A\u0005B\u0005}\u0001\"CA\u0012\u0001\u0005\u0005I\u0011IA\u0013\u0011%\t9\u0003AA\u0001\n\u0003\nI\u0003C\u0005\u0002,\u0001\t\t\u0011\"\u0011\u0002.\u001dI\u0011\u0011\u0007\u000e\u0002\u0002#\u0005\u00111\u0007\u0004\t3i\t\t\u0011#\u0001\u00026!1ai\u0005C\u0001\u0003\u000fB\u0011\"a\n\u0014\u0003\u0003%)%!\u000b\t\u0013\u0005%3#!A\u0005\u0002\u0006-\u0003\"CA.\'\u0005\u0005I\u0011QA/\u0011%\t)hEA\u0001\n\u0013\t9HA\u0003SS\u001eDGO\u0003\u0002\u001c9\u0005!Q\u000f^5m\u0015\u0005i\u0012!B:dC2\f7\u0001A\u000b\u0004A\u001d\u00124\u0003\u0002\u0001\"i]\u0002BAI\u0012&c5\t!$\u0003\u0002%5\t1Q)\u001b;iKJ\u0004\"AJ\u0014\r\u0001\u00111\u0001\u0006\u0001CC\u0002%\u0012\u0011!Q\t\u0003U9\u0002\"a\u000b\u0017\u000e\u0003qI!!\f\u000f\u0003\u000f9{G\u000f[5oOB\u00111fL\u0005\u0003aq\u00111!\u00118z!\t1#\u0007\u0002\u00044\u0001\u0011\u0015\r!\u000b\u0002\u0002\u0005B\u00111&N\u0005\u0003mq\u0011q\u0001\u0015:pIV\u001cG\u000f\u0005\u00029\u0001:\u0011\u0011H\u0010\b\u0003uuj\u0011a\u000f\u0006\u0003yy\ta\u0001\u0010:p_Rt\u0014\"A\u000f\n\u0005}b\u0012a\u00029bG.\fw-Z\u0005\u0003\u0003\n\u0013AbU3sS\u0006d\u0017N_1cY\u0016T!a\u0010\u000f\u0002\u000bY\fG.^3\u0016\u0003E\naA^1mk\u0016\u0004\u0013A\u0002\u001fj]&$h\b\u0006\u0002I\u0013B!!\u0005A\u00132\u0011\u0015\u00195\u00011\u00012\u0003\u0019I7\u000fT3giV\tA\n\u0005\u0002,\u001b&\u0011a\n\b\u0002\b\u0005>|G.Z1o\u0003\u001dI7OU5hQR\f\u0001b^5uQ2+g\r^\u000b\u0003%V+\u0012a\u0015\t\u0005E\r\"\u0016\u0007\u0005\u0002\'+\u0012)aK\u0002b\u0001/\n\u0011\u0011)M\t\u0003K9\nAaY8qsV\u0019!,X0\u0015\u0005m\u0003\u0007\u0003\u0002\u0012\u00019z\u0003\"AJ/\u0005\u000b!:!\u0019A\u0015\u0011\u0005\u0019zF!B\u001a\b\u0005\u0004I\u0003bB\"\b!\u0003\u0005\rAX\u0001\u000fG>\u0004\u0018\u0010\n3fM\u0006,H\u000e\u001e\u00132+\r\u0019gn\\\u000b\u0002I*\u0012\u0011\'Z\u0016\u0002MB\u0011q\r\\\u0007\u0002Q*\u0011\u0011N[\u0001\nk:\u001c\u0007.Z2lK\u0012T!a\u001b\u000f\u0002\u0015\u0005tgn\u001c;bi&|g.\u0003\u0002nQ\n\tRO\\2iK\u000e\\W\r\u001a,be&\fgnY3\u0005\u000b!B!\u0019A\u0015\u0005\u000bMB!\u0019A\u0015\u0002\u001bA\u0014x\u000eZ;diB\u0013XMZ5y+\u0005\u0011\bCA:y\u001b\u0005!(BA;w\u0003\u0011a\u0017M\\4\u000b\u0003]\fAA[1wC&\u0011\u0011\u0010\u001e\u0002\u0007\'R\u0014\u0018N\\4\u0002\u0019A\u0014x\u000eZ;di\u0006\u0013\u0018\u000e^=\u0016\u0003q\u0004\"aK?\n\u0005yd\"aA%oi\u0006q\u0001O]8ek\u000e$X\t\\3nK:$Hc\u0001\u0018\u0002\u0004!A\u0011QA\u0006\u0002\u0002\u0003\u0007A0A\u0002yIE\nq\u0002\u001d:pIV\u001cG/\u0013;fe\u0006$xN]\u000b\u0003\u0003\u0017\u0001R!!\u0004\u0002\u00149j!!a\u0004\u000b\u0007\u0005EA$\u0001\u0006d_2dWm\u0019;j_:LA!!\u0006\u0002\u0010\tA\u0011\n^3sCR|\'/\u0001\u0005dC:,\u0015/^1m)\ra\u00151\u0004\u0005\t\u0003\u000bi\u0011\u0011!a\u0001]\u0005\u0011\u0002O]8ek\u000e$X\t\\3nK:$h*Y7f)\r\u0011\u0018\u0011\u0005\u0005\t\u0003\u000bq\u0011\u0011!a\u0001y\u0006A\u0001.Y:i\u0007>$W\rF\u0001}\u0003!!xn\u0015;sS:<G#\u0001:\u0002\r\u0015\fX/\u00197t)\ra\u0015q\u0006\u0005\t\u0003\u000b\t\u0012\u0011!a\u0001]\u0005)!+[4iiB\u0011!eE\n\u0006\'\u0005]\u0012Q\b\t\u0004W\u0005e\u0012bAA\u001e9\t1\u0011I\\=SK\u001a\u0004B!a\u0010\u0002F5\u0011\u0011\u0011\t\u0006\u0004\u0003\u00072\u0018AA5p\u0013\r\t\u0015\u0011\t\u000b\u0003\u0003g\tQ!\u00199qYf,b!!\u0014\u0002T\u0005]C\u0003BA(\u00033\u0002bA\t\u0001\u0002R\u0005U\u0003c\u0001\u0014\u0002T\u0011)\u0001F\u0006b\u0001SA\u0019a%a\u0016\u0005\u000bM2\"\u0019A\u0015\t\r\r3\u0002\u0019AA+\u0003\u001d)h.\u00199qYf,b!a\u0018\u0002t\u0005%D\u0003BA1\u0003W\u0002RaKA2\u0003OJ1!!\u001a\u001d\u0005\u0019y\u0005\u000f^5p]B\u0019a%!\u001b\u0005\u000bM:\"\u0019A\u0015\t\u0013\u00055t#!AA\u0002\u0005=\u0014a\u0001=%aA1!\u0005AA9\u0003O\u00022AJA:\t\u0015AsC1\u0001*\u000319(/\u001b;f%\u0016\u0004H.Y2f)\t\tI\bE\u0002t\u0003wJ1!! u\u0005\u0019y%M[3di\u0002"
    )
  ScalaInlineInfo: length = 0x54 (unknown attribute)
   01 01 00 10 00 1F 00 20 01 00 48 00 49 01 00 2E
   00 1D 01 00 2F 00 23 01 00 63 00 49 01 00 4F 00
   38 01 00 28 00 29 01 00 2A 00 29 01 00 37 00 38
   01 00 39 00 3A 01 00 4A 00 4B 01 00 42 00 43 01
   00 33 00 34 01 00 59 00 34 01 00 0C 00 23 01 00
   2B 00 2C 01
  ScalaSig: length = 0x3 (unknown attribute)
   05 02 00
