Classfile /Users/mw/Projects/slang-braindump/.jar/jar8/assemble/slang-braindump/assemble/content/scala/util/Using$.class
  Last modified May 29, 2022; size 20831 bytes
  SHA-256 checksum b4557c30730545ab1d74ae66c5271e521220da26bf82c9c0b6fbf68dcee88ba5
  Compiled from "Using.scala"
public final class scala.util.Using$
  minor version: 0
  major version: 52
  flags: (0x0031) ACC_PUBLIC, ACC_FINAL, ACC_SUPER
  this_class: #2                          // scala/util/Using$
  super_class: #4                         // java/lang/Object
  interfaces: 0, fields: 1, methods: 20, attributes: 4
Constant pool:
    #1 = Utf8               scala/util/Using$
    #2 = Class              #1            // scala/util/Using$
    #3 = Utf8               java/lang/Object
    #4 = Class              #3            // java/lang/Object
    #5 = Utf8               Using.scala
    #6 = Utf8               scala/util/Using$Releasable
    #7 = Class              #6            // scala/util/Using$Releasable
    #8 = Utf8               scala/util/Using
    #9 = Class              #8            // scala/util/Using
   #10 = Utf8               Releasable
   #11 = Utf8               MODULE$
   #12 = Utf8               Lscala/util/Using$;
   #13 = Utf8               <clinit>
   #14 = Utf8               ()V
   #15 = Utf8               <init>
   #16 = NameAndType        #15:#14       // "<init>":()V
   #17 = Methodref          #2.#16        // scala/util/Using$."<init>":()V
   #18 = NameAndType        #11:#12       // MODULE$:Lscala/util/Using$;
   #19 = Fieldref           #2.#18        // scala/util/Using$.MODULE$:Lscala/util/Using$;
   #20 = Utf8               apply
   #21 = Utf8               (Lscala/Function0;Lscala/Function1;Lscala/util/Using$Releasable;)Lscala/util/Try;
   #22 = Utf8               <R:Ljava/lang/Object;A:Ljava/lang/Object;>(Lscala/Function0<TR;>;Lscala/Function1<TR;TA;>;Lscala/util/Using$Releasable<TR;>;)Lscala/util/Try<TA;>;
   #23 = Utf8               resource
   #24 = Utf8               f
   #25 = Utf8               evidence$1
   #26 = Utf8               java/lang/Throwable
   #27 = Class              #26           // java/lang/Throwable
   #28 = Utf8               scala/util/Try$
   #29 = Class              #28           // scala/util/Try$
   #30 = Utf8               Lscala/util/Try$;
   #31 = NameAndType        #11:#30       // MODULE$:Lscala/util/Try$;
   #32 = Fieldref           #29.#31       // scala/util/Try$.MODULE$:Lscala/util/Try$;
   #33 = Utf8               scala/util/Success
   #34 = Class              #33           // scala/util/Success
   #35 = Utf8               $anonfun$apply$1
   #36 = Utf8               (Lscala/Function0;Lscala/Function1;Lscala/util/Using$Releasable;)Ljava/lang/Object;
   #37 = NameAndType        #35:#36       // $anonfun$apply$1:(Lscala/Function0;Lscala/Function1;Lscala/util/Using$Releasable;)Ljava/lang/Object;
   #38 = Methodref          #2.#37        // scala/util/Using$.$anonfun$apply$1:(Lscala/Function0;Lscala/Function1;Lscala/util/Using$Releasable;)Ljava/lang/Object;
   #39 = Utf8               (Ljava/lang/Object;)V
   #40 = NameAndType        #15:#39       // "<init>":(Ljava/lang/Object;)V
   #41 = Methodref          #34.#40       // scala/util/Success."<init>":(Ljava/lang/Object;)V
   #42 = Utf8               scala/util/control/NonFatal$
   #43 = Class              #42           // scala/util/control/NonFatal$
   #44 = Utf8               Lscala/util/control/NonFatal$;
   #45 = NameAndType        #11:#44       // MODULE$:Lscala/util/control/NonFatal$;
   #46 = Fieldref           #43.#45       // scala/util/control/NonFatal$.MODULE$:Lscala/util/control/NonFatal$;
   #47 = Utf8               unapply
   #48 = Utf8               (Ljava/lang/Throwable;)Lscala/Option;
   #49 = NameAndType        #47:#48       // unapply:(Ljava/lang/Throwable;)Lscala/Option;
   #50 = Methodref          #43.#49       // scala/util/control/NonFatal$.unapply:(Ljava/lang/Throwable;)Lscala/Option;
   #51 = Utf8               scala/Option
   #52 = Class              #51           // scala/Option
   #53 = Utf8               isEmpty
   #54 = Utf8               ()Z
   #55 = NameAndType        #53:#54       // isEmpty:()Z
   #56 = Methodref          #52.#55       // scala/Option.isEmpty:()Z
   #57 = Utf8               get
   #58 = Utf8               ()Ljava/lang/Object;
   #59 = NameAndType        #57:#58       // get:()Ljava/lang/Object;
   #60 = Methodref          #52.#59       // scala/Option.get:()Ljava/lang/Object;
   #61 = Utf8               scala/util/Failure
   #62 = Class              #61           // scala/util/Failure
   #63 = Utf8               (Ljava/lang/Throwable;)V
   #64 = NameAndType        #15:#63       // "<init>":(Ljava/lang/Throwable;)V
   #65 = Methodref          #62.#64       // scala/util/Failure."<init>":(Ljava/lang/Throwable;)V
   #66 = Utf8               this
   #67 = Utf8               Lscala/Function0;
   #68 = Utf8               Lscala/Function1;
   #69 = Utf8               Lscala/util/Using$Releasable;
   #70 = Utf8               apply_e
   #71 = Utf8               Ljava/lang/Throwable;
   #72 = Utf8               scala/Function0
   #73 = Class              #72           // scala/Function0
   #74 = Utf8               scala/Function1
   #75 = Class              #74           // scala/Function1
   #76 = Utf8               scala$util$Using$$preferentiallySuppress
   #77 = Utf8               (Ljava/lang/Throwable;Ljava/lang/Throwable;)Ljava/lang/Throwable;
   #78 = Utf8               primary
   #79 = Utf8               secondary
   #80 = Utf8               score$1
   #81 = Utf8               (Ljava/lang/Throwable;)I
   #82 = NameAndType        #80:#81       // score$1:(Ljava/lang/Throwable;)I
   #83 = Methodref          #2.#82        // scala/util/Using$.score$1:(Ljava/lang/Throwable;)I
   #84 = Utf8               addSuppressed
   #85 = NameAndType        #84:#63       // addSuppressed:(Ljava/lang/Throwable;)V
   #86 = Methodref          #27.#85       // java/lang/Throwable.addSuppressed:(Ljava/lang/Throwable;)V
   #87 = Utf8               (Ljava/lang/Object;Lscala/Function1;Lscala/util/Using$Releasable;)Ljava/lang/Object;
   #88 = Utf8               <R:Ljava/lang/Object;A:Ljava/lang/Object;>(TR;Lscala/Function1<TR;TA;>;Lscala/util/Using$Releasable<TR;>;)TA;
   #89 = Utf8               body
   #90 = Utf8               releasable
   #91 = Utf8               java/lang/NullPointerException
   #92 = Class              #91           // java/lang/NullPointerException
   #93 = Utf8               null resource
   #94 = String             #93           // null resource
   #95 = Utf8               (Ljava/lang/String;)V
   #96 = NameAndType        #15:#95       // "<init>":(Ljava/lang/String;)V
   #97 = Methodref          #92.#96       // java/lang/NullPointerException."<init>":(Ljava/lang/String;)V
   #98 = Utf8               (Ljava/lang/Object;)Ljava/lang/Object;
   #99 = NameAndType        #20:#98       // apply:(Ljava/lang/Object;)Ljava/lang/Object;
  #100 = InterfaceMethodref #75.#99       // scala/Function1.apply:(Ljava/lang/Object;)Ljava/lang/Object;
  #101 = Utf8               release
  #102 = NameAndType        #101:#39      // release:(Ljava/lang/Object;)V
  #103 = InterfaceMethodref #7.#102       // scala/util/Using$Releasable.release:(Ljava/lang/Object;)V
  #104 = NameAndType        #76:#77       // scala$util$Using$$preferentiallySuppress:(Ljava/lang/Throwable;Ljava/lang/Throwable;)Ljava/lang/Throwable;
  #105 = Methodref          #2.#104       // scala/util/Using$.scala$util$Using$$preferentiallySuppress:(Ljava/lang/Throwable;Ljava/lang/Throwable;)Ljava/lang/Throwable;
  #106 = Utf8               other
  #107 = Utf8               toThrow
  #108 = Utf8               Ljava/lang/Object;
  #109 = Utf8               resources
  #110 = Utf8               (Ljava/lang/Object;Lscala/Function0;Lscala/Function2;Lscala/util/Using$Releasable;Lscala/util/Using$Releasable;)Ljava/lang/Object;
  #111 = Utf8               <R1:Ljava/lang/Object;R2:Ljava/lang/Object;A:Ljava/lang/Object;>(TR1;Lscala/Function0<TR2;>;Lscala/Function2<TR1;TR2;TA;>;Lscala/util/Using$Releasable<TR1;>;Lscala/util/Using$Releasable<TR2;>;)TA;
  #112 = Utf8               resource1
  #113 = Utf8               resource2
  #114 = Utf8               evidence$4
  #115 = Utf8               evidence$5
  #116 = NameAndType        #20:#58       // apply:()Ljava/lang/Object;
  #117 = InterfaceMethodref #73.#116      // scala/Function0.apply:()Ljava/lang/Object;
  #118 = Utf8               scala/Function2
  #119 = Class              #118          // scala/Function2
  #120 = Utf8               (Ljava/lang/Object;Ljava/lang/Object;)Ljava/lang/Object;
  #121 = NameAndType        #20:#120      // apply:(Ljava/lang/Object;Ljava/lang/Object;)Ljava/lang/Object;
  #122 = InterfaceMethodref #119.#121     // scala/Function2.apply:(Ljava/lang/Object;Ljava/lang/Object;)Ljava/lang/Object;
  #123 = Utf8               Lscala/Function2;
  #124 = Utf8               resource_other
  #125 = Utf8               resource_toThrow
  #126 = Utf8               $anonfun$resources$1_resource_other
  #127 = Utf8               $anonfun$resources$1_resource_toThrow
  #128 = Utf8               $anonfun$resources$1_resource_this
  #129 = Utf8               $anonfun$resources$1_resource_resource
  #130 = Utf8               (Ljava/lang/Object;Lscala/Function0;Lscala/Function0;Lscala/Function3;Lscala/util/Using$Releasable;Lscala/util/Using$Releasable;Lscala/util/Using$Releasable;)Ljava/lang/Object;
  #131 = Utf8               <R1:Ljava/lang/Object;R2:Ljava/lang/Object;R3:Ljava/lang/Object;A:Ljava/lang/Object;>(TR1;Lscala/Function0<TR2;>;Lscala/Function0<TR3;>;Lscala/Function3<TR1;TR2;TR3;TA;>;Lscala/util/Using$Releasable<TR1;>;Lscala/util/Using$Releasable<TR2;>;Lscala/util/Using$Releasable<TR3;>;)TA;
  #132 = Utf8               resource3
  #133 = Utf8               evidence$6
  #134 = Utf8               evidence$7
  #135 = Utf8               evidence$8
  #136 = Utf8               scala/Function3
  #137 = Class              #136          // scala/Function3
  #138 = Utf8               (Ljava/lang/Object;Ljava/lang/Object;Ljava/lang/Object;)Ljava/lang/Object;
  #139 = NameAndType        #20:#138      // apply:(Ljava/lang/Object;Ljava/lang/Object;Ljava/lang/Object;)Ljava/lang/Object;
  #140 = InterfaceMethodref #137.#139     // scala/Function3.apply:(Ljava/lang/Object;Ljava/lang/Object;Ljava/lang/Object;)Ljava/lang/Object;
  #141 = Utf8               Lscala/Function3;
  #142 = Utf8               $anonfun$resources$3_resource_other
  #143 = Utf8               $anonfun$resources$3_resource_toThrow
  #144 = Utf8               $anonfun$resources$3_resource_this
  #145 = Utf8               $anonfun$resources$3_resource_resource
  #146 = Utf8               $anonfun$resources$3_$anonfun$resources$4_resource_other
  #147 = Utf8               $anonfun$resources$3_$anonfun$resources$4_resource_toThrow
  #148 = Utf8               $anonfun$resources$3_$anonfun$resources$4_resource_this
  #149 = Utf8               $anonfun$resources$3_$anonfun$resources$4_resource_resource
  #150 = Utf8               (Ljava/lang/Object;Lscala/Function0;Lscala/Function0;Lscala/Function0;Lscala/Function4;Lscala/util/Using$Releasable;Lscala/util/Using$Releasable;Lscala/util/Using$Releasable;Lscala/util/Using$Releasable;)Ljava/lang/Object;
  #151 = Utf8               <R1:Ljava/lang/Object;R2:Ljava/lang/Object;R3:Ljava/lang/Object;R4:Ljava/lang/Object;A:Ljava/lang/Object;>(TR1;Lscala/Function0<TR2;>;Lscala/Function0<TR3;>;Lscala/Function0<TR4;>;Lscala/Function4<TR1;TR2;TR3;TR4;TA;>;Lscala/util/Using$Releasable<TR1;>;Lscala/util/Using$Releasable<TR2;>;Lscala/util/Using$Releasable<TR3;>;Lscala/util/Using$Releasable<TR4;>;)TA;
  #152 = Utf8               resource4
  #153 = Utf8               evidence$9
  #154 = Utf8               evidence$10
  #155 = Utf8               evidence$11
  #156 = Utf8               evidence$12
  #157 = Utf8               scala/Function4
  #158 = Class              #157          // scala/Function4
  #159 = Utf8               (Ljava/lang/Object;Ljava/lang/Object;Ljava/lang/Object;Ljava/lang/Object;)Ljava/lang/Object;
  #160 = NameAndType        #20:#159      // apply:(Ljava/lang/Object;Ljava/lang/Object;Ljava/lang/Object;Ljava/lang/Object;)Ljava/lang/Object;
  #161 = InterfaceMethodref #158.#160     // scala/Function4.apply:(Ljava/lang/Object;Ljava/lang/Object;Ljava/lang/Object;Ljava/lang/Object;)Ljava/lang/Object;
  #162 = Utf8               Lscala/Function4;
  #163 = Utf8               $anonfun$resources$6_resource_other
  #164 = Utf8               $anonfun$resources$6_resource_toThrow
  #165 = Utf8               $anonfun$resources$6_resource_this
  #166 = Utf8               $anonfun$resources$6_resource_resource
  #167 = Utf8               $anonfun$resources$6_$anonfun$resources$7_resource_other
  #168 = Utf8               $anonfun$resources$6_$anonfun$resources$7_resource_toThrow
  #169 = Utf8               $anonfun$resources$6_$anonfun$resources$7_resource_this
  #170 = Utf8               $anonfun$resources$6_$anonfun$resources$7_resource_resource
  #171 = Utf8               $anonfun$resources$8_resource_other
  #172 = Utf8               $anonfun$resources$8_resource_toThrow
  #173 = Utf8               $anonfun$resources$8_resource_this
  #174 = Utf8               $anonfun$resources$8_resource_resource
  #175 = Utf8               resource$1
  #176 = Utf8               f$1
  #177 = Utf8               evidence$1$1
  #178 = Utf8               resource_this
  #179 = Utf8               resource_resource
  #180 = Utf8               t
  #181 = Utf8               java/lang/VirtualMachineError
  #182 = Class              #181          // java/lang/VirtualMachineError
  #183 = Utf8               java/lang/LinkageError
  #184 = Class              #183          // java/lang/LinkageError
  #185 = Utf8               java/lang/InterruptedException
  #186 = Class              #185          // java/lang/InterruptedException
  #187 = Utf8               java/lang/ThreadDeath
  #188 = Class              #187          // java/lang/ThreadDeath
  #189 = Utf8               scala/util/control/ControlThrowable
  #190 = Class              #189          // scala/util/control/ControlThrowable
  #191 = Utf8               (Ljava/lang/Throwable;)Z
  #192 = NameAndType        #20:#191      // apply:(Ljava/lang/Throwable;)Z
  #193 = Methodref          #43.#192      // scala/util/control/NonFatal$.apply:(Ljava/lang/Throwable;)Z
  #194 = Utf8               suppress$1
  #195 = Utf8               suppressed
  #196 = Utf8               $anonfun$resources$2
  #197 = Utf8               (Lscala/Function2;Ljava/lang/Object;Ljava/lang/Object;)Ljava/lang/Object;
  #198 = Utf8               body$1
  #199 = Utf8               r1$1
  #200 = Utf8               r2
  #201 = Utf8               $anonfun$resources$1
  #202 = Utf8               (Lscala/Function0;Lscala/Function2;Lscala/util/Using$Releasable;Ljava/lang/Object;)Ljava/lang/Object;
  #203 = Utf8               resource2$1
  #204 = Utf8               evidence$5$1
  #205 = Utf8               r1
  #206 = Utf8               $anonfun$resources$5
  #207 = Utf8               (Lscala/Function3;Ljava/lang/Object;Ljava/lang/Object;Ljava/lang/Object;)Ljava/lang/Object;
  #208 = Utf8               body$2
  #209 = Utf8               r1$2
  #210 = Utf8               r2$1
  #211 = Utf8               r3
  #212 = Utf8               $anonfun$resources$4
  #213 = Utf8               (Lscala/Function0;Lscala/Function3;Ljava/lang/Object;Lscala/util/Using$Releasable;Ljava/lang/Object;)Ljava/lang/Object;
  #214 = Utf8               resource3$1
  #215 = Utf8               evidence$8$1
  #216 = Utf8               $anonfun$resources$3
  #217 = Utf8               (Lscala/Function0;Lscala/Function0;Lscala/Function3;Lscala/util/Using$Releasable;Lscala/util/Using$Releasable;Ljava/lang/Object;)Ljava/lang/Object;
  #218 = Utf8               resource2$2
  #219 = Utf8               evidence$7$1
  #220 = Utf8               $anonfun$resources$4_resource_other
  #221 = Utf8               $anonfun$resources$4_resource_toThrow
  #222 = Utf8               $anonfun$resources$4_resource_this
  #223 = Utf8               $anonfun$resources$4_resource_resource
  #224 = Utf8               $anonfun$resources$9
  #225 = Utf8               (Lscala/Function4;Ljava/lang/Object;Ljava/lang/Object;Ljava/lang/Object;Ljava/lang/Object;)Ljava/lang/Object;
  #226 = Utf8               body$3
  #227 = Utf8               r1$3
  #228 = Utf8               r2$2
  #229 = Utf8               r3$1
  #230 = Utf8               r4
  #231 = Utf8               $anonfun$resources$8
  #232 = Utf8               (Lscala/Function0;Lscala/Function4;Ljava/lang/Object;Ljava/lang/Object;Lscala/util/Using$Releasable;Ljava/lang/Object;)Ljava/lang/Object;
  #233 = Utf8               resource4$1
  #234 = Utf8               evidence$12$1
  #235 = Utf8               $anonfun$resources$7
  #236 = Utf8               (Lscala/Function0;Lscala/Function0;Lscala/Function4;Ljava/lang/Object;Lscala/util/Using$Releasable;Lscala/util/Using$Releasable;Ljava/lang/Object;)Ljava/lang/Object;
  #237 = Utf8               resource3$2
  #238 = Utf8               evidence$11$1
  #239 = Utf8               $anonfun$resources$6
  #240 = Utf8               (Lscala/Function0;Lscala/Function0;Lscala/Function0;Lscala/Function4;Lscala/util/Using$Releasable;Lscala/util/Using$Releasable;Lscala/util/Using$Releasable;Ljava/lang/Object;)Ljava/lang/Object;
  #241 = Utf8               resource2$3
  #242 = Utf8               evidence$10$1
  #243 = Utf8               $anonfun$resources$7_resource_other
  #244 = Utf8               $anonfun$resources$7_resource_toThrow
  #245 = Utf8               $anonfun$resources$7_resource_this
  #246 = Utf8               $anonfun$resources$7_resource_resource
  #247 = Methodref          #4.#16        // java/lang/Object."<init>":()V
  #248 = Utf8               Code
  #249 = Utf8               LineNumberTable
  #250 = Utf8               StackMapTable
  #251 = Utf8               LocalVariableTable
  #252 = Utf8               Signature
  #253 = Utf8               MethodParameters
  #254 = Utf8               InnerClasses
  #255 = Utf8               SourceFile
  #256 = Utf8               ScalaInlineInfo
  #257 = Utf8               Scala
{
  public static final scala.util.Using$ MODULE$;
    descriptor: Lscala/util/Using$;
    flags: (0x0019) ACC_PUBLIC, ACC_STATIC, ACC_FINAL

  public static {};
    descriptor: ()V
    flags: (0x0009) ACC_PUBLIC, ACC_STATIC
    Code:
      stack=2, locals=0, args_size=0
         0: new           #2                  // class scala/util/Using$
         3: dup
         4: invokespecial #17                 // Method "<init>":()V
         7: putstatic     #19                 // Field MODULE$:Lscala/util/Using$;
        10: return
      LineNumberTable:
        line 104: 0

  public <R extends java.lang.Object, A extends java.lang.Object> scala.util.Try<A> apply(scala.Function0<R>, scala.Function1<R, A>, scala.util.Using$Releasable<R>);
    descriptor: (Lscala/Function0;Lscala/Function1;Lscala/util/Using$Releasable;)Lscala/util/Try;
    flags: (0x0001) ACC_PUBLIC
    Code:
      stack=5, locals=8, args_size=4
         0: getstatic     #32                 // Field scala/util/Try$.MODULE$:Lscala/util/Try$;
         3: pop
         4: new           #34                 // class scala/util/Success
         7: dup
         8: aload_1
         9: aload_2
        10: aload_3
        11: invokestatic  #38                 // Method $anonfun$apply$1:(Lscala/Function0;Lscala/Function1;Lscala/util/Using$Releasable;)Ljava/lang/Object;
        14: invokespecial #41                 // Method scala/util/Success."<init>":(Ljava/lang/Object;)V
        17: areturn
        18: astore        5
        20: aload         5
        22: ifnull        67
        25: getstatic     #46                 // Field scala/util/control/NonFatal$.MODULE$:Lscala/util/control/NonFatal$;
        28: aload         5
        30: invokevirtual #50                 // Method scala/util/control/NonFatal$.unapply:(Ljava/lang/Throwable;)Lscala/Option;
        33: astore        6
        35: aload         6
        37: invokevirtual #56                 // Method scala/Option.isEmpty:()Z
        40: ifne          67
        43: aload         6
        45: invokevirtual #60                 // Method scala/Option.get:()Ljava/lang/Object;
        48: checkcast     #27                 // class java/lang/Throwable
        51: astore        7
        53: new           #62                 // class scala/util/Failure
        56: dup
        57: aload         7
        59: invokespecial #65                 // Method scala/util/Failure."<init>":(Ljava/lang/Throwable;)V
        62: astore        4
        64: goto          70
        67: aload         5
        69: athrow
        70: aload         4
        72: areturn
      Exception table:
         from    to  target type
             4    17    18   Class java/lang/Throwable
      StackMapTable: number_of_entries = 3
        frame_type = 82 /* same_locals_1_stack_item */
          stack = [ class java/lang/Throwable ]
        frame_type = 253 /* append */
          offset_delta = 48
          locals = [ top, class java/lang/Throwable ]
        frame_type = 255 /* full_frame */
          offset_delta = 2
          locals = [ class scala/util/Using$, class scala/Function0, class scala/Function1, class scala/util/Using$Releasable, class scala/util/Failure, class java/lang/Throwable, class scala/Option, class java/lang/Throwable ]
          stack = []
      LineNumberTable:
        line 113: 0
      LocalVariableTable:
        Start  Length  Slot  Name   Signature
            0      73     0  this   Lscala/util/Using$;
            0      73     1 resource   Lscala/Function0;
            0      73     2     f   Lscala/Function1;
            0      73     3 evidence$1   Lscala/util/Using$Releasable;
           53      14     7 apply_e   Ljava/lang/Throwable;
    Signature: #22                          // <R:Ljava/lang/Object;A:Ljava/lang/Object;>(Lscala/Function0<TR;>;Lscala/Function1<TR;TA;>;Lscala/util/Using$Releasable<TR;>;)Lscala/util/Try<TA;>;
    MethodParameters:
      Name                           Flags
      resource                       final
      f                              final
      evidence$1                     final

  public java.lang.Throwable scala$util$Using$$preferentiallySuppress(java.lang.Throwable, java.lang.Throwable);
    descriptor: (Ljava/lang/Throwable;Ljava/lang/Throwable;)Ljava/lang/Throwable;
    flags: (0x0001) ACC_PUBLIC
    Code:
      stack=2, locals=3, args_size=3
         0: aload_2
         1: invokestatic  #83                 // Method score$1:(Ljava/lang/Throwable;)I
         4: aload_1
         5: invokestatic  #83                 // Method score$1:(Ljava/lang/Throwable;)I
         8: if_icmple     18
        11: aload_2
        12: aload_1
        13: invokevirtual #86                 // Method java/lang/Throwable.addSuppressed:(Ljava/lang/Throwable;)V
        16: aload_2
        17: areturn
        18: aload_1
        19: aload_2
        20: invokevirtual #86                 // Method java/lang/Throwable.addSuppressed:(Ljava/lang/Throwable;)V
        23: aload_1
        24: areturn
      StackMapTable: number_of_entries = 1
        frame_type = 18 /* same */
      LineNumberTable:
        line 239: 0
        line 237: 11
        line 239: 16
        line 237: 18
        line 240: 23
      LocalVariableTable:
        Start  Length  Slot  Name   Signature
            0      25     0  this   Lscala/util/Using$;
            0      25     1 primary   Ljava/lang/Throwable;
            0      25     2 secondary   Ljava/lang/Throwable;
    MethodParameters:
      Name                           Flags
      primary                        final
      secondary                      final

  public <R extends java.lang.Object, A extends java.lang.Object> A resource(R, scala.Function1<R, A>, scala.util.Using$Releasable<R>);
    descriptor: (Ljava/lang/Object;Lscala/Function1;Lscala/util/Using$Releasable;)Ljava/lang/Object;
    flags: (0x0001) ACC_PUBLIC
    Code:
      stack=3, locals=8, args_size=4
         0: aload_1
         1: ifnonnull     14
         4: new           #92                 // class java/lang/NullPointerException
         7: dup
         8: ldc           #94                 // String null resource
        10: invokespecial #97                 // Method java/lang/NullPointerException."<init>":(Ljava/lang/String;)V
        13: athrow
        14: aconst_null
        15: astore        4
        17: aload_2
        18: aload_1
        19: invokeinterface #100,  2          // InterfaceMethod scala/Function1.apply:(Ljava/lang/Object;)Ljava/lang/Object;
        24: goto          85
        27: astore        4
        29: aconst_null
        30: goto          85
        33: astore        6
        35: aload         4
        37: ifnonnull     50
        40: aload_3
        41: aload_1
        42: invokeinterface #103,  2          // InterfaceMethod scala/util/Using$Releasable.release:(Ljava/lang/Object;)V
        47: goto          82
        50: aload_3
        51: aload_1
        52: invokeinterface #103,  2          // InterfaceMethod scala/util/Using$Releasable.release:(Ljava/lang/Object;)V
        57: goto          79
        60: astore        7
        62: aload_0
        63: aload         4
        65: aload         7
        67: invokevirtual #105                // Method scala$util$Using$$preferentiallySuppress:(Ljava/lang/Throwable;Ljava/lang/Throwable;)Ljava/lang/Throwable;
        70: astore        4
        72: goto          79
        75: pop
        76: aload         4
        78: athrow
        79: aload         4
        81: athrow
        82: aload         6
        84: athrow
        85: astore        5
        87: aload         4
        89: ifnonnull     102
        92: aload_3
        93: aload_1
        94: invokeinterface #103,  2          // InterfaceMethod scala/util/Using$Releasable.release:(Ljava/lang/Object;)V
        99: goto          134
       102: aload_3
       103: aload_1
       104: invokeinterface #103,  2          // InterfaceMethod scala/util/Using$Releasable.release:(Ljava/lang/Object;)V
       109: goto          131
       112: astore        7
       114: aload_0
       115: aload         4
       117: aload         7
       119: invokevirtual #105                // Method scala$util$Using$$preferentiallySuppress:(Ljava/lang/Throwable;Ljava/lang/Throwable;)Ljava/lang/Throwable;
       122: astore        4
       124: goto          131
       127: pop
       128: aload         4
       130: athrow
       131: aload         4
       133: athrow
       134: aload         5
       136: areturn
      Exception table:
         from    to  target type
            17    24    27   Class java/lang/Throwable
            17    33    33   any
            50    57    60   Class java/lang/Throwable
            50    75    75   any
           102   109   112   Class java/lang/Throwable
           102   127   127   any
      StackMapTable: number_of_entries = 14
        frame_type = 14 /* same */
        frame_type = 255 /* full_frame */
          offset_delta = 12
          locals = [ class scala/util/Using$, class java/lang/Object, class scala/Function1, class scala/util/Using$Releasable, null ]
          stack = [ class java/lang/Throwable ]
        frame_type = 255 /* full_frame */
          offset_delta = 5
          locals = [ class scala/util/Using$, class java/lang/Object, class scala/Function1, class scala/util/Using$Releasable, class java/lang/Throwable ]
          stack = [ class java/lang/Throwable ]
        frame_type = 253 /* append */
          offset_delta = 16
          locals = [ top, class java/lang/Throwable ]
        frame_type = 73 /* same_locals_1_stack_item */
          stack = [ class java/lang/Throwable ]
        frame_type = 78 /* same_locals_1_stack_item */
          stack = [ class java/lang/Throwable ]
        frame_type = 3 /* same */
        frame_type = 2 /* same */
        frame_type = 255 /* full_frame */
          offset_delta = 2
          locals = [ class scala/util/Using$, class java/lang/Object, class scala/Function1, class scala/util/Using$Releasable, class java/lang/Throwable ]
          stack = [ class java/lang/Object ]
        frame_type = 252 /* append */
          offset_delta = 16
          locals = [ class java/lang/Object ]
        frame_type = 73 /* same_locals_1_stack_item */
          stack = [ class java/lang/Throwable ]
        frame_type = 78 /* same_locals_1_stack_item */
          stack = [ class java/lang/Throwable ]
        frame_type = 3 /* same */
        frame_type = 2 /* same */
      LineNumberTable:
        line 257: 0
        line 259: 14
        line 261: 17
        line 264: 27
        line 265: 29
        line 267: 35
        line 269: 50
        line 270: 62
        line 271: 76
        line 267: 87
        line 269: 102
        line 270: 114
        line 271: 128
      LocalVariableTable:
        Start  Length  Slot  Name   Signature
           60      12     7 other   Ljava/lang/Throwable;
          112      12     7 other   Ljava/lang/Throwable;
           17     119     4 toThrow   Ljava/lang/Throwable;
            0     137     0  this   Lscala/util/Using$;
            0     137     1 resource   Ljava/lang/Object;
            0     137     2  body   Lscala/Function1;
            0     137     3 releasable   Lscala/util/Using$Releasable;
    Signature: #88                          // <R:Ljava/lang/Object;A:Ljava/lang/Object;>(TR;Lscala/Function1<TR;TA;>;Lscala/util/Using$Releasable<TR;>;)TA;
    MethodParameters:
      Name                           Flags
      resource                       final
      body                           final
      releasable                     final

  public <R1 extends java.lang.Object, R2 extends java.lang.Object, A extends java.lang.Object> A resources(R1, scala.Function0<R2>, scala.Function2<R1, R2, A>, scala.util.Using$Releasable<R1>, scala.util.Using$Releasable<R2>);
    descriptor: (Ljava/lang/Object;Lscala/Function0;Lscala/Function2;Lscala/util/Using$Releasable;Lscala/util/Using$Releasable;)Ljava/lang/Object;
    flags: (0x0001) ACC_PUBLIC
    Code:
      stack=3, locals=16, args_size=6
         0: aload_1
         1: ifnonnull     14
         4: new           #92                 // class java/lang/NullPointerException
         7: dup
         8: ldc           #94                 // String null resource
        10: invokespecial #97                 // Method java/lang/NullPointerException."<init>":(Ljava/lang/String;)V
        13: athrow
        14: aconst_null
        15: astore        6
        17: getstatic     #19                 // Field MODULE$:Lscala/util/Using$;
        20: aload_2
        21: invokeinterface #117,  1          // InterfaceMethod scala/Function0.apply:()Ljava/lang/Object;
        26: astore        11
        28: astore        10
        30: aload         11
        32: ifnonnull     45
        35: new           #92                 // class java/lang/NullPointerException
        38: dup
        39: ldc           #94                 // String null resource
        41: invokespecial #97                 // Method java/lang/NullPointerException."<init>":(Ljava/lang/String;)V
        44: athrow
        45: aconst_null
        46: astore        12
        48: aload_3
        49: aload_1
        50: aload         11
        52: invokeinterface #122,  3          // InterfaceMethod scala/Function2.apply:(Ljava/lang/Object;Ljava/lang/Object;)Ljava/lang/Object;
        57: goto          123
        60: astore        12
        62: aconst_null
        63: goto          123
        66: astore        14
        68: aload         12
        70: ifnonnull     85
        73: aload         5
        75: aload         11
        77: invokeinterface #103,  2          // InterfaceMethod scala/util/Using$Releasable.release:(Ljava/lang/Object;)V
        82: goto          120
        85: aload         5
        87: aload         11
        89: invokeinterface #103,  2          // InterfaceMethod scala/util/Using$Releasable.release:(Ljava/lang/Object;)V
        94: goto          117
        97: astore        15
        99: aload         10
       101: aload         12
       103: aload         15
       105: invokevirtual #105                // Method scala$util$Using$$preferentiallySuppress:(Ljava/lang/Throwable;Ljava/lang/Throwable;)Ljava/lang/Throwable;
       108: astore        12
       110: goto          117
       113: pop
       114: aload         12
       116: athrow
       117: aload         12
       119: athrow
       120: aload         14
       122: athrow
       123: astore        13
       125: aload         12
       127: ifnonnull     142
       130: aload         5
       132: aload         11
       134: invokeinterface #103,  2          // InterfaceMethod scala/util/Using$Releasable.release:(Ljava/lang/Object;)V
       139: goto          177
       142: aload         5
       144: aload         11
       146: invokeinterface #103,  2          // InterfaceMethod scala/util/Using$Releasable.release:(Ljava/lang/Object;)V
       151: goto          174
       154: astore        15
       156: aload         10
       158: aload         12
       160: aload         15
       162: invokevirtual #105                // Method scala$util$Using$$preferentiallySuppress:(Ljava/lang/Throwable;Ljava/lang/Throwable;)Ljava/lang/Throwable;
       165: astore        12
       167: goto          174
       170: pop
       171: aload         12
       173: athrow
       174: aload         12
       176: athrow
       177: aload         13
       179: aconst_null
       180: astore        10
       182: aconst_null
       183: astore        11
       185: aconst_null
       186: astore        13
       188: goto          251
       191: astore        6
       193: aconst_null
       194: goto          251
       197: astore        8
       199: aload         6
       201: ifnonnull     215
       204: aload         4
       206: aload_1
       207: invokeinterface #103,  2          // InterfaceMethod scala/util/Using$Releasable.release:(Ljava/lang/Object;)V
       212: goto          248
       215: aload         4
       217: aload_1
       218: invokeinterface #103,  2          // InterfaceMethod scala/util/Using$Releasable.release:(Ljava/lang/Object;)V
       223: goto          245
       226: astore        9
       228: aload_0
       229: aload         6
       231: aload         9
       233: invokevirtual #105                // Method scala$util$Using$$preferentiallySuppress:(Ljava/lang/Throwable;Ljava/lang/Throwable;)Ljava/lang/Throwable;
       236: astore        6
       238: goto          245
       241: pop
       242: aload         6
       244: athrow
       245: aload         6
       247: athrow
       248: aload         8
       250: athrow
       251: astore        7
       253: aload         6
       255: ifnonnull     269
       258: aload         4
       260: aload_1
       261: invokeinterface #103,  2          // InterfaceMethod scala/util/Using$Releasable.release:(Ljava/lang/Object;)V
       266: goto          302
       269: aload         4
       271: aload_1
       272: invokeinterface #103,  2          // InterfaceMethod scala/util/Using$Releasable.release:(Ljava/lang/Object;)V
       277: goto          299
       280: astore        9
       282: aload_0
       283: aload         6
       285: aload         9
       287: invokevirtual #105                // Method scala$util$Using$$preferentiallySuppress:(Ljava/lang/Throwable;Ljava/lang/Throwable;)Ljava/lang/Throwable;
       290: astore        6
       292: goto          299
       295: pop
       296: aload         6
       298: athrow
       299: aload         6
       301: athrow
       302: aload         7
       304: areturn
      Exception table:
         from    to  target type
            48    57    60   Class java/lang/Throwable
            48    66    66   any
            85    94    97   Class java/lang/Throwable
            85   113   113   any
           142   151   154   Class java/lang/Throwable
           142   170   170   any
            17   188   191   Class java/lang/Throwable
            17   197   197   any
           215   223   226   Class java/lang/Throwable
           215   241   241   any
           269   277   280   Class java/lang/Throwable
           269   295   295   any
      StackMapTable: number_of_entries = 28
        frame_type = 14 /* same */
        frame_type = 255 /* full_frame */
          offset_delta = 30
          locals = [ class scala/util/Using$, class java/lang/Object, class scala/Function0, class scala/Function2, class scala/util/Using$Releasable, class scala/util/Using$Releasable, null, top, top, top, class scala/util/Using$, class java/lang/Object ]
          stack = []
        frame_type = 255 /* full_frame */
          offset_delta = 14
          locals = [ class scala/util/Using$, class java/lang/Object, class scala/Function0, class scala/Function2, class scala/util/Using$Releasable, class scala/util/Using$Releasable, null, top, top, top, class scala/util/Using$, class java/lang/Object, null ]
          stack = [ class java/lang/Throwable ]
        frame_type = 255 /* full_frame */
          offset_delta = 5
          locals = [ class scala/util/Using$, class java/lang/Object, class scala/Function0, class scala/Function2, class scala/util/Using$Releasable, class scala/util/Using$Releasable, null, top, top, top, class scala/util/Using$, class java/lang/Object, class java/lang/Throwable ]
          stack = [ class java/lang/Throwable ]
        frame_type = 253 /* append */
          offset_delta = 18
          locals = [ top, class java/lang/Throwable ]
        frame_type = 75 /* same_locals_1_stack_item */
          stack = [ class java/lang/Throwable ]
        frame_type = 79 /* same_locals_1_stack_item */
          stack = [ class java/lang/Throwable ]
        frame_type = 3 /* same */
        frame_type = 2 /* same */
        frame_type = 255 /* full_frame */
          offset_delta = 2
          locals = [ class scala/util/Using$, class java/lang/Object, class scala/Function0, class scala/Function2, class scala/util/Using$Releasable, class scala/util/Using$Releasable, null, top, top, top, class scala/util/Using$, class java/lang/Object, class java/lang/Throwable ]
          stack = [ class java/lang/Object ]
        frame_type = 252 /* append */
          offset_delta = 18
          locals = [ class java/lang/Object ]
        frame_type = 75 /* same_locals_1_stack_item */
          stack = [ class java/lang/Throwable ]
        frame_type = 79 /* same_locals_1_stack_item */
          stack = [ class java/lang/Throwable ]
        frame_type = 3 /* same */
        frame_type = 2 /* same */
        frame_type = 255 /* full_frame */
          offset_delta = 13
          locals = [ class scala/util/Using$, class java/lang/Object, class scala/Function0, class scala/Function2, class scala/util/Using$Releasable, class scala/util/Using$Releasable, null ]
          stack = [ class java/lang/Throwable ]
        frame_type = 255 /* full_frame */
          offset_delta = 5
          locals = [ class scala/util/Using$, class java/lang/Object, class scala/Function0, class scala/Function2, class scala/util/Using$Releasable, class scala/util/Using$Releasable, class java/lang/Throwable ]
          stack = [ class java/lang/Throwable ]
        frame_type = 253 /* append */
          offset_delta = 17
          locals = [ top, class java/lang/Throwable ]
        frame_type = 74 /* same_locals_1_stack_item */
          stack = [ class java/lang/Throwable ]
        frame_type = 78 /* same_locals_1_stack_item */
          stack = [ class java/lang/Throwable ]
        frame_type = 3 /* same */
        frame_type = 2 /* same */
        frame_type = 255 /* full_frame */
          offset_delta = 2
          locals = [ class scala/util/Using$, class java/lang/Object, class scala/Function0, class scala/Function2, class scala/util/Using$Releasable, class scala/util/Using$Releasable, class java/lang/Throwable ]
          stack = [ class java/lang/Object ]
        frame_type = 252 /* append */
          offset_delta = 17
          locals = [ class java/lang/Object ]
        frame_type = 74 /* same_locals_1_stack_item */
          stack = [ class java/lang/Throwable ]
        frame_type = 78 /* same_locals_1_stack_item */
          stack = [ class java/lang/Throwable ]
        frame_type = 3 /* same */
        frame_type = 2 /* same */
      LineNumberTable:
        line 257: 0
        line 259: 14
        line 297: 17
        line 257: 30
        line 259: 45
        line 298: 48
        line 261: 57
        line 264: 60
        line 265: 62
        line 267: 68
        line 269: 85
        line 270: 99
        line 271: 114
        line 267: 125
        line 269: 142
        line 270: 156
        line 271: 171
        line 297: 177
        line 261: 188
        line 264: 191
        line 265: 193
        line 267: 199
        line 269: 215
        line 270: 228
        line 271: 242
        line 267: 253
        line 269: 269
        line 270: 282
        line 271: 296
        line 296: 302
      LocalVariableTable:
        Start  Length  Slot  Name   Signature
            0     305     0  this   Lscala/util/Using$;
            0     305     1 resource1   Ljava/lang/Object;
            0     305     2 resource2   Lscala/Function0;
            0     305     3  body   Lscala/Function2;
            0     305     4 evidence$4   Lscala/util/Using$Releasable;
            0     305     5 evidence$5   Lscala/util/Using$Releasable;
          226      12     9 resource_other   Ljava/lang/Throwable;
          280      12     9 resource_other   Ljava/lang/Throwable;
           17     285     6 resource_toThrow   Ljava/lang/Throwable;
           97      13    15 $anonfun$resources$1_resource_other   Ljava/lang/Throwable;
          154      13    15 $anonfun$resources$1_resource_other   Ljava/lang/Throwable;
           48     129    12 $anonfun$resources$1_resource_toThrow   Ljava/lang/Throwable;
           30     147    10 $anonfun$resources$1_resource_this   Lscala/util/Using$;
           30     147    11 $anonfun$resources$1_resource_resource   Ljava/lang/Object;
    Signature: #111                         // <R1:Ljava/lang/Object;R2:Ljava/lang/Object;A:Ljava/lang/Object;>(TR1;Lscala/Function0<TR2;>;Lscala/Function2<TR1;TR2;TA;>;Lscala/util/Using$Releasable<TR1;>;Lscala/util/Using$Releasable<TR2;>;)TA;
    MethodParameters:
      Name                           Flags
      resource1                      final
      resource2                      final
      body                           final
      evidence$4                     final
      evidence$5                     final

  public <R1 extends java.lang.Object, R2 extends java.lang.Object, R3 extends java.lang.Object, A extends java.lang.Object> A resources(R1, scala.Function0<R2>, scala.Function0<R3>, scala.Function3<R1, R2, R3, A>, scala.util.Using$Releasable<R1>, scala.util.Using$Releasable<R2>, scala.util.Using$Releasable<R3>);
    descriptor: (Ljava/lang/Object;Lscala/Function0;Lscala/Function0;Lscala/Function3;Lscala/util/Using$Releasable;Lscala/util/Using$Releasable;Lscala/util/Using$Releasable;)Ljava/lang/Object;
    flags: (0x0001) ACC_PUBLIC
    Code:
      stack=4, locals=24, args_size=8
         0: aload_1
         1: ifnonnull     14
         4: new           #92                 // class java/lang/NullPointerException
         7: dup
         8: ldc           #94                 // String null resource
        10: invokespecial #97                 // Method java/lang/NullPointerException."<init>":(Ljava/lang/String;)V
        13: athrow
        14: aconst_null
        15: astore        8
        17: getstatic     #19                 // Field MODULE$:Lscala/util/Using$;
        20: aload_2
        21: invokeinterface #117,  1          // InterfaceMethod scala/Function0.apply:()Ljava/lang/Object;
        26: astore        13
        28: astore        12
        30: aload         13
        32: ifnonnull     45
        35: new           #92                 // class java/lang/NullPointerException
        38: dup
        39: ldc           #94                 // String null resource
        41: invokespecial #97                 // Method java/lang/NullPointerException."<init>":(Ljava/lang/String;)V
        44: athrow
        45: aconst_null
        46: astore        14
        48: getstatic     #19                 // Field MODULE$:Lscala/util/Using$;
        51: aload_3
        52: invokeinterface #117,  1          // InterfaceMethod scala/Function0.apply:()Ljava/lang/Object;
        57: astore        19
        59: astore        18
        61: aload         19
        63: ifnonnull     76
        66: new           #92                 // class java/lang/NullPointerException
        69: dup
        70: ldc           #94                 // String null resource
        72: invokespecial #97                 // Method java/lang/NullPointerException."<init>":(Ljava/lang/String;)V
        75: athrow
        76: aconst_null
        77: astore        20
        79: aload         4
        81: aload_1
        82: aload         13
        84: aload         19
        86: invokeinterface #140,  4          // InterfaceMethod scala/Function3.apply:(Ljava/lang/Object;Ljava/lang/Object;Ljava/lang/Object;)Ljava/lang/Object;
        91: goto          157
        94: astore        20
        96: aconst_null
        97: goto          157
       100: astore        22
       102: aload         20
       104: ifnonnull     119
       107: aload         7
       109: aload         19
       111: invokeinterface #103,  2          // InterfaceMethod scala/util/Using$Releasable.release:(Ljava/lang/Object;)V
       116: goto          154
       119: aload         7
       121: aload         19
       123: invokeinterface #103,  2          // InterfaceMethod scala/util/Using$Releasable.release:(Ljava/lang/Object;)V
       128: goto          151
       131: astore        23
       133: aload         18
       135: aload         20
       137: aload         23
       139: invokevirtual #105                // Method scala$util$Using$$preferentiallySuppress:(Ljava/lang/Throwable;Ljava/lang/Throwable;)Ljava/lang/Throwable;
       142: astore        20
       144: goto          151
       147: pop
       148: aload         20
       150: athrow
       151: aload         20
       153: athrow
       154: aload         22
       156: athrow
       157: astore        21
       159: aload         20
       161: ifnonnull     176
       164: aload         7
       166: aload         19
       168: invokeinterface #103,  2          // InterfaceMethod scala/util/Using$Releasable.release:(Ljava/lang/Object;)V
       173: goto          211
       176: aload         7
       178: aload         19
       180: invokeinterface #103,  2          // InterfaceMethod scala/util/Using$Releasable.release:(Ljava/lang/Object;)V
       185: goto          208
       188: astore        23
       190: aload         18
       192: aload         20
       194: aload         23
       196: invokevirtual #105                // Method scala$util$Using$$preferentiallySuppress:(Ljava/lang/Throwable;Ljava/lang/Throwable;)Ljava/lang/Throwable;
       199: astore        20
       201: goto          208
       204: pop
       205: aload         20
       207: athrow
       208: aload         20
       210: athrow
       211: aload         21
       213: aconst_null
       214: astore        18
       216: aconst_null
       217: astore        19
       219: aconst_null
       220: astore        21
       222: goto          288
       225: astore        14
       227: aconst_null
       228: goto          288
       231: astore        16
       233: aload         14
       235: ifnonnull     250
       238: aload         6
       240: aload         13
       242: invokeinterface #103,  2          // InterfaceMethod scala/util/Using$Releasable.release:(Ljava/lang/Object;)V
       247: goto          285
       250: aload         6
       252: aload         13
       254: invokeinterface #103,  2          // InterfaceMethod scala/util/Using$Releasable.release:(Ljava/lang/Object;)V
       259: goto          282
       262: astore        17
       264: aload         12
       266: aload         14
       268: aload         17
       270: invokevirtual #105                // Method scala$util$Using$$preferentiallySuppress:(Ljava/lang/Throwable;Ljava/lang/Throwable;)Ljava/lang/Throwable;
       273: astore        14
       275: goto          282
       278: pop
       279: aload         14
       281: athrow
       282: aload         14
       284: athrow
       285: aload         16
       287: athrow
       288: astore        15
       290: aload         14
       292: ifnonnull     307
       295: aload         6
       297: aload         13
       299: invokeinterface #103,  2          // InterfaceMethod scala/util/Using$Releasable.release:(Ljava/lang/Object;)V
       304: goto          342
       307: aload         6
       309: aload         13
       311: invokeinterface #103,  2          // InterfaceMethod scala/util/Using$Releasable.release:(Ljava/lang/Object;)V
       316: goto          339
       319: astore        17
       321: aload         12
       323: aload         14
       325: aload         17
       327: invokevirtual #105                // Method scala$util$Using$$preferentiallySuppress:(Ljava/lang/Throwable;Ljava/lang/Throwable;)Ljava/lang/Throwable;
       330: astore        14
       332: goto          339
       335: pop
       336: aload         14
       338: athrow
       339: aload         14
       341: athrow
       342: aload         15
       344: aconst_null
       345: astore        12
       347: aconst_null
       348: astore        13
       350: aconst_null
       351: astore        15
       353: aconst_null
       354: astore        18
       356: aconst_null
       357: astore        19
       359: aconst_null
       360: astore        20
       362: aconst_null
       363: astore        21
       365: aconst_null
       366: astore        22
       368: aconst_null
       369: astore        23
       371: goto          434
       374: astore        8
       376: aconst_null
       377: goto          434
       380: astore        10
       382: aload         8
       384: ifnonnull     398
       387: aload         5
       389: aload_1
       390: invokeinterface #103,  2          // InterfaceMethod scala/util/Using$Releasable.release:(Ljava/lang/Object;)V
       395: goto          431
       398: aload         5
       400: aload_1
       401: invokeinterface #103,  2          // InterfaceMethod scala/util/Using$Releasable.release:(Ljava/lang/Object;)V
       406: goto          428
       409: astore        11
       411: aload_0
       412: aload         8
       414: aload         11
       416: invokevirtual #105                // Method scala$util$Using$$preferentiallySuppress:(Ljava/lang/Throwable;Ljava/lang/Throwable;)Ljava/lang/Throwable;
       419: astore        8
       421: goto          428
       424: pop
       425: aload         8
       427: athrow
       428: aload         8
       430: athrow
       431: aload         10
       433: athrow
       434: astore        9
       436: aload         8
       438: ifnonnull     452
       441: aload         5
       443: aload_1
       444: invokeinterface #103,  2          // InterfaceMethod scala/util/Using$Releasable.release:(Ljava/lang/Object;)V
       449: goto          485
       452: aload         5
       454: aload_1
       455: invokeinterface #103,  2          // InterfaceMethod scala/util/Using$Releasable.release:(Ljava/lang/Object;)V
       460: goto          482
       463: astore        11
       465: aload_0
       466: aload         8
       468: aload         11
       470: invokevirtual #105                // Method scala$util$Using$$preferentiallySuppress:(Ljava/lang/Throwable;Ljava/lang/Throwable;)Ljava/lang/Throwable;
       473: astore        8
       475: goto          482
       478: pop
       479: aload         8
       481: athrow
       482: aload         8
       484: athrow
       485: aload         9
       487: areturn
      Exception table:
         from    to  target type
            79    91    94   Class java/lang/Throwable
            79   100   100   any
           119   128   131   Class java/lang/Throwable
           119   147   147   any
           176   185   188   Class java/lang/Throwable
           176   204   204   any
            48   222   225   Class java/lang/Throwable
            48   231   231   any
           250   259   262   Class java/lang/Throwable
           250   278   278   any
           307   316   319   Class java/lang/Throwable
           307   335   335   any
            17   371   374   Class java/lang/Throwable
            17   380   380   any
           398   406   409   Class java/lang/Throwable
           398   424   424   any
           452   460   463   Class java/lang/Throwable
           452   478   478   any
      StackMapTable: number_of_entries = 42
        frame_type = 14 /* same */
        frame_type = 255 /* full_frame */
          offset_delta = 30
          locals = [ class scala/util/Using$, class java/lang/Object, class scala/Function0, class scala/Function0, class scala/Function3, class scala/util/Using$Releasable, class scala/util/Using$Releasable, class scala/util/Using$Releasable, null, top, top, top, class scala/util/Using$, class java/lang/Object ]
          stack = []
        frame_type = 255 /* full_frame */
          offset_delta = 30
          locals = [ class scala/util/Using$, class java/lang/Object, class scala/Function0, class scala/Function0, class scala/Function3, class scala/util/Using$Releasable, class scala/util/Using$Releasable, class scala/util/Using$Releasable, null, top, top, top, class scala/util/Using$, class java/lang/Object, null, top, top, top, class scala/util/Using$, class java/lang/Object ]
          stack = []
        frame_type = 255 /* full_frame */
          offset_delta = 17
          locals = [ class scala/util/Using$, class java/lang/Object, class scala/Function0, class scala/Function0, class scala/Function3, class scala/util/Using$Releasable, class scala/util/Using$Releasable, class scala/util/Using$Releasable, null, top, top, top, class scala/util/Using$, class java/lang/Object, null, top, top, top, class scala/util/Using$, class java/lang/Object, null ]
          stack = [ class java/lang/Throwable ]
        frame_type = 255 /* full_frame */
          offset_delta = 5
          locals = [ class scala/util/Using$, class java/lang/Object, class scala/Function0, class scala/Function0, class scala/Function3, class scala/util/Using$Releasable, class scala/util/Using$Releasable, class scala/util/Using$Releasable, null, top, top, top, class scala/util/Using$, class java/lang/Object, null, top, top, top, class scala/util/Using$, class java/lang/Object, class java/lang/Throwable ]
          stack = [ class java/lang/Throwable ]
        frame_type = 253 /* append */
          offset_delta = 18
          locals = [ top, class java/lang/Throwable ]
        frame_type = 75 /* same_locals_1_stack_item */
          stack = [ class java/lang/Throwable ]
        frame_type = 79 /* same_locals_1_stack_item */
          stack = [ class java/lang/Throwable ]
        frame_type = 3 /* same */
        frame_type = 2 /* same */
        frame_type = 255 /* full_frame */
          offset_delta = 2
          locals = [ class scala/util/Using$, class java/lang/Object, class scala/Function0, class scala/Function0, class scala/Function3, class scala/util/Using$Releasable, class scala/util/Using$Releasable, class scala/util/Using$Releasable, null, top, top, top, class scala/util/Using$, class java/lang/Object, null, top, top, top, class scala/util/Using$, class java/lang/Object, class java/lang/Throwable ]
          stack = [ class java/lang/Object ]
        frame_type = 252 /* append */
          offset_delta = 18
          locals = [ class java/lang/Object ]
        frame_type = 75 /* same_locals_1_stack_item */
          stack = [ class java/lang/Throwable ]
        frame_type = 79 /* same_locals_1_stack_item */
          stack = [ class java/lang/Throwable ]
        frame_type = 3 /* same */
        frame_type = 2 /* same */
        frame_type = 255 /* full_frame */
          offset_delta = 13
          locals = [ class scala/util/Using$, class java/lang/Object, class scala/Function0, class scala/Function0, class scala/Function3, class scala/util/Using$Releasable, class scala/util/Using$Releasable, class scala/util/Using$Releasable, null, top, top, top, class scala/util/Using$, class java/lang/Object, null ]
          stack = [ class java/lang/Throwable ]
        frame_type = 255 /* full_frame */
          offset_delta = 5
          locals = [ class scala/util/Using$, class java/lang/Object, class scala/Function0, class scala/Function0, class scala/Function3, class scala/util/Using$Releasable, class scala/util/Using$Releasable, class scala/util/Using$Releasable, null, top, top, top, class scala/util/Using$, class java/lang/Object, class java/lang/Throwable ]
          stack = [ class java/lang/Throwable ]
        frame_type = 253 /* append */
          offset_delta = 18
          locals = [ top, class java/lang/Throwable ]
        frame_type = 75 /* same_locals_1_stack_item */
          stack = [ class java/lang/Throwable ]
        frame_type = 79 /* same_locals_1_stack_item */
          stack = [ class java/lang/Throwable ]
        frame_type = 3 /* same */
        frame_type = 2 /* same */
        frame_type = 255 /* full_frame */
          offset_delta = 2
          locals = [ class scala/util/Using$, class java/lang/Object, class scala/Function0, class scala/Function0, class scala/Function3, class scala/util/Using$Releasable, class scala/util/Using$Releasable, class scala/util/Using$Releasable, null, top, top, top, class scala/util/Using$, class java/lang/Object, class java/lang/Throwable ]
          stack = [ class java/lang/Object ]
        frame_type = 252 /* append */
          offset_delta = 18
          locals = [ class java/lang/Object ]
        frame_type = 75 /* same_locals_1_stack_item */
          stack = [ class java/lang/Throwable ]
        frame_type = 79 /* same_locals_1_stack_item */
          stack = [ class java/lang/Throwable ]
        frame_type = 3 /* same */
        frame_type = 2 /* same */
        frame_type = 255 /* full_frame */
          offset_delta = 31
          locals = [ class scala/util/Using$, class java/lang/Object, class scala/Function0, class scala/Function0, class scala/Function3, class scala/util/Using$Releasable, class scala/util/Using$Releasable, class scala/util/Using$Releasable, null ]
          stack = [ class java/lang/Throwable ]
        frame_type = 255 /* full_frame */
          offset_delta = 5
          locals = [ class scala/util/Using$, class java/lang/Object, class scala/Function0, class scala/Function0, class scala/Function3, class scala/util/Using$Releasable, class scala/util/Using$Releasable, class scala/util/Using$Releasable, class java/lang/Throwable ]
          stack = [ class java/lang/Throwable ]
        frame_type = 253 /* append */
          offset_delta = 17
          locals = [ top, class java/lang/Throwable ]
        frame_type = 74 /* same_locals_1_stack_item */
          stack = [ class java/lang/Throwable ]
        frame_type = 78 /* same_locals_1_stack_item */
          stack = [ class java/lang/Throwable ]
        frame_type = 3 /* same */
        frame_type = 2 /* same */
        frame_type = 255 /* full_frame */
          offset_delta = 2
          locals = [ class scala/util/Using$, class java/lang/Object, class scala/Function0, class scala/Function0, class scala/Function3, class scala/util/Using$Releasable, class scala/util/Using$Releasable, class scala/util/Using$Releasable, class java/lang/Throwable ]
          stack = [ class java/lang/Object ]
        frame_type = 252 /* append */
          offset_delta = 17
          locals = [ class java/lang/Object ]
        frame_type = 74 /* same_locals_1_stack_item */
          stack = [ class java/lang/Throwable ]
        frame_type = 78 /* same_locals_1_stack_item */
          stack = [ class java/lang/Throwable ]
        frame_type = 3 /* same */
        frame_type = 2 /* same */
      LineNumberTable:
        line 257: 0
        line 259: 14
        line 326: 17
        line 257: 30
        line 259: 45
        line 327: 48
        line 257: 61
        line 259: 76
        line 328: 79
        line 261: 91
        line 264: 94
        line 265: 96
        line 267: 102
        line 269: 119
        line 270: 133
        line 271: 148
        line 267: 159
        line 269: 176
        line 270: 190
        line 271: 205
        line 327: 211
        line 261: 222
        line 264: 225
        line 265: 227
        line 267: 233
        line 269: 250
        line 270: 264
        line 271: 279
        line 267: 290
        line 269: 307
        line 270: 321
        line 271: 336
        line 326: 342
        line 261: 353
        line 264: 374
        line 265: 376
        line 267: 382
        line 269: 398
        line 270: 411
        line 271: 425
        line 267: 436
        line 269: 452
        line 270: 465
        line 271: 479
        line 325: 485
      LocalVariableTable:
        Start  Length  Slot  Name   Signature
            0     488     0  this   Lscala/util/Using$;
            0     488     1 resource1   Ljava/lang/Object;
            0     488     2 resource2   Lscala/Function0;
            0     488     3 resource3   Lscala/Function0;
            0     488     4  body   Lscala/Function3;
            0     488     5 evidence$6   Lscala/util/Using$Releasable;
            0     488     6 evidence$7   Lscala/util/Using$Releasable;
            0     488     7 evidence$8   Lscala/util/Using$Releasable;
          409      12    11 resource_other   Ljava/lang/Throwable;
          463      12    11 resource_other   Ljava/lang/Throwable;
           17     468     8 resource_toThrow   Ljava/lang/Throwable;
          262      13    17 $anonfun$resources$3_resource_other   Ljava/lang/Throwable;
          319      13    17 $anonfun$resources$3_resource_other   Ljava/lang/Throwable;
           48     294    14 $anonfun$resources$3_resource_toThrow   Ljava/lang/Throwable;
           30     312    12 $anonfun$resources$3_resource_this   Lscala/util/Using$;
           30     312    13 $anonfun$resources$3_resource_resource   Ljava/lang/Object;
          131      13    23 $anonfun$resources$3_$anonfun$resources$4_resource_other   Ljava/lang/Throwable;
          188      13    23 $anonfun$resources$3_$anonfun$resources$4_resource_other   Ljava/lang/Throwable;
           79     132    20 $anonfun$resources$3_$anonfun$resources$4_resource_toThrow   Ljava/lang/Throwable;
           61     150    18 $anonfun$resources$3_$anonfun$resources$4_resource_this   Lscala/util/Using$;
           61     150    19 $anonfun$resources$3_$anonfun$resources$4_resource_resource   Ljava/lang/Object;
    Signature: #131                         // <R1:Ljava/lang/Object;R2:Ljava/lang/Object;R3:Ljava/lang/Object;A:Ljava/lang/Object;>(TR1;Lscala/Function0<TR2;>;Lscala/Function0<TR3;>;Lscala/Function3<TR1;TR2;TR3;TA;>;Lscala/util/Using$Releasable<TR1;>;Lscala/util/Using$Releasable<TR2;>;Lscala/util/Using$Releasable<TR3;>;)TA;
    MethodParameters:
      Name                           Flags
      resource1                      final
      resource2                      final
      resource3                      final
      body                           final
      evidence$6                     final
      evidence$7                     final
      evidence$8                     final

  public <R1 extends java.lang.Object, R2 extends java.lang.Object, R3 extends java.lang.Object, R4 extends java.lang.Object, A extends java.lang.Object> A resources(R1, scala.Function0<R2>, scala.Function0<R3>, scala.Function0<R4>, scala.Function4<R1, R2, R3, R4, A>, scala.util.Using$Releasable<R1>, scala.util.Using$Releasable<R2>, scala.util.Using$Releasable<R3>, scala.util.Using$Releasable<R4>);
    descriptor: (Ljava/lang/Object;Lscala/Function0;Lscala/Function0;Lscala/Function0;Lscala/Function4;Lscala/util/Using$Releasable;Lscala/util/Using$Releasable;Lscala/util/Using$Releasable;Lscala/util/Using$Releasable;)Ljava/lang/Object;
    flags: (0x0001) ACC_PUBLIC
    Code:
      stack=5, locals=32, args_size=10
         0: aload_1
         1: ifnonnull     14
         4: new           #92                 // class java/lang/NullPointerException
         7: dup
         8: ldc           #94                 // String null resource
        10: invokespecial #97                 // Method java/lang/NullPointerException."<init>":(Ljava/lang/String;)V
        13: athrow
        14: aconst_null
        15: astore        10
        17: getstatic     #19                 // Field MODULE$:Lscala/util/Using$;
        20: aload_2
        21: invokeinterface #117,  1          // InterfaceMethod scala/Function0.apply:()Ljava/lang/Object;
        26: astore        15
        28: astore        14
        30: aload         15
        32: ifnonnull     45
        35: new           #92                 // class java/lang/NullPointerException
        38: dup
        39: ldc           #94                 // String null resource
        41: invokespecial #97                 // Method java/lang/NullPointerException."<init>":(Ljava/lang/String;)V
        44: athrow
        45: aconst_null
        46: astore        16
        48: getstatic     #19                 // Field MODULE$:Lscala/util/Using$;
        51: aload_3
        52: invokeinterface #117,  1          // InterfaceMethod scala/Function0.apply:()Ljava/lang/Object;
        57: astore        21
        59: astore        20
        61: aload         21
        63: ifnonnull     76
        66: new           #92                 // class java/lang/NullPointerException
        69: dup
        70: ldc           #94                 // String null resource
        72: invokespecial #97                 // Method java/lang/NullPointerException."<init>":(Ljava/lang/String;)V
        75: athrow
        76: aconst_null
        77: astore        22
        79: getstatic     #19                 // Field MODULE$:Lscala/util/Using$;
        82: aload         4
        84: invokeinterface #117,  1          // InterfaceMethod scala/Function0.apply:()Ljava/lang/Object;
        89: astore        27
        91: astore        26
        93: aload         27
        95: ifnonnull     108
        98: new           #92                 // class java/lang/NullPointerException
       101: dup
       102: ldc           #94                 // String null resource
       104: invokespecial #97                 // Method java/lang/NullPointerException."<init>":(Ljava/lang/String;)V
       107: athrow
       108: aconst_null
       109: astore        28
       111: aload         5
       113: aload_1
       114: aload         15
       116: aload         21
       118: aload         27
       120: invokeinterface #161,  5          // InterfaceMethod scala/Function4.apply:(Ljava/lang/Object;Ljava/lang/Object;Ljava/lang/Object;Ljava/lang/Object;)Ljava/lang/Object;
       125: goto          191
       128: astore        28
       130: aconst_null
       131: goto          191
       134: astore        30
       136: aload         28
       138: ifnonnull     153
       141: aload         9
       143: aload         27
       145: invokeinterface #103,  2          // InterfaceMethod scala/util/Using$Releasable.release:(Ljava/lang/Object;)V
       150: goto          188
       153: aload         9
       155: aload         27
       157: invokeinterface #103,  2          // InterfaceMethod scala/util/Using$Releasable.release:(Ljava/lang/Object;)V
       162: goto          185
       165: astore        31
       167: aload         26
       169: aload         28
       171: aload         31
       173: invokevirtual #105                // Method scala$util$Using$$preferentiallySuppress:(Ljava/lang/Throwable;Ljava/lang/Throwable;)Ljava/lang/Throwable;
       176: astore        28
       178: goto          185
       181: pop
       182: aload         28
       184: athrow
       185: aload         28
       187: athrow
       188: aload         30
       190: athrow
       191: astore        29
       193: aload         28
       195: ifnonnull     210
       198: aload         9
       200: aload         27
       202: invokeinterface #103,  2          // InterfaceMethod scala/util/Using$Releasable.release:(Ljava/lang/Object;)V
       207: goto          245
       210: aload         9
       212: aload         27
       214: invokeinterface #103,  2          // InterfaceMethod scala/util/Using$Releasable.release:(Ljava/lang/Object;)V
       219: goto          242
       222: astore        31
       224: aload         26
       226: aload         28
       228: aload         31
       230: invokevirtual #105                // Method scala$util$Using$$preferentiallySuppress:(Ljava/lang/Throwable;Ljava/lang/Throwable;)Ljava/lang/Throwable;
       233: astore        28
       235: goto          242
       238: pop
       239: aload         28
       241: athrow
       242: aload         28
       244: athrow
       245: aload         29
       247: aconst_null
       248: astore        26
       250: aconst_null
       251: astore        27
       253: aconst_null
       254: astore        29
       256: goto          322
       259: astore        22
       261: aconst_null
       262: goto          322
       265: astore        24
       267: aload         22
       269: ifnonnull     284
       272: aload         8
       274: aload         21
       276: invokeinterface #103,  2          // InterfaceMethod scala/util/Using$Releasable.release:(Ljava/lang/Object;)V
       281: goto          319
       284: aload         8
       286: aload         21
       288: invokeinterface #103,  2          // InterfaceMethod scala/util/Using$Releasable.release:(Ljava/lang/Object;)V
       293: goto          316
       296: astore        25
       298: aload         20
       300: aload         22
       302: aload         25
       304: invokevirtual #105                // Method scala$util$Using$$preferentiallySuppress:(Ljava/lang/Throwable;Ljava/lang/Throwable;)Ljava/lang/Throwable;
       307: astore        22
       309: goto          316
       312: pop
       313: aload         22
       315: athrow
       316: aload         22
       318: athrow
       319: aload         24
       321: athrow
       322: astore        23
       324: aload         22
       326: ifnonnull     341
       329: aload         8
       331: aload         21
       333: invokeinterface #103,  2          // InterfaceMethod scala/util/Using$Releasable.release:(Ljava/lang/Object;)V
       338: goto          376
       341: aload         8
       343: aload         21
       345: invokeinterface #103,  2          // InterfaceMethod scala/util/Using$Releasable.release:(Ljava/lang/Object;)V
       350: goto          373
       353: astore        25
       355: aload         20
       357: aload         22
       359: aload         25
       361: invokevirtual #105                // Method scala$util$Using$$preferentiallySuppress:(Ljava/lang/Throwable;Ljava/lang/Throwable;)Ljava/lang/Throwable;
       364: astore        22
       366: goto          373
       369: pop
       370: aload         22
       372: athrow
       373: aload         22
       375: athrow
       376: aload         23
       378: aconst_null
       379: astore        20
       381: aconst_null
       382: astore        21
       384: aconst_null
       385: astore        23
       387: goto          453
       390: astore        16
       392: aconst_null
       393: goto          453
       396: astore        18
       398: aload         16
       400: ifnonnull     415
       403: aload         7
       405: aload         15
       407: invokeinterface #103,  2          // InterfaceMethod scala/util/Using$Releasable.release:(Ljava/lang/Object;)V
       412: goto          450
       415: aload         7
       417: aload         15
       419: invokeinterface #103,  2          // InterfaceMethod scala/util/Using$Releasable.release:(Ljava/lang/Object;)V
       424: goto          447
       427: astore        19
       429: aload         14
       431: aload         16
       433: aload         19
       435: invokevirtual #105                // Method scala$util$Using$$preferentiallySuppress:(Ljava/lang/Throwable;Ljava/lang/Throwable;)Ljava/lang/Throwable;
       438: astore        16
       440: goto          447
       443: pop
       444: aload         16
       446: athrow
       447: aload         16
       449: athrow
       450: aload         18
       452: athrow
       453: astore        17
       455: aload         16
       457: ifnonnull     472
       460: aload         7
       462: aload         15
       464: invokeinterface #103,  2          // InterfaceMethod scala/util/Using$Releasable.release:(Ljava/lang/Object;)V
       469: goto          507
       472: aload         7
       474: aload         15
       476: invokeinterface #103,  2          // InterfaceMethod scala/util/Using$Releasable.release:(Ljava/lang/Object;)V
       481: goto          504
       484: astore        19
       486: aload         14
       488: aload         16
       490: aload         19
       492: invokevirtual #105                // Method scala$util$Using$$preferentiallySuppress:(Ljava/lang/Throwable;Ljava/lang/Throwable;)Ljava/lang/Throwable;
       495: astore        16
       497: goto          504
       500: pop
       501: aload         16
       503: athrow
       504: aload         16
       506: athrow
       507: aload         17
       509: aconst_null
       510: astore        14
       512: aconst_null
       513: astore        15
       515: aconst_null
       516: astore        17
       518: aconst_null
       519: astore        20
       521: aconst_null
       522: astore        21
       524: aconst_null
       525: astore        22
       527: aconst_null
       528: astore        23
       530: aconst_null
       531: astore        24
       533: aconst_null
       534: astore        25
       536: goto          599
       539: astore        10
       541: aconst_null
       542: goto          599
       545: astore        12
       547: aload         10
       549: ifnonnull     563
       552: aload         6
       554: aload_1
       555: invokeinterface #103,  2          // InterfaceMethod scala/util/Using$Releasable.release:(Ljava/lang/Object;)V
       560: goto          596
       563: aload         6
       565: aload_1
       566: invokeinterface #103,  2          // InterfaceMethod scala/util/Using$Releasable.release:(Ljava/lang/Object;)V
       571: goto          593
       574: astore        13
       576: aload_0
       577: aload         10
       579: aload         13
       581: invokevirtual #105                // Method scala$util$Using$$preferentiallySuppress:(Ljava/lang/Throwable;Ljava/lang/Throwable;)Ljava/lang/Throwable;
       584: astore        10
       586: goto          593
       589: pop
       590: aload         10
       592: athrow
       593: aload         10
       595: athrow
       596: aload         12
       598: athrow
       599: astore        11
       601: aload         10
       603: ifnonnull     617
       606: aload         6
       608: aload_1
       609: invokeinterface #103,  2          // InterfaceMethod scala/util/Using$Releasable.release:(Ljava/lang/Object;)V
       614: goto          650
       617: aload         6
       619: aload_1
       620: invokeinterface #103,  2          // InterfaceMethod scala/util/Using$Releasable.release:(Ljava/lang/Object;)V
       625: goto          647
       628: astore        13
       630: aload_0
       631: aload         10
       633: aload         13
       635: invokevirtual #105                // Method scala$util$Using$$preferentiallySuppress:(Ljava/lang/Throwable;Ljava/lang/Throwable;)Ljava/lang/Throwable;
       638: astore        10
       640: goto          647
       643: pop
       644: aload         10
       646: athrow
       647: aload         10
       649: athrow
       650: aload         11
       652: areturn
      Exception table:
         from    to  target type
           111   125   128   Class java/lang/Throwable
           111   134   134   any
           153   162   165   Class java/lang/Throwable
           153   181   181   any
           210   219   222   Class java/lang/Throwable
           210   238   238   any
            79   256   259   Class java/lang/Throwable
            79   265   265   any
           284   293   296   Class java/lang/Throwable
           284   312   312   any
           341   350   353   Class java/lang/Throwable
           341   369   369   any
            48   387   390   Class java/lang/Throwable
            48   396   396   any
           415   424   427   Class java/lang/Throwable
           415   443   443   any
           472   481   484   Class java/lang/Throwable
           472   500   500   any
            17   536   539   Class java/lang/Throwable
            17   545   545   any
           563   571   574   Class java/lang/Throwable
           563   589   589   any
           617   625   628   Class java/lang/Throwable
           617   643   643   any
      StackMapTable: number_of_entries = 56
        frame_type = 14 /* same */
        frame_type = 255 /* full_frame */
          offset_delta = 30
          locals = [ class scala/util/Using$, class java/lang/Object, class scala/Function0, class scala/Function0, class scala/Function0, class scala/Function4, class scala/util/Using$Releasable, class scala/util/Using$Releasable, class scala/util/Using$Releasable, class scala/util/Using$Releasable, null, top, top, top, class scala/util/Using$, class java/lang/Object ]
          stack = []
        frame_type = 255 /* full_frame */
          offset_delta = 30
          locals = [ class scala/util/Using$, class java/lang/Object, class scala/Function0, class scala/Function0, class scala/Function0, class scala/Function4, class scala/util/Using$Releasable, class scala/util/Using$Releasable, class scala/util/Using$Releasable, class scala/util/Using$Releasable, null, top, top, top, class scala/util/Using$, class java/lang/Object, null, top, top, top, class scala/util/Using$, class java/lang/Object ]
          stack = []
        frame_type = 255 /* full_frame */
          offset_delta = 31
          locals = [ class scala/util/Using$, class java/lang/Object, class scala/Function0, class scala/Function0, class scala/Function0, class scala/Function4, class scala/util/Using$Releasable, class scala/util/Using$Releasable, class scala/util/Using$Releasable, class scala/util/Using$Releasable, null, top, top, top, class scala/util/Using$, class java/lang/Object, null, top, top, top, class scala/util/Using$, class java/lang/Object, null, top, top, top, class scala/util/Using$, class java/lang/Object ]
          stack = []
        frame_type = 255 /* full_frame */
          offset_delta = 19
          locals = [ class scala/util/Using$, class java/lang/Object, class scala/Function0, class scala/Function0, class scala/Function0, class scala/Function4, class scala/util/Using$Releasable, class scala/util/Using$Releasable, class scala/util/Using$Releasable, class scala/util/Using$Releasable, null, top, top, top, class scala/util/Using$, class java/lang/Object, null, top, top, top, class scala/util/Using$, class java/lang/Object, null, top, top, top, class scala/util/Using$, class java/lang/Object, null ]
          stack = [ class java/lang/Throwable ]
        frame_type = 255 /* full_frame */
          offset_delta = 5
          locals = [ class scala/util/Using$, class java/lang/Object, class scala/Function0, class scala/Function0, class scala/Function0, class scala/Function4, class scala/util/Using$Releasable, class scala/util/Using$Releasable, class scala/util/Using$Releasable, class scala/util/Using$Releasable, null, top, top, top, class scala/util/Using$, class java/lang/Object, null, top, top, top, class scala/util/Using$, class java/lang/Object, null, top, top, top, class scala/util/Using$, class java/lang/Object, class java/lang/Throwable ]
          stack = [ class java/lang/Throwable ]
        frame_type = 253 /* append */
          offset_delta = 18
          locals = [ top, class java/lang/Throwable ]
        frame_type = 75 /* same_locals_1_stack_item */
          stack = [ class java/lang/Throwable ]
        frame_type = 79 /* same_locals_1_stack_item */
          stack = [ class java/lang/Throwable ]
        frame_type = 3 /* same */
        frame_type = 2 /* same */
        frame_type = 255 /* full_frame */
          offset_delta = 2
          locals = [ class scala/util/Using$, class java/lang/Object, class scala/Function0, class scala/Function0, class scala/Function0, class scala/Function4, class scala/util/Using$Releasable, class scala/util/Using$Releasable, class scala/util/Using$Releasable, class scala/util/Using$Releasable, null, top, top, top, class scala/util/Using$, class java/lang/Object, null, top, top, top, class scala/util/Using$, class java/lang/Object, null, top, top, top, class scala/util/Using$, class java/lang/Object, class java/lang/Throwable ]
          stack = [ class java/lang/Object ]
        frame_type = 252 /* append */
          offset_delta = 18
          locals = [ class java/lang/Object ]
        frame_type = 75 /* same_locals_1_stack_item */
          stack = [ class java/lang/Throwable ]
        frame_type = 79 /* same_locals_1_stack_item */
          stack = [ class java/lang/Throwable ]
        frame_type = 3 /* same */
        frame_type = 2 /* same */
        frame_type = 255 /* full_frame */
          offset_delta = 13
          locals = [ class scala/util/Using$, class java/lang/Object, class scala/Function0, class scala/Function0, class scala/Function0, class scala/Function4, class scala/util/Using$Releasable, class scala/util/Using$Releasable, class scala/util/Using$Releasable, class scala/util/Using$Releasable, null, top, top, top, class scala/util/Using$, class java/lang/Object, null, top, top, top, class scala/util/Using$, class java/lang/Object, null ]
          stack = [ class java/lang/Throwable ]
        frame_type = 255 /* full_frame */
          offset_delta = 5
          locals = [ class scala/util/Using$, class java/lang/Object, class scala/Function0, class scala/Function0, class scala/Function0, class scala/Function4, class scala/util/Using$Releasable, class scala/util/Using$Releasable, class scala/util/Using$Releasable, class scala/util/Using$Releasable, null, top, top, top, class scala/util/Using$, class java/lang/Object, null, top, top, top, class scala/util/Using$, class java/lang/Object, class java/lang/Throwable ]
          stack = [ class java/lang/Throwable ]
        frame_type = 253 /* append */
          offset_delta = 18
          locals = [ top, class java/lang/Throwable ]
        frame_type = 75 /* same_locals_1_stack_item */
          stack = [ class java/lang/Throwable ]
        frame_type = 79 /* same_locals_1_stack_item */
          stack = [ class java/lang/Throwable ]
        frame_type = 3 /* same */
        frame_type = 2 /* same */
        frame_type = 255 /* full_frame */
          offset_delta = 2
          locals = [ class scala/util/Using$, class java/lang/Object, class scala/Function0, class scala/Function0, class scala/Function0, class scala/Function4, class scala/util/Using$Releasable, class scala/util/Using$Releasable, class scala/util/Using$Releasable, class scala/util/Using$Releasable, null, top, top, top, class scala/util/Using$, class java/lang/Object, null, top, top, top, class scala/util/Using$, class java/lang/Object, class java/lang/Throwable ]
          stack = [ class java/lang/Object ]
        frame_type = 252 /* append */
          offset_delta = 18
          locals = [ class java/lang/Object ]
        frame_type = 75 /* same_locals_1_stack_item */
          stack = [ class java/lang/Throwable ]
        frame_type = 79 /* same_locals_1_stack_item */
          stack = [ class java/lang/Throwable ]
        frame_type = 3 /* same */
        frame_type = 2 /* same */
        frame_type = 255 /* full_frame */
          offset_delta = 13
          locals = [ class scala/util/Using$, class java/lang/Object, class scala/Function0, class scala/Function0, class scala/Function0, class scala/Function4, class scala/util/Using$Releasable, class scala/util/Using$Releasable, class scala/util/Using$Releasable, class scala/util/Using$Releasable, null, top, top, top, class scala/util/Using$, class java/lang/Object, null ]
          stack = [ class java/lang/Throwable ]
        frame_type = 255 /* full_frame */
          offset_delta = 5
          locals = [ class scala/util/Using$, class java/lang/Object, class scala/Function0, class scala/Function0, class scala/Function0, class scala/Function4, class scala/util/Using$Releasable, class scala/util/Using$Releasable, class scala/util/Using$Releasable, class scala/util/Using$Releasable, null, top, top, top, class scala/util/Using$, class java/lang/Object, class java/lang/Throwable ]
          stack = [ class java/lang/Throwable ]
        frame_type = 253 /* append */
          offset_delta = 18
          locals = [ top, class java/lang/Throwable ]
        frame_type = 75 /* same_locals_1_stack_item */
          stack = [ class java/lang/Throwable ]
        frame_type = 79 /* same_locals_1_stack_item */
          stack = [ class java/lang/Throwable ]
        frame_type = 3 /* same */
        frame_type = 2 /* same */
        frame_type = 255 /* full_frame */
          offset_delta = 2
          locals = [ class scala/util/Using$, class java/lang/Object, class scala/Function0, class scala/Function0, class scala/Function0, class scala/Function4, class scala/util/Using$Releasable, class scala/util/Using$Releasable, class scala/util/Using$Releasable, class scala/util/Using$Releasable, null, top, top, top, class scala/util/Using$, class java/lang/Object, class java/lang/Throwable ]
          stack = [ class java/lang/Object ]
        frame_type = 252 /* append */
          offset_delta = 18
          locals = [ class java/lang/Object ]
        frame_type = 75 /* same_locals_1_stack_item */
          stack = [ class java/lang/Throwable ]
        frame_type = 79 /* same_locals_1_stack_item */
          stack = [ class java/lang/Throwable ]
        frame_type = 3 /* same */
        frame_type = 2 /* same */
        frame_type = 255 /* full_frame */
          offset_delta = 31
          locals = [ class scala/util/Using$, class java/lang/Object, class scala/Function0, class scala/Function0, class scala/Function0, class scala/Function4, class scala/util/Using$Releasable, class scala/util/Using$Releasable, class scala/util/Using$Releasable, class scala/util/Using$Releasable, null ]
          stack = [ class java/lang/Throwable ]
        frame_type = 255 /* full_frame */
          offset_delta = 5
          locals = [ class scala/util/Using$, class java/lang/Object, class scala/Function0, class scala/Function0, class scala/Function0, class scala/Function4, class scala/util/Using$Releasable, class scala/util/Using$Releasable, class scala/util/Using$Releasable, class scala/util/Using$Releasable, class java/lang/Throwable ]
          stack = [ class java/lang/Throwable ]
        frame_type = 253 /* append */
          offset_delta = 17
          locals = [ top, class java/lang/Throwable ]
        frame_type = 74 /* same_locals_1_stack_item */
          stack = [ class java/lang/Throwable ]
        frame_type = 78 /* same_locals_1_stack_item */
          stack = [ class java/lang/Throwable ]
        frame_type = 3 /* same */
        frame_type = 2 /* same */
        frame_type = 255 /* full_frame */
          offset_delta = 2
          locals = [ class scala/util/Using$, class java/lang/Object, class scala/Function0, class scala/Function0, class scala/Function0, class scala/Function4, class scala/util/Using$Releasable, class scala/util/Using$Releasable, class scala/util/Using$Releasable, class scala/util/Using$Releasable, class java/lang/Throwable ]
          stack = [ class java/lang/Object ]
        frame_type = 252 /* append */
          offset_delta = 17
          locals = [ class java/lang/Object ]
        frame_type = 74 /* same_locals_1_stack_item */
          stack = [ class java/lang/Throwable ]
        frame_type = 78 /* same_locals_1_stack_item */
          stack = [ class java/lang/Throwable ]
        frame_type = 3 /* same */
        frame_type = 2 /* same */
      LineNumberTable:
        line 257: 0
        line 259: 14
        line 360: 17
        line 257: 30
        line 259: 45
        line 361: 48
        line 257: 61
        line 259: 76
        line 362: 79
        line 257: 93
        line 259: 108
        line 363: 111
        line 261: 125
        line 264: 128
        line 265: 130
        line 267: 136
        line 269: 153
        line 270: 167
        line 271: 182
        line 267: 193
        line 269: 210
        line 270: 224
        line 271: 239
        line 362: 245
        line 261: 256
        line 264: 259
        line 265: 261
        line 267: 267
        line 269: 284
        line 270: 298
        line 271: 313
        line 267: 324
        line 269: 341
        line 270: 355
        line 271: 370
        line 361: 376
        line 261: 387
        line 264: 390
        line 265: 392
        line 267: 398
        line 269: 415
        line 270: 429
        line 271: 444
        line 267: 455
        line 269: 472
        line 270: 486
        line 271: 501
        line 360: 507
        line 261: 518
        line 264: 539
        line 265: 541
        line 267: 547
        line 269: 563
        line 270: 576
        line 271: 590
        line 267: 601
        line 269: 617
        line 270: 630
        line 271: 644
        line 359: 650
      LocalVariableTable:
        Start  Length  Slot  Name   Signature
            0     653     0  this   Lscala/util/Using$;
            0     653     1 resource1   Ljava/lang/Object;
            0     653     2 resource2   Lscala/Function0;
            0     653     3 resource3   Lscala/Function0;
            0     653     4 resource4   Lscala/Function0;
            0     653     5  body   Lscala/Function4;
            0     653     6 evidence$9   Lscala/util/Using$Releasable;
            0     653     7 evidence$10   Lscala/util/Using$Releasable;
            0     653     8 evidence$11   Lscala/util/Using$Releasable;
            0     653     9 evidence$12   Lscala/util/Using$Releasable;
          574      12    13 resource_other   Ljava/lang/Throwable;
          628      12    13 resource_other   Ljava/lang/Throwable;
           17     633    10 resource_toThrow   Ljava/lang/Throwable;
          427      13    19 $anonfun$resources$6_resource_other   Ljava/lang/Throwable;
          484      13    19 $anonfun$resources$6_resource_other   Ljava/lang/Throwable;
           48     459    16 $anonfun$resources$6_resource_toThrow   Ljava/lang/Throwable;
           30     477    14 $anonfun$resources$6_resource_this   Lscala/util/Using$;
           30     477    15 $anonfun$resources$6_resource_resource   Ljava/lang/Object;
          296      13    25 $anonfun$resources$6_$anonfun$resources$7_resource_other   Ljava/lang/Throwable;
          353      13    25 $anonfun$resources$6_$anonfun$resources$7_resource_other   Ljava/lang/Throwable;
           79     297    22 $anonfun$resources$6_$anonfun$resources$7_resource_toThrow   Ljava/lang/Throwable;
           61     315    20 $anonfun$resources$6_$anonfun$resources$7_resource_this   Lscala/util/Using$;
           61     315    21 $anonfun$resources$6_$anonfun$resources$7_resource_resource   Ljava/lang/Object;
          165      13    31 $anonfun$resources$8_resource_other   Ljava/lang/Throwable;
          222      13    31 $anonfun$resources$8_resource_other   Ljava/lang/Throwable;
          111     134    28 $anonfun$resources$8_resource_toThrow   Ljava/lang/Throwable;
           93     152    26 $anonfun$resources$8_resource_this   Lscala/util/Using$;
           93     152    27 $anonfun$resources$8_resource_resource   Ljava/lang/Object;
    Signature: #151                         // <R1:Ljava/lang/Object;R2:Ljava/lang/Object;R3:Ljava/lang/Object;R4:Ljava/lang/Object;A:Ljava/lang/Object;>(TR1;Lscala/Function0<TR2;>;Lscala/Function0<TR3;>;Lscala/Function0<TR4;>;Lscala/Function4<TR1;TR2;TR3;TR4;TA;>;Lscala/util/Using$Releasable<TR1;>;Lscala/util/Using$Releasable<TR2;>;Lscala/util/Using$Releasable<TR3;>;Lscala/util/Using$Releasable<TR4;>;)TA;
    MethodParameters:
      Name                           Flags
      resource1                      final
      resource2                      final
      resource3                      final
      resource4                      final
      body                           final
      evidence$9                     final
      evidence$10                    final
      evidence$11                    final
      evidence$12                    final

  public static final java.lang.Object $anonfun$apply$1(scala.Function0, scala.Function1, scala.util.Using$Releasable);
    descriptor: (Lscala/Function0;Lscala/Function1;Lscala/util/Using$Releasable;)Ljava/lang/Object;
    flags: (0x1019) ACC_PUBLIC, ACC_STATIC, ACC_FINAL, ACC_SYNTHETIC
    Code:
      stack=3, locals=9, args_size=3
         0: getstatic     #19                 // Field MODULE$:Lscala/util/Using$;
         3: aload_0
         4: invokeinterface #117,  1          // InterfaceMethod scala/Function0.apply:()Ljava/lang/Object;
         9: astore        4
        11: astore_3
        12: aload         4
        14: ifnonnull     27
        17: new           #92                 // class java/lang/NullPointerException
        20: dup
        21: ldc           #94                 // String null resource
        23: invokespecial #97                 // Method java/lang/NullPointerException."<init>":(Ljava/lang/String;)V
        26: athrow
        27: aconst_null
        28: astore        5
        30: aload_1
        31: aload         4
        33: invokeinterface #100,  2          // InterfaceMethod scala/Function1.apply:(Ljava/lang/Object;)Ljava/lang/Object;
        38: goto          101
        41: astore        5
        43: aconst_null
        44: goto          101
        47: astore        7
        49: aload         5
        51: ifnonnull     65
        54: aload_2
        55: aload         4
        57: invokeinterface #103,  2          // InterfaceMethod scala/util/Using$Releasable.release:(Ljava/lang/Object;)V
        62: goto          98
        65: aload_2
        66: aload         4
        68: invokeinterface #103,  2          // InterfaceMethod scala/util/Using$Releasable.release:(Ljava/lang/Object;)V
        73: goto          95
        76: astore        8
        78: aload_3
        79: aload         5
        81: aload         8
        83: invokevirtual #105                // Method scala$util$Using$$preferentiallySuppress:(Ljava/lang/Throwable;Ljava/lang/Throwable;)Ljava/lang/Throwable;
        86: astore        5
        88: goto          95
        91: pop
        92: aload         5
        94: athrow
        95: aload         5
        97: athrow
        98: aload         7
       100: athrow
       101: astore        6
       103: aload         5
       105: ifnonnull     119
       108: aload_2
       109: aload         4
       111: invokeinterface #103,  2          // InterfaceMethod scala/util/Using$Releasable.release:(Ljava/lang/Object;)V
       116: goto          152
       119: aload_2
       120: aload         4
       122: invokeinterface #103,  2          // InterfaceMethod scala/util/Using$Releasable.release:(Ljava/lang/Object;)V
       127: goto          149
       130: astore        8
       132: aload_3
       133: aload         5
       135: aload         8
       137: invokevirtual #105                // Method scala$util$Using$$preferentiallySuppress:(Ljava/lang/Throwable;Ljava/lang/Throwable;)Ljava/lang/Throwable;
       140: astore        5
       142: goto          149
       145: pop
       146: aload         5
       148: athrow
       149: aload         5
       151: athrow
       152: aload         6
       154: areturn
      Exception table:
         from    to  target type
            30    38    41   Class java/lang/Throwable
            30    47    47   any
            65    73    76   Class java/lang/Throwable
            65    91    91   any
           119   127   130   Class java/lang/Throwable
           119   145   145   any
      StackMapTable: number_of_entries = 14
        frame_type = 253 /* append */
          offset_delta = 27
          locals = [ class scala/util/Using$, class java/lang/Object ]
        frame_type = 255 /* full_frame */
          offset_delta = 13
          locals = [ class scala/Function0, class scala/Function1, class scala/util/Using$Releasable, class scala/util/Using$, class java/lang/Object, null ]
          stack = [ class java/lang/Throwable ]
        frame_type = 255 /* full_frame */
          offset_delta = 5
          locals = [ class scala/Function0, class scala/Function1, class scala/util/Using$Releasable, class scala/util/Using$, class java/lang/Object, class java/lang/Throwable ]
          stack = [ class java/lang/Throwable ]
        frame_type = 253 /* append */
          offset_delta = 17
          locals = [ top, class java/lang/Throwable ]
        frame_type = 74 /* same_locals_1_stack_item */
          stack = [ class java/lang/Throwable ]
        frame_type = 78 /* same_locals_1_stack_item */
          stack = [ class java/lang/Throwable ]
        frame_type = 3 /* same */
        frame_type = 2 /* same */
        frame_type = 255 /* full_frame */
          offset_delta = 2
          locals = [ class scala/Function0, class scala/Function1, class scala/util/Using$Releasable, class scala/util/Using$, class java/lang/Object, class java/lang/Throwable ]
          stack = [ class java/lang/Object ]
        frame_type = 252 /* append */
          offset_delta = 17
          locals = [ class java/lang/Object ]
        frame_type = 74 /* same_locals_1_stack_item */
          stack = [ class java/lang/Throwable ]
        frame_type = 78 /* same_locals_1_stack_item */
          stack = [ class java/lang/Throwable ]
        frame_type = 3 /* same */
        frame_type = 2 /* same */
      LineNumberTable:
        line 113: 0
        line 257: 12
        line 259: 27
        line 261: 30
        line 264: 41
        line 265: 43
        line 267: 49
        line 269: 65
        line 270: 78
        line 271: 92
        line 267: 103
        line 269: 119
        line 270: 132
        line 271: 146
        line 113: 152
      LocalVariableTable:
        Start  Length  Slot  Name   Signature
            0     155     0 resource$1   Lscala/Function0;
            0     155     1   f$1   Lscala/Function1;
            0     155     2 evidence$1$1   Lscala/util/Using$Releasable;
           76      12     8 resource_other   Ljava/lang/Throwable;
          130      12     8 resource_other   Ljava/lang/Throwable;
           30     122     5 resource_toThrow   Ljava/lang/Throwable;
           12     140     3 resource_this   Lscala/util/Using$;
           12     140     4 resource_resource   Ljava/lang/Object;
    MethodParameters:
      Name                           Flags
      resource$1                     final
      f$1                            final
      evidence$1$1                   final

  private static final int score$1(java.lang.Throwable);
    descriptor: (Ljava/lang/Throwable;)I
    flags: (0x001a) ACC_PRIVATE, ACC_STATIC, ACC_FINAL
    Code:
      stack=2, locals=3, args_size=1
         0: aload_0
         1: instanceof    #182                // class java/lang/VirtualMachineError
         4: ifeq          12
         7: iconst_4
         8: istore_1
         9: goto          88
        12: aload_0
        13: instanceof    #184                // class java/lang/LinkageError
        16: ifeq          24
        19: iconst_3
        20: istore_1
        21: goto          88
        24: aload_0
        25: instanceof    #186                // class java/lang/InterruptedException
        28: ifeq          36
        31: iconst_1
        32: istore_2
        33: goto          50
        36: aload_0
        37: instanceof    #188                // class java/lang/ThreadDeath
        40: ifeq          48
        43: iconst_1
        44: istore_2
        45: goto          50
        48: iconst_0
        49: istore_2
        50: iload_2
        51: ifeq          59
        54: iconst_2
        55: istore_1
        56: goto          88
        59: aload_0
        60: instanceof    #190                // class scala/util/control/ControlThrowable
        63: ifeq          71
        66: iconst_0
        67: istore_1
        68: goto          88
        71: getstatic     #46                 // Field scala/util/control/NonFatal$.MODULE$:Lscala/util/control/NonFatal$;
        74: aload_0
        75: invokevirtual #193                // Method scala/util/control/NonFatal$.apply:(Ljava/lang/Throwable;)Z
        78: ifne          86
        81: iconst_1
        82: istore_1
        83: goto          88
        86: iconst_m1
        87: istore_1
        88: iload_1
        89: ireturn
      StackMapTable: number_of_entries = 9
        frame_type = 12 /* same */
        frame_type = 11 /* same */
        frame_type = 11 /* same */
        frame_type = 11 /* same */
        frame_type = 253 /* append */
          offset_delta = 1
          locals = [ top, int ]
        frame_type = 8 /* same */
        frame_type = 11 /* same */
        frame_type = 14 /* same */
        frame_type = 255 /* full_frame */
          offset_delta = 1
          locals = [ class java/lang/Throwable, int ]
          stack = []
      LineNumberTable:
        line 230: 0
        line 231: 12
        line 232: 24
        line 233: 59
        line 234: 71
        line 235: 86
        line 229: 88
      LocalVariableTable:
        Start  Length  Slot  Name   Signature
            0      90     0     t   Ljava/lang/Throwable;
    MethodParameters:
      Name                           Flags
      t                              final

  private static final java.lang.Throwable suppress$1(java.lang.Throwable, java.lang.Throwable);
    descriptor: (Ljava/lang/Throwable;Ljava/lang/Throwable;)Ljava/lang/Throwable;
    flags: (0x001a) ACC_PRIVATE, ACC_STATIC, ACC_FINAL
    Code:
      stack=2, locals=2, args_size=2
         0: aload_0
         1: aload_1
         2: invokevirtual #86                 // Method java/lang/Throwable.addSuppressed:(Ljava/lang/Throwable;)V
         5: aload_0
         6: areturn
      LineNumberTable:
        line 237: 0
      LocalVariableTable:
        Start  Length  Slot  Name   Signature
            0       7     0     t   Ljava/lang/Throwable;
            0       7     1 suppressed   Ljava/lang/Throwable;
    MethodParameters:
      Name                           Flags
      t                              final
      suppressed                     final

  public static final java.lang.Object $anonfun$resources$2(scala.Function2, java.lang.Object, java.lang.Object);
    descriptor: (Lscala/Function2;Ljava/lang/Object;Ljava/lang/Object;)Ljava/lang/Object;
    flags: (0x1019) ACC_PUBLIC, ACC_STATIC, ACC_FINAL, ACC_SYNTHETIC
    Code:
      stack=3, locals=3, args_size=3
         0: aload_0
         1: aload_1
         2: aload_2
         3: invokeinterface #122,  3          // InterfaceMethod scala/Function2.apply:(Ljava/lang/Object;Ljava/lang/Object;)Ljava/lang/Object;
         8: areturn
      LineNumberTable:
        line 298: 0
      LocalVariableTable:
        Start  Length  Slot  Name   Signature
            0       9     0 body$1   Lscala/Function2;
            0       9     1  r1$1   Ljava/lang/Object;
            0       9     2    r2   Ljava/lang/Object;
    MethodParameters:
      Name                           Flags
      body$1                         final
      r1$1                           final
      r2                             final

  public static final java.lang.Object $anonfun$resources$1(scala.Function0, scala.Function2, scala.util.Using$Releasable, java.lang.Object);
    descriptor: (Lscala/Function0;Lscala/Function2;Lscala/util/Using$Releasable;Ljava/lang/Object;)Ljava/lang/Object;
    flags: (0x1019) ACC_PUBLIC, ACC_STATIC, ACC_FINAL, ACC_SYNTHETIC
    Code:
      stack=3, locals=10, args_size=4
         0: getstatic     #19                 // Field MODULE$:Lscala/util/Using$;
         3: aload_0
         4: invokeinterface #117,  1          // InterfaceMethod scala/Function0.apply:()Ljava/lang/Object;
         9: astore        5
        11: astore        4
        13: aload         5
        15: ifnonnull     28
        18: new           #92                 // class java/lang/NullPointerException
        21: dup
        22: ldc           #94                 // String null resource
        24: invokespecial #97                 // Method java/lang/NullPointerException."<init>":(Ljava/lang/String;)V
        27: athrow
        28: aconst_null
        29: astore        6
        31: aload_1
        32: aload_3
        33: aload         5
        35: invokeinterface #122,  3          // InterfaceMethod scala/Function2.apply:(Ljava/lang/Object;Ljava/lang/Object;)Ljava/lang/Object;
        40: goto          104
        43: astore        6
        45: aconst_null
        46: goto          104
        49: astore        8
        51: aload         6
        53: ifnonnull     67
        56: aload_2
        57: aload         5
        59: invokeinterface #103,  2          // InterfaceMethod scala/util/Using$Releasable.release:(Ljava/lang/Object;)V
        64: goto          101
        67: aload_2
        68: aload         5
        70: invokeinterface #103,  2          // InterfaceMethod scala/util/Using$Releasable.release:(Ljava/lang/Object;)V
        75: goto          98
        78: astore        9
        80: aload         4
        82: aload         6
        84: aload         9
        86: invokevirtual #105                // Method scala$util$Using$$preferentiallySuppress:(Ljava/lang/Throwable;Ljava/lang/Throwable;)Ljava/lang/Throwable;
        89: astore        6
        91: goto          98
        94: pop
        95: aload         6
        97: athrow
        98: aload         6
       100: athrow
       101: aload         8
       103: athrow
       104: astore        7
       106: aload         6
       108: ifnonnull     122
       111: aload_2
       112: aload         5
       114: invokeinterface #103,  2          // InterfaceMethod scala/util/Using$Releasable.release:(Ljava/lang/Object;)V
       119: goto          156
       122: aload_2
       123: aload         5
       125: invokeinterface #103,  2          // InterfaceMethod scala/util/Using$Releasable.release:(Ljava/lang/Object;)V
       130: goto          153
       133: astore        9
       135: aload         4
       137: aload         6
       139: aload         9
       141: invokevirtual #105                // Method scala$util$Using$$preferentiallySuppress:(Ljava/lang/Throwable;Ljava/lang/Throwable;)Ljava/lang/Throwable;
       144: astore        6
       146: goto          153
       149: pop
       150: aload         6
       152: athrow
       153: aload         6
       155: athrow
       156: aload         7
       158: areturn
      Exception table:
         from    to  target type
            31    40    43   Class java/lang/Throwable
            31    49    49   any
            67    75    78   Class java/lang/Throwable
            67    94    94   any
           122   130   133   Class java/lang/Throwable
           122   149   149   any
      StackMapTable: number_of_entries = 14
        frame_type = 253 /* append */
          offset_delta = 28
          locals = [ class scala/util/Using$, class java/lang/Object ]
        frame_type = 255 /* full_frame */
          offset_delta = 14
          locals = [ class scala/Function0, class scala/Function2, class scala/util/Using$Releasable, class java/lang/Object, class scala/util/Using$, class java/lang/Object, null ]
          stack = [ class java/lang/Throwable ]
        frame_type = 255 /* full_frame */
          offset_delta = 5
          locals = [ class scala/Function0, class scala/Function2, class scala/util/Using$Releasable, class java/lang/Object, class scala/util/Using$, class java/lang/Object, class java/lang/Throwable ]
          stack = [ class java/lang/Throwable ]
        frame_type = 253 /* append */
          offset_delta = 17
          locals = [ top, class java/lang/Throwable ]
        frame_type = 74 /* same_locals_1_stack_item */
          stack = [ class java/lang/Throwable ]
        frame_type = 79 /* same_locals_1_stack_item */
          stack = [ class java/lang/Throwable ]
        frame_type = 3 /* same */
        frame_type = 2 /* same */
        frame_type = 255 /* full_frame */
          offset_delta = 2
          locals = [ class scala/Function0, class scala/Function2, class scala/util/Using$Releasable, class java/lang/Object, class scala/util/Using$, class java/lang/Object, class java/lang/Throwable ]
          stack = [ class java/lang/Object ]
        frame_type = 252 /* append */
          offset_delta = 17
          locals = [ class java/lang/Object ]
        frame_type = 74 /* same_locals_1_stack_item */
          stack = [ class java/lang/Throwable ]
        frame_type = 79 /* same_locals_1_stack_item */
          stack = [ class java/lang/Throwable ]
        frame_type = 3 /* same */
        frame_type = 2 /* same */
      LineNumberTable:
        line 297: 0
        line 257: 13
        line 259: 28
        line 298: 31
        line 261: 40
        line 264: 43
        line 265: 45
        line 267: 51
        line 269: 67
        line 270: 80
        line 271: 95
        line 267: 106
        line 269: 122
        line 270: 135
        line 271: 150
        line 297: 156
      LocalVariableTable:
        Start  Length  Slot  Name   Signature
            0     159     0 resource2$1   Lscala/Function0;
            0     159     1 body$1   Lscala/Function2;
            0     159     2 evidence$5$1   Lscala/util/Using$Releasable;
            0     159     3    r1   Ljava/lang/Object;
           78      13     9 resource_other   Ljava/lang/Throwable;
          133      13     9 resource_other   Ljava/lang/Throwable;
           31     125     6 resource_toThrow   Ljava/lang/Throwable;
           13     143     4 resource_this   Lscala/util/Using$;
           13     143     5 resource_resource   Ljava/lang/Object;
    MethodParameters:
      Name                           Flags
      resource2$1                    final
      body$1                         final
      evidence$5$1                   final
      r1                             final

  public static final java.lang.Object $anonfun$resources$5(scala.Function3, java.lang.Object, java.lang.Object, java.lang.Object);
    descriptor: (Lscala/Function3;Ljava/lang/Object;Ljava/lang/Object;Ljava/lang/Object;)Ljava/lang/Object;
    flags: (0x1019) ACC_PUBLIC, ACC_STATIC, ACC_FINAL, ACC_SYNTHETIC
    Code:
      stack=4, locals=4, args_size=4
         0: aload_0
         1: aload_1
         2: aload_2
         3: aload_3
         4: invokeinterface #140,  4          // InterfaceMethod scala/Function3.apply:(Ljava/lang/Object;Ljava/lang/Object;Ljava/lang/Object;)Ljava/lang/Object;
         9: areturn
      LineNumberTable:
        line 328: 0
      LocalVariableTable:
        Start  Length  Slot  Name   Signature
            0      10     0 body$2   Lscala/Function3;
            0      10     1  r1$2   Ljava/lang/Object;
            0      10     2  r2$1   Ljava/lang/Object;
            0      10     3    r3   Ljava/lang/Object;
    MethodParameters:
      Name                           Flags
      body$2                         final
      r1$2                           final
      r2$1                           final
      r3                             final

  public static final java.lang.Object $anonfun$resources$4(scala.Function0, scala.Function3, java.lang.Object, scala.util.Using$Releasable, java.lang.Object);
    descriptor: (Lscala/Function0;Lscala/Function3;Ljava/lang/Object;Lscala/util/Using$Releasable;Ljava/lang/Object;)Ljava/lang/Object;
    flags: (0x1019) ACC_PUBLIC, ACC_STATIC, ACC_FINAL, ACC_SYNTHETIC
    Code:
      stack=4, locals=11, args_size=5
         0: getstatic     #19                 // Field MODULE$:Lscala/util/Using$;
         3: aload_0
         4: invokeinterface #117,  1          // InterfaceMethod scala/Function0.apply:()Ljava/lang/Object;
         9: astore        6
        11: astore        5
        13: aload         6
        15: ifnonnull     28
        18: new           #92                 // class java/lang/NullPointerException
        21: dup
        22: ldc           #94                 // String null resource
        24: invokespecial #97                 // Method java/lang/NullPointerException."<init>":(Ljava/lang/String;)V
        27: athrow
        28: aconst_null
        29: astore        7
        31: aload_1
        32: aload_2
        33: aload         4
        35: aload         6
        37: invokeinterface #140,  4          // InterfaceMethod scala/Function3.apply:(Ljava/lang/Object;Ljava/lang/Object;Ljava/lang/Object;)Ljava/lang/Object;
        42: goto          106
        45: astore        7
        47: aconst_null
        48: goto          106
        51: astore        9
        53: aload         7
        55: ifnonnull     69
        58: aload_3
        59: aload         6
        61: invokeinterface #103,  2          // InterfaceMethod scala/util/Using$Releasable.release:(Ljava/lang/Object;)V
        66: goto          103
        69: aload_3
        70: aload         6
        72: invokeinterface #103,  2          // InterfaceMethod scala/util/Using$Releasable.release:(Ljava/lang/Object;)V
        77: goto          100
        80: astore        10
        82: aload         5
        84: aload         7
        86: aload         10
        88: invokevirtual #105                // Method scala$util$Using$$preferentiallySuppress:(Ljava/lang/Throwable;Ljava/lang/Throwable;)Ljava/lang/Throwable;
        91: astore        7
        93: goto          100
        96: pop
        97: aload         7
        99: athrow
       100: aload         7
       102: athrow
       103: aload         9
       105: athrow
       106: astore        8
       108: aload         7
       110: ifnonnull     124
       113: aload_3
       114: aload         6
       116: invokeinterface #103,  2          // InterfaceMethod scala/util/Using$Releasable.release:(Ljava/lang/Object;)V
       121: goto          158
       124: aload_3
       125: aload         6
       127: invokeinterface #103,  2          // InterfaceMethod scala/util/Using$Releasable.release:(Ljava/lang/Object;)V
       132: goto          155
       135: astore        10
       137: aload         5
       139: aload         7
       141: aload         10
       143: invokevirtual #105                // Method scala$util$Using$$preferentiallySuppress:(Ljava/lang/Throwable;Ljava/lang/Throwable;)Ljava/lang/Throwable;
       146: astore        7
       148: goto          155
       151: pop
       152: aload         7
       154: athrow
       155: aload         7
       157: athrow
       158: aload         8
       160: areturn
      Exception table:
         from    to  target type
            31    42    45   Class java/lang/Throwable
            31    51    51   any
            69    77    80   Class java/lang/Throwable
            69    96    96   any
           124   132   135   Class java/lang/Throwable
           124   151   151   any
      StackMapTable: number_of_entries = 14
        frame_type = 253 /* append */
          offset_delta = 28
          locals = [ class scala/util/Using$, class java/lang/Object ]
        frame_type = 255 /* full_frame */
          offset_delta = 16
          locals = [ class scala/Function0, class scala/Function3, class java/lang/Object, class scala/util/Using$Releasable, class java/lang/Object, class scala/util/Using$, class java/lang/Object, null ]
          stack = [ class java/lang/Throwable ]
        frame_type = 255 /* full_frame */
          offset_delta = 5
          locals = [ class scala/Function0, class scala/Function3, class java/lang/Object, class scala/util/Using$Releasable, class java/lang/Object, class scala/util/Using$, class java/lang/Object, class java/lang/Throwable ]
          stack = [ class java/lang/Throwable ]
        frame_type = 253 /* append */
          offset_delta = 17
          locals = [ top, class java/lang/Throwable ]
        frame_type = 74 /* same_locals_1_stack_item */
          stack = [ class java/lang/Throwable ]
        frame_type = 79 /* same_locals_1_stack_item */
          stack = [ class java/lang/Throwable ]
        frame_type = 3 /* same */
        frame_type = 2 /* same */
        frame_type = 255 /* full_frame */
          offset_delta = 2
          locals = [ class scala/Function0, class scala/Function3, class java/lang/Object, class scala/util/Using$Releasable, class java/lang/Object, class scala/util/Using$, class java/lang/Object, class java/lang/Throwable ]
          stack = [ class java/lang/Object ]
        frame_type = 252 /* append */
          offset_delta = 17
          locals = [ class java/lang/Object ]
        frame_type = 74 /* same_locals_1_stack_item */
          stack = [ class java/lang/Throwable ]
        frame_type = 79 /* same_locals_1_stack_item */
          stack = [ class java/lang/Throwable ]
        frame_type = 3 /* same */
        frame_type = 2 /* same */
      LineNumberTable:
        line 327: 0
        line 257: 13
        line 259: 28
        line 328: 31
        line 261: 42
        line 264: 45
        line 265: 47
        line 267: 53
        line 269: 69
        line 270: 82
        line 271: 97
        line 267: 108
        line 269: 124
        line 270: 137
        line 271: 152
        line 327: 158
      LocalVariableTable:
        Start  Length  Slot  Name   Signature
            0     161     0 resource3$1   Lscala/Function0;
            0     161     1 body$2   Lscala/Function3;
            0     161     2  r1$2   Ljava/lang/Object;
            0     161     3 evidence$8$1   Lscala/util/Using$Releasable;
            0     161     4    r2   Ljava/lang/Object;
           80      13    10 resource_other   Ljava/lang/Throwable;
          135      13    10 resource_other   Ljava/lang/Throwable;
           31     127     7 resource_toThrow   Ljava/lang/Throwable;
           13     145     5 resource_this   Lscala/util/Using$;
           13     145     6 resource_resource   Ljava/lang/Object;
    MethodParameters:
      Name                           Flags
      resource3$1                    final
      body$2                         final
      r1$2                           final
      evidence$8$1                   final
      r2                             final

  public static final java.lang.Object $anonfun$resources$3(scala.Function0, scala.Function0, scala.Function3, scala.util.Using$Releasable, scala.util.Using$Releasable, java.lang.Object);
    descriptor: (Lscala/Function0;Lscala/Function0;Lscala/Function3;Lscala/util/Using$Releasable;Lscala/util/Using$Releasable;Ljava/lang/Object;)Ljava/lang/Object;
    flags: (0x1019) ACC_PUBLIC, ACC_STATIC, ACC_FINAL, ACC_SYNTHETIC
    Code:
      stack=4, locals=18, args_size=6
         0: getstatic     #19                 // Field MODULE$:Lscala/util/Using$;
         3: aload_0
         4: invokeinterface #117,  1          // InterfaceMethod scala/Function0.apply:()Ljava/lang/Object;
         9: astore        7
        11: astore        6
        13: aload         7
        15: ifnonnull     28
        18: new           #92                 // class java/lang/NullPointerException
        21: dup
        22: ldc           #94                 // String null resource
        24: invokespecial #97                 // Method java/lang/NullPointerException."<init>":(Ljava/lang/String;)V
        27: athrow
        28: aconst_null
        29: astore        8
        31: getstatic     #19                 // Field MODULE$:Lscala/util/Using$;
        34: aload_1
        35: invokeinterface #117,  1          // InterfaceMethod scala/Function0.apply:()Ljava/lang/Object;
        40: astore        13
        42: astore        12
        44: aload         13
        46: ifnonnull     59
        49: new           #92                 // class java/lang/NullPointerException
        52: dup
        53: ldc           #94                 // String null resource
        55: invokespecial #97                 // Method java/lang/NullPointerException."<init>":(Ljava/lang/String;)V
        58: athrow
        59: aconst_null
        60: astore        14
        62: aload_2
        63: aload         5
        65: aload         7
        67: aload         13
        69: invokeinterface #140,  4          // InterfaceMethod scala/Function3.apply:(Ljava/lang/Object;Ljava/lang/Object;Ljava/lang/Object;)Ljava/lang/Object;
        74: goto          138
        77: astore        14
        79: aconst_null
        80: goto          138
        83: astore        16
        85: aload         14
        87: ifnonnull     101
        90: aload_3
        91: aload         13
        93: invokeinterface #103,  2          // InterfaceMethod scala/util/Using$Releasable.release:(Ljava/lang/Object;)V
        98: goto          135
       101: aload_3
       102: aload         13
       104: invokeinterface #103,  2          // InterfaceMethod scala/util/Using$Releasable.release:(Ljava/lang/Object;)V
       109: goto          132
       112: astore        17
       114: aload         12
       116: aload         14
       118: aload         17
       120: invokevirtual #105                // Method scala$util$Using$$preferentiallySuppress:(Ljava/lang/Throwable;Ljava/lang/Throwable;)Ljava/lang/Throwable;
       123: astore        14
       125: goto          132
       128: pop
       129: aload         14
       131: athrow
       132: aload         14
       134: athrow
       135: aload         16
       137: athrow
       138: astore        15
       140: aload         14
       142: ifnonnull     156
       145: aload_3
       146: aload         13
       148: invokeinterface #103,  2          // InterfaceMethod scala/util/Using$Releasable.release:(Ljava/lang/Object;)V
       153: goto          190
       156: aload_3
       157: aload         13
       159: invokeinterface #103,  2          // InterfaceMethod scala/util/Using$Releasable.release:(Ljava/lang/Object;)V
       164: goto          187
       167: astore        17
       169: aload         12
       171: aload         14
       173: aload         17
       175: invokevirtual #105                // Method scala$util$Using$$preferentiallySuppress:(Ljava/lang/Throwable;Ljava/lang/Throwable;)Ljava/lang/Throwable;
       178: astore        14
       180: goto          187
       183: pop
       184: aload         14
       186: athrow
       187: aload         14
       189: athrow
       190: aload         15
       192: aconst_null
       193: astore        12
       195: aconst_null
       196: astore        13
       198: aconst_null
       199: astore        15
       201: goto          267
       204: astore        8
       206: aconst_null
       207: goto          267
       210: astore        10
       212: aload         8
       214: ifnonnull     229
       217: aload         4
       219: aload         7
       221: invokeinterface #103,  2          // InterfaceMethod scala/util/Using$Releasable.release:(Ljava/lang/Object;)V
       226: goto          264
       229: aload         4
       231: aload         7
       233: invokeinterface #103,  2          // InterfaceMethod scala/util/Using$Releasable.release:(Ljava/lang/Object;)V
       238: goto          261
       241: astore        11
       243: aload         6
       245: aload         8
       247: aload         11
       249: invokevirtual #105                // Method scala$util$Using$$preferentiallySuppress:(Ljava/lang/Throwable;Ljava/lang/Throwable;)Ljava/lang/Throwable;
       252: astore        8
       254: goto          261
       257: pop
       258: aload         8
       260: athrow
       261: aload         8
       263: athrow
       264: aload         10
       266: athrow
       267: astore        9
       269: aload         8
       271: ifnonnull     286
       274: aload         4
       276: aload         7
       278: invokeinterface #103,  2          // InterfaceMethod scala/util/Using$Releasable.release:(Ljava/lang/Object;)V
       283: goto          321
       286: aload         4
       288: aload         7
       290: invokeinterface #103,  2          // InterfaceMethod scala/util/Using$Releasable.release:(Ljava/lang/Object;)V
       295: goto          318
       298: astore        11
       300: aload         6
       302: aload         8
       304: aload         11
       306: invokevirtual #105                // Method scala$util$Using$$preferentiallySuppress:(Ljava/lang/Throwable;Ljava/lang/Throwable;)Ljava/lang/Throwable;
       309: astore        8
       311: goto          318
       314: pop
       315: aload         8
       317: athrow
       318: aload         8
       320: athrow
       321: aload         9
       323: areturn
      Exception table:
         from    to  target type
            62    74    77   Class java/lang/Throwable
            62    83    83   any
           101   109   112   Class java/lang/Throwable
           101   128   128   any
           156   164   167   Class java/lang/Throwable
           156   183   183   any
            31   201   204   Class java/lang/Throwable
            31   210   210   any
           229   238   241   Class java/lang/Throwable
           229   257   257   any
           286   295   298   Class java/lang/Throwable
           286   314   314   any
      StackMapTable: number_of_entries = 28
        frame_type = 253 /* append */
          offset_delta = 28
          locals = [ class scala/util/Using$, class java/lang/Object ]
        frame_type = 255 /* full_frame */
          offset_delta = 30
          locals = [ class scala/Function0, class scala/Function0, class scala/Function3, class scala/util/Using$Releasable, class scala/util/Using$Releasable, class java/lang/Object, class scala/util/Using$, class java/lang/Object, null, top, top, top, class scala/util/Using$, class java/lang/Object ]
          stack = []
        frame_type = 255 /* full_frame */
          offset_delta = 17
          locals = [ class scala/Function0, class scala/Function0, class scala/Function3, class scala/util/Using$Releasable, class scala/util/Using$Releasable, class java/lang/Object, class scala/util/Using$, class java/lang/Object, null, top, top, top, class scala/util/Using$, class java/lang/Object, null ]
          stack = [ class java/lang/Throwable ]
        frame_type = 255 /* full_frame */
          offset_delta = 5
          locals = [ class scala/Function0, class scala/Function0, class scala/Function3, class scala/util/Using$Releasable, class scala/util/Using$Releasable, class java/lang/Object, class scala/util/Using$, class java/lang/Object, null, top, top, top, class scala/util/Using$, class java/lang/Object, class java/lang/Throwable ]
          stack = [ class java/lang/Throwable ]
        frame_type = 253 /* append */
          offset_delta = 17
          locals = [ top, class java/lang/Throwable ]
        frame_type = 74 /* same_locals_1_stack_item */
          stack = [ class java/lang/Throwable ]
        frame_type = 79 /* same_locals_1_stack_item */
          stack = [ class java/lang/Throwable ]
        frame_type = 3 /* same */
        frame_type = 2 /* same */
        frame_type = 255 /* full_frame */
          offset_delta = 2
          locals = [ class scala/Function0, class scala/Function0, class scala/Function3, class scala/util/Using$Releasable, class scala/util/Using$Releasable, class java/lang/Object, class scala/util/Using$, class java/lang/Object, null, top, top, top, class scala/util/Using$, class java/lang/Object, class java/lang/Throwable ]
          stack = [ class java/lang/Object ]
        frame_type = 252 /* append */
          offset_delta = 17
          locals = [ class java/lang/Object ]
        frame_type = 74 /* same_locals_1_stack_item */
          stack = [ class java/lang/Throwable ]
        frame_type = 79 /* same_locals_1_stack_item */
          stack = [ class java/lang/Throwable ]
        frame_type = 3 /* same */
        frame_type = 2 /* same */
        frame_type = 255 /* full_frame */
          offset_delta = 13
          locals = [ class scala/Function0, class scala/Function0, class scala/Function3, class scala/util/Using$Releasable, class scala/util/Using$Releasable, class java/lang/Object, class scala/util/Using$, class java/lang/Object, null ]
          stack = [ class java/lang/Throwable ]
        frame_type = 255 /* full_frame */
          offset_delta = 5
          locals = [ class scala/Function0, class scala/Function0, class scala/Function3, class scala/util/Using$Releasable, class scala/util/Using$Releasable, class java/lang/Object, class scala/util/Using$, class java/lang/Object, class java/lang/Throwable ]
          stack = [ class java/lang/Throwable ]
        frame_type = 253 /* append */
          offset_delta = 18
          locals = [ top, class java/lang/Throwable ]
        frame_type = 75 /* same_locals_1_stack_item */
          stack = [ class java/lang/Throwable ]
        frame_type = 79 /* same_locals_1_stack_item */
          stack = [ class java/lang/Throwable ]
        frame_type = 3 /* same */
        frame_type = 2 /* same */
        frame_type = 255 /* full_frame */
          offset_delta = 2
          locals = [ class scala/Function0, class scala/Function0, class scala/Function3, class scala/util/Using$Releasable, class scala/util/Using$Releasable, class java/lang/Object, class scala/util/Using$, class java/lang/Object, class java/lang/Throwable ]
          stack = [ class java/lang/Object ]
        frame_type = 252 /* append */
          offset_delta = 18
          locals = [ class java/lang/Object ]
        frame_type = 75 /* same_locals_1_stack_item */
          stack = [ class java/lang/Throwable ]
        frame_type = 79 /* same_locals_1_stack_item */
          stack = [ class java/lang/Throwable ]
        frame_type = 3 /* same */
        frame_type = 2 /* same */
      LineNumberTable:
        line 326: 0
        line 257: 13
        line 259: 28
        line 327: 31
        line 257: 44
        line 259: 59
        line 328: 62
        line 261: 74
        line 264: 77
        line 265: 79
        line 267: 85
        line 269: 101
        line 270: 114
        line 271: 129
        line 267: 140
        line 269: 156
        line 270: 169
        line 271: 184
        line 327: 190
        line 261: 201
        line 264: 204
        line 265: 206
        line 267: 212
        line 269: 229
        line 270: 243
        line 271: 258
        line 267: 269
        line 269: 286
        line 270: 300
        line 271: 315
        line 326: 321
      LocalVariableTable:
        Start  Length  Slot  Name   Signature
            0     324     0 resource2$2   Lscala/Function0;
            0     324     1 resource3$1   Lscala/Function0;
            0     324     2 body$2   Lscala/Function3;
            0     324     3 evidence$8$1   Lscala/util/Using$Releasable;
            0     324     4 evidence$7$1   Lscala/util/Using$Releasable;
            0     324     5    r1   Ljava/lang/Object;
          241      13    11 resource_other   Ljava/lang/Throwable;
          298      13    11 resource_other   Ljava/lang/Throwable;
           31     290     8 resource_toThrow   Ljava/lang/Throwable;
           13     308     6 resource_this   Lscala/util/Using$;
           13     308     7 resource_resource   Ljava/lang/Object;
          112      13    17 $anonfun$resources$4_resource_other   Ljava/lang/Throwable;
          167      13    17 $anonfun$resources$4_resource_other   Ljava/lang/Throwable;
           62     128    14 $anonfun$resources$4_resource_toThrow   Ljava/lang/Throwable;
           44     146    12 $anonfun$resources$4_resource_this   Lscala/util/Using$;
           44     146    13 $anonfun$resources$4_resource_resource   Ljava/lang/Object;
    MethodParameters:
      Name                           Flags
      resource2$2                    final
      resource3$1                    final
      body$2                         final
      evidence$8$1                   final
      evidence$7$1                   final
      r1                             final

  public static final java.lang.Object $anonfun$resources$9(scala.Function4, java.lang.Object, java.lang.Object, java.lang.Object, java.lang.Object);
    descriptor: (Lscala/Function4;Ljava/lang/Object;Ljava/lang/Object;Ljava/lang/Object;Ljava/lang/Object;)Ljava/lang/Object;
    flags: (0x1019) ACC_PUBLIC, ACC_STATIC, ACC_FINAL, ACC_SYNTHETIC
    Code:
      stack=5, locals=5, args_size=5
         0: aload_0
         1: aload_1
         2: aload_2
         3: aload_3
         4: aload         4
         6: invokeinterface #161,  5          // InterfaceMethod scala/Function4.apply:(Ljava/lang/Object;Ljava/lang/Object;Ljava/lang/Object;Ljava/lang/Object;)Ljava/lang/Object;
        11: areturn
      LineNumberTable:
        line 363: 0
      LocalVariableTable:
        Start  Length  Slot  Name   Signature
            0      12     0 body$3   Lscala/Function4;
            0      12     1  r1$3   Ljava/lang/Object;
            0      12     2  r2$2   Ljava/lang/Object;
            0      12     3  r3$1   Ljava/lang/Object;
            0      12     4    r4   Ljava/lang/Object;
    MethodParameters:
      Name                           Flags
      body$3                         final
      r1$3                           final
      r2$2                           final
      r3$1                           final
      r4                             final

  public static final java.lang.Object $anonfun$resources$8(scala.Function0, scala.Function4, java.lang.Object, java.lang.Object, scala.util.Using$Releasable, java.lang.Object);
    descriptor: (Lscala/Function0;Lscala/Function4;Ljava/lang/Object;Ljava/lang/Object;Lscala/util/Using$Releasable;Ljava/lang/Object;)Ljava/lang/Object;
    flags: (0x1019) ACC_PUBLIC, ACC_STATIC, ACC_FINAL, ACC_SYNTHETIC
    Code:
      stack=5, locals=12, args_size=6
         0: getstatic     #19                 // Field MODULE$:Lscala/util/Using$;
         3: aload_0
         4: invokeinterface #117,  1          // InterfaceMethod scala/Function0.apply:()Ljava/lang/Object;
         9: astore        7
        11: astore        6
        13: aload         7
        15: ifnonnull     28
        18: new           #92                 // class java/lang/NullPointerException
        21: dup
        22: ldc           #94                 // String null resource
        24: invokespecial #97                 // Method java/lang/NullPointerException."<init>":(Ljava/lang/String;)V
        27: athrow
        28: aconst_null
        29: astore        8
        31: aload_1
        32: aload_2
        33: aload_3
        34: aload         5
        36: aload         7
        38: invokeinterface #161,  5          // InterfaceMethod scala/Function4.apply:(Ljava/lang/Object;Ljava/lang/Object;Ljava/lang/Object;Ljava/lang/Object;)Ljava/lang/Object;
        43: goto          109
        46: astore        8
        48: aconst_null
        49: goto          109
        52: astore        10
        54: aload         8
        56: ifnonnull     71
        59: aload         4
        61: aload         7
        63: invokeinterface #103,  2          // InterfaceMethod scala/util/Using$Releasable.release:(Ljava/lang/Object;)V
        68: goto          106
        71: aload         4
        73: aload         7
        75: invokeinterface #103,  2          // InterfaceMethod scala/util/Using$Releasable.release:(Ljava/lang/Object;)V
        80: goto          103
        83: astore        11
        85: aload         6
        87: aload         8
        89: aload         11
        91: invokevirtual #105                // Method scala$util$Using$$preferentiallySuppress:(Ljava/lang/Throwable;Ljava/lang/Throwable;)Ljava/lang/Throwable;
        94: astore        8
        96: goto          103
        99: pop
       100: aload         8
       102: athrow
       103: aload         8
       105: athrow
       106: aload         10
       108: athrow
       109: astore        9
       111: aload         8
       113: ifnonnull     128
       116: aload         4
       118: aload         7
       120: invokeinterface #103,  2          // InterfaceMethod scala/util/Using$Releasable.release:(Ljava/lang/Object;)V
       125: goto          163
       128: aload         4
       130: aload         7
       132: invokeinterface #103,  2          // InterfaceMethod scala/util/Using$Releasable.release:(Ljava/lang/Object;)V
       137: goto          160
       140: astore        11
       142: aload         6
       144: aload         8
       146: aload         11
       148: invokevirtual #105                // Method scala$util$Using$$preferentiallySuppress:(Ljava/lang/Throwable;Ljava/lang/Throwable;)Ljava/lang/Throwable;
       151: astore        8
       153: goto          160
       156: pop
       157: aload         8
       159: athrow
       160: aload         8
       162: athrow
       163: aload         9
       165: areturn
      Exception table:
         from    to  target type
            31    43    46   Class java/lang/Throwable
            31    52    52   any
            71    80    83   Class java/lang/Throwable
            71    99    99   any
           128   137   140   Class java/lang/Throwable
           128   156   156   any
      StackMapTable: number_of_entries = 14
        frame_type = 253 /* append */
          offset_delta = 28
          locals = [ class scala/util/Using$, class java/lang/Object ]
        frame_type = 255 /* full_frame */
          offset_delta = 17
          locals = [ class scala/Function0, class scala/Function4, class java/lang/Object, class java/lang/Object, class scala/util/Using$Releasable, class java/lang/Object, class scala/util/Using$, class java/lang/Object, null ]
          stack = [ class java/lang/Throwable ]
        frame_type = 255 /* full_frame */
          offset_delta = 5
          locals = [ class scala/Function0, class scala/Function4, class java/lang/Object, class java/lang/Object, class scala/util/Using$Releasable, class java/lang/Object, class scala/util/Using$, class java/lang/Object, class java/lang/Throwable ]
          stack = [ class java/lang/Throwable ]
        frame_type = 253 /* append */
          offset_delta = 18
          locals = [ top, class java/lang/Throwable ]
        frame_type = 75 /* same_locals_1_stack_item */
          stack = [ class java/lang/Throwable ]
        frame_type = 79 /* same_locals_1_stack_item */
          stack = [ class java/lang/Throwable ]
        frame_type = 3 /* same */
        frame_type = 2 /* same */
        frame_type = 255 /* full_frame */
          offset_delta = 2
          locals = [ class scala/Function0, class scala/Function4, class java/lang/Object, class java/lang/Object, class scala/util/Using$Releasable, class java/lang/Object, class scala/util/Using$, class java/lang/Object, class java/lang/Throwable ]
          stack = [ class java/lang/Object ]
        frame_type = 252 /* append */
          offset_delta = 18
          locals = [ class java/lang/Object ]
        frame_type = 75 /* same_locals_1_stack_item */
          stack = [ class java/lang/Throwable ]
        frame_type = 79 /* same_locals_1_stack_item */
          stack = [ class java/lang/Throwable ]
        frame_type = 3 /* same */
        frame_type = 2 /* same */
      LineNumberTable:
        line 362: 0
        line 257: 13
        line 259: 28
        line 363: 31
        line 261: 43
        line 264: 46
        line 265: 48
        line 267: 54
        line 269: 71
        line 270: 85
        line 271: 100
        line 267: 111
        line 269: 128
        line 270: 142
        line 271: 157
        line 362: 163
      LocalVariableTable:
        Start  Length  Slot  Name   Signature
            0     166     0 resource4$1   Lscala/Function0;
            0     166     1 body$3   Lscala/Function4;
            0     166     2  r1$3   Ljava/lang/Object;
            0     166     3  r2$2   Ljava/lang/Object;
            0     166     4 evidence$12$1   Lscala/util/Using$Releasable;
            0     166     5    r3   Ljava/lang/Object;
           83      13    11 resource_other   Ljava/lang/Throwable;
          140      13    11 resource_other   Ljava/lang/Throwable;
           31     132     8 resource_toThrow   Ljava/lang/Throwable;
           13     150     6 resource_this   Lscala/util/Using$;
           13     150     7 resource_resource   Ljava/lang/Object;
    MethodParameters:
      Name                           Flags
      resource4$1                    final
      body$3                         final
      r1$3                           final
      r2$2                           final
      evidence$12$1                  final
      r3                             final

  public static final java.lang.Object $anonfun$resources$7(scala.Function0, scala.Function0, scala.Function4, java.lang.Object, scala.util.Using$Releasable, scala.util.Using$Releasable, java.lang.Object);
    descriptor: (Lscala/Function0;Lscala/Function0;Lscala/Function4;Ljava/lang/Object;Lscala/util/Using$Releasable;Lscala/util/Using$Releasable;Ljava/lang/Object;)Ljava/lang/Object;
    flags: (0x1019) ACC_PUBLIC, ACC_STATIC, ACC_FINAL, ACC_SYNTHETIC
    Code:
      stack=5, locals=19, args_size=7
         0: getstatic     #19                 // Field MODULE$:Lscala/util/Using$;
         3: aload_0
         4: invokeinterface #117,  1          // InterfaceMethod scala/Function0.apply:()Ljava/lang/Object;
         9: astore        8
        11: astore        7
        13: aload         8
        15: ifnonnull     28
        18: new           #92                 // class java/lang/NullPointerException
        21: dup
        22: ldc           #94                 // String null resource
        24: invokespecial #97                 // Method java/lang/NullPointerException."<init>":(Ljava/lang/String;)V
        27: athrow
        28: aconst_null
        29: astore        9
        31: getstatic     #19                 // Field MODULE$:Lscala/util/Using$;
        34: aload_1
        35: invokeinterface #117,  1          // InterfaceMethod scala/Function0.apply:()Ljava/lang/Object;
        40: astore        14
        42: astore        13
        44: aload         14
        46: ifnonnull     59
        49: new           #92                 // class java/lang/NullPointerException
        52: dup
        53: ldc           #94                 // String null resource
        55: invokespecial #97                 // Method java/lang/NullPointerException."<init>":(Ljava/lang/String;)V
        58: athrow
        59: aconst_null
        60: astore        15
        62: aload_2
        63: aload_3
        64: aload         6
        66: aload         8
        68: aload         14
        70: invokeinterface #161,  5          // InterfaceMethod scala/Function4.apply:(Ljava/lang/Object;Ljava/lang/Object;Ljava/lang/Object;Ljava/lang/Object;)Ljava/lang/Object;
        75: goto          141
        78: astore        15
        80: aconst_null
        81: goto          141
        84: astore        17
        86: aload         15
        88: ifnonnull     103
        91: aload         4
        93: aload         14
        95: invokeinterface #103,  2          // InterfaceMethod scala/util/Using$Releasable.release:(Ljava/lang/Object;)V
       100: goto          138
       103: aload         4
       105: aload         14
       107: invokeinterface #103,  2          // InterfaceMethod scala/util/Using$Releasable.release:(Ljava/lang/Object;)V
       112: goto          135
       115: astore        18
       117: aload         13
       119: aload         15
       121: aload         18
       123: invokevirtual #105                // Method scala$util$Using$$preferentiallySuppress:(Ljava/lang/Throwable;Ljava/lang/Throwable;)Ljava/lang/Throwable;
       126: astore        15
       128: goto          135
       131: pop
       132: aload         15
       134: athrow
       135: aload         15
       137: athrow
       138: aload         17
       140: athrow
       141: astore        16
       143: aload         15
       145: ifnonnull     160
       148: aload         4
       150: aload         14
       152: invokeinterface #103,  2          // InterfaceMethod scala/util/Using$Releasable.release:(Ljava/lang/Object;)V
       157: goto          195
       160: aload         4
       162: aload         14
       164: invokeinterface #103,  2          // InterfaceMethod scala/util/Using$Releasable.release:(Ljava/lang/Object;)V
       169: goto          192
       172: astore        18
       174: aload         13
       176: aload         15
       178: aload         18
       180: invokevirtual #105                // Method scala$util$Using$$preferentiallySuppress:(Ljava/lang/Throwable;Ljava/lang/Throwable;)Ljava/lang/Throwable;
       183: astore        15
       185: goto          192
       188: pop
       189: aload         15
       191: athrow
       192: aload         15
       194: athrow
       195: aload         16
       197: aconst_null
       198: astore        13
       200: aconst_null
       201: astore        14
       203: aconst_null
       204: astore        16
       206: goto          272
       209: astore        9
       211: aconst_null
       212: goto          272
       215: astore        11
       217: aload         9
       219: ifnonnull     234
       222: aload         5
       224: aload         8
       226: invokeinterface #103,  2          // InterfaceMethod scala/util/Using$Releasable.release:(Ljava/lang/Object;)V
       231: goto          269
       234: aload         5
       236: aload         8
       238: invokeinterface #103,  2          // InterfaceMethod scala/util/Using$Releasable.release:(Ljava/lang/Object;)V
       243: goto          266
       246: astore        12
       248: aload         7
       250: aload         9
       252: aload         12
       254: invokevirtual #105                // Method scala$util$Using$$preferentiallySuppress:(Ljava/lang/Throwable;Ljava/lang/Throwable;)Ljava/lang/Throwable;
       257: astore        9
       259: goto          266
       262: pop
       263: aload         9
       265: athrow
       266: aload         9
       268: athrow
       269: aload         11
       271: athrow
       272: astore        10
       274: aload         9
       276: ifnonnull     291
       279: aload         5
       281: aload         8
       283: invokeinterface #103,  2          // InterfaceMethod scala/util/Using$Releasable.release:(Ljava/lang/Object;)V
       288: goto          326
       291: aload         5
       293: aload         8
       295: invokeinterface #103,  2          // InterfaceMethod scala/util/Using$Releasable.release:(Ljava/lang/Object;)V
       300: goto          323
       303: astore        12
       305: aload         7
       307: aload         9
       309: aload         12
       311: invokevirtual #105                // Method scala$util$Using$$preferentiallySuppress:(Ljava/lang/Throwable;Ljava/lang/Throwable;)Ljava/lang/Throwable;
       314: astore        9
       316: goto          323
       319: pop
       320: aload         9
       322: athrow
       323: aload         9
       325: athrow
       326: aload         10
       328: areturn
      Exception table:
         from    to  target type
            62    75    78   Class java/lang/Throwable
            62    84    84   any
           103   112   115   Class java/lang/Throwable
           103   131   131   any
           160   169   172   Class java/lang/Throwable
           160   188   188   any
            31   206   209   Class java/lang/Throwable
            31   215   215   any
           234   243   246   Class java/lang/Throwable
           234   262   262   any
           291   300   303   Class java/lang/Throwable
           291   319   319   any
      StackMapTable: number_of_entries = 28
        frame_type = 253 /* append */
          offset_delta = 28
          locals = [ class scala/util/Using$, class java/lang/Object ]
        frame_type = 255 /* full_frame */
          offset_delta = 30
          locals = [ class scala/Function0, class scala/Function0, class scala/Function4, class java/lang/Object, class scala/util/Using$Releasable, class scala/util/Using$Releasable, class java/lang/Object, class scala/util/Using$, class java/lang/Object, null, top, top, top, class scala/util/Using$, class java/lang/Object ]
          stack = []
        frame_type = 255 /* full_frame */
          offset_delta = 18
          locals = [ class scala/Function0, class scala/Function0, class scala/Function4, class java/lang/Object, class scala/util/Using$Releasable, class scala/util/Using$Releasable, class java/lang/Object, class scala/util/Using$, class java/lang/Object, null, top, top, top, class scala/util/Using$, class java/lang/Object, null ]
          stack = [ class java/lang/Throwable ]
        frame_type = 255 /* full_frame */
          offset_delta = 5
          locals = [ class scala/Function0, class scala/Function0, class scala/Function4, class java/lang/Object, class scala/util/Using$Releasable, class scala/util/Using$Releasable, class java/lang/Object, class scala/util/Using$, class java/lang/Object, null, top, top, top, class scala/util/Using$, class java/lang/Object, class java/lang/Throwable ]
          stack = [ class java/lang/Throwable ]
        frame_type = 253 /* append */
          offset_delta = 18
          locals = [ top, class java/lang/Throwable ]
        frame_type = 75 /* same_locals_1_stack_item */
          stack = [ class java/lang/Throwable ]
        frame_type = 79 /* same_locals_1_stack_item */
          stack = [ class java/lang/Throwable ]
        frame_type = 3 /* same */
        frame_type = 2 /* same */
        frame_type = 255 /* full_frame */
          offset_delta = 2
          locals = [ class scala/Function0, class scala/Function0, class scala/Function4, class java/lang/Object, class scala/util/Using$Releasable, class scala/util/Using$Releasable, class java/lang/Object, class scala/util/Using$, class java/lang/Object, null, top, top, top, class scala/util/Using$, class java/lang/Object, class java/lang/Throwable ]
          stack = [ class java/lang/Object ]
        frame_type = 252 /* append */
          offset_delta = 18
          locals = [ class java/lang/Object ]
        frame_type = 75 /* same_locals_1_stack_item */
          stack = [ class java/lang/Throwable ]
        frame_type = 79 /* same_locals_1_stack_item */
          stack = [ class java/lang/Throwable ]
        frame_type = 3 /* same */
        frame_type = 2 /* same */
        frame_type = 255 /* full_frame */
          offset_delta = 13
          locals = [ class scala/Function0, class scala/Function0, class scala/Function4, class java/lang/Object, class scala/util/Using$Releasable, class scala/util/Using$Releasable, class java/lang/Object, class scala/util/Using$, class java/lang/Object, null ]
          stack = [ class java/lang/Throwable ]
        frame_type = 255 /* full_frame */
          offset_delta = 5
          locals = [ class scala/Function0, class scala/Function0, class scala/Function4, class java/lang/Object, class scala/util/Using$Releasable, class scala/util/Using$Releasable, class java/lang/Object, class scala/util/Using$, class java/lang/Object, class java/lang/Throwable ]
          stack = [ class java/lang/Throwable ]
        frame_type = 253 /* append */
          offset_delta = 18
          locals = [ top, class java/lang/Throwable ]
        frame_type = 75 /* same_locals_1_stack_item */
          stack = [ class java/lang/Throwable ]
        frame_type = 79 /* same_locals_1_stack_item */
          stack = [ class java/lang/Throwable ]
        frame_type = 3 /* same */
        frame_type = 2 /* same */
        frame_type = 255 /* full_frame */
          offset_delta = 2
          locals = [ class scala/Function0, class scala/Function0, class scala/Function4, class java/lang/Object, class scala/util/Using$Releasable, class scala/util/Using$Releasable, class java/lang/Object, class scala/util/Using$, class java/lang/Object, class java/lang/Throwable ]
          stack = [ class java/lang/Object ]
        frame_type = 252 /* append */
          offset_delta = 18
          locals = [ class java/lang/Object ]
        frame_type = 75 /* same_locals_1_stack_item */
          stack = [ class java/lang/Throwable ]
        frame_type = 79 /* same_locals_1_stack_item */
          stack = [ class java/lang/Throwable ]
        frame_type = 3 /* same */
        frame_type = 2 /* same */
      LineNumberTable:
        line 361: 0
        line 257: 13
        line 259: 28
        line 362: 31
        line 257: 44
        line 259: 59
        line 363: 62
        line 261: 75
        line 264: 78
        line 265: 80
        line 267: 86
        line 269: 103
        line 270: 117
        line 271: 132
        line 267: 143
        line 269: 160
        line 270: 174
        line 271: 189
        line 362: 195
        line 261: 206
        line 264: 209
        line 265: 211
        line 267: 217
        line 269: 234
        line 270: 248
        line 271: 263
        line 267: 274
        line 269: 291
        line 270: 305
        line 271: 320
        line 361: 326
      LocalVariableTable:
        Start  Length  Slot  Name   Signature
            0     329     0 resource3$2   Lscala/Function0;
            0     329     1 resource4$1   Lscala/Function0;
            0     329     2 body$3   Lscala/Function4;
            0     329     3  r1$3   Ljava/lang/Object;
            0     329     4 evidence$12$1   Lscala/util/Using$Releasable;
            0     329     5 evidence$11$1   Lscala/util/Using$Releasable;
            0     329     6    r2   Ljava/lang/Object;
          246      13    12 resource_other   Ljava/lang/Throwable;
          303      13    12 resource_other   Ljava/lang/Throwable;
           31     295     9 resource_toThrow   Ljava/lang/Throwable;
           13     313     7 resource_this   Lscala/util/Using$;
           13     313     8 resource_resource   Ljava/lang/Object;
          115      13    18 $anonfun$resources$8_resource_other   Ljava/lang/Throwable;
          172      13    18 $anonfun$resources$8_resource_other   Ljava/lang/Throwable;
           62     133    15 $anonfun$resources$8_resource_toThrow   Ljava/lang/Throwable;
           44     151    13 $anonfun$resources$8_resource_this   Lscala/util/Using$;
           44     151    14 $anonfun$resources$8_resource_resource   Ljava/lang/Object;
    MethodParameters:
      Name                           Flags
      resource3$2                    final
      resource4$1                    final
      body$3                         final
      r1$3                           final
      evidence$12$1                  final
      evidence$11$1                  final
      r2                             final

  public static final java.lang.Object $anonfun$resources$6(scala.Function0, scala.Function0, scala.Function0, scala.Function4, scala.util.Using$Releasable, scala.util.Using$Releasable, scala.util.Using$Releasable, java.lang.Object);
    descriptor: (Lscala/Function0;Lscala/Function0;Lscala/Function0;Lscala/Function4;Lscala/util/Using$Releasable;Lscala/util/Using$Releasable;Lscala/util/Using$Releasable;Ljava/lang/Object;)Ljava/lang/Object;
    flags: (0x1019) ACC_PUBLIC, ACC_STATIC, ACC_FINAL, ACC_SYNTHETIC
    Code:
      stack=5, locals=26, args_size=8
         0: getstatic     #19                 // Field MODULE$:Lscala/util/Using$;
         3: aload_0
         4: invokeinterface #117,  1          // InterfaceMethod scala/Function0.apply:()Ljava/lang/Object;
         9: astore        9
        11: astore        8
        13: aload         9
        15: ifnonnull     28
        18: new           #92                 // class java/lang/NullPointerException
        21: dup
        22: ldc           #94                 // String null resource
        24: invokespecial #97                 // Method java/lang/NullPointerException."<init>":(Ljava/lang/String;)V
        27: athrow
        28: aconst_null
        29: astore        10
        31: getstatic     #19                 // Field MODULE$:Lscala/util/Using$;
        34: aload_1
        35: invokeinterface #117,  1          // InterfaceMethod scala/Function0.apply:()Ljava/lang/Object;
        40: astore        15
        42: astore        14
        44: aload         15
        46: ifnonnull     59
        49: new           #92                 // class java/lang/NullPointerException
        52: dup
        53: ldc           #94                 // String null resource
        55: invokespecial #97                 // Method java/lang/NullPointerException."<init>":(Ljava/lang/String;)V
        58: athrow
        59: aconst_null
        60: astore        16
        62: getstatic     #19                 // Field MODULE$:Lscala/util/Using$;
        65: aload_2
        66: invokeinterface #117,  1          // InterfaceMethod scala/Function0.apply:()Ljava/lang/Object;
        71: astore        21
        73: astore        20
        75: aload         21
        77: ifnonnull     90
        80: new           #92                 // class java/lang/NullPointerException
        83: dup
        84: ldc           #94                 // String null resource
        86: invokespecial #97                 // Method java/lang/NullPointerException."<init>":(Ljava/lang/String;)V
        89: athrow
        90: aconst_null
        91: astore        22
        93: aload_3
        94: aload         7
        96: aload         9
        98: aload         15
       100: aload         21
       102: invokeinterface #161,  5          // InterfaceMethod scala/Function4.apply:(Ljava/lang/Object;Ljava/lang/Object;Ljava/lang/Object;Ljava/lang/Object;)Ljava/lang/Object;
       107: goto          173
       110: astore        22
       112: aconst_null
       113: goto          173
       116: astore        24
       118: aload         22
       120: ifnonnull     135
       123: aload         4
       125: aload         21
       127: invokeinterface #103,  2          // InterfaceMethod scala/util/Using$Releasable.release:(Ljava/lang/Object;)V
       132: goto          170
       135: aload         4
       137: aload         21
       139: invokeinterface #103,  2          // InterfaceMethod scala/util/Using$Releasable.release:(Ljava/lang/Object;)V
       144: goto          167
       147: astore        25
       149: aload         20
       151: aload         22
       153: aload         25
       155: invokevirtual #105                // Method scala$util$Using$$preferentiallySuppress:(Ljava/lang/Throwable;Ljava/lang/Throwable;)Ljava/lang/Throwable;
       158: astore        22
       160: goto          167
       163: pop
       164: aload         22
       166: athrow
       167: aload         22
       169: athrow
       170: aload         24
       172: athrow
       173: astore        23
       175: aload         22
       177: ifnonnull     192
       180: aload         4
       182: aload         21
       184: invokeinterface #103,  2          // InterfaceMethod scala/util/Using$Releasable.release:(Ljava/lang/Object;)V
       189: goto          227
       192: aload         4
       194: aload         21
       196: invokeinterface #103,  2          // InterfaceMethod scala/util/Using$Releasable.release:(Ljava/lang/Object;)V
       201: goto          224
       204: astore        25
       206: aload         20
       208: aload         22
       210: aload         25
       212: invokevirtual #105                // Method scala$util$Using$$preferentiallySuppress:(Ljava/lang/Throwable;Ljava/lang/Throwable;)Ljava/lang/Throwable;
       215: astore        22
       217: goto          224
       220: pop
       221: aload         22
       223: athrow
       224: aload         22
       226: athrow
       227: aload         23
       229: aconst_null
       230: astore        20
       232: aconst_null
       233: astore        21
       235: aconst_null
       236: astore        23
       238: goto          304
       241: astore        16
       243: aconst_null
       244: goto          304
       247: astore        18
       249: aload         16
       251: ifnonnull     266
       254: aload         5
       256: aload         15
       258: invokeinterface #103,  2          // InterfaceMethod scala/util/Using$Releasable.release:(Ljava/lang/Object;)V
       263: goto          301
       266: aload         5
       268: aload         15
       270: invokeinterface #103,  2          // InterfaceMethod scala/util/Using$Releasable.release:(Ljava/lang/Object;)V
       275: goto          298
       278: astore        19
       280: aload         14
       282: aload         16
       284: aload         19
       286: invokevirtual #105                // Method scala$util$Using$$preferentiallySuppress:(Ljava/lang/Throwable;Ljava/lang/Throwable;)Ljava/lang/Throwable;
       289: astore        16
       291: goto          298
       294: pop
       295: aload         16
       297: athrow
       298: aload         16
       300: athrow
       301: aload         18
       303: athrow
       304: astore        17
       306: aload         16
       308: ifnonnull     323
       311: aload         5
       313: aload         15
       315: invokeinterface #103,  2          // InterfaceMethod scala/util/Using$Releasable.release:(Ljava/lang/Object;)V
       320: goto          358
       323: aload         5
       325: aload         15
       327: invokeinterface #103,  2          // InterfaceMethod scala/util/Using$Releasable.release:(Ljava/lang/Object;)V
       332: goto          355
       335: astore        19
       337: aload         14
       339: aload         16
       341: aload         19
       343: invokevirtual #105                // Method scala$util$Using$$preferentiallySuppress:(Ljava/lang/Throwable;Ljava/lang/Throwable;)Ljava/lang/Throwable;
       346: astore        16
       348: goto          355
       351: pop
       352: aload         16
       354: athrow
       355: aload         16
       357: athrow
       358: aload         17
       360: aconst_null
       361: astore        14
       363: aconst_null
       364: astore        15
       366: aconst_null
       367: astore        17
       369: goto          435
       372: astore        10
       374: aconst_null
       375: goto          435
       378: astore        12
       380: aload         10
       382: ifnonnull     397
       385: aload         6
       387: aload         9
       389: invokeinterface #103,  2          // InterfaceMethod scala/util/Using$Releasable.release:(Ljava/lang/Object;)V
       394: goto          432
       397: aload         6
       399: aload         9
       401: invokeinterface #103,  2          // InterfaceMethod scala/util/Using$Releasable.release:(Ljava/lang/Object;)V
       406: goto          429
       409: astore        13
       411: aload         8
       413: aload         10
       415: aload         13
       417: invokevirtual #105                // Method scala$util$Using$$preferentiallySuppress:(Ljava/lang/Throwable;Ljava/lang/Throwable;)Ljava/lang/Throwable;
       420: astore        10
       422: goto          429
       425: pop
       426: aload         10
       428: athrow
       429: aload         10
       431: athrow
       432: aload         12
       434: athrow
       435: astore        11
       437: aload         10
       439: ifnonnull     454
       442: aload         6
       444: aload         9
       446: invokeinterface #103,  2          // InterfaceMethod scala/util/Using$Releasable.release:(Ljava/lang/Object;)V
       451: goto          489
       454: aload         6
       456: aload         9
       458: invokeinterface #103,  2          // InterfaceMethod scala/util/Using$Releasable.release:(Ljava/lang/Object;)V
       463: goto          486
       466: astore        13
       468: aload         8
       470: aload         10
       472: aload         13
       474: invokevirtual #105                // Method scala$util$Using$$preferentiallySuppress:(Ljava/lang/Throwable;Ljava/lang/Throwable;)Ljava/lang/Throwable;
       477: astore        10
       479: goto          486
       482: pop
       483: aload         10
       485: athrow
       486: aload         10
       488: athrow
       489: aload         11
       491: areturn
      Exception table:
         from    to  target type
            93   107   110   Class java/lang/Throwable
            93   116   116   any
           135   144   147   Class java/lang/Throwable
           135   163   163   any
           192   201   204   Class java/lang/Throwable
           192   220   220   any
            62   238   241   Class java/lang/Throwable
            62   247   247   any
           266   275   278   Class java/lang/Throwable
           266   294   294   any
           323   332   335   Class java/lang/Throwable
           323   351   351   any
            31   369   372   Class java/lang/Throwable
            31   378   378   any
           397   406   409   Class java/lang/Throwable
           397   425   425   any
           454   463   466   Class java/lang/Throwable
           454   482   482   any
      StackMapTable: number_of_entries = 42
        frame_type = 253 /* append */
          offset_delta = 28
          locals = [ class scala/util/Using$, class java/lang/Object ]
        frame_type = 255 /* full_frame */
          offset_delta = 30
          locals = [ class scala/Function0, class scala/Function0, class scala/Function0, class scala/Function4, class scala/util/Using$Releasable, class scala/util/Using$Releasable, class scala/util/Using$Releasable, class java/lang/Object, class scala/util/Using$, class java/lang/Object, null, top, top, top, class scala/util/Using$, class java/lang/Object ]
          stack = []
        frame_type = 255 /* full_frame */
          offset_delta = 30
          locals = [ class scala/Function0, class scala/Function0, class scala/Function0, class scala/Function4, class scala/util/Using$Releasable, class scala/util/Using$Releasable, class scala/util/Using$Releasable, class java/lang/Object, class scala/util/Using$, class java/lang/Object, null, top, top, top, class scala/util/Using$, class java/lang/Object, null, top, top, top, class scala/util/Using$, class java/lang/Object ]
          stack = []
        frame_type = 255 /* full_frame */
          offset_delta = 19
          locals = [ class scala/Function0, class scala/Function0, class scala/Function0, class scala/Function4, class scala/util/Using$Releasable, class scala/util/Using$Releasable, class scala/util/Using$Releasable, class java/lang/Object, class scala/util/Using$, class java/lang/Object, null, top, top, top, class scala/util/Using$, class java/lang/Object, null, top, top, top, class scala/util/Using$, class java/lang/Object, null ]
          stack = [ class java/lang/Throwable ]
        frame_type = 255 /* full_frame */
          offset_delta = 5
          locals = [ class scala/Function0, class scala/Function0, class scala/Function0, class scala/Function4, class scala/util/Using$Releasable, class scala/util/Using$Releasable, class scala/util/Using$Releasable, class java/lang/Object, class scala/util/Using$, class java/lang/Object, null, top, top, top, class scala/util/Using$, class java/lang/Object, null, top, top, top, class scala/util/Using$, class java/lang/Object, class java/lang/Throwable ]
          stack = [ class java/lang/Throwable ]
        frame_type = 253 /* append */
          offset_delta = 18
          locals = [ top, class java/lang/Throwable ]
        frame_type = 75 /* same_locals_1_stack_item */
          stack = [ class java/lang/Throwable ]
        frame_type = 79 /* same_locals_1_stack_item */
          stack = [ class java/lang/Throwable ]
        frame_type = 3 /* same */
        frame_type = 2 /* same */
        frame_type = 255 /* full_frame */
          offset_delta = 2
          locals = [ class scala/Function0, class scala/Function0, class scala/Function0, class scala/Function4, class scala/util/Using$Releasable, class scala/util/Using$Releasable, class scala/util/Using$Releasable, class java/lang/Object, class scala/util/Using$, class java/lang/Object, null, top, top, top, class scala/util/Using$, class java/lang/Object, null, top, top, top, class scala/util/Using$, class java/lang/Object, class java/lang/Throwable ]
          stack = [ class java/lang/Object ]
        frame_type = 252 /* append */
          offset_delta = 18
          locals = [ class java/lang/Object ]
        frame_type = 75 /* same_locals_1_stack_item */
          stack = [ class java/lang/Throwable ]
        frame_type = 79 /* same_locals_1_stack_item */
          stack = [ class java/lang/Throwable ]
        frame_type = 3 /* same */
        frame_type = 2 /* same */
        frame_type = 255 /* full_frame */
          offset_delta = 13
          locals = [ class scala/Function0, class scala/Function0, class scala/Function0, class scala/Function4, class scala/util/Using$Releasable, class scala/util/Using$Releasable, class scala/util/Using$Releasable, class java/lang/Object, class scala/util/Using$, class java/lang/Object, null, top, top, top, class scala/util/Using$, class java/lang/Object, null ]
          stack = [ class java/lang/Throwable ]
        frame_type = 255 /* full_frame */
          offset_delta = 5
          locals = [ class scala/Function0, class scala/Function0, class scala/Function0, class scala/Function4, class scala/util/Using$Releasable, class scala/util/Using$Releasable, class scala/util/Using$Releasable, class java/lang/Object, class scala/util/Using$, class java/lang/Object, null, top, top, top, class scala/util/Using$, class java/lang/Object, class java/lang/Throwable ]
          stack = [ class java/lang/Throwable ]
        frame_type = 253 /* append */
          offset_delta = 18
          locals = [ top, class java/lang/Throwable ]
        frame_type = 75 /* same_locals_1_stack_item */
          stack = [ class java/lang/Throwable ]
        frame_type = 79 /* same_locals_1_stack_item */
          stack = [ class java/lang/Throwable ]
        frame_type = 3 /* same */
        frame_type = 2 /* same */
        frame_type = 255 /* full_frame */
          offset_delta = 2
          locals = [ class scala/Function0, class scala/Function0, class scala/Function0, class scala/Function4, class scala/util/Using$Releasable, class scala/util/Using$Releasable, class scala/util/Using$Releasable, class java/lang/Object, class scala/util/Using$, class java/lang/Object, null, top, top, top, class scala/util/Using$, class java/lang/Object, class java/lang/Throwable ]
          stack = [ class java/lang/Object ]
        frame_type = 252 /* append */
          offset_delta = 18
          locals = [ class java/lang/Object ]
        frame_type = 75 /* same_locals_1_stack_item */
          stack = [ class java/lang/Throwable ]
        frame_type = 79 /* same_locals_1_stack_item */
          stack = [ class java/lang/Throwable ]
        frame_type = 3 /* same */
        frame_type = 2 /* same */
        frame_type = 255 /* full_frame */
          offset_delta = 13
          locals = [ class scala/Function0, class scala/Function0, class scala/Function0, class scala/Function4, class scala/util/Using$Releasable, class scala/util/Using$Releasable, class scala/util/Using$Releasable, class java/lang/Object, class scala/util/Using$, class java/lang/Object, null ]
          stack = [ class java/lang/Throwable ]
        frame_type = 255 /* full_frame */
          offset_delta = 5
          locals = [ class scala/Function0, class scala/Function0, class scala/Function0, class scala/Function4, class scala/util/Using$Releasable, class scala/util/Using$Releasable, class scala/util/Using$Releasable, class java/lang/Object, class scala/util/Using$, class java/lang/Object, class java/lang/Throwable ]
          stack = [ class java/lang/Throwable ]
        frame_type = 253 /* append */
          offset_delta = 18
          locals = [ top, class java/lang/Throwable ]
        frame_type = 75 /* same_locals_1_stack_item */
          stack = [ class java/lang/Throwable ]
        frame_type = 79 /* same_locals_1_stack_item */
          stack = [ class java/lang/Throwable ]
        frame_type = 3 /* same */
        frame_type = 2 /* same */
        frame_type = 255 /* full_frame */
          offset_delta = 2
          locals = [ class scala/Function0, class scala/Function0, class scala/Function0, class scala/Function4, class scala/util/Using$Releasable, class scala/util/Using$Releasable, class scala/util/Using$Releasable, class java/lang/Object, class scala/util/Using$, class java/lang/Object, class java/lang/Throwable ]
          stack = [ class java/lang/Object ]
        frame_type = 252 /* append */
          offset_delta = 18
          locals = [ class java/lang/Object ]
        frame_type = 75 /* same_locals_1_stack_item */
          stack = [ class java/lang/Throwable ]
        frame_type = 79 /* same_locals_1_stack_item */
          stack = [ class java/lang/Throwable ]
        frame_type = 3 /* same */
        frame_type = 2 /* same */
      LineNumberTable:
        line 360: 0
        line 257: 13
        line 259: 28
        line 361: 31
        line 257: 44
        line 259: 59
        line 362: 62
        line 257: 75
        line 259: 90
        line 363: 93
        line 261: 107
        line 264: 110
        line 265: 112
        line 267: 118
        line 269: 135
        line 270: 149
        line 271: 164
        line 267: 175
        line 269: 192
        line 270: 206
        line 271: 221
        line 362: 227
        line 261: 238
        line 264: 241
        line 265: 243
        line 267: 249
        line 269: 266
        line 270: 280
        line 271: 295
        line 267: 306
        line 269: 323
        line 270: 337
        line 271: 352
        line 361: 358
        line 261: 369
        line 264: 372
        line 265: 374
        line 267: 380
        line 269: 397
        line 270: 411
        line 271: 426
        line 267: 437
        line 269: 454
        line 270: 468
        line 271: 483
        line 360: 489
      LocalVariableTable:
        Start  Length  Slot  Name   Signature
            0     492     0 resource2$3   Lscala/Function0;
            0     492     1 resource3$2   Lscala/Function0;
            0     492     2 resource4$1   Lscala/Function0;
            0     492     3 body$3   Lscala/Function4;
            0     492     4 evidence$12$1   Lscala/util/Using$Releasable;
            0     492     5 evidence$11$1   Lscala/util/Using$Releasable;
            0     492     6 evidence$10$1   Lscala/util/Using$Releasable;
            0     492     7    r1   Ljava/lang/Object;
          409      13    13 resource_other   Ljava/lang/Throwable;
          466      13    13 resource_other   Ljava/lang/Throwable;
           31     458    10 resource_toThrow   Ljava/lang/Throwable;
           13     476     8 resource_this   Lscala/util/Using$;
           13     476     9 resource_resource   Ljava/lang/Object;
          278      13    19 $anonfun$resources$7_resource_other   Ljava/lang/Throwable;
          335      13    19 $anonfun$resources$7_resource_other   Ljava/lang/Throwable;
           62     296    16 $anonfun$resources$7_resource_toThrow   Ljava/lang/Throwable;
           44     314    14 $anonfun$resources$7_resource_this   Lscala/util/Using$;
           44     314    15 $anonfun$resources$7_resource_resource   Ljava/lang/Object;
          147      13    25 $anonfun$resources$8_resource_other   Ljava/lang/Throwable;
          204      13    25 $anonfun$resources$8_resource_other   Ljava/lang/Throwable;
           93     134    22 $anonfun$resources$8_resource_toThrow   Ljava/lang/Throwable;
           75     152    20 $anonfun$resources$8_resource_this   Lscala/util/Using$;
           75     152    21 $anonfun$resources$8_resource_resource   Ljava/lang/Object;
    MethodParameters:
      Name                           Flags
      resource2$3                    final
      resource3$2                    final
      resource4$1                    final
      body$3                         final
      evidence$12$1                  final
      evidence$11$1                  final
      evidence$10$1                  final
      r1                             final

  private scala.util.Using$();
    descriptor: ()V
    flags: (0x0002) ACC_PRIVATE
    Code:
      stack=1, locals=1, args_size=1
         0: aload_0
         1: invokespecial #247                // Method java/lang/Object."<init>":()V
         4: return
      LineNumberTable:
        line 104: 0
      LocalVariableTable:
        Start  Length  Slot  Name   Signature
            0       5     0  this   Lscala/util/Using$;
}
InnerClasses:
  public static #10= #7 of #9;            // Releasable=class scala/util/Using$Releasable of class scala/util/Using
SourceFile: "Using.scala"
  ScalaInlineInfo: length = 0x63 (unknown attribute)
   01 01 00 13 00 23 00 24 01 00 C9 00 CA 01 00 C4
   00 C5 01 00 D8 00 D9 01 00 D4 00 D5 01 00 CE 00
   CF 01 00 EF 00 F0 01 00 EB 00 EC 01 00 E7 00 E8
   01 00 E0 00 E1 01 00 0F 00 0E 01 00 14 00 15 01
   00 17 00 57 01 00 6D 00 96 01 00 6D 00 82 01 00
   6D 00 6E 01 00 4C 00 4D 01 00 50 00 51 01 00 C2
   00 4D 05
  Scala: length = 0x0 (unknown attribute)

