Classfile /Users/mw/Projects/slang-braindump/.jar/jar11/assemble/slang-braindump/assemble/content/com/fasterxml/jackson/databind/deser/std/StackTraceElementDeserializer.class
  Last modified May 29, 2022; size 4622 bytes
  SHA-256 checksum 75d7958ff0e847352f26effa034f48706ca8b992cbff308d067337758ffc20e3
  Compiled from "StackTraceElementDeserializer.java"
public class com.fasterxml.jackson.databind.deser.std.StackTraceElementDeserializer extends com.fasterxml.jackson.databind.deser.std.StdScalarDeserializer<java.lang.StackTraceElement>
  minor version: 0
  major version: 52
  flags: (0x0021) ACC_PUBLIC, ACC_SUPER
  this_class: #37                         // com/fasterxml/jackson/databind/deser/std/StackTraceElementDeserializer
  super_class: #38                        // com/fasterxml/jackson/databind/deser/std/StdScalarDeserializer
  interfaces: 0, fields: 1, methods: 5, attributes: 2
Constant pool:
    #1 = Class              #92           // java/lang/StackTraceElement
    #2 = Methodref          #38.#93       // com/fasterxml/jackson/databind/deser/std/StdScalarDeserializer."<init>":(Ljava/lang/Class;)V
    #3 = Methodref          #94.#95       // com/fasterxml/jackson/core/JsonParser.currentToken:()Lcom/fasterxml/jackson/core/JsonToken;
    #4 = Fieldref           #96.#97       // com/fasterxml/jackson/core/JsonToken.START_OBJECT:Lcom/fasterxml/jackson/core/JsonToken;
    #5 = String             #98           //
    #6 = Methodref          #94.#99       // com/fasterxml/jackson/core/JsonParser.nextValue:()Lcom/fasterxml/jackson/core/JsonToken;
    #7 = Fieldref           #96.#100      // com/fasterxml/jackson/core/JsonToken.END_OBJECT:Lcom/fasterxml/jackson/core/JsonToken;
    #8 = Methodref          #94.#101      // com/fasterxml/jackson/core/JsonParser.currentName:()Ljava/lang/String;
    #9 = String             #55           // className
   #10 = Methodref          #102.#103     // java/lang/String.equals:(Ljava/lang/Object;)Z
   #11 = Methodref          #94.#104      // com/fasterxml/jackson/core/JsonParser.getText:()Ljava/lang/String;
   #12 = String             #60           // classLoaderName
   #13 = String             #57           // fileName
   #14 = String             #61           // lineNumber
   #15 = Methodref          #96.#105      // com/fasterxml/jackson/core/JsonToken.isNumeric:()Z
   #16 = Methodref          #94.#106      // com/fasterxml/jackson/core/JsonParser.getIntValue:()I
   #17 = Methodref          #37.#107      // com/fasterxml/jackson/databind/deser/std/StackTraceElementDeserializer._parseIntPrimitive:(Lcom/fasterxml/jackson/core/JsonParser;Lcom/fasterxml/jackson/databind/DeserializationContext;)I
   #18 = String             #56           // methodName
   #19 = String             #108          // nativeMethod
   #20 = String             #58           // moduleName
   #21 = String             #59           // moduleVersion
   #22 = String             #109          // declaringClass
   #23 = String             #110          // format
   #24 = Fieldref           #37.#111      // com/fasterxml/jackson/databind/deser/std/StackTraceElementDeserializer._valueClass:Ljava/lang/Class;
   #25 = Methodref          #37.#112      // com/fasterxml/jackson/databind/deser/std/StackTraceElementDeserializer.handleUnknownProperty:(Lcom/fasterxml/jackson/core/JsonParser;Lcom/fasterxml/jackson/databind/DeserializationContext;Ljava/lang/Object;Ljava/lang/String;)V
   #26 = Methodref          #94.#113      // com/fasterxml/jackson/core/JsonParser.skipChildren:()Lcom/fasterxml/jackson/core/JsonParser;
   #27 = Methodref          #37.#114      // com/fasterxml/jackson/databind/deser/std/StackTraceElementDeserializer.constructValue:(Lcom/fasterxml/jackson/databind/DeserializationContext;Ljava/lang/String;Ljava/lang/String;Ljava/lang/String;ILjava/lang/String;Ljava/lang/String;Ljava/lang/String;)Ljava/lang/StackTraceElement;
   #28 = Fieldref           #96.#115      // com/fasterxml/jackson/core/JsonToken.START_ARRAY:Lcom/fasterxml/jackson/core/JsonToken;
   #29 = Fieldref           #116.#117     // com/fasterxml/jackson/databind/DeserializationFeature.UNWRAP_SINGLE_VALUE_ARRAYS:Lcom/fasterxml/jackson/databind/DeserializationFeature;
   #30 = Methodref          #118.#119     // com/fasterxml/jackson/databind/DeserializationContext.isEnabled:(Lcom/fasterxml/jackson/databind/DeserializationFeature;)Z
   #31 = Methodref          #94.#120      // com/fasterxml/jackson/core/JsonParser.nextToken:()Lcom/fasterxml/jackson/core/JsonToken;
   #32 = Methodref          #37.#121      // com/fasterxml/jackson/databind/deser/std/StackTraceElementDeserializer.deserialize:(Lcom/fasterxml/jackson/core/JsonParser;Lcom/fasterxml/jackson/databind/DeserializationContext;)Ljava/lang/StackTraceElement;
   #33 = Fieldref           #96.#122      // com/fasterxml/jackson/core/JsonToken.END_ARRAY:Lcom/fasterxml/jackson/core/JsonToken;
   #34 = Methodref          #37.#123      // com/fasterxml/jackson/databind/deser/std/StackTraceElementDeserializer.handleMissingEndArrayForSingle:(Lcom/fasterxml/jackson/core/JsonParser;Lcom/fasterxml/jackson/databind/DeserializationContext;)V
   #35 = Methodref          #118.#124     // com/fasterxml/jackson/databind/DeserializationContext.handleUnexpectedToken:(Ljava/lang/Class;Lcom/fasterxml/jackson/core/JsonParser;)Ljava/lang/Object;
   #36 = Methodref          #1.#125       // java/lang/StackTraceElement."<init>":(Ljava/lang/String;Ljava/lang/String;Ljava/lang/String;I)V
   #37 = Class              #126          // com/fasterxml/jackson/databind/deser/std/StackTraceElementDeserializer
   #38 = Class              #127          // com/fasterxml/jackson/databind/deser/std/StdScalarDeserializer
   #39 = Utf8               serialVersionUID
   #40 = Utf8               J
   #41 = Utf8               ConstantValue
   #42 = Long               1l
   #44 = Utf8               <init>
   #45 = Utf8               ()V
   #46 = Utf8               Code
   #47 = Utf8               LineNumberTable
   #48 = Utf8               LocalVariableTable
   #49 = Utf8               this
   #50 = Utf8               Lcom/fasterxml/jackson/databind/deser/std/StackTraceElementDeserializer;
   #51 = Utf8               deserialize
   #52 = Utf8               (Lcom/fasterxml/jackson/core/JsonParser;Lcom/fasterxml/jackson/databind/DeserializationContext;)Ljava/lang/StackTraceElement;
   #53 = Utf8               propName
   #54 = Utf8               Ljava/lang/String;
   #55 = Utf8               className
   #56 = Utf8               methodName
   #57 = Utf8               fileName
   #58 = Utf8               moduleName
   #59 = Utf8               moduleVersion
   #60 = Utf8               classLoaderName
   #61 = Utf8               lineNumber
   #62 = Utf8               I
   #63 = Utf8               value
   #64 = Utf8               Ljava/lang/StackTraceElement;
   #65 = Utf8               p
   #66 = Utf8               Lcom/fasterxml/jackson/core/JsonParser;
   #67 = Utf8               ctxt
   #68 = Utf8               Lcom/fasterxml/jackson/databind/DeserializationContext;
   #69 = Utf8               t
   #70 = Utf8               Lcom/fasterxml/jackson/core/JsonToken;
   #71 = Utf8               StackMapTable
   #72 = Class              #126          // com/fasterxml/jackson/databind/deser/std/StackTraceElementDeserializer
   #73 = Class              #128          // com/fasterxml/jackson/core/JsonParser
   #74 = Class              #129          // com/fasterxml/jackson/databind/DeserializationContext
   #75 = Class              #130          // com/fasterxml/jackson/core/JsonToken
   #76 = Class              #131          // java/lang/String
   #77 = Class              #92           // java/lang/StackTraceElement
   #78 = Utf8               Exceptions
   #79 = Class              #132          // java/io/IOException
   #80 = Utf8               constructValue
   #81 = Utf8               (Lcom/fasterxml/jackson/databind/DeserializationContext;Ljava/lang/String;Ljava/lang/String;Ljava/lang/String;ILjava/lang/String;Ljava/lang/String;)Ljava/lang/StackTraceElement;
   #82 = Utf8               Deprecated
   #83 = Utf8               RuntimeVisibleAnnotations
   #84 = Utf8               Ljava/lang/Deprecated;
   #85 = Utf8               (Lcom/fasterxml/jackson/databind/DeserializationContext;Ljava/lang/String;Ljava/lang/String;Ljava/lang/String;ILjava/lang/String;Ljava/lang/String;Ljava/lang/String;)Ljava/lang/StackTraceElement;
   #86 = Utf8               (Lcom/fasterxml/jackson/core/JsonParser;Lcom/fasterxml/jackson/databind/DeserializationContext;)Ljava/lang/Object;
   #87 = Class              #133          // com/fasterxml/jackson/core/JacksonException
   #88 = Utf8               Signature
   #89 = Utf8               Lcom/fasterxml/jackson/databind/deser/std/StdScalarDeserializer<Ljava/lang/StackTraceElement;>;
   #90 = Utf8               SourceFile
   #91 = Utf8               StackTraceElementDeserializer.java
   #92 = Utf8               java/lang/StackTraceElement
   #93 = NameAndType        #44:#134      // "<init>":(Ljava/lang/Class;)V
   #94 = Class              #128          // com/fasterxml/jackson/core/JsonParser
   #95 = NameAndType        #135:#136     // currentToken:()Lcom/fasterxml/jackson/core/JsonToken;
   #96 = Class              #130          // com/fasterxml/jackson/core/JsonToken
   #97 = NameAndType        #137:#70      // START_OBJECT:Lcom/fasterxml/jackson/core/JsonToken;
   #98 = Utf8
   #99 = NameAndType        #138:#136     // nextValue:()Lcom/fasterxml/jackson/core/JsonToken;
  #100 = NameAndType        #139:#70      // END_OBJECT:Lcom/fasterxml/jackson/core/JsonToken;
  #101 = NameAndType        #140:#141     // currentName:()Ljava/lang/String;
  #102 = Class              #131          // java/lang/String
  #103 = NameAndType        #142:#143     // equals:(Ljava/lang/Object;)Z
  #104 = NameAndType        #144:#141     // getText:()Ljava/lang/String;
  #105 = NameAndType        #145:#146     // isNumeric:()Z
  #106 = NameAndType        #147:#148     // getIntValue:()I
  #107 = NameAndType        #149:#150     // _parseIntPrimitive:(Lcom/fasterxml/jackson/core/JsonParser;Lcom/fasterxml/jackson/databind/DeserializationContext;)I
  #108 = Utf8               nativeMethod
  #109 = Utf8               declaringClass
  #110 = Utf8               format
  #111 = NameAndType        #151:#152     // _valueClass:Ljava/lang/Class;
  #112 = NameAndType        #153:#154     // handleUnknownProperty:(Lcom/fasterxml/jackson/core/JsonParser;Lcom/fasterxml/jackson/databind/DeserializationContext;Ljava/lang/Object;Ljava/lang/String;)V
  #113 = NameAndType        #155:#156     // skipChildren:()Lcom/fasterxml/jackson/core/JsonParser;
  #114 = NameAndType        #80:#85       // constructValue:(Lcom/fasterxml/jackson/databind/DeserializationContext;Ljava/lang/String;Ljava/lang/String;Ljava/lang/String;ILjava/lang/String;Ljava/lang/String;Ljava/lang/String;)Ljava/lang/StackTraceElement;
  #115 = NameAndType        #157:#70      // START_ARRAY:Lcom/fasterxml/jackson/core/JsonToken;
  #116 = Class              #158          // com/fasterxml/jackson/databind/DeserializationFeature
  #117 = NameAndType        #159:#160     // UNWRAP_SINGLE_VALUE_ARRAYS:Lcom/fasterxml/jackson/databind/DeserializationFeature;
  #118 = Class              #129          // com/fasterxml/jackson/databind/DeserializationContext
  #119 = NameAndType        #161:#162     // isEnabled:(Lcom/fasterxml/jackson/databind/DeserializationFeature;)Z
  #120 = NameAndType        #163:#136     // nextToken:()Lcom/fasterxml/jackson/core/JsonToken;
  #121 = NameAndType        #51:#52       // deserialize:(Lcom/fasterxml/jackson/core/JsonParser;Lcom/fasterxml/jackson/databind/DeserializationContext;)Ljava/lang/StackTraceElement;
  #122 = NameAndType        #164:#70      // END_ARRAY:Lcom/fasterxml/jackson/core/JsonToken;
  #123 = NameAndType        #165:#166     // handleMissingEndArrayForSingle:(Lcom/fasterxml/jackson/core/JsonParser;Lcom/fasterxml/jackson/databind/DeserializationContext;)V
  #124 = NameAndType        #167:#168     // handleUnexpectedToken:(Ljava/lang/Class;Lcom/fasterxml/jackson/core/JsonParser;)Ljava/lang/Object;
  #125 = NameAndType        #44:#169      // "<init>":(Ljava/lang/String;Ljava/lang/String;Ljava/lang/String;I)V
  #126 = Utf8               com/fasterxml/jackson/databind/deser/std/StackTraceElementDeserializer
  #127 = Utf8               com/fasterxml/jackson/databind/deser/std/StdScalarDeserializer
  #128 = Utf8               com/fasterxml/jackson/core/JsonParser
  #129 = Utf8               com/fasterxml/jackson/databind/DeserializationContext
  #130 = Utf8               com/fasterxml/jackson/core/JsonToken
  #131 = Utf8               java/lang/String
  #132 = Utf8               java/io/IOException
  #133 = Utf8               com/fasterxml/jackson/core/JacksonException
  #134 = Utf8               (Ljava/lang/Class;)V
  #135 = Utf8               currentToken
  #136 = Utf8               ()Lcom/fasterxml/jackson/core/JsonToken;
  #137 = Utf8               START_OBJECT
  #138 = Utf8               nextValue
  #139 = Utf8               END_OBJECT
  #140 = Utf8               currentName
  #141 = Utf8               ()Ljava/lang/String;
  #142 = Utf8               equals
  #143 = Utf8               (Ljava/lang/Object;)Z
  #144 = Utf8               getText
  #145 = Utf8               isNumeric
  #146 = Utf8               ()Z
  #147 = Utf8               getIntValue
  #148 = Utf8               ()I
  #149 = Utf8               _parseIntPrimitive
  #150 = Utf8               (Lcom/fasterxml/jackson/core/JsonParser;Lcom/fasterxml/jackson/databind/DeserializationContext;)I
  #151 = Utf8               _valueClass
  #152 = Utf8               Ljava/lang/Class;
  #153 = Utf8               handleUnknownProperty
  #154 = Utf8               (Lcom/fasterxml/jackson/core/JsonParser;Lcom/fasterxml/jackson/databind/DeserializationContext;Ljava/lang/Object;Ljava/lang/String;)V
  #155 = Utf8               skipChildren
  #156 = Utf8               ()Lcom/fasterxml/jackson/core/JsonParser;
  #157 = Utf8               START_ARRAY
  #158 = Utf8               com/fasterxml/jackson/databind/DeserializationFeature
  #159 = Utf8               UNWRAP_SINGLE_VALUE_ARRAYS
  #160 = Utf8               Lcom/fasterxml/jackson/databind/DeserializationFeature;
  #161 = Utf8               isEnabled
  #162 = Utf8               (Lcom/fasterxml/jackson/databind/DeserializationFeature;)Z
  #163 = Utf8               nextToken
  #164 = Utf8               END_ARRAY
  #165 = Utf8               handleMissingEndArrayForSingle
  #166 = Utf8               (Lcom/fasterxml/jackson/core/JsonParser;Lcom/fasterxml/jackson/databind/DeserializationContext;)V
  #167 = Utf8               handleUnexpectedToken
  #168 = Utf8               (Ljava/lang/Class;Lcom/fasterxml/jackson/core/JsonParser;)Ljava/lang/Object;
  #169 = Utf8               (Ljava/lang/String;Ljava/lang/String;Ljava/lang/String;I)V
{
  private static final long serialVersionUID;
    descriptor: J
    flags: (0x001a) ACC_PRIVATE, ACC_STATIC, ACC_FINAL
    ConstantValue: long 1l

  public com.fasterxml.jackson.databind.deser.std.StackTraceElementDeserializer();
    descriptor: ()V
    flags: (0x0001) ACC_PUBLIC
    Code:
      stack=2, locals=1, args_size=1
         0: aload_0
         1: ldc           #1                  // class java/lang/StackTraceElement
         3: invokespecial #2                  // Method com/fasterxml/jackson/databind/deser/std/StdScalarDeserializer."<init>":(Ljava/lang/Class;)V
         6: return
      LineNumberTable:
        line 16: 0
      LocalVariableTable:
        Start  Length  Slot  Name   Signature
            0       7     0  this   Lcom/fasterxml/jackson/databind/deser/std/StackTraceElementDeserializer;

  public java.lang.StackTraceElement deserialize(com.fasterxml.jackson.core.JsonParser, com.fasterxml.jackson.databind.DeserializationContext) throws java.io.IOException;
    descriptor: (Lcom/fasterxml/jackson/core/JsonParser;Lcom/fasterxml/jackson/databind/DeserializationContext;)Ljava/lang/StackTraceElement;
    flags: (0x0001) ACC_PUBLIC
    Code:
      stack=9, locals=12, args_size=3
         0: aload_1
         1: invokevirtual #3                  // Method com/fasterxml/jackson/core/JsonParser.currentToken:()Lcom/fasterxml/jackson/core/JsonToken;
         4: astore_3
         5: aload_3
         6: getstatic     #4                  // Field com/fasterxml/jackson/core/JsonToken.START_OBJECT:Lcom/fasterxml/jackson/core/JsonToken;
         9: if_acmpne     281
        12: ldc           #5                  // String
        14: astore        4
        16: ldc           #5                  // String
        18: astore        5
        20: ldc           #5                  // String
        22: astore        6
        24: aconst_null
        25: astore        7
        27: aconst_null
        28: astore        8
        30: aconst_null
        31: astore        9
        33: iconst_m1
        34: istore        10
        36: aload_1
        37: invokevirtual #6                  // Method com/fasterxml/jackson/core/JsonParser.nextValue:()Lcom/fasterxml/jackson/core/JsonToken;
        40: dup
        41: astore_3
        42: getstatic     #7                  // Field com/fasterxml/jackson/core/JsonToken.END_OBJECT:Lcom/fasterxml/jackson/core/JsonToken;
        45: if_acmpeq     261
        48: aload_1
        49: invokevirtual #8                  // Method com/fasterxml/jackson/core/JsonParser.currentName:()Ljava/lang/String;
        52: astore        11
        54: ldc           #9                  // String className
        56: aload         11
        58: invokevirtual #10                 // Method java/lang/String.equals:(Ljava/lang/Object;)Z
        61: ifeq          73
        64: aload_1
        65: invokevirtual #11                 // Method com/fasterxml/jackson/core/JsonParser.getText:()Ljava/lang/String;
        68: astore        4
        70: goto          253
        73: ldc           #12                 // String classLoaderName
        75: aload         11
        77: invokevirtual #10                 // Method java/lang/String.equals:(Ljava/lang/Object;)Z
        80: ifeq          92
        83: aload_1
        84: invokevirtual #11                 // Method com/fasterxml/jackson/core/JsonParser.getText:()Ljava/lang/String;
        87: astore        9
        89: goto          253
        92: ldc           #13                 // String fileName
        94: aload         11
        96: invokevirtual #10                 // Method java/lang/String.equals:(Ljava/lang/Object;)Z
        99: ifeq          111
       102: aload_1
       103: invokevirtual #11                 // Method com/fasterxml/jackson/core/JsonParser.getText:()Ljava/lang/String;
       106: astore        6
       108: goto          253
       111: ldc           #14                 // String lineNumber
       113: aload         11
       115: invokevirtual #10                 // Method java/lang/String.equals:(Ljava/lang/Object;)Z
       118: ifeq          148
       121: aload_3
       122: invokevirtual #15                 // Method com/fasterxml/jackson/core/JsonToken.isNumeric:()Z
       125: ifeq          137
       128: aload_1
       129: invokevirtual #16                 // Method com/fasterxml/jackson/core/JsonParser.getIntValue:()I
       132: istore        10
       134: goto          253
       137: aload_0
       138: aload_1
       139: aload_2
       140: invokevirtual #17                 // Method _parseIntPrimitive:(Lcom/fasterxml/jackson/core/JsonParser;Lcom/fasterxml/jackson/databind/DeserializationContext;)I
       143: istore        10
       145: goto          253
       148: ldc           #18                 // String methodName
       150: aload         11
       152: invokevirtual #10                 // Method java/lang/String.equals:(Ljava/lang/Object;)Z
       155: ifeq          167
       158: aload_1
       159: invokevirtual #11                 // Method com/fasterxml/jackson/core/JsonParser.getText:()Ljava/lang/String;
       162: astore        5
       164: goto          253
       167: ldc           #19                 // String nativeMethod
       169: aload         11
       171: invokevirtual #10                 // Method java/lang/String.equals:(Ljava/lang/Object;)Z
       174: ifeq          180
       177: goto          253
       180: ldc           #20                 // String moduleName
       182: aload         11
       184: invokevirtual #10                 // Method java/lang/String.equals:(Ljava/lang/Object;)Z
       187: ifeq          199
       190: aload_1
       191: invokevirtual #11                 // Method com/fasterxml/jackson/core/JsonParser.getText:()Ljava/lang/String;
       194: astore        7
       196: goto          253
       199: ldc           #21                 // String moduleVersion
       201: aload         11
       203: invokevirtual #10                 // Method java/lang/String.equals:(Ljava/lang/Object;)Z
       206: ifeq          218
       209: aload_1
       210: invokevirtual #11                 // Method com/fasterxml/jackson/core/JsonParser.getText:()Ljava/lang/String;
       213: astore        8
       215: goto          253
       218: ldc           #22                 // String declaringClass
       220: aload         11
       222: invokevirtual #10                 // Method java/lang/String.equals:(Ljava/lang/Object;)Z
       225: ifne          253
       228: ldc           #23                 // String format
       230: aload         11
       232: invokevirtual #10                 // Method java/lang/String.equals:(Ljava/lang/Object;)Z
       235: ifeq          241
       238: goto          253
       241: aload_0
       242: aload_1
       243: aload_2
       244: aload_0
       245: getfield      #24                 // Field _valueClass:Ljava/lang/Class;
       248: aload         11
       250: invokevirtual #25                 // Method handleUnknownProperty:(Lcom/fasterxml/jackson/core/JsonParser;Lcom/fasterxml/jackson/databind/DeserializationContext;Ljava/lang/Object;Ljava/lang/String;)V
       253: aload_1
       254: invokevirtual #26                 // Method com/fasterxml/jackson/core/JsonParser.skipChildren:()Lcom/fasterxml/jackson/core/JsonParser;
       257: pop
       258: goto          36
       261: aload_0
       262: aload_2
       263: aload         4
       265: aload         5
       267: aload         6
       269: iload         10
       271: aload         7
       273: aload         8
       275: aload         9
       277: invokevirtual #27                 // Method constructValue:(Lcom/fasterxml/jackson/databind/DeserializationContext;Ljava/lang/String;Ljava/lang/String;Ljava/lang/String;ILjava/lang/String;Ljava/lang/String;Ljava/lang/String;)Ljava/lang/StackTraceElement;
       280: areturn
       281: aload_3
       282: getstatic     #28                 // Field com/fasterxml/jackson/core/JsonToken.START_ARRAY:Lcom/fasterxml/jackson/core/JsonToken;
       285: if_acmpne     330
       288: aload_2
       289: getstatic     #29                 // Field com/fasterxml/jackson/databind/DeserializationFeature.UNWRAP_SINGLE_VALUE_ARRAYS:Lcom/fasterxml/jackson/databind/DeserializationFeature;
       292: invokevirtual #30                 // Method com/fasterxml/jackson/databind/DeserializationContext.isEnabled:(Lcom/fasterxml/jackson/databind/DeserializationFeature;)Z
       295: ifeq          330
       298: aload_1
       299: invokevirtual #31                 // Method com/fasterxml/jackson/core/JsonParser.nextToken:()Lcom/fasterxml/jackson/core/JsonToken;
       302: pop
       303: aload_0
       304: aload_1
       305: aload_2
       306: invokevirtual #32                 // Method deserialize:(Lcom/fasterxml/jackson/core/JsonParser;Lcom/fasterxml/jackson/databind/DeserializationContext;)Ljava/lang/StackTraceElement;
       309: astore        4
       311: aload_1
       312: invokevirtual #31                 // Method com/fasterxml/jackson/core/JsonParser.nextToken:()Lcom/fasterxml/jackson/core/JsonToken;
       315: getstatic     #33                 // Field com/fasterxml/jackson/core/JsonToken.END_ARRAY:Lcom/fasterxml/jackson/core/JsonToken;
       318: if_acmpeq     327
       321: aload_0
       322: aload_1
       323: aload_2
       324: invokevirtual #34                 // Method handleMissingEndArrayForSingle:(Lcom/fasterxml/jackson/core/JsonParser;Lcom/fasterxml/jackson/databind/DeserializationContext;)V
       327: aload         4
       329: areturn
       330: aload_2
       331: aload_0
       332: getfield      #24                 // Field _valueClass:Ljava/lang/Class;
       335: aload_1
       336: invokevirtual #35                 // Method com/fasterxml/jackson/databind/DeserializationContext.handleUnexpectedToken:(Ljava/lang/Class;Lcom/fasterxml/jackson/core/JsonParser;)Ljava/lang/Object;
       339: checkcast     #1                  // class java/lang/StackTraceElement
       342: areturn
      LineNumberTable:
        line 21: 0
        line 23: 5
        line 24: 12
        line 26: 24
        line 27: 30
        line 28: 33
        line 30: 36
        line 31: 48
        line 33: 54
        line 34: 64
        line 35: 73
        line 36: 83
        line 37: 92
        line 38: 102
        line 39: 111
        line 40: 121
        line 41: 128
        line 43: 137
        line 45: 148
        line 46: 158
        line 47: 167
        line 49: 180
        line 50: 190
        line 51: 199
        line 52: 209
        line 53: 218
        line 54: 232
        line 58: 241
        line 60: 253
        line 61: 258
        line 62: 261
        line 64: 281
        line 65: 298
        line 66: 303
        line 67: 311
        line 68: 321
        line 70: 327
        line 72: 330
      LocalVariableTable:
        Start  Length  Slot  Name   Signature
           54     204    11 propName   Ljava/lang/String;
           16     265     4 className   Ljava/lang/String;
           20     261     5 methodName   Ljava/lang/String;
           24     257     6 fileName   Ljava/lang/String;
           27     254     7 moduleName   Ljava/lang/String;
           30     251     8 moduleVersion   Ljava/lang/String;
           33     248     9 classLoaderName   Ljava/lang/String;
           36     245    10 lineNumber   I
          311      19     4 value   Ljava/lang/StackTraceElement;
            0     343     0  this   Lcom/fasterxml/jackson/databind/deser/std/StackTraceElementDeserializer;
            0     343     1     p   Lcom/fasterxml/jackson/core/JsonParser;
            0     343     2  ctxt   Lcom/fasterxml/jackson/databind/DeserializationContext;
            5     338     3     t   Lcom/fasterxml/jackson/core/JsonToken;
      StackMapTable: number_of_entries = 16
        frame_type = 255 /* full_frame */
          offset_delta = 36
          locals = [ class com/fasterxml/jackson/databind/deser/std/StackTraceElementDeserializer, class com/fasterxml/jackson/core/JsonParser, class com/fasterxml/jackson/databind/DeserializationContext, class com/fasterxml/jackson/core/JsonToken, class java/lang/String, class java/lang/String, class java/lang/String, class java/lang/String, class java/lang/String, class java/lang/String, int ]
          stack = []
        frame_type = 252 /* append */
          offset_delta = 36
          locals = [ class java/lang/String ]
        frame_type = 18 /* same */
        frame_type = 18 /* same */
        frame_type = 25 /* same */
        frame_type = 10 /* same */
        frame_type = 18 /* same */
        frame_type = 12 /* same */
        frame_type = 18 /* same */
        frame_type = 18 /* same */
        frame_type = 22 /* same */
        frame_type = 11 /* same */
        frame_type = 250 /* chop */
          offset_delta = 7
        frame_type = 255 /* full_frame */
          offset_delta = 19
          locals = [ class com/fasterxml/jackson/databind/deser/std/StackTraceElementDeserializer, class com/fasterxml/jackson/core/JsonParser, class com/fasterxml/jackson/databind/DeserializationContext, class com/fasterxml/jackson/core/JsonToken ]
          stack = []
        frame_type = 252 /* append */
          offset_delta = 45
          locals = [ class java/lang/StackTraceElement ]
        frame_type = 250 /* chop */
          offset_delta = 2
    Exceptions:
      throws java.io.IOException

  protected java.lang.StackTraceElement constructValue(com.fasterxml.jackson.databind.DeserializationContext, java.lang.String, java.lang.String, java.lang.String, int, java.lang.String, java.lang.String);
    descriptor: (Lcom/fasterxml/jackson/databind/DeserializationContext;Ljava/lang/String;Ljava/lang/String;Ljava/lang/String;ILjava/lang/String;Ljava/lang/String;)Ljava/lang/StackTraceElement;
    flags: (0x0004) ACC_PROTECTED
    Code:
      stack=9, locals=8, args_size=8
         0: aload_0
         1: aload_1
         2: aload_2
         3: aload_3
         4: aload         4
         6: iload         5
         8: aload         6
        10: aload         7
        12: aconst_null
        13: invokevirtual #27                 // Method constructValue:(Lcom/fasterxml/jackson/databind/DeserializationContext;Ljava/lang/String;Ljava/lang/String;Ljava/lang/String;ILjava/lang/String;Ljava/lang/String;Ljava/lang/String;)Ljava/lang/StackTraceElement;
        16: areturn
      LineNumberTable:
        line 79: 0
      LocalVariableTable:
        Start  Length  Slot  Name   Signature
            0      17     0  this   Lcom/fasterxml/jackson/databind/deser/std/StackTraceElementDeserializer;
            0      17     1  ctxt   Lcom/fasterxml/jackson/databind/DeserializationContext;
            0      17     2 className   Ljava/lang/String;
            0      17     3 methodName   Ljava/lang/String;
            0      17     4 fileName   Ljava/lang/String;
            0      17     5 lineNumber   I
            0      17     6 moduleName   Ljava/lang/String;
            0      17     7 moduleVersion   Ljava/lang/String;
    Deprecated: true
    RuntimeVisibleAnnotations:
      0: #84()
        java.lang.Deprecated

  protected java.lang.StackTraceElement constructValue(com.fasterxml.jackson.databind.DeserializationContext, java.lang.String, java.lang.String, java.lang.String, int, java.lang.String, java.lang.String, java.lang.String);
    descriptor: (Lcom/fasterxml/jackson/databind/DeserializationContext;Ljava/lang/String;Ljava/lang/String;Ljava/lang/String;ILjava/lang/String;Ljava/lang/String;Ljava/lang/String;)Ljava/lang/StackTraceElement;
    flags: (0x0004) ACC_PROTECTED
    Code:
      stack=6, locals=9, args_size=9
         0: new           #1                  // class java/lang/StackTraceElement
         3: dup
         4: aload_2
         5: aload_3
         6: aload         4
         8: iload         5
        10: invokespecial #36                 // Method java/lang/StackTraceElement."<init>":(Ljava/lang/String;Ljava/lang/String;Ljava/lang/String;I)V
        13: areturn
      LineNumberTable:
        line 94: 0
      LocalVariableTable:
        Start  Length  Slot  Name   Signature
            0      14     0  this   Lcom/fasterxml/jackson/databind/deser/std/StackTraceElementDeserializer;
            0      14     1  ctxt   Lcom/fasterxml/jackson/databind/DeserializationContext;
            0      14     2 className   Ljava/lang/String;
            0      14     3 methodName   Ljava/lang/String;
            0      14     4 fileName   Ljava/lang/String;
            0      14     5 lineNumber   I
            0      14     6 moduleName   Ljava/lang/String;
            0      14     7 moduleVersion   Ljava/lang/String;
            0      14     8 classLoaderName   Ljava/lang/String;

  public java.lang.Object deserialize(com.fasterxml.jackson.core.JsonParser, com.fasterxml.jackson.databind.DeserializationContext) throws java.io.IOException, com.fasterxml.jackson.core.JacksonException;
    descriptor: (Lcom/fasterxml/jackson/core/JsonParser;Lcom/fasterxml/jackson/databind/DeserializationContext;)Ljava/lang/Object;
    flags: (0x1041) ACC_PUBLIC, ACC_BRIDGE, ACC_SYNTHETIC
    Code:
      stack=3, locals=3, args_size=3
         0: aload_0
         1: aload_1
         2: aload_2
         3: invokevirtual #32                 // Method deserialize:(Lcom/fasterxml/jackson/core/JsonParser;Lcom/fasterxml/jackson/databind/DeserializationContext;)Ljava/lang/StackTraceElement;
         6: areturn
      LineNumberTable:
        line 11: 0
      LocalVariableTable:
        Start  Length  Slot  Name   Signature
            0       7     0  this   Lcom/fasterxml/jackson/databind/deser/std/StackTraceElementDeserializer;
    Exceptions:
      throws java.io.IOException, com.fasterxml.jackson.core.JacksonException
}
Signature: #89                          // Lcom/fasterxml/jackson/databind/deser/std/StdScalarDeserializer<Ljava/lang/StackTraceElement;>;
SourceFile: "StackTraceElementDeserializer.java"
