Classfile /Users/mw/Projects/slang-braindump/.jar/jar11/assemble/slang-braindump/assemble/content/com/fasterxml/jackson/databind/deser/std/StdNodeBasedDeserializer.class
  Last modified May 29, 2022; size 3664 bytes
  SHA-256 checksum e52601018fc0208910694ac5c03285b6556c7f8aabce90a06a6346f4c02c8fc3
  Compiled from "StdNodeBasedDeserializer.java"
public abstract class com.fasterxml.jackson.databind.deser.std.StdNodeBasedDeserializer<T extends java.lang.Object> extends com.fasterxml.jackson.databind.deser.std.StdDeserializer<T> implements com.fasterxml.jackson.databind.deser.ResolvableDeserializer
  minor version: 0
  major version: 52
  flags: (0x0421) ACC_PUBLIC, ACC_SUPER, ACC_ABSTRACT
  this_class: #11                         // com/fasterxml/jackson/databind/deser/std/StdNodeBasedDeserializer
  super_class: #12                        // com/fasterxml/jackson/databind/deser/std/StdDeserializer
  interfaces: 1, fields: 2, methods: 7, attributes: 2
Constant pool:
   #1 = Methodref          #12.#66        // com/fasterxml/jackson/databind/deser/std/StdDeserializer."<init>":(Lcom/fasterxml/jackson/databind/JavaType;)V
   #2 = Methodref          #12.#67        // com/fasterxml/jackson/databind/deser/std/StdDeserializer."<init>":(Ljava/lang/Class;)V
   #3 = Methodref          #12.#68        // com/fasterxml/jackson/databind/deser/std/StdDeserializer."<init>":(Lcom/fasterxml/jackson/databind/deser/std/StdDeserializer;)V
   #4 = Fieldref           #11.#69        // com/fasterxml/jackson/databind/deser/std/StdNodeBasedDeserializer._treeDeserializer:Lcom/fasterxml/jackson/databind/JsonDeserializer;
   #5 = Class              #70            // com/fasterxml/jackson/databind/JsonNode
   #6 = Methodref          #71.#72        // com/fasterxml/jackson/databind/DeserializationContext.constructType:(Ljava/lang/Class;)Lcom/fasterxml/jackson/databind/JavaType;
   #7 = Methodref          #71.#73        // com/fasterxml/jackson/databind/DeserializationContext.findRootValueDeserializer:(Lcom/fasterxml/jackson/databind/JavaType;)Lcom/fasterxml/jackson/databind/JsonDeserializer;
   #8 = Methodref          #74.#75        // com/fasterxml/jackson/databind/JsonDeserializer.deserialize:(Lcom/fasterxml/jackson/core/JsonParser;Lcom/fasterxml/jackson/databind/DeserializationContext;)Ljava/lang/Object;
   #9 = Methodref          #11.#76        // com/fasterxml/jackson/databind/deser/std/StdNodeBasedDeserializer.convert:(Lcom/fasterxml/jackson/databind/JsonNode;Lcom/fasterxml/jackson/databind/DeserializationContext;)Ljava/lang/Object;
  #10 = Methodref          #74.#77        // com/fasterxml/jackson/databind/JsonDeserializer.deserializeWithType:(Lcom/fasterxml/jackson/core/JsonParser;Lcom/fasterxml/jackson/databind/DeserializationContext;Lcom/fasterxml/jackson/databind/jsontype/TypeDeserializer;)Ljava/lang/Object;
  #11 = Class              #78            // com/fasterxml/jackson/databind/deser/std/StdNodeBasedDeserializer
  #12 = Class              #79            // com/fasterxml/jackson/databind/deser/std/StdDeserializer
  #13 = Class              #80            // com/fasterxml/jackson/databind/deser/ResolvableDeserializer
  #14 = Utf8               serialVersionUID
  #15 = Utf8               J
  #16 = Utf8               ConstantValue
  #17 = Long               1l
  #19 = Utf8               _treeDeserializer
  #20 = Utf8               Lcom/fasterxml/jackson/databind/JsonDeserializer;
  #21 = Utf8               Signature
  #22 = Utf8               Lcom/fasterxml/jackson/databind/JsonDeserializer<Ljava/lang/Object;>;
  #23 = Utf8               <init>
  #24 = Utf8               (Lcom/fasterxml/jackson/databind/JavaType;)V
  #25 = Utf8               Code
  #26 = Utf8               LineNumberTable
  #27 = Utf8               LocalVariableTable
  #28 = Utf8               this
  #29 = Utf8               Lcom/fasterxml/jackson/databind/deser/std/StdNodeBasedDeserializer;
  #30 = Utf8               targetType
  #31 = Utf8               Lcom/fasterxml/jackson/databind/JavaType;
  #32 = Utf8               LocalVariableTypeTable
  #33 = Utf8               Lcom/fasterxml/jackson/databind/deser/std/StdNodeBasedDeserializer<TT;>;
  #34 = Utf8               (Ljava/lang/Class;)V
  #35 = Utf8               Ljava/lang/Class;
  #36 = Utf8               Ljava/lang/Class<TT;>;
  #37 = Utf8               (Ljava/lang/Class<TT;>;)V
  #38 = Utf8               (Lcom/fasterxml/jackson/databind/deser/std/StdNodeBasedDeserializer;)V
  #39 = Utf8               src
  #40 = Utf8               Lcom/fasterxml/jackson/databind/deser/std/StdNodeBasedDeserializer<*>;
  #41 = Utf8               (Lcom/fasterxml/jackson/databind/deser/std/StdNodeBasedDeserializer<*>;)V
  #42 = Utf8               resolve
  #43 = Utf8               (Lcom/fasterxml/jackson/databind/DeserializationContext;)V
  #44 = Utf8               ctxt
  #45 = Utf8               Lcom/fasterxml/jackson/databind/DeserializationContext;
  #46 = Utf8               Exceptions
  #47 = Class              #81            // com/fasterxml/jackson/databind/JsonMappingException
  #48 = Utf8               convert
  #49 = Utf8               (Lcom/fasterxml/jackson/databind/JsonNode;Lcom/fasterxml/jackson/databind/DeserializationContext;)Ljava/lang/Object;
  #50 = Class              #82            // java/io/IOException
  #51 = Utf8               (Lcom/fasterxml/jackson/databind/JsonNode;Lcom/fasterxml/jackson/databind/DeserializationContext;)TT;
  #52 = Utf8               deserialize
  #53 = Utf8               (Lcom/fasterxml/jackson/core/JsonParser;Lcom/fasterxml/jackson/databind/DeserializationContext;)Ljava/lang/Object;
  #54 = Utf8               jp
  #55 = Utf8               Lcom/fasterxml/jackson/core/JsonParser;
  #56 = Utf8               n
  #57 = Utf8               Lcom/fasterxml/jackson/databind/JsonNode;
  #58 = Utf8               (Lcom/fasterxml/jackson/core/JsonParser;Lcom/fasterxml/jackson/databind/DeserializationContext;)TT;
  #59 = Utf8               deserializeWithType
  #60 = Utf8               (Lcom/fasterxml/jackson/core/JsonParser;Lcom/fasterxml/jackson/databind/DeserializationContext;Lcom/fasterxml/jackson/databind/jsontype/TypeDeserializer;)Ljava/lang/Object;
  #61 = Utf8               td
  #62 = Utf8               Lcom/fasterxml/jackson/databind/jsontype/TypeDeserializer;
  #63 = Utf8               <T:Ljava/lang/Object;>Lcom/fasterxml/jackson/databind/deser/std/StdDeserializer<TT;>;Lcom/fasterxml/jackson/databind/deser/ResolvableDeserializer;
  #64 = Utf8               SourceFile
  #65 = Utf8               StdNodeBasedDeserializer.java
  #66 = NameAndType        #23:#24        // "<init>":(Lcom/fasterxml/jackson/databind/JavaType;)V
  #67 = NameAndType        #23:#34        // "<init>":(Ljava/lang/Class;)V
  #68 = NameAndType        #23:#83        // "<init>":(Lcom/fasterxml/jackson/databind/deser/std/StdDeserializer;)V
  #69 = NameAndType        #19:#20        // _treeDeserializer:Lcom/fasterxml/jackson/databind/JsonDeserializer;
  #70 = Utf8               com/fasterxml/jackson/databind/JsonNode
  #71 = Class              #84            // com/fasterxml/jackson/databind/DeserializationContext
  #72 = NameAndType        #85:#86        // constructType:(Ljava/lang/Class;)Lcom/fasterxml/jackson/databind/JavaType;
  #73 = NameAndType        #87:#88        // findRootValueDeserializer:(Lcom/fasterxml/jackson/databind/JavaType;)Lcom/fasterxml/jackson/databind/JsonDeserializer;
  #74 = Class              #89            // com/fasterxml/jackson/databind/JsonDeserializer
  #75 = NameAndType        #52:#53        // deserialize:(Lcom/fasterxml/jackson/core/JsonParser;Lcom/fasterxml/jackson/databind/DeserializationContext;)Ljava/lang/Object;
  #76 = NameAndType        #48:#49        // convert:(Lcom/fasterxml/jackson/databind/JsonNode;Lcom/fasterxml/jackson/databind/DeserializationContext;)Ljava/lang/Object;
  #77 = NameAndType        #59:#60        // deserializeWithType:(Lcom/fasterxml/jackson/core/JsonParser;Lcom/fasterxml/jackson/databind/DeserializationContext;Lcom/fasterxml/jackson/databind/jsontype/TypeDeserializer;)Ljava/lang/Object;
  #78 = Utf8               com/fasterxml/jackson/databind/deser/std/StdNodeBasedDeserializer
  #79 = Utf8               com/fasterxml/jackson/databind/deser/std/StdDeserializer
  #80 = Utf8               com/fasterxml/jackson/databind/deser/ResolvableDeserializer
  #81 = Utf8               com/fasterxml/jackson/databind/JsonMappingException
  #82 = Utf8               java/io/IOException
  #83 = Utf8               (Lcom/fasterxml/jackson/databind/deser/std/StdDeserializer;)V
  #84 = Utf8               com/fasterxml/jackson/databind/DeserializationContext
  #85 = Utf8               constructType
  #86 = Utf8               (Ljava/lang/Class;)Lcom/fasterxml/jackson/databind/JavaType;
  #87 = Utf8               findRootValueDeserializer
  #88 = Utf8               (Lcom/fasterxml/jackson/databind/JavaType;)Lcom/fasterxml/jackson/databind/JsonDeserializer;
  #89 = Utf8               com/fasterxml/jackson/databind/JsonDeserializer
{
  private static final long serialVersionUID;
    descriptor: J
    flags: (0x001a) ACC_PRIVATE, ACC_STATIC, ACC_FINAL
    ConstantValue: long 1l

  protected com.fasterxml.jackson.databind.JsonDeserializer<java.lang.Object> _treeDeserializer;
    descriptor: Lcom/fasterxml/jackson/databind/JsonDeserializer;
    flags: (0x0004) ACC_PROTECTED
    Signature: #22                          // Lcom/fasterxml/jackson/databind/JsonDeserializer<Ljava/lang/Object;>;

  protected com.fasterxml.jackson.databind.deser.std.StdNodeBasedDeserializer(com.fasterxml.jackson.databind.JavaType);
    descriptor: (Lcom/fasterxml/jackson/databind/JavaType;)V
    flags: (0x0004) ACC_PROTECTED
    Code:
      stack=2, locals=2, args_size=2
         0: aload_0
         1: aload_1
         2: invokespecial #1                  // Method com/fasterxml/jackson/databind/deser/std/StdDeserializer."<init>":(Lcom/fasterxml/jackson/databind/JavaType;)V
         5: return
      LineNumberTable:
        line 35: 0
        line 36: 5
      LocalVariableTable:
        Start  Length  Slot  Name   Signature
            0       6     0  this   Lcom/fasterxml/jackson/databind/deser/std/StdNodeBasedDeserializer;
            0       6     1 targetType   Lcom/fasterxml/jackson/databind/JavaType;
      LocalVariableTypeTable:
        Start  Length  Slot  Name   Signature
            0       6     0  this   Lcom/fasterxml/jackson/databind/deser/std/StdNodeBasedDeserializer<TT;>;

  protected com.fasterxml.jackson.databind.deser.std.StdNodeBasedDeserializer(java.lang.Class<T>);
    descriptor: (Ljava/lang/Class;)V
    flags: (0x0004) ACC_PROTECTED
    Code:
      stack=2, locals=2, args_size=2
         0: aload_0
         1: aload_1
         2: invokespecial #2                  // Method com/fasterxml/jackson/databind/deser/std/StdDeserializer."<init>":(Ljava/lang/Class;)V
         5: return
      LineNumberTable:
        line 39: 0
        line 40: 5
      LocalVariableTable:
        Start  Length  Slot  Name   Signature
            0       6     0  this   Lcom/fasterxml/jackson/databind/deser/std/StdNodeBasedDeserializer;
            0       6     1 targetType   Ljava/lang/Class;
      LocalVariableTypeTable:
        Start  Length  Slot  Name   Signature
            0       6     0  this   Lcom/fasterxml/jackson/databind/deser/std/StdNodeBasedDeserializer<TT;>;
            0       6     1 targetType   Ljava/lang/Class<TT;>;
    Signature: #37                          // (Ljava/lang/Class<TT;>;)V

  protected com.fasterxml.jackson.databind.deser.std.StdNodeBasedDeserializer(com.fasterxml.jackson.databind.deser.std.StdNodeBasedDeserializer<?>);
    descriptor: (Lcom/fasterxml/jackson/databind/deser/std/StdNodeBasedDeserializer;)V
    flags: (0x0004) ACC_PROTECTED
    Code:
      stack=2, locals=2, args_size=2
         0: aload_0
         1: aload_1
         2: invokespecial #3                  // Method com/fasterxml/jackson/databind/deser/std/StdDeserializer."<init>":(Lcom/fasterxml/jackson/databind/deser/std/StdDeserializer;)V
         5: aload_0
         6: aload_1
         7: getfield      #4                  // Field _treeDeserializer:Lcom/fasterxml/jackson/databind/JsonDeserializer;
        10: putfield      #4                  // Field _treeDeserializer:Lcom/fasterxml/jackson/databind/JsonDeserializer;
        13: return
      LineNumberTable:
        line 47: 0
        line 48: 5
        line 49: 13
      LocalVariableTable:
        Start  Length  Slot  Name   Signature
            0      14     0  this   Lcom/fasterxml/jackson/databind/deser/std/StdNodeBasedDeserializer;
            0      14     1   src   Lcom/fasterxml/jackson/databind/deser/std/StdNodeBasedDeserializer;
      LocalVariableTypeTable:
        Start  Length  Slot  Name   Signature
            0      14     0  this   Lcom/fasterxml/jackson/databind/deser/std/StdNodeBasedDeserializer<TT;>;
            0      14     1   src   Lcom/fasterxml/jackson/databind/deser/std/StdNodeBasedDeserializer<*>;
    Signature: #41                          // (Lcom/fasterxml/jackson/databind/deser/std/StdNodeBasedDeserializer<*>;)V

  public void resolve(com.fasterxml.jackson.databind.DeserializationContext) throws com.fasterxml.jackson.databind.JsonMappingException;
    descriptor: (Lcom/fasterxml/jackson/databind/DeserializationContext;)V
    flags: (0x0001) ACC_PUBLIC
    Code:
      stack=4, locals=2, args_size=2
         0: aload_0
         1: aload_1
         2: aload_1
         3: ldc           #5                  // class com/fasterxml/jackson/databind/JsonNode
         5: invokevirtual #6                  // Method com/fasterxml/jackson/databind/DeserializationContext.constructType:(Ljava/lang/Class;)Lcom/fasterxml/jackson/databind/JavaType;
         8: invokevirtual #7                  // Method com/fasterxml/jackson/databind/DeserializationContext.findRootValueDeserializer:(Lcom/fasterxml/jackson/databind/JavaType;)Lcom/fasterxml/jackson/databind/JsonDeserializer;
        11: putfield      #4                  // Field _treeDeserializer:Lcom/fasterxml/jackson/databind/JsonDeserializer;
        14: return
      LineNumberTable:
        line 53: 0
        line 54: 14
      LocalVariableTable:
        Start  Length  Slot  Name   Signature
            0      15     0  this   Lcom/fasterxml/jackson/databind/deser/std/StdNodeBasedDeserializer;
            0      15     1  ctxt   Lcom/fasterxml/jackson/databind/DeserializationContext;
      LocalVariableTypeTable:
        Start  Length  Slot  Name   Signature
            0      15     0  this   Lcom/fasterxml/jackson/databind/deser/std/StdNodeBasedDeserializer<TT;>;
    Exceptions:
      throws com.fasterxml.jackson.databind.JsonMappingException

  public abstract T convert(com.fasterxml.jackson.databind.JsonNode, com.fasterxml.jackson.databind.DeserializationContext) throws java.io.IOException;
    descriptor: (Lcom/fasterxml/jackson/databind/JsonNode;Lcom/fasterxml/jackson/databind/DeserializationContext;)Ljava/lang/Object;
    flags: (0x0401) ACC_PUBLIC, ACC_ABSTRACT
    Exceptions:
      throws java.io.IOException
    Signature: #51                          // (Lcom/fasterxml/jackson/databind/JsonNode;Lcom/fasterxml/jackson/databind/DeserializationContext;)TT;

  public T deserialize(com.fasterxml.jackson.core.JsonParser, com.fasterxml.jackson.databind.DeserializationContext) throws java.io.IOException;
    descriptor: (Lcom/fasterxml/jackson/core/JsonParser;Lcom/fasterxml/jackson/databind/DeserializationContext;)Ljava/lang/Object;
    flags: (0x0001) ACC_PUBLIC
    Code:
      stack=3, locals=4, args_size=3
         0: aload_0
         1: getfield      #4                  // Field _treeDeserializer:Lcom/fasterxml/jackson/databind/JsonDeserializer;
         4: aload_1
         5: aload_2
         6: invokevirtual #8                  // Method com/fasterxml/jackson/databind/JsonDeserializer.deserialize:(Lcom/fasterxml/jackson/core/JsonParser;Lcom/fasterxml/jackson/databind/DeserializationContext;)Ljava/lang/Object;
         9: checkcast     #5                  // class com/fasterxml/jackson/databind/JsonNode
        12: astore_3
        13: aload_0
        14: aload_3
        15: aload_2
        16: invokevirtual #9                  // Method convert:(Lcom/fasterxml/jackson/databind/JsonNode;Lcom/fasterxml/jackson/databind/DeserializationContext;)Ljava/lang/Object;
        19: areturn
      LineNumberTable:
        line 72: 0
        line 73: 13
      LocalVariableTable:
        Start  Length  Slot  Name   Signature
            0      20     0  this   Lcom/fasterxml/jackson/databind/deser/std/StdNodeBasedDeserializer;
            0      20     1    jp   Lcom/fasterxml/jackson/core/JsonParser;
            0      20     2  ctxt   Lcom/fasterxml/jackson/databind/DeserializationContext;
           13       7     3     n   Lcom/fasterxml/jackson/databind/JsonNode;
      LocalVariableTypeTable:
        Start  Length  Slot  Name   Signature
            0      20     0  this   Lcom/fasterxml/jackson/databind/deser/std/StdNodeBasedDeserializer<TT;>;
    Exceptions:
      throws java.io.IOException
    Signature: #58                          // (Lcom/fasterxml/jackson/core/JsonParser;Lcom/fasterxml/jackson/databind/DeserializationContext;)TT;

  public java.lang.Object deserializeWithType(com.fasterxml.jackson.core.JsonParser, com.fasterxml.jackson.databind.DeserializationContext, com.fasterxml.jackson.databind.jsontype.TypeDeserializer) throws java.io.IOException;
    descriptor: (Lcom/fasterxml/jackson/core/JsonParser;Lcom/fasterxml/jackson/databind/DeserializationContext;Lcom/fasterxml/jackson/databind/jsontype/TypeDeserializer;)Ljava/lang/Object;
    flags: (0x0001) ACC_PUBLIC
    Code:
      stack=4, locals=5, args_size=4
         0: aload_0
         1: getfield      #4                  // Field _treeDeserializer:Lcom/fasterxml/jackson/databind/JsonDeserializer;
         4: aload_1
         5: aload_2
         6: aload_3
         7: invokevirtual #10                 // Method com/fasterxml/jackson/databind/JsonDeserializer.deserializeWithType:(Lcom/fasterxml/jackson/core/JsonParser;Lcom/fasterxml/jackson/databind/DeserializationContext;Lcom/fasterxml/jackson/databind/jsontype/TypeDeserializer;)Ljava/lang/Object;
        10: checkcast     #5                  // class com/fasterxml/jackson/databind/JsonNode
        13: astore        4
        15: aload_0
        16: aload         4
        18: aload_2
        19: invokevirtual #9                  // Method convert:(Lcom/fasterxml/jackson/databind/JsonNode;Lcom/fasterxml/jackson/databind/DeserializationContext;)Ljava/lang/Object;
        22: areturn
      LineNumberTable:
        line 83: 0
        line 84: 15
      LocalVariableTable:
        Start  Length  Slot  Name   Signature
            0      23     0  this   Lcom/fasterxml/jackson/databind/deser/std/StdNodeBasedDeserializer;
            0      23     1    jp   Lcom/fasterxml/jackson/core/JsonParser;
            0      23     2  ctxt   Lcom/fasterxml/jackson/databind/DeserializationContext;
            0      23     3    td   Lcom/fasterxml/jackson/databind/jsontype/TypeDeserializer;
           15       8     4     n   Lcom/fasterxml/jackson/databind/JsonNode;
      LocalVariableTypeTable:
        Start  Length  Slot  Name   Signature
            0      23     0  this   Lcom/fasterxml/jackson/databind/deser/std/StdNodeBasedDeserializer<TT;>;
    Exceptions:
      throws java.io.IOException
}
Signature: #63                          // <T:Ljava/lang/Object;>Lcom/fasterxml/jackson/databind/deser/std/StdDeserializer<TT;>;Lcom/fasterxml/jackson/databind/deser/ResolvableDeserializer;
SourceFile: "StdNodeBasedDeserializer.java"
