Classfile /Users/mw/Projects/slang-braindump/.jar/jar8/assemble/slang-braindump/assemble/content/scala/concurrent/impl/CompletionLatch.class
  Last modified May 29, 2022; size 6908 bytes
  SHA-256 checksum 2dbfc510fc4dd59f3c12343594f37955f097bbb3ec139ec1dc64347e7fbc9dfc
  Compiled from "Promise.scala"
public final class scala.concurrent.impl.CompletionLatch<T extends java.lang.Object> extends java.util.concurrent.locks.AbstractQueuedSynchronizer implements scala.Function1<scala.util.Try<T>, scala.runtime.BoxedUnit>
  minor version: 0
  major version: 52
  flags: (0x0031) ACC_PUBLIC, ACC_FINAL, ACC_SUPER
  this_class: #2                          // scala/concurrent/impl/CompletionLatch
  super_class: #5                         // java/util/concurrent/locks/AbstractQueuedSynchronizer
  interfaces: 1, fields: 1, methods: 33, attributes: 5
Constant pool:
    #1 = Utf8               scala/concurrent/impl/CompletionLatch
    #2 = Class              #1            // scala/concurrent/impl/CompletionLatch
    #3 = Utf8               <T:Ljava/lang/Object;>Ljava/util/concurrent/locks/AbstractQueuedSynchronizer;Lscala/Function1<Lscala/util/Try<TT;>;Lscala/runtime/BoxedUnit;>;
    #4 = Utf8               java/util/concurrent/locks/AbstractQueuedSynchronizer
    #5 = Class              #4            // java/util/concurrent/locks/AbstractQueuedSynchronizer
    #6 = Utf8               scala/Function1
    #7 = Class              #6            // scala/Function1
    #8 = Utf8               Promise.scala
    #9 = Utf8               Lscala/reflect/ScalaSignature;
   #10 = Utf8               bytes
   #11 = Utf8               \u0006\u000513Qa\u0002\u0005\u0003\u00119AQa\r\u0001\u0005\u0002QBaa\u000e\u0001!B\u0013y\u0002\"\u0002\u001d\u0001\t\u000bI\u0004\"\u0002\u001e\u0001\t#Z\u0004\"B!\u0001\t#\u0012\u0005\"\u0002%\u0001\t\u0003J%aD\"p[BdW\r^5p]2\u000bGo\u00195\u000b\u0005%Q\u0011\u0001B5na2T!a\u0003\u0007\u0002\u0015\r|gnY;se\u0016tGOC\u0001\u000e\u0003\u0015\u00198-\u00197b+\tyaeE\u0002\u0001!m\u0001\"!E\r\u000e\u0003IQ!a\u0005\u000b\u0002\u000b1|7m[:\u000b\u0005-)\"B\u0001\f\u0018\u0003\u0011)H/\u001b7\u000b\u0003a\tAA[1wC&\u0011!D\u0005\u0002\u001b\u0003\n\u001cHO]1diF+X-^3e\'ft7\r\u001b:p]&TXM\u001d\t\u00059uy\u0002\'D\u0001\r\u0013\tqBBA\u0005Gk:\u001cG/[8ocA\u0019\u0001E\t\u0013\u000e\u0003\u0005R!A\u0006\u0007\n\u0005\r\n#a\u0001+ssB\u0011QE\n\u0007\u0001\t\u00159\u0003A1\u0001*\u0005\u0005!6\u0001A\t\u0003U5\u0002\"\u0001H\u0016\n\u00051b!a\u0002(pi\"Lgn\u001a\t\u000399J!a\f\u0007\u0003\u0007\u0005s\u0017\u0010\u0005\u0002\u001dc%\u0011!\u0007\u0004\u0002\u0005+:LG/\u0001\u0004=S:LGO\u0010\u000b\u0002kA\u0019a\u0007\u0001\u0013\u000e\u0003!\tqa\u0018:fgVdG/\u0001\u0004sKN,H\u000e^\u000b\u0002?\u0005\u0001BO]=BGF,\u0018N]3TQ\u0006\u0014X\r\u001a\u000b\u0003y}\u0002\"\u0001H\u001f\n\u0005yb!aA%oi\")\u0001\t\u0002a\u0001y\u00059\u0011n\u001a8pe\u0016$\u0017\u0001\u0005;ssJ+G.Z1tKNC\u0017M]3e)\t\u0019e\t\u0005\u0002\u001d\t&\u0011Q\t\u0004\u0002\b\u0005>|G.Z1o\u0011\u00159U\u00011\u0001=\u0003\u0019IwM\\8sK\u0006)\u0011\r\u001d9msR\u0011\u0001G\u0013\u0005\u0006\u0017\u001a\u0001\raH\u0001\u0006m\u0006dW/\u001a
   #12 = Utf8               _result
   #13 = Utf8               Lscala/util/Try;
   #14 = Utf8               Lscala/util/Try<TT;>;
   #15 = Utf8               apply$mcZD$sp
   #16 = Utf8               (D)Z
   #17 = Utf8               v1
   #18 = Utf8               apply$mcZD$sp$
   #19 = Utf8               (Lscala/Function1;D)Z
   #20 = NameAndType        #18:#19       // apply$mcZD$sp$:(Lscala/Function1;D)Z
   #21 = InterfaceMethodref #7.#20        // scala/Function1.apply$mcZD$sp$:(Lscala/Function1;D)Z
   #22 = Utf8               this
   #23 = Utf8               Lscala/concurrent/impl/CompletionLatch;
   #24 = Utf8               D
   #25 = Utf8               apply$mcDD$sp
   #26 = Utf8               (D)D
   #27 = Utf8               apply$mcDD$sp$
   #28 = Utf8               (Lscala/Function1;D)D
   #29 = NameAndType        #27:#28       // apply$mcDD$sp$:(Lscala/Function1;D)D
   #30 = InterfaceMethodref #7.#29        // scala/Function1.apply$mcDD$sp$:(Lscala/Function1;D)D
   #31 = Utf8               apply$mcFD$sp
   #32 = Utf8               (D)F
   #33 = Utf8               apply$mcFD$sp$
   #34 = Utf8               (Lscala/Function1;D)F
   #35 = NameAndType        #33:#34       // apply$mcFD$sp$:(Lscala/Function1;D)F
   #36 = InterfaceMethodref #7.#35        // scala/Function1.apply$mcFD$sp$:(Lscala/Function1;D)F
   #37 = Utf8               apply$mcID$sp
   #38 = Utf8               (D)I
   #39 = Utf8               apply$mcID$sp$
   #40 = Utf8               (Lscala/Function1;D)I
   #41 = NameAndType        #39:#40       // apply$mcID$sp$:(Lscala/Function1;D)I
   #42 = InterfaceMethodref #7.#41        // scala/Function1.apply$mcID$sp$:(Lscala/Function1;D)I
   #43 = Utf8               apply$mcJD$sp
   #44 = Utf8               (D)J
   #45 = Utf8               apply$mcJD$sp$
   #46 = Utf8               (Lscala/Function1;D)J
   #47 = NameAndType        #45:#46       // apply$mcJD$sp$:(Lscala/Function1;D)J
   #48 = InterfaceMethodref #7.#47        // scala/Function1.apply$mcJD$sp$:(Lscala/Function1;D)J
   #49 = Utf8               apply$mcVD$sp
   #50 = Utf8               (D)V
   #51 = Utf8               apply$mcVD$sp$
   #52 = Utf8               (Lscala/Function1;D)V
   #53 = NameAndType        #51:#52       // apply$mcVD$sp$:(Lscala/Function1;D)V
   #54 = InterfaceMethodref #7.#53        // scala/Function1.apply$mcVD$sp$:(Lscala/Function1;D)V
   #55 = Utf8               apply$mcZF$sp
   #56 = Utf8               (F)Z
   #57 = Utf8               apply$mcZF$sp$
   #58 = Utf8               (Lscala/Function1;F)Z
   #59 = NameAndType        #57:#58       // apply$mcZF$sp$:(Lscala/Function1;F)Z
   #60 = InterfaceMethodref #7.#59        // scala/Function1.apply$mcZF$sp$:(Lscala/Function1;F)Z
   #61 = Utf8               F
   #62 = Utf8               apply$mcDF$sp
   #63 = Utf8               (F)D
   #64 = Utf8               apply$mcDF$sp$
   #65 = Utf8               (Lscala/Function1;F)D
   #66 = NameAndType        #64:#65       // apply$mcDF$sp$:(Lscala/Function1;F)D
   #67 = InterfaceMethodref #7.#66        // scala/Function1.apply$mcDF$sp$:(Lscala/Function1;F)D
   #68 = Utf8               apply$mcFF$sp
   #69 = Utf8               (F)F
   #70 = Utf8               apply$mcFF$sp$
   #71 = Utf8               (Lscala/Function1;F)F
   #72 = NameAndType        #70:#71       // apply$mcFF$sp$:(Lscala/Function1;F)F
   #73 = InterfaceMethodref #7.#72        // scala/Function1.apply$mcFF$sp$:(Lscala/Function1;F)F
   #74 = Utf8               apply$mcIF$sp
   #75 = Utf8               (F)I
   #76 = Utf8               apply$mcIF$sp$
   #77 = Utf8               (Lscala/Function1;F)I
   #78 = NameAndType        #76:#77       // apply$mcIF$sp$:(Lscala/Function1;F)I
   #79 = InterfaceMethodref #7.#78        // scala/Function1.apply$mcIF$sp$:(Lscala/Function1;F)I
   #80 = Utf8               apply$mcJF$sp
   #81 = Utf8               (F)J
   #82 = Utf8               apply$mcJF$sp$
   #83 = Utf8               (Lscala/Function1;F)J
   #84 = NameAndType        #82:#83       // apply$mcJF$sp$:(Lscala/Function1;F)J
   #85 = InterfaceMethodref #7.#84        // scala/Function1.apply$mcJF$sp$:(Lscala/Function1;F)J
   #86 = Utf8               apply$mcVF$sp
   #87 = Utf8               (F)V
   #88 = Utf8               apply$mcVF$sp$
   #89 = Utf8               (Lscala/Function1;F)V
   #90 = NameAndType        #88:#89       // apply$mcVF$sp$:(Lscala/Function1;F)V
   #91 = InterfaceMethodref #7.#90        // scala/Function1.apply$mcVF$sp$:(Lscala/Function1;F)V
   #92 = Utf8               apply$mcZI$sp
   #93 = Utf8               (I)Z
   #94 = Utf8               apply$mcZI$sp$
   #95 = Utf8               (Lscala/Function1;I)Z
   #96 = NameAndType        #94:#95       // apply$mcZI$sp$:(Lscala/Function1;I)Z
   #97 = InterfaceMethodref #7.#96        // scala/Function1.apply$mcZI$sp$:(Lscala/Function1;I)Z
   #98 = Utf8               I
   #99 = Utf8               apply$mcDI$sp
  #100 = Utf8               (I)D
  #101 = Utf8               apply$mcDI$sp$
  #102 = Utf8               (Lscala/Function1;I)D
  #103 = NameAndType        #101:#102     // apply$mcDI$sp$:(Lscala/Function1;I)D
  #104 = InterfaceMethodref #7.#103       // scala/Function1.apply$mcDI$sp$:(Lscala/Function1;I)D
  #105 = Utf8               apply$mcFI$sp
  #106 = Utf8               (I)F
  #107 = Utf8               apply$mcFI$sp$
  #108 = Utf8               (Lscala/Function1;I)F
  #109 = NameAndType        #107:#108     // apply$mcFI$sp$:(Lscala/Function1;I)F
  #110 = InterfaceMethodref #7.#109       // scala/Function1.apply$mcFI$sp$:(Lscala/Function1;I)F
  #111 = Utf8               apply$mcII$sp
  #112 = Utf8               (I)I
  #113 = Utf8               apply$mcII$sp$
  #114 = Utf8               (Lscala/Function1;I)I
  #115 = NameAndType        #113:#114     // apply$mcII$sp$:(Lscala/Function1;I)I
  #116 = InterfaceMethodref #7.#115       // scala/Function1.apply$mcII$sp$:(Lscala/Function1;I)I
  #117 = Utf8               apply$mcJI$sp
  #118 = Utf8               (I)J
  #119 = Utf8               apply$mcJI$sp$
  #120 = Utf8               (Lscala/Function1;I)J
  #121 = NameAndType        #119:#120     // apply$mcJI$sp$:(Lscala/Function1;I)J
  #122 = InterfaceMethodref #7.#121       // scala/Function1.apply$mcJI$sp$:(Lscala/Function1;I)J
  #123 = Utf8               apply$mcVI$sp
  #124 = Utf8               (I)V
  #125 = Utf8               apply$mcVI$sp$
  #126 = Utf8               (Lscala/Function1;I)V
  #127 = NameAndType        #125:#126     // apply$mcVI$sp$:(Lscala/Function1;I)V
  #128 = InterfaceMethodref #7.#127       // scala/Function1.apply$mcVI$sp$:(Lscala/Function1;I)V
  #129 = Utf8               apply$mcZJ$sp
  #130 = Utf8               (J)Z
  #131 = Utf8               apply$mcZJ$sp$
  #132 = Utf8               (Lscala/Function1;J)Z
  #133 = NameAndType        #131:#132     // apply$mcZJ$sp$:(Lscala/Function1;J)Z
  #134 = InterfaceMethodref #7.#133       // scala/Function1.apply$mcZJ$sp$:(Lscala/Function1;J)Z
  #135 = Utf8               J
  #136 = Utf8               apply$mcDJ$sp
  #137 = Utf8               (J)D
  #138 = Utf8               apply$mcDJ$sp$
  #139 = Utf8               (Lscala/Function1;J)D
  #140 = NameAndType        #138:#139     // apply$mcDJ$sp$:(Lscala/Function1;J)D
  #141 = InterfaceMethodref #7.#140       // scala/Function1.apply$mcDJ$sp$:(Lscala/Function1;J)D
  #142 = Utf8               apply$mcFJ$sp
  #143 = Utf8               (J)F
  #144 = Utf8               apply$mcFJ$sp$
  #145 = Utf8               (Lscala/Function1;J)F
  #146 = NameAndType        #144:#145     // apply$mcFJ$sp$:(Lscala/Function1;J)F
  #147 = InterfaceMethodref #7.#146       // scala/Function1.apply$mcFJ$sp$:(Lscala/Function1;J)F
  #148 = Utf8               apply$mcIJ$sp
  #149 = Utf8               (J)I
  #150 = Utf8               apply$mcIJ$sp$
  #151 = Utf8               (Lscala/Function1;J)I
  #152 = NameAndType        #150:#151     // apply$mcIJ$sp$:(Lscala/Function1;J)I
  #153 = InterfaceMethodref #7.#152       // scala/Function1.apply$mcIJ$sp$:(Lscala/Function1;J)I
  #154 = Utf8               apply$mcJJ$sp
  #155 = Utf8               (J)J
  #156 = Utf8               apply$mcJJ$sp$
  #157 = Utf8               (Lscala/Function1;J)J
  #158 = NameAndType        #156:#157     // apply$mcJJ$sp$:(Lscala/Function1;J)J
  #159 = InterfaceMethodref #7.#158       // scala/Function1.apply$mcJJ$sp$:(Lscala/Function1;J)J
  #160 = Utf8               apply$mcVJ$sp
  #161 = Utf8               (J)V
  #162 = Utf8               apply$mcVJ$sp$
  #163 = Utf8               (Lscala/Function1;J)V
  #164 = NameAndType        #162:#163     // apply$mcVJ$sp$:(Lscala/Function1;J)V
  #165 = InterfaceMethodref #7.#164       // scala/Function1.apply$mcVJ$sp$:(Lscala/Function1;J)V
  #166 = Utf8               compose
  #167 = Utf8               (Lscala/Function1;)Lscala/Function1;
  #168 = Utf8               <A$:Ljava/lang/Object;>(Lscala/Function1<TA$;Lscala/util/Try<TT;>;>;)Lscala/Function1<TA$;Lscala/runtime/BoxedUnit;>;
  #169 = Utf8               g
  #170 = Utf8               compose$
  #171 = Utf8               (Lscala/Function1;Lscala/Function1;)Lscala/Function1;
  #172 = NameAndType        #170:#171     // compose$:(Lscala/Function1;Lscala/Function1;)Lscala/Function1;
  #173 = InterfaceMethodref #7.#172       // scala/Function1.compose$:(Lscala/Function1;Lscala/Function1;)Lscala/Function1;
  #174 = Utf8               Lscala/Function1;
  #175 = Utf8               andThen
  #176 = Utf8               <A$:Ljava/lang/Object;>(Lscala/Function1<Lscala/runtime/BoxedUnit;TA$;>;)Lscala/Function1<Lscala/util/Try<TT;>;TA$;>;
  #177 = Utf8               andThen$
  #178 = NameAndType        #177:#171     // andThen$:(Lscala/Function1;Lscala/Function1;)Lscala/Function1;
  #179 = InterfaceMethodref #7.#178       // scala/Function1.andThen$:(Lscala/Function1;Lscala/Function1;)Lscala/Function1;
  #180 = Utf8               toString
  #181 = Utf8               ()Ljava/lang/String;
  #182 = Utf8               toString$
  #183 = Utf8               (Lscala/Function1;)Ljava/lang/String;
  #184 = NameAndType        #182:#183     // toString$:(Lscala/Function1;)Ljava/lang/String;
  #185 = InterfaceMethodref #7.#184       // scala/Function1.toString$:(Lscala/Function1;)Ljava/lang/String;
  #186 = Utf8               result
  #187 = Utf8               ()Lscala/util/Try;
  #188 = Utf8               ()Lscala/util/Try<TT;>;
  #189 = NameAndType        #12:#13       // _result:Lscala/util/Try;
  #190 = Fieldref           #2.#189       // scala/concurrent/impl/CompletionLatch._result:Lscala/util/Try;
  #191 = Utf8               tryAcquireShared
  #192 = Utf8               ignored
  #193 = Utf8               getState
  #194 = Utf8               ()I
  #195 = NameAndType        #193:#194     // getState:()I
  #196 = Methodref          #2.#195       // scala/concurrent/impl/CompletionLatch.getState:()I
  #197 = Utf8               tryReleaseShared
  #198 = Utf8               ignore
  #199 = Utf8               setState
  #200 = NameAndType        #199:#124     // setState:(I)V
  #201 = Methodref          #2.#200       // scala/concurrent/impl/CompletionLatch.setState:(I)V
  #202 = Utf8               apply
  #203 = Utf8               (Lscala/util/Try;)V
  #204 = Utf8               (Lscala/util/Try<TT;>;)V
  #205 = Utf8               value
  #206 = Utf8               releaseShared
  #207 = NameAndType        #206:#93      // releaseShared:(I)Z
  #208 = Methodref          #2.#207       // scala/concurrent/impl/CompletionLatch.releaseShared:(I)Z
  #209 = Utf8               (Ljava/lang/Object;)Ljava/lang/Object;
  #210 = Utf8               scala/util/Try
  #211 = Class              #210          // scala/util/Try
  #212 = NameAndType        #202:#203     // apply:(Lscala/util/Try;)V
  #213 = Methodref          #2.#212       // scala/concurrent/impl/CompletionLatch.apply:(Lscala/util/Try;)V
  #214 = Utf8               scala/runtime/BoxedUnit
  #215 = Class              #214          // scala/runtime/BoxedUnit
  #216 = Utf8               UNIT
  #217 = Utf8               Lscala/runtime/BoxedUnit;
  #218 = NameAndType        #216:#217     // UNIT:Lscala/runtime/BoxedUnit;
  #219 = Fieldref           #215.#218     // scala/runtime/BoxedUnit.UNIT:Lscala/runtime/BoxedUnit;
  #220 = Utf8               Ljava/lang/Object;
  #221 = Utf8               <init>
  #222 = Utf8               ()V
  #223 = NameAndType        #221:#222     // "<init>":()V
  #224 = Methodref          #5.#223       // java/util/concurrent/locks/AbstractQueuedSynchronizer."<init>":()V
  #225 = Utf8               Signature
  #226 = Utf8               Code
  #227 = Utf8               LineNumberTable
  #228 = Utf8               LocalVariableTable
  #229 = Utf8               MethodParameters
  #230 = Utf8               StackMapTable
  #231 = Utf8               SourceFile
  #232 = Utf8               RuntimeVisibleAnnotations
  #233 = Utf8               ScalaInlineInfo
  #234 = Utf8               ScalaSig
{
  private scala.util.Try<T> _result;
    descriptor: Lscala/util/Try;
    flags: (0x0002) ACC_PRIVATE
    Signature: #14                          // Lscala/util/Try<TT;>;

  public boolean apply$mcZD$sp(double);
    descriptor: (D)Z
    flags: (0x0001) ACC_PUBLIC
    Code:
      stack=3, locals=3, args_size=2
         0: aload_0
         1: dload_1
         2: invokestatic  #21                 // InterfaceMethod scala/Function1.apply$mcZD$sp$:(Lscala/Function1;D)Z
         5: ireturn
      LineNumberTable:
        line 33: 0
      LocalVariableTable:
        Start  Length  Slot  Name   Signature
            0       6     0  this   Lscala/concurrent/impl/CompletionLatch;
            0       6     1    v1   D
    MethodParameters:
      Name                           Flags
      v1                             final

  public double apply$mcDD$sp(double);
    descriptor: (D)D
    flags: (0x0001) ACC_PUBLIC
    Code:
      stack=3, locals=3, args_size=2
         0: aload_0
         1: dload_1
         2: invokestatic  #30                 // InterfaceMethod scala/Function1.apply$mcDD$sp$:(Lscala/Function1;D)D
         5: dreturn
      LineNumberTable:
        line 33: 0
      LocalVariableTable:
        Start  Length  Slot  Name   Signature
            0       6     0  this   Lscala/concurrent/impl/CompletionLatch;
            0       6     1    v1   D
    MethodParameters:
      Name                           Flags
      v1                             final

  public float apply$mcFD$sp(double);
    descriptor: (D)F
    flags: (0x0001) ACC_PUBLIC
    Code:
      stack=3, locals=3, args_size=2
         0: aload_0
         1: dload_1
         2: invokestatic  #36                 // InterfaceMethod scala/Function1.apply$mcFD$sp$:(Lscala/Function1;D)F
         5: freturn
      LineNumberTable:
        line 33: 0
      LocalVariableTable:
        Start  Length  Slot  Name   Signature
            0       6     0  this   Lscala/concurrent/impl/CompletionLatch;
            0       6     1    v1   D
    MethodParameters:
      Name                           Flags
      v1                             final

  public int apply$mcID$sp(double);
    descriptor: (D)I
    flags: (0x0001) ACC_PUBLIC
    Code:
      stack=3, locals=3, args_size=2
         0: aload_0
         1: dload_1
         2: invokestatic  #42                 // InterfaceMethod scala/Function1.apply$mcID$sp$:(Lscala/Function1;D)I
         5: ireturn
      LineNumberTable:
        line 33: 0
      LocalVariableTable:
        Start  Length  Slot  Name   Signature
            0       6     0  this   Lscala/concurrent/impl/CompletionLatch;
            0       6     1    v1   D
    MethodParameters:
      Name                           Flags
      v1                             final

  public long apply$mcJD$sp(double);
    descriptor: (D)J
    flags: (0x0001) ACC_PUBLIC
    Code:
      stack=3, locals=3, args_size=2
         0: aload_0
         1: dload_1
         2: invokestatic  #48                 // InterfaceMethod scala/Function1.apply$mcJD$sp$:(Lscala/Function1;D)J
         5: lreturn
      LineNumberTable:
        line 33: 0
      LocalVariableTable:
        Start  Length  Slot  Name   Signature
            0       6     0  this   Lscala/concurrent/impl/CompletionLatch;
            0       6     1    v1   D
    MethodParameters:
      Name                           Flags
      v1                             final

  public void apply$mcVD$sp(double);
    descriptor: (D)V
    flags: (0x0001) ACC_PUBLIC
    Code:
      stack=3, locals=3, args_size=2
         0: aload_0
         1: dload_1
         2: invokestatic  #54                 // InterfaceMethod scala/Function1.apply$mcVD$sp$:(Lscala/Function1;D)V
         5: return
      LineNumberTable:
        line 33: 0
      LocalVariableTable:
        Start  Length  Slot  Name   Signature
            0       6     0  this   Lscala/concurrent/impl/CompletionLatch;
            0       6     1    v1   D
    MethodParameters:
      Name                           Flags
      v1                             final

  public boolean apply$mcZF$sp(float);
    descriptor: (F)Z
    flags: (0x0001) ACC_PUBLIC
    Code:
      stack=2, locals=2, args_size=2
         0: aload_0
         1: fload_1
         2: invokestatic  #60                 // InterfaceMethod scala/Function1.apply$mcZF$sp$:(Lscala/Function1;F)Z
         5: ireturn
      LineNumberTable:
        line 33: 0
      LocalVariableTable:
        Start  Length  Slot  Name   Signature
            0       6     0  this   Lscala/concurrent/impl/CompletionLatch;
            0       6     1    v1   F
    MethodParameters:
      Name                           Flags
      v1                             final

  public double apply$mcDF$sp(float);
    descriptor: (F)D
    flags: (0x0001) ACC_PUBLIC
    Code:
      stack=2, locals=2, args_size=2
         0: aload_0
         1: fload_1
         2: invokestatic  #67                 // InterfaceMethod scala/Function1.apply$mcDF$sp$:(Lscala/Function1;F)D
         5: dreturn
      LineNumberTable:
        line 33: 0
      LocalVariableTable:
        Start  Length  Slot  Name   Signature
            0       6     0  this   Lscala/concurrent/impl/CompletionLatch;
            0       6     1    v1   F
    MethodParameters:
      Name                           Flags
      v1                             final

  public float apply$mcFF$sp(float);
    descriptor: (F)F
    flags: (0x0001) ACC_PUBLIC
    Code:
      stack=2, locals=2, args_size=2
         0: aload_0
         1: fload_1
         2: invokestatic  #73                 // InterfaceMethod scala/Function1.apply$mcFF$sp$:(Lscala/Function1;F)F
         5: freturn
      LineNumberTable:
        line 33: 0
      LocalVariableTable:
        Start  Length  Slot  Name   Signature
            0       6     0  this   Lscala/concurrent/impl/CompletionLatch;
            0       6     1    v1   F
    MethodParameters:
      Name                           Flags
      v1                             final

  public int apply$mcIF$sp(float);
    descriptor: (F)I
    flags: (0x0001) ACC_PUBLIC
    Code:
      stack=2, locals=2, args_size=2
         0: aload_0
         1: fload_1
         2: invokestatic  #79                 // InterfaceMethod scala/Function1.apply$mcIF$sp$:(Lscala/Function1;F)I
         5: ireturn
      LineNumberTable:
        line 33: 0
      LocalVariableTable:
        Start  Length  Slot  Name   Signature
            0       6     0  this   Lscala/concurrent/impl/CompletionLatch;
            0       6     1    v1   F
    MethodParameters:
      Name                           Flags
      v1                             final

  public long apply$mcJF$sp(float);
    descriptor: (F)J
    flags: (0x0001) ACC_PUBLIC
    Code:
      stack=2, locals=2, args_size=2
         0: aload_0
         1: fload_1
         2: invokestatic  #85                 // InterfaceMethod scala/Function1.apply$mcJF$sp$:(Lscala/Function1;F)J
         5: lreturn
      LineNumberTable:
        line 33: 0
      LocalVariableTable:
        Start  Length  Slot  Name   Signature
            0       6     0  this   Lscala/concurrent/impl/CompletionLatch;
            0       6     1    v1   F
    MethodParameters:
      Name                           Flags
      v1                             final

  public void apply$mcVF$sp(float);
    descriptor: (F)V
    flags: (0x0001) ACC_PUBLIC
    Code:
      stack=2, locals=2, args_size=2
         0: aload_0
         1: fload_1
         2: invokestatic  #91                 // InterfaceMethod scala/Function1.apply$mcVF$sp$:(Lscala/Function1;F)V
         5: return
      LineNumberTable:
        line 33: 0
      LocalVariableTable:
        Start  Length  Slot  Name   Signature
            0       6     0  this   Lscala/concurrent/impl/CompletionLatch;
            0       6     1    v1   F
    MethodParameters:
      Name                           Flags
      v1                             final

  public boolean apply$mcZI$sp(int);
    descriptor: (I)Z
    flags: (0x0001) ACC_PUBLIC
    Code:
      stack=2, locals=2, args_size=2
         0: aload_0
         1: iload_1
         2: invokestatic  #97                 // InterfaceMethod scala/Function1.apply$mcZI$sp$:(Lscala/Function1;I)Z
         5: ireturn
      LineNumberTable:
        line 33: 0
      LocalVariableTable:
        Start  Length  Slot  Name   Signature
            0       6     0  this   Lscala/concurrent/impl/CompletionLatch;
            0       6     1    v1   I
    MethodParameters:
      Name                           Flags
      v1                             final

  public double apply$mcDI$sp(int);
    descriptor: (I)D
    flags: (0x0001) ACC_PUBLIC
    Code:
      stack=2, locals=2, args_size=2
         0: aload_0
         1: iload_1
         2: invokestatic  #104                // InterfaceMethod scala/Function1.apply$mcDI$sp$:(Lscala/Function1;I)D
         5: dreturn
      LineNumberTable:
        line 33: 0
      LocalVariableTable:
        Start  Length  Slot  Name   Signature
            0       6     0  this   Lscala/concurrent/impl/CompletionLatch;
            0       6     1    v1   I
    MethodParameters:
      Name                           Flags
      v1                             final

  public float apply$mcFI$sp(int);
    descriptor: (I)F
    flags: (0x0001) ACC_PUBLIC
    Code:
      stack=2, locals=2, args_size=2
         0: aload_0
         1: iload_1
         2: invokestatic  #110                // InterfaceMethod scala/Function1.apply$mcFI$sp$:(Lscala/Function1;I)F
         5: freturn
      LineNumberTable:
        line 33: 0
      LocalVariableTable:
        Start  Length  Slot  Name   Signature
            0       6     0  this   Lscala/concurrent/impl/CompletionLatch;
            0       6     1    v1   I
    MethodParameters:
      Name                           Flags
      v1                             final

  public int apply$mcII$sp(int);
    descriptor: (I)I
    flags: (0x0001) ACC_PUBLIC
    Code:
      stack=2, locals=2, args_size=2
         0: aload_0
         1: iload_1
         2: invokestatic  #116                // InterfaceMethod scala/Function1.apply$mcII$sp$:(Lscala/Function1;I)I
         5: ireturn
      LineNumberTable:
        line 33: 0
      LocalVariableTable:
        Start  Length  Slot  Name   Signature
            0       6     0  this   Lscala/concurrent/impl/CompletionLatch;
            0       6     1    v1   I
    MethodParameters:
      Name                           Flags
      v1                             final

  public long apply$mcJI$sp(int);
    descriptor: (I)J
    flags: (0x0001) ACC_PUBLIC
    Code:
      stack=2, locals=2, args_size=2
         0: aload_0
         1: iload_1
         2: invokestatic  #122                // InterfaceMethod scala/Function1.apply$mcJI$sp$:(Lscala/Function1;I)J
         5: lreturn
      LineNumberTable:
        line 33: 0
      LocalVariableTable:
        Start  Length  Slot  Name   Signature
            0       6     0  this   Lscala/concurrent/impl/CompletionLatch;
            0       6     1    v1   I
    MethodParameters:
      Name                           Flags
      v1                             final

  public void apply$mcVI$sp(int);
    descriptor: (I)V
    flags: (0x0001) ACC_PUBLIC
    Code:
      stack=2, locals=2, args_size=2
         0: aload_0
         1: iload_1
         2: invokestatic  #128                // InterfaceMethod scala/Function1.apply$mcVI$sp$:(Lscala/Function1;I)V
         5: return
      LineNumberTable:
        line 33: 0
      LocalVariableTable:
        Start  Length  Slot  Name   Signature
            0       6     0  this   Lscala/concurrent/impl/CompletionLatch;
            0       6     1    v1   I
    MethodParameters:
      Name                           Flags
      v1                             final

  public boolean apply$mcZJ$sp(long);
    descriptor: (J)Z
    flags: (0x0001) ACC_PUBLIC
    Code:
      stack=3, locals=3, args_size=2
         0: aload_0
         1: lload_1
         2: invokestatic  #134                // InterfaceMethod scala/Function1.apply$mcZJ$sp$:(Lscala/Function1;J)Z
         5: ireturn
      LineNumberTable:
        line 33: 0
      LocalVariableTable:
        Start  Length  Slot  Name   Signature
            0       6     0  this   Lscala/concurrent/impl/CompletionLatch;
            0       6     1    v1   J
    MethodParameters:
      Name                           Flags
      v1                             final

  public double apply$mcDJ$sp(long);
    descriptor: (J)D
    flags: (0x0001) ACC_PUBLIC
    Code:
      stack=3, locals=3, args_size=2
         0: aload_0
         1: lload_1
         2: invokestatic  #141                // InterfaceMethod scala/Function1.apply$mcDJ$sp$:(Lscala/Function1;J)D
         5: dreturn
      LineNumberTable:
        line 33: 0
      LocalVariableTable:
        Start  Length  Slot  Name   Signature
            0       6     0  this   Lscala/concurrent/impl/CompletionLatch;
            0       6     1    v1   J
    MethodParameters:
      Name                           Flags
      v1                             final

  public float apply$mcFJ$sp(long);
    descriptor: (J)F
    flags: (0x0001) ACC_PUBLIC
    Code:
      stack=3, locals=3, args_size=2
         0: aload_0
         1: lload_1
         2: invokestatic  #147                // InterfaceMethod scala/Function1.apply$mcFJ$sp$:(Lscala/Function1;J)F
         5: freturn
      LineNumberTable:
        line 33: 0
      LocalVariableTable:
        Start  Length  Slot  Name   Signature
            0       6     0  this   Lscala/concurrent/impl/CompletionLatch;
            0       6     1    v1   J
    MethodParameters:
      Name                           Flags
      v1                             final

  public int apply$mcIJ$sp(long);
    descriptor: (J)I
    flags: (0x0001) ACC_PUBLIC
    Code:
      stack=3, locals=3, args_size=2
         0: aload_0
         1: lload_1
         2: invokestatic  #153                // InterfaceMethod scala/Function1.apply$mcIJ$sp$:(Lscala/Function1;J)I
         5: ireturn
      LineNumberTable:
        line 33: 0
      LocalVariableTable:
        Start  Length  Slot  Name   Signature
            0       6     0  this   Lscala/concurrent/impl/CompletionLatch;
            0       6     1    v1   J
    MethodParameters:
      Name                           Flags
      v1                             final

  public long apply$mcJJ$sp(long);
    descriptor: (J)J
    flags: (0x0001) ACC_PUBLIC
    Code:
      stack=3, locals=3, args_size=2
         0: aload_0
         1: lload_1
         2: invokestatic  #159                // InterfaceMethod scala/Function1.apply$mcJJ$sp$:(Lscala/Function1;J)J
         5: lreturn
      LineNumberTable:
        line 33: 0
      LocalVariableTable:
        Start  Length  Slot  Name   Signature
            0       6     0  this   Lscala/concurrent/impl/CompletionLatch;
            0       6     1    v1   J
    MethodParameters:
      Name                           Flags
      v1                             final

  public void apply$mcVJ$sp(long);
    descriptor: (J)V
    flags: (0x0001) ACC_PUBLIC
    Code:
      stack=3, locals=3, args_size=2
         0: aload_0
         1: lload_1
         2: invokestatic  #165                // InterfaceMethod scala/Function1.apply$mcVJ$sp$:(Lscala/Function1;J)V
         5: return
      LineNumberTable:
        line 33: 0
      LocalVariableTable:
        Start  Length  Slot  Name   Signature
            0       6     0  this   Lscala/concurrent/impl/CompletionLatch;
            0       6     1    v1   J
    MethodParameters:
      Name                           Flags
      v1                             final

  public <A$ extends java.lang.Object> scala.Function1<A$, scala.runtime.BoxedUnit> compose(scala.Function1<A$, scala.util.Try<T>>);
    descriptor: (Lscala/Function1;)Lscala/Function1;
    flags: (0x0001) ACC_PUBLIC
    Code:
      stack=2, locals=2, args_size=2
         0: aload_0
         1: aload_1
         2: invokestatic  #173                // InterfaceMethod scala/Function1.compose$:(Lscala/Function1;Lscala/Function1;)Lscala/Function1;
         5: areturn
      LineNumberTable:
        line 33: 0
      LocalVariableTable:
        Start  Length  Slot  Name   Signature
            0       6     0  this   Lscala/concurrent/impl/CompletionLatch;
            0       6     1     g   Lscala/Function1;
    Signature: #168                         // <A$:Ljava/lang/Object;>(Lscala/Function1<TA$;Lscala/util/Try<TT;>;>;)Lscala/Function1<TA$;Lscala/runtime/BoxedUnit;>;
    MethodParameters:
      Name                           Flags
      g                              final

  public <A$ extends java.lang.Object> scala.Function1<scala.util.Try<T>, A$> andThen(scala.Function1<scala.runtime.BoxedUnit, A$>);
    descriptor: (Lscala/Function1;)Lscala/Function1;
    flags: (0x0001) ACC_PUBLIC
    Code:
      stack=2, locals=2, args_size=2
         0: aload_0
         1: aload_1
         2: invokestatic  #179                // InterfaceMethod scala/Function1.andThen$:(Lscala/Function1;Lscala/Function1;)Lscala/Function1;
         5: areturn
      LineNumberTable:
        line 33: 0
      LocalVariableTable:
        Start  Length  Slot  Name   Signature
            0       6     0  this   Lscala/concurrent/impl/CompletionLatch;
            0       6     1     g   Lscala/Function1;
    Signature: #176                         // <A$:Ljava/lang/Object;>(Lscala/Function1<Lscala/runtime/BoxedUnit;TA$;>;)Lscala/Function1<Lscala/util/Try<TT;>;TA$;>;
    MethodParameters:
      Name                           Flags
      g                              final

  public java.lang.String toString();
    descriptor: ()Ljava/lang/String;
    flags: (0x0001) ACC_PUBLIC
    Code:
      stack=1, locals=1, args_size=1
         0: aload_0
         1: invokestatic  #185                // InterfaceMethod scala/Function1.toString$:(Lscala/Function1;)Ljava/lang/String;
         4: areturn
      LineNumberTable:
        line 33: 0
      LocalVariableTable:
        Start  Length  Slot  Name   Signature
            0       5     0  this   Lscala/concurrent/impl/CompletionLatch;

  public final scala.util.Try<T> result();
    descriptor: ()Lscala/util/Try;
    flags: (0x0011) ACC_PUBLIC, ACC_FINAL
    Code:
      stack=1, locals=1, args_size=1
         0: aload_0
         1: getfield      #190                // Field _result:Lscala/util/Try;
         4: areturn
      LineNumberTable:
        line 36: 0
      LocalVariableTable:
        Start  Length  Slot  Name   Signature
            0       5     0  this   Lscala/concurrent/impl/CompletionLatch;
    Signature: #188                         // ()Lscala/util/Try<TT;>;

  public int tryAcquireShared(int);
    descriptor: (I)I
    flags: (0x0001) ACC_PUBLIC
    Code:
      stack=2, locals=2, args_size=2
         0: aload_0
         1: invokevirtual #196                // Method getState:()I
         4: iconst_0
         5: if_icmpeq     10
         8: iconst_1
         9: ireturn
        10: iconst_m1
        11: ireturn
      StackMapTable: number_of_entries = 1
        frame_type = 10 /* same */
      LineNumberTable:
        line 37: 0
      LocalVariableTable:
        Start  Length  Slot  Name   Signature
            0      12     0  this   Lscala/concurrent/impl/CompletionLatch;
            0      12     1 ignored   I
    MethodParameters:
      Name                           Flags
      ignored                        final

  public boolean tryReleaseShared(int);
    descriptor: (I)Z
    flags: (0x0001) ACC_PUBLIC
    Code:
      stack=2, locals=2, args_size=2
         0: aload_0
         1: iconst_1
         2: invokevirtual #201                // Method setState:(I)V
         5: iconst_1
         6: ireturn
      LineNumberTable:
        line 39: 0
        line 40: 5
      LocalVariableTable:
        Start  Length  Slot  Name   Signature
            0       7     0  this   Lscala/concurrent/impl/CompletionLatch;
            0       7     1 ignore   I
    MethodParameters:
      Name                           Flags
      ignore                         final

  public void apply(scala.util.Try<T>);
    descriptor: (Lscala/util/Try;)V
    flags: (0x0001) ACC_PUBLIC
    Code:
      stack=2, locals=2, args_size=2
         0: aload_0
         1: aload_1
         2: putfield      #190                // Field _result:Lscala/util/Try;
         5: aload_0
         6: iconst_1
         7: invokevirtual #208                // Method releaseShared:(I)Z
        10: pop
        11: return
      LineNumberTable:
        line 43: 0
        line 44: 5
      LocalVariableTable:
        Start  Length  Slot  Name   Signature
            0      12     0  this   Lscala/concurrent/impl/CompletionLatch;
            0      12     1 value   Lscala/util/Try;
    Signature: #204                         // (Lscala/util/Try<TT;>;)V
    MethodParameters:
      Name                           Flags
      value                          final

  public java.lang.Object apply(java.lang.Object);
    descriptor: (Ljava/lang/Object;)Ljava/lang/Object;
    flags: (0x1041) ACC_PUBLIC, ACC_BRIDGE, ACC_SYNTHETIC
    Code:
      stack=2, locals=2, args_size=2
         0: aload_0
         1: aload_1
         2: checkcast     #211                // class scala/util/Try
         5: invokevirtual #213                // Method apply:(Lscala/util/Try;)V
         8: getstatic     #219                // Field scala/runtime/BoxedUnit.UNIT:Lscala/runtime/BoxedUnit;
        11: areturn
      LineNumberTable:
        line 33: 0
      LocalVariableTable:
        Start  Length  Slot  Name   Signature
            0      12     0  this   Lscala/concurrent/impl/CompletionLatch;
            0      12     1    v1   Ljava/lang/Object;
    MethodParameters:
      Name                           Flags
      v1                             final

  public scala.concurrent.impl.CompletionLatch();
    descriptor: ()V
    flags: (0x0001) ACC_PUBLIC
    Code:
      stack=2, locals=1, args_size=1
         0: aload_0
         1: invokespecial #224                // Method java/util/concurrent/locks/AbstractQueuedSynchronizer."<init>":()V
         4: aload_0
         5: aconst_null
         6: putfield      #190                // Field _result:Lscala/util/Try;
         9: return
      LineNumberTable:
        line 33: 0
        line 35: 4
        line 33: 9
      LocalVariableTable:
        Start  Length  Slot  Name   Signature
            0      10     0  this   Lscala/concurrent/impl/CompletionLatch;
}
Signature: #3                           // <T:Ljava/lang/Object;>Ljava/util/concurrent/locks/AbstractQueuedSynchronizer;Lscala/Function1<Lscala/util/Try<TT;>;Lscala/runtime/BoxedUnit;>;
SourceFile: "Promise.scala"
RuntimeVisibleAnnotations:
  0: #9(#10=s#11)
    scala.reflect.ScalaSignature(
      bytes="\u0006\u000513Qa\u0002\u0005\u0003\u00119AQa\r\u0001\u0005\u0002QBaa\u000e\u0001!B\u0013y\u0002\"\u0002\u001d\u0001\t\u000bI\u0004\"\u0002\u001e\u0001\t#Z\u0004\"B!\u0001\t#\u0012\u0005\"\u0002%\u0001\t\u0003J%aD\"p[BdW\r^5p]2\u000bGo\u00195\u000b\u0005%Q\u0011\u0001B5na2T!a\u0003\u0007\u0002\u0015\r|gnY;se\u0016tGOC\u0001\u000e\u0003\u0015\u00198-\u00197b+\tyaeE\u0002\u0001!m\u0001\"!E\r\u000e\u0003IQ!a\u0005\u000b\u0002\u000b1|7m[:\u000b\u0005-)\"B\u0001\f\u0018\u0003\u0011)H/\u001b7\u000b\u0003a\tAA[1wC&\u0011!D\u0005\u0002\u001b\u0003\n\u001cHO]1diF+X-^3e\'ft7\r\u001b:p]&TXM\u001d\t\u00059uy\u0002\'D\u0001\r\u0013\tqBBA\u0005Gk:\u001cG/[8ocA\u0019\u0001E\t\u0013\u000e\u0003\u0005R!A\u0006\u0007\n\u0005\r\n#a\u0001+ssB\u0011QE\n\u0007\u0001\t\u00159\u0003A1\u0001*\u0005\u0005!6\u0001A\t\u0003U5\u0002\"\u0001H\u0016\n\u00051b!a\u0002(pi\"Lgn\u001a\t\u000399J!a\f\u0007\u0003\u0007\u0005s\u0017\u0010\u0005\u0002\u001dc%\u0011!\u0007\u0004\u0002\u0005+:LG/\u0001\u0004=S:LGO\u0010\u000b\u0002kA\u0019a\u0007\u0001\u0013\u000e\u0003!\tqa\u0018:fgVdG/\u0001\u0004sKN,H\u000e^\u000b\u0002?\u0005\u0001BO]=BGF,\u0018N]3TQ\u0006\u0014X\r\u001a\u000b\u0003y}\u0002\"\u0001H\u001f\n\u0005yb!aA%oi\")\u0001\t\u0002a\u0001y\u00059\u0011n\u001a8pe\u0016$\u0017\u0001\u0005;ssJ+G.Z1tKNC\u0017M]3e)\t\u0019e\t\u0005\u0002\u001d\t&\u0011Q\t\u0004\u0002\b\u0005>|G.Z1o\u0011\u00159U\u00011\u0001=\u0003\u0019IwM\\8sK\u0006)\u0011\r\u001d9msR\u0011\u0001G\u0013\u0005\u0006\u0017\u001a\u0001\raH\u0001\u0006m\u0006dW/\u001a"
    )
  ScalaInlineInfo: length = 0xA9 (unknown attribute)
   01 01 00 21 00 DD 00 DE 01 00 AF 00 A7 01 00 CA
   00 D1 01 00 CA 00 CB 01 00 19 00 1A 01 00 3E 00
   3F 01 00 63 00 64 01 00 88 00 89 01 00 1F 00 20
   01 00 44 00 45 01 00 69 00 6A 01 00 8E 00 8F 01
   00 25 00 26 01 00 4A 00 4B 01 00 6F 00 70 01 00
   94 00 95 01 00 2B 00 2C 01 00 50 00 51 01 00 75
   00 76 01 00 9A 00 9B 01 00 31 00 32 01 00 56 00
   57 01 00 7B 00 7C 01 00 A0 00 A1 01 00 0F 00 10
   01 00 37 00 38 01 00 5C 00 5D 01 00 81 00 82 01
   00 A6 00 A7 01 00 BA 00 BB 01 00 B4 00 B5 01 00
   BF 00 70 01 00 C5 00 5D 01
  ScalaSig: length = 0x3 (unknown attribute)
   05 02 00
