Classfile /Users/mw/Projects/slang-braindump/.jar/jar8/assemble/slang-braindump/assemble/content/scala/concurrent/impl/ExecutionContextImpl$$anon$3.class
  Last modified May 29, 2022; size 2116 bytes
  SHA-256 checksum c3929de5c71165d735c9eb4067e3ebb360fa3142e9612df34a1727bbef370cba
  Compiled from "ExecutionContextImpl.scala"
public final class scala.concurrent.impl.ExecutionContextImpl$$anon$3 extends java.util.concurrent.ForkJoinPool implements scala.concurrent.ExecutionContextExecutorService
  minor version: 0
  major version: 52
  flags: (0x0031) ACC_PUBLIC, ACC_FINAL, ACC_SUPER
  this_class: #2                          // scala/concurrent/impl/ExecutionContextImpl$$anon$3
  super_class: #4                         // java/util/concurrent/ForkJoinPool
  interfaces: 1, fields: 0, methods: 3, attributes: 5
Constant pool:
   #1 = Utf8               scala/concurrent/impl/ExecutionContextImpl$$anon$3
   #2 = Class              #1             // scala/concurrent/impl/ExecutionContextImpl$$anon$3
   #3 = Utf8               java/util/concurrent/ForkJoinPool
   #4 = Class              #3             // java/util/concurrent/ForkJoinPool
   #5 = Utf8               scala/concurrent/ExecutionContextExecutorService
   #6 = Class              #5             // scala/concurrent/ExecutionContextExecutorService
   #7 = Utf8               ExecutionContextImpl.scala
   #8 = Utf8               scala/concurrent/impl/ExecutionContextImpl$
   #9 = Class              #8             // scala/concurrent/impl/ExecutionContextImpl$
  #10 = Utf8               createDefaultExecutorService
  #11 = Utf8               (Lscala/Function1;)Lscala/concurrent/ExecutionContextExecutorService;
  #12 = NameAndType        #10:#11        // createDefaultExecutorService:(Lscala/Function1;)Lscala/concurrent/ExecutionContextExecutorService;
  #13 = Utf8               java/lang/Thread$UncaughtExceptionHandler
  #14 = Class              #13            // java/lang/Thread$UncaughtExceptionHandler
  #15 = Utf8               java/lang/Thread
  #16 = Class              #15            // java/lang/Thread
  #17 = Utf8               UncaughtExceptionHandler
  #18 = Utf8               java/util/concurrent/ForkJoinPool$ForkJoinWorkerThreadFactory
  #19 = Class              #18            // java/util/concurrent/ForkJoinPool$ForkJoinWorkerThreadFactory
  #20 = Utf8               ForkJoinWorkerThreadFactory
  #21 = Utf8               scala/concurrent/impl/ExecutionContextImpl$DefaultThreadFactory
  #22 = Class              #21            // scala/concurrent/impl/ExecutionContextImpl$DefaultThreadFactory
  #23 = Utf8               scala/concurrent/impl/ExecutionContextImpl
  #24 = Class              #23            // scala/concurrent/impl/ExecutionContextImpl
  #25 = Utf8               DefaultThreadFactory
  #26 = Utf8               prepare
  #27 = Utf8               ()Lscala/concurrent/ExecutionContext;
  #28 = Utf8               scala/concurrent/ExecutionContext
  #29 = Class              #28            // scala/concurrent/ExecutionContext
  #30 = Utf8               prepare$
  #31 = Utf8               (Lscala/concurrent/ExecutionContext;)Lscala/concurrent/ExecutionContext;
  #32 = NameAndType        #30:#31        // prepare$:(Lscala/concurrent/ExecutionContext;)Lscala/concurrent/ExecutionContext;
  #33 = InterfaceMethodref #29.#32        // scala/concurrent/ExecutionContext.prepare$:(Lscala/concurrent/ExecutionContext;)Lscala/concurrent/ExecutionContext;
  #34 = Utf8               this
  #35 = Utf8               Lscala/concurrent/impl/ExecutionContextImpl$$anon$3;
  #36 = Utf8               reportFailure
  #37 = Utf8               (Ljava/lang/Throwable;)V
  #38 = Utf8               cause
  #39 = Utf8               getUncaughtExceptionHandler
  #40 = Utf8               ()Ljava/lang/Thread$UncaughtExceptionHandler;
  #41 = NameAndType        #39:#40        // getUncaughtExceptionHandler:()Ljava/lang/Thread$UncaughtExceptionHandler;
  #42 = Methodref          #2.#41         // scala/concurrent/impl/ExecutionContextImpl$$anon$3.getUncaughtExceptionHandler:()Ljava/lang/Thread$UncaughtExceptionHandler;
  #43 = Utf8               currentThread
  #44 = Utf8               ()Ljava/lang/Thread;
  #45 = NameAndType        #43:#44        // currentThread:()Ljava/lang/Thread;
  #46 = Methodref          #16.#45        // java/lang/Thread.currentThread:()Ljava/lang/Thread;
  #47 = Utf8               uncaughtException
  #48 = Utf8               (Ljava/lang/Thread;Ljava/lang/Throwable;)V
  #49 = NameAndType        #47:#48        // uncaughtException:(Ljava/lang/Thread;Ljava/lang/Throwable;)V
  #50 = InterfaceMethodref #14.#49        // java/lang/Thread$UncaughtExceptionHandler.uncaughtException:(Ljava/lang/Thread;Ljava/lang/Throwable;)V
  #51 = Utf8               Ljava/lang/Throwable;
  #52 = Utf8               <init>
  #53 = Utf8               (ILscala/concurrent/impl/ExecutionContextImpl$DefaultThreadFactory;)V
  #54 = Utf8               desiredParallelism$1
  #55 = Utf8               threadFactory$1
  #56 = Utf8               uncaught
  #57 = NameAndType        #56:#40        // uncaught:()Ljava/lang/Thread$UncaughtExceptionHandler;
  #58 = Methodref          #22.#57        // scala/concurrent/impl/ExecutionContextImpl$DefaultThreadFactory.uncaught:()Ljava/lang/Thread$UncaughtExceptionHandler;
  #59 = Utf8               (ILjava/util/concurrent/ForkJoinPool$ForkJoinWorkerThreadFactory;Ljava/lang/Thread$UncaughtExceptionHandler;Z)V
  #60 = NameAndType        #52:#59        // "<init>":(ILjava/util/concurrent/ForkJoinPool$ForkJoinWorkerThreadFactory;Ljava/lang/Thread$UncaughtExceptionHandler;Z)V
  #61 = Methodref          #4.#60         // java/util/concurrent/ForkJoinPool."<init>":(ILjava/util/concurrent/ForkJoinPool$ForkJoinWorkerThreadFactory;Ljava/lang/Thread$UncaughtExceptionHandler;Z)V
  #62 = Utf8               I
  #63 = Utf8               Lscala/concurrent/impl/ExecutionContextImpl$DefaultThreadFactory;
  #64 = Utf8               Code
  #65 = Utf8               LineNumberTable
  #66 = Utf8               LocalVariableTable
  #67 = Utf8               Deprecated
  #68 = Utf8               StackMapTable
  #69 = Utf8               MethodParameters
  #70 = Utf8               InnerClasses
  #71 = Utf8               EnclosingMethod
  #72 = Utf8               SourceFile
  #73 = Utf8               ScalaInlineInfo
  #74 = Utf8               Scala
{
  public scala.concurrent.ExecutionContext prepare();
    descriptor: ()Lscala/concurrent/ExecutionContext;
    flags: (0x0001) ACC_PUBLIC
    Code:
      stack=1, locals=1, args_size=1
         0: aload_0
         1: invokestatic  #33                 // InterfaceMethod scala/concurrent/ExecutionContext.prepare$:(Lscala/concurrent/ExecutionContext;)Lscala/concurrent/ExecutionContext;
         4: areturn
      LineNumberTable:
        line 101: 0
      LocalVariableTable:
        Start  Length  Slot  Name   Signature
            0       5     0  this   Lscala/concurrent/impl/ExecutionContextImpl$$anon$3;
    Deprecated: true

  public final void reportFailure(java.lang.Throwable);
    descriptor: (Ljava/lang/Throwable;)V
    flags: (0x0011) ACC_PUBLIC, ACC_FINAL
    Code:
      stack=3, locals=3, args_size=2
         0: aload_0
         1: invokevirtual #42                 // Method getUncaughtExceptionHandler:()Ljava/lang/Thread$UncaughtExceptionHandler;
         4: astore_2
         5: aload_2
         6: ifnonnull     10
         9: return
        10: aload_2
        11: invokestatic  #46                 // Method java/lang/Thread.currentThread:()Ljava/lang/Thread;
        14: aload_1
        15: invokeinterface #50,  3           // InterfaceMethod java/lang/Thread$UncaughtExceptionHandler.uncaughtException:(Ljava/lang/Thread;Ljava/lang/Throwable;)V
        20: return
      StackMapTable: number_of_entries = 1
        frame_type = 252 /* append */
          offset_delta = 10
          locals = [ class java/lang/Thread$UncaughtExceptionHandler ]
      LineNumberTable:
        line 103: 0
        line 104: 5
        line 105: 10
        line 103: 20
      LocalVariableTable:
        Start  Length  Slot  Name   Signature
            0      21     0  this   Lscala/concurrent/impl/ExecutionContextImpl$$anon$3;
            0      21     1 cause   Ljava/lang/Throwable;
    MethodParameters:
      Name                           Flags
      cause                          final

  public scala.concurrent.impl.ExecutionContextImpl$$anon$3(int, scala.concurrent.impl.ExecutionContextImpl$DefaultThreadFactory);
    descriptor: (ILscala/concurrent/impl/ExecutionContextImpl$DefaultThreadFactory;)V
    flags: (0x0001) ACC_PUBLIC
    Code:
      stack=5, locals=3, args_size=3
         0: aload_0
         1: iload_1
         2: aload_2
         3: aload_2
         4: invokevirtual #58                 // Method scala/concurrent/impl/ExecutionContextImpl$DefaultThreadFactory.uncaught:()Ljava/lang/Thread$UncaughtExceptionHandler;
         7: iconst_1
         8: invokespecial #61                 // Method java/util/concurrent/ForkJoinPool."<init>":(ILjava/util/concurrent/ForkJoinPool$ForkJoinWorkerThreadFactory;Ljava/lang/Thread$UncaughtExceptionHandler;Z)V
        11: return
      LineNumberTable:
        line 101: 0
      LocalVariableTable:
        Start  Length  Slot  Name   Signature
            0      12     0  this   Lscala/concurrent/impl/ExecutionContextImpl$$anon$3;
            0      12     1 desiredParallelism$1   I
            0      12     2 threadFactory$1   Lscala/concurrent/impl/ExecutionContextImpl$DefaultThreadFactory;
    MethodParameters:
      Name                           Flags
      desiredParallelism$1           final
      threadFactory$1                final
}
InnerClasses:
  public static #17= #14 of #16;          // UncaughtExceptionHandler=class java/lang/Thread$UncaughtExceptionHandler of class java/lang/Thread
  public static #20= #19 of #4;           // ForkJoinWorkerThreadFactory=class java/util/concurrent/ForkJoinPool$ForkJoinWorkerThreadFactory of class java/util/concurrent/ForkJoinPool
  public final #2;                        // class scala/concurrent/impl/ExecutionContextImpl$$anon$3
  public static final #25= #22 of #24;    // DefaultThreadFactory=class scala/concurrent/impl/ExecutionContextImpl$DefaultThreadFactory of class scala/concurrent/impl/ExecutionContextImpl
EnclosingMethod: #9.#12                 // scala.concurrent.impl.ExecutionContextImpl$.createDefaultExecutorService
SourceFile: "ExecutionContextImpl.scala"
  ScalaInlineInfo: length = 0x13 (unknown attribute)
   01 01 00 03 00 34 00 35 01 00 1A 00 1B 01 00 24
   00 25 01
  Scala: length = 0x0 (unknown attribute)

