Classfile /Users/mw/Projects/slang-braindump/.jar/jar8/assemble/slang-braindump/assemble/content/scala/concurrent/impl/ExecutionContextImpl$.class
  Last modified May 29, 2022; size 5663 bytes
  SHA-256 checksum 2e5d1f8b4d9205f1d0bd47782bbda66b4e1b6ccf12d5be77310d2204ef2d04f2
  Compiled from "ExecutionContextImpl.scala"
public final class scala.concurrent.impl.ExecutionContextImpl$
  minor version: 0
  major version: 52
  flags: (0x0031) ACC_PUBLIC, ACC_FINAL, ACC_SUPER
  this_class: #2                          // scala/concurrent/impl/ExecutionContextImpl$
  super_class: #4                         // java/lang/Object
  interfaces: 0, fields: 1, methods: 9, attributes: 5
Constant pool:
    #1 = Utf8               scala/concurrent/impl/ExecutionContextImpl$
    #2 = Class              #1            // scala/concurrent/impl/ExecutionContextImpl$
    #3 = Utf8               java/lang/Object
    #4 = Class              #3            // java/lang/Object
    #5 = Utf8               ExecutionContextImpl.scala
    #6 = Utf8               java/lang/Thread$UncaughtExceptionHandler
    #7 = Class              #6            // java/lang/Thread$UncaughtExceptionHandler
    #8 = Utf8               java/lang/Thread
    #9 = Class              #8            // java/lang/Thread
   #10 = Utf8               UncaughtExceptionHandler
   #11 = Utf8               java/lang/invoke/MethodHandles$Lookup
   #12 = Class              #11           // java/lang/invoke/MethodHandles$Lookup
   #13 = Utf8               java/lang/invoke/MethodHandles
   #14 = Class              #13           // java/lang/invoke/MethodHandles
   #15 = Utf8               Lookup
   #16 = Utf8               scala/concurrent/impl/ExecutionContextImpl$$anon$3
   #17 = Class              #16           // scala/concurrent/impl/ExecutionContextImpl$$anon$3
   #18 = Utf8               scala/concurrent/impl/ExecutionContextImpl$$anon$4
   #19 = Class              #18           // scala/concurrent/impl/ExecutionContextImpl$$anon$4
   #20 = Utf8               scala/concurrent/impl/ExecutionContextImpl$DefaultThreadFactory
   #21 = Class              #20           // scala/concurrent/impl/ExecutionContextImpl$DefaultThreadFactory
   #22 = Utf8               scala/concurrent/impl/ExecutionContextImpl
   #23 = Class              #22           // scala/concurrent/impl/ExecutionContextImpl
   #24 = Utf8               DefaultThreadFactory
   #25 = Utf8               MODULE$
   #26 = Utf8               Lscala/concurrent/impl/ExecutionContextImpl$;
   #27 = Utf8               <clinit>
   #28 = Utf8               ()V
   #29 = Utf8               <init>
   #30 = NameAndType        #29:#28       // "<init>":()V
   #31 = Methodref          #2.#30        // scala/concurrent/impl/ExecutionContextImpl$."<init>":()V
   #32 = NameAndType        #25:#26       // MODULE$:Lscala/concurrent/impl/ExecutionContextImpl$;
   #33 = Fieldref           #2.#32        // scala/concurrent/impl/ExecutionContextImpl$.MODULE$:Lscala/concurrent/impl/ExecutionContextImpl$;
   #34 = Utf8               createDefaultExecutorService
   #35 = Utf8               (Lscala/Function1;)Lscala/concurrent/ExecutionContextExecutorService;
   #36 = Utf8               (Lscala/Function1<Ljava/lang/Throwable;Lscala/runtime/BoxedUnit;>;)Lscala/concurrent/ExecutionContextExecutorService;
   #37 = Utf8               reporter
   #38 = Utf8               scala/math/package$
   #39 = Class              #38           // scala/math/package$
   #40 = Utf8               Lscala/math/package$;
   #41 = NameAndType        #25:#40       // MODULE$:Lscala/math/package$;
   #42 = Fieldref           #39.#41       // scala/math/package$.MODULE$:Lscala/math/package$;
   #43 = Utf8               scala.concurrent.context.minThreads
   #44 = String             #43           // scala.concurrent.context.minThreads
   #45 = Utf8               1
   #46 = String             #45           // 1
   #47 = Utf8               getInt$1
   #48 = Utf8               (Ljava/lang/String;Ljava/lang/String;)I
   #49 = NameAndType        #47:#48       // getInt$1:(Ljava/lang/String;Ljava/lang/String;)I
   #50 = Methodref          #2.#49        // scala/concurrent/impl/ExecutionContextImpl$.getInt$1:(Ljava/lang/String;Ljava/lang/String;)I
   #51 = Utf8               scala.concurrent.context.numThreads
   #52 = String             #51           // scala.concurrent.context.numThreads
   #53 = Utf8               x1
   #54 = String             #53           // x1
   #55 = Utf8               java/lang/Math
   #56 = Class              #55           // java/lang/Math
   #57 = Utf8               max
   #58 = Utf8               (II)I
   #59 = NameAndType        #57:#58       // max:(II)I
   #60 = Methodref          #56.#59       // java/lang/Math.max:(II)I
   #61 = Utf8               scala.concurrent.context.maxThreads
   #62 = String             #61           // scala.concurrent.context.maxThreads
   #63 = Utf8               min
   #64 = NameAndType        #63:#58       // min:(II)I
   #65 = Methodref          #56.#64       // java/lang/Math.min:(II)I
   #66 = Utf8               scala.concurrent.context.maxExtraThreads
   #67 = String             #66           // scala.concurrent.context.maxExtraThreads
   #68 = Utf8               256
   #69 = String             #68           // 256
   #70 = Utf8               scala-execution-context-global
   #71 = String             #70           // scala-execution-context-global
   #72 = Utf8               (Ljava/lang/Thread;Ljava/lang/Throwable;)V
   #73 = MethodType         #72           //  (Ljava/lang/Thread;Ljava/lang/Throwable;)V
   #74 = Utf8               $anonfun$createDefaultExecutorService$1
   #75 = Utf8               (Lscala/Function1;Ljava/lang/Thread;Ljava/lang/Throwable;)V
   #76 = NameAndType        #74:#75       // $anonfun$createDefaultExecutorService$1:(Lscala/Function1;Ljava/lang/Thread;Ljava/lang/Throwable;)V
   #77 = Methodref          #2.#76        // scala/concurrent/impl/ExecutionContextImpl$.$anonfun$createDefaultExecutorService$1:(Lscala/Function1;Ljava/lang/Thread;Ljava/lang/Throwable;)V
   #78 = MethodHandle       6:#77         // REF_invokeStatic scala/concurrent/impl/ExecutionContextImpl$.$anonfun$createDefaultExecutorService$1:(Lscala/Function1;Ljava/lang/Thread;Ljava/lang/Throwable;)V
   #79 = Integer            0
   #80 = Utf8               java/lang/invoke/LambdaMetafactory
   #81 = Class              #80           // java/lang/invoke/LambdaMetafactory
   #82 = Utf8               altMetafactory
   #83 = Utf8               (Ljava/lang/invoke/MethodHandles$Lookup;Ljava/lang/String;Ljava/lang/invoke/MethodType;[Ljava/lang/Object;)Ljava/lang/invoke/CallSite;
   #84 = NameAndType        #82:#83       // altMetafactory:(Ljava/lang/invoke/MethodHandles$Lookup;Ljava/lang/String;Ljava/lang/invoke/MethodType;[Ljava/lang/Object;)Ljava/lang/invoke/CallSite;
   #85 = Methodref          #81.#84       // java/lang/invoke/LambdaMetafactory.altMetafactory:(Ljava/lang/invoke/MethodHandles$Lookup;Ljava/lang/String;Ljava/lang/invoke/MethodType;[Ljava/lang/Object;)Ljava/lang/invoke/CallSite;
   #86 = MethodHandle       6:#85         // REF_invokeStatic java/lang/invoke/LambdaMetafactory.altMetafactory:(Ljava/lang/invoke/MethodHandles$Lookup;Ljava/lang/String;Ljava/lang/invoke/MethodType;[Ljava/lang/Object;)Ljava/lang/invoke/CallSite;
   #87 = Utf8               uncaughtException
   #88 = Utf8               (Lscala/Function1;)Ljava/lang/Thread$UncaughtExceptionHandler;
   #89 = NameAndType        #87:#88       // uncaughtException:(Lscala/Function1;)Ljava/lang/Thread$UncaughtExceptionHandler;
   #90 = InvokeDynamic      #0:#89        // #0:uncaughtException:(Lscala/Function1;)Ljava/lang/Thread$UncaughtExceptionHandler;
   #91 = Utf8               (ZILjava/lang/String;Ljava/lang/Thread$UncaughtExceptionHandler;)V
   #92 = NameAndType        #29:#91       // "<init>":(ZILjava/lang/String;Ljava/lang/Thread$UncaughtExceptionHandler;)V
   #93 = Methodref          #21.#92       // scala/concurrent/impl/ExecutionContextImpl$DefaultThreadFactory."<init>":(ZILjava/lang/String;Ljava/lang/Thread$UncaughtExceptionHandler;)V
   #94 = Utf8               (ILscala/concurrent/impl/ExecutionContextImpl$DefaultThreadFactory;)V
   #95 = NameAndType        #29:#94       // "<init>":(ILscala/concurrent/impl/ExecutionContextImpl$DefaultThreadFactory;)V
   #96 = Methodref          #17.#95       // scala/concurrent/impl/ExecutionContextImpl$$anon$3."<init>":(ILscala/concurrent/impl/ExecutionContextImpl$DefaultThreadFactory;)V
   #97 = Utf8               threadFactory
   #98 = Utf8               Lscala/concurrent/impl/ExecutionContextImpl$DefaultThreadFactory;
   #99 = Utf8               this
  #100 = Utf8               Lscala/Function1;
  #101 = Utf8               min_y
  #102 = Utf8               I
  #103 = Utf8               fromExecutor
  #104 = Utf8               (Ljava/util/concurrent/Executor;Lscala/Function1;)Lscala/concurrent/ExecutionContextExecutor;
  #105 = Utf8               (Ljava/util/concurrent/Executor;Lscala/Function1<Ljava/lang/Throwable;Lscala/runtime/BoxedUnit;>;)Lscala/concurrent/ExecutionContextExecutor;
  #106 = Utf8               e
  #107 = Utf8               (Ljava/util/concurrent/Executor;Lscala/Function1;)V
  #108 = NameAndType        #29:#107      // "<init>":(Ljava/util/concurrent/Executor;Lscala/Function1;)V
  #109 = Methodref          #23.#108      // scala/concurrent/impl/ExecutionContextImpl."<init>":(Ljava/util/concurrent/Executor;Lscala/Function1;)V
  #110 = Utf8               Ljava/util/concurrent/Executor;
  #111 = Utf8               createDefaultExecutorService_threadFactory
  #112 = Utf8               createDefaultExecutorService_min_y
  #113 = Utf8               fromExecutor$default$2
  #114 = Utf8               ()Lscala/Function1;
  #115 = Utf8               ()Lscala/Function1<Ljava/lang/Throwable;Lscala/runtime/BoxedUnit;>;
  #116 = Utf8               scala/concurrent/ExecutionContext$
  #117 = Class              #116          // scala/concurrent/ExecutionContext$
  #118 = Utf8               Lscala/concurrent/ExecutionContext$;
  #119 = NameAndType        #25:#118      // MODULE$:Lscala/concurrent/ExecutionContext$;
  #120 = Fieldref           #117.#119     // scala/concurrent/ExecutionContext$.MODULE$:Lscala/concurrent/ExecutionContext$;
  #121 = Utf8               defaultReporter
  #122 = NameAndType        #121:#114     // defaultReporter:()Lscala/Function1;
  #123 = Methodref          #117.#122     // scala/concurrent/ExecutionContext$.defaultReporter:()Lscala/Function1;
  #124 = Utf8               fromExecutorService
  #125 = Utf8               (Ljava/util/concurrent/ExecutorService;Lscala/Function1;)Lscala/concurrent/ExecutionContextExecutorService;
  #126 = Utf8               (Ljava/util/concurrent/ExecutorService;Lscala/Function1<Ljava/lang/Throwable;Lscala/runtime/BoxedUnit;>;)Lscala/concurrent/ExecutionContextExecutorService;
  #127 = Utf8               es
  #128 = Utf8               (Ljava/util/concurrent/ExecutorService;Lscala/Function1;)V
  #129 = NameAndType        #29:#128      // "<init>":(Ljava/util/concurrent/ExecutorService;Lscala/Function1;)V
  #130 = Methodref          #19.#129      // scala/concurrent/impl/ExecutionContextImpl$$anon$4."<init>":(Ljava/util/concurrent/ExecutorService;Lscala/Function1;)V
  #131 = Utf8               Ljava/util/concurrent/ExecutorService;
  #132 = Utf8               fromExecutorService$default$2
  #133 = Utf8               name
  #134 = Utf8               default
  #135 = Utf8               java/lang/SecurityException
  #136 = Class              #135          // java/lang/SecurityException
  #137 = Utf8               java/lang/System
  #138 = Class              #137          // java/lang/System
  #139 = Utf8               getProperty
  #140 = Utf8               (Ljava/lang/String;Ljava/lang/String;)Ljava/lang/String;
  #141 = NameAndType        #139:#140     // getProperty:(Ljava/lang/String;Ljava/lang/String;)Ljava/lang/String;
  #142 = Methodref          #138.#141     // java/lang/System.getProperty:(Ljava/lang/String;Ljava/lang/String;)Ljava/lang/String;
  #143 = Utf8               java/lang/String
  #144 = Class              #143          // java/lang/String
  #145 = Utf8               hashCode
  #146 = Utf8               ()I
  #147 = NameAndType        #145:#146     // hashCode:()I
  #148 = Methodref          #144.#147     // java/lang/String.hashCode:()I
  #149 = Utf8               charAt
  #150 = Utf8               (I)C
  #151 = NameAndType        #149:#150     // charAt:(I)C
  #152 = Methodref          #144.#151     // java/lang/String.charAt:(I)C
  #153 = Utf8               scala/runtime/RichDouble$
  #154 = Class              #153          // scala/runtime/RichDouble$
  #155 = Utf8               Lscala/runtime/RichDouble$;
  #156 = NameAndType        #25:#155      // MODULE$:Lscala/runtime/RichDouble$;
  #157 = Fieldref           #154.#156     // scala/runtime/RichDouble$.MODULE$:Lscala/runtime/RichDouble$;
  #158 = Utf8               java/lang/Runtime
  #159 = Class              #158          // java/lang/Runtime
  #160 = Utf8               getRuntime
  #161 = Utf8               ()Ljava/lang/Runtime;
  #162 = NameAndType        #160:#161     // getRuntime:()Ljava/lang/Runtime;
  #163 = Methodref          #159.#162     // java/lang/Runtime.getRuntime:()Ljava/lang/Runtime;
  #164 = Utf8               availableProcessors
  #165 = NameAndType        #164:#146     // availableProcessors:()I
  #166 = Methodref          #159.#165     // java/lang/Runtime.availableProcessors:()I
  #167 = Utf8               substring
  #168 = Utf8               (I)Ljava/lang/String;
  #169 = NameAndType        #167:#168     // substring:(I)Ljava/lang/String;
  #170 = Methodref          #144.#169     // java/lang/String.substring:(I)Ljava/lang/String;
  #171 = Utf8               java/lang/Double
  #172 = Class              #171          // java/lang/Double
  #173 = Utf8               parseDouble
  #174 = Utf8               (Ljava/lang/String;)D
  #175 = NameAndType        #173:#174     // parseDouble:(Ljava/lang/String;)D
  #176 = Methodref          #172.#175     // java/lang/Double.parseDouble:(Ljava/lang/String;)D
  #177 = Utf8               ceil
  #178 = Utf8               (D)D
  #179 = NameAndType        #177:#178     // ceil:(D)D
  #180 = Methodref          #56.#179      // java/lang/Math.ceil:(D)D
  #181 = Utf8               java/lang/Integer
  #182 = Class              #181          // java/lang/Integer
  #183 = Utf8               parseInt
  #184 = Utf8               (Ljava/lang/String;)I
  #185 = NameAndType        #183:#184     // parseInt:(Ljava/lang/String;)I
  #186 = Methodref          #182.#185     // java/lang/Integer.parseInt:(Ljava/lang/String;)I
  #187 = Utf8               Ljava/lang/String;
  #188 = Utf8               reporter$1
  #189 = Utf8               thread
  #190 = Utf8               cause
  #191 = Utf8               scala/Function1
  #192 = Class              #191          // scala/Function1
  #193 = Utf8               apply
  #194 = Utf8               (Ljava/lang/Object;)Ljava/lang/Object;
  #195 = NameAndType        #193:#194     // apply:(Ljava/lang/Object;)Ljava/lang/Object;
  #196 = InterfaceMethodref #192.#195     // scala/Function1.apply:(Ljava/lang/Object;)Ljava/lang/Object;
  #197 = Utf8               Ljava/lang/Thread;
  #198 = Utf8               Ljava/lang/Throwable;
  #199 = Methodref          #4.#30        // java/lang/Object."<init>":()V
  #200 = Utf8               Code
  #201 = Utf8               LineNumberTable
  #202 = Utf8               LocalVariableTable
  #203 = Utf8               Signature
  #204 = Utf8               MethodParameters
  #205 = Utf8               StackMapTable
  #206 = Utf8               InnerClasses
  #207 = Utf8               SourceFile
  #208 = Utf8               BootstrapMethods
  #209 = Utf8               ScalaInlineInfo
  #210 = Utf8               Scala
{
  public static final scala.concurrent.impl.ExecutionContextImpl$ MODULE$;
    descriptor: Lscala/concurrent/impl/ExecutionContextImpl$;
    flags: (0x0019) ACC_PUBLIC, ACC_STATIC, ACC_FINAL

  public static {};
    descriptor: ()V
    flags: (0x0009) ACC_PUBLIC, ACC_STATIC
    Code:
      stack=2, locals=0, args_size=0
         0: new           #2                  // class scala/concurrent/impl/ExecutionContextImpl$
         3: dup
         4: invokespecial #31                 // Method "<init>":()V
         7: putstatic     #33                 // Field MODULE$:Lscala/concurrent/impl/ExecutionContextImpl$;
        10: return
      LineNumberTable:
        line 25: 0

  public scala.concurrent.ExecutionContextExecutorService createDefaultExecutorService(scala.Function1<java.lang.Throwable, scala.runtime.BoxedUnit>);
    descriptor: (Lscala/Function1;)Lscala/concurrent/ExecutionContextExecutorService;
    flags: (0x0001) ACC_PUBLIC
    Code:
      stack=6, locals=6, args_size=2
         0: getstatic     #42                 // Field scala/math/package$.MODULE$:Lscala/math/package$;
         3: pop
         4: getstatic     #42                 // Field scala/math/package$.MODULE$:Lscala/math/package$;
         7: pop
         8: ldc           #44                 // String scala.concurrent.context.minThreads
        10: ldc           #46                 // String 1
        12: invokestatic  #50                 // Method getInt$1:(Ljava/lang/String;Ljava/lang/String;)I
        15: ldc           #52                 // String scala.concurrent.context.numThreads
        17: ldc           #54                 // String x1
        19: invokestatic  #50                 // Method getInt$1:(Ljava/lang/String;Ljava/lang/String;)I
        22: invokestatic  #60                 // Method java/lang/Math.max:(II)I
        25: istore_3
        26: ldc           #62                 // String scala.concurrent.context.maxThreads
        28: ldc           #54                 // String x1
        30: invokestatic  #50                 // Method getInt$1:(Ljava/lang/String;Ljava/lang/String;)I
        33: istore        4
        35: iload_3
        36: iload         4
        38: invokestatic  #65                 // Method java/lang/Math.min:(II)I
        41: istore        5
        43: new           #21                 // class scala/concurrent/impl/ExecutionContextImpl$DefaultThreadFactory
        46: dup
        47: iconst_1
        48: ldc           #67                 // String scala.concurrent.context.maxExtraThreads
        50: ldc           #69                 // String 256
        52: invokestatic  #50                 // Method getInt$1:(Ljava/lang/String;Ljava/lang/String;)I
        55: ldc           #71                 // String scala-execution-context-global
        57: aload_1
        58: invokedynamic #90,  0             // InvokeDynamic #0:uncaughtException:(Lscala/Function1;)Ljava/lang/Thread$UncaughtExceptionHandler;
        63: invokespecial #93                 // Method scala/concurrent/impl/ExecutionContextImpl$DefaultThreadFactory."<init>":(ZILjava/lang/String;Ljava/lang/Thread$UncaughtExceptionHandler;)V
        66: astore_2
        67: new           #17                 // class scala/concurrent/impl/ExecutionContextImpl$$anon$3
        70: dup
        71: iload         5
        73: aload_2
        74: invokespecial #96                 // Method scala/concurrent/impl/ExecutionContextImpl$$anon$3."<init>":(ILscala/concurrent/impl/ExecutionContextImpl$DefaultThreadFactory;)V
        77: areturn
      LineNumberTable:
        line 89: 0
        line 90: 4
        line 91: 8
        line 92: 15
        line 93: 26
        line 96: 43
        line 97: 48
        line 98: 55
        line 99: 57
        line 101: 67
      LocalVariableTable:
        Start  Length  Slot  Name   Signature
           67      10     2 threadFactory   Lscala/concurrent/impl/ExecutionContextImpl$DefaultThreadFactory;
            0      78     0  this   Lscala/concurrent/impl/ExecutionContextImpl$;
            0      78     1 reporter   Lscala/Function1;
           35       8     4 min_y   I
    Signature: #36                          // (Lscala/Function1<Ljava/lang/Throwable;Lscala/runtime/BoxedUnit;>;)Lscala/concurrent/ExecutionContextExecutorService;
    MethodParameters:
      Name                           Flags
      reporter                       final

  public scala.concurrent.ExecutionContextExecutor fromExecutor(java.util.concurrent.Executor, scala.Function1<java.lang.Throwable, scala.runtime.BoxedUnit>);
    descriptor: (Ljava/util/concurrent/Executor;Lscala/Function1;)Lscala/concurrent/ExecutionContextExecutor;
    flags: (0x0001) ACC_PUBLIC
    Code:
      stack=6, locals=9, args_size=3
         0: aload_1
         1: ifnonnull     99
         4: getstatic     #42                 // Field scala/math/package$.MODULE$:Lscala/math/package$;
         7: pop
         8: getstatic     #42                 // Field scala/math/package$.MODULE$:Lscala/math/package$;
        11: pop
        12: ldc           #44                 // String scala.concurrent.context.minThreads
        14: ldc           #46                 // String 1
        16: invokestatic  #50                 // Method getInt$1:(Ljava/lang/String;Ljava/lang/String;)I
        19: ldc           #52                 // String scala.concurrent.context.numThreads
        21: ldc           #54                 // String x1
        23: invokestatic  #50                 // Method getInt$1:(Ljava/lang/String;Ljava/lang/String;)I
        26: invokestatic  #60                 // Method java/lang/Math.max:(II)I
        29: istore        5
        31: ldc           #62                 // String scala.concurrent.context.maxThreads
        33: ldc           #54                 // String x1
        35: invokestatic  #50                 // Method getInt$1:(Ljava/lang/String;Ljava/lang/String;)I
        38: istore        6
        40: iload         5
        42: iload         6
        44: invokestatic  #65                 // Method java/lang/Math.min:(II)I
        47: istore        7
        49: new           #21                 // class scala/concurrent/impl/ExecutionContextImpl$DefaultThreadFactory
        52: dup
        53: iconst_1
        54: ldc           #67                 // String scala.concurrent.context.maxExtraThreads
        56: ldc           #69                 // String 256
        58: invokestatic  #50                 // Method getInt$1:(Ljava/lang/String;Ljava/lang/String;)I
        61: ldc           #71                 // String scala-execution-context-global
        63: aload_2
        64: invokedynamic #90,  0             // InvokeDynamic #0:uncaughtException:(Lscala/Function1;)Ljava/lang/Thread$UncaughtExceptionHandler;
        69: invokespecial #93                 // Method scala/concurrent/impl/ExecutionContextImpl$DefaultThreadFactory."<init>":(ZILjava/lang/String;Ljava/lang/Thread$UncaughtExceptionHandler;)V
        72: astore        4
        74: new           #17                 // class scala/concurrent/impl/ExecutionContextImpl$$anon$3
        77: dup
        78: iload         7
        80: aload         4
        82: invokespecial #96                 // Method scala/concurrent/impl/ExecutionContextImpl$$anon$3."<init>":(ILscala/concurrent/impl/ExecutionContextImpl$DefaultThreadFactory;)V
        85: astore        8
        87: aload         8
        89: aconst_null
        90: astore        4
        92: aconst_null
        93: astore        8
        95: astore_3
        96: goto          109
        99: new           #23                 // class scala/concurrent/impl/ExecutionContextImpl
       102: dup
       103: aload_1
       104: aload_2
       105: invokespecial #109                // Method scala/concurrent/impl/ExecutionContextImpl."<init>":(Ljava/util/concurrent/Executor;Lscala/Function1;)V
       108: astore_3
       109: aload_3
       110: areturn
      StackMapTable: number_of_entries = 2
        frame_type = 251 /* same_frame_extended */
          offset_delta = 99
        frame_type = 252 /* append */
          offset_delta = 9
          locals = [ class java/lang/Object ]
      LineNumberTable:
        line 112: 0
        line 89: 4
        line 90: 8
        line 91: 12
        line 92: 19
        line 93: 31
        line 96: 49
        line 97: 54
        line 98: 61
        line 99: 63
        line 101: 74
        line 112: 87
        line 113: 99
        line 111: 109
      LocalVariableTable:
        Start  Length  Slot  Name   Signature
            0     111     0  this   Lscala/concurrent/impl/ExecutionContextImpl$;
            0     111     1     e   Ljava/util/concurrent/Executor;
            0     111     2 reporter   Lscala/Function1;
           74      11     4 createDefaultExecutorService_threadFactory   Lscala/concurrent/impl/ExecutionContextImpl$DefaultThreadFactory;
           40       9     6 createDefaultExecutorService_min_y   I
    Signature: #105                         // (Ljava/util/concurrent/Executor;Lscala/Function1<Ljava/lang/Throwable;Lscala/runtime/BoxedUnit;>;)Lscala/concurrent/ExecutionContextExecutor;
    MethodParameters:
      Name                           Flags
      e                              final
      reporter                       final

  public scala.Function1<java.lang.Throwable, scala.runtime.BoxedUnit> fromExecutor$default$2();
    descriptor: ()Lscala/Function1;
    flags: (0x0001) ACC_PUBLIC
    Code:
      stack=1, locals=1, args_size=1
         0: getstatic     #120                // Field scala/concurrent/ExecutionContext$.MODULE$:Lscala/concurrent/ExecutionContext$;
         3: invokevirtual #123                // Method scala/concurrent/ExecutionContext$.defaultReporter:()Lscala/Function1;
         6: areturn
      LineNumberTable:
        line 110: 0
      LocalVariableTable:
        Start  Length  Slot  Name   Signature
            0       7     0  this   Lscala/concurrent/impl/ExecutionContextImpl$;
    Signature: #115                         // ()Lscala/Function1<Ljava/lang/Throwable;Lscala/runtime/BoxedUnit;>;

  public scala.concurrent.ExecutionContextExecutorService fromExecutorService(java.util.concurrent.ExecutorService, scala.Function1<java.lang.Throwable, scala.runtime.BoxedUnit>);
    descriptor: (Ljava/util/concurrent/ExecutorService;Lscala/Function1;)Lscala/concurrent/ExecutionContextExecutorService;
    flags: (0x0001) ACC_PUBLIC
    Code:
      stack=6, locals=9, args_size=3
         0: aload_1
         1: ifnonnull     99
         4: getstatic     #42                 // Field scala/math/package$.MODULE$:Lscala/math/package$;
         7: pop
         8: getstatic     #42                 // Field scala/math/package$.MODULE$:Lscala/math/package$;
        11: pop
        12: ldc           #44                 // String scala.concurrent.context.minThreads
        14: ldc           #46                 // String 1
        16: invokestatic  #50                 // Method getInt$1:(Ljava/lang/String;Ljava/lang/String;)I
        19: ldc           #52                 // String scala.concurrent.context.numThreads
        21: ldc           #54                 // String x1
        23: invokestatic  #50                 // Method getInt$1:(Ljava/lang/String;Ljava/lang/String;)I
        26: invokestatic  #60                 // Method java/lang/Math.max:(II)I
        29: istore        5
        31: ldc           #62                 // String scala.concurrent.context.maxThreads
        33: ldc           #54                 // String x1
        35: invokestatic  #50                 // Method getInt$1:(Ljava/lang/String;Ljava/lang/String;)I
        38: istore        6
        40: iload         5
        42: iload         6
        44: invokestatic  #65                 // Method java/lang/Math.min:(II)I
        47: istore        7
        49: new           #21                 // class scala/concurrent/impl/ExecutionContextImpl$DefaultThreadFactory
        52: dup
        53: iconst_1
        54: ldc           #67                 // String scala.concurrent.context.maxExtraThreads
        56: ldc           #69                 // String 256
        58: invokestatic  #50                 // Method getInt$1:(Ljava/lang/String;Ljava/lang/String;)I
        61: ldc           #71                 // String scala-execution-context-global
        63: aload_2
        64: invokedynamic #90,  0             // InvokeDynamic #0:uncaughtException:(Lscala/Function1;)Ljava/lang/Thread$UncaughtExceptionHandler;
        69: invokespecial #93                 // Method scala/concurrent/impl/ExecutionContextImpl$DefaultThreadFactory."<init>":(ZILjava/lang/String;Ljava/lang/Thread$UncaughtExceptionHandler;)V
        72: astore        4
        74: new           #17                 // class scala/concurrent/impl/ExecutionContextImpl$$anon$3
        77: dup
        78: iload         7
        80: aload         4
        82: invokespecial #96                 // Method scala/concurrent/impl/ExecutionContextImpl$$anon$3."<init>":(ILscala/concurrent/impl/ExecutionContextImpl$DefaultThreadFactory;)V
        85: astore        8
        87: aload         8
        89: aconst_null
        90: astore        4
        92: aconst_null
        93: astore        8
        95: astore_3
        96: goto          109
        99: new           #19                 // class scala/concurrent/impl/ExecutionContextImpl$$anon$4
       102: dup
       103: aload_1
       104: aload_2
       105: invokespecial #130                // Method scala/concurrent/impl/ExecutionContextImpl$$anon$4."<init>":(Ljava/util/concurrent/ExecutorService;Lscala/Function1;)V
       108: astore_3
       109: aload_3
       110: areturn
      StackMapTable: number_of_entries = 2
        frame_type = 251 /* same_frame_extended */
          offset_delta = 99
        frame_type = 252 /* append */
          offset_delta = 9
          locals = [ class java/lang/Object ]
      LineNumberTable:
        line 118: 0
        line 89: 4
        line 90: 8
        line 91: 12
        line 92: 19
        line 93: 31
        line 96: 49
        line 97: 54
        line 98: 61
        line 99: 63
        line 101: 74
        line 118: 87
        line 120: 99
        line 117: 109
      LocalVariableTable:
        Start  Length  Slot  Name   Signature
            0     111     0  this   Lscala/concurrent/impl/ExecutionContextImpl$;
            0     111     1    es   Ljava/util/concurrent/ExecutorService;
            0     111     2 reporter   Lscala/Function1;
           74      11     4 createDefaultExecutorService_threadFactory   Lscala/concurrent/impl/ExecutionContextImpl$DefaultThreadFactory;
           40       9     6 createDefaultExecutorService_min_y   I
    Signature: #126                         // (Ljava/util/concurrent/ExecutorService;Lscala/Function1<Ljava/lang/Throwable;Lscala/runtime/BoxedUnit;>;)Lscala/concurrent/ExecutionContextExecutorService;
    MethodParameters:
      Name                           Flags
      es                             final
      reporter                       final

  public scala.Function1<java.lang.Throwable, scala.runtime.BoxedUnit> fromExecutorService$default$2();
    descriptor: ()Lscala/Function1;
    flags: (0x0001) ACC_PUBLIC
    Code:
      stack=1, locals=1, args_size=1
         0: getstatic     #120                // Field scala/concurrent/ExecutionContext$.MODULE$:Lscala/concurrent/ExecutionContext$;
         3: invokevirtual #123                // Method scala/concurrent/ExecutionContext$.defaultReporter:()Lscala/Function1;
         6: areturn
      LineNumberTable:
        line 116: 0
      LocalVariableTable:
        Start  Length  Slot  Name   Signature
            0       7     0  this   Lscala/concurrent/impl/ExecutionContextImpl$;
    Signature: #115                         // ()Lscala/Function1<Ljava/lang/Throwable;Lscala/runtime/BoxedUnit;>;

  private static final int getInt$1(java.lang.String, java.lang.String);
    descriptor: (Ljava/lang/String;Ljava/lang/String;)I
    flags: (0x001a) ACC_PRIVATE, ACC_STATIC, ACC_FINAL
    Code:
      stack=4, locals=5, args_size=2
         0: aload_0
         1: aload_1
         2: invokestatic  #142                // Method java/lang/System.getProperty:(Ljava/lang/String;Ljava/lang/String;)Ljava/lang/String;
         5: goto          10
         8: pop
         9: aload_1
        10: astore_2
        11: aload_2
        12: ifnonnull     19
        15: iconst_0
        16: goto          23
        19: aload_2
        20: invokevirtual #148                // Method java/lang/String.hashCode:()I
        23: lookupswitch  { // 0
                 default: 32
            }
        32: aload_2
        33: iconst_0
        34: invokevirtual #152                // Method java/lang/String.charAt:(I)C
        37: bipush        120
        39: if_icmpne     73
        42: getstatic     #157                // Field scala/runtime/RichDouble$.MODULE$:Lscala/runtime/RichDouble$;
        45: pop
        46: invokestatic  #163                // Method java/lang/Runtime.getRuntime:()Ljava/lang/Runtime;
        49: invokevirtual #166                // Method java/lang/Runtime.availableProcessors:()I
        52: i2d
        53: aload_2
        54: iconst_1
        55: invokevirtual #170                // Method java/lang/String.substring:(I)Ljava/lang/String;
        58: invokestatic  #176                // Method java/lang/Double.parseDouble:(Ljava/lang/String;)D
        61: dmul
        62: dstore_3
        63: getstatic     #42                 // Field scala/math/package$.MODULE$:Lscala/math/package$;
        66: pop
        67: dload_3
        68: invokestatic  #180                // Method java/lang/Math.ceil:(D)D
        71: d2i
        72: ireturn
        73: aload_2
        74: invokestatic  #186                // Method java/lang/Integer.parseInt:(Ljava/lang/String;)I
        77: ireturn
      Exception table:
         from    to  target type
             0     5     8   Class java/lang/SecurityException
      StackMapTable: number_of_entries = 6
        frame_type = 72 /* same_locals_1_stack_item */
          stack = [ class java/lang/SecurityException ]
        frame_type = 65 /* same_locals_1_stack_item */
          stack = [ class java/lang/String ]
        frame_type = 252 /* append */
          offset_delta = 8
          locals = [ class java/lang/String ]
        frame_type = 67 /* same_locals_1_stack_item */
          stack = [ int ]
        frame_type = 8 /* same */
        frame_type = 40 /* same */
      LineNumberTable:
        line 81: 0
        line 82: 9
        line 81: 11
        line 84: 32
        line 85: 73
        line 81: 77
      LocalVariableTable:
        Start  Length  Slot  Name   Signature
            0      78     0  name   Ljava/lang/String;
            0      78     1 default   Ljava/lang/String;
    MethodParameters:
      Name                           Flags
      name                           final
      default                        final

  public static final void $anonfun$createDefaultExecutorService$1(scala.Function1, java.lang.Thread, java.lang.Throwable);
    descriptor: (Lscala/Function1;Ljava/lang/Thread;Ljava/lang/Throwable;)V
    flags: (0x1019) ACC_PUBLIC, ACC_STATIC, ACC_FINAL, ACC_SYNTHETIC
    Code:
      stack=2, locals=3, args_size=3
         0: aload_0
         1: aload_2
         2: invokeinterface #196,  2          // InterfaceMethod scala/Function1.apply:(Ljava/lang/Object;)Ljava/lang/Object;
         7: pop
         8: return
      LineNumberTable:
        line 99: 0
      LocalVariableTable:
        Start  Length  Slot  Name   Signature
            0       9     0 reporter$1   Lscala/Function1;
            0       9     1 thread   Ljava/lang/Thread;
            0       9     2 cause   Ljava/lang/Throwable;
    MethodParameters:
      Name                           Flags
      reporter$1                     final
      thread                         final
      cause                          final

  private scala.concurrent.impl.ExecutionContextImpl$();
    descriptor: ()V
    flags: (0x0002) ACC_PRIVATE
    Code:
      stack=1, locals=1, args_size=1
         0: aload_0
         1: invokespecial #199                // Method java/lang/Object."<init>":()V
         4: return
      LineNumberTable:
        line 25: 0
      LocalVariableTable:
        Start  Length  Slot  Name   Signature
            0       5     0  this   Lscala/concurrent/impl/ExecutionContextImpl$;
}
InnerClasses:
  public static #10= #7 of #9;            // UncaughtExceptionHandler=class java/lang/Thread$UncaughtExceptionHandler of class java/lang/Thread
  public static final #15= #12 of #14;    // Lookup=class java/lang/invoke/MethodHandles$Lookup of class java/lang/invoke/MethodHandles
  public final #17;                       // class scala/concurrent/impl/ExecutionContextImpl$$anon$3
  public final #19;                       // class scala/concurrent/impl/ExecutionContextImpl$$anon$4
  public static final #24= #21 of #23;    // DefaultThreadFactory=class scala/concurrent/impl/ExecutionContextImpl$DefaultThreadFactory of class scala/concurrent/impl/ExecutionContextImpl
SourceFile: "ExecutionContextImpl.scala"
BootstrapMethods:
  0: #86 REF_invokeStatic java/lang/invoke/LambdaMetafactory.altMetafactory:(Ljava/lang/invoke/MethodHandles$Lookup;Ljava/lang/String;Ljava/lang/invoke/MethodType;[Ljava/lang/Object;)Ljava/lang/invoke/CallSite;
    Method arguments:
      #73 (Ljava/lang/Thread;Ljava/lang/Throwable;)V
      #78 REF_invokeStatic scala/concurrent/impl/ExecutionContextImpl$.$anonfun$createDefaultExecutorService$1:(Lscala/Function1;Ljava/lang/Thread;Ljava/lang/Throwable;)V
      #73 (Ljava/lang/Thread;Ljava/lang/Throwable;)V
      #79 0
  ScalaInlineInfo: length = 0x2C (unknown attribute)
   01 01 00 08 00 4A 00 4B 01 00 1D 00 1C 01 00 22
   00 23 01 00 67 00 68 01 00 71 00 72 01 00 7C 00
   7D 01 00 84 00 72 01 00 2F 00 30 01
  Scala: length = 0x0 (unknown attribute)

