Classfile /Users/mw/Projects/slang-braindump/.jar/jar8/assemble/slang-braindump/assemble/content/scala/concurrent/impl/Promise$DefaultPromise.class
  Last modified May 29, 2022; size 27645 bytes
  SHA-256 checksum a78d3b492605a0603dbc5d040d4d6be2c871fe83b5803ea7d5a08c19adf6b192
  Compiled from "Promise.scala"
public class scala.concurrent.impl.Promise$DefaultPromise<T extends java.lang.Object> extends java.util.concurrent.atomic.AtomicReference<java.lang.Object> implements scala.concurrent.Promise<T>, scala.concurrent.Future<T>, scala.Function1<scala.util.Try<T>, scala.runtime.BoxedUnit>
  minor version: 0
  major version: 52
  flags: (0x0021) ACC_PUBLIC, ACC_SUPER
  this_class: #2                          // scala/concurrent/impl/Promise$DefaultPromise
  super_class: #5                         // java/util/concurrent/atomic/AtomicReference
  interfaces: 3, fields: 0, methods: 84, attributes: 6
Constant pool:
    #1 = Utf8               scala/concurrent/impl/Promise$DefaultPromise
    #2 = Class              #1            // scala/concurrent/impl/Promise$DefaultPromise
    #3 = Utf8               <T:Ljava/lang/Object;>Ljava/util/concurrent/atomic/AtomicReference<Ljava/lang/Object;>;Lscala/concurrent/Promise<TT;>;Lscala/concurrent/Future<TT;>;Lscala/Function1<Lscala/util/Try<TT;>;Lscala/runtime/BoxedUnit;>;
    #4 = Utf8               java/util/concurrent/atomic/AtomicReference
    #5 = Class              #4            // java/util/concurrent/atomic/AtomicReference
    #6 = Utf8               scala/concurrent/Promise
    #7 = Class              #6            // scala/concurrent/Promise
    #8 = Utf8               scala/concurrent/Future
    #9 = Class              #8            // scala/concurrent/Future
   #10 = Utf8               scala/Function1
   #11 = Class              #10           // scala/Function1
   #12 = Utf8               Promise.scala
   #13 = Utf8               java/lang/invoke/MethodHandles$Lookup
   #14 = Class              #13           // java/lang/invoke/MethodHandles$Lookup
   #15 = Utf8               java/lang/invoke/MethodHandles
   #16 = Class              #15           // java/lang/invoke/MethodHandles
   #17 = Utf8               Lookup
   #18 = Utf8               scala/concurrent/ExecutionContext$parasitic$
   #19 = Class              #18           // scala/concurrent/ExecutionContext$parasitic$
   #20 = Utf8               scala/concurrent/ExecutionContext
   #21 = Class              #20           // scala/concurrent/ExecutionContext
   #22 = Utf8               parasitic$
   #23 = Utf8               scala/concurrent/duration/Duration$Infinite
   #24 = Class              #23           // scala/concurrent/duration/Duration$Infinite
   #25 = Utf8               scala/concurrent/duration/Duration
   #26 = Class              #25           // scala/concurrent/duration/Duration
   #27 = Utf8               Infinite
   #28 = Utf8               scala/concurrent/impl/Promise$Callbacks
   #29 = Class              #28           // scala/concurrent/impl/Promise$Callbacks
   #30 = Utf8               scala/concurrent/impl/Promise
   #31 = Class              #30           // scala/concurrent/impl/Promise
   #32 = Utf8               Callbacks
   #33 = Utf8               DefaultPromise
   #34 = Utf8               scala/concurrent/impl/Promise$Link
   #35 = Class              #34           // scala/concurrent/impl/Promise$Link
   #36 = Utf8               Link
   #37 = Utf8               scala/concurrent/impl/Promise$ManyCallbacks
   #38 = Class              #37           // scala/concurrent/impl/Promise$ManyCallbacks
   #39 = Utf8               ManyCallbacks
   #40 = Utf8               scala/concurrent/impl/Promise$Transformation
   #41 = Class              #40           // scala/concurrent/impl/Promise$Transformation
   #42 = Utf8               Transformation
   #43 = Utf8               apply$mcZD$sp
   #44 = Utf8               (D)Z
   #45 = Utf8               v1
   #46 = Utf8               apply$mcZD$sp$
   #47 = Utf8               (Lscala/Function1;D)Z
   #48 = NameAndType        #46:#47       // apply$mcZD$sp$:(Lscala/Function1;D)Z
   #49 = InterfaceMethodref #11.#48       // scala/Function1.apply$mcZD$sp$:(Lscala/Function1;D)Z
   #50 = Utf8               this
   #51 = Utf8               Lscala/concurrent/impl/Promise$DefaultPromise;
   #52 = Utf8               D
   #53 = Utf8               apply$mcDD$sp
   #54 = Utf8               (D)D
   #55 = Utf8               apply$mcDD$sp$
   #56 = Utf8               (Lscala/Function1;D)D
   #57 = NameAndType        #55:#56       // apply$mcDD$sp$:(Lscala/Function1;D)D
   #58 = InterfaceMethodref #11.#57       // scala/Function1.apply$mcDD$sp$:(Lscala/Function1;D)D
   #59 = Utf8               apply$mcFD$sp
   #60 = Utf8               (D)F
   #61 = Utf8               apply$mcFD$sp$
   #62 = Utf8               (Lscala/Function1;D)F
   #63 = NameAndType        #61:#62       // apply$mcFD$sp$:(Lscala/Function1;D)F
   #64 = InterfaceMethodref #11.#63       // scala/Function1.apply$mcFD$sp$:(Lscala/Function1;D)F
   #65 = Utf8               apply$mcID$sp
   #66 = Utf8               (D)I
   #67 = Utf8               apply$mcID$sp$
   #68 = Utf8               (Lscala/Function1;D)I
   #69 = NameAndType        #67:#68       // apply$mcID$sp$:(Lscala/Function1;D)I
   #70 = InterfaceMethodref #11.#69       // scala/Function1.apply$mcID$sp$:(Lscala/Function1;D)I
   #71 = Utf8               apply$mcJD$sp
   #72 = Utf8               (D)J
   #73 = Utf8               apply$mcJD$sp$
   #74 = Utf8               (Lscala/Function1;D)J
   #75 = NameAndType        #73:#74       // apply$mcJD$sp$:(Lscala/Function1;D)J
   #76 = InterfaceMethodref #11.#75       // scala/Function1.apply$mcJD$sp$:(Lscala/Function1;D)J
   #77 = Utf8               apply$mcVD$sp
   #78 = Utf8               (D)V
   #79 = Utf8               apply$mcVD$sp$
   #80 = Utf8               (Lscala/Function1;D)V
   #81 = NameAndType        #79:#80       // apply$mcVD$sp$:(Lscala/Function1;D)V
   #82 = InterfaceMethodref #11.#81       // scala/Function1.apply$mcVD$sp$:(Lscala/Function1;D)V
   #83 = Utf8               apply$mcZF$sp
   #84 = Utf8               (F)Z
   #85 = Utf8               apply$mcZF$sp$
   #86 = Utf8               (Lscala/Function1;F)Z
   #87 = NameAndType        #85:#86       // apply$mcZF$sp$:(Lscala/Function1;F)Z
   #88 = InterfaceMethodref #11.#87       // scala/Function1.apply$mcZF$sp$:(Lscala/Function1;F)Z
   #89 = Utf8               F
   #90 = Utf8               apply$mcDF$sp
   #91 = Utf8               (F)D
   #92 = Utf8               apply$mcDF$sp$
   #93 = Utf8               (Lscala/Function1;F)D
   #94 = NameAndType        #92:#93       // apply$mcDF$sp$:(Lscala/Function1;F)D
   #95 = InterfaceMethodref #11.#94       // scala/Function1.apply$mcDF$sp$:(Lscala/Function1;F)D
   #96 = Utf8               apply$mcFF$sp
   #97 = Utf8               (F)F
   #98 = Utf8               apply$mcFF$sp$
   #99 = Utf8               (Lscala/Function1;F)F
  #100 = NameAndType        #98:#99       // apply$mcFF$sp$:(Lscala/Function1;F)F
  #101 = InterfaceMethodref #11.#100      // scala/Function1.apply$mcFF$sp$:(Lscala/Function1;F)F
  #102 = Utf8               apply$mcIF$sp
  #103 = Utf8               (F)I
  #104 = Utf8               apply$mcIF$sp$
  #105 = Utf8               (Lscala/Function1;F)I
  #106 = NameAndType        #104:#105     // apply$mcIF$sp$:(Lscala/Function1;F)I
  #107 = InterfaceMethodref #11.#106      // scala/Function1.apply$mcIF$sp$:(Lscala/Function1;F)I
  #108 = Utf8               apply$mcJF$sp
  #109 = Utf8               (F)J
  #110 = Utf8               apply$mcJF$sp$
  #111 = Utf8               (Lscala/Function1;F)J
  #112 = NameAndType        #110:#111     // apply$mcJF$sp$:(Lscala/Function1;F)J
  #113 = InterfaceMethodref #11.#112      // scala/Function1.apply$mcJF$sp$:(Lscala/Function1;F)J
  #114 = Utf8               apply$mcVF$sp
  #115 = Utf8               (F)V
  #116 = Utf8               apply$mcVF$sp$
  #117 = Utf8               (Lscala/Function1;F)V
  #118 = NameAndType        #116:#117     // apply$mcVF$sp$:(Lscala/Function1;F)V
  #119 = InterfaceMethodref #11.#118      // scala/Function1.apply$mcVF$sp$:(Lscala/Function1;F)V
  #120 = Utf8               apply$mcZI$sp
  #121 = Utf8               (I)Z
  #122 = Utf8               apply$mcZI$sp$
  #123 = Utf8               (Lscala/Function1;I)Z
  #124 = NameAndType        #122:#123     // apply$mcZI$sp$:(Lscala/Function1;I)Z
  #125 = InterfaceMethodref #11.#124      // scala/Function1.apply$mcZI$sp$:(Lscala/Function1;I)Z
  #126 = Utf8               I
  #127 = Utf8               apply$mcDI$sp
  #128 = Utf8               (I)D
  #129 = Utf8               apply$mcDI$sp$
  #130 = Utf8               (Lscala/Function1;I)D
  #131 = NameAndType        #129:#130     // apply$mcDI$sp$:(Lscala/Function1;I)D
  #132 = InterfaceMethodref #11.#131      // scala/Function1.apply$mcDI$sp$:(Lscala/Function1;I)D
  #133 = Utf8               apply$mcFI$sp
  #134 = Utf8               (I)F
  #135 = Utf8               apply$mcFI$sp$
  #136 = Utf8               (Lscala/Function1;I)F
  #137 = NameAndType        #135:#136     // apply$mcFI$sp$:(Lscala/Function1;I)F
  #138 = InterfaceMethodref #11.#137      // scala/Function1.apply$mcFI$sp$:(Lscala/Function1;I)F
  #139 = Utf8               apply$mcII$sp
  #140 = Utf8               (I)I
  #141 = Utf8               apply$mcII$sp$
  #142 = Utf8               (Lscala/Function1;I)I
  #143 = NameAndType        #141:#142     // apply$mcII$sp$:(Lscala/Function1;I)I
  #144 = InterfaceMethodref #11.#143      // scala/Function1.apply$mcII$sp$:(Lscala/Function1;I)I
  #145 = Utf8               apply$mcJI$sp
  #146 = Utf8               (I)J
  #147 = Utf8               apply$mcJI$sp$
  #148 = Utf8               (Lscala/Function1;I)J
  #149 = NameAndType        #147:#148     // apply$mcJI$sp$:(Lscala/Function1;I)J
  #150 = InterfaceMethodref #11.#149      // scala/Function1.apply$mcJI$sp$:(Lscala/Function1;I)J
  #151 = Utf8               apply$mcVI$sp
  #152 = Utf8               (I)V
  #153 = Utf8               apply$mcVI$sp$
  #154 = Utf8               (Lscala/Function1;I)V
  #155 = NameAndType        #153:#154     // apply$mcVI$sp$:(Lscala/Function1;I)V
  #156 = InterfaceMethodref #11.#155      // scala/Function1.apply$mcVI$sp$:(Lscala/Function1;I)V
  #157 = Utf8               apply$mcZJ$sp
  #158 = Utf8               (J)Z
  #159 = Utf8               apply$mcZJ$sp$
  #160 = Utf8               (Lscala/Function1;J)Z
  #161 = NameAndType        #159:#160     // apply$mcZJ$sp$:(Lscala/Function1;J)Z
  #162 = InterfaceMethodref #11.#161      // scala/Function1.apply$mcZJ$sp$:(Lscala/Function1;J)Z
  #163 = Utf8               J
  #164 = Utf8               apply$mcDJ$sp
  #165 = Utf8               (J)D
  #166 = Utf8               apply$mcDJ$sp$
  #167 = Utf8               (Lscala/Function1;J)D
  #168 = NameAndType        #166:#167     // apply$mcDJ$sp$:(Lscala/Function1;J)D
  #169 = InterfaceMethodref #11.#168      // scala/Function1.apply$mcDJ$sp$:(Lscala/Function1;J)D
  #170 = Utf8               apply$mcFJ$sp
  #171 = Utf8               (J)F
  #172 = Utf8               apply$mcFJ$sp$
  #173 = Utf8               (Lscala/Function1;J)F
  #174 = NameAndType        #172:#173     // apply$mcFJ$sp$:(Lscala/Function1;J)F
  #175 = InterfaceMethodref #11.#174      // scala/Function1.apply$mcFJ$sp$:(Lscala/Function1;J)F
  #176 = Utf8               apply$mcIJ$sp
  #177 = Utf8               (J)I
  #178 = Utf8               apply$mcIJ$sp$
  #179 = Utf8               (Lscala/Function1;J)I
  #180 = NameAndType        #178:#179     // apply$mcIJ$sp$:(Lscala/Function1;J)I
  #181 = InterfaceMethodref #11.#180      // scala/Function1.apply$mcIJ$sp$:(Lscala/Function1;J)I
  #182 = Utf8               apply$mcJJ$sp
  #183 = Utf8               (J)J
  #184 = Utf8               apply$mcJJ$sp$
  #185 = Utf8               (Lscala/Function1;J)J
  #186 = NameAndType        #184:#185     // apply$mcJJ$sp$:(Lscala/Function1;J)J
  #187 = InterfaceMethodref #11.#186      // scala/Function1.apply$mcJJ$sp$:(Lscala/Function1;J)J
  #188 = Utf8               apply$mcVJ$sp
  #189 = Utf8               (J)V
  #190 = Utf8               apply$mcVJ$sp$
  #191 = Utf8               (Lscala/Function1;J)V
  #192 = NameAndType        #190:#191     // apply$mcVJ$sp$:(Lscala/Function1;J)V
  #193 = InterfaceMethodref #11.#192      // scala/Function1.apply$mcVJ$sp$:(Lscala/Function1;J)V
  #194 = Utf8               compose
  #195 = Utf8               (Lscala/Function1;)Lscala/Function1;
  #196 = Utf8               <A$:Ljava/lang/Object;>(Lscala/Function1<TA$;Lscala/util/Try<TT;>;>;)Lscala/Function1<TA$;Lscala/runtime/BoxedUnit;>;
  #197 = Utf8               g
  #198 = Utf8               compose$
  #199 = Utf8               (Lscala/Function1;Lscala/Function1;)Lscala/Function1;
  #200 = NameAndType        #198:#199     // compose$:(Lscala/Function1;Lscala/Function1;)Lscala/Function1;
  #201 = InterfaceMethodref #11.#200      // scala/Function1.compose$:(Lscala/Function1;Lscala/Function1;)Lscala/Function1;
  #202 = Utf8               Lscala/Function1;
  #203 = Utf8               andThen
  #204 = Utf8               <A$:Ljava/lang/Object;>(Lscala/Function1<Lscala/runtime/BoxedUnit;TA$;>;)Lscala/Function1<Lscala/util/Try<TT;>;TA$;>;
  #205 = Utf8               andThen$
  #206 = NameAndType        #205:#199     // andThen$:(Lscala/Function1;Lscala/Function1;)Lscala/Function1;
  #207 = InterfaceMethodref #11.#206      // scala/Function1.andThen$:(Lscala/Function1;Lscala/Function1;)Lscala/Function1;
  #208 = Utf8               transform
  #209 = Utf8               (Lscala/Function1;Lscala/Function1;Lscala/concurrent/ExecutionContext;)Lscala/concurrent/Future;
  #210 = Utf8               <S:Ljava/lang/Object;>(Lscala/Function1<TT;TS;>;Lscala/Function1<Ljava/lang/Throwable;Ljava/lang/Throwable;>;Lscala/concurrent/ExecutionContext;)Lscala/concurrent/Future<TS;>;
  #211 = Utf8               s
  #212 = Utf8               f
  #213 = Utf8               executor
  #214 = Utf8               transform$
  #215 = Utf8               (Lscala/concurrent/Future;Lscala/Function1;Lscala/Function1;Lscala/concurrent/ExecutionContext;)Lscala/concurrent/Future;
  #216 = NameAndType        #214:#215     // transform$:(Lscala/concurrent/Future;Lscala/Function1;Lscala/Function1;Lscala/concurrent/ExecutionContext;)Lscala/concurrent/Future;
  #217 = InterfaceMethodref #9.#216       // scala/concurrent/Future.transform$:(Lscala/concurrent/Future;Lscala/Function1;Lscala/Function1;Lscala/concurrent/ExecutionContext;)Lscala/concurrent/Future;
  #218 = Utf8               Lscala/concurrent/ExecutionContext;
  #219 = Utf8               flatten
  #220 = Utf8               (Lscala/$less$colon$less;)Lscala/concurrent/Future;
  #221 = Utf8               <S:Ljava/lang/Object;>(Lscala/$less$colon$less<TT;Lscala/concurrent/Future<TS;>;>;)Lscala/concurrent/Future<TS;>;
  #222 = Utf8               ev
  #223 = Utf8               flatten$
  #224 = Utf8               (Lscala/concurrent/Future;Lscala/$less$colon$less;)Lscala/concurrent/Future;
  #225 = NameAndType        #223:#224     // flatten$:(Lscala/concurrent/Future;Lscala/$less$colon$less;)Lscala/concurrent/Future;
  #226 = InterfaceMethodref #9.#225       // scala/concurrent/Future.flatten$:(Lscala/concurrent/Future;Lscala/$less$colon$less;)Lscala/concurrent/Future;
  #227 = Utf8               Lscala/$less$colon$less;
  #228 = Utf8               withFilter
  #229 = Utf8               (Lscala/Function1;Lscala/concurrent/ExecutionContext;)Lscala/concurrent/Future;
  #230 = Utf8               (Lscala/Function1<TT;Ljava/lang/Object;>;Lscala/concurrent/ExecutionContext;)Lscala/concurrent/Future<TT;>;
  #231 = Utf8               p
  #232 = Utf8               withFilter$
  #233 = Utf8               (Lscala/concurrent/Future;Lscala/Function1;Lscala/concurrent/ExecutionContext;)Lscala/concurrent/Future;
  #234 = NameAndType        #232:#233     // withFilter$:(Lscala/concurrent/Future;Lscala/Function1;Lscala/concurrent/ExecutionContext;)Lscala/concurrent/Future;
  #235 = InterfaceMethodref #9.#234       // scala/concurrent/Future.withFilter$:(Lscala/concurrent/Future;Lscala/Function1;Lscala/concurrent/ExecutionContext;)Lscala/concurrent/Future;
  #236 = Utf8               zip
  #237 = Utf8               (Lscala/concurrent/Future;)Lscala/concurrent/Future;
  #238 = Utf8               <U:Ljava/lang/Object;>(Lscala/concurrent/Future<TU;>;)Lscala/concurrent/Future<Lscala/Tuple2<TT;TU;>;>;
  #239 = Utf8               that
  #240 = Utf8               zip$
  #241 = Utf8               (Lscala/concurrent/Future;Lscala/concurrent/Future;)Lscala/concurrent/Future;
  #242 = NameAndType        #240:#241     // zip$:(Lscala/concurrent/Future;Lscala/concurrent/Future;)Lscala/concurrent/Future;
  #243 = InterfaceMethodref #9.#242       // scala/concurrent/Future.zip$:(Lscala/concurrent/Future;Lscala/concurrent/Future;)Lscala/concurrent/Future;
  #244 = Utf8               Lscala/concurrent/Future;
  #245 = Utf8               fallbackTo
  #246 = Utf8               <U:Ljava/lang/Object;>(Lscala/concurrent/Future<TU;>;)Lscala/concurrent/Future<TU;>;
  #247 = Utf8               fallbackTo$
  #248 = NameAndType        #247:#241     // fallbackTo$:(Lscala/concurrent/Future;Lscala/concurrent/Future;)Lscala/concurrent/Future;
  #249 = InterfaceMethodref #9.#248       // scala/concurrent/Future.fallbackTo$:(Lscala/concurrent/Future;Lscala/concurrent/Future;)Lscala/concurrent/Future;
  #250 = Utf8               (Lscala/PartialFunction;Lscala/concurrent/ExecutionContext;)Lscala/concurrent/Future;
  #251 = Utf8               <U:Ljava/lang/Object;>(Lscala/PartialFunction<Lscala/util/Try<TT;>;TU;>;Lscala/concurrent/ExecutionContext;)Lscala/concurrent/Future<TT;>;
  #252 = Utf8               pf
  #253 = Utf8               (Lscala/concurrent/Future;Lscala/PartialFunction;Lscala/concurrent/ExecutionContext;)Lscala/concurrent/Future;
  #254 = NameAndType        #205:#253     // andThen$:(Lscala/concurrent/Future;Lscala/PartialFunction;Lscala/concurrent/ExecutionContext;)Lscala/concurrent/Future;
  #255 = InterfaceMethodref #9.#254       // scala/concurrent/Future.andThen$:(Lscala/concurrent/Future;Lscala/PartialFunction;Lscala/concurrent/ExecutionContext;)Lscala/concurrent/Future;
  #256 = Utf8               Lscala/PartialFunction;
  #257 = Utf8               complete
  #258 = Utf8               (Lscala/util/Try;)Lscala/concurrent/Promise;
  #259 = Utf8               (Lscala/util/Try<TT;>;)Lscala/concurrent/Promise<TT;>;
  #260 = Utf8               result
  #261 = Utf8               complete$
  #262 = Utf8               (Lscala/concurrent/Promise;Lscala/util/Try;)Lscala/concurrent/Promise;
  #263 = NameAndType        #261:#262     // complete$:(Lscala/concurrent/Promise;Lscala/util/Try;)Lscala/concurrent/Promise;
  #264 = InterfaceMethodref #7.#263       // scala/concurrent/Promise.complete$:(Lscala/concurrent/Promise;Lscala/util/Try;)Lscala/concurrent/Promise;
  #265 = Utf8               Lscala/util/Try;
  #266 = Utf8               tryCompleteWith
  #267 = Utf8               (Lscala/concurrent/Future;)Lscala/concurrent/Promise;
  #268 = Utf8               (Lscala/concurrent/Future<TT;>;)Lscala/concurrent/Promise<TT;>;
  #269 = Utf8               other
  #270 = Utf8               tryCompleteWith$
  #271 = Utf8               (Lscala/concurrent/Promise;Lscala/concurrent/Future;)Lscala/concurrent/Promise;
  #272 = NameAndType        #270:#271     // tryCompleteWith$:(Lscala/concurrent/Promise;Lscala/concurrent/Future;)Lscala/concurrent/Promise;
  #273 = InterfaceMethodref #7.#272       // scala/concurrent/Promise.tryCompleteWith$:(Lscala/concurrent/Promise;Lscala/concurrent/Future;)Lscala/concurrent/Promise;
  #274 = Utf8               success
  #275 = Utf8               (Ljava/lang/Object;)Lscala/concurrent/Promise;
  #276 = Utf8               (TT;)Lscala/concurrent/Promise<TT;>;
  #277 = Utf8               value
  #278 = Utf8               success$
  #279 = Utf8               (Lscala/concurrent/Promise;Ljava/lang/Object;)Lscala/concurrent/Promise;
  #280 = NameAndType        #278:#279     // success$:(Lscala/concurrent/Promise;Ljava/lang/Object;)Lscala/concurrent/Promise;
  #281 = InterfaceMethodref #7.#280       // scala/concurrent/Promise.success$:(Lscala/concurrent/Promise;Ljava/lang/Object;)Lscala/concurrent/Promise;
  #282 = Utf8               Ljava/lang/Object;
  #283 = Utf8               trySuccess
  #284 = Utf8               (Ljava/lang/Object;)Z
  #285 = Utf8               (TT;)Z
  #286 = Utf8               trySuccess$
  #287 = Utf8               (Lscala/concurrent/Promise;Ljava/lang/Object;)Z
  #288 = NameAndType        #286:#287     // trySuccess$:(Lscala/concurrent/Promise;Ljava/lang/Object;)Z
  #289 = InterfaceMethodref #7.#288       // scala/concurrent/Promise.trySuccess$:(Lscala/concurrent/Promise;Ljava/lang/Object;)Z
  #290 = Utf8               failure
  #291 = Utf8               (Ljava/lang/Throwable;)Lscala/concurrent/Promise;
  #292 = Utf8               (Ljava/lang/Throwable;)Lscala/concurrent/Promise<TT;>;
  #293 = Utf8               cause
  #294 = Utf8               failure$
  #295 = Utf8               (Lscala/concurrent/Promise;Ljava/lang/Throwable;)Lscala/concurrent/Promise;
  #296 = NameAndType        #294:#295     // failure$:(Lscala/concurrent/Promise;Ljava/lang/Throwable;)Lscala/concurrent/Promise;
  #297 = InterfaceMethodref #7.#296       // scala/concurrent/Promise.failure$:(Lscala/concurrent/Promise;Ljava/lang/Throwable;)Lscala/concurrent/Promise;
  #298 = Utf8               Ljava/lang/Throwable;
  #299 = Utf8               tryFailure
  #300 = Utf8               (Ljava/lang/Throwable;)Z
  #301 = Utf8               tryFailure$
  #302 = Utf8               (Lscala/concurrent/Promise;Ljava/lang/Throwable;)Z
  #303 = NameAndType        #301:#302     // tryFailure$:(Lscala/concurrent/Promise;Ljava/lang/Throwable;)Z
  #304 = InterfaceMethodref #7.#303       // scala/concurrent/Promise.tryFailure$:(Lscala/concurrent/Promise;Ljava/lang/Throwable;)Z
  #305 = Utf8               apply
  #306 = Utf8               (Lscala/util/Try;)V
  #307 = Utf8               (Lscala/util/Try<TT;>;)V
  #308 = Utf8               resolved
  #309 = Utf8               get
  #310 = Utf8               ()Ljava/lang/Object;
  #311 = NameAndType        #309:#310     // get:()Ljava/lang/Object;
  #312 = Methodref          #2.#311       // scala/concurrent/impl/Promise$DefaultPromise.get:()Ljava/lang/Object;
  #313 = Utf8               tryComplete0
  #314 = Utf8               (Ljava/lang/Object;Lscala/util/Try;)Z
  #315 = NameAndType        #313:#314     // tryComplete0:(Ljava/lang/Object;Lscala/util/Try;)Z
  #316 = Methodref          #2.#315       // scala/concurrent/impl/Promise$DefaultPromise.tryComplete0:(Ljava/lang/Object;Lscala/util/Try;)Z
  #317 = Utf8               future
  #318 = Utf8               ()Lscala/concurrent/Future;
  #319 = Utf8               ()Lscala/concurrent/Future<TT;>;
  #320 = Utf8               <S:Ljava/lang/Object;>(Lscala/Function1<Lscala/util/Try<TT;>;Lscala/util/Try<TS;>;>;Lscala/concurrent/ExecutionContext;)Lscala/concurrent/Future<TS;>;
  #321 = Utf8               <init>
  #322 = Utf8               (ILscala/Function1;Lscala/concurrent/ExecutionContext;)V
  #323 = NameAndType        #321:#322     // "<init>":(ILscala/Function1;Lscala/concurrent/ExecutionContext;)V
  #324 = Methodref          #41.#323      // scala/concurrent/impl/Promise$Transformation."<init>":(ILscala/Function1;Lscala/concurrent/ExecutionContext;)V
  #325 = Utf8               dispatchOrAddCallbacks
  #326 = Utf8               (Ljava/lang/Object;Lscala/concurrent/impl/Promise$Callbacks;)Lscala/concurrent/impl/Promise$Callbacks;
  #327 = NameAndType        #325:#326     // dispatchOrAddCallbacks:(Ljava/lang/Object;Lscala/concurrent/impl/Promise$Callbacks;)Lscala/concurrent/impl/Promise$Callbacks;
  #328 = Methodref          #2.#327       // scala/concurrent/impl/Promise$DefaultPromise.dispatchOrAddCallbacks:(Ljava/lang/Object;Lscala/concurrent/impl/Promise$Callbacks;)Lscala/concurrent/impl/Promise$Callbacks;
  #329 = Utf8               transformWith
  #330 = Utf8               <S:Ljava/lang/Object;>(Lscala/Function1<Lscala/util/Try<TT;>;Lscala/concurrent/Future<TS;>;>;Lscala/concurrent/ExecutionContext;)Lscala/concurrent/Future<TS;>;
  #331 = Utf8               zipWith
  #332 = Utf8               (Lscala/concurrent/Future;Lscala/Function2;Lscala/concurrent/ExecutionContext;)Lscala/concurrent/Future;
  #333 = Utf8               <U:Ljava/lang/Object;R:Ljava/lang/Object;>(Lscala/concurrent/Future<TU;>;Lscala/Function2<TT;TU;TR;>;Lscala/concurrent/ExecutionContext;)Lscala/concurrent/Future<TR;>;
  #334 = Utf8               scala/util/Try
  #335 = Class              #334          // scala/util/Try
  #336 = Utf8               isFailure
  #337 = Utf8               ()Z
  #338 = NameAndType        #336:#337     // isFailure:()Z
  #339 = Methodref          #335.#338     // scala/util/Try.isFailure:()Z
  #340 = Utf8               scala/util/Success
  #341 = Class              #340          // scala/util/Success
  #342 = NameAndType        #277:#310     // value:()Ljava/lang/Object;
  #343 = Methodref          #341.#342     // scala/util/Success.value:()Ljava/lang/Object;
  #344 = Utf8               (Ljava/lang/Object;)Ljava/lang/Object;
  #345 = MethodType         #344          //  (Ljava/lang/Object;)Ljava/lang/Object;
  #346 = Utf8               $anonfun$zipWith$1
  #347 = Utf8               (Lscala/Function2;Ljava/lang/Object;Ljava/lang/Object;)Ljava/lang/Object;
  #348 = NameAndType        #346:#347     // $anonfun$zipWith$1:(Lscala/Function2;Ljava/lang/Object;Ljava/lang/Object;)Ljava/lang/Object;
  #349 = Methodref          #2.#348       // scala/concurrent/impl/Promise$DefaultPromise.$anonfun$zipWith$1:(Lscala/Function2;Ljava/lang/Object;Ljava/lang/Object;)Ljava/lang/Object;
  #350 = MethodHandle       6:#349        // REF_invokeStatic scala/concurrent/impl/Promise$DefaultPromise.$anonfun$zipWith$1:(Lscala/Function2;Ljava/lang/Object;Ljava/lang/Object;)Ljava/lang/Object;
  #351 = Integer            1
  #352 = Utf8               java/lang/invoke/LambdaMetafactory
  #353 = Class              #352          // java/lang/invoke/LambdaMetafactory
  #354 = Utf8               altMetafactory
  #355 = Utf8               (Ljava/lang/invoke/MethodHandles$Lookup;Ljava/lang/String;Ljava/lang/invoke/MethodType;[Ljava/lang/Object;)Ljava/lang/invoke/CallSite;
  #356 = NameAndType        #354:#355     // altMetafactory:(Ljava/lang/invoke/MethodHandles$Lookup;Ljava/lang/String;Ljava/lang/invoke/MethodType;[Ljava/lang/Object;)Ljava/lang/invoke/CallSite;
  #357 = Methodref          #353.#356     // java/lang/invoke/LambdaMetafactory.altMetafactory:(Ljava/lang/invoke/MethodHandles$Lookup;Ljava/lang/String;Ljava/lang/invoke/MethodType;[Ljava/lang/Object;)Ljava/lang/invoke/CallSite;
  #358 = MethodHandle       6:#357        // REF_invokeStatic java/lang/invoke/LambdaMetafactory.altMetafactory:(Ljava/lang/invoke/MethodHandles$Lookup;Ljava/lang/String;Ljava/lang/invoke/MethodType;[Ljava/lang/Object;)Ljava/lang/invoke/CallSite;
  #359 = Utf8               (Lscala/Function2;Ljava/lang/Object;)Lscala/Function1;
  #360 = NameAndType        #305:#359     // apply:(Lscala/Function2;Ljava/lang/Object;)Lscala/Function1;
  #361 = InvokeDynamic      #0:#360       // #0:apply:(Lscala/Function2;Ljava/lang/Object;)Lscala/Function1;
  #362 = Utf8               map
  #363 = NameAndType        #362:#229     // map:(Lscala/Function1;Lscala/concurrent/ExecutionContext;)Lscala/concurrent/Future;
  #364 = InterfaceMethodref #9.#363       // scala/concurrent/Future.map:(Lscala/Function1;Lscala/concurrent/ExecutionContext;)Lscala/concurrent/Future;
  #365 = Utf8               ()V
  #366 = NameAndType        #321:#365     // "<init>":()V
  #367 = Methodref          #5.#366       // java/util/concurrent/atomic/AtomicReference."<init>":()V
  #368 = Methodref          #2.#366       // scala/concurrent/impl/Promise$DefaultPromise."<init>":()V
  #369 = Utf8               $anonfun$zipWith$2$adapted
  #370 = Utf8               (Ljava/util/concurrent/atomic/AtomicReference;Lscala/concurrent/impl/Promise$DefaultPromise;Lscala/Function2;Lscala/util/Try;)Ljava/lang/Object;
  #371 = NameAndType        #369:#370     // $anonfun$zipWith$2$adapted:(Ljava/util/concurrent/atomic/AtomicReference;Lscala/concurrent/impl/Promise$DefaultPromise;Lscala/Function2;Lscala/util/Try;)Ljava/lang/Object;
  #372 = Methodref          #2.#371       // scala/concurrent/impl/Promise$DefaultPromise.$anonfun$zipWith$2$adapted:(Ljava/util/concurrent/atomic/AtomicReference;Lscala/concurrent/impl/Promise$DefaultPromise;Lscala/Function2;Lscala/util/Try;)Ljava/lang/Object;
  #373 = MethodHandle       6:#372        // REF_invokeStatic scala/concurrent/impl/Promise$DefaultPromise.$anonfun$zipWith$2$adapted:(Ljava/util/concurrent/atomic/AtomicReference;Lscala/concurrent/impl/Promise$DefaultPromise;Lscala/Function2;Lscala/util/Try;)Ljava/lang/Object;
  #374 = Utf8               (Lscala/util/Try;)Ljava/lang/Object;
  #375 = MethodType         #374          //  (Lscala/util/Try;)Ljava/lang/Object;
  #376 = Integer            5
  #377 = Utf8               (Ljava/util/concurrent/atomic/AtomicReference;Lscala/concurrent/impl/Promise$DefaultPromise;Lscala/Function2;)Lscala/Function1;
  #378 = NameAndType        #305:#377     // apply:(Ljava/util/concurrent/atomic/AtomicReference;Lscala/concurrent/impl/Promise$DefaultPromise;Lscala/Function2;)Lscala/Function1;
  #379 = InvokeDynamic      #1:#378       // #1:apply:(Ljava/util/concurrent/atomic/AtomicReference;Lscala/concurrent/impl/Promise$DefaultPromise;Lscala/Function2;)Lscala/Function1;
  #380 = Utf8               $anonfun$zipWith$3$adapted
  #381 = NameAndType        #380:#370     // $anonfun$zipWith$3$adapted:(Ljava/util/concurrent/atomic/AtomicReference;Lscala/concurrent/impl/Promise$DefaultPromise;Lscala/Function2;Lscala/util/Try;)Ljava/lang/Object;
  #382 = Methodref          #2.#381       // scala/concurrent/impl/Promise$DefaultPromise.$anonfun$zipWith$3$adapted:(Ljava/util/concurrent/atomic/AtomicReference;Lscala/concurrent/impl/Promise$DefaultPromise;Lscala/Function2;Lscala/util/Try;)Ljava/lang/Object;
  #383 = MethodHandle       6:#382        // REF_invokeStatic scala/concurrent/impl/Promise$DefaultPromise.$anonfun$zipWith$3$adapted:(Ljava/util/concurrent/atomic/AtomicReference;Lscala/concurrent/impl/Promise$DefaultPromise;Lscala/Function2;Lscala/util/Try;)Ljava/lang/Object;
  #384 = InvokeDynamic      #2:#378       // #2:apply:(Ljava/util/concurrent/atomic/AtomicReference;Lscala/concurrent/impl/Promise$DefaultPromise;Lscala/Function2;)Lscala/Function1;
  #385 = Utf8               onComplete
  #386 = Utf8               (Lscala/Function1;Lscala/concurrent/ExecutionContext;)V
  #387 = NameAndType        #385:#386     // onComplete:(Lscala/Function1;Lscala/concurrent/ExecutionContext;)V
  #388 = InterfaceMethodref #9.#387       // scala/concurrent/Future.onComplete:(Lscala/Function1;Lscala/concurrent/ExecutionContext;)V
  #389 = Utf8               l
  #390 = Utf8               buffer
  #391 = Utf8               Ljava/util/concurrent/atomic/AtomicReference;
  #392 = Utf8               zipped
  #393 = Utf8               thisF
  #394 = Utf8               thatF
  #395 = Utf8               state
  #396 = Utf8               Lscala/Function2;
  #397 = Utf8               get_this
  #398 = Utf8               Lscala/util/Success;
  #399 = Utf8               java/lang/Object
  #400 = Class              #399          // java/lang/Object
  #401 = Utf8               foreach
  #402 = Utf8               <U:Ljava/lang/Object;>(Lscala/Function1<TT;TU;>;Lscala/concurrent/ExecutionContext;)V
  #403 = Utf8               scala/util/Failure
  #404 = Class              #403          // scala/util/Failure
  #405 = Utf8               flatMap
  #406 = Utf8               <S:Ljava/lang/Object;>(Lscala/Function1<TT;Lscala/concurrent/Future<TS;>;>;Lscala/concurrent/ExecutionContext;)Lscala/concurrent/Future<TS;>;
  #407 = Utf8               <S:Ljava/lang/Object;>(Lscala/Function1<TT;TS;>;Lscala/concurrent/ExecutionContext;)Lscala/concurrent/Future<TS;>;
  #408 = Utf8               filter
  #409 = Utf8               collect
  #410 = Utf8               <S:Ljava/lang/Object;>(Lscala/PartialFunction<TT;TS;>;Lscala/concurrent/ExecutionContext;)Lscala/concurrent/Future<TS;>;
  #411 = Utf8               recoverWith
  #412 = Utf8               <U:Ljava/lang/Object;>(Lscala/PartialFunction<Ljava/lang/Throwable;Lscala/concurrent/Future<TU;>;>;Lscala/concurrent/ExecutionContext;)Lscala/concurrent/Future<TU;>;
  #413 = Utf8               recover
  #414 = Utf8               <U:Ljava/lang/Object;>(Lscala/PartialFunction<Ljava/lang/Throwable;TU;>;Lscala/concurrent/ExecutionContext;)Lscala/concurrent/Future<TU;>;
  #415 = Utf8               mapTo
  #416 = Utf8               (Lscala/reflect/ClassTag;)Lscala/concurrent/Future;
  #417 = Utf8               <S:Ljava/lang/Object;>(Lscala/reflect/ClassTag<TS;>;)Lscala/concurrent/Future<TS;>;
  #418 = Utf8               tag
  #419 = Utf8               mapTo$
  #420 = Utf8               (Lscala/concurrent/Future;Lscala/reflect/ClassTag;)Lscala/concurrent/Future;
  #421 = NameAndType        #419:#420     // mapTo$:(Lscala/concurrent/Future;Lscala/reflect/ClassTag;)Lscala/concurrent/Future;
  #422 = InterfaceMethodref #9.#421       // scala/concurrent/Future.mapTo$:(Lscala/concurrent/Future;Lscala/reflect/ClassTag;)Lscala/concurrent/Future;
  #423 = Utf8               Lscala/reflect/ClassTag;
  #424 = Utf8               <U:Ljava/lang/Object;>(Lscala/Function1<Lscala/util/Try<TT;>;TU;>;Lscala/concurrent/ExecutionContext;)V
  #425 = Utf8               func
  #426 = Utf8               failed
  #427 = Utf8               ()Lscala/concurrent/Future<Ljava/lang/Throwable;>;
  #428 = Utf8               failed$
  #429 = NameAndType        #428:#237     // failed$:(Lscala/concurrent/Future;)Lscala/concurrent/Future;
  #430 = InterfaceMethodref #9.#429       // scala/concurrent/Future.failed$:(Lscala/concurrent/Future;)Lscala/concurrent/Future;
  #431 = Utf8               scala/concurrent/Future$
  #432 = Class              #431          // scala/concurrent/Future$
  #433 = Utf8               MODULE$
  #434 = Utf8               Lscala/concurrent/Future$;
  #435 = NameAndType        #433:#434     // MODULE$:Lscala/concurrent/Future$;
  #436 = Fieldref           #432.#435     // scala/concurrent/Future$.MODULE$:Lscala/concurrent/Future$;
  #437 = Utf8               failedFailureFuture
  #438 = NameAndType        #437:#318     // failedFailureFuture:()Lscala/concurrent/Future;
  #439 = Methodref          #432.#438     // scala/concurrent/Future$.failedFailureFuture:()Lscala/concurrent/Future;
  #440 = Utf8               toString
  #441 = Utf8               ()Ljava/lang/String;
  #442 = Utf8               java/lang/StringBuilder
  #443 = Class              #442          // java/lang/StringBuilder
  #444 = Integer            8
  #445 = NameAndType        #321:#152     // "<init>":(I)V
  #446 = Methodref          #443.#445     // java/lang/StringBuilder."<init>":(I)V
  #447 = Utf8               Future(
  #448 = String             #447          // Future(
  #449 = Utf8               append
  #450 = Utf8               (Ljava/lang/String;)Ljava/lang/StringBuilder;
  #451 = NameAndType        #449:#450     // append:(Ljava/lang/String;)Ljava/lang/StringBuilder;
  #452 = Methodref          #443.#451     // java/lang/StringBuilder.append:(Ljava/lang/String;)Ljava/lang/StringBuilder;
  #453 = Utf8               (Ljava/lang/Object;)Ljava/lang/StringBuilder;
  #454 = NameAndType        #449:#453     // append:(Ljava/lang/Object;)Ljava/lang/StringBuilder;
  #455 = Methodref          #443.#454     // java/lang/StringBuilder.append:(Ljava/lang/Object;)Ljava/lang/StringBuilder;
  #456 = Utf8               )
  #457 = String             #456          // )
  #458 = NameAndType        #440:#441     // toString:()Ljava/lang/String;
  #459 = Methodref          #443.#458     // java/lang/StringBuilder.toString:()Ljava/lang/String;
  #460 = Utf8               promise
  #461 = Utf8               (Lscala/concurrent/impl/Promise$DefaultPromise;)Lscala/concurrent/impl/Promise$DefaultPromise;
  #462 = NameAndType        #460:#461     // promise:(Lscala/concurrent/impl/Promise$DefaultPromise;)Lscala/concurrent/impl/Promise$DefaultPromise;
  #463 = Methodref          #35.#462      // scala/concurrent/impl/Promise$Link.promise:(Lscala/concurrent/impl/Promise$DefaultPromise;)Lscala/concurrent/impl/Promise$DefaultPromise;
  #464 = Utf8               Future(<not completed>)
  #465 = String             #464          // Future(<not completed>)
  #466 = Utf8               tryAwait0
  #467 = Utf8               (Lscala/concurrent/duration/Duration;)Lscala/util/Try;
  #468 = Utf8               (Lscala/concurrent/duration/Duration;)Lscala/util/Try<TT;>;
  #469 = Utf8               atMost
  #470 = Utf8               scala/concurrent/duration/Duration$
  #471 = Class              #470          // scala/concurrent/duration/Duration$
  #472 = Utf8               Lscala/concurrent/duration/Duration$;
  #473 = NameAndType        #433:#472     // MODULE$:Lscala/concurrent/duration/Duration$;
  #474 = Fieldref           #471.#473     // scala/concurrent/duration/Duration$.MODULE$:Lscala/concurrent/duration/Duration$;
  #475 = Utf8               Undefined
  #476 = Utf8               ()Lscala/concurrent/duration/Duration$Infinite;
  #477 = NameAndType        #475:#476     // Undefined:()Lscala/concurrent/duration/Duration$Infinite;
  #478 = Methodref          #471.#477     // scala/concurrent/duration/Duration$.Undefined:()Lscala/concurrent/duration/Duration$Infinite;
  #479 = Utf8               value0
  #480 = Utf8               ()Lscala/util/Try;
  #481 = NameAndType        #479:#480     // value0:()Lscala/util/Try;
  #482 = Methodref          #2.#481       // scala/concurrent/impl/Promise$DefaultPromise.value0:()Lscala/util/Try;
  #483 = Utf8               Zero
  #484 = Utf8               ()Lscala/concurrent/duration/FiniteDuration;
  #485 = NameAndType        #483:#484     // Zero:()Lscala/concurrent/duration/FiniteDuration;
  #486 = Methodref          #471.#485     // scala/concurrent/duration/Duration$.Zero:()Lscala/concurrent/duration/FiniteDuration;
  #487 = Utf8               $less$eq
  #488 = NameAndType        #487:#284     // $less$eq:(Ljava/lang/Object;)Z
  #489 = Methodref          #26.#488      // scala/concurrent/duration/Duration.$less$eq:(Ljava/lang/Object;)Z
  #490 = Utf8               scala/concurrent/impl/CompletionLatch
  #491 = Class              #490          // scala/concurrent/impl/CompletionLatch
  #492 = Methodref          #491.#366     // scala/concurrent/impl/CompletionLatch."<init>":()V
  #493 = Utf8               Lscala/concurrent/ExecutionContext$parasitic$;
  #494 = NameAndType        #433:#493     // MODULE$:Lscala/concurrent/ExecutionContext$parasitic$;
  #495 = Fieldref           #19.#494      // scala/concurrent/ExecutionContext$parasitic$.MODULE$:Lscala/concurrent/ExecutionContext$parasitic$;
  #496 = Methodref          #2.#387       // scala/concurrent/impl/Promise$DefaultPromise.onComplete:(Lscala/Function1;Lscala/concurrent/ExecutionContext;)V
  #497 = Utf8               isFinite
  #498 = NameAndType        #497:#337     // isFinite:()Z
  #499 = Methodref          #26.#498      // scala/concurrent/duration/Duration.isFinite:()Z
  #500 = Utf8               toNanos
  #501 = Utf8               ()J
  #502 = NameAndType        #500:#501     // toNanos:()J
  #503 = Methodref          #26.#502      // scala/concurrent/duration/Duration.toNanos:()J
  #504 = Utf8               tryAcquireSharedNanos
  #505 = Utf8               (IJ)Z
  #506 = NameAndType        #504:#505     // tryAcquireSharedNanos:(IJ)Z
  #507 = Methodref          #491.#506     // scala/concurrent/impl/CompletionLatch.tryAcquireSharedNanos:(IJ)Z
  #508 = Utf8               acquireSharedInterruptibly
  #509 = NameAndType        #508:#152     // acquireSharedInterruptibly:(I)V
  #510 = Methodref          #491.#509     // scala/concurrent/impl/CompletionLatch.acquireSharedInterruptibly:(I)V
  #511 = NameAndType        #260:#480     // result:()Lscala/util/Try;
  #512 = Methodref          #491.#511     // scala/concurrent/impl/CompletionLatch.result:()Lscala/util/Try;
  #513 = Utf8               java/util/concurrent/TimeoutException
  #514 = Class              #513          // java/util/concurrent/TimeoutException
  #515 = Integer            25
  #516 = Utf8               Future timed out after [
  #517 = String             #516          // Future timed out after [
  #518 = Utf8               ]
  #519 = String             #518          // ]
  #520 = Utf8               (Ljava/lang/String;)V
  #521 = NameAndType        #321:#520     // "<init>":(Ljava/lang/String;)V
  #522 = Methodref          #514.#521     // java/util/concurrent/TimeoutException."<init>":(Ljava/lang/String;)V
  #523 = Utf8               java/lang/IllegalArgumentException
  #524 = Class              #523          // java/lang/IllegalArgumentException
  #525 = Utf8               Cannot wait for Undefined duration of time
  #526 = String             #525          // Cannot wait for Undefined duration of time
  #527 = Methodref          #524.#521     // java/lang/IllegalArgumentException."<init>":(Ljava/lang/String;)V
  #528 = Utf8               Lscala/concurrent/impl/CompletionLatch;
  #529 = Utf8               r
  #530 = Utf8               v
  #531 = Utf8               Lscala/concurrent/duration/Duration;
  #532 = Utf8               ready
  #533 = Utf8               (Lscala/concurrent/duration/Duration;Lscala/concurrent/CanAwait;)Lscala/concurrent/impl/Promise$DefaultPromise;
  #534 = Utf8               (Lscala/concurrent/duration/Duration;Lscala/concurrent/CanAwait;)Lscala/concurrent/impl/Promise$DefaultPromise<TT;>;^Ljava/util/concurrent/TimeoutException;^Ljava/lang/InterruptedException;
  #535 = Utf8               java/lang/InterruptedException
  #536 = Class              #535          // java/lang/InterruptedException
  #537 = Utf8               permit
  #538 = NameAndType        #466:#467     // tryAwait0:(Lscala/concurrent/duration/Duration;)Lscala/util/Try;
  #539 = Methodref          #2.#538       // scala/concurrent/impl/Promise$DefaultPromise.tryAwait0:(Lscala/concurrent/duration/Duration;)Lscala/util/Try;
  #540 = Utf8               Lscala/concurrent/CanAwait;
  #541 = Utf8               (Lscala/concurrent/duration/Duration;Lscala/concurrent/CanAwait;)Ljava/lang/Object;
  #542 = Utf8               (Lscala/concurrent/duration/Duration;Lscala/concurrent/CanAwait;)TT;^Ljava/lang/Exception;
  #543 = Utf8               java/lang/Exception
  #544 = Class              #543          // java/lang/Exception
  #545 = Methodref          #335.#311     // scala/util/Try.get:()Ljava/lang/Object;
  #546 = Utf8               isCompleted
  #547 = Utf8               ()Lscala/Option;
  #548 = Utf8               ()Lscala/Option<Lscala/util/Try<TT;>;>;
  #549 = Utf8               scala/Option$
  #550 = Class              #549          // scala/Option$
  #551 = Utf8               Lscala/Option$;
  #552 = NameAndType        #433:#551     // MODULE$:Lscala/Option$;
  #553 = Fieldref           #550.#552     // scala/Option$.MODULE$:Lscala/Option$;
  #554 = Utf8               (Ljava/lang/Object;)Lscala/Option;
  #555 = NameAndType        #305:#554     // apply:(Ljava/lang/Object;)Lscala/Option;
  #556 = Methodref          #550.#555     // scala/Option$.apply:(Ljava/lang/Object;)Lscala/Option;
  #557 = Utf8               ()Lscala/util/Try<TT;>;
  #558 = Utf8               tryComplete
  #559 = Utf8               (Lscala/util/Try;)Z
  #560 = Utf8               (Lscala/util/Try<TT;>;)Z
  #561 = Utf8               scala/concurrent/impl/Promise$
  #562 = Class              #561          // scala/concurrent/impl/Promise$
  #563 = Utf8               Lscala/concurrent/impl/Promise$;
  #564 = NameAndType        #433:#563     // MODULE$:Lscala/concurrent/impl/Promise$;
  #565 = Fieldref           #562.#564     // scala/concurrent/impl/Promise$.MODULE$:Lscala/concurrent/impl/Promise$;
  #566 = Utf8               scala$concurrent$impl$Promise$$resolve
  #567 = Utf8               (Lscala/util/Try;)Lscala/util/Try;
  #568 = NameAndType        #566:#567     // scala$concurrent$impl$Promise$$resolve:(Lscala/util/Try;)Lscala/util/Try;
  #569 = Methodref          #562.#568     // scala/concurrent/impl/Promise$.scala$concurrent$impl$Promise$$resolve:(Lscala/util/Try;)Lscala/util/Try;
  #570 = Utf8               (Ljava/lang/Object;Lscala/util/Try<TT;>;)Z
  #571 = Utf8               compareAndSet
  #572 = Utf8               (Ljava/lang/Object;Ljava/lang/Object;)Z
  #573 = NameAndType        #571:#572     // compareAndSet:(Ljava/lang/Object;Ljava/lang/Object;)Z
  #574 = Methodref          #2.#573       // scala/concurrent/impl/Promise$DefaultPromise.compareAndSet:(Ljava/lang/Object;Ljava/lang/Object;)Z
  #575 = Utf8               scala$concurrent$impl$Promise$$Noop
  #576 = Utf8               Lscala/concurrent/impl/Promise$Transformation;
  #577 = NameAndType        #575:#576     // scala$concurrent$impl$Promise$$Noop:Lscala/concurrent/impl/Promise$Transformation;
  #578 = Fieldref           #562.#577     // scala/concurrent/impl/Promise$.scala$concurrent$impl$Promise$$Noop:Lscala/concurrent/impl/Promise$Transformation;
  #579 = Utf8               submitWithValue
  #580 = Utf8               (Lscala/concurrent/impl/Promise$Callbacks;Lscala/util/Try;)V
  #581 = NameAndType        #579:#580     // submitWithValue:(Lscala/concurrent/impl/Promise$Callbacks;Lscala/util/Try;)V
  #582 = Methodref          #2.#581       // scala/concurrent/impl/Promise$DefaultPromise.submitWithValue:(Lscala/concurrent/impl/Promise$Callbacks;Lscala/util/Try;)V
  #583 = Utf8               completeWith
  #584 = Utf8               (Lscala/concurrent/Future;)Lscala/concurrent/impl/Promise$DefaultPromise;
  #585 = Utf8               (Lscala/concurrent/Future<TT;>;)Lscala/concurrent/impl/Promise$DefaultPromise<TT;>;
  #586 = NameAndType        #277:#547     // value:()Lscala/Option;
  #587 = InterfaceMethodref #9.#586       // scala/concurrent/Future.value:()Lscala/Option;
  #588 = Utf8               scala/$less$colon$less$
  #589 = Class              #588          // scala/$less$colon$less$
  #590 = Utf8               Lscala/$less$colon$less$;
  #591 = NameAndType        #433:#590     // MODULE$:Lscala/$less$colon$less$;
  #592 = Fieldref           #589.#591     // scala/$less$colon$less$.MODULE$:Lscala/$less$colon$less$;
  #593 = Utf8               refl
  #594 = Utf8               ()Lscala/$eq$colon$eq;
  #595 = NameAndType        #593:#594     // refl:()Lscala/$eq$colon$eq;
  #596 = Methodref          #589.#595     // scala/$less$colon$less$.refl:()Lscala/$eq$colon$eq;
  #597 = Utf8               scala/Option
  #598 = Class              #597          // scala/Option
  #599 = Utf8               isEmpty
  #600 = NameAndType        #599:#337     // isEmpty:()Z
  #601 = Methodref          #598.#600     // scala/Option.isEmpty:()Z
  #602 = Utf8               scala/$less$colon$less
  #603 = Class              #602          // scala/$less$colon$less
  #604 = NameAndType        #305:#344     // apply:(Ljava/lang/Object;)Ljava/lang/Object;
  #605 = Methodref          #603.#604     // scala/$less$colon$less.apply:(Ljava/lang/Object;)Ljava/lang/Object;
  #606 = Methodref          #598.#311     // scala/Option.get:()Ljava/lang/Object;
  #607 = Utf8               orNull_this
  #608 = Utf8               Lscala/Option;
  #609 = Utf8               orNull_ev
  #610 = Utf8               scala/$eq$colon$eq
  #611 = Class              #610          // scala/$eq$colon$eq
  #612 = Utf8               <C::Lscala/concurrent/impl/Promise$Callbacks<TT;>;>(Ljava/lang/Object;TC;)TC;
  #613 = Utf8               callbacks
  #614 = Utf8               concatCallbacks
  #615 = Utf8               (Lscala/concurrent/impl/Promise$Callbacks;Lscala/concurrent/impl/Promise$Callbacks;)Lscala/concurrent/impl/Promise$Callbacks;
  #616 = NameAndType        #614:#615     // concatCallbacks:(Lscala/concurrent/impl/Promise$Callbacks;Lscala/concurrent/impl/Promise$Callbacks;)Lscala/concurrent/impl/Promise$Callbacks;
  #617 = Methodref          #2.#616       // scala/concurrent/impl/Promise$DefaultPromise.concatCallbacks:(Lscala/concurrent/impl/Promise$Callbacks;Lscala/concurrent/impl/Promise$Callbacks;)Lscala/concurrent/impl/Promise$Callbacks;
  #618 = Utf8               Lscala/concurrent/impl/Promise$Callbacks;
  #619 = Utf8               (Lscala/concurrent/impl/Promise$Callbacks<TT;>;Lscala/concurrent/impl/Promise$Callbacks<TT;>;)Lscala/concurrent/impl/Promise$Callbacks<TT;>;
  #620 = Utf8               left
  #621 = Utf8               right
  #622 = Utf8               (Lscala/concurrent/impl/Promise$Transformation;Lscala/concurrent/impl/Promise$Callbacks;)V
  #623 = NameAndType        #321:#622     // "<init>":(Lscala/concurrent/impl/Promise$Transformation;Lscala/concurrent/impl/Promise$Callbacks;)V
  #624 = Methodref          #38.#623      // scala/concurrent/impl/Promise$ManyCallbacks."<init>":(Lscala/concurrent/impl/Promise$Transformation;Lscala/concurrent/impl/Promise$Callbacks;)V
  #625 = Utf8               rest
  #626 = Utf8               ()Lscala/concurrent/impl/Promise$Callbacks;
  #627 = NameAndType        #625:#626     // rest:()Lscala/concurrent/impl/Promise$Callbacks;
  #628 = Methodref          #38.#627      // scala/concurrent/impl/Promise$ManyCallbacks.rest:()Lscala/concurrent/impl/Promise$Callbacks;
  #629 = Utf8               first
  #630 = Utf8               ()Lscala/concurrent/impl/Promise$Transformation;
  #631 = NameAndType        #629:#630     // first:()Lscala/concurrent/impl/Promise$Transformation;
  #632 = Methodref          #38.#631      // scala/concurrent/impl/Promise$ManyCallbacks.first:()Lscala/concurrent/impl/Promise$Transformation;
  #633 = Utf8               m
  #634 = Utf8               Lscala/concurrent/impl/Promise$ManyCallbacks;
  #635 = Utf8               (Lscala/concurrent/impl/Promise$Callbacks<TT;>;Lscala/util/Try<TT;>;)V
  #636 = Utf8               (Lscala/util/Try;)Lscala/concurrent/impl/Promise$Transformation;
  #637 = NameAndType        #579:#636     // submitWithValue:(Lscala/util/Try;)Lscala/concurrent/impl/Promise$Transformation;
  #638 = Methodref          #41.#637      // scala/concurrent/impl/Promise$Transformation.submitWithValue:(Lscala/util/Try;)Lscala/concurrent/impl/Promise$Transformation;
  #639 = Utf8               linkRootOf
  #640 = Utf8               (Lscala/concurrent/impl/Promise$DefaultPromise;Lscala/concurrent/impl/Promise$Link;)V
  #641 = Utf8               (Lscala/concurrent/impl/Promise$DefaultPromise<TT;>;Lscala/concurrent/impl/Promise$Link<TT;>;)V
  #642 = Utf8               target
  #643 = Utf8               link
  #644 = Utf8               java/lang/IllegalStateException
  #645 = Class              #644          // java/lang/IllegalStateException
  #646 = Utf8               Cannot link completed promises together
  #647 = String             #646          // Cannot link completed promises together
  #648 = Methodref          #645.#521     // java/lang/IllegalStateException."<init>":(Ljava/lang/String;)V
  #649 = Utf8               (Lscala/concurrent/impl/Promise$DefaultPromise;)V
  #650 = NameAndType        #321:#649     // "<init>":(Lscala/concurrent/impl/Promise$DefaultPromise;)V
  #651 = Methodref          #35.#650      // scala/concurrent/impl/Promise$Link."<init>":(Lscala/concurrent/impl/Promise$DefaultPromise;)V
  #652 = Utf8               Lscala/concurrent/impl/Promise$Link;
  #653 = Utf8               unlink
  #654 = Methodref          #35.#311      // scala/concurrent/impl/Promise$Link.get:()Ljava/lang/Object;
  #655 = Utf8               writeObject
  #656 = Utf8               (Ljava/io/ObjectOutputStream;)V
  #657 = Utf8               java/io/IOException
  #658 = Class              #657          // java/io/IOException
  #659 = Utf8               out
  #660 = Utf8               java/io/NotSerializableException
  #661 = Class              #660          // java/io/NotSerializableException
  #662 = Utf8               Promises and Futures cannot be serialized
  #663 = String             #662          // Promises and Futures cannot be serialized
  #664 = Methodref          #661.#521     // java/io/NotSerializableException."<init>":(Ljava/lang/String;)V
  #665 = Utf8               Ljava/io/ObjectOutputStream;
  #666 = Utf8               readObject
  #667 = Utf8               (Ljava/io/ObjectInputStream;)V
  #668 = Utf8               java/lang/ClassNotFoundException
  #669 = Class              #668          // java/lang/ClassNotFoundException
  #670 = Utf8               in
  #671 = Utf8               Promises and Futures cannot be deserialized
  #672 = String             #671          // Promises and Futures cannot be deserialized
  #673 = Utf8               Ljava/io/ObjectInputStream;
  #674 = NameAndType        #583:#584     // completeWith:(Lscala/concurrent/Future;)Lscala/concurrent/impl/Promise$DefaultPromise;
  #675 = Methodref          #2.#674       // scala/concurrent/impl/Promise$DefaultPromise.completeWith:(Lscala/concurrent/Future;)Lscala/concurrent/impl/Promise$DefaultPromise;
  #676 = Utf8               (Lscala/concurrent/duration/Duration;Lscala/concurrent/CanAwait;)Lscala/concurrent/Awaitable;
  #677 = NameAndType        #532:#533     // ready:(Lscala/concurrent/duration/Duration;Lscala/concurrent/CanAwait;)Lscala/concurrent/impl/Promise$DefaultPromise;
  #678 = Methodref          #2.#677       // scala/concurrent/impl/Promise$DefaultPromise.ready:(Lscala/concurrent/duration/Duration;Lscala/concurrent/CanAwait;)Lscala/concurrent/impl/Promise$DefaultPromise;
  #679 = NameAndType        #305:#306     // apply:(Lscala/util/Try;)V
  #680 = Methodref          #2.#679       // scala/concurrent/impl/Promise$DefaultPromise.apply:(Lscala/util/Try;)V
  #681 = Utf8               scala/runtime/BoxedUnit
  #682 = Class              #681          // scala/runtime/BoxedUnit
  #683 = Utf8               UNIT
  #684 = Utf8               Lscala/runtime/BoxedUnit;
  #685 = NameAndType        #683:#684     // UNIT:Lscala/runtime/BoxedUnit;
  #686 = Fieldref           #682.#685     // scala/runtime/BoxedUnit.UNIT:Lscala/runtime/BoxedUnit;
  #687 = Utf8               f$1
  #688 = Utf8               l$1
  #689 = Utf8               scala/Function2
  #690 = Class              #689          // scala/Function2
  #691 = Utf8               (Ljava/lang/Object;Ljava/lang/Object;)Ljava/lang/Object;
  #692 = NameAndType        #305:#691     // apply:(Ljava/lang/Object;Ljava/lang/Object;)Ljava/lang/Object;
  #693 = InterfaceMethodref #690.#692     // scala/Function2.apply:(Ljava/lang/Object;Ljava/lang/Object;)Ljava/lang/Object;
  #694 = Utf8               liftedTree1$1
  #695 = Utf8               (Lscala/Function2;Lscala/util/Success;Lscala/util/Success;)Lscala/util/Try;
  #696 = Utf8               x2$1
  #697 = Utf8               right$1
  #698 = Utf8               java/lang/Throwable
  #699 = Class              #698          // java/lang/Throwable
  #700 = Utf8               (Ljava/lang/Object;)V
  #701 = NameAndType        #321:#700     // "<init>":(Ljava/lang/Object;)V
  #702 = Methodref          #341.#701     // scala/util/Success."<init>":(Ljava/lang/Object;)V
  #703 = Utf8               scala/util/control/NonFatal$
  #704 = Class              #703          // scala/util/control/NonFatal$
  #705 = Utf8               Lscala/util/control/NonFatal$;
  #706 = NameAndType        #433:#705     // MODULE$:Lscala/util/control/NonFatal$;
  #707 = Fieldref           #704.#706     // scala/util/control/NonFatal$.MODULE$:Lscala/util/control/NonFatal$;
  #708 = NameAndType        #305:#300     // apply:(Ljava/lang/Throwable;)Z
  #709 = Methodref          #704.#708     // scala/util/control/NonFatal$.apply:(Ljava/lang/Throwable;)Z
  #710 = Utf8               (Ljava/lang/Throwable;)V
  #711 = NameAndType        #321:#710     // "<init>":(Ljava/lang/Throwable;)V
  #712 = Methodref          #404.#711     // scala/util/Failure."<init>":(Ljava/lang/Throwable;)V
  #713 = Utf8               $anonfun$zipWith$2
  #714 = Utf8               (Ljava/util/concurrent/atomic/AtomicReference;Lscala/concurrent/impl/Promise$DefaultPromise;Lscala/Function2;Lscala/util/Try;)V
  #715 = Utf8               buffer$1
  #716 = Utf8               zipped$1
  #717 = Utf8               x0$1
  #718 = Utf8               getAndSet
  #719 = NameAndType        #718:#344     // getAndSet:(Ljava/lang/Object;)Ljava/lang/Object;
  #720 = Methodref          #5.#719       // java/util/concurrent/atomic/AtomicReference.getAndSet:(Ljava/lang/Object;)Ljava/lang/Object;
  #721 = NameAndType        #694:#695     // liftedTree1$1:(Lscala/Function2;Lscala/util/Success;Lscala/util/Success;)Lscala/util/Try;
  #722 = Methodref          #2.#721       // scala/concurrent/impl/Promise$DefaultPromise.liftedTree1$1:(Lscala/Function2;Lscala/util/Success;Lscala/util/Success;)Lscala/util/Try;
  #723 = NameAndType        #558:#559     // tryComplete:(Lscala/util/Try;)Z
  #724 = Methodref          #2.#723       // scala/concurrent/impl/Promise$DefaultPromise.tryComplete:(Lscala/util/Try;)Z
  #725 = Utf8               liftedTree2$1
  #726 = Utf8               left$1
  #727 = Utf8               x2$2
  #728 = Utf8               $anonfun$zipWith$3
  #729 = Utf8               x0$2
  #730 = NameAndType        #725:#695     // liftedTree2$1:(Lscala/Function2;Lscala/util/Success;Lscala/util/Success;)Lscala/util/Try;
  #731 = Methodref          #2.#730       // scala/concurrent/impl/Promise$DefaultPromise.liftedTree2$1:(Lscala/Function2;Lscala/util/Success;Lscala/util/Success;)Lscala/util/Try;
  #732 = Utf8               initial
  #733 = Methodref          #5.#701       // java/util/concurrent/atomic/AtomicReference."<init>":(Ljava/lang/Object;)V
  #734 = Methodref          #2.#701       // scala/concurrent/impl/Promise$DefaultPromise."<init>":(Ljava/lang/Object;)V
  #735 = NameAndType        #713:#714     // $anonfun$zipWith$2:(Ljava/util/concurrent/atomic/AtomicReference;Lscala/concurrent/impl/Promise$DefaultPromise;Lscala/Function2;Lscala/util/Try;)V
  #736 = Methodref          #2.#735       // scala/concurrent/impl/Promise$DefaultPromise.$anonfun$zipWith$2:(Ljava/util/concurrent/atomic/AtomicReference;Lscala/concurrent/impl/Promise$DefaultPromise;Lscala/Function2;Lscala/util/Try;)V
  #737 = NameAndType        #728:#714     // $anonfun$zipWith$3:(Ljava/util/concurrent/atomic/AtomicReference;Lscala/concurrent/impl/Promise$DefaultPromise;Lscala/Function2;Lscala/util/Try;)V
  #738 = Methodref          #2.#737       // scala/concurrent/impl/Promise$DefaultPromise.$anonfun$zipWith$3:(Ljava/util/concurrent/atomic/AtomicReference;Lscala/concurrent/impl/Promise$DefaultPromise;Lscala/Function2;Lscala/util/Try;)V
  #739 = Utf8               $deserializeLambda$
  #740 = Utf8               (Ljava/lang/invoke/SerializedLambda;)Ljava/lang/Object;
  #741 = Utf8               scala/runtime/LambdaDeserialize
  #742 = Class              #741          // scala/runtime/LambdaDeserialize
  #743 = Utf8               bootstrap
  #744 = Utf8               (Ljava/lang/invoke/MethodHandles$Lookup;Ljava/lang/String;Ljava/lang/invoke/MethodType;[Ljava/lang/invoke/MethodHandle;)Ljava/lang/invoke/CallSite;
  #745 = NameAndType        #743:#744     // bootstrap:(Ljava/lang/invoke/MethodHandles$Lookup;Ljava/lang/String;Ljava/lang/invoke/MethodType;[Ljava/lang/invoke/MethodHandle;)Ljava/lang/invoke/CallSite;
  #746 = Methodref          #742.#745     // scala/runtime/LambdaDeserialize.bootstrap:(Ljava/lang/invoke/MethodHandles$Lookup;Ljava/lang/String;Ljava/lang/invoke/MethodType;[Ljava/lang/invoke/MethodHandle;)Ljava/lang/invoke/CallSite;
  #747 = MethodHandle       6:#746        // REF_invokeStatic scala/runtime/LambdaDeserialize.bootstrap:(Ljava/lang/invoke/MethodHandles$Lookup;Ljava/lang/String;Ljava/lang/invoke/MethodType;[Ljava/lang/invoke/MethodHandle;)Ljava/lang/invoke/CallSite;
  #748 = Utf8               lambdaDeserialize
  #749 = NameAndType        #748:#740     // lambdaDeserialize:(Ljava/lang/invoke/SerializedLambda;)Ljava/lang/Object;
  #750 = InvokeDynamic      #3:#749       // #3:lambdaDeserialize:(Ljava/lang/invoke/SerializedLambda;)Ljava/lang/Object;
  #751 = Utf8               Code
  #752 = Utf8               LineNumberTable
  #753 = Utf8               LocalVariableTable
  #754 = Utf8               MethodParameters
  #755 = Utf8               Signature
  #756 = Utf8               Deprecated
  #757 = Utf8               StackMapTable
  #758 = Utf8               Exceptions
  #759 = Utf8               InnerClasses
  #760 = Utf8               SourceFile
  #761 = Utf8               BootstrapMethods
  #762 = Utf8               ScalaInlineInfo
  #763 = Utf8               Scala
{
  public boolean apply$mcZD$sp(double);
    descriptor: (D)Z
    flags: (0x0001) ACC_PUBLIC
    Code:
      stack=3, locals=3, args_size=2
         0: aload_0
         1: dload_1
         2: invokestatic  #49                 // InterfaceMethod scala/Function1.apply$mcZD$sp$:(Lscala/Function1;D)Z
         5: ireturn
      LineNumberTable:
        line 104: 0
      LocalVariableTable:
        Start  Length  Slot  Name   Signature
            0       6     0  this   Lscala/concurrent/impl/Promise$DefaultPromise;
            0       6     1    v1   D
    MethodParameters:
      Name                           Flags
      v1                             final

  public double apply$mcDD$sp(double);
    descriptor: (D)D
    flags: (0x0001) ACC_PUBLIC
    Code:
      stack=3, locals=3, args_size=2
         0: aload_0
         1: dload_1
         2: invokestatic  #58                 // InterfaceMethod scala/Function1.apply$mcDD$sp$:(Lscala/Function1;D)D
         5: dreturn
      LineNumberTable:
        line 104: 0
      LocalVariableTable:
        Start  Length  Slot  Name   Signature
            0       6     0  this   Lscala/concurrent/impl/Promise$DefaultPromise;
            0       6     1    v1   D
    MethodParameters:
      Name                           Flags
      v1                             final

  public float apply$mcFD$sp(double);
    descriptor: (D)F
    flags: (0x0001) ACC_PUBLIC
    Code:
      stack=3, locals=3, args_size=2
         0: aload_0
         1: dload_1
         2: invokestatic  #64                 // InterfaceMethod scala/Function1.apply$mcFD$sp$:(Lscala/Function1;D)F
         5: freturn
      LineNumberTable:
        line 104: 0
      LocalVariableTable:
        Start  Length  Slot  Name   Signature
            0       6     0  this   Lscala/concurrent/impl/Promise$DefaultPromise;
            0       6     1    v1   D
    MethodParameters:
      Name                           Flags
      v1                             final

  public int apply$mcID$sp(double);
    descriptor: (D)I
    flags: (0x0001) ACC_PUBLIC
    Code:
      stack=3, locals=3, args_size=2
         0: aload_0
         1: dload_1
         2: invokestatic  #70                 // InterfaceMethod scala/Function1.apply$mcID$sp$:(Lscala/Function1;D)I
         5: ireturn
      LineNumberTable:
        line 104: 0
      LocalVariableTable:
        Start  Length  Slot  Name   Signature
            0       6     0  this   Lscala/concurrent/impl/Promise$DefaultPromise;
            0       6     1    v1   D
    MethodParameters:
      Name                           Flags
      v1                             final

  public long apply$mcJD$sp(double);
    descriptor: (D)J
    flags: (0x0001) ACC_PUBLIC
    Code:
      stack=3, locals=3, args_size=2
         0: aload_0
         1: dload_1
         2: invokestatic  #76                 // InterfaceMethod scala/Function1.apply$mcJD$sp$:(Lscala/Function1;D)J
         5: lreturn
      LineNumberTable:
        line 104: 0
      LocalVariableTable:
        Start  Length  Slot  Name   Signature
            0       6     0  this   Lscala/concurrent/impl/Promise$DefaultPromise;
            0       6     1    v1   D
    MethodParameters:
      Name                           Flags
      v1                             final

  public void apply$mcVD$sp(double);
    descriptor: (D)V
    flags: (0x0001) ACC_PUBLIC
    Code:
      stack=3, locals=3, args_size=2
         0: aload_0
         1: dload_1
         2: invokestatic  #82                 // InterfaceMethod scala/Function1.apply$mcVD$sp$:(Lscala/Function1;D)V
         5: return
      LineNumberTable:
        line 104: 0
      LocalVariableTable:
        Start  Length  Slot  Name   Signature
            0       6     0  this   Lscala/concurrent/impl/Promise$DefaultPromise;
            0       6     1    v1   D
    MethodParameters:
      Name                           Flags
      v1                             final

  public boolean apply$mcZF$sp(float);
    descriptor: (F)Z
    flags: (0x0001) ACC_PUBLIC
    Code:
      stack=2, locals=2, args_size=2
         0: aload_0
         1: fload_1
         2: invokestatic  #88                 // InterfaceMethod scala/Function1.apply$mcZF$sp$:(Lscala/Function1;F)Z
         5: ireturn
      LineNumberTable:
        line 104: 0
      LocalVariableTable:
        Start  Length  Slot  Name   Signature
            0       6     0  this   Lscala/concurrent/impl/Promise$DefaultPromise;
            0       6     1    v1   F
    MethodParameters:
      Name                           Flags
      v1                             final

  public double apply$mcDF$sp(float);
    descriptor: (F)D
    flags: (0x0001) ACC_PUBLIC
    Code:
      stack=2, locals=2, args_size=2
         0: aload_0
         1: fload_1
         2: invokestatic  #95                 // InterfaceMethod scala/Function1.apply$mcDF$sp$:(Lscala/Function1;F)D
         5: dreturn
      LineNumberTable:
        line 104: 0
      LocalVariableTable:
        Start  Length  Slot  Name   Signature
            0       6     0  this   Lscala/concurrent/impl/Promise$DefaultPromise;
            0       6     1    v1   F
    MethodParameters:
      Name                           Flags
      v1                             final

  public float apply$mcFF$sp(float);
    descriptor: (F)F
    flags: (0x0001) ACC_PUBLIC
    Code:
      stack=2, locals=2, args_size=2
         0: aload_0
         1: fload_1
         2: invokestatic  #101                // InterfaceMethod scala/Function1.apply$mcFF$sp$:(Lscala/Function1;F)F
         5: freturn
      LineNumberTable:
        line 104: 0
      LocalVariableTable:
        Start  Length  Slot  Name   Signature
            0       6     0  this   Lscala/concurrent/impl/Promise$DefaultPromise;
            0       6     1    v1   F
    MethodParameters:
      Name                           Flags
      v1                             final

  public int apply$mcIF$sp(float);
    descriptor: (F)I
    flags: (0x0001) ACC_PUBLIC
    Code:
      stack=2, locals=2, args_size=2
         0: aload_0
         1: fload_1
         2: invokestatic  #107                // InterfaceMethod scala/Function1.apply$mcIF$sp$:(Lscala/Function1;F)I
         5: ireturn
      LineNumberTable:
        line 104: 0
      LocalVariableTable:
        Start  Length  Slot  Name   Signature
            0       6     0  this   Lscala/concurrent/impl/Promise$DefaultPromise;
            0       6     1    v1   F
    MethodParameters:
      Name                           Flags
      v1                             final

  public long apply$mcJF$sp(float);
    descriptor: (F)J
    flags: (0x0001) ACC_PUBLIC
    Code:
      stack=2, locals=2, args_size=2
         0: aload_0
         1: fload_1
         2: invokestatic  #113                // InterfaceMethod scala/Function1.apply$mcJF$sp$:(Lscala/Function1;F)J
         5: lreturn
      LineNumberTable:
        line 104: 0
      LocalVariableTable:
        Start  Length  Slot  Name   Signature
            0       6     0  this   Lscala/concurrent/impl/Promise$DefaultPromise;
            0       6     1    v1   F
    MethodParameters:
      Name                           Flags
      v1                             final

  public void apply$mcVF$sp(float);
    descriptor: (F)V
    flags: (0x0001) ACC_PUBLIC
    Code:
      stack=2, locals=2, args_size=2
         0: aload_0
         1: fload_1
         2: invokestatic  #119                // InterfaceMethod scala/Function1.apply$mcVF$sp$:(Lscala/Function1;F)V
         5: return
      LineNumberTable:
        line 104: 0
      LocalVariableTable:
        Start  Length  Slot  Name   Signature
            0       6     0  this   Lscala/concurrent/impl/Promise$DefaultPromise;
            0       6     1    v1   F
    MethodParameters:
      Name                           Flags
      v1                             final

  public boolean apply$mcZI$sp(int);
    descriptor: (I)Z
    flags: (0x0001) ACC_PUBLIC
    Code:
      stack=2, locals=2, args_size=2
         0: aload_0
         1: iload_1
         2: invokestatic  #125                // InterfaceMethod scala/Function1.apply$mcZI$sp$:(Lscala/Function1;I)Z
         5: ireturn
      LineNumberTable:
        line 104: 0
      LocalVariableTable:
        Start  Length  Slot  Name   Signature
            0       6     0  this   Lscala/concurrent/impl/Promise$DefaultPromise;
            0       6     1    v1   I
    MethodParameters:
      Name                           Flags
      v1                             final

  public double apply$mcDI$sp(int);
    descriptor: (I)D
    flags: (0x0001) ACC_PUBLIC
    Code:
      stack=2, locals=2, args_size=2
         0: aload_0
         1: iload_1
         2: invokestatic  #132                // InterfaceMethod scala/Function1.apply$mcDI$sp$:(Lscala/Function1;I)D
         5: dreturn
      LineNumberTable:
        line 104: 0
      LocalVariableTable:
        Start  Length  Slot  Name   Signature
            0       6     0  this   Lscala/concurrent/impl/Promise$DefaultPromise;
            0       6     1    v1   I
    MethodParameters:
      Name                           Flags
      v1                             final

  public float apply$mcFI$sp(int);
    descriptor: (I)F
    flags: (0x0001) ACC_PUBLIC
    Code:
      stack=2, locals=2, args_size=2
         0: aload_0
         1: iload_1
         2: invokestatic  #138                // InterfaceMethod scala/Function1.apply$mcFI$sp$:(Lscala/Function1;I)F
         5: freturn
      LineNumberTable:
        line 104: 0
      LocalVariableTable:
        Start  Length  Slot  Name   Signature
            0       6     0  this   Lscala/concurrent/impl/Promise$DefaultPromise;
            0       6     1    v1   I
    MethodParameters:
      Name                           Flags
      v1                             final

  public int apply$mcII$sp(int);
    descriptor: (I)I
    flags: (0x0001) ACC_PUBLIC
    Code:
      stack=2, locals=2, args_size=2
         0: aload_0
         1: iload_1
         2: invokestatic  #144                // InterfaceMethod scala/Function1.apply$mcII$sp$:(Lscala/Function1;I)I
         5: ireturn
      LineNumberTable:
        line 104: 0
      LocalVariableTable:
        Start  Length  Slot  Name   Signature
            0       6     0  this   Lscala/concurrent/impl/Promise$DefaultPromise;
            0       6     1    v1   I
    MethodParameters:
      Name                           Flags
      v1                             final

  public long apply$mcJI$sp(int);
    descriptor: (I)J
    flags: (0x0001) ACC_PUBLIC
    Code:
      stack=2, locals=2, args_size=2
         0: aload_0
         1: iload_1
         2: invokestatic  #150                // InterfaceMethod scala/Function1.apply$mcJI$sp$:(Lscala/Function1;I)J
         5: lreturn
      LineNumberTable:
        line 104: 0
      LocalVariableTable:
        Start  Length  Slot  Name   Signature
            0       6     0  this   Lscala/concurrent/impl/Promise$DefaultPromise;
            0       6     1    v1   I
    MethodParameters:
      Name                           Flags
      v1                             final

  public void apply$mcVI$sp(int);
    descriptor: (I)V
    flags: (0x0001) ACC_PUBLIC
    Code:
      stack=2, locals=2, args_size=2
         0: aload_0
         1: iload_1
         2: invokestatic  #156                // InterfaceMethod scala/Function1.apply$mcVI$sp$:(Lscala/Function1;I)V
         5: return
      LineNumberTable:
        line 104: 0
      LocalVariableTable:
        Start  Length  Slot  Name   Signature
            0       6     0  this   Lscala/concurrent/impl/Promise$DefaultPromise;
            0       6     1    v1   I
    MethodParameters:
      Name                           Flags
      v1                             final

  public boolean apply$mcZJ$sp(long);
    descriptor: (J)Z
    flags: (0x0001) ACC_PUBLIC
    Code:
      stack=3, locals=3, args_size=2
         0: aload_0
         1: lload_1
         2: invokestatic  #162                // InterfaceMethod scala/Function1.apply$mcZJ$sp$:(Lscala/Function1;J)Z
         5: ireturn
      LineNumberTable:
        line 104: 0
      LocalVariableTable:
        Start  Length  Slot  Name   Signature
            0       6     0  this   Lscala/concurrent/impl/Promise$DefaultPromise;
            0       6     1    v1   J
    MethodParameters:
      Name                           Flags
      v1                             final

  public double apply$mcDJ$sp(long);
    descriptor: (J)D
    flags: (0x0001) ACC_PUBLIC
    Code:
      stack=3, locals=3, args_size=2
         0: aload_0
         1: lload_1
         2: invokestatic  #169                // InterfaceMethod scala/Function1.apply$mcDJ$sp$:(Lscala/Function1;J)D
         5: dreturn
      LineNumberTable:
        line 104: 0
      LocalVariableTable:
        Start  Length  Slot  Name   Signature
            0       6     0  this   Lscala/concurrent/impl/Promise$DefaultPromise;
            0       6     1    v1   J
    MethodParameters:
      Name                           Flags
      v1                             final

  public float apply$mcFJ$sp(long);
    descriptor: (J)F
    flags: (0x0001) ACC_PUBLIC
    Code:
      stack=3, locals=3, args_size=2
         0: aload_0
         1: lload_1
         2: invokestatic  #175                // InterfaceMethod scala/Function1.apply$mcFJ$sp$:(Lscala/Function1;J)F
         5: freturn
      LineNumberTable:
        line 104: 0
      LocalVariableTable:
        Start  Length  Slot  Name   Signature
            0       6     0  this   Lscala/concurrent/impl/Promise$DefaultPromise;
            0       6     1    v1   J
    MethodParameters:
      Name                           Flags
      v1                             final

  public int apply$mcIJ$sp(long);
    descriptor: (J)I
    flags: (0x0001) ACC_PUBLIC
    Code:
      stack=3, locals=3, args_size=2
         0: aload_0
         1: lload_1
         2: invokestatic  #181                // InterfaceMethod scala/Function1.apply$mcIJ$sp$:(Lscala/Function1;J)I
         5: ireturn
      LineNumberTable:
        line 104: 0
      LocalVariableTable:
        Start  Length  Slot  Name   Signature
            0       6     0  this   Lscala/concurrent/impl/Promise$DefaultPromise;
            0       6     1    v1   J
    MethodParameters:
      Name                           Flags
      v1                             final

  public long apply$mcJJ$sp(long);
    descriptor: (J)J
    flags: (0x0001) ACC_PUBLIC
    Code:
      stack=3, locals=3, args_size=2
         0: aload_0
         1: lload_1
         2: invokestatic  #187                // InterfaceMethod scala/Function1.apply$mcJJ$sp$:(Lscala/Function1;J)J
         5: lreturn
      LineNumberTable:
        line 104: 0
      LocalVariableTable:
        Start  Length  Slot  Name   Signature
            0       6     0  this   Lscala/concurrent/impl/Promise$DefaultPromise;
            0       6     1    v1   J
    MethodParameters:
      Name                           Flags
      v1                             final

  public void apply$mcVJ$sp(long);
    descriptor: (J)V
    flags: (0x0001) ACC_PUBLIC
    Code:
      stack=3, locals=3, args_size=2
         0: aload_0
         1: lload_1
         2: invokestatic  #193                // InterfaceMethod scala/Function1.apply$mcVJ$sp$:(Lscala/Function1;J)V
         5: return
      LineNumberTable:
        line 104: 0
      LocalVariableTable:
        Start  Length  Slot  Name   Signature
            0       6     0  this   Lscala/concurrent/impl/Promise$DefaultPromise;
            0       6     1    v1   J
    MethodParameters:
      Name                           Flags
      v1                             final

  public <A$ extends java.lang.Object> scala.Function1<A$, scala.runtime.BoxedUnit> compose(scala.Function1<A$, scala.util.Try<T>>);
    descriptor: (Lscala/Function1;)Lscala/Function1;
    flags: (0x0001) ACC_PUBLIC
    Code:
      stack=2, locals=2, args_size=2
         0: aload_0
         1: aload_1
         2: invokestatic  #201                // InterfaceMethod scala/Function1.compose$:(Lscala/Function1;Lscala/Function1;)Lscala/Function1;
         5: areturn
      LineNumberTable:
        line 104: 0
      LocalVariableTable:
        Start  Length  Slot  Name   Signature
            0       6     0  this   Lscala/concurrent/impl/Promise$DefaultPromise;
            0       6     1     g   Lscala/Function1;
    Signature: #196                         // <A$:Ljava/lang/Object;>(Lscala/Function1<TA$;Lscala/util/Try<TT;>;>;)Lscala/Function1<TA$;Lscala/runtime/BoxedUnit;>;
    MethodParameters:
      Name                           Flags
      g                              final

  public <A$ extends java.lang.Object> scala.Function1<scala.util.Try<T>, A$> andThen(scala.Function1<scala.runtime.BoxedUnit, A$>);
    descriptor: (Lscala/Function1;)Lscala/Function1;
    flags: (0x0001) ACC_PUBLIC
    Code:
      stack=2, locals=2, args_size=2
         0: aload_0
         1: aload_1
         2: invokestatic  #207                // InterfaceMethod scala/Function1.andThen$:(Lscala/Function1;Lscala/Function1;)Lscala/Function1;
         5: areturn
      LineNumberTable:
        line 104: 0
      LocalVariableTable:
        Start  Length  Slot  Name   Signature
            0       6     0  this   Lscala/concurrent/impl/Promise$DefaultPromise;
            0       6     1     g   Lscala/Function1;
    Signature: #204                         // <A$:Ljava/lang/Object;>(Lscala/Function1<Lscala/runtime/BoxedUnit;TA$;>;)Lscala/Function1<Lscala/util/Try<TT;>;TA$;>;
    MethodParameters:
      Name                           Flags
      g                              final

  public <S extends java.lang.Object> scala.concurrent.Future<S> transform(scala.Function1<T, S>, scala.Function1<java.lang.Throwable, java.lang.Throwable>, scala.concurrent.ExecutionContext);
    descriptor: (Lscala/Function1;Lscala/Function1;Lscala/concurrent/ExecutionContext;)Lscala/concurrent/Future;
    flags: (0x0001) ACC_PUBLIC
    Code:
      stack=4, locals=4, args_size=4
         0: aload_0
         1: aload_1
         2: aload_2
         3: aload_3
         4: invokestatic  #217                // InterfaceMethod scala/concurrent/Future.transform$:(Lscala/concurrent/Future;Lscala/Function1;Lscala/Function1;Lscala/concurrent/ExecutionContext;)Lscala/concurrent/Future;
         7: areturn
      LineNumberTable:
        line 104: 0
      LocalVariableTable:
        Start  Length  Slot  Name   Signature
            0       8     0  this   Lscala/concurrent/impl/Promise$DefaultPromise;
            0       8     1     s   Lscala/Function1;
            0       8     2     f   Lscala/Function1;
            0       8     3 executor   Lscala/concurrent/ExecutionContext;
    Signature: #210                         // <S:Ljava/lang/Object;>(Lscala/Function1<TT;TS;>;Lscala/Function1<Ljava/lang/Throwable;Ljava/lang/Throwable;>;Lscala/concurrent/ExecutionContext;)Lscala/concurrent/Future<TS;>;
    MethodParameters:
      Name                           Flags
      s                              final
      f                              final
      executor                       final

  public <S extends java.lang.Object> scala.concurrent.Future<S> flatten(scala.$less$colon$less<T, scala.concurrent.Future<S>>);
    descriptor: (Lscala/$less$colon$less;)Lscala/concurrent/Future;
    flags: (0x0001) ACC_PUBLIC
    Code:
      stack=2, locals=2, args_size=2
         0: aload_0
         1: aload_1
         2: invokestatic  #226                // InterfaceMethod scala/concurrent/Future.flatten$:(Lscala/concurrent/Future;Lscala/$less$colon$less;)Lscala/concurrent/Future;
         5: areturn
      LineNumberTable:
        line 104: 0
      LocalVariableTable:
        Start  Length  Slot  Name   Signature
            0       6     0  this   Lscala/concurrent/impl/Promise$DefaultPromise;
            0       6     1    ev   Lscala/$less$colon$less;
    Signature: #221                         // <S:Ljava/lang/Object;>(Lscala/$less$colon$less<TT;Lscala/concurrent/Future<TS;>;>;)Lscala/concurrent/Future<TS;>;
    MethodParameters:
      Name                           Flags
      ev                             final

  public final scala.concurrent.Future<T> withFilter(scala.Function1<T, java.lang.Object>, scala.concurrent.ExecutionContext);
    descriptor: (Lscala/Function1;Lscala/concurrent/ExecutionContext;)Lscala/concurrent/Future;
    flags: (0x0011) ACC_PUBLIC, ACC_FINAL
    Code:
      stack=3, locals=3, args_size=3
         0: aload_0
         1: aload_1
         2: aload_2
         3: invokestatic  #235                // InterfaceMethod scala/concurrent/Future.withFilter$:(Lscala/concurrent/Future;Lscala/Function1;Lscala/concurrent/ExecutionContext;)Lscala/concurrent/Future;
         6: areturn
      LineNumberTable:
        line 104: 0
      LocalVariableTable:
        Start  Length  Slot  Name   Signature
            0       7     0  this   Lscala/concurrent/impl/Promise$DefaultPromise;
            0       7     1     p   Lscala/Function1;
            0       7     2 executor   Lscala/concurrent/ExecutionContext;
    Signature: #230                         // (Lscala/Function1<TT;Ljava/lang/Object;>;Lscala/concurrent/ExecutionContext;)Lscala/concurrent/Future<TT;>;
    MethodParameters:
      Name                           Flags
      p                              final
      executor                       final

  public <U extends java.lang.Object> scala.concurrent.Future<scala.Tuple2<T, U>> zip(scala.concurrent.Future<U>);
    descriptor: (Lscala/concurrent/Future;)Lscala/concurrent/Future;
    flags: (0x0001) ACC_PUBLIC
    Code:
      stack=2, locals=2, args_size=2
         0: aload_0
         1: aload_1
         2: invokestatic  #243                // InterfaceMethod scala/concurrent/Future.zip$:(Lscala/concurrent/Future;Lscala/concurrent/Future;)Lscala/concurrent/Future;
         5: areturn
      LineNumberTable:
        line 104: 0
      LocalVariableTable:
        Start  Length  Slot  Name   Signature
            0       6     0  this   Lscala/concurrent/impl/Promise$DefaultPromise;
            0       6     1  that   Lscala/concurrent/Future;
    Signature: #238                         // <U:Ljava/lang/Object;>(Lscala/concurrent/Future<TU;>;)Lscala/concurrent/Future<Lscala/Tuple2<TT;TU;>;>;
    MethodParameters:
      Name                           Flags
      that                           final

  public <U extends java.lang.Object> scala.concurrent.Future<U> fallbackTo(scala.concurrent.Future<U>);
    descriptor: (Lscala/concurrent/Future;)Lscala/concurrent/Future;
    flags: (0x0001) ACC_PUBLIC
    Code:
      stack=2, locals=2, args_size=2
         0: aload_0
         1: aload_1
         2: invokestatic  #249                // InterfaceMethod scala/concurrent/Future.fallbackTo$:(Lscala/concurrent/Future;Lscala/concurrent/Future;)Lscala/concurrent/Future;
         5: areturn
      LineNumberTable:
        line 104: 0
      LocalVariableTable:
        Start  Length  Slot  Name   Signature
            0       6     0  this   Lscala/concurrent/impl/Promise$DefaultPromise;
            0       6     1  that   Lscala/concurrent/Future;
    Signature: #246                         // <U:Ljava/lang/Object;>(Lscala/concurrent/Future<TU;>;)Lscala/concurrent/Future<TU;>;
    MethodParameters:
      Name                           Flags
      that                           final

  public <U extends java.lang.Object> scala.concurrent.Future<T> andThen(scala.PartialFunction<scala.util.Try<T>, U>, scala.concurrent.ExecutionContext);
    descriptor: (Lscala/PartialFunction;Lscala/concurrent/ExecutionContext;)Lscala/concurrent/Future;
    flags: (0x0001) ACC_PUBLIC
    Code:
      stack=3, locals=3, args_size=3
         0: aload_0
         1: aload_1
         2: aload_2
         3: invokestatic  #255                // InterfaceMethod scala/concurrent/Future.andThen$:(Lscala/concurrent/Future;Lscala/PartialFunction;Lscala/concurrent/ExecutionContext;)Lscala/concurrent/Future;
         6: areturn
      LineNumberTable:
        line 104: 0
      LocalVariableTable:
        Start  Length  Slot  Name   Signature
            0       7     0  this   Lscala/concurrent/impl/Promise$DefaultPromise;
            0       7     1    pf   Lscala/PartialFunction;
            0       7     2 executor   Lscala/concurrent/ExecutionContext;
    Signature: #251                         // <U:Ljava/lang/Object;>(Lscala/PartialFunction<Lscala/util/Try<TT;>;TU;>;Lscala/concurrent/ExecutionContext;)Lscala/concurrent/Future<TT;>;
    MethodParameters:
      Name                           Flags
      pf                             final
      executor                       final

  public scala.concurrent.Promise<T> complete(scala.util.Try<T>);
    descriptor: (Lscala/util/Try;)Lscala/concurrent/Promise;
    flags: (0x0001) ACC_PUBLIC
    Code:
      stack=2, locals=2, args_size=2
         0: aload_0
         1: aload_1
         2: invokestatic  #264                // InterfaceMethod scala/concurrent/Promise.complete$:(Lscala/concurrent/Promise;Lscala/util/Try;)Lscala/concurrent/Promise;
         5: areturn
      LineNumberTable:
        line 104: 0
      LocalVariableTable:
        Start  Length  Slot  Name   Signature
            0       6     0  this   Lscala/concurrent/impl/Promise$DefaultPromise;
            0       6     1 result   Lscala/util/Try;
    Signature: #259                         // (Lscala/util/Try<TT;>;)Lscala/concurrent/Promise<TT;>;
    MethodParameters:
      Name                           Flags
      result                         final

  public final scala.concurrent.Promise<T> tryCompleteWith(scala.concurrent.Future<T>);
    descriptor: (Lscala/concurrent/Future;)Lscala/concurrent/Promise;
    flags: (0x0011) ACC_PUBLIC, ACC_FINAL
    Code:
      stack=2, locals=2, args_size=2
         0: aload_0
         1: aload_1
         2: invokestatic  #273                // InterfaceMethod scala/concurrent/Promise.tryCompleteWith$:(Lscala/concurrent/Promise;Lscala/concurrent/Future;)Lscala/concurrent/Promise;
         5: areturn
      LineNumberTable:
        line 104: 0
      LocalVariableTable:
        Start  Length  Slot  Name   Signature
            0       6     0  this   Lscala/concurrent/impl/Promise$DefaultPromise;
            0       6     1 other   Lscala/concurrent/Future;
    Signature: #268                         // (Lscala/concurrent/Future<TT;>;)Lscala/concurrent/Promise<TT;>;
    Deprecated: true
    MethodParameters:
      Name                           Flags
      other                          final

  public scala.concurrent.Promise<T> success(T);
    descriptor: (Ljava/lang/Object;)Lscala/concurrent/Promise;
    flags: (0x0001) ACC_PUBLIC
    Code:
      stack=2, locals=2, args_size=2
         0: aload_0
         1: aload_1
         2: invokestatic  #281                // InterfaceMethod scala/concurrent/Promise.success$:(Lscala/concurrent/Promise;Ljava/lang/Object;)Lscala/concurrent/Promise;
         5: areturn
      LineNumberTable:
        line 104: 0
      LocalVariableTable:
        Start  Length  Slot  Name   Signature
            0       6     0  this   Lscala/concurrent/impl/Promise$DefaultPromise;
            0       6     1 value   Ljava/lang/Object;
    Signature: #276                         // (TT;)Lscala/concurrent/Promise<TT;>;
    MethodParameters:
      Name                           Flags
      value                          final

  public boolean trySuccess(T);
    descriptor: (Ljava/lang/Object;)Z
    flags: (0x0001) ACC_PUBLIC
    Code:
      stack=2, locals=2, args_size=2
         0: aload_0
         1: aload_1
         2: invokestatic  #289                // InterfaceMethod scala/concurrent/Promise.trySuccess$:(Lscala/concurrent/Promise;Ljava/lang/Object;)Z
         5: ireturn
      LineNumberTable:
        line 104: 0
      LocalVariableTable:
        Start  Length  Slot  Name   Signature
            0       6     0  this   Lscala/concurrent/impl/Promise$DefaultPromise;
            0       6     1 value   Ljava/lang/Object;
    Signature: #285                         // (TT;)Z
    MethodParameters:
      Name                           Flags
      value                          final

  public scala.concurrent.Promise<T> failure(java.lang.Throwable);
    descriptor: (Ljava/lang/Throwable;)Lscala/concurrent/Promise;
    flags: (0x0001) ACC_PUBLIC
    Code:
      stack=2, locals=2, args_size=2
         0: aload_0
         1: aload_1
         2: invokestatic  #297                // InterfaceMethod scala/concurrent/Promise.failure$:(Lscala/concurrent/Promise;Ljava/lang/Throwable;)Lscala/concurrent/Promise;
         5: areturn
      LineNumberTable:
        line 104: 0
      LocalVariableTable:
        Start  Length  Slot  Name   Signature
            0       6     0  this   Lscala/concurrent/impl/Promise$DefaultPromise;
            0       6     1 cause   Ljava/lang/Throwable;
    Signature: #292                         // (Ljava/lang/Throwable;)Lscala/concurrent/Promise<TT;>;
    MethodParameters:
      Name                           Flags
      cause                          final

  public boolean tryFailure(java.lang.Throwable);
    descriptor: (Ljava/lang/Throwable;)Z
    flags: (0x0001) ACC_PUBLIC
    Code:
      stack=2, locals=2, args_size=2
         0: aload_0
         1: aload_1
         2: invokestatic  #304                // InterfaceMethod scala/concurrent/Promise.tryFailure$:(Lscala/concurrent/Promise;Ljava/lang/Throwable;)Z
         5: ireturn
      LineNumberTable:
        line 104: 0
      LocalVariableTable:
        Start  Length  Slot  Name   Signature
            0       6     0  this   Lscala/concurrent/impl/Promise$DefaultPromise;
            0       6     1 cause   Ljava/lang/Throwable;
    MethodParameters:
      Name                           Flags
      cause                          final

  public final void apply(scala.util.Try<T>);
    descriptor: (Lscala/util/Try;)V
    flags: (0x0011) ACC_PUBLIC, ACC_FINAL
    Code:
      stack=3, locals=2, args_size=2
         0: aload_0
         1: aload_0
         2: invokevirtual #312                // Method get:()Ljava/lang/Object;
         5: aload_1
         6: invokevirtual #316                // Method tryComplete0:(Ljava/lang/Object;Lscala/util/Try;)Z
         9: pop
        10: return
      LineNumberTable:
        line 120: 0
      LocalVariableTable:
        Start  Length  Slot  Name   Signature
            0      11     0  this   Lscala/concurrent/impl/Promise$DefaultPromise;
            0      11     1 resolved   Lscala/util/Try;
    Signature: #307                         // (Lscala/util/Try<TT;>;)V
    MethodParameters:
      Name                           Flags
      resolved                       final

  public final scala.concurrent.Future<T> future();
    descriptor: ()Lscala/concurrent/Future;
    flags: (0x0011) ACC_PUBLIC, ACC_FINAL
    Code:
      stack=1, locals=1, args_size=1
         0: aload_0
         1: areturn
      LineNumberTable:
        line 125: 0
      LocalVariableTable:
        Start  Length  Slot  Name   Signature
            0       2     0  this   Lscala/concurrent/impl/Promise$DefaultPromise;
    Signature: #319                         // ()Lscala/concurrent/Future<TT;>;

  public final <S extends java.lang.Object> scala.concurrent.Future<S> transform(scala.Function1<scala.util.Try<T>, scala.util.Try<S>>, scala.concurrent.ExecutionContext);
    descriptor: (Lscala/Function1;Lscala/concurrent/ExecutionContext;)Lscala/concurrent/Future;
    flags: (0x0011) ACC_PUBLIC, ACC_FINAL
    Code:
      stack=7, locals=3, args_size=3
         0: aload_0
         1: aload_0
         2: invokevirtual #312                // Method get:()Ljava/lang/Object;
         5: new           #41                 // class scala/concurrent/impl/Promise$Transformation
         8: dup
         9: iconst_3
        10: aload_1
        11: aload_2
        12: invokespecial #324                // Method scala/concurrent/impl/Promise$Transformation."<init>":(ILscala/Function1;Lscala/concurrent/ExecutionContext;)V
        15: invokespecial #328                // Method dispatchOrAddCallbacks:(Ljava/lang/Object;Lscala/concurrent/impl/Promise$Callbacks;)Lscala/concurrent/impl/Promise$Callbacks;
        18: checkcast     #9                  // class scala/concurrent/Future
        21: areturn
      LineNumberTable:
        line 128: 0
      LocalVariableTable:
        Start  Length  Slot  Name   Signature
            0      22     0  this   Lscala/concurrent/impl/Promise$DefaultPromise;
            0      22     1     f   Lscala/Function1;
            0      22     2 executor   Lscala/concurrent/ExecutionContext;
    Signature: #320                         // <S:Ljava/lang/Object;>(Lscala/Function1<Lscala/util/Try<TT;>;Lscala/util/Try<TS;>;>;Lscala/concurrent/ExecutionContext;)Lscala/concurrent/Future<TS;>;
    MethodParameters:
      Name                           Flags
      f                              final
      executor                       final

  public final <S extends java.lang.Object> scala.concurrent.Future<S> transformWith(scala.Function1<scala.util.Try<T>, scala.concurrent.Future<S>>, scala.concurrent.ExecutionContext);
    descriptor: (Lscala/Function1;Lscala/concurrent/ExecutionContext;)Lscala/concurrent/Future;
    flags: (0x0011) ACC_PUBLIC, ACC_FINAL
    Code:
      stack=7, locals=3, args_size=3
         0: aload_0
         1: aload_0
         2: invokevirtual #312                // Method get:()Ljava/lang/Object;
         5: new           #41                 // class scala/concurrent/impl/Promise$Transformation
         8: dup
         9: iconst_4
        10: aload_1
        11: aload_2
        12: invokespecial #324                // Method scala/concurrent/impl/Promise$Transformation."<init>":(ILscala/Function1;Lscala/concurrent/ExecutionContext;)V
        15: invokespecial #328                // Method dispatchOrAddCallbacks:(Ljava/lang/Object;Lscala/concurrent/impl/Promise$Callbacks;)Lscala/concurrent/impl/Promise$Callbacks;
        18: checkcast     #9                  // class scala/concurrent/Future
        21: areturn
      LineNumberTable:
        line 131: 0
      LocalVariableTable:
        Start  Length  Slot  Name   Signature
            0      22     0  this   Lscala/concurrent/impl/Promise$DefaultPromise;
            0      22     1     f   Lscala/Function1;
            0      22     2 executor   Lscala/concurrent/ExecutionContext;
    Signature: #330                         // <S:Ljava/lang/Object;>(Lscala/Function1<Lscala/util/Try<TT;>;Lscala/concurrent/Future<TS;>;>;Lscala/concurrent/ExecutionContext;)Lscala/concurrent/Future<TS;>;
    MethodParameters:
      Name                           Flags
      f                              final
      executor                       final

  public final <U extends java.lang.Object, R extends java.lang.Object> scala.concurrent.Future<R> zipWith(scala.concurrent.Future<U>, scala.Function2<T, U, R>, scala.concurrent.ExecutionContext);
    descriptor: (Lscala/concurrent/Future;Lscala/Function2;Lscala/concurrent/ExecutionContext;)Lscala/concurrent/Future;
    flags: (0x0011) ACC_PUBLIC, ACC_FINAL
    Code:
      stack=7, locals=12, args_size=4
         0: aload_0
         1: invokevirtual #312                // Method get:()Ljava/lang/Object;
         4: astore        4
         6: aload         4
         8: instanceof    #335                // class scala/util/Try
        11: ifeq          73
        14: aload         4
        16: checkcast     #335                // class scala/util/Try
        19: invokevirtual #339                // Method scala/util/Try.isFailure:()Z
        22: ifeq          27
        25: aload_0
        26: areturn
        27: aload         4
        29: checkcast     #341                // class scala/util/Success
        32: dup
        33: ifnonnull     38
        36: aconst_null
        37: athrow
        38: astore        10
        40: aload         10
        42: invokevirtual #343                // Method scala/util/Success.value:()Ljava/lang/Object;
        45: astore        11
        47: aload         11
        49: aconst_null
        50: astore        10
        52: aconst_null
        53: astore        11
        55: astore        5
        57: aload_1
        58: aload_2
        59: aload         5
        61: invokedynamic #361,  0            // InvokeDynamic #0:apply:(Lscala/Function2;Ljava/lang/Object;)Lscala/Function1;
        66: aload_3
        67: invokeinterface #364,  3          // InterfaceMethod scala/concurrent/Future.map:(Lscala/Function1;Lscala/concurrent/ExecutionContext;)Lscala/concurrent/Future;
        72: areturn
        73: new           #5                  // class java/util/concurrent/atomic/AtomicReference
        76: dup
        77: invokespecial #367                // Method java/util/concurrent/atomic/AtomicReference."<init>":()V
        80: astore        6
        82: new           #2                  // class scala/concurrent/impl/Promise$DefaultPromise
        85: dup
        86: invokespecial #368                // Method "<init>":()V
        89: astore        7
        91: aload         6
        93: aload         7
        95: aload_2
        96: invokedynamic #379,  0            // InvokeDynamic #1:apply:(Ljava/util/concurrent/atomic/AtomicReference;Lscala/concurrent/impl/Promise$DefaultPromise;Lscala/Function2;)Lscala/Function1;
       101: astore        8
       103: aload         6
       105: aload         7
       107: aload_2
       108: invokedynamic #384,  0            // InvokeDynamic #2:apply:(Ljava/util/concurrent/atomic/AtomicReference;Lscala/concurrent/impl/Promise$DefaultPromise;Lscala/Function2;)Lscala/Function1;
       113: astore        9
       115: aload_0
       116: aload         4
       118: new           #41                 // class scala/concurrent/impl/Promise$Transformation
       121: dup
       122: bipush        6
       124: aload         8
       126: aload_3
       127: invokespecial #324                // Method scala/concurrent/impl/Promise$Transformation."<init>":(ILscala/Function1;Lscala/concurrent/ExecutionContext;)V
       130: invokespecial #328                // Method dispatchOrAddCallbacks:(Ljava/lang/Object;Lscala/concurrent/impl/Promise$Callbacks;)Lscala/concurrent/impl/Promise$Callbacks;
       133: pop
       134: aload_1
       135: aload         9
       137: aload_3
       138: invokeinterface #388,  3          // InterfaceMethod scala/concurrent/Future.onComplete:(Lscala/Function1;Lscala/concurrent/ExecutionContext;)V
       143: aload         7
       145: areturn
      StackMapTable: number_of_entries = 3
        frame_type = 252 /* append */
          offset_delta = 27
          locals = [ class java/lang/Object ]
        frame_type = 74 /* same_locals_1_stack_item */
          stack = [ class scala/util/Success ]
        frame_type = 34 /* same */
      LineNumberTable:
        line 134: 0
        line 135: 6
        line 136: 14
        line 138: 27
        line 139: 57
        line 142: 73
        line 143: 82
        line 145: 91
        line 154: 103
        line 163: 115
        line 164: 134
        line 125: 143
        line 165: 143
      LocalVariableTable:
        Start  Length  Slot  Name   Signature
           57      15     5     l   Ljava/lang/Object;
           82      63     6 buffer   Ljava/util/concurrent/atomic/AtomicReference;
           91      54     7 zipped   Lscala/concurrent/impl/Promise$DefaultPromise;
          103      42     8 thisF   Lscala/Function1;
          115      30     9 thatF   Lscala/Function1;
            6     139     4 state   Ljava/lang/Object;
            0     146     0  this   Lscala/concurrent/impl/Promise$DefaultPromise;
            0     146     1  that   Lscala/concurrent/Future;
            0     146     2     f   Lscala/Function2;
            0     146     3 executor   Lscala/concurrent/ExecutionContext;
           40       7    10 get_this   Lscala/util/Success;
    Signature: #333                         // <U:Ljava/lang/Object;R:Ljava/lang/Object;>(Lscala/concurrent/Future<TU;>;Lscala/Function2<TT;TU;TR;>;Lscala/concurrent/ExecutionContext;)Lscala/concurrent/Future<TR;>;
    MethodParameters:
      Name                           Flags
      that                           final
      f                              final
      executor                       final

  public final <U extends java.lang.Object> void foreach(scala.Function1<T, U>, scala.concurrent.ExecutionContext);
    descriptor: (Lscala/Function1;Lscala/concurrent/ExecutionContext;)V
    flags: (0x0011) ACC_PUBLIC, ACC_FINAL
    Code:
      stack=7, locals=4, args_size=3
         0: aload_0
         1: invokevirtual #312                // Method get:()Ljava/lang/Object;
         4: astore_3
         5: aload_3
         6: instanceof    #404                // class scala/util/Failure
         9: ifne          28
        12: aload_0
        13: aload_3
        14: new           #41                 // class scala/concurrent/impl/Promise$Transformation
        17: dup
        18: iconst_5
        19: aload_1
        20: aload_2
        21: invokespecial #324                // Method scala/concurrent/impl/Promise$Transformation."<init>":(ILscala/Function1;Lscala/concurrent/ExecutionContext;)V
        24: invokespecial #328                // Method dispatchOrAddCallbacks:(Ljava/lang/Object;Lscala/concurrent/impl/Promise$Callbacks;)Lscala/concurrent/impl/Promise$Callbacks;
        27: pop
        28: return
      StackMapTable: number_of_entries = 1
        frame_type = 252 /* append */
          offset_delta = 28
          locals = [ class java/lang/Object ]
      LineNumberTable:
        line 170: 0
        line 171: 5
      LocalVariableTable:
        Start  Length  Slot  Name   Signature
            5      23     3 state   Ljava/lang/Object;
            0      29     0  this   Lscala/concurrent/impl/Promise$DefaultPromise;
            0      29     1     f   Lscala/Function1;
            0      29     2 executor   Lscala/concurrent/ExecutionContext;
    Signature: #402                         // <U:Ljava/lang/Object;>(Lscala/Function1<TT;TU;>;Lscala/concurrent/ExecutionContext;)V
    MethodParameters:
      Name                           Flags
      f                              final
      executor                       final

  public final <S extends java.lang.Object> scala.concurrent.Future<S> flatMap(scala.Function1<T, scala.concurrent.Future<S>>, scala.concurrent.ExecutionContext);
    descriptor: (Lscala/Function1;Lscala/concurrent/ExecutionContext;)Lscala/concurrent/Future;
    flags: (0x0011) ACC_PUBLIC, ACC_FINAL
    Code:
      stack=7, locals=4, args_size=3
         0: aload_0
         1: invokevirtual #312                // Method get:()Ljava/lang/Object;
         4: astore_3
         5: aload_3
         6: instanceof    #404                // class scala/util/Failure
         9: ifne          31
        12: aload_0
        13: aload_3
        14: new           #41                 // class scala/concurrent/impl/Promise$Transformation
        17: dup
        18: iconst_2
        19: aload_1
        20: aload_2
        21: invokespecial #324                // Method scala/concurrent/impl/Promise$Transformation."<init>":(ILscala/Function1;Lscala/concurrent/ExecutionContext;)V
        24: invokespecial #328                // Method dispatchOrAddCallbacks:(Ljava/lang/Object;Lscala/concurrent/impl/Promise$Callbacks;)Lscala/concurrent/impl/Promise$Callbacks;
        27: checkcast     #9                  // class scala/concurrent/Future
        30: areturn
        31: aload_0
        32: areturn
      StackMapTable: number_of_entries = 1
        frame_type = 252 /* append */
          offset_delta = 31
          locals = [ class java/lang/Object ]
      LineNumberTable:
        line 175: 0
        line 176: 5
        line 177: 31
      LocalVariableTable:
        Start  Length  Slot  Name   Signature
            5      27     3 state   Ljava/lang/Object;
            0      33     0  this   Lscala/concurrent/impl/Promise$DefaultPromise;
            0      33     1     f   Lscala/Function1;
            0      33     2 executor   Lscala/concurrent/ExecutionContext;
    Signature: #406                         // <S:Ljava/lang/Object;>(Lscala/Function1<TT;Lscala/concurrent/Future<TS;>;>;Lscala/concurrent/ExecutionContext;)Lscala/concurrent/Future<TS;>;
    MethodParameters:
      Name                           Flags
      f                              final
      executor                       final

  public final <S extends java.lang.Object> scala.concurrent.Future<S> map(scala.Function1<T, S>, scala.concurrent.ExecutionContext);
    descriptor: (Lscala/Function1;Lscala/concurrent/ExecutionContext;)Lscala/concurrent/Future;
    flags: (0x0011) ACC_PUBLIC, ACC_FINAL
    Code:
      stack=7, locals=4, args_size=3
         0: aload_0
         1: invokevirtual #312                // Method get:()Ljava/lang/Object;
         4: astore_3
         5: aload_3
         6: instanceof    #404                // class scala/util/Failure
         9: ifne          31
        12: aload_0
        13: aload_3
        14: new           #41                 // class scala/concurrent/impl/Promise$Transformation
        17: dup
        18: iconst_1
        19: aload_1
        20: aload_2
        21: invokespecial #324                // Method scala/concurrent/impl/Promise$Transformation."<init>":(ILscala/Function1;Lscala/concurrent/ExecutionContext;)V
        24: invokespecial #328                // Method dispatchOrAddCallbacks:(Ljava/lang/Object;Lscala/concurrent/impl/Promise$Callbacks;)Lscala/concurrent/impl/Promise$Callbacks;
        27: checkcast     #9                  // class scala/concurrent/Future
        30: areturn
        31: aload_0
        32: areturn
      StackMapTable: number_of_entries = 1
        frame_type = 252 /* append */
          offset_delta = 31
          locals = [ class java/lang/Object ]
      LineNumberTable:
        line 181: 0
        line 182: 5
        line 183: 31
      LocalVariableTable:
        Start  Length  Slot  Name   Signature
            5      27     3 state   Ljava/lang/Object;
            0      33     0  this   Lscala/concurrent/impl/Promise$DefaultPromise;
            0      33     1     f   Lscala/Function1;
            0      33     2 executor   Lscala/concurrent/ExecutionContext;
    Signature: #407                         // <S:Ljava/lang/Object;>(Lscala/Function1<TT;TS;>;Lscala/concurrent/ExecutionContext;)Lscala/concurrent/Future<TS;>;
    MethodParameters:
      Name                           Flags
      f                              final
      executor                       final

  public final scala.concurrent.Future<T> filter(scala.Function1<T, java.lang.Object>, scala.concurrent.ExecutionContext);
    descriptor: (Lscala/Function1;Lscala/concurrent/ExecutionContext;)Lscala/concurrent/Future;
    flags: (0x0011) ACC_PUBLIC, ACC_FINAL
    Code:
      stack=7, locals=4, args_size=3
         0: aload_0
         1: invokevirtual #312                // Method get:()Ljava/lang/Object;
         4: astore_3
         5: aload_3
         6: instanceof    #404                // class scala/util/Failure
         9: ifne          32
        12: aload_0
        13: aload_3
        14: new           #41                 // class scala/concurrent/impl/Promise$Transformation
        17: dup
        18: bipush        9
        20: aload_1
        21: aload_2
        22: invokespecial #324                // Method scala/concurrent/impl/Promise$Transformation."<init>":(ILscala/Function1;Lscala/concurrent/ExecutionContext;)V
        25: invokespecial #328                // Method dispatchOrAddCallbacks:(Ljava/lang/Object;Lscala/concurrent/impl/Promise$Callbacks;)Lscala/concurrent/impl/Promise$Callbacks;
        28: checkcast     #9                  // class scala/concurrent/Future
        31: areturn
        32: aload_0
        33: areturn
      StackMapTable: number_of_entries = 1
        frame_type = 252 /* append */
          offset_delta = 32
          locals = [ class java/lang/Object ]
      LineNumberTable:
        line 187: 0
        line 188: 5
        line 189: 32
      LocalVariableTable:
        Start  Length  Slot  Name   Signature
            5      28     3 state   Ljava/lang/Object;
            0      34     0  this   Lscala/concurrent/impl/Promise$DefaultPromise;
            0      34     1     p   Lscala/Function1;
            0      34     2 executor   Lscala/concurrent/ExecutionContext;
    Signature: #230                         // (Lscala/Function1<TT;Ljava/lang/Object;>;Lscala/concurrent/ExecutionContext;)Lscala/concurrent/Future<TT;>;
    MethodParameters:
      Name                           Flags
      p                              final
      executor                       final

  public final <S extends java.lang.Object> scala.concurrent.Future<S> collect(scala.PartialFunction<T, S>, scala.concurrent.ExecutionContext);
    descriptor: (Lscala/PartialFunction;Lscala/concurrent/ExecutionContext;)Lscala/concurrent/Future;
    flags: (0x0011) ACC_PUBLIC, ACC_FINAL
    Code:
      stack=7, locals=4, args_size=3
         0: aload_0
         1: invokevirtual #312                // Method get:()Ljava/lang/Object;
         4: astore_3
         5: aload_3
         6: instanceof    #404                // class scala/util/Failure
         9: ifne          32
        12: aload_0
        13: aload_3
        14: new           #41                 // class scala/concurrent/impl/Promise$Transformation
        17: dup
        18: bipush        10
        20: aload_1
        21: aload_2
        22: invokespecial #324                // Method scala/concurrent/impl/Promise$Transformation."<init>":(ILscala/Function1;Lscala/concurrent/ExecutionContext;)V
        25: invokespecial #328                // Method dispatchOrAddCallbacks:(Ljava/lang/Object;Lscala/concurrent/impl/Promise$Callbacks;)Lscala/concurrent/impl/Promise$Callbacks;
        28: checkcast     #9                  // class scala/concurrent/Future
        31: areturn
        32: aload_0
        33: areturn
      StackMapTable: number_of_entries = 1
        frame_type = 252 /* append */
          offset_delta = 32
          locals = [ class java/lang/Object ]
      LineNumberTable:
        line 193: 0
        line 194: 5
        line 195: 32
      LocalVariableTable:
        Start  Length  Slot  Name   Signature
            5      28     3 state   Ljava/lang/Object;
            0      34     0  this   Lscala/concurrent/impl/Promise$DefaultPromise;
            0      34     1    pf   Lscala/PartialFunction;
            0      34     2 executor   Lscala/concurrent/ExecutionContext;
    Signature: #410                         // <S:Ljava/lang/Object;>(Lscala/PartialFunction<TT;TS;>;Lscala/concurrent/ExecutionContext;)Lscala/concurrent/Future<TS;>;
    MethodParameters:
      Name                           Flags
      pf                             final
      executor                       final

  public final <U extends java.lang.Object> scala.concurrent.Future<U> recoverWith(scala.PartialFunction<java.lang.Throwable, scala.concurrent.Future<U>>, scala.concurrent.ExecutionContext);
    descriptor: (Lscala/PartialFunction;Lscala/concurrent/ExecutionContext;)Lscala/concurrent/Future;
    flags: (0x0011) ACC_PUBLIC, ACC_FINAL
    Code:
      stack=7, locals=4, args_size=3
         0: aload_0
         1: invokevirtual #312                // Method get:()Ljava/lang/Object;
         4: astore_3
         5: aload_3
         6: instanceof    #341                // class scala/util/Success
         9: ifne          32
        12: aload_0
        13: aload_3
        14: new           #41                 // class scala/concurrent/impl/Promise$Transformation
        17: dup
        18: bipush        8
        20: aload_1
        21: aload_2
        22: invokespecial #324                // Method scala/concurrent/impl/Promise$Transformation."<init>":(ILscala/Function1;Lscala/concurrent/ExecutionContext;)V
        25: invokespecial #328                // Method dispatchOrAddCallbacks:(Ljava/lang/Object;Lscala/concurrent/impl/Promise$Callbacks;)Lscala/concurrent/impl/Promise$Callbacks;
        28: checkcast     #9                  // class scala/concurrent/Future
        31: areturn
        32: aload_0
        33: areturn
      StackMapTable: number_of_entries = 1
        frame_type = 252 /* append */
          offset_delta = 32
          locals = [ class java/lang/Object ]
      LineNumberTable:
        line 199: 0
        line 200: 5
        line 201: 32
      LocalVariableTable:
        Start  Length  Slot  Name   Signature
            5      28     3 state   Ljava/lang/Object;
            0      34     0  this   Lscala/concurrent/impl/Promise$DefaultPromise;
            0      34     1    pf   Lscala/PartialFunction;
            0      34     2 executor   Lscala/concurrent/ExecutionContext;
    Signature: #412                         // <U:Ljava/lang/Object;>(Lscala/PartialFunction<Ljava/lang/Throwable;Lscala/concurrent/Future<TU;>;>;Lscala/concurrent/ExecutionContext;)Lscala/concurrent/Future<TU;>;
    MethodParameters:
      Name                           Flags
      pf                             final
      executor                       final

  public final <U extends java.lang.Object> scala.concurrent.Future<U> recover(scala.PartialFunction<java.lang.Throwable, U>, scala.concurrent.ExecutionContext);
    descriptor: (Lscala/PartialFunction;Lscala/concurrent/ExecutionContext;)Lscala/concurrent/Future;
    flags: (0x0011) ACC_PUBLIC, ACC_FINAL
    Code:
      stack=7, locals=4, args_size=3
         0: aload_0
         1: invokevirtual #312                // Method get:()Ljava/lang/Object;
         4: astore_3
         5: aload_3
         6: instanceof    #341                // class scala/util/Success
         9: ifne          32
        12: aload_0
        13: aload_3
        14: new           #41                 // class scala/concurrent/impl/Promise$Transformation
        17: dup
        18: bipush        7
        20: aload_1
        21: aload_2
        22: invokespecial #324                // Method scala/concurrent/impl/Promise$Transformation."<init>":(ILscala/Function1;Lscala/concurrent/ExecutionContext;)V
        25: invokespecial #328                // Method dispatchOrAddCallbacks:(Ljava/lang/Object;Lscala/concurrent/impl/Promise$Callbacks;)Lscala/concurrent/impl/Promise$Callbacks;
        28: checkcast     #9                  // class scala/concurrent/Future
        31: areturn
        32: aload_0
        33: areturn
      StackMapTable: number_of_entries = 1
        frame_type = 252 /* append */
          offset_delta = 32
          locals = [ class java/lang/Object ]
      LineNumberTable:
        line 205: 0
        line 206: 5
        line 207: 32
      LocalVariableTable:
        Start  Length  Slot  Name   Signature
            5      28     3 state   Ljava/lang/Object;
            0      34     0  this   Lscala/concurrent/impl/Promise$DefaultPromise;
            0      34     1    pf   Lscala/PartialFunction;
            0      34     2 executor   Lscala/concurrent/ExecutionContext;
    Signature: #414                         // <U:Ljava/lang/Object;>(Lscala/PartialFunction<Ljava/lang/Throwable;TU;>;Lscala/concurrent/ExecutionContext;)Lscala/concurrent/Future<TU;>;
    MethodParameters:
      Name                           Flags
      pf                             final
      executor                       final

  public final <S extends java.lang.Object> scala.concurrent.Future<S> mapTo(scala.reflect.ClassTag<S>);
    descriptor: (Lscala/reflect/ClassTag;)Lscala/concurrent/Future;
    flags: (0x0011) ACC_PUBLIC, ACC_FINAL
    Code:
      stack=2, locals=2, args_size=2
         0: aload_0
         1: invokevirtual #312                // Method get:()Ljava/lang/Object;
         4: instanceof    #404                // class scala/util/Failure
         7: ifne          16
        10: aload_0
        11: aload_1
        12: invokestatic  #422                // InterfaceMethod scala/concurrent/Future.mapTo$:(Lscala/concurrent/Future;Lscala/reflect/ClassTag;)Lscala/concurrent/Future;
        15: areturn
        16: aload_0
        17: areturn
      StackMapTable: number_of_entries = 1
        frame_type = 16 /* same */
      LineNumberTable:
        line 211: 0
        line 212: 16
      LocalVariableTable:
        Start  Length  Slot  Name   Signature
            0      18     0  this   Lscala/concurrent/impl/Promise$DefaultPromise;
            0      18     1   tag   Lscala/reflect/ClassTag;
    Signature: #417                         // <S:Ljava/lang/Object;>(Lscala/reflect/ClassTag<TS;>;)Lscala/concurrent/Future<TS;>;
    MethodParameters:
      Name                           Flags
      tag                            final

  public final <U extends java.lang.Object> void onComplete(scala.Function1<scala.util.Try<T>, U>, scala.concurrent.ExecutionContext);
    descriptor: (Lscala/Function1;Lscala/concurrent/ExecutionContext;)V
    flags: (0x0011) ACC_PUBLIC, ACC_FINAL
    Code:
      stack=7, locals=3, args_size=3
         0: aload_0
         1: aload_0
         2: invokevirtual #312                // Method get:()Ljava/lang/Object;
         5: new           #41                 // class scala/concurrent/impl/Promise$Transformation
         8: dup
         9: bipush        6
        11: aload_1
        12: aload_2
        13: invokespecial #324                // Method scala/concurrent/impl/Promise$Transformation."<init>":(ILscala/Function1;Lscala/concurrent/ExecutionContext;)V
        16: invokespecial #328                // Method dispatchOrAddCallbacks:(Ljava/lang/Object;Lscala/concurrent/impl/Promise$Callbacks;)Lscala/concurrent/impl/Promise$Callbacks;
        19: pop
        20: return
      LineNumberTable:
        line 216: 0
      LocalVariableTable:
        Start  Length  Slot  Name   Signature
            0      21     0  this   Lscala/concurrent/impl/Promise$DefaultPromise;
            0      21     1  func   Lscala/Function1;
            0      21     2 executor   Lscala/concurrent/ExecutionContext;
    Signature: #424                         // <U:Ljava/lang/Object;>(Lscala/Function1<Lscala/util/Try<TT;>;TU;>;Lscala/concurrent/ExecutionContext;)V
    MethodParameters:
      Name                           Flags
      func                           final
      executor                       final

  public final scala.concurrent.Future<java.lang.Throwable> failed();
    descriptor: ()Lscala/concurrent/Future;
    flags: (0x0011) ACC_PUBLIC, ACC_FINAL
    Code:
      stack=1, locals=1, args_size=1
         0: aload_0
         1: invokevirtual #312                // Method get:()Ljava/lang/Object;
         4: instanceof    #341                // class scala/util/Success
         7: ifne          15
        10: aload_0
        11: invokestatic  #430                // InterfaceMethod scala/concurrent/Future.failed$:(Lscala/concurrent/Future;)Lscala/concurrent/Future;
        14: areturn
        15: getstatic     #436                // Field scala/concurrent/Future$.MODULE$:Lscala/concurrent/Future$;
        18: invokevirtual #439                // Method scala/concurrent/Future$.failedFailureFuture:()Lscala/concurrent/Future;
        21: areturn
      StackMapTable: number_of_entries = 1
        frame_type = 15 /* same */
      LineNumberTable:
        line 219: 0
        line 220: 15
      LocalVariableTable:
        Start  Length  Slot  Name   Signature
            0      22     0  this   Lscala/concurrent/impl/Promise$DefaultPromise;
    Signature: #427                         // ()Lscala/concurrent/Future<Ljava/lang/Throwable;>;

  public final java.lang.String toString();
    descriptor: ()Ljava/lang/String;
    flags: (0x0011) ACC_PUBLIC, ACC_FINAL
    Code:
      stack=3, locals=2, args_size=1
         0: aload_0
         1: invokevirtual #312                // Method get:()Ljava/lang/Object;
         4: astore_1
         5: aload_1
         6: instanceof    #335                // class scala/util/Try
         9: ifeq          42
        12: new           #443                // class java/lang/StringBuilder
        15: dup
        16: ldc_w         #444                // int 8
        19: invokespecial #446                // Method java/lang/StringBuilder."<init>":(I)V
        22: ldc_w         #448                // String Future(
        25: invokevirtual #452                // Method java/lang/StringBuilder.append:(Ljava/lang/String;)Ljava/lang/StringBuilder;
        28: aload_1
        29: invokevirtual #455                // Method java/lang/StringBuilder.append:(Ljava/lang/Object;)Ljava/lang/StringBuilder;
        32: ldc_w         #457                // String )
        35: invokevirtual #452                // Method java/lang/StringBuilder.append:(Ljava/lang/String;)Ljava/lang/StringBuilder;
        38: invokevirtual #459                // Method java/lang/StringBuilder.toString:()Ljava/lang/String;
        41: areturn
        42: aload_1
        43: instanceof    #35                 // class scala/concurrent/impl/Promise$Link
        46: ifeq          61
        49: aload_1
        50: checkcast     #35                 // class scala/concurrent/impl/Promise$Link
        53: aload_0
        54: invokevirtual #463                // Method scala/concurrent/impl/Promise$Link.promise:(Lscala/concurrent/impl/Promise$DefaultPromise;)Lscala/concurrent/impl/Promise$DefaultPromise;
        57: astore_0
        58: goto          0
        61: ldc_w         #465                // String Future(<not completed>)
        64: areturn
      StackMapTable: number_of_entries = 3
        frame_type = 0 /* same */
        frame_type = 252 /* append */
          offset_delta = 41
          locals = [ class java/lang/Object ]
        frame_type = 18 /* same */
      LineNumberTable:
        line 223: 0
        line 224: 5
        line 225: 42
        line 226: 61
      LocalVariableTable:
        Start  Length  Slot  Name   Signature
            5      59     1 state   Ljava/lang/Object;
            0      65     0  this   Lscala/concurrent/impl/Promise$DefaultPromise;

  private final scala.util.Try<T> tryAwait0(scala.concurrent.duration.Duration);
    descriptor: (Lscala/concurrent/duration/Duration;)Lscala/util/Try;
    flags: (0x0012) ACC_PRIVATE, ACC_FINAL
    Code:
      stack=5, locals=5, args_size=2
         0: aload_1
         1: getstatic     #474                // Field scala/concurrent/duration/Duration$.MODULE$:Lscala/concurrent/duration/Duration$;
         4: invokevirtual #478                // Method scala/concurrent/duration/Duration$.Undefined:()Lscala/concurrent/duration/Duration$Infinite;
         7: if_acmpeq     132
        10: aload_0
        11: invokespecial #482                // Method value0:()Lscala/util/Try;
        14: astore_2
        15: aload_2
        16: ifnull        21
        19: aload_2
        20: areturn
        21: aload_1
        22: getstatic     #474                // Field scala/concurrent/duration/Duration$.MODULE$:Lscala/concurrent/duration/Duration$;
        25: invokevirtual #486                // Method scala/concurrent/duration/Duration$.Zero:()Lscala/concurrent/duration/FiniteDuration;
        28: invokevirtual #489                // Method scala/concurrent/duration/Duration.$less$eq:(Ljava/lang/Object;)Z
        31: ifeq          38
        34: aconst_null
        35: goto          88
        38: new           #491                // class scala/concurrent/impl/CompletionLatch
        41: dup
        42: invokespecial #492                // Method scala/concurrent/impl/CompletionLatch."<init>":()V
        45: astore        4
        47: aload_0
        48: aload         4
        50: getstatic     #495                // Field scala/concurrent/ExecutionContext$parasitic$.MODULE$:Lscala/concurrent/ExecutionContext$parasitic$;
        53: invokevirtual #496                // Method onComplete:(Lscala/Function1;Lscala/concurrent/ExecutionContext;)V
        56: aload_1
        57: invokevirtual #499                // Method scala/concurrent/duration/Duration.isFinite:()Z
        60: ifeq          77
        63: aload         4
        65: iconst_1
        66: aload_1
        67: invokevirtual #503                // Method scala/concurrent/duration/Duration.toNanos:()J
        70: invokevirtual #507                // Method scala/concurrent/impl/CompletionLatch.tryAcquireSharedNanos:(IJ)Z
        73: pop
        74: goto          83
        77: aload         4
        79: iconst_1
        80: invokevirtual #510                // Method scala/concurrent/impl/CompletionLatch.acquireSharedInterruptibly:(I)V
        83: aload         4
        85: invokevirtual #512                // Method scala/concurrent/impl/CompletionLatch.result:()Lscala/util/Try;
        88: astore_3
        89: aload_3
        90: ifnull        95
        93: aload_3
        94: areturn
        95: new           #514                // class java/util/concurrent/TimeoutException
        98: dup
        99: new           #443                // class java/lang/StringBuilder
       102: dup
       103: ldc_w         #515                // int 25
       106: invokespecial #446                // Method java/lang/StringBuilder."<init>":(I)V
       109: ldc_w         #517                // String Future timed out after [
       112: invokevirtual #452                // Method java/lang/StringBuilder.append:(Ljava/lang/String;)Ljava/lang/StringBuilder;
       115: aload_1
       116: invokevirtual #455                // Method java/lang/StringBuilder.append:(Ljava/lang/Object;)Ljava/lang/StringBuilder;
       119: ldc_w         #519                // String ]
       122: invokevirtual #452                // Method java/lang/StringBuilder.append:(Ljava/lang/String;)Ljava/lang/StringBuilder;
       125: invokevirtual #459                // Method java/lang/StringBuilder.toString:()Ljava/lang/String;
       128: invokespecial #522                // Method java/util/concurrent/TimeoutException."<init>":(Ljava/lang/String;)V
       131: athrow
       132: new           #524                // class java/lang/IllegalArgumentException
       135: dup
       136: ldc_w         #526                // String Cannot wait for Undefined duration of time
       139: invokespecial #527                // Method java/lang/IllegalArgumentException."<init>":(Ljava/lang/String;)V
       142: athrow
      StackMapTable: number_of_entries = 7
        frame_type = 252 /* append */
          offset_delta = 21
          locals = [ class scala/util/Try ]
        frame_type = 16 /* same */
        frame_type = 253 /* append */
          offset_delta = 38
          locals = [ top, class scala/concurrent/impl/CompletionLatch ]
        frame_type = 5 /* same */
        frame_type = 255 /* full_frame */
          offset_delta = 4
          locals = [ class scala/concurrent/impl/Promise$DefaultPromise, class scala/concurrent/duration/Duration, class scala/util/Try ]
          stack = [ class scala/util/Try ]
        frame_type = 252 /* append */
          offset_delta = 6
          locals = [ class scala/util/Try ]
        frame_type = 249 /* chop */
          offset_delta = 36
      LineNumberTable:
        line 230: 0
        line 231: 10
        line 232: 15
        line 235: 21
        line 237: 38
        line 238: 47
        line 240: 56
        line 241: 63
        line 243: 77
        line 245: 83
        line 247: 89
        line 248: 95
        line 250: 132
      LocalVariableTable:
        Start  Length  Slot  Name   Signature
           47      41     4     l   Lscala/concurrent/impl/CompletionLatch;
           89      43     3     r   Lscala/util/Try;
           15     117     2     v   Lscala/util/Try;
            0     143     0  this   Lscala/concurrent/impl/Promise$DefaultPromise;
            0     143     1 atMost   Lscala/concurrent/duration/Duration;
    Signature: #468                         // (Lscala/concurrent/duration/Duration;)Lscala/util/Try<TT;>;
    MethodParameters:
      Name                           Flags
      atMost                         final

  public final scala.concurrent.impl.Promise$DefaultPromise<T> ready(scala.concurrent.duration.Duration, scala.concurrent.CanAwait) throws java/util/concurrent/TimeoutException, java/lang/InterruptedException;
    descriptor: (Lscala/concurrent/duration/Duration;Lscala/concurrent/CanAwait;)Lscala/concurrent/impl/Promise$DefaultPromise;
    flags: (0x0011) ACC_PUBLIC, ACC_FINAL
    Code:
      stack=2, locals=3, args_size=3
         0: aload_0
         1: aload_1
         2: invokespecial #539                // Method tryAwait0:(Lscala/concurrent/duration/Duration;)Lscala/util/Try;
         5: pop
         6: aload_0
         7: areturn
      LineNumberTable:
        line 255: 0
        line 256: 6
      LocalVariableTable:
        Start  Length  Slot  Name   Signature
            0       8     0  this   Lscala/concurrent/impl/Promise$DefaultPromise;
            0       8     1 atMost   Lscala/concurrent/duration/Duration;
            0       8     2 permit   Lscala/concurrent/CanAwait;
    Exceptions:
      throws java.util.concurrent.TimeoutException, java.lang.InterruptedException
    Signature: #534                         // (Lscala/concurrent/duration/Duration;Lscala/concurrent/CanAwait;)Lscala/concurrent/impl/Promise$DefaultPromise<TT;>;^Ljava/util/concurrent/TimeoutException;^Ljava/lang/InterruptedException;
    MethodParameters:
      Name                           Flags
      atMost                         final
      permit                         final

  public final T result(scala.concurrent.duration.Duration, scala.concurrent.CanAwait) throws java/lang/Exception;
    descriptor: (Lscala/concurrent/duration/Duration;Lscala/concurrent/CanAwait;)Ljava/lang/Object;
    flags: (0x0011) ACC_PUBLIC, ACC_FINAL
    Code:
      stack=2, locals=3, args_size=3
         0: aload_0
         1: aload_1
         2: invokespecial #539                // Method tryAwait0:(Lscala/concurrent/duration/Duration;)Lscala/util/Try;
         5: invokevirtual #545                // Method scala/util/Try.get:()Ljava/lang/Object;
         8: areturn
      LineNumberTable:
        line 261: 0
      LocalVariableTable:
        Start  Length  Slot  Name   Signature
            0       9     0  this   Lscala/concurrent/impl/Promise$DefaultPromise;
            0       9     1 atMost   Lscala/concurrent/duration/Duration;
            0       9     2 permit   Lscala/concurrent/CanAwait;
    Exceptions:
      throws java.lang.Exception
    Signature: #542                         // (Lscala/concurrent/duration/Duration;Lscala/concurrent/CanAwait;)TT;^Ljava/lang/Exception;
    MethodParameters:
      Name                           Flags
      atMost                         final
      permit                         final

  public final boolean isCompleted();
    descriptor: ()Z
    flags: (0x0011) ACC_PUBLIC, ACC_FINAL
    Code:
      stack=1, locals=1, args_size=1
         0: aload_0
         1: invokespecial #482                // Method value0:()Lscala/util/Try;
         4: ifnull        9
         7: iconst_1
         8: ireturn
         9: iconst_0
        10: ireturn
      StackMapTable: number_of_entries = 1
        frame_type = 9 /* same */
      LineNumberTable:
        line 263: 0
      LocalVariableTable:
        Start  Length  Slot  Name   Signature
            0      11     0  this   Lscala/concurrent/impl/Promise$DefaultPromise;

  public final scala.Option<scala.util.Try<T>> value();
    descriptor: ()Lscala/Option;
    flags: (0x0011) ACC_PUBLIC, ACC_FINAL
    Code:
      stack=2, locals=1, args_size=1
         0: getstatic     #553                // Field scala/Option$.MODULE$:Lscala/Option$;
         3: aload_0
         4: invokespecial #482                // Method value0:()Lscala/util/Try;
         7: invokevirtual #556                // Method scala/Option$.apply:(Ljava/lang/Object;)Lscala/Option;
        10: areturn
      LineNumberTable:
        line 265: 0
      LocalVariableTable:
        Start  Length  Slot  Name   Signature
            0      11     0  this   Lscala/concurrent/impl/Promise$DefaultPromise;
    Signature: #548                         // ()Lscala/Option<Lscala/util/Try<TT;>;>;

  private final scala.util.Try<T> value0();
    descriptor: ()Lscala/util/Try;
    flags: (0x0012) ACC_PRIVATE, ACC_FINAL
    Code:
      stack=2, locals=2, args_size=1
         0: aload_0
         1: invokevirtual #312                // Method get:()Ljava/lang/Object;
         4: astore_1
         5: aload_1
         6: instanceof    #335                // class scala/util/Try
         9: ifeq          17
        12: aload_1
        13: checkcast     #335                // class scala/util/Try
        16: areturn
        17: aload_1
        18: instanceof    #35                 // class scala/concurrent/impl/Promise$Link
        21: ifeq          36
        24: aload_1
        25: checkcast     #35                 // class scala/concurrent/impl/Promise$Link
        28: aload_0
        29: invokevirtual #463                // Method scala/concurrent/impl/Promise$Link.promise:(Lscala/concurrent/impl/Promise$DefaultPromise;)Lscala/concurrent/impl/Promise$DefaultPromise;
        32: astore_0
        33: goto          0
        36: aconst_null
        37: areturn
      StackMapTable: number_of_entries = 3
        frame_type = 0 /* same */
        frame_type = 252 /* append */
          offset_delta = 16
          locals = [ class java/lang/Object ]
        frame_type = 18 /* same */
      LineNumberTable:
        line 269: 0
        line 270: 5
        line 271: 17
        line 272: 36
      LocalVariableTable:
        Start  Length  Slot  Name   Signature
            5      32     1 state   Ljava/lang/Object;
            0      38     0  this   Lscala/concurrent/impl/Promise$DefaultPromise;
    Signature: #557                         // ()Lscala/util/Try<TT;>;

  public final boolean tryComplete(scala.util.Try<T>);
    descriptor: (Lscala/util/Try;)Z
    flags: (0x0011) ACC_PUBLIC, ACC_FINAL
    Code:
      stack=4, locals=3, args_size=2
         0: aload_0
         1: invokevirtual #312                // Method get:()Ljava/lang/Object;
         4: astore_2
         5: aload_2
         6: instanceof    #335                // class scala/util/Try
         9: ifeq          14
        12: iconst_0
        13: ireturn
        14: aload_0
        15: aload_2
        16: getstatic     #565                // Field scala/concurrent/impl/Promise$.MODULE$:Lscala/concurrent/impl/Promise$;
        19: aload_1
        20: invokevirtual #569                // Method scala/concurrent/impl/Promise$.scala$concurrent$impl$Promise$$resolve:(Lscala/util/Try;)Lscala/util/Try;
        23: invokevirtual #316                // Method tryComplete0:(Ljava/lang/Object;Lscala/util/Try;)Z
        26: ireturn
      StackMapTable: number_of_entries = 1
        frame_type = 252 /* append */
          offset_delta = 14
          locals = [ class java/lang/Object ]
      LineNumberTable:
        line 276: 0
        line 277: 5
        line 278: 14
      LocalVariableTable:
        Start  Length  Slot  Name   Signature
            5      21     2 state   Ljava/lang/Object;
            0      27     0  this   Lscala/concurrent/impl/Promise$DefaultPromise;
            0      27     1 value   Lscala/util/Try;
    Signature: #560                         // (Lscala/util/Try<TT;>;)Z
    MethodParameters:
      Name                           Flags
      value                          final

  public final boolean tryComplete0(java.lang.Object, scala.util.Try<T>);
    descriptor: (Ljava/lang/Object;Lscala/util/Try;)Z
    flags: (0x0011) ACC_PUBLIC, ACC_FINAL
    Code:
      stack=3, locals=4, args_size=3
         0: aload_1
         1: instanceof    #29                 // class scala/concurrent/impl/Promise$Callbacks
         4: ifeq          44
         7: aload_0
         8: aload_1
         9: aload_2
        10: invokevirtual #574                // Method compareAndSet:(Ljava/lang/Object;Ljava/lang/Object;)Z
        13: ifeq          34
        16: aload_1
        17: getstatic     #578                // Field scala/concurrent/impl/Promise$.scala$concurrent$impl$Promise$$Noop:Lscala/concurrent/impl/Promise$Transformation;
        20: if_acmpeq     32
        23: aload_0
        24: aload_1
        25: checkcast     #29                 // class scala/concurrent/impl/Promise$Callbacks
        28: aload_2
        29: invokespecial #582                // Method submitWithValue:(Lscala/concurrent/impl/Promise$Callbacks;Lscala/util/Try;)V
        32: iconst_1
        33: ireturn
        34: aload_0
        35: invokevirtual #312                // Method get:()Ljava/lang/Object;
        38: aload_2
        39: astore_2
        40: astore_1
        41: goto          0
        44: aload_1
        45: instanceof    #35                 // class scala/concurrent/impl/Promise$Link
        48: ifeq          79
        51: aload_1
        52: checkcast     #35                 // class scala/concurrent/impl/Promise$Link
        55: aload_0
        56: invokevirtual #463                // Method scala/concurrent/impl/Promise$Link.promise:(Lscala/concurrent/impl/Promise$DefaultPromise;)Lscala/concurrent/impl/Promise$DefaultPromise;
        59: astore_3
        60: aload_3
        61: aload_0
        62: if_acmpeq     77
        65: aload_3
        66: aload_3
        67: invokevirtual #312                // Method get:()Ljava/lang/Object;
        70: aload_2
        71: astore_2
        72: astore_1
        73: astore_0
        74: goto          0
        77: iconst_0
        78: ireturn
        79: iconst_0
        80: ireturn
      StackMapTable: number_of_entries = 6
        frame_type = 0 /* same */
        frame_type = 31 /* same */
        frame_type = 1 /* same */
        frame_type = 9 /* same */
        frame_type = 252 /* append */
          offset_delta = 32
          locals = [ class scala/concurrent/impl/Promise$DefaultPromise ]
        frame_type = 250 /* chop */
          offset_delta = 1
      LineNumberTable:
        line 283: 0
        line 284: 7
        line 285: 16
        line 286: 32
        line 287: 34
        line 288: 44
        line 289: 51
        line 290: 60
        line 291: 79
      LocalVariableTable:
        Start  Length  Slot  Name   Signature
           60      18     3     p   Lscala/concurrent/impl/Promise$DefaultPromise;
            0      81     0  this   Lscala/concurrent/impl/Promise$DefaultPromise;
            0      81     1 state   Ljava/lang/Object;
            0      81     2 resolved   Lscala/util/Try;
    Signature: #570                         // (Ljava/lang/Object;Lscala/util/Try<TT;>;)Z
    MethodParameters:
      Name                           Flags
      state                          final
      resolved                       final

  public final scala.concurrent.impl.Promise$DefaultPromise<T> completeWith(scala.concurrent.Future<T>);
    descriptor: (Lscala/concurrent/Future;)Lscala/concurrent/impl/Promise$DefaultPromise;
    flags: (0x0011) ACC_PUBLIC, ACC_FINAL
    Code:
      stack=3, locals=6, args_size=2
         0: aload_1
         1: aload_0
         2: if_acmpeq     112
         5: aload_0
         6: invokevirtual #312                // Method get:()Ljava/lang/Object;
         9: astore_2
        10: aload_2
        11: instanceof    #335                // class scala/util/Try
        14: ifne          112
        17: aload_1
        18: instanceof    #2                  // class scala/concurrent/impl/Promise$DefaultPromise
        21: ifeq          34
        24: aload_1
        25: checkcast     #2                  // class scala/concurrent/impl/Promise$DefaultPromise
        28: invokespecial #482                // Method value0:()Lscala/util/Try;
        31: goto          87
        34: aload_1
        35: invokeinterface #587,  1          // InterfaceMethod scala/concurrent/Future.value:()Lscala/Option;
        40: getstatic     #592                // Field scala/$less$colon$less$.MODULE$:Lscala/$less$colon$less$;
        43: invokevirtual #596                // Method scala/$less$colon$less$.refl:()Lscala/$eq$colon$eq;
        46: astore        5
        48: dup
        49: ifnonnull     54
        52: aconst_null
        53: athrow
        54: astore        4
        56: aload         4
        58: invokevirtual #601                // Method scala/Option.isEmpty:()Z
        61: ifeq          73
        64: aload         5
        66: aconst_null
        67: invokevirtual #605                // Method scala/$less$colon$less.apply:(Ljava/lang/Object;)Ljava/lang/Object;
        70: goto          78
        73: aload         4
        75: invokevirtual #606                // Method scala/Option.get:()Ljava/lang/Object;
        78: aconst_null
        79: astore        4
        81: aconst_null
        82: astore        5
        84: checkcast     #335                // class scala/util/Try
        87: astore_3
        88: aload_3
        89: ifnull        102
        92: aload_0
        93: aload_2
        94: aload_3
        95: invokevirtual #316                // Method tryComplete0:(Ljava/lang/Object;Lscala/util/Try;)Z
        98: pop
        99: goto          112
       102: aload_1
       103: aload_0
       104: getstatic     #495                // Field scala/concurrent/ExecutionContext$parasitic$.MODULE$:Lscala/concurrent/ExecutionContext$parasitic$;
       107: invokeinterface #388,  3          // InterfaceMethod scala/concurrent/Future.onComplete:(Lscala/Function1;Lscala/concurrent/ExecutionContext;)V
       112: aload_0
       113: areturn
      StackMapTable: number_of_entries = 7
        frame_type = 252 /* append */
          offset_delta = 34
          locals = [ class java/lang/Object ]
        frame_type = 255 /* full_frame */
          offset_delta = 19
          locals = [ class scala/concurrent/impl/Promise$DefaultPromise, class scala/concurrent/Future, class java/lang/Object, top, top, class scala/$eq$colon$eq ]
          stack = [ class scala/Option ]
        frame_type = 255 /* full_frame */
          offset_delta = 18
          locals = [ class scala/concurrent/impl/Promise$DefaultPromise, class scala/concurrent/Future, class java/lang/Object, top, class scala/Option, class scala/$eq$colon$eq ]
          stack = []
        frame_type = 68 /* same_locals_1_stack_item */
          stack = [ class java/lang/Object ]
        frame_type = 255 /* full_frame */
          offset_delta = 8
          locals = [ class scala/concurrent/impl/Promise$DefaultPromise, class scala/concurrent/Future, class java/lang/Object ]
          stack = [ class scala/util/Try ]
        frame_type = 252 /* append */
          offset_delta = 14
          locals = [ class scala/util/Try ]
        frame_type = 249 /* chop */
          offset_delta = 9
      LineNumberTable:
        line 294: 0
        line 295: 5
        line 296: 10
        line 297: 17
        line 298: 88
        line 299: 102
        line 303: 112
      LocalVariableTable:
        Start  Length  Slot  Name   Signature
           88      24     3 resolved   Lscala/util/Try;
           10     102     2 state   Ljava/lang/Object;
            0     114     0  this   Lscala/concurrent/impl/Promise$DefaultPromise;
            0     114     1 other   Lscala/concurrent/Future;
           56      22     4 orNull_this   Lscala/Option;
           56      22     5 orNull_ev   Lscala/$less$colon$less;
    Signature: #585                         // (Lscala/concurrent/Future<TT;>;)Lscala/concurrent/impl/Promise$DefaultPromise<TT;>;
    MethodParameters:
      Name                           Flags
      other                          final

  private final <C extends scala.concurrent.impl.Promise$Callbacks<T>> C dispatchOrAddCallbacks(java.lang.Object, C);
    descriptor: (Ljava/lang/Object;Lscala/concurrent/impl/Promise$Callbacks;)Lscala/concurrent/impl/Promise$Callbacks;
    flags: (0x0012) ACC_PRIVATE, ACC_FINAL
    Code:
      stack=5, locals=4, args_size=3
         0: aload_1
         1: instanceof    #335                // class scala/util/Try
         4: ifeq          18
         7: aload_0
         8: aload_2
         9: aload_1
        10: checkcast     #335                // class scala/util/Try
        13: invokespecial #582                // Method submitWithValue:(Lscala/concurrent/impl/Promise$Callbacks;Lscala/util/Try;)V
        16: aload_2
        17: areturn
        18: aload_1
        19: instanceof    #29                 // class scala/concurrent/impl/Promise$Callbacks
        22: ifeq          65
        25: aload_0
        26: aload_1
        27: aload_1
        28: getstatic     #578                // Field scala/concurrent/impl/Promise$.scala$concurrent$impl$Promise$$Noop:Lscala/concurrent/impl/Promise$Transformation;
        31: if_acmpeq     46
        34: aload_0
        35: aload_2
        36: aload_1
        37: checkcast     #29                 // class scala/concurrent/impl/Promise$Callbacks
        40: invokespecial #617                // Method concatCallbacks:(Lscala/concurrent/impl/Promise$Callbacks;Lscala/concurrent/impl/Promise$Callbacks;)Lscala/concurrent/impl/Promise$Callbacks;
        43: goto          47
        46: aload_2
        47: invokevirtual #574                // Method compareAndSet:(Ljava/lang/Object;Ljava/lang/Object;)Z
        50: ifeq          55
        53: aload_2
        54: areturn
        55: aload_0
        56: invokevirtual #312                // Method get:()Ljava/lang/Object;
        59: aload_2
        60: astore_2
        61: astore_1
        62: goto          0
        65: aload_1
        66: checkcast     #35                 // class scala/concurrent/impl/Promise$Link
        69: aload_0
        70: invokevirtual #463                // Method scala/concurrent/impl/Promise$Link.promise:(Lscala/concurrent/impl/Promise$DefaultPromise;)Lscala/concurrent/impl/Promise$DefaultPromise;
        73: astore_3
        74: aload_3
        75: aload_3
        76: invokevirtual #312                // Method get:()Ljava/lang/Object;
        79: aload_2
        80: astore_2
        81: astore_1
        82: astore_0
        83: goto          0
      StackMapTable: number_of_entries = 6
        frame_type = 0 /* same */
        frame_type = 17 /* same */
        frame_type = 255 /* full_frame */
          offset_delta = 27
          locals = [ class scala/concurrent/impl/Promise$DefaultPromise, class java/lang/Object, class scala/concurrent/impl/Promise$Callbacks ]
          stack = [ class scala/concurrent/impl/Promise$DefaultPromise, class java/lang/Object ]
        frame_type = 255 /* full_frame */
          offset_delta = 0
          locals = [ class scala/concurrent/impl/Promise$DefaultPromise, class java/lang/Object, class scala/concurrent/impl/Promise$Callbacks ]
          stack = [ class scala/concurrent/impl/Promise$DefaultPromise, class java/lang/Object, class scala/concurrent/impl/Promise$Callbacks ]
        frame_type = 7 /* same */
        frame_type = 9 /* same */
      LineNumberTable:
        line 311: 0
        line 312: 7
        line 313: 16
        line 314: 18
        line 315: 25
        line 316: 55
        line 318: 65
        line 319: 74
      LocalVariableTable:
        Start  Length  Slot  Name   Signature
           74      12     3     p   Lscala/concurrent/impl/Promise$DefaultPromise;
            0      86     0  this   Lscala/concurrent/impl/Promise$DefaultPromise;
            0      86     1 state   Ljava/lang/Object;
            0      86     2 callbacks   Lscala/concurrent/impl/Promise$Callbacks;
    Signature: #612                         // <C::Lscala/concurrent/impl/Promise$Callbacks<TT;>;>(Ljava/lang/Object;TC;)TC;
    MethodParameters:
      Name                           Flags
      state                          final
      callbacks                      final

  private final scala.concurrent.impl.Promise$Callbacks<T> concatCallbacks(scala.concurrent.impl.Promise$Callbacks<T>, scala.concurrent.impl.Promise$Callbacks<T>);
    descriptor: (Lscala/concurrent/impl/Promise$Callbacks;Lscala/concurrent/impl/Promise$Callbacks;)Lscala/concurrent/impl/Promise$Callbacks;
    flags: (0x0012) ACC_PRIVATE, ACC_FINAL
    Code:
      stack=5, locals=4, args_size=3
         0: aload_1
         1: instanceof    #41                 // class scala/concurrent/impl/Promise$Transformation
         4: ifeq          20
         7: new           #38                 // class scala/concurrent/impl/Promise$ManyCallbacks
        10: dup
        11: aload_1
        12: checkcast     #41                 // class scala/concurrent/impl/Promise$Transformation
        15: aload_2
        16: invokespecial #624                // Method scala/concurrent/impl/Promise$ManyCallbacks."<init>":(Lscala/concurrent/impl/Promise$Transformation;Lscala/concurrent/impl/Promise$Callbacks;)V
        19: areturn
        20: aload_1
        21: checkcast     #38                 // class scala/concurrent/impl/Promise$ManyCallbacks
        24: astore_3
        25: aload_3
        26: invokevirtual #628                // Method scala/concurrent/impl/Promise$ManyCallbacks.rest:()Lscala/concurrent/impl/Promise$Callbacks;
        29: new           #38                 // class scala/concurrent/impl/Promise$ManyCallbacks
        32: dup
        33: aload_3
        34: invokevirtual #632                // Method scala/concurrent/impl/Promise$ManyCallbacks.first:()Lscala/concurrent/impl/Promise$Transformation;
        37: aload_2
        38: invokespecial #624                // Method scala/concurrent/impl/Promise$ManyCallbacks."<init>":(Lscala/concurrent/impl/Promise$Transformation;Lscala/concurrent/impl/Promise$Callbacks;)V
        41: astore_2
        42: astore_1
        43: goto          0
      StackMapTable: number_of_entries = 2
        frame_type = 0 /* same */
        frame_type = 19 /* same */
      LineNumberTable:
        line 324: 0
        line 326: 20
        line 327: 25
      LocalVariableTable:
        Start  Length  Slot  Name   Signature
           25      21     3     m   Lscala/concurrent/impl/Promise$ManyCallbacks;
            0      46     0  this   Lscala/concurrent/impl/Promise$DefaultPromise;
            0      46     1  left   Lscala/concurrent/impl/Promise$Callbacks;
            0      46     2 right   Lscala/concurrent/impl/Promise$Callbacks;
    Signature: #619                         // (Lscala/concurrent/impl/Promise$Callbacks<TT;>;Lscala/concurrent/impl/Promise$Callbacks<TT;>;)Lscala/concurrent/impl/Promise$Callbacks<TT;>;
    MethodParameters:
      Name                           Flags
      left                           final
      right                          final

  private final void submitWithValue(scala.concurrent.impl.Promise$Callbacks<T>, scala.util.Try<T>);
    descriptor: (Lscala/concurrent/impl/Promise$Callbacks;Lscala/util/Try;)V
    flags: (0x0012) ACC_PRIVATE, ACC_FINAL
    Code:
      stack=2, locals=4, args_size=3
         0: aload_1
         1: instanceof    #38                 // class scala/concurrent/impl/Promise$ManyCallbacks
         4: ifeq          31
         7: aload_1
         8: checkcast     #38                 // class scala/concurrent/impl/Promise$ManyCallbacks
        11: astore_3
        12: aload_3
        13: invokevirtual #632                // Method scala/concurrent/impl/Promise$ManyCallbacks.first:()Lscala/concurrent/impl/Promise$Transformation;
        16: aload_2
        17: invokevirtual #638                // Method scala/concurrent/impl/Promise$Transformation.submitWithValue:(Lscala/util/Try;)Lscala/concurrent/impl/Promise$Transformation;
        20: pop
        21: aload_3
        22: invokevirtual #628                // Method scala/concurrent/impl/Promise$ManyCallbacks.rest:()Lscala/concurrent/impl/Promise$Callbacks;
        25: aload_2
        26: astore_2
        27: astore_1
        28: goto          0
        31: aload_1
        32: checkcast     #41                 // class scala/concurrent/impl/Promise$Transformation
        35: aload_2
        36: invokevirtual #638                // Method scala/concurrent/impl/Promise$Transformation.submitWithValue:(Lscala/util/Try;)Lscala/concurrent/impl/Promise$Transformation;
        39: pop
        40: return
      StackMapTable: number_of_entries = 2
        frame_type = 0 /* same */
        frame_type = 30 /* same */
      LineNumberTable:
        line 333: 0
        line 334: 7
        line 335: 12
        line 336: 21
        line 338: 31
        line 333: 40
      LocalVariableTable:
        Start  Length  Slot  Name   Signature
           12      19     3     m   Lscala/concurrent/impl/Promise$ManyCallbacks;
            0      41     0  this   Lscala/concurrent/impl/Promise$DefaultPromise;
            0      41     1 callbacks   Lscala/concurrent/impl/Promise$Callbacks;
            0      41     2 resolved   Lscala/util/Try;
    Signature: #635                         // (Lscala/concurrent/impl/Promise$Callbacks<TT;>;Lscala/util/Try<TT;>;)V
    MethodParameters:
      Name                           Flags
      callbacks                      final
      resolved                       final

  public final void linkRootOf(scala.concurrent.impl.Promise$DefaultPromise<T>, scala.concurrent.impl.Promise$Link<T>);
    descriptor: (Lscala/concurrent/impl/Promise$DefaultPromise;Lscala/concurrent/impl/Promise$Link;)V
    flags: (0x0011) ACC_PUBLIC, ACC_FINAL
    Code:
      stack=3, locals=6, args_size=3
         0: aload_0
         1: aload_1
         2: if_acmpeq     140
         5: aload_0
         6: invokevirtual #312                // Method get:()Ljava/lang/Object;
         9: astore_3
        10: aload_3
        11: instanceof    #335                // class scala/util/Try
        14: ifeq          43
        17: aload_1
        18: aload_1
        19: invokevirtual #312                // Method get:()Ljava/lang/Object;
        22: aload_3
        23: checkcast     #335                // class scala/util/Try
        26: invokevirtual #316                // Method tryComplete0:(Ljava/lang/Object;Lscala/util/Try;)Z
        29: ifne          140
        32: new           #645                // class java/lang/IllegalStateException
        35: dup
        36: ldc_w         #647                // String Cannot link completed promises together
        39: invokespecial #648                // Method java/lang/IllegalStateException."<init>":(Ljava/lang/String;)V
        42: athrow
        43: aload_3
        44: instanceof    #29                 // class scala/concurrent/impl/Promise$Callbacks
        47: ifeq          124
        50: aload_2
        51: ifnull        58
        54: aload_2
        55: goto          66
        58: new           #35                 // class scala/concurrent/impl/Promise$Link
        61: dup
        62: aload_1
        63: invokespecial #651                // Method scala/concurrent/impl/Promise$Link."<init>":(Lscala/concurrent/impl/Promise$DefaultPromise;)V
        66: astore        4
        68: aload         4
        70: aload_0
        71: invokevirtual #463                // Method scala/concurrent/impl/Promise$Link.promise:(Lscala/concurrent/impl/Promise$DefaultPromise;)Lscala/concurrent/impl/Promise$DefaultPromise;
        74: astore        5
        76: aload_0
        77: aload         5
        79: if_acmpeq     115
        82: aload_0
        83: aload_3
        84: aload         4
        86: invokevirtual #574                // Method compareAndSet:(Ljava/lang/Object;Ljava/lang/Object;)Z
        89: ifeq          115
        92: aload_3
        93: getstatic     #578                // Field scala/concurrent/impl/Promise$.scala$concurrent$impl$Promise$$Noop:Lscala/concurrent/impl/Promise$Transformation;
        96: if_acmpeq     140
        99: aload         5
       101: aload         5
       103: invokevirtual #312                // Method get:()Ljava/lang/Object;
       106: aload_3
       107: checkcast     #29                 // class scala/concurrent/impl/Promise$Callbacks
       110: invokespecial #328                // Method dispatchOrAddCallbacks:(Ljava/lang/Object;Lscala/concurrent/impl/Promise$Callbacks;)Lscala/concurrent/impl/Promise$Callbacks;
       113: pop
       114: return
       115: aload         5
       117: aload         4
       119: astore_2
       120: astore_1
       121: goto          0
       124: aload_3
       125: checkcast     #35                 // class scala/concurrent/impl/Promise$Link
       128: aload_0
       129: invokevirtual #463                // Method scala/concurrent/impl/Promise$Link.promise:(Lscala/concurrent/impl/Promise$DefaultPromise;)Lscala/concurrent/impl/Promise$DefaultPromise;
       132: aload_1
       133: aload_2
       134: astore_2
       135: astore_1
       136: astore_0
       137: goto          0
       140: return
      StackMapTable: number_of_entries = 7
        frame_type = 0 /* same */
        frame_type = 252 /* append */
          offset_delta = 42
          locals = [ class java/lang/Object ]
        frame_type = 14 /* same */
        frame_type = 71 /* same_locals_1_stack_item */
          stack = [ class scala/concurrent/impl/Promise$Link ]
        frame_type = 253 /* append */
          offset_delta = 48
          locals = [ class scala/concurrent/impl/Promise$Link, class scala/concurrent/impl/Promise$DefaultPromise ]
        frame_type = 249 /* chop */
          offset_delta = 8
        frame_type = 250 /* chop */
          offset_delta = 15
      LineNumberTable:
        line 344: 0
        line 345: 5
        line 346: 10
        line 347: 17
        line 348: 32
        line 349: 43
        line 350: 50
        line 351: 68
        line 352: 76
        line 353: 92
        line 354: 115
        line 356: 124
        line 344: 140
      LocalVariableTable:
        Start  Length  Slot  Name   Signature
           68      56     4     l   Lscala/concurrent/impl/Promise$Link;
           76      48     5     p   Lscala/concurrent/impl/Promise$DefaultPromise;
           10     130     3 state   Ljava/lang/Object;
            0     141     0  this   Lscala/concurrent/impl/Promise$DefaultPromise;
            0     141     1 target   Lscala/concurrent/impl/Promise$DefaultPromise;
            0     141     2  link   Lscala/concurrent/impl/Promise$Link;
    Signature: #641                         // (Lscala/concurrent/impl/Promise$DefaultPromise<TT;>;Lscala/concurrent/impl/Promise$Link<TT;>;)V
    MethodParameters:
      Name                           Flags
      target                         final
      link                           final

  public final void unlink(scala.util.Try<T>);
    descriptor: (Lscala/util/Try;)V
    flags: (0x0011) ACC_PUBLIC, ACC_FINAL
    Code:
      stack=3, locals=3, args_size=2
         0: aload_0
         1: invokevirtual #312                // Method get:()Ljava/lang/Object;
         4: astore_2
         5: aload_2
         6: instanceof    #35                 // class scala/concurrent/impl/Promise$Link
         9: ifeq          41
        12: aload_0
        13: aload_2
        14: aload_1
        15: invokevirtual #574                // Method compareAndSet:(Ljava/lang/Object;Ljava/lang/Object;)Z
        18: ifeq          34
        21: aload_2
        22: checkcast     #35                 // class scala/concurrent/impl/Promise$Link
        25: invokevirtual #654                // Method scala/concurrent/impl/Promise$Link.get:()Ljava/lang/Object;
        28: checkcast     #2                  // class scala/concurrent/impl/Promise$DefaultPromise
        31: goto          35
        34: aload_0
        35: aload_1
        36: astore_1
        37: astore_0
        38: goto          0
        41: aload_0
        42: aload_2
        43: aload_1
        44: invokevirtual #316                // Method tryComplete0:(Ljava/lang/Object;Lscala/util/Try;)Z
        47: pop
        48: return
      StackMapTable: number_of_entries = 4
        frame_type = 0 /* same */
        frame_type = 252 /* append */
          offset_delta = 33
          locals = [ class java/lang/Object ]
        frame_type = 64 /* same_locals_1_stack_item */
          stack = [ class scala/concurrent/impl/Promise$DefaultPromise ]
        frame_type = 5 /* same */
      LineNumberTable:
        line 364: 0
        line 365: 5
        line 366: 12
        line 367: 35
        line 368: 41
        line 363: 48
      LocalVariableTable:
        Start  Length  Slot  Name   Signature
            5      43     2 state   Ljava/lang/Object;
            0      49     0  this   Lscala/concurrent/impl/Promise$DefaultPromise;
            0      49     1 resolved   Lscala/util/Try;
    Signature: #307                         // (Lscala/util/Try<TT;>;)V
    MethodParameters:
      Name                           Flags
      resolved                       final

  private void writeObject(java.io.ObjectOutputStream) throws java.io.IOException;
    descriptor: (Ljava/io/ObjectOutputStream;)V
    flags: (0x0002) ACC_PRIVATE
    Code:
      stack=3, locals=2, args_size=2
         0: new           #661                // class java/io/NotSerializableException
         3: dup
         4: ldc_w         #663                // String Promises and Futures cannot be serialized
         7: invokespecial #664                // Method java/io/NotSerializableException."<init>":(Ljava/lang/String;)V
        10: athrow
      LineNumberTable:
        line 373: 0
      LocalVariableTable:
        Start  Length  Slot  Name   Signature
            0      11     0  this   Lscala/concurrent/impl/Promise$DefaultPromise;
            0      11     1   out   Ljava/io/ObjectOutputStream;
    Exceptions:
      throws java.io.IOException
    MethodParameters:
      Name                           Flags
      out                            final

  private void readObject(java.io.ObjectInputStream) throws java.io.IOException, java.lang.ClassNotFoundException;
    descriptor: (Ljava/io/ObjectInputStream;)V
    flags: (0x0002) ACC_PRIVATE
    Code:
      stack=3, locals=2, args_size=2
         0: new           #661                // class java/io/NotSerializableException
         3: dup
         4: ldc_w         #672                // String Promises and Futures cannot be deserialized
         7: invokespecial #664                // Method java/io/NotSerializableException."<init>":(Ljava/lang/String;)V
        10: athrow
      LineNumberTable:
        line 378: 0
      LocalVariableTable:
        Start  Length  Slot  Name   Signature
            0      11     0  this   Lscala/concurrent/impl/Promise$DefaultPromise;
            0      11     1    in   Ljava/io/ObjectInputStream;
    Exceptions:
      throws java.io.IOException, java.lang.ClassNotFoundException
    MethodParameters:
      Name                           Flags
      in                             final

  public final scala.concurrent.Promise completeWith(scala.concurrent.Future);
    descriptor: (Lscala/concurrent/Future;)Lscala/concurrent/Promise;
    flags: (0x1051) ACC_PUBLIC, ACC_FINAL, ACC_BRIDGE, ACC_SYNTHETIC
    Code:
      stack=2, locals=2, args_size=2
         0: aload_0
         1: aload_1
         2: invokevirtual #675                // Method completeWith:(Lscala/concurrent/Future;)Lscala/concurrent/impl/Promise$DefaultPromise;
         5: areturn
      LineNumberTable:
        line 104: 0
      LocalVariableTable:
        Start  Length  Slot  Name   Signature
            0       6     0  this   Lscala/concurrent/impl/Promise$DefaultPromise;
            0       6     1 other   Lscala/concurrent/Future;
    MethodParameters:
      Name                           Flags
      other                          final

  public final scala.concurrent.Awaitable ready(scala.concurrent.duration.Duration, scala.concurrent.CanAwait) throws java.util.concurrent.TimeoutException, java.lang.InterruptedException;
    descriptor: (Lscala/concurrent/duration/Duration;Lscala/concurrent/CanAwait;)Lscala/concurrent/Awaitable;
    flags: (0x1051) ACC_PUBLIC, ACC_FINAL, ACC_BRIDGE, ACC_SYNTHETIC
    Code:
      stack=3, locals=3, args_size=3
         0: aload_0
         1: aload_1
         2: aload_2
         3: invokevirtual #678                // Method ready:(Lscala/concurrent/duration/Duration;Lscala/concurrent/CanAwait;)Lscala/concurrent/impl/Promise$DefaultPromise;
         6: areturn
      LineNumberTable:
        line 104: 0
      LocalVariableTable:
        Start  Length  Slot  Name   Signature
            0       7     0  this   Lscala/concurrent/impl/Promise$DefaultPromise;
            0       7     1 atMost   Lscala/concurrent/duration/Duration;
            0       7     2 permit   Lscala/concurrent/CanAwait;
    Exceptions:
      throws java.util.concurrent.TimeoutException, java.lang.InterruptedException
    MethodParameters:
      Name                           Flags
      atMost                         final
      permit                         final

  public final java.lang.Object apply(java.lang.Object);
    descriptor: (Ljava/lang/Object;)Ljava/lang/Object;
    flags: (0x1051) ACC_PUBLIC, ACC_FINAL, ACC_BRIDGE, ACC_SYNTHETIC
    Code:
      stack=2, locals=2, args_size=2
         0: aload_0
         1: aload_1
         2: checkcast     #335                // class scala/util/Try
         5: invokevirtual #680                // Method apply:(Lscala/util/Try;)V
         8: getstatic     #686                // Field scala/runtime/BoxedUnit.UNIT:Lscala/runtime/BoxedUnit;
        11: areturn
      LineNumberTable:
        line 104: 0
      LocalVariableTable:
        Start  Length  Slot  Name   Signature
            0      12     0  this   Lscala/concurrent/impl/Promise$DefaultPromise;
            0      12     1    v1   Ljava/lang/Object;
    MethodParameters:
      Name                           Flags
      v1                             final

  public static final java.lang.Object $anonfun$zipWith$1(scala.Function2, java.lang.Object, java.lang.Object);
    descriptor: (Lscala/Function2;Ljava/lang/Object;Ljava/lang/Object;)Ljava/lang/Object;
    flags: (0x1019) ACC_PUBLIC, ACC_STATIC, ACC_FINAL, ACC_SYNTHETIC
    Code:
      stack=3, locals=3, args_size=3
         0: aload_0
         1: aload_1
         2: aload_2
         3: invokeinterface #693,  3          // InterfaceMethod scala/Function2.apply:(Ljava/lang/Object;Ljava/lang/Object;)Ljava/lang/Object;
         8: areturn
      LineNumberTable:
        line 139: 0
      LocalVariableTable:
        Start  Length  Slot  Name   Signature
            0       9     0   f$1   Lscala/Function2;
            0       9     1   l$1   Ljava/lang/Object;
            0       9     2     r   Ljava/lang/Object;
    MethodParameters:
      Name                           Flags
      f$1                            final
      l$1                            final
      r                              final

  private static final scala.util.Try liftedTree1$1(scala.Function2, scala.util.Success, scala.util.Success);
    descriptor: (Lscala/Function2;Lscala/util/Success;Lscala/util/Success;)Lscala/util/Try;
    flags: (0x101a) ACC_PRIVATE, ACC_STATIC, ACC_FINAL, ACC_SYNTHETIC
    Code:
      stack=5, locals=5, args_size=3
         0: new           #341                // class scala/util/Success
         3: dup
         4: aload_0
         5: aload_1
         6: ifnonnull     11
         9: aconst_null
        10: athrow
        11: aload_1
        12: invokevirtual #343                // Method scala/util/Success.value:()Ljava/lang/Object;
        15: aload_2
        16: ifnonnull     21
        19: aconst_null
        20: athrow
        21: aload_2
        22: invokevirtual #343                // Method scala/util/Success.value:()Ljava/lang/Object;
        25: invokeinterface #693,  3          // InterfaceMethod scala/Function2.apply:(Ljava/lang/Object;Ljava/lang/Object;)Ljava/lang/Object;
        30: invokespecial #702                // Method scala/util/Success."<init>":(Ljava/lang/Object;)V
        33: areturn
        34: astore        4
        36: getstatic     #707                // Field scala/util/control/NonFatal$.MODULE$:Lscala/util/control/NonFatal$;
        39: aload         4
        41: invokevirtual #709                // Method scala/util/control/NonFatal$.apply:(Ljava/lang/Throwable;)Z
        44: ifeq          60
        47: new           #404                // class scala/util/Failure
        50: dup
        51: aload         4
        53: invokespecial #712                // Method scala/util/Failure."<init>":(Ljava/lang/Throwable;)V
        56: astore_3
        57: goto          63
        60: aload         4
        62: athrow
        63: aload_3
        64: areturn
      Exception table:
         from    to  target type
             0    33    34   Class java/lang/Throwable
      StackMapTable: number_of_entries = 5
        frame_type = 255 /* full_frame */
          offset_delta = 11
          locals = [ class scala/Function2, class scala/util/Success, class scala/util/Success ]
          stack = [ uninitialized 0, uninitialized 0, class scala/Function2 ]
        frame_type = 255 /* full_frame */
          offset_delta = 9
          locals = [ class scala/Function2, class scala/util/Success, class scala/util/Success ]
          stack = [ uninitialized 0, uninitialized 0, class scala/Function2, class java/lang/Object ]
        frame_type = 76 /* same_locals_1_stack_item */
          stack = [ class java/lang/Throwable ]
        frame_type = 253 /* append */
          offset_delta = 25
          locals = [ top, class java/lang/Throwable ]
        frame_type = 255 /* full_frame */
          offset_delta = 2
          locals = [ class scala/Function2, class scala/util/Success, class scala/util/Success, class scala/util/Failure, class java/lang/Throwable ]
          stack = []
      LineNumberTable:
        line 149: 0
      LocalVariableTable:
        Start  Length  Slot  Name   Signature
            0      65     0   f$1   Lscala/Function2;
            0      65     1  x2$1   Lscala/util/Success;
            0      65     2 right$1   Lscala/util/Success;
    MethodParameters:
      Name                           Flags
      f$1                            final
      x2$1                           final
      right$1                        final

  public static final void $anonfun$zipWith$2(java.util.concurrent.atomic.AtomicReference, scala.concurrent.impl.Promise$DefaultPromise, scala.Function2, scala.util.Try);
    descriptor: (Ljava/util/concurrent/atomic/AtomicReference;Lscala/concurrent/impl/Promise$DefaultPromise;Lscala/Function2;Lscala/util/Try;)V
    flags: (0x1019) ACC_PUBLIC, ACC_STATIC, ACC_FINAL, ACC_SYNTHETIC
    Code:
      stack=4, locals=6, args_size=4
         0: aload_3
         1: instanceof    #341                // class scala/util/Success
         4: ifeq          43
         7: aload_3
         8: checkcast     #341                // class scala/util/Success
        11: astore        4
        13: aload_0
        14: aload         4
        16: invokevirtual #720                // Method java/util/concurrent/atomic/AtomicReference.getAndSet:(Ljava/lang/Object;)Ljava/lang/Object;
        19: checkcast     #341                // class scala/util/Success
        22: astore        5
        24: aload         5
        26: ifnull        52
        29: aload_1
        30: aload_2
        31: aload         4
        33: aload         5
        35: invokestatic  #722                // Method liftedTree1$1:(Lscala/Function2;Lscala/util/Success;Lscala/util/Success;)Lscala/util/Try;
        38: invokevirtual #724                // Method tryComplete:(Lscala/util/Try;)Z
        41: pop
        42: return
        43: aload_1
        44: aload_3
        45: checkcast     #404                // class scala/util/Failure
        48: invokevirtual #724                // Method tryComplete:(Lscala/util/Try;)Z
        51: pop
        52: return
      StackMapTable: number_of_entries = 2
        frame_type = 43 /* same */
        frame_type = 8 /* same */
      LineNumberTable:
        line 146: 0
        line 147: 13
        line 148: 24
        line 149: 29
        line 151: 43
        line 145: 52
      LocalVariableTable:
        Start  Length  Slot  Name   Signature
           24      19     5 right   Lscala/util/Success;
            0      53     0 buffer$1   Ljava/util/concurrent/atomic/AtomicReference;
            0      53     1 zipped$1   Lscala/concurrent/impl/Promise$DefaultPromise;
            0      53     2   f$1   Lscala/Function2;
            0      53     3  x0$1   Lscala/util/Try;
    MethodParameters:
      Name                           Flags
      buffer$1                       final
      zipped$1                       final
      f$1                            final
      x0$1                           final

  private static final scala.util.Try liftedTree2$1(scala.Function2, scala.util.Success, scala.util.Success);
    descriptor: (Lscala/Function2;Lscala/util/Success;Lscala/util/Success;)Lscala/util/Try;
    flags: (0x101a) ACC_PRIVATE, ACC_STATIC, ACC_FINAL, ACC_SYNTHETIC
    Code:
      stack=5, locals=5, args_size=3
         0: new           #341                // class scala/util/Success
         3: dup
         4: aload_0
         5: aload_1
         6: ifnonnull     11
         9: aconst_null
        10: athrow
        11: aload_1
        12: invokevirtual #343                // Method scala/util/Success.value:()Ljava/lang/Object;
        15: aload_2
        16: ifnonnull     21
        19: aconst_null
        20: athrow
        21: aload_2
        22: invokevirtual #343                // Method scala/util/Success.value:()Ljava/lang/Object;
        25: invokeinterface #693,  3          // InterfaceMethod scala/Function2.apply:(Ljava/lang/Object;Ljava/lang/Object;)Ljava/lang/Object;
        30: invokespecial #702                // Method scala/util/Success."<init>":(Ljava/lang/Object;)V
        33: areturn
        34: astore        4
        36: getstatic     #707                // Field scala/util/control/NonFatal$.MODULE$:Lscala/util/control/NonFatal$;
        39: aload         4
        41: invokevirtual #709                // Method scala/util/control/NonFatal$.apply:(Ljava/lang/Throwable;)Z
        44: ifeq          60
        47: new           #404                // class scala/util/Failure
        50: dup
        51: aload         4
        53: invokespecial #712                // Method scala/util/Failure."<init>":(Ljava/lang/Throwable;)V
        56: astore_3
        57: goto          63
        60: aload         4
        62: athrow
        63: aload_3
        64: areturn
      Exception table:
         from    to  target type
             0    33    34   Class java/lang/Throwable
      StackMapTable: number_of_entries = 5
        frame_type = 255 /* full_frame */
          offset_delta = 11
          locals = [ class scala/Function2, class scala/util/Success, class scala/util/Success ]
          stack = [ uninitialized 0, uninitialized 0, class scala/Function2 ]
        frame_type = 255 /* full_frame */
          offset_delta = 9
          locals = [ class scala/Function2, class scala/util/Success, class scala/util/Success ]
          stack = [ uninitialized 0, uninitialized 0, class scala/Function2, class java/lang/Object ]
        frame_type = 76 /* same_locals_1_stack_item */
          stack = [ class java/lang/Throwable ]
        frame_type = 253 /* append */
          offset_delta = 25
          locals = [ top, class java/lang/Throwable ]
        frame_type = 255 /* full_frame */
          offset_delta = 2
          locals = [ class scala/Function2, class scala/util/Success, class scala/util/Success, class scala/util/Failure, class java/lang/Throwable ]
          stack = []
      LineNumberTable:
        line 158: 0
      LocalVariableTable:
        Start  Length  Slot  Name   Signature
            0      65     0   f$1   Lscala/Function2;
            0      65     1 left$1   Lscala/util/Success;
            0      65     2  x2$2   Lscala/util/Success;
    MethodParameters:
      Name                           Flags
      f$1                            final
      left$1                         final
      x2$2                           final

  public static final void $anonfun$zipWith$3(java.util.concurrent.atomic.AtomicReference, scala.concurrent.impl.Promise$DefaultPromise, scala.Function2, scala.util.Try);
    descriptor: (Ljava/util/concurrent/atomic/AtomicReference;Lscala/concurrent/impl/Promise$DefaultPromise;Lscala/Function2;Lscala/util/Try;)V
    flags: (0x1019) ACC_PUBLIC, ACC_STATIC, ACC_FINAL, ACC_SYNTHETIC
    Code:
      stack=4, locals=6, args_size=4
         0: aload_3
         1: instanceof    #341                // class scala/util/Success
         4: ifeq          43
         7: aload_3
         8: checkcast     #341                // class scala/util/Success
        11: astore        4
        13: aload_0
        14: aload         4
        16: invokevirtual #720                // Method java/util/concurrent/atomic/AtomicReference.getAndSet:(Ljava/lang/Object;)Ljava/lang/Object;
        19: checkcast     #341                // class scala/util/Success
        22: astore        5
        24: aload         5
        26: ifnull        52
        29: aload_1
        30: aload_2
        31: aload         5
        33: aload         4
        35: invokestatic  #731                // Method liftedTree2$1:(Lscala/Function2;Lscala/util/Success;Lscala/util/Success;)Lscala/util/Try;
        38: invokevirtual #724                // Method tryComplete:(Lscala/util/Try;)Z
        41: pop
        42: return
        43: aload_1
        44: aload_3
        45: checkcast     #404                // class scala/util/Failure
        48: invokevirtual #724                // Method tryComplete:(Lscala/util/Try;)Z
        51: pop
        52: return
      StackMapTable: number_of_entries = 2
        frame_type = 43 /* same */
        frame_type = 8 /* same */
      LineNumberTable:
        line 155: 0
        line 156: 13
        line 157: 24
        line 158: 29
        line 160: 43
        line 154: 52
      LocalVariableTable:
        Start  Length  Slot  Name   Signature
           24      19     5  left   Lscala/util/Success;
            0      53     0 buffer$1   Ljava/util/concurrent/atomic/AtomicReference;
            0      53     1 zipped$1   Lscala/concurrent/impl/Promise$DefaultPromise;
            0      53     2   f$1   Lscala/Function2;
            0      53     3  x0$2   Lscala/util/Try;
    MethodParameters:
      Name                           Flags
      buffer$1                       final
      zipped$1                       final
      f$1                            final
      x0$2                           final

  private scala.concurrent.impl.Promise$DefaultPromise(java.lang.Object);
    descriptor: (Ljava/lang/Object;)V
    flags: (0x0002) ACC_PRIVATE
    Code:
      stack=2, locals=2, args_size=2
         0: aload_0
         1: aload_1
         2: invokespecial #733                // Method java/util/concurrent/atomic/AtomicReference."<init>":(Ljava/lang/Object;)V
         5: return
      LineNumberTable:
        line 104: 0
      LocalVariableTable:
        Start  Length  Slot  Name   Signature
            0       6     0  this   Lscala/concurrent/impl/Promise$DefaultPromise;
            0       6     1 initial   Ljava/lang/Object;
    MethodParameters:
      Name                           Flags
      initial                        final

  public scala.concurrent.impl.Promise$DefaultPromise(scala.util.Try<T>);
    descriptor: (Lscala/util/Try;)V
    flags: (0x0001) ACC_PUBLIC
    Code:
      stack=3, locals=2, args_size=2
         0: aload_0
         1: getstatic     #565                // Field scala/concurrent/impl/Promise$.MODULE$:Lscala/concurrent/impl/Promise$;
         4: aload_1
         5: invokevirtual #569                // Method scala/concurrent/impl/Promise$.scala$concurrent$impl$Promise$$resolve:(Lscala/util/Try;)Lscala/util/Try;
         8: invokespecial #734                // Method "<init>":(Ljava/lang/Object;)V
        11: return
      LineNumberTable:
        line 108: 0
      LocalVariableTable:
        Start  Length  Slot  Name   Signature
            0      12     0  this   Lscala/concurrent/impl/Promise$DefaultPromise;
            0      12     1 result   Lscala/util/Try;
    Signature: #307                         // (Lscala/util/Try<TT;>;)V
    MethodParameters:
      Name                           Flags
      result                         final

  public scala.concurrent.impl.Promise$DefaultPromise();
    descriptor: ()V
    flags: (0x0001) ACC_PUBLIC
    Code:
      stack=2, locals=1, args_size=1
         0: aload_0
         1: getstatic     #578                // Field scala/concurrent/impl/Promise$.scala$concurrent$impl$Promise$$Noop:Lscala/concurrent/impl/Promise$Transformation;
         4: invokespecial #734                // Method "<init>":(Ljava/lang/Object;)V
         7: return
      LineNumberTable:
        line 113: 0
      LocalVariableTable:
        Start  Length  Slot  Name   Signature
            0       8     0  this   Lscala/concurrent/impl/Promise$DefaultPromise;

  public static final java.lang.Object $anonfun$zipWith$2$adapted(java.util.concurrent.atomic.AtomicReference, scala.concurrent.impl.Promise$DefaultPromise, scala.Function2, scala.util.Try);
    descriptor: (Ljava/util/concurrent/atomic/AtomicReference;Lscala/concurrent/impl/Promise$DefaultPromise;Lscala/Function2;Lscala/util/Try;)Ljava/lang/Object;
    flags: (0x1019) ACC_PUBLIC, ACC_STATIC, ACC_FINAL, ACC_SYNTHETIC
    Code:
      stack=4, locals=4, args_size=4
         0: aload_0
         1: aload_1
         2: aload_2
         3: aload_3
         4: invokestatic  #736                // Method $anonfun$zipWith$2:(Ljava/util/concurrent/atomic/AtomicReference;Lscala/concurrent/impl/Promise$DefaultPromise;Lscala/Function2;Lscala/util/Try;)V
         7: getstatic     #686                // Field scala/runtime/BoxedUnit.UNIT:Lscala/runtime/BoxedUnit;
        10: areturn
      LineNumberTable:
        line 145: 0
      LocalVariableTable:
        Start  Length  Slot  Name   Signature
            0      11     0 buffer$1   Ljava/util/concurrent/atomic/AtomicReference;
            0      11     1 zipped$1   Lscala/concurrent/impl/Promise$DefaultPromise;
            0      11     2   f$1   Lscala/Function2;
            0      11     3  x0$1   Lscala/util/Try;
    MethodParameters:
      Name                           Flags
      buffer$1                       final
      zipped$1                       final
      f$1                            final
      x0$1                           final

  public static final java.lang.Object $anonfun$zipWith$3$adapted(java.util.concurrent.atomic.AtomicReference, scala.concurrent.impl.Promise$DefaultPromise, scala.Function2, scala.util.Try);
    descriptor: (Ljava/util/concurrent/atomic/AtomicReference;Lscala/concurrent/impl/Promise$DefaultPromise;Lscala/Function2;Lscala/util/Try;)Ljava/lang/Object;
    flags: (0x1019) ACC_PUBLIC, ACC_STATIC, ACC_FINAL, ACC_SYNTHETIC
    Code:
      stack=4, locals=4, args_size=4
         0: aload_0
         1: aload_1
         2: aload_2
         3: aload_3
         4: invokestatic  #738                // Method $anonfun$zipWith$3:(Ljava/util/concurrent/atomic/AtomicReference;Lscala/concurrent/impl/Promise$DefaultPromise;Lscala/Function2;Lscala/util/Try;)V
         7: getstatic     #686                // Field scala/runtime/BoxedUnit.UNIT:Lscala/runtime/BoxedUnit;
        10: areturn
      LineNumberTable:
        line 154: 0
      LocalVariableTable:
        Start  Length  Slot  Name   Signature
            0      11     0 buffer$1   Ljava/util/concurrent/atomic/AtomicReference;
            0      11     1 zipped$1   Lscala/concurrent/impl/Promise$DefaultPromise;
            0      11     2   f$1   Lscala/Function2;
            0      11     3  x0$2   Lscala/util/Try;
    MethodParameters:
      Name                           Flags
      buffer$1                       final
      zipped$1                       final
      f$1                            final
      x0$2                           final

  private static java.lang.Object $deserializeLambda$(java.lang.invoke.SerializedLambda);
    descriptor: (Ljava/lang/invoke/SerializedLambda;)Ljava/lang/Object;
    flags: (0x100a) ACC_PRIVATE, ACC_STATIC, ACC_SYNTHETIC
    Code:
      stack=1, locals=1, args_size=1
         0: aload_0
         1: invokedynamic #750,  0            // InvokeDynamic #3:lambdaDeserialize:(Ljava/lang/invoke/SerializedLambda;)Ljava/lang/Object;
         6: areturn
}
InnerClasses:
  public static final #17= #14 of #16;    // Lookup=class java/lang/invoke/MethodHandles$Lookup of class java/lang/invoke/MethodHandles
  public static #22= #19 of #21;          // parasitic$=class scala/concurrent/ExecutionContext$parasitic$ of class scala/concurrent/ExecutionContext
  public static abstract #27= #24 of #26; // Infinite=class scala/concurrent/duration/Duration$Infinite of class scala/concurrent/duration/Duration
  public static #32= #29 of #31;          // Callbacks=class scala/concurrent/impl/Promise$Callbacks of class scala/concurrent/impl/Promise
  public static #33= #2 of #31;           // DefaultPromise=class scala/concurrent/impl/Promise$DefaultPromise of class scala/concurrent/impl/Promise
  public static final #36= #35 of #31;    // Link=class scala/concurrent/impl/Promise$Link of class scala/concurrent/impl/Promise
  public static final #39= #38 of #31;    // ManyCallbacks=class scala/concurrent/impl/Promise$ManyCallbacks of class scala/concurrent/impl/Promise
  public static final #42= #41 of #31;    // Transformation=class scala/concurrent/impl/Promise$Transformation of class scala/concurrent/impl/Promise
Signature: #3                           // <T:Ljava/lang/Object;>Ljava/util/concurrent/atomic/AtomicReference<Ljava/lang/Object;>;Lscala/concurrent/Promise<TT;>;Lscala/concurrent/Future<TT;>;Lscala/Function1<Lscala/util/Try<TT;>;Lscala/runtime/BoxedUnit;>;
SourceFile: "Promise.scala"
BootstrapMethods:
  0: #358 REF_invokeStatic java/lang/invoke/LambdaMetafactory.altMetafactory:(Ljava/lang/invoke/MethodHandles$Lookup;Ljava/lang/String;Ljava/lang/invoke/MethodType;[Ljava/lang/Object;)Ljava/lang/invoke/CallSite;
    Method arguments:
      #345 (Ljava/lang/Object;)Ljava/lang/Object;
      #350 REF_invokeStatic scala/concurrent/impl/Promise$DefaultPromise.$anonfun$zipWith$1:(Lscala/Function2;Ljava/lang/Object;Ljava/lang/Object;)Ljava/lang/Object;
      #345 (Ljava/lang/Object;)Ljava/lang/Object;
      #351 1
  1: #358 REF_invokeStatic java/lang/invoke/LambdaMetafactory.altMetafactory:(Ljava/lang/invoke/MethodHandles$Lookup;Ljava/lang/String;Ljava/lang/invoke/MethodType;[Ljava/lang/Object;)Ljava/lang/invoke/CallSite;
    Method arguments:
      #345 (Ljava/lang/Object;)Ljava/lang/Object;
      #373 REF_invokeStatic scala/concurrent/impl/Promise$DefaultPromise.$anonfun$zipWith$2$adapted:(Ljava/util/concurrent/atomic/AtomicReference;Lscala/concurrent/impl/Promise$DefaultPromise;Lscala/Function2;Lscala/util/Try;)Ljava/lang/Object;
      #375 (Lscala/util/Try;)Ljava/lang/Object;
      #376 5
      #351 1
      #375 (Lscala/util/Try;)Ljava/lang/Object;
  2: #358 REF_invokeStatic java/lang/invoke/LambdaMetafactory.altMetafactory:(Ljava/lang/invoke/MethodHandles$Lookup;Ljava/lang/String;Ljava/lang/invoke/MethodType;[Ljava/lang/Object;)Ljava/lang/invoke/CallSite;
    Method arguments:
      #345 (Ljava/lang/Object;)Ljava/lang/Object;
      #383 REF_invokeStatic scala/concurrent/impl/Promise$DefaultPromise.$anonfun$zipWith$3$adapted:(Ljava/util/concurrent/atomic/AtomicReference;Lscala/concurrent/impl/Promise$DefaultPromise;Lscala/Function2;Lscala/util/Try;)Ljava/lang/Object;
      #375 (Lscala/util/Try;)Ljava/lang/Object;
      #376 5
      #351 1
      #375 (Lscala/util/Try;)Ljava/lang/Object;
  3: #747 REF_invokeStatic scala/runtime/LambdaDeserialize.bootstrap:(Ljava/lang/invoke/MethodHandles$Lookup;Ljava/lang/String;Ljava/lang/invoke/MethodType;[Ljava/lang/invoke/MethodHandle;)Ljava/lang/invoke/CallSite;
    Method arguments:
      #350 REF_invokeStatic scala/concurrent/impl/Promise$DefaultPromise.$anonfun$zipWith$1:(Lscala/Function2;Ljava/lang/Object;Ljava/lang/Object;)Ljava/lang/Object;
      #373 REF_invokeStatic scala/concurrent/impl/Promise$DefaultPromise.$anonfun$zipWith$2$adapted:(Ljava/util/concurrent/atomic/AtomicReference;Lscala/concurrent/impl/Promise$DefaultPromise;Lscala/Function2;Lscala/util/Try;)Ljava/lang/Object;
      #383 REF_invokeStatic scala/concurrent/impl/Promise$DefaultPromise.$anonfun$zipWith$3$adapted:(Ljava/util/concurrent/atomic/AtomicReference;Lscala/concurrent/impl/Promise$DefaultPromise;Lscala/Function2;Lscala/util/Try;)Ljava/lang/Object;
  ScalaInlineInfo: length = 0x1A3 (unknown attribute)
   01 00 00 53 01 5A 01 5B 01 02 C9 02 CA 01 01 71
   01 72 01 02 D8 02 CA 01 01 7C 01 72 01 01 41 01
   6D 01 01 41 02 BC 01 01 41 01 32 01 00 CB 00 C3
   00 00 CB 00 FA 00 01 31 01 58 01 01 31 01 32 01
   00 35 00 36 00 00 5A 00 5B 00 00 7F 00 80 00 00
   A4 00 A5 00 00 3B 00 3C 00 00 60 00 61 00 00 85
   00 86 00 00 AA 00 AB 00 00 41 00 42 00 00 66 00
   67 00 00 8B 00 8C 00 00 B0 00 B1 00 00 47 00 48
   00 00 6C 00 6D 00 00 91 00 92 00 00 B6 00 B7 00
   00 4D 00 4E 00 00 72 00 73 00 00 97 00 98 00 00
   BC 00 BD 00 00 2B 00 2C 00 00 53 00 54 00 00 78
   00 79 00 00 9D 00 9E 00 01 99 00 FA 01 01 01 01
   02 00 02 47 01 0B 01 02 47 02 48 01 00 C2 00 C3
   00 02 66 02 67 01 01 45 01 46 01 01 AA 01 3E 01
   01 22 01 23 00 00 F5 00 ED 00 01 98 00 E5 01 01
   95 00 E5 01 00 DB 00 DC 00 01 91 01 82 01 01 3D
   01 3E 01 02 22 01 51 01 02 B6 02 B7 01 02 D5 02
   B7 01 02 7F 02 80 01 01 6A 00 E5 01 01 9F 01 A0
   01 01 81 01 82 01 02 9A 02 9B 01 02 14 02 A4 01
   02 14 02 15 01 01 9D 00 FA 01 01 9B 00 FA 01 01
   04 02 1D 01 02 43 02 44 01 01 12 01 13 00 01 B8
   01 B9 01 00 D0 00 D1 00 00 D0 00 E5 01 01 49 00
   E5 01 01 D2 01 D3 01 02 2E 02 2F 01 01 39 01 3A
   01 01 0A 01 0B 01 01 2B 01 2C 00 01 1B 01 1C 00
   02 8D 01 32 01 01 15 02 23 01 01 DF 01 E0 01 00
   E4 00 E5 01 02 8F 02 90 01 00 EC 00 ED 00 01 4B
   01 4C 01
  Scala: length = 0x0 (unknown attribute)

