Classfile /Users/mw/Projects/slang-braindump/.jar/jar8/assemble/slang-braindump/assemble/content/org/scalatest/funspec/AnyFunSpecLike.class
  Last modified May 29, 2022; size 20647 bytes
  SHA-256 checksum 3e6ead3cc3c14a9cd3f43ff87b6271e41b993d9be89f85affd4b9faeddeb03ae
  Compiled from "AnyFunSpecLike.scala"
public interface org.scalatest.funspec.AnyFunSpecLike extends org.scalatest.TestSuite,org.scalatest.TestRegistration,org.scalatest.Informing,org.scalatest.Notifying,org.scalatest.Alerting,org.scalatest.Documenting
  minor version: 0
  major version: 52
  flags: (0x0601) ACC_PUBLIC, ACC_INTERFACE, ACC_ABSTRACT
  this_class: #2                          // org/scalatest/funspec/AnyFunSpecLike
  super_class: #4                         // java/lang/Object
  interfaces: 6, fields: 0, methods: 61, attributes: 6
Constant pool:
    #1 = Utf8               org/scalatest/funspec/AnyFunSpecLike
    #2 = Class              #1            // org/scalatest/funspec/AnyFunSpecLike
    #3 = Utf8               java/lang/Object
    #4 = Class              #3            // java/lang/Object
    #5 = Utf8               org/scalatest/TestSuite
    #6 = Class              #5            // org/scalatest/TestSuite
    #7 = Utf8               org/scalatest/TestRegistration
    #8 = Class              #7            // org/scalatest/TestRegistration
    #9 = Utf8               org/scalatest/Informing
   #10 = Class              #9            // org/scalatest/Informing
   #11 = Utf8               org/scalatest/Notifying
   #12 = Class              #11           // org/scalatest/Notifying
   #13 = Utf8               org/scalatest/Alerting
   #14 = Class              #13           // org/scalatest/Alerting
   #15 = Utf8               org/scalatest/Documenting
   #16 = Class              #15           // org/scalatest/Documenting
   #17 = Utf8               AnyFunSpecLike.scala
   #18 = Utf8               Lorg/scalatest/Finders;
   #19 = Utf8               value
   #20 = Utf8               org.scalatest.finders.FunSpecFinder
   #21 = Utf8               Lscala/reflect/ScalaSignature;
   #22 = Utf8               bytes
   #23 = Utf8               \u0006\u0005\t\u0015ga\u0002\u0015*!\u0003\r\t\u0001\r\u0005\u0006\u0015\u0002!\ta\u0013\u0005\b\u001f\u0002\u0011\r\u0011\"\u0004Q\u0011!!\u0006A1A\u0005\u0002-*\u0006\"\u00020\u0001\t#y\u0006\"B2\u0001\t#!\u0007\"\u00025\u0001\t#I\u0007\"B7\u0001\t#q\u0007\"\u0002:\u0001\t\u001b\u0019\bbBA\u001c\u0001\u0011\u0015\u0011\u0011\b\u0005\b\u0003\u000f\u0002AQBA%\u0011\u001d\t)\u0006\u0001C\u0003\u0003/2a!!\u001a\u0001\u0011\u0005\u001d\u0004bBA5\u0019\u0011\u0005\u00111\u000e\u0005\b\u0003cbAQBA:\u0011\u001d\t\t\t\u0004C\u0001\u0003\u0007Cq!!%\r\t\u0003\t\u0019\nC\u0004\u0002&2!\t!a*\t\u0013\u0005-\u0006A1A\u0005\u0012\u00055fABAX\u0001!\t\t\fC\u0004\u0002jM!\t!a-\t\u000f\u0005E4\u0003\"\u0004\u00028\"9\u0011\u0011Q\n\u0005\u0002\u0005\r\u0007bBAI\'\u0011\u0005\u0011\u0011\u001b\u0005\b\u0003K\u001bB\u0011AAk\u0011%\tI\u000e\u0001b\u0001\n#\tY\u000eC\u0004\u0002^\u0002!i!a8\t\u000f\u0005-\b\u0001\"\u0005\u0002n\"9\u00111 \u0001\u0005\u000e\u0005u\bb\u0002B\u0007\u0001\u0011E!q\u0002\u0005\b\u00057\u0001A\u0011\tB\u000f\u0011\u001d\u0011)\u0003\u0001C)\u0005OAqA!\u0010\u0001\t\u0003\u0012y\u0004C\u0004\u0003H\u0001!\tF!\u0013\t\u000f\tU\u0003\u0001\"\u0011\u0003X!I!Q\f\u0001C\u0002\u0013E!q\f\u0005\n\u0005C\u0002!\u0019!C#\u0005GBqA!\u001f\u0001\t\u0003\u0012Y\bC\u0005\u0003\u0010\u0002\t\n\u0011\"\u0001\u0003\u0012\"q!q\u0015\u0001\u0011\u0002\u0007\u0005\t\u0011\"\u0003\u0003*\n=&AD!os\u001a+hn\u00159fG2K7.\u001a\u0006\u0003U-\nqAZ;ogB,7M\u0003\u0002-[\u0005I1oY1mCR,7\u000f\u001e\u0006\u0002]\u0005\u0019qN]4\u0004\u0001MA\u0001!M\u001c<}\u0005#u\t\u0005\u00023k5\t1GC\u00015\u0003\u0015\u00198-\u00197b\u0013\t14G\u0001\u0004B]f\u0014VM\u001a\t\u0003qej\u0011aK\u0005\u0003u-\u0012\u0011\u0002V3tiN+\u0018\u000e^3\u0011\u0005ab\u0014BA\u001f,\u0005A!Vm\u001d;SK\u001eL7\u000f\u001e:bi&|g\u000e\u0005\u00029\u007f%\u0011\u0001i\u000b\u0002\n\u0013:4wN]7j]\u001e\u0004\"\u0001\u000f\"\n\u0005\r[#!\u0003(pi&4\u00170\u001b8h!\tAT)\u0003\u0002GW\tA\u0011\t\\3si&tw\r\u0005\u00029\u0011&\u0011\u0011j\u000b\u0002\f\t>\u001cW/\\3oi&tw-\u0001\u0004%S:LG\u000f\n\u000b\u0002\u0019B\u0011!\'T\u0005\u0003\u001dN\u0012A!\u00168ji\u00061QM\\4j]\u0016,\u0012!\u0015\t\u0003qIK!aU\u0016\u0003\r\u0015sw-\u001b8f\u00039\u0019x.\u001e:dK\u001aKG.\u001a(b[\u0016,\u0012A\u0016\t\u0003/rk\u0011\u0001\u0017\u0006\u00033j\u000bA\u0001\\1oO*\t1,\u0001\u0003kCZ\f\u0017BA/Y\u0005\u0019\u0019FO]5oO\u0006!\u0011N\u001c4p+\u0005\u0001\u0007C\u0001\u001db\u0013\t\u00117F\u0001\u0005J]\u001a|\'/\\3s\u0003\u0011qw\u000e^3\u0016\u0003\u0015\u0004\"\u0001\u000f4\n\u0005\u001d\\#\u0001\u0003(pi&4\u0017.\u001a:\u0002\u000b\u0005dWM\u001d;\u0016\u0003)\u0004\"\u0001O6\n\u00051\\#aB!mKJ$XM]\u0001\u0007[\u0006\u00148.\u001e9\u0016\u0003=\u0004\"\u0001\u000f9\n\u0005E\\#A\u0003#pGVlWM\u001c;fe\u0006\u0001\"/Z4jgR,\'\u000fV3ti&k\u0007\u000f\u001c\u000b\u0006i\u0006=\u0011q\u0005\u000b\u0004\u0019Vl\bB\u0002<\t\t\u0003\u0007q/A\u0004uKN$h)\u001e8\u0011\u0007IB(0\u0003\u0002zg\tAAHY=oC6,g\b\u0005\u00023w&\u0011Ap\r\u0002\u0004\u0003:L\b\"\u0002@\t\u0001\u0004y\u0018a\u00019pgB!\u0011\u0011AA\u0006\u001b\t\t\u0019A\u0003\u0003\u0002\u0006\u0005\u001d\u0011AB:pkJ\u001cWMC\u0002\u0002\n5\n\u0011b]2bY\u0006\u001cG/[2\n\t\u00055\u00111\u0001\u0002\t!>\u001c\u0018\u000e^5p]\"9\u0011\u0011\u0003\u0005A\u0002\u0005M\u0011\u0001\u0003;fgR$V\r\u001f;\u0011\t\u0005U\u00111\u0005\b\u0005\u0003/\ty\u0002E\u0002\u0002\u001aMj!!a\u0007\u000b\u0007\u0005uq&\u0001\u0004=e>|GOP\u0005\u0004\u0003C\u0019\u0014A\u0002)sK\u0012,g-C\u0002^\u0003KQ1!!\t4\u0011\u001d\tI\u0003\u0003a\u0001\u0003W\t\u0001\u0002^3tiR\u000bwm\u001d\t\u0006e\u00055\u0012\u0011G\u0005\u0004\u0003_\u0019$A\u0003\u001fsKB,\u0017\r^3e}A\u0019\u0001(a\r\n\u0007\u0005U2FA\u0002UC\u001e\fAB]3hSN$XM\u001d+fgR$b!a\u000f\u0002D\u0005\u0015C\u0003BA\u001f\u0003\u0003\"2\u0001TA \u0011\u0015q\u0018\u0002q\u0001\u0000\u0011\u00191\u0018\u0002\"a\u0001o\"9\u0011\u0011C\u0005A\u0002\u0005M\u0001bBA\u0015\u0013\u0001\u0007\u00111F\u0001\u0018e\u0016<\u0017n\u001d;fe&;gn\u001c:fIR+7\u000f^%na2$b!a\u0013\u0002R\u0005MC#\u0002\'\u0002N\u0005=\u0003B\u0002<\u000b\t\u0003\u0007q\u000fC\u0003\u007f\u0015\u0001\u0007q\u0010C\u0004\u0002\u0012)\u0001\r!a\u0005\t\u000f\u0005%\"\u00021\u0001\u0002,\u0005\u0019\"/Z4jgR,\'/S4o_J,G\rV3tiR1\u0011\u0011LA1\u0003G\"B!a\u0017\u0002`Q\u0019A*!\u0018\t\u000by\\\u00019A@\t\rY\\A\u00111\u0001x\u0011\u001d\t\tb\u0003a\u0001\u0003\'Aq!!\u000b\f\u0001\u0004\tYC\u0001\u0004Ji^{\'\u000fZ\n\u0003\u0019E\na\u0001P5oSRtDCAA7!\r\ty\u0007D\u0007\u0002\u0001\u0005I\u0011\r\u001d9ms&k\u0007\u000f\u001c\u000b\u0007\u0003k\nY(a \u0015\u000b1\u000b9(!\u001f\t\rYtA\u00111\u0001x\u0011\u0015qh\u00021\u0001\u0000\u0011\u001d\tiH\u0004a\u0001\u0003\'\t\u0001b\u001d9fGR+\u0007\u0010\u001e\u0005\b\u0003Sq\u0001\u0019AA\u0016\u0003\u0015\t\u0007\u000f\u001d7z)\u0019\t))!$\u0002\u0010R!\u0011qQAF)\ra\u0015\u0011\u0012\u0005\u0006}>\u0001\u001da \u0005\u0007m>!\t\u0019A<\t\u000f\u0005ut\u00021\u0001\u0002\u0014!9\u0011\u0011F\bA\u0002\u0005-\u0012AB:i_VdG\r\u0006\u0003\u0002\u0016\u0006\u0005\u0006\u0003BAL\u0003;k!!!\'\u000b\u0007\u0005m5&A\u0003wKJ\u00147/\u0003\u0003\u0002 \u0006e%A\u0003\"fQ\u00064XmV8sI\"9\u00111\u0015\tA\u0002\u0005U\u0015A\u00032fQ\u00064XmV8sI\u0006!Q.^:u)\u0011\t)*!+\t\u000f\u0005\r\u0016\u00031\u0001\u0002\u0016\u0006\u0011\u0011\u000e^\u000b\u0003\u0003[\u0012\u0001\u0002\u00165fs^{\'\u000fZ\n\u0003\'E\"\"!!.\u0011\u0007\u0005=4\u0003\u0006\u0004\u0002:\u0006}\u0016\u0011\u0019\u000b\u0006\u0019\u0006m\u0016Q\u0018\u0005\u0007mV!\t\u0019A<\t\u000by,\u0002\u0019A@\t\u000f\u0005uT\u00031\u0001\u0002\u0014!9\u0011\u0011F\u000bA\u0002\u0005-BCBAc\u0003\u001b\fy\r\u0006\u0003\u0002H\u0006-Gc\u0001\'\u0002J\")aP\u0006a\u0002\u007f\"1aO\u0006CA\u0002]Dq!! \u0017\u0001\u0004\t\u0019\u0002C\u0004\u0002*Y\u0001\r!a\u000b\u0015\t\u0005U\u00151\u001b\u0005\b\u0003G;\u0002\u0019AAK)\u0011\t)*a6\t\u000f\u0005\r\u0006\u00041\u0001\u0002\u0016\u0006!A\u000f[3z+\t\t),\u0001\u0006jO:|\'/Z%na2$b!!9\u0002h\u0006%H#\u0002\'\u0002d\u0006\u0015\bB\u0002<\u001b\t\u0003\u0007q\u000fC\u0003\u007f5\u0001\u0007q\u0010C\u0004\u0002\u0012i\u0001\r!a\u0005\t\u000f\u0005%\"\u00041\u0001\u0002,\u00051\u0011n\u001a8pe\u0016$b!a<\u0002x\u0006eH\u0003BAy\u0003k$2\u0001TAz\u0011\u0015q8\u0004q\u0001\u0000\u0011\u001918\u0004\"a\u0001o\"9\u0011\u0011C\u000eA\u0002\u0005M\u0001bBA\u00157\u0001\u0007\u00111F\u0001\rI\u0016\u001c8M]5cK&k\u0007\u000f\u001c\u000b\u0005\u0003\u007f\u0014I\u0001F\u0003M\u0005\u0003\u00119\u0001\u0003\u0005\u0003\u0004q!\t\u0019\u0001B\u0003\u0003\r1WO\u001c\t\u0004ead\u0005\"\u0002@\u001d\u0001\u0004y\bb\u0002B\u00069\u0001\u0007\u00111C\u0001\fI\u0016\u001c8M]5qi&|g.\u0001\u0005eKN\u001c\'/\u001b2f)\u0011\u0011\tB!\u0007\u0015\t\tM!q\u0003\u000b\u0004\u0019\nU\u0001\"\u0002@\u001e\u0001\by\b\u0002\u0003B\u0002;\u0011\u0005\rA!\u0002\t\u000f\t-Q\u00041\u0001\u0002\u0014\u0005IA/Z:u\u001d\u0006lWm]\u000b\u0003\u0005?\u0001b!!\u0006\u0003\"\u0005M\u0011\u0002\u0002B\u0012\u0003K\u00111aU3u\u0003\u001d\u0011XO\u001c+fgR$bA!\u000b\u00030\tM\u0002c\u0001\u001d\u0003,%\u0019!QF\u0016\u0003\rM#\u0018\r^;t\u0011\u001d\u0011\td\ba\u0001\u0003\'\t\u0001\u0002^3ti:\u000bW.\u001a\u0005\b\u0005ky\u0002\u0019\u0001B\u001c\u0003\u0011\t\'oZ:\u0011\u0007a\u0012I$C\u0002\u0003<-\u0012A!\u0011:hg\u0006!A/Y4t+\t\u0011\t\u0005\u0005\u0005\u0002\u0016\t\r\u00131\u0003B\u0010\u0013\u0011\u0011)%!\n\u0003\u00075\u000b\u0007/\u0001\u0005sk:$Vm\u001d;t)\u0019\u0011ICa\u0013\u0003T!9!\u0011G\u0011A\u0002\t5\u0003#\u0002\u001a\u0003P\u0005M\u0011b\u0001B)g\t1q\n\u001d;j_:DqA!\u000e\"\u0001\u0004\u00119$A\u0002sk:$bA!\u000b\u0003Z\tm\u0003b\u0002B\u0019E\u0001\u0007!Q\n\u0005\b\u0005k\u0011\u0003\u0019\u0001B\u001c\u0003\u0019\u0011W\r[1wKV\u0011\u0011QS\u0001\ngRLH.\u001a(b[\u0016,\"!a\u0005)\u0017\u0011\u00129G!\u001c\u0003p\tM$Q\u000f\t\u0004e\t%\u0014b\u0001B6g\tQA-\u001a9sK\u000e\fG/\u001a3\u0002\u000f5,7o]1hK\u0006\u0012!\u0011O\u0001})\",\u0007e\u001d;zY\u0016t\u0015-\\3!Y&4WmY=dY\u0016\u0004S.\u001a;i_\u0012\u0004\u0003.Y:!E\u0016,g\u000e\t3faJ,7-\u0019;fI\u0002\ng\u000e\u001a\u0011xS2d\u0007EY3!e\u0016lwN^3eA%t\u0007%\u0019\u0011gkR,(/\u001a\u0011wKJ\u001c\u0018n\u001c8!_\u001a\u00043kY1mCR+7\u000f\u001e\u0011xSRD\u0007E\\8!e\u0016\u0004H.Y2f[\u0016tGOL\u0001\u0006g&t7-Z\u0011\u0003\u0005o\nQa\r\u00182]A\n1\u0002^3ti\u0012\u000bG/\u0019$peR1!Q\u0010BB\u0005\u000b\u00032\u0001\u000fB@\u0013\r\u0011\ti\u000b\u0002\t)\u0016\u001cH\u000fR1uC\"9!\u0011G\u0013A\u0002\u0005M\u0001\"\u0003BDKA\u0005\t\u0019\u0001BE\u00031!\b.Z\"p]\u001aLw-T1q!\rA$1R\u0005\u0004\u0005\u001b[#!C\"p]\u001aLw-T1q\u0003U!Xm\u001d;ECR\fgi\u001c:%I\u00164\u0017-\u001e7uII*\"Aa%+\t\t%%QS\u0016\u0003\u0005/\u0003BA!\'\u0003$6\u0011!1\u0014\u0006\u0005\u0005;\u0013y*A\u0005v]\u000eDWmY6fI*\u0019!\u0011U\u001a\u0002\u0015\u0005tgn\u001c;bi&|g.\u0003\u0003\u0003&\nm%!E;oG\",7m[3e-\u0006\u0014\u0018.\u00198dK\u0006I1/\u001e9fe\u0012\u0012XO\u001c\u000b\u0007\u0005S\u0011YK!,\t\u000f\tEr\u00051\u0001\u0003N!9!QG\u0014A\u0002\t]\u0012\u0002\u0002B+\u0005cK1Aa-,\u0005\u0015\u0019V/\u001b;fQ\u001d\u0001!q\u0017B_\u0005\u007f\u00032\u0001\u000fB]\u0013\r\u0011Yl\u000b\u0002\b\r&tG-\u001a:t\u0003\u00151\u0018\r\\;fY\t\u0011\t-\t\u0002\u0003D\u0006\u0019sN]4/g\u000e\fG.\u0019;fgRtc-\u001b8eKJ\u001chFR;o\'B,7MR5oI\u0016\u0014\b
   #24 = Utf8               java/lang/invoke/MethodHandles$Lookup
   #25 = Class              #24           // java/lang/invoke/MethodHandles$Lookup
   #26 = Utf8               java/lang/invoke/MethodHandles
   #27 = Class              #26           // java/lang/invoke/MethodHandles
   #28 = Utf8               Lookup
   #29 = Utf8               org/scalatest/SuperEngine$Bundle
   #30 = Class              #29           // org/scalatest/SuperEngine$Bundle
   #31 = Utf8               org/scalatest/SuperEngine
   #32 = Class              #31           // org/scalatest/SuperEngine
   #33 = Utf8               Bundle
   #34 = Utf8               org/scalatest/SuperEngine$TestLeaf
   #35 = Class              #34           // org/scalatest/SuperEngine$TestLeaf
   #36 = Utf8               TestLeaf
   #37 = Utf8               org/scalatest/TestSuite$NoArgTest
   #38 = Class              #37           // org/scalatest/TestSuite$NoArgTest
   #39 = Utf8               NoArgTest
   #40 = Utf8               org/scalatest/funspec/AnyFunSpecLike$$anon$1
   #41 = Class              #40           // org/scalatest/funspec/AnyFunSpecLike$$anon$1
   #42 = Utf8               org/scalatest/funspec/AnyFunSpecLike$ItWord
   #43 = Class              #42           // org/scalatest/funspec/AnyFunSpecLike$ItWord
   #44 = Utf8               ItWord
   #45 = Utf8               org/scalatest/funspec/AnyFunSpecLike$TheyWord
   #46 = Class              #45           // org/scalatest/funspec/AnyFunSpecLike$TheyWord
   #47 = Utf8               TheyWord
   #48 = Utf8               org$scalatest$funspec$AnyFunSpecLike$_setter_$org$scalatest$funspec$AnyFunSpecLike$$engine_$eq
   #49 = Utf8               (Lorg/scalatest/Engine;)V
   #50 = Utf8               x$1
   #51 = Utf8               org$scalatest$funspec$AnyFunSpecLike$_setter_$sourceFileName_$eq
   #52 = Utf8               (Ljava/lang/String;)V
   #53 = Utf8               org$scalatest$funspec$AnyFunSpecLike$_setter_$it_$eq
   #54 = Utf8               (Lorg/scalatest/funspec/AnyFunSpecLike$ItWord;)V
   #55 = Utf8               org$scalatest$funspec$AnyFunSpecLike$_setter_$they_$eq
   #56 = Utf8               (Lorg/scalatest/funspec/AnyFunSpecLike$TheyWord;)V
   #57 = Utf8               org$scalatest$funspec$AnyFunSpecLike$_setter_$behave_$eq
   #58 = Utf8               (Lorg/scalatest/verbs/BehaveWord;)V
   #59 = Utf8               org$scalatest$funspec$AnyFunSpecLike$_setter_$styleName_$eq
   #60 = Utf8               org$scalatest$funspec$AnyFunSpecLike$$super$run
   #61 = Utf8               (Lscala/Option;Lorg/scalatest/Args;)Lorg/scalatest/Status;
   #62 = Utf8               testName
   #63 = Utf8               args
   #64 = Utf8               org$scalatest$funspec$AnyFunSpecLike$$engine
   #65 = Utf8               ()Lorg/scalatest/Engine;
   #66 = Utf8               sourceFileName
   #67 = Utf8               ()Ljava/lang/String;
   #68 = Utf8               info$
   #69 = Utf8               (Lorg/scalatest/funspec/AnyFunSpecLike;)Lorg/scalatest/Informer;
   #70 = Utf8               $this
   #71 = Utf8               info
   #72 = Utf8               ()Lorg/scalatest/Informer;
   #73 = NameAndType        #71:#72       // info:()Lorg/scalatest/Informer;
   #74 = InterfaceMethodref #2.#73        // org/scalatest/funspec/AnyFunSpecLike.info:()Lorg/scalatest/Informer;
   #75 = Utf8               Lorg/scalatest/funspec/AnyFunSpecLike;
   #76 = NameAndType        #64:#65       // org$scalatest$funspec$AnyFunSpecLike$$engine:()Lorg/scalatest/Engine;
   #77 = InterfaceMethodref #2.#76        // org/scalatest/funspec/AnyFunSpecLike.org$scalatest$funspec$AnyFunSpecLike$$engine:()Lorg/scalatest/Engine;
   #78 = Utf8               org/scalatest/Engine
   #79 = Class              #78           // org/scalatest/Engine
   #80 = Utf8               atomicInformer
   #81 = Utf8               ()Ljava/util/concurrent/atomic/AtomicReference;
   #82 = NameAndType        #80:#81       // atomicInformer:()Ljava/util/concurrent/atomic/AtomicReference;
   #83 = Methodref          #79.#82       // org/scalatest/Engine.atomicInformer:()Ljava/util/concurrent/atomic/AtomicReference;
   #84 = Utf8               java/util/concurrent/atomic/AtomicReference
   #85 = Class              #84           // java/util/concurrent/atomic/AtomicReference
   #86 = Utf8               get
   #87 = Utf8               ()Ljava/lang/Object;
   #88 = NameAndType        #86:#87       // get:()Ljava/lang/Object;
   #89 = Methodref          #85.#88       // java/util/concurrent/atomic/AtomicReference.get:()Ljava/lang/Object;
   #90 = Utf8               org/scalatest/Informer
   #91 = Class              #90           // org/scalatest/Informer
   #92 = Utf8               this
   #93 = Utf8               note$
   #94 = Utf8               (Lorg/scalatest/funspec/AnyFunSpecLike;)Lorg/scalatest/Notifier;
   #95 = Utf8               note
   #96 = Utf8               ()Lorg/scalatest/Notifier;
   #97 = NameAndType        #95:#96       // note:()Lorg/scalatest/Notifier;
   #98 = InterfaceMethodref #2.#97        // org/scalatest/funspec/AnyFunSpecLike.note:()Lorg/scalatest/Notifier;
   #99 = Utf8               atomicNotifier
  #100 = NameAndType        #99:#81       // atomicNotifier:()Ljava/util/concurrent/atomic/AtomicReference;
  #101 = Methodref          #79.#100      // org/scalatest/Engine.atomicNotifier:()Ljava/util/concurrent/atomic/AtomicReference;
  #102 = Utf8               org/scalatest/Notifier
  #103 = Class              #102          // org/scalatest/Notifier
  #104 = Utf8               alert$
  #105 = Utf8               (Lorg/scalatest/funspec/AnyFunSpecLike;)Lorg/scalatest/Alerter;
  #106 = Utf8               alert
  #107 = Utf8               ()Lorg/scalatest/Alerter;
  #108 = NameAndType        #106:#107     // alert:()Lorg/scalatest/Alerter;
  #109 = InterfaceMethodref #2.#108       // org/scalatest/funspec/AnyFunSpecLike.alert:()Lorg/scalatest/Alerter;
  #110 = Utf8               atomicAlerter
  #111 = NameAndType        #110:#81      // atomicAlerter:()Ljava/util/concurrent/atomic/AtomicReference;
  #112 = Methodref          #79.#111      // org/scalatest/Engine.atomicAlerter:()Ljava/util/concurrent/atomic/AtomicReference;
  #113 = Utf8               org/scalatest/Alerter
  #114 = Class              #113          // org/scalatest/Alerter
  #115 = Utf8               markup$
  #116 = Utf8               (Lorg/scalatest/funspec/AnyFunSpecLike;)Lorg/scalatest/Documenter;
  #117 = Utf8               markup
  #118 = Utf8               ()Lorg/scalatest/Documenter;
  #119 = NameAndType        #117:#118     // markup:()Lorg/scalatest/Documenter;
  #120 = InterfaceMethodref #2.#119       // org/scalatest/funspec/AnyFunSpecLike.markup:()Lorg/scalatest/Documenter;
  #121 = Utf8               atomicDocumenter
  #122 = NameAndType        #121:#81      // atomicDocumenter:()Ljava/util/concurrent/atomic/AtomicReference;
  #123 = Methodref          #79.#122      // org/scalatest/Engine.atomicDocumenter:()Ljava/util/concurrent/atomic/AtomicReference;
  #124 = Utf8               org/scalatest/Documenter
  #125 = Class              #124          // org/scalatest/Documenter
  #126 = Utf8               registerTestImpl
  #127 = Utf8               (Ljava/lang/String;Lscala/collection/immutable/Seq;Lscala/Function0;Lorg/scalactic/source/Position;)V
  #128 = Utf8               (Ljava/lang/String;Lscala/collection/immutable/Seq<Lorg/scalatest/Tag;>;Lscala/Function0<Ljava/lang/Object;>;Lorg/scalactic/source/Position;)V
  #129 = Utf8               testText
  #130 = Utf8               testTags
  #131 = Utf8               testFun
  #132 = Utf8               pos
  #133 = Utf8               org/scalatest/Transformer
  #134 = Class              #133          // org/scalatest/Transformer
  #135 = Utf8               <init>
  #136 = Utf8               (Lscala/Function0;)V
  #137 = NameAndType        #135:#136     // "<init>":(Lscala/Function0;)V
  #138 = Methodref          #134.#137     // org/scalatest/Transformer."<init>":(Lscala/Function0;)V
  #139 = MethodType         #87           //  ()Ljava/lang/Object;
  #140 = Utf8               $anonfun$registerTestImpl$1
  #141 = NameAndType        #140:#67      // $anonfun$registerTestImpl$1:()Ljava/lang/String;
  #142 = InterfaceMethodref #2.#141       // org/scalatest/funspec/AnyFunSpecLike.$anonfun$registerTestImpl$1:()Ljava/lang/String;
  #143 = MethodHandle       6:#142        // REF_invokeStatic org/scalatest/funspec/AnyFunSpecLike.$anonfun$registerTestImpl$1:()Ljava/lang/String;
  #144 = MethodType         #67           //  ()Ljava/lang/String;
  #145 = Integer            5
  #146 = Integer            1
  #147 = Utf8               java/lang/invoke/LambdaMetafactory
  #148 = Class              #147          // java/lang/invoke/LambdaMetafactory
  #149 = Utf8               altMetafactory
  #150 = Utf8               (Ljava/lang/invoke/MethodHandles$Lookup;Ljava/lang/String;Ljava/lang/invoke/MethodType;[Ljava/lang/Object;)Ljava/lang/invoke/CallSite;
  #151 = NameAndType        #149:#150     // altMetafactory:(Ljava/lang/invoke/MethodHandles$Lookup;Ljava/lang/String;Ljava/lang/invoke/MethodType;[Ljava/lang/Object;)Ljava/lang/invoke/CallSite;
  #152 = Methodref          #148.#151     // java/lang/invoke/LambdaMetafactory.altMetafactory:(Ljava/lang/invoke/MethodHandles$Lookup;Ljava/lang/String;Ljava/lang/invoke/MethodType;[Ljava/lang/Object;)Ljava/lang/invoke/CallSite;
  #153 = MethodHandle       6:#152        // REF_invokeStatic java/lang/invoke/LambdaMetafactory.altMetafactory:(Ljava/lang/invoke/MethodHandles$Lookup;Ljava/lang/String;Ljava/lang/invoke/MethodType;[Ljava/lang/Object;)Ljava/lang/invoke/CallSite;
  #154 = Utf8               apply
  #155 = Utf8               ()Lscala/Function0;
  #156 = NameAndType        #154:#155     // apply:()Lscala/Function0;
  #157 = InvokeDynamic      #0:#156       // #0:apply:()Lscala/Function0;
  #158 = NameAndType        #66:#67       // sourceFileName:()Ljava/lang/String;
  #159 = InterfaceMethodref #2.#158       // org/scalatest/funspec/AnyFunSpecLike.sourceFileName:()Ljava/lang/String;
  #160 = Utf8               registerTest
  #161 = String             #160          // registerTest
  #162 = Utf8               scala/None$
  #163 = Class              #162          // scala/None$
  #164 = Utf8               MODULE$
  #165 = Utf8               Lscala/None$;
  #166 = NameAndType        #164:#165     // MODULE$:Lscala/None$;
  #167 = Fieldref           #163.#166     // scala/None$.MODULE$:Lscala/None$;
  #168 = Utf8               scala/Some
  #169 = Class              #168          // scala/Some
  #170 = Utf8               (Ljava/lang/Object;)V
  #171 = NameAndType        #135:#170     // "<init>":(Ljava/lang/Object;)V
  #172 = Methodref          #169.#171     // scala/Some."<init>":(Ljava/lang/Object;)V
  #173 = Utf8               (Ljava/lang/String;Ljava/lang/Object;Lscala/Function0;Ljava/lang/String;Ljava/lang/String;IILscala/Option;Lscala/Option;Lscala/Option;Lscala/Option;Lscala/collection/immutable/Seq;)Ljava/lang/String;
  #174 = NameAndType        #160:#173     // registerTest:(Ljava/lang/String;Ljava/lang/Object;Lscala/Function0;Ljava/lang/String;Ljava/lang/String;IILscala/Option;Lscala/Option;Lscala/Option;Lscala/Option;Lscala/collection/immutable/Seq;)Ljava/lang/String;
  #175 = Methodref          #79.#174      // org/scalatest/Engine.registerTest:(Ljava/lang/String;Ljava/lang/Object;Lscala/Function0;Ljava/lang/String;Ljava/lang/String;IILscala/Option;Lscala/Option;Lscala/Option;Lscala/Option;Lscala/collection/immutable/Seq;)Ljava/lang/String;
  #176 = Utf8               stackDepthAdjustment
  #177 = Utf8               I
  #178 = Utf8               Ljava/lang/String;
  #179 = Utf8               Lscala/collection/immutable/Seq;
  #180 = Utf8               Lscala/Function0;
  #181 = Utf8               Lorg/scalactic/source/Position;
  #182 = Utf8               registerTest$
  #183 = Utf8               (Lorg/scalatest/funspec/AnyFunSpecLike;Ljava/lang/String;Lscala/collection/immutable/Seq;Lscala/Function0;Lorg/scalactic/source/Position;)V
  #184 = NameAndType        #160:#127     // registerTest:(Ljava/lang/String;Lscala/collection/immutable/Seq;Lscala/Function0;Lorg/scalactic/source/Position;)V
  #185 = InterfaceMethodref #2.#184       // org/scalatest/funspec/AnyFunSpecLike.registerTest:(Ljava/lang/String;Lscala/collection/immutable/Seq;Lscala/Function0;Lorg/scalactic/source/Position;)V
  #186 = NameAndType        #126:#127     // registerTestImpl:(Ljava/lang/String;Lscala/collection/immutable/Seq;Lscala/Function0;Lorg/scalactic/source/Position;)V
  #187 = InterfaceMethodref #2.#186       // org/scalatest/funspec/AnyFunSpecLike.registerTestImpl:(Ljava/lang/String;Lscala/collection/immutable/Seq;Lscala/Function0;Lorg/scalactic/source/Position;)V
  #188 = Utf8               registerIgnoredTestImpl
  #189 = Utf8               $anonfun$registerIgnoredTestImpl$1
  #190 = NameAndType        #189:#67      // $anonfun$registerIgnoredTestImpl$1:()Ljava/lang/String;
  #191 = InterfaceMethodref #2.#190       // org/scalatest/funspec/AnyFunSpecLike.$anonfun$registerIgnoredTestImpl$1:()Ljava/lang/String;
  #192 = MethodHandle       6:#191        // REF_invokeStatic org/scalatest/funspec/AnyFunSpecLike.$anonfun$registerIgnoredTestImpl$1:()Ljava/lang/String;
  #193 = InvokeDynamic      #1:#156       // #1:apply:()Lscala/Function0;
  #194 = Utf8               registerIgnoredTest
  #195 = String             #194          // registerIgnoredTest
  #196 = Utf8               (Ljava/lang/String;Ljava/lang/Object;Lscala/Function0;Ljava/lang/String;Ljava/lang/String;IILscala/Option;Lscala/Option;Lscala/collection/immutable/Seq;)V
  #197 = NameAndType        #194:#196     // registerIgnoredTest:(Ljava/lang/String;Ljava/lang/Object;Lscala/Function0;Ljava/lang/String;Ljava/lang/String;IILscala/Option;Lscala/Option;Lscala/collection/immutable/Seq;)V
  #198 = Methodref          #79.#197      // org/scalatest/Engine.registerIgnoredTest:(Ljava/lang/String;Ljava/lang/Object;Lscala/Function0;Ljava/lang/String;Ljava/lang/String;IILscala/Option;Lscala/Option;Lscala/collection/immutable/Seq;)V
  #199 = Utf8               registerIgnoredTest$
  #200 = NameAndType        #194:#127     // registerIgnoredTest:(Ljava/lang/String;Lscala/collection/immutable/Seq;Lscala/Function0;Lorg/scalactic/source/Position;)V
  #201 = InterfaceMethodref #2.#200       // org/scalatest/funspec/AnyFunSpecLike.registerIgnoredTest:(Ljava/lang/String;Lscala/collection/immutable/Seq;Lscala/Function0;Lorg/scalactic/source/Position;)V
  #202 = NameAndType        #188:#127     // registerIgnoredTestImpl:(Ljava/lang/String;Lscala/collection/immutable/Seq;Lscala/Function0;Lorg/scalactic/source/Position;)V
  #203 = InterfaceMethodref #2.#202       // org/scalatest/funspec/AnyFunSpecLike.registerIgnoredTestImpl:(Ljava/lang/String;Lscala/collection/immutable/Seq;Lscala/Function0;Lorg/scalactic/source/Position;)V
  #204 = Utf8               it
  #205 = Utf8               ()Lorg/scalatest/funspec/AnyFunSpecLike$ItWord;
  #206 = Utf8               they
  #207 = Utf8               ()Lorg/scalatest/funspec/AnyFunSpecLike$TheyWord;
  #208 = Utf8               ignoreImpl
  #209 = Utf8               $anonfun$ignoreImpl$1
  #210 = NameAndType        #209:#67      // $anonfun$ignoreImpl$1:()Ljava/lang/String;
  #211 = InterfaceMethodref #2.#210       // org/scalatest/funspec/AnyFunSpecLike.$anonfun$ignoreImpl$1:()Ljava/lang/String;
  #212 = MethodHandle       6:#211        // REF_invokeStatic org/scalatest/funspec/AnyFunSpecLike.$anonfun$ignoreImpl$1:()Ljava/lang/String;
  #213 = InvokeDynamic      #2:#156       // #2:apply:()Lscala/Function0;
  #214 = Utf8               ignore
  #215 = String             #214          // ignore
  #216 = Utf8               stackDepth
  #217 = Utf8               ignore$
  #218 = NameAndType        #214:#127     // ignore:(Ljava/lang/String;Lscala/collection/immutable/Seq;Lscala/Function0;Lorg/scalactic/source/Position;)V
  #219 = InterfaceMethodref #2.#218       // org/scalatest/funspec/AnyFunSpecLike.ignore:(Ljava/lang/String;Lscala/collection/immutable/Seq;Lscala/Function0;Lorg/scalactic/source/Position;)V
  #220 = NameAndType        #208:#127     // ignoreImpl:(Ljava/lang/String;Lscala/collection/immutable/Seq;Lscala/Function0;Lorg/scalactic/source/Position;)V
  #221 = InterfaceMethodref #2.#220       // org/scalatest/funspec/AnyFunSpecLike.ignoreImpl:(Ljava/lang/String;Lscala/collection/immutable/Seq;Lscala/Function0;Lorg/scalactic/source/Position;)V
  #222 = Utf8               describeImpl
  #223 = Utf8               (Ljava/lang/String;Lscala/Function0;Lorg/scalactic/source/Position;)V
  #224 = Utf8               (Ljava/lang/String;Lscala/Function0<Lscala/runtime/BoxedUnit;>;Lorg/scalactic/source/Position;)V
  #225 = Utf8               description
  #226 = Utf8               fun
  #227 = Utf8               java/lang/Throwable
  #228 = Class              #227          // java/lang/Throwable
  #229 = Utf8               $anonfun$describeImpl$1
  #230 = NameAndType        #229:#67      // $anonfun$describeImpl$1:()Ljava/lang/String;
  #231 = InterfaceMethodref #2.#230       // org/scalatest/funspec/AnyFunSpecLike.$anonfun$describeImpl$1:()Ljava/lang/String;
  #232 = MethodHandle       6:#231        // REF_invokeStatic org/scalatest/funspec/AnyFunSpecLike.$anonfun$describeImpl$1:()Ljava/lang/String;
  #233 = InvokeDynamic      #3:#156       // #3:apply:()Lscala/Function0;
  #234 = Utf8               describe
  #235 = String             #234          // describe
  #236 = Utf8               registerNestedBranch
  #237 = Utf8               (Ljava/lang/String;Lscala/Option;Lscala/Function0;Lscala/Function0;Ljava/lang/String;Ljava/lang/String;IILscala/Option;Lscala/Option;)V
  #238 = NameAndType        #236:#237     // registerNestedBranch:(Ljava/lang/String;Lscala/Option;Lscala/Function0;Lscala/Function0;Ljava/lang/String;Ljava/lang/String;IILscala/Option;Lscala/Option;)V
  #239 = Methodref          #79.#238      // org/scalatest/Engine.registerNestedBranch:(Ljava/lang/String;Lscala/Option;Lscala/Function0;Lscala/Function0;Ljava/lang/String;Ljava/lang/String;IILscala/Option;Lscala/Option;)V
  #240 = Utf8               org/scalatest/exceptions/TestFailedException
  #241 = Class              #240          // org/scalatest/exceptions/TestFailedException
  #242 = Utf8               org/scalatest/exceptions/NotAllowedException
  #243 = Class              #242          // org/scalatest/exceptions/NotAllowedException
  #244 = Utf8               org/scalatest/FailureMessages$
  #245 = Class              #244          // org/scalatest/FailureMessages$
  #246 = Utf8               Lorg/scalatest/FailureMessages$;
  #247 = NameAndType        #164:#246     // MODULE$:Lorg/scalatest/FailureMessages$;
  #248 = Fieldref           #245.#247     // org/scalatest/FailureMessages$.MODULE$:Lorg/scalatest/FailureMessages$;
  #249 = Utf8               assertionShouldBePutInsideItOrTheyClauseNotDescribeClause
  #250 = NameAndType        #249:#67      // assertionShouldBePutInsideItOrTheyClauseNotDescribeClause:()Ljava/lang/String;
  #251 = Methodref          #245.#250     // org/scalatest/FailureMessages$.assertionShouldBePutInsideItOrTheyClauseNotDescribeClause:()Ljava/lang/String;
  #252 = Utf8               position
  #253 = Utf8               ()Lscala/Option;
  #254 = NameAndType        #252:#253     // position:()Lscala/Option;
  #255 = Methodref          #241.#254     // org/scalatest/exceptions/TestFailedException.position:()Lscala/Option;
  #256 = Utf8               $anonfun$describeImpl$2
  #257 = Utf8               (Lorg/scalactic/source/Position;)Lorg/scalactic/source/Position;
  #258 = NameAndType        #256:#257     // $anonfun$describeImpl$2:(Lorg/scalactic/source/Position;)Lorg/scalactic/source/Position;
  #259 = InterfaceMethodref #2.#258       // org/scalatest/funspec/AnyFunSpecLike.$anonfun$describeImpl$2:(Lorg/scalactic/source/Position;)Lorg/scalactic/source/Position;
  #260 = MethodHandle       6:#259        // REF_invokeStatic org/scalatest/funspec/AnyFunSpecLike.$anonfun$describeImpl$2:(Lorg/scalactic/source/Position;)Lorg/scalactic/source/Position;
  #261 = Utf8               ()Lorg/scalactic/source/Position;
  #262 = MethodType         #261          //  ()Lorg/scalactic/source/Position;
  #263 = Utf8               (Lorg/scalactic/source/Position;)Lscala/Function0;
  #264 = NameAndType        #154:#263     // apply:(Lorg/scalactic/source/Position;)Lscala/Function0;
  #265 = InvokeDynamic      #4:#264       // #4:apply:(Lorg/scalactic/source/Position;)Lscala/Function0;
  #266 = Utf8               scala/Option
  #267 = Class              #266          // scala/Option
  #268 = Utf8               getOrElse
  #269 = Utf8               (Lscala/Function0;)Ljava/lang/Object;
  #270 = NameAndType        #268:#269     // getOrElse:(Lscala/Function0;)Ljava/lang/Object;
  #271 = Methodref          #267.#270     // scala/Option.getOrElse:(Lscala/Function0;)Ljava/lang/Object;
  #272 = Utf8               org/scalactic/source/Position
  #273 = Class              #272          // org/scalactic/source/Position
  #274 = Utf8               (Ljava/lang/String;Lscala/Option;Lorg/scalactic/source/Position;)V
  #275 = NameAndType        #135:#274     // "<init>":(Ljava/lang/String;Lscala/Option;Lorg/scalactic/source/Position;)V
  #276 = Methodref          #243.#275     // org/scalatest/exceptions/NotAllowedException."<init>":(Ljava/lang/String;Lscala/Option;Lorg/scalactic/source/Position;)V
  #277 = Utf8               org/scalatest/exceptions/TestCanceledException
  #278 = Class              #277          // org/scalatest/exceptions/TestCanceledException
  #279 = Methodref          #278.#254     // org/scalatest/exceptions/TestCanceledException.position:()Lscala/Option;
  #280 = Utf8               $anonfun$describeImpl$3
  #281 = NameAndType        #280:#257     // $anonfun$describeImpl$3:(Lorg/scalactic/source/Position;)Lorg/scalactic/source/Position;
  #282 = InterfaceMethodref #2.#281       // org/scalatest/funspec/AnyFunSpecLike.$anonfun$describeImpl$3:(Lorg/scalactic/source/Position;)Lorg/scalactic/source/Position;
  #283 = MethodHandle       6:#282        // REF_invokeStatic org/scalatest/funspec/AnyFunSpecLike.$anonfun$describeImpl$3:(Lorg/scalactic/source/Position;)Lorg/scalactic/source/Position;
  #284 = InvokeDynamic      #5:#264       // #5:apply:(Lorg/scalactic/source/Position;)Lscala/Function0;
  #285 = Utf8               org/scalatest/exceptions/DuplicateTestNameException
  #286 = Class              #285          // org/scalatest/exceptions/DuplicateTestNameException
  #287 = Utf8               org/scalactic/Prettifier$
  #288 = Class              #287          // org/scalactic/Prettifier$
  #289 = Utf8               Lorg/scalactic/Prettifier$;
  #290 = NameAndType        #164:#289     // MODULE$:Lorg/scalactic/Prettifier$;
  #291 = Fieldref           #288.#290     // org/scalactic/Prettifier$.MODULE$:Lorg/scalactic/Prettifier$;
  #292 = Utf8               default
  #293 = Utf8               ()Lorg/scalactic/Prettifier;
  #294 = NameAndType        #292:#293     // default:()Lorg/scalactic/Prettifier;
  #295 = Methodref          #288.#294     // org/scalactic/Prettifier$.default:()Lorg/scalactic/Prettifier;
  #296 = Utf8               org/scalatest/UnquotedString$
  #297 = Class              #296          // org/scalatest/UnquotedString$
  #298 = Utf8               Lorg/scalatest/UnquotedString$;
  #299 = NameAndType        #164:#298     // MODULE$:Lorg/scalatest/UnquotedString$;
  #300 = Fieldref           #297.#299     // org/scalatest/UnquotedString$.MODULE$:Lorg/scalatest/UnquotedString$;
  #301 = Utf8               getClass
  #302 = Utf8               ()Ljava/lang/Class;
  #303 = NameAndType        #301:#302     // getClass:()Ljava/lang/Class;
  #304 = Methodref          #286.#303     // org/scalatest/exceptions/DuplicateTestNameException.getClass:()Ljava/lang/Class;
  #305 = Utf8               java/lang/Class
  #306 = Class              #305          // java/lang/Class
  #307 = Utf8               getName
  #308 = NameAndType        #307:#67      // getName:()Ljava/lang/String;
  #309 = Methodref          #306.#308     // java/lang/Class.getName:()Ljava/lang/String;
  #310 = Utf8               (Ljava/lang/String;)Lorg/scalatest/UnquotedString;
  #311 = NameAndType        #154:#310     // apply:(Ljava/lang/String;)Lorg/scalatest/UnquotedString;
  #312 = Methodref          #297.#311     // org/scalatest/UnquotedString$.apply:(Ljava/lang/String;)Lorg/scalatest/UnquotedString;
  #313 = Utf8               getMessage
  #314 = NameAndType        #313:#67      // getMessage:()Ljava/lang/String;
  #315 = Methodref          #286.#314     // org/scalatest/exceptions/DuplicateTestNameException.getMessage:()Ljava/lang/String;
  #316 = Utf8               exceptionWasThrownInDescribeClause
  #317 = Utf8               (Lorg/scalactic/Prettifier;Ljava/lang/Object;Ljava/lang/Object;Ljava/lang/Object;)Ljava/lang/String;
  #318 = NameAndType        #316:#317     // exceptionWasThrownInDescribeClause:(Lorg/scalactic/Prettifier;Ljava/lang/Object;Ljava/lang/Object;Ljava/lang/Object;)Ljava/lang/String;
  #319 = Methodref          #245.#318     // org/scalatest/FailureMessages$.exceptionWasThrownInDescribeClause:(Lorg/scalactic/Prettifier;Ljava/lang/Object;Ljava/lang/Object;Ljava/lang/Object;)Ljava/lang/String;
  #320 = Methodref          #286.#254     // org/scalatest/exceptions/DuplicateTestNameException.position:()Lscala/Option;
  #321 = Utf8               $anonfun$describeImpl$4
  #322 = NameAndType        #321:#257     // $anonfun$describeImpl$4:(Lorg/scalactic/source/Position;)Lorg/scalactic/source/Position;
  #323 = InterfaceMethodref #2.#322       // org/scalatest/funspec/AnyFunSpecLike.$anonfun$describeImpl$4:(Lorg/scalactic/source/Position;)Lorg/scalactic/source/Position;
  #324 = MethodHandle       6:#323        // REF_invokeStatic org/scalatest/funspec/AnyFunSpecLike.$anonfun$describeImpl$4:(Lorg/scalactic/source/Position;)Lorg/scalactic/source/Position;
  #325 = InvokeDynamic      #6:#264       // #6:apply:(Lorg/scalactic/source/Position;)Lscala/Function0;
  #326 = Utf8               org/scalatest/Suite$
  #327 = Class              #326          // org/scalatest/Suite$
  #328 = Utf8               Lorg/scalatest/Suite$;
  #329 = NameAndType        #164:#328     // MODULE$:Lorg/scalatest/Suite$;
  #330 = Fieldref           #327.#329     // org/scalatest/Suite$.MODULE$:Lorg/scalatest/Suite$;
  #331 = Utf8               anExceptionThatShouldCauseAnAbort
  #332 = Utf8               (Ljava/lang/Throwable;)Z
  #333 = NameAndType        #331:#332     // anExceptionThatShouldCauseAnAbort:(Ljava/lang/Throwable;)Z
  #334 = Methodref          #327.#333     // org/scalatest/Suite$.anExceptionThatShouldCauseAnAbort:(Ljava/lang/Throwable;)Z
  #335 = Methodref          #228.#303     // java/lang/Throwable.getClass:()Ljava/lang/Class;
  #336 = Methodref          #228.#314     // java/lang/Throwable.getMessage:()Ljava/lang/String;
  #337 = Utf8               java/lang/String
  #338 = Class              #337          // java/lang/String
  #339 = Utf8               scala/Function0
  #340 = Class              #339          // scala/Function0
  #341 = Utf8               describe$
  #342 = Utf8               (Lorg/scalatest/funspec/AnyFunSpecLike;Ljava/lang/String;Lscala/Function0;Lorg/scalactic/source/Position;)V
  #343 = NameAndType        #234:#223     // describe:(Ljava/lang/String;Lscala/Function0;Lorg/scalactic/source/Position;)V
  #344 = InterfaceMethodref #2.#343       // org/scalatest/funspec/AnyFunSpecLike.describe:(Ljava/lang/String;Lscala/Function0;Lorg/scalactic/source/Position;)V
  #345 = NameAndType        #222:#223     // describeImpl:(Ljava/lang/String;Lscala/Function0;Lorg/scalactic/source/Position;)V
  #346 = InterfaceMethodref #2.#345       // org/scalatest/funspec/AnyFunSpecLike.describeImpl:(Ljava/lang/String;Lscala/Function0;Lorg/scalactic/source/Position;)V
  #347 = Utf8               testNames$
  #348 = Utf8               (Lorg/scalatest/funspec/AnyFunSpecLike;)Lscala/collection/immutable/Set;
  #349 = Utf8               testNames
  #350 = Utf8               ()Lscala/collection/immutable/Set;
  #351 = NameAndType        #349:#350     // testNames:()Lscala/collection/immutable/Set;
  #352 = InterfaceMethodref #2.#351       // org/scalatest/funspec/AnyFunSpecLike.testNames:()Lscala/collection/immutable/Set;
  #353 = Utf8               ()Lscala/collection/immutable/Set<Ljava/lang/String;>;
  #354 = Utf8               org/scalatest/InsertionOrderSet$
  #355 = Class              #354          // org/scalatest/InsertionOrderSet$
  #356 = Utf8               Lorg/scalatest/InsertionOrderSet$;
  #357 = NameAndType        #164:#356     // MODULE$:Lorg/scalatest/InsertionOrderSet$;
  #358 = Fieldref           #355.#357     // org/scalatest/InsertionOrderSet$.MODULE$:Lorg/scalatest/InsertionOrderSet$;
  #359 = Utf8               atomic
  #360 = NameAndType        #359:#81      // atomic:()Ljava/util/concurrent/atomic/AtomicReference;
  #361 = Methodref          #79.#360      // org/scalatest/Engine.atomic:()Ljava/util/concurrent/atomic/AtomicReference;
  #362 = Utf8               testNamesList
  #363 = Utf8               ()Lscala/collection/immutable/List;
  #364 = NameAndType        #362:#363     // testNamesList:()Lscala/collection/immutable/List;
  #365 = Methodref          #30.#364      // org/scalatest/SuperEngine$Bundle.testNamesList:()Lscala/collection/immutable/List;
  #366 = Utf8               (Lscala/collection/immutable/List;)Lscala/collection/immutable/Set;
  #367 = NameAndType        #154:#366     // apply:(Lscala/collection/immutable/List;)Lscala/collection/immutable/Set;
  #368 = Methodref          #355.#367     // org/scalatest/InsertionOrderSet$.apply:(Lscala/collection/immutable/List;)Lscala/collection/immutable/Set;
  #369 = Utf8               runTest$
  #370 = Utf8               (Lorg/scalatest/funspec/AnyFunSpecLike;Ljava/lang/String;Lorg/scalatest/Args;)Lorg/scalatest/Status;
  #371 = Utf8               runTest
  #372 = Utf8               (Ljava/lang/String;Lorg/scalatest/Args;)Lorg/scalatest/Status;
  #373 = NameAndType        #371:#372     // runTest:(Ljava/lang/String;Lorg/scalatest/Args;)Lorg/scalatest/Status;
  #374 = InterfaceMethodref #2.#373       // org/scalatest/funspec/AnyFunSpecLike.runTest:(Ljava/lang/String;Lorg/scalatest/Args;)Lorg/scalatest/Status;
  #375 = Utf8               Lorg/scalatest/Args;
  #376 = Utf8               (Ljava/lang/Object;)Ljava/lang/Object;
  #377 = MethodType         #376          //  (Ljava/lang/Object;)Ljava/lang/Object;
  #378 = Utf8               $anonfun$runTest$1
  #379 = Utf8               (Lorg/scalatest/funspec/AnyFunSpecLike;Lorg/scalatest/Args;Ljava/lang/String;Lorg/scalatest/SuperEngine$TestLeaf;)Lorg/scalatest/Outcome;
  #380 = NameAndType        #378:#379     // $anonfun$runTest$1:(Lorg/scalatest/funspec/AnyFunSpecLike;Lorg/scalatest/Args;Ljava/lang/String;Lorg/scalatest/SuperEngine$TestLeaf;)Lorg/scalatest/Outcome;
  #381 = InterfaceMethodref #2.#380       // org/scalatest/funspec/AnyFunSpecLike.$anonfun$runTest$1:(Lorg/scalatest/funspec/AnyFunSpecLike;Lorg/scalatest/Args;Ljava/lang/String;Lorg/scalatest/SuperEngine$TestLeaf;)Lorg/scalatest/Outcome;
  #382 = MethodHandle       6:#381        // REF_invokeStatic org/scalatest/funspec/AnyFunSpecLike.$anonfun$runTest$1:(Lorg/scalatest/funspec/AnyFunSpecLike;Lorg/scalatest/Args;Ljava/lang/String;Lorg/scalatest/SuperEngine$TestLeaf;)Lorg/scalatest/Outcome;
  #383 = Utf8               (Lorg/scalatest/SuperEngine$TestLeaf;)Lorg/scalatest/Outcome;
  #384 = MethodType         #383          //  (Lorg/scalatest/SuperEngine$TestLeaf;)Lorg/scalatest/Outcome;
  #385 = Utf8               (Lorg/scalatest/funspec/AnyFunSpecLike;Lorg/scalatest/Args;Ljava/lang/String;)Lscala/Function1;
  #386 = NameAndType        #154:#385     // apply:(Lorg/scalatest/funspec/AnyFunSpecLike;Lorg/scalatest/Args;Ljava/lang/String;)Lscala/Function1;
  #387 = InvokeDynamic      #7:#386       // #7:apply:(Lorg/scalatest/funspec/AnyFunSpecLike;Lorg/scalatest/Args;Ljava/lang/String;)Lscala/Function1;
  #388 = Utf8               runTestImpl
  #389 = Utf8               (Lorg/scalatest/Suite;Ljava/lang/String;Lorg/scalatest/Args;ZLscala/Function1;)Lorg/scalatest/Status;
  #390 = NameAndType        #388:#389     // runTestImpl:(Lorg/scalatest/Suite;Ljava/lang/String;Lorg/scalatest/Args;ZLscala/Function1;)Lorg/scalatest/Status;
  #391 = Methodref          #79.#390      // org/scalatest/Engine.runTestImpl:(Lorg/scalatest/Suite;Ljava/lang/String;Lorg/scalatest/Args;ZLscala/Function1;)Lorg/scalatest/Status;
  #392 = Utf8               tags$
  #393 = Utf8               (Lorg/scalatest/funspec/AnyFunSpecLike;)Lscala/collection/immutable/Map;
  #394 = Utf8               tags
  #395 = Utf8               ()Lscala/collection/immutable/Map;
  #396 = NameAndType        #394:#395     // tags:()Lscala/collection/immutable/Map;
  #397 = InterfaceMethodref #2.#396       // org/scalatest/funspec/AnyFunSpecLike.tags:()Lscala/collection/immutable/Map;
  #398 = Utf8               ()Lscala/collection/immutable/Map<Ljava/lang/String;Lscala/collection/immutable/Set<Ljava/lang/String;>;>;
  #399 = Utf8               tagsMap
  #400 = NameAndType        #399:#395     // tagsMap:()Lscala/collection/immutable/Map;
  #401 = Methodref          #30.#400      // org/scalatest/SuperEngine$Bundle.tagsMap:()Lscala/collection/immutable/Map;
  #402 = Utf8               autoTagClassAnnotations
  #403 = Utf8               (Lscala/collection/immutable/Map;Lorg/scalatest/Suite;)Lscala/collection/immutable/Map;
  #404 = NameAndType        #402:#403     // autoTagClassAnnotations:(Lscala/collection/immutable/Map;Lorg/scalatest/Suite;)Lscala/collection/immutable/Map;
  #405 = Methodref          #327.#404     // org/scalatest/Suite$.autoTagClassAnnotations:(Lscala/collection/immutable/Map;Lorg/scalatest/Suite;)Lscala/collection/immutable/Map;
  #406 = Utf8               runTests$
  #407 = Utf8               (Lorg/scalatest/funspec/AnyFunSpecLike;Lscala/Option;Lorg/scalatest/Args;)Lorg/scalatest/Status;
  #408 = Utf8               runTests
  #409 = NameAndType        #408:#61      // runTests:(Lscala/Option;Lorg/scalatest/Args;)Lorg/scalatest/Status;
  #410 = InterfaceMethodref #2.#409       // org/scalatest/funspec/AnyFunSpecLike.runTests:(Lscala/Option;Lorg/scalatest/Args;)Lorg/scalatest/Status;
  #411 = Utf8               Lscala/Option;
  #412 = Utf8               (Lscala/Option<Ljava/lang/String;>;Lorg/scalatest/Args;)Lorg/scalatest/Status;
  #413 = Utf8               (Ljava/lang/Object;Ljava/lang/Object;)Ljava/lang/Object;
  #414 = MethodType         #413          //  (Ljava/lang/Object;Ljava/lang/Object;)Ljava/lang/Object;
  #415 = Utf8               $anonfun$runTests$1
  #416 = NameAndType        #415:#370     // $anonfun$runTests$1:(Lorg/scalatest/funspec/AnyFunSpecLike;Ljava/lang/String;Lorg/scalatest/Args;)Lorg/scalatest/Status;
  #417 = InterfaceMethodref #2.#416       // org/scalatest/funspec/AnyFunSpecLike.$anonfun$runTests$1:(Lorg/scalatest/funspec/AnyFunSpecLike;Ljava/lang/String;Lorg/scalatest/Args;)Lorg/scalatest/Status;
  #418 = MethodHandle       6:#417        // REF_invokeStatic org/scalatest/funspec/AnyFunSpecLike.$anonfun$runTests$1:(Lorg/scalatest/funspec/AnyFunSpecLike;Ljava/lang/String;Lorg/scalatest/Args;)Lorg/scalatest/Status;
  #419 = MethodType         #372          //  (Ljava/lang/String;Lorg/scalatest/Args;)Lorg/scalatest/Status;
  #420 = Utf8               (Lorg/scalatest/funspec/AnyFunSpecLike;)Lscala/Function2;
  #421 = NameAndType        #154:#420     // apply:(Lorg/scalatest/funspec/AnyFunSpecLike;)Lscala/Function2;
  #422 = InvokeDynamic      #8:#421       // #8:apply:(Lorg/scalatest/funspec/AnyFunSpecLike;)Lscala/Function2;
  #423 = Utf8               runTestsImpl
  #424 = Utf8               (Lorg/scalatest/Suite;Lscala/Option;Lorg/scalatest/Args;Lorg/scalatest/Informer;ZLscala/Function2;)Lorg/scalatest/Status;
  #425 = NameAndType        #423:#424     // runTestsImpl:(Lorg/scalatest/Suite;Lscala/Option;Lorg/scalatest/Args;Lorg/scalatest/Informer;ZLscala/Function2;)Lorg/scalatest/Status;
  #426 = Methodref          #79.#425      // org/scalatest/Engine.runTestsImpl:(Lorg/scalatest/Suite;Lscala/Option;Lorg/scalatest/Args;Lorg/scalatest/Informer;ZLscala/Function2;)Lorg/scalatest/Status;
  #427 = Utf8               run$
  #428 = Utf8               run
  #429 = NameAndType        #428:#61      // run:(Lscala/Option;Lorg/scalatest/Args;)Lorg/scalatest/Status;
  #430 = InterfaceMethodref #2.#429       // org/scalatest/funspec/AnyFunSpecLike.run:(Lscala/Option;Lorg/scalatest/Args;)Lorg/scalatest/Status;
  #431 = Utf8               $anonfun$run$1
  #432 = NameAndType        #431:#407     // $anonfun$run$1:(Lorg/scalatest/funspec/AnyFunSpecLike;Lscala/Option;Lorg/scalatest/Args;)Lorg/scalatest/Status;
  #433 = InterfaceMethodref #2.#432       // org/scalatest/funspec/AnyFunSpecLike.$anonfun$run$1:(Lorg/scalatest/funspec/AnyFunSpecLike;Lscala/Option;Lorg/scalatest/Args;)Lorg/scalatest/Status;
  #434 = MethodHandle       6:#433        // REF_invokeStatic org/scalatest/funspec/AnyFunSpecLike.$anonfun$run$1:(Lorg/scalatest/funspec/AnyFunSpecLike;Lscala/Option;Lorg/scalatest/Args;)Lorg/scalatest/Status;
  #435 = MethodType         #61           //  (Lscala/Option;Lorg/scalatest/Args;)Lorg/scalatest/Status;
  #436 = InvokeDynamic      #9:#421       // #9:apply:(Lorg/scalatest/funspec/AnyFunSpecLike;)Lscala/Function2;
  #437 = Utf8               runImpl
  #438 = Utf8               (Lorg/scalatest/Suite;Lscala/Option;Lorg/scalatest/Args;Lscala/Function2;)Lorg/scalatest/Status;
  #439 = NameAndType        #437:#438     // runImpl:(Lorg/scalatest/Suite;Lscala/Option;Lorg/scalatest/Args;Lscala/Function2;)Lorg/scalatest/Status;
  #440 = Methodref          #79.#439      // org/scalatest/Engine.runImpl:(Lorg/scalatest/Suite;Lscala/Option;Lorg/scalatest/Args;Lscala/Function2;)Lorg/scalatest/Status;
  #441 = Utf8               behave
  #442 = Utf8               ()Lorg/scalatest/verbs/BehaveWord;
  #443 = Utf8               styleName
  #444 = Utf8               testDataFor$
  #445 = Utf8               (Lorg/scalatest/funspec/AnyFunSpecLike;Ljava/lang/String;Lorg/scalatest/ConfigMap;)Lorg/scalatest/TestData;
  #446 = Utf8               theConfigMap
  #447 = Utf8               testDataFor
  #448 = Utf8               (Ljava/lang/String;Lorg/scalatest/ConfigMap;)Lorg/scalatest/TestData;
  #449 = NameAndType        #447:#448     // testDataFor:(Ljava/lang/String;Lorg/scalatest/ConfigMap;)Lorg/scalatest/TestData;
  #450 = InterfaceMethodref #2.#449       // org/scalatest/funspec/AnyFunSpecLike.testDataFor:(Ljava/lang/String;Lorg/scalatest/ConfigMap;)Lorg/scalatest/TestData;
  #451 = Utf8               Lorg/scalatest/ConfigMap;
  #452 = Utf8               createTestDataFor
  #453 = Utf8               (Ljava/lang/String;Lorg/scalatest/ConfigMap;Lorg/scalatest/Suite;)Lorg/scalatest/TestData;
  #454 = NameAndType        #452:#453     // createTestDataFor:(Ljava/lang/String;Lorg/scalatest/ConfigMap;Lorg/scalatest/Suite;)Lorg/scalatest/TestData;
  #455 = Methodref          #79.#454      // org/scalatest/Engine.createTestDataFor:(Ljava/lang/String;Lorg/scalatest/ConfigMap;Lorg/scalatest/Suite;)Lorg/scalatest/TestData;
  #456 = Utf8               testDataFor$default$2$
  #457 = Utf8               (Lorg/scalatest/funspec/AnyFunSpecLike;)Lorg/scalatest/ConfigMap;
  #458 = Utf8               testDataFor$default$2
  #459 = Utf8               ()Lorg/scalatest/ConfigMap;
  #460 = NameAndType        #458:#459     // testDataFor$default$2:()Lorg/scalatest/ConfigMap;
  #461 = InterfaceMethodref #2.#460       // org/scalatest/funspec/AnyFunSpecLike.testDataFor$default$2:()Lorg/scalatest/ConfigMap;
  #462 = Utf8               org/scalatest/ConfigMap$
  #463 = Class              #462          // org/scalatest/ConfigMap$
  #464 = Utf8               Lorg/scalatest/ConfigMap$;
  #465 = NameAndType        #164:#464     // MODULE$:Lorg/scalatest/ConfigMap$;
  #466 = Fieldref           #463.#465     // org/scalatest/ConfigMap$.MODULE$:Lorg/scalatest/ConfigMap$;
  #467 = Utf8               empty
  #468 = NameAndType        #467:#459     // empty:()Lorg/scalatest/ConfigMap;
  #469 = Methodref          #463.#468     // org/scalatest/ConfigMap$.empty:()Lorg/scalatest/ConfigMap;
  #470 = Utf8               $anonfun$engine$1
  #471 = Utf8               org/scalatest/Resources$
  #472 = Class              #471          // org/scalatest/Resources$
  #473 = Utf8               Lorg/scalatest/Resources$;
  #474 = NameAndType        #164:#473     // MODULE$:Lorg/scalatest/Resources$;
  #475 = Fieldref           #472.#474     // org/scalatest/Resources$.MODULE$:Lorg/scalatest/Resources$;
  #476 = Utf8               concurrentSpecMod
  #477 = NameAndType        #476:#67      // concurrentSpecMod:()Ljava/lang/String;
  #478 = Methodref          #472.#477     // org/scalatest/Resources$.concurrentSpecMod:()Ljava/lang/String;
  #479 = Utf8               testCannotBeNestedInsideAnotherTest
  #480 = NameAndType        #479:#67      // testCannotBeNestedInsideAnotherTest:()Ljava/lang/String;
  #481 = Methodref          #472.#480     // org/scalatest/Resources$.testCannotBeNestedInsideAnotherTest:()Ljava/lang/String;
  #482 = Utf8               ignoreCannotAppearInsideAnItOrAThey
  #483 = NameAndType        #482:#67      // ignoreCannotAppearInsideAnItOrAThey:()Ljava/lang/String;
  #484 = Methodref          #472.#483     // org/scalatest/Resources$.ignoreCannotAppearInsideAnItOrAThey:()Ljava/lang/String;
  #485 = Utf8               describeCannotAppearInsideAnIt
  #486 = NameAndType        #485:#67      // describeCannotAppearInsideAnIt:()Ljava/lang/String;
  #487 = Methodref          #472.#486     // org/scalatest/Resources$.describeCannotAppearInsideAnIt:()Ljava/lang/String;
  #488 = Utf8               pos$1
  #489 = Utf8               invokeWithFixture$1
  #490 = Utf8               (Lorg/scalatest/SuperEngine$TestLeaf;Lorg/scalatest/Args;Ljava/lang/String;)Lorg/scalatest/Outcome;
  #491 = Utf8               theTest
  #492 = Utf8               args$1
  #493 = Utf8               testName$1
  #494 = Utf8               org/scalatest/Args
  #495 = Class              #494          // org/scalatest/Args
  #496 = Utf8               configMap
  #497 = NameAndType        #496:#459     // configMap:()Lorg/scalatest/ConfigMap;
  #498 = Methodref          #495.#497     // org/scalatest/Args.configMap:()Lorg/scalatest/ConfigMap;
  #499 = Utf8               (Lorg/scalatest/funspec/AnyFunSpecLike;Lorg/scalatest/TestData;Lorg/scalatest/SuperEngine$TestLeaf;)V
  #500 = NameAndType        #135:#499     // "<init>":(Lorg/scalatest/funspec/AnyFunSpecLike;Lorg/scalatest/TestData;Lorg/scalatest/SuperEngine$TestLeaf;)V
  #501 = Methodref          #41.#500      // org/scalatest/funspec/AnyFunSpecLike$$anon$1."<init>":(Lorg/scalatest/funspec/AnyFunSpecLike;Lorg/scalatest/TestData;Lorg/scalatest/SuperEngine$TestLeaf;)V
  #502 = Utf8               withFixture
  #503 = Utf8               (Lorg/scalatest/TestSuite$NoArgTest;)Lorg/scalatest/Outcome;
  #504 = NameAndType        #502:#503     // withFixture:(Lorg/scalatest/TestSuite$NoArgTest;)Lorg/scalatest/Outcome;
  #505 = InterfaceMethodref #2.#504       // org/scalatest/funspec/AnyFunSpecLike.withFixture:(Lorg/scalatest/TestSuite$NoArgTest;)Lorg/scalatest/Outcome;
  #506 = Utf8               testData
  #507 = Utf8               Lorg/scalatest/TestData;
  #508 = Utf8               Lorg/scalatest/SuperEngine$TestLeaf;
  #509 = NameAndType        #489:#490     // invokeWithFixture$1:(Lorg/scalatest/SuperEngine$TestLeaf;Lorg/scalatest/Args;Ljava/lang/String;)Lorg/scalatest/Outcome;
  #510 = InterfaceMethodref #2.#509       // org/scalatest/funspec/AnyFunSpecLike.invokeWithFixture$1:(Lorg/scalatest/SuperEngine$TestLeaf;Lorg/scalatest/Args;Ljava/lang/String;)Lorg/scalatest/Outcome;
  #511 = NameAndType        #60:#61       // org$scalatest$funspec$AnyFunSpecLike$$super$run:(Lscala/Option;Lorg/scalatest/Args;)Lorg/scalatest/Status;
  #512 = InterfaceMethodref #2.#511       // org/scalatest/funspec/AnyFunSpecLike.org$scalatest$funspec$AnyFunSpecLike$$super$run:(Lscala/Option;Lorg/scalatest/Args;)Lorg/scalatest/Status;
  #513 = Utf8               $init$
  #514 = Utf8               (Lorg/scalatest/funspec/AnyFunSpecLike;)V
  #515 = NameAndType        #470:#67      // $anonfun$engine$1:()Ljava/lang/String;
  #516 = InterfaceMethodref #2.#515       // org/scalatest/funspec/AnyFunSpecLike.$anonfun$engine$1:()Ljava/lang/String;
  #517 = MethodHandle       6:#516        // REF_invokeStatic org/scalatest/funspec/AnyFunSpecLike.$anonfun$engine$1:()Ljava/lang/String;
  #518 = InvokeDynamic      #10:#156      // #10:apply:()Lscala/Function0;
  #519 = Utf8               FunSpec
  #520 = String             #519          // FunSpec
  #521 = Utf8               (Lscala/Function0;Ljava/lang/String;)V
  #522 = NameAndType        #135:#521     // "<init>":(Lscala/Function0;Ljava/lang/String;)V
  #523 = Methodref          #79.#522      // org/scalatest/Engine."<init>":(Lscala/Function0;Ljava/lang/String;)V
  #524 = NameAndType        #48:#49       // org$scalatest$funspec$AnyFunSpecLike$_setter_$org$scalatest$funspec$AnyFunSpecLike$$engine_$eq:(Lorg/scalatest/Engine;)V
  #525 = InterfaceMethodref #2.#524       // org/scalatest/funspec/AnyFunSpecLike.org$scalatest$funspec$AnyFunSpecLike$_setter_$org$scalatest$funspec$AnyFunSpecLike$$engine_$eq:(Lorg/scalatest/Engine;)V
  #526 = String             #17           // AnyFunSpecLike.scala
  #527 = NameAndType        #51:#52       // org$scalatest$funspec$AnyFunSpecLike$_setter_$sourceFileName_$eq:(Ljava/lang/String;)V
  #528 = InterfaceMethodref #2.#527       // org/scalatest/funspec/AnyFunSpecLike.org$scalatest$funspec$AnyFunSpecLike$_setter_$sourceFileName_$eq:(Ljava/lang/String;)V
  #529 = NameAndType        #135:#514     // "<init>":(Lorg/scalatest/funspec/AnyFunSpecLike;)V
  #530 = Methodref          #43.#529      // org/scalatest/funspec/AnyFunSpecLike$ItWord."<init>":(Lorg/scalatest/funspec/AnyFunSpecLike;)V
  #531 = NameAndType        #53:#54       // org$scalatest$funspec$AnyFunSpecLike$_setter_$it_$eq:(Lorg/scalatest/funspec/AnyFunSpecLike$ItWord;)V
  #532 = InterfaceMethodref #2.#531       // org/scalatest/funspec/AnyFunSpecLike.org$scalatest$funspec$AnyFunSpecLike$_setter_$it_$eq:(Lorg/scalatest/funspec/AnyFunSpecLike$ItWord;)V
  #533 = Methodref          #46.#529      // org/scalatest/funspec/AnyFunSpecLike$TheyWord."<init>":(Lorg/scalatest/funspec/AnyFunSpecLike;)V
  #534 = NameAndType        #55:#56       // org$scalatest$funspec$AnyFunSpecLike$_setter_$they_$eq:(Lorg/scalatest/funspec/AnyFunSpecLike$TheyWord;)V
  #535 = InterfaceMethodref #2.#534       // org/scalatest/funspec/AnyFunSpecLike.org$scalatest$funspec$AnyFunSpecLike$_setter_$they_$eq:(Lorg/scalatest/funspec/AnyFunSpecLike$TheyWord;)V
  #536 = Utf8               org/scalatest/verbs/BehaveWord
  #537 = Class              #536          // org/scalatest/verbs/BehaveWord
  #538 = Utf8               ()V
  #539 = NameAndType        #135:#538     // "<init>":()V
  #540 = Methodref          #537.#539     // org/scalatest/verbs/BehaveWord."<init>":()V
  #541 = NameAndType        #57:#58       // org$scalatest$funspec$AnyFunSpecLike$_setter_$behave_$eq:(Lorg/scalatest/verbs/BehaveWord;)V
  #542 = InterfaceMethodref #2.#541       // org/scalatest/funspec/AnyFunSpecLike.org$scalatest$funspec$AnyFunSpecLike$_setter_$behave_$eq:(Lorg/scalatest/verbs/BehaveWord;)V
  #543 = Utf8               org.scalatest.FunSpec
  #544 = String             #543          // org.scalatest.FunSpec
  #545 = NameAndType        #59:#52       // org$scalatest$funspec$AnyFunSpecLike$_setter_$styleName_$eq:(Ljava/lang/String;)V
  #546 = InterfaceMethodref #2.#545       // org/scalatest/funspec/AnyFunSpecLike.org$scalatest$funspec$AnyFunSpecLike$_setter_$styleName_$eq:(Ljava/lang/String;)V
  #547 = Utf8               $deserializeLambda$
  #548 = Utf8               (Ljava/lang/invoke/SerializedLambda;)Ljava/lang/Object;
  #549 = Utf8               scala/runtime/LambdaDeserialize
  #550 = Class              #549          // scala/runtime/LambdaDeserialize
  #551 = Utf8               bootstrap
  #552 = Utf8               (Ljava/lang/invoke/MethodHandles$Lookup;Ljava/lang/String;Ljava/lang/invoke/MethodType;[Ljava/lang/invoke/MethodHandle;)Ljava/lang/invoke/CallSite;
  #553 = NameAndType        #551:#552     // bootstrap:(Ljava/lang/invoke/MethodHandles$Lookup;Ljava/lang/String;Ljava/lang/invoke/MethodType;[Ljava/lang/invoke/MethodHandle;)Ljava/lang/invoke/CallSite;
  #554 = Methodref          #550.#553     // scala/runtime/LambdaDeserialize.bootstrap:(Ljava/lang/invoke/MethodHandles$Lookup;Ljava/lang/String;Ljava/lang/invoke/MethodType;[Ljava/lang/invoke/MethodHandle;)Ljava/lang/invoke/CallSite;
  #555 = MethodHandle       6:#554        // REF_invokeStatic scala/runtime/LambdaDeserialize.bootstrap:(Ljava/lang/invoke/MethodHandles$Lookup;Ljava/lang/String;Ljava/lang/invoke/MethodType;[Ljava/lang/invoke/MethodHandle;)Ljava/lang/invoke/CallSite;
  #556 = Utf8               lambdaDeserialize
  #557 = NameAndType        #556:#548     // lambdaDeserialize:(Ljava/lang/invoke/SerializedLambda;)Ljava/lang/Object;
  #558 = InvokeDynamic      #11:#557      // #11:lambdaDeserialize:(Ljava/lang/invoke/SerializedLambda;)Ljava/lang/Object;
  #559 = Utf8               MethodParameters
  #560 = Utf8               Code
  #561 = Utf8               LineNumberTable
  #562 = Utf8               LocalVariableTable
  #563 = Utf8               Signature
  #564 = Utf8               StackMapTable
  #565 = Utf8               Deprecated
  #566 = Utf8               InnerClasses
  #567 = Utf8               SourceFile
  #568 = Utf8               RuntimeVisibleAnnotations
  #569 = Utf8               BootstrapMethods
  #570 = Utf8               ScalaInlineInfo
  #571 = Utf8               ScalaSig
{
  public abstract void org$scalatest$funspec$AnyFunSpecLike$_setter_$org$scalatest$funspec$AnyFunSpecLike$$engine_$eq(org.scalatest.Engine);
    descriptor: (Lorg/scalatest/Engine;)V
    flags: (0x0401) ACC_PUBLIC, ACC_ABSTRACT
    MethodParameters:
      Name                           Flags
      x$1                            final

  public abstract void org$scalatest$funspec$AnyFunSpecLike$_setter_$sourceFileName_$eq(java.lang.String);
    descriptor: (Ljava/lang/String;)V
    flags: (0x0401) ACC_PUBLIC, ACC_ABSTRACT
    MethodParameters:
      Name                           Flags
      x$1                            final

  public abstract void org$scalatest$funspec$AnyFunSpecLike$_setter_$it_$eq(org.scalatest.funspec.AnyFunSpecLike$ItWord);
    descriptor: (Lorg/scalatest/funspec/AnyFunSpecLike$ItWord;)V
    flags: (0x0401) ACC_PUBLIC, ACC_ABSTRACT
    MethodParameters:
      Name                           Flags
      x$1                            final

  public abstract void org$scalatest$funspec$AnyFunSpecLike$_setter_$they_$eq(org.scalatest.funspec.AnyFunSpecLike$TheyWord);
    descriptor: (Lorg/scalatest/funspec/AnyFunSpecLike$TheyWord;)V
    flags: (0x0401) ACC_PUBLIC, ACC_ABSTRACT
    MethodParameters:
      Name                           Flags
      x$1                            final

  public abstract void org$scalatest$funspec$AnyFunSpecLike$_setter_$behave_$eq(org.scalatest.verbs.BehaveWord);
    descriptor: (Lorg/scalatest/verbs/BehaveWord;)V
    flags: (0x0401) ACC_PUBLIC, ACC_ABSTRACT
    MethodParameters:
      Name                           Flags
      x$1                            final

  public abstract void org$scalatest$funspec$AnyFunSpecLike$_setter_$styleName_$eq(java.lang.String);
    descriptor: (Ljava/lang/String;)V
    flags: (0x0401) ACC_PUBLIC, ACC_ABSTRACT
    MethodParameters:
      Name                           Flags
      x$1                            final

  public abstract org.scalatest.Status org$scalatest$funspec$AnyFunSpecLike$$super$run(scala.Option, org.scalatest.Args);
    descriptor: (Lscala/Option;Lorg/scalatest/Args;)Lorg/scalatest/Status;
    flags: (0x1401) ACC_PUBLIC, ACC_ABSTRACT, ACC_SYNTHETIC
    MethodParameters:
      Name                           Flags
      testName                       final
      args                           final

  public abstract org.scalatest.Engine org$scalatest$funspec$AnyFunSpecLike$$engine();
    descriptor: ()Lorg/scalatest/Engine;
    flags: (0x0401) ACC_PUBLIC, ACC_ABSTRACT

  public abstract java.lang.String sourceFileName();
    descriptor: ()Ljava/lang/String;
    flags: (0x0401) ACC_PUBLIC, ACC_ABSTRACT

  public static org.scalatest.Informer info$(org.scalatest.funspec.AnyFunSpecLike);
    descriptor: (Lorg/scalatest/funspec/AnyFunSpecLike;)Lorg/scalatest/Informer;
    flags: (0x1009) ACC_PUBLIC, ACC_STATIC, ACC_SYNTHETIC
    Code:
      stack=1, locals=1, args_size=1
         0: aload_0
         1: invokespecial #74                 // InterfaceMethod info:()Lorg/scalatest/Informer;
         4: areturn
      LineNumberTable:
        line 66: 0
      LocalVariableTable:
        Start  Length  Slot  Name   Signature
            0       5     0 $this   Lorg/scalatest/funspec/AnyFunSpecLike;
    MethodParameters:
      Name                           Flags
      $this                          final synthetic

  public default org.scalatest.Informer info();
    descriptor: ()Lorg/scalatest/Informer;
    flags: (0x0001) ACC_PUBLIC
    Code:
      stack=1, locals=1, args_size=1
         0: aload_0
         1: invokeinterface #77,  1           // InterfaceMethod org$scalatest$funspec$AnyFunSpecLike$$engine:()Lorg/scalatest/Engine;
         6: invokevirtual #83                 // Method org/scalatest/Engine.atomicInformer:()Ljava/util/concurrent/atomic/AtomicReference;
         9: invokevirtual #89                 // Method java/util/concurrent/atomic/AtomicReference.get:()Ljava/lang/Object;
        12: checkcast     #91                 // class org/scalatest/Informer
        15: areturn
      LineNumberTable:
        line 66: 0
      LocalVariableTable:
        Start  Length  Slot  Name   Signature
            0      16     0  this   Lorg/scalatest/funspec/AnyFunSpecLike;

  public static org.scalatest.Notifier note$(org.scalatest.funspec.AnyFunSpecLike);
    descriptor: (Lorg/scalatest/funspec/AnyFunSpecLike;)Lorg/scalatest/Notifier;
    flags: (0x1009) ACC_PUBLIC, ACC_STATIC, ACC_SYNTHETIC
    Code:
      stack=1, locals=1, args_size=1
         0: aload_0
         1: invokespecial #98                 // InterfaceMethod note:()Lorg/scalatest/Notifier;
         4: areturn
      LineNumberTable:
        line 76: 0
      LocalVariableTable:
        Start  Length  Slot  Name   Signature
            0       5     0 $this   Lorg/scalatest/funspec/AnyFunSpecLike;
    MethodParameters:
      Name                           Flags
      $this                          final synthetic

  public default org.scalatest.Notifier note();
    descriptor: ()Lorg/scalatest/Notifier;
    flags: (0x0001) ACC_PUBLIC
    Code:
      stack=1, locals=1, args_size=1
         0: aload_0
         1: invokeinterface #77,  1           // InterfaceMethod org$scalatest$funspec$AnyFunSpecLike$$engine:()Lorg/scalatest/Engine;
         6: invokevirtual #101                // Method org/scalatest/Engine.atomicNotifier:()Ljava/util/concurrent/atomic/AtomicReference;
         9: invokevirtual #89                 // Method java/util/concurrent/atomic/AtomicReference.get:()Ljava/lang/Object;
        12: checkcast     #103                // class org/scalatest/Notifier
        15: areturn
      LineNumberTable:
        line 76: 0
      LocalVariableTable:
        Start  Length  Slot  Name   Signature
            0      16     0  this   Lorg/scalatest/funspec/AnyFunSpecLike;

  public static org.scalatest.Alerter alert$(org.scalatest.funspec.AnyFunSpecLike);
    descriptor: (Lorg/scalatest/funspec/AnyFunSpecLike;)Lorg/scalatest/Alerter;
    flags: (0x1009) ACC_PUBLIC, ACC_STATIC, ACC_SYNTHETIC
    Code:
      stack=1, locals=1, args_size=1
         0: aload_0
         1: invokespecial #109                // InterfaceMethod alert:()Lorg/scalatest/Alerter;
         4: areturn
      LineNumberTable:
        line 86: 0
      LocalVariableTable:
        Start  Length  Slot  Name   Signature
            0       5     0 $this   Lorg/scalatest/funspec/AnyFunSpecLike;
    MethodParameters:
      Name                           Flags
      $this                          final synthetic

  public default org.scalatest.Alerter alert();
    descriptor: ()Lorg/scalatest/Alerter;
    flags: (0x0001) ACC_PUBLIC
    Code:
      stack=1, locals=1, args_size=1
         0: aload_0
         1: invokeinterface #77,  1           // InterfaceMethod org$scalatest$funspec$AnyFunSpecLike$$engine:()Lorg/scalatest/Engine;
         6: invokevirtual #112                // Method org/scalatest/Engine.atomicAlerter:()Ljava/util/concurrent/atomic/AtomicReference;
         9: invokevirtual #89                 // Method java/util/concurrent/atomic/AtomicReference.get:()Ljava/lang/Object;
        12: checkcast     #114                // class org/scalatest/Alerter
        15: areturn
      LineNumberTable:
        line 86: 0
      LocalVariableTable:
        Start  Length  Slot  Name   Signature
            0      16     0  this   Lorg/scalatest/funspec/AnyFunSpecLike;

  public static org.scalatest.Documenter markup$(org.scalatest.funspec.AnyFunSpecLike);
    descriptor: (Lorg/scalatest/funspec/AnyFunSpecLike;)Lorg/scalatest/Documenter;
    flags: (0x1009) ACC_PUBLIC, ACC_STATIC, ACC_SYNTHETIC
    Code:
      stack=1, locals=1, args_size=1
         0: aload_0
         1: invokespecial #120                // InterfaceMethod markup:()Lorg/scalatest/Documenter;
         4: areturn
      LineNumberTable:
        line 97: 0
      LocalVariableTable:
        Start  Length  Slot  Name   Signature
            0       5     0 $this   Lorg/scalatest/funspec/AnyFunSpecLike;
    MethodParameters:
      Name                           Flags
      $this                          final synthetic

  public default org.scalatest.Documenter markup();
    descriptor: ()Lorg/scalatest/Documenter;
    flags: (0x0001) ACC_PUBLIC
    Code:
      stack=1, locals=1, args_size=1
         0: aload_0
         1: invokeinterface #77,  1           // InterfaceMethod org$scalatest$funspec$AnyFunSpecLike$$engine:()Lorg/scalatest/Engine;
         6: invokevirtual #123                // Method org/scalatest/Engine.atomicDocumenter:()Ljava/util/concurrent/atomic/AtomicReference;
         9: invokevirtual #89                 // Method java/util/concurrent/atomic/AtomicReference.get:()Ljava/lang/Object;
        12: checkcast     #125                // class org/scalatest/Documenter
        15: areturn
      LineNumberTable:
        line 97: 0
      LocalVariableTable:
        Start  Length  Slot  Name   Signature
            0      16     0  this   Lorg/scalatest/funspec/AnyFunSpecLike;

  private void registerTestImpl(java.lang.String, scala.collection.immutable.Seq<org.scalatest.Tag>, scala.Function0<java.lang.Object>, org.scalactic.source.Position);
    descriptor: (Ljava/lang/String;Lscala/collection/immutable/Seq;Lscala/Function0;Lorg/scalactic/source/Position;)V
    flags: (0x0002) ACC_PRIVATE
    Code:
      stack=13, locals=6, args_size=5
         0: bipush        -2
         2: istore        5
         4: aload_0
         5: invokeinterface #77,  1           // InterfaceMethod org$scalatest$funspec$AnyFunSpecLike$$engine:()Lorg/scalatest/Engine;
        10: aload_1
        11: new           #134                // class org/scalatest/Transformer
        14: dup
        15: aload_3
        16: invokespecial #138                // Method org/scalatest/Transformer."<init>":(Lscala/Function0;)V
        19: invokedynamic #157,  0            // InvokeDynamic #0:apply:()Lscala/Function0;
        24: aload_0
        25: invokeinterface #159,  1          // InterfaceMethod sourceFileName:()Ljava/lang/String;
        30: ldc           #161                // String registerTest
        32: iconst_5
        33: iload         5
        35: getstatic     #167                // Field scala/None$.MODULE$:Lscala/None$;
        38: getstatic     #167                // Field scala/None$.MODULE$:Lscala/None$;
        41: new           #169                // class scala/Some
        44: dup
        45: aload         4
        47: invokespecial #172                // Method scala/Some."<init>":(Ljava/lang/Object;)V
        50: getstatic     #167                // Field scala/None$.MODULE$:Lscala/None$;
        53: aload_2
        54: invokevirtual #175                // Method org/scalatest/Engine.registerTest:(Ljava/lang/String;Ljava/lang/Object;Lscala/Function0;Ljava/lang/String;Ljava/lang/String;IILscala/Option;Lscala/Option;Lscala/Option;Lscala/Option;Lscala/collection/immutable/Seq;)Ljava/lang/String;
        57: pop
        58: return
      LineNumberTable:
        line 101: 0
        line 104: 4
      LocalVariableTable:
        Start  Length  Slot  Name   Signature
            4      54     5 stackDepthAdjustment   I
            0      59     0  this   Lorg/scalatest/funspec/AnyFunSpecLike;
            0      59     1 testText   Ljava/lang/String;
            0      59     2 testTags   Lscala/collection/immutable/Seq;
            0      59     3 testFun   Lscala/Function0;
            0      59     4   pos   Lorg/scalactic/source/Position;
    Signature: #128                         // (Ljava/lang/String;Lscala/collection/immutable/Seq<Lorg/scalatest/Tag;>;Lscala/Function0<Ljava/lang/Object;>;Lorg/scalactic/source/Position;)V
    MethodParameters:
      Name                           Flags
      testText                       final
      testTags                       final
      testFun                        final
      pos                            final

  public static void registerTest$(org.scalatest.funspec.AnyFunSpecLike, java.lang.String, scala.collection.immutable.Seq, scala.Function0, org.scalactic.source.Position);
    descriptor: (Lorg/scalatest/funspec/AnyFunSpecLike;Ljava/lang/String;Lscala/collection/immutable/Seq;Lscala/Function0;Lorg/scalactic/source/Position;)V
    flags: (0x1009) ACC_PUBLIC, ACC_STATIC, ACC_SYNTHETIC
    Code:
      stack=5, locals=5, args_size=5
         0: aload_0
         1: aload_1
         2: aload_2
         3: aload_3
         4: aload         4
         6: invokespecial #185                // InterfaceMethod registerTest:(Ljava/lang/String;Lscala/collection/immutable/Seq;Lscala/Function0;Lorg/scalactic/source/Position;)V
         9: return
      LineNumberTable:
        line 108: 0
      LocalVariableTable:
        Start  Length  Slot  Name   Signature
            0      10     0 $this   Lorg/scalatest/funspec/AnyFunSpecLike;
            0      10     1 testText   Ljava/lang/String;
            0      10     2 testTags   Lscala/collection/immutable/Seq;
            0      10     3 testFun   Lscala/Function0;
            0      10     4   pos   Lorg/scalactic/source/Position;
    MethodParameters:
      Name                           Flags
      $this                          final synthetic
      testText                       final
      testTags                       final
      testFun                        final
      pos                            final

  public default void registerTest(java.lang.String, scala.collection.immutable.Seq<org.scalatest.Tag>, scala.Function0<java.lang.Object>, org.scalactic.source.Position);
    descriptor: (Ljava/lang/String;Lscala/collection/immutable/Seq;Lscala/Function0;Lorg/scalactic/source/Position;)V
    flags: (0x0001) ACC_PUBLIC
    Code:
      stack=5, locals=5, args_size=5
         0: aload_0
         1: aload_1
         2: aload_2
         3: aload_3
         4: aload         4
         6: invokespecial #187                // InterfaceMethod registerTestImpl:(Ljava/lang/String;Lscala/collection/immutable/Seq;Lscala/Function0;Lorg/scalactic/source/Position;)V
         9: return
      LineNumberTable:
        line 109: 0
      LocalVariableTable:
        Start  Length  Slot  Name   Signature
            0      10     0  this   Lorg/scalatest/funspec/AnyFunSpecLike;
            0      10     1 testText   Ljava/lang/String;
            0      10     2 testTags   Lscala/collection/immutable/Seq;
            0      10     3 testFun   Lscala/Function0;
            0      10     4   pos   Lorg/scalactic/source/Position;
    Signature: #128                         // (Ljava/lang/String;Lscala/collection/immutable/Seq<Lorg/scalatest/Tag;>;Lscala/Function0<Ljava/lang/Object;>;Lorg/scalactic/source/Position;)V
    MethodParameters:
      Name                           Flags
      testText                       final
      testTags                       final
      testFun                        final
      pos                            final

  private void registerIgnoredTestImpl(java.lang.String, scala.collection.immutable.Seq<org.scalatest.Tag>, scala.Function0<java.lang.Object>, org.scalactic.source.Position);
    descriptor: (Ljava/lang/String;Lscala/collection/immutable/Seq;Lscala/Function0;Lorg/scalactic/source/Position;)V
    flags: (0x0002) ACC_PRIVATE
    Code:
      stack=12, locals=6, args_size=5
         0: bipush        -3
         2: istore        5
         4: aload_0
         5: invokeinterface #77,  1           // InterfaceMethod org$scalatest$funspec$AnyFunSpecLike$$engine:()Lorg/scalatest/Engine;
        10: aload_1
        11: new           #134                // class org/scalatest/Transformer
        14: dup
        15: aload_3
        16: invokespecial #138                // Method org/scalatest/Transformer."<init>":(Lscala/Function0;)V
        19: invokedynamic #193,  0            // InvokeDynamic #1:apply:()Lscala/Function0;
        24: aload_0
        25: invokeinterface #159,  1          // InterfaceMethod sourceFileName:()Ljava/lang/String;
        30: ldc           #195                // String registerIgnoredTest
        32: iconst_4
        33: iload         5
        35: getstatic     #167                // Field scala/None$.MODULE$:Lscala/None$;
        38: new           #169                // class scala/Some
        41: dup
        42: aload         4
        44: invokespecial #172                // Method scala/Some."<init>":(Ljava/lang/Object;)V
        47: aload_2
        48: invokevirtual #198                // Method org/scalatest/Engine.registerIgnoredTest:(Ljava/lang/String;Ljava/lang/Object;Lscala/Function0;Ljava/lang/String;Ljava/lang/String;IILscala/Option;Lscala/Option;Lscala/collection/immutable/Seq;)V
        51: return
      LineNumberTable:
        line 118: 0
        line 121: 4
      LocalVariableTable:
        Start  Length  Slot  Name   Signature
            4      47     5 stackDepthAdjustment   I
            0      52     0  this   Lorg/scalatest/funspec/AnyFunSpecLike;
            0      52     1 testText   Ljava/lang/String;
            0      52     2 testTags   Lscala/collection/immutable/Seq;
            0      52     3 testFun   Lscala/Function0;
            0      52     4   pos   Lorg/scalactic/source/Position;
    Signature: #128                         // (Ljava/lang/String;Lscala/collection/immutable/Seq<Lorg/scalatest/Tag;>;Lscala/Function0<Ljava/lang/Object;>;Lorg/scalactic/source/Position;)V
    MethodParameters:
      Name                           Flags
      testText                       final
      testTags                       final
      testFun                        final
      pos                            final

  public static void registerIgnoredTest$(org.scalatest.funspec.AnyFunSpecLike, java.lang.String, scala.collection.immutable.Seq, scala.Function0, org.scalactic.source.Position);
    descriptor: (Lorg/scalatest/funspec/AnyFunSpecLike;Ljava/lang/String;Lscala/collection/immutable/Seq;Lscala/Function0;Lorg/scalactic/source/Position;)V
    flags: (0x1009) ACC_PUBLIC, ACC_STATIC, ACC_SYNTHETIC
    Code:
      stack=5, locals=5, args_size=5
         0: aload_0
         1: aload_1
         2: aload_2
         3: aload_3
         4: aload         4
         6: invokespecial #201                // InterfaceMethod registerIgnoredTest:(Ljava/lang/String;Lscala/collection/immutable/Seq;Lscala/Function0;Lorg/scalactic/source/Position;)V
         9: return
      LineNumberTable:
        line 125: 0
      LocalVariableTable:
        Start  Length  Slot  Name   Signature
            0      10     0 $this   Lorg/scalatest/funspec/AnyFunSpecLike;
            0      10     1 testText   Ljava/lang/String;
            0      10     2 testTags   Lscala/collection/immutable/Seq;
            0      10     3 testFun   Lscala/Function0;
            0      10     4   pos   Lorg/scalactic/source/Position;
    MethodParameters:
      Name                           Flags
      $this                          final synthetic
      testText                       final
      testTags                       final
      testFun                        final
      pos                            final

  public default void registerIgnoredTest(java.lang.String, scala.collection.immutable.Seq<org.scalatest.Tag>, scala.Function0<java.lang.Object>, org.scalactic.source.Position);
    descriptor: (Ljava/lang/String;Lscala/collection/immutable/Seq;Lscala/Function0;Lorg/scalactic/source/Position;)V
    flags: (0x0001) ACC_PUBLIC
    Code:
      stack=5, locals=5, args_size=5
         0: aload_0
         1: aload_1
         2: aload_2
         3: aload_3
         4: aload         4
         6: invokespecial #203                // InterfaceMethod registerIgnoredTestImpl:(Ljava/lang/String;Lscala/collection/immutable/Seq;Lscala/Function0;Lorg/scalactic/source/Position;)V
         9: return
      LineNumberTable:
        line 126: 0
      LocalVariableTable:
        Start  Length  Slot  Name   Signature
            0      10     0  this   Lorg/scalatest/funspec/AnyFunSpecLike;
            0      10     1 testText   Ljava/lang/String;
            0      10     2 testTags   Lscala/collection/immutable/Seq;
            0      10     3 testFun   Lscala/Function0;
            0      10     4   pos   Lorg/scalactic/source/Position;
    Signature: #128                         // (Ljava/lang/String;Lscala/collection/immutable/Seq<Lorg/scalatest/Tag;>;Lscala/Function0<Ljava/lang/Object;>;Lorg/scalactic/source/Position;)V
    MethodParameters:
      Name                           Flags
      testText                       final
      testTags                       final
      testFun                        final
      pos                            final

  public abstract org.scalatest.funspec.AnyFunSpecLike$ItWord it();
    descriptor: ()Lorg/scalatest/funspec/AnyFunSpecLike$ItWord;
    flags: (0x0401) ACC_PUBLIC, ACC_ABSTRACT

  public abstract org.scalatest.funspec.AnyFunSpecLike$TheyWord they();
    descriptor: ()Lorg/scalatest/funspec/AnyFunSpecLike$TheyWord;
    flags: (0x0401) ACC_PUBLIC, ACC_ABSTRACT

  private void ignoreImpl(java.lang.String, scala.collection.immutable.Seq<org.scalatest.Tag>, scala.Function0<java.lang.Object>, org.scalactic.source.Position);
    descriptor: (Ljava/lang/String;Lscala/collection/immutable/Seq;Lscala/Function0;Lorg/scalactic/source/Position;)V
    flags: (0x0002) ACC_PRIVATE
    Code:
      stack=12, locals=7, args_size=5
         0: iconst_4
         1: istore        5
         3: bipush        -3
         5: istore        6
         7: aload_0
         8: invokeinterface #77,  1           // InterfaceMethod org$scalatest$funspec$AnyFunSpecLike$$engine:()Lorg/scalatest/Engine;
        13: aload_1
        14: new           #134                // class org/scalatest/Transformer
        17: dup
        18: aload_3
        19: invokespecial #138                // Method org/scalatest/Transformer."<init>":(Lscala/Function0;)V
        22: invokedynamic #213,  0            // InvokeDynamic #2:apply:()Lscala/Function0;
        27: aload_0
        28: invokeinterface #159,  1          // InterfaceMethod sourceFileName:()Ljava/lang/String;
        33: ldc           #215                // String ignore
        35: iload         5
        37: iload         6
        39: getstatic     #167                // Field scala/None$.MODULE$:Lscala/None$;
        42: new           #169                // class scala/Some
        45: dup
        46: aload         4
        48: invokespecial #172                // Method scala/Some."<init>":(Ljava/lang/Object;)V
        51: aload_2
        52: invokevirtual #198                // Method org/scalatest/Engine.registerIgnoredTest:(Ljava/lang/String;Ljava/lang/Object;Lscala/Function0;Ljava/lang/String;Ljava/lang/String;IILscala/Option;Lscala/Option;Lscala/collection/immutable/Seq;)V
        55: return
      LineNumberTable:
        line 389: 0
        line 390: 3
        line 394: 7
      LocalVariableTable:
        Start  Length  Slot  Name   Signature
            3      52     5 stackDepth   I
            7      48     6 stackDepthAdjustment   I
            0      56     0  this   Lorg/scalatest/funspec/AnyFunSpecLike;
            0      56     1 testText   Ljava/lang/String;
            0      56     2 testTags   Lscala/collection/immutable/Seq;
            0      56     3 testFun   Lscala/Function0;
            0      56     4   pos   Lorg/scalactic/source/Position;
    Signature: #128                         // (Ljava/lang/String;Lscala/collection/immutable/Seq<Lorg/scalatest/Tag;>;Lscala/Function0<Ljava/lang/Object;>;Lorg/scalactic/source/Position;)V
    MethodParameters:
      Name                           Flags
      testText                       final
      testTags                       final
      testFun                        final
      pos                            final

  public static void ignore$(org.scalatest.funspec.AnyFunSpecLike, java.lang.String, scala.collection.immutable.Seq, scala.Function0, org.scalactic.source.Position);
    descriptor: (Lorg/scalatest/funspec/AnyFunSpecLike;Ljava/lang/String;Lscala/collection/immutable/Seq;Lscala/Function0;Lorg/scalactic/source/Position;)V
    flags: (0x1009) ACC_PUBLIC, ACC_STATIC, ACC_SYNTHETIC
    Code:
      stack=5, locals=5, args_size=5
         0: aload_0
         1: aload_1
         2: aload_2
         3: aload_3
         4: aload         4
         6: invokespecial #219                // InterfaceMethod ignore:(Ljava/lang/String;Lscala/collection/immutable/Seq;Lscala/Function0;Lorg/scalactic/source/Position;)V
         9: return
      LineNumberTable:
        line 416: 0
      LocalVariableTable:
        Start  Length  Slot  Name   Signature
            0      10     0 $this   Lorg/scalatest/funspec/AnyFunSpecLike;
            0      10     1 testText   Ljava/lang/String;
            0      10     2 testTags   Lscala/collection/immutable/Seq;
            0      10     3 testFun   Lscala/Function0;
            0      10     4   pos   Lorg/scalactic/source/Position;
    MethodParameters:
      Name                           Flags
      $this                          final synthetic
      testText                       final
      testTags                       final
      testFun                        final
      pos                            final

  public default void ignore(java.lang.String, scala.collection.immutable.Seq<org.scalatest.Tag>, scala.Function0<java.lang.Object>, org.scalactic.source.Position);
    descriptor: (Ljava/lang/String;Lscala/collection/immutable/Seq;Lscala/Function0;Lorg/scalactic/source/Position;)V
    flags: (0x0001) ACC_PUBLIC
    Code:
      stack=5, locals=5, args_size=5
         0: aload_0
         1: aload_1
         2: aload_2
         3: aload_3
         4: aload         4
         6: invokespecial #221                // InterfaceMethod ignoreImpl:(Ljava/lang/String;Lscala/collection/immutable/Seq;Lscala/Function0;Lorg/scalactic/source/Position;)V
         9: return
      LineNumberTable:
        line 417: 0
      LocalVariableTable:
        Start  Length  Slot  Name   Signature
            0      10     0  this   Lorg/scalatest/funspec/AnyFunSpecLike;
            0      10     1 testText   Ljava/lang/String;
            0      10     2 testTags   Lscala/collection/immutable/Seq;
            0      10     3 testFun   Lscala/Function0;
            0      10     4   pos   Lorg/scalactic/source/Position;
    Signature: #128                         // (Ljava/lang/String;Lscala/collection/immutable/Seq<Lorg/scalatest/Tag;>;Lscala/Function0<Ljava/lang/Object;>;Lorg/scalactic/source/Position;)V
    MethodParameters:
      Name                           Flags
      testText                       final
      testTags                       final
      testFun                        final
      pos                            final

  private void describeImpl(java.lang.String, scala.Function0<scala.runtime.BoxedUnit>, org.scalactic.source.Position);
    descriptor: (Ljava/lang/String;Lscala/Function0;Lorg/scalactic/source/Position;)V
    flags: (0x0002) ACC_PRIVATE
    Code:
      stack=13, locals=13, args_size=4
         0: iconst_4
         1: istore        5
         3: aload_0
         4: invokeinterface #77,  1           // InterfaceMethod org$scalatest$funspec$AnyFunSpecLike$$engine:()Lorg/scalatest/Engine;
         9: aload_1
        10: getstatic     #167                // Field scala/None$.MODULE$:Lscala/None$;
        13: aload_2
        14: invokedynamic #233,  0            // InvokeDynamic #3:apply:()Lscala/Function0;
        19: aload_0
        20: invokeinterface #159,  1          // InterfaceMethod sourceFileName:()Ljava/lang/String;
        25: ldc           #235                // String describe
        27: iload         5
        29: bipush        -2
        31: getstatic     #167                // Field scala/None$.MODULE$:Lscala/None$;
        34: new           #169                // class scala/Some
        37: dup
        38: aload_3
        39: invokespecial #172                // Method scala/Some."<init>":(Ljava/lang/Object;)V
        42: invokevirtual #239                // Method org/scalatest/Engine.registerNestedBranch:(Ljava/lang/String;Lscala/Option;Lscala/Function0;Lscala/Function0;Ljava/lang/String;Ljava/lang/String;IILscala/Option;Lscala/Option;)V
        45: goto          348
        48: astore        6
        50: aload         6
        52: astore        7
        54: aload         7
        56: instanceof    #241                // class org/scalatest/exceptions/TestFailedException
        59: ifeq          109
        62: aload         7
        64: checkcast     #241                // class org/scalatest/exceptions/TestFailedException
        67: astore        8
        69: new           #243                // class org/scalatest/exceptions/NotAllowedException
        72: dup
        73: getstatic     #248                // Field org/scalatest/FailureMessages$.MODULE$:Lorg/scalatest/FailureMessages$;
        76: invokevirtual #251                // Method org/scalatest/FailureMessages$.assertionShouldBePutInsideItOrTheyClauseNotDescribeClause:()Ljava/lang/String;
        79: new           #169                // class scala/Some
        82: dup
        83: aload         8
        85: invokespecial #172                // Method scala/Some."<init>":(Ljava/lang/Object;)V
        88: aload         8
        90: invokevirtual #255                // Method org/scalatest/exceptions/TestFailedException.position:()Lscala/Option;
        93: aload_3
        94: invokedynamic #265,  0            // InvokeDynamic #4:apply:(Lorg/scalactic/source/Position;)Lscala/Function0;
        99: invokevirtual #271                // Method scala/Option.getOrElse:(Lscala/Function0;)Ljava/lang/Object;
       102: checkcast     #273                // class org/scalactic/source/Position
       105: invokespecial #276                // Method org/scalatest/exceptions/NotAllowedException."<init>":(Ljava/lang/String;Lscala/Option;Lorg/scalactic/source/Position;)V
       108: athrow
       109: goto          112
       112: aload         7
       114: instanceof    #278                // class org/scalatest/exceptions/TestCanceledException
       117: ifeq          167
       120: aload         7
       122: checkcast     #278                // class org/scalatest/exceptions/TestCanceledException
       125: astore        9
       127: new           #243                // class org/scalatest/exceptions/NotAllowedException
       130: dup
       131: getstatic     #248                // Field org/scalatest/FailureMessages$.MODULE$:Lorg/scalatest/FailureMessages$;
       134: invokevirtual #251                // Method org/scalatest/FailureMessages$.assertionShouldBePutInsideItOrTheyClauseNotDescribeClause:()Ljava/lang/String;
       137: new           #169                // class scala/Some
       140: dup
       141: aload         9
       143: invokespecial #172                // Method scala/Some."<init>":(Ljava/lang/Object;)V
       146: aload         9
       148: invokevirtual #279                // Method org/scalatest/exceptions/TestCanceledException.position:()Lscala/Option;
       151: aload_3
       152: invokedynamic #284,  0            // InvokeDynamic #5:apply:(Lorg/scalactic/source/Position;)Lscala/Function0;
       157: invokevirtual #271                // Method scala/Option.getOrElse:(Lscala/Function0;)Ljava/lang/Object;
       160: checkcast     #273                // class org/scalactic/source/Position
       163: invokespecial #276                // Method org/scalatest/exceptions/NotAllowedException."<init>":(Ljava/lang/String;Lscala/Option;Lorg/scalactic/source/Position;)V
       166: athrow
       167: goto          170
       170: aload         7
       172: instanceof    #286                // class org/scalatest/exceptions/DuplicateTestNameException
       175: ifeq          251
       178: aload         7
       180: checkcast     #286                // class org/scalatest/exceptions/DuplicateTestNameException
       183: astore        10
       185: new           #243                // class org/scalatest/exceptions/NotAllowedException
       188: dup
       189: getstatic     #248                // Field org/scalatest/FailureMessages$.MODULE$:Lorg/scalatest/FailureMessages$;
       192: getstatic     #291                // Field org/scalactic/Prettifier$.MODULE$:Lorg/scalactic/Prettifier$;
       195: invokevirtual #295                // Method org/scalactic/Prettifier$.default:()Lorg/scalactic/Prettifier;
       198: getstatic     #300                // Field org/scalatest/UnquotedString$.MODULE$:Lorg/scalatest/UnquotedString$;
       201: aload         10
       203: invokevirtual #304                // Method org/scalatest/exceptions/DuplicateTestNameException.getClass:()Ljava/lang/Class;
       206: invokevirtual #309                // Method java/lang/Class.getName:()Ljava/lang/String;
       209: invokevirtual #312                // Method org/scalatest/UnquotedString$.apply:(Ljava/lang/String;)Lorg/scalatest/UnquotedString;
       212: aload_1
       213: aload         10
       215: invokevirtual #315                // Method org/scalatest/exceptions/DuplicateTestNameException.getMessage:()Ljava/lang/String;
       218: invokevirtual #319                // Method org/scalatest/FailureMessages$.exceptionWasThrownInDescribeClause:(Lorg/scalactic/Prettifier;Ljava/lang/Object;Ljava/lang/Object;Ljava/lang/Object;)Ljava/lang/String;
       221: new           #169                // class scala/Some
       224: dup
       225: aload         10
       227: invokespecial #172                // Method scala/Some."<init>":(Ljava/lang/Object;)V
       230: aload         10
       232: invokevirtual #320                // Method org/scalatest/exceptions/DuplicateTestNameException.position:()Lscala/Option;
       235: aload_3
       236: invokedynamic #325,  0            // InvokeDynamic #6:apply:(Lorg/scalactic/source/Position;)Lscala/Function0;
       241: invokevirtual #271                // Method scala/Option.getOrElse:(Lscala/Function0;)Ljava/lang/Object;
       244: checkcast     #273                // class org/scalactic/source/Position
       247: invokespecial #276                // Method org/scalatest/exceptions/NotAllowedException."<init>":(Ljava/lang/String;Lscala/Option;Lorg/scalactic/source/Position;)V
       250: athrow
       251: goto          254
       254: aload         7
       256: ifnull        327
       259: aload         7
       261: astore        11
       263: getstatic     #330                // Field org/scalatest/Suite$.MODULE$:Lorg/scalatest/Suite$;
       266: aload         11
       268: invokevirtual #334                // Method org/scalatest/Suite$.anExceptionThatShouldCauseAnAbort:(Ljava/lang/Throwable;)Z
       271: ifne          324
       274: new           #243                // class org/scalatest/exceptions/NotAllowedException
       277: dup
       278: getstatic     #248                // Field org/scalatest/FailureMessages$.MODULE$:Lorg/scalatest/FailureMessages$;
       281: getstatic     #291                // Field org/scalactic/Prettifier$.MODULE$:Lorg/scalactic/Prettifier$;
       284: invokevirtual #295                // Method org/scalactic/Prettifier$.default:()Lorg/scalactic/Prettifier;
       287: getstatic     #300                // Field org/scalatest/UnquotedString$.MODULE$:Lorg/scalatest/UnquotedString$;
       290: aload         11
       292: invokevirtual #335                // Method java/lang/Throwable.getClass:()Ljava/lang/Class;
       295: invokevirtual #309                // Method java/lang/Class.getName:()Ljava/lang/String;
       298: invokevirtual #312                // Method org/scalatest/UnquotedString$.apply:(Ljava/lang/String;)Lorg/scalatest/UnquotedString;
       301: aload_1
       302: aload         11
       304: invokevirtual #336                // Method java/lang/Throwable.getMessage:()Ljava/lang/String;
       307: invokevirtual #319                // Method org/scalatest/FailureMessages$.exceptionWasThrownInDescribeClause:(Lorg/scalactic/Prettifier;Ljava/lang/Object;Ljava/lang/Object;Ljava/lang/Object;)Ljava/lang/String;
       310: new           #169                // class scala/Some
       313: dup
       314: aload         11
       316: invokespecial #172                // Method scala/Some."<init>":(Ljava/lang/Object;)V
       319: aload_3
       320: invokespecial #276                // Method org/scalatest/exceptions/NotAllowedException."<init>":(Ljava/lang/String;Lscala/Option;Lorg/scalactic/source/Position;)V
       323: athrow
       324: goto          330
       327: goto          330
       330: aload         7
       332: ifnull        342
       335: aload         7
       337: astore        12
       339: aload         12
       341: athrow
       342: goto          345
       345: aload         6
       347: athrow
       348: return
      Exception table:
         from    to  target type
             3    45    48   Class java/lang/Throwable
      StackMapTable: number_of_entries = 13
        frame_type = 255 /* full_frame */
          offset_delta = 48
          locals = [ class org/scalatest/funspec/AnyFunSpecLike, class java/lang/String, class scala/Function0, class org/scalactic/source/Position, top, int ]
          stack = [ class java/lang/Throwable ]
        frame_type = 253 /* append */
          offset_delta = 60
          locals = [ class java/lang/Throwable, class java/lang/Throwable ]
        frame_type = 2 /* same */
        frame_type = 54 /* same */
        frame_type = 2 /* same */
        frame_type = 251 /* same_frame_extended */
          offset_delta = 80
        frame_type = 2 /* same */
        frame_type = 255 /* full_frame */
          offset_delta = 69
          locals = [ class org/scalatest/funspec/AnyFunSpecLike, class java/lang/String, class scala/Function0, class org/scalactic/source/Position, top, int, class java/lang/Throwable, class java/lang/Throwable, top, top, top, class java/lang/Throwable ]
          stack = []
        frame_type = 255 /* full_frame */
          offset_delta = 2
          locals = [ class org/scalatest/funspec/AnyFunSpecLike, class java/lang/String, class scala/Function0, class org/scalactic/source/Position, top, int, class java/lang/Throwable, class java/lang/Throwable ]
          stack = []
        frame_type = 2 /* same */
        frame_type = 11 /* same */
        frame_type = 2 /* same */
        frame_type = 249 /* chop */
          offset_delta = 2
      LineNumberTable:
        line 426: 0
        line 430: 3
        line 433: 50
        line 433: 54
        line 434: 112
        line 435: 170
        line 436: 254
        line 437: 330
        line 429: 345
      LocalVariableTable:
        Start  Length  Slot  Name   Signature
            3     345     5 stackDepth   I
            0     349     0  this   Lorg/scalatest/funspec/AnyFunSpecLike;
            0     349     1 description   Ljava/lang/String;
            0     349     2   fun   Lscala/Function0;
            0     349     3   pos   Lorg/scalactic/source/Position;
    Signature: #224                         // (Ljava/lang/String;Lscala/Function0<Lscala/runtime/BoxedUnit;>;Lorg/scalactic/source/Position;)V
    MethodParameters:
      Name                           Flags
      description                    final
      fun                            final
      pos                            final

  public static void describe$(org.scalatest.funspec.AnyFunSpecLike, java.lang.String, scala.Function0, org.scalactic.source.Position);
    descriptor: (Lorg/scalatest/funspec/AnyFunSpecLike;Ljava/lang/String;Lscala/Function0;Lorg/scalactic/source/Position;)V
    flags: (0x1009) ACC_PUBLIC, ACC_STATIC, ACC_SYNTHETIC
    Code:
      stack=4, locals=4, args_size=4
         0: aload_0
         1: aload_1
         2: aload_2
         3: aload_3
         4: invokespecial #344                // InterfaceMethod describe:(Ljava/lang/String;Lscala/Function0;Lorg/scalactic/source/Position;)V
         7: return
      LineNumberTable:
        line 448: 0
      LocalVariableTable:
        Start  Length  Slot  Name   Signature
            0       8     0 $this   Lorg/scalatest/funspec/AnyFunSpecLike;
            0       8     1 description   Ljava/lang/String;
            0       8     2   fun   Lscala/Function0;
            0       8     3   pos   Lorg/scalactic/source/Position;
    MethodParameters:
      Name                           Flags
      $this                          final synthetic
      description                    final
      fun                            final
      pos                            final

  public default void describe(java.lang.String, scala.Function0<scala.runtime.BoxedUnit>, org.scalactic.source.Position);
    descriptor: (Ljava/lang/String;Lscala/Function0;Lorg/scalactic/source/Position;)V
    flags: (0x0001) ACC_PUBLIC
    Code:
      stack=4, locals=4, args_size=4
         0: aload_0
         1: aload_1
         2: aload_2
         3: aload_3
         4: invokespecial #346                // InterfaceMethod describeImpl:(Ljava/lang/String;Lscala/Function0;Lorg/scalactic/source/Position;)V
         7: return
      LineNumberTable:
        line 449: 0
      LocalVariableTable:
        Start  Length  Slot  Name   Signature
            0       8     0  this   Lorg/scalatest/funspec/AnyFunSpecLike;
            0       8     1 description   Ljava/lang/String;
            0       8     2   fun   Lscala/Function0;
            0       8     3   pos   Lorg/scalactic/source/Position;
    Signature: #224                         // (Ljava/lang/String;Lscala/Function0<Lscala/runtime/BoxedUnit;>;Lorg/scalactic/source/Position;)V
    MethodParameters:
      Name                           Flags
      description                    final
      fun                            final
      pos                            final

  public static scala.collection.immutable.Set testNames$(org.scalatest.funspec.AnyFunSpecLike);
    descriptor: (Lorg/scalatest/funspec/AnyFunSpecLike;)Lscala/collection/immutable/Set;
    flags: (0x1009) ACC_PUBLIC, ACC_STATIC, ACC_SYNTHETIC
    Code:
      stack=1, locals=1, args_size=1
         0: aload_0
         1: invokespecial #352                // InterfaceMethod testNames:()Lscala/collection/immutable/Set;
         4: areturn
      LineNumberTable:
        line 492: 0
      LocalVariableTable:
        Start  Length  Slot  Name   Signature
            0       5     0 $this   Lorg/scalatest/funspec/AnyFunSpecLike;
    MethodParameters:
      Name                           Flags
      $this                          final synthetic

  public default scala.collection.immutable.Set<java.lang.String> testNames();
    descriptor: ()Lscala/collection/immutable/Set;
    flags: (0x0001) ACC_PUBLIC
    Code:
      stack=2, locals=1, args_size=1
         0: getstatic     #358                // Field org/scalatest/InsertionOrderSet$.MODULE$:Lorg/scalatest/InsertionOrderSet$;
         3: aload_0
         4: invokeinterface #77,  1           // InterfaceMethod org$scalatest$funspec$AnyFunSpecLike$$engine:()Lorg/scalatest/Engine;
         9: invokevirtual #361                // Method org/scalatest/Engine.atomic:()Ljava/util/concurrent/atomic/AtomicReference;
        12: invokevirtual #89                 // Method java/util/concurrent/atomic/AtomicReference.get:()Ljava/lang/Object;
        15: checkcast     #30                 // class org/scalatest/SuperEngine$Bundle
        18: invokevirtual #365                // Method org/scalatest/SuperEngine$Bundle.testNamesList:()Lscala/collection/immutable/List;
        21: invokevirtual #368                // Method org/scalatest/InsertionOrderSet$.apply:(Lscala/collection/immutable/List;)Lscala/collection/immutable/Set;
        24: areturn
      LineNumberTable:
        line 493: 0
      LocalVariableTable:
        Start  Length  Slot  Name   Signature
            0      25     0  this   Lorg/scalatest/funspec/AnyFunSpecLike;
    Signature: #353                         // ()Lscala/collection/immutable/Set<Ljava/lang/String;>;

  public static org.scalatest.Status runTest$(org.scalatest.funspec.AnyFunSpecLike, java.lang.String, org.scalatest.Args);
    descriptor: (Lorg/scalatest/funspec/AnyFunSpecLike;Ljava/lang/String;Lorg/scalatest/Args;)Lorg/scalatest/Status;
    flags: (0x1009) ACC_PUBLIC, ACC_STATIC, ACC_SYNTHETIC
    Code:
      stack=3, locals=3, args_size=3
         0: aload_0
         1: aload_1
         2: aload_2
         3: invokespecial #374                // InterfaceMethod runTest:(Ljava/lang/String;Lorg/scalatest/Args;)Lorg/scalatest/Status;
         6: areturn
      LineNumberTable:
        line 509: 0
      LocalVariableTable:
        Start  Length  Slot  Name   Signature
            0       7     0 $this   Lorg/scalatest/funspec/AnyFunSpecLike;
            0       7     1 testName   Ljava/lang/String;
            0       7     2  args   Lorg/scalatest/Args;
    MethodParameters:
      Name                           Flags
      $this                          final synthetic
      testName                       final
      args                           final

  public default org.scalatest.Status runTest(java.lang.String, org.scalatest.Args);
    descriptor: (Ljava/lang/String;Lorg/scalatest/Args;)Lorg/scalatest/Status;
    flags: (0x0001) ACC_PUBLIC
    Code:
      stack=8, locals=3, args_size=3
         0: aload_0
         1: invokeinterface #77,  1           // InterfaceMethod org$scalatest$funspec$AnyFunSpecLike$$engine:()Lorg/scalatest/Engine;
         6: aload_0
         7: aload_1
         8: aload_2
         9: iconst_1
        10: aload_0
        11: aload_2
        12: aload_1
        13: invokedynamic #387,  0            // InvokeDynamic #7:apply:(Lorg/scalatest/funspec/AnyFunSpecLike;Lorg/scalatest/Args;Ljava/lang/String;)Lscala/Function1;
        18: invokevirtual #391                // Method org/scalatest/Engine.runTestImpl:(Lorg/scalatest/Suite;Ljava/lang/String;Lorg/scalatest/Args;ZLscala/Function1;)Lorg/scalatest/Status;
        21: areturn
      LineNumberTable:
        line 527: 0
      LocalVariableTable:
        Start  Length  Slot  Name   Signature
            0      22     0  this   Lorg/scalatest/funspec/AnyFunSpecLike;
            0      22     1 testName   Ljava/lang/String;
            0      22     2  args   Lorg/scalatest/Args;
    MethodParameters:
      Name                           Flags
      testName                       final
      args                           final

  public static scala.collection.immutable.Map tags$(org.scalatest.funspec.AnyFunSpecLike);
    descriptor: (Lorg/scalatest/funspec/AnyFunSpecLike;)Lscala/collection/immutable/Map;
    flags: (0x1009) ACC_PUBLIC, ACC_STATIC, ACC_SYNTHETIC
    Code:
      stack=1, locals=1, args_size=1
         0: aload_0
         1: invokespecial #397                // InterfaceMethod tags:()Lscala/collection/immutable/Map;
         4: areturn
      LineNumberTable:
        line 545: 0
      LocalVariableTable:
        Start  Length  Slot  Name   Signature
            0       5     0 $this   Lorg/scalatest/funspec/AnyFunSpecLike;
    MethodParameters:
      Name                           Flags
      $this                          final synthetic

  public default scala.collection.immutable.Map<java.lang.String, scala.collection.immutable.Set<java.lang.String>> tags();
    descriptor: ()Lscala/collection/immutable/Map;
    flags: (0x0001) ACC_PUBLIC
    Code:
      stack=3, locals=1, args_size=1
         0: getstatic     #330                // Field org/scalatest/Suite$.MODULE$:Lorg/scalatest/Suite$;
         3: aload_0
         4: invokeinterface #77,  1           // InterfaceMethod org$scalatest$funspec$AnyFunSpecLike$$engine:()Lorg/scalatest/Engine;
         9: invokevirtual #361                // Method org/scalatest/Engine.atomic:()Ljava/util/concurrent/atomic/AtomicReference;
        12: invokevirtual #89                 // Method java/util/concurrent/atomic/AtomicReference.get:()Ljava/lang/Object;
        15: checkcast     #30                 // class org/scalatest/SuperEngine$Bundle
        18: invokevirtual #401                // Method org/scalatest/SuperEngine$Bundle.tagsMap:()Lscala/collection/immutable/Map;
        21: aload_0
        22: invokevirtual #405                // Method org/scalatest/Suite$.autoTagClassAnnotations:(Lscala/collection/immutable/Map;Lorg/scalatest/Suite;)Lscala/collection/immutable/Map;
        25: areturn
      LineNumberTable:
        line 545: 0
      LocalVariableTable:
        Start  Length  Slot  Name   Signature
            0      26     0  this   Lorg/scalatest/funspec/AnyFunSpecLike;
    Signature: #398                         // ()Lscala/collection/immutable/Map<Ljava/lang/String;Lscala/collection/immutable/Set<Ljava/lang/String;>;>;

  public static org.scalatest.Status runTests$(org.scalatest.funspec.AnyFunSpecLike, scala.Option, org.scalatest.Args);
    descriptor: (Lorg/scalatest/funspec/AnyFunSpecLike;Lscala/Option;Lorg/scalatest/Args;)Lorg/scalatest/Status;
    flags: (0x1009) ACC_PUBLIC, ACC_STATIC, ACC_SYNTHETIC
    Code:
      stack=3, locals=3, args_size=3
         0: aload_0
         1: aload_1
         2: aload_2
         3: invokespecial #410                // InterfaceMethod runTests:(Lscala/Option;Lorg/scalatest/Args;)Lorg/scalatest/Status;
         6: areturn
      LineNumberTable:
        line 559: 0
      LocalVariableTable:
        Start  Length  Slot  Name   Signature
            0       7     0 $this   Lorg/scalatest/funspec/AnyFunSpecLike;
            0       7     1 testName   Lscala/Option;
            0       7     2  args   Lorg/scalatest/Args;
    MethodParameters:
      Name                           Flags
      $this                          final synthetic
      testName                       final
      args                           final

  public default org.scalatest.Status runTests(scala.Option<java.lang.String>, org.scalatest.Args);
    descriptor: (Lscala/Option;Lorg/scalatest/Args;)Lorg/scalatest/Status;
    flags: (0x0001) ACC_PUBLIC
    Code:
      stack=7, locals=3, args_size=3
         0: aload_0
         1: invokeinterface #77,  1           // InterfaceMethod org$scalatest$funspec$AnyFunSpecLike$$engine:()Lorg/scalatest/Engine;
         6: aload_0
         7: aload_1
         8: aload_2
         9: aload_0
        10: invokeinterface #74,  1           // InterfaceMethod info:()Lorg/scalatest/Informer;
        15: iconst_1
        16: aload_0
        17: invokedynamic #422,  0            // InvokeDynamic #8:apply:(Lorg/scalatest/funspec/AnyFunSpecLike;)Lscala/Function2;
        22: invokevirtual #426                // Method org/scalatest/Engine.runTestsImpl:(Lorg/scalatest/Suite;Lscala/Option;Lorg/scalatest/Args;Lorg/scalatest/Informer;ZLscala/Function2;)Lorg/scalatest/Status;
        25: areturn
      LineNumberTable:
        line 560: 0
      LocalVariableTable:
        Start  Length  Slot  Name   Signature
            0      26     0  this   Lorg/scalatest/funspec/AnyFunSpecLike;
            0      26     1 testName   Lscala/Option;
            0      26     2  args   Lorg/scalatest/Args;
    Signature: #412                         // (Lscala/Option<Ljava/lang/String;>;Lorg/scalatest/Args;)Lorg/scalatest/Status;
    MethodParameters:
      Name                           Flags
      testName                       final
      args                           final

  public static org.scalatest.Status run$(org.scalatest.funspec.AnyFunSpecLike, scala.Option, org.scalatest.Args);
    descriptor: (Lorg/scalatest/funspec/AnyFunSpecLike;Lscala/Option;Lorg/scalatest/Args;)Lorg/scalatest/Status;
    flags: (0x1009) ACC_PUBLIC, ACC_STATIC, ACC_SYNTHETIC
    Code:
      stack=3, locals=3, args_size=3
         0: aload_0
         1: aload_1
         2: aload_2
         3: invokespecial #430                // InterfaceMethod run:(Lscala/Option;Lorg/scalatest/Args;)Lorg/scalatest/Status;
         6: areturn
      LineNumberTable:
        line 563: 0
      LocalVariableTable:
        Start  Length  Slot  Name   Signature
            0       7     0 $this   Lorg/scalatest/funspec/AnyFunSpecLike;
            0       7     1 testName   Lscala/Option;
            0       7     2  args   Lorg/scalatest/Args;
    MethodParameters:
      Name                           Flags
      $this                          final synthetic
      testName                       final
      args                           final

  public default org.scalatest.Status run(scala.Option<java.lang.String>, org.scalatest.Args);
    descriptor: (Lscala/Option;Lorg/scalatest/Args;)Lorg/scalatest/Status;
    flags: (0x0001) ACC_PUBLIC
    Code:
      stack=5, locals=3, args_size=3
         0: aload_0
         1: invokeinterface #77,  1           // InterfaceMethod org$scalatest$funspec$AnyFunSpecLike$$engine:()Lorg/scalatest/Engine;
         6: aload_0
         7: aload_1
         8: aload_2
         9: aload_0
        10: invokedynamic #436,  0            // InvokeDynamic #9:apply:(Lorg/scalatest/funspec/AnyFunSpecLike;)Lscala/Function2;
        15: invokevirtual #440                // Method org/scalatest/Engine.runImpl:(Lorg/scalatest/Suite;Lscala/Option;Lorg/scalatest/Args;Lscala/Function2;)Lorg/scalatest/Status;
        18: areturn
      LineNumberTable:
        line 564: 0
      LocalVariableTable:
        Start  Length  Slot  Name   Signature
            0      19     0  this   Lorg/scalatest/funspec/AnyFunSpecLike;
            0      19     1 testName   Lscala/Option;
            0      19     2  args   Lorg/scalatest/Args;
    Signature: #412                         // (Lscala/Option<Ljava/lang/String;>;Lorg/scalatest/Args;)Lorg/scalatest/Status;
    MethodParameters:
      Name                           Flags
      testName                       final
      args                           final

  public abstract org.scalatest.verbs.BehaveWord behave();
    descriptor: ()Lorg/scalatest/verbs/BehaveWord;
    flags: (0x0401) ACC_PUBLIC, ACC_ABSTRACT

  public abstract java.lang.String styleName();
    descriptor: ()Ljava/lang/String;
    flags: (0x0401) ACC_PUBLIC, ACC_ABSTRACT
    Deprecated: true

  public static org.scalatest.TestData testDataFor$(org.scalatest.funspec.AnyFunSpecLike, java.lang.String, org.scalatest.ConfigMap);
    descriptor: (Lorg/scalatest/funspec/AnyFunSpecLike;Ljava/lang/String;Lorg/scalatest/ConfigMap;)Lorg/scalatest/TestData;
    flags: (0x1009) ACC_PUBLIC, ACC_STATIC, ACC_SYNTHETIC
    Code:
      stack=3, locals=3, args_size=3
         0: aload_0
         1: aload_1
         2: aload_2
         3: invokespecial #450                // InterfaceMethod testDataFor:(Ljava/lang/String;Lorg/scalatest/ConfigMap;)Lorg/scalatest/TestData;
         6: areturn
      LineNumberTable:
        line 595: 0
      LocalVariableTable:
        Start  Length  Slot  Name   Signature
            0       7     0 $this   Lorg/scalatest/funspec/AnyFunSpecLike;
            0       7     1 testName   Ljava/lang/String;
            0       7     2 theConfigMap   Lorg/scalatest/ConfigMap;
    MethodParameters:
      Name                           Flags
      $this                          final synthetic
      testName                       final
      theConfigMap                   final

  public default org.scalatest.TestData testDataFor(java.lang.String, org.scalatest.ConfigMap);
    descriptor: (Ljava/lang/String;Lorg/scalatest/ConfigMap;)Lorg/scalatest/TestData;
    flags: (0x0001) ACC_PUBLIC
    Code:
      stack=4, locals=3, args_size=3
         0: aload_0
         1: invokeinterface #77,  1           // InterfaceMethod org$scalatest$funspec$AnyFunSpecLike$$engine:()Lorg/scalatest/Engine;
         6: aload_1
         7: aload_2
         8: aload_0
         9: invokevirtual #455                // Method org/scalatest/Engine.createTestDataFor:(Ljava/lang/String;Lorg/scalatest/ConfigMap;Lorg/scalatest/Suite;)Lorg/scalatest/TestData;
        12: areturn
      LineNumberTable:
        line 595: 0
      LocalVariableTable:
        Start  Length  Slot  Name   Signature
            0      13     0  this   Lorg/scalatest/funspec/AnyFunSpecLike;
            0      13     1 testName   Ljava/lang/String;
            0      13     2 theConfigMap   Lorg/scalatest/ConfigMap;
    MethodParameters:
      Name                           Flags
      testName                       final
      theConfigMap                   final

  public static org.scalatest.ConfigMap testDataFor$default$2$(org.scalatest.funspec.AnyFunSpecLike);
    descriptor: (Lorg/scalatest/funspec/AnyFunSpecLike;)Lorg/scalatest/ConfigMap;
    flags: (0x1009) ACC_PUBLIC, ACC_STATIC, ACC_SYNTHETIC
    Code:
      stack=1, locals=1, args_size=1
         0: aload_0
         1: invokespecial #461                // InterfaceMethod testDataFor$default$2:()Lorg/scalatest/ConfigMap;
         4: areturn
      LineNumberTable:
        line 595: 0
      LocalVariableTable:
        Start  Length  Slot  Name   Signature
            0       5     0 $this   Lorg/scalatest/funspec/AnyFunSpecLike;
    MethodParameters:
      Name                           Flags
      $this                          final synthetic

  public default org.scalatest.ConfigMap testDataFor$default$2();
    descriptor: ()Lorg/scalatest/ConfigMap;
    flags: (0x0001) ACC_PUBLIC
    Code:
      stack=1, locals=1, args_size=1
         0: getstatic     #466                // Field org/scalatest/ConfigMap$.MODULE$:Lorg/scalatest/ConfigMap$;
         3: invokevirtual #469                // Method org/scalatest/ConfigMap$.empty:()Lorg/scalatest/ConfigMap;
         6: areturn
      LineNumberTable:
        line 595: 0
      LocalVariableTable:
        Start  Length  Slot  Name   Signature
            0       7     0  this   Lorg/scalatest/funspec/AnyFunSpecLike;

  public static java.lang.String $anonfun$engine$1();
    descriptor: ()Ljava/lang/String;
    flags: (0x1009) ACC_PUBLIC, ACC_STATIC, ACC_SYNTHETIC
    Code:
      stack=1, locals=0, args_size=0
         0: getstatic     #475                // Field org/scalatest/Resources$.MODULE$:Lorg/scalatest/Resources$;
         3: invokevirtual #478                // Method org/scalatest/Resources$.concurrentSpecMod:()Ljava/lang/String;
         6: areturn
      LineNumberTable:
        line 51: 0

  public static java.lang.String $anonfun$registerTestImpl$1();
    descriptor: ()Ljava/lang/String;
    flags: (0x1009) ACC_PUBLIC, ACC_STATIC, ACC_SYNTHETIC
    Code:
      stack=1, locals=0, args_size=0
         0: getstatic     #475                // Field org/scalatest/Resources$.MODULE$:Lorg/scalatest/Resources$;
         3: invokevirtual #481                // Method org/scalatest/Resources$.testCannotBeNestedInsideAnotherTest:()Ljava/lang/String;
         6: areturn
      LineNumberTable:
        line 104: 0

  public static java.lang.String $anonfun$registerIgnoredTestImpl$1();
    descriptor: ()Ljava/lang/String;
    flags: (0x1009) ACC_PUBLIC, ACC_STATIC, ACC_SYNTHETIC
    Code:
      stack=1, locals=0, args_size=0
         0: getstatic     #475                // Field org/scalatest/Resources$.MODULE$:Lorg/scalatest/Resources$;
         3: invokevirtual #481                // Method org/scalatest/Resources$.testCannotBeNestedInsideAnotherTest:()Ljava/lang/String;
         6: areturn
      LineNumberTable:
        line 121: 0

  public static java.lang.String $anonfun$ignoreImpl$1();
    descriptor: ()Ljava/lang/String;
    flags: (0x1009) ACC_PUBLIC, ACC_STATIC, ACC_SYNTHETIC
    Code:
      stack=1, locals=0, args_size=0
         0: getstatic     #475                // Field org/scalatest/Resources$.MODULE$:Lorg/scalatest/Resources$;
         3: invokevirtual #484                // Method org/scalatest/Resources$.ignoreCannotAppearInsideAnItOrAThey:()Ljava/lang/String;
         6: areturn
      LineNumberTable:
        line 394: 0

  public static java.lang.String $anonfun$describeImpl$1();
    descriptor: ()Ljava/lang/String;
    flags: (0x1009) ACC_PUBLIC, ACC_STATIC, ACC_SYNTHETIC
    Code:
      stack=1, locals=0, args_size=0
         0: getstatic     #475                // Field org/scalatest/Resources$.MODULE$:Lorg/scalatest/Resources$;
         3: invokevirtual #487                // Method org/scalatest/Resources$.describeCannotAppearInsideAnIt:()Ljava/lang/String;
         6: areturn
      LineNumberTable:
        line 430: 0

  public static org.scalactic.source.Position $anonfun$describeImpl$2(org.scalactic.source.Position);
    descriptor: (Lorg/scalactic/source/Position;)Lorg/scalactic/source/Position;
    flags: (0x1009) ACC_PUBLIC, ACC_STATIC, ACC_SYNTHETIC
    Code:
      stack=1, locals=1, args_size=1
         0: aload_0
         1: areturn
      LineNumberTable:
        line 433: 0
      LocalVariableTable:
        Start  Length  Slot  Name   Signature
            0       2     0 pos$1   Lorg/scalactic/source/Position;
    MethodParameters:
      Name                           Flags
      pos$1                          final

  public static org.scalactic.source.Position $anonfun$describeImpl$3(org.scalactic.source.Position);
    descriptor: (Lorg/scalactic/source/Position;)Lorg/scalactic/source/Position;
    flags: (0x1009) ACC_PUBLIC, ACC_STATIC, ACC_SYNTHETIC
    Code:
      stack=1, locals=1, args_size=1
         0: aload_0
         1: areturn
      LineNumberTable:
        line 434: 0
      LocalVariableTable:
        Start  Length  Slot  Name   Signature
            0       2     0 pos$1   Lorg/scalactic/source/Position;
    MethodParameters:
      Name                           Flags
      pos$1                          final

  public static org.scalactic.source.Position $anonfun$describeImpl$4(org.scalactic.source.Position);
    descriptor: (Lorg/scalactic/source/Position;)Lorg/scalactic/source/Position;
    flags: (0x1009) ACC_PUBLIC, ACC_STATIC, ACC_SYNTHETIC
    Code:
      stack=1, locals=1, args_size=1
         0: aload_0
         1: areturn
      LineNumberTable:
        line 435: 0
      LocalVariableTable:
        Start  Length  Slot  Name   Signature
            0       2     0 pos$1   Lorg/scalactic/source/Position;
    MethodParameters:
      Name                           Flags
      pos$1                          final

  private org.scalatest.Outcome invokeWithFixture$1(org.scalatest.SuperEngine$TestLeaf, org.scalatest.Args, java.lang.String);
    descriptor: (Lorg/scalatest/SuperEngine$TestLeaf;Lorg/scalatest/Args;Ljava/lang/String;)Lorg/scalatest/Outcome;
    flags: (0x0002) ACC_PRIVATE
    Code:
      stack=6, locals=6, args_size=4
         0: aload_2
         1: invokevirtual #498                // Method org/scalatest/Args.configMap:()Lorg/scalatest/ConfigMap;
         4: astore        4
         6: aload_0
         7: aload_3
         8: aload         4
        10: invokeinterface #450,  3          // InterfaceMethod testDataFor:(Ljava/lang/String;Lorg/scalatest/ConfigMap;)Lorg/scalatest/TestData;
        15: astore        5
        17: aload_0
        18: new           #41                 // class org/scalatest/funspec/AnyFunSpecLike$$anon$1
        21: dup
        22: aconst_null
        23: aload         5
        25: aload_1
        26: invokespecial #501                // Method org/scalatest/funspec/AnyFunSpecLike$$anon$1."<init>":(Lorg/scalatest/funspec/AnyFunSpecLike;Lorg/scalatest/TestData;Lorg/scalatest/SuperEngine$TestLeaf;)V
        29: invokeinterface #505,  2          // InterfaceMethod withFixture:(Lorg/scalatest/TestSuite$NoArgTest;)Lorg/scalatest/Outcome;
        34: areturn
      LineNumberTable:
        line 512: 0
        line 513: 6
        line 514: 17
        line 515: 18
      LocalVariableTable:
        Start  Length  Slot  Name   Signature
            6      28     4 theConfigMap   Lorg/scalatest/ConfigMap;
           17      17     5 testData   Lorg/scalatest/TestData;
            0      35     0  this   Lorg/scalatest/funspec/AnyFunSpecLike;
            0      35     1 theTest   Lorg/scalatest/SuperEngine$TestLeaf;
            0      35     2 args$1   Lorg/scalatest/Args;
            0      35     3 testName$1   Ljava/lang/String;
    MethodParameters:
      Name                           Flags
      theTest                        final
      args$1                         final
      testName$1                     final

  public static org.scalatest.Outcome $anonfun$runTest$1(org.scalatest.funspec.AnyFunSpecLike, org.scalatest.Args, java.lang.String, org.scalatest.SuperEngine$TestLeaf);
    descriptor: (Lorg/scalatest/funspec/AnyFunSpecLike;Lorg/scalatest/Args;Ljava/lang/String;Lorg/scalatest/SuperEngine$TestLeaf;)Lorg/scalatest/Outcome;
    flags: (0x1009) ACC_PUBLIC, ACC_STATIC, ACC_SYNTHETIC
    Code:
      stack=4, locals=4, args_size=4
         0: aload_0
         1: aload_3
         2: aload_1
         3: aload_2
         4: invokespecial #510                // InterfaceMethod invokeWithFixture$1:(Lorg/scalatest/SuperEngine$TestLeaf;Lorg/scalatest/Args;Ljava/lang/String;)Lorg/scalatest/Outcome;
         7: areturn
      LineNumberTable:
        line 527: 0
      LocalVariableTable:
        Start  Length  Slot  Name   Signature
            0       8     0 $this   Lorg/scalatest/funspec/AnyFunSpecLike;
            0       8     1 args$1   Lorg/scalatest/Args;
            0       8     2 testName$1   Ljava/lang/String;
            0       8     3 theTest   Lorg/scalatest/SuperEngine$TestLeaf;
    MethodParameters:
      Name                           Flags
      $this                          final synthetic
      args$1                         final
      testName$1                     final
      theTest                        final

  public static org.scalatest.Status $anonfun$runTests$1(org.scalatest.funspec.AnyFunSpecLike, java.lang.String, org.scalatest.Args);
    descriptor: (Lorg/scalatest/funspec/AnyFunSpecLike;Ljava/lang/String;Lorg/scalatest/Args;)Lorg/scalatest/Status;
    flags: (0x1009) ACC_PUBLIC, ACC_STATIC, ACC_SYNTHETIC
    Code:
      stack=3, locals=3, args_size=3
         0: aload_0
         1: aload_1
         2: aload_2
         3: invokeinterface #374,  3          // InterfaceMethod runTest:(Ljava/lang/String;Lorg/scalatest/Args;)Lorg/scalatest/Status;
         8: areturn
      LineNumberTable:
        line 560: 0
      LocalVariableTable:
        Start  Length  Slot  Name   Signature
            0       9     0 $this   Lorg/scalatest/funspec/AnyFunSpecLike;
            0       9     1 testName   Ljava/lang/String;
            0       9     2  args   Lorg/scalatest/Args;
    MethodParameters:
      Name                           Flags
      $this                          final synthetic
      testName                       final
      args                           final

  public static org.scalatest.Status $anonfun$run$1(org.scalatest.funspec.AnyFunSpecLike, scala.Option, org.scalatest.Args);
    descriptor: (Lorg/scalatest/funspec/AnyFunSpecLike;Lscala/Option;Lorg/scalatest/Args;)Lorg/scalatest/Status;
    flags: (0x1009) ACC_PUBLIC, ACC_STATIC, ACC_SYNTHETIC
    Code:
      stack=3, locals=3, args_size=3
         0: aload_0
         1: aload_1
         2: aload_2
         3: invokeinterface #512,  3          // InterfaceMethod org$scalatest$funspec$AnyFunSpecLike$$super$run:(Lscala/Option;Lorg/scalatest/Args;)Lorg/scalatest/Status;
         8: areturn
      LineNumberTable:
        line 564: 0
      LocalVariableTable:
        Start  Length  Slot  Name   Signature
            0       9     0 $this   Lorg/scalatest/funspec/AnyFunSpecLike;
            0       9     1 testName   Lscala/Option;
            0       9     2  args   Lorg/scalatest/Args;
    MethodParameters:
      Name                           Flags
      $this                          final synthetic
      testName                       final
      args                           final

  public static void $init$(org.scalatest.funspec.AnyFunSpecLike);
    descriptor: (Lorg/scalatest/funspec/AnyFunSpecLike;)V
    flags: (0x0009) ACC_PUBLIC, ACC_STATIC
    Code:
      stack=5, locals=1, args_size=1
         0: aload_0
         1: new           #79                 // class org/scalatest/Engine
         4: dup
         5: invokedynamic #518,  0            // InvokeDynamic #10:apply:()Lscala/Function0;
        10: ldc_w         #520                // String FunSpec
        13: invokespecial #523                // Method org/scalatest/Engine."<init>":(Lscala/Function0;Ljava/lang/String;)V
        16: invokeinterface #525,  2          // InterfaceMethod org$scalatest$funspec$AnyFunSpecLike$_setter_$org$scalatest$funspec$AnyFunSpecLike$$engine_$eq:(Lorg/scalatest/Engine;)V
        21: aload_0
        22: ldc_w         #526                // String AnyFunSpecLike.scala
        25: invokeinterface #528,  2          // InterfaceMethod org$scalatest$funspec$AnyFunSpecLike$_setter_$sourceFileName_$eq:(Ljava/lang/String;)V
        30: aload_0
        31: new           #43                 // class org/scalatest/funspec/AnyFunSpecLike$ItWord
        34: dup
        35: aload_0
        36: invokespecial #530                // Method org/scalatest/funspec/AnyFunSpecLike$ItWord."<init>":(Lorg/scalatest/funspec/AnyFunSpecLike;)V
        39: invokeinterface #532,  2          // InterfaceMethod org$scalatest$funspec$AnyFunSpecLike$_setter_$it_$eq:(Lorg/scalatest/funspec/AnyFunSpecLike$ItWord;)V
        44: aload_0
        45: new           #46                 // class org/scalatest/funspec/AnyFunSpecLike$TheyWord
        48: dup
        49: aload_0
        50: invokespecial #533                // Method org/scalatest/funspec/AnyFunSpecLike$TheyWord."<init>":(Lorg/scalatest/funspec/AnyFunSpecLike;)V
        53: invokeinterface #535,  2          // InterfaceMethod org$scalatest$funspec$AnyFunSpecLike$_setter_$they_$eq:(Lorg/scalatest/funspec/AnyFunSpecLike$TheyWord;)V
        58: aload_0
        59: new           #537                // class org/scalatest/verbs/BehaveWord
        62: dup
        63: invokespecial #540                // Method org/scalatest/verbs/BehaveWord."<init>":()V
        66: invokeinterface #542,  2          // InterfaceMethod org$scalatest$funspec$AnyFunSpecLike$_setter_$behave_$eq:(Lorg/scalatest/verbs/BehaveWord;)V
        71: aload_0
        72: ldc_w         #544                // String org.scalatest.FunSpec
        75: invokeinterface #546,  2          // InterfaceMethod org$scalatest$funspec$AnyFunSpecLike$_setter_$styleName_$eq:(Ljava/lang/String;)V
        80: return
      LineNumberTable:
        line 51: 0
        line 55: 21
        line 264: 30
        line 385: 44
        line 584: 58
        line 593: 71
        line 49: 80
      LocalVariableTable:
        Start  Length  Slot  Name   Signature
            0      81     0 $this   Lorg/scalatest/funspec/AnyFunSpecLike;
    MethodParameters:
      Name                           Flags
      $this                          final synthetic

  private static java.lang.Object $deserializeLambda$(java.lang.invoke.SerializedLambda);
    descriptor: (Ljava/lang/invoke/SerializedLambda;)Ljava/lang/Object;
    flags: (0x100a) ACC_PRIVATE, ACC_STATIC, ACC_SYNTHETIC
    Code:
      stack=1, locals=1, args_size=1
         0: aload_0
         1: invokedynamic #558,  0            // InvokeDynamic #11:lambdaDeserialize:(Ljava/lang/invoke/SerializedLambda;)Ljava/lang/Object;
         6: areturn
}
InnerClasses:
  public static final #28= #25 of #27;    // Lookup=class java/lang/invoke/MethodHandles$Lookup of class java/lang/invoke/MethodHandles
  public #33= #30 of #32;                 // Bundle=class org/scalatest/SuperEngine$Bundle of class org/scalatest/SuperEngine
  public #36= #35 of #32;                 // TestLeaf=class org/scalatest/SuperEngine$TestLeaf of class org/scalatest/SuperEngine
  public #39= #38 of #6;                  // NoArgTest=class org/scalatest/TestSuite$NoArgTest of class org/scalatest/TestSuite
  public final #41;                       // class org/scalatest/funspec/AnyFunSpecLike$$anon$1
  public #44= #43 of #2;                  // ItWord=class org/scalatest/funspec/AnyFunSpecLike$ItWord of class org/scalatest/funspec/AnyFunSpecLike
  public #47= #46 of #2;                  // TheyWord=class org/scalatest/funspec/AnyFunSpecLike$TheyWord of class org/scalatest/funspec/AnyFunSpecLike
SourceFile: "AnyFunSpecLike.scala"
RuntimeVisibleAnnotations:
  0: #18(#19=[s#20])
    org.scalatest.Finders(
      value=["org.scalatest.finders.FunSpecFinder"]
    )
  1: #21(#22=s#23)
    scala.reflect.ScalaSignature(
      bytes="\u0006\u0005\t\u0015ga\u0002\u0015*!\u0003\r\t\u0001\r\u0005\u0006\u0015\u0002!\ta\u0013\u0005\b\u001f\u0002\u0011\r\u0011\"\u0004Q\u0011!!\u0006A1A\u0005\u0002-*\u0006\"\u00020\u0001\t#y\u0006\"B2\u0001\t#!\u0007\"\u00025\u0001\t#I\u0007\"B7\u0001\t#q\u0007\"\u0002:\u0001\t\u001b\u0019\bbBA\u001c\u0001\u0011\u0015\u0011\u0011\b\u0005\b\u0003\u000f\u0002AQBA%\u0011\u001d\t)\u0006\u0001C\u0003\u0003/2a!!\u001a\u0001\u0011\u0005\u001d\u0004bBA5\u0019\u0011\u0005\u00111\u000e\u0005\b\u0003cbAQBA:\u0011\u001d\t\t\t\u0004C\u0001\u0003\u0007Cq!!%\r\t\u0003\t\u0019\nC\u0004\u0002&2!\t!a*\t\u0013\u0005-\u0006A1A\u0005\u0012\u00055fABAX\u0001!\t\t\fC\u0004\u0002jM!\t!a-\t\u000f\u0005E4\u0003\"\u0004\u00028\"9\u0011\u0011Q\n\u0005\u0002\u0005\r\u0007bBAI\'\u0011\u0005\u0011\u0011\u001b\u0005\b\u0003K\u001bB\u0011AAk\u0011%\tI\u000e\u0001b\u0001\n#\tY\u000eC\u0004\u0002^\u0002!i!a8\t\u000f\u0005-\b\u0001\"\u0005\u0002n\"9\u00111 \u0001\u0005\u000e\u0005u\bb\u0002B\u0007\u0001\u0011E!q\u0002\u0005\b\u00057\u0001A\u0011\tB\u000f\u0011\u001d\u0011)\u0003\u0001C)\u0005OAqA!\u0010\u0001\t\u0003\u0012y\u0004C\u0004\u0003H\u0001!\tF!\u0013\t\u000f\tU\u0003\u0001\"\u0011\u0003X!I!Q\f\u0001C\u0002\u0013E!q\f\u0005\n\u0005C\u0002!\u0019!C#\u0005GBqA!\u001f\u0001\t\u0003\u0012Y\bC\u0005\u0003\u0010\u0002\t\n\u0011\"\u0001\u0003\u0012\"q!q\u0015\u0001\u0011\u0002\u0007\u0005\t\u0011\"\u0003\u0003*\n=&AD!os\u001a+hn\u00159fG2K7.\u001a\u0006\u0003U-\nqAZ;ogB,7M\u0003\u0002-[\u0005I1oY1mCR,7\u000f\u001e\u0006\u0002]\u0005\u0019qN]4\u0004\u0001MA\u0001!M\u001c<}\u0005#u\t\u0005\u00023k5\t1GC\u00015\u0003\u0015\u00198-\u00197b\u0013\t14G\u0001\u0004B]f\u0014VM\u001a\t\u0003qej\u0011aK\u0005\u0003u-\u0012\u0011\u0002V3tiN+\u0018\u000e^3\u0011\u0005ab\u0014BA\u001f,\u0005A!Vm\u001d;SK\u001eL7\u000f\u001e:bi&|g\u000e\u0005\u00029\u007f%\u0011\u0001i\u000b\u0002\n\u0013:4wN]7j]\u001e\u0004\"\u0001\u000f\"\n\u0005\r[#!\u0003(pi&4\u00170\u001b8h!\tAT)\u0003\u0002GW\tA\u0011\t\\3si&tw\r\u0005\u00029\u0011&\u0011\u0011j\u000b\u0002\f\t>\u001cW/\\3oi&tw-\u0001\u0004%S:LG\u000f\n\u000b\u0002\u0019B\u0011!\'T\u0005\u0003\u001dN\u0012A!\u00168ji\u00061QM\\4j]\u0016,\u0012!\u0015\t\u0003qIK!aU\u0016\u0003\r\u0015sw-\u001b8f\u00039\u0019x.\u001e:dK\u001aKG.\u001a(b[\u0016,\u0012A\u0016\t\u0003/rk\u0011\u0001\u0017\u0006\u00033j\u000bA\u0001\\1oO*\t1,\u0001\u0003kCZ\f\u0017BA/Y\u0005\u0019\u0019FO]5oO\u0006!\u0011N\u001c4p+\u0005\u0001\u0007C\u0001\u001db\u0013\t\u00117F\u0001\u0005J]\u001a|\'/\\3s\u0003\u0011qw\u000e^3\u0016\u0003\u0015\u0004\"\u0001\u000f4\n\u0005\u001d\\#\u0001\u0003(pi&4\u0017.\u001a:\u0002\u000b\u0005dWM\u001d;\u0016\u0003)\u0004\"\u0001O6\n\u00051\\#aB!mKJ$XM]\u0001\u0007[\u0006\u00148.\u001e9\u0016\u0003=\u0004\"\u0001\u000f9\n\u0005E\\#A\u0003#pGVlWM\u001c;fe\u0006\u0001\"/Z4jgR,\'\u000fV3ti&k\u0007\u000f\u001c\u000b\u0006i\u0006=\u0011q\u0005\u000b\u0004\u0019Vl\bB\u0002<\t\t\u0003\u0007q/A\u0004uKN$h)\u001e8\u0011\u0007IB(0\u0003\u0002zg\tAAHY=oC6,g\b\u0005\u00023w&\u0011Ap\r\u0002\u0004\u0003:L\b\"\u0002@\t\u0001\u0004y\u0018a\u00019pgB!\u0011\u0011AA\u0006\u001b\t\t\u0019A\u0003\u0003\u0002\u0006\u0005\u001d\u0011AB:pkJ\u001cWMC\u0002\u0002\n5\n\u0011b]2bY\u0006\u001cG/[2\n\t\u00055\u00111\u0001\u0002\t!>\u001c\u0018\u000e^5p]\"9\u0011\u0011\u0003\u0005A\u0002\u0005M\u0011\u0001\u0003;fgR$V\r\u001f;\u0011\t\u0005U\u00111\u0005\b\u0005\u0003/\ty\u0002E\u0002\u0002\u001aMj!!a\u0007\u000b\u0007\u0005uq&\u0001\u0004=e>|GOP\u0005\u0004\u0003C\u0019\u0014A\u0002)sK\u0012,g-C\u0002^\u0003KQ1!!\t4\u0011\u001d\tI\u0003\u0003a\u0001\u0003W\t\u0001\u0002^3tiR\u000bwm\u001d\t\u0006e\u00055\u0012\u0011G\u0005\u0004\u0003_\u0019$A\u0003\u001fsKB,\u0017\r^3e}A\u0019\u0001(a\r\n\u0007\u0005U2FA\u0002UC\u001e\fAB]3hSN$XM\u001d+fgR$b!a\u000f\u0002D\u0005\u0015C\u0003BA\u001f\u0003\u0003\"2\u0001TA \u0011\u0015q\u0018\u0002q\u0001\u0000\u0011\u00191\u0018\u0002\"a\u0001o\"9\u0011\u0011C\u0005A\u0002\u0005M\u0001bBA\u0015\u0013\u0001\u0007\u00111F\u0001\u0018e\u0016<\u0017n\u001d;fe&;gn\u001c:fIR+7\u000f^%na2$b!a\u0013\u0002R\u0005MC#\u0002\'\u0002N\u0005=\u0003B\u0002<\u000b\t\u0003\u0007q\u000fC\u0003\u007f\u0015\u0001\u0007q\u0010C\u0004\u0002\u0012)\u0001\r!a\u0005\t\u000f\u0005%\"\u00021\u0001\u0002,\u0005\u0019\"/Z4jgR,\'/S4o_J,G\rV3tiR1\u0011\u0011LA1\u0003G\"B!a\u0017\u0002`Q\u0019A*!\u0018\t\u000by\\\u00019A@\t\rY\\A\u00111\u0001x\u0011\u001d\t\tb\u0003a\u0001\u0003\'Aq!!\u000b\f\u0001\u0004\tYC\u0001\u0004Ji^{\'\u000fZ\n\u0003\u0019E\na\u0001P5oSRtDCAA7!\r\ty\u0007D\u0007\u0002\u0001\u0005I\u0011\r\u001d9ms&k\u0007\u000f\u001c\u000b\u0007\u0003k\nY(a \u0015\u000b1\u000b9(!\u001f\t\rYtA\u00111\u0001x\u0011\u0015qh\u00021\u0001\u0000\u0011\u001d\tiH\u0004a\u0001\u0003\'\t\u0001b\u001d9fGR+\u0007\u0010\u001e\u0005\b\u0003Sq\u0001\u0019AA\u0016\u0003\u0015\t\u0007\u000f\u001d7z)\u0019\t))!$\u0002\u0010R!\u0011qQAF)\ra\u0015\u0011\u0012\u0005\u0006}>\u0001\u001da \u0005\u0007m>!\t\u0019A<\t\u000f\u0005ut\u00021\u0001\u0002\u0014!9\u0011\u0011F\bA\u0002\u0005-\u0012AB:i_VdG\r\u0006\u0003\u0002\u0016\u0006\u0005\u0006\u0003BAL\u0003;k!!!\'\u000b\u0007\u0005m5&A\u0003wKJ\u00147/\u0003\u0003\u0002 \u0006e%A\u0003\"fQ\u00064XmV8sI\"9\u00111\u0015\tA\u0002\u0005U\u0015A\u00032fQ\u00064XmV8sI\u0006!Q.^:u)\u0011\t)*!+\t\u000f\u0005\r\u0016\u00031\u0001\u0002\u0016\u0006\u0011\u0011\u000e^\u000b\u0003\u0003[\u0012\u0001\u0002\u00165fs^{\'\u000fZ\n\u0003\'E\"\"!!.\u0011\u0007\u0005=4\u0003\u0006\u0004\u0002:\u0006}\u0016\u0011\u0019\u000b\u0006\u0019\u0006m\u0016Q\u0018\u0005\u0007mV!\t\u0019A<\t\u000by,\u0002\u0019A@\t\u000f\u0005uT\u00031\u0001\u0002\u0014!9\u0011\u0011F\u000bA\u0002\u0005-BCBAc\u0003\u001b\fy\r\u0006\u0003\u0002H\u0006-Gc\u0001\'\u0002J\")aP\u0006a\u0002\u007f\"1aO\u0006CA\u0002]Dq!! \u0017\u0001\u0004\t\u0019\u0002C\u0004\u0002*Y\u0001\r!a\u000b\u0015\t\u0005U\u00151\u001b\u0005\b\u0003G;\u0002\u0019AAK)\u0011\t)*a6\t\u000f\u0005\r\u0006\u00041\u0001\u0002\u0016\u0006!A\u000f[3z+\t\t),\u0001\u0006jO:|\'/Z%na2$b!!9\u0002h\u0006%H#\u0002\'\u0002d\u0006\u0015\bB\u0002<\u001b\t\u0003\u0007q\u000fC\u0003\u007f5\u0001\u0007q\u0010C\u0004\u0002\u0012i\u0001\r!a\u0005\t\u000f\u0005%\"\u00041\u0001\u0002,\u00051\u0011n\u001a8pe\u0016$b!a<\u0002x\u0006eH\u0003BAy\u0003k$2\u0001TAz\u0011\u0015q8\u0004q\u0001\u0000\u0011\u001918\u0004\"a\u0001o\"9\u0011\u0011C\u000eA\u0002\u0005M\u0001bBA\u00157\u0001\u0007\u00111F\u0001\rI\u0016\u001c8M]5cK&k\u0007\u000f\u001c\u000b\u0005\u0003\u007f\u0014I\u0001F\u0003M\u0005\u0003\u00119\u0001\u0003\u0005\u0003\u0004q!\t\u0019\u0001B\u0003\u0003\r1WO\u001c\t\u0004ead\u0005\"\u0002@\u001d\u0001\u0004y\bb\u0002B\u00069\u0001\u0007\u00111C\u0001\fI\u0016\u001c8M]5qi&|g.\u0001\u0005eKN\u001c\'/\u001b2f)\u0011\u0011\tB!\u0007\u0015\t\tM!q\u0003\u000b\u0004\u0019\nU\u0001\"\u0002@\u001e\u0001\by\b\u0002\u0003B\u0002;\u0011\u0005\rA!\u0002\t\u000f\t-Q\u00041\u0001\u0002\u0014\u0005IA/Z:u\u001d\u0006lWm]\u000b\u0003\u0005?\u0001b!!\u0006\u0003\"\u0005M\u0011\u0002\u0002B\u0012\u0003K\u00111aU3u\u0003\u001d\u0011XO\u001c+fgR$bA!\u000b\u00030\tM\u0002c\u0001\u001d\u0003,%\u0019!QF\u0016\u0003\rM#\u0018\r^;t\u0011\u001d\u0011\td\ba\u0001\u0003\'\t\u0001\u0002^3ti:\u000bW.\u001a\u0005\b\u0005ky\u0002\u0019\u0001B\u001c\u0003\u0011\t\'oZ:\u0011\u0007a\u0012I$C\u0002\u0003<-\u0012A!\u0011:hg\u0006!A/Y4t+\t\u0011\t\u0005\u0005\u0005\u0002\u0016\t\r\u00131\u0003B\u0010\u0013\u0011\u0011)%!\n\u0003\u00075\u000b\u0007/\u0001\u0005sk:$Vm\u001d;t)\u0019\u0011ICa\u0013\u0003T!9!\u0011G\u0011A\u0002\t5\u0003#\u0002\u001a\u0003P\u0005M\u0011b\u0001B)g\t1q\n\u001d;j_:DqA!\u000e\"\u0001\u0004\u00119$A\u0002sk:$bA!\u000b\u0003Z\tm\u0003b\u0002B\u0019E\u0001\u0007!Q\n\u0005\b\u0005k\u0011\u0003\u0019\u0001B\u001c\u0003\u0019\u0011W\r[1wKV\u0011\u0011QS\u0001\ngRLH.\u001a(b[\u0016,\"!a\u0005)\u0017\u0011\u00129G!\u001c\u0003p\tM$Q\u000f\t\u0004e\t%\u0014b\u0001B6g\tQA-\u001a9sK\u000e\fG/\u001a3\u0002\u000f5,7o]1hK\u0006\u0012!\u0011O\u0001})\",\u0007e\u001d;zY\u0016t\u0015-\\3!Y&4WmY=dY\u0016\u0004S.\u001a;i_\u0012\u0004\u0003.Y:!E\u0016,g\u000e\t3faJ,7-\u0019;fI\u0002\ng\u000e\u001a\u0011xS2d\u0007EY3!e\u0016lwN^3eA%t\u0007%\u0019\u0011gkR,(/\u001a\u0011wKJ\u001c\u0018n\u001c8!_\u001a\u00043kY1mCR+7\u000f\u001e\u0011xSRD\u0007E\\8!e\u0016\u0004H.Y2f[\u0016tGOL\u0001\u0006g&t7-Z\u0011\u0003\u0005o\nQa\r\u00182]A\n1\u0002^3ti\u0012\u000bG/\u0019$peR1!Q\u0010BB\u0005\u000b\u00032\u0001\u000fB@\u0013\r\u0011\ti\u000b\u0002\t)\u0016\u001cH\u000fR1uC\"9!\u0011G\u0013A\u0002\u0005M\u0001\"\u0003BDKA\u0005\t\u0019\u0001BE\u00031!\b.Z\"p]\u001aLw-T1q!\rA$1R\u0005\u0004\u0005\u001b[#!C\"p]\u001aLw-T1q\u0003U!Xm\u001d;ECR\fgi\u001c:%I\u00164\u0017-\u001e7uII*\"Aa%+\t\t%%QS\u0016\u0003\u0005/\u0003BA!\'\u0003$6\u0011!1\u0014\u0006\u0005\u0005;\u0013y*A\u0005v]\u000eDWmY6fI*\u0019!\u0011U\u001a\u0002\u0015\u0005tgn\u001c;bi&|g.\u0003\u0003\u0003&\nm%!E;oG\",7m[3e-\u0006\u0014\u0018.\u00198dK\u0006I1/\u001e9fe\u0012\u0012XO\u001c\u000b\u0007\u0005S\u0011YK!,\t\u000f\tEr\u00051\u0001\u0003N!9!QG\u0014A\u0002\t]\u0012\u0002\u0002B+\u0005cK1Aa-,\u0005\u0015\u0019V/\u001b;fQ\u001d\u0001!q\u0017B_\u0005\u007f\u00032\u0001\u000fB]\u0013\r\u0011Yl\u000b\u0002\b\r&tG-\u001a:t\u0003\u00151\u0018\r\\;fY\t\u0011\t-\t\u0002\u0003D\u0006\u0019sN]4/g\u000e\fG.\u0019;fgRtc-\u001b8eKJ\u001chFR;o\'B,7MR5oI\u0016\u0014\b"
    )
BootstrapMethods:
  0: #153 REF_invokeStatic java/lang/invoke/LambdaMetafactory.altMetafactory:(Ljava/lang/invoke/MethodHandles$Lookup;Ljava/lang/String;Ljava/lang/invoke/MethodType;[Ljava/lang/Object;)Ljava/lang/invoke/CallSite;
    Method arguments:
      #139 ()Ljava/lang/Object;
      #143 REF_invokeStatic org/scalatest/funspec/AnyFunSpecLike.$anonfun$registerTestImpl$1:()Ljava/lang/String;
      #144 ()Ljava/lang/String;
      #145 5
      #146 1
      #144 ()Ljava/lang/String;
  1: #153 REF_invokeStatic java/lang/invoke/LambdaMetafactory.altMetafactory:(Ljava/lang/invoke/MethodHandles$Lookup;Ljava/lang/String;Ljava/lang/invoke/MethodType;[Ljava/lang/Object;)Ljava/lang/invoke/CallSite;
    Method arguments:
      #139 ()Ljava/lang/Object;
      #192 REF_invokeStatic org/scalatest/funspec/AnyFunSpecLike.$anonfun$registerIgnoredTestImpl$1:()Ljava/lang/String;
      #144 ()Ljava/lang/String;
      #145 5
      #146 1
      #144 ()Ljava/lang/String;
  2: #153 REF_invokeStatic java/lang/invoke/LambdaMetafactory.altMetafactory:(Ljava/lang/invoke/MethodHandles$Lookup;Ljava/lang/String;Ljava/lang/invoke/MethodType;[Ljava/lang/Object;)Ljava/lang/invoke/CallSite;
    Method arguments:
      #139 ()Ljava/lang/Object;
      #212 REF_invokeStatic org/scalatest/funspec/AnyFunSpecLike.$anonfun$ignoreImpl$1:()Ljava/lang/String;
      #144 ()Ljava/lang/String;
      #145 5
      #146 1
      #144 ()Ljava/lang/String;
  3: #153 REF_invokeStatic java/lang/invoke/LambdaMetafactory.altMetafactory:(Ljava/lang/invoke/MethodHandles$Lookup;Ljava/lang/String;Ljava/lang/invoke/MethodType;[Ljava/lang/Object;)Ljava/lang/invoke/CallSite;
    Method arguments:
      #139 ()Ljava/lang/Object;
      #232 REF_invokeStatic org/scalatest/funspec/AnyFunSpecLike.$anonfun$describeImpl$1:()Ljava/lang/String;
      #144 ()Ljava/lang/String;
      #145 5
      #146 1
      #144 ()Ljava/lang/String;
  4: #153 REF_invokeStatic java/lang/invoke/LambdaMetafactory.altMetafactory:(Ljava/lang/invoke/MethodHandles$Lookup;Ljava/lang/String;Ljava/lang/invoke/MethodType;[Ljava/lang/Object;)Ljava/lang/invoke/CallSite;
    Method arguments:
      #139 ()Ljava/lang/Object;
      #260 REF_invokeStatic org/scalatest/funspec/AnyFunSpecLike.$anonfun$describeImpl$2:(Lorg/scalactic/source/Position;)Lorg/scalactic/source/Position;
      #262 ()Lorg/scalactic/source/Position;
      #145 5
      #146 1
      #262 ()Lorg/scalactic/source/Position;
  5: #153 REF_invokeStatic java/lang/invoke/LambdaMetafactory.altMetafactory:(Ljava/lang/invoke/MethodHandles$Lookup;Ljava/lang/String;Ljava/lang/invoke/MethodType;[Ljava/lang/Object;)Ljava/lang/invoke/CallSite;
    Method arguments:
      #139 ()Ljava/lang/Object;
      #283 REF_invokeStatic org/scalatest/funspec/AnyFunSpecLike.$anonfun$describeImpl$3:(Lorg/scalactic/source/Position;)Lorg/scalactic/source/Position;
      #262 ()Lorg/scalactic/source/Position;
      #145 5
      #146 1
      #262 ()Lorg/scalactic/source/Position;
  6: #153 REF_invokeStatic java/lang/invoke/LambdaMetafactory.altMetafactory:(Ljava/lang/invoke/MethodHandles$Lookup;Ljava/lang/String;Ljava/lang/invoke/MethodType;[Ljava/lang/Object;)Ljava/lang/invoke/CallSite;
    Method arguments:
      #139 ()Ljava/lang/Object;
      #324 REF_invokeStatic org/scalatest/funspec/AnyFunSpecLike.$anonfun$describeImpl$4:(Lorg/scalactic/source/Position;)Lorg/scalactic/source/Position;
      #262 ()Lorg/scalactic/source/Position;
      #145 5
      #146 1
      #262 ()Lorg/scalactic/source/Position;
  7: #153 REF_invokeStatic java/lang/invoke/LambdaMetafactory.altMetafactory:(Ljava/lang/invoke/MethodHandles$Lookup;Ljava/lang/String;Ljava/lang/invoke/MethodType;[Ljava/lang/Object;)Ljava/lang/invoke/CallSite;
    Method arguments:
      #377 (Ljava/lang/Object;)Ljava/lang/Object;
      #382 REF_invokeStatic org/scalatest/funspec/AnyFunSpecLike.$anonfun$runTest$1:(Lorg/scalatest/funspec/AnyFunSpecLike;Lorg/scalatest/Args;Ljava/lang/String;Lorg/scalatest/SuperEngine$TestLeaf;)Lorg/scalatest/Outcome;
      #384 (Lorg/scalatest/SuperEngine$TestLeaf;)Lorg/scalatest/Outcome;
      #145 5
      #146 1
      #384 (Lorg/scalatest/SuperEngine$TestLeaf;)Lorg/scalatest/Outcome;
  8: #153 REF_invokeStatic java/lang/invoke/LambdaMetafactory.altMetafactory:(Ljava/lang/invoke/MethodHandles$Lookup;Ljava/lang/String;Ljava/lang/invoke/MethodType;[Ljava/lang/Object;)Ljava/lang/invoke/CallSite;
    Method arguments:
      #414 (Ljava/lang/Object;Ljava/lang/Object;)Ljava/lang/Object;
      #418 REF_invokeStatic org/scalatest/funspec/AnyFunSpecLike.$anonfun$runTests$1:(Lorg/scalatest/funspec/AnyFunSpecLike;Ljava/lang/String;Lorg/scalatest/Args;)Lorg/scalatest/Status;
      #419 (Ljava/lang/String;Lorg/scalatest/Args;)Lorg/scalatest/Status;
      #145 5
      #146 1
      #419 (Ljava/lang/String;Lorg/scalatest/Args;)Lorg/scalatest/Status;
  9: #153 REF_invokeStatic java/lang/invoke/LambdaMetafactory.altMetafactory:(Ljava/lang/invoke/MethodHandles$Lookup;Ljava/lang/String;Ljava/lang/invoke/MethodType;[Ljava/lang/Object;)Ljava/lang/invoke/CallSite;
    Method arguments:
      #414 (Ljava/lang/Object;Ljava/lang/Object;)Ljava/lang/Object;
      #434 REF_invokeStatic org/scalatest/funspec/AnyFunSpecLike.$anonfun$run$1:(Lorg/scalatest/funspec/AnyFunSpecLike;Lscala/Option;Lorg/scalatest/Args;)Lorg/scalatest/Status;
      #435 (Lscala/Option;Lorg/scalatest/Args;)Lorg/scalatest/Status;
      #145 5
      #146 1
      #435 (Lscala/Option;Lorg/scalatest/Args;)Lorg/scalatest/Status;
  10: #153 REF_invokeStatic java/lang/invoke/LambdaMetafactory.altMetafactory:(Ljava/lang/invoke/MethodHandles$Lookup;Ljava/lang/String;Ljava/lang/invoke/MethodType;[Ljava/lang/Object;)Ljava/lang/invoke/CallSite;
    Method arguments:
      #139 ()Ljava/lang/Object;
      #517 REF_invokeStatic org/scalatest/funspec/AnyFunSpecLike.$anonfun$engine$1:()Ljava/lang/String;
      #144 ()Ljava/lang/String;
      #145 5
      #146 1
      #144 ()Ljava/lang/String;
  11: #555 REF_invokeStatic scala/runtime/LambdaDeserialize.bootstrap:(Ljava/lang/invoke/MethodHandles$Lookup;Ljava/lang/String;Ljava/lang/invoke/MethodType;[Ljava/lang/invoke/MethodHandle;)Ljava/lang/invoke/CallSite;
    Method arguments:
      #232 REF_invokeStatic org/scalatest/funspec/AnyFunSpecLike.$anonfun$describeImpl$1:()Ljava/lang/String;
      #260 REF_invokeStatic org/scalatest/funspec/AnyFunSpecLike.$anonfun$describeImpl$2:(Lorg/scalactic/source/Position;)Lorg/scalactic/source/Position;
      #283 REF_invokeStatic org/scalatest/funspec/AnyFunSpecLike.$anonfun$describeImpl$3:(Lorg/scalactic/source/Position;)Lorg/scalactic/source/Position;
      #324 REF_invokeStatic org/scalatest/funspec/AnyFunSpecLike.$anonfun$describeImpl$4:(Lorg/scalactic/source/Position;)Lorg/scalactic/source/Position;
      #517 REF_invokeStatic org/scalatest/funspec/AnyFunSpecLike.$anonfun$engine$1:()Ljava/lang/String;
      #212 REF_invokeStatic org/scalatest/funspec/AnyFunSpecLike.$anonfun$ignoreImpl$1:()Ljava/lang/String;
      #192 REF_invokeStatic org/scalatest/funspec/AnyFunSpecLike.$anonfun$registerIgnoredTestImpl$1:()Ljava/lang/String;
      #143 REF_invokeStatic org/scalatest/funspec/AnyFunSpecLike.$anonfun$registerTestImpl$1:()Ljava/lang/String;
      #434 REF_invokeStatic org/scalatest/funspec/AnyFunSpecLike.$anonfun$run$1:(Lorg/scalatest/funspec/AnyFunSpecLike;Lscala/Option;Lorg/scalatest/Args;)Lorg/scalatest/Status;
      #382 REF_invokeStatic org/scalatest/funspec/AnyFunSpecLike.$anonfun$runTest$1:(Lorg/scalatest/funspec/AnyFunSpecLike;Lorg/scalatest/Args;Ljava/lang/String;Lorg/scalatest/SuperEngine$TestLeaf;)Lorg/scalatest/Outcome;
      #418 REF_invokeStatic org/scalatest/funspec/AnyFunSpecLike.$anonfun$runTests$1:(Lorg/scalatest/funspec/AnyFunSpecLike;Ljava/lang/String;Lorg/scalatest/Args;)Lorg/scalatest/Status;
  ScalaInlineInfo: length = 0x130 (unknown attribute)
   01 00 00 3C 00 E5 00 43 01 01 00 01 01 01 01 18
   01 01 01 01 41 01 01 01 01 D6 00 43 01 00 D1 00
   43 01 00 BD 00 43 01 00 8C 00 43 01 01 AF 01 97
   01 01 7A 01 7B 01 01 9F 01 72 01 02 01 02 02 01
   00 6A 00 6B 00 00 68 00 69 01 01 B9 01 BA 00 00
   EA 00 DF 00 01 55 01 56 01 00 DE 00 DF 01 00 D6
   00 7F 00 00 D9 00 B7 01 00 D0 00 7F 01 00 47 00
   48 00 00 44 00 45 01 01 E9 01 EA 01 00 CC 00 CD
   00 00 75 00 76 00 00 73 00 74 01 00 5F 00 60 00
   00 5D 00 5E 01 00 40 00 41 00 00 3C 00 3D 01 00
   39 00 3A 00 00 35 00 36 00 00 30 00 31 00 00 33
   00 34 00 00 3B 00 34 00 00 37 00 38 00 00 C2 00
   7F 01 00 C7 00 B7 01 00 BC 00 7F 01 00 A0 00 7F
   01 00 B6 00 B7 01 00 7E 00 7F 01 01 AC 00 3D 00
   01 AB 01 97 01 01 73 01 74 00 01 71 01 72 01 01
   98 00 3D 00 01 96 01 97 01 00 42 00 43 00 01 BB
   00 43 00 01 8A 01 8B 00 01 88 01 89 01 01 BF 01
   C0 00 01 BC 01 BD 01 01 CA 01 CB 00 01 C8 01 C9
   01 01 5D 01 5E 00 01 5B 01 5C 01 00 CE 00 CF 00

  ScalaSig: length = 0x3 (unknown attribute)
   05 02 00
