Classfile /Users/mw/Projects/slang-braindump/.jar/jar8/assemble/slang-braindump/assemble/content/org/scalatest/funspec/AnyFunSpecLike$ItWord.class
  Last modified May 29, 2022; size 3551 bytes
  SHA-256 checksum 81b76b92b3c93fb81d816e1546302f4a2d1edd660cc3421efad2fb4c9585d006
  Compiled from "AnyFunSpecLike.scala"
public class org.scalatest.funspec.AnyFunSpecLike$ItWord
  minor version: 0
  major version: 52
  flags: (0x0021) ACC_PUBLIC, ACC_SUPER
  this_class: #2                          // org/scalatest/funspec/AnyFunSpecLike$ItWord
  super_class: #4                         // java/lang/Object
  interfaces: 0, fields: 1, methods: 8, attributes: 5
Constant pool:
    #1 = Utf8               org/scalatest/funspec/AnyFunSpecLike$ItWord
    #2 = Class              #1            // org/scalatest/funspec/AnyFunSpecLike$ItWord
    #3 = Utf8               java/lang/Object
    #4 = Class              #3            // java/lang/Object
    #5 = Utf8               AnyFunSpecLike.scala
    #6 = Utf8               java/lang/invoke/MethodHandles$Lookup
    #7 = Class              #6            // java/lang/invoke/MethodHandles$Lookup
    #8 = Utf8               java/lang/invoke/MethodHandles
    #9 = Class              #8            // java/lang/invoke/MethodHandles
   #10 = Utf8               Lookup
   #11 = Utf8               org/scalatest/funspec/AnyFunSpecLike
   #12 = Class              #11           // org/scalatest/funspec/AnyFunSpecLike
   #13 = Utf8               ItWord
   #14 = Utf8               $outer
   #15 = Utf8               Lorg/scalatest/funspec/AnyFunSpecLike;
   #16 = Utf8               applyImpl
   #17 = Utf8               (Ljava/lang/String;Lscala/collection/immutable/Seq;Lscala/Function0;Lorg/scalactic/source/Position;)V
   #18 = Utf8               (Ljava/lang/String;Lscala/collection/immutable/Seq<Lorg/scalatest/Tag;>;Lscala/Function0<Ljava/lang/Object;>;Lorg/scalactic/source/Position;)V
   #19 = Utf8               specText
   #20 = Utf8               testTags
   #21 = Utf8               testFun
   #22 = Utf8               pos
   #23 = Utf8               org$scalatest$funspec$AnyFunSpecLike$ItWord$$$outer
   #24 = Utf8               ()Lorg/scalatest/funspec/AnyFunSpecLike;
   #25 = NameAndType        #23:#24       // org$scalatest$funspec$AnyFunSpecLike$ItWord$$$outer:()Lorg/scalatest/funspec/AnyFunSpecLike;
   #26 = Methodref          #2.#25        // org/scalatest/funspec/AnyFunSpecLike$ItWord.org$scalatest$funspec$AnyFunSpecLike$ItWord$$$outer:()Lorg/scalatest/funspec/AnyFunSpecLike;
   #27 = Utf8               org$scalatest$funspec$AnyFunSpecLike$$engine
   #28 = Utf8               ()Lorg/scalatest/Engine;
   #29 = NameAndType        #27:#28       // org$scalatest$funspec$AnyFunSpecLike$$engine:()Lorg/scalatest/Engine;
   #30 = InterfaceMethodref #12.#29       // org/scalatest/funspec/AnyFunSpecLike.org$scalatest$funspec$AnyFunSpecLike$$engine:()Lorg/scalatest/Engine;
   #31 = Utf8               org/scalatest/Transformer
   #32 = Class              #31           // org/scalatest/Transformer
   #33 = Utf8               <init>
   #34 = Utf8               (Lscala/Function0;)V
   #35 = NameAndType        #33:#34       // "<init>":(Lscala/Function0;)V
   #36 = Methodref          #32.#35       // org/scalatest/Transformer."<init>":(Lscala/Function0;)V
   #37 = Utf8               ()Ljava/lang/Object;
   #38 = MethodType         #37           //  ()Ljava/lang/Object;
   #39 = Utf8               $anonfun$applyImpl$1
   #40 = Utf8               ()Ljava/lang/String;
   #41 = NameAndType        #39:#40       // $anonfun$applyImpl$1:()Ljava/lang/String;
   #42 = Methodref          #2.#41        // org/scalatest/funspec/AnyFunSpecLike$ItWord.$anonfun$applyImpl$1:()Ljava/lang/String;
   #43 = MethodHandle       6:#42         // REF_invokeStatic org/scalatest/funspec/AnyFunSpecLike$ItWord.$anonfun$applyImpl$1:()Ljava/lang/String;
   #44 = MethodType         #40           //  ()Ljava/lang/String;
   #45 = Integer            5
   #46 = Integer            1
   #47 = Utf8               java/lang/invoke/LambdaMetafactory
   #48 = Class              #47           // java/lang/invoke/LambdaMetafactory
   #49 = Utf8               altMetafactory
   #50 = Utf8               (Ljava/lang/invoke/MethodHandles$Lookup;Ljava/lang/String;Ljava/lang/invoke/MethodType;[Ljava/lang/Object;)Ljava/lang/invoke/CallSite;
   #51 = NameAndType        #49:#50       // altMetafactory:(Ljava/lang/invoke/MethodHandles$Lookup;Ljava/lang/String;Ljava/lang/invoke/MethodType;[Ljava/lang/Object;)Ljava/lang/invoke/CallSite;
   #52 = Methodref          #48.#51       // java/lang/invoke/LambdaMetafactory.altMetafactory:(Ljava/lang/invoke/MethodHandles$Lookup;Ljava/lang/String;Ljava/lang/invoke/MethodType;[Ljava/lang/Object;)Ljava/lang/invoke/CallSite;
   #53 = MethodHandle       6:#52         // REF_invokeStatic java/lang/invoke/LambdaMetafactory.altMetafactory:(Ljava/lang/invoke/MethodHandles$Lookup;Ljava/lang/String;Ljava/lang/invoke/MethodType;[Ljava/lang/Object;)Ljava/lang/invoke/CallSite;
   #54 = Utf8               apply
   #55 = Utf8               ()Lscala/Function0;
   #56 = NameAndType        #54:#55       // apply:()Lscala/Function0;
   #57 = InvokeDynamic      #0:#56        // #0:apply:()Lscala/Function0;
   #58 = Utf8               sourceFileName
   #59 = NameAndType        #58:#40       // sourceFileName:()Ljava/lang/String;
   #60 = InterfaceMethodref #12.#59       // org/scalatest/funspec/AnyFunSpecLike.sourceFileName:()Ljava/lang/String;
   #61 = String             #54           // apply
   #62 = Utf8               scala/None$
   #63 = Class              #62           // scala/None$
   #64 = Utf8               MODULE$
   #65 = Utf8               Lscala/None$;
   #66 = NameAndType        #64:#65       // MODULE$:Lscala/None$;
   #67 = Fieldref           #63.#66       // scala/None$.MODULE$:Lscala/None$;
   #68 = Utf8               scala/Some
   #69 = Class              #68           // scala/Some
   #70 = Utf8               (Ljava/lang/Object;)V
   #71 = NameAndType        #33:#70       // "<init>":(Ljava/lang/Object;)V
   #72 = Methodref          #69.#71       // scala/Some."<init>":(Ljava/lang/Object;)V
   #73 = Utf8               org/scalatest/Engine
   #74 = Class              #73           // org/scalatest/Engine
   #75 = Utf8               registerTest
   #76 = Utf8               (Ljava/lang/String;Ljava/lang/Object;Lscala/Function0;Ljava/lang/String;Ljava/lang/String;IILscala/Option;Lscala/Option;Lscala/Option;Lscala/Option;Lscala/collection/immutable/Seq;)Ljava/lang/String;
   #77 = NameAndType        #75:#76       // registerTest:(Ljava/lang/String;Ljava/lang/Object;Lscala/Function0;Ljava/lang/String;Ljava/lang/String;IILscala/Option;Lscala/Option;Lscala/Option;Lscala/Option;Lscala/collection/immutable/Seq;)Ljava/lang/String;
   #78 = Methodref          #74.#77       // org/scalatest/Engine.registerTest:(Ljava/lang/String;Ljava/lang/Object;Lscala/Function0;Ljava/lang/String;Ljava/lang/String;IILscala/Option;Lscala/Option;Lscala/Option;Lscala/Option;Lscala/collection/immutable/Seq;)Ljava/lang/String;
   #79 = Utf8               stackDepth
   #80 = Utf8               I
   #81 = Utf8               stackDepthAdjustment
   #82 = Utf8               this
   #83 = Utf8               Lorg/scalatest/funspec/AnyFunSpecLike$ItWord;
   #84 = Utf8               Ljava/lang/String;
   #85 = Utf8               Lscala/collection/immutable/Seq;
   #86 = Utf8               Lscala/Function0;
   #87 = Utf8               Lorg/scalactic/source/Position;
   #88 = NameAndType        #16:#17       // applyImpl:(Ljava/lang/String;Lscala/collection/immutable/Seq;Lscala/Function0;Lorg/scalactic/source/Position;)V
   #89 = Methodref          #2.#88        // org/scalatest/funspec/AnyFunSpecLike$ItWord.applyImpl:(Ljava/lang/String;Lscala/collection/immutable/Seq;Lscala/Function0;Lorg/scalactic/source/Position;)V
   #90 = Utf8               should
   #91 = Utf8               (Lorg/scalatest/verbs/BehaveWord;)Lorg/scalatest/verbs/BehaveWord;
   #92 = Utf8               behaveWord
   #93 = Utf8               Lorg/scalatest/verbs/BehaveWord;
   #94 = Utf8               must
   #95 = NameAndType        #14:#15       // $outer:Lorg/scalatest/funspec/AnyFunSpecLike;
   #96 = Fieldref           #2.#95        // org/scalatest/funspec/AnyFunSpecLike$ItWord.$outer:Lorg/scalatest/funspec/AnyFunSpecLike;
   #97 = Utf8               org/scalatest/Resources$
   #98 = Class              #97           // org/scalatest/Resources$
   #99 = Utf8               Lorg/scalatest/Resources$;
  #100 = NameAndType        #64:#99       // MODULE$:Lorg/scalatest/Resources$;
  #101 = Fieldref           #98.#100      // org/scalatest/Resources$.MODULE$:Lorg/scalatest/Resources$;
  #102 = Utf8               itCannotAppearInsideAnotherItOrThey
  #103 = NameAndType        #102:#40      // itCannotAppearInsideAnotherItOrThey:()Ljava/lang/String;
  #104 = Methodref          #98.#103      // org/scalatest/Resources$.itCannotAppearInsideAnotherItOrThey:()Ljava/lang/String;
  #105 = Utf8               (Lorg/scalatest/funspec/AnyFunSpecLike;)V
  #106 = Utf8               ()V
  #107 = NameAndType        #33:#106      // "<init>":()V
  #108 = Methodref          #4.#107       // java/lang/Object."<init>":()V
  #109 = Utf8               $deserializeLambda$
  #110 = Utf8               (Ljava/lang/invoke/SerializedLambda;)Ljava/lang/Object;
  #111 = Utf8               scala/runtime/LambdaDeserialize
  #112 = Class              #111          // scala/runtime/LambdaDeserialize
  #113 = Utf8               bootstrap
  #114 = Utf8               (Ljava/lang/invoke/MethodHandles$Lookup;Ljava/lang/String;Ljava/lang/invoke/MethodType;[Ljava/lang/invoke/MethodHandle;)Ljava/lang/invoke/CallSite;
  #115 = NameAndType        #113:#114     // bootstrap:(Ljava/lang/invoke/MethodHandles$Lookup;Ljava/lang/String;Ljava/lang/invoke/MethodType;[Ljava/lang/invoke/MethodHandle;)Ljava/lang/invoke/CallSite;
  #116 = Methodref          #112.#115     // scala/runtime/LambdaDeserialize.bootstrap:(Ljava/lang/invoke/MethodHandles$Lookup;Ljava/lang/String;Ljava/lang/invoke/MethodType;[Ljava/lang/invoke/MethodHandle;)Ljava/lang/invoke/CallSite;
  #117 = MethodHandle       6:#116        // REF_invokeStatic scala/runtime/LambdaDeserialize.bootstrap:(Ljava/lang/invoke/MethodHandles$Lookup;Ljava/lang/String;Ljava/lang/invoke/MethodType;[Ljava/lang/invoke/MethodHandle;)Ljava/lang/invoke/CallSite;
  #118 = Utf8               lambdaDeserialize
  #119 = NameAndType        #118:#110     // lambdaDeserialize:(Ljava/lang/invoke/SerializedLambda;)Ljava/lang/Object;
  #120 = InvokeDynamic      #1:#119       // #1:lambdaDeserialize:(Ljava/lang/invoke/SerializedLambda;)Ljava/lang/Object;
  #121 = Utf8               Code
  #122 = Utf8               LineNumberTable
  #123 = Utf8               LocalVariableTable
  #124 = Utf8               Signature
  #125 = Utf8               MethodParameters
  #126 = Utf8               StackMapTable
  #127 = Utf8               InnerClasses
  #128 = Utf8               SourceFile
  #129 = Utf8               BootstrapMethods
  #130 = Utf8               ScalaInlineInfo
  #131 = Utf8               Scala
{
  public final org.scalatest.funspec.AnyFunSpecLike $outer;
    descriptor: Lorg/scalatest/funspec/AnyFunSpecLike;
    flags: (0x1011) ACC_PUBLIC, ACC_FINAL, ACC_SYNTHETIC

  private final void applyImpl(java.lang.String, scala.collection.immutable.Seq<org.scalatest.Tag>, scala.Function0<java.lang.Object>, org.scalactic.source.Position);
    descriptor: (Ljava/lang/String;Lscala/collection/immutable/Seq;Lscala/Function0;Lorg/scalactic/source/Position;)V
    flags: (0x0012) ACC_PRIVATE, ACC_FINAL
    Code:
      stack=13, locals=7, args_size=5
         0: iconst_3
         1: istore        5
         3: bipush        -2
         5: istore        6
         7: aload_0
         8: invokevirtual #26                 // Method org$scalatest$funspec$AnyFunSpecLike$ItWord$$$outer:()Lorg/scalatest/funspec/AnyFunSpecLike;
        11: invokeinterface #30,  1           // InterfaceMethod org/scalatest/funspec/AnyFunSpecLike.org$scalatest$funspec$AnyFunSpecLike$$engine:()Lorg/scalatest/Engine;
        16: aload_1
        17: new           #32                 // class org/scalatest/Transformer
        20: dup
        21: aload_3
        22: invokespecial #36                 // Method org/scalatest/Transformer."<init>":(Lscala/Function0;)V
        25: invokedynamic #57,  0             // InvokeDynamic #0:apply:()Lscala/Function0;
        30: aload_0
        31: invokevirtual #26                 // Method org$scalatest$funspec$AnyFunSpecLike$ItWord$$$outer:()Lorg/scalatest/funspec/AnyFunSpecLike;
        34: invokeinterface #60,  1           // InterfaceMethod org/scalatest/funspec/AnyFunSpecLike.sourceFileName:()Ljava/lang/String;
        39: ldc           #61                 // String apply
        41: iload         5
        43: iload         6
        45: getstatic     #67                 // Field scala/None$.MODULE$:Lscala/None$;
        48: getstatic     #67                 // Field scala/None$.MODULE$:Lscala/None$;
        51: new           #69                 // class scala/Some
        54: dup
        55: aload         4
        57: invokespecial #72                 // Method scala/Some."<init>":(Ljava/lang/Object;)V
        60: getstatic     #67                 // Field scala/None$.MODULE$:Lscala/None$;
        63: aload_2
        64: invokevirtual #78                 // Method org/scalatest/Engine.registerTest:(Ljava/lang/String;Ljava/lang/Object;Lscala/Function0;Ljava/lang/String;Ljava/lang/String;IILscala/Option;Lscala/Option;Lscala/Option;Lscala/Option;Lscala/collection/immutable/Seq;)Ljava/lang/String;
        67: pop
        68: return
      LineNumberTable:
        line 163: 0
        line 164: 3
        line 168: 7
      LocalVariableTable:
        Start  Length  Slot  Name   Signature
            3      65     5 stackDepth   I
            7      61     6 stackDepthAdjustment   I
            0      69     0  this   Lorg/scalatest/funspec/AnyFunSpecLike$ItWord;
            0      69     1 specText   Ljava/lang/String;
            0      69     2 testTags   Lscala/collection/immutable/Seq;
            0      69     3 testFun   Lscala/Function0;
            0      69     4   pos   Lorg/scalactic/source/Position;
    Signature: #18                          // (Ljava/lang/String;Lscala/collection/immutable/Seq<Lorg/scalatest/Tag;>;Lscala/Function0<Ljava/lang/Object;>;Lorg/scalactic/source/Position;)V
    MethodParameters:
      Name                           Flags
      specText                       final
      testTags                       final
      testFun                        final
      pos                            final

  public void apply(java.lang.String, scala.collection.immutable.Seq<org.scalatest.Tag>, scala.Function0<java.lang.Object>, org.scalactic.source.Position);
    descriptor: (Ljava/lang/String;Lscala/collection/immutable/Seq;Lscala/Function0;Lorg/scalactic/source/Position;)V
    flags: (0x0001) ACC_PUBLIC
    Code:
      stack=5, locals=7, args_size=5
         0: iconst_3
         1: istore        5
         3: bipush        -2
         5: istore        6
         7: aload_0
         8: aload_1
         9: aload_2
        10: aload_3
        11: aload         4
        13: invokespecial #89                 // Method applyImpl:(Ljava/lang/String;Lscala/collection/immutable/Seq;Lscala/Function0;Lorg/scalactic/source/Position;)V
        16: return
      LineNumberTable:
        line 192: 0
        line 193: 3
        line 197: 7
      LocalVariableTable:
        Start  Length  Slot  Name   Signature
            3      13     5 stackDepth   I
            7       9     6 stackDepthAdjustment   I
            0      17     0  this   Lorg/scalatest/funspec/AnyFunSpecLike$ItWord;
            0      17     1 specText   Ljava/lang/String;
            0      17     2 testTags   Lscala/collection/immutable/Seq;
            0      17     3 testFun   Lscala/Function0;
            0      17     4   pos   Lorg/scalactic/source/Position;
    Signature: #18                          // (Ljava/lang/String;Lscala/collection/immutable/Seq<Lorg/scalatest/Tag;>;Lscala/Function0<Ljava/lang/Object;>;Lorg/scalactic/source/Position;)V
    MethodParameters:
      Name                           Flags
      specText                       final
      testTags                       final
      testFun                        final
      pos                            final

  public org.scalatest.verbs.BehaveWord should(org.scalatest.verbs.BehaveWord);
    descriptor: (Lorg/scalatest/verbs/BehaveWord;)Lorg/scalatest/verbs/BehaveWord;
    flags: (0x0001) ACC_PUBLIC
    Code:
      stack=1, locals=2, args_size=2
         0: aload_1
         1: areturn
      LineNumberTable:
        line 221: 0
      LocalVariableTable:
        Start  Length  Slot  Name   Signature
            0       2     0  this   Lorg/scalatest/funspec/AnyFunSpecLike$ItWord;
            0       2     1 behaveWord   Lorg/scalatest/verbs/BehaveWord;
    MethodParameters:
      Name                           Flags
      behaveWord                     final

  public org.scalatest.verbs.BehaveWord must(org.scalatest.verbs.BehaveWord);
    descriptor: (Lorg/scalatest/verbs/BehaveWord;)Lorg/scalatest/verbs/BehaveWord;
    flags: (0x0001) ACC_PUBLIC
    Code:
      stack=1, locals=2, args_size=2
         0: aload_1
         1: areturn
      LineNumberTable:
        line 240: 0
      LocalVariableTable:
        Start  Length  Slot  Name   Signature
            0       2     0  this   Lorg/scalatest/funspec/AnyFunSpecLike$ItWord;
            0       2     1 behaveWord   Lorg/scalatest/verbs/BehaveWord;
    MethodParameters:
      Name                           Flags
      behaveWord                     final

  public org.scalatest.funspec.AnyFunSpecLike org$scalatest$funspec$AnyFunSpecLike$ItWord$$$outer();
    descriptor: ()Lorg/scalatest/funspec/AnyFunSpecLike;
    flags: (0x1001) ACC_PUBLIC, ACC_SYNTHETIC
    Code:
      stack=1, locals=1, args_size=1
         0: aload_0
         1: getfield      #96                 // Field $outer:Lorg/scalatest/funspec/AnyFunSpecLike;
         4: areturn
      LineNumberTable:
        line 159: 0
      LocalVariableTable:
        Start  Length  Slot  Name   Signature
            0       5     0  this   Lorg/scalatest/funspec/AnyFunSpecLike$ItWord;

  public static final java.lang.String $anonfun$applyImpl$1();
    descriptor: ()Ljava/lang/String;
    flags: (0x1019) ACC_PUBLIC, ACC_STATIC, ACC_FINAL, ACC_SYNTHETIC
    Code:
      stack=1, locals=0, args_size=0
         0: getstatic     #101                // Field org/scalatest/Resources$.MODULE$:Lorg/scalatest/Resources$;
         3: invokevirtual #104                // Method org/scalatest/Resources$.itCannotAppearInsideAnotherItOrThey:()Ljava/lang/String;
         6: areturn
      LineNumberTable:
        line 168: 0

  public org.scalatest.funspec.AnyFunSpecLike$ItWord(org.scalatest.funspec.AnyFunSpecLike);
    descriptor: (Lorg/scalatest/funspec/AnyFunSpecLike;)V
    flags: (0x0001) ACC_PUBLIC
    Code:
      stack=2, locals=2, args_size=2
         0: aload_1
         1: ifnonnull     6
         4: aconst_null
         5: athrow
         6: aload_0
         7: aload_1
         8: putfield      #96                 // Field $outer:Lorg/scalatest/funspec/AnyFunSpecLike;
        11: aload_0
        12: invokespecial #108                // Method java/lang/Object."<init>":()V
        15: return
      StackMapTable: number_of_entries = 1
        frame_type = 6 /* same */
      LineNumberTable:
        line 159: 0
        line 264: 11
        line 159: 15
      LocalVariableTable:
        Start  Length  Slot  Name   Signature
            0      16     0  this   Lorg/scalatest/funspec/AnyFunSpecLike$ItWord;
            0      16     1 $outer   Lorg/scalatest/funspec/AnyFunSpecLike;
    MethodParameters:
      Name                           Flags
      $outer                         final synthetic

  private static java.lang.Object $deserializeLambda$(java.lang.invoke.SerializedLambda);
    descriptor: (Ljava/lang/invoke/SerializedLambda;)Ljava/lang/Object;
    flags: (0x100a) ACC_PRIVATE, ACC_STATIC, ACC_SYNTHETIC
    Code:
      stack=1, locals=1, args_size=1
         0: aload_0
         1: invokedynamic #120,  0            // InvokeDynamic #1:lambdaDeserialize:(Ljava/lang/invoke/SerializedLambda;)Ljava/lang/Object;
         6: areturn
}
InnerClasses:
  public static final #10= #7 of #9;      // Lookup=class java/lang/invoke/MethodHandles$Lookup of class java/lang/invoke/MethodHandles
  public #13= #2 of #12;                  // ItWord=class org/scalatest/funspec/AnyFunSpecLike$ItWord of class org/scalatest/funspec/AnyFunSpecLike
SourceFile: "AnyFunSpecLike.scala"
BootstrapMethods:
  0: #53 REF_invokeStatic java/lang/invoke/LambdaMetafactory.altMetafactory:(Ljava/lang/invoke/MethodHandles$Lookup;Ljava/lang/String;Ljava/lang/invoke/MethodType;[Ljava/lang/Object;)Ljava/lang/invoke/CallSite;
    Method arguments:
      #38 ()Ljava/lang/Object;
      #43 REF_invokeStatic org/scalatest/funspec/AnyFunSpecLike$ItWord.$anonfun$applyImpl$1:()Ljava/lang/String;
      #44 ()Ljava/lang/String;
      #45 5
      #46 1
      #44 ()Ljava/lang/String;
  1: #117 REF_invokeStatic scala/runtime/LambdaDeserialize.bootstrap:(Ljava/lang/invoke/MethodHandles$Lookup;Ljava/lang/String;Ljava/lang/invoke/MethodType;[Ljava/lang/invoke/MethodHandle;)Ljava/lang/invoke/CallSite;
    Method arguments:
      #43 REF_invokeStatic org/scalatest/funspec/AnyFunSpecLike$ItWord.$anonfun$applyImpl$1:()Ljava/lang/String;
  ScalaInlineInfo: length = 0x27 (unknown attribute)
   01 00 00 07 00 27 00 28 01 00 21 00 69 00 00 36
   00 11 00 00 10 00 11 01 00 5E 00 5B 00 00 17 00
   18 00 00 5A 00 5B 00
  Scala: length = 0x0 (unknown attribute)

