Classfile /Users/mw/Projects/slang-braindump/.jar/jar8/assemble/slang-braindump/assemble/content/scala/collection/compat/package.class
  Last modified May 29, 2022; size 1207 bytes
  SHA-256 checksum 27d89b3b3f0760fbf4818009c1de18cbe8abfab99f85adcf0c280fbaa82c22c2
  Compiled from "package.scala"
public final class scala.collection.compat.package
  minor version: 0
  major version: 52
  flags: (0x0031) ACC_PUBLIC, ACC_FINAL, ACC_SUPER
  this_class: #2                          // scala/collection/compat/package
  super_class: #4                         // java/lang/Object
  interfaces: 0, fields: 0, methods: 3, attributes: 3
Constant pool:
   #1 = Utf8               scala/collection/compat/package
   #2 = Class              #1             // scala/collection/compat/package
   #3 = Utf8               java/lang/Object
   #4 = Class              #3             // java/lang/Object
   #5 = Utf8               package.scala
   #6 = Utf8               Lscala/reflect/ScalaSignature;
   #7 = Utf8               bytes
   #8 = Utf8               \u0006\u0005e;Q\u0001D\u0007\t\u0002Q1QAF\u0007\t\u0002]AQ\u0001H\u0001\u0005\u0002u)AAH\u0001\u0001?!9\u0011\'\u0001b\u0001\n\u0003\u0011\u0004B\u0002\u001f\u0002A\u0003%1\'\u0002\u0003>\u0003\u0001q\u0004b\u0002%\u0002\u0005\u0004%\t!\u0013\u0005\u0007\u0019\u0006\u0001\u000b\u0011\u0002&\u0006\t5\u000b\u0001A\u0014\u0005\b)\u0006\u0011\r\u0011\"\u0001V\u0011\u0019A\u0016\u0001)A\u0005-\u00069\u0001/Y2lC\u001e,\'B\u0001\b\u0010\u0003\u0019\u0019w.\u001c9bi*\u0011\u0001#E\u0001\u000bG>dG.Z2uS>t\'\"\u0001\n\u0002\u000bM\u001c\u0017\r\\1\u0004\u0001A\u0011Q#A\u0007\u0002\u001b\t9\u0001/Y2lC\u001e,7CA\u0001\u0019!\tI\"$D\u0001\u0012\u0013\tY\u0012C\u0001\u0004B]f\u0014VMZ\u0001\u0007y%t\u0017\u000e\u001e \u0015\u0003Q\u0011qAR1di>\u0014\u00180F\u0002!K=\u0002B!\t\u0012$]5\tq\"\u0003\u0002\u001f\u001fA\u0011A%\n\u0007\u0001\t\u001913\u0001#b\u0001O\t\t\u0011)\u0005\u0002)WA\u0011\u0011$K\u0005\u0003UE\u0011qAT8uQ&tw\r\u0005\u0002\u001aY%\u0011Q&\u0005\u0002\u0004\u0003:L\bC\u0001\u00130\t\u0019\u00014\u0001\"b\u0001O\t\t1)A\u0004GC\u000e$xN]=\u0016\u0003Mr!\u0001N\u001e\u000f\u0005URdB\u0001\u001c:\u001b\u00059$B\u0001\u001d\u0014\u0003\u0019a$o\\8u}%\t!#\u0003\u0002\u0011#%\u0011\u0011gD\u0001\t\r\u0006\u001cGo\u001c:zA\tI!)^5mI\u001a\u0013x.\\\u000b\u0005\u007f\t+u\tE\u0003\"\u0001\u0006#e)\u0003\u0002>\u001fA\u0011AE\u0011\u0003\u0007\u0007\u001aA)\u0019A\u0014\u0003\t\u0019\u0013x.\u001c\t\u0003I\u0015#aA\n\u0004\t\u0006\u00049\u0003C\u0001\u0013H\t\u0019\u0001d\u0001\"b\u0001O\u0005I!)^5mI\u001a\u0013x.\\\u000b\u0002\u0015:\u0011AgS\u0005\u0003\u0011>\t!BQ;jY\u00124%o\\7!\u00051IE/\u001a:bE2,wJ\\2f+\ty%\u000bE\u0002\"!FK!!T\b\u0011\u0005\u0011\u0012FAB*\n\t\u000b\u0007qEA\u0001Y\u00031IE/\u001a:bE2,wJ\\2f+\u00051fB\u0001\u001bX\u0013\t!v\"A\u0007Ji\u0016\u0014\u0018M\u00197f\u001f:\u001cW\r\t
   #9 = Utf8               IterableOnce
  #10 = Utf8               ()Lscala/collection/IterableOnce$;
  #11 = Utf8               scala/collection/compat/package$
  #12 = Class              #11            // scala/collection/compat/package$
  #13 = Utf8               MODULE$
  #14 = Utf8               Lscala/collection/compat/package$;
  #15 = NameAndType        #13:#14        // MODULE$:Lscala/collection/compat/package$;
  #16 = Fieldref           #12.#15        // scala/collection/compat/package$.MODULE$:Lscala/collection/compat/package$;
  #17 = NameAndType        #9:#10         // IterableOnce:()Lscala/collection/IterableOnce$;
  #18 = Methodref          #12.#17        // scala/collection/compat/package$.IterableOnce:()Lscala/collection/IterableOnce$;
  #19 = Utf8               BuildFrom
  #20 = Utf8               ()Lscala/collection/BuildFrom$;
  #21 = NameAndType        #19:#20        // BuildFrom:()Lscala/collection/BuildFrom$;
  #22 = Methodref          #12.#21        // scala/collection/compat/package$.BuildFrom:()Lscala/collection/BuildFrom$;
  #23 = Utf8               Factory
  #24 = Utf8               ()Lscala/collection/Factory$;
  #25 = NameAndType        #23:#24        // Factory:()Lscala/collection/Factory$;
  #26 = Methodref          #12.#25        // scala/collection/compat/package$.Factory:()Lscala/collection/Factory$;
  #27 = Utf8               Code
  #28 = Utf8               SourceFile
  #29 = Utf8               RuntimeVisibleAnnotations
  #30 = Utf8               ScalaSig
{
  public static scala.collection.IterableOnce$ IterableOnce();
    descriptor: ()Lscala/collection/IterableOnce$;
    flags: (0x0009) ACC_PUBLIC, ACC_STATIC
    Code:
      stack=1, locals=0, args_size=0
         0: getstatic     #16                 // Field scala/collection/compat/package$.MODULE$:Lscala/collection/compat/package$;
         3: invokevirtual #18                 // Method scala/collection/compat/package$.IterableOnce:()Lscala/collection/IterableOnce$;
         6: areturn

  public static scala.collection.BuildFrom$ BuildFrom();
    descriptor: ()Lscala/collection/BuildFrom$;
    flags: (0x0009) ACC_PUBLIC, ACC_STATIC
    Code:
      stack=1, locals=0, args_size=0
         0: getstatic     #16                 // Field scala/collection/compat/package$.MODULE$:Lscala/collection/compat/package$;
         3: invokevirtual #22                 // Method scala/collection/compat/package$.BuildFrom:()Lscala/collection/BuildFrom$;
         6: areturn

  public static scala.collection.Factory$ Factory();
    descriptor: ()Lscala/collection/Factory$;
    flags: (0x0009) ACC_PUBLIC, ACC_STATIC
    Code:
      stack=1, locals=0, args_size=0
         0: getstatic     #16                 // Field scala/collection/compat/package$.MODULE$:Lscala/collection/compat/package$;
         3: invokevirtual #26                 // Method scala/collection/compat/package$.Factory:()Lscala/collection/Factory$;
         6: areturn
}
SourceFile: "package.scala"
RuntimeVisibleAnnotations:
  0: #6(#7=s#8)
    scala.reflect.ScalaSignature(
      bytes="\u0006\u0005e;Q\u0001D\u0007\t\u0002Q1QAF\u0007\t\u0002]AQ\u0001H\u0001\u0005\u0002u)AAH\u0001\u0001?!9\u0011\'\u0001b\u0001\n\u0003\u0011\u0004B\u0002\u001f\u0002A\u0003%1\'\u0002\u0003>\u0003\u0001q\u0004b\u0002%\u0002\u0005\u0004%\t!\u0013\u0005\u0007\u0019\u0006\u0001\u000b\u0011\u0002&\u0006\t5\u000b\u0001A\u0014\u0005\b)\u0006\u0011\r\u0011\"\u0001V\u0011\u0019A\u0016\u0001)A\u0005-\u00069\u0001/Y2lC\u001e,\'B\u0001\b\u0010\u0003\u0019\u0019w.\u001c9bi*\u0011\u0001#E\u0001\u000bG>dG.Z2uS>t\'\"\u0001\n\u0002\u000bM\u001c\u0017\r\\1\u0004\u0001A\u0011Q#A\u0007\u0002\u001b\t9\u0001/Y2lC\u001e,7CA\u0001\u0019!\tI\"$D\u0001\u0012\u0013\tY\u0012C\u0001\u0004B]f\u0014VMZ\u0001\u0007y%t\u0017\u000e\u001e \u0015\u0003Q\u0011qAR1di>\u0014\u00180F\u0002!K=\u0002B!\t\u0012$]5\tq\"\u0003\u0002\u001f\u001fA\u0011A%\n\u0007\u0001\t\u001913\u0001#b\u0001O\t\t\u0011)\u0005\u0002)WA\u0011\u0011$K\u0005\u0003UE\u0011qAT8uQ&tw\r\u0005\u0002\u001aY%\u0011Q&\u0005\u0002\u0004\u0003:L\bC\u0001\u00130\t\u0019\u00014\u0001\"b\u0001O\t\t1)A\u0004GC\u000e$xN]=\u0016\u0003Mr!\u0001N\u001e\u000f\u0005URdB\u0001\u001c:\u001b\u00059$B\u0001\u001d\u0014\u0003\u0019a$o\\8u}%\t!#\u0003\u0002\u0011#%\u0011\u0011gD\u0001\t\r\u0006\u001cGo\u001c:zA\tI!)^5mI\u001a\u0013x.\\\u000b\u0005\u007f\t+u\tE\u0003\"\u0001\u0006#e)\u0003\u0002>\u001fA\u0011AE\u0011\u0003\u0007\u0007\u001aA)\u0019A\u0014\u0003\t\u0019\u0013x.\u001c\t\u0003I\u0015#aA\n\u0004\t\u0006\u00049\u0003C\u0001\u0013H\t\u0019\u0001d\u0001\"b\u0001O\u0005I!)^5mI\u001a\u0013x.\\\u000b\u0002\u0015:\u0011AgS\u0005\u0003\u0011>\t!BQ;jY\u00124%o\\7!\u00051IE/\u001a:bE2,wJ\\2f+\ty%\u000bE\u0002\"!FK!!T\b\u0011\u0005\u0011\u0012FAB*\n\t\u000b\u0007qEA\u0001Y\u00031IE/\u001a:bE2,wJ\\2f+\u00051fB\u0001\u001bX\u0013\t!v\"A\u0007Ji\u0016\u0014\u0018M\u00197f\u001f:\u001cW\r\t"
    )
  ScalaSig: length = 0x3 (unknown attribute)
   05 02 00
