Classfile /Users/mw/Projects/slang-braindump/.jar/jar8/assemble/slang-braindump/assemble/content/coursier/core/Exclusions.class
  Last modified May 29, 2022; size 3277 bytes
  SHA-256 checksum 246124af78b0f43db6728c94ac92d79e25613786e02327537fa97320653717ad
  Compiled from "Exclusions.scala"
public final class coursier.core.Exclusions
  minor version: 0
  major version: 52
  flags: (0x0031) ACC_PUBLIC, ACC_FINAL, ACC_SUPER
  this_class: #2                          // coursier/core/Exclusions
  super_class: #4                         // java/lang/Object
  interfaces: 0, fields: 0, methods: 9, attributes: 3
Constant pool:
   #1 = Utf8               coursier/core/Exclusions
   #2 = Class              #1             // coursier/core/Exclusions
   #3 = Utf8               java/lang/Object
   #4 = Class              #3             // java/lang/Object
   #5 = Utf8               Exclusions.scala
   #6 = Utf8               Lscala/reflect/ScalaSignature;
   #7 = Utf8               bytes
   #8 = Utf8               \u0006\u0005\u001d<Q\u0001E\t\t\u0002Y1Q\u0001G\t\t\u0002eAQ\u0001I\u0001\u0005\u0002\u0005BQAI\u0001\u0005\u0002\rBQAQ\u0001\u0005\u0002\rCQ\u0001S\u0001\u0005\u0002%CqaS\u0001C\u0002\u0013\u0005A\n\u0003\u0004N\u0003\u0001\u0006I!\u000e\u0005\b\u001d\u0006\u0011\r\u0011\"\u0001P\u0011\u0019\u0001\u0016\u0001)A\u0005s!9\u0011+\u0001b\u0001\n\u0003\u0011\u0006B\u0002.\u0002A\u0003%1\u000bC\u0004\\\u0003\t\u0007I\u0011\u0001*\t\rq\u000b\u0001\u0015!\u0003T\u0011\u0015i\u0016\u0001\"\u0001_\u0011\u0015\u0019\u0017\u0001\"\u0001e\u0003))\u0005p\u00197vg&|gn\u001d\u0006\u0003%M\tAaY8sK*\tA#\u0001\u0005d_V\u00148/[3s\u0007\u0001\u0001\"aF\u0001\u000e\u0003E\u0011!\"\u0012=dYV\u001c\u0018n\u001c8t\'\t\t!\u0004\u0005\u0002\u001c=5\tADC\u0001\u001e\u0003\u0015\u00198-\u00197b\u0013\tyBD\u0001\u0004B]f\u0014VMZ\u0001\u0007y%t\u0017\u000e\u001e \u0015\u0003Y\t\u0011\u0002]1si&$\u0018n\u001c8\u0015\u0005\u0011\u0002\u0005CB\u000e&O)BD(\u0003\u0002\'9\t1A+\u001e9mKR\u0002\"a\u0007\u0015\n\u0005%b\"a\u0002\"p_2,\u0017M\u001c\t\u0004WI*dB\u0001\u00171!\tiC$D\u0001/\u0015\tyS#\u0001\u0004=e>|GOP\u0005\u0003cq\ta\u0001\u0015:fI\u00164\u0017BA\u001a5\u0005\r\u0019V\r\u001e\u0006\u0003cq\u0001\"a\u0006\u001c\n\u0005]\n\"\u0001D(sO\u0006t\u0017N_1uS>t\u0007cA\u00163sA\u0011qCO\u0005\u0003wE\u0011!\"T8ek2,g*Y7f!\rY#\'\u0010\t\u00057y*\u0014(\u0003\u0002@9\t1A+\u001e9mKJBQ!Q\u0002A\u0002q\n!\"\u001a=dYV\u001c\u0018n\u001c8t\u0003\u0015\t\u0007\u000f\u001d7z)\t!u\tE\u0003\u001c\u000bVJt%\u0003\u0002G9\tIa)\u001e8di&|gN\r\u0005\u0006\u0003\u0012\u0001\r\u0001P\u0001\t[&t\u0017.\\5{KR\u0011AH\u0013\u0005\u0006\u0003\u0016\u0001\r\u0001P\u0001\u0011C2dwJ]4b]&T\u0018\r^5p]N,\u0012!N\u0001\u0012C2dwJ]4b]&T\u0018\r^5p]N\u0004\u0013\u0001C1mY:\u000bW.Z:\u0016\u0003e\n\u0011\"\u00197m\u001d\u0006lWm\u001d\u0011\u0002\ti,\'o\\\u000b\u0002\'B\u0019A+W\u001f\u000e\u0003US!AV,\u0002\u0013%lW.\u001e;bE2,\'B\u0001-\u001d\u0003)\u0019w\u000e\u001c7fGRLwN\\\u0005\u0003gU\u000bQA_3s_\u0002\n1a\u001c8f\u0003\u0011yg.\u001a\u0011\u0002\t)|\u0017N\u001c\u000b\u0004y}\u000b\u0007\"\u00021\u000f\u0001\u0004a\u0014!\u0001=\t\u000b\tt\u0001\u0019\u0001\u001f\u0002\u0003e\fA!\\3fiR\u0019A(\u001a4\t\u000b\u0001|\u0001\u0019\u0001\u001f\t\u000b\t|\u0001\u0019\u0001\u001f
   #9 = Utf8               meet
  #10 = Utf8               (Lscala/collection/immutable/Set;Lscala/collection/immutable/Set;)Lscala/collection/immutable/Set;
  #11 = Utf8               (Lscala/collection/immutable/Set<Lscala/Tuple2<Lcoursier/core/Organization;Lcoursier/core/ModuleName;>;>;Lscala/collection/immutable/Set<Lscala/Tuple2<Lcoursier/core/Organization;Lcoursier/core/ModuleName;>;>;)Lscala/collection/immutable/Set<Lscala/Tuple2<Lcoursier/core/Organization;Lcoursier/core/ModuleName;>;>;
  #12 = Utf8               x
  #13 = Utf8               y
  #14 = Utf8               coursier/core/Exclusions$
  #15 = Class              #14            // coursier/core/Exclusions$
  #16 = Utf8               MODULE$
  #17 = Utf8               Lcoursier/core/Exclusions$;
  #18 = NameAndType        #16:#17        // MODULE$:Lcoursier/core/Exclusions$;
  #19 = Fieldref           #15.#18        // coursier/core/Exclusions$.MODULE$:Lcoursier/core/Exclusions$;
  #20 = NameAndType        #9:#10         // meet:(Lscala/collection/immutable/Set;Lscala/collection/immutable/Set;)Lscala/collection/immutable/Set;
  #21 = Methodref          #15.#20        // coursier/core/Exclusions$.meet:(Lscala/collection/immutable/Set;Lscala/collection/immutable/Set;)Lscala/collection/immutable/Set;
  #22 = Utf8               join
  #23 = NameAndType        #22:#10        // join:(Lscala/collection/immutable/Set;Lscala/collection/immutable/Set;)Lscala/collection/immutable/Set;
  #24 = Methodref          #15.#23        // coursier/core/Exclusions$.join:(Lscala/collection/immutable/Set;Lscala/collection/immutable/Set;)Lscala/collection/immutable/Set;
  #25 = Utf8               one
  #26 = Utf8               ()Lscala/collection/immutable/Set;
  #27 = Utf8               ()Lscala/collection/immutable/Set<Lscala/Tuple2<Lcoursier/core/Organization;Lcoursier/core/ModuleName;>;>;
  #28 = NameAndType        #25:#26        // one:()Lscala/collection/immutable/Set;
  #29 = Methodref          #15.#28        // coursier/core/Exclusions$.one:()Lscala/collection/immutable/Set;
  #30 = Utf8               zero
  #31 = NameAndType        #30:#26        // zero:()Lscala/collection/immutable/Set;
  #32 = Methodref          #15.#31        // coursier/core/Exclusions$.zero:()Lscala/collection/immutable/Set;
  #33 = Utf8               allNames
  #34 = Utf8               ()Ljava/lang/String;
  #35 = NameAndType        #33:#34        // allNames:()Ljava/lang/String;
  #36 = Methodref          #15.#35        // coursier/core/Exclusions$.allNames:()Ljava/lang/String;
  #37 = Utf8               allOrganizations
  #38 = NameAndType        #37:#34        // allOrganizations:()Ljava/lang/String;
  #39 = Methodref          #15.#38        // coursier/core/Exclusions$.allOrganizations:()Ljava/lang/String;
  #40 = Utf8               minimize
  #41 = Utf8               (Lscala/collection/immutable/Set;)Lscala/collection/immutable/Set;
  #42 = Utf8               (Lscala/collection/immutable/Set<Lscala/Tuple2<Lcoursier/core/Organization;Lcoursier/core/ModuleName;>;>;)Lscala/collection/immutable/Set<Lscala/Tuple2<Lcoursier/core/Organization;Lcoursier/core/ModuleName;>;>;
  #43 = Utf8               exclusions
  #44 = NameAndType        #40:#41        // minimize:(Lscala/collection/immutable/Set;)Lscala/collection/immutable/Set;
  #45 = Methodref          #15.#44        // coursier/core/Exclusions$.minimize:(Lscala/collection/immutable/Set;)Lscala/collection/immutable/Set;
  #46 = Utf8               apply
  #47 = Utf8               (Lscala/collection/immutable/Set;)Lscala/Function2;
  #48 = Utf8               (Lscala/collection/immutable/Set<Lscala/Tuple2<Lcoursier/core/Organization;Lcoursier/core/ModuleName;>;>;)Lscala/Function2<Lcoursier/core/Organization;Lcoursier/core/ModuleName;Ljava/lang/Object;>;
  #49 = NameAndType        #46:#47        // apply:(Lscala/collection/immutable/Set;)Lscala/Function2;
  #50 = Methodref          #15.#49        // coursier/core/Exclusions$.apply:(Lscala/collection/immutable/Set;)Lscala/Function2;
  #51 = Utf8               partition
  #52 = Utf8               (Lscala/collection/immutable/Set;)Lscala/Tuple4;
  #53 = Utf8               (Lscala/collection/immutable/Set<Lscala/Tuple2<Lcoursier/core/Organization;Lcoursier/core/ModuleName;>;>;)Lscala/Tuple4<Ljava/lang/Object;Lscala/collection/immutable/Set<Lcoursier/core/Organization;>;Lscala/collection/immutable/Set<Lcoursier/core/ModuleName;>;Lscala/collection/immutable/Set<Lscala/Tuple2<Lcoursier/core/Organization;Lcoursier/core/ModuleName;>;>;>;
  #54 = NameAndType        #51:#52        // partition:(Lscala/collection/immutable/Set;)Lscala/Tuple4;
  #55 = Methodref          #15.#54        // coursier/core/Exclusions$.partition:(Lscala/collection/immutable/Set;)Lscala/Tuple4;
  #56 = Utf8               Code
  #57 = Utf8               Signature
  #58 = Utf8               MethodParameters
  #59 = Utf8               SourceFile
  #60 = Utf8               RuntimeVisibleAnnotations
  #61 = Utf8               ScalaSig
{
  public static scala.collection.immutable.Set<scala.Tuple2<coursier.core.Organization, coursier.core.ModuleName>> meet(scala.collection.immutable.Set<scala.Tuple2<coursier.core.Organization, coursier.core.ModuleName>>, scala.collection.immutable.Set<scala.Tuple2<coursier.core.Organization, coursier.core.ModuleName>>);
    descriptor: (Lscala/collection/immutable/Set;Lscala/collection/immutable/Set;)Lscala/collection/immutable/Set;
    flags: (0x0009) ACC_PUBLIC, ACC_STATIC
    Code:
      stack=3, locals=2, args_size=2
         0: getstatic     #19                 // Field coursier/core/Exclusions$.MODULE$:Lcoursier/core/Exclusions$;
         3: aload_0
         4: aload_1
         5: invokevirtual #21                 // Method coursier/core/Exclusions$.meet:(Lscala/collection/immutable/Set;Lscala/collection/immutable/Set;)Lscala/collection/immutable/Set;
         8: areturn
    Signature: #11                          // (Lscala/collection/immutable/Set<Lscala/Tuple2<Lcoursier/core/Organization;Lcoursier/core/ModuleName;>;>;Lscala/collection/immutable/Set<Lscala/Tuple2<Lcoursier/core/Organization;Lcoursier/core/ModuleName;>;>;)Lscala/collection/immutable/Set<Lscala/Tuple2<Lcoursier/core/Organization;Lcoursier/core/ModuleName;>;>;
    MethodParameters:
      Name                           Flags
      x                              final
      y                              final

  public static scala.collection.immutable.Set<scala.Tuple2<coursier.core.Organization, coursier.core.ModuleName>> join(scala.collection.immutable.Set<scala.Tuple2<coursier.core.Organization, coursier.core.ModuleName>>, scala.collection.immutable.Set<scala.Tuple2<coursier.core.Organization, coursier.core.ModuleName>>);
    descriptor: (Lscala/collection/immutable/Set;Lscala/collection/immutable/Set;)Lscala/collection/immutable/Set;
    flags: (0x0009) ACC_PUBLIC, ACC_STATIC
    Code:
      stack=3, locals=2, args_size=2
         0: getstatic     #19                 // Field coursier/core/Exclusions$.MODULE$:Lcoursier/core/Exclusions$;
         3: aload_0
         4: aload_1
         5: invokevirtual #24                 // Method coursier/core/Exclusions$.join:(Lscala/collection/immutable/Set;Lscala/collection/immutable/Set;)Lscala/collection/immutable/Set;
         8: areturn
    Signature: #11                          // (Lscala/collection/immutable/Set<Lscala/Tuple2<Lcoursier/core/Organization;Lcoursier/core/ModuleName;>;>;Lscala/collection/immutable/Set<Lscala/Tuple2<Lcoursier/core/Organization;Lcoursier/core/ModuleName;>;>;)Lscala/collection/immutable/Set<Lscala/Tuple2<Lcoursier/core/Organization;Lcoursier/core/ModuleName;>;>;
    MethodParameters:
      Name                           Flags
      x                              final
      y                              final

  public static scala.collection.immutable.Set<scala.Tuple2<coursier.core.Organization, coursier.core.ModuleName>> one();
    descriptor: ()Lscala/collection/immutable/Set;
    flags: (0x0009) ACC_PUBLIC, ACC_STATIC
    Code:
      stack=1, locals=0, args_size=0
         0: getstatic     #19                 // Field coursier/core/Exclusions$.MODULE$:Lcoursier/core/Exclusions$;
         3: invokevirtual #29                 // Method coursier/core/Exclusions$.one:()Lscala/collection/immutable/Set;
         6: areturn
    Signature: #27                          // ()Lscala/collection/immutable/Set<Lscala/Tuple2<Lcoursier/core/Organization;Lcoursier/core/ModuleName;>;>;

  public static scala.collection.immutable.Set<scala.Tuple2<coursier.core.Organization, coursier.core.ModuleName>> zero();
    descriptor: ()Lscala/collection/immutable/Set;
    flags: (0x0009) ACC_PUBLIC, ACC_STATIC
    Code:
      stack=1, locals=0, args_size=0
         0: getstatic     #19                 // Field coursier/core/Exclusions$.MODULE$:Lcoursier/core/Exclusions$;
         3: invokevirtual #32                 // Method coursier/core/Exclusions$.zero:()Lscala/collection/immutable/Set;
         6: areturn
    Signature: #27                          // ()Lscala/collection/immutable/Set<Lscala/Tuple2<Lcoursier/core/Organization;Lcoursier/core/ModuleName;>;>;

  public static java.lang.String allNames();
    descriptor: ()Ljava/lang/String;
    flags: (0x0009) ACC_PUBLIC, ACC_STATIC
    Code:
      stack=1, locals=0, args_size=0
         0: getstatic     #19                 // Field coursier/core/Exclusions$.MODULE$:Lcoursier/core/Exclusions$;
         3: invokevirtual #36                 // Method coursier/core/Exclusions$.allNames:()Ljava/lang/String;
         6: areturn

  public static java.lang.String allOrganizations();
    descriptor: ()Ljava/lang/String;
    flags: (0x0009) ACC_PUBLIC, ACC_STATIC
    Code:
      stack=1, locals=0, args_size=0
         0: getstatic     #19                 // Field coursier/core/Exclusions$.MODULE$:Lcoursier/core/Exclusions$;
         3: invokevirtual #39                 // Method coursier/core/Exclusions$.allOrganizations:()Ljava/lang/String;
         6: areturn

  public static scala.collection.immutable.Set<scala.Tuple2<coursier.core.Organization, coursier.core.ModuleName>> minimize(scala.collection.immutable.Set<scala.Tuple2<coursier.core.Organization, coursier.core.ModuleName>>);
    descriptor: (Lscala/collection/immutable/Set;)Lscala/collection/immutable/Set;
    flags: (0x0009) ACC_PUBLIC, ACC_STATIC
    Code:
      stack=2, locals=1, args_size=1
         0: getstatic     #19                 // Field coursier/core/Exclusions$.MODULE$:Lcoursier/core/Exclusions$;
         3: aload_0
         4: invokevirtual #45                 // Method coursier/core/Exclusions$.minimize:(Lscala/collection/immutable/Set;)Lscala/collection/immutable/Set;
         7: areturn
    Signature: #42                          // (Lscala/collection/immutable/Set<Lscala/Tuple2<Lcoursier/core/Organization;Lcoursier/core/ModuleName;>;>;)Lscala/collection/immutable/Set<Lscala/Tuple2<Lcoursier/core/Organization;Lcoursier/core/ModuleName;>;>;
    MethodParameters:
      Name                           Flags
      exclusions                     final

  public static scala.Function2<coursier.core.Organization, coursier.core.ModuleName, java.lang.Object> apply(scala.collection.immutable.Set<scala.Tuple2<coursier.core.Organization, coursier.core.ModuleName>>);
    descriptor: (Lscala/collection/immutable/Set;)Lscala/Function2;
    flags: (0x0009) ACC_PUBLIC, ACC_STATIC
    Code:
      stack=2, locals=1, args_size=1
         0: getstatic     #19                 // Field coursier/core/Exclusions$.MODULE$:Lcoursier/core/Exclusions$;
         3: aload_0
         4: invokevirtual #50                 // Method coursier/core/Exclusions$.apply:(Lscala/collection/immutable/Set;)Lscala/Function2;
         7: areturn
    Signature: #48                          // (Lscala/collection/immutable/Set<Lscala/Tuple2<Lcoursier/core/Organization;Lcoursier/core/ModuleName;>;>;)Lscala/Function2<Lcoursier/core/Organization;Lcoursier/core/ModuleName;Ljava/lang/Object;>;
    MethodParameters:
      Name                           Flags
      exclusions                     final

  public static scala.Tuple4<java.lang.Object, scala.collection.immutable.Set<coursier.core.Organization>, scala.collection.immutable.Set<coursier.core.ModuleName>, scala.collection.immutable.Set<scala.Tuple2<coursier.core.Organization, coursier.core.ModuleName>>> partition(scala.collection.immutable.Set<scala.Tuple2<coursier.core.Organization, coursier.core.ModuleName>>);
    descriptor: (Lscala/collection/immutable/Set;)Lscala/Tuple4;
    flags: (0x0009) ACC_PUBLIC, ACC_STATIC
    Code:
      stack=2, locals=1, args_size=1
         0: getstatic     #19                 // Field coursier/core/Exclusions$.MODULE$:Lcoursier/core/Exclusions$;
         3: aload_0
         4: invokevirtual #55                 // Method coursier/core/Exclusions$.partition:(Lscala/collection/immutable/Set;)Lscala/Tuple4;
         7: areturn
    Signature: #53                          // (Lscala/collection/immutable/Set<Lscala/Tuple2<Lcoursier/core/Organization;Lcoursier/core/ModuleName;>;>;)Lscala/Tuple4<Ljava/lang/Object;Lscala/collection/immutable/Set<Lcoursier/core/Organization;>;Lscala/collection/immutable/Set<Lcoursier/core/ModuleName;>;Lscala/collection/immutable/Set<Lscala/Tuple2<Lcoursier/core/Organization;Lcoursier/core/ModuleName;>;>;>;
    MethodParameters:
      Name                           Flags
      exclusions                     final
}
SourceFile: "Exclusions.scala"
RuntimeVisibleAnnotations:
  0: #6(#7=s#8)
    scala.reflect.ScalaSignature(
      bytes="\u0006\u0005\u001d<Q\u0001E\t\t\u0002Y1Q\u0001G\t\t\u0002eAQ\u0001I\u0001\u0005\u0002\u0005BQAI\u0001\u0005\u0002\rBQAQ\u0001\u0005\u0002\rCQ\u0001S\u0001\u0005\u0002%CqaS\u0001C\u0002\u0013\u0005A\n\u0003\u0004N\u0003\u0001\u0006I!\u000e\u0005\b\u001d\u0006\u0011\r\u0011\"\u0001P\u0011\u0019\u0001\u0016\u0001)A\u0005s!9\u0011+\u0001b\u0001\n\u0003\u0011\u0006B\u0002.\u0002A\u0003%1\u000bC\u0004\\\u0003\t\u0007I\u0011\u0001*\t\rq\u000b\u0001\u0015!\u0003T\u0011\u0015i\u0016\u0001\"\u0001_\u0011\u0015\u0019\u0017\u0001\"\u0001e\u0003))\u0005p\u00197vg&|gn\u001d\u0006\u0003%M\tAaY8sK*\tA#\u0001\u0005d_V\u00148/[3s\u0007\u0001\u0001\"aF\u0001\u000e\u0003E\u0011!\"\u0012=dYV\u001c\u0018n\u001c8t\'\t\t!\u0004\u0005\u0002\u001c=5\tADC\u0001\u001e\u0003\u0015\u00198-\u00197b\u0013\tyBD\u0001\u0004B]f\u0014VMZ\u0001\u0007y%t\u0017\u000e\u001e \u0015\u0003Y\t\u0011\u0002]1si&$\u0018n\u001c8\u0015\u0005\u0011\u0002\u0005CB\u000e&O)BD(\u0003\u0002\'9\t1A+\u001e9mKR\u0002\"a\u0007\u0015\n\u0005%b\"a\u0002\"p_2,\u0017M\u001c\t\u0004WI*dB\u0001\u00171!\tiC$D\u0001/\u0015\tyS#\u0001\u0004=e>|GOP\u0005\u0003cq\ta\u0001\u0015:fI\u00164\u0017BA\u001a5\u0005\r\u0019V\r\u001e\u0006\u0003cq\u0001\"a\u0006\u001c\n\u0005]\n\"\u0001D(sO\u0006t\u0017N_1uS>t\u0007cA\u00163sA\u0011qCO\u0005\u0003wE\u0011!\"T8ek2,g*Y7f!\rY#\'\u0010\t\u00057y*\u0014(\u0003\u0002@9\t1A+\u001e9mKJBQ!Q\u0002A\u0002q\n!\"\u001a=dYV\u001c\u0018n\u001c8t\u0003\u0015\t\u0007\u000f\u001d7z)\t!u\tE\u0003\u001c\u000bVJt%\u0003\u0002G9\tIa)\u001e8di&|gN\r\u0005\u0006\u0003\u0012\u0001\r\u0001P\u0001\t[&t\u0017.\\5{KR\u0011AH\u0013\u0005\u0006\u0003\u0016\u0001\r\u0001P\u0001\u0011C2dwJ]4b]&T\u0018\r^5p]N,\u0012!N\u0001\u0012C2dwJ]4b]&T\u0018\r^5p]N\u0004\u0013\u0001C1mY:\u000bW.Z:\u0016\u0003e\n\u0011\"\u00197m\u001d\u0006lWm\u001d\u0011\u0002\ti,\'o\\\u000b\u0002\'B\u0019A+W\u001f\u000e\u0003US!AV,\u0002\u0013%lW.\u001e;bE2,\'B\u0001-\u001d\u0003)\u0019w\u000e\u001c7fGRLwN\\\u0005\u0003gU\u000bQA_3s_\u0002\n1a\u001c8f\u0003\u0011yg.\u001a\u0011\u0002\t)|\u0017N\u001c\u000b\u0004y}\u000b\u0007\"\u00021\u000f\u0001\u0004a\u0014!\u0001=\t\u000b\tt\u0001\u0019\u0001\u001f\u0002\u0003e\fA!\\3fiR\u0019A(\u001a4\t\u000b\u0001|\u0001\u0019\u0001\u001f\t\u000b\t|\u0001\u0019\u0001\u001f"
    )
  ScalaSig: length = 0x3 (unknown attribute)
   05 02 00
