Classfile /Users/mw/Projects/slang-braindump/.jar/jar8/assemble/slang-braindump/assemble/content/coursier/core/Latest$.class
  Last modified May 29, 2022; size 1723 bytes
  SHA-256 checksum c3151cdbc3150bbb33c247db25ba84835bff2096f97da2041092d6713f92db12
  Compiled from "Latest.scala"
public final class coursier.core.Latest$ implements java.io.Serializable
  minor version: 0
  major version: 52
  flags: (0x0031) ACC_PUBLIC, ACC_FINAL, ACC_SUPER
  this_class: #2                          // coursier/core/Latest$
  super_class: #4                         // java/lang/Object
  interfaces: 1, fields: 1, methods: 4, attributes: 4
Constant pool:
   #1 = Utf8               coursier/core/Latest$
   #2 = Class              #1             // coursier/core/Latest$
   #3 = Utf8               java/lang/Object
   #4 = Class              #3             // java/lang/Object
   #5 = Utf8               java/io/Serializable
   #6 = Class              #5             // java/io/Serializable
   #7 = Utf8               Latest.scala
   #8 = Utf8               coursier/core/Latest$Integration$
   #9 = Class              #8             // coursier/core/Latest$Integration$
  #10 = Utf8               coursier/core/Latest
  #11 = Class              #10            // coursier/core/Latest
  #12 = Utf8
  #13 = Utf8               coursier/core/Latest$Release$
  #14 = Class              #13            // coursier/core/Latest$Release$
  #15 = Utf8               coursier/core/Latest$Stable$
  #16 = Class              #15            // coursier/core/Latest$Stable$
  #17 = Utf8               MODULE$
  #18 = Utf8               Lcoursier/core/Latest$;
  #19 = Utf8               <clinit>
  #20 = Utf8               ()V
  #21 = Utf8               <init>
  #22 = NameAndType        #21:#20        // "<init>":()V
  #23 = Methodref          #2.#22         // coursier/core/Latest$."<init>":()V
  #24 = NameAndType        #17:#18        // MODULE$:Lcoursier/core/Latest$;
  #25 = Fieldref           #2.#24         // coursier/core/Latest$.MODULE$:Lcoursier/core/Latest$;
  #26 = Utf8               apply
  #27 = Utf8               (Ljava/lang/String;)Lscala/Option;
  #28 = Utf8               (Ljava/lang/String;)Lscala/Option<Lcoursier/core/Latest;>;
  #29 = Utf8               s
  #30 = Utf8               java/lang/String
  #31 = Class              #30            // java/lang/String
  #32 = Utf8               hashCode
  #33 = Utf8               ()I
  #34 = NameAndType        #32:#33        // hashCode:()I
  #35 = Methodref          #31.#34        // java/lang/String.hashCode:()I
  #36 = Utf8               latest.release
  #37 = String             #36            // latest.release
  #38 = Utf8               equals
  #39 = Utf8               (Ljava/lang/Object;)Z
  #40 = NameAndType        #38:#39        // equals:(Ljava/lang/Object;)Z
  #41 = Methodref          #31.#40        // java/lang/String.equals:(Ljava/lang/Object;)Z
  #42 = Utf8               latest.integration
  #43 = String             #42            // latest.integration
  #44 = Utf8               latest.stable
  #45 = String             #44            // latest.stable
  #46 = Utf8               scala/Some
  #47 = Class              #46            // scala/Some
  #48 = Utf8               Lcoursier/core/Latest$Integration$;
  #49 = NameAndType        #17:#48        // MODULE$:Lcoursier/core/Latest$Integration$;
  #50 = Fieldref           #9.#49         // coursier/core/Latest$Integration$.MODULE$:Lcoursier/core/Latest$Integration$;
  #51 = Utf8               (Ljava/lang/Object;)V
  #52 = NameAndType        #21:#51        // "<init>":(Ljava/lang/Object;)V
  #53 = Methodref          #47.#52        // scala/Some."<init>":(Ljava/lang/Object;)V
  #54 = Utf8               Lcoursier/core/Latest$Release$;
  #55 = NameAndType        #17:#54        // MODULE$:Lcoursier/core/Latest$Release$;
  #56 = Fieldref           #14.#55        // coursier/core/Latest$Release$.MODULE$:Lcoursier/core/Latest$Release$;
  #57 = Utf8               Lcoursier/core/Latest$Stable$;
  #58 = NameAndType        #17:#57        // MODULE$:Lcoursier/core/Latest$Stable$;
  #59 = Fieldref           #16.#58        // coursier/core/Latest$Stable$.MODULE$:Lcoursier/core/Latest$Stable$;
  #60 = Utf8               scala/None$
  #61 = Class              #60            // scala/None$
  #62 = Utf8               Lscala/None$;
  #63 = NameAndType        #17:#62        // MODULE$:Lscala/None$;
  #64 = Fieldref           #61.#63        // scala/None$.MODULE$:Lscala/None$;
  #65 = Utf8               scala/Option
  #66 = Class              #65            // scala/Option
  #67 = Utf8               this
  #68 = Utf8               Ljava/lang/String;
  #69 = Utf8               writeReplace
  #70 = Utf8               ()Ljava/lang/Object;
  #71 = Utf8               scala/runtime/ModuleSerializationProxy
  #72 = Class              #71            // scala/runtime/ModuleSerializationProxy
  #73 = Utf8               (Ljava/lang/Class;)V
  #74 = NameAndType        #21:#73        // "<init>":(Ljava/lang/Class;)V
  #75 = Methodref          #72.#74        // scala/runtime/ModuleSerializationProxy."<init>":(Ljava/lang/Class;)V
  #76 = Methodref          #4.#22         // java/lang/Object."<init>":()V
  #77 = Utf8               Code
  #78 = Utf8               LineNumberTable
  #79 = Utf8               StackMapTable
  #80 = Utf8               LocalVariableTable
  #81 = Utf8               Signature
  #82 = Utf8               MethodParameters
  #83 = Utf8               InnerClasses
  #84 = Utf8               SourceFile
  #85 = Utf8               ScalaInlineInfo
  #86 = Utf8               Scala
{
  public static final coursier.core.Latest$ MODULE$;
    descriptor: Lcoursier/core/Latest$;
    flags: (0x0019) ACC_PUBLIC, ACC_STATIC, ACC_FINAL

  public static {};
    descriptor: ()V
    flags: (0x0009) ACC_PUBLIC, ACC_STATIC
    Code:
      stack=2, locals=0, args_size=0
         0: new           #2                  // class coursier/core/Latest$
         3: dup
         4: invokespecial #23                 // Method "<init>":()V
         7: putstatic     #25                 // Field MODULE$:Lcoursier/core/Latest$;
        10: return
      LineNumberTable:
        line 5: 0

  public scala.Option<coursier.core.Latest> apply(java.lang.String);
    descriptor: (Ljava/lang/String;)Lscala/Option;
    flags: (0x0001) ACC_PUBLIC
    Code:
      stack=3, locals=4, args_size=2
         0: aload_1
         1: astore_3
         2: aload_3
         3: ifnonnull     10
         6: iconst_0
         7: goto          14
        10: aload_3
        11: invokevirtual #35                 // Method java/lang/String.hashCode:()I
        14: lookupswitch  { // 3
             -1150857056: 48
              1483385325: 63
              1529047938: 78
                 default: 93
            }
        48: ldc           #37                 // String latest.release
        50: aload_3
        51: invokevirtual #41                 // Method java/lang/String.equals:(Ljava/lang/Object;)Z
        54: ifeq          60
        57: goto          110
        60: goto          138
        63: ldc           #43                 // String latest.integration
        65: aload_3
        66: invokevirtual #41                 // Method java/lang/String.equals:(Ljava/lang/Object;)Z
        69: ifeq          75
        72: goto          96
        75: goto          138
        78: ldc           #45                 // String latest.stable
        80: aload_3
        81: invokevirtual #41                 // Method java/lang/String.equals:(Ljava/lang/Object;)Z
        84: ifeq          90
        87: goto          124
        90: goto          138
        93: goto          138
        96: new           #47                 // class scala/Some
        99: dup
       100: getstatic     #50                 // Field coursier/core/Latest$Integration$.MODULE$:Lcoursier/core/Latest$Integration$;
       103: invokespecial #53                 // Method scala/Some."<init>":(Ljava/lang/Object;)V
       106: astore_2
       107: goto          145
       110: new           #47                 // class scala/Some
       113: dup
       114: getstatic     #56                 // Field coursier/core/Latest$Release$.MODULE$:Lcoursier/core/Latest$Release$;
       117: invokespecial #53                 // Method scala/Some."<init>":(Ljava/lang/Object;)V
       120: astore_2
       121: goto          145
       124: new           #47                 // class scala/Some
       127: dup
       128: getstatic     #59                 // Field coursier/core/Latest$Stable$.MODULE$:Lcoursier/core/Latest$Stable$;
       131: invokespecial #53                 // Method scala/Some."<init>":(Ljava/lang/Object;)V
       134: astore_2
       135: goto          145
       138: getstatic     #64                 // Field scala/None$.MODULE$:Lscala/None$;
       141: astore_2
       142: goto          145
       145: aload_2
       146: areturn
      StackMapTable: number_of_entries = 14
        frame_type = 253 /* append */
          offset_delta = 10
          locals = [ top, class java/lang/String ]
        frame_type = 67 /* same_locals_1_stack_item */
          stack = [ int ]
        frame_type = 33 /* same */
        frame_type = 11 /* same */
        frame_type = 2 /* same */
        frame_type = 11 /* same */
        frame_type = 2 /* same */
        frame_type = 11 /* same */
        frame_type = 2 /* same */
        frame_type = 2 /* same */
        frame_type = 13 /* same */
        frame_type = 13 /* same */
        frame_type = 13 /* same */
        frame_type = 255 /* full_frame */
          offset_delta = 6
          locals = [ class coursier/core/Latest$, class java/lang/String, class scala/Option, class java/lang/String ]
          stack = []
      LineNumberTable:
        line 11: 0
        line 13: 48
        line 11: 60
        line 12: 63
        line 11: 75
        line 14: 78
        line 11: 90
        line 12: 96
        line 13: 110
        line 14: 124
        line 15: 138
        line 11: 145
      LocalVariableTable:
        Start  Length  Slot  Name   Signature
            0     147     0  this   Lcoursier/core/Latest$;
            0     147     1     s   Ljava/lang/String;
    Signature: #28                          // (Ljava/lang/String;)Lscala/Option<Lcoursier/core/Latest;>;
    MethodParameters:
      Name                           Flags
      s                              final

  private java.lang.Object writeReplace();
    descriptor: ()Ljava/lang/Object;
    flags: (0x0002) ACC_PRIVATE
    Code:
      stack=3, locals=1, args_size=1
         0: new           #72                 // class scala/runtime/ModuleSerializationProxy
         3: dup
         4: ldc           #2                  // class coursier/core/Latest$
         6: invokespecial #75                 // Method scala/runtime/ModuleSerializationProxy."<init>":(Ljava/lang/Class;)V
         9: areturn
      LineNumberTable:
        line 5: 0
      LocalVariableTable:
        Start  Length  Slot  Name   Signature
            0      10     0  this   Lcoursier/core/Latest$;

  private coursier.core.Latest$();
    descriptor: ()V
    flags: (0x0002) ACC_PRIVATE
    Code:
      stack=1, locals=1, args_size=1
         0: aload_0
         1: invokespecial #76                 // Method java/lang/Object."<init>":()V
         4: return
      LineNumberTable:
        line 17: 0
        line 5: 4
      LocalVariableTable:
        Start  Length  Slot  Name   Signature
            0       5     0  this   Lcoursier/core/Latest$;
}
InnerClasses:
  public static #12= #9 of #11;           // =class coursier/core/Latest$Integration$ of class coursier/core/Latest
  public static #12= #14 of #11;          // =class coursier/core/Latest$Release$ of class coursier/core/Latest
  public static #12= #16 of #11;          // =class coursier/core/Latest$Stable$ of class coursier/core/Latest
SourceFile: "Latest.scala"
  ScalaInlineInfo: length = 0x13 (unknown attribute)
   01 01 00 03 00 17 00 16 01 00 1C 00 1D 01 00 47
   00 48 01
  Scala: length = 0x0 (unknown attribute)

