Classfile /Users/mw/Projects/slang-braindump/.jar/jar8/assemble/slang-braindump/assemble/content/coursier/core/Missing.class
  Last modified May 29, 2022; size 17176 bytes
  SHA-256 checksum 599c33fbf2533230fb15777d9b87ef515baef58b7d9cdc93d4ac4066fa113674
  Compiled from "ResolutionProcess.scala"
public final class coursier.core.Missing extends coursier.core.ResolutionProcess
  minor version: 0
  major version: 52
  flags: (0x0031) ACC_PUBLIC, ACC_FINAL, ACC_SUPER
  this_class: #2                          // coursier/core/Missing
  super_class: #4                         // coursier/core/ResolutionProcess
  interfaces: 0, fields: 3, methods: 37, attributes: 6
Constant pool:
    #1 = Utf8               coursier/core/Missing
    #2 = Class              #1            // coursier/core/Missing
    #3 = Utf8               coursier/core/ResolutionProcess
    #4 = Class              #3            // coursier/core/ResolutionProcess
    #5 = Utf8               ResolutionProcess.scala
    #6 = Utf8               Lscala/reflect/ScalaSignature;
    #7 = Utf8               bytes
    #8 = Utf8               \u0006\u0005\u0005\u0015d\u0001\u0002\u000e\u001c\u0005\u0001B\u0001b\u000e\u0001\u0003\u0006\u0004%\t\u0001\u000f\u0005\t\u0015\u0002\u0011\t\u0011)A\u0005s!A1\n\u0001BC\u0002\u0013\u0005A\n\u0003\u0005Q\u0001\t\u0005\t\u0015!\u0003N\u0011!\t\u0006A!b\u0001\n\u0003\u0011\u0006\u0002\u0003,\u0001\u0005\u0003\u0005\u000b\u0011B*\t\u000b]\u0003A\u0011\u0001-\t\u000bu\u0003A\u0011\u00010\t\u000b!\u0004A\u0011A5\t\u000b-\u0004A\u0011\u00017\t\u000b9\u0004A\u0011A8\t\u000bE\u0004A\u0011\t:\t\u000bi\u0004A\u0011I>\t\u000f\u0005%\u0001\u0001\"\u0011\u0002\f!9\u0011q\u0002\u0001\u0005B\u0005E\u0001bBA\r\u0001\u0011%\u00111\u0004\u0005\b\u0003G\u0001A\u0011IA\u0013\u0011\u001d\t9\u0003\u0001C!\u0003SAq!a\u000b\u0001\t\u0003\ni\u0003C\u0004\u00024\u0001!\t%!\u000e\b\u000f\u0005e2\u0004#\u0001\u0002<\u00191!d\u0007E\u0001\u0003{Aaa\u0016\f\u0005\u0002\u0005=\u0003bBA)-\u0011\u0005\u00111\u000b\u0005\n\u000372\u0012\u0011!C\u0005\u0003;\u0012q!T5tg&twM\u0003\u0002\u001d;\u0005!1m\u001c:f\u0015\u0005q\u0012\u0001C2pkJ\u001c\u0018.\u001a:\u0004\u0001M!\u0001!I\u0013,!\t\u00113%D\u0001\u001c\u0013\t!3DA\tSKN|G.\u001e;j_:\u0004&o\\2fgN\u0004\"AJ\u0015\u000e\u0003\u001dR\u0011\u0001K\u0001\u0006g\u000e\fG.Y\u0005\u0003U\u001d\u0012q\u0001\u0015:pIV\u001cG\u000f\u0005\u0002-i9\u0011QF\r\b\u0003]Ej\u0011a\f\u0006\u0003a}\ta\u0001\u0010:p_Rt\u0014\"\u0001\u0015\n\u0005M:\u0013a\u00029bG.\fw-Z\u0005\u0003kY\u0012AbU3sS\u0006d\u0017N_1cY\u0016T!aM\u0014\u0002\u000f5L7o]5oOV\t\u0011\bE\u0002-uqJ!a\u000f\u001c\u0003\u0007M+\u0017\u000f\u0005\u0003\'{}\u0012\u0015B\u0001 (\u0005\u0019!V\u000f\u001d7feA\u0011!\u0005Q\u0005\u0003\u0003n\u0011a!T8ek2,\u0007CA\"H\u001d\t!U\t\u0005\u0002/O%\u0011aiJ\u0001\u0007!J,G-\u001a4\n\u0005!K%AB*ue&twM\u0003\u0002GO\u0005AQ.[:tS:<\u0007%A\u0004dkJ\u0014XM\u001c;\u0016\u00035\u0003\"A\t(\n\u0005=[\"A\u0003*fg>dW\u000f^5p]\u0006A1-\u001e:sK:$\b%\u0001\u0003d_:$X#A*\u0011\t\u0019\"V*I\u0005\u0003+\u001e\u0012\u0011BR;oGRLwN\\\u0019\u0002\u000b\r|g\u000e\u001e\u0011\u0002\rqJg.\u001b;?)\u0011I&l\u0017/\u0011\u0005\t\u0002\u0001\"B\u001c\b\u0001\u0004I\u0004\"B&\b\u0001\u0004i\u0005\"B)\b\u0001\u0004\u0019\u0016!\u00028fqR\u0004DCA\u0011`\u0011\u0015\u0001\u0007\u00021\u0001b\u0003\u001d\u0011Xm];miN\u0004\"AY3\u000f\u0005\t\u001a\u0017B\u00013\u001c\u0003E\u0011Vm]8mkRLwN\u001c)s_\u000e,7o]\u0005\u0003M\u001e\u0014!!\u0014#\u000b\u0005\u0011\\\u0012aC<ji\"l\u0015n]:j]\u001e$\"!\u00176\t\u000b]J\u0001\u0019A\u001d\u0002\u0017]LG\u000f[\"veJ,g\u000e\u001e\u000b\u000336DQa\u0013\u0006A\u00025\u000b\u0001b^5uQ\u000e{g\u000e\u001e\u000b\u00033BDQ!U\u0006A\u0002M\u000b\u0001\u0002^8TiJLgn\u001a\u000b\u0002gB\u0011A/_\u0007\u0002k*\u0011ao^\u0001\u0005Y\u0006twMC\u0001y\u0003\u0011Q\u0017M^1\n\u0005!+\u0018\u0001C2b]\u0016\u000bX/\u00197\u0015\u0005q|\bC\u0001\u0014~\u0013\tqxEA\u0004C_>dW-\u00198\t\u000f\u0005\u0005Q\u00021\u0001\u0002\u0004\u0005\u0019qN\u00196\u0011\u0007\u0019\n)!C\u0002\u0002\b\u001d\u00121!\u00118z\u0003\u0019)\u0017/^1mgR\u0019A0!\u0004\t\u000f\u0005\u0005a\u00021\u0001\u0002\u0004\u0005A\u0001.Y:i\u0007>$W\r\u0006\u0002\u0002\u0014A\u0019a%!\u0006\n\u0007\u0005]qEA\u0002J]R\fQ\u0001^;qY\u0016,\"!!\b\u0011\r\u0019\ny\"O\'T\u0013\r\t\tc\n\u0002\u0007)V\u0004H.Z\u001a\u0002\u001bA\u0014x\u000eZ;diB\u0013XMZ5y+\u0005\u0019\u0018\u0001\u00049s_\u0012,8\r^!sSRLXCAA\n\u00039\u0001(o\u001c3vGR,E.Z7f]R$B!a\u0001\u00020!9\u0011\u0011G\nA\u0002\u0005M\u0011!\u00018\u0002%A\u0014x\u000eZ;di\u0016cW-\\3oi:\u000bW.\u001a\u000b\u0004g\u0006]\u0002bBA\u0019)\u0001\u0007\u00111C\u0001\b\u001b&\u001c8/\u001b8h!\t\u0011ccE\u0003\u0017\u0003\u007f\t)\u0005E\u0002\'\u0003\u0003J1!a\u0011(\u0005\u0019\te.\u001f*fMB!\u0011qIA\'\u001b\t\tIEC\u0002\u0002L]\f!![8\n\u0007U\nI\u0005\u0006\u0002\u0002<\u0005)\u0011\r\u001d9msR9\u0011,!\u0016\u0002X\u0005e\u0003\"B\u001c\u0019\u0001\u0004I\u0004\"B&\u0019\u0001\u0004i\u0005\"B)\u0019\u0001\u0004\u0019\u0016\u0001D<sSR,\'+\u001a9mC\u000e,GCAA0!\r!\u0018\u0011M\u0005\u0004\u0003G*(AB(cU\u0016\u001cG\u000f
    #9 = Utf8               coursier/core/Missing$$anonfun$1
   #10 = Class              #9            // coursier/core/Missing$$anonfun$1
   #11 = Utf8               coursier/core/Missing$$anonfun$2
   #12 = Class              #11           // coursier/core/Missing$$anonfun$2
   #13 = Utf8               java/lang/invoke/MethodHandles$Lookup
   #14 = Class              #13           // java/lang/invoke/MethodHandles$Lookup
   #15 = Utf8               java/lang/invoke/MethodHandles
   #16 = Class              #15           // java/lang/invoke/MethodHandles
   #17 = Utf8               Lookup
   #18 = Utf8               scala/Predef$ArrowAssoc$
   #19 = Class              #18           // scala/Predef$ArrowAssoc$
   #20 = Utf8               scala/Predef
   #21 = Class              #20           // scala/Predef
   #22 = Utf8
   #23 = Utf8               scala/math/Ordering$Int$
   #24 = Class              #23           // scala/math/Ordering$Int$
   #25 = Utf8               scala/math/Ordering
   #26 = Class              #25           // scala/math/Ordering
   #27 = Utf8               missing
   #28 = Utf8               Lscala/collection/immutable/Seq;
   #29 = Utf8               Lscala/collection/immutable/Seq<Lscala/Tuple2<Lcoursier/core/Module;Ljava/lang/String;>;>;
   #30 = Utf8               current
   #31 = Utf8               Lcoursier/core/Resolution;
   #32 = Utf8               cont
   #33 = Utf8               Lscala/Function1;
   #34 = Utf8               Lscala/Function1<Lcoursier/core/Resolution;Lcoursier/core/ResolutionProcess;>;
   #35 = Utf8               apply
   #36 = Utf8               (Lscala/collection/immutable/Seq;Lcoursier/core/Resolution;Lscala/Function1;)Lcoursier/core/Missing;
   #37 = Utf8               (Lscala/collection/immutable/Seq<Lscala/Tuple2<Lcoursier/core/Module;Ljava/lang/String;>;>;Lcoursier/core/Resolution;Lscala/Function1<Lcoursier/core/Resolution;Lcoursier/core/ResolutionProcess;>;)Lcoursier/core/Missing;
   #38 = Utf8               coursier/core/Missing$
   #39 = Class              #38           // coursier/core/Missing$
   #40 = Utf8               MODULE$
   #41 = Utf8               Lcoursier/core/Missing$;
   #42 = NameAndType        #40:#41       // MODULE$:Lcoursier/core/Missing$;
   #43 = Fieldref           #39.#42       // coursier/core/Missing$.MODULE$:Lcoursier/core/Missing$;
   #44 = NameAndType        #35:#36       // apply:(Lscala/collection/immutable/Seq;Lcoursier/core/Resolution;Lscala/Function1;)Lcoursier/core/Missing;
   #45 = Methodref          #39.#44       // coursier/core/Missing$.apply:(Lscala/collection/immutable/Seq;Lcoursier/core/Resolution;Lscala/Function1;)Lcoursier/core/Missing;
   #46 = Utf8               ()Lscala/collection/immutable/Seq;
   #47 = Utf8               ()Lscala/collection/immutable/Seq<Lscala/Tuple2<Lcoursier/core/Module;Ljava/lang/String;>;>;
   #48 = NameAndType        #27:#28       // missing:Lscala/collection/immutable/Seq;
   #49 = Fieldref           #2.#48        // coursier/core/Missing.missing:Lscala/collection/immutable/Seq;
   #50 = Utf8               this
   #51 = Utf8               Lcoursier/core/Missing;
   #52 = Utf8               ()Lcoursier/core/Resolution;
   #53 = NameAndType        #30:#31       // current:Lcoursier/core/Resolution;
   #54 = Fieldref           #2.#53        // coursier/core/Missing.current:Lcoursier/core/Resolution;
   #55 = Utf8               ()Lscala/Function1;
   #56 = Utf8               ()Lscala/Function1<Lcoursier/core/Resolution;Lcoursier/core/ResolutionProcess;>;
   #57 = NameAndType        #32:#33       // cont:Lscala/Function1;
   #58 = Fieldref           #2.#57        // coursier/core/Missing.cont:Lscala/Function1;
   #59 = Utf8               next0
   #60 = Utf8               (Lscala/collection/immutable/Seq;)Lcoursier/core/ResolutionProcess;
   #61 = Utf8               (Lscala/collection/immutable/Seq<Lscala/Tuple2<Lscala/Tuple2<Lcoursier/core/Module;Ljava/lang/String;>;Lscala/util/Either<Lscala/collection/immutable/Seq<Ljava/lang/String;>;Lscala/Tuple2<Lcoursier/core/ArtifactSource;Lcoursier/core/Project;>;>;>;>;)Lcoursier/core/ResolutionProcess;
   #62 = Utf8               results
   #63 = Utf8               <init>
   #64 = Utf8               (Lcoursier/core/Missing;)V
   #65 = NameAndType        #63:#64       // "<init>":(Lcoursier/core/Missing;)V
   #66 = Methodref          #10.#65       // coursier/core/Missing$$anonfun$1."<init>":(Lcoursier/core/Missing;)V
   #67 = Utf8               scala/collection/immutable/Seq
   #68 = Class              #67           // scala/collection/immutable/Seq
   #69 = Utf8               collect
   #70 = Utf8               (Lscala/PartialFunction;)Ljava/lang/Object;
   #71 = NameAndType        #69:#70       // collect:(Lscala/PartialFunction;)Ljava/lang/Object;
   #72 = InterfaceMethodref #68.#71       // scala/collection/immutable/Seq.collect:(Lscala/PartialFunction;)Ljava/lang/Object;
   #73 = Methodref          #12.#65       // coursier/core/Missing$$anonfun$2."<init>":(Lcoursier/core/Missing;)V
   #74 = NameAndType        #30:#52       // current:()Lcoursier/core/Resolution;
   #75 = Methodref          #2.#74        // coursier/core/Missing.current:()Lcoursier/core/Resolution;
   #76 = Utf8               coursier/core/Resolution
   #77 = Class              #76           // coursier/core/Resolution
   #78 = Utf8               addToErrorCache
   #79 = Utf8               (Lscala/collection/Iterable;)Lcoursier/core/Resolution;
   #80 = NameAndType        #78:#79       // addToErrorCache:(Lscala/collection/Iterable;)Lcoursier/core/Resolution;
   #81 = Methodref          #77.#80       // coursier/core/Resolution.addToErrorCache:(Lscala/collection/Iterable;)Lcoursier/core/Resolution;
   #82 = Utf8               cont0$1
   #83 = Utf8               (Lcoursier/core/Resolution;Lscala/collection/immutable/Seq;)Lcoursier/core/ResolutionProcess;
   #84 = NameAndType        #82:#83       // cont0$1:(Lcoursier/core/Resolution;Lscala/collection/immutable/Seq;)Lcoursier/core/ResolutionProcess;
   #85 = Methodref          #2.#84        // coursier/core/Missing.cont0$1:(Lcoursier/core/Resolution;Lscala/collection/immutable/Seq;)Lcoursier/core/ResolutionProcess;
   #86 = Utf8               errors
   #87 = Utf8               successes
   #88 = Utf8               current0
   #89 = Utf8               withMissing
   #90 = Utf8               (Lscala/collection/immutable/Seq;)Lcoursier/core/Missing;
   #91 = Utf8               (Lscala/collection/immutable/Seq<Lscala/Tuple2<Lcoursier/core/Module;Ljava/lang/String;>;>;)Lcoursier/core/Missing;
   #92 = NameAndType        #32:#55       // cont:()Lscala/Function1;
   #93 = Methodref          #2.#92        // coursier/core/Missing.cont:()Lscala/Function1;
   #94 = Utf8               (Lscala/collection/immutable/Seq;Lcoursier/core/Resolution;Lscala/Function1;)V
   #95 = NameAndType        #63:#94       // "<init>":(Lscala/collection/immutable/Seq;Lcoursier/core/Resolution;Lscala/Function1;)V
   #96 = Methodref          #2.#95        // coursier/core/Missing."<init>":(Lscala/collection/immutable/Seq;Lcoursier/core/Resolution;Lscala/Function1;)V
   #97 = Utf8               withCurrent
   #98 = Utf8               (Lcoursier/core/Resolution;)Lcoursier/core/Missing;
   #99 = NameAndType        #27:#46       // missing:()Lscala/collection/immutable/Seq;
  #100 = Methodref          #2.#99        // coursier/core/Missing.missing:()Lscala/collection/immutable/Seq;
  #101 = Utf8               withCont
  #102 = Utf8               (Lscala/Function1;)Lcoursier/core/Missing;
  #103 = Utf8               (Lscala/Function1<Lcoursier/core/Resolution;Lcoursier/core/ResolutionProcess;>;)Lcoursier/core/Missing;
  #104 = Utf8               toString
  #105 = Utf8               ()Ljava/lang/String;
  #106 = Utf8               java/lang/StringBuilder
  #107 = Class              #106          // java/lang/StringBuilder
  #108 = Utf8               Missing(
  #109 = String             #108          // Missing(
  #110 = Utf8               (Ljava/lang/String;)V
  #111 = NameAndType        #63:#110      // "<init>":(Ljava/lang/String;)V
  #112 = Methodref          #107.#111     // java/lang/StringBuilder."<init>":(Ljava/lang/String;)V
  #113 = Utf8               java/lang/String
  #114 = Class              #113          // java/lang/String
  #115 = Utf8               valueOf
  #116 = Utf8               (Ljava/lang/Object;)Ljava/lang/String;
  #117 = NameAndType        #115:#116     // valueOf:(Ljava/lang/Object;)Ljava/lang/String;
  #118 = Methodref          #114.#117     // java/lang/String.valueOf:(Ljava/lang/Object;)Ljava/lang/String;
  #119 = Utf8               append
  #120 = Utf8               (Ljava/lang/String;)Ljava/lang/StringBuilder;
  #121 = NameAndType        #119:#120     // append:(Ljava/lang/String;)Ljava/lang/StringBuilder;
  #122 = Methodref          #107.#121     // java/lang/StringBuilder.append:(Ljava/lang/String;)Ljava/lang/StringBuilder;
  #123 = Utf8               ,
  #124 = String             #123          // ,
  #125 = Utf8               )
  #126 = String             #125          // )
  #127 = NameAndType        #104:#105     // toString:()Ljava/lang/String;
  #128 = Methodref          #107.#127     // java/lang/StringBuilder.toString:()Ljava/lang/String;
  #129 = Utf8               b
  #130 = Utf8               Ljava/lang/StringBuilder;
  #131 = Utf8               canEqual
  #132 = Utf8               (Ljava/lang/Object;)Z
  #133 = Utf8               obj
  #134 = Utf8               Ljava/lang/Object;
  #135 = Utf8               equals
  #136 = NameAndType        #131:#132     // canEqual:(Ljava/lang/Object;)Z
  #137 = Methodref          #2.#136       // coursier/core/Missing.canEqual:(Ljava/lang/Object;)Z
  #138 = Utf8               java/lang/Object
  #139 = Class              #138          // java/lang/Object
  #140 = NameAndType        #135:#132     // equals:(Ljava/lang/Object;)Z
  #141 = Methodref          #139.#140     // java/lang/Object.equals:(Ljava/lang/Object;)Z
  #142 = Utf8               scala/Function1
  #143 = Class              #142          // scala/Function1
  #144 = Utf8               other
  #145 = Utf8               hashCode
  #146 = Utf8               ()I
  #147 = Utf8               Missing
  #148 = String             #147          // Missing
  #149 = Utf8               scala/runtime/Statics
  #150 = Class              #149          // scala/runtime/Statics
  #151 = Utf8               anyHash
  #152 = Utf8               (Ljava/lang/Object;)I
  #153 = NameAndType        #151:#152     // anyHash:(Ljava/lang/Object;)I
  #154 = Methodref          #150.#153     // scala/runtime/Statics.anyHash:(Ljava/lang/Object;)I
  #155 = Utf8               code
  #156 = Utf8               I
  #157 = Utf8               tuple
  #158 = Utf8               ()Lscala/Tuple3;
  #159 = Utf8               ()Lscala/Tuple3<Lscala/collection/immutable/Seq<Lscala/Tuple2<Lcoursier/core/Module;Ljava/lang/String;>;>;Lcoursier/core/Resolution;Lscala/Function1<Lcoursier/core/Resolution;Lcoursier/core/ResolutionProcess;>;>;
  #160 = Utf8               scala/Tuple3
  #161 = Class              #160          // scala/Tuple3
  #162 = Utf8               (Ljava/lang/Object;Ljava/lang/Object;Ljava/lang/Object;)V
  #163 = NameAndType        #63:#162      // "<init>":(Ljava/lang/Object;Ljava/lang/Object;Ljava/lang/Object;)V
  #164 = Methodref          #161.#163     // scala/Tuple3."<init>":(Ljava/lang/Object;Ljava/lang/Object;Ljava/lang/Object;)V
  #165 = Utf8               productPrefix
  #166 = Utf8               productArity
  #167 = Utf8               productElement
  #168 = Utf8               (I)Ljava/lang/Object;
  #169 = Utf8               n
  #170 = Utf8               java/lang/IndexOutOfBoundsException
  #171 = Class              #170          // java/lang/IndexOutOfBoundsException
  #172 = Utf8               scala/runtime/BoxesRunTime
  #173 = Class              #172          // scala/runtime/BoxesRunTime
  #174 = Utf8               boxToInteger
  #175 = Utf8               (I)Ljava/lang/Integer;
  #176 = NameAndType        #174:#175     // boxToInteger:(I)Ljava/lang/Integer;
  #177 = Methodref          #173.#176     // scala/runtime/BoxesRunTime.boxToInteger:(I)Ljava/lang/Integer;
  #178 = Methodref          #139.#127     // java/lang/Object.toString:()Ljava/lang/String;
  #179 = Methodref          #171.#111     // java/lang/IndexOutOfBoundsException."<init>":(Ljava/lang/String;)V
  #180 = Utf8               productElementName
  #181 = Utf8               (I)Ljava/lang/String;
  #182 = String             #27           // missing
  #183 = String             #30           // current
  #184 = String             #32           // cont
  #185 = Utf8               $anonfun$next0$1
  #186 = Utf8               (Lcoursier/core/Resolution;Lscala/Tuple2;)Z
  #187 = Utf8               res$1
  #188 = Utf8               x0$1
  #189 = Utf8               scala/Tuple2
  #190 = Class              #189          // scala/Tuple2
  #191 = Utf8               _1
  #192 = Utf8               ()Ljava/lang/Object;
  #193 = NameAndType        #191:#192     // _1:()Ljava/lang/Object;
  #194 = Methodref          #190.#193     // scala/Tuple2._1:()Ljava/lang/Object;
  #195 = Utf8               projectCache
  #196 = Utf8               ()Lscala/collection/immutable/Map;
  #197 = NameAndType        #195:#196     // projectCache:()Lscala/collection/immutable/Map;
  #198 = Methodref          #77.#197      // coursier/core/Resolution.projectCache:()Lscala/collection/immutable/Map;
  #199 = Utf8               scala/collection/immutable/Map
  #200 = Class              #199          // scala/collection/immutable/Map
  #201 = Utf8               contains
  #202 = NameAndType        #201:#132     // contains:(Ljava/lang/Object;)Z
  #203 = InterfaceMethodref #200.#202     // scala/collection/immutable/Map.contains:(Ljava/lang/Object;)Z
  #204 = Utf8               scala/MatchError
  #205 = Class              #204          // scala/MatchError
  #206 = Utf8               (Ljava/lang/Object;)V
  #207 = NameAndType        #63:#206      // "<init>":(Ljava/lang/Object;)V
  #208 = Methodref          #205.#207     // scala/MatchError."<init>":(Ljava/lang/Object;)V
  #209 = Utf8               modVer
  #210 = Utf8               Lscala/Tuple2;
  #211 = Utf8               $anonfun$next0$2
  #212 = Utf8               (Lcoursier/core/Resolution;Lscala/Tuple2;)Lscala/Tuple2;
  #213 = Utf8               x0$2
  #214 = Utf8               _2
  #215 = NameAndType        #214:#192     // _2:()Ljava/lang/Object;
  #216 = Methodref          #190.#215     // scala/Tuple2._2:()Ljava/lang/Object;
  #217 = Utf8               coursier/core/Project
  #218 = Class              #217          // coursier/core/Project
  #219 = Utf8               Lscala/Predef$ArrowAssoc$;
  #220 = NameAndType        #40:#219      // MODULE$:Lscala/Predef$ArrowAssoc$;
  #221 = Fieldref           #19.#220      // scala/Predef$ArrowAssoc$.MODULE$:Lscala/Predef$ArrowAssoc$;
  #222 = Utf8               scala/Predef$
  #223 = Class              #222          // scala/Predef$
  #224 = Utf8               Lscala/Predef$;
  #225 = NameAndType        #40:#224      // MODULE$:Lscala/Predef$;
  #226 = Fieldref           #223.#225     // scala/Predef$.MODULE$:Lscala/Predef$;
  #227 = Utf8               ArrowAssoc
  #228 = Utf8               (Ljava/lang/Object;)Ljava/lang/Object;
  #229 = NameAndType        #227:#228     // ArrowAssoc:(Ljava/lang/Object;)Ljava/lang/Object;
  #230 = Methodref          #223.#229     // scala/Predef$.ArrowAssoc:(Ljava/lang/Object;)Ljava/lang/Object;
  #231 = Utf8               dependencyManagementMissing
  #232 = Utf8               (Lcoursier/core/Project;)Lscala/collection/immutable/Set;
  #233 = NameAndType        #231:#232     // dependencyManagementMissing:(Lcoursier/core/Project;)Lscala/collection/immutable/Set;
  #234 = Methodref          #77.#233      // coursier/core/Resolution.dependencyManagementMissing:(Lcoursier/core/Project;)Lscala/collection/immutable/Set;
  #235 = Utf8               $minus$greater$extension
  #236 = Utf8               (Ljava/lang/Object;Ljava/lang/Object;)Lscala/Tuple2;
  #237 = NameAndType        #235:#236     // $minus$greater$extension:(Ljava/lang/Object;Ljava/lang/Object;)Lscala/Tuple2;
  #238 = Methodref          #19.#237      // scala/Predef$ArrowAssoc$.$minus$greater$extension:(Ljava/lang/Object;Ljava/lang/Object;)Lscala/Tuple2;
  #239 = Utf8               proj
  #240 = Utf8               Lcoursier/core/Project;
  #241 = Utf8               $anonfun$next0$3
  #242 = Utf8               (Lscala/Tuple2;)Lscala/collection/immutable/Set;
  #243 = Utf8               x$1
  #244 = Utf8               scala/collection/immutable/Set
  #245 = Class              #244          // scala/collection/immutable/Set
  #246 = Utf8               $anonfun$next0$4
  #247 = Utf8               (Lscala/collection/immutable/Set;Lscala/collection/immutable/Set;)Lscala/collection/immutable/Set;
  #248 = Utf8               x$2
  #249 = Utf8               x$3
  #250 = Utf8               $plus$plus
  #251 = Utf8               (Lscala/collection/IterableOnce;)Lscala/collection/SetOps;
  #252 = NameAndType        #250:#251     // $plus$plus:(Lscala/collection/IterableOnce;)Lscala/collection/SetOps;
  #253 = InterfaceMethodref #245.#252     // scala/collection/immutable/Set.$plus$plus:(Lscala/collection/IterableOnce;)Lscala/collection/SetOps;
  #254 = Utf8               Lscala/collection/immutable/Set;
  #255 = Utf8               $anonfun$next0$5
  #256 = Utf8               (Lscala/Tuple2;)Lscala/Tuple2;
  #257 = Utf8               x$4
  #258 = Utf8               $anonfun$next0$6
  #259 = Utf8               (Lscala/Tuple2;)I
  #260 = Utf8               x$5
  #261 = Utf8               scala/collection/IterableOnceOps
  #262 = Class              #261          // scala/collection/IterableOnceOps
  #263 = Utf8               size
  #264 = NameAndType        #263:#146     // size:()I
  #265 = InterfaceMethodref #262.#264     // scala/collection/IterableOnceOps.size:()I
  #266 = Utf8               $anonfun$next0$7
  #267 = Utf8               (ILscala/Tuple2;)Z
  #268 = Utf8               min$1
  #269 = InterfaceMethodref #245.#264     // scala/collection/immutable/Set.size:()I
  #270 = Utf8               v
  #271 = Utf8               $anonfun$next0$8
  #272 = Utf8               (Lscala/collection/immutable/List;Lscala/Tuple2;)Lscala/collection/immutable/List;
  #273 = Utf8               x$7
  #274 = Utf8               x$8
  #275 = Utf8               scala/collection/immutable/List
  #276 = Class              #275          // scala/collection/immutable/List
  #277 = Utf8               $colon$colon
  #278 = Utf8               (Ljava/lang/Object;)Lscala/collection/immutable/List;
  #279 = NameAndType        #277:#278     // $colon$colon:(Ljava/lang/Object;)Lscala/collection/immutable/List;
  #280 = Methodref          #276.#279     // scala/collection/immutable/List.$colon$colon:(Ljava/lang/Object;)Lscala/collection/immutable/List;
  #281 = Utf8               Lscala/collection/immutable/List;
  #282 = Utf8               $anonfun$next0$9
  #283 = Utf8               x$9
  #284 = Utf8               $anonfun$next0$10
  #285 = Utf8               (Lscala/collection/immutable/Set;Lscala/Tuple2;)Lscala/Tuple2;
  #286 = Utf8               remainingKeys$1
  #287 = Utf8               intersect
  #288 = Utf8               (Lscala/collection/Set;)Lscala/collection/SetOps;
  #289 = NameAndType        #287:#288     // intersect:(Lscala/collection/Set;)Lscala/collection/SetOps;
  #290 = InterfaceMethodref #245.#289     // scala/collection/immutable/Set.intersect:(Lscala/collection/Set;)Lscala/collection/SetOps;
  #291 = Utf8               k
  #292 = Utf8               order$1
  #293 = Utf8               (Lscala/collection/immutable/Map;Lscala/collection/immutable/List;)Lscala/collection/immutable/List;
  #294 = Utf8               map
  #295 = Utf8               acc
  #296 = Utf8               isEmpty
  #297 = Utf8               ()Z
  #298 = NameAndType        #296:#297     // isEmpty:()Z
  #299 = InterfaceMethodref #200.#298     // scala/collection/immutable/Map.isEmpty:()Z
  #300 = Utf8               reverse
  #301 = Utf8               ()Lscala/collection/immutable/List;
  #302 = NameAndType        #300:#301     // reverse:()Lscala/collection/immutable/List;
  #303 = Methodref          #276.#302     // scala/collection/immutable/List.reverse:()Lscala/collection/immutable/List;
  #304 = MethodType         #228          //  (Ljava/lang/Object;)Ljava/lang/Object;
  #305 = Utf8               $anonfun$next0$6$adapted
  #306 = Utf8               (Lscala/Tuple2;)Ljava/lang/Object;
  #307 = NameAndType        #305:#306     // $anonfun$next0$6$adapted:(Lscala/Tuple2;)Ljava/lang/Object;
  #308 = Methodref          #2.#307       // coursier/core/Missing.$anonfun$next0$6$adapted:(Lscala/Tuple2;)Ljava/lang/Object;
  #309 = MethodHandle       6:#308        // REF_invokeStatic coursier/core/Missing.$anonfun$next0$6$adapted:(Lscala/Tuple2;)Ljava/lang/Object;
  #310 = MethodType         #306          //  (Lscala/Tuple2;)Ljava/lang/Object;
  #311 = Integer            5
  #312 = Integer            1
  #313 = Utf8               java/lang/invoke/LambdaMetafactory
  #314 = Class              #313          // java/lang/invoke/LambdaMetafactory
  #315 = Utf8               altMetafactory
  #316 = Utf8               (Ljava/lang/invoke/MethodHandles$Lookup;Ljava/lang/String;Ljava/lang/invoke/MethodType;[Ljava/lang/Object;)Ljava/lang/invoke/CallSite;
  #317 = NameAndType        #315:#316     // altMetafactory:(Ljava/lang/invoke/MethodHandles$Lookup;Ljava/lang/String;Ljava/lang/invoke/MethodType;[Ljava/lang/Object;)Ljava/lang/invoke/CallSite;
  #318 = Methodref          #314.#317     // java/lang/invoke/LambdaMetafactory.altMetafactory:(Ljava/lang/invoke/MethodHandles$Lookup;Ljava/lang/String;Ljava/lang/invoke/MethodType;[Ljava/lang/Object;)Ljava/lang/invoke/CallSite;
  #319 = MethodHandle       6:#318        // REF_invokeStatic java/lang/invoke/LambdaMetafactory.altMetafactory:(Ljava/lang/invoke/MethodHandles$Lookup;Ljava/lang/String;Ljava/lang/invoke/MethodType;[Ljava/lang/Object;)Ljava/lang/invoke/CallSite;
  #320 = NameAndType        #35:#55       // apply:()Lscala/Function1;
  #321 = InvokeDynamic      #0:#320       // #0:apply:()Lscala/Function1;
  #322 = Utf8               (Lscala/Function1;)Ljava/lang/Object;
  #323 = NameAndType        #294:#322     // map:(Lscala/Function1;)Ljava/lang/Object;
  #324 = InterfaceMethodref #200.#323     // scala/collection/immutable/Map.map:(Lscala/Function1;)Ljava/lang/Object;
  #325 = Utf8               Lscala/math/Ordering$Int$;
  #326 = NameAndType        #40:#325      // MODULE$:Lscala/math/Ordering$Int$;
  #327 = Fieldref           #24.#326      // scala/math/Ordering$Int$.MODULE$:Lscala/math/Ordering$Int$;
  #328 = Utf8               min
  #329 = Utf8               (Lscala/math/Ordering;)Ljava/lang/Object;
  #330 = NameAndType        #328:#329     // min:(Lscala/math/Ordering;)Ljava/lang/Object;
  #331 = InterfaceMethodref #262.#330     // scala/collection/IterableOnceOps.min:(Lscala/math/Ordering;)Ljava/lang/Object;
  #332 = Utf8               unboxToInt
  #333 = NameAndType        #332:#152     // unboxToInt:(Ljava/lang/Object;)I
  #334 = Methodref          #173.#333     // scala/runtime/BoxesRunTime.unboxToInt:(Ljava/lang/Object;)I
  #335 = Utf8               $anonfun$next0$7$adapted
  #336 = Utf8               (ILscala/Tuple2;)Ljava/lang/Object;
  #337 = NameAndType        #335:#336     // $anonfun$next0$7$adapted:(ILscala/Tuple2;)Ljava/lang/Object;
  #338 = Methodref          #2.#337       // coursier/core/Missing.$anonfun$next0$7$adapted:(ILscala/Tuple2;)Ljava/lang/Object;
  #339 = MethodHandle       6:#338        // REF_invokeStatic coursier/core/Missing.$anonfun$next0$7$adapted:(ILscala/Tuple2;)Ljava/lang/Object;
  #340 = Utf8               (I)Lscala/Function1;
  #341 = NameAndType        #35:#340      // apply:(I)Lscala/Function1;
  #342 = InvokeDynamic      #1:#341       // #1:apply:(I)Lscala/Function1;
  #343 = Utf8               partition
  #344 = Utf8               (Lscala/Function1;)Lscala/Tuple2;
  #345 = NameAndType        #343:#344     // partition:(Lscala/Function1;)Lscala/Tuple2;
  #346 = InterfaceMethodref #200.#345     // scala/collection/immutable/Map.partition:(Lscala/Function1;)Lscala/Tuple2;
  #347 = Utf8               (Ljava/lang/Object;Ljava/lang/Object;)V
  #348 = NameAndType        #63:#347      // "<init>":(Ljava/lang/Object;Ljava/lang/Object;)V
  #349 = Methodref          #190.#348     // scala/Tuple2."<init>":(Ljava/lang/Object;Ljava/lang/Object;)V
  #350 = Utf8               keys
  #351 = Utf8               ()Lscala/collection/Iterable;
  #352 = NameAndType        #350:#351     // keys:()Lscala/collection/Iterable;
  #353 = InterfaceMethodref #200.#352     // scala/collection/immutable/Map.keys:()Lscala/collection/Iterable;
  #354 = Utf8               (Ljava/lang/Object;Ljava/lang/Object;)Ljava/lang/Object;
  #355 = MethodType         #354          //  (Ljava/lang/Object;Ljava/lang/Object;)Ljava/lang/Object;
  #356 = NameAndType        #271:#272     // $anonfun$next0$8:(Lscala/collection/immutable/List;Lscala/Tuple2;)Lscala/collection/immutable/List;
  #357 = Methodref          #2.#356       // coursier/core/Missing.$anonfun$next0$8:(Lscala/collection/immutable/List;Lscala/Tuple2;)Lscala/collection/immutable/List;
  #358 = MethodHandle       6:#357        // REF_invokeStatic coursier/core/Missing.$anonfun$next0$8:(Lscala/collection/immutable/List;Lscala/Tuple2;)Lscala/collection/immutable/List;
  #359 = MethodType         #272          //  (Lscala/collection/immutable/List;Lscala/Tuple2;)Lscala/collection/immutable/List;
  #360 = Utf8               ()Lscala/Function2;
  #361 = NameAndType        #35:#360      // apply:()Lscala/Function2;
  #362 = InvokeDynamic      #2:#361       // #2:apply:()Lscala/Function2;
  #363 = Utf8               scala/collection/Iterable
  #364 = Class              #363          // scala/collection/Iterable
  #365 = Utf8               foldLeft
  #366 = Utf8               (Ljava/lang/Object;Lscala/Function2;)Ljava/lang/Object;
  #367 = NameAndType        #365:#366     // foldLeft:(Ljava/lang/Object;Lscala/Function2;)Ljava/lang/Object;
  #368 = InterfaceMethodref #364.#367     // scala/collection/Iterable.foldLeft:(Ljava/lang/Object;Lscala/Function2;)Ljava/lang/Object;
  #369 = Utf8               keySet
  #370 = Utf8               ()Lscala/collection/immutable/Set;
  #371 = NameAndType        #369:#370     // keySet:()Lscala/collection/immutable/Set;
  #372 = InterfaceMethodref #200.#371     // scala/collection/immutable/Map.keySet:()Lscala/collection/immutable/Set;
  #373 = NameAndType        #282:#256     // $anonfun$next0$9:(Lscala/Tuple2;)Lscala/Tuple2;
  #374 = Methodref          #2.#373       // coursier/core/Missing.$anonfun$next0$9:(Lscala/Tuple2;)Lscala/Tuple2;
  #375 = MethodHandle       6:#374        // REF_invokeStatic coursier/core/Missing.$anonfun$next0$9:(Lscala/Tuple2;)Lscala/Tuple2;
  #376 = MethodType         #256          //  (Lscala/Tuple2;)Lscala/Tuple2;
  #377 = InvokeDynamic      #3:#320       // #3:apply:()Lscala/Function1;
  #378 = InterfaceMethodref #245.#323     // scala/collection/immutable/Set.map:(Lscala/Function1;)Ljava/lang/Object;
  #379 = NameAndType        #284:#285     // $anonfun$next0$10:(Lscala/collection/immutable/Set;Lscala/Tuple2;)Lscala/Tuple2;
  #380 = Methodref          #2.#379       // coursier/core/Missing.$anonfun$next0$10:(Lscala/collection/immutable/Set;Lscala/Tuple2;)Lscala/Tuple2;
  #381 = MethodHandle       6:#380        // REF_invokeStatic coursier/core/Missing.$anonfun$next0$10:(Lscala/collection/immutable/Set;Lscala/Tuple2;)Lscala/Tuple2;
  #382 = Utf8               (Lscala/collection/immutable/Set;)Lscala/Function1;
  #383 = NameAndType        #35:#382      // apply:(Lscala/collection/immutable/Set;)Lscala/Function1;
  #384 = InvokeDynamic      #4:#383       // #4:apply:(Lscala/collection/immutable/Set;)Lscala/Function1;
  #385 = Utf8               (Lscala/Function1;)Lscala/collection/IterableOps;
  #386 = NameAndType        #294:#385     // map:(Lscala/Function1;)Lscala/collection/IterableOps;
  #387 = InterfaceMethodref #200.#386     // scala/collection/immutable/Map.map:(Lscala/Function1;)Lscala/collection/IterableOps;
  #388 = Utf8               toAdd
  #389 = Utf8               Lscala/collection/immutable/Map;
  #390 = Utf8               remaining
  #391 = Utf8               acc0
  #392 = Utf8               remainingKeys
  #393 = Utf8               map0
  #394 = Utf8               $anonfun$next0$11
  #395 = Utf8               modVer$1
  #396 = Utf8               x0$3
  #397 = Utf8               $anonfun$next0$12
  #398 = Utf8               (Lcoursier/core/Resolution;Lscala/Tuple2;)Lcoursier/core/Resolution;
  #399 = Utf8               x0$4
  #400 = Utf8               x1$1
  #401 = Utf8               coursier/core/ArtifactSource
  #402 = Class              #401          // coursier/core/ArtifactSource
  #403 = Utf8               scala/runtime/ScalaRunTime$
  #404 = Class              #403          // scala/runtime/ScalaRunTime$
  #405 = Utf8               Lscala/runtime/ScalaRunTime$;
  #406 = NameAndType        #40:#405      // MODULE$:Lscala/runtime/ScalaRunTime$;
  #407 = Fieldref           #404.#406     // scala/runtime/ScalaRunTime$.MODULE$:Lscala/runtime/ScalaRunTime$;
  #408 = Utf8               [Ljava/lang/Object;
  #409 = Class              #408          // "[Ljava/lang/Object;"
  #410 = Utf8               wrapRefArray
  #411 = Utf8               ([Ljava/lang/Object;)Lscala/collection/immutable/ArraySeq;
  #412 = NameAndType        #410:#411     // wrapRefArray:([Ljava/lang/Object;)Lscala/collection/immutable/ArraySeq;
  #413 = Methodref          #404.#412     // scala/runtime/ScalaRunTime$.wrapRefArray:([Ljava/lang/Object;)Lscala/collection/immutable/ArraySeq;
  #414 = Utf8               addToProjectCache
  #415 = Utf8               (Lscala/collection/immutable/Seq;)Lcoursier/core/Resolution;
  #416 = NameAndType        #414:#415     // addToProjectCache:(Lscala/collection/immutable/Seq;)Lcoursier/core/Resolution;
  #417 = Methodref          #77.#416      // coursier/core/Resolution.addToProjectCache:(Lscala/collection/immutable/Seq;)Lcoursier/core/Resolution;
  #418 = Utf8               source
  #419 = Utf8               Lcoursier/core/ArtifactSource;
  #420 = Utf8               modVer0
  #421 = Utf8               $anonfun$next0$13
  #422 = Utf8               (Lcoursier/core/Missing;Lscala/collection/immutable/Seq;Lcoursier/core/Resolution;)Lcoursier/core/ResolutionProcess;
  #423 = Utf8               $this
  #424 = Utf8               successes$1
  #425 = Utf8               res
  #426 = Utf8               $anonfun$next0$1$adapted
  #427 = Utf8               (Lcoursier/core/Resolution;Lscala/Tuple2;)Ljava/lang/Object;
  #428 = NameAndType        #426:#427     // $anonfun$next0$1$adapted:(Lcoursier/core/Resolution;Lscala/Tuple2;)Ljava/lang/Object;
  #429 = Methodref          #2.#428       // coursier/core/Missing.$anonfun$next0$1$adapted:(Lcoursier/core/Resolution;Lscala/Tuple2;)Ljava/lang/Object;
  #430 = MethodHandle       6:#429        // REF_invokeStatic coursier/core/Missing.$anonfun$next0$1$adapted:(Lcoursier/core/Resolution;Lscala/Tuple2;)Ljava/lang/Object;
  #431 = Utf8               (Lcoursier/core/Resolution;)Lscala/Function1;
  #432 = NameAndType        #35:#431      // apply:(Lcoursier/core/Resolution;)Lscala/Function1;
  #433 = InvokeDynamic      #5:#432       // #5:apply:(Lcoursier/core/Resolution;)Lscala/Function1;
  #434 = Utf8               filter
  #435 = NameAndType        #434:#322     // filter:(Lscala/Function1;)Ljava/lang/Object;
  #436 = InterfaceMethodref #68.#435      // scala/collection/immutable/Seq.filter:(Lscala/Function1;)Ljava/lang/Object;
  #437 = NameAndType        #211:#212     // $anonfun$next0$2:(Lcoursier/core/Resolution;Lscala/Tuple2;)Lscala/Tuple2;
  #438 = Methodref          #2.#437       // coursier/core/Missing.$anonfun$next0$2:(Lcoursier/core/Resolution;Lscala/Tuple2;)Lscala/Tuple2;
  #439 = MethodHandle       6:#438        // REF_invokeStatic coursier/core/Missing.$anonfun$next0$2:(Lcoursier/core/Resolution;Lscala/Tuple2;)Lscala/Tuple2;
  #440 = InvokeDynamic      #6:#432       // #6:apply:(Lcoursier/core/Resolution;)Lscala/Function1;
  #441 = InterfaceMethodref #68.#323      // scala/collection/immutable/Seq.map:(Lscala/Function1;)Ljava/lang/Object;
  #442 = NameAndType        #241:#242     // $anonfun$next0$3:(Lscala/Tuple2;)Lscala/collection/immutable/Set;
  #443 = Methodref          #2.#442       // coursier/core/Missing.$anonfun$next0$3:(Lscala/Tuple2;)Lscala/collection/immutable/Set;
  #444 = MethodHandle       6:#443        // REF_invokeStatic coursier/core/Missing.$anonfun$next0$3:(Lscala/Tuple2;)Lscala/collection/immutable/Set;
  #445 = MethodType         #242          //  (Lscala/Tuple2;)Lscala/collection/immutable/Set;
  #446 = InvokeDynamic      #7:#320       // #7:apply:()Lscala/Function1;
  #447 = Utf8               Set
  #448 = Utf8               ()Lscala/collection/immutable/Set$;
  #449 = NameAndType        #447:#448     // Set:()Lscala/collection/immutable/Set$;
  #450 = Methodref          #223.#449     // scala/Predef$.Set:()Lscala/collection/immutable/Set$;
  #451 = Utf8               scala/collection/immutable/Set$
  #452 = Class              #451          // scala/collection/immutable/Set$
  #453 = Utf8               empty
  #454 = NameAndType        #453:#370     // empty:()Lscala/collection/immutable/Set;
  #455 = Methodref          #452.#454     // scala/collection/immutable/Set$.empty:()Lscala/collection/immutable/Set;
  #456 = NameAndType        #246:#247     // $anonfun$next0$4:(Lscala/collection/immutable/Set;Lscala/collection/immutable/Set;)Lscala/collection/immutable/Set;
  #457 = Methodref          #2.#456       // coursier/core/Missing.$anonfun$next0$4:(Lscala/collection/immutable/Set;Lscala/collection/immutable/Set;)Lscala/collection/immutable/Set;
  #458 = MethodHandle       6:#457        // REF_invokeStatic coursier/core/Missing.$anonfun$next0$4:(Lscala/collection/immutable/Set;Lscala/collection/immutable/Set;)Lscala/collection/immutable/Set;
  #459 = MethodType         #247          //  (Lscala/collection/immutable/Set;Lscala/collection/immutable/Set;)Lscala/collection/immutable/Set;
  #460 = InvokeDynamic      #8:#361       // #8:apply:()Lscala/Function2;
  #461 = Utf8               fold
  #462 = NameAndType        #461:#366     // fold:(Ljava/lang/Object;Lscala/Function2;)Ljava/lang/Object;
  #463 = InterfaceMethodref #262.#462     // scala/collection/IterableOnceOps.fold:(Ljava/lang/Object;Lscala/Function2;)Ljava/lang/Object;
  #464 = InterfaceMethodref #245.#298     // scala/collection/immutable/Set.isEmpty:()Z
  #465 = NameAndType        #255:#256     // $anonfun$next0$5:(Lscala/Tuple2;)Lscala/Tuple2;
  #466 = Methodref          #2.#465       // coursier/core/Missing.$anonfun$next0$5:(Lscala/Tuple2;)Lscala/Tuple2;
  #467 = MethodHandle       6:#466        // REF_invokeStatic coursier/core/Missing.$anonfun$next0$5:(Lscala/Tuple2;)Lscala/Tuple2;
  #468 = InvokeDynamic      #9:#320       // #9:apply:()Lscala/Function1;
  #469 = Utf8               toSet
  #470 = NameAndType        #469:#370     // toSet:()Lscala/collection/immutable/Set;
  #471 = InterfaceMethodref #262.#470     // scala/collection/IterableOnceOps.toSet:()Lscala/collection/immutable/Set;
  #472 = NameAndType        #394:#285     // $anonfun$next0$11:(Lscala/collection/immutable/Set;Lscala/Tuple2;)Lscala/Tuple2;
  #473 = Methodref          #2.#472       // coursier/core/Missing.$anonfun$next0$11:(Lscala/collection/immutable/Set;Lscala/Tuple2;)Lscala/Tuple2;
  #474 = MethodHandle       6:#473        // REF_invokeStatic coursier/core/Missing.$anonfun$next0$11:(Lscala/collection/immutable/Set;Lscala/Tuple2;)Lscala/Tuple2;
  #475 = InvokeDynamic      #10:#383      // #10:apply:(Lscala/collection/immutable/Set;)Lscala/Function1;
  #476 = Utf8               scala/$less$colon$less$
  #477 = Class              #476          // scala/$less$colon$less$
  #478 = Utf8               Lscala/$less$colon$less$;
  #479 = NameAndType        #40:#478      // MODULE$:Lscala/$less$colon$less$;
  #480 = Fieldref           #477.#479     // scala/$less$colon$less$.MODULE$:Lscala/$less$colon$less$;
  #481 = Utf8               refl
  #482 = Utf8               ()Lscala/$eq$colon$eq;
  #483 = NameAndType        #481:#482     // refl:()Lscala/$eq$colon$eq;
  #484 = Methodref          #477.#483     // scala/$less$colon$less$.refl:()Lscala/$eq$colon$eq;
  #485 = Utf8               toMap
  #486 = Utf8               (Lscala/$less$colon$less;)Lscala/collection/immutable/Map;
  #487 = NameAndType        #485:#486     // toMap:(Lscala/$less$colon$less;)Lscala/collection/immutable/Map;
  #488 = InterfaceMethodref #262.#487     // scala/collection/IterableOnceOps.toMap:(Lscala/$less$colon$less;)Lscala/collection/immutable/Map;
  #489 = Utf8               scala/collection/immutable/Nil$
  #490 = Class              #489          // scala/collection/immutable/Nil$
  #491 = Utf8               Lscala/collection/immutable/Nil$;
  #492 = NameAndType        #40:#491      // MODULE$:Lscala/collection/immutable/Nil$;
  #493 = Fieldref           #490.#492     // scala/collection/immutable/Nil$.MODULE$:Lscala/collection/immutable/Nil$;
  #494 = NameAndType        #292:#293     // order$1:(Lscala/collection/immutable/Map;Lscala/collection/immutable/List;)Lscala/collection/immutable/List;
  #495 = Methodref          #2.#494       // coursier/core/Missing.order$1:(Lscala/collection/immutable/Map;Lscala/collection/immutable/List;)Lscala/collection/immutable/List;
  #496 = NameAndType        #397:#398     // $anonfun$next0$12:(Lcoursier/core/Resolution;Lscala/Tuple2;)Lcoursier/core/Resolution;
  #497 = Methodref          #2.#496       // coursier/core/Missing.$anonfun$next0$12:(Lcoursier/core/Resolution;Lscala/Tuple2;)Lcoursier/core/Resolution;
  #498 = MethodHandle       6:#497        // REF_invokeStatic coursier/core/Missing.$anonfun$next0$12:(Lcoursier/core/Resolution;Lscala/Tuple2;)Lcoursier/core/Resolution;
  #499 = MethodType         #398          //  (Lcoursier/core/Resolution;Lscala/Tuple2;)Lcoursier/core/Resolution;
  #500 = InvokeDynamic      #11:#361      // #11:apply:()Lscala/Function2;
  #501 = Methodref          #276.#367     // scala/collection/immutable/List.foldLeft:(Ljava/lang/Object;Lscala/Function2;)Ljava/lang/Object;
  #502 = Utf8               coursier/core/Continue$
  #503 = Class              #502          // coursier/core/Continue$
  #504 = Utf8               Lcoursier/core/Continue$;
  #505 = NameAndType        #40:#504      // MODULE$:Lcoursier/core/Continue$;
  #506 = Fieldref           #503.#505     // coursier/core/Continue$.MODULE$:Lcoursier/core/Continue$;
  #507 = Utf8               (Lcoursier/core/Resolution;Lscala/Function1;)Lcoursier/core/Continue;
  #508 = NameAndType        #35:#507      // apply:(Lcoursier/core/Resolution;Lscala/Function1;)Lcoursier/core/Continue;
  #509 = Methodref          #503.#508     // coursier/core/Continue$.apply:(Lcoursier/core/Resolution;Lscala/Function1;)Lcoursier/core/Continue;
  #510 = Utf8               toSeq
  #511 = NameAndType        #510:#46      // toSeq:()Lscala/collection/immutable/Seq;
  #512 = InterfaceMethodref #245.#511     // scala/collection/immutable/Set.toSeq:()Lscala/collection/immutable/Seq;
  #513 = NameAndType        #421:#422     // $anonfun$next0$13:(Lcoursier/core/Missing;Lscala/collection/immutable/Seq;Lcoursier/core/Resolution;)Lcoursier/core/ResolutionProcess;
  #514 = Methodref          #2.#513       // coursier/core/Missing.$anonfun$next0$13:(Lcoursier/core/Missing;Lscala/collection/immutable/Seq;Lcoursier/core/Resolution;)Lcoursier/core/ResolutionProcess;
  #515 = MethodHandle       6:#514        // REF_invokeStatic coursier/core/Missing.$anonfun$next0$13:(Lcoursier/core/Missing;Lscala/collection/immutable/Seq;Lcoursier/core/Resolution;)Lcoursier/core/ResolutionProcess;
  #516 = Utf8               (Lcoursier/core/Resolution;)Lcoursier/core/ResolutionProcess;
  #517 = MethodType         #516          //  (Lcoursier/core/Resolution;)Lcoursier/core/ResolutionProcess;
  #518 = Utf8               (Lcoursier/core/Missing;Lscala/collection/immutable/Seq;)Lscala/Function1;
  #519 = NameAndType        #35:#518      // apply:(Lcoursier/core/Missing;Lscala/collection/immutable/Seq;)Lscala/Function1;
  #520 = InvokeDynamic      #12:#519      // #12:apply:(Lcoursier/core/Missing;Lscala/collection/immutable/Seq;)Lscala/Function1;
  #521 = Utf8               orderedSuccesses
  #522 = Utf8               res0
  #523 = Utf8               remainingSuccesses
  #524 = Utf8               depMgmtMissing0
  #525 = Utf8               depMgmtMissing
  #526 = Utf8               (Lscala/collection/immutable/Seq<Lscala/Tuple2<Lcoursier/core/Module;Ljava/lang/String;>;>;Lcoursier/core/Resolution;Lscala/Function1<Lcoursier/core/Resolution;Lcoursier/core/ResolutionProcess;>;)V
  #527 = Utf8               ()V
  #528 = NameAndType        #63:#527      // "<init>":()V
  #529 = Methodref          #4.#528       // coursier/core/ResolutionProcess."<init>":()V
  #530 = NameAndType        #258:#259     // $anonfun$next0$6:(Lscala/Tuple2;)I
  #531 = Methodref          #2.#530       // coursier/core/Missing.$anonfun$next0$6:(Lscala/Tuple2;)I
  #532 = NameAndType        #266:#267     // $anonfun$next0$7:(ILscala/Tuple2;)Z
  #533 = Methodref          #2.#532       // coursier/core/Missing.$anonfun$next0$7:(ILscala/Tuple2;)Z
  #534 = Utf8               boxToBoolean
  #535 = Utf8               (Z)Ljava/lang/Boolean;
  #536 = NameAndType        #534:#535     // boxToBoolean:(Z)Ljava/lang/Boolean;
  #537 = Methodref          #173.#536     // scala/runtime/BoxesRunTime.boxToBoolean:(Z)Ljava/lang/Boolean;
  #538 = NameAndType        #185:#186     // $anonfun$next0$1:(Lcoursier/core/Resolution;Lscala/Tuple2;)Z
  #539 = Methodref          #2.#538       // coursier/core/Missing.$anonfun$next0$1:(Lcoursier/core/Resolution;Lscala/Tuple2;)Z
  #540 = Utf8               $deserializeLambda$
  #541 = Utf8               (Ljava/lang/invoke/SerializedLambda;)Ljava/lang/Object;
  #542 = Utf8               scala/runtime/LambdaDeserialize
  #543 = Class              #542          // scala/runtime/LambdaDeserialize
  #544 = Utf8               bootstrap
  #545 = Utf8               (Ljava/lang/invoke/MethodHandles$Lookup;Ljava/lang/String;Ljava/lang/invoke/MethodType;[Ljava/lang/invoke/MethodHandle;)Ljava/lang/invoke/CallSite;
  #546 = NameAndType        #544:#545     // bootstrap:(Ljava/lang/invoke/MethodHandles$Lookup;Ljava/lang/String;Ljava/lang/invoke/MethodType;[Ljava/lang/invoke/MethodHandle;)Ljava/lang/invoke/CallSite;
  #547 = Methodref          #543.#546     // scala/runtime/LambdaDeserialize.bootstrap:(Ljava/lang/invoke/MethodHandles$Lookup;Ljava/lang/String;Ljava/lang/invoke/MethodType;[Ljava/lang/invoke/MethodHandle;)Ljava/lang/invoke/CallSite;
  #548 = MethodHandle       6:#547        // REF_invokeStatic scala/runtime/LambdaDeserialize.bootstrap:(Ljava/lang/invoke/MethodHandles$Lookup;Ljava/lang/String;Ljava/lang/invoke/MethodType;[Ljava/lang/invoke/MethodHandle;)Ljava/lang/invoke/CallSite;
  #549 = Utf8               lambdaDeserialize
  #550 = NameAndType        #549:#541     // lambdaDeserialize:(Ljava/lang/invoke/SerializedLambda;)Ljava/lang/Object;
  #551 = InvokeDynamic      #13:#550      // #13:lambdaDeserialize:(Ljava/lang/invoke/SerializedLambda;)Ljava/lang/Object;
  #552 = Utf8               Signature
  #553 = Utf8               Code
  #554 = Utf8               MethodParameters
  #555 = Utf8               LineNumberTable
  #556 = Utf8               LocalVariableTable
  #557 = Utf8               StackMapTable
  #558 = Utf8               InnerClasses
  #559 = Utf8               SourceFile
  #560 = Utf8               RuntimeVisibleAnnotations
  #561 = Utf8               BootstrapMethods
  #562 = Utf8               ScalaInlineInfo
  #563 = Utf8               ScalaSig
{
  private final scala.collection.immutable.Seq<scala.Tuple2<coursier.core.Module, java.lang.String>> missing;
    descriptor: Lscala/collection/immutable/Seq;
    flags: (0x0012) ACC_PRIVATE, ACC_FINAL
    Signature: #29                          // Lscala/collection/immutable/Seq<Lscala/Tuple2<Lcoursier/core/Module;Ljava/lang/String;>;>;

  private final coursier.core.Resolution current;
    descriptor: Lcoursier/core/Resolution;
    flags: (0x0012) ACC_PRIVATE, ACC_FINAL

  private final scala.Function1<coursier.core.Resolution, coursier.core.ResolutionProcess> cont;
    descriptor: Lscala/Function1;
    flags: (0x0012) ACC_PRIVATE, ACC_FINAL
    Signature: #34                          // Lscala/Function1<Lcoursier/core/Resolution;Lcoursier/core/ResolutionProcess;>;

  public static coursier.core.Missing apply(scala.collection.immutable.Seq<scala.Tuple2<coursier.core.Module, java.lang.String>>, coursier.core.Resolution, scala.Function1<coursier.core.Resolution, coursier.core.ResolutionProcess>);
    descriptor: (Lscala/collection/immutable/Seq;Lcoursier/core/Resolution;Lscala/Function1;)Lcoursier/core/Missing;
    flags: (0x0009) ACC_PUBLIC, ACC_STATIC
    Code:
      stack=4, locals=3, args_size=3
         0: getstatic     #43                 // Field coursier/core/Missing$.MODULE$:Lcoursier/core/Missing$;
         3: aload_0
         4: aload_1
         5: aload_2
         6: invokevirtual #45                 // Method coursier/core/Missing$.apply:(Lscala/collection/immutable/Seq;Lcoursier/core/Resolution;Lscala/Function1;)Lcoursier/core/Missing;
         9: areturn
    Signature: #37                          // (Lscala/collection/immutable/Seq<Lscala/Tuple2<Lcoursier/core/Module;Ljava/lang/String;>;>;Lcoursier/core/Resolution;Lscala/Function1<Lcoursier/core/Resolution;Lcoursier/core/ResolutionProcess;>;)Lcoursier/core/Missing;
    MethodParameters:
      Name                           Flags
      missing                        final
      current                        final
      cont                           final

  public scala.collection.immutable.Seq<scala.Tuple2<coursier.core.Module, java.lang.String>> missing();
    descriptor: ()Lscala/collection/immutable/Seq;
    flags: (0x0001) ACC_PUBLIC
    Code:
      stack=1, locals=1, args_size=1
         0: aload_0
         1: getfield      #49                 // Field missing:Lscala/collection/immutable/Seq;
         4: areturn
      LineNumberTable:
        line 61: 0
      LocalVariableTable:
        Start  Length  Slot  Name   Signature
            0       5     0  this   Lcoursier/core/Missing;
    Signature: #47                          // ()Lscala/collection/immutable/Seq<Lscala/Tuple2<Lcoursier/core/Module;Ljava/lang/String;>;>;

  public coursier.core.Resolution current();
    descriptor: ()Lcoursier/core/Resolution;
    flags: (0x0001) ACC_PUBLIC
    Code:
      stack=1, locals=1, args_size=1
         0: aload_0
         1: getfield      #54                 // Field current:Lcoursier/core/Resolution;
         4: areturn
      LineNumberTable:
        line 61: 0
      LocalVariableTable:
        Start  Length  Slot  Name   Signature
            0       5     0  this   Lcoursier/core/Missing;

  public scala.Function1<coursier.core.Resolution, coursier.core.ResolutionProcess> cont();
    descriptor: ()Lscala/Function1;
    flags: (0x0001) ACC_PUBLIC
    Code:
      stack=1, locals=1, args_size=1
         0: aload_0
         1: getfield      #58                 // Field cont:Lscala/Function1;
         4: areturn
      LineNumberTable:
        line 61: 0
      LocalVariableTable:
        Start  Length  Slot  Name   Signature
            0       5     0  this   Lcoursier/core/Missing;
    Signature: #56                          // ()Lscala/Function1<Lcoursier/core/Resolution;Lcoursier/core/ResolutionProcess;>;

  public coursier.core.ResolutionProcess next0(scala.collection.immutable.Seq<scala.Tuple2<scala.Tuple2<coursier.core.Module, java.lang.String>, scala.util.Either<scala.collection.immutable.Seq<java.lang.String>, scala.Tuple2<coursier.core.ArtifactSource, coursier.core.Project>>>>);
    descriptor: (Lscala/collection/immutable/Seq;)Lcoursier/core/ResolutionProcess;
    flags: (0x0001) ACC_PUBLIC
    Code:
      stack=4, locals=5, args_size=2
         0: aload_1
         1: new           #10                 // class coursier/core/Missing$$anonfun$1
         4: dup
         5: aconst_null
         6: invokespecial #66                 // Method coursier/core/Missing$$anonfun$1."<init>":(Lcoursier/core/Missing;)V
         9: invokeinterface #72,  2           // InterfaceMethod scala/collection/immutable/Seq.collect:(Lscala/PartialFunction;)Ljava/lang/Object;
        14: checkcast     #68                 // class scala/collection/immutable/Seq
        17: astore_2
        18: aload_1
        19: new           #12                 // class coursier/core/Missing$$anonfun$2
        22: dup
        23: aconst_null
        24: invokespecial #73                 // Method coursier/core/Missing$$anonfun$2."<init>":(Lcoursier/core/Missing;)V
        27: invokeinterface #72,  2           // InterfaceMethod scala/collection/immutable/Seq.collect:(Lscala/PartialFunction;)Ljava/lang/Object;
        32: checkcast     #68                 // class scala/collection/immutable/Seq
        35: astore_3
        36: aload_0
        37: invokevirtual #75                 // Method current:()Lcoursier/core/Resolution;
        40: aload_2
        41: invokevirtual #81                 // Method coursier/core/Resolution.addToErrorCache:(Lscala/collection/Iterable;)Lcoursier/core/Resolution;
        44: astore        4
        46: aload_0
        47: aload         4
        49: aload_3
        50: invokespecial #85                 // Method cont0$1:(Lcoursier/core/Resolution;Lscala/collection/immutable/Seq;)Lcoursier/core/ResolutionProcess;
        53: areturn
      LineNumberTable:
        line 69: 0
        line 73: 18
        line 129: 36
        line 131: 46
      LocalVariableTable:
        Start  Length  Slot  Name   Signature
           18      35     2 errors   Lscala/collection/immutable/Seq;
           36      17     3 successes   Lscala/collection/immutable/Seq;
           46       7     4 current0   Lcoursier/core/Resolution;
            0      54     0  this   Lcoursier/core/Missing;
            0      54     1 results   Lscala/collection/immutable/Seq;
    Signature: #61                          // (Lscala/collection/immutable/Seq<Lscala/Tuple2<Lscala/Tuple2<Lcoursier/core/Module;Ljava/lang/String;>;Lscala/util/Either<Lscala/collection/immutable/Seq<Ljava/lang/String;>;Lscala/Tuple2<Lcoursier/core/ArtifactSource;Lcoursier/core/Project;>;>;>;>;)Lcoursier/core/ResolutionProcess;
    MethodParameters:
      Name                           Flags
      results                        final

  public coursier.core.Missing withMissing(scala.collection.immutable.Seq<scala.Tuple2<coursier.core.Module, java.lang.String>>);
    descriptor: (Lscala/collection/immutable/Seq;)Lcoursier/core/Missing;
    flags: (0x0001) ACC_PUBLIC
    Code:
      stack=5, locals=2, args_size=2
         0: new           #2                  // class coursier/core/Missing
         3: dup
         4: aload_1
         5: aload_0
         6: invokevirtual #75                 // Method current:()Lcoursier/core/Resolution;
         9: aload_0
        10: invokevirtual #93                 // Method cont:()Lscala/Function1;
        13: invokespecial #96                 // Method "<init>":(Lscala/collection/immutable/Seq;Lcoursier/core/Resolution;Lscala/Function1;)V
        16: areturn
      LineNumberTable:
        line 61: 0
      LocalVariableTable:
        Start  Length  Slot  Name   Signature
            0      17     0  this   Lcoursier/core/Missing;
            0      17     1 missing   Lscala/collection/immutable/Seq;
    Signature: #91                          // (Lscala/collection/immutable/Seq<Lscala/Tuple2<Lcoursier/core/Module;Ljava/lang/String;>;>;)Lcoursier/core/Missing;
    MethodParameters:
      Name                           Flags
      missing                        final

  public coursier.core.Missing withCurrent(coursier.core.Resolution);
    descriptor: (Lcoursier/core/Resolution;)Lcoursier/core/Missing;
    flags: (0x0001) ACC_PUBLIC
    Code:
      stack=5, locals=2, args_size=2
         0: new           #2                  // class coursier/core/Missing
         3: dup
         4: aload_0
         5: invokevirtual #100                // Method missing:()Lscala/collection/immutable/Seq;
         8: aload_1
         9: aload_0
        10: invokevirtual #93                 // Method cont:()Lscala/Function1;
        13: invokespecial #96                 // Method "<init>":(Lscala/collection/immutable/Seq;Lcoursier/core/Resolution;Lscala/Function1;)V
        16: areturn
      LineNumberTable:
        line 61: 0
      LocalVariableTable:
        Start  Length  Slot  Name   Signature
            0      17     0  this   Lcoursier/core/Missing;
            0      17     1 current   Lcoursier/core/Resolution;
    MethodParameters:
      Name                           Flags
      current                        final

  public coursier.core.Missing withCont(scala.Function1<coursier.core.Resolution, coursier.core.ResolutionProcess>);
    descriptor: (Lscala/Function1;)Lcoursier/core/Missing;
    flags: (0x0001) ACC_PUBLIC
    Code:
      stack=5, locals=2, args_size=2
         0: new           #2                  // class coursier/core/Missing
         3: dup
         4: aload_0
         5: invokevirtual #100                // Method missing:()Lscala/collection/immutable/Seq;
         8: aload_0
         9: invokevirtual #75                 // Method current:()Lcoursier/core/Resolution;
        12: aload_1
        13: invokespecial #96                 // Method "<init>":(Lscala/collection/immutable/Seq;Lcoursier/core/Resolution;Lscala/Function1;)V
        16: areturn
      LineNumberTable:
        line 61: 0
      LocalVariableTable:
        Start  Length  Slot  Name   Signature
            0      17     0  this   Lcoursier/core/Missing;
            0      17     1  cont   Lscala/Function1;
    Signature: #103                         // (Lscala/Function1<Lcoursier/core/Resolution;Lcoursier/core/ResolutionProcess;>;)Lcoursier/core/Missing;
    MethodParameters:
      Name                           Flags
      cont                           final

  public java.lang.String toString();
    descriptor: ()Ljava/lang/String;
    flags: (0x0001) ACC_PUBLIC
    Code:
      stack=3, locals=2, args_size=1
         0: new           #107                // class java/lang/StringBuilder
         3: dup
         4: ldc           #109                // String Missing(
         6: invokespecial #112                // Method java/lang/StringBuilder."<init>":(Ljava/lang/String;)V
         9: astore_1
        10: aload_1
        11: aload_0
        12: invokevirtual #100                // Method missing:()Lscala/collection/immutable/Seq;
        15: invokestatic  #118                // Method java/lang/String.valueOf:(Ljava/lang/Object;)Ljava/lang/String;
        18: invokevirtual #122                // Method java/lang/StringBuilder.append:(Ljava/lang/String;)Ljava/lang/StringBuilder;
        21: pop
        22: aload_1
        23: ldc           #124                // String ,
        25: invokevirtual #122                // Method java/lang/StringBuilder.append:(Ljava/lang/String;)Ljava/lang/StringBuilder;
        28: pop
        29: aload_1
        30: aload_0
        31: invokevirtual #75                 // Method current:()Lcoursier/core/Resolution;
        34: invokestatic  #118                // Method java/lang/String.valueOf:(Ljava/lang/Object;)Ljava/lang/String;
        37: invokevirtual #122                // Method java/lang/StringBuilder.append:(Ljava/lang/String;)Ljava/lang/StringBuilder;
        40: pop
        41: aload_1
        42: ldc           #124                // String ,
        44: invokevirtual #122                // Method java/lang/StringBuilder.append:(Ljava/lang/String;)Ljava/lang/StringBuilder;
        47: pop
        48: aload_1
        49: aload_0
        50: invokevirtual #93                 // Method cont:()Lscala/Function1;
        53: invokestatic  #118                // Method java/lang/String.valueOf:(Ljava/lang/Object;)Ljava/lang/String;
        56: invokevirtual #122                // Method java/lang/StringBuilder.append:(Ljava/lang/String;)Ljava/lang/StringBuilder;
        59: pop
        60: aload_1
        61: ldc           #126                // String )
        63: invokevirtual #122                // Method java/lang/StringBuilder.append:(Ljava/lang/String;)Ljava/lang/StringBuilder;
        66: pop
        67: aload_1
        68: invokevirtual #128                // Method java/lang/StringBuilder.toString:()Ljava/lang/String;
        71: areturn
      LineNumberTable:
        line 61: 0
      LocalVariableTable:
        Start  Length  Slot  Name   Signature
           10      61     1     b   Ljava/lang/StringBuilder;
            0      72     0  this   Lcoursier/core/Missing;

  public boolean canEqual(java.lang.Object);
    descriptor: (Ljava/lang/Object;)Z
    flags: (0x0001) ACC_PUBLIC
    Code:
      stack=1, locals=2, args_size=2
         0: aload_1
         1: ifnull        15
         4: aload_1
         5: instanceof    #2                  // class coursier/core/Missing
         8: ifeq          15
        11: iconst_1
        12: goto          16
        15: iconst_0
        16: ireturn
      StackMapTable: number_of_entries = 2
        frame_type = 15 /* same */
        frame_type = 64 /* same_locals_1_stack_item */
          stack = [ int ]
      LineNumberTable:
        line 61: 0
      LocalVariableTable:
        Start  Length  Slot  Name   Signature
            0      17     0  this   Lcoursier/core/Missing;
            0      17     1   obj   Ljava/lang/Object;
    MethodParameters:
      Name                           Flags
      obj                            final

  public boolean equals(java.lang.Object);
    descriptor: (Ljava/lang/Object;)Z
    flags: (0x0001) ACC_PUBLIC
    Code:
      stack=2, locals=6, args_size=2
         0: aload_0
         1: aload_1
         2: if_acmpeq     120
         5: aload_0
         6: aload_1
         7: invokevirtual #137                // Method canEqual:(Ljava/lang/Object;)Z
        10: ifeq          124
        13: aload_1
        14: checkcast     #2                  // class coursier/core/Missing
        17: astore_2
        18: iconst_1
        19: ifeq          116
        22: aload_0
        23: invokevirtual #100                // Method missing:()Lscala/collection/immutable/Seq;
        26: aload_2
        27: invokevirtual #100                // Method missing:()Lscala/collection/immutable/Seq;
        30: astore_3
        31: dup
        32: ifnonnull     43
        35: pop
        36: aload_3
        37: ifnull        50
        40: goto          116
        43: aload_3
        44: invokevirtual #141                // Method java/lang/Object.equals:(Ljava/lang/Object;)Z
        47: ifeq          116
        50: aload_0
        51: invokevirtual #75                 // Method current:()Lcoursier/core/Resolution;
        54: aload_2
        55: invokevirtual #75                 // Method current:()Lcoursier/core/Resolution;
        58: astore        4
        60: dup
        61: ifnonnull     73
        64: pop
        65: aload         4
        67: ifnull        81
        70: goto          116
        73: aload         4
        75: invokevirtual #141                // Method java/lang/Object.equals:(Ljava/lang/Object;)Z
        78: ifeq          116
        81: aload_0
        82: invokevirtual #93                 // Method cont:()Lscala/Function1;
        85: aload_2
        86: invokevirtual #93                 // Method cont:()Lscala/Function1;
        89: astore        5
        91: dup
        92: ifnonnull     104
        95: pop
        96: aload         5
        98: ifnull        112
       101: goto          116
       104: aload         5
       106: invokevirtual #141                // Method java/lang/Object.equals:(Ljava/lang/Object;)Z
       109: ifeq          116
       112: iconst_1
       113: goto          117
       116: iconst_0
       117: ifeq          124
       120: iconst_1
       121: goto          125
       124: iconst_0
       125: ireturn
      StackMapTable: number_of_entries = 11
        frame_type = 255 /* full_frame */
          offset_delta = 43
          locals = [ class coursier/core/Missing, class java/lang/Object, class coursier/core/Missing, class scala/collection/immutable/Seq ]
          stack = [ class scala/collection/immutable/Seq ]
        frame_type = 6 /* same */
        frame_type = 255 /* full_frame */
          offset_delta = 22
          locals = [ class coursier/core/Missing, class java/lang/Object, class coursier/core/Missing, class scala/collection/immutable/Seq, class coursier/core/Resolution ]
          stack = [ class coursier/core/Resolution ]
        frame_type = 7 /* same */
        frame_type = 255 /* full_frame */
          offset_delta = 22
          locals = [ class coursier/core/Missing, class java/lang/Object, class coursier/core/Missing, class scala/collection/immutable/Seq, class coursier/core/Resolution, class scala/Function1 ]
          stack = [ class scala/Function1 ]
        frame_type = 7 /* same */
        frame_type = 248 /* chop */
          offset_delta = 3
        frame_type = 64 /* same_locals_1_stack_item */
          stack = [ int ]
        frame_type = 250 /* chop */
          offset_delta = 2
        frame_type = 3 /* same */
        frame_type = 64 /* same_locals_1_stack_item */
          stack = [ int ]
      LineNumberTable:
        line 61: 0
      LocalVariableTable:
        Start  Length  Slot  Name   Signature
           18      99     2 other   Lcoursier/core/Missing;
            0     126     0  this   Lcoursier/core/Missing;
            0     126     1   obj   Ljava/lang/Object;
    MethodParameters:
      Name                           Flags
      obj                            final

  public int hashCode();
    descriptor: ()I
    flags: (0x0001) ACC_PUBLIC
    Code:
      stack=2, locals=2, args_size=1
         0: bipush        17
         2: ldc           #148                // String Missing
         4: invokestatic  #154                // Method scala/runtime/Statics.anyHash:(Ljava/lang/Object;)I
         7: iadd
         8: istore_1
         9: bipush        37
        11: iload_1
        12: imul
        13: aload_0
        14: invokevirtual #100                // Method missing:()Lscala/collection/immutable/Seq;
        17: invokestatic  #154                // Method scala/runtime/Statics.anyHash:(Ljava/lang/Object;)I
        20: iadd
        21: istore_1
        22: bipush        37
        24: iload_1
        25: imul
        26: aload_0
        27: invokevirtual #75                 // Method current:()Lcoursier/core/Resolution;
        30: invokestatic  #154                // Method scala/runtime/Statics.anyHash:(Ljava/lang/Object;)I
        33: iadd
        34: istore_1
        35: bipush        37
        37: iload_1
        38: imul
        39: aload_0
        40: invokevirtual #93                 // Method cont:()Lscala/Function1;
        43: invokestatic  #154                // Method scala/runtime/Statics.anyHash:(Ljava/lang/Object;)I
        46: iadd
        47: istore_1
        48: bipush        37
        50: iload_1
        51: imul
        52: ireturn
      LineNumberTable:
        line 61: 0
      LocalVariableTable:
        Start  Length  Slot  Name   Signature
            9      43     1  code   I
            0      53     0  this   Lcoursier/core/Missing;

  private scala.Tuple3<scala.collection.immutable.Seq<scala.Tuple2<coursier.core.Module, java.lang.String>>, coursier.core.Resolution, scala.Function1<coursier.core.Resolution, coursier.core.ResolutionProcess>> tuple();
    descriptor: ()Lscala/Tuple3;
    flags: (0x0002) ACC_PRIVATE
    Code:
      stack=5, locals=1, args_size=1
         0: new           #161                // class scala/Tuple3
         3: dup
         4: aload_0
         5: invokevirtual #100                // Method missing:()Lscala/collection/immutable/Seq;
         8: aload_0
         9: invokevirtual #75                 // Method current:()Lcoursier/core/Resolution;
        12: aload_0
        13: invokevirtual #93                 // Method cont:()Lscala/Function1;
        16: invokespecial #164                // Method scala/Tuple3."<init>":(Ljava/lang/Object;Ljava/lang/Object;Ljava/lang/Object;)V
        19: areturn
      LineNumberTable:
        line 61: 0
      LocalVariableTable:
        Start  Length  Slot  Name   Signature
            0      20     0  this   Lcoursier/core/Missing;
    Signature: #159                         // ()Lscala/Tuple3<Lscala/collection/immutable/Seq<Lscala/Tuple2<Lcoursier/core/Module;Ljava/lang/String;>;>;Lcoursier/core/Resolution;Lscala/Function1<Lcoursier/core/Resolution;Lcoursier/core/ResolutionProcess;>;>;

  public java.lang.String productPrefix();
    descriptor: ()Ljava/lang/String;
    flags: (0x0001) ACC_PUBLIC
    Code:
      stack=1, locals=1, args_size=1
         0: ldc           #148                // String Missing
         2: areturn
      LineNumberTable:
        line 61: 0
      LocalVariableTable:
        Start  Length  Slot  Name   Signature
            0       3     0  this   Lcoursier/core/Missing;

  public int productArity();
    descriptor: ()I
    flags: (0x0001) ACC_PUBLIC
    Code:
      stack=1, locals=1, args_size=1
         0: iconst_3
         1: ireturn
      LineNumberTable:
        line 61: 0
      LocalVariableTable:
        Start  Length  Slot  Name   Signature
            0       2     0  this   Lcoursier/core/Missing;

  public java.lang.Object productElement(int);
    descriptor: (I)Ljava/lang/Object;
    flags: (0x0001) ACC_PUBLIC
    Code:
      stack=3, locals=3, args_size=2
         0: iload_1
         1: istore_2
         2: iload_2
         3: tableswitch   { // 0 to 2
                       0: 28
                       1: 35
                       2: 42
                 default: 49
            }
        28: aload_0
        29: invokevirtual #100                // Method missing:()Lscala/collection/immutable/Seq;
        32: goto          64
        35: aload_0
        36: invokevirtual #75                 // Method current:()Lcoursier/core/Resolution;
        39: goto          64
        42: aload_0
        43: invokevirtual #93                 // Method cont:()Lscala/Function1;
        46: goto          64
        49: new           #171                // class java/lang/IndexOutOfBoundsException
        52: dup
        53: iload_2
        54: invokestatic  #177                // Method scala/runtime/BoxesRunTime.boxToInteger:(I)Ljava/lang/Integer;
        57: invokevirtual #178                // Method java/lang/Object.toString:()Ljava/lang/String;
        60: invokespecial #179                // Method java/lang/IndexOutOfBoundsException."<init>":(Ljava/lang/String;)V
        63: athrow
        64: areturn
      StackMapTable: number_of_entries = 5
        frame_type = 252 /* append */
          offset_delta = 28
          locals = [ int ]
        frame_type = 6 /* same */
        frame_type = 6 /* same */
        frame_type = 6 /* same */
        frame_type = 78 /* same_locals_1_stack_item */
          stack = [ class java/lang/Object ]
      LineNumberTable:
        line 61: 0
      LocalVariableTable:
        Start  Length  Slot  Name   Signature
            0      65     0  this   Lcoursier/core/Missing;
            0      65     1     n   I
    MethodParameters:
      Name                           Flags
      n                              final

  public java.lang.String productElementName(int);
    descriptor: (I)Ljava/lang/String;
    flags: (0x0001) ACC_PUBLIC
    Code:
      stack=3, locals=3, args_size=2
         0: iload_1
         1: istore_2
         2: iload_2
         3: tableswitch   { // 0 to 2
                       0: 28
                       1: 33
                       2: 38
                 default: 43
            }
        28: ldc           #182                // String missing
        30: goto          58
        33: ldc           #183                // String current
        35: goto          58
        38: ldc           #184                // String cont
        40: goto          58
        43: new           #171                // class java/lang/IndexOutOfBoundsException
        46: dup
        47: iload_2
        48: invokestatic  #177                // Method scala/runtime/BoxesRunTime.boxToInteger:(I)Ljava/lang/Integer;
        51: invokevirtual #178                // Method java/lang/Object.toString:()Ljava/lang/String;
        54: invokespecial #179                // Method java/lang/IndexOutOfBoundsException."<init>":(Ljava/lang/String;)V
        57: athrow
        58: areturn
      StackMapTable: number_of_entries = 5
        frame_type = 252 /* append */
          offset_delta = 28
          locals = [ int ]
        frame_type = 4 /* same */
        frame_type = 4 /* same */
        frame_type = 4 /* same */
        frame_type = 78 /* same_locals_1_stack_item */
          stack = [ class java/lang/String ]
      LineNumberTable:
        line 61: 0
      LocalVariableTable:
        Start  Length  Slot  Name   Signature
            0      59     0  this   Lcoursier/core/Missing;
            0      59     1     n   I
    MethodParameters:
      Name                           Flags
      n                              final

  public static final boolean $anonfun$next0$1(coursier.core.Resolution, scala.Tuple2);
    descriptor: (Lcoursier/core/Resolution;Lscala/Tuple2;)Z
    flags: (0x1019) ACC_PUBLIC, ACC_STATIC, ACC_FINAL, ACC_SYNTHETIC
    Code:
      stack=3, locals=5, args_size=2
         0: aload_1
         1: astore_3
         2: aload_3
         3: ifnull        38
         6: aload_3
         7: invokevirtual #194                // Method scala/Tuple2._1:()Ljava/lang/Object;
        10: checkcast     #190                // class scala/Tuple2
        13: astore        4
        15: aload_0
        16: invokevirtual #198                // Method coursier/core/Resolution.projectCache:()Lscala/collection/immutable/Map;
        19: aload         4
        21: invokeinterface #203,  2          // InterfaceMethod scala/collection/immutable/Map.contains:(Ljava/lang/Object;)Z
        26: ifne          33
        29: iconst_1
        30: goto          34
        33: iconst_0
        34: istore_2
        35: goto          50
        38: goto          41
        41: new           #205                // class scala/MatchError
        44: dup
        45: aload_3
        46: invokespecial #208                // Method scala/MatchError."<init>":(Ljava/lang/Object;)V
        49: athrow
        50: iload_2
        51: ireturn
      StackMapTable: number_of_entries = 5
        frame_type = 254 /* append */
          offset_delta = 33
          locals = [ top, class scala/Tuple2, class scala/Tuple2 ]
        frame_type = 64 /* same_locals_1_stack_item */
          stack = [ int ]
        frame_type = 250 /* chop */
          offset_delta = 3
        frame_type = 2 /* same */
        frame_type = 255 /* full_frame */
          offset_delta = 8
          locals = [ class coursier/core/Resolution, class scala/Tuple2, int, class scala/Tuple2, class scala/Tuple2 ]
          stack = []
      LineNumberTable:
        line 80: 0
        line 81: 2
        line 82: 15
        line 81: 38
        line 80: 41
      LocalVariableTable:
        Start  Length  Slot  Name   Signature
           15      23     4 modVer   Lscala/Tuple2;
            0      52     0 res$1   Lcoursier/core/Resolution;
            0      52     1  x0$1   Lscala/Tuple2;
    MethodParameters:
      Name                           Flags
      res$1                          final
      x0$1                           final

  public static final scala.Tuple2 $anonfun$next0$2(coursier.core.Resolution, scala.Tuple2);
    descriptor: (Lcoursier/core/Resolution;Lscala/Tuple2;)Lscala/Tuple2;
    flags: (0x1019) ACC_PUBLIC, ACC_STATIC, ACC_FINAL, ACC_SYNTHETIC
    Code:
      stack=4, locals=6, args_size=2
         0: aload_1
         1: astore_3
         2: aload_3
         3: ifnull        56
         6: aload_3
         7: invokevirtual #216                // Method scala/Tuple2._2:()Ljava/lang/Object;
        10: checkcast     #190                // class scala/Tuple2
        13: astore        4
        15: aload         4
        17: ifnull        53
        20: aload         4
        22: invokevirtual #216                // Method scala/Tuple2._2:()Ljava/lang/Object;
        25: checkcast     #218                // class coursier/core/Project
        28: astore        5
        30: getstatic     #221                // Field scala/Predef$ArrowAssoc$.MODULE$:Lscala/Predef$ArrowAssoc$;
        33: getstatic     #226                // Field scala/Predef$.MODULE$:Lscala/Predef$;
        36: aload_3
        37: invokevirtual #230                // Method scala/Predef$.ArrowAssoc:(Ljava/lang/Object;)Ljava/lang/Object;
        40: aload_0
        41: aload         5
        43: invokevirtual #234                // Method coursier/core/Resolution.dependencyManagementMissing:(Lcoursier/core/Project;)Lscala/collection/immutable/Set;
        46: invokevirtual #238                // Method scala/Predef$ArrowAssoc$.$minus$greater$extension:(Ljava/lang/Object;Ljava/lang/Object;)Lscala/Tuple2;
        49: astore_2
        50: goto          68
        53: goto          59
        56: goto          59
        59: new           #205                // class scala/MatchError
        62: dup
        63: aload_3
        64: invokespecial #208                // Method scala/MatchError."<init>":(Ljava/lang/Object;)V
        67: athrow
        68: aload_2
        69: areturn
      StackMapTable: number_of_entries = 4
        frame_type = 254 /* append */
          offset_delta = 53
          locals = [ top, class scala/Tuple2, class scala/Tuple2 ]
        frame_type = 250 /* chop */
          offset_delta = 2
        frame_type = 2 /* same */
        frame_type = 255 /* full_frame */
          offset_delta = 8
          locals = [ class coursier/core/Resolution, class scala/Tuple2, class scala/Tuple2, class scala/Tuple2, class scala/Tuple2, class coursier/core/Project ]
          stack = []
      LineNumberTable:
        line 85: 0
        line 86: 2
        line 87: 30
        line 86: 53
        line 85: 59
      LocalVariableTable:
        Start  Length  Slot  Name   Signature
           30      23     5  proj   Lcoursier/core/Project;
            0      70     0 res$1   Lcoursier/core/Resolution;
            0      70     1  x0$2   Lscala/Tuple2;
    MethodParameters:
      Name                           Flags
      res$1                          final
      x0$2                           final

  public static final scala.collection.immutable.Set $anonfun$next0$3(scala.Tuple2);
    descriptor: (Lscala/Tuple2;)Lscala/collection/immutable/Set;
    flags: (0x1019) ACC_PUBLIC, ACC_STATIC, ACC_FINAL, ACC_SYNTHETIC
    Code:
      stack=1, locals=1, args_size=1
         0: aload_0
         1: invokevirtual #216                // Method scala/Tuple2._2:()Ljava/lang/Object;
         4: checkcast     #245                // class scala/collection/immutable/Set
         7: areturn
      LineNumberTable:
        line 90: 0
      LocalVariableTable:
        Start  Length  Slot  Name   Signature
            0       8     0   x$1   Lscala/Tuple2;
    MethodParameters:
      Name                           Flags
      x$1                            final

  public static final scala.collection.immutable.Set $anonfun$next0$4(scala.collection.immutable.Set, scala.collection.immutable.Set);
    descriptor: (Lscala/collection/immutable/Set;Lscala/collection/immutable/Set;)Lscala/collection/immutable/Set;
    flags: (0x1019) ACC_PUBLIC, ACC_STATIC, ACC_FINAL, ACC_SYNTHETIC
    Code:
      stack=2, locals=2, args_size=2
         0: aload_0
         1: aload_1
         2: invokeinterface #253,  2          // InterfaceMethod scala/collection/immutable/Set.$plus$plus:(Lscala/collection/IterableOnce;)Lscala/collection/SetOps;
         7: checkcast     #245                // class scala/collection/immutable/Set
        10: areturn
      LineNumberTable:
        line 90: 0
      LocalVariableTable:
        Start  Length  Slot  Name   Signature
            0      11     0   x$2   Lscala/collection/immutable/Set;
            0      11     1   x$3   Lscala/collection/immutable/Set;
    MethodParameters:
      Name                           Flags
      x$2                            final
      x$3                            final

  public static final scala.Tuple2 $anonfun$next0$5(scala.Tuple2);
    descriptor: (Lscala/Tuple2;)Lscala/Tuple2;
    flags: (0x1019) ACC_PUBLIC, ACC_STATIC, ACC_FINAL, ACC_SYNTHETIC
    Code:
      stack=1, locals=1, args_size=1
         0: aload_0
         1: invokevirtual #194                // Method scala/Tuple2._1:()Ljava/lang/Object;
         4: checkcast     #190                // class scala/Tuple2
         7: invokevirtual #194                // Method scala/Tuple2._1:()Ljava/lang/Object;
        10: checkcast     #190                // class scala/Tuple2
        13: areturn
      LineNumberTable:
        line 95: 0
      LocalVariableTable:
        Start  Length  Slot  Name   Signature
            0      14     0   x$4   Lscala/Tuple2;
    MethodParameters:
      Name                           Flags
      x$4                            final

  public static final int $anonfun$next0$6(scala.Tuple2);
    descriptor: (Lscala/Tuple2;)I
    flags: (0x1019) ACC_PUBLIC, ACC_STATIC, ACC_FINAL, ACC_SYNTHETIC
    Code:
      stack=1, locals=1, args_size=1
         0: aload_0
         1: invokevirtual #216                // Method scala/Tuple2._2:()Ljava/lang/Object;
         4: checkcast     #262                // class scala/collection/IterableOnceOps
         7: invokeinterface #265,  1          // InterfaceMethod scala/collection/IterableOnceOps.size:()I
        12: ireturn
      LineNumberTable:
        line 102: 0
      LocalVariableTable:
        Start  Length  Slot  Name   Signature
            0      13     0   x$5   Lscala/Tuple2;
    MethodParameters:
      Name                           Flags
      x$5                            final

  public static final boolean $anonfun$next0$7(int, scala.Tuple2);
    descriptor: (ILscala/Tuple2;)Z
    flags: (0x1019) ACC_PUBLIC, ACC_STATIC, ACC_FINAL, ACC_SYNTHETIC
    Code:
      stack=3, locals=5, args_size=2
         0: aload_1
         1: astore_3
         2: aload_3
         3: ifnull        35
         6: aload_3
         7: invokevirtual #216                // Method scala/Tuple2._2:()Ljava/lang/Object;
        10: checkcast     #245                // class scala/collection/immutable/Set
        13: astore        4
        15: aload         4
        17: invokeinterface #269,  1          // InterfaceMethod scala/collection/immutable/Set.size:()I
        22: iload_0
        23: if_icmpne     30
        26: iconst_1
        27: goto          31
        30: iconst_0
        31: istore_2
        32: goto          47
        35: goto          38
        38: new           #205                // class scala/MatchError
        41: dup
        42: aload_3
        43: invokespecial #208                // Method scala/MatchError."<init>":(Ljava/lang/Object;)V
        46: athrow
        47: iload_2
        48: ireturn
      StackMapTable: number_of_entries = 5
        frame_type = 254 /* append */
          offset_delta = 30
          locals = [ top, class scala/Tuple2, class scala/collection/immutable/Set ]
        frame_type = 64 /* same_locals_1_stack_item */
          stack = [ int ]
        frame_type = 250 /* chop */
          offset_delta = 3
        frame_type = 2 /* same */
        frame_type = 255 /* full_frame */
          offset_delta = 8
          locals = [ int, class scala/Tuple2, int, class scala/Tuple2, class scala/collection/immutable/Set ]
          stack = []
      LineNumberTable:
        line 103: 0
        line 104: 2
        line 103: 38
      LocalVariableTable:
        Start  Length  Slot  Name   Signature
           15      20     4     v   Lscala/collection/immutable/Set;
            0      49     0 min$1   I
            0      49     1  x0$1   Lscala/Tuple2;
    MethodParameters:
      Name                           Flags
      min$1                          final
      x0$1                           final

  public static final scala.collection.immutable.List $anonfun$next0$8(scala.collection.immutable.List, scala.Tuple2);
    descriptor: (Lscala/collection/immutable/List;Lscala/Tuple2;)Lscala/collection/immutable/List;
    flags: (0x1019) ACC_PUBLIC, ACC_STATIC, ACC_FINAL, ACC_SYNTHETIC
    Code:
      stack=2, locals=2, args_size=2
         0: aload_0
         1: aload_1
         2: invokevirtual #280                // Method scala/collection/immutable/List.$colon$colon:(Ljava/lang/Object;)Lscala/collection/immutable/List;
         5: areturn
      LineNumberTable:
        line 106: 0
      LocalVariableTable:
        Start  Length  Slot  Name   Signature
            0       6     0   x$7   Lscala/collection/immutable/List;
            0       6     1   x$8   Lscala/Tuple2;
    MethodParameters:
      Name                           Flags
      x$7                            final
      x$8                            final

  public static final scala.Tuple2 $anonfun$next0$9(scala.Tuple2);
    descriptor: (Lscala/Tuple2;)Lscala/Tuple2;
    flags: (0x1019) ACC_PUBLIC, ACC_STATIC, ACC_FINAL, ACC_SYNTHETIC
    Code:
      stack=1, locals=1, args_size=1
         0: aload_0
         1: invokevirtual #194                // Method scala/Tuple2._1:()Ljava/lang/Object;
         4: checkcast     #190                // class scala/Tuple2
         7: areturn
      LineNumberTable:
        line 107: 0
      LocalVariableTable:
        Start  Length  Slot  Name   Signature
            0       8     0   x$9   Lscala/Tuple2;
    MethodParameters:
      Name                           Flags
      x$9                            final

  public static final scala.Tuple2 $anonfun$next0$10(scala.collection.immutable.Set, scala.Tuple2);
    descriptor: (Lscala/collection/immutable/Set;Lscala/Tuple2;)Lscala/Tuple2;
    flags: (0x1019) ACC_PUBLIC, ACC_STATIC, ACC_FINAL, ACC_SYNTHETIC
    Code:
      stack=4, locals=6, args_size=2
         0: aload_1
         1: astore_3
         2: aload_3
         3: ifnull        50
         6: aload_3
         7: invokevirtual #194                // Method scala/Tuple2._1:()Ljava/lang/Object;
        10: checkcast     #190                // class scala/Tuple2
        13: astore        4
        15: aload_3
        16: invokevirtual #216                // Method scala/Tuple2._2:()Ljava/lang/Object;
        19: checkcast     #245                // class scala/collection/immutable/Set
        22: astore        5
        24: getstatic     #221                // Field scala/Predef$ArrowAssoc$.MODULE$:Lscala/Predef$ArrowAssoc$;
        27: getstatic     #226                // Field scala/Predef$.MODULE$:Lscala/Predef$;
        30: aload         4
        32: invokevirtual #230                // Method scala/Predef$.ArrowAssoc:(Ljava/lang/Object;)Ljava/lang/Object;
        35: aload         5
        37: aload_0
        38: invokeinterface #290,  2          // InterfaceMethod scala/collection/immutable/Set.intersect:(Lscala/collection/Set;)Lscala/collection/SetOps;
        43: invokevirtual #238                // Method scala/Predef$ArrowAssoc$.$minus$greater$extension:(Ljava/lang/Object;Ljava/lang/Object;)Lscala/Tuple2;
        46: astore_2
        47: goto          62
        50: goto          53
        53: new           #205                // class scala/MatchError
        56: dup
        57: aload_3
        58: invokespecial #208                // Method scala/MatchError."<init>":(Ljava/lang/Object;)V
        61: athrow
        62: aload_2
        63: areturn
      StackMapTable: number_of_entries = 3
        frame_type = 253 /* append */
          offset_delta = 50
          locals = [ top, class scala/Tuple2 ]
        frame_type = 2 /* same */
        frame_type = 255 /* full_frame */
          offset_delta = 8
          locals = [ class scala/collection/immutable/Set, class scala/Tuple2, class scala/Tuple2, class scala/Tuple2, class scala/Tuple2, class scala/collection/immutable/Set ]
          stack = []
      LineNumberTable:
        line 108: 0
        line 109: 2
        line 110: 24
        line 109: 50
        line 108: 53
      LocalVariableTable:
        Start  Length  Slot  Name   Signature
           15      35     4     k   Lscala/Tuple2;
           24      26     5     v   Lscala/collection/immutable/Set;
            0      64     0 remainingKeys$1   Lscala/collection/immutable/Set;
            0      64     1  x0$2   Lscala/Tuple2;
    MethodParameters:
      Name                           Flags
      remainingKeys$1                final
      x0$2                           final

  private final scala.collection.immutable.List order$1(scala.collection.immutable.Map, scala.collection.immutable.List);
    descriptor: (Lscala/collection/immutable/Map;Lscala/collection/immutable/List;)Lscala/collection/immutable/List;
    flags: (0x0012) ACC_PRIVATE, ACC_FINAL
    Code:
      stack=4, locals=15, args_size=3
         0: aload_1
         1: invokeinterface #299,  1          // InterfaceMethod scala/collection/immutable/Map.isEmpty:()Z
         6: ifeq          16
         9: aload_2
        10: invokevirtual #303                // Method scala/collection/immutable/List.reverse:()Lscala/collection/immutable/List;
        13: goto          209
        16: aload_1
        17: invokedynamic #321,  0            // InvokeDynamic #0:apply:()Lscala/Function1;
        22: invokeinterface #324,  2          // InterfaceMethod scala/collection/immutable/Map.map:(Lscala/Function1;)Ljava/lang/Object;
        27: checkcast     #262                // class scala/collection/IterableOnceOps
        30: getstatic     #327                // Field scala/math/Ordering$Int$.MODULE$:Lscala/math/Ordering$Int$;
        33: invokeinterface #331,  2          // InterfaceMethod scala/collection/IterableOnceOps.min:(Lscala/math/Ordering;)Ljava/lang/Object;
        38: invokestatic  #334                // Method scala/runtime/BoxesRunTime.unboxToInt:(Ljava/lang/Object;)I
        41: istore        5
        43: aload_1
        44: iload         5
        46: invokedynamic #342,  0            // InvokeDynamic #1:apply:(I)Lscala/Function1;
        51: invokeinterface #346,  2          // InterfaceMethod scala/collection/immutable/Map.partition:(Lscala/Function1;)Lscala/Tuple2;
        56: astore        7
        58: aload         7
        60: ifnull        99
        63: aload         7
        65: invokevirtual #194                // Method scala/Tuple2._1:()Ljava/lang/Object;
        68: checkcast     #200                // class scala/collection/immutable/Map
        71: astore        8
        73: aload         7
        75: invokevirtual #216                // Method scala/Tuple2._2:()Ljava/lang/Object;
        78: checkcast     #200                // class scala/collection/immutable/Map
        81: astore        9
        83: new           #190                // class scala/Tuple2
        86: dup
        87: aload         8
        89: aload         9
        91: invokespecial #349                // Method scala/Tuple2."<init>":(Ljava/lang/Object;Ljava/lang/Object;)V
        94: astore        4
        96: goto          112
        99: goto          102
       102: new           #205                // class scala/MatchError
       105: dup
       106: aload         7
       108: invokespecial #208                // Method scala/MatchError."<init>":(Ljava/lang/Object;)V
       111: athrow
       112: aload         4
       114: astore        6
       116: aload         6
       118: invokevirtual #194                // Method scala/Tuple2._1:()Ljava/lang/Object;
       121: checkcast     #200                // class scala/collection/immutable/Map
       124: astore        10
       126: aload         6
       128: invokevirtual #216                // Method scala/Tuple2._2:()Ljava/lang/Object;
       131: checkcast     #200                // class scala/collection/immutable/Map
       134: astore        11
       136: aload         10
       138: invokeinterface #353,  1          // InterfaceMethod scala/collection/immutable/Map.keys:()Lscala/collection/Iterable;
       143: aload_2
       144: invokedynamic #362,  0            // InvokeDynamic #2:apply:()Lscala/Function2;
       149: invokeinterface #368,  3          // InterfaceMethod scala/collection/Iterable.foldLeft:(Ljava/lang/Object;Lscala/Function2;)Ljava/lang/Object;
       154: checkcast     #276                // class scala/collection/immutable/List
       157: astore        12
       159: aload         11
       161: invokeinterface #372,  1          // InterfaceMethod scala/collection/immutable/Map.keySet:()Lscala/collection/immutable/Set;
       166: invokedynamic #377,  0            // InvokeDynamic #3:apply:()Lscala/Function1;
       171: invokeinterface #378,  2          // InterfaceMethod scala/collection/immutable/Set.map:(Lscala/Function1;)Ljava/lang/Object;
       176: checkcast     #245                // class scala/collection/immutable/Set
       179: astore        13
       181: aload         11
       183: aload         13
       185: invokedynamic #384,  0            // InvokeDynamic #4:apply:(Lscala/collection/immutable/Set;)Lscala/Function1;
       190: invokeinterface #387,  2          // InterfaceMethod scala/collection/immutable/Map.map:(Lscala/Function1;)Lscala/collection/IterableOps;
       195: checkcast     #200                // class scala/collection/immutable/Map
       198: astore        14
       200: aload         14
       202: aload         12
       204: astore_2
       205: astore_1
       206: goto          0
       209: areturn
      StackMapTable: number_of_entries = 6
        frame_type = 0 /* same */
        frame_type = 15 /* same */
        frame_type = 255 /* full_frame */
          offset_delta = 82
          locals = [ class coursier/core/Missing, class scala/collection/immutable/Map, class scala/collection/immutable/List, top, top, int, top, class scala/Tuple2 ]
          stack = []
        frame_type = 2 /* same */
        frame_type = 255 /* full_frame */
          offset_delta = 9
          locals = [ class coursier/core/Missing, class scala/collection/immutable/Map, class scala/collection/immutable/List, top, class scala/Tuple2, int, top, class scala/Tuple2, class scala/collection/immutable/Map, class scala/collection/immutable/Map ]
          stack = []
        frame_type = 255 /* full_frame */
          offset_delta = 96
          locals = [ class coursier/core/Missing, class scala/collection/immutable/Map, class scala/collection/immutable/List ]
          stack = [ class scala/collection/immutable/List ]
      LineNumberTable:
        line 99: 0
        line 100: 9
        line 102: 16
        line 103: 43
        line 106: 136
        line 107: 159
        line 108: 181
        line 112: 200
      LocalVariableTable:
        Start  Length  Slot  Name   Signature
           73      26     8 toAdd   Lscala/collection/immutable/Map;
           83      16     9 remaining   Lscala/collection/immutable/Map;
           43     166     5   min   I
          126      83    10 toAdd   Lscala/collection/immutable/Map;
          136      73    11 remaining   Lscala/collection/immutable/Map;
          159      50    12  acc0   Lscala/collection/immutable/List;
          181      28    13 remainingKeys   Lscala/collection/immutable/Set;
          200       9    14  map0   Lscala/collection/immutable/Map;
            0     210     0  this   Lcoursier/core/Missing;
            0     210     1   map   Lscala/collection/immutable/Map;
            0     210     2   acc   Lscala/collection/immutable/List;
    MethodParameters:
      Name                           Flags
      map                            final
      acc                            final

  public static final scala.Tuple2 $anonfun$next0$11(scala.collection.immutable.Set, scala.Tuple2);
    descriptor: (Lscala/collection/immutable/Set;Lscala/Tuple2;)Lscala/Tuple2;
    flags: (0x1019) ACC_PUBLIC, ACC_STATIC, ACC_FINAL, ACC_SYNTHETIC
    Code:
      stack=4, locals=6, args_size=2
         0: aload_1
         1: astore_3
         2: aload_3
         3: ifnull        50
         6: aload_3
         7: invokevirtual #194                // Method scala/Tuple2._1:()Ljava/lang/Object;
        10: checkcast     #190                // class scala/Tuple2
        13: astore        4
        15: aload_3
        16: invokevirtual #216                // Method scala/Tuple2._2:()Ljava/lang/Object;
        19: checkcast     #245                // class scala/collection/immutable/Set
        22: astore        5
        24: getstatic     #221                // Field scala/Predef$ArrowAssoc$.MODULE$:Lscala/Predef$ArrowAssoc$;
        27: getstatic     #226                // Field scala/Predef$.MODULE$:Lscala/Predef$;
        30: aload         4
        32: invokevirtual #230                // Method scala/Predef$.ArrowAssoc:(Ljava/lang/Object;)Ljava/lang/Object;
        35: aload         5
        37: aload_0
        38: invokeinterface #290,  2          // InterfaceMethod scala/collection/immutable/Set.intersect:(Lscala/collection/Set;)Lscala/collection/SetOps;
        43: invokevirtual #238                // Method scala/Predef$ArrowAssoc$.$minus$greater$extension:(Ljava/lang/Object;Ljava/lang/Object;)Lscala/Tuple2;
        46: astore_2
        47: goto          62
        50: goto          53
        53: new           #205                // class scala/MatchError
        56: dup
        57: aload_3
        58: invokespecial #208                // Method scala/MatchError."<init>":(Ljava/lang/Object;)V
        61: athrow
        62: aload_2
        63: areturn
      StackMapTable: number_of_entries = 3
        frame_type = 253 /* append */
          offset_delta = 50
          locals = [ top, class scala/Tuple2 ]
        frame_type = 2 /* same */
        frame_type = 255 /* full_frame */
          offset_delta = 8
          locals = [ class scala/collection/immutable/Set, class scala/Tuple2, class scala/Tuple2, class scala/Tuple2, class scala/Tuple2, class scala/collection/immutable/Set ]
          stack = []
      LineNumberTable:
        line 115: 0
      LocalVariableTable:
        Start  Length  Slot  Name   Signature
           15      35     4     k   Lscala/Tuple2;
           24      26     5     v   Lscala/collection/immutable/Set;
            0      64     0 modVer$1   Lscala/collection/immutable/Set;
            0      64     1  x0$3   Lscala/Tuple2;
    MethodParameters:
      Name                           Flags
      modVer$1                       final
      x0$3                           final

  public static final coursier.core.Resolution $anonfun$next0$12(coursier.core.Resolution, scala.Tuple2);
    descriptor: (Lcoursier/core/Resolution;Lscala/Tuple2;)Lcoursier/core/Resolution;
    flags: (0x1019) ACC_PUBLIC, ACC_STATIC, ACC_FINAL, ACC_SYNTHETIC
    Code:
      stack=11, locals=10, args_size=2
         0: new           #190                // class scala/Tuple2
         3: dup
         4: aload_0
         5: aload_1
         6: invokespecial #349                // Method scala/Tuple2."<init>":(Ljava/lang/Object;Ljava/lang/Object;)V
         9: astore_3
        10: aload_3
        11: ifnull        138
        14: aload_3
        15: invokevirtual #194                // Method scala/Tuple2._1:()Ljava/lang/Object;
        18: checkcast     #77                 // class coursier/core/Resolution
        21: astore        4
        23: aload_3
        24: invokevirtual #216                // Method scala/Tuple2._2:()Ljava/lang/Object;
        27: checkcast     #190                // class scala/Tuple2
        30: astore        5
        32: aload         5
        34: ifnull        135
        37: aload         5
        39: invokevirtual #194                // Method scala/Tuple2._1:()Ljava/lang/Object;
        42: checkcast     #190                // class scala/Tuple2
        45: astore        6
        47: aload         5
        49: invokevirtual #216                // Method scala/Tuple2._2:()Ljava/lang/Object;
        52: checkcast     #190                // class scala/Tuple2
        55: astore        7
        57: aload         7
        59: ifnull        132
        62: aload         7
        64: invokevirtual #194                // Method scala/Tuple2._1:()Ljava/lang/Object;
        67: checkcast     #402                // class coursier/core/ArtifactSource
        70: astore        8
        72: aload         7
        74: invokevirtual #216                // Method scala/Tuple2._2:()Ljava/lang/Object;
        77: checkcast     #218                // class coursier/core/Project
        80: astore        9
        82: aload         4
        84: getstatic     #407                // Field scala/runtime/ScalaRunTime$.MODULE$:Lscala/runtime/ScalaRunTime$;
        87: iconst_1
        88: anewarray     #190                // class scala/Tuple2
        91: dup
        92: iconst_0
        93: getstatic     #221                // Field scala/Predef$ArrowAssoc$.MODULE$:Lscala/Predef$ArrowAssoc$;
        96: getstatic     #226                // Field scala/Predef$.MODULE$:Lscala/Predef$;
        99: aload         6
       101: invokevirtual #230                // Method scala/Predef$.ArrowAssoc:(Ljava/lang/Object;)Ljava/lang/Object;
       104: new           #190                // class scala/Tuple2
       107: dup
       108: aload         8
       110: aload         9
       112: invokespecial #349                // Method scala/Tuple2."<init>":(Ljava/lang/Object;Ljava/lang/Object;)V
       115: invokevirtual #238                // Method scala/Predef$ArrowAssoc$.$minus$greater$extension:(Ljava/lang/Object;Ljava/lang/Object;)Lscala/Tuple2;
       118: aastore
       119: checkcast     #409                // class "[Ljava/lang/Object;"
       122: invokevirtual #413                // Method scala/runtime/ScalaRunTime$.wrapRefArray:([Ljava/lang/Object;)Lscala/collection/immutable/ArraySeq;
       125: invokevirtual #417                // Method coursier/core/Resolution.addToProjectCache:(Lscala/collection/immutable/Seq;)Lcoursier/core/Resolution;
       128: astore_2
       129: goto          150
       132: goto          141
       135: goto          141
       138: goto          141
       141: new           #205                // class scala/MatchError
       144: dup
       145: aload_3
       146: invokespecial #208                // Method scala/MatchError."<init>":(Ljava/lang/Object;)V
       149: athrow
       150: aload_2
       151: areturn
      StackMapTable: number_of_entries = 5
        frame_type = 255 /* full_frame */
          offset_delta = 132
          locals = [ class coursier/core/Resolution, class scala/Tuple2, top, class scala/Tuple2, class coursier/core/Resolution, class scala/Tuple2, class scala/Tuple2, class scala/Tuple2 ]
          stack = []
        frame_type = 249 /* chop */
          offset_delta = 2
        frame_type = 249 /* chop */
          offset_delta = 2
        frame_type = 2 /* same */
        frame_type = 255 /* full_frame */
          offset_delta = 8
          locals = [ class coursier/core/Resolution, class scala/Tuple2, class coursier/core/Resolution, class scala/Tuple2, class coursier/core/Resolution, class scala/Tuple2, class scala/Tuple2, class scala/Tuple2, class coursier/core/ArtifactSource, class coursier/core/Project ]
          stack = []
      LineNumberTable:
        line 117: 0
        line 118: 10
        line 119: 82
        line 120: 96
        line 118: 132
        line 117: 141
      LocalVariableTable:
        Start  Length  Slot  Name   Signature
           72      60     8 source   Lcoursier/core/ArtifactSource;
           82      50     9  proj   Lcoursier/core/Project;
           47      88     6 modVer0   Lscala/Tuple2;
           23     115     4   acc   Lcoursier/core/Resolution;
            0     152     0  x0$4   Lcoursier/core/Resolution;
            0     152     1  x1$1   Lscala/Tuple2;
    MethodParameters:
      Name                           Flags
      x0$4                           final
      x1$1                           final

  public static final coursier.core.ResolutionProcess $anonfun$next0$13(coursier.core.Missing, scala.collection.immutable.Seq, coursier.core.Resolution);
    descriptor: (Lcoursier/core/Missing;Lscala/collection/immutable/Seq;Lcoursier/core/Resolution;)Lcoursier/core/ResolutionProcess;
    flags: (0x1019) ACC_PUBLIC, ACC_STATIC, ACC_FINAL, ACC_SYNTHETIC
    Code:
      stack=3, locals=3, args_size=3
         0: aload_0
         1: aload_2
         2: aload_1
         3: invokespecial #85                 // Method cont0$1:(Lcoursier/core/Resolution;Lscala/collection/immutable/Seq;)Lcoursier/core/ResolutionProcess;
         6: areturn
      LineNumberTable:
        line 126: 0
      LocalVariableTable:
        Start  Length  Slot  Name   Signature
            0       7     0 $this   Lcoursier/core/Missing;
            0       7     1 successes$1   Lscala/collection/immutable/Seq;
            0       7     2   res   Lcoursier/core/Resolution;
    MethodParameters:
      Name                           Flags
      $this                          final synthetic
      successes$1                    final
      res                            final

  private final coursier.core.ResolutionProcess cont0$1(coursier.core.Resolution, scala.collection.immutable.Seq);
    descriptor: (Lcoursier/core/Resolution;Lscala/collection/immutable/Seq;)Lcoursier/core/ResolutionProcess;
    flags: (0x0012) ACC_PRIVATE, ACC_FINAL
    Code:
      stack=5, locals=9, args_size=3
         0: aload_2
         1: aload_1
         2: invokedynamic #433,  0            // InvokeDynamic #5:apply:(Lcoursier/core/Resolution;)Lscala/Function1;
         7: invokeinterface #436,  2          // InterfaceMethod scala/collection/immutable/Seq.filter:(Lscala/Function1;)Ljava/lang/Object;
        12: checkcast     #68                 // class scala/collection/immutable/Seq
        15: astore_3
        16: aload_3
        17: aload_1
        18: invokedynamic #440,  0            // InvokeDynamic #6:apply:(Lcoursier/core/Resolution;)Lscala/Function1;
        23: invokeinterface #441,  2          // InterfaceMethod scala/collection/immutable/Seq.map:(Lscala/Function1;)Ljava/lang/Object;
        28: checkcast     #68                 // class scala/collection/immutable/Seq
        31: astore        4
        33: aload         4
        35: invokedynamic #446,  0            // InvokeDynamic #7:apply:()Lscala/Function1;
        40: invokeinterface #441,  2          // InterfaceMethod scala/collection/immutable/Seq.map:(Lscala/Function1;)Ljava/lang/Object;
        45: checkcast     #262                // class scala/collection/IterableOnceOps
        48: getstatic     #226                // Field scala/Predef$.MODULE$:Lscala/Predef$;
        51: invokevirtual #450                // Method scala/Predef$.Set:()Lscala/collection/immutable/Set$;
        54: invokevirtual #455                // Method scala/collection/immutable/Set$.empty:()Lscala/collection/immutable/Set;
        57: invokedynamic #460,  0            // InvokeDynamic #8:apply:()Lscala/Function2;
        62: invokeinterface #463,  3          // InterfaceMethod scala/collection/IterableOnceOps.fold:(Ljava/lang/Object;Lscala/Function2;)Ljava/lang/Object;
        67: checkcast     #245                // class scala/collection/immutable/Set
        70: astore        5
        72: aload         5
        74: invokeinterface #464,  1          // InterfaceMethod scala/collection/immutable/Set.isEmpty:()Z
        79: ifeq          172
        82: aload         4
        84: invokedynamic #468,  0            // InvokeDynamic #9:apply:()Lscala/Function1;
        89: invokeinterface #441,  2          // InterfaceMethod scala/collection/immutable/Seq.map:(Lscala/Function1;)Ljava/lang/Object;
        94: checkcast     #262                // class scala/collection/IterableOnceOps
        97: invokeinterface #471,  1          // InterfaceMethod scala/collection/IterableOnceOps.toSet:()Lscala/collection/immutable/Set;
       102: astore        6
       104: aload_0
       105: aload         4
       107: aload         6
       109: invokedynamic #475,  0            // InvokeDynamic #10:apply:(Lscala/collection/immutable/Set;)Lscala/Function1;
       114: invokeinterface #441,  2          // InterfaceMethod scala/collection/immutable/Seq.map:(Lscala/Function1;)Ljava/lang/Object;
       119: checkcast     #262                // class scala/collection/IterableOnceOps
       122: getstatic     #480                // Field scala/$less$colon$less$.MODULE$:Lscala/$less$colon$less$;
       125: invokevirtual #484                // Method scala/$less$colon$less$.refl:()Lscala/$eq$colon$eq;
       128: invokeinterface #488,  2          // InterfaceMethod scala/collection/IterableOnceOps.toMap:(Lscala/$less$colon$less;)Lscala/collection/immutable/Map;
       133: getstatic     #493                // Field scala/collection/immutable/Nil$.MODULE$:Lscala/collection/immutable/Nil$;
       136: invokespecial #495                // Method order$1:(Lscala/collection/immutable/Map;Lscala/collection/immutable/List;)Lscala/collection/immutable/List;
       139: astore        7
       141: aload         7
       143: aload_1
       144: invokedynamic #500,  0            // InvokeDynamic #11:apply:()Lscala/Function2;
       149: invokevirtual #501                // Method scala/collection/immutable/List.foldLeft:(Ljava/lang/Object;Lscala/Function2;)Ljava/lang/Object;
       152: checkcast     #77                 // class coursier/core/Resolution
       155: astore        8
       157: getstatic     #506                // Field coursier/core/Continue$.MODULE$:Lcoursier/core/Continue$;
       160: aload         8
       162: aload_0
       163: invokevirtual #93                 // Method cont:()Lscala/Function1;
       166: invokevirtual #509                // Method coursier/core/Continue$.apply:(Lcoursier/core/Resolution;Lscala/Function1;)Lcoursier/core/Continue;
       169: goto          193
       172: getstatic     #43                 // Field coursier/core/Missing$.MODULE$:Lcoursier/core/Missing$;
       175: aload         5
       177: invokeinterface #512,  1          // InterfaceMethod scala/collection/immutable/Set.toSeq:()Lscala/collection/immutable/Seq;
       182: aload_1
       183: aload_0
       184: aload_2
       185: invokedynamic #520,  0            // InvokeDynamic #12:apply:(Lcoursier/core/Missing;Lscala/collection/immutable/Seq;)Lscala/Function1;
       190: invokevirtual #45                 // Method coursier/core/Missing$.apply:(Lscala/collection/immutable/Seq;Lcoursier/core/Resolution;Lscala/Function1;)Lcoursier/core/Missing;
       193: areturn
      StackMapTable: number_of_entries = 2
        frame_type = 254 /* append */
          offset_delta = 172
          locals = [ class scala/collection/immutable/Seq, class scala/collection/immutable/Seq, class scala/collection/immutable/Set ]
        frame_type = 84 /* same_locals_1_stack_item */
          stack = [ class coursier/core/ResolutionProcess ]
      LineNumberTable:
        line 80: 0
        line 85: 16
        line 90: 33
        line 92: 72
        line 95: 82
        line 115: 104
        line 117: 141
        line 124: 157
        line 126: 172
      LocalVariableTable:
        Start  Length  Slot  Name   Signature
          104      65     6 modVer   Lscala/collection/immutable/Set;
          141      28     7 orderedSuccesses   Lscala/collection/immutable/List;
          157      12     8  res0   Lcoursier/core/Resolution;
           16     177     3 remainingSuccesses   Lscala/collection/immutable/Seq;
           33     160     4 depMgmtMissing0   Lscala/collection/immutable/Seq;
           72     121     5 depMgmtMissing   Lscala/collection/immutable/Set;
            0     194     0  this   Lcoursier/core/Missing;
            0     194     1   res   Lcoursier/core/Resolution;
            0     194     2 successes$1   Lscala/collection/immutable/Seq;
    MethodParameters:
      Name                           Flags
      res                            final
      successes$1                    final

  public coursier.core.Missing(scala.collection.immutable.Seq<scala.Tuple2<coursier.core.Module, java.lang.String>>, coursier.core.Resolution, scala.Function1<coursier.core.Resolution, coursier.core.ResolutionProcess>);
    descriptor: (Lscala/collection/immutable/Seq;Lcoursier/core/Resolution;Lscala/Function1;)V
    flags: (0x0001) ACC_PUBLIC
    Code:
      stack=2, locals=4, args_size=4
         0: aload_0
         1: aload_1
         2: putfield      #49                 // Field missing:Lscala/collection/immutable/Seq;
         5: aload_0
         6: aload_2
         7: putfield      #54                 // Field current:Lcoursier/core/Resolution;
        10: aload_0
        11: aload_3
        12: putfield      #58                 // Field cont:Lscala/Function1;
        15: aload_0
        16: invokespecial #529                // Method coursier/core/ResolutionProcess."<init>":()V
        19: return
      LineNumberTable:
        line 61: 0
        line 65: 15
        line 61: 19
      LocalVariableTable:
        Start  Length  Slot  Name   Signature
            0      20     0  this   Lcoursier/core/Missing;
            0      20     1 missing   Lscala/collection/immutable/Seq;
            0      20     2 current   Lcoursier/core/Resolution;
            0      20     3  cont   Lscala/Function1;
    Signature: #526                         // (Lscala/collection/immutable/Seq<Lscala/Tuple2<Lcoursier/core/Module;Ljava/lang/String;>;>;Lcoursier/core/Resolution;Lscala/Function1<Lcoursier/core/Resolution;Lcoursier/core/ResolutionProcess;>;)V
    MethodParameters:
      Name                           Flags
      missing                        final
      current                        final
      cont                           final

  public static final java.lang.Object $anonfun$next0$6$adapted(scala.Tuple2);
    descriptor: (Lscala/Tuple2;)Ljava/lang/Object;
    flags: (0x1019) ACC_PUBLIC, ACC_STATIC, ACC_FINAL, ACC_SYNTHETIC
    Code:
      stack=1, locals=1, args_size=1
         0: aload_0
         1: invokestatic  #531                // Method $anonfun$next0$6:(Lscala/Tuple2;)I
         4: invokestatic  #177                // Method scala/runtime/BoxesRunTime.boxToInteger:(I)Ljava/lang/Integer;
         7: areturn
      LineNumberTable:
        line 102: 0
      LocalVariableTable:
        Start  Length  Slot  Name   Signature
            0       8     0   x$5   Lscala/Tuple2;
    MethodParameters:
      Name                           Flags
      x$5                            final

  public static final java.lang.Object $anonfun$next0$7$adapted(int, scala.Tuple2);
    descriptor: (ILscala/Tuple2;)Ljava/lang/Object;
    flags: (0x1019) ACC_PUBLIC, ACC_STATIC, ACC_FINAL, ACC_SYNTHETIC
    Code:
      stack=2, locals=2, args_size=2
         0: iload_0
         1: aload_1
         2: invokestatic  #533                // Method $anonfun$next0$7:(ILscala/Tuple2;)Z
         5: invokestatic  #537                // Method scala/runtime/BoxesRunTime.boxToBoolean:(Z)Ljava/lang/Boolean;
         8: areturn
      LineNumberTable:
        line 103: 0
      LocalVariableTable:
        Start  Length  Slot  Name   Signature
            0       9     0 min$1   I
            0       9     1  x0$1   Lscala/Tuple2;
    MethodParameters:
      Name                           Flags
      min$1                          final
      x0$1                           final

  public static final java.lang.Object $anonfun$next0$1$adapted(coursier.core.Resolution, scala.Tuple2);
    descriptor: (Lcoursier/core/Resolution;Lscala/Tuple2;)Ljava/lang/Object;
    flags: (0x1019) ACC_PUBLIC, ACC_STATIC, ACC_FINAL, ACC_SYNTHETIC
    Code:
      stack=2, locals=2, args_size=2
         0: aload_0
         1: aload_1
         2: invokestatic  #539                // Method $anonfun$next0$1:(Lcoursier/core/Resolution;Lscala/Tuple2;)Z
         5: invokestatic  #537                // Method scala/runtime/BoxesRunTime.boxToBoolean:(Z)Ljava/lang/Boolean;
         8: areturn
      LineNumberTable:
        line 80: 0
      LocalVariableTable:
        Start  Length  Slot  Name   Signature
            0       9     0 res$1   Lcoursier/core/Resolution;
            0       9     1  x0$1   Lscala/Tuple2;
    MethodParameters:
      Name                           Flags
      res$1                          final
      x0$1                           final

  private static java.lang.Object $deserializeLambda$(java.lang.invoke.SerializedLambda);
    descriptor: (Ljava/lang/invoke/SerializedLambda;)Ljava/lang/Object;
    flags: (0x100a) ACC_PRIVATE, ACC_STATIC, ACC_SYNTHETIC
    Code:
      stack=1, locals=1, args_size=1
         0: aload_0
         1: invokedynamic #551,  0            // InvokeDynamic #13:lambdaDeserialize:(Ljava/lang/invoke/SerializedLambda;)Ljava/lang/Object;
         6: areturn
}
InnerClasses:
  public final #10;                       // class coursier/core/Missing$$anonfun$1
  public final #12;                       // class coursier/core/Missing$$anonfun$2
  public static final #17= #14 of #16;    // Lookup=class java/lang/invoke/MethodHandles$Lookup of class java/lang/invoke/MethodHandles
  public static #22= #19 of #21;          // =class scala/Predef$ArrowAssoc$ of class scala/Predef
  public static #22= #24 of #26;          // =class scala/math/Ordering$Int$ of class scala/math/Ordering
SourceFile: "ResolutionProcess.scala"
RuntimeVisibleAnnotations:
  0: #6(#7=s#8)
    scala.reflect.ScalaSignature(
      bytes="\u0006\u0005\u0005\u0015d\u0001\u0002\u000e\u001c\u0005\u0001B\u0001b\u000e\u0001\u0003\u0006\u0004%\t\u0001\u000f\u0005\t\u0015\u0002\u0011\t\u0011)A\u0005s!A1\n\u0001BC\u0002\u0013\u0005A\n\u0003\u0005Q\u0001\t\u0005\t\u0015!\u0003N\u0011!\t\u0006A!b\u0001\n\u0003\u0011\u0006\u0002\u0003,\u0001\u0005\u0003\u0005\u000b\u0011B*\t\u000b]\u0003A\u0011\u0001-\t\u000bu\u0003A\u0011\u00010\t\u000b!\u0004A\u0011A5\t\u000b-\u0004A\u0011\u00017\t\u000b9\u0004A\u0011A8\t\u000bE\u0004A\u0011\t:\t\u000bi\u0004A\u0011I>\t\u000f\u0005%\u0001\u0001\"\u0011\u0002\f!9\u0011q\u0002\u0001\u0005B\u0005E\u0001bBA\r\u0001\u0011%\u00111\u0004\u0005\b\u0003G\u0001A\u0011IA\u0013\u0011\u001d\t9\u0003\u0001C!\u0003SAq!a\u000b\u0001\t\u0003\ni\u0003C\u0004\u00024\u0001!\t%!\u000e\b\u000f\u0005e2\u0004#\u0001\u0002<\u00191!d\u0007E\u0001\u0003{Aaa\u0016\f\u0005\u0002\u0005=\u0003bBA)-\u0011\u0005\u00111\u000b\u0005\n\u000372\u0012\u0011!C\u0005\u0003;\u0012q!T5tg&twM\u0003\u0002\u001d;\u0005!1m\u001c:f\u0015\u0005q\u0012\u0001C2pkJ\u001c\u0018.\u001a:\u0004\u0001M!\u0001!I\u0013,!\t\u00113%D\u0001\u001c\u0013\t!3DA\tSKN|G.\u001e;j_:\u0004&o\\2fgN\u0004\"AJ\u0015\u000e\u0003\u001dR\u0011\u0001K\u0001\u0006g\u000e\fG.Y\u0005\u0003U\u001d\u0012q\u0001\u0015:pIV\u001cG\u000f\u0005\u0002-i9\u0011QF\r\b\u0003]Ej\u0011a\f\u0006\u0003a}\ta\u0001\u0010:p_Rt\u0014\"\u0001\u0015\n\u0005M:\u0013a\u00029bG.\fw-Z\u0005\u0003kY\u0012AbU3sS\u0006d\u0017N_1cY\u0016T!aM\u0014\u0002\u000f5L7o]5oOV\t\u0011\bE\u0002-uqJ!a\u000f\u001c\u0003\u0007M+\u0017\u000f\u0005\u0003\'{}\u0012\u0015B\u0001 (\u0005\u0019!V\u000f\u001d7feA\u0011!\u0005Q\u0005\u0003\u0003n\u0011a!T8ek2,\u0007CA\"H\u001d\t!U\t\u0005\u0002/O%\u0011aiJ\u0001\u0007!J,G-\u001a4\n\u0005!K%AB*ue&twM\u0003\u0002GO\u0005AQ.[:tS:<\u0007%A\u0004dkJ\u0014XM\u001c;\u0016\u00035\u0003\"A\t(\n\u0005=[\"A\u0003*fg>dW\u000f^5p]\u0006A1-\u001e:sK:$\b%\u0001\u0003d_:$X#A*\u0011\t\u0019\"V*I\u0005\u0003+\u001e\u0012\u0011BR;oGRLwN\\\u0019\u0002\u000b\r|g\u000e\u001e\u0011\u0002\rqJg.\u001b;?)\u0011I&l\u0017/\u0011\u0005\t\u0002\u0001\"B\u001c\b\u0001\u0004I\u0004\"B&\b\u0001\u0004i\u0005\"B)\b\u0001\u0004\u0019\u0016!\u00028fqR\u0004DCA\u0011`\u0011\u0015\u0001\u0007\u00021\u0001b\u0003\u001d\u0011Xm];miN\u0004\"AY3\u000f\u0005\t\u001a\u0017B\u00013\u001c\u0003E\u0011Vm]8mkRLwN\u001c)s_\u000e,7o]\u0005\u0003M\u001e\u0014!!\u0014#\u000b\u0005\u0011\\\u0012aC<ji\"l\u0015n]:j]\u001e$\"!\u00176\t\u000b]J\u0001\u0019A\u001d\u0002\u0017]LG\u000f[\"veJ,g\u000e\u001e\u000b\u000336DQa\u0013\u0006A\u00025\u000b\u0001b^5uQ\u000e{g\u000e\u001e\u000b\u00033BDQ!U\u0006A\u0002M\u000b\u0001\u0002^8TiJLgn\u001a\u000b\u0002gB\u0011A/_\u0007\u0002k*\u0011ao^\u0001\u0005Y\u0006twMC\u0001y\u0003\u0011Q\u0017M^1\n\u0005!+\u0018\u0001C2b]\u0016\u000bX/\u00197\u0015\u0005q|\bC\u0001\u0014~\u0013\tqxEA\u0004C_>dW-\u00198\t\u000f\u0005\u0005Q\u00021\u0001\u0002\u0004\u0005\u0019qN\u00196\u0011\u0007\u0019\n)!C\u0002\u0002\b\u001d\u00121!\u00118z\u0003\u0019)\u0017/^1mgR\u0019A0!\u0004\t\u000f\u0005\u0005a\u00021\u0001\u0002\u0004\u0005A\u0001.Y:i\u0007>$W\r\u0006\u0002\u0002\u0014A\u0019a%!\u0006\n\u0007\u0005]qEA\u0002J]R\fQ\u0001^;qY\u0016,\"!!\b\u0011\r\u0019\ny\"O\'T\u0013\r\t\tc\n\u0002\u0007)V\u0004H.Z\u001a\u0002\u001bA\u0014x\u000eZ;diB\u0013XMZ5y+\u0005\u0019\u0018\u0001\u00049s_\u0012,8\r^!sSRLXCAA\n\u00039\u0001(o\u001c3vGR,E.Z7f]R$B!a\u0001\u00020!9\u0011\u0011G\nA\u0002\u0005M\u0011!\u00018\u0002%A\u0014x\u000eZ;di\u0016cW-\\3oi:\u000bW.\u001a\u000b\u0004g\u0006]\u0002bBA\u0019)\u0001\u0007\u00111C\u0001\b\u001b&\u001c8/\u001b8h!\t\u0011ccE\u0003\u0017\u0003\u007f\t)\u0005E\u0002\'\u0003\u0003J1!a\u0011(\u0005\u0019\te.\u001f*fMB!\u0011qIA\'\u001b\t\tIEC\u0002\u0002L]\f!![8\n\u0007U\nI\u0005\u0006\u0002\u0002<\u0005)\u0011\r\u001d9msR9\u0011,!\u0016\u0002X\u0005e\u0003\"B\u001c\u0019\u0001\u0004I\u0004\"B&\u0019\u0001\u0004i\u0005\"B)\u0019\u0001\u0004\u0019\u0016\u0001D<sSR,\'+\u001a9mC\u000e,GCAA0!\r!\u0018\u0011M\u0005\u0004\u0003G*(AB(cU\u0016\u001cG\u000f"
    )
BootstrapMethods:
  0: #319 REF_invokeStatic java/lang/invoke/LambdaMetafactory.altMetafactory:(Ljava/lang/invoke/MethodHandles$Lookup;Ljava/lang/String;Ljava/lang/invoke/MethodType;[Ljava/lang/Object;)Ljava/lang/invoke/CallSite;
    Method arguments:
      #304 (Ljava/lang/Object;)Ljava/lang/Object;
      #309 REF_invokeStatic coursier/core/Missing.$anonfun$next0$6$adapted:(Lscala/Tuple2;)Ljava/lang/Object;
      #310 (Lscala/Tuple2;)Ljava/lang/Object;
      #311 5
      #312 1
      #310 (Lscala/Tuple2;)Ljava/lang/Object;
  1: #319 REF_invokeStatic java/lang/invoke/LambdaMetafactory.altMetafactory:(Ljava/lang/invoke/MethodHandles$Lookup;Ljava/lang/String;Ljava/lang/invoke/MethodType;[Ljava/lang/Object;)Ljava/lang/invoke/CallSite;
    Method arguments:
      #304 (Ljava/lang/Object;)Ljava/lang/Object;
      #339 REF_invokeStatic coursier/core/Missing.$anonfun$next0$7$adapted:(ILscala/Tuple2;)Ljava/lang/Object;
      #310 (Lscala/Tuple2;)Ljava/lang/Object;
      #311 5
      #312 1
      #310 (Lscala/Tuple2;)Ljava/lang/Object;
  2: #319 REF_invokeStatic java/lang/invoke/LambdaMetafactory.altMetafactory:(Ljava/lang/invoke/MethodHandles$Lookup;Ljava/lang/String;Ljava/lang/invoke/MethodType;[Ljava/lang/Object;)Ljava/lang/invoke/CallSite;
    Method arguments:
      #355 (Ljava/lang/Object;Ljava/lang/Object;)Ljava/lang/Object;
      #358 REF_invokeStatic coursier/core/Missing.$anonfun$next0$8:(Lscala/collection/immutable/List;Lscala/Tuple2;)Lscala/collection/immutable/List;
      #359 (Lscala/collection/immutable/List;Lscala/Tuple2;)Lscala/collection/immutable/List;
      #311 5
      #312 1
      #359 (Lscala/collection/immutable/List;Lscala/Tuple2;)Lscala/collection/immutable/List;
  3: #319 REF_invokeStatic java/lang/invoke/LambdaMetafactory.altMetafactory:(Ljava/lang/invoke/MethodHandles$Lookup;Ljava/lang/String;Ljava/lang/invoke/MethodType;[Ljava/lang/Object;)Ljava/lang/invoke/CallSite;
    Method arguments:
      #304 (Ljava/lang/Object;)Ljava/lang/Object;
      #375 REF_invokeStatic coursier/core/Missing.$anonfun$next0$9:(Lscala/Tuple2;)Lscala/Tuple2;
      #376 (Lscala/Tuple2;)Lscala/Tuple2;
      #311 5
      #312 1
      #376 (Lscala/Tuple2;)Lscala/Tuple2;
  4: #319 REF_invokeStatic java/lang/invoke/LambdaMetafactory.altMetafactory:(Ljava/lang/invoke/MethodHandles$Lookup;Ljava/lang/String;Ljava/lang/invoke/MethodType;[Ljava/lang/Object;)Ljava/lang/invoke/CallSite;
    Method arguments:
      #304 (Ljava/lang/Object;)Ljava/lang/Object;
      #381 REF_invokeStatic coursier/core/Missing.$anonfun$next0$10:(Lscala/collection/immutable/Set;Lscala/Tuple2;)Lscala/Tuple2;
      #376 (Lscala/Tuple2;)Lscala/Tuple2;
      #311 5
      #312 1
      #376 (Lscala/Tuple2;)Lscala/Tuple2;
  5: #319 REF_invokeStatic java/lang/invoke/LambdaMetafactory.altMetafactory:(Ljava/lang/invoke/MethodHandles$Lookup;Ljava/lang/String;Ljava/lang/invoke/MethodType;[Ljava/lang/Object;)Ljava/lang/invoke/CallSite;
    Method arguments:
      #304 (Ljava/lang/Object;)Ljava/lang/Object;
      #430 REF_invokeStatic coursier/core/Missing.$anonfun$next0$1$adapted:(Lcoursier/core/Resolution;Lscala/Tuple2;)Ljava/lang/Object;
      #310 (Lscala/Tuple2;)Ljava/lang/Object;
      #311 5
      #312 1
      #310 (Lscala/Tuple2;)Ljava/lang/Object;
  6: #319 REF_invokeStatic java/lang/invoke/LambdaMetafactory.altMetafactory:(Ljava/lang/invoke/MethodHandles$Lookup;Ljava/lang/String;Ljava/lang/invoke/MethodType;[Ljava/lang/Object;)Ljava/lang/invoke/CallSite;
    Method arguments:
      #304 (Ljava/lang/Object;)Ljava/lang/Object;
      #439 REF_invokeStatic coursier/core/Missing.$anonfun$next0$2:(Lcoursier/core/Resolution;Lscala/Tuple2;)Lscala/Tuple2;
      #376 (Lscala/Tuple2;)Lscala/Tuple2;
      #311 5
      #312 1
      #376 (Lscala/Tuple2;)Lscala/Tuple2;
  7: #319 REF_invokeStatic java/lang/invoke/LambdaMetafactory.altMetafactory:(Ljava/lang/invoke/MethodHandles$Lookup;Ljava/lang/String;Ljava/lang/invoke/MethodType;[Ljava/lang/Object;)Ljava/lang/invoke/CallSite;
    Method arguments:
      #304 (Ljava/lang/Object;)Ljava/lang/Object;
      #444 REF_invokeStatic coursier/core/Missing.$anonfun$next0$3:(Lscala/Tuple2;)Lscala/collection/immutable/Set;
      #445 (Lscala/Tuple2;)Lscala/collection/immutable/Set;
      #311 5
      #312 1
      #445 (Lscala/Tuple2;)Lscala/collection/immutable/Set;
  8: #319 REF_invokeStatic java/lang/invoke/LambdaMetafactory.altMetafactory:(Ljava/lang/invoke/MethodHandles$Lookup;Ljava/lang/String;Ljava/lang/invoke/MethodType;[Ljava/lang/Object;)Ljava/lang/invoke/CallSite;
    Method arguments:
      #355 (Ljava/lang/Object;Ljava/lang/Object;)Ljava/lang/Object;
      #458 REF_invokeStatic coursier/core/Missing.$anonfun$next0$4:(Lscala/collection/immutable/Set;Lscala/collection/immutable/Set;)Lscala/collection/immutable/Set;
      #459 (Lscala/collection/immutable/Set;Lscala/collection/immutable/Set;)Lscala/collection/immutable/Set;
      #311 5
      #312 1
      #459 (Lscala/collection/immutable/Set;Lscala/collection/immutable/Set;)Lscala/collection/immutable/Set;
  9: #319 REF_invokeStatic java/lang/invoke/LambdaMetafactory.altMetafactory:(Ljava/lang/invoke/MethodHandles$Lookup;Ljava/lang/String;Ljava/lang/invoke/MethodType;[Ljava/lang/Object;)Ljava/lang/invoke/CallSite;
    Method arguments:
      #304 (Ljava/lang/Object;)Ljava/lang/Object;
      #467 REF_invokeStatic coursier/core/Missing.$anonfun$next0$5:(Lscala/Tuple2;)Lscala/Tuple2;
      #376 (Lscala/Tuple2;)Lscala/Tuple2;
      #311 5
      #312 1
      #376 (Lscala/Tuple2;)Lscala/Tuple2;
  10: #319 REF_invokeStatic java/lang/invoke/LambdaMetafactory.altMetafactory:(Ljava/lang/invoke/MethodHandles$Lookup;Ljava/lang/String;Ljava/lang/invoke/MethodType;[Ljava/lang/Object;)Ljava/lang/invoke/CallSite;
    Method arguments:
      #304 (Ljava/lang/Object;)Ljava/lang/Object;
      #474 REF_invokeStatic coursier/core/Missing.$anonfun$next0$11:(Lscala/collection/immutable/Set;Lscala/Tuple2;)Lscala/Tuple2;
      #376 (Lscala/Tuple2;)Lscala/Tuple2;
      #311 5
      #312 1
      #376 (Lscala/Tuple2;)Lscala/Tuple2;
  11: #319 REF_invokeStatic java/lang/invoke/LambdaMetafactory.altMetafactory:(Ljava/lang/invoke/MethodHandles$Lookup;Ljava/lang/String;Ljava/lang/invoke/MethodType;[Ljava/lang/Object;)Ljava/lang/invoke/CallSite;
    Method arguments:
      #355 (Ljava/lang/Object;Ljava/lang/Object;)Ljava/lang/Object;
      #498 REF_invokeStatic coursier/core/Missing.$anonfun$next0$12:(Lcoursier/core/Resolution;Lscala/Tuple2;)Lcoursier/core/Resolution;
      #499 (Lcoursier/core/Resolution;Lscala/Tuple2;)Lcoursier/core/Resolution;
      #311 5
      #312 1
      #499 (Lcoursier/core/Resolution;Lscala/Tuple2;)Lcoursier/core/Resolution;
  12: #319 REF_invokeStatic java/lang/invoke/LambdaMetafactory.altMetafactory:(Ljava/lang/invoke/MethodHandles$Lookup;Ljava/lang/String;Ljava/lang/invoke/MethodType;[Ljava/lang/Object;)Ljava/lang/invoke/CallSite;
    Method arguments:
      #304 (Ljava/lang/Object;)Ljava/lang/Object;
      #515 REF_invokeStatic coursier/core/Missing.$anonfun$next0$13:(Lcoursier/core/Missing;Lscala/collection/immutable/Seq;Lcoursier/core/Resolution;)Lcoursier/core/ResolutionProcess;
      #517 (Lcoursier/core/Resolution;)Lcoursier/core/ResolutionProcess;
      #311 5
      #312 1
      #517 (Lcoursier/core/Resolution;)Lcoursier/core/ResolutionProcess;
  13: #548 REF_invokeStatic scala/runtime/LambdaDeserialize.bootstrap:(Ljava/lang/invoke/MethodHandles$Lookup;Ljava/lang/String;Ljava/lang/invoke/MethodType;[Ljava/lang/invoke/MethodHandle;)Ljava/lang/invoke/CallSite;
    Method arguments:
      #430 REF_invokeStatic coursier/core/Missing.$anonfun$next0$1$adapted:(Lcoursier/core/Resolution;Lscala/Tuple2;)Ljava/lang/Object;
      #381 REF_invokeStatic coursier/core/Missing.$anonfun$next0$10:(Lscala/collection/immutable/Set;Lscala/Tuple2;)Lscala/Tuple2;
      #474 REF_invokeStatic coursier/core/Missing.$anonfun$next0$11:(Lscala/collection/immutable/Set;Lscala/Tuple2;)Lscala/Tuple2;
      #498 REF_invokeStatic coursier/core/Missing.$anonfun$next0$12:(Lcoursier/core/Resolution;Lscala/Tuple2;)Lcoursier/core/Resolution;
      #515 REF_invokeStatic coursier/core/Missing.$anonfun$next0$13:(Lcoursier/core/Missing;Lscala/collection/immutable/Seq;Lcoursier/core/Resolution;)Lcoursier/core/ResolutionProcess;
      #439 REF_invokeStatic coursier/core/Missing.$anonfun$next0$2:(Lcoursier/core/Resolution;Lscala/Tuple2;)Lscala/Tuple2;
      #444 REF_invokeStatic coursier/core/Missing.$anonfun$next0$3:(Lscala/Tuple2;)Lscala/collection/immutable/Set;
      #458 REF_invokeStatic coursier/core/Missing.$anonfun$next0$4:(Lscala/collection/immutable/Set;Lscala/collection/immutable/Set;)Lscala/collection/immutable/Set;
      #467 REF_invokeStatic coursier/core/Missing.$anonfun$next0$5:(Lscala/Tuple2;)Lscala/Tuple2;
      #309 REF_invokeStatic coursier/core/Missing.$anonfun$next0$6$adapted:(Lscala/Tuple2;)Ljava/lang/Object;
      #339 REF_invokeStatic coursier/core/Missing.$anonfun$next0$7$adapted:(ILscala/Tuple2;)Ljava/lang/Object;
      #358 REF_invokeStatic coursier/core/Missing.$anonfun$next0$8:(Lscala/collection/immutable/List;Lscala/Tuple2;)Lscala/collection/immutable/List;
      #375 REF_invokeStatic coursier/core/Missing.$anonfun$next0$9:(Lscala/Tuple2;)Lscala/Tuple2;
  ScalaInlineInfo: length = 0xB3 (unknown attribute)
   01 01 00 23 00 BA 00 BB 01 01 AB 01 AC 01 01 1D
   01 1E 01 01 8B 01 1E 01 01 8E 01 8F 01 01 A6 01
   A7 01 00 D4 00 D5 01 00 F2 00 F3 01 00 F7 00 F8
   01 01 00 01 01 01 01 03 01 04 01 01 32 01 33 01
   01 0B 01 0C 01 01 50 01 51 01 01 10 01 11 01 01
   1B 01 01 01 00 40 00 5F 01 00 84 00 85 01 00 21
   00 38 01 00 53 00 54 01 00 1F 00 35 01 00 88 00
   85 01 00 92 00 93 01 00 1C 00 2F 01 00 3C 00 3D
   01 01 25 01 26 01 00 A7 00 93 01 00 A8 00 A9 01
   00 B5 00 B6 01 00 A6 00 6A 01 00 69 00 6A 01 00
   9E 00 9F 01 00 66 00 67 01 00 62 00 63 01 00 5A
   00 5B 01
  ScalaSig: length = 0x3 (unknown attribute)
   05 02 00
