Classfile /Users/mw/Projects/slang-braindump/.jar/jar8/assemble/slang-braindump/assemble/content/coursier/core/Orders.class
  Last modified May 29, 2022; size 4412 bytes
  SHA-256 checksum a351108f1a1447add661bda69f1a425d1a5e0ef7d86969f5c3e7a6565c0112c2
  Compiled from "Orders.scala"
public final class coursier.core.Orders
  minor version: 0
  major version: 52
  flags: (0x0031) ACC_PUBLIC, ACC_FINAL, ACC_SUPER
  this_class: #2                          // coursier/core/Orders
  super_class: #4                         // java/lang/Object
  interfaces: 0, fields: 0, methods: 6, attributes: 4
Constant pool:
   #1 = Utf8               coursier/core/Orders
   #2 = Class              #1             // coursier/core/Orders
   #3 = Utf8               java/lang/Object
   #4 = Class              #3             // java/lang/Object
   #5 = Utf8               Orders.scala
   #6 = Utf8               Lscala/reflect/ScalaSignature;
   #7 = Utf8               bytes
   #8 = Utf8               \u0006\u0005\u0005\rt!B\t\u0013\u0011\u00039b!B\r\u0013\u0011\u0003Q\u0002\"B\u0011\u0002\t\u0003\u0011caB\u0012\u0002!\u0003\r\t\u0001\n\u0005\u0006m\r!\ta\u000e\u0005\u0006w\r!\t\u0001\u0010\u0005\u0006\u0019\u0006!\t!\u0014\u0005\u0007Y\u0006!\tAE7\t\u000b=\fA\u0011\u00019\t\u000bU\fA\u0011\u0002<\t\u000ba\fA\u0011B=\t\u000f\u0005\r\u0011\u0001\"\u0001\u0002\u0006!9\u0011QC\u0001\u0005\u0002\u0005]\u0001\"CA\u001e\u0003\t\u0007I\u0011AA\u001f\u0011!\t\u0019%\u0001Q\u0001\n\u0005}\u0002\"CA$\u0003\t\u0007I\u0011AA%\u0011!\ty&\u0001Q\u0001\n\u0005-\u0013AB(sI\u0016\u00148O\u0003\u0002\u0014)\u0005!1m\u001c:f\u0015\u0005)\u0012\u0001C2pkJ\u001c\u0018.\u001a:\u0004\u0001A\u0011\u0001$A\u0007\u0002%\t1qJ\u001d3feN\u001c\"!A\u000e\u0011\u0005qyR\"A\u000f\u000b\u0003y\tQa]2bY\u0006L!\u0001I\u000f\u0003\r\u0005s\u0017PU3g\u0003\u0019a\u0014N\\5u}Q\tqCA\bQCJ$\u0018.\u00197Pe\u0012,\'/\u001b8h+\t)SfE\u0002\u00047\u0019\u00022a\n\u0016,\u001b\u0005A#BA\u0015\u001e\u0003\u0011i\u0017\r\u001e5\n\u0005\rB\u0003C\u0001\u0017.\u0019\u0001!QAL\u0002C\u0002=\u0012\u0011\u0001V\t\u0003aM\u0002\"\u0001H\u0019\n\u0005Ij\"a\u0002(pi\"Lgn\u001a\t\u00039QJ!!N\u000f\u0003\u0007\u0005s\u00170\u0001\u0004%S:LG\u000f\n\u000b\u0002qA\u0011A$O\u0005\u0003uu\u0011A!\u00168ji\u0006!A\u000e^3r)\ri\u0004I\u0011\t\u00039yJ!aP\u000f\u0003\u000f\t{w\u000e\\3b]\")\u0011)\u0002a\u0001W\u0005\t\u0001\u0010C\u0003D\u000b\u0001\u00071&A\u0001zQ\u0011\u0019Q\t\u0013&\u0011\u0005q1\u0015BA$\u001e\u0005)!W\r\u001d:fG\u0006$X\rZ\u0011\u0002\u0013\u00069t+\u001b7mA1L7.\u001a7zA\t,\u0007E]3n_Z,G\rI1uAM|W.\u001a\u0011q_&tG\u000fI5oA\u0019,H/\u001e:fAY,\'o]5p]N\f\u0013aS\u0001\ne9\u0002d\u0006M\u0017S\u0007N\n\u0011#\u00197m\u0007>tg-[4ve\u0006$\u0018n\u001c8t)\tqu\f\u0005\u0003P-fcfB\u0001)U!\t\tV$D\u0001S\u0015\t\u0019f#\u0001\u0004=e>|GOP\u0005\u0003+v\ta\u0001\u0015:fI\u00164\u0017BA,Y\u0005\ri\u0015\r\u001d\u0006\u0003+v\u0001\"\u0001\u0007.\n\u0005m\u0013\"!D\"p]\u001aLw-\u001e:bi&|g\u000eE\u0002P;fK!A\u0018-\u0003\u0007M+G\u000fC\u0003a\r\u0001\u0007\u0011-\u0001\bd_:4\u0017nZ;sCRLwN\\:\u0011\t=3\u0016L\u0019\t\u0004G\"LfB\u00013g\u001d\t\tV-C\u0001\u001f\u0013\t9W$A\u0004qC\u000e\\\u0017mZ3\n\u0005%T\'aA*fc*\u0011q-\b\u0015\u0005\r\u0015C%*\u0001\nbY2\u001cuN\u001c4jOV\u0014\u0018\r^5p]N\u0004DC\u0001(o\u0011\u0015\u0001w\u00011\u0001b\u0003e\u0019wN\u001c4jOV\u0014\u0018\r^5p]B\u000b\'\u000f^5bY>\u0013H-\u001a:\u0015\u0005E\u001c\bc\u0001:\u000436\t\u0011\u0001C\u0003a\u0011\u0001\u0007\u0011\r\u000b\u0003\t\u000b\"S\u0015AG2p]\u001aLw-\u001e:bi&|g\u000eU1si&\fGn\u0014:eKJ\u0004DCA9x\u0011\u0015\u0001\u0017\u00021\u0001b\u0003e1\u0017\r\u001c7cC\u000e\\7i\u001c8gS\u001eLeMT3dKN\u001c\u0018M]=\u0015\u0007ilx\u0010\u0005\u0002\u0019w&\u0011AP\u0005\u0002\u000b\t\u0016\u0004XM\u001c3f]\u000eL\b\"\u0002@\u000b\u0001\u0004Q\u0018a\u00013fa\"1\u0011\u0011\u0001\u0006A\u0002q\u000bqaY8oM&<7/A\u000bnS:$U\r]3oI\u0016t7-[3t+:\u001c\u0018MZ3\u0015\r\u0005\u001d\u0011\u0011BA\u0007!\ryUL\u001f\u0005\b\u0003\u0017Y\u0001\u0019AA\u0004\u00031!W\r]3oI\u0016t7-[3t\u0011\u0019\t\ta\u0003a\u0001C\"*1\"RA\t\u0015\u0006\u0012\u00111C\u0001U\u0007\u0006t\u0007eZ5wK\u0002JgnY8se\u0016\u001cG\u000f\t:fgVdGo\u001d\u0011.A]LG\u000e\u001c\u0011mS.,G.\u001f\u0011cK\u0002\u0012X-\\8wK\u0012\u0004\u0013\r\u001e\u0011t_6,\u0007\u0005]8j]R\u0004\u0013N\u001c\u0011gkR,(/\u001a\u0011wKJ\u001c\u0018n\u001c8t\u0003=i\u0017N\u001c#fa\u0016tG-\u001a8dS\u0016\u001cHCBA\u0004\u00033\tY\u0002C\u0004\u0002\f1\u0001\r!a\u0002\t\u000f\u0005\u0005A\u00021\u0001\u0002\u001eA1A$a\b\u0002$\u0005L1!!\t\u001e\u0005%1UO\\2uS>t\u0017\u0007E\u0004\u001d\u0003K\tI#a\f\n\u0007\u0005\u001dRD\u0001\u0004UkBdWM\r\t\u00041\u0005-\u0012bAA\u0017%\t1Qj\u001c3vY\u0016\u00042aTA\u0019\u0013\r\t\u0019\u0004\u0017\u0002\u0007\'R\u0014\u0018N\\4)\u000b1)\u0015q\u0007&\"\u0005\u0005e\u0012!a\rDC:\u0004s-\u001b<fA%t7m\u001c:sK\u000e$\bE]3tk2$8\u000fI\u0017!o&dG\u000e\t7jW\u0016d\u0017\u0010\t2fAI,Wn\u001c<fI\u0002\nG\u000fI:p[\u0016\u0004\u0003o\\5oi\u0002Jg\u000e\t4viV\u0014X\r\t<feNLwN\\:-AU\u001cX\r\t#fa\u0016tG-\u001a8dsN+GOL7j]&l\u0017N_3e\'\u0016$\b%\u001b8ti\u0016\fG\r\t;pA5Lg.[7ju\u0016\u0004\u0013\r\t3fa\u0016tG-\u001a8ds\u0002\u001aX\r^\u0001\u0015_B$\u0018n\u001c8bYB\u000b\'\u000f^5bY>\u0013H-\u001a:\u0016\u0005\u0005}\u0002c\u0001:\u0004{!\"Q\"\u0012%K\u0003Uy\u0007\u000f^5p]\u0006d\u0007+\u0019:uS\u0006dwJ\u001d3fe\u0002BCAD#I\u0015\u00061R\r_2mkNLwN\\:QCJ$\u0018.\u00197Pe\u0012,\'/\u0006\u0002\u0002LA!!oAA\'!\u0011yU,a\u0014\u0011\u000fq\t)#!\u0015\u0002XA\u0019\u0001$a\u0015\n\u0007\u0005U#C\u0001\u0007Pe\u001e\fg.\u001b>bi&|g\u000eE\u0002\u0019\u00033J1!a\u0017\u0013\u0005)iu\u000eZ;mK:\u000bW.\u001a\u0015\u0006\u001f\u0015\u000b\tBS\u0001\u0018Kb\u001cG.^:j_:\u001c\b+\u0019:uS\u0006dwJ\u001d3fe\u0002BS\u0001E#\u0002\u0012)\u0003
   #9 = Utf8               coursier/core/Orders$PartialOrdering
  #10 = Class              #9             // coursier/core/Orders$PartialOrdering
  #11 = Utf8               PartialOrdering
  #12 = Utf8               exclusionsPartialOrder
  #13 = Utf8               ()Lcoursier/core/Orders$PartialOrdering;
  #14 = Utf8               ()Lcoursier/core/Orders$PartialOrdering<Lscala/collection/immutable/Set<Lscala/Tuple2<Lcoursier/core/Organization;Lcoursier/core/ModuleName;>;>;>;
  #15 = Utf8               coursier/core/Orders$
  #16 = Class              #15            // coursier/core/Orders$
  #17 = Utf8               MODULE$
  #18 = Utf8               Lcoursier/core/Orders$;
  #19 = NameAndType        #17:#18        // MODULE$:Lcoursier/core/Orders$;
  #20 = Fieldref           #16.#19        // coursier/core/Orders$.MODULE$:Lcoursier/core/Orders$;
  #21 = NameAndType        #12:#13        // exclusionsPartialOrder:()Lcoursier/core/Orders$PartialOrdering;
  #22 = Methodref          #16.#21        // coursier/core/Orders$.exclusionsPartialOrder:()Lcoursier/core/Orders$PartialOrdering;
  #23 = Utf8               optionalPartialOrder
  #24 = Utf8               ()Lcoursier/core/Orders$PartialOrdering<Ljava/lang/Object;>;
  #25 = NameAndType        #23:#13        // optionalPartialOrder:()Lcoursier/core/Orders$PartialOrdering;
  #26 = Methodref          #16.#25        // coursier/core/Orders$.optionalPartialOrder:()Lcoursier/core/Orders$PartialOrdering;
  #27 = Utf8               minDependencies
  #28 = Utf8               (Lscala/collection/immutable/Set;Lscala/Function1;)Lscala/collection/immutable/Set;
  #29 = Utf8               (Lscala/collection/immutable/Set<Lcoursier/core/Dependency;>;Lscala/Function1<Lscala/Tuple2<Lcoursier/core/Module;Ljava/lang/String;>;Lscala/collection/immutable/Map<Lcoursier/core/Configuration;Lscala/collection/immutable/Seq<Lcoursier/core/Configuration;>;>;>;)Lscala/collection/immutable/Set<Lcoursier/core/Dependency;>;
  #30 = Utf8               dependencies
  #31 = Utf8               configs
  #32 = NameAndType        #27:#28        // minDependencies:(Lscala/collection/immutable/Set;Lscala/Function1;)Lscala/collection/immutable/Set;
  #33 = Methodref          #16.#32        // coursier/core/Orders$.minDependencies:(Lscala/collection/immutable/Set;Lscala/Function1;)Lscala/collection/immutable/Set;
  #34 = Utf8               minDependenciesUnsafe
  #35 = Utf8               (Lscala/collection/immutable/Set;Lscala/collection/immutable/Map;)Lscala/collection/immutable/Set;
  #36 = Utf8               (Lscala/collection/immutable/Set<Lcoursier/core/Dependency;>;Lscala/collection/immutable/Map<Lcoursier/core/Configuration;Lscala/collection/immutable/Seq<Lcoursier/core/Configuration;>;>;)Lscala/collection/immutable/Set<Lcoursier/core/Dependency;>;
  #37 = NameAndType        #34:#35        // minDependenciesUnsafe:(Lscala/collection/immutable/Set;Lscala/collection/immutable/Map;)Lscala/collection/immutable/Set;
  #38 = Methodref          #16.#37        // coursier/core/Orders$.minDependenciesUnsafe:(Lscala/collection/immutable/Set;Lscala/collection/immutable/Map;)Lscala/collection/immutable/Set;
  #39 = Utf8               configurationPartialOrder
  #40 = Utf8               (Lscala/collection/immutable/Map;)Lcoursier/core/Orders$PartialOrdering;
  #41 = Utf8               (Lscala/collection/immutable/Map<Lcoursier/core/Configuration;Lscala/collection/immutable/Seq<Lcoursier/core/Configuration;>;>;)Lcoursier/core/Orders$PartialOrdering<Lcoursier/core/Configuration;>;
  #42 = Utf8               configurations
  #43 = NameAndType        #39:#40        // configurationPartialOrder:(Lscala/collection/immutable/Map;)Lcoursier/core/Orders$PartialOrdering;
  #44 = Methodref          #16.#43        // coursier/core/Orders$.configurationPartialOrder:(Lscala/collection/immutable/Map;)Lcoursier/core/Orders$PartialOrdering;
  #45 = Utf8               allConfigurations
  #46 = Utf8               (Lscala/collection/immutable/Map;)Lscala/collection/immutable/Map;
  #47 = Utf8               (Lscala/collection/immutable/Map<Lcoursier/core/Configuration;Lscala/collection/immutable/Seq<Lcoursier/core/Configuration;>;>;)Lscala/collection/immutable/Map<Lcoursier/core/Configuration;Lscala/collection/immutable/Set<Lcoursier/core/Configuration;>;>;
  #48 = NameAndType        #45:#46        // allConfigurations:(Lscala/collection/immutable/Map;)Lscala/collection/immutable/Map;
  #49 = Methodref          #16.#48        // coursier/core/Orders$.allConfigurations:(Lscala/collection/immutable/Map;)Lscala/collection/immutable/Map;
  #50 = Utf8               Code
  #51 = Utf8               Signature
  #52 = Utf8               Deprecated
  #53 = Utf8               MethodParameters
  #54 = Utf8               InnerClasses
  #55 = Utf8               SourceFile
  #56 = Utf8               RuntimeVisibleAnnotations
  #57 = Utf8               ScalaSig
{
  public static coursier.core.Orders$PartialOrdering<scala.collection.immutable.Set<scala.Tuple2<coursier.core.Organization, coursier.core.ModuleName>>> exclusionsPartialOrder();
    descriptor: ()Lcoursier/core/Orders$PartialOrdering;
    flags: (0x0009) ACC_PUBLIC, ACC_STATIC
    Code:
      stack=1, locals=0, args_size=0
         0: getstatic     #20                 // Field coursier/core/Orders$.MODULE$:Lcoursier/core/Orders$;
         3: invokevirtual #22                 // Method coursier/core/Orders$.exclusionsPartialOrder:()Lcoursier/core/Orders$PartialOrdering;
         6: areturn
    Signature: #14                          // ()Lcoursier/core/Orders$PartialOrdering<Lscala/collection/immutable/Set<Lscala/Tuple2<Lcoursier/core/Organization;Lcoursier/core/ModuleName;>;>;>;
    Deprecated: true

  public static coursier.core.Orders$PartialOrdering<java.lang.Object> optionalPartialOrder();
    descriptor: ()Lcoursier/core/Orders$PartialOrdering;
    flags: (0x0009) ACC_PUBLIC, ACC_STATIC
    Code:
      stack=1, locals=0, args_size=0
         0: getstatic     #20                 // Field coursier/core/Orders$.MODULE$:Lcoursier/core/Orders$;
         3: invokevirtual #26                 // Method coursier/core/Orders$.optionalPartialOrder:()Lcoursier/core/Orders$PartialOrdering;
         6: areturn
    Signature: #24                          // ()Lcoursier/core/Orders$PartialOrdering<Ljava/lang/Object;>;
    Deprecated: true

  public static scala.collection.immutable.Set<coursier.core.Dependency> minDependencies(scala.collection.immutable.Set<coursier.core.Dependency>, scala.Function1<scala.Tuple2<coursier.core.Module, java.lang.String>, scala.collection.immutable.Map<coursier.core.Configuration, scala.collection.immutable.Seq<coursier.core.Configuration>>>);
    descriptor: (Lscala/collection/immutable/Set;Lscala/Function1;)Lscala/collection/immutable/Set;
    flags: (0x0009) ACC_PUBLIC, ACC_STATIC
    Code:
      stack=3, locals=2, args_size=2
         0: getstatic     #20                 // Field coursier/core/Orders$.MODULE$:Lcoursier/core/Orders$;
         3: aload_0
         4: aload_1
         5: invokevirtual #33                 // Method coursier/core/Orders$.minDependencies:(Lscala/collection/immutable/Set;Lscala/Function1;)Lscala/collection/immutable/Set;
         8: areturn
    Signature: #29                          // (Lscala/collection/immutable/Set<Lcoursier/core/Dependency;>;Lscala/Function1<Lscala/Tuple2<Lcoursier/core/Module;Ljava/lang/String;>;Lscala/collection/immutable/Map<Lcoursier/core/Configuration;Lscala/collection/immutable/Seq<Lcoursier/core/Configuration;>;>;>;)Lscala/collection/immutable/Set<Lcoursier/core/Dependency;>;
    Deprecated: true
    MethodParameters:
      Name                           Flags
      dependencies                   final
      configs                        final

  public static scala.collection.immutable.Set<coursier.core.Dependency> minDependenciesUnsafe(scala.collection.immutable.Set<coursier.core.Dependency>, scala.collection.immutable.Map<coursier.core.Configuration, scala.collection.immutable.Seq<coursier.core.Configuration>>);
    descriptor: (Lscala/collection/immutable/Set;Lscala/collection/immutable/Map;)Lscala/collection/immutable/Set;
    flags: (0x0009) ACC_PUBLIC, ACC_STATIC
    Code:
      stack=3, locals=2, args_size=2
         0: getstatic     #20                 // Field coursier/core/Orders$.MODULE$:Lcoursier/core/Orders$;
         3: aload_0
         4: aload_1
         5: invokevirtual #38                 // Method coursier/core/Orders$.minDependenciesUnsafe:(Lscala/collection/immutable/Set;Lscala/collection/immutable/Map;)Lscala/collection/immutable/Set;
         8: areturn
    Signature: #36                          // (Lscala/collection/immutable/Set<Lcoursier/core/Dependency;>;Lscala/collection/immutable/Map<Lcoursier/core/Configuration;Lscala/collection/immutable/Seq<Lcoursier/core/Configuration;>;>;)Lscala/collection/immutable/Set<Lcoursier/core/Dependency;>;
    Deprecated: true
    MethodParameters:
      Name                           Flags
      dependencies                   final
      configs                        final

  public static coursier.core.Orders$PartialOrdering<coursier.core.Configuration> configurationPartialOrder(scala.collection.immutable.Map<coursier.core.Configuration, scala.collection.immutable.Seq<coursier.core.Configuration>>);
    descriptor: (Lscala/collection/immutable/Map;)Lcoursier/core/Orders$PartialOrdering;
    flags: (0x0009) ACC_PUBLIC, ACC_STATIC
    Code:
      stack=2, locals=1, args_size=1
         0: getstatic     #20                 // Field coursier/core/Orders$.MODULE$:Lcoursier/core/Orders$;
         3: aload_0
         4: invokevirtual #44                 // Method coursier/core/Orders$.configurationPartialOrder:(Lscala/collection/immutable/Map;)Lcoursier/core/Orders$PartialOrdering;
         7: areturn
    Signature: #41                          // (Lscala/collection/immutable/Map<Lcoursier/core/Configuration;Lscala/collection/immutable/Seq<Lcoursier/core/Configuration;>;>;)Lcoursier/core/Orders$PartialOrdering<Lcoursier/core/Configuration;>;
    Deprecated: true
    MethodParameters:
      Name                           Flags
      configurations                 final

  public static scala.collection.immutable.Map<coursier.core.Configuration, scala.collection.immutable.Set<coursier.core.Configuration>> allConfigurations(scala.collection.immutable.Map<coursier.core.Configuration, scala.collection.immutable.Seq<coursier.core.Configuration>>);
    descriptor: (Lscala/collection/immutable/Map;)Lscala/collection/immutable/Map;
    flags: (0x0009) ACC_PUBLIC, ACC_STATIC
    Code:
      stack=2, locals=1, args_size=1
         0: getstatic     #20                 // Field coursier/core/Orders$.MODULE$:Lcoursier/core/Orders$;
         3: aload_0
         4: invokevirtual #49                 // Method coursier/core/Orders$.allConfigurations:(Lscala/collection/immutable/Map;)Lscala/collection/immutable/Map;
         7: areturn
    Signature: #47                          // (Lscala/collection/immutable/Map<Lcoursier/core/Configuration;Lscala/collection/immutable/Seq<Lcoursier/core/Configuration;>;>;)Lscala/collection/immutable/Map<Lcoursier/core/Configuration;Lscala/collection/immutable/Set<Lcoursier/core/Configuration;>;>;
    Deprecated: true
    MethodParameters:
      Name                           Flags
      configurations                 final
}
InnerClasses:
  public static #11= #10 of #2;           // PartialOrdering=class coursier/core/Orders$PartialOrdering of class coursier/core/Orders
SourceFile: "Orders.scala"
RuntimeVisibleAnnotations:
  0: #6(#7=s#8)
    scala.reflect.ScalaSignature(
      bytes="\u0006\u0005\u0005\rt!B\t\u0013\u0011\u00039b!B\r\u0013\u0011\u0003Q\u0002\"B\u0011\u0002\t\u0003\u0011caB\u0012\u0002!\u0003\r\t\u0001\n\u0005\u0006m\r!\ta\u000e\u0005\u0006w\r!\t\u0001\u0010\u0005\u0006\u0019\u0006!\t!\u0014\u0005\u0007Y\u0006!\tAE7\t\u000b=\fA\u0011\u00019\t\u000bU\fA\u0011\u0002<\t\u000ba\fA\u0011B=\t\u000f\u0005\r\u0011\u0001\"\u0001\u0002\u0006!9\u0011QC\u0001\u0005\u0002\u0005]\u0001\"CA\u001e\u0003\t\u0007I\u0011AA\u001f\u0011!\t\u0019%\u0001Q\u0001\n\u0005}\u0002\"CA$\u0003\t\u0007I\u0011AA%\u0011!\ty&\u0001Q\u0001\n\u0005-\u0013AB(sI\u0016\u00148O\u0003\u0002\u0014)\u0005!1m\u001c:f\u0015\u0005)\u0012\u0001C2pkJ\u001c\u0018.\u001a:\u0004\u0001A\u0011\u0001$A\u0007\u0002%\t1qJ\u001d3feN\u001c\"!A\u000e\u0011\u0005qyR\"A\u000f\u000b\u0003y\tQa]2bY\u0006L!\u0001I\u000f\u0003\r\u0005s\u0017PU3g\u0003\u0019a\u0014N\\5u}Q\tqCA\bQCJ$\u0018.\u00197Pe\u0012,\'/\u001b8h+\t)SfE\u0002\u00047\u0019\u00022a\n\u0016,\u001b\u0005A#BA\u0015\u001e\u0003\u0011i\u0017\r\u001e5\n\u0005\rB\u0003C\u0001\u0017.\u0019\u0001!QAL\u0002C\u0002=\u0012\u0011\u0001V\t\u0003aM\u0002\"\u0001H\u0019\n\u0005Ij\"a\u0002(pi\"Lgn\u001a\t\u00039QJ!!N\u000f\u0003\u0007\u0005s\u00170\u0001\u0004%S:LG\u000f\n\u000b\u0002qA\u0011A$O\u0005\u0003uu\u0011A!\u00168ji\u0006!A\u000e^3r)\ri\u0004I\u0011\t\u00039yJ!aP\u000f\u0003\u000f\t{w\u000e\\3b]\")\u0011)\u0002a\u0001W\u0005\t\u0001\u0010C\u0003D\u000b\u0001\u00071&A\u0001zQ\u0011\u0019Q\t\u0013&\u0011\u0005q1\u0015BA$\u001e\u0005)!W\r\u001d:fG\u0006$X\rZ\u0011\u0002\u0013\u00069t+\u001b7mA1L7.\u001a7zA\t,\u0007E]3n_Z,G\rI1uAM|W.\u001a\u0011q_&tG\u000fI5oA\u0019,H/\u001e:fAY,\'o]5p]N\f\u0013aS\u0001\ne9\u0002d\u0006M\u0017S\u0007N\n\u0011#\u00197m\u0007>tg-[4ve\u0006$\u0018n\u001c8t)\tqu\f\u0005\u0003P-fcfB\u0001)U!\t\tV$D\u0001S\u0015\t\u0019f#\u0001\u0004=e>|GOP\u0005\u0003+v\ta\u0001\u0015:fI\u00164\u0017BA,Y\u0005\ri\u0015\r\u001d\u0006\u0003+v\u0001\"\u0001\u0007.\n\u0005m\u0013\"!D\"p]\u001aLw-\u001e:bi&|g\u000eE\u0002P;fK!A\u0018-\u0003\u0007M+G\u000fC\u0003a\r\u0001\u0007\u0011-\u0001\bd_:4\u0017nZ;sCRLwN\\:\u0011\t=3\u0016L\u0019\t\u0004G\"LfB\u00013g\u001d\t\tV-C\u0001\u001f\u0013\t9W$A\u0004qC\u000e\\\u0017mZ3\n\u0005%T\'aA*fc*\u0011q-\b\u0015\u0005\r\u0015C%*\u0001\nbY2\u001cuN\u001c4jOV\u0014\u0018\r^5p]N\u0004DC\u0001(o\u0011\u0015\u0001w\u00011\u0001b\u0003e\u0019wN\u001c4jOV\u0014\u0018\r^5p]B\u000b\'\u000f^5bY>\u0013H-\u001a:\u0015\u0005E\u001c\bc\u0001:\u000436\t\u0011\u0001C\u0003a\u0011\u0001\u0007\u0011\r\u000b\u0003\t\u000b\"S\u0015AG2p]\u001aLw-\u001e:bi&|g\u000eU1si&\fGn\u0014:eKJ\u0004DCA9x\u0011\u0015\u0001\u0017\u00021\u0001b\u0003e1\u0017\r\u001c7cC\u000e\\7i\u001c8gS\u001eLeMT3dKN\u001c\u0018M]=\u0015\u0007ilx\u0010\u0005\u0002\u0019w&\u0011AP\u0005\u0002\u000b\t\u0016\u0004XM\u001c3f]\u000eL\b\"\u0002@\u000b\u0001\u0004Q\u0018a\u00013fa\"1\u0011\u0011\u0001\u0006A\u0002q\u000bqaY8oM&<7/A\u000bnS:$U\r]3oI\u0016t7-[3t+:\u001c\u0018MZ3\u0015\r\u0005\u001d\u0011\u0011BA\u0007!\ryUL\u001f\u0005\b\u0003\u0017Y\u0001\u0019AA\u0004\u00031!W\r]3oI\u0016t7-[3t\u0011\u0019\t\ta\u0003a\u0001C\"*1\"RA\t\u0015\u0006\u0012\u00111C\u0001U\u0007\u0006t\u0007eZ5wK\u0002JgnY8se\u0016\u001cG\u000f\t:fgVdGo\u001d\u0011.A]LG\u000e\u001c\u0011mS.,G.\u001f\u0011cK\u0002\u0012X-\\8wK\u0012\u0004\u0013\r\u001e\u0011t_6,\u0007\u0005]8j]R\u0004\u0013N\u001c\u0011gkR,(/\u001a\u0011wKJ\u001c\u0018n\u001c8t\u0003=i\u0017N\u001c#fa\u0016tG-\u001a8dS\u0016\u001cHCBA\u0004\u00033\tY\u0002C\u0004\u0002\f1\u0001\r!a\u0002\t\u000f\u0005\u0005A\u00021\u0001\u0002\u001eA1A$a\b\u0002$\u0005L1!!\t\u001e\u0005%1UO\\2uS>t\u0017\u0007E\u0004\u001d\u0003K\tI#a\f\n\u0007\u0005\u001dRD\u0001\u0004UkBdWM\r\t\u00041\u0005-\u0012bAA\u0017%\t1Qj\u001c3vY\u0016\u00042aTA\u0019\u0013\r\t\u0019\u0004\u0017\u0002\u0007\'R\u0014\u0018N\\4)\u000b1)\u0015q\u0007&\"\u0005\u0005e\u0012!a\rDC:\u0004s-\u001b<fA%t7m\u001c:sK\u000e$\bE]3tk2$8\u000fI\u0017!o&dG\u000e\t7jW\u0016d\u0017\u0010\t2fAI,Wn\u001c<fI\u0002\nG\u000fI:p[\u0016\u0004\u0003o\\5oi\u0002Jg\u000e\t4viV\u0014X\r\t<feNLwN\\:-AU\u001cX\r\t#fa\u0016tG-\u001a8dsN+GOL7j]&l\u0017N_3e\'\u0016$\b%\u001b8ti\u0016\fG\r\t;pA5Lg.[7ju\u0016\u0004\u0013\r\t3fa\u0016tG-\u001a8ds\u0002\u001aX\r^\u0001\u0015_B$\u0018n\u001c8bYB\u000b\'\u000f^5bY>\u0013H-\u001a:\u0016\u0005\u0005}\u0002c\u0001:\u0004{!\"Q\"\u0012%K\u0003Uy\u0007\u000f^5p]\u0006d\u0007+\u0019:uS\u0006dwJ\u001d3fe\u0002BCAD#I\u0015\u00061R\r_2mkNLwN\\:QCJ$\u0018.\u00197Pe\u0012,\'/\u0006\u0002\u0002LA!!oAA\'!\u0011yU,a\u0014\u0011\u000fq\t)#!\u0015\u0002XA\u0019\u0001$a\u0015\n\u0007\u0005U#C\u0001\u0007Pe\u001e\fg.\u001b>bi&|g\u000eE\u0002\u0019\u00033J1!a\u0017\u0013\u0005)iu\u000eZ;mK:\u000bW.\u001a\u0015\u0006\u001f\u0015\u000b\tBS\u0001\u0018Kb\u001cG.^:j_:\u001c\b+\u0019:uS\u0006dwJ\u001d3fe\u0002BS\u0001E#\u0002\u0012)\u0003"
    )
  ScalaSig: length = 0x3 (unknown attribute)
   05 02 00
