Classfile /Users/mw/Projects/slang-braindump/.jar/jar8/assemble/slang-braindump/assemble/content/coursier/core/Reconciliation$.class
  Last modified May 29, 2022; size 4832 bytes
  SHA-256 checksum 6b545884513fe16427108e23ca6bb2f3e2e8513620f44c0b8369ad8cf3f822ff
  Compiled from "Reconciliation.scala"
public final class coursier.core.Reconciliation$
  minor version: 0
  major version: 52
  flags: (0x0031) ACC_PUBLIC, ACC_FINAL, ACC_SUPER
  this_class: #2                          // coursier/core/Reconciliation$
  super_class: #4                         // java/lang/Object
  interfaces: 0, fields: 1, methods: 11, attributes: 5
Constant pool:
    #1 = Utf8               coursier/core/Reconciliation$
    #2 = Class              #1            // coursier/core/Reconciliation$
    #3 = Utf8               java/lang/Object
    #4 = Class              #3            // java/lang/Object
    #5 = Utf8               Reconciliation.scala
    #6 = Utf8               coursier/core/Reconciliation$Default$
    #7 = Class              #6            // coursier/core/Reconciliation$Default$
    #8 = Utf8               coursier/core/Reconciliation
    #9 = Class              #8            // coursier/core/Reconciliation
   #10 = Utf8
   #11 = Utf8               coursier/core/Reconciliation$Relaxed$
   #12 = Class              #11           // coursier/core/Reconciliation$Relaxed$
   #13 = Utf8               coursier/core/Reconciliation$SemVer$
   #14 = Class              #13           // coursier/core/Reconciliation$SemVer$
   #15 = Utf8               coursier/core/Reconciliation$Strict$
   #16 = Class              #15           // coursier/core/Reconciliation$Strict$
   #17 = Utf8               java/lang/invoke/MethodHandles$Lookup
   #18 = Class              #17           // java/lang/invoke/MethodHandles$Lookup
   #19 = Utf8               java/lang/invoke/MethodHandles
   #20 = Class              #19           // java/lang/invoke/MethodHandles
   #21 = Utf8               Lookup
   #22 = Utf8               MODULE$
   #23 = Utf8               Lcoursier/core/Reconciliation$;
   #24 = Utf8               <clinit>
   #25 = Utf8               ()V
   #26 = Utf8               <init>
   #27 = NameAndType        #26:#25       // "<init>":()V
   #28 = Methodref          #2.#27        // coursier/core/Reconciliation$."<init>":()V
   #29 = NameAndType        #22:#23       // MODULE$:Lcoursier/core/Reconciliation$;
   #30 = Fieldref           #2.#29        // coursier/core/Reconciliation$.MODULE$:Lcoursier/core/Reconciliation$;
   #31 = Utf8               LatestIntegration
   #32 = Utf8               ()Ljava/lang/String;
   #33 = Utf8               latest.integration
   #34 = String             #33           // latest.integration
   #35 = Utf8               this
   #36 = Utf8               LatestRelease
   #37 = Utf8               latest.release
   #38 = String             #37           // latest.release
   #39 = Utf8               LatestStable
   #40 = Utf8               latest.stable
   #41 = String             #40           // latest.stable
   #42 = Utf8               coursier$core$Reconciliation$$splitStandard
   #43 = Utf8               (Lscala/collection/immutable/Seq;)Lscala/Tuple2;
   #44 = Utf8               (Lscala/collection/immutable/Seq<Ljava/lang/String;>;)Lscala/Tuple2<Lscala/collection/immutable/Seq<Ljava/lang/String;>;Lscala/collection/immutable/Seq<Ljava/lang/String;>;>;
   #45 = Utf8               versions
   #46 = Utf8               scala/collection/immutable/Seq
   #47 = Class              #46           // scala/collection/immutable/Seq
   #48 = Utf8               distinct
   #49 = Utf8               ()Ljava/lang/Object;
   #50 = NameAndType        #48:#49       // distinct:()Ljava/lang/Object;
   #51 = InterfaceMethodref #47.#50       // scala/collection/immutable/Seq.distinct:()Ljava/lang/Object;
   #52 = Utf8               scala/collection/IterableOps
   #53 = Class              #52           // scala/collection/IterableOps
   #54 = Utf8               (Ljava/lang/Object;)Ljava/lang/Object;
   #55 = MethodType         #54           //  (Ljava/lang/Object;)Ljava/lang/Object;
   #56 = Utf8               $anonfun$splitStandard$1$adapted
   #57 = Utf8               (Ljava/lang/String;)Ljava/lang/Object;
   #58 = NameAndType        #56:#57       // $anonfun$splitStandard$1$adapted:(Ljava/lang/String;)Ljava/lang/Object;
   #59 = Methodref          #2.#58        // coursier/core/Reconciliation$.$anonfun$splitStandard$1$adapted:(Ljava/lang/String;)Ljava/lang/Object;
   #60 = MethodHandle       6:#59         // REF_invokeStatic coursier/core/Reconciliation$.$anonfun$splitStandard$1$adapted:(Ljava/lang/String;)Ljava/lang/Object;
   #61 = MethodType         #57           //  (Ljava/lang/String;)Ljava/lang/Object;
   #62 = Integer            5
   #63 = Integer            1
   #64 = Utf8               java/lang/invoke/LambdaMetafactory
   #65 = Class              #64           // java/lang/invoke/LambdaMetafactory
   #66 = Utf8               altMetafactory
   #67 = Utf8               (Ljava/lang/invoke/MethodHandles$Lookup;Ljava/lang/String;Ljava/lang/invoke/MethodType;[Ljava/lang/Object;)Ljava/lang/invoke/CallSite;
   #68 = NameAndType        #66:#67       // altMetafactory:(Ljava/lang/invoke/MethodHandles$Lookup;Ljava/lang/String;Ljava/lang/invoke/MethodType;[Ljava/lang/Object;)Ljava/lang/invoke/CallSite;
   #69 = Methodref          #65.#68       // java/lang/invoke/LambdaMetafactory.altMetafactory:(Ljava/lang/invoke/MethodHandles$Lookup;Ljava/lang/String;Ljava/lang/invoke/MethodType;[Ljava/lang/Object;)Ljava/lang/invoke/CallSite;
   #70 = MethodHandle       6:#69         // REF_invokeStatic java/lang/invoke/LambdaMetafactory.altMetafactory:(Ljava/lang/invoke/MethodHandles$Lookup;Ljava/lang/String;Ljava/lang/invoke/MethodType;[Ljava/lang/Object;)Ljava/lang/invoke/CallSite;
   #71 = Utf8               apply
   #72 = Utf8               ()Lscala/Function1;
   #73 = NameAndType        #71:#72       // apply:()Lscala/Function1;
   #74 = InvokeDynamic      #0:#73        // #0:apply:()Lscala/Function1;
   #75 = Utf8               partition
   #76 = Utf8               (Lscala/Function1;)Lscala/Tuple2;
   #77 = NameAndType        #75:#76       // partition:(Lscala/Function1;)Lscala/Tuple2;
   #78 = InterfaceMethodref #53.#77       // scala/collection/IterableOps.partition:(Lscala/Function1;)Lscala/Tuple2;
   #79 = Utf8               Lscala/collection/immutable/Seq;
   #80 = Utf8               coursier$core$Reconciliation$$retainLatestOpt
   #81 = Utf8               (Lscala/collection/immutable/Seq;)Lscala/Option;
   #82 = Utf8               (Lscala/collection/immutable/Seq<Ljava/lang/String;>;)Lscala/Option<Ljava/lang/String;>;
   #83 = Utf8               latests
   #84 = Utf8               isEmpty
   #85 = Utf8               ()Z
   #86 = NameAndType        #84:#85       // isEmpty:()Z
   #87 = InterfaceMethodref #47.#86       // scala/collection/immutable/Seq.isEmpty:()Z
   #88 = Utf8               scala/None$
   #89 = Class              #88           // scala/None$
   #90 = Utf8               Lscala/None$;
   #91 = NameAndType        #22:#90       // MODULE$:Lscala/None$;
   #92 = Fieldref           #89.#91       // scala/None$.MODULE$:Lscala/None$;
   #93 = Utf8               lengthCompare
   #94 = Utf8               (I)I
   #95 = NameAndType        #93:#94       // lengthCompare:(I)I
   #96 = InterfaceMethodref #47.#95       // scala/collection/immutable/Seq.lengthCompare:(I)I
   #97 = Utf8               headOption
   #98 = Utf8               ()Lscala/Option;
   #99 = NameAndType        #97:#98       // headOption:()Lscala/Option;
  #100 = InterfaceMethodref #47.#99       // scala/collection/immutable/Seq.headOption:()Lscala/Option;
  #101 = Utf8               toSet
  #102 = Utf8               ()Lscala/collection/immutable/Set;
  #103 = NameAndType        #101:#102     // toSet:()Lscala/collection/immutable/Set;
  #104 = InterfaceMethodref #47.#103      // scala/collection/immutable/Seq.toSet:()Lscala/collection/immutable/Set;
  #105 = Utf8               scala/collection/immutable/Set
  #106 = Class              #105          // scala/collection/immutable/Set
  #107 = Utf8               (Ljava/lang/Object;)Z
  #108 = NameAndType        #71:#107      // apply:(Ljava/lang/Object;)Z
  #109 = InterfaceMethodref #106.#108     // scala/collection/immutable/Set.apply:(Ljava/lang/Object;)Z
  #110 = Utf8               scala/Predef$
  #111 = Class              #110          // scala/Predef$
  #112 = Utf8               Lscala/Predef$;
  #113 = NameAndType        #22:#112      // MODULE$:Lscala/Predef$;
  #114 = Fieldref           #111.#113     // scala/Predef$.MODULE$:Lscala/Predef$;
  #115 = Utf8               assert
  #116 = Utf8               (Z)V
  #117 = NameAndType        #115:#116     // assert:(Z)V
  #118 = Methodref          #111.#117     // scala/Predef$.assert:(Z)V
  #119 = Utf8               java/lang/String
  #120 = Class              #119          // java/lang/String
  #121 = Utf8               scala/Some
  #122 = Class              #121          // scala/Some
  #123 = Utf8               (Ljava/lang/Object;)V
  #124 = NameAndType        #26:#123      // "<init>":(Ljava/lang/Object;)V
  #125 = Methodref          #122.#124     // scala/Some."<init>":(Ljava/lang/Object;)V
  #126 = Utf8               scala/Option
  #127 = Class              #126          // scala/Option
  #128 = Utf8               set
  #129 = Utf8               Lscala/collection/immutable/Set;
  #130 = Utf8               retained
  #131 = Utf8               Ljava/lang/String;
  #132 = Utf8               (Ljava/lang/String;)Lscala/Option;
  #133 = Utf8               (Ljava/lang/String;)Lscala/Option<Lcoursier/core/Reconciliation;>;
  #134 = Utf8               input
  #135 = Utf8               hashCode
  #136 = Utf8               ()I
  #137 = NameAndType        #135:#136     // hashCode:()I
  #138 = Methodref          #120.#137     // java/lang/String.hashCode:()I
  #139 = Utf8               semver
  #140 = String             #139          // semver
  #141 = Utf8               equals
  #142 = NameAndType        #141:#107     // equals:(Ljava/lang/Object;)Z
  #143 = Methodref          #120.#142     // java/lang/String.equals:(Ljava/lang/Object;)Z
  #144 = Utf8               strict
  #145 = String             #144          // strict
  #146 = Utf8               relaxed
  #147 = String             #146          // relaxed
  #148 = Utf8               default
  #149 = String             #148          // default
  #150 = Utf8               Lcoursier/core/Reconciliation$Default$;
  #151 = NameAndType        #22:#150      // MODULE$:Lcoursier/core/Reconciliation$Default$;
  #152 = Fieldref           #7.#151       // coursier/core/Reconciliation$Default$.MODULE$:Lcoursier/core/Reconciliation$Default$;
  #153 = Utf8               Lcoursier/core/Reconciliation$Relaxed$;
  #154 = NameAndType        #22:#153      // MODULE$:Lcoursier/core/Reconciliation$Relaxed$;
  #155 = Fieldref           #12.#154      // coursier/core/Reconciliation$Relaxed$.MODULE$:Lcoursier/core/Reconciliation$Relaxed$;
  #156 = Utf8               Lcoursier/core/Reconciliation$Strict$;
  #157 = NameAndType        #22:#156      // MODULE$:Lcoursier/core/Reconciliation$Strict$;
  #158 = Fieldref           #16.#157      // coursier/core/Reconciliation$Strict$.MODULE$:Lcoursier/core/Reconciliation$Strict$;
  #159 = Utf8               Lcoursier/core/Reconciliation$SemVer$;
  #160 = NameAndType        #22:#159      // MODULE$:Lcoursier/core/Reconciliation$SemVer$;
  #161 = Fieldref           #14.#160      // coursier/core/Reconciliation$SemVer$.MODULE$:Lcoursier/core/Reconciliation$SemVer$;
  #162 = Utf8               $anonfun$splitStandard$1
  #163 = Utf8               (Ljava/lang/String;)Z
  #164 = Utf8               x0$1
  #165 = Methodref          #4.#27        // java/lang/Object."<init>":()V
  #166 = NameAndType        #162:#163     // $anonfun$splitStandard$1:(Ljava/lang/String;)Z
  #167 = Methodref          #2.#166       // coursier/core/Reconciliation$.$anonfun$splitStandard$1:(Ljava/lang/String;)Z
  #168 = Utf8               scala/runtime/BoxesRunTime
  #169 = Class              #168          // scala/runtime/BoxesRunTime
  #170 = Utf8               boxToBoolean
  #171 = Utf8               (Z)Ljava/lang/Boolean;
  #172 = NameAndType        #170:#171     // boxToBoolean:(Z)Ljava/lang/Boolean;
  #173 = Methodref          #169.#172     // scala/runtime/BoxesRunTime.boxToBoolean:(Z)Ljava/lang/Boolean;
  #174 = Utf8               $deserializeLambda$
  #175 = Utf8               (Ljava/lang/invoke/SerializedLambda;)Ljava/lang/Object;
  #176 = Utf8               scala/runtime/LambdaDeserialize
  #177 = Class              #176          // scala/runtime/LambdaDeserialize
  #178 = Utf8               bootstrap
  #179 = Utf8               (Ljava/lang/invoke/MethodHandles$Lookup;Ljava/lang/String;Ljava/lang/invoke/MethodType;[Ljava/lang/invoke/MethodHandle;)Ljava/lang/invoke/CallSite;
  #180 = NameAndType        #178:#179     // bootstrap:(Ljava/lang/invoke/MethodHandles$Lookup;Ljava/lang/String;Ljava/lang/invoke/MethodType;[Ljava/lang/invoke/MethodHandle;)Ljava/lang/invoke/CallSite;
  #181 = Methodref          #177.#180     // scala/runtime/LambdaDeserialize.bootstrap:(Ljava/lang/invoke/MethodHandles$Lookup;Ljava/lang/String;Ljava/lang/invoke/MethodType;[Ljava/lang/invoke/MethodHandle;)Ljava/lang/invoke/CallSite;
  #182 = MethodHandle       6:#181        // REF_invokeStatic scala/runtime/LambdaDeserialize.bootstrap:(Ljava/lang/invoke/MethodHandles$Lookup;Ljava/lang/String;Ljava/lang/invoke/MethodType;[Ljava/lang/invoke/MethodHandle;)Ljava/lang/invoke/CallSite;
  #183 = Utf8               lambdaDeserialize
  #184 = NameAndType        #183:#175     // lambdaDeserialize:(Ljava/lang/invoke/SerializedLambda;)Ljava/lang/Object;
  #185 = InvokeDynamic      #1:#184       // #1:lambdaDeserialize:(Ljava/lang/invoke/SerializedLambda;)Ljava/lang/Object;
  #186 = Utf8               Code
  #187 = Utf8               LineNumberTable
  #188 = Utf8               LocalVariableTable
  #189 = Utf8               Signature
  #190 = Utf8               MethodParameters
  #191 = Utf8               StackMapTable
  #192 = Utf8               InnerClasses
  #193 = Utf8               SourceFile
  #194 = Utf8               BootstrapMethods
  #195 = Utf8               ScalaInlineInfo
  #196 = Utf8               Scala
{
  public static final coursier.core.Reconciliation$ MODULE$;
    descriptor: Lcoursier/core/Reconciliation$;
    flags: (0x0019) ACC_PUBLIC, ACC_STATIC, ACC_FINAL

  public static {};
    descriptor: ()V
    flags: (0x0009) ACC_PUBLIC, ACC_STATIC
    Code:
      stack=2, locals=0, args_size=0
         0: new           #2                  // class coursier/core/Reconciliation$
         3: dup
         4: invokespecial #28                 // Method "<init>":()V
         7: putstatic     #30                 // Field MODULE$:Lcoursier/core/Reconciliation$;
        10: return
      LineNumberTable:
        line 15: 0

  private final java.lang.String LatestIntegration();
    descriptor: ()Ljava/lang/String;
    flags: (0x0012) ACC_PRIVATE, ACC_FINAL
    Code:
      stack=1, locals=1, args_size=1
         0: ldc           #34                 // String latest.integration
         2: areturn
      LocalVariableTable:
        Start  Length  Slot  Name   Signature
            0       3     0  this   Lcoursier/core/Reconciliation$;

  private final java.lang.String LatestRelease();
    descriptor: ()Ljava/lang/String;
    flags: (0x0012) ACC_PRIVATE, ACC_FINAL
    Code:
      stack=1, locals=1, args_size=1
         0: ldc           #38                 // String latest.release
         2: areturn
      LocalVariableTable:
        Start  Length  Slot  Name   Signature
            0       3     0  this   Lcoursier/core/Reconciliation$;

  private final java.lang.String LatestStable();
    descriptor: ()Ljava/lang/String;
    flags: (0x0012) ACC_PRIVATE, ACC_FINAL
    Code:
      stack=1, locals=1, args_size=1
         0: ldc           #41                 // String latest.stable
         2: areturn
      LocalVariableTable:
        Start  Length  Slot  Name   Signature
            0       3     0  this   Lcoursier/core/Reconciliation$;

  public scala.Tuple2<scala.collection.immutable.Seq<java.lang.String>, scala.collection.immutable.Seq<java.lang.String>> coursier$core$Reconciliation$$splitStandard(scala.collection.immutable.Seq<java.lang.String>);
    descriptor: (Lscala/collection/immutable/Seq;)Lscala/Tuple2;
    flags: (0x0001) ACC_PUBLIC
    Code:
      stack=2, locals=2, args_size=2
         0: aload_1
         1: invokeinterface #51,  1           // InterfaceMethod scala/collection/immutable/Seq.distinct:()Ljava/lang/Object;
         6: checkcast     #53                 // class scala/collection/IterableOps
         9: invokedynamic #74,  0             // InvokeDynamic #0:apply:()Lscala/Function1;
        14: invokeinterface #78,  2           // InterfaceMethod scala/collection/IterableOps.partition:(Lscala/Function1;)Lscala/Tuple2;
        19: areturn
      LineNumberTable:
        line 21: 0
      LocalVariableTable:
        Start  Length  Slot  Name   Signature
            0      20     0  this   Lcoursier/core/Reconciliation$;
            0      20     1 versions   Lscala/collection/immutable/Seq;
    Signature: #44                          // (Lscala/collection/immutable/Seq<Ljava/lang/String;>;)Lscala/Tuple2<Lscala/collection/immutable/Seq<Ljava/lang/String;>;Lscala/collection/immutable/Seq<Ljava/lang/String;>;>;
    MethodParameters:
      Name                           Flags
      versions                       final

  public scala.Option<java.lang.String> coursier$core$Reconciliation$$retainLatestOpt(scala.collection.immutable.Seq<java.lang.String>);
    descriptor: (Lscala/collection/immutable/Seq;)Lscala/Option;
    flags: (0x0001) ACC_PUBLIC
    Code:
      stack=3, locals=4, args_size=2
         0: aload_1
         1: invokeinterface #87,  1           // InterfaceMethod scala/collection/immutable/Seq.isEmpty:()Z
         6: ifeq          15
         9: getstatic     #92                 // Field scala/None$.MODULE$:Lscala/None$;
        12: goto          99
        15: aload_1
        16: iconst_1
        17: invokeinterface #96,  2           // InterfaceMethod scala/collection/immutable/Seq.lengthCompare:(I)I
        22: iconst_0
        23: if_icmpne     35
        26: aload_1
        27: invokeinterface #100,  1          // InterfaceMethod scala/collection/immutable/Seq.headOption:()Lscala/Option;
        32: goto          99
        35: aload_1
        36: invokeinterface #104,  1          // InterfaceMethod scala/collection/immutable/Seq.toSet:()Lscala/collection/immutable/Set;
        41: astore_2
        42: aload_2
        43: ldc           #34                 // String latest.integration
        45: invokeinterface #109,  2          // InterfaceMethod scala/collection/immutable/Set.apply:(Ljava/lang/Object;)Z
        50: ifeq          58
        53: ldc           #34                 // String latest.integration
        55: goto          90
        58: aload_2
        59: ldc           #38                 // String latest.release
        61: invokeinterface #109,  2          // InterfaceMethod scala/collection/immutable/Set.apply:(Ljava/lang/Object;)Z
        66: ifeq          74
        69: ldc           #38                 // String latest.release
        71: goto          90
        74: getstatic     #114                // Field scala/Predef$.MODULE$:Lscala/Predef$;
        77: aload_2
        78: ldc           #41                 // String latest.stable
        80: invokeinterface #109,  2          // InterfaceMethod scala/collection/immutable/Set.apply:(Ljava/lang/Object;)Z
        85: invokevirtual #118                // Method scala/Predef$.assert:(Z)V
        88: ldc           #41                 // String latest.stable
        90: astore_3
        91: new           #122                // class scala/Some
        94: dup
        95: aload_3
        96: invokespecial #125                // Method scala/Some."<init>":(Ljava/lang/Object;)V
        99: areturn
      StackMapTable: number_of_entries = 6
        frame_type = 15 /* same */
        frame_type = 19 /* same */
        frame_type = 252 /* append */
          offset_delta = 22
          locals = [ class scala/collection/immutable/Set ]
        frame_type = 15 /* same */
        frame_type = 79 /* same_locals_1_stack_item */
          stack = [ class java/lang/String ]
        frame_type = 255 /* full_frame */
          offset_delta = 8
          locals = [ class coursier/core/Reconciliation$, class scala/collection/immutable/Seq ]
          stack = [ class scala/Option ]
      LineNumberTable:
        line 29: 0
        line 30: 15
        line 32: 35
        line 34: 42
        line 35: 53
        line 36: 58
        line 37: 69
        line 40: 74
        line 41: 88
        line 43: 91
      LocalVariableTable:
        Start  Length  Slot  Name   Signature
           42      57     2   set   Lscala/collection/immutable/Set;
           91       8     3 retained   Ljava/lang/String;
            0     100     0  this   Lcoursier/core/Reconciliation$;
            0     100     1 latests   Lscala/collection/immutable/Seq;
    Signature: #82                          // (Lscala/collection/immutable/Seq<Ljava/lang/String;>;)Lscala/Option<Ljava/lang/String;>;
    MethodParameters:
      Name                           Flags
      latests                        final

  public scala.Option<coursier.core.Reconciliation> apply(java.lang.String);
    descriptor: (Ljava/lang/String;)Lscala/Option;
    flags: (0x0001) ACC_PUBLIC
    Code:
      stack=3, locals=4, args_size=2
         0: aload_1
         1: astore_3
         2: aload_3
         3: ifnonnull     10
         6: iconst_0
         7: goto          14
        10: aload_3
        11: invokevirtual #138                // Method java/lang/String.hashCode:()I
        14: lookupswitch  { // 4
              -905975448: 56
              -891986231: 71
              1090497327: 86
              1544803905: 101
                 default: 116
            }
        56: ldc           #140                // String semver
        58: aload_3
        59: invokevirtual #143                // Method java/lang/String.equals:(Ljava/lang/Object;)Z
        62: ifeq          68
        65: goto          161
        68: goto          175
        71: ldc           #145                // String strict
        73: aload_3
        74: invokevirtual #143                // Method java/lang/String.equals:(Ljava/lang/Object;)Z
        77: ifeq          83
        80: goto          147
        83: goto          175
        86: ldc           #147                // String relaxed
        88: aload_3
        89: invokevirtual #143                // Method java/lang/String.equals:(Ljava/lang/Object;)Z
        92: ifeq          98
        95: goto          133
        98: goto          175
       101: ldc           #149                // String default
       103: aload_3
       104: invokevirtual #143                // Method java/lang/String.equals:(Ljava/lang/Object;)Z
       107: ifeq          113
       110: goto          119
       113: goto          175
       116: goto          175
       119: new           #122                // class scala/Some
       122: dup
       123: getstatic     #152                // Field coursier/core/Reconciliation$Default$.MODULE$:Lcoursier/core/Reconciliation$Default$;
       126: invokespecial #125                // Method scala/Some."<init>":(Ljava/lang/Object;)V
       129: astore_2
       130: goto          182
       133: new           #122                // class scala/Some
       136: dup
       137: getstatic     #155                // Field coursier/core/Reconciliation$Relaxed$.MODULE$:Lcoursier/core/Reconciliation$Relaxed$;
       140: invokespecial #125                // Method scala/Some."<init>":(Ljava/lang/Object;)V
       143: astore_2
       144: goto          182
       147: new           #122                // class scala/Some
       150: dup
       151: getstatic     #158                // Field coursier/core/Reconciliation$Strict$.MODULE$:Lcoursier/core/Reconciliation$Strict$;
       154: invokespecial #125                // Method scala/Some."<init>":(Ljava/lang/Object;)V
       157: astore_2
       158: goto          182
       161: new           #122                // class scala/Some
       164: dup
       165: getstatic     #161                // Field coursier/core/Reconciliation$SemVer$.MODULE$:Lcoursier/core/Reconciliation$SemVer$;
       168: invokespecial #125                // Method scala/Some."<init>":(Ljava/lang/Object;)V
       171: astore_2
       172: goto          182
       175: getstatic     #92                 // Field scala/None$.MODULE$:Lscala/None$;
       178: astore_2
       179: goto          182
       182: aload_2
       183: areturn
      StackMapTable: number_of_entries = 17
        frame_type = 253 /* append */
          offset_delta = 10
          locals = [ top, class java/lang/String ]
        frame_type = 67 /* same_locals_1_stack_item */
          stack = [ int ]
        frame_type = 41 /* same */
        frame_type = 11 /* same */
        frame_type = 2 /* same */
        frame_type = 11 /* same */
        frame_type = 2 /* same */
        frame_type = 11 /* same */
        frame_type = 2 /* same */
        frame_type = 11 /* same */
        frame_type = 2 /* same */
        frame_type = 2 /* same */
        frame_type = 13 /* same */
        frame_type = 13 /* same */
        frame_type = 13 /* same */
        frame_type = 13 /* same */
        frame_type = 255 /* full_frame */
          offset_delta = 6
          locals = [ class coursier/core/Reconciliation$, class java/lang/String, class scala/Option, class java/lang/String ]
          stack = []
      LineNumberTable:
        line 137: 0
        line 141: 56
        line 137: 68
        line 140: 71
        line 137: 83
        line 139: 86
        line 137: 98
        line 138: 101
        line 137: 113
        line 138: 119
        line 139: 133
        line 140: 147
        line 141: 161
        line 142: 175
        line 137: 182
      LocalVariableTable:
        Start  Length  Slot  Name   Signature
            0     184     0  this   Lcoursier/core/Reconciliation$;
            0     184     1 input   Ljava/lang/String;
    Signature: #133                         // (Ljava/lang/String;)Lscala/Option<Lcoursier/core/Reconciliation;>;
    MethodParameters:
      Name                           Flags
      input                          final

  public static final boolean $anonfun$splitStandard$1(java.lang.String);
    descriptor: (Ljava/lang/String;)Z
    flags: (0x1019) ACC_PUBLIC, ACC_STATIC, ACC_FINAL, ACC_SYNTHETIC
    Code:
      stack=2, locals=3, args_size=1
         0: aload_0
         1: astore_2
         2: aload_2
         3: ifnonnull     10
         6: iconst_0
         7: goto          14
        10: aload_2
        11: invokevirtual #138                // Method java/lang/String.hashCode:()I
        14: lookupswitch  { // 3
             -1150857056: 48
              1483385325: 63
              1529047938: 78
                 default: 93
            }
        48: ldc           #38                 // String latest.release
        50: aload_2
        51: invokevirtual #143                // Method java/lang/String.equals:(Ljava/lang/Object;)Z
        54: ifeq          60
        57: goto          101
        60: goto          111
        63: ldc           #34                 // String latest.integration
        65: aload_2
        66: invokevirtual #143                // Method java/lang/String.equals:(Ljava/lang/Object;)Z
        69: ifeq          75
        72: goto          96
        75: goto          111
        78: ldc           #41                 // String latest.stable
        80: aload_2
        81: invokevirtual #143                // Method java/lang/String.equals:(Ljava/lang/Object;)Z
        84: ifeq          90
        87: goto          106
        90: goto          111
        93: goto          111
        96: iconst_0
        97: istore_1
        98: goto          116
       101: iconst_0
       102: istore_1
       103: goto          116
       106: iconst_0
       107: istore_1
       108: goto          116
       111: iconst_1
       112: istore_1
       113: goto          116
       116: iload_1
       117: ireturn
      StackMapTable: number_of_entries = 14
        frame_type = 253 /* append */
          offset_delta = 10
          locals = [ top, class java/lang/String ]
        frame_type = 67 /* same_locals_1_stack_item */
          stack = [ int ]
        frame_type = 33 /* same */
        frame_type = 11 /* same */
        frame_type = 2 /* same */
        frame_type = 11 /* same */
        frame_type = 2 /* same */
        frame_type = 11 /* same */
        frame_type = 2 /* same */
        frame_type = 2 /* same */
        frame_type = 4 /* same */
        frame_type = 4 /* same */
        frame_type = 4 /* same */
        frame_type = 255 /* full_frame */
          offset_delta = 4
          locals = [ class java/lang/String, int, class java/lang/String ]
          stack = []
      LineNumberTable:
        line 21: 0
        line 23: 48
        line 21: 60
        line 22: 63
        line 21: 75
        line 24: 78
        line 21: 90
        line 22: 96
        line 23: 101
        line 24: 106
        line 25: 111
        line 21: 116
      LocalVariableTable:
        Start  Length  Slot  Name   Signature
            0     118     0  x0$1   Ljava/lang/String;
    MethodParameters:
      Name                           Flags
      x0$1                           final

  private coursier.core.Reconciliation$();
    descriptor: ()V
    flags: (0x0002) ACC_PRIVATE
    Code:
      stack=1, locals=1, args_size=1
         0: aload_0
         1: invokespecial #165                // Method java/lang/Object."<init>":()V
         4: return
      LineNumberTable:
        line 144: 0
        line 15: 4
      LocalVariableTable:
        Start  Length  Slot  Name   Signature
            0       5     0  this   Lcoursier/core/Reconciliation$;

  public static final java.lang.Object $anonfun$splitStandard$1$adapted(java.lang.String);
    descriptor: (Ljava/lang/String;)Ljava/lang/Object;
    flags: (0x1019) ACC_PUBLIC, ACC_STATIC, ACC_FINAL, ACC_SYNTHETIC
    Code:
      stack=1, locals=1, args_size=1
         0: aload_0
         1: invokestatic  #167                // Method $anonfun$splitStandard$1:(Ljava/lang/String;)Z
         4: invokestatic  #173                // Method scala/runtime/BoxesRunTime.boxToBoolean:(Z)Ljava/lang/Boolean;
         7: areturn
      LineNumberTable:
        line 21: 0
      LocalVariableTable:
        Start  Length  Slot  Name   Signature
            0       8     0  x0$1   Ljava/lang/String;
    MethodParameters:
      Name                           Flags
      x0$1                           final

  private static java.lang.Object $deserializeLambda$(java.lang.invoke.SerializedLambda);
    descriptor: (Ljava/lang/invoke/SerializedLambda;)Ljava/lang/Object;
    flags: (0x100a) ACC_PRIVATE, ACC_STATIC, ACC_SYNTHETIC
    Code:
      stack=1, locals=1, args_size=1
         0: aload_0
         1: invokedynamic #185,  0            // InvokeDynamic #1:lambdaDeserialize:(Ljava/lang/invoke/SerializedLambda;)Ljava/lang/Object;
         6: areturn
}
InnerClasses:
  public static #10= #7 of #9;            // =class coursier/core/Reconciliation$Default$ of class coursier/core/Reconciliation
  public static #10= #12 of #9;           // =class coursier/core/Reconciliation$Relaxed$ of class coursier/core/Reconciliation
  public static #10= #14 of #9;           // =class coursier/core/Reconciliation$SemVer$ of class coursier/core/Reconciliation
  public static #10= #16 of #9;           // =class coursier/core/Reconciliation$Strict$ of class coursier/core/Reconciliation
  public static final #21= #18 of #20;    // Lookup=class java/lang/invoke/MethodHandles$Lookup of class java/lang/invoke/MethodHandles
SourceFile: "Reconciliation.scala"
BootstrapMethods:
  0: #70 REF_invokeStatic java/lang/invoke/LambdaMetafactory.altMetafactory:(Ljava/lang/invoke/MethodHandles$Lookup;Ljava/lang/String;Ljava/lang/invoke/MethodType;[Ljava/lang/Object;)Ljava/lang/invoke/CallSite;
    Method arguments:
      #55 (Ljava/lang/Object;)Ljava/lang/Object;
      #60 REF_invokeStatic coursier/core/Reconciliation$.$anonfun$splitStandard$1$adapted:(Ljava/lang/String;)Ljava/lang/Object;
      #61 (Ljava/lang/String;)Ljava/lang/Object;
      #62 5
      #63 1
      #61 (Ljava/lang/String;)Ljava/lang/Object;
  1: #182 REF_invokeStatic scala/runtime/LambdaDeserialize.bootstrap:(Ljava/lang/invoke/MethodHandles$Lookup;Ljava/lang/String;Ljava/lang/invoke/MethodType;[Ljava/lang/invoke/MethodHandle;)Ljava/lang/invoke/CallSite;
    Method arguments:
      #60 REF_invokeStatic coursier/core/Reconciliation$.$anonfun$splitStandard$1$adapted:(Ljava/lang/String;)Ljava/lang/Object;
  ScalaInlineInfo: length = 0x31 (unknown attribute)
   01 01 00 09 00 A5 00 A6 01 00 3B 00 3C 01 00 1D
   00 1C 01 00 22 00 23 01 00 27 00 23 01 00 2A 00
   23 01 00 4A 00 87 01 00 53 00 54 01 00 2D 00 2E
   01
  Scala: length = 0x0 (unknown attribute)

