Classfile /Users/mw/Projects/slang-braindump/.jar/jar8/assemble/slang-braindump/assemble/content/coursier/core/Repository$Complete$Input$Ver.class
  Last modified May 29, 2022; size 4656 bytes
  SHA-256 checksum d1434ce170479bd4fe33c76d4c481023dafb4c6e84e9abfc49f7f43bbb3e5dbd
  Compiled from "Repository.scala"
public final class coursier.core.Repository$Complete$Input$Ver extends coursier.core.Repository$Complete$Input
  minor version: 0
  major version: 52
  flags: (0x0031) ACC_PUBLIC, ACC_FINAL, ACC_SUPER
  this_class: #2                          // coursier/core/Repository$Complete$Input$Ver
  super_class: #4                         // coursier/core/Repository$Complete$Input
  interfaces: 0, fields: 3, methods: 18, attributes: 4
Constant pool:
    #1 = Utf8               coursier/core/Repository$Complete$Input$Ver
    #2 = Class              #1            // coursier/core/Repository$Complete$Input$Ver
    #3 = Utf8               coursier/core/Repository$Complete$Input
    #4 = Class              #3            // coursier/core/Repository$Complete$Input
    #5 = Utf8               Repository.scala
    #6 = Utf8               coursier/core/Repository$Complete$
    #7 = Class              #6            // coursier/core/Repository$Complete$
    #8 = Utf8               coursier/core/Repository
    #9 = Class              #8            // coursier/core/Repository
   #10 = Utf8
   #11 = Utf8               Input
   #12 = Utf8               coursier/core/Repository$Complete$Input$
   #13 = Class              #12           // coursier/core/Repository$Complete$Input$
   #14 = Utf8               coursier/core/Repository$Complete$Input$Name
   #15 = Class              #14           // coursier/core/Repository$Complete$Input$Name
   #16 = Utf8               Name
   #17 = Utf8               coursier/core/Repository$Complete$Input$Name$
   #18 = Class              #17           // coursier/core/Repository$Complete$Input$Name$
   #19 = Utf8               coursier/core/Repository$Complete$Input$Org
   #20 = Class              #19           // coursier/core/Repository$Complete$Input$Org
   #21 = Utf8               Org
   #22 = Utf8               Ver
   #23 = Utf8               module
   #24 = Utf8               Lcoursier/core/Module;
   #25 = Utf8               input
   #26 = Utf8               Ljava/lang/String;
   #27 = Utf8               from
   #28 = Utf8               I
   #29 = Utf8               ()Lcoursier/core/Module;
   #30 = NameAndType        #23:#24       // module:Lcoursier/core/Module;
   #31 = Fieldref           #2.#30        // coursier/core/Repository$Complete$Input$Ver.module:Lcoursier/core/Module;
   #32 = Utf8               this
   #33 = Utf8               Lcoursier/core/Repository$Complete$Input$Ver;
   #34 = Utf8               ()Ljava/lang/String;
   #35 = NameAndType        #25:#26       // input:Ljava/lang/String;
   #36 = Fieldref           #2.#35        // coursier/core/Repository$Complete$Input$Ver.input:Ljava/lang/String;
   #37 = Utf8               ()I
   #38 = NameAndType        #27:#28       // from:I
   #39 = Fieldref           #2.#38        // coursier/core/Repository$Complete$Input$Ver.from:I
   #40 = Utf8               orgInput
   #41 = Utf8               ()Lcoursier/core/Repository$Complete$Input$Org;
   #42 = Utf8               nameInput
   #43 = Utf8               ()Lcoursier/core/Repository$Complete$Input$Name;
   #44 = NameAndType        #42:#43       // nameInput:()Lcoursier/core/Repository$Complete$Input$Name;
   #45 = Methodref          #2.#44        // coursier/core/Repository$Complete$Input$Ver.nameInput:()Lcoursier/core/Repository$Complete$Input$Name;
   #46 = NameAndType        #40:#41       // orgInput:()Lcoursier/core/Repository$Complete$Input$Org;
   #47 = Methodref          #15.#46       // coursier/core/Repository$Complete$Input$Name.orgInput:()Lcoursier/core/Repository$Complete$Input$Org;
   #48 = NameAndType        #23:#29       // module:()Lcoursier/core/Module;
   #49 = Methodref          #2.#48        // coursier/core/Repository$Complete$Input$Ver.module:()Lcoursier/core/Module;
   #50 = Utf8               coursier/core/Module
   #51 = Class              #50           // coursier/core/Module
   #52 = Utf8               repr
   #53 = NameAndType        #52:#34       // repr:()Ljava/lang/String;
   #54 = Methodref          #51.#53       // coursier/core/Module.repr:()Ljava/lang/String;
   #55 = Utf8               MODULE$
   #56 = Utf8               Lcoursier/core/Repository$Complete$Input$Name$;
   #57 = NameAndType        #55:#56       // MODULE$:Lcoursier/core/Repository$Complete$Input$Name$;
   #58 = Fieldref           #18.#57       // coursier/core/Repository$Complete$Input$Name$.MODULE$:Lcoursier/core/Repository$Complete$Input$Name$;
   #59 = Utf8               organization
   #60 = NameAndType        #59:#34       // organization:()Ljava/lang/String;
   #61 = Methodref          #51.#60       // coursier/core/Module.organization:()Ljava/lang/String;
   #62 = Utf8               java/lang/String
   #63 = Class              #62           // java/lang/String
   #64 = Utf8               length
   #65 = NameAndType        #64:#37       // length:()I
   #66 = Methodref          #63.#65       // java/lang/String.length:()I
   #67 = String             #10           //
   #68 = Utf8               apply
   #69 = Utf8               (Ljava/lang/String;Ljava/lang/String;ILjava/lang/String;)Lcoursier/core/Repository$Complete$Input$Name;
   #70 = NameAndType        #68:#69       // apply:(Ljava/lang/String;Ljava/lang/String;ILjava/lang/String;)Lcoursier/core/Repository$Complete$Input$Name;
   #71 = Methodref          #18.#70       // coursier/core/Repository$Complete$Input$Name$.apply:(Ljava/lang/String;Ljava/lang/String;ILjava/lang/String;)Lcoursier/core/Repository$Complete$Input$Name;
   #72 = Utf8               truncatedInput
   #73 = Utf8               withModule
   #74 = Utf8               (Lcoursier/core/Module;)Lcoursier/core/Repository$Complete$Input$Ver;
   #75 = NameAndType        #25:#34       // input:()Ljava/lang/String;
   #76 = Methodref          #2.#75        // coursier/core/Repository$Complete$Input$Ver.input:()Ljava/lang/String;
   #77 = NameAndType        #27:#37       // from:()I
   #78 = Methodref          #2.#77        // coursier/core/Repository$Complete$Input$Ver.from:()I
   #79 = Utf8               <init>
   #80 = Utf8               (Lcoursier/core/Module;Ljava/lang/String;I)V
   #81 = NameAndType        #79:#80       // "<init>":(Lcoursier/core/Module;Ljava/lang/String;I)V
   #82 = Methodref          #2.#81        // coursier/core/Repository$Complete$Input$Ver."<init>":(Lcoursier/core/Module;Ljava/lang/String;I)V
   #83 = Utf8               withInput
   #84 = Utf8               (Ljava/lang/String;)Lcoursier/core/Repository$Complete$Input$Ver;
   #85 = Utf8               withFrom
   #86 = Utf8               (I)Lcoursier/core/Repository$Complete$Input$Ver;
   #87 = Utf8               toString
   #88 = Utf8               java/lang/StringBuilder
   #89 = Class              #88           // java/lang/StringBuilder
   #90 = Utf8               Ver(
   #91 = String             #90           // Ver(
   #92 = Utf8               (Ljava/lang/String;)V
   #93 = NameAndType        #79:#92       // "<init>":(Ljava/lang/String;)V
   #94 = Methodref          #89.#93       // java/lang/StringBuilder."<init>":(Ljava/lang/String;)V
   #95 = Utf8               valueOf
   #96 = Utf8               (Ljava/lang/Object;)Ljava/lang/String;
   #97 = NameAndType        #95:#96       // valueOf:(Ljava/lang/Object;)Ljava/lang/String;
   #98 = Methodref          #63.#97       // java/lang/String.valueOf:(Ljava/lang/Object;)Ljava/lang/String;
   #99 = Utf8               append
  #100 = Utf8               (Ljava/lang/String;)Ljava/lang/StringBuilder;
  #101 = NameAndType        #99:#100      // append:(Ljava/lang/String;)Ljava/lang/StringBuilder;
  #102 = Methodref          #89.#101      // java/lang/StringBuilder.append:(Ljava/lang/String;)Ljava/lang/StringBuilder;
  #103 = Utf8               ,
  #104 = String             #103          // ,
  #105 = Utf8               (I)Ljava/lang/String;
  #106 = NameAndType        #95:#105      // valueOf:(I)Ljava/lang/String;
  #107 = Methodref          #63.#106      // java/lang/String.valueOf:(I)Ljava/lang/String;
  #108 = Utf8               )
  #109 = String             #108          // )
  #110 = NameAndType        #87:#34       // toString:()Ljava/lang/String;
  #111 = Methodref          #89.#110      // java/lang/StringBuilder.toString:()Ljava/lang/String;
  #112 = Utf8               b
  #113 = Utf8               Ljava/lang/StringBuilder;
  #114 = Utf8               canEqual
  #115 = Utf8               (Ljava/lang/Object;)Z
  #116 = Utf8               obj
  #117 = Utf8               Ljava/lang/Object;
  #118 = Utf8               equals
  #119 = NameAndType        #114:#115     // canEqual:(Ljava/lang/Object;)Z
  #120 = Methodref          #2.#119       // coursier/core/Repository$Complete$Input$Ver.canEqual:(Ljava/lang/Object;)Z
  #121 = Utf8               java/lang/Object
  #122 = Class              #121          // java/lang/Object
  #123 = NameAndType        #118:#115     // equals:(Ljava/lang/Object;)Z
  #124 = Methodref          #122.#123     // java/lang/Object.equals:(Ljava/lang/Object;)Z
  #125 = Utf8               other
  #126 = Utf8               hashCode
  #127 = String             #22           // Ver
  #128 = Utf8               scala/runtime/Statics
  #129 = Class              #128          // scala/runtime/Statics
  #130 = Utf8               anyHash
  #131 = Utf8               (Ljava/lang/Object;)I
  #132 = NameAndType        #130:#131     // anyHash:(Ljava/lang/Object;)I
  #133 = Methodref          #129.#132     // scala/runtime/Statics.anyHash:(Ljava/lang/Object;)I
  #134 = Utf8               code
  #135 = Utf8               tuple
  #136 = Utf8               ()Lscala/Tuple3;
  #137 = Utf8               ()Lscala/Tuple3<Lcoursier/core/Module;Ljava/lang/String;Ljava/lang/Object;>;
  #138 = Utf8               scala/Tuple3
  #139 = Class              #138          // scala/Tuple3
  #140 = Utf8               scala/runtime/BoxesRunTime
  #141 = Class              #140          // scala/runtime/BoxesRunTime
  #142 = Utf8               boxToInteger
  #143 = Utf8               (I)Ljava/lang/Integer;
  #144 = NameAndType        #142:#143     // boxToInteger:(I)Ljava/lang/Integer;
  #145 = Methodref          #141.#144     // scala/runtime/BoxesRunTime.boxToInteger:(I)Ljava/lang/Integer;
  #146 = Utf8               (Ljava/lang/Object;Ljava/lang/Object;Ljava/lang/Object;)V
  #147 = NameAndType        #79:#146      // "<init>":(Ljava/lang/Object;Ljava/lang/Object;Ljava/lang/Object;)V
  #148 = Methodref          #139.#147     // scala/Tuple3."<init>":(Ljava/lang/Object;Ljava/lang/Object;Ljava/lang/Object;)V
  #149 = Utf8               productPrefix
  #150 = Utf8               productArity
  #151 = Utf8               productElement
  #152 = Utf8               (I)Ljava/lang/Object;
  #153 = Utf8               n
  #154 = Utf8               java/lang/IndexOutOfBoundsException
  #155 = Class              #154          // java/lang/IndexOutOfBoundsException
  #156 = Methodref          #122.#110     // java/lang/Object.toString:()Ljava/lang/String;
  #157 = Methodref          #155.#93      // java/lang/IndexOutOfBoundsException."<init>":(Ljava/lang/String;)V
  #158 = Utf8               productElementName
  #159 = String             #23           // module
  #160 = String             #25           // input
  #161 = String             #27           // from
  #162 = Utf8               ()V
  #163 = NameAndType        #79:#162      // "<init>":()V
  #164 = Methodref          #4.#163       // coursier/core/Repository$Complete$Input."<init>":()V
  #165 = Utf8               Code
  #166 = Utf8               LineNumberTable
  #167 = Utf8               LocalVariableTable
  #168 = Utf8               MethodParameters
  #169 = Utf8               StackMapTable
  #170 = Utf8               Signature
  #171 = Utf8               InnerClasses
  #172 = Utf8               SourceFile
  #173 = Utf8               ScalaInlineInfo
  #174 = Utf8               Scala
{
  private final coursier.core.Module module;
    descriptor: Lcoursier/core/Module;
    flags: (0x0012) ACC_PRIVATE, ACC_FINAL

  private final java.lang.String input;
    descriptor: Ljava/lang/String;
    flags: (0x0012) ACC_PRIVATE, ACC_FINAL

  private final int from;
    descriptor: I
    flags: (0x0012) ACC_PRIVATE, ACC_FINAL

  public coursier.core.Module module();
    descriptor: ()Lcoursier/core/Module;
    flags: (0x0001) ACC_PUBLIC
    Code:
      stack=1, locals=1, args_size=1
         0: aload_0
         1: getfield      #31                 // Field module:Lcoursier/core/Module;
         4: areturn
      LineNumberTable:
        line 260: 0
      LocalVariableTable:
        Start  Length  Slot  Name   Signature
            0       5     0  this   Lcoursier/core/Repository$Complete$Input$Ver;

  public java.lang.String input();
    descriptor: ()Ljava/lang/String;
    flags: (0x0001) ACC_PUBLIC
    Code:
      stack=1, locals=1, args_size=1
         0: aload_0
         1: getfield      #36                 // Field input:Ljava/lang/String;
         4: areturn
      LineNumberTable:
        line 260: 0
      LocalVariableTable:
        Start  Length  Slot  Name   Signature
            0       5     0  this   Lcoursier/core/Repository$Complete$Input$Ver;

  public int from();
    descriptor: ()I
    flags: (0x0001) ACC_PUBLIC
    Code:
      stack=1, locals=1, args_size=1
         0: aload_0
         1: getfield      #39                 // Field from:I
         4: ireturn
      LineNumberTable:
        line 260: 0
      LocalVariableTable:
        Start  Length  Slot  Name   Signature
            0       5     0  this   Lcoursier/core/Repository$Complete$Input$Ver;

  public coursier.core.Repository$Complete$Input$Org orgInput();
    descriptor: ()Lcoursier/core/Repository$Complete$Input$Org;
    flags: (0x0001) ACC_PUBLIC
    Code:
      stack=1, locals=1, args_size=1
         0: aload_0
         1: invokevirtual #45                 // Method nameInput:()Lcoursier/core/Repository$Complete$Input$Name;
         4: invokevirtual #47                 // Method coursier/core/Repository$Complete$Input$Name.orgInput:()Lcoursier/core/Repository$Complete$Input$Org;
         7: areturn
      LineNumberTable:
        line 262: 0
      LocalVariableTable:
        Start  Length  Slot  Name   Signature
            0       8     0  this   Lcoursier/core/Repository$Complete$Input$Ver;

  public coursier.core.Repository$Complete$Input$Name nameInput();
    descriptor: ()Lcoursier/core/Repository$Complete$Input$Name;
    flags: (0x0001) ACC_PUBLIC
    Code:
      stack=5, locals=2, args_size=1
         0: aload_0
         1: invokevirtual #49                 // Method module:()Lcoursier/core/Module;
         4: invokevirtual #54                 // Method coursier/core/Module.repr:()Ljava/lang/String;
         7: astore_1
         8: getstatic     #58                 // Field coursier/core/Repository$Complete$Input$Name$.MODULE$:Lcoursier/core/Repository$Complete$Input$Name$;
        11: aload_0
        12: invokevirtual #49                 // Method module:()Lcoursier/core/Module;
        15: invokevirtual #61                 // Method coursier/core/Module.organization:()Ljava/lang/String;
        18: aload_1
        19: aload_0
        20: invokevirtual #49                 // Method module:()Lcoursier/core/Module;
        23: invokevirtual #61                 // Method coursier/core/Module.organization:()Ljava/lang/String;
        26: invokevirtual #66                 // Method java/lang/String.length:()I
        29: iconst_1
        30: iadd
        31: ldc           #67                 // String
        33: invokevirtual #71                 // Method coursier/core/Repository$Complete$Input$Name$.apply:(Ljava/lang/String;Ljava/lang/String;ILjava/lang/String;)Lcoursier/core/Repository$Complete$Input$Name;
        36: areturn
      LineNumberTable:
        line 264: 0
        line 265: 8
      LocalVariableTable:
        Start  Length  Slot  Name   Signature
            8      28     1 truncatedInput   Ljava/lang/String;
            0      37     0  this   Lcoursier/core/Repository$Complete$Input$Ver;

  public coursier.core.Repository$Complete$Input$Ver withModule(coursier.core.Module);
    descriptor: (Lcoursier/core/Module;)Lcoursier/core/Repository$Complete$Input$Ver;
    flags: (0x0001) ACC_PUBLIC
    Code:
      stack=5, locals=2, args_size=2
         0: new           #2                  // class coursier/core/Repository$Complete$Input$Ver
         3: dup
         4: aload_1
         5: aload_0
         6: invokevirtual #76                 // Method input:()Ljava/lang/String;
         9: aload_0
        10: invokevirtual #78                 // Method from:()I
        13: invokespecial #82                 // Method "<init>":(Lcoursier/core/Module;Ljava/lang/String;I)V
        16: areturn
      LineNumberTable:
        line 260: 0
      LocalVariableTable:
        Start  Length  Slot  Name   Signature
            0      17     0  this   Lcoursier/core/Repository$Complete$Input$Ver;
            0      17     1 module   Lcoursier/core/Module;
    MethodParameters:
      Name                           Flags
      module                         final

  public coursier.core.Repository$Complete$Input$Ver withInput(java.lang.String);
    descriptor: (Ljava/lang/String;)Lcoursier/core/Repository$Complete$Input$Ver;
    flags: (0x0001) ACC_PUBLIC
    Code:
      stack=5, locals=2, args_size=2
         0: new           #2                  // class coursier/core/Repository$Complete$Input$Ver
         3: dup
         4: aload_0
         5: invokevirtual #49                 // Method module:()Lcoursier/core/Module;
         8: aload_1
         9: aload_0
        10: invokevirtual #78                 // Method from:()I
        13: invokespecial #82                 // Method "<init>":(Lcoursier/core/Module;Ljava/lang/String;I)V
        16: areturn
      LineNumberTable:
        line 260: 0
      LocalVariableTable:
        Start  Length  Slot  Name   Signature
            0      17     0  this   Lcoursier/core/Repository$Complete$Input$Ver;
            0      17     1 input   Ljava/lang/String;
    MethodParameters:
      Name                           Flags
      input                          final

  public coursier.core.Repository$Complete$Input$Ver withFrom(int);
    descriptor: (I)Lcoursier/core/Repository$Complete$Input$Ver;
    flags: (0x0001) ACC_PUBLIC
    Code:
      stack=5, locals=2, args_size=2
         0: new           #2                  // class coursier/core/Repository$Complete$Input$Ver
         3: dup
         4: aload_0
         5: invokevirtual #49                 // Method module:()Lcoursier/core/Module;
         8: aload_0
         9: invokevirtual #76                 // Method input:()Ljava/lang/String;
        12: iload_1
        13: invokespecial #82                 // Method "<init>":(Lcoursier/core/Module;Ljava/lang/String;I)V
        16: areturn
      LineNumberTable:
        line 260: 0
      LocalVariableTable:
        Start  Length  Slot  Name   Signature
            0      17     0  this   Lcoursier/core/Repository$Complete$Input$Ver;
            0      17     1  from   I
    MethodParameters:
      Name                           Flags
      from                           final

  public java.lang.String toString();
    descriptor: ()Ljava/lang/String;
    flags: (0x0001) ACC_PUBLIC
    Code:
      stack=3, locals=2, args_size=1
         0: new           #89                 // class java/lang/StringBuilder
         3: dup
         4: ldc           #91                 // String Ver(
         6: invokespecial #94                 // Method java/lang/StringBuilder."<init>":(Ljava/lang/String;)V
         9: astore_1
        10: aload_1
        11: aload_0
        12: invokevirtual #49                 // Method module:()Lcoursier/core/Module;
        15: invokestatic  #98                 // Method java/lang/String.valueOf:(Ljava/lang/Object;)Ljava/lang/String;
        18: invokevirtual #102                // Method java/lang/StringBuilder.append:(Ljava/lang/String;)Ljava/lang/StringBuilder;
        21: pop
        22: aload_1
        23: ldc           #104                // String ,
        25: invokevirtual #102                // Method java/lang/StringBuilder.append:(Ljava/lang/String;)Ljava/lang/StringBuilder;
        28: pop
        29: aload_1
        30: aload_0
        31: invokevirtual #76                 // Method input:()Ljava/lang/String;
        34: invokestatic  #98                 // Method java/lang/String.valueOf:(Ljava/lang/Object;)Ljava/lang/String;
        37: invokevirtual #102                // Method java/lang/StringBuilder.append:(Ljava/lang/String;)Ljava/lang/StringBuilder;
        40: pop
        41: aload_1
        42: ldc           #104                // String ,
        44: invokevirtual #102                // Method java/lang/StringBuilder.append:(Ljava/lang/String;)Ljava/lang/StringBuilder;
        47: pop
        48: aload_1
        49: aload_0
        50: invokevirtual #78                 // Method from:()I
        53: invokestatic  #107                // Method java/lang/String.valueOf:(I)Ljava/lang/String;
        56: invokevirtual #102                // Method java/lang/StringBuilder.append:(Ljava/lang/String;)Ljava/lang/StringBuilder;
        59: pop
        60: aload_1
        61: ldc           #109                // String )
        63: invokevirtual #102                // Method java/lang/StringBuilder.append:(Ljava/lang/String;)Ljava/lang/StringBuilder;
        66: pop
        67: aload_1
        68: invokevirtual #111                // Method java/lang/StringBuilder.toString:()Ljava/lang/String;
        71: areturn
      LineNumberTable:
        line 260: 0
      LocalVariableTable:
        Start  Length  Slot  Name   Signature
           10      61     1     b   Ljava/lang/StringBuilder;
            0      72     0  this   Lcoursier/core/Repository$Complete$Input$Ver;

  public boolean canEqual(java.lang.Object);
    descriptor: (Ljava/lang/Object;)Z
    flags: (0x0001) ACC_PUBLIC
    Code:
      stack=1, locals=2, args_size=2
         0: aload_1
         1: ifnull        15
         4: aload_1
         5: instanceof    #2                  // class coursier/core/Repository$Complete$Input$Ver
         8: ifeq          15
        11: iconst_1
        12: goto          16
        15: iconst_0
        16: ireturn
      StackMapTable: number_of_entries = 2
        frame_type = 15 /* same */
        frame_type = 64 /* same_locals_1_stack_item */
          stack = [ int ]
      LineNumberTable:
        line 260: 0
      LocalVariableTable:
        Start  Length  Slot  Name   Signature
            0      17     0  this   Lcoursier/core/Repository$Complete$Input$Ver;
            0      17     1   obj   Ljava/lang/Object;
    MethodParameters:
      Name                           Flags
      obj                            final

  public boolean equals(java.lang.Object);
    descriptor: (Ljava/lang/Object;)Z
    flags: (0x0001) ACC_PUBLIC
    Code:
      stack=2, locals=5, args_size=2
         0: aload_0
         1: aload_1
         2: if_acmpeq     100
         5: aload_0
         6: aload_1
         7: invokevirtual #120                // Method canEqual:(Ljava/lang/Object;)Z
        10: ifeq          104
        13: aload_1
        14: checkcast     #2                  // class coursier/core/Repository$Complete$Input$Ver
        17: astore_2
        18: iconst_1
        19: ifeq          96
        22: aload_0
        23: invokevirtual #49                 // Method module:()Lcoursier/core/Module;
        26: aload_2
        27: invokevirtual #49                 // Method module:()Lcoursier/core/Module;
        30: astore_3
        31: dup
        32: ifnonnull     43
        35: pop
        36: aload_3
        37: ifnull        50
        40: goto          96
        43: aload_3
        44: invokevirtual #124                // Method java/lang/Object.equals:(Ljava/lang/Object;)Z
        47: ifeq          96
        50: aload_0
        51: invokevirtual #76                 // Method input:()Ljava/lang/String;
        54: aload_2
        55: invokevirtual #76                 // Method input:()Ljava/lang/String;
        58: astore        4
        60: dup
        61: ifnonnull     73
        64: pop
        65: aload         4
        67: ifnull        81
        70: goto          96
        73: aload         4
        75: invokevirtual #124                // Method java/lang/Object.equals:(Ljava/lang/Object;)Z
        78: ifeq          96
        81: aload_0
        82: invokevirtual #78                 // Method from:()I
        85: aload_2
        86: invokevirtual #78                 // Method from:()I
        89: if_icmpne     96
        92: iconst_1
        93: goto          97
        96: iconst_0
        97: ifeq          104
       100: iconst_1
       101: goto          105
       104: iconst_0
       105: ireturn
      StackMapTable: number_of_entries = 9
        frame_type = 255 /* full_frame */
          offset_delta = 43
          locals = [ class coursier/core/Repository$Complete$Input$Ver, class java/lang/Object, class coursier/core/Repository$Complete$Input$Ver, class coursier/core/Module ]
          stack = [ class coursier/core/Module ]
        frame_type = 6 /* same */
        frame_type = 255 /* full_frame */
          offset_delta = 22
          locals = [ class coursier/core/Repository$Complete$Input$Ver, class java/lang/Object, class coursier/core/Repository$Complete$Input$Ver, class coursier/core/Module, class java/lang/String ]
          stack = [ class java/lang/String ]
        frame_type = 7 /* same */
        frame_type = 249 /* chop */
          offset_delta = 14
        frame_type = 64 /* same_locals_1_stack_item */
          stack = [ int ]
        frame_type = 250 /* chop */
          offset_delta = 2
        frame_type = 3 /* same */
        frame_type = 64 /* same_locals_1_stack_item */
          stack = [ int ]
      LineNumberTable:
        line 260: 0
      LocalVariableTable:
        Start  Length  Slot  Name   Signature
           18      79     2 other   Lcoursier/core/Repository$Complete$Input$Ver;
            0     106     0  this   Lcoursier/core/Repository$Complete$Input$Ver;
            0     106     1   obj   Ljava/lang/Object;
    MethodParameters:
      Name                           Flags
      obj                            final

  public int hashCode();
    descriptor: ()I
    flags: (0x0001) ACC_PUBLIC
    Code:
      stack=2, locals=2, args_size=1
         0: bipush        17
         2: ldc           #127                // String Ver
         4: invokestatic  #133                // Method scala/runtime/Statics.anyHash:(Ljava/lang/Object;)I
         7: iadd
         8: istore_1
         9: bipush        37
        11: iload_1
        12: imul
        13: aload_0
        14: invokevirtual #49                 // Method module:()Lcoursier/core/Module;
        17: invokestatic  #133                // Method scala/runtime/Statics.anyHash:(Ljava/lang/Object;)I
        20: iadd
        21: istore_1
        22: bipush        37
        24: iload_1
        25: imul
        26: aload_0
        27: invokevirtual #76                 // Method input:()Ljava/lang/String;
        30: invokestatic  #133                // Method scala/runtime/Statics.anyHash:(Ljava/lang/Object;)I
        33: iadd
        34: istore_1
        35: bipush        37
        37: iload_1
        38: imul
        39: aload_0
        40: invokevirtual #78                 // Method from:()I
        43: iadd
        44: istore_1
        45: bipush        37
        47: iload_1
        48: imul
        49: ireturn
      LineNumberTable:
        line 260: 0
      LocalVariableTable:
        Start  Length  Slot  Name   Signature
            9      40     1  code   I
            0      50     0  this   Lcoursier/core/Repository$Complete$Input$Ver;

  private scala.Tuple3<coursier.core.Module, java.lang.String, java.lang.Object> tuple();
    descriptor: ()Lscala/Tuple3;
    flags: (0x0002) ACC_PRIVATE
    Code:
      stack=5, locals=1, args_size=1
         0: new           #139                // class scala/Tuple3
         3: dup
         4: aload_0
         5: invokevirtual #49                 // Method module:()Lcoursier/core/Module;
         8: aload_0
         9: invokevirtual #76                 // Method input:()Ljava/lang/String;
        12: aload_0
        13: invokevirtual #78                 // Method from:()I
        16: invokestatic  #145                // Method scala/runtime/BoxesRunTime.boxToInteger:(I)Ljava/lang/Integer;
        19: invokespecial #148                // Method scala/Tuple3."<init>":(Ljava/lang/Object;Ljava/lang/Object;Ljava/lang/Object;)V
        22: areturn
      LineNumberTable:
        line 260: 0
      LocalVariableTable:
        Start  Length  Slot  Name   Signature
            0      23     0  this   Lcoursier/core/Repository$Complete$Input$Ver;
    Signature: #137                         // ()Lscala/Tuple3<Lcoursier/core/Module;Ljava/lang/String;Ljava/lang/Object;>;

  public java.lang.String productPrefix();
    descriptor: ()Ljava/lang/String;
    flags: (0x0001) ACC_PUBLIC
    Code:
      stack=1, locals=1, args_size=1
         0: ldc           #127                // String Ver
         2: areturn
      LineNumberTable:
        line 260: 0
      LocalVariableTable:
        Start  Length  Slot  Name   Signature
            0       3     0  this   Lcoursier/core/Repository$Complete$Input$Ver;

  public int productArity();
    descriptor: ()I
    flags: (0x0001) ACC_PUBLIC
    Code:
      stack=1, locals=1, args_size=1
         0: iconst_3
         1: ireturn
      LineNumberTable:
        line 260: 0
      LocalVariableTable:
        Start  Length  Slot  Name   Signature
            0       2     0  this   Lcoursier/core/Repository$Complete$Input$Ver;

  public java.lang.Object productElement(int);
    descriptor: (I)Ljava/lang/Object;
    flags: (0x0001) ACC_PUBLIC
    Code:
      stack=3, locals=3, args_size=2
         0: iload_1
         1: istore_2
         2: iload_2
         3: tableswitch   { // 0 to 2
                       0: 28
                       1: 35
                       2: 42
                 default: 52
            }
        28: aload_0
        29: invokevirtual #49                 // Method module:()Lcoursier/core/Module;
        32: goto          67
        35: aload_0
        36: invokevirtual #76                 // Method input:()Ljava/lang/String;
        39: goto          67
        42: aload_0
        43: invokevirtual #78                 // Method from:()I
        46: invokestatic  #145                // Method scala/runtime/BoxesRunTime.boxToInteger:(I)Ljava/lang/Integer;
        49: goto          67
        52: new           #155                // class java/lang/IndexOutOfBoundsException
        55: dup
        56: iload_2
        57: invokestatic  #145                // Method scala/runtime/BoxesRunTime.boxToInteger:(I)Ljava/lang/Integer;
        60: invokevirtual #156                // Method java/lang/Object.toString:()Ljava/lang/String;
        63: invokespecial #157                // Method java/lang/IndexOutOfBoundsException."<init>":(Ljava/lang/String;)V
        66: athrow
        67: areturn
      StackMapTable: number_of_entries = 5
        frame_type = 252 /* append */
          offset_delta = 28
          locals = [ int ]
        frame_type = 6 /* same */
        frame_type = 6 /* same */
        frame_type = 9 /* same */
        frame_type = 78 /* same_locals_1_stack_item */
          stack = [ class java/lang/Object ]
      LineNumberTable:
        line 260: 0
      LocalVariableTable:
        Start  Length  Slot  Name   Signature
            0      68     0  this   Lcoursier/core/Repository$Complete$Input$Ver;
            0      68     1     n   I
    MethodParameters:
      Name                           Flags
      n                              final

  public java.lang.String productElementName(int);
    descriptor: (I)Ljava/lang/String;
    flags: (0x0001) ACC_PUBLIC
    Code:
      stack=3, locals=3, args_size=2
         0: iload_1
         1: istore_2
         2: iload_2
         3: tableswitch   { // 0 to 2
                       0: 28
                       1: 33
                       2: 38
                 default: 43
            }
        28: ldc           #159                // String module
        30: goto          58
        33: ldc           #160                // String input
        35: goto          58
        38: ldc           #161                // String from
        40: goto          58
        43: new           #155                // class java/lang/IndexOutOfBoundsException
        46: dup
        47: iload_2
        48: invokestatic  #145                // Method scala/runtime/BoxesRunTime.boxToInteger:(I)Ljava/lang/Integer;
        51: invokevirtual #156                // Method java/lang/Object.toString:()Ljava/lang/String;
        54: invokespecial #157                // Method java/lang/IndexOutOfBoundsException."<init>":(Ljava/lang/String;)V
        57: athrow
        58: areturn
      StackMapTable: number_of_entries = 5
        frame_type = 252 /* append */
          offset_delta = 28
          locals = [ int ]
        frame_type = 4 /* same */
        frame_type = 4 /* same */
        frame_type = 4 /* same */
        frame_type = 78 /* same_locals_1_stack_item */
          stack = [ class java/lang/String ]
      LineNumberTable:
        line 260: 0
      LocalVariableTable:
        Start  Length  Slot  Name   Signature
            0      59     0  this   Lcoursier/core/Repository$Complete$Input$Ver;
            0      59     1     n   I
    MethodParameters:
      Name                           Flags
      n                              final

  public coursier.core.Repository$Complete$Input$Ver(coursier.core.Module, java.lang.String, int);
    descriptor: (Lcoursier/core/Module;Ljava/lang/String;I)V
    flags: (0x0001) ACC_PUBLIC
    Code:
      stack=2, locals=4, args_size=4
         0: aload_0
         1: aload_1
         2: putfield      #31                 // Field module:Lcoursier/core/Module;
         5: aload_0
         6: aload_2
         7: putfield      #36                 // Field input:Ljava/lang/String;
        10: aload_0
        11: iload_3
        12: putfield      #39                 // Field from:I
        15: aload_0
        16: invokespecial #164                // Method coursier/core/Repository$Complete$Input."<init>":()V
        19: return
      LineNumberTable:
        line 260: 0
      LocalVariableTable:
        Start  Length  Slot  Name   Signature
            0      20     0  this   Lcoursier/core/Repository$Complete$Input$Ver;
            0      20     1 module   Lcoursier/core/Module;
            0      20     2 input   Ljava/lang/String;
            0      20     3  from   I
    MethodParameters:
      Name                           Flags
      module                         final
      input                          final
      from                           final
}
InnerClasses:
  public static #10= #7 of #9;            // =class coursier/core/Repository$Complete$ of class coursier/core/Repository
  public static abstract #11= #4 of #7;   // Input=class coursier/core/Repository$Complete$Input of class coursier/core/Repository$Complete$
  public static #10= #13 of #7;           // =class coursier/core/Repository$Complete$Input$ of class coursier/core/Repository$Complete$
  public static final #16= #15 of #13;    // Name=class coursier/core/Repository$Complete$Input$Name of class coursier/core/Repository$Complete$Input$
  public static #10= #18 of #13;          // =class coursier/core/Repository$Complete$Input$Name$ of class coursier/core/Repository$Complete$Input$
  public static final #21= #20 of #13;    // Org=class coursier/core/Repository$Complete$Input$Org of class coursier/core/Repository$Complete$Input$
  public static final #22= #2 of #13;     // Ver=class coursier/core/Repository$Complete$Input$Ver of class coursier/core/Repository$Complete$Input$
SourceFile: "Repository.scala"
  ScalaInlineInfo: length = 0x5E (unknown attribute)
   01 01 00 12 00 52 00 53 01 00 75 00 76 01 00 79
   00 76 01 00 1D 00 27 01 00 81 00 27 01 00 1B 00
   24 01 00 19 00 1F 01 00 2C 00 2D 01 00 2A 00 2B
   01 00 99 00 27 01 00 9A 00 9B 01 00 A1 00 6C 01
   00 98 00 24 01 00 5A 00 24 01 00 8A 00 8B 01 00
   58 00 59 01 00 56 00 57 01 00 4C 00 4D 01
  Scala: length = 0x0 (unknown attribute)

