Classfile /Users/mw/Projects/slang-braindump/.jar/jar8/assemble/slang-braindump/assemble/content/coursier/core/Repository$Complete$Input$Name$.class
  Last modified May 29, 2022; size 1324 bytes
  SHA-256 checksum 36d4c971f947151b54612af2bacc7b6d87341cbcb5e4513e6c0557740397d912
  Compiled from "Repository.scala"
public class coursier.core.Repository$Complete$Input$Name$ implements java.io.Serializable
  minor version: 0
  major version: 52
  flags: (0x0021) ACC_PUBLIC, ACC_SUPER
  this_class: #2                          // coursier/core/Repository$Complete$Input$Name$
  super_class: #4                         // java/lang/Object
  interfaces: 1, fields: 1, methods: 4, attributes: 4
Constant pool:
   #1 = Utf8               coursier/core/Repository$Complete$Input$Name$
   #2 = Class              #1             // coursier/core/Repository$Complete$Input$Name$
   #3 = Utf8               java/lang/Object
   #4 = Class              #3             // java/lang/Object
   #5 = Utf8               java/io/Serializable
   #6 = Class              #5             // java/io/Serializable
   #7 = Utf8               Repository.scala
   #8 = Utf8               coursier/core/Repository$Complete$
   #9 = Class              #8             // coursier/core/Repository$Complete$
  #10 = Utf8               coursier/core/Repository
  #11 = Class              #10            // coursier/core/Repository
  #12 = Utf8
  #13 = Utf8               coursier/core/Repository$Complete$Input$
  #14 = Class              #13            // coursier/core/Repository$Complete$Input$
  #15 = Utf8               coursier/core/Repository$Complete$Input$Name
  #16 = Class              #15            // coursier/core/Repository$Complete$Input$Name
  #17 = Utf8               Name
  #18 = Utf8               MODULE$
  #19 = Utf8               Lcoursier/core/Repository$Complete$Input$Name$;
  #20 = Utf8               <clinit>
  #21 = Utf8               ()V
  #22 = Utf8               <init>
  #23 = NameAndType        #22:#21        // "<init>":()V
  #24 = Methodref          #2.#23         // coursier/core/Repository$Complete$Input$Name$."<init>":()V
  #25 = NameAndType        #18:#19        // MODULE$:Lcoursier/core/Repository$Complete$Input$Name$;
  #26 = Fieldref           #2.#25         // coursier/core/Repository$Complete$Input$Name$.MODULE$:Lcoursier/core/Repository$Complete$Input$Name$;
  #27 = Utf8               apply
  #28 = Utf8               (Ljava/lang/String;Ljava/lang/String;ILjava/lang/String;)Lcoursier/core/Repository$Complete$Input$Name;
  #29 = Utf8               organization
  #30 = Utf8               input
  #31 = Utf8               from
  #32 = Utf8               requiredSuffix
  #33 = Utf8               (Ljava/lang/String;Ljava/lang/String;ILjava/lang/String;)V
  #34 = NameAndType        #22:#33        // "<init>":(Ljava/lang/String;Ljava/lang/String;ILjava/lang/String;)V
  #35 = Methodref          #16.#34        // coursier/core/Repository$Complete$Input$Name."<init>":(Ljava/lang/String;Ljava/lang/String;ILjava/lang/String;)V
  #36 = Utf8               this
  #37 = Utf8               Ljava/lang/String;
  #38 = Utf8               I
  #39 = Utf8               writeReplace
  #40 = Utf8               ()Ljava/lang/Object;
  #41 = Utf8               scala/runtime/ModuleSerializationProxy
  #42 = Class              #41            // scala/runtime/ModuleSerializationProxy
  #43 = Utf8               (Ljava/lang/Class;)V
  #44 = NameAndType        #22:#43        // "<init>":(Ljava/lang/Class;)V
  #45 = Methodref          #42.#44        // scala/runtime/ModuleSerializationProxy."<init>":(Ljava/lang/Class;)V
  #46 = Methodref          #4.#23         // java/lang/Object."<init>":()V
  #47 = Utf8               Code
  #48 = Utf8               LineNumberTable
  #49 = Utf8               LocalVariableTable
  #50 = Utf8               MethodParameters
  #51 = Utf8               InnerClasses
  #52 = Utf8               SourceFile
  #53 = Utf8               ScalaInlineInfo
  #54 = Utf8               Scala
{
  public static final coursier.core.Repository$Complete$Input$Name$ MODULE$;
    descriptor: Lcoursier/core/Repository$Complete$Input$Name$;
    flags: (0x0019) ACC_PUBLIC, ACC_STATIC, ACC_FINAL

  public static {};
    descriptor: ()V
    flags: (0x0009) ACC_PUBLIC, ACC_STATIC
    Code:
      stack=2, locals=0, args_size=0
         0: new           #2                  // class coursier/core/Repository$Complete$Input$Name$
         3: dup
         4: invokespecial #24                 // Method "<init>":()V
         7: putstatic     #26                 // Field MODULE$:Lcoursier/core/Repository$Complete$Input$Name$;
        10: return
      LineNumberTable:
        line 256: 0

  public coursier.core.Repository$Complete$Input$Name apply(java.lang.String, java.lang.String, int, java.lang.String);
    descriptor: (Ljava/lang/String;Ljava/lang/String;ILjava/lang/String;)Lcoursier/core/Repository$Complete$Input$Name;
    flags: (0x0001) ACC_PUBLIC
    Code:
      stack=6, locals=5, args_size=5
         0: new           #16                 // class coursier/core/Repository$Complete$Input$Name
         3: dup
         4: aload_1
         5: aload_2
         6: iload_3
         7: aload         4
         9: invokespecial #35                 // Method coursier/core/Repository$Complete$Input$Name."<init>":(Ljava/lang/String;Ljava/lang/String;ILjava/lang/String;)V
        12: areturn
      LineNumberTable:
        line 256: 0
      LocalVariableTable:
        Start  Length  Slot  Name   Signature
            0      13     0  this   Lcoursier/core/Repository$Complete$Input$Name$;
            0      13     1 organization   Ljava/lang/String;
            0      13     2 input   Ljava/lang/String;
            0      13     3  from   I
            0      13     4 requiredSuffix   Ljava/lang/String;
    MethodParameters:
      Name                           Flags
      organization                   final
      input                          final
      from                           final
      requiredSuffix                 final

  private java.lang.Object writeReplace();
    descriptor: ()Ljava/lang/Object;
    flags: (0x0002) ACC_PRIVATE
    Code:
      stack=3, locals=1, args_size=1
         0: new           #42                 // class scala/runtime/ModuleSerializationProxy
         3: dup
         4: ldc           #2                  // class coursier/core/Repository$Complete$Input$Name$
         6: invokespecial #45                 // Method scala/runtime/ModuleSerializationProxy."<init>":(Ljava/lang/Class;)V
         9: areturn
      LineNumberTable:
        line 256: 0
      LocalVariableTable:
        Start  Length  Slot  Name   Signature
            0      10     0  this   Lcoursier/core/Repository$Complete$Input$Name$;

  public coursier.core.Repository$Complete$Input$Name$();
    descriptor: ()V
    flags: (0x0001) ACC_PUBLIC
    Code:
      stack=1, locals=1, args_size=1
         0: aload_0
         1: invokespecial #46                 // Method java/lang/Object."<init>":()V
         4: return
      LineNumberTable:
        line 256: 0
      LocalVariableTable:
        Start  Length  Slot  Name   Signature
            0       5     0  this   Lcoursier/core/Repository$Complete$Input$Name$;
}
InnerClasses:
  public static #12= #9 of #11;           // =class coursier/core/Repository$Complete$ of class coursier/core/Repository
  public static #12= #14 of #9;           // =class coursier/core/Repository$Complete$Input$ of class coursier/core/Repository$Complete$
  public static final #17= #16 of #14;    // Name=class coursier/core/Repository$Complete$Input$Name of class coursier/core/Repository$Complete$Input$
  public static #12= #2 of #14;           // =class coursier/core/Repository$Complete$Input$Name$ of class coursier/core/Repository$Complete$Input$
SourceFile: "Repository.scala"
  ScalaInlineInfo: length = 0x13 (unknown attribute)
   01 01 00 03 00 18 00 17 01 00 1D 00 1E 01 00 29
   00 2A 01
  Scala: length = 0x0 (unknown attribute)

