Classfile /Users/mw/Projects/slang-braindump/.jar/jar8/assemble/slang-braindump/assemble/content/coursier/core/Repository$ArtifactExtensions$.class
  Last modified May 29, 2022; size 3497 bytes
  SHA-256 checksum f77a4a952acdb0da004747bf2b44676ba3763ed3e5e44cb2e92cb7633bd1bd82
  Compiled from "Repository.scala"
public class coursier.core.Repository$ArtifactExtensions$
  minor version: 0
  major version: 52
  flags: (0x0021) ACC_PUBLIC, ACC_SUPER
  this_class: #2                          // coursier/core/Repository$ArtifactExtensions$
  super_class: #4                         // java/lang/Object
  interfaces: 0, fields: 1, methods: 6, attributes: 4
Constant pool:
    #1 = Utf8               coursier/core/Repository$ArtifactExtensions$
    #2 = Class              #1            // coursier/core/Repository$ArtifactExtensions$
    #3 = Utf8               java/lang/Object
    #4 = Class              #3            // java/lang/Object
    #5 = Utf8               Repository.scala
    #6 = Utf8               coursier/core/Repository$ArtifactExtensions
    #7 = Class              #6            // coursier/core/Repository$ArtifactExtensions
    #8 = Utf8               coursier/core/Repository
    #9 = Class              #8            // coursier/core/Repository
   #10 = Utf8               ArtifactExtensions
   #11 = Utf8
   #12 = Utf8               scala/Predef$ArrowAssoc$
   #13 = Class              #12           // scala/Predef$ArrowAssoc$
   #14 = Utf8               scala/Predef
   #15 = Class              #14           // scala/Predef
   #16 = Utf8               MODULE$
   #17 = Utf8               Lcoursier/core/Repository$ArtifactExtensions$;
   #18 = Utf8               <clinit>
   #19 = Utf8               ()V
   #20 = Utf8               <init>
   #21 = NameAndType        #20:#19       // "<init>":()V
   #22 = Methodref          #2.#21        // coursier/core/Repository$ArtifactExtensions$."<init>":()V
   #23 = NameAndType        #16:#17       // MODULE$:Lcoursier/core/Repository$ArtifactExtensions$;
   #24 = Fieldref           #2.#23        // coursier/core/Repository$ArtifactExtensions$.MODULE$:Lcoursier/core/Repository$ArtifactExtensions$;
   #25 = Utf8               withDefaultChecksums$extension
   #26 = Utf8               (Lcoursier/util/Artifact;)Lcoursier/util/Artifact;
   #27 = Utf8               $this
   #28 = Utf8               coursier/util/Artifact
   #29 = Class              #28           // coursier/util/Artifact
   #30 = Utf8               checksumUrls
   #31 = Utf8               ()Lscala/collection/immutable/Map;
   #32 = NameAndType        #30:#31       // checksumUrls:()Lscala/collection/immutable/Map;
   #33 = Methodref          #29.#32       // coursier/util/Artifact.checksumUrls:()Lscala/collection/immutable/Map;
   #34 = Utf8               scala/collection/immutable/$colon$colon
   #35 = Class              #34           // scala/collection/immutable/$colon$colon
   #36 = Utf8               Lscala/Predef$ArrowAssoc$;
   #37 = NameAndType        #16:#36       // MODULE$:Lscala/Predef$ArrowAssoc$;
   #38 = Fieldref           #13.#37       // scala/Predef$ArrowAssoc$.MODULE$:Lscala/Predef$ArrowAssoc$;
   #39 = Utf8               scala/Predef$
   #40 = Class              #39           // scala/Predef$
   #41 = Utf8               Lscala/Predef$;
   #42 = NameAndType        #16:#41       // MODULE$:Lscala/Predef$;
   #43 = Fieldref           #40.#42       // scala/Predef$.MODULE$:Lscala/Predef$;
   #44 = Utf8               MD5
   #45 = String             #44           // MD5
   #46 = Utf8               ArrowAssoc
   #47 = Utf8               (Ljava/lang/Object;)Ljava/lang/Object;
   #48 = NameAndType        #46:#47       // ArrowAssoc:(Ljava/lang/Object;)Ljava/lang/Object;
   #49 = Methodref          #40.#48       // scala/Predef$.ArrowAssoc:(Ljava/lang/Object;)Ljava/lang/Object;
   #50 = Utf8               java/lang/StringBuilder
   #51 = Class              #50           // java/lang/StringBuilder
   #52 = Integer            4
   #53 = Utf8               (I)V
   #54 = NameAndType        #20:#53       // "<init>":(I)V
   #55 = Methodref          #51.#54       // java/lang/StringBuilder."<init>":(I)V
   #56 = Utf8               url
   #57 = Utf8               ()Ljava/lang/String;
   #58 = NameAndType        #56:#57       // url:()Ljava/lang/String;
   #59 = Methodref          #29.#58       // coursier/util/Artifact.url:()Ljava/lang/String;
   #60 = Utf8               append
   #61 = Utf8               (Ljava/lang/String;)Ljava/lang/StringBuilder;
   #62 = NameAndType        #60:#61       // append:(Ljava/lang/String;)Ljava/lang/StringBuilder;
   #63 = Methodref          #51.#62       // java/lang/StringBuilder.append:(Ljava/lang/String;)Ljava/lang/StringBuilder;
   #64 = Utf8               .md5
   #65 = String             #64           // .md5
   #66 = Utf8               toString
   #67 = NameAndType        #66:#57       // toString:()Ljava/lang/String;
   #68 = Methodref          #51.#67       // java/lang/StringBuilder.toString:()Ljava/lang/String;
   #69 = Utf8               $minus$greater$extension
   #70 = Utf8               (Ljava/lang/Object;Ljava/lang/Object;)Lscala/Tuple2;
   #71 = NameAndType        #69:#70       // $minus$greater$extension:(Ljava/lang/Object;Ljava/lang/Object;)Lscala/Tuple2;
   #72 = Methodref          #13.#71       // scala/Predef$ArrowAssoc$.$minus$greater$extension:(Ljava/lang/Object;Ljava/lang/Object;)Lscala/Tuple2;
   #73 = Utf8               SHA-1
   #74 = String             #73           // SHA-1
   #75 = Integer            5
   #76 = Utf8               .sha1
   #77 = String             #76           // .sha1
   #78 = Utf8               SHA-256
   #79 = String             #78           // SHA-256
   #80 = Integer            7
   #81 = Utf8               .sha256
   #82 = String             #81           // .sha256
   #83 = Utf8               scala/collection/immutable/Nil$
   #84 = Class              #83           // scala/collection/immutable/Nil$
   #85 = Utf8               Lscala/collection/immutable/Nil$;
   #86 = NameAndType        #16:#85       // MODULE$:Lscala/collection/immutable/Nil$;
   #87 = Fieldref           #84.#86       // scala/collection/immutable/Nil$.MODULE$:Lscala/collection/immutable/Nil$;
   #88 = Utf8               (Ljava/lang/Object;Lscala/collection/immutable/List;)V
   #89 = NameAndType        #20:#88       // "<init>":(Ljava/lang/Object;Lscala/collection/immutable/List;)V
   #90 = Methodref          #35.#89       // scala/collection/immutable/$colon$colon."<init>":(Ljava/lang/Object;Lscala/collection/immutable/List;)V
   #91 = Utf8               scala/collection/immutable/Map
   #92 = Class              #91           // scala/collection/immutable/Map
   #93 = Utf8               $plus$plus
   #94 = Utf8               (Lscala/collection/IterableOnce;)Lscala/collection/IterableOps;
   #95 = NameAndType        #93:#94       // $plus$plus:(Lscala/collection/IterableOnce;)Lscala/collection/IterableOps;
   #96 = InterfaceMethodref #92.#95       // scala/collection/immutable/Map.$plus$plus:(Lscala/collection/IterableOnce;)Lscala/collection/IterableOps;
   #97 = Utf8               withChecksumUrls
   #98 = Utf8               (Lscala/collection/immutable/Map;)Lcoursier/util/Artifact;
   #99 = NameAndType        #97:#98       // withChecksumUrls:(Lscala/collection/immutable/Map;)Lcoursier/util/Artifact;
  #100 = Methodref          #29.#99       // coursier/util/Artifact.withChecksumUrls:(Lscala/collection/immutable/Map;)Lcoursier/util/Artifact;
  #101 = Utf8               this
  #102 = Utf8               Lcoursier/util/Artifact;
  #103 = Utf8               withDefaultSignature$extension
  #104 = Utf8               extra
  #105 = NameAndType        #104:#31      // extra:()Lscala/collection/immutable/Map;
  #106 = Methodref          #29.#105      // coursier/util/Artifact.extra:()Lscala/collection/immutable/Map;
  #107 = Utf8               sig
  #108 = String             #107          // sig
  #109 = Utf8               coursier/core/Repository$
  #110 = Class              #109          // coursier/core/Repository$
  #111 = Utf8               Lcoursier/core/Repository$;
  #112 = NameAndType        #16:#111      // MODULE$:Lcoursier/core/Repository$;
  #113 = Fieldref           #110.#112     // coursier/core/Repository$.MODULE$:Lcoursier/core/Repository$;
  #114 = Utf8               coursier/util/Artifact$
  #115 = Class              #114          // coursier/util/Artifact$
  #116 = Utf8               Lcoursier/util/Artifact$;
  #117 = NameAndType        #16:#116      // MODULE$:Lcoursier/util/Artifact$;
  #118 = Fieldref           #115.#117     // coursier/util/Artifact$.MODULE$:Lcoursier/util/Artifact$;
  #119 = Utf8               .asc
  #120 = String             #119          // .asc
  #121 = Utf8               Map
  #122 = Utf8               ()Lscala/collection/immutable/Map$;
  #123 = NameAndType        #121:#122     // Map:()Lscala/collection/immutable/Map$;
  #124 = Methodref          #40.#123      // scala/Predef$.Map:()Lscala/collection/immutable/Map$;
  #125 = Utf8               scala/collection/immutable/Map$
  #126 = Class              #125          // scala/collection/immutable/Map$
  #127 = Utf8               empty
  #128 = NameAndType        #127:#31      // empty:()Lscala/collection/immutable/Map;
  #129 = Methodref          #126.#128     // scala/collection/immutable/Map$.empty:()Lscala/collection/immutable/Map;
  #130 = Utf8               changing
  #131 = Utf8               ()Z
  #132 = NameAndType        #130:#131     // changing:()Z
  #133 = Methodref          #29.#132      // coursier/util/Artifact.changing:()Z
  #134 = Utf8               authentication
  #135 = Utf8               ()Lscala/Option;
  #136 = NameAndType        #134:#135     // authentication:()Lscala/Option;
  #137 = Methodref          #29.#136      // coursier/util/Artifact.authentication:()Lscala/Option;
  #138 = Utf8               apply
  #139 = Utf8               (Ljava/lang/String;Lscala/collection/immutable/Map;Lscala/collection/immutable/Map;ZZLscala/Option;)Lcoursier/util/Artifact;
  #140 = NameAndType        #138:#139     // apply:(Ljava/lang/String;Lscala/collection/immutable/Map;Lscala/collection/immutable/Map;ZZLscala/Option;)Lcoursier/util/Artifact;
  #141 = Methodref          #115.#140     // coursier/util/Artifact$.apply:(Ljava/lang/String;Lscala/collection/immutable/Map;Lscala/collection/immutable/Map;ZZLscala/Option;)Lcoursier/util/Artifact;
  #142 = NameAndType        #10:#26       // ArtifactExtensions:(Lcoursier/util/Artifact;)Lcoursier/util/Artifact;
  #143 = Methodref          #110.#142     // coursier/core/Repository$.ArtifactExtensions:(Lcoursier/util/Artifact;)Lcoursier/util/Artifact;
  #144 = NameAndType        #25:#26       // withDefaultChecksums$extension:(Lcoursier/util/Artifact;)Lcoursier/util/Artifact;
  #145 = Methodref          #2.#144       // coursier/core/Repository$ArtifactExtensions$.withDefaultChecksums$extension:(Lcoursier/util/Artifact;)Lcoursier/util/Artifact;
  #146 = Utf8               withExtra
  #147 = NameAndType        #146:#98      // withExtra:(Lscala/collection/immutable/Map;)Lcoursier/util/Artifact;
  #148 = Methodref          #29.#147      // coursier/util/Artifact.withExtra:(Lscala/collection/immutable/Map;)Lcoursier/util/Artifact;
  #149 = Utf8               hashCode$extension
  #150 = Utf8               (Lcoursier/util/Artifact;)I
  #151 = Utf8               hashCode
  #152 = Utf8               ()I
  #153 = NameAndType        #151:#152     // hashCode:()I
  #154 = Methodref          #29.#153      // coursier/util/Artifact.hashCode:()I
  #155 = Utf8               equals$extension
  #156 = Utf8               (Lcoursier/util/Artifact;Ljava/lang/Object;)Z
  #157 = Utf8               x$1
  #158 = Utf8               underlying
  #159 = Utf8               ()Lcoursier/util/Artifact;
  #160 = NameAndType        #158:#159     // underlying:()Lcoursier/util/Artifact;
  #161 = Methodref          #7.#160       // coursier/core/Repository$ArtifactExtensions.underlying:()Lcoursier/util/Artifact;
  #162 = Utf8               equals
  #163 = Utf8               (Ljava/lang/Object;)Z
  #164 = NameAndType        #162:#163     // equals:(Ljava/lang/Object;)Z
  #165 = Methodref          #4.#164       // java/lang/Object.equals:(Ljava/lang/Object;)Z
  #166 = Utf8               Ljava/lang/Object;
  #167 = Methodref          #4.#21        // java/lang/Object."<init>":()V
  #168 = Utf8               Code
  #169 = Utf8               LineNumberTable
  #170 = Utf8               LocalVariableTable
  #171 = Utf8               MethodParameters
  #172 = Utf8               StackMapTable
  #173 = Utf8               InnerClasses
  #174 = Utf8               SourceFile
  #175 = Utf8               ScalaInlineInfo
  #176 = Utf8               Scala
{
  public static final coursier.core.Repository$ArtifactExtensions$ MODULE$;
    descriptor: Lcoursier/core/Repository$ArtifactExtensions$;
    flags: (0x0019) ACC_PUBLIC, ACC_STATIC, ACC_FINAL

  public static {};
    descriptor: ()V
    flags: (0x0009) ACC_PUBLIC, ACC_STATIC
    Code:
      stack=2, locals=0, args_size=0
         0: new           #2                  // class coursier/core/Repository$ArtifactExtensions$
         3: dup
         4: invokespecial #22                 // Method "<init>":()V
         7: putstatic     #24                 // Field MODULE$:Lcoursier/core/Repository$ArtifactExtensions$;
        10: return
      LineNumberTable:
        line 98: 0

  public final coursier.util.Artifact withDefaultChecksums$extension(coursier.util.Artifact);
    descriptor: (Lcoursier/util/Artifact;)Lcoursier/util/Artifact;
    flags: (0x0011) ACC_PUBLIC, ACC_FINAL
    Code:
      stack=15, locals=2, args_size=2
         0: aload_1
         1: aload_1
         2: invokevirtual #33                 // Method coursier/util/Artifact.checksumUrls:()Lscala/collection/immutable/Map;
         5: new           #35                 // class scala/collection/immutable/$colon$colon
         8: dup
         9: getstatic     #38                 // Field scala/Predef$ArrowAssoc$.MODULE$:Lscala/Predef$ArrowAssoc$;
        12: getstatic     #43                 // Field scala/Predef$.MODULE$:Lscala/Predef$;
        15: ldc           #45                 // String MD5
        17: invokevirtual #49                 // Method scala/Predef$.ArrowAssoc:(Ljava/lang/Object;)Ljava/lang/Object;
        20: new           #51                 // class java/lang/StringBuilder
        23: dup
        24: ldc           #52                 // int 4
        26: invokespecial #55                 // Method java/lang/StringBuilder."<init>":(I)V
        29: aload_1
        30: invokevirtual #59                 // Method coursier/util/Artifact.url:()Ljava/lang/String;
        33: invokevirtual #63                 // Method java/lang/StringBuilder.append:(Ljava/lang/String;)Ljava/lang/StringBuilder;
        36: ldc           #65                 // String .md5
        38: invokevirtual #63                 // Method java/lang/StringBuilder.append:(Ljava/lang/String;)Ljava/lang/StringBuilder;
        41: invokevirtual #68                 // Method java/lang/StringBuilder.toString:()Ljava/lang/String;
        44: invokevirtual #72                 // Method scala/Predef$ArrowAssoc$.$minus$greater$extension:(Ljava/lang/Object;Ljava/lang/Object;)Lscala/Tuple2;
        47: new           #35                 // class scala/collection/immutable/$colon$colon
        50: dup
        51: getstatic     #38                 // Field scala/Predef$ArrowAssoc$.MODULE$:Lscala/Predef$ArrowAssoc$;
        54: getstatic     #43                 // Field scala/Predef$.MODULE$:Lscala/Predef$;
        57: ldc           #74                 // String SHA-1
        59: invokevirtual #49                 // Method scala/Predef$.ArrowAssoc:(Ljava/lang/Object;)Ljava/lang/Object;
        62: new           #51                 // class java/lang/StringBuilder
        65: dup
        66: ldc           #75                 // int 5
        68: invokespecial #55                 // Method java/lang/StringBuilder."<init>":(I)V
        71: aload_1
        72: invokevirtual #59                 // Method coursier/util/Artifact.url:()Ljava/lang/String;
        75: invokevirtual #63                 // Method java/lang/StringBuilder.append:(Ljava/lang/String;)Ljava/lang/StringBuilder;
        78: ldc           #77                 // String .sha1
        80: invokevirtual #63                 // Method java/lang/StringBuilder.append:(Ljava/lang/String;)Ljava/lang/StringBuilder;
        83: invokevirtual #68                 // Method java/lang/StringBuilder.toString:()Ljava/lang/String;
        86: invokevirtual #72                 // Method scala/Predef$ArrowAssoc$.$minus$greater$extension:(Ljava/lang/Object;Ljava/lang/Object;)Lscala/Tuple2;
        89: new           #35                 // class scala/collection/immutable/$colon$colon
        92: dup
        93: getstatic     #38                 // Field scala/Predef$ArrowAssoc$.MODULE$:Lscala/Predef$ArrowAssoc$;
        96: getstatic     #43                 // Field scala/Predef$.MODULE$:Lscala/Predef$;
        99: ldc           #79                 // String SHA-256
       101: invokevirtual #49                 // Method scala/Predef$.ArrowAssoc:(Ljava/lang/Object;)Ljava/lang/Object;
       104: new           #51                 // class java/lang/StringBuilder
       107: dup
       108: ldc           #80                 // int 7
       110: invokespecial #55                 // Method java/lang/StringBuilder."<init>":(I)V
       113: aload_1
       114: invokevirtual #59                 // Method coursier/util/Artifact.url:()Ljava/lang/String;
       117: invokevirtual #63                 // Method java/lang/StringBuilder.append:(Ljava/lang/String;)Ljava/lang/StringBuilder;
       120: ldc           #82                 // String .sha256
       122: invokevirtual #63                 // Method java/lang/StringBuilder.append:(Ljava/lang/String;)Ljava/lang/StringBuilder;
       125: invokevirtual #68                 // Method java/lang/StringBuilder.toString:()Ljava/lang/String;
       128: invokevirtual #72                 // Method scala/Predef$ArrowAssoc$.$minus$greater$extension:(Ljava/lang/Object;Ljava/lang/Object;)Lscala/Tuple2;
       131: getstatic     #87                 // Field scala/collection/immutable/Nil$.MODULE$:Lscala/collection/immutable/Nil$;
       134: invokespecial #90                 // Method scala/collection/immutable/$colon$colon."<init>":(Ljava/lang/Object;Lscala/collection/immutable/List;)V
       137: invokespecial #90                 // Method scala/collection/immutable/$colon$colon."<init>":(Ljava/lang/Object;Lscala/collection/immutable/List;)V
       140: invokespecial #90                 // Method scala/collection/immutable/$colon$colon."<init>":(Ljava/lang/Object;Lscala/collection/immutable/List;)V
       143: invokeinterface #96,  2           // InterfaceMethod scala/collection/immutable/Map.$plus$plus:(Lscala/collection/IterableOnce;)Lscala/collection/IterableOps;
       148: checkcast     #92                 // class scala/collection/immutable/Map
       151: invokevirtual #100                // Method coursier/util/Artifact.withChecksumUrls:(Lscala/collection/immutable/Map;)Lcoursier/util/Artifact;
       154: areturn
      LineNumberTable:
        line 100: 0
        line 101: 12
        line 100: 47
        line 102: 54
        line 100: 89
        line 103: 96
        line 100: 131
      LocalVariableTable:
        Start  Length  Slot  Name   Signature
            0     155     0  this   Lcoursier/core/Repository$ArtifactExtensions$;
            0     155     1 $this   Lcoursier/util/Artifact;
    MethodParameters:
      Name                           Flags
      $this                          final

  public final coursier.util.Artifact withDefaultSignature$extension(coursier.util.Artifact);
    descriptor: (Lcoursier/util/Artifact;)Lcoursier/util/Artifact;
    flags: (0x0011) ACC_PUBLIC, ACC_FINAL
    Code:
      stack=15, locals=2, args_size=2
         0: aload_1
         1: aload_1
         2: invokevirtual #106                // Method coursier/util/Artifact.extra:()Lscala/collection/immutable/Map;
         5: new           #35                 // class scala/collection/immutable/$colon$colon
         8: dup
         9: getstatic     #38                 // Field scala/Predef$ArrowAssoc$.MODULE$:Lscala/Predef$ArrowAssoc$;
        12: getstatic     #43                 // Field scala/Predef$.MODULE$:Lscala/Predef$;
        15: ldc           #108                // String sig
        17: invokevirtual #49                 // Method scala/Predef$.ArrowAssoc:(Ljava/lang/Object;)Ljava/lang/Object;
        20: aload_0
        21: getstatic     #113                // Field coursier/core/Repository$.MODULE$:Lcoursier/core/Repository$;
        24: getstatic     #118                // Field coursier/util/Artifact$.MODULE$:Lcoursier/util/Artifact$;
        27: new           #51                 // class java/lang/StringBuilder
        30: dup
        31: ldc           #52                 // int 4
        33: invokespecial #55                 // Method java/lang/StringBuilder."<init>":(I)V
        36: aload_1
        37: invokevirtual #59                 // Method coursier/util/Artifact.url:()Ljava/lang/String;
        40: invokevirtual #63                 // Method java/lang/StringBuilder.append:(Ljava/lang/String;)Ljava/lang/StringBuilder;
        43: ldc           #120                // String .asc
        45: invokevirtual #63                 // Method java/lang/StringBuilder.append:(Ljava/lang/String;)Ljava/lang/StringBuilder;
        48: invokevirtual #68                 // Method java/lang/StringBuilder.toString:()Ljava/lang/String;
        51: getstatic     #43                 // Field scala/Predef$.MODULE$:Lscala/Predef$;
        54: invokevirtual #124                // Method scala/Predef$.Map:()Lscala/collection/immutable/Map$;
        57: invokevirtual #129                // Method scala/collection/immutable/Map$.empty:()Lscala/collection/immutable/Map;
        60: getstatic     #43                 // Field scala/Predef$.MODULE$:Lscala/Predef$;
        63: invokevirtual #124                // Method scala/Predef$.Map:()Lscala/collection/immutable/Map$;
        66: invokevirtual #129                // Method scala/collection/immutable/Map$.empty:()Lscala/collection/immutable/Map;
        69: aload_1
        70: invokevirtual #133                // Method coursier/util/Artifact.changing:()Z
        73: iconst_1
        74: aload_1
        75: invokevirtual #137                // Method coursier/util/Artifact.authentication:()Lscala/Option;
        78: invokevirtual #141                // Method coursier/util/Artifact$.apply:(Ljava/lang/String;Lscala/collection/immutable/Map;Lscala/collection/immutable/Map;ZZLscala/Option;)Lcoursier/util/Artifact;
        81: invokevirtual #143                // Method coursier/core/Repository$.ArtifactExtensions:(Lcoursier/util/Artifact;)Lcoursier/util/Artifact;
        84: invokevirtual #145                // Method withDefaultChecksums$extension:(Lcoursier/util/Artifact;)Lcoursier/util/Artifact;
        87: invokevirtual #72                 // Method scala/Predef$ArrowAssoc$.$minus$greater$extension:(Ljava/lang/Object;Ljava/lang/Object;)Lscala/Tuple2;
        90: getstatic     #87                 // Field scala/collection/immutable/Nil$.MODULE$:Lscala/collection/immutable/Nil$;
        93: invokespecial #90                 // Method scala/collection/immutable/$colon$colon."<init>":(Ljava/lang/Object;Lscala/collection/immutable/List;)V
        96: invokeinterface #96,  2           // InterfaceMethod scala/collection/immutable/Map.$plus$plus:(Lscala/collection/IterableOnce;)Lscala/collection/IterableOps;
       101: checkcast     #92                 // class scala/collection/immutable/Map
       104: invokevirtual #148                // Method coursier/util/Artifact.withExtra:(Lscala/collection/immutable/Map;)Lcoursier/util/Artifact;
       107: areturn
      LineNumberTable:
        line 106: 0
        line 107: 12
        line 106: 20
        line 108: 21
        line 109: 27
        line 110: 51
        line 111: 60
        line 112: 69
        line 113: 73
        line 114: 74
        line 106: 90
      LocalVariableTable:
        Start  Length  Slot  Name   Signature
            0     108     0  this   Lcoursier/core/Repository$ArtifactExtensions$;
            0     108     1 $this   Lcoursier/util/Artifact;
    MethodParameters:
      Name                           Flags
      $this                          final

  public final int hashCode$extension(coursier.util.Artifact);
    descriptor: (Lcoursier/util/Artifact;)I
    flags: (0x0011) ACC_PUBLIC, ACC_FINAL
    Code:
      stack=1, locals=2, args_size=2
         0: aload_1
         1: invokevirtual #154                // Method coursier/util/Artifact.hashCode:()I
         4: ireturn
      LineNumberTable:
        line 98: 0
      LocalVariableTable:
        Start  Length  Slot  Name   Signature
            0       5     0  this   Lcoursier/core/Repository$ArtifactExtensions$;
            0       5     1 $this   Lcoursier/util/Artifact;
    MethodParameters:
      Name                           Flags
      $this                          final

  public final boolean equals$extension(coursier.util.Artifact, java.lang.Object);
    descriptor: (Lcoursier/util/Artifact;Ljava/lang/Object;)Z
    flags: (0x0011) ACC_PUBLIC, ACC_FINAL
    Code:
      stack=2, locals=7, args_size=3
         0: aload_2
         1: astore        4
         3: aload         4
         5: instanceof    #7                  // class coursier/core/Repository$ArtifactExtensions
         8: ifeq          16
        11: iconst_1
        12: istore_3
        13: goto          24
        16: goto          19
        19: iconst_0
        20: istore_3
        21: goto          24
        24: iload_3
        25: ifeq          83
        28: aload_2
        29: ifnonnull     36
        32: aconst_null
        33: goto          43
        36: aload_2
        37: checkcast     #7                  // class coursier/core/Repository$ArtifactExtensions
        40: invokevirtual #161                // Method coursier/core/Repository$ArtifactExtensions.underlying:()Lcoursier/util/Artifact;
        43: astore        5
        45: aload_1
        46: aload         5
        48: astore        6
        50: dup
        51: ifnonnull     63
        54: pop
        55: aload         6
        57: ifnull        71
        60: goto          75
        63: aload         6
        65: invokevirtual #165                // Method java/lang/Object.equals:(Ljava/lang/Object;)Z
        68: ifeq          75
        71: iconst_1
        72: goto          76
        75: iconst_0
        76: ifeq          83
        79: iconst_1
        80: goto          84
        83: iconst_0
        84: ireturn
      StackMapTable: number_of_entries = 11
        frame_type = 253 /* append */
          offset_delta = 16
          locals = [ top, class java/lang/Object ]
        frame_type = 2 /* same */
        frame_type = 255 /* full_frame */
          offset_delta = 4
          locals = [ class coursier/core/Repository$ArtifactExtensions$, class coursier/util/Artifact, class java/lang/Object, int, class java/lang/Object ]
          stack = []
        frame_type = 11 /* same */
        frame_type = 70 /* same_locals_1_stack_item */
          stack = [ class coursier/util/Artifact ]
        frame_type = 255 /* full_frame */
          offset_delta = 19
          locals = [ class coursier/core/Repository$ArtifactExtensions$, class coursier/util/Artifact, class java/lang/Object, int, class java/lang/Object, class coursier/util/Artifact, class coursier/util/Artifact ]
          stack = [ class coursier/util/Artifact ]
        frame_type = 7 /* same */
        frame_type = 3 /* same */
        frame_type = 64 /* same_locals_1_stack_item */
          stack = [ int ]
        frame_type = 249 /* chop */
          offset_delta = 6
        frame_type = 64 /* same_locals_1_stack_item */
          stack = [ int ]
      LineNumberTable:
        line 98: 0
      LocalVariableTable:
        Start  Length  Slot  Name   Signature
            0      85     0  this   Lcoursier/core/Repository$ArtifactExtensions$;
            0      85     1 $this   Lcoursier/util/Artifact;
            0      85     2   x$1   Ljava/lang/Object;
    MethodParameters:
      Name                           Flags
      $this                          final
      x$1                            final

  public coursier.core.Repository$ArtifactExtensions$();
    descriptor: ()V
    flags: (0x0001) ACC_PUBLIC
    Code:
      stack=1, locals=1, args_size=1
         0: aload_0
         1: invokespecial #167                // Method java/lang/Object."<init>":()V
         4: return
      LineNumberTable:
        line 98: 0
      LocalVariableTable:
        Start  Length  Slot  Name   Signature
            0       5     0  this   Lcoursier/core/Repository$ArtifactExtensions$;
}
InnerClasses:
  public static final #10= #7 of #9;      // ArtifactExtensions=class coursier/core/Repository$ArtifactExtensions of class coursier/core/Repository
  public static #11= #2 of #9;            // =class coursier/core/Repository$ArtifactExtensions$ of class coursier/core/Repository
  public static #11= #13 of #15;          // =class scala/Predef$ArrowAssoc$ of class scala/Predef
SourceFile: "Repository.scala"
  ScalaInlineInfo: length = 0x1D (unknown attribute)
   01 01 00 05 00 15 00 14 01 00 9C 00 9D 01 00 96
   00 97 01 00 1A 00 1B 01 00 68 00 1B 01
  Scala: length = 0x0 (unknown attribute)

