Classfile /Users/mw/Projects/slang-braindump/.jar/jar8/assemble/slang-braindump/assemble/content/coursier/core/Resolution$DepMgmt$.class
  Last modified May 29, 2022; size 4016 bytes
  SHA-256 checksum cffc61c25859e87626d410ede7da815acc04567cb6d2be2c494fba993cabd229
  Compiled from "Resolution.scala"
public class coursier.core.Resolution$DepMgmt$
  minor version: 0
  major version: 52
  flags: (0x0021) ACC_PUBLIC, ACC_SUPER
  this_class: #2                          // coursier/core/Resolution$DepMgmt$
  super_class: #4                         // java/lang/Object
  interfaces: 0, fields: 1, methods: 4, attributes: 4
Constant pool:
    #1 = Utf8               coursier/core/Resolution$DepMgmt$
    #2 = Class              #1            // coursier/core/Resolution$DepMgmt$
    #3 = Utf8               java/lang/Object
    #4 = Class              #3            // java/lang/Object
    #5 = Utf8               Resolution.scala
    #6 = Utf8               coursier/core/Resolution
    #7 = Class              #6            // coursier/core/Resolution
    #8 = Utf8
    #9 = Utf8               MODULE$
   #10 = Utf8               Lcoursier/core/Resolution$DepMgmt$;
   #11 = Utf8               <clinit>
   #12 = Utf8               ()V
   #13 = Utf8               <init>
   #14 = NameAndType        #13:#12       // "<init>":()V
   #15 = Methodref          #2.#14        // coursier/core/Resolution$DepMgmt$."<init>":()V
   #16 = NameAndType        #9:#10        // MODULE$:Lcoursier/core/Resolution$DepMgmt$;
   #17 = Fieldref           #2.#16        // coursier/core/Resolution$DepMgmt$.MODULE$:Lcoursier/core/Resolution$DepMgmt$;
   #18 = Utf8               key
   #19 = Utf8               (Lcoursier/core/Dependency;)Lscala/Tuple4;
   #20 = Utf8               (Lcoursier/core/Dependency;)Lscala/Tuple4<Lcoursier/core/Organization;Lcoursier/core/ModuleName;Lcoursier/core/Type;Lcoursier/core/Classifier;>;
   #21 = Utf8               dep
   #22 = Utf8               scala/Tuple4
   #23 = Class              #22           // scala/Tuple4
   #24 = Utf8               coursier/core/Organization
   #25 = Class              #24           // coursier/core/Organization
   #26 = Utf8               coursier/core/Dependency
   #27 = Class              #26           // coursier/core/Dependency
   #28 = Utf8               module
   #29 = Utf8               ()Lcoursier/core/Module;
   #30 = NameAndType        #28:#29       // module:()Lcoursier/core/Module;
   #31 = Methodref          #27.#30       // coursier/core/Dependency.module:()Lcoursier/core/Module;
   #32 = Utf8               coursier/core/Module
   #33 = Class              #32           // coursier/core/Module
   #34 = Utf8               organization
   #35 = Utf8               ()Ljava/lang/String;
   #36 = NameAndType        #34:#35       // organization:()Ljava/lang/String;
   #37 = Methodref          #33.#36       // coursier/core/Module.organization:()Ljava/lang/String;
   #38 = Utf8               (Ljava/lang/String;)V
   #39 = NameAndType        #13:#38       // "<init>":(Ljava/lang/String;)V
   #40 = Methodref          #25.#39       // coursier/core/Organization."<init>":(Ljava/lang/String;)V
   #41 = Utf8               coursier/core/ModuleName
   #42 = Class              #41           // coursier/core/ModuleName
   #43 = Utf8               name
   #44 = NameAndType        #43:#35       // name:()Ljava/lang/String;
   #45 = Methodref          #33.#44       // coursier/core/Module.name:()Ljava/lang/String;
   #46 = Methodref          #42.#39       // coursier/core/ModuleName."<init>":(Ljava/lang/String;)V
   #47 = Utf8               coursier/core/Type$
   #48 = Class              #47           // coursier/core/Type$
   #49 = Utf8               Lcoursier/core/Type$;
   #50 = NameAndType        #9:#49        // MODULE$:Lcoursier/core/Type$;
   #51 = Fieldref           #48.#50       // coursier/core/Type$.MODULE$:Lcoursier/core/Type$;
   #52 = Utf8               attributes
   #53 = Utf8               ()Lcoursier/core/Attributes;
   #54 = NameAndType        #52:#53       // attributes:()Lcoursier/core/Attributes;
   #55 = Methodref          #27.#54       // coursier/core/Dependency.attributes:()Lcoursier/core/Attributes;
   #56 = Utf8               coursier/core/Attributes
   #57 = Class              #56           // coursier/core/Attributes
   #58 = Utf8               type
   #59 = NameAndType        #58:#35       // type:()Ljava/lang/String;
   #60 = Methodref          #57.#59       // coursier/core/Attributes.type:()Ljava/lang/String;
   #61 = Utf8               isEmpty$extension
   #62 = Utf8               (Ljava/lang/String;)Z
   #63 = NameAndType        #61:#62       // isEmpty$extension:(Ljava/lang/String;)Z
   #64 = Methodref          #48.#63       // coursier/core/Type$.isEmpty$extension:(Ljava/lang/String;)Z
   #65 = Utf8               coursier/core/Type
   #66 = Class              #65           // coursier/core/Type
   #67 = Utf8               jar
   #68 = NameAndType        #67:#35       // jar:()Ljava/lang/String;
   #69 = Methodref          #48.#68       // coursier/core/Type$.jar:()Ljava/lang/String;
   #70 = Methodref          #66.#39       // coursier/core/Type."<init>":(Ljava/lang/String;)V
   #71 = Utf8               coursier/core/Classifier
   #72 = Class              #71           // coursier/core/Classifier
   #73 = Utf8               classifier
   #74 = NameAndType        #73:#35       // classifier:()Ljava/lang/String;
   #75 = Methodref          #57.#74       // coursier/core/Attributes.classifier:()Ljava/lang/String;
   #76 = Methodref          #72.#39       // coursier/core/Classifier."<init>":(Ljava/lang/String;)V
   #77 = Utf8               (Ljava/lang/Object;Ljava/lang/Object;Ljava/lang/Object;Ljava/lang/Object;)V
   #78 = NameAndType        #13:#77       // "<init>":(Ljava/lang/Object;Ljava/lang/Object;Ljava/lang/Object;Ljava/lang/Object;)V
   #79 = Methodref          #23.#78       // scala/Tuple4."<init>":(Ljava/lang/Object;Ljava/lang/Object;Ljava/lang/Object;Ljava/lang/Object;)V
   #80 = Utf8               this
   #81 = Utf8               Lcoursier/core/Dependency;
   #82 = Utf8               addSeq
   #83 = Utf8               (Lscala/collection/immutable/Map;Lscala/collection/immutable/Seq;)Lscala/collection/immutable/Map;
   #84 = Utf8               (Lscala/collection/immutable/Map<Lscala/Tuple4<Lcoursier/core/Organization;Lcoursier/core/ModuleName;Lcoursier/core/Type;Lcoursier/core/Classifier;>;Lscala/Tuple2<Lcoursier/core/Configuration;Lcoursier/core/Dependency;>;>;Lscala/collection/immutable/Seq<Lscala/Tuple2<Lcoursier/core/Configuration;Lcoursier/core/Dependency;>;>;)Lscala/collection/immutable/Map<Lscala/Tuple4<Lcoursier/core/Organization;Lcoursier/core/ModuleName;Lcoursier/core/Type;Lcoursier/core/Classifier;>;Lscala/Tuple2<Lcoursier/core/Configuration;Lcoursier/core/Dependency;>;>;
   #85 = Utf8               dict
   #86 = Utf8               deps
   #87 = Utf8               scala/collection/immutable/Seq
   #88 = Class              #87           // scala/collection/immutable/Seq
   #89 = Utf8               isEmpty
   #90 = Utf8               ()Z
   #91 = NameAndType        #89:#90       // isEmpty:()Z
   #92 = InterfaceMethodref #88.#91       // scala/collection/immutable/Seq.isEmpty:()Z
   #93 = Utf8               scala/collection/mutable/HashMap
   #94 = Class              #93           // scala/collection/mutable/HashMap
   #95 = Methodref          #94.#14       // scala/collection/mutable/HashMap."<init>":()V
   #96 = Utf8               scala/collection/immutable/Map
   #97 = Class              #96           // scala/collection/immutable/Map
   #98 = Utf8               size
   #99 = Utf8               ()I
  #100 = NameAndType        #98:#99       // size:()I
  #101 = InterfaceMethodref #97.#100      // scala/collection/immutable/Map.size:()I
  #102 = Utf8               length
  #103 = NameAndType        #102:#99      // length:()I
  #104 = InterfaceMethodref #88.#103      // scala/collection/immutable/Seq.length:()I
  #105 = Utf8               sizeHint
  #106 = Utf8               (I)V
  #107 = NameAndType        #105:#106     // sizeHint:(I)V
  #108 = Methodref          #94.#107      // scala/collection/mutable/HashMap.sizeHint:(I)V
  #109 = Utf8               $plus$plus$eq
  #110 = Utf8               (Lscala/collection/IterableOnce;)Lscala/collection/mutable/Growable;
  #111 = NameAndType        #109:#110     // $plus$plus$eq:(Lscala/collection/IterableOnce;)Lscala/collection/mutable/Growable;
  #112 = Methodref          #94.#111      // scala/collection/mutable/HashMap.$plus$plus$eq:(Lscala/collection/IterableOnce;)Lscala/collection/mutable/Growable;
  #113 = Utf8               iterator
  #114 = Utf8               ()Lscala/collection/Iterator;
  #115 = NameAndType        #113:#114     // iterator:()Lscala/collection/Iterator;
  #116 = InterfaceMethodref #88.#115      // scala/collection/immutable/Seq.iterator:()Lscala/collection/Iterator;
  #117 = Utf8               scala/collection/Iterator
  #118 = Class              #117          // scala/collection/Iterator
  #119 = Utf8               hasNext
  #120 = NameAndType        #119:#90      // hasNext:()Z
  #121 = InterfaceMethodref #118.#120     // scala/collection/Iterator.hasNext:()Z
  #122 = Utf8               next
  #123 = Utf8               ()Ljava/lang/Object;
  #124 = NameAndType        #122:#123     // next:()Ljava/lang/Object;
  #125 = InterfaceMethodref #118.#124     // scala/collection/Iterator.next:()Ljava/lang/Object;
  #126 = Utf8               scala/Tuple2
  #127 = Class              #126          // scala/Tuple2
  #128 = Utf8               _2
  #129 = NameAndType        #128:#123     // _2:()Ljava/lang/Object;
  #130 = Methodref          #127.#129     // scala/Tuple2._2:()Ljava/lang/Object;
  #131 = NameAndType        #18:#19       // key:(Lcoursier/core/Dependency;)Lscala/Tuple4;
  #132 = Methodref          #2.#131       // coursier/core/Resolution$DepMgmt$.key:(Lcoursier/core/Dependency;)Lscala/Tuple4;
  #133 = Utf8               contains
  #134 = Utf8               (Ljava/lang/Object;)Z
  #135 = NameAndType        #133:#134     // contains:(Ljava/lang/Object;)Z
  #136 = Methodref          #94.#135      // scala/collection/mutable/HashMap.contains:(Ljava/lang/Object;)Z
  #137 = Utf8               (Ljava/lang/Object;Ljava/lang/Object;)V
  #138 = NameAndType        #13:#137      // "<init>":(Ljava/lang/Object;Ljava/lang/Object;)V
  #139 = Methodref          #127.#138     // scala/Tuple2."<init>":(Ljava/lang/Object;Ljava/lang/Object;)V
  #140 = Utf8               $plus$eq
  #141 = Utf8               (Ljava/lang/Object;)Lscala/collection/mutable/Growable;
  #142 = NameAndType        #140:#141     // $plus$eq:(Ljava/lang/Object;)Lscala/collection/mutable/Growable;
  #143 = Methodref          #94.#142      // scala/collection/mutable/HashMap.$plus$eq:(Ljava/lang/Object;)Lscala/collection/mutable/Growable;
  #144 = Utf8               scala/runtime/BoxedUnit
  #145 = Class              #144          // scala/runtime/BoxedUnit
  #146 = Utf8               UNIT
  #147 = Utf8               Lscala/runtime/BoxedUnit;
  #148 = NameAndType        #146:#147     // UNIT:Lscala/runtime/BoxedUnit;
  #149 = Fieldref           #145.#148     // scala/runtime/BoxedUnit.UNIT:Lscala/runtime/BoxedUnit;
  #150 = Utf8               result
  #151 = Utf8               ()Lscala/collection/mutable/MapOps;
  #152 = NameAndType        #150:#151     // result:()Lscala/collection/mutable/MapOps;
  #153 = Methodref          #94.#152      // scala/collection/mutable/HashMap.result:()Lscala/collection/mutable/MapOps;
  #154 = Utf8               scala/$less$colon$less$
  #155 = Class              #154          // scala/$less$colon$less$
  #156 = Utf8               Lscala/$less$colon$less$;
  #157 = NameAndType        #9:#156       // MODULE$:Lscala/$less$colon$less$;
  #158 = Fieldref           #155.#157     // scala/$less$colon$less$.MODULE$:Lscala/$less$colon$less$;
  #159 = Utf8               refl
  #160 = Utf8               ()Lscala/$eq$colon$eq;
  #161 = NameAndType        #159:#160     // refl:()Lscala/$eq$colon$eq;
  #162 = Methodref          #155.#161     // scala/$less$colon$less$.refl:()Lscala/$eq$colon$eq;
  #163 = Utf8               scala/collection/mutable/MapOps
  #164 = Class              #163          // scala/collection/mutable/MapOps
  #165 = Utf8               toMap
  #166 = Utf8               (Lscala/$less$colon$less;)Lscala/collection/immutable/Map;
  #167 = NameAndType        #165:#166     // toMap:(Lscala/$less$colon$less;)Lscala/collection/immutable/Map;
  #168 = InterfaceMethodref #164.#167     // scala/collection/mutable/MapOps.toMap:(Lscala/$less$colon$less;)Lscala/collection/immutable/Map;
  #169 = Utf8               elem
  #170 = Utf8               Lscala/Tuple2;
  #171 = Utf8               key0
  #172 = Utf8               Lscala/Tuple4;
  #173 = Utf8               b
  #174 = Utf8               Lscala/collection/mutable/HashMap;
  #175 = Utf8               it
  #176 = Utf8               Lscala/collection/Iterator;
  #177 = Utf8               Lscala/collection/immutable/Map;
  #178 = Utf8               Lscala/collection/immutable/Seq;
  #179 = Methodref          #4.#14        // java/lang/Object."<init>":()V
  #180 = Utf8               Code
  #181 = Utf8               LineNumberTable
  #182 = Utf8               StackMapTable
  #183 = Utf8               LocalVariableTable
  #184 = Utf8               Signature
  #185 = Utf8               MethodParameters
  #186 = Utf8               InnerClasses
  #187 = Utf8               SourceFile
  #188 = Utf8               ScalaInlineInfo
  #189 = Utf8               Scala
{
  public static final coursier.core.Resolution$DepMgmt$ MODULE$;
    descriptor: Lcoursier/core/Resolution$DepMgmt$;
    flags: (0x0019) ACC_PUBLIC, ACC_STATIC, ACC_FINAL

  public static {};
    descriptor: ()V
    flags: (0x0009) ACC_PUBLIC, ACC_STATIC
    Code:
      stack=2, locals=0, args_size=0
         0: new           #2                  // class coursier/core/Resolution$DepMgmt$
         3: dup
         4: invokespecial #15                 // Method "<init>":()V
         7: putstatic     #17                 // Field MODULE$:Lcoursier/core/Resolution$DepMgmt$;
        10: return
      LineNumberTable:
        line 60: 0

  public scala.Tuple4<coursier.core.Organization, coursier.core.ModuleName, coursier.core.Type, coursier.core.Classifier> key(coursier.core.Dependency);
    descriptor: (Lcoursier/core/Dependency;)Lscala/Tuple4;
    flags: (0x0001) ACC_PUBLIC
    Code:
      stack=8, locals=2, args_size=2
         0: new           #23                 // class scala/Tuple4
         3: dup
         4: new           #25                 // class coursier/core/Organization
         7: dup
         8: aload_1
         9: invokevirtual #31                 // Method coursier/core/Dependency.module:()Lcoursier/core/Module;
        12: invokevirtual #37                 // Method coursier/core/Module.organization:()Ljava/lang/String;
        15: invokespecial #40                 // Method coursier/core/Organization."<init>":(Ljava/lang/String;)V
        18: new           #42                 // class coursier/core/ModuleName
        21: dup
        22: aload_1
        23: invokevirtual #31                 // Method coursier/core/Dependency.module:()Lcoursier/core/Module;
        26: invokevirtual #45                 // Method coursier/core/Module.name:()Ljava/lang/String;
        29: invokespecial #46                 // Method coursier/core/ModuleName."<init>":(Ljava/lang/String;)V
        32: getstatic     #51                 // Field coursier/core/Type$.MODULE$:Lcoursier/core/Type$;
        35: aload_1
        36: invokevirtual #55                 // Method coursier/core/Dependency.attributes:()Lcoursier/core/Attributes;
        39: invokevirtual #60                 // Method coursier/core/Attributes.type:()Ljava/lang/String;
        42: invokevirtual #64                 // Method coursier/core/Type$.isEmpty$extension:(Ljava/lang/String;)Z
        45: ifeq          64
        48: new           #66                 // class coursier/core/Type
        51: dup
        52: getstatic     #51                 // Field coursier/core/Type$.MODULE$:Lcoursier/core/Type$;
        55: invokevirtual #69                 // Method coursier/core/Type$.jar:()Ljava/lang/String;
        58: invokespecial #70                 // Method coursier/core/Type."<init>":(Ljava/lang/String;)V
        61: goto          78
        64: new           #66                 // class coursier/core/Type
        67: dup
        68: aload_1
        69: invokevirtual #55                 // Method coursier/core/Dependency.attributes:()Lcoursier/core/Attributes;
        72: invokevirtual #60                 // Method coursier/core/Attributes.type:()Ljava/lang/String;
        75: invokespecial #70                 // Method coursier/core/Type."<init>":(Ljava/lang/String;)V
        78: new           #72                 // class coursier/core/Classifier
        81: dup
        82: aload_1
        83: invokevirtual #55                 // Method coursier/core/Dependency.attributes:()Lcoursier/core/Attributes;
        86: invokevirtual #75                 // Method coursier/core/Attributes.classifier:()Ljava/lang/String;
        89: invokespecial #76                 // Method coursier/core/Classifier."<init>":(Ljava/lang/String;)V
        92: invokespecial #79                 // Method scala/Tuple4."<init>":(Ljava/lang/Object;Ljava/lang/Object;Ljava/lang/Object;Ljava/lang/Object;)V
        95: areturn
      StackMapTable: number_of_entries = 2
        frame_type = 255 /* full_frame */
          offset_delta = 64
          locals = [ class coursier/core/Resolution$DepMgmt$, class coursier/core/Dependency ]
          stack = [ uninitialized 0, uninitialized 0, class coursier/core/Organization, class coursier/core/ModuleName ]
        frame_type = 255 /* full_frame */
          offset_delta = 13
          locals = [ class coursier/core/Resolution$DepMgmt$, class coursier/core/Dependency ]
          stack = [ uninitialized 0, uninitialized 0, class coursier/core/Organization, class coursier/core/ModuleName, class coursier/core/Type ]
      LineNumberTable:
        line 64: 0
      LocalVariableTable:
        Start  Length  Slot  Name   Signature
            0      96     0  this   Lcoursier/core/Resolution$DepMgmt$;
            0      96     1   dep   Lcoursier/core/Dependency;
    Signature: #20                          // (Lcoursier/core/Dependency;)Lscala/Tuple4<Lcoursier/core/Organization;Lcoursier/core/ModuleName;Lcoursier/core/Type;Lcoursier/core/Classifier;>;
    MethodParameters:
      Name                           Flags
      dep                            final

  public scala.collection.immutable.Map<scala.Tuple4<coursier.core.Organization, coursier.core.ModuleName, coursier.core.Type, coursier.core.Classifier>, scala.Tuple2<coursier.core.Configuration, coursier.core.Dependency>> addSeq(scala.collection.immutable.Map<scala.Tuple4<coursier.core.Organization, coursier.core.ModuleName, coursier.core.Type, coursier.core.Classifier>, scala.Tuple2<coursier.core.Configuration, coursier.core.Dependency>>, scala.collection.immutable.Seq<scala.Tuple2<coursier.core.Configuration, coursier.core.Dependency>>);
    descriptor: (Lscala/collection/immutable/Map;Lscala/collection/immutable/Seq;)Lscala/collection/immutable/Map;
    flags: (0x0001) ACC_PUBLIC
    Code:
      stack=5, locals=7, args_size=3
         0: aload_2
         1: invokeinterface #92,  1           // InterfaceMethod scala/collection/immutable/Seq.isEmpty:()Z
         6: ifeq          13
         9: aload_1
        10: goto          137
        13: new           #94                 // class scala/collection/mutable/HashMap
        16: dup
        17: invokespecial #95                 // Method scala/collection/mutable/HashMap."<init>":()V
        20: astore_3
        21: aload_3
        22: aload_1
        23: invokeinterface #101,  1          // InterfaceMethod scala/collection/immutable/Map.size:()I
        28: aload_2
        29: invokeinterface #104,  1          // InterfaceMethod scala/collection/immutable/Seq.length:()I
        34: iadd
        35: invokevirtual #108                // Method scala/collection/mutable/HashMap.sizeHint:(I)V
        38: aload_3
        39: aload_1
        40: invokevirtual #112                // Method scala/collection/mutable/HashMap.$plus$plus$eq:(Lscala/collection/IterableOnce;)Lscala/collection/mutable/Growable;
        43: pop
        44: aload_2
        45: invokeinterface #116,  1          // InterfaceMethod scala/collection/immutable/Seq.iterator:()Lscala/collection/Iterator;
        50: astore        4
        52: aload         4
        54: invokeinterface #121,  1          // InterfaceMethod scala/collection/Iterator.hasNext:()Z
        59: ifeq          122
        62: aload         4
        64: invokeinterface #125,  1          // InterfaceMethod scala/collection/Iterator.next:()Ljava/lang/Object;
        69: checkcast     #127                // class scala/Tuple2
        72: astore        5
        74: aload_0
        75: aload         5
        77: invokevirtual #130                // Method scala/Tuple2._2:()Ljava/lang/Object;
        80: checkcast     #27                 // class coursier/core/Dependency
        83: invokevirtual #132                // Method key:(Lcoursier/core/Dependency;)Lscala/Tuple4;
        86: astore        6
        88: aload_3
        89: aload         6
        91: invokevirtual #136                // Method scala/collection/mutable/HashMap.contains:(Ljava/lang/Object;)Z
        94: ifne          115
        97: aload_3
        98: new           #127                // class scala/Tuple2
       101: dup
       102: aload         6
       104: aload         5
       106: invokespecial #139                // Method scala/Tuple2."<init>":(Ljava/lang/Object;Ljava/lang/Object;)V
       109: invokevirtual #143                // Method scala/collection/mutable/HashMap.$plus$eq:(Ljava/lang/Object;)Lscala/collection/mutable/Growable;
       112: goto          118
       115: getstatic     #149                // Field scala/runtime/BoxedUnit.UNIT:Lscala/runtime/BoxedUnit;
       118: pop
       119: goto          52
       122: aload_3
       123: invokevirtual #153                // Method scala/collection/mutable/HashMap.result:()Lscala/collection/mutable/MapOps;
       126: getstatic     #158                // Field scala/$less$colon$less$.MODULE$:Lscala/$less$colon$less$;
       129: invokevirtual #162                // Method scala/$less$colon$less$.refl:()Lscala/$eq$colon$eq;
       132: invokeinterface #168,  2          // InterfaceMethod scala/collection/mutable/MapOps.toMap:(Lscala/$less$colon$less;)Lscala/collection/immutable/Map;
       137: areturn
      StackMapTable: number_of_entries = 6
        frame_type = 13 /* same */
        frame_type = 253 /* append */
          offset_delta = 38
          locals = [ class scala/collection/mutable/HashMap, class scala/collection/Iterator ]
        frame_type = 253 /* append */
          offset_delta = 62
          locals = [ class scala/Tuple2, class scala/Tuple4 ]
        frame_type = 66 /* same_locals_1_stack_item */
          stack = [ class java/lang/Object ]
        frame_type = 249 /* chop */
          offset_delta = 3
        frame_type = 255 /* full_frame */
          offset_delta = 14
          locals = [ class coursier/core/Resolution$DepMgmt$, class scala/collection/immutable/Map, class scala/collection/immutable/Seq ]
          stack = [ class scala/collection/immutable/Map ]
      LineNumberTable:
        line 70: 0
        line 71: 9
        line 73: 13
        line 74: 21
        line 75: 38
        line 76: 44
        line 77: 52
        line 78: 62
        line 79: 74
        line 80: 88
        line 81: 97
        line 80: 115
        line 77: 119
        line 83: 122
        line 84: 126
      LocalVariableTable:
        Start  Length  Slot  Name   Signature
           74      45     5  elem   Lscala/Tuple2;
           88      31     6  key0   Lscala/Tuple4;
           21     116     3     b   Lscala/collection/mutable/HashMap;
           52      85     4    it   Lscala/collection/Iterator;
            0     138     0  this   Lcoursier/core/Resolution$DepMgmt$;
            0     138     1  dict   Lscala/collection/immutable/Map;
            0     138     2  deps   Lscala/collection/immutable/Seq;
    Signature: #84                          // (Lscala/collection/immutable/Map<Lscala/Tuple4<Lcoursier/core/Organization;Lcoursier/core/ModuleName;Lcoursier/core/Type;Lcoursier/core/Classifier;>;Lscala/Tuple2<Lcoursier/core/Configuration;Lcoursier/core/Dependency;>;>;Lscala/collection/immutable/Seq<Lscala/Tuple2<Lcoursier/core/Configuration;Lcoursier/core/Dependency;>;>;)Lscala/collection/immutable/Map<Lscala/Tuple4<Lcoursier/core/Organization;Lcoursier/core/ModuleName;Lcoursier/core/Type;Lcoursier/core/Classifier;>;Lscala/Tuple2<Lcoursier/core/Configuration;Lcoursier/core/Dependency;>;>;
    MethodParameters:
      Name                           Flags
      dict                           final
      deps                           final

  public coursier.core.Resolution$DepMgmt$();
    descriptor: ()V
    flags: (0x0001) ACC_PUBLIC
    Code:
      stack=1, locals=1, args_size=1
         0: aload_0
         1: invokespecial #179                // Method java/lang/Object."<init>":()V
         4: return
      LineNumberTable:
        line 88: 0
        line 60: 4
      LocalVariableTable:
        Start  Length  Slot  Name   Signature
            0       5     0  this   Lcoursier/core/Resolution$DepMgmt$;
}
InnerClasses:
  public static #8= #2 of #7;             // =class coursier/core/Resolution$DepMgmt$ of class coursier/core/Resolution
SourceFile: "Resolution.scala"
  ScalaInlineInfo: length = 0x13 (unknown attribute)
   01 01 00 03 00 0D 00 0C 01 00 52 00 53 01 00 12
   00 13 01
  Scala: length = 0x0 (unknown attribute)

