Classfile /Users/mw/Projects/slang-braindump/.jar/jar8/assemble/slang-braindump/assemble/content/coursier/core/SnapshotVersioning$.class
  Last modified May 29, 2022; size 1979 bytes
  SHA-256 checksum 9ce08d517048d0b41929fdbcf8176d410dcb46f344738c84803a1a4ba3c6feb5
  Compiled from "Definitions.scala"
public final class coursier.core.SnapshotVersioning$ implements java.io.Serializable
  minor version: 0
  major version: 52
  flags: (0x0031) ACC_PUBLIC, ACC_FINAL, ACC_SUPER
  this_class: #2                          // coursier/core/SnapshotVersioning$
  super_class: #4                         // java/lang/Object
  interfaces: 1, fields: 1, methods: 4, attributes: 4
Constant pool:
   #1 = Utf8               coursier/core/SnapshotVersioning$
   #2 = Class              #1             // coursier/core/SnapshotVersioning$
   #3 = Utf8               java/lang/Object
   #4 = Class              #3             // java/lang/Object
   #5 = Utf8               java/io/Serializable
   #6 = Class              #5             // java/io/Serializable
   #7 = Utf8               Definitions.scala
   #8 = Utf8               coursier/core/Versions$DateTime
   #9 = Class              #8             // coursier/core/Versions$DateTime
  #10 = Utf8               coursier/core/Versions
  #11 = Class              #10            // coursier/core/Versions
  #12 = Utf8               DateTime
  #13 = Utf8               MODULE$
  #14 = Utf8               Lcoursier/core/SnapshotVersioning$;
  #15 = Utf8               <clinit>
  #16 = Utf8               ()V
  #17 = Utf8               <init>
  #18 = NameAndType        #17:#16        // "<init>":()V
  #19 = Methodref          #2.#18         // coursier/core/SnapshotVersioning$."<init>":()V
  #20 = NameAndType        #13:#14        // MODULE$:Lcoursier/core/SnapshotVersioning$;
  #21 = Fieldref           #2.#20         // coursier/core/SnapshotVersioning$.MODULE$:Lcoursier/core/SnapshotVersioning$;
  #22 = Utf8               apply
  #23 = Utf8               (Lcoursier/core/Module;Ljava/lang/String;Ljava/lang/String;Ljava/lang/String;Ljava/lang/String;Lscala/Option;Lscala/Option;Lscala/Option;Lscala/collection/immutable/Seq;)Lcoursier/core/SnapshotVersioning;
  #24 = Utf8               (Lcoursier/core/Module;Ljava/lang/String;Ljava/lang/String;Ljava/lang/String;Ljava/lang/String;Lscala/Option<Ljava/lang/Object;>;Lscala/Option<Ljava/lang/Object;>;Lscala/Option<Lcoursier/core/Versions$DateTime;>;Lscala/collection/immutable/Seq<Lcoursier/core/SnapshotVersion;>;)Lcoursier/core/SnapshotVersioning;
  #25 = Utf8               module
  #26 = Utf8               version
  #27 = Utf8               latest
  #28 = Utf8               release
  #29 = Utf8               timestamp
  #30 = Utf8               buildNumber
  #31 = Utf8               localCopy
  #32 = Utf8               lastUpdated
  #33 = Utf8               snapshotVersions
  #34 = Utf8               coursier/core/SnapshotVersioning
  #35 = Class              #34            // coursier/core/SnapshotVersioning
  #36 = Utf8               (Lcoursier/core/Module;Ljava/lang/String;Ljava/lang/String;Ljava/lang/String;Ljava/lang/String;Lscala/Option;Lscala/Option;Lscala/Option;Lscala/collection/immutable/Seq;)V
  #37 = NameAndType        #17:#36        // "<init>":(Lcoursier/core/Module;Ljava/lang/String;Ljava/lang/String;Ljava/lang/String;Ljava/lang/String;Lscala/Option;Lscala/Option;Lscala/Option;Lscala/collection/immutable/Seq;)V
  #38 = Methodref          #35.#37        // coursier/core/SnapshotVersioning."<init>":(Lcoursier/core/Module;Ljava/lang/String;Ljava/lang/String;Ljava/lang/String;Ljava/lang/String;Lscala/Option;Lscala/Option;Lscala/Option;Lscala/collection/immutable/Seq;)V
  #39 = Utf8               this
  #40 = Utf8               Lcoursier/core/Module;
  #41 = Utf8               Ljava/lang/String;
  #42 = Utf8               Lscala/Option;
  #43 = Utf8               Lscala/collection/immutable/Seq;
  #44 = Utf8               writeReplace
  #45 = Utf8               ()Ljava/lang/Object;
  #46 = Utf8               scala/runtime/ModuleSerializationProxy
  #47 = Class              #46            // scala/runtime/ModuleSerializationProxy
  #48 = Utf8               (Ljava/lang/Class;)V
  #49 = NameAndType        #17:#48        // "<init>":(Ljava/lang/Class;)V
  #50 = Methodref          #47.#49        // scala/runtime/ModuleSerializationProxy."<init>":(Ljava/lang/Class;)V
  #51 = Methodref          #4.#18         // java/lang/Object."<init>":()V
  #52 = Utf8               Code
  #53 = Utf8               LineNumberTable
  #54 = Utf8               LocalVariableTable
  #55 = Utf8               Signature
  #56 = Utf8               MethodParameters
  #57 = Utf8               InnerClasses
  #58 = Utf8               SourceFile
  #59 = Utf8               ScalaInlineInfo
  #60 = Utf8               Scala
{
  public static final coursier.core.SnapshotVersioning$ MODULE$;
    descriptor: Lcoursier/core/SnapshotVersioning$;
    flags: (0x0019) ACC_PUBLIC, ACC_STATIC, ACC_FINAL

  public static {};
    descriptor: ()V
    flags: (0x0009) ACC_PUBLIC, ACC_STATIC
    Code:
      stack=2, locals=0, args_size=0
         0: new           #2                  // class coursier/core/SnapshotVersioning$
         3: dup
         4: invokespecial #19                 // Method "<init>":()V
         7: putstatic     #21                 // Field MODULE$:Lcoursier/core/SnapshotVersioning$;
        10: return
      LineNumberTable:
        line 372: 0

  public coursier.core.SnapshotVersioning apply(coursier.core.Module, java.lang.String, java.lang.String, java.lang.String, java.lang.String, scala.Option<java.lang.Object>, scala.Option<java.lang.Object>, scala.Option<coursier.core.Versions$DateTime>, scala.collection.immutable.Seq<coursier.core.SnapshotVersion>);
    descriptor: (Lcoursier/core/Module;Ljava/lang/String;Ljava/lang/String;Ljava/lang/String;Ljava/lang/String;Lscala/Option;Lscala/Option;Lscala/Option;Lscala/collection/immutable/Seq;)Lcoursier/core/SnapshotVersioning;
    flags: (0x0001) ACC_PUBLIC
    Code:
      stack=11, locals=10, args_size=10
         0: new           #35                 // class coursier/core/SnapshotVersioning
         3: dup
         4: aload_1
         5: aload_2
         6: aload_3
         7: aload         4
         9: aload         5
        11: aload         6
        13: aload         7
        15: aload         8
        17: aload         9
        19: invokespecial #38                 // Method coursier/core/SnapshotVersioning."<init>":(Lcoursier/core/Module;Ljava/lang/String;Ljava/lang/String;Ljava/lang/String;Ljava/lang/String;Lscala/Option;Lscala/Option;Lscala/Option;Lscala/collection/immutable/Seq;)V
        22: areturn
      LineNumberTable:
        line 372: 0
      LocalVariableTable:
        Start  Length  Slot  Name   Signature
            0      23     0  this   Lcoursier/core/SnapshotVersioning$;
            0      23     1 module   Lcoursier/core/Module;
            0      23     2 version   Ljava/lang/String;
            0      23     3 latest   Ljava/lang/String;
            0      23     4 release   Ljava/lang/String;
            0      23     5 timestamp   Ljava/lang/String;
            0      23     6 buildNumber   Lscala/Option;
            0      23     7 localCopy   Lscala/Option;
            0      23     8 lastUpdated   Lscala/Option;
            0      23     9 snapshotVersions   Lscala/collection/immutable/Seq;
    Signature: #24                          // (Lcoursier/core/Module;Ljava/lang/String;Ljava/lang/String;Ljava/lang/String;Ljava/lang/String;Lscala/Option<Ljava/lang/Object;>;Lscala/Option<Ljava/lang/Object;>;Lscala/Option<Lcoursier/core/Versions$DateTime;>;Lscala/collection/immutable/Seq<Lcoursier/core/SnapshotVersion;>;)Lcoursier/core/SnapshotVersioning;
    MethodParameters:
      Name                           Flags
      module                         final
      version                        final
      latest                         final
      release                        final
      timestamp                      final
      buildNumber                    final
      localCopy                      final
      lastUpdated                    final
      snapshotVersions               final

  private java.lang.Object writeReplace();
    descriptor: ()Ljava/lang/Object;
    flags: (0x0002) ACC_PRIVATE
    Code:
      stack=3, locals=1, args_size=1
         0: new           #47                 // class scala/runtime/ModuleSerializationProxy
         3: dup
         4: ldc           #2                  // class coursier/core/SnapshotVersioning$
         6: invokespecial #50                 // Method scala/runtime/ModuleSerializationProxy."<init>":(Ljava/lang/Class;)V
         9: areturn
      LineNumberTable:
        line 372: 0
      LocalVariableTable:
        Start  Length  Slot  Name   Signature
            0      10     0  this   Lcoursier/core/SnapshotVersioning$;

  private coursier.core.SnapshotVersioning$();
    descriptor: ()V
    flags: (0x0002) ACC_PRIVATE
    Code:
      stack=1, locals=1, args_size=1
         0: aload_0
         1: invokespecial #51                 // Method java/lang/Object."<init>":()V
         4: return
      LineNumberTable:
        line 372: 0
      LocalVariableTable:
        Start  Length  Slot  Name   Signature
            0       5     0  this   Lcoursier/core/SnapshotVersioning$;
}
InnerClasses:
  public static final #12= #9 of #11;     // DateTime=class coursier/core/Versions$DateTime of class coursier/core/Versions
SourceFile: "Definitions.scala"
  ScalaInlineInfo: length = 0x13 (unknown attribute)
   01 01 00 03 00 11 00 10 01 00 16 00 17 01 00 2C
   00 2D 01
  Scala: length = 0x0 (unknown attribute)

