Classfile /Users/mw/Projects/slang-braindump/.jar/jar8/assemble/slang-braindump/assemble/content/coursier/core/Type.class
  Last modified May 29, 2022; size 8581 bytes
  SHA-256 checksum 5fcdc4f7b26871ed046881d2ef1c967cf716e0479defc7bb694376b5189e94e4
  Compiled from "Definitions.scala"
public final class coursier.core.Type implements scala.Product,java.io.Serializable
  minor version: 0
  major version: 52
  flags: (0x0031) ACC_PUBLIC, ACC_FINAL, ACC_SUPER
  this_class: #2                          // coursier/core/Type
  super_class: #4                         // java/lang/Object
  interfaces: 2, fields: 1, methods: 47, attributes: 5
Constant pool:
    #1 = Utf8               coursier/core/Type
    #2 = Class              #1            // coursier/core/Type
    #3 = Utf8               java/lang/Object
    #4 = Class              #3            // java/lang/Object
    #5 = Utf8               scala/Product
    #6 = Class              #5            // scala/Product
    #7 = Utf8               java/io/Serializable
    #8 = Class              #7            // java/io/Serializable
    #9 = Utf8               Definitions.scala
   #10 = Utf8               Lscala/reflect/ScalaSignature;
   #11 = Utf8               bytes
   #12 = Utf8               \u0006\u0005\t5e\u0001B\'O\u0005NC\u0001\"\u001b\u0001\u0003\u0016\u0004%\tA\u001b\u0005\tg\u0002\u0011\t\u0012)A\u0005W\")A\u000f\u0001C\u0001k\")\u0011\u0010\u0001C\u0001u\")a\u0010\u0001C\u0001u\"1q\u0010\u0001C\u0001\u0003\u0003Aq!!\u0004\u0001\t\u0003\ty\u0001C\u0005\u0002\u0018\u0001\t\t\u0011\"\u0001\u0002\u001a!I\u0011Q\u0004\u0001\u0012\u0002\u0013\u0005\u0011q\u0004\u0005\n\u0003k\u0001\u0011\u0011!C!\u0003oA\u0011\"a\u0012\u0001\u0003\u0003%\t!!\u0013\t\u0013\u0005E\u0003!!A\u0005\u0002\u0005M\u0003\"CA0\u0001\u0005\u0005I\u0011IA1\u0011%\ty\u0007AA\u0001\n\u0003\t\t\bC\u0005\u0002v\u0001\t\t\u0011\"\u0011\u0002x!I\u00111\u0010\u0001\u0002\u0002\u0013\u0005\u0013Q\u0010\u0005\n\u0003\u007f\u0002\u0011\u0011!C!\u0003\u0003C\u0011\"!\"\u0001\u0003\u0003%\t%a\"\b\u000f\u0005%e\n#\u0001\u0002\f\u001a1QJ\u0014E\u0001\u0003\u001bCa\u0001\u001e\u000b\u0005\u0002\u0005}\u0005\"CAQ)\t\u0007I1AAR\u0011!\tY\u000b\u0006Q\u0001\n\u0005\u0015\u0006\"CAW)\t\u0007I\u0011AAX\u0011\u001d\t\t\f\u0006Q\u0001\nYD\u0011\"a-\u0015\u0005\u0004%\t!a,\t\u000f\u0005UF\u0003)A\u0005m\"I\u0011q\u0017\u000bC\u0002\u0013\u0005\u0011q\u0016\u0005\b\u0003s#\u0002\u0015!\u0003w\u0011%\tY\f\u0006b\u0001\n\u0003\ty\u000bC\u0004\u0002>R\u0001\u000b\u0011\u0002<\t\u0013\u0005}FC1A\u0005\u0002\u0005=\u0006bBAa)\u0001\u0006IA\u001e\u0005\n\u0003\u0007$\"\u0019!C\u0001\u0003_Cq!!2\u0015A\u0003%a\u000fC\u0005\u0002HR\u0011\r\u0011\"\u0001\u00020\"9\u0011\u0011\u001a\u000b!\u0002\u00131\b\"CAf)\t\u0007I\u0011AAX\u0011\u001d\ti\r\u0006Q\u0001\nYD\u0011\"a4\u0015\u0005\u0004%\t!a,\t\u000f\u0005EG\u0003)A\u0005m\"I\u00111\u001b\u000bC\u0002\u0013\u0005\u0011q\u0016\u0005\b\u0003+$\u0002\u0015!\u0003w\u0011%\t9\u000e\u0006b\u0001\n\u0003\ty\u000bC\u0004\u0002ZR\u0001\u000b\u0011\u0002<\b\u000f\u0005mG\u0003#\u0001\u0002^\u001a9\u0011\u0011\u001d\u000b\t\u0002\u0005\r\bB\u0002;0\t\u0003\t)\u000fC\u0005\u0002h>\u0012\r\u0011\"\u0001\u00020\"9\u0011\u0011^\u0018!\u0002\u00131\b\"CAv_\t\u0007I\u0011AAX\u0011\u001d\tio\fQ\u0001\nYD\u0011\"a<0\u0005\u0004%\t!a,\t\u000f\u0005Ex\u0006)A\u0005m\"I\u00111_\u0018C\u0002\u0013\u0005\u0011q\u0016\u0005\b\u0003k|\u0003\u0015!\u0003w\u0011%\t9p\fb\u0001\n\u0003\ty\u000bC\u0004\u0002z>\u0002\u000b\u0011\u0002<\t\u0013\u0005mH#!A\u0005\u0002\u0006u\b\"\u0003B\u0001)\u0005\u0005I\u0011\u0011B\u0002\u0011%\u0011y\u0001FA\u0001\n\u0013\u0011\t\u0002C\u0004\u0003\u001aQ!)Aa\u0007\t\u000f\t\u0005B\u0003\"\u0002\u0003$!9!q\u0005\u000b\u0005\u0006\t%\u0002b\u0002B\u0019)\u0011\u0015!1\u0007\u0005\n\u0005o!\u0012\u0011!C\u0003\u0005sA\u0011B!\u0011\u0015#\u0003%)Aa\u0011\t\u0013\t\u001dC#!A\u0005\u0006\t%\u0003\"\u0003B\')\u0005\u0005IQ\u0001B(\u0011%\u0011\u0019\u0006FA\u0001\n\u000b\u0011)\u0006C\u0005\u0003^Q\t\t\u0011\"\u0002\u0003`!I!1\r\u000b\u0002\u0002\u0013\u0015!Q\r\u0005\n\u0005[\"\u0012\u0011!C\u0003\u0005_B\u0011Ba\u001e\u0015\u0003\u0003%)A!\u001f\t\u0013\tuD#!A\u0005\u0006\t}\u0004\"\u0003BD)\u0005\u0005IQ\u0001BE\u0005\u0011!\u0016\u0010]3\u000b\u0005=\u0003\u0016\u0001B2pe\u0016T\u0011!U\u0001\tG>,(o]5fe\u000e\u00011\u0003\u0002\u0001U5v\u0003\"!\u0016-\u000e\u0003YS\u0011aV\u0001\u0006g\u000e\fG.Y\u0005\u00033Z\u0013a!\u00118z-\u0006d\u0007CA+\\\u0013\tafKA\u0004Qe>$Wo\u0019;\u0011\u0005y3gBA0e\u001d\t\u00017-D\u0001b\u0015\t\u0011\'+\u0001\u0004=e>|GOP\u0005\u0002/&\u0011QMV\u0001\ba\u0006\u001c7.Y4f\u0013\t9\u0007N\u0001\u0007TKJL\u0017\r\\5{C\ndWM\u0003\u0002f-\u0006)a/\u00197vKV\t1\u000e\u0005\u0002ma:\u0011QN\u001c\t\u0003AZK!a\u001c,\u0002\rA\u0013X\rZ3g\u0013\t\t(O\u0001\u0004TiJLgn\u001a\u0006\u0003_Z\u000baA^1mk\u0016\u0004\u0013A\u0002\u001fj]&$h\b\u0006\u0002wqB\u0011q\u000fA\u0007\u0002\u001d\")\u0011n\u0001a\u0001W\u00069\u0011n]#naRLX#A>\u0011\u0005Uc\u0018BA?W\u0005\u001d\u0011un\u001c7fC:\f\u0001B\\8o\u000b6\u0004H/_\u0001\u0004[\u0006\u0004Hc\u0001<\u0002\u0004!9\u0011Q\u0001\u0004A\u0002\u0005\u001d\u0011!\u00014\u0011\u000bU\u000bIa[6\n\u0007\u0005-aKA\u0005Gk:\u001cG/[8oc\u0005Y\u0011m]#yi\u0016t7/[8o+\t\t\t\u0002E\u0002x\u0003\'I1!!\u0006O\u0005%)\u0005\u0010^3og&|g.\u0001\u0003d_BLHc\u0001<\u0002\u001c!9\u0011\u000e\u0003I\u0001\u0002\u0004Y\u0017AD2paf$C-\u001a4bk2$H%M\u000b\u0003\u0003CQ3a[A\u0012W\t\t)\u0003\u0005\u0003\u0002(\u0005ERBAA\u0015\u0015\u0011\tY#!\f\u0002\u0013Ut7\r[3dW\u0016$\'bAA\u0018-\u0006Q\u0011M\u001c8pi\u0006$\u0018n\u001c8\n\t\u0005M\u0012\u0011\u0006\u0002\u0012k:\u001c\u0007.Z2lK\u00124\u0016M]5b]\u000e,\u0017!\u00049s_\u0012,8\r\u001e)sK\u001aL\u00070\u0006\u0002\u0002:A!\u00111HA#\u001b\t\tiD\u0003\u0003\u0002@\u0005\u0005\u0013\u0001\u00027b]\u001eT!!a\u0011\u0002\t)\fg/Y\u0005\u0004c\u0006u\u0012\u0001\u00049s_\u0012,8\r^!sSRLXCAA&!\r)\u0016QJ\u0005\u0004\u0003\u001f2&aA%oi\u0006q\u0001O]8ek\u000e$X\t\\3nK:$H\u0003BA+\u00037\u00022!VA,\u0013\r\tIF\u0016\u0002\u0004\u0003:L\b\"CA/\u0019\u0005\u0005\t\u0019AA&\u0003\rAH%M\u0001\u0010aJ|G-^2u\u0013R,\'/\u0019;peV\u0011\u00111\r\t\u0007\u0003K\nY\'!\u0016\u000e\u0005\u0005\u001d$bAA5-\u0006Q1m\u001c7mK\u000e$\u0018n\u001c8\n\t\u00055\u0014q\r\u0002\t\u0013R,\'/\u0019;pe\u0006A1-\u00198FcV\fG\u000eF\u0002|\u0003gB\u0011\"!\u0018\u000f\u0003\u0003\u0005\r!!\u0016\u0002%A\u0014x\u000eZ;di\u0016cW-\\3oi:\u000bW.\u001a\u000b\u0005\u0003s\tI\bC\u0005\u0002^=\t\t\u00111\u0001\u0002L\u0005A\u0001.Y:i\u0007>$W\r\u0006\u0002\u0002L\u00051Q-];bYN$2a_AB\u0011%\ti&EA\u0001\u0002\u0004\t)&\u0001\u0005u_N#(/\u001b8h)\t\tI$\u0001\u0003UsB,\u0007CA<\u0015\'\u0015!\u0012qRAK!\r)\u0016\u0011S\u0005\u0004\u0003\'3&AB!osJ+g\r\u0005\u0003\u0002\u0018\u0006uUBAAM\u0015\u0011\tY*!\u0011\u0002\u0005%|\u0017bA4\u0002\u001aR\u0011\u00111R\u0001\t_J$WM]5oOV\u0011\u0011Q\u0015\t\u0005=\u0006\u001df/C\u0002\u0002*\"\u0014\u0001b\u0014:eKJLgnZ\u0001\n_J$WM]5oO\u0002\n1A[1s+\u00051\u0018\u0001\u00026be\u0002\nq\u0001^3ti*\u000b\'/\u0001\u0005uKN$(*\u0019:!\u0003\u0019\u0011WO\u001c3mK\u00069!-\u001e8eY\u0016\u0004\u0013a\u00013pG\u0006!Am\\2!\u0003\u0019\u0019x.\u001e:dK\u000691o\\;sG\u0016\u0004\u0013a\u00026bm\u0006$wnY\u0001\tU\u00064\u0018\rZ8dA\u0005Q!.\u0019<b\'>,(oY3\u0002\u0017)\fg/Y*pkJ\u001cW\rI\u0001\u0004SZL\u0018\u0001B5ws\u0002\n1\u0001]8n\u0003\u0011\u0001x.\u001c\u0011\u0002\u000b\u0015l\u0007\u000f^=\u0002\r\u0015l\u0007\u000f^=!\u0003\r\tG\u000e\\\u0001\u0005C2d\u0007%\u0001\u0004Fq>$\u0018n\u0019\t\u0004\u0003?|S\"\u0001\u000b\u0003\r\u0015Cx\u000e^5d\'\ry\u0013q\u0012\u000b\u0003\u0003;\f1\"\\1wK:\u0004F.^4j]\u0006aQ.\u0019<f]BcWoZ5oA\u0005iQm\u00197jaN,\u0007\u000b\\;hS:\fa\"Z2mSB\u001cX\r\u00157vO&t\u0007%A\u0002iWJ\nA\u0001[63A\u0005)qN\u001d2ji\u00061qN\u001d2ji\u0002\n\u0001b]2bY\u0006T\u0015M]\u0001\ng\u000e\fG.\u0019&be\u0002\nQ!\u00199qYf$2A^A\u0000\u0011\u0015I7\b1\u0001l\u0003\u001d)h.\u00199qYf$BA!\u0002\u0003\fA!QKa\u0002l\u0013\r\u0011IA\u0016\u0002\u0007\u001fB$\u0018n\u001c8\t\u0011\t5A(!AA\u0002Y\f1\u0001\u001f\u00131\u000319(/\u001b;f%\u0016\u0004H.Y2f)\t\u0011\u0019\u0002\u0005\u0003\u0002<\tU\u0011\u0002\u0002B\f\u0003{\u0011aa\u00142kK\u000e$\u0018!E5t\u000b6\u0004H/\u001f\u0013fqR,gn]5p]R\u00191P!\b\t\r\t}a\b1\u0001w\u0003\u0015!C\u000f[5t\u0003IqwN\\#naRLH%\u001a=uK:\u001c\u0018n\u001c8\u0015\u0007m\u0014)\u0003\u0003\u0004\u0003 }\u0002\rA^\u0001\u000e[\u0006\u0004H%\u001a=uK:\u001c\u0018n\u001c8\u0015\t\t-\"q\u0006\u000b\u0004m\n5\u0002bBA\u0003\u0001\u0002\u0007\u0011q\u0001\u0005\u0007\u0005?\u0001\u0005\u0019\u0001<\u0002+\u0005\u001cX\t\u001f;f]NLwN\u001c\u0013fqR,gn]5p]R!\u0011\u0011\u0003B\u001b\u0011\u0019\u0011y\"\u0011a\u0001m\u0006q1m\u001c9zI\u0015DH/\u001a8tS>tG\u0003\u0002B\u001e\u0005\u007f!2A\u001eB\u001f\u0011\u001dI\'\t%AA\u0002-DaAa\bC\u0001\u00041\u0018\u0001G2paf$C-\u001a4bk2$H%\r\u0013fqR,gn]5p]R!\u0011\u0011\u0005B#\u0011\u0019\u0011yb\u0011a\u0001m\u00069\u0002O]8ek\u000e$\bK]3gSb$S\r\u001f;f]NLwN\u001c\u000b\u0005\u0003s\u0011Y\u0005\u0003\u0004\u0003 \u0011\u0003\rA^\u0001\u0017aJ|G-^2u\u0003JLG/\u001f\u0013fqR,gn]5p]R!\u00111\nB)\u0011\u0019\u0011y\"\u0012a\u0001m\u0006A\u0002O]8ek\u000e$X\t\\3nK:$H%\u001a=uK:\u001c\u0018n\u001c8\u0015\t\t]#1\f\u000b\u0005\u0003+\u0012I\u0006C\u0005\u0002^\u0019\u000b\t\u00111\u0001\u0002L!1!q\u0004$A\u0002Y\f\u0011\u0004\u001d:pIV\u001cG/\u0013;fe\u0006$xN\u001d\u0013fqR,gn]5p]R!\u00111\rB1\u0011\u0019\u0011yb\u0012a\u0001m\u0006\u00112-\u00198FcV\fG\u000eJ3yi\u0016t7/[8o)\u0011\u00119Ga\u001b\u0015\u0007m\u0014I\u0007C\u0005\u0002^!\u000b\t\u00111\u0001\u0002V!1!q\u0004%A\u0002Y\fA\u0004\u001d:pIV\u001cG/\u00127f[\u0016tGOT1nK\u0012*\u0007\u0010^3og&|g\u000e\u0006\u0003\u0003r\tUD\u0003BA\u001d\u0005gB\u0011\"!\u0018J\u0003\u0003\u0005\r!a\u0013\t\r\t}\u0011\n1\u0001w\u0003IA\u0017m\u001d5D_\u0012,G%\u001a=uK:\u001c\u0018n\u001c8\u0015\t\u0005u$1\u0010\u0005\u0007\u0005?Q\u0005\u0019\u0001<\u0002!\u0015\fX/\u00197tI\u0015DH/\u001a8tS>tG\u0003\u0002BA\u0005\u000b#2a\u001fBB\u0011%\tifSA\u0001\u0002\u0004\t)\u0006\u0003\u0004\u0003 -\u0003\rA^\u0001\u0013i>\u001cFO]5oO\u0012*\u0007\u0010^3og&|g\u000e\u0006\u0003\u0002\b\n-\u0005B\u0002B\u0010\u0019\u0002\u0007a\u000f
   #13 = Utf8               coursier/core/Type$Exotic$
   #14 = Class              #13           // coursier/core/Type$Exotic$
   #15 = Utf8
   #16 = Utf8               value
   #17 = Utf8               Ljava/lang/String;
   #18 = Utf8               toString$extension
   #19 = Utf8               (Ljava/lang/String;)Ljava/lang/String;
   #20 = Utf8               $this
   #21 = Utf8               coursier/core/Type$
   #22 = Class              #21           // coursier/core/Type$
   #23 = Utf8               MODULE$
   #24 = Utf8               Lcoursier/core/Type$;
   #25 = NameAndType        #23:#24       // MODULE$:Lcoursier/core/Type$;
   #26 = Fieldref           #22.#25       // coursier/core/Type$.MODULE$:Lcoursier/core/Type$;
   #27 = NameAndType        #18:#19       // toString$extension:(Ljava/lang/String;)Ljava/lang/String;
   #28 = Methodref          #22.#27       // coursier/core/Type$.toString$extension:(Ljava/lang/String;)Ljava/lang/String;
   #29 = Utf8               equals$extension
   #30 = Utf8               (Ljava/lang/String;Ljava/lang/Object;)Z
   #31 = Utf8               x$1
   #32 = NameAndType        #29:#30       // equals$extension:(Ljava/lang/String;Ljava/lang/Object;)Z
   #33 = Methodref          #22.#32       // coursier/core/Type$.equals$extension:(Ljava/lang/String;Ljava/lang/Object;)Z
   #34 = Utf8               hashCode$extension
   #35 = Utf8               (Ljava/lang/String;)I
   #36 = NameAndType        #34:#35       // hashCode$extension:(Ljava/lang/String;)I
   #37 = Methodref          #22.#36       // coursier/core/Type$.hashCode$extension:(Ljava/lang/String;)I
   #38 = Utf8               productElementName$extension
   #39 = Utf8               (Ljava/lang/String;I)Ljava/lang/String;
   #40 = NameAndType        #38:#39       // productElementName$extension:(Ljava/lang/String;I)Ljava/lang/String;
   #41 = Methodref          #22.#40       // coursier/core/Type$.productElementName$extension:(Ljava/lang/String;I)Ljava/lang/String;
   #42 = Utf8               canEqual$extension
   #43 = NameAndType        #42:#30       // canEqual$extension:(Ljava/lang/String;Ljava/lang/Object;)Z
   #44 = Methodref          #22.#43       // coursier/core/Type$.canEqual$extension:(Ljava/lang/String;Ljava/lang/Object;)Z
   #45 = Utf8               productIterator$extension
   #46 = Utf8               (Ljava/lang/String;)Lscala/collection/Iterator;
   #47 = Utf8               (Ljava/lang/String;)Lscala/collection/Iterator<Ljava/lang/Object;>;
   #48 = NameAndType        #45:#46       // productIterator$extension:(Ljava/lang/String;)Lscala/collection/Iterator;
   #49 = Methodref          #22.#48       // coursier/core/Type$.productIterator$extension:(Ljava/lang/String;)Lscala/collection/Iterator;
   #50 = Utf8               productElement$extension
   #51 = Utf8               (Ljava/lang/String;I)Ljava/lang/Object;
   #52 = NameAndType        #50:#51       // productElement$extension:(Ljava/lang/String;I)Ljava/lang/Object;
   #53 = Methodref          #22.#52       // coursier/core/Type$.productElement$extension:(Ljava/lang/String;I)Ljava/lang/Object;
   #54 = Utf8               productArity$extension
   #55 = NameAndType        #54:#35       // productArity$extension:(Ljava/lang/String;)I
   #56 = Methodref          #22.#55       // coursier/core/Type$.productArity$extension:(Ljava/lang/String;)I
   #57 = Utf8               productPrefix$extension
   #58 = NameAndType        #57:#19       // productPrefix$extension:(Ljava/lang/String;)Ljava/lang/String;
   #59 = Methodref          #22.#58       // coursier/core/Type$.productPrefix$extension:(Ljava/lang/String;)Ljava/lang/String;
   #60 = Utf8               copy$default$1$extension
   #61 = NameAndType        #60:#19       // copy$default$1$extension:(Ljava/lang/String;)Ljava/lang/String;
   #62 = Methodref          #22.#61       // coursier/core/Type$.copy$default$1$extension:(Ljava/lang/String;)Ljava/lang/String;
   #63 = Utf8               copy$extension
   #64 = Utf8               (Ljava/lang/String;Ljava/lang/String;)Ljava/lang/String;
   #65 = NameAndType        #63:#64       // copy$extension:(Ljava/lang/String;Ljava/lang/String;)Ljava/lang/String;
   #66 = Methodref          #22.#65       // coursier/core/Type$.copy$extension:(Ljava/lang/String;Ljava/lang/String;)Ljava/lang/String;
   #67 = Utf8               asExtension$extension
   #68 = NameAndType        #67:#19       // asExtension$extension:(Ljava/lang/String;)Ljava/lang/String;
   #69 = Methodref          #22.#68       // coursier/core/Type$.asExtension$extension:(Ljava/lang/String;)Ljava/lang/String;
   #70 = Utf8               map$extension
   #71 = Utf8               (Ljava/lang/String;Lscala/Function1;)Ljava/lang/String;
   #72 = Utf8               f
   #73 = NameAndType        #70:#71       // map$extension:(Ljava/lang/String;Lscala/Function1;)Ljava/lang/String;
   #74 = Methodref          #22.#73       // coursier/core/Type$.map$extension:(Ljava/lang/String;Lscala/Function1;)Ljava/lang/String;
   #75 = Utf8               nonEmpty$extension
   #76 = Utf8               (Ljava/lang/String;)Z
   #77 = NameAndType        #75:#76       // nonEmpty$extension:(Ljava/lang/String;)Z
   #78 = Methodref          #22.#77       // coursier/core/Type$.nonEmpty$extension:(Ljava/lang/String;)Z
   #79 = Utf8               isEmpty$extension
   #80 = NameAndType        #79:#76       // isEmpty$extension:(Ljava/lang/String;)Z
   #81 = Methodref          #22.#80       // coursier/core/Type$.isEmpty$extension:(Ljava/lang/String;)Z
   #82 = Utf8               unapply
   #83 = Utf8               (Ljava/lang/String;)Lscala/Option;
   #84 = Utf8               (Ljava/lang/String;)Lscala/Option<Ljava/lang/String;>;
   #85 = Utf8               x$0
   #86 = NameAndType        #82:#83       // unapply:(Ljava/lang/String;)Lscala/Option;
   #87 = Methodref          #22.#86       // coursier/core/Type$.unapply:(Ljava/lang/String;)Lscala/Option;
   #88 = Utf8               apply
   #89 = NameAndType        #88:#19       // apply:(Ljava/lang/String;)Ljava/lang/String;
   #90 = Methodref          #22.#89       // coursier/core/Type$.apply:(Ljava/lang/String;)Ljava/lang/String;
   #91 = Utf8               all
   #92 = Utf8               ()Ljava/lang/String;
   #93 = NameAndType        #91:#92       // all:()Ljava/lang/String;
   #94 = Methodref          #22.#93       // coursier/core/Type$.all:()Ljava/lang/String;
   #95 = Utf8               empty
   #96 = NameAndType        #95:#92       // empty:()Ljava/lang/String;
   #97 = Methodref          #22.#96       // coursier/core/Type$.empty:()Ljava/lang/String;
   #98 = Utf8               pom
   #99 = NameAndType        #98:#92       // pom:()Ljava/lang/String;
  #100 = Methodref          #22.#99       // coursier/core/Type$.pom:()Ljava/lang/String;
  #101 = Utf8               ivy
  #102 = NameAndType        #101:#92      // ivy:()Ljava/lang/String;
  #103 = Methodref          #22.#102      // coursier/core/Type$.ivy:()Ljava/lang/String;
  #104 = Utf8               javaSource
  #105 = NameAndType        #104:#92      // javaSource:()Ljava/lang/String;
  #106 = Methodref          #22.#105      // coursier/core/Type$.javaSource:()Ljava/lang/String;
  #107 = Utf8               javadoc
  #108 = NameAndType        #107:#92      // javadoc:()Ljava/lang/String;
  #109 = Methodref          #22.#108      // coursier/core/Type$.javadoc:()Ljava/lang/String;
  #110 = Utf8               source
  #111 = NameAndType        #110:#92      // source:()Ljava/lang/String;
  #112 = Methodref          #22.#111      // coursier/core/Type$.source:()Ljava/lang/String;
  #113 = Utf8               doc
  #114 = NameAndType        #113:#92      // doc:()Ljava/lang/String;
  #115 = Methodref          #22.#114      // coursier/core/Type$.doc:()Ljava/lang/String;
  #116 = Utf8               bundle
  #117 = NameAndType        #116:#92      // bundle:()Ljava/lang/String;
  #118 = Methodref          #22.#117      // coursier/core/Type$.bundle:()Ljava/lang/String;
  #119 = Utf8               testJar
  #120 = NameAndType        #119:#92      // testJar:()Ljava/lang/String;
  #121 = Methodref          #22.#120      // coursier/core/Type$.testJar:()Ljava/lang/String;
  #122 = Utf8               jar
  #123 = NameAndType        #122:#92      // jar:()Ljava/lang/String;
  #124 = Methodref          #22.#123      // coursier/core/Type$.jar:()Ljava/lang/String;
  #125 = Utf8               ordering
  #126 = Utf8               ()Lscala/math/Ordering;
  #127 = Utf8               ()Lscala/math/Ordering<Lcoursier/core/Type;>;
  #128 = NameAndType        #125:#126     // ordering:()Lscala/math/Ordering;
  #129 = Methodref          #22.#128      // coursier/core/Type$.ordering:()Lscala/math/Ordering;
  #130 = Utf8               productElementNames
  #131 = Utf8               ()Lscala/collection/Iterator;
  #132 = Utf8               ()Lscala/collection/Iterator<Ljava/lang/String;>;
  #133 = Utf8               productElementNames$
  #134 = Utf8               (Lscala/Product;)Lscala/collection/Iterator;
  #135 = NameAndType        #133:#134     // productElementNames$:(Lscala/Product;)Lscala/collection/Iterator;
  #136 = InterfaceMethodref #6.#135       // scala/Product.productElementNames$:(Lscala/Product;)Lscala/collection/Iterator;
  #137 = Utf8               this
  #138 = Utf8               Lcoursier/core/Type;
  #139 = NameAndType        #16:#17       // value:Ljava/lang/String;
  #140 = Fieldref           #2.#139       // coursier/core/Type.value:Ljava/lang/String;
  #141 = Utf8               isEmpty
  #142 = Utf8               ()Z
  #143 = NameAndType        #16:#92       // value:()Ljava/lang/String;
  #144 = Methodref          #2.#143       // coursier/core/Type.value:()Ljava/lang/String;
  #145 = Utf8               nonEmpty
  #146 = Utf8               map
  #147 = Utf8               (Lscala/Function1;)Ljava/lang/String;
  #148 = Utf8               (Lscala/Function1<Ljava/lang/String;Ljava/lang/String;>;)Ljava/lang/String;
  #149 = Utf8               Lscala/Function1;
  #150 = Utf8               asExtension
  #151 = Utf8               copy
  #152 = Utf8               copy$default$1
  #153 = Utf8               productPrefix
  #154 = Utf8               productArity
  #155 = Utf8               ()I
  #156 = Utf8               productElement
  #157 = Utf8               (I)Ljava/lang/Object;
  #158 = Utf8               I
  #159 = Utf8               productIterator
  #160 = Utf8               ()Lscala/collection/Iterator<Ljava/lang/Object;>;
  #161 = Utf8               canEqual
  #162 = Utf8               (Ljava/lang/Object;)Z
  #163 = Utf8               Ljava/lang/Object;
  #164 = Utf8               productElementName
  #165 = Utf8               (I)Ljava/lang/String;
  #166 = Utf8               hashCode
  #167 = Utf8               equals
  #168 = Utf8               toString
  #169 = Utf8               <init>
  #170 = Utf8               (Ljava/lang/String;)V
  #171 = Utf8               ()V
  #172 = NameAndType        #169:#171     // "<init>":()V
  #173 = Methodref          #4.#172       // java/lang/Object."<init>":()V
  #174 = Utf8               $init$
  #175 = Utf8               (Lscala/Product;)V
  #176 = NameAndType        #174:#175     // $init$:(Lscala/Product;)V
  #177 = InterfaceMethodref #6.#176       // scala/Product.$init$:(Lscala/Product;)V
  #178 = Utf8               Code
  #179 = Utf8               MethodParameters
  #180 = Utf8               Signature
  #181 = Utf8               LineNumberTable
  #182 = Utf8               LocalVariableTable
  #183 = Utf8               InnerClasses
  #184 = Utf8               SourceFile
  #185 = Utf8               RuntimeVisibleAnnotations
  #186 = Utf8               ScalaInlineInfo
  #187 = Utf8               ScalaSig
{
  private final java.lang.String value;
    descriptor: Ljava/lang/String;
    flags: (0x0012) ACC_PRIVATE, ACC_FINAL

  public static java.lang.String toString$extension(java.lang.String);
    descriptor: (Ljava/lang/String;)Ljava/lang/String;
    flags: (0x0009) ACC_PUBLIC, ACC_STATIC
    Code:
      stack=2, locals=1, args_size=1
         0: getstatic     #26                 // Field coursier/core/Type$.MODULE$:Lcoursier/core/Type$;
         3: aload_0
         4: invokevirtual #28                 // Method coursier/core/Type$.toString$extension:(Ljava/lang/String;)Ljava/lang/String;
         7: areturn
    MethodParameters:
      Name                           Flags
      $this                          final

  public static boolean equals$extension(java.lang.String, java.lang.Object);
    descriptor: (Ljava/lang/String;Ljava/lang/Object;)Z
    flags: (0x0009) ACC_PUBLIC, ACC_STATIC
    Code:
      stack=3, locals=2, args_size=2
         0: getstatic     #26                 // Field coursier/core/Type$.MODULE$:Lcoursier/core/Type$;
         3: aload_0
         4: aload_1
         5: invokevirtual #33                 // Method coursier/core/Type$.equals$extension:(Ljava/lang/String;Ljava/lang/Object;)Z
         8: ireturn
    MethodParameters:
      Name                           Flags
      $this                          final
      x$1                            final

  public static int hashCode$extension(java.lang.String);
    descriptor: (Ljava/lang/String;)I
    flags: (0x0009) ACC_PUBLIC, ACC_STATIC
    Code:
      stack=2, locals=1, args_size=1
         0: getstatic     #26                 // Field coursier/core/Type$.MODULE$:Lcoursier/core/Type$;
         3: aload_0
         4: invokevirtual #37                 // Method coursier/core/Type$.hashCode$extension:(Ljava/lang/String;)I
         7: ireturn
    MethodParameters:
      Name                           Flags
      $this                          final

  public static java.lang.String productElementName$extension(java.lang.String, int);
    descriptor: (Ljava/lang/String;I)Ljava/lang/String;
    flags: (0x0009) ACC_PUBLIC, ACC_STATIC
    Code:
      stack=3, locals=2, args_size=2
         0: getstatic     #26                 // Field coursier/core/Type$.MODULE$:Lcoursier/core/Type$;
         3: aload_0
         4: iload_1
         5: invokevirtual #41                 // Method coursier/core/Type$.productElementName$extension:(Ljava/lang/String;I)Ljava/lang/String;
         8: areturn
    MethodParameters:
      Name                           Flags
      $this                          final
      x$1                            final

  public static boolean canEqual$extension(java.lang.String, java.lang.Object);
    descriptor: (Ljava/lang/String;Ljava/lang/Object;)Z
    flags: (0x0009) ACC_PUBLIC, ACC_STATIC
    Code:
      stack=3, locals=2, args_size=2
         0: getstatic     #26                 // Field coursier/core/Type$.MODULE$:Lcoursier/core/Type$;
         3: aload_0
         4: aload_1
         5: invokevirtual #44                 // Method coursier/core/Type$.canEqual$extension:(Ljava/lang/String;Ljava/lang/Object;)Z
         8: ireturn
    MethodParameters:
      Name                           Flags
      $this                          final
      x$1                            final

  public static scala.collection.Iterator<java.lang.Object> productIterator$extension(java.lang.String);
    descriptor: (Ljava/lang/String;)Lscala/collection/Iterator;
    flags: (0x0009) ACC_PUBLIC, ACC_STATIC
    Code:
      stack=2, locals=1, args_size=1
         0: getstatic     #26                 // Field coursier/core/Type$.MODULE$:Lcoursier/core/Type$;
         3: aload_0
         4: invokevirtual #49                 // Method coursier/core/Type$.productIterator$extension:(Ljava/lang/String;)Lscala/collection/Iterator;
         7: areturn
    Signature: #47                          // (Ljava/lang/String;)Lscala/collection/Iterator<Ljava/lang/Object;>;
    MethodParameters:
      Name                           Flags
      $this                          final

  public static java.lang.Object productElement$extension(java.lang.String, int);
    descriptor: (Ljava/lang/String;I)Ljava/lang/Object;
    flags: (0x0009) ACC_PUBLIC, ACC_STATIC
    Code:
      stack=3, locals=2, args_size=2
         0: getstatic     #26                 // Field coursier/core/Type$.MODULE$:Lcoursier/core/Type$;
         3: aload_0
         4: iload_1
         5: invokevirtual #53                 // Method coursier/core/Type$.productElement$extension:(Ljava/lang/String;I)Ljava/lang/Object;
         8: areturn
    MethodParameters:
      Name                           Flags
      $this                          final
      x$1                            final

  public static int productArity$extension(java.lang.String);
    descriptor: (Ljava/lang/String;)I
    flags: (0x0009) ACC_PUBLIC, ACC_STATIC
    Code:
      stack=2, locals=1, args_size=1
         0: getstatic     #26                 // Field coursier/core/Type$.MODULE$:Lcoursier/core/Type$;
         3: aload_0
         4: invokevirtual #56                 // Method coursier/core/Type$.productArity$extension:(Ljava/lang/String;)I
         7: ireturn
    MethodParameters:
      Name                           Flags
      $this                          final

  public static java.lang.String productPrefix$extension(java.lang.String);
    descriptor: (Ljava/lang/String;)Ljava/lang/String;
    flags: (0x0009) ACC_PUBLIC, ACC_STATIC
    Code:
      stack=2, locals=1, args_size=1
         0: getstatic     #26                 // Field coursier/core/Type$.MODULE$:Lcoursier/core/Type$;
         3: aload_0
         4: invokevirtual #59                 // Method coursier/core/Type$.productPrefix$extension:(Ljava/lang/String;)Ljava/lang/String;
         7: areturn
    MethodParameters:
      Name                           Flags
      $this                          final

  public static java.lang.String copy$default$1$extension(java.lang.String);
    descriptor: (Ljava/lang/String;)Ljava/lang/String;
    flags: (0x0009) ACC_PUBLIC, ACC_STATIC
    Code:
      stack=2, locals=1, args_size=1
         0: getstatic     #26                 // Field coursier/core/Type$.MODULE$:Lcoursier/core/Type$;
         3: aload_0
         4: invokevirtual #62                 // Method coursier/core/Type$.copy$default$1$extension:(Ljava/lang/String;)Ljava/lang/String;
         7: areturn
    MethodParameters:
      Name                           Flags
      $this                          final

  public static java.lang.String copy$extension(java.lang.String, java.lang.String);
    descriptor: (Ljava/lang/String;Ljava/lang/String;)Ljava/lang/String;
    flags: (0x0009) ACC_PUBLIC, ACC_STATIC
    Code:
      stack=3, locals=2, args_size=2
         0: getstatic     #26                 // Field coursier/core/Type$.MODULE$:Lcoursier/core/Type$;
         3: aload_0
         4: aload_1
         5: invokevirtual #66                 // Method coursier/core/Type$.copy$extension:(Ljava/lang/String;Ljava/lang/String;)Ljava/lang/String;
         8: areturn
    MethodParameters:
      Name                           Flags
      $this                          final
      value                          final

  public static java.lang.String asExtension$extension(java.lang.String);
    descriptor: (Ljava/lang/String;)Ljava/lang/String;
    flags: (0x0009) ACC_PUBLIC, ACC_STATIC
    Code:
      stack=2, locals=1, args_size=1
         0: getstatic     #26                 // Field coursier/core/Type$.MODULE$:Lcoursier/core/Type$;
         3: aload_0
         4: invokevirtual #69                 // Method coursier/core/Type$.asExtension$extension:(Ljava/lang/String;)Ljava/lang/String;
         7: areturn
    MethodParameters:
      Name                           Flags
      $this                          final

  public static java.lang.String map$extension(java.lang.String, scala.Function1);
    descriptor: (Ljava/lang/String;Lscala/Function1;)Ljava/lang/String;
    flags: (0x0009) ACC_PUBLIC, ACC_STATIC
    Code:
      stack=3, locals=2, args_size=2
         0: getstatic     #26                 // Field coursier/core/Type$.MODULE$:Lcoursier/core/Type$;
         3: aload_0
         4: aload_1
         5: invokevirtual #74                 // Method coursier/core/Type$.map$extension:(Ljava/lang/String;Lscala/Function1;)Ljava/lang/String;
         8: areturn
    MethodParameters:
      Name                           Flags
      $this                          final
      f                              final

  public static boolean nonEmpty$extension(java.lang.String);
    descriptor: (Ljava/lang/String;)Z
    flags: (0x0009) ACC_PUBLIC, ACC_STATIC
    Code:
      stack=2, locals=1, args_size=1
         0: getstatic     #26                 // Field coursier/core/Type$.MODULE$:Lcoursier/core/Type$;
         3: aload_0
         4: invokevirtual #78                 // Method coursier/core/Type$.nonEmpty$extension:(Ljava/lang/String;)Z
         7: ireturn
    MethodParameters:
      Name                           Flags
      $this                          final

  public static boolean isEmpty$extension(java.lang.String);
    descriptor: (Ljava/lang/String;)Z
    flags: (0x0009) ACC_PUBLIC, ACC_STATIC
    Code:
      stack=2, locals=1, args_size=1
         0: getstatic     #26                 // Field coursier/core/Type$.MODULE$:Lcoursier/core/Type$;
         3: aload_0
         4: invokevirtual #81                 // Method coursier/core/Type$.isEmpty$extension:(Ljava/lang/String;)Z
         7: ireturn
    MethodParameters:
      Name                           Flags
      $this                          final

  public static scala.Option<java.lang.String> unapply(java.lang.String);
    descriptor: (Ljava/lang/String;)Lscala/Option;
    flags: (0x0009) ACC_PUBLIC, ACC_STATIC
    Code:
      stack=2, locals=1, args_size=1
         0: getstatic     #26                 // Field coursier/core/Type$.MODULE$:Lcoursier/core/Type$;
         3: aload_0
         4: invokevirtual #87                 // Method coursier/core/Type$.unapply:(Ljava/lang/String;)Lscala/Option;
         7: areturn
    Signature: #84                          // (Ljava/lang/String;)Lscala/Option<Ljava/lang/String;>;
    MethodParameters:
      Name                           Flags
      x$0                            final

  public static java.lang.String apply(java.lang.String);
    descriptor: (Ljava/lang/String;)Ljava/lang/String;
    flags: (0x0009) ACC_PUBLIC, ACC_STATIC
    Code:
      stack=2, locals=1, args_size=1
         0: getstatic     #26                 // Field coursier/core/Type$.MODULE$:Lcoursier/core/Type$;
         3: aload_0
         4: invokevirtual #90                 // Method coursier/core/Type$.apply:(Ljava/lang/String;)Ljava/lang/String;
         7: areturn
    MethodParameters:
      Name                           Flags
      value                          final

  public static java.lang.String all();
    descriptor: ()Ljava/lang/String;
    flags: (0x0009) ACC_PUBLIC, ACC_STATIC
    Code:
      stack=1, locals=0, args_size=0
         0: getstatic     #26                 // Field coursier/core/Type$.MODULE$:Lcoursier/core/Type$;
         3: invokevirtual #94                 // Method coursier/core/Type$.all:()Ljava/lang/String;
         6: areturn

  public static java.lang.String empty();
    descriptor: ()Ljava/lang/String;
    flags: (0x0009) ACC_PUBLIC, ACC_STATIC
    Code:
      stack=1, locals=0, args_size=0
         0: getstatic     #26                 // Field coursier/core/Type$.MODULE$:Lcoursier/core/Type$;
         3: invokevirtual #97                 // Method coursier/core/Type$.empty:()Ljava/lang/String;
         6: areturn

  public static java.lang.String pom();
    descriptor: ()Ljava/lang/String;
    flags: (0x0009) ACC_PUBLIC, ACC_STATIC
    Code:
      stack=1, locals=0, args_size=0
         0: getstatic     #26                 // Field coursier/core/Type$.MODULE$:Lcoursier/core/Type$;
         3: invokevirtual #100                // Method coursier/core/Type$.pom:()Ljava/lang/String;
         6: areturn

  public static java.lang.String ivy();
    descriptor: ()Ljava/lang/String;
    flags: (0x0009) ACC_PUBLIC, ACC_STATIC
    Code:
      stack=1, locals=0, args_size=0
         0: getstatic     #26                 // Field coursier/core/Type$.MODULE$:Lcoursier/core/Type$;
         3: invokevirtual #103                // Method coursier/core/Type$.ivy:()Ljava/lang/String;
         6: areturn

  public static java.lang.String javaSource();
    descriptor: ()Ljava/lang/String;
    flags: (0x0009) ACC_PUBLIC, ACC_STATIC
    Code:
      stack=1, locals=0, args_size=0
         0: getstatic     #26                 // Field coursier/core/Type$.MODULE$:Lcoursier/core/Type$;
         3: invokevirtual #106                // Method coursier/core/Type$.javaSource:()Ljava/lang/String;
         6: areturn

  public static java.lang.String javadoc();
    descriptor: ()Ljava/lang/String;
    flags: (0x0009) ACC_PUBLIC, ACC_STATIC
    Code:
      stack=1, locals=0, args_size=0
         0: getstatic     #26                 // Field coursier/core/Type$.MODULE$:Lcoursier/core/Type$;
         3: invokevirtual #109                // Method coursier/core/Type$.javadoc:()Ljava/lang/String;
         6: areturn

  public static java.lang.String source();
    descriptor: ()Ljava/lang/String;
    flags: (0x0009) ACC_PUBLIC, ACC_STATIC
    Code:
      stack=1, locals=0, args_size=0
         0: getstatic     #26                 // Field coursier/core/Type$.MODULE$:Lcoursier/core/Type$;
         3: invokevirtual #112                // Method coursier/core/Type$.source:()Ljava/lang/String;
         6: areturn

  public static java.lang.String doc();
    descriptor: ()Ljava/lang/String;
    flags: (0x0009) ACC_PUBLIC, ACC_STATIC
    Code:
      stack=1, locals=0, args_size=0
         0: getstatic     #26                 // Field coursier/core/Type$.MODULE$:Lcoursier/core/Type$;
         3: invokevirtual #115                // Method coursier/core/Type$.doc:()Ljava/lang/String;
         6: areturn

  public static java.lang.String bundle();
    descriptor: ()Ljava/lang/String;
    flags: (0x0009) ACC_PUBLIC, ACC_STATIC
    Code:
      stack=1, locals=0, args_size=0
         0: getstatic     #26                 // Field coursier/core/Type$.MODULE$:Lcoursier/core/Type$;
         3: invokevirtual #118                // Method coursier/core/Type$.bundle:()Ljava/lang/String;
         6: areturn

  public static java.lang.String testJar();
    descriptor: ()Ljava/lang/String;
    flags: (0x0009) ACC_PUBLIC, ACC_STATIC
    Code:
      stack=1, locals=0, args_size=0
         0: getstatic     #26                 // Field coursier/core/Type$.MODULE$:Lcoursier/core/Type$;
         3: invokevirtual #121                // Method coursier/core/Type$.testJar:()Ljava/lang/String;
         6: areturn

  public static java.lang.String jar();
    descriptor: ()Ljava/lang/String;
    flags: (0x0009) ACC_PUBLIC, ACC_STATIC
    Code:
      stack=1, locals=0, args_size=0
         0: getstatic     #26                 // Field coursier/core/Type$.MODULE$:Lcoursier/core/Type$;
         3: invokevirtual #124                // Method coursier/core/Type$.jar:()Ljava/lang/String;
         6: areturn

  public static scala.math.Ordering<coursier.core.Type> ordering();
    descriptor: ()Lscala/math/Ordering;
    flags: (0x0009) ACC_PUBLIC, ACC_STATIC
    Code:
      stack=1, locals=0, args_size=0
         0: getstatic     #26                 // Field coursier/core/Type$.MODULE$:Lcoursier/core/Type$;
         3: invokevirtual #129                // Method coursier/core/Type$.ordering:()Lscala/math/Ordering;
         6: areturn
    Signature: #127                         // ()Lscala/math/Ordering<Lcoursier/core/Type;>;

  public scala.collection.Iterator<java.lang.String> productElementNames();
    descriptor: ()Lscala/collection/Iterator;
    flags: (0x0001) ACC_PUBLIC
    Code:
      stack=1, locals=1, args_size=1
         0: aload_0
         1: invokestatic  #136                // InterfaceMethod scala/Product.productElementNames$:(Lscala/Product;)Lscala/collection/Iterator;
         4: areturn
      LineNumberTable:
        line 83: 0
      LocalVariableTable:
        Start  Length  Slot  Name   Signature
            0       5     0  this   Lcoursier/core/Type;
    Signature: #132                         // ()Lscala/collection/Iterator<Ljava/lang/String;>;

  public java.lang.String value();
    descriptor: ()Ljava/lang/String;
    flags: (0x0001) ACC_PUBLIC
    Code:
      stack=1, locals=1, args_size=1
         0: aload_0
         1: getfield      #140                // Field value:Ljava/lang/String;
         4: areturn
      LineNumberTable:
        line 83: 0
      LocalVariableTable:
        Start  Length  Slot  Name   Signature
            0       5     0  this   Lcoursier/core/Type;

  public boolean isEmpty();
    descriptor: ()Z
    flags: (0x0001) ACC_PUBLIC
    Code:
      stack=2, locals=1, args_size=1
         0: getstatic     #26                 // Field coursier/core/Type$.MODULE$:Lcoursier/core/Type$;
         3: aload_0
         4: invokevirtual #144                // Method value:()Ljava/lang/String;
         7: invokevirtual #81                 // Method coursier/core/Type$.isEmpty$extension:(Ljava/lang/String;)Z
        10: ireturn
      LineNumberTable:
        line 85: 0
      LocalVariableTable:
        Start  Length  Slot  Name   Signature
            0      11     0  this   Lcoursier/core/Type;

  public boolean nonEmpty();
    descriptor: ()Z
    flags: (0x0001) ACC_PUBLIC
    Code:
      stack=2, locals=1, args_size=1
         0: getstatic     #26                 // Field coursier/core/Type$.MODULE$:Lcoursier/core/Type$;
         3: aload_0
         4: invokevirtual #144                // Method value:()Ljava/lang/String;
         7: invokevirtual #78                 // Method coursier/core/Type$.nonEmpty$extension:(Ljava/lang/String;)Z
        10: ireturn
      LineNumberTable:
        line 87: 0
      LocalVariableTable:
        Start  Length  Slot  Name   Signature
            0      11     0  this   Lcoursier/core/Type;

  public java.lang.String map(scala.Function1<java.lang.String, java.lang.String>);
    descriptor: (Lscala/Function1;)Ljava/lang/String;
    flags: (0x0001) ACC_PUBLIC
    Code:
      stack=3, locals=2, args_size=2
         0: getstatic     #26                 // Field coursier/core/Type$.MODULE$:Lcoursier/core/Type$;
         3: aload_0
         4: invokevirtual #144                // Method value:()Ljava/lang/String;
         7: aload_1
         8: invokevirtual #74                 // Method coursier/core/Type$.map$extension:(Ljava/lang/String;Lscala/Function1;)Ljava/lang/String;
        11: areturn
      LineNumberTable:
        line 89: 0
      LocalVariableTable:
        Start  Length  Slot  Name   Signature
            0      12     0  this   Lcoursier/core/Type;
            0      12     1     f   Lscala/Function1;
    Signature: #148                         // (Lscala/Function1<Ljava/lang/String;Ljava/lang/String;>;)Ljava/lang/String;
    MethodParameters:
      Name                           Flags
      f                              final

  public java.lang.String asExtension();
    descriptor: ()Ljava/lang/String;
    flags: (0x0001) ACC_PUBLIC
    Code:
      stack=2, locals=1, args_size=1
         0: getstatic     #26                 // Field coursier/core/Type$.MODULE$:Lcoursier/core/Type$;
         3: aload_0
         4: invokevirtual #144                // Method value:()Ljava/lang/String;
         7: invokevirtual #69                 // Method coursier/core/Type$.asExtension$extension:(Ljava/lang/String;)Ljava/lang/String;
        10: areturn
      LineNumberTable:
        line 92: 0
      LocalVariableTable:
        Start  Length  Slot  Name   Signature
            0      11     0  this   Lcoursier/core/Type;

  public java.lang.String copy(java.lang.String);
    descriptor: (Ljava/lang/String;)Ljava/lang/String;
    flags: (0x0001) ACC_PUBLIC
    Code:
      stack=3, locals=2, args_size=2
         0: getstatic     #26                 // Field coursier/core/Type$.MODULE$:Lcoursier/core/Type$;
         3: aload_0
         4: invokevirtual #144                // Method value:()Ljava/lang/String;
         7: aload_1
         8: invokevirtual #66                 // Method coursier/core/Type$.copy$extension:(Ljava/lang/String;Ljava/lang/String;)Ljava/lang/String;
        11: areturn
      LineNumberTable:
        line 83: 0
      LocalVariableTable:
        Start  Length  Slot  Name   Signature
            0      12     0  this   Lcoursier/core/Type;
            0      12     1 value   Ljava/lang/String;
    MethodParameters:
      Name                           Flags
      value                          final

  public java.lang.String copy$default$1();
    descriptor: ()Ljava/lang/String;
    flags: (0x0001) ACC_PUBLIC
    Code:
      stack=2, locals=1, args_size=1
         0: getstatic     #26                 // Field coursier/core/Type$.MODULE$:Lcoursier/core/Type$;
         3: aload_0
         4: invokevirtual #144                // Method value:()Ljava/lang/String;
         7: invokevirtual #62                 // Method coursier/core/Type$.copy$default$1$extension:(Ljava/lang/String;)Ljava/lang/String;
        10: areturn
      LineNumberTable:
        line 83: 0
      LocalVariableTable:
        Start  Length  Slot  Name   Signature
            0      11     0  this   Lcoursier/core/Type;

  public java.lang.String productPrefix();
    descriptor: ()Ljava/lang/String;
    flags: (0x0001) ACC_PUBLIC
    Code:
      stack=2, locals=1, args_size=1
         0: getstatic     #26                 // Field coursier/core/Type$.MODULE$:Lcoursier/core/Type$;
         3: aload_0
         4: invokevirtual #144                // Method value:()Ljava/lang/String;
         7: invokevirtual #59                 // Method coursier/core/Type$.productPrefix$extension:(Ljava/lang/String;)Ljava/lang/String;
        10: areturn
      LineNumberTable:
        line 83: 0
      LocalVariableTable:
        Start  Length  Slot  Name   Signature
            0      11     0  this   Lcoursier/core/Type;

  public int productArity();
    descriptor: ()I
    flags: (0x0001) ACC_PUBLIC
    Code:
      stack=2, locals=1, args_size=1
         0: getstatic     #26                 // Field coursier/core/Type$.MODULE$:Lcoursier/core/Type$;
         3: aload_0
         4: invokevirtual #144                // Method value:()Ljava/lang/String;
         7: invokevirtual #56                 // Method coursier/core/Type$.productArity$extension:(Ljava/lang/String;)I
        10: ireturn
      LineNumberTable:
        line 83: 0
      LocalVariableTable:
        Start  Length  Slot  Name   Signature
            0      11     0  this   Lcoursier/core/Type;

  public java.lang.Object productElement(int);
    descriptor: (I)Ljava/lang/Object;
    flags: (0x0001) ACC_PUBLIC
    Code:
      stack=3, locals=2, args_size=2
         0: getstatic     #26                 // Field coursier/core/Type$.MODULE$:Lcoursier/core/Type$;
         3: aload_0
         4: invokevirtual #144                // Method value:()Ljava/lang/String;
         7: iload_1
         8: invokevirtual #53                 // Method coursier/core/Type$.productElement$extension:(Ljava/lang/String;I)Ljava/lang/Object;
        11: areturn
      LineNumberTable:
        line 83: 0
      LocalVariableTable:
        Start  Length  Slot  Name   Signature
            0      12     0  this   Lcoursier/core/Type;
            0      12     1   x$1   I
    MethodParameters:
      Name                           Flags
      x$1                            final

  public scala.collection.Iterator<java.lang.Object> productIterator();
    descriptor: ()Lscala/collection/Iterator;
    flags: (0x0001) ACC_PUBLIC
    Code:
      stack=2, locals=1, args_size=1
         0: getstatic     #26                 // Field coursier/core/Type$.MODULE$:Lcoursier/core/Type$;
         3: aload_0
         4: invokevirtual #144                // Method value:()Ljava/lang/String;
         7: invokevirtual #49                 // Method coursier/core/Type$.productIterator$extension:(Ljava/lang/String;)Lscala/collection/Iterator;
        10: areturn
      LineNumberTable:
        line 83: 0
      LocalVariableTable:
        Start  Length  Slot  Name   Signature
            0      11     0  this   Lcoursier/core/Type;
    Signature: #160                         // ()Lscala/collection/Iterator<Ljava/lang/Object;>;

  public boolean canEqual(java.lang.Object);
    descriptor: (Ljava/lang/Object;)Z
    flags: (0x0001) ACC_PUBLIC
    Code:
      stack=3, locals=2, args_size=2
         0: getstatic     #26                 // Field coursier/core/Type$.MODULE$:Lcoursier/core/Type$;
         3: aload_0
         4: invokevirtual #144                // Method value:()Ljava/lang/String;
         7: aload_1
         8: invokevirtual #44                 // Method coursier/core/Type$.canEqual$extension:(Ljava/lang/String;Ljava/lang/Object;)Z
        11: ireturn
      LineNumberTable:
        line 83: 0
      LocalVariableTable:
        Start  Length  Slot  Name   Signature
            0      12     0  this   Lcoursier/core/Type;
            0      12     1   x$1   Ljava/lang/Object;
    MethodParameters:
      Name                           Flags
      x$1                            final

  public java.lang.String productElementName(int);
    descriptor: (I)Ljava/lang/String;
    flags: (0x0001) ACC_PUBLIC
    Code:
      stack=3, locals=2, args_size=2
         0: getstatic     #26                 // Field coursier/core/Type$.MODULE$:Lcoursier/core/Type$;
         3: aload_0
         4: invokevirtual #144                // Method value:()Ljava/lang/String;
         7: iload_1
         8: invokevirtual #41                 // Method coursier/core/Type$.productElementName$extension:(Ljava/lang/String;I)Ljava/lang/String;
        11: areturn
      LineNumberTable:
        line 83: 0
      LocalVariableTable:
        Start  Length  Slot  Name   Signature
            0      12     0  this   Lcoursier/core/Type;
            0      12     1   x$1   I
    MethodParameters:
      Name                           Flags
      x$1                            final

  public int hashCode();
    descriptor: ()I
    flags: (0x0001) ACC_PUBLIC
    Code:
      stack=2, locals=1, args_size=1
         0: getstatic     #26                 // Field coursier/core/Type$.MODULE$:Lcoursier/core/Type$;
         3: aload_0
         4: invokevirtual #144                // Method value:()Ljava/lang/String;
         7: invokevirtual #37                 // Method coursier/core/Type$.hashCode$extension:(Ljava/lang/String;)I
        10: ireturn
      LineNumberTable:
        line 83: 0
      LocalVariableTable:
        Start  Length  Slot  Name   Signature
            0      11     0  this   Lcoursier/core/Type;

  public boolean equals(java.lang.Object);
    descriptor: (Ljava/lang/Object;)Z
    flags: (0x0001) ACC_PUBLIC
    Code:
      stack=3, locals=2, args_size=2
         0: getstatic     #26                 // Field coursier/core/Type$.MODULE$:Lcoursier/core/Type$;
         3: aload_0
         4: invokevirtual #144                // Method value:()Ljava/lang/String;
         7: aload_1
         8: invokevirtual #33                 // Method coursier/core/Type$.equals$extension:(Ljava/lang/String;Ljava/lang/Object;)Z
        11: ireturn
      LineNumberTable:
        line 83: 0
      LocalVariableTable:
        Start  Length  Slot  Name   Signature
            0      12     0  this   Lcoursier/core/Type;
            0      12     1   x$1   Ljava/lang/Object;
    MethodParameters:
      Name                           Flags
      x$1                            final

  public java.lang.String toString();
    descriptor: ()Ljava/lang/String;
    flags: (0x0001) ACC_PUBLIC
    Code:
      stack=2, locals=1, args_size=1
         0: getstatic     #26                 // Field coursier/core/Type$.MODULE$:Lcoursier/core/Type$;
         3: aload_0
         4: invokevirtual #144                // Method value:()Ljava/lang/String;
         7: invokevirtual #28                 // Method coursier/core/Type$.toString$extension:(Ljava/lang/String;)Ljava/lang/String;
        10: areturn
      LineNumberTable:
        line 83: 0
      LocalVariableTable:
        Start  Length  Slot  Name   Signature
            0      11     0  this   Lcoursier/core/Type;

  public coursier.core.Type(java.lang.String);
    descriptor: (Ljava/lang/String;)V
    flags: (0x0001) ACC_PUBLIC
    Code:
      stack=2, locals=2, args_size=2
         0: aload_0
         1: aload_1
         2: putfield      #140                // Field value:Ljava/lang/String;
         5: aload_0
         6: invokespecial #173                // Method java/lang/Object."<init>":()V
         9: aload_0
        10: invokestatic  #177                // InterfaceMethod scala/Product.$init$:(Lscala/Product;)V
        13: return
      LineNumberTable:
        line 83: 0
      LocalVariableTable:
        Start  Length  Slot  Name   Signature
            0      14     0  this   Lcoursier/core/Type;
            0      14     1 value   Ljava/lang/String;
    MethodParameters:
      Name                           Flags
      value                          final
}
InnerClasses:
  public static #15= #14 of #2;           // =class coursier/core/Type$Exotic$ of class coursier/core/Type
SourceFile: "Definitions.scala"
RuntimeVisibleAnnotations:
  0: #10(#11=s#12)
    scala.reflect.ScalaSignature(
      bytes="\u0006\u0005\t5e\u0001B\'O\u0005NC\u0001\"\u001b\u0001\u0003\u0016\u0004%\tA\u001b\u0005\tg\u0002\u0011\t\u0012)A\u0005W\")A\u000f\u0001C\u0001k\")\u0011\u0010\u0001C\u0001u\")a\u0010\u0001C\u0001u\"1q\u0010\u0001C\u0001\u0003\u0003Aq!!\u0004\u0001\t\u0003\ty\u0001C\u0005\u0002\u0018\u0001\t\t\u0011\"\u0001\u0002\u001a!I\u0011Q\u0004\u0001\u0012\u0002\u0013\u0005\u0011q\u0004\u0005\n\u0003k\u0001\u0011\u0011!C!\u0003oA\u0011\"a\u0012\u0001\u0003\u0003%\t!!\u0013\t\u0013\u0005E\u0003!!A\u0005\u0002\u0005M\u0003\"CA0\u0001\u0005\u0005I\u0011IA1\u0011%\ty\u0007AA\u0001\n\u0003\t\t\bC\u0005\u0002v\u0001\t\t\u0011\"\u0011\u0002x!I\u00111\u0010\u0001\u0002\u0002\u0013\u0005\u0013Q\u0010\u0005\n\u0003\u007f\u0002\u0011\u0011!C!\u0003\u0003C\u0011\"!\"\u0001\u0003\u0003%\t%a\"\b\u000f\u0005%e\n#\u0001\u0002\f\u001a1QJ\u0014E\u0001\u0003\u001bCa\u0001\u001e\u000b\u0005\u0002\u0005}\u0005\"CAQ)\t\u0007I1AAR\u0011!\tY\u000b\u0006Q\u0001\n\u0005\u0015\u0006\"CAW)\t\u0007I\u0011AAX\u0011\u001d\t\t\f\u0006Q\u0001\nYD\u0011\"a-\u0015\u0005\u0004%\t!a,\t\u000f\u0005UF\u0003)A\u0005m\"I\u0011q\u0017\u000bC\u0002\u0013\u0005\u0011q\u0016\u0005\b\u0003s#\u0002\u0015!\u0003w\u0011%\tY\f\u0006b\u0001\n\u0003\ty\u000bC\u0004\u0002>R\u0001\u000b\u0011\u0002<\t\u0013\u0005}FC1A\u0005\u0002\u0005=\u0006bBAa)\u0001\u0006IA\u001e\u0005\n\u0003\u0007$\"\u0019!C\u0001\u0003_Cq!!2\u0015A\u0003%a\u000fC\u0005\u0002HR\u0011\r\u0011\"\u0001\u00020\"9\u0011\u0011\u001a\u000b!\u0002\u00131\b\"CAf)\t\u0007I\u0011AAX\u0011\u001d\ti\r\u0006Q\u0001\nYD\u0011\"a4\u0015\u0005\u0004%\t!a,\t\u000f\u0005EG\u0003)A\u0005m\"I\u00111\u001b\u000bC\u0002\u0013\u0005\u0011q\u0016\u0005\b\u0003+$\u0002\u0015!\u0003w\u0011%\t9\u000e\u0006b\u0001\n\u0003\ty\u000bC\u0004\u0002ZR\u0001\u000b\u0011\u0002<\b\u000f\u0005mG\u0003#\u0001\u0002^\u001a9\u0011\u0011\u001d\u000b\t\u0002\u0005\r\bB\u0002;0\t\u0003\t)\u000fC\u0005\u0002h>\u0012\r\u0011\"\u0001\u00020\"9\u0011\u0011^\u0018!\u0002\u00131\b\"CAv_\t\u0007I\u0011AAX\u0011\u001d\tio\fQ\u0001\nYD\u0011\"a<0\u0005\u0004%\t!a,\t\u000f\u0005Ex\u0006)A\u0005m\"I\u00111_\u0018C\u0002\u0013\u0005\u0011q\u0016\u0005\b\u0003k|\u0003\u0015!\u0003w\u0011%\t9p\fb\u0001\n\u0003\ty\u000bC\u0004\u0002z>\u0002\u000b\u0011\u0002<\t\u0013\u0005mH#!A\u0005\u0002\u0006u\b\"\u0003B\u0001)\u0005\u0005I\u0011\u0011B\u0002\u0011%\u0011y\u0001FA\u0001\n\u0013\u0011\t\u0002C\u0004\u0003\u001aQ!)Aa\u0007\t\u000f\t\u0005B\u0003\"\u0002\u0003$!9!q\u0005\u000b\u0005\u0006\t%\u0002b\u0002B\u0019)\u0011\u0015!1\u0007\u0005\n\u0005o!\u0012\u0011!C\u0003\u0005sA\u0011B!\u0011\u0015#\u0003%)Aa\u0011\t\u0013\t\u001dC#!A\u0005\u0006\t%\u0003\"\u0003B\')\u0005\u0005IQ\u0001B(\u0011%\u0011\u0019\u0006FA\u0001\n\u000b\u0011)\u0006C\u0005\u0003^Q\t\t\u0011\"\u0002\u0003`!I!1\r\u000b\u0002\u0002\u0013\u0015!Q\r\u0005\n\u0005[\"\u0012\u0011!C\u0003\u0005_B\u0011Ba\u001e\u0015\u0003\u0003%)A!\u001f\t\u0013\tuD#!A\u0005\u0006\t}\u0004\"\u0003BD)\u0005\u0005IQ\u0001BE\u0005\u0011!\u0016\u0010]3\u000b\u0005=\u0003\u0016\u0001B2pe\u0016T\u0011!U\u0001\tG>,(o]5fe\u000e\u00011\u0003\u0002\u0001U5v\u0003\"!\u0016-\u000e\u0003YS\u0011aV\u0001\u0006g\u000e\fG.Y\u0005\u00033Z\u0013a!\u00118z-\u0006d\u0007CA+\\\u0013\tafKA\u0004Qe>$Wo\u0019;\u0011\u0005y3gBA0e\u001d\t\u00017-D\u0001b\u0015\t\u0011\'+\u0001\u0004=e>|GOP\u0005\u0002/&\u0011QMV\u0001\ba\u0006\u001c7.Y4f\u0013\t9\u0007N\u0001\u0007TKJL\u0017\r\\5{C\ndWM\u0003\u0002f-\u0006)a/\u00197vKV\t1\u000e\u0005\u0002ma:\u0011QN\u001c\t\u0003AZK!a\u001c,\u0002\rA\u0013X\rZ3g\u0013\t\t(O\u0001\u0004TiJLgn\u001a\u0006\u0003_Z\u000baA^1mk\u0016\u0004\u0013A\u0002\u001fj]&$h\b\u0006\u0002wqB\u0011q\u000fA\u0007\u0002\u001d\")\u0011n\u0001a\u0001W\u00069\u0011n]#naRLX#A>\u0011\u0005Uc\u0018BA?W\u0005\u001d\u0011un\u001c7fC:\f\u0001B\\8o\u000b6\u0004H/_\u0001\u0004[\u0006\u0004Hc\u0001<\u0002\u0004!9\u0011Q\u0001\u0004A\u0002\u0005\u001d\u0011!\u00014\u0011\u000bU\u000bIa[6\n\u0007\u0005-aKA\u0005Gk:\u001cG/[8oc\u0005Y\u0011m]#yi\u0016t7/[8o+\t\t\t\u0002E\u0002x\u0003\'I1!!\u0006O\u0005%)\u0005\u0010^3og&|g.\u0001\u0003d_BLHc\u0001<\u0002\u001c!9\u0011\u000e\u0003I\u0001\u0002\u0004Y\u0017AD2paf$C-\u001a4bk2$H%M\u000b\u0003\u0003CQ3a[A\u0012W\t\t)\u0003\u0005\u0003\u0002(\u0005ERBAA\u0015\u0015\u0011\tY#!\f\u0002\u0013Ut7\r[3dW\u0016$\'bAA\u0018-\u0006Q\u0011M\u001c8pi\u0006$\u0018n\u001c8\n\t\u0005M\u0012\u0011\u0006\u0002\u0012k:\u001c\u0007.Z2lK\u00124\u0016M]5b]\u000e,\u0017!\u00049s_\u0012,8\r\u001e)sK\u001aL\u00070\u0006\u0002\u0002:A!\u00111HA#\u001b\t\tiD\u0003\u0003\u0002@\u0005\u0005\u0013\u0001\u00027b]\u001eT!!a\u0011\u0002\t)\fg/Y\u0005\u0004c\u0006u\u0012\u0001\u00049s_\u0012,8\r^!sSRLXCAA&!\r)\u0016QJ\u0005\u0004\u0003\u001f2&aA%oi\u0006q\u0001O]8ek\u000e$X\t\\3nK:$H\u0003BA+\u00037\u00022!VA,\u0013\r\tIF\u0016\u0002\u0004\u0003:L\b\"CA/\u0019\u0005\u0005\t\u0019AA&\u0003\rAH%M\u0001\u0010aJ|G-^2u\u0013R,\'/\u0019;peV\u0011\u00111\r\t\u0007\u0003K\nY\'!\u0016\u000e\u0005\u0005\u001d$bAA5-\u0006Q1m\u001c7mK\u000e$\u0018n\u001c8\n\t\u00055\u0014q\r\u0002\t\u0013R,\'/\u0019;pe\u0006A1-\u00198FcV\fG\u000eF\u0002|\u0003gB\u0011\"!\u0018\u000f\u0003\u0003\u0005\r!!\u0016\u0002%A\u0014x\u000eZ;di\u0016cW-\\3oi:\u000bW.\u001a\u000b\u0005\u0003s\tI\bC\u0005\u0002^=\t\t\u00111\u0001\u0002L\u0005A\u0001.Y:i\u0007>$W\r\u0006\u0002\u0002L\u00051Q-];bYN$2a_AB\u0011%\ti&EA\u0001\u0002\u0004\t)&\u0001\u0005u_N#(/\u001b8h)\t\tI$\u0001\u0003UsB,\u0007CA<\u0015\'\u0015!\u0012qRAK!\r)\u0016\u0011S\u0005\u0004\u0003\'3&AB!osJ+g\r\u0005\u0003\u0002\u0018\u0006uUBAAM\u0015\u0011\tY*!\u0011\u0002\u0005%|\u0017bA4\u0002\u001aR\u0011\u00111R\u0001\t_J$WM]5oOV\u0011\u0011Q\u0015\t\u0005=\u0006\u001df/C\u0002\u0002*\"\u0014\u0001b\u0014:eKJLgnZ\u0001\n_J$WM]5oO\u0002\n1A[1s+\u00051\u0018\u0001\u00026be\u0002\nq\u0001^3ti*\u000b\'/\u0001\u0005uKN$(*\u0019:!\u0003\u0019\u0011WO\u001c3mK\u00069!-\u001e8eY\u0016\u0004\u0013a\u00013pG\u0006!Am\\2!\u0003\u0019\u0019x.\u001e:dK\u000691o\\;sG\u0016\u0004\u0013a\u00026bm\u0006$wnY\u0001\tU\u00064\u0018\rZ8dA\u0005Q!.\u0019<b\'>,(oY3\u0002\u0017)\fg/Y*pkJ\u001cW\rI\u0001\u0004SZL\u0018\u0001B5ws\u0002\n1\u0001]8n\u0003\u0011\u0001x.\u001c\u0011\u0002\u000b\u0015l\u0007\u000f^=\u0002\r\u0015l\u0007\u000f^=!\u0003\r\tG\u000e\\\u0001\u0005C2d\u0007%\u0001\u0004Fq>$\u0018n\u0019\t\u0004\u0003?|S\"\u0001\u000b\u0003\r\u0015Cx\u000e^5d\'\ry\u0013q\u0012\u000b\u0003\u0003;\f1\"\\1wK:\u0004F.^4j]\u0006aQ.\u0019<f]BcWoZ5oA\u0005iQm\u00197jaN,\u0007\u000b\\;hS:\fa\"Z2mSB\u001cX\r\u00157vO&t\u0007%A\u0002iWJ\nA\u0001[63A\u0005)qN\u001d2ji\u00061qN\u001d2ji\u0002\n\u0001b]2bY\u0006T\u0015M]\u0001\ng\u000e\fG.\u0019&be\u0002\nQ!\u00199qYf$2A^A\u0000\u0011\u0015I7\b1\u0001l\u0003\u001d)h.\u00199qYf$BA!\u0002\u0003\fA!QKa\u0002l\u0013\r\u0011IA\u0016\u0002\u0007\u001fB$\u0018n\u001c8\t\u0011\t5A(!AA\u0002Y\f1\u0001\u001f\u00131\u000319(/\u001b;f%\u0016\u0004H.Y2f)\t\u0011\u0019\u0002\u0005\u0003\u0002<\tU\u0011\u0002\u0002B\f\u0003{\u0011aa\u00142kK\u000e$\u0018!E5t\u000b6\u0004H/\u001f\u0013fqR,gn]5p]R\u00191P!\b\t\r\t}a\b1\u0001w\u0003\u0015!C\u000f[5t\u0003IqwN\\#naRLH%\u001a=uK:\u001c\u0018n\u001c8\u0015\u0007m\u0014)\u0003\u0003\u0004\u0003 }\u0002\rA^\u0001\u000e[\u0006\u0004H%\u001a=uK:\u001c\u0018n\u001c8\u0015\t\t-\"q\u0006\u000b\u0004m\n5\u0002bBA\u0003\u0001\u0002\u0007\u0011q\u0001\u0005\u0007\u0005?\u0001\u0005\u0019\u0001<\u0002+\u0005\u001cX\t\u001f;f]NLwN\u001c\u0013fqR,gn]5p]R!\u0011\u0011\u0003B\u001b\u0011\u0019\u0011y\"\u0011a\u0001m\u0006q1m\u001c9zI\u0015DH/\u001a8tS>tG\u0003\u0002B\u001e\u0005\u007f!2A\u001eB\u001f\u0011\u001dI\'\t%AA\u0002-DaAa\bC\u0001\u00041\u0018\u0001G2paf$C-\u001a4bk2$H%\r\u0013fqR,gn]5p]R!\u0011\u0011\u0005B#\u0011\u0019\u0011yb\u0011a\u0001m\u00069\u0002O]8ek\u000e$\bK]3gSb$S\r\u001f;f]NLwN\u001c\u000b\u0005\u0003s\u0011Y\u0005\u0003\u0004\u0003 \u0011\u0003\rA^\u0001\u0017aJ|G-^2u\u0003JLG/\u001f\u0013fqR,gn]5p]R!\u00111\nB)\u0011\u0019\u0011y\"\u0012a\u0001m\u0006A\u0002O]8ek\u000e$X\t\\3nK:$H%\u001a=uK:\u001c\u0018n\u001c8\u0015\t\t]#1\f\u000b\u0005\u0003+\u0012I\u0006C\u0005\u0002^\u0019\u000b\t\u00111\u0001\u0002L!1!q\u0004$A\u0002Y\f\u0011\u0004\u001d:pIV\u001cG/\u0013;fe\u0006$xN\u001d\u0013fqR,gn]5p]R!\u00111\rB1\u0011\u0019\u0011yb\u0012a\u0001m\u0006\u00112-\u00198FcV\fG\u000eJ3yi\u0016t7/[8o)\u0011\u00119Ga\u001b\u0015\u0007m\u0014I\u0007C\u0005\u0002^!\u000b\t\u00111\u0001\u0002V!1!q\u0004%A\u0002Y\fA\u0004\u001d:pIV\u001cG/\u00127f[\u0016tGOT1nK\u0012*\u0007\u0010^3og&|g\u000e\u0006\u0003\u0003r\tUD\u0003BA\u001d\u0005gB\u0011\"!\u0018J\u0003\u0003\u0005\r!a\u0013\t\r\t}\u0011\n1\u0001w\u0003IA\u0017m\u001d5D_\u0012,G%\u001a=uK:\u001c\u0018n\u001c8\u0015\t\u0005u$1\u0010\u0005\u0007\u0005?Q\u0005\u0019\u0001<\u0002!\u0015\fX/\u00197tI\u0015DH/\u001a8tS>tG\u0003\u0002BA\u0005\u000b#2a\u001fBB\u0011%\tifSA\u0001\u0002\u0004\t)\u0006\u0003\u0004\u0003 -\u0003\rA^\u0001\u0013i>\u001cFO]5oO\u0012*\u0007\u0010^3og&|g\u000e\u0006\u0003\u0002\b\n-\u0005B\u0002B\u0010\u0019\u0002\u0007a\u000f"
    )
  ScalaInlineInfo: length = 0x5E (unknown attribute)
   01 01 00 12 00 A9 00 AA 01 00 96 00 5C 01 00 A1
   00 A2 01 00 97 00 13 01 00 98 00 5C 01 00 A7 00
   A2 01 00 A6 00 9B 01 00 8D 00 8E 01 00 92 00 93
   01 00 91 00 8E 01 00 9A 00 9B 01 00 9C 00 9D 01
   00 A4 00 A5 01 00 82 00 83 01 00 9F 00 83 01 00
   99 00 5C 01 00 A8 00 5C 01 00 10 00 5C 01
  ScalaSig: length = 0x3 (unknown attribute)
   05 02 00
