Classfile /Users/mw/Projects/slang-braindump/.jar/jar11/assemble/slang-braindump/assemble/content/org/sireum/conversions/B$.class
  Last modified May 29, 2022; size 2995 bytes
  SHA-256 checksum d85df97607d515a0156890d8f7fd0d7074b17fcb5606e53e15adcfbe6f2479e8
  Compiled from "conversions.scala"
public final class org.sireum.conversions.B$
  minor version: 0
  major version: 52
  flags: (0x0031) ACC_PUBLIC, ACC_FINAL, ACC_SUPER
  this_class: #2                          // org/sireum/conversions/B$
  super_class: #4                         // java/lang/Object
  interfaces: 0, fields: 1, methods: 24, attributes: 3
Constant pool:
    #1 = Utf8               org/sireum/conversions/B$
    #2 = Class              #1            // org/sireum/conversions/B$
    #3 = Utf8               java/lang/Object
    #4 = Class              #3            // java/lang/Object
    #5 = Utf8               conversions.scala
    #6 = Utf8               MODULE$
    #7 = Utf8               Lorg/sireum/conversions/B$;
    #8 = Utf8               <clinit>
    #9 = Utf8               ()V
   #10 = Utf8               <init>
   #11 = NameAndType        #10:#9        // "<init>":()V
   #12 = Methodref          #2.#11        // org/sireum/conversions/B$."<init>":()V
   #13 = NameAndType        #6:#7         // MODULE$:Lorg/sireum/conversions/B$;
   #14 = Fieldref           #2.#13        // org/sireum/conversions/B$.MODULE$:Lorg/sireum/conversions/B$;
   #15 = Utf8               toB
   #16 = Utf8               (Z)Z
   #17 = Utf8               b
   #18 = Utf8               org/sireum/conversions/B_Ext$
   #19 = Class              #18           // org/sireum/conversions/B_Ext$
   #20 = Utf8               Lorg/sireum/conversions/B_Ext$;
   #21 = NameAndType        #6:#20        // MODULE$:Lorg/sireum/conversions/B_Ext$;
   #22 = Fieldref           #19.#21       // org/sireum/conversions/B_Ext$.MODULE$:Lorg/sireum/conversions/B_Ext$;
   #23 = NameAndType        #15:#16       // toB:(Z)Z
   #24 = Methodref          #19.#23       // org/sireum/conversions/B_Ext$.toB:(Z)Z
   #25 = Utf8               this
   #26 = Utf8               Z
   #27 = Utf8               toZ
   #28 = Utf8               (Z)Lorg/sireum/Z;
   #29 = NameAndType        #27:#28       // toZ:(Z)Lorg/sireum/Z;
   #30 = Methodref          #19.#29       // org/sireum/conversions/B_Ext$.toZ:(Z)Lorg/sireum/Z;
   #31 = Utf8               toZ8
   #32 = NameAndType        #31:#28       // toZ8:(Z)Lorg/sireum/Z;
   #33 = Methodref          #19.#32       // org/sireum/conversions/B_Ext$.toZ8:(Z)Lorg/sireum/Z;
   #34 = Utf8               toZ16
   #35 = NameAndType        #34:#28       // toZ16:(Z)Lorg/sireum/Z;
   #36 = Methodref          #19.#35       // org/sireum/conversions/B_Ext$.toZ16:(Z)Lorg/sireum/Z;
   #37 = Utf8               toZ32
   #38 = NameAndType        #37:#28       // toZ32:(Z)Lorg/sireum/Z;
   #39 = Methodref          #19.#38       // org/sireum/conversions/B_Ext$.toZ32:(Z)Lorg/sireum/Z;
   #40 = Utf8               toZ64
   #41 = NameAndType        #40:#28       // toZ64:(Z)Lorg/sireum/Z;
   #42 = Methodref          #19.#41       // org/sireum/conversions/B_Ext$.toZ64:(Z)Lorg/sireum/Z;
   #43 = Utf8               toN
   #44 = NameAndType        #43:#28       // toN:(Z)Lorg/sireum/Z;
   #45 = Methodref          #19.#44       // org/sireum/conversions/B_Ext$.toN:(Z)Lorg/sireum/Z;
   #46 = Utf8               toN8
   #47 = NameAndType        #46:#28       // toN8:(Z)Lorg/sireum/Z;
   #48 = Methodref          #19.#47       // org/sireum/conversions/B_Ext$.toN8:(Z)Lorg/sireum/Z;
   #49 = Utf8               toN16
   #50 = NameAndType        #49:#28       // toN16:(Z)Lorg/sireum/Z;
   #51 = Methodref          #19.#50       // org/sireum/conversions/B_Ext$.toN16:(Z)Lorg/sireum/Z;
   #52 = Utf8               toN32
   #53 = NameAndType        #52:#28       // toN32:(Z)Lorg/sireum/Z;
   #54 = Methodref          #19.#53       // org/sireum/conversions/B_Ext$.toN32:(Z)Lorg/sireum/Z;
   #55 = Utf8               toN64
   #56 = NameAndType        #55:#28       // toN64:(Z)Lorg/sireum/Z;
   #57 = Methodref          #19.#56       // org/sireum/conversions/B_Ext$.toN64:(Z)Lorg/sireum/Z;
   #58 = Utf8               toS8
   #59 = Utf8               (Z)B
   #60 = NameAndType        #58:#59       // toS8:(Z)B
   #61 = Methodref          #19.#60       // org/sireum/conversions/B_Ext$.toS8:(Z)B
   #62 = Utf8               toS16
   #63 = Utf8               (Z)S
   #64 = NameAndType        #62:#63       // toS16:(Z)S
   #65 = Methodref          #19.#64       // org/sireum/conversions/B_Ext$.toS16:(Z)S
   #66 = Utf8               toS32
   #67 = Utf8               (Z)I
   #68 = NameAndType        #66:#67       // toS32:(Z)I
   #69 = Methodref          #19.#68       // org/sireum/conversions/B_Ext$.toS32:(Z)I
   #70 = Utf8               toS64
   #71 = Utf8               (Z)J
   #72 = NameAndType        #70:#71       // toS64:(Z)J
   #73 = Methodref          #19.#72       // org/sireum/conversions/B_Ext$.toS64:(Z)J
   #74 = Utf8               toU8
   #75 = NameAndType        #74:#59       // toU8:(Z)B
   #76 = Methodref          #19.#75       // org/sireum/conversions/B_Ext$.toU8:(Z)B
   #77 = Utf8               toU16
   #78 = NameAndType        #77:#63       // toU16:(Z)S
   #79 = Methodref          #19.#78       // org/sireum/conversions/B_Ext$.toU16:(Z)S
   #80 = Utf8               toU32
   #81 = NameAndType        #80:#67       // toU32:(Z)I
   #82 = Methodref          #19.#81       // org/sireum/conversions/B_Ext$.toU32:(Z)I
   #83 = Utf8               toU64
   #84 = NameAndType        #83:#71       // toU64:(Z)J
   #85 = Methodref          #19.#84       // org/sireum/conversions/B_Ext$.toU64:(Z)J
   #86 = Utf8               toF32
   #87 = Utf8               (Z)F
   #88 = NameAndType        #86:#87       // toF32:(Z)F
   #89 = Methodref          #19.#88       // org/sireum/conversions/B_Ext$.toF32:(Z)F
   #90 = Utf8               toF64
   #91 = Utf8               (Z)D
   #92 = NameAndType        #90:#91       // toF64:(Z)D
   #93 = Methodref          #19.#92       // org/sireum/conversions/B_Ext$.toF64:(Z)D
   #94 = Utf8               toR
   #95 = Utf8               (Z)Lscala/math/BigDecimal;
   #96 = NameAndType        #94:#95       // toR:(Z)Lscala/math/BigDecimal;
   #97 = Methodref          #19.#96       // org/sireum/conversions/B_Ext$.toR:(Z)Lscala/math/BigDecimal;
   #98 = Methodref          #4.#11        // java/lang/Object."<init>":()V
   #99 = Utf8               Code
  #100 = Utf8               LineNumberTable
  #101 = Utf8               LocalVariableTable
  #102 = Utf8               MethodParameters
  #103 = Utf8               SourceFile
  #104 = Utf8               ScalaInlineInfo
  #105 = Utf8               Scala
{
  public static final org.sireum.conversions.B$ MODULE$;
    descriptor: Lorg/sireum/conversions/B$;
    flags: (0x0019) ACC_PUBLIC, ACC_STATIC, ACC_FINAL

  public static {};
    descriptor: ()V
    flags: (0x0009) ACC_PUBLIC, ACC_STATIC
    Code:
      stack=2, locals=0, args_size=0
         0: new           #2                  // class org/sireum/conversions/B$
         3: dup
         4: invokespecial #12                 // Method "<init>":()V
         7: putstatic     #14                 // Field MODULE$:Lorg/sireum/conversions/B$;
        10: return
      LineNumberTable:
        line 35: 0

  public boolean toB(boolean);
    descriptor: (Z)Z
    flags: (0x0001) ACC_PUBLIC
    Code:
      stack=2, locals=2, args_size=2
         0: getstatic     #22                 // Field org/sireum/conversions/B_Ext$.MODULE$:Lorg/sireum/conversions/B_Ext$;
         3: iload_1
         4: invokevirtual #24                 // Method org/sireum/conversions/B_Ext$.toB:(Z)Z
         7: ireturn
      LineNumberTable:
        line 37: 0
      LocalVariableTable:
        Start  Length  Slot  Name   Signature
            0       8     0  this   Lorg/sireum/conversions/B$;
            0       8     1     b   Z
    MethodParameters:
      Name                           Flags
      b                              final

  public org.sireum.Z toZ(boolean);
    descriptor: (Z)Lorg/sireum/Z;
    flags: (0x0001) ACC_PUBLIC
    Code:
      stack=2, locals=2, args_size=2
         0: getstatic     #22                 // Field org/sireum/conversions/B_Ext$.MODULE$:Lorg/sireum/conversions/B_Ext$;
         3: iload_1
         4: invokevirtual #30                 // Method org/sireum/conversions/B_Ext$.toZ:(Z)Lorg/sireum/Z;
         7: areturn
      LineNumberTable:
        line 39: 0
      LocalVariableTable:
        Start  Length  Slot  Name   Signature
            0       8     0  this   Lorg/sireum/conversions/B$;
            0       8     1     b   Z
    MethodParameters:
      Name                           Flags
      b                              final

  public org.sireum.Z toZ8(boolean);
    descriptor: (Z)Lorg/sireum/Z;
    flags: (0x0001) ACC_PUBLIC
    Code:
      stack=2, locals=2, args_size=2
         0: getstatic     #22                 // Field org/sireum/conversions/B_Ext$.MODULE$:Lorg/sireum/conversions/B_Ext$;
         3: iload_1
         4: invokevirtual #33                 // Method org/sireum/conversions/B_Ext$.toZ8:(Z)Lorg/sireum/Z;
         7: areturn
      LineNumberTable:
        line 41: 0
      LocalVariableTable:
        Start  Length  Slot  Name   Signature
            0       8     0  this   Lorg/sireum/conversions/B$;
            0       8     1     b   Z
    MethodParameters:
      Name                           Flags
      b                              final

  public org.sireum.Z toZ16(boolean);
    descriptor: (Z)Lorg/sireum/Z;
    flags: (0x0001) ACC_PUBLIC
    Code:
      stack=2, locals=2, args_size=2
         0: getstatic     #22                 // Field org/sireum/conversions/B_Ext$.MODULE$:Lorg/sireum/conversions/B_Ext$;
         3: iload_1
         4: invokevirtual #36                 // Method org/sireum/conversions/B_Ext$.toZ16:(Z)Lorg/sireum/Z;
         7: areturn
      LineNumberTable:
        line 43: 0
      LocalVariableTable:
        Start  Length  Slot  Name   Signature
            0       8     0  this   Lorg/sireum/conversions/B$;
            0       8     1     b   Z
    MethodParameters:
      Name                           Flags
      b                              final

  public org.sireum.Z toZ32(boolean);
    descriptor: (Z)Lorg/sireum/Z;
    flags: (0x0001) ACC_PUBLIC
    Code:
      stack=2, locals=2, args_size=2
         0: getstatic     #22                 // Field org/sireum/conversions/B_Ext$.MODULE$:Lorg/sireum/conversions/B_Ext$;
         3: iload_1
         4: invokevirtual #39                 // Method org/sireum/conversions/B_Ext$.toZ32:(Z)Lorg/sireum/Z;
         7: areturn
      LineNumberTable:
        line 45: 0
      LocalVariableTable:
        Start  Length  Slot  Name   Signature
            0       8     0  this   Lorg/sireum/conversions/B$;
            0       8     1     b   Z
    MethodParameters:
      Name                           Flags
      b                              final

  public org.sireum.Z toZ64(boolean);
    descriptor: (Z)Lorg/sireum/Z;
    flags: (0x0001) ACC_PUBLIC
    Code:
      stack=2, locals=2, args_size=2
         0: getstatic     #22                 // Field org/sireum/conversions/B_Ext$.MODULE$:Lorg/sireum/conversions/B_Ext$;
         3: iload_1
         4: invokevirtual #42                 // Method org/sireum/conversions/B_Ext$.toZ64:(Z)Lorg/sireum/Z;
         7: areturn
      LineNumberTable:
        line 47: 0
      LocalVariableTable:
        Start  Length  Slot  Name   Signature
            0       8     0  this   Lorg/sireum/conversions/B$;
            0       8     1     b   Z
    MethodParameters:
      Name                           Flags
      b                              final

  public org.sireum.Z toN(boolean);
    descriptor: (Z)Lorg/sireum/Z;
    flags: (0x0001) ACC_PUBLIC
    Code:
      stack=2, locals=2, args_size=2
         0: getstatic     #22                 // Field org/sireum/conversions/B_Ext$.MODULE$:Lorg/sireum/conversions/B_Ext$;
         3: iload_1
         4: invokevirtual #45                 // Method org/sireum/conversions/B_Ext$.toN:(Z)Lorg/sireum/Z;
         7: areturn
      LineNumberTable:
        line 49: 0
      LocalVariableTable:
        Start  Length  Slot  Name   Signature
            0       8     0  this   Lorg/sireum/conversions/B$;
            0       8     1     b   Z
    MethodParameters:
      Name                           Flags
      b                              final

  public org.sireum.Z toN8(boolean);
    descriptor: (Z)Lorg/sireum/Z;
    flags: (0x0001) ACC_PUBLIC
    Code:
      stack=2, locals=2, args_size=2
         0: getstatic     #22                 // Field org/sireum/conversions/B_Ext$.MODULE$:Lorg/sireum/conversions/B_Ext$;
         3: iload_1
         4: invokevirtual #48                 // Method org/sireum/conversions/B_Ext$.toN8:(Z)Lorg/sireum/Z;
         7: areturn
      LineNumberTable:
        line 52: 0
      LocalVariableTable:
        Start  Length  Slot  Name   Signature
            0       8     0  this   Lorg/sireum/conversions/B$;
            0       8     1     b   Z
    MethodParameters:
      Name                           Flags
      b                              final

  public org.sireum.Z toN16(boolean);
    descriptor: (Z)Lorg/sireum/Z;
    flags: (0x0001) ACC_PUBLIC
    Code:
      stack=2, locals=2, args_size=2
         0: getstatic     #22                 // Field org/sireum/conversions/B_Ext$.MODULE$:Lorg/sireum/conversions/B_Ext$;
         3: iload_1
         4: invokevirtual #51                 // Method org/sireum/conversions/B_Ext$.toN16:(Z)Lorg/sireum/Z;
         7: areturn
      LineNumberTable:
        line 55: 0
      LocalVariableTable:
        Start  Length  Slot  Name   Signature
            0       8     0  this   Lorg/sireum/conversions/B$;
            0       8     1     b   Z
    MethodParameters:
      Name                           Flags
      b                              final

  public org.sireum.Z toN32(boolean);
    descriptor: (Z)Lorg/sireum/Z;
    flags: (0x0001) ACC_PUBLIC
    Code:
      stack=2, locals=2, args_size=2
         0: getstatic     #22                 // Field org/sireum/conversions/B_Ext$.MODULE$:Lorg/sireum/conversions/B_Ext$;
         3: iload_1
         4: invokevirtual #54                 // Method org/sireum/conversions/B_Ext$.toN32:(Z)Lorg/sireum/Z;
         7: areturn
      LineNumberTable:
        line 58: 0
      LocalVariableTable:
        Start  Length  Slot  Name   Signature
            0       8     0  this   Lorg/sireum/conversions/B$;
            0       8     1     b   Z
    MethodParameters:
      Name                           Flags
      b                              final

  public org.sireum.Z toN64(boolean);
    descriptor: (Z)Lorg/sireum/Z;
    flags: (0x0001) ACC_PUBLIC
    Code:
      stack=2, locals=2, args_size=2
         0: getstatic     #22                 // Field org/sireum/conversions/B_Ext$.MODULE$:Lorg/sireum/conversions/B_Ext$;
         3: iload_1
         4: invokevirtual #57                 // Method org/sireum/conversions/B_Ext$.toN64:(Z)Lorg/sireum/Z;
         7: areturn
      LineNumberTable:
        line 61: 0
      LocalVariableTable:
        Start  Length  Slot  Name   Signature
            0       8     0  this   Lorg/sireum/conversions/B$;
            0       8     1     b   Z
    MethodParameters:
      Name                           Flags
      b                              final

  public byte toS8(boolean);
    descriptor: (Z)B
    flags: (0x0001) ACC_PUBLIC
    Code:
      stack=2, locals=2, args_size=2
         0: getstatic     #22                 // Field org/sireum/conversions/B_Ext$.MODULE$:Lorg/sireum/conversions/B_Ext$;
         3: iload_1
         4: invokevirtual #61                 // Method org/sireum/conversions/B_Ext$.toS8:(Z)B
         7: ireturn
      LineNumberTable:
        line 64: 0
      LocalVariableTable:
        Start  Length  Slot  Name   Signature
            0       8     0  this   Lorg/sireum/conversions/B$;
            0       8     1     b   Z
    MethodParameters:
      Name                           Flags
      b                              final

  public short toS16(boolean);
    descriptor: (Z)S
    flags: (0x0001) ACC_PUBLIC
    Code:
      stack=2, locals=2, args_size=2
         0: getstatic     #22                 // Field org/sireum/conversions/B_Ext$.MODULE$:Lorg/sireum/conversions/B_Ext$;
         3: iload_1
         4: invokevirtual #65                 // Method org/sireum/conversions/B_Ext$.toS16:(Z)S
         7: ireturn
      LineNumberTable:
        line 67: 0
      LocalVariableTable:
        Start  Length  Slot  Name   Signature
            0       8     0  this   Lorg/sireum/conversions/B$;
            0       8     1     b   Z
    MethodParameters:
      Name                           Flags
      b                              final

  public int toS32(boolean);
    descriptor: (Z)I
    flags: (0x0001) ACC_PUBLIC
    Code:
      stack=2, locals=2, args_size=2
         0: getstatic     #22                 // Field org/sireum/conversions/B_Ext$.MODULE$:Lorg/sireum/conversions/B_Ext$;
         3: iload_1
         4: invokevirtual #69                 // Method org/sireum/conversions/B_Ext$.toS32:(Z)I
         7: ireturn
      LineNumberTable:
        line 70: 0
      LocalVariableTable:
        Start  Length  Slot  Name   Signature
            0       8     0  this   Lorg/sireum/conversions/B$;
            0       8     1     b   Z
    MethodParameters:
      Name                           Flags
      b                              final

  public long toS64(boolean);
    descriptor: (Z)J
    flags: (0x0001) ACC_PUBLIC
    Code:
      stack=2, locals=2, args_size=2
         0: getstatic     #22                 // Field org/sireum/conversions/B_Ext$.MODULE$:Lorg/sireum/conversions/B_Ext$;
         3: iload_1
         4: invokevirtual #73                 // Method org/sireum/conversions/B_Ext$.toS64:(Z)J
         7: lreturn
      LineNumberTable:
        line 73: 0
      LocalVariableTable:
        Start  Length  Slot  Name   Signature
            0       8     0  this   Lorg/sireum/conversions/B$;
            0       8     1     b   Z
    MethodParameters:
      Name                           Flags
      b                              final

  public byte toU8(boolean);
    descriptor: (Z)B
    flags: (0x0001) ACC_PUBLIC
    Code:
      stack=2, locals=2, args_size=2
         0: getstatic     #22                 // Field org/sireum/conversions/B_Ext$.MODULE$:Lorg/sireum/conversions/B_Ext$;
         3: iload_1
         4: invokevirtual #76                 // Method org/sireum/conversions/B_Ext$.toU8:(Z)B
         7: ireturn
      LineNumberTable:
        line 76: 0
      LocalVariableTable:
        Start  Length  Slot  Name   Signature
            0       8     0  this   Lorg/sireum/conversions/B$;
            0       8     1     b   Z
    MethodParameters:
      Name                           Flags
      b                              final

  public short toU16(boolean);
    descriptor: (Z)S
    flags: (0x0001) ACC_PUBLIC
    Code:
      stack=2, locals=2, args_size=2
         0: getstatic     #22                 // Field org/sireum/conversions/B_Ext$.MODULE$:Lorg/sireum/conversions/B_Ext$;
         3: iload_1
         4: invokevirtual #79                 // Method org/sireum/conversions/B_Ext$.toU16:(Z)S
         7: ireturn
      LineNumberTable:
        line 79: 0
      LocalVariableTable:
        Start  Length  Slot  Name   Signature
            0       8     0  this   Lorg/sireum/conversions/B$;
            0       8     1     b   Z
    MethodParameters:
      Name                           Flags
      b                              final

  public int toU32(boolean);
    descriptor: (Z)I
    flags: (0x0001) ACC_PUBLIC
    Code:
      stack=2, locals=2, args_size=2
         0: getstatic     #22                 // Field org/sireum/conversions/B_Ext$.MODULE$:Lorg/sireum/conversions/B_Ext$;
         3: iload_1
         4: invokevirtual #82                 // Method org/sireum/conversions/B_Ext$.toU32:(Z)I
         7: ireturn
      LineNumberTable:
        line 82: 0
      LocalVariableTable:
        Start  Length  Slot  Name   Signature
            0       8     0  this   Lorg/sireum/conversions/B$;
            0       8     1     b   Z
    MethodParameters:
      Name                           Flags
      b                              final

  public long toU64(boolean);
    descriptor: (Z)J
    flags: (0x0001) ACC_PUBLIC
    Code:
      stack=2, locals=2, args_size=2
         0: getstatic     #22                 // Field org/sireum/conversions/B_Ext$.MODULE$:Lorg/sireum/conversions/B_Ext$;
         3: iload_1
         4: invokevirtual #85                 // Method org/sireum/conversions/B_Ext$.toU64:(Z)J
         7: lreturn
      LineNumberTable:
        line 85: 0
      LocalVariableTable:
        Start  Length  Slot  Name   Signature
            0       8     0  this   Lorg/sireum/conversions/B$;
            0       8     1     b   Z
    MethodParameters:
      Name                           Flags
      b                              final

  public float toF32(boolean);
    descriptor: (Z)F
    flags: (0x0001) ACC_PUBLIC
    Code:
      stack=2, locals=2, args_size=2
         0: getstatic     #22                 // Field org/sireum/conversions/B_Ext$.MODULE$:Lorg/sireum/conversions/B_Ext$;
         3: iload_1
         4: invokevirtual #89                 // Method org/sireum/conversions/B_Ext$.toF32:(Z)F
         7: freturn
      LineNumberTable:
        line 88: 0
      LocalVariableTable:
        Start  Length  Slot  Name   Signature
            0       8     0  this   Lorg/sireum/conversions/B$;
            0       8     1     b   Z
    MethodParameters:
      Name                           Flags
      b                              final

  public double toF64(boolean);
    descriptor: (Z)D
    flags: (0x0001) ACC_PUBLIC
    Code:
      stack=2, locals=2, args_size=2
         0: getstatic     #22                 // Field org/sireum/conversions/B_Ext$.MODULE$:Lorg/sireum/conversions/B_Ext$;
         3: iload_1
         4: invokevirtual #93                 // Method org/sireum/conversions/B_Ext$.toF64:(Z)D
         7: dreturn
      LineNumberTable:
        line 91: 0
      LocalVariableTable:
        Start  Length  Slot  Name   Signature
            0       8     0  this   Lorg/sireum/conversions/B$;
            0       8     1     b   Z
    MethodParameters:
      Name                           Flags
      b                              final

  public scala.math.BigDecimal toR(boolean);
    descriptor: (Z)Lscala/math/BigDecimal;
    flags: (0x0001) ACC_PUBLIC
    Code:
      stack=2, locals=2, args_size=2
         0: getstatic     #22                 // Field org/sireum/conversions/B_Ext$.MODULE$:Lorg/sireum/conversions/B_Ext$;
         3: iload_1
         4: invokevirtual #97                 // Method org/sireum/conversions/B_Ext$.toR:(Z)Lscala/math/BigDecimal;
         7: areturn
      LineNumberTable:
        line 94: 0
      LocalVariableTable:
        Start  Length  Slot  Name   Signature
            0       8     0  this   Lorg/sireum/conversions/B$;
            0       8     1     b   Z
    MethodParameters:
      Name                           Flags
      b                              final

  private org.sireum.conversions.B$();
    descriptor: ()V
    flags: (0x0002) ACC_PRIVATE
    Code:
      stack=1, locals=1, args_size=1
         0: aload_0
         1: invokespecial #98                 // Method java/lang/Object."<init>":()V
         4: return
      LineNumberTable:
        line 35: 0
      LocalVariableTable:
        Start  Length  Slot  Name   Signature
            0       5     0  this   Lorg/sireum/conversions/B$;
}
SourceFile: "conversions.scala"
  ScalaInlineInfo: length = 0x77 (unknown attribute)
   01 01 00 17 00 0A 00 09 01 00 0F 00 10 01 00 56
   00 57 01 00 5A 00 5B 01 00 2B 00 1C 01 00 31 00
   1C 01 00 34 00 1C 01 00 37 00 1C 01 00 2E 00 1C
   01 00 5E 00 5F 01 00 3E 00 3F 01 00 42 00 43 01
   00 46 00 47 01 00 3A 00 3B 01 00 4D 00 3F 01 00
   50 00 43 01 00 53 00 47 01 00 4A 00 3B 01 00 1B
   00 1C 01 00 22 00 1C 01 00 25 00 1C 01 00 28 00
   1C 01 00 1F 00 1C 01
  Scala: length = 0x0 (unknown attribute)

