Classfile /Users/mw/Projects/slang-braindump/.jar/jar11/assemble/slang-braindump/assemble/content/org/sireum/conversions/ISB_Ext$.class
  Last modified May 29, 2022; size 2581 bytes
  SHA-256 checksum ecf520bafd671ad7b87e4b902f932f306ce47d10fe6b27365f1e6d04a2709dfc
  Compiled from "extension.scala"
public final class org.sireum.conversions.ISB_Ext$
  minor version: 0
  major version: 52
  flags: (0x0031) ACC_PUBLIC, ACC_FINAL, ACC_SUPER
  this_class: #2                          // org/sireum/conversions/ISB_Ext$
  super_class: #4                         // java/lang/Object
  interfaces: 0, fields: 1, methods: 5, attributes: 4
Constant pool:
    #1 = Utf8               org/sireum/conversions/ISB_Ext$
    #2 = Class              #1            // org/sireum/conversions/ISB_Ext$
    #3 = Utf8               java/lang/Object
    #4 = Class              #3            // java/lang/Object
    #5 = Utf8               extension.scala
    #6 = Utf8               org/sireum/B$Boxer$
    #7 = Class              #6            // org/sireum/B$Boxer$
    #8 = Utf8               org/sireum/B
    #9 = Class              #8            // org/sireum/B
   #10 = Utf8               Boxer$
   #11 = Utf8               org/sireum/U8$Boxer$
   #12 = Class              #11           // org/sireum/U8$Boxer$
   #13 = Utf8               org/sireum/U8
   #14 = Class              #13           // org/sireum/U8
   #15 = Utf8               MODULE$
   #16 = Utf8               Lorg/sireum/conversions/ISB_Ext$;
   #17 = Utf8               <clinit>
   #18 = Utf8               ()V
   #19 = Utf8               <init>
   #20 = NameAndType        #19:#18       // "<init>":()V
   #21 = Methodref          #2.#20        // org/sireum/conversions/ISB_Ext$."<init>":()V
   #22 = NameAndType        #15:#16       // MODULE$:Lorg/sireum/conversions/ISB_Ext$;
   #23 = Fieldref           #2.#22        // org/sireum/conversions/ISB_Ext$.MODULE$:Lorg/sireum/conversions/ISB_Ext$;
   #24 = Utf8               fromISU8
   #25 = Utf8               (Lorg/sireum/IS;)Lorg/sireum/IS;
   #26 = Utf8               <I:Ljava/lang/Object;>(Lorg/sireum/IS<TI;Lorg/sireum/U8;>;)Lorg/sireum/IS<TI;Lorg/sireum/B;>;
   #27 = Utf8               s
   #28 = Utf8               org/sireum/IS
   #29 = Class              #28           // org/sireum/IS
   #30 = Utf8               companion
   #31 = Utf8               ()Lorg/sireum/$ZCompanion;
   #32 = NameAndType        #30:#31       // companion:()Lorg/sireum/$ZCompanion;
   #33 = Methodref          #29.#32       // org/sireum/IS.companion:()Lorg/sireum/$ZCompanion;
   #34 = Utf8               data
   #35 = Utf8               ()Ljava/lang/Object;
   #36 = NameAndType        #34:#35       // data:()Ljava/lang/Object;
   #37 = Methodref          #29.#36       // org/sireum/IS.data:()Ljava/lang/Object;
   #38 = Utf8               [B
   #39 = Class              #38           // "[B"
   #40 = Utf8               clone
   #41 = NameAndType        #40:#35       // clone:()Ljava/lang/Object;
   #42 = Methodref          #39.#41       // "[B".clone:()Ljava/lang/Object;
   #43 = Utf8               length
   #44 = Utf8               ()Lorg/sireum/Z;
   #45 = NameAndType        #43:#44       // length:()Lorg/sireum/Z;
   #46 = Methodref          #29.#45       // org/sireum/IS.length:()Lorg/sireum/Z;
   #47 = Utf8               org/sireum/Z$
   #48 = Class              #47           // org/sireum/Z$
   #49 = Utf8               Lorg/sireum/Z$;
   #50 = NameAndType        #15:#49       // MODULE$:Lorg/sireum/Z$;
   #51 = Fieldref           #48.#50       // org/sireum/Z$.MODULE$:Lorg/sireum/Z$;
   #52 = Utf8               apply
   #53 = Utf8               (I)Lorg/sireum/Z;
   #54 = NameAndType        #52:#53       // apply:(I)Lorg/sireum/Z;
   #55 = Methodref          #48.#54       // org/sireum/Z$.apply:(I)Lorg/sireum/Z;
   #56 = Utf8               org/sireum/Z
   #57 = Class              #56           // org/sireum/Z
   #58 = Utf8               $times
   #59 = Utf8               (Lorg/sireum/Z;)Lorg/sireum/Z;
   #60 = NameAndType        #58:#59       // $times:(Lorg/sireum/Z;)Lorg/sireum/Z;
   #61 = InterfaceMethodref #57.#60       // org/sireum/Z.$times:(Lorg/sireum/Z;)Lorg/sireum/Z;
   #62 = Utf8               Lorg/sireum/B$Boxer$;
   #63 = NameAndType        #15:#62       // MODULE$:Lorg/sireum/B$Boxer$;
   #64 = Fieldref           #7.#63        // org/sireum/B$Boxer$.MODULE$:Lorg/sireum/B$Boxer$;
   #65 = Utf8               (Lorg/sireum/$ZCompanion;Ljava/lang/Object;Lorg/sireum/Z;Lorg/sireum/$internal/Boxer;)V
   #66 = NameAndType        #19:#65       // "<init>":(Lorg/sireum/$ZCompanion;Ljava/lang/Object;Lorg/sireum/Z;Lorg/sireum/$internal/Boxer;)V
   #67 = Methodref          #29.#66       // org/sireum/IS."<init>":(Lorg/sireum/$ZCompanion;Ljava/lang/Object;Lorg/sireum/Z;Lorg/sireum/$internal/Boxer;)V
   #68 = Utf8               this
   #69 = Utf8               Lorg/sireum/IS;
   #70 = Utf8               toISU8
   #71 = Utf8               <I:Ljava/lang/Object;>(Lorg/sireum/IS<TI;Lorg/sireum/B;>;)Lorg/sireum/IS<TI;Lorg/sireum/U8;>;
   #72 = Utf8               $div
   #73 = NameAndType        #72:#59       // $div:(Lorg/sireum/Z;)Lorg/sireum/Z;
   #74 = InterfaceMethodref #57.#73       // org/sireum/Z.$div:(Lorg/sireum/Z;)Lorg/sireum/Z;
   #75 = Utf8               $percent
   #76 = NameAndType        #75:#59       // $percent:(Lorg/sireum/Z;)Lorg/sireum/Z;
   #77 = InterfaceMethodref #57.#76       // org/sireum/Z.$percent:(Lorg/sireum/Z;)Lorg/sireum/Z;
   #78 = Utf8               scala/runtime/BoxesRunTime
   #79 = Class              #78           // scala/runtime/BoxesRunTime
   #80 = Utf8               boxToInteger
   #81 = Utf8               (I)Ljava/lang/Integer;
   #82 = NameAndType        #80:#81       // boxToInteger:(I)Ljava/lang/Integer;
   #83 = Methodref          #79.#82       // scala/runtime/BoxesRunTime.boxToInteger:(I)Ljava/lang/Integer;
   #84 = Utf8               equals
   #85 = Utf8               (Ljava/lang/Object;)Z
   #86 = NameAndType        #84:#85       // equals:(Ljava/lang/Object;)Z
   #87 = Methodref          #4.#86        // java/lang/Object.equals:(Ljava/lang/Object;)Z
   #88 = Utf8               $plus
   #89 = NameAndType        #88:#59       // $plus:(Lorg/sireum/Z;)Lorg/sireum/Z;
   #90 = InterfaceMethodref #57.#89       // org/sireum/Z.$plus:(Lorg/sireum/Z;)Lorg/sireum/Z;
   #91 = Utf8               Lorg/sireum/U8$Boxer$;
   #92 = NameAndType        #15:#91       // MODULE$:Lorg/sireum/U8$Boxer$;
   #93 = Fieldref           #12.#92       // org/sireum/U8$Boxer$.MODULE$:Lorg/sireum/U8$Boxer$;
   #94 = Utf8               java/lang/Integer
   #95 = Class              #94           // java/lang/Integer
   #96 = Utf8               org/sireum/$ZCompanion
   #97 = Class              #96           // org/sireum/$ZCompanion
   #98 = Utf8               toMSU8
   #99 = Utf8               (Lorg/sireum/IS;)Lorg/sireum/MS;
  #100 = Utf8               <I:Ljava/lang/Object;>(Lorg/sireum/IS<TI;Lorg/sireum/B;>;)Lorg/sireum/MS<TI;Lorg/sireum/U8;>;
  #101 = Utf8               org/sireum/MS
  #102 = Class              #101          // org/sireum/MS
  #103 = Methodref          #102.#66      // org/sireum/MS."<init>":(Lorg/sireum/$ZCompanion;Ljava/lang/Object;Lorg/sireum/Z;Lorg/sireum/$internal/Boxer;)V
  #104 = Methodref          #4.#20        // java/lang/Object."<init>":()V
  #105 = Utf8               Code
  #106 = Utf8               LineNumberTable
  #107 = Utf8               LocalVariableTable
  #108 = Utf8               Signature
  #109 = Utf8               MethodParameters
  #110 = Utf8               StackMapTable
  #111 = Utf8               InnerClasses
  #112 = Utf8               SourceFile
  #113 = Utf8               ScalaInlineInfo
  #114 = Utf8               Scala
{
  public static final org.sireum.conversions.ISB_Ext$ MODULE$;
    descriptor: Lorg/sireum/conversions/ISB_Ext$;
    flags: (0x0019) ACC_PUBLIC, ACC_STATIC, ACC_FINAL

  public static {};
    descriptor: ()V
    flags: (0x0009) ACC_PUBLIC, ACC_STATIC
    Code:
      stack=2, locals=0, args_size=0
         0: new           #2                  // class org/sireum/conversions/ISB_Ext$
         3: dup
         4: invokespecial #21                 // Method "<init>":()V
         7: putstatic     #23                 // Field MODULE$:Lorg/sireum/conversions/ISB_Ext$;
        10: return
      LineNumberTable:
        line 2211: 0

  public <I extends java.lang.Object> org.sireum.IS<I, org.sireum.B> fromISU8(org.sireum.IS<I, org.sireum.U8>);
    descriptor: (Lorg/sireum/IS;)Lorg/sireum/IS;
    flags: (0x0001) ACC_PUBLIC
    Code:
      stack=7, locals=2, args_size=2
         0: new           #29                 // class org/sireum/IS
         3: dup
         4: aload_1
         5: invokevirtual #33                 // Method org/sireum/IS.companion:()Lorg/sireum/$ZCompanion;
         8: aload_1
         9: invokevirtual #37                 // Method org/sireum/IS.data:()Ljava/lang/Object;
        12: checkcast     #39                 // class "[B"
        15: invokevirtual #42                 // Method "[B".clone:()Ljava/lang/Object;
        18: aload_1
        19: invokevirtual #46                 // Method org/sireum/IS.length:()Lorg/sireum/Z;
        22: getstatic     #51                 // Field org/sireum/Z$.MODULE$:Lorg/sireum/Z$;
        25: bipush        8
        27: invokevirtual #55                 // Method org/sireum/Z$.apply:(I)Lorg/sireum/Z;
        30: invokeinterface #61,  2           // InterfaceMethod org/sireum/Z.$times:(Lorg/sireum/Z;)Lorg/sireum/Z;
        35: getstatic     #64                 // Field org/sireum/B$Boxer$.MODULE$:Lorg/sireum/B$Boxer$;
        38: invokespecial #67                 // Method org/sireum/IS."<init>":(Lorg/sireum/$ZCompanion;Ljava/lang/Object;Lorg/sireum/Z;Lorg/sireum/$internal/Boxer;)V
        41: areturn
      LineNumberTable:
        line 2213: 0
      LocalVariableTable:
        Start  Length  Slot  Name   Signature
            0      42     0  this   Lorg/sireum/conversions/ISB_Ext$;
            0      42     1     s   Lorg/sireum/IS;
    Signature: #26                          // <I:Ljava/lang/Object;>(Lorg/sireum/IS<TI;Lorg/sireum/U8;>;)Lorg/sireum/IS<TI;Lorg/sireum/B;>;
    MethodParameters:
      Name                           Flags
      s                              final

  public <I extends java.lang.Object> org.sireum.IS<I, org.sireum.U8> toISU8(org.sireum.IS<I, org.sireum.B>);
    descriptor: (Lorg/sireum/IS;)Lorg/sireum/IS;
    flags: (0x0001) ACC_PUBLIC
    Code:
      stack=8, locals=3, args_size=2
         0: new           #29                 // class org/sireum/IS
         3: dup
         4: aload_1
         5: invokevirtual #33                 // Method org/sireum/IS.companion:()Lorg/sireum/$ZCompanion;
         8: aload_1
         9: invokevirtual #37                 // Method org/sireum/IS.data:()Ljava/lang/Object;
        12: checkcast     #39                 // class "[B"
        15: invokevirtual #42                 // Method "[B".clone:()Ljava/lang/Object;
        18: aload_1
        19: invokevirtual #46                 // Method org/sireum/IS.length:()Lorg/sireum/Z;
        22: getstatic     #51                 // Field org/sireum/Z$.MODULE$:Lorg/sireum/Z$;
        25: bipush        8
        27: invokevirtual #55                 // Method org/sireum/Z$.apply:(I)Lorg/sireum/Z;
        30: invokeinterface #74,  2           // InterfaceMethod org/sireum/Z.$div:(Lorg/sireum/Z;)Lorg/sireum/Z;
        35: aload_1
        36: invokevirtual #46                 // Method org/sireum/IS.length:()Lorg/sireum/Z;
        39: getstatic     #51                 // Field org/sireum/Z$.MODULE$:Lorg/sireum/Z$;
        42: bipush        8
        44: invokevirtual #55                 // Method org/sireum/Z$.apply:(I)Lorg/sireum/Z;
        47: invokeinterface #77,  2           // InterfaceMethod org/sireum/Z.$percent:(Lorg/sireum/Z;)Lorg/sireum/Z;
        52: iconst_0
        53: invokestatic  #83                 // Method scala/runtime/BoxesRunTime.boxToInteger:(I)Ljava/lang/Integer;
        56: astore_2
        57: dup
        58: ifnonnull     69
        61: pop
        62: aload_2
        63: ifnull        76
        66: goto          86
        69: aload_2
        70: invokevirtual #87                 // Method java/lang/Object.equals:(Ljava/lang/Object;)Z
        73: ifeq          86
        76: getstatic     #51                 // Field org/sireum/Z$.MODULE$:Lorg/sireum/Z$;
        79: iconst_0
        80: invokevirtual #55                 // Method org/sireum/Z$.apply:(I)Lorg/sireum/Z;
        83: goto          93
        86: getstatic     #51                 // Field org/sireum/Z$.MODULE$:Lorg/sireum/Z$;
        89: iconst_1
        90: invokevirtual #55                 // Method org/sireum/Z$.apply:(I)Lorg/sireum/Z;
        93: invokeinterface #90,  2           // InterfaceMethod org/sireum/Z.$plus:(Lorg/sireum/Z;)Lorg/sireum/Z;
        98: getstatic     #93                 // Field org/sireum/U8$Boxer$.MODULE$:Lorg/sireum/U8$Boxer$;
       101: invokespecial #67                 // Method org/sireum/IS."<init>":(Lorg/sireum/$ZCompanion;Ljava/lang/Object;Lorg/sireum/Z;Lorg/sireum/$internal/Boxer;)V
       104: areturn
      StackMapTable: number_of_entries = 4
        frame_type = 255 /* full_frame */
          offset_delta = 69
          locals = [ class org/sireum/conversions/ISB_Ext$, class org/sireum/IS, class java/lang/Integer ]
          stack = [ uninitialized 0, uninitialized 0, class org/sireum/$ZCompanion, class java/lang/Object, class org/sireum/Z, class org/sireum/Z ]
        frame_type = 255 /* full_frame */
          offset_delta = 6
          locals = [ class org/sireum/conversions/ISB_Ext$, class org/sireum/IS, class java/lang/Integer ]
          stack = [ uninitialized 0, uninitialized 0, class org/sireum/$ZCompanion, class java/lang/Object, class org/sireum/Z ]
        frame_type = 255 /* full_frame */
          offset_delta = 9
          locals = [ class org/sireum/conversions/ISB_Ext$, class org/sireum/IS, class java/lang/Integer ]
          stack = [ uninitialized 0, uninitialized 0, class org/sireum/$ZCompanion, class java/lang/Object, class org/sireum/Z ]
        frame_type = 255 /* full_frame */
          offset_delta = 6
          locals = [ class org/sireum/conversions/ISB_Ext$, class org/sireum/IS, class java/lang/Integer ]
          stack = [ uninitialized 0, uninitialized 0, class org/sireum/$ZCompanion, class java/lang/Object, class org/sireum/Z, class org/sireum/Z ]
      LineNumberTable:
        line 2216: 0
      LocalVariableTable:
        Start  Length  Slot  Name   Signature
            0     105     0  this   Lorg/sireum/conversions/ISB_Ext$;
            0     105     1     s   Lorg/sireum/IS;
    Signature: #71                          // <I:Ljava/lang/Object;>(Lorg/sireum/IS<TI;Lorg/sireum/B;>;)Lorg/sireum/IS<TI;Lorg/sireum/U8;>;
    MethodParameters:
      Name                           Flags
      s                              final

  public <I extends java.lang.Object> org.sireum.MS<I, org.sireum.U8> toMSU8(org.sireum.IS<I, org.sireum.B>);
    descriptor: (Lorg/sireum/IS;)Lorg/sireum/MS;
    flags: (0x0001) ACC_PUBLIC
    Code:
      stack=8, locals=3, args_size=2
         0: new           #102                // class org/sireum/MS
         3: dup
         4: aload_1
         5: invokevirtual #33                 // Method org/sireum/IS.companion:()Lorg/sireum/$ZCompanion;
         8: aload_1
         9: invokevirtual #37                 // Method org/sireum/IS.data:()Ljava/lang/Object;
        12: checkcast     #39                 // class "[B"
        15: invokevirtual #42                 // Method "[B".clone:()Ljava/lang/Object;
        18: aload_1
        19: invokevirtual #46                 // Method org/sireum/IS.length:()Lorg/sireum/Z;
        22: getstatic     #51                 // Field org/sireum/Z$.MODULE$:Lorg/sireum/Z$;
        25: bipush        8
        27: invokevirtual #55                 // Method org/sireum/Z$.apply:(I)Lorg/sireum/Z;
        30: invokeinterface #74,  2           // InterfaceMethod org/sireum/Z.$div:(Lorg/sireum/Z;)Lorg/sireum/Z;
        35: aload_1
        36: invokevirtual #46                 // Method org/sireum/IS.length:()Lorg/sireum/Z;
        39: getstatic     #51                 // Field org/sireum/Z$.MODULE$:Lorg/sireum/Z$;
        42: bipush        8
        44: invokevirtual #55                 // Method org/sireum/Z$.apply:(I)Lorg/sireum/Z;
        47: invokeinterface #77,  2           // InterfaceMethod org/sireum/Z.$percent:(Lorg/sireum/Z;)Lorg/sireum/Z;
        52: iconst_0
        53: invokestatic  #83                 // Method scala/runtime/BoxesRunTime.boxToInteger:(I)Ljava/lang/Integer;
        56: astore_2
        57: dup
        58: ifnonnull     69
        61: pop
        62: aload_2
        63: ifnull        76
        66: goto          86
        69: aload_2
        70: invokevirtual #87                 // Method java/lang/Object.equals:(Ljava/lang/Object;)Z
        73: ifeq          86
        76: getstatic     #51                 // Field org/sireum/Z$.MODULE$:Lorg/sireum/Z$;
        79: iconst_0
        80: invokevirtual #55                 // Method org/sireum/Z$.apply:(I)Lorg/sireum/Z;
        83: goto          93
        86: getstatic     #51                 // Field org/sireum/Z$.MODULE$:Lorg/sireum/Z$;
        89: iconst_1
        90: invokevirtual #55                 // Method org/sireum/Z$.apply:(I)Lorg/sireum/Z;
        93: invokeinterface #90,  2           // InterfaceMethod org/sireum/Z.$plus:(Lorg/sireum/Z;)Lorg/sireum/Z;
        98: getstatic     #93                 // Field org/sireum/U8$Boxer$.MODULE$:Lorg/sireum/U8$Boxer$;
       101: invokespecial #103                // Method org/sireum/MS."<init>":(Lorg/sireum/$ZCompanion;Ljava/lang/Object;Lorg/sireum/Z;Lorg/sireum/$internal/Boxer;)V
       104: areturn
      StackMapTable: number_of_entries = 4
        frame_type = 255 /* full_frame */
          offset_delta = 69
          locals = [ class org/sireum/conversions/ISB_Ext$, class org/sireum/IS, class java/lang/Integer ]
          stack = [ uninitialized 0, uninitialized 0, class org/sireum/$ZCompanion, class java/lang/Object, class org/sireum/Z, class org/sireum/Z ]
        frame_type = 255 /* full_frame */
          offset_delta = 6
          locals = [ class org/sireum/conversions/ISB_Ext$, class org/sireum/IS, class java/lang/Integer ]
          stack = [ uninitialized 0, uninitialized 0, class org/sireum/$ZCompanion, class java/lang/Object, class org/sireum/Z ]
        frame_type = 255 /* full_frame */
          offset_delta = 9
          locals = [ class org/sireum/conversions/ISB_Ext$, class org/sireum/IS, class java/lang/Integer ]
          stack = [ uninitialized 0, uninitialized 0, class org/sireum/$ZCompanion, class java/lang/Object, class org/sireum/Z ]
        frame_type = 255 /* full_frame */
          offset_delta = 6
          locals = [ class org/sireum/conversions/ISB_Ext$, class org/sireum/IS, class java/lang/Integer ]
          stack = [ uninitialized 0, uninitialized 0, class org/sireum/$ZCompanion, class java/lang/Object, class org/sireum/Z, class org/sireum/Z ]
      LineNumberTable:
        line 2219: 0
      LocalVariableTable:
        Start  Length  Slot  Name   Signature
            0     105     0  this   Lorg/sireum/conversions/ISB_Ext$;
            0     105     1     s   Lorg/sireum/IS;
    Signature: #100                         // <I:Ljava/lang/Object;>(Lorg/sireum/IS<TI;Lorg/sireum/B;>;)Lorg/sireum/MS<TI;Lorg/sireum/U8;>;
    MethodParameters:
      Name                           Flags
      s                              final

  private org.sireum.conversions.ISB_Ext$();
    descriptor: ()V
    flags: (0x0002) ACC_PRIVATE
    Code:
      stack=1, locals=1, args_size=1
         0: aload_0
         1: invokespecial #104                // Method java/lang/Object."<init>":()V
         4: return
      LineNumberTable:
        line 2211: 0
      LocalVariableTable:
        Start  Length  Slot  Name   Signature
            0       5     0  this   Lorg/sireum/conversions/ISB_Ext$;
}
InnerClasses:
  public static #10= #7 of #9;            // Boxer$=class org/sireum/B$Boxer$ of class org/sireum/B
  public static #10= #12 of #14;          // Boxer$=class org/sireum/U8$Boxer$ of class org/sireum/U8
SourceFile: "extension.scala"
  ScalaInlineInfo: length = 0x18 (unknown attribute)
   01 01 00 04 00 13 00 12 01 00 18 00 19 01 00 46
   00 19 01 00 62 00 63 01
  Scala: length = 0x0 (unknown attribute)

