Classfile /Users/mw/Projects/slang-braindump/.jar/jar11/assemble/slang-braindump/assemble/content/org/sireum/conversions/String.class
  Last modified May 29, 2022; size 3036 bytes
  SHA-256 checksum 2b56ff797a775dae133652d98dcc8aaffcb91d07aa88c100b3e1e1e5be9abcf6
  Compiled from "conversions.scala"
public final class org.sireum.conversions.String
  minor version: 0
  major version: 52
  flags: (0x0031) ACC_PUBLIC, ACC_FINAL, ACC_SUPER
  this_class: #2                          // org/sireum/conversions/String
  super_class: #4                         // java/lang/Object
  interfaces: 0, fields: 0, methods: 11, attributes: 3
Constant pool:
   #1 = Utf8               org/sireum/conversions/String
   #2 = Class              #1             // org/sireum/conversions/String
   #3 = Utf8               java/lang/Object
   #4 = Class              #3             // java/lang/Object
   #5 = Utf8               conversions.scala
   #6 = Utf8               Lscala/reflect/ScalaSignature;
   #7 = Utf8               bytes
   #8 = Utf8               \u0006\u0005\u0005}q!\u0002\b\u0010\u0011\u00031b!\u0002\r\u0010\u0011\u0003I\u0002\"\u0002\u0011\u0002\t\u0003\t\u0003\"\u0002\u0012\u0002\t\u0003\u0019\u0003\"B\u001d\u0002\t\u0003Q\u0004\"\u0002 \u0002\t\u0003y\u0004\"B*\u0002\t\u0003!\u0006\"B/\u0002\t\u0003q\u0006\"\u00022\u0002\t\u0003\u0019\u0007\"B4\u0002\t\u0003A\u0007\"\u00027\u0002\t\u0003i\u0007\"B:\u0002\t\u0003!\b\"\u0002=\u0002\t\u0003I\b\"\u0002?\u0002\t\u0003i\u0018AB*ue&twM\u0003\u0002\u0011#\u0005Y1m\u001c8wKJ\u001c\u0018n\u001c8t\u0015\t\u00112#\u0001\u0004tSJ,W/\u001c\u0006\u0002)\u0005\u0019qN]4\u0004\u0001A\u0011q#A\u0007\u0002\u001f\t11\u000b\u001e:j]\u001e\u001c\"!\u0001\u000e\u0011\u0005mqR\"\u0001\u000f\u000b\u0003u\tQa]2bY\u0006L!a\b\u000f\u0003\r\u0005s\u0017PU3g\u0003\u0019a\u0014N\\5u}Q\ta#\u0001\u0006ge>l\')Y:fmQ\"\"\u0001J\u001a\u0011\t\u00152\u0003&M\u0007\u0002#%\u0011q%\u0005\u0002\u0007\u000b&$\b.\u001a:\u0011\t\u0015J3FL\u0005\u0003UE\u0011!!S*\u0011\u0005\u0015b\u0013BA\u0017\u0012\u0005\u0005Q\u0006CA\u00130\u0013\t\u0001\u0014C\u0001\u0002VqA\u0011QEM\u0005\u00031EAQ\u0001N\u0002A\u0002E\n\u0011a\u001d\u0015\u0003\u0007Y\u0002\"!J\u001c\n\u0005a\n\"\u0001\u00029ve\u0016\f\u0001\u0002^8CCN,g\u0007\u000e\u000b\u0003cmBQ\u0001\u0010\u0003A\u0002!\nA\u0001Z1uC\"\u0012AAN\u0001\bMJ|WnQ5t+\t\u0001e\t\u0006\u00022\u0003\")!)\u0002a\u0001\u0007\u0006\u00111m\u001d\t\u0005K%\"u\n\u0005\u0002F\r2\u0001A!B$\u0006\u0005\u0004A%!A%\u0012\u0005%c\u0005CA\u000eK\u0013\tYEDA\u0004O_RD\u0017N\\4\u0011\u0005mi\u0015B\u0001(\u001d\u0005\r\te.\u001f\t\u0003KAK!!U\t\u0003\u0003\rC#!\u0002\u001c\u0002\u000f\u0019\u0014x.\\\"ngV\u0011Qk\u0017\u000b\u0003cYCQA\u0011\u0004A\u0002]\u0003B!\n-[\u001f&\u0011\u0011,\u0005\u0002\u0003\u001bN\u0003\"!R.\u0005\u000b\u001d3!\u0019\u0001%)\u0005\u00191\u0014\u0001\u00034s_6,\u0006([:\u0015\u0005Ez\u0006\"\u00021\b\u0001\u0004A\u0013aA;9g\"\u0012qAN\u0001\tMJ|W.\u0016\u001dngR\u0011\u0011\u0007\u001a\u0005\u0006A\"\u0001\r!\u001a\t\u0005Ka[c\u0006\u000b\u0002\tm\u0005)Ao\\\"jgR\u0011\u0011N\u001b\t\u0005K%Zs\nC\u00035\u0013\u0001\u0007\u0011\u0007\u000b\u0002\nm\u0005IAo\\\"TiJ,\u0017-\u001c\u000b\u0003]F\u00042!J8P\u0013\t\u0001\u0018CA\u0002KK:DQ\u0001\u000e\u0006A\u0002EB#A\u0003\u001c\u0002\u000bQ|7)\\:\u0015\u0005U4\b\u0003B\u0013YW=CQ\u0001N\u0006A\u0002EB#a\u0003\u001c\u0002\rQ|W\u000bO5t)\tA#\u0010C\u00035\u0019\u0001\u0007\u0011\u0007\u000b\u0002\rm\u00051Ao\\+9[N$\"!\u001a@\t\u000bQj\u0001\u0019A\u0019)\u000551\u0004&B\u0001\u0002\u0004\u0005%\u0001cA\u0013\u0002\u0006%\u0019\u0011qA\t\u0003\u0007\u0015DH/\r\u0005$c\u0005-\u00111CA\u0007\u0013\u0011\ti!a\u0004\u00027\u0011bWm]:j]&$He\u001a:fCR,\'\u000f\n3fM\u0006,H\u000e\u001e\u00132\u0015\r\t\t\"E\u0001\u0004Kb$\u0018\'C\u0012\u0002\u0016\u0005]\u0011\u0011DA\t\u001d\r)\u0013qC\u0005\u0004\u0003#\t\u0012\'\u0002\u0012&#\u0005m!AB:je\u0016,X\u000eK\u0003\u0001\u0003\u0007\tI\u0001
   #9 = Utf8               toU8ms
  #10 = Utf8               (Ljava/lang/String;)Lorg/sireum/MS;
  #11 = Utf8               (Ljava/lang/String;)Lorg/sireum/MS<Lorg/sireum/Z;Lorg/sireum/U8;>;
  #12 = Utf8               s
  #13 = Utf8               org/sireum/conversions/String$
  #14 = Class              #13            // org/sireum/conversions/String$
  #15 = Utf8               MODULE$
  #16 = Utf8               Lorg/sireum/conversions/String$;
  #17 = NameAndType        #15:#16        // MODULE$:Lorg/sireum/conversions/String$;
  #18 = Fieldref           #14.#17        // org/sireum/conversions/String$.MODULE$:Lorg/sireum/conversions/String$;
  #19 = NameAndType        #9:#10         // toU8ms:(Ljava/lang/String;)Lorg/sireum/MS;
  #20 = Methodref          #14.#19        // org/sireum/conversions/String$.toU8ms:(Ljava/lang/String;)Lorg/sireum/MS;
  #21 = Utf8               Ljava/lang/String;
  #22 = Utf8               toU8is
  #23 = Utf8               (Ljava/lang/String;)Lorg/sireum/IS;
  #24 = Utf8               (Ljava/lang/String;)Lorg/sireum/IS<Lorg/sireum/Z;Lorg/sireum/U8;>;
  #25 = NameAndType        #22:#23        // toU8is:(Ljava/lang/String;)Lorg/sireum/IS;
  #26 = Methodref          #14.#25        // org/sireum/conversions/String$.toU8is:(Ljava/lang/String;)Lorg/sireum/IS;
  #27 = Utf8               toCms
  #28 = Utf8               (Ljava/lang/String;)Lorg/sireum/MS<Lorg/sireum/Z;Lorg/sireum/C;>;
  #29 = NameAndType        #27:#10        // toCms:(Ljava/lang/String;)Lorg/sireum/MS;
  #30 = Methodref          #14.#29        // org/sireum/conversions/String$.toCms:(Ljava/lang/String;)Lorg/sireum/MS;
  #31 = Utf8               toCStream
  #32 = Utf8               (Ljava/lang/String;)Lorg/sireum/Jen;
  #33 = Utf8               (Ljava/lang/String;)Lorg/sireum/Jen<Lorg/sireum/C;>;
  #34 = NameAndType        #31:#32        // toCStream:(Ljava/lang/String;)Lorg/sireum/Jen;
  #35 = Methodref          #14.#34        // org/sireum/conversions/String$.toCStream:(Ljava/lang/String;)Lorg/sireum/Jen;
  #36 = Utf8               toCis
  #37 = Utf8               (Ljava/lang/String;)Lorg/sireum/IS<Lorg/sireum/Z;Lorg/sireum/C;>;
  #38 = NameAndType        #36:#23        // toCis:(Ljava/lang/String;)Lorg/sireum/IS;
  #39 = Methodref          #14.#38        // org/sireum/conversions/String$.toCis:(Ljava/lang/String;)Lorg/sireum/IS;
  #40 = Utf8               fromU8ms
  #41 = Utf8               (Lorg/sireum/MS;)Ljava/lang/String;
  #42 = Utf8               u8s
  #43 = NameAndType        #40:#41        // fromU8ms:(Lorg/sireum/MS;)Ljava/lang/String;
  #44 = Methodref          #14.#43        // org/sireum/conversions/String$.fromU8ms:(Lorg/sireum/MS;)Ljava/lang/String;
  #45 = Utf8               Lorg/sireum/MS;
  #46 = Utf8               fromU8is
  #47 = Utf8               (Lorg/sireum/IS;)Ljava/lang/String;
  #48 = NameAndType        #46:#47        // fromU8is:(Lorg/sireum/IS;)Ljava/lang/String;
  #49 = Methodref          #14.#48        // org/sireum/conversions/String$.fromU8is:(Lorg/sireum/IS;)Ljava/lang/String;
  #50 = Utf8               Lorg/sireum/IS;
  #51 = Utf8               fromCms
  #52 = Utf8               cs
  #53 = NameAndType        #51:#41        // fromCms:(Lorg/sireum/MS;)Ljava/lang/String;
  #54 = Methodref          #14.#53        // org/sireum/conversions/String$.fromCms:(Lorg/sireum/MS;)Ljava/lang/String;
  #55 = Utf8               fromCis
  #56 = NameAndType        #55:#47        // fromCis:(Lorg/sireum/IS;)Ljava/lang/String;
  #57 = Methodref          #14.#56        // org/sireum/conversions/String$.fromCis:(Lorg/sireum/IS;)Ljava/lang/String;
  #58 = Utf8               toBase64
  #59 = Utf8               data
  #60 = NameAndType        #58:#47        // toBase64:(Lorg/sireum/IS;)Ljava/lang/String;
  #61 = Methodref          #14.#60        // org/sireum/conversions/String$.toBase64:(Lorg/sireum/IS;)Ljava/lang/String;
  #62 = Utf8               fromBase64
  #63 = Utf8               (Ljava/lang/String;)Lorg/sireum/Either;
  #64 = Utf8               (Ljava/lang/String;)Lorg/sireum/Either<Lorg/sireum/IS<Lorg/sireum/Z;Lorg/sireum/U8;>;Lorg/sireum/String;>;
  #65 = NameAndType        #62:#63        // fromBase64:(Ljava/lang/String;)Lorg/sireum/Either;
  #66 = Methodref          #14.#65        // org/sireum/conversions/String$.fromBase64:(Ljava/lang/String;)Lorg/sireum/Either;
  #67 = Utf8               Code
  #68 = Utf8               LocalVariableTable
  #69 = Utf8               Signature
  #70 = Utf8               MethodParameters
  #71 = Utf8               SourceFile
  #72 = Utf8               RuntimeVisibleAnnotations
  #73 = Utf8               ScalaSig
{
  public static org.sireum.MS<org.sireum.Z, org.sireum.U8> toU8ms(java.lang.String);
    descriptor: (Ljava/lang/String;)Lorg/sireum/MS;
    flags: (0x0009) ACC_PUBLIC, ACC_STATIC
    Code:
      stack=2, locals=1, args_size=1
         0: getstatic     #18                 // Field org/sireum/conversions/String$.MODULE$:Lorg/sireum/conversions/String$;
         3: aload_0
         4: invokevirtual #20                 // Method org/sireum/conversions/String$.toU8ms:(Ljava/lang/String;)Lorg/sireum/MS;
         7: areturn
      LocalVariableTable:
        Start  Length  Slot  Name   Signature
            0       8     0     s   Ljava/lang/String;
    Signature: #11                          // (Ljava/lang/String;)Lorg/sireum/MS<Lorg/sireum/Z;Lorg/sireum/U8;>;
    MethodParameters:
      Name                           Flags
      s                              final

  public static org.sireum.IS<org.sireum.Z, org.sireum.U8> toU8is(java.lang.String);
    descriptor: (Ljava/lang/String;)Lorg/sireum/IS;
    flags: (0x0009) ACC_PUBLIC, ACC_STATIC
    Code:
      stack=2, locals=1, args_size=1
         0: getstatic     #18                 // Field org/sireum/conversions/String$.MODULE$:Lorg/sireum/conversions/String$;
         3: aload_0
         4: invokevirtual #26                 // Method org/sireum/conversions/String$.toU8is:(Ljava/lang/String;)Lorg/sireum/IS;
         7: areturn
      LocalVariableTable:
        Start  Length  Slot  Name   Signature
            0       8     0     s   Ljava/lang/String;
    Signature: #24                          // (Ljava/lang/String;)Lorg/sireum/IS<Lorg/sireum/Z;Lorg/sireum/U8;>;
    MethodParameters:
      Name                           Flags
      s                              final

  public static org.sireum.MS<org.sireum.Z, org.sireum.C> toCms(java.lang.String);
    descriptor: (Ljava/lang/String;)Lorg/sireum/MS;
    flags: (0x0009) ACC_PUBLIC, ACC_STATIC
    Code:
      stack=2, locals=1, args_size=1
         0: getstatic     #18                 // Field org/sireum/conversions/String$.MODULE$:Lorg/sireum/conversions/String$;
         3: aload_0
         4: invokevirtual #30                 // Method org/sireum/conversions/String$.toCms:(Ljava/lang/String;)Lorg/sireum/MS;
         7: areturn
      LocalVariableTable:
        Start  Length  Slot  Name   Signature
            0       8     0     s   Ljava/lang/String;
    Signature: #28                          // (Ljava/lang/String;)Lorg/sireum/MS<Lorg/sireum/Z;Lorg/sireum/C;>;
    MethodParameters:
      Name                           Flags
      s                              final

  public static org.sireum.Jen<org.sireum.C> toCStream(java.lang.String);
    descriptor: (Ljava/lang/String;)Lorg/sireum/Jen;
    flags: (0x0009) ACC_PUBLIC, ACC_STATIC
    Code:
      stack=2, locals=1, args_size=1
         0: getstatic     #18                 // Field org/sireum/conversions/String$.MODULE$:Lorg/sireum/conversions/String$;
         3: aload_0
         4: invokevirtual #35                 // Method org/sireum/conversions/String$.toCStream:(Ljava/lang/String;)Lorg/sireum/Jen;
         7: areturn
      LocalVariableTable:
        Start  Length  Slot  Name   Signature
            0       8     0     s   Ljava/lang/String;
    Signature: #33                          // (Ljava/lang/String;)Lorg/sireum/Jen<Lorg/sireum/C;>;
    MethodParameters:
      Name                           Flags
      s                              final

  public static org.sireum.IS<org.sireum.Z, org.sireum.C> toCis(java.lang.String);
    descriptor: (Ljava/lang/String;)Lorg/sireum/IS;
    flags: (0x0009) ACC_PUBLIC, ACC_STATIC
    Code:
      stack=2, locals=1, args_size=1
         0: getstatic     #18                 // Field org/sireum/conversions/String$.MODULE$:Lorg/sireum/conversions/String$;
         3: aload_0
         4: invokevirtual #39                 // Method org/sireum/conversions/String$.toCis:(Ljava/lang/String;)Lorg/sireum/IS;
         7: areturn
      LocalVariableTable:
        Start  Length  Slot  Name   Signature
            0       8     0     s   Ljava/lang/String;
    Signature: #37                          // (Ljava/lang/String;)Lorg/sireum/IS<Lorg/sireum/Z;Lorg/sireum/C;>;
    MethodParameters:
      Name                           Flags
      s                              final

  public static java.lang.String fromU8ms(org.sireum.MS);
    descriptor: (Lorg/sireum/MS;)Ljava/lang/String;
    flags: (0x0009) ACC_PUBLIC, ACC_STATIC
    Code:
      stack=2, locals=1, args_size=1
         0: getstatic     #18                 // Field org/sireum/conversions/String$.MODULE$:Lorg/sireum/conversions/String$;
         3: aload_0
         4: invokevirtual #44                 // Method org/sireum/conversions/String$.fromU8ms:(Lorg/sireum/MS;)Ljava/lang/String;
         7: areturn
      LocalVariableTable:
        Start  Length  Slot  Name   Signature
            0       8     0   u8s   Lorg/sireum/MS;
    MethodParameters:
      Name                           Flags
      u8s                            final

  public static java.lang.String fromU8is(org.sireum.IS);
    descriptor: (Lorg/sireum/IS;)Ljava/lang/String;
    flags: (0x0009) ACC_PUBLIC, ACC_STATIC
    Code:
      stack=2, locals=1, args_size=1
         0: getstatic     #18                 // Field org/sireum/conversions/String$.MODULE$:Lorg/sireum/conversions/String$;
         3: aload_0
         4: invokevirtual #49                 // Method org/sireum/conversions/String$.fromU8is:(Lorg/sireum/IS;)Ljava/lang/String;
         7: areturn
      LocalVariableTable:
        Start  Length  Slot  Name   Signature
            0       8     0   u8s   Lorg/sireum/IS;
    MethodParameters:
      Name                           Flags
      u8s                            final

  public static java.lang.String fromCms(org.sireum.MS);
    descriptor: (Lorg/sireum/MS;)Ljava/lang/String;
    flags: (0x0009) ACC_PUBLIC, ACC_STATIC
    Code:
      stack=2, locals=1, args_size=1
         0: getstatic     #18                 // Field org/sireum/conversions/String$.MODULE$:Lorg/sireum/conversions/String$;
         3: aload_0
         4: invokevirtual #54                 // Method org/sireum/conversions/String$.fromCms:(Lorg/sireum/MS;)Ljava/lang/String;
         7: areturn
      LocalVariableTable:
        Start  Length  Slot  Name   Signature
            0       8     0    cs   Lorg/sireum/MS;
    MethodParameters:
      Name                           Flags
      cs                             final

  public static java.lang.String fromCis(org.sireum.IS);
    descriptor: (Lorg/sireum/IS;)Ljava/lang/String;
    flags: (0x0009) ACC_PUBLIC, ACC_STATIC
    Code:
      stack=2, locals=1, args_size=1
         0: getstatic     #18                 // Field org/sireum/conversions/String$.MODULE$:Lorg/sireum/conversions/String$;
         3: aload_0
         4: invokevirtual #57                 // Method org/sireum/conversions/String$.fromCis:(Lorg/sireum/IS;)Ljava/lang/String;
         7: areturn
      LocalVariableTable:
        Start  Length  Slot  Name   Signature
            0       8     0    cs   Lorg/sireum/IS;
    MethodParameters:
      Name                           Flags
      cs                             final

  public static java.lang.String toBase64(org.sireum.IS);
    descriptor: (Lorg/sireum/IS;)Ljava/lang/String;
    flags: (0x0009) ACC_PUBLIC, ACC_STATIC
    Code:
      stack=2, locals=1, args_size=1
         0: getstatic     #18                 // Field org/sireum/conversions/String$.MODULE$:Lorg/sireum/conversions/String$;
         3: aload_0
         4: invokevirtual #61                 // Method org/sireum/conversions/String$.toBase64:(Lorg/sireum/IS;)Ljava/lang/String;
         7: areturn
      LocalVariableTable:
        Start  Length  Slot  Name   Signature
            0       8     0  data   Lorg/sireum/IS;
    MethodParameters:
      Name                           Flags
      data                           final

  public static org.sireum.Either<org.sireum.IS<org.sireum.Z, org.sireum.U8>, org.sireum.String> fromBase64(java.lang.String);
    descriptor: (Ljava/lang/String;)Lorg/sireum/Either;
    flags: (0x0009) ACC_PUBLIC, ACC_STATIC
    Code:
      stack=2, locals=1, args_size=1
         0: getstatic     #18                 // Field org/sireum/conversions/String$.MODULE$:Lorg/sireum/conversions/String$;
         3: aload_0
         4: invokevirtual #66                 // Method org/sireum/conversions/String$.fromBase64:(Ljava/lang/String;)Lorg/sireum/Either;
         7: areturn
      LocalVariableTable:
        Start  Length  Slot  Name   Signature
            0       8     0     s   Ljava/lang/String;
    Signature: #64                          // (Ljava/lang/String;)Lorg/sireum/Either<Lorg/sireum/IS<Lorg/sireum/Z;Lorg/sireum/U8;>;Lorg/sireum/String;>;
    MethodParameters:
      Name                           Flags
      s                              final
}
SourceFile: "conversions.scala"
RuntimeVisibleAnnotations:
  0: #6(#7=s#8)
    scala.reflect.ScalaSignature(
      bytes="\u0006\u0005\u0005}q!\u0002\b\u0010\u0011\u00031b!\u0002\r\u0010\u0011\u0003I\u0002\"\u0002\u0011\u0002\t\u0003\t\u0003\"\u0002\u0012\u0002\t\u0003\u0019\u0003\"B\u001d\u0002\t\u0003Q\u0004\"\u0002 \u0002\t\u0003y\u0004\"B*\u0002\t\u0003!\u0006\"B/\u0002\t\u0003q\u0006\"\u00022\u0002\t\u0003\u0019\u0007\"B4\u0002\t\u0003A\u0007\"\u00027\u0002\t\u0003i\u0007\"B:\u0002\t\u0003!\b\"\u0002=\u0002\t\u0003I\b\"\u0002?\u0002\t\u0003i\u0018AB*ue&twM\u0003\u0002\u0011#\u0005Y1m\u001c8wKJ\u001c\u0018n\u001c8t\u0015\t\u00112#\u0001\u0004tSJ,W/\u001c\u0006\u0002)\u0005\u0019qN]4\u0004\u0001A\u0011q#A\u0007\u0002\u001f\t11\u000b\u001e:j]\u001e\u001c\"!\u0001\u000e\u0011\u0005mqR\"\u0001\u000f\u000b\u0003u\tQa]2bY\u0006L!a\b\u000f\u0003\r\u0005s\u0017PU3g\u0003\u0019a\u0014N\\5u}Q\ta#\u0001\u0006ge>l\')Y:fmQ\"\"\u0001J\u001a\u0011\t\u00152\u0003&M\u0007\u0002#%\u0011q%\u0005\u0002\u0007\u000b&$\b.\u001a:\u0011\t\u0015J3FL\u0005\u0003UE\u0011!!S*\u0011\u0005\u0015b\u0013BA\u0017\u0012\u0005\u0005Q\u0006CA\u00130\u0013\t\u0001\u0014C\u0001\u0002VqA\u0011QEM\u0005\u00031EAQ\u0001N\u0002A\u0002E\n\u0011a\u001d\u0015\u0003\u0007Y\u0002\"!J\u001c\n\u0005a\n\"\u0001\u00029ve\u0016\f\u0001\u0002^8CCN,g\u0007\u000e\u000b\u0003cmBQ\u0001\u0010\u0003A\u0002!\nA\u0001Z1uC\"\u0012AAN\u0001\bMJ|WnQ5t+\t\u0001e\t\u0006\u00022\u0003\")!)\u0002a\u0001\u0007\u0006\u00111m\u001d\t\u0005K%\"u\n\u0005\u0002F\r2\u0001A!B$\u0006\u0005\u0004A%!A%\u0012\u0005%c\u0005CA\u000eK\u0013\tYEDA\u0004O_RD\u0017N\\4\u0011\u0005mi\u0015B\u0001(\u001d\u0005\r\te.\u001f\t\u0003KAK!!U\t\u0003\u0003\rC#!\u0002\u001c\u0002\u000f\u0019\u0014x.\\\"ngV\u0011Qk\u0017\u000b\u0003cYCQA\u0011\u0004A\u0002]\u0003B!\n-[\u001f&\u0011\u0011,\u0005\u0002\u0003\u001bN\u0003\"!R.\u0005\u000b\u001d3!\u0019\u0001%)\u0005\u00191\u0014\u0001\u00034s_6,\u0006([:\u0015\u0005Ez\u0006\"\u00021\b\u0001\u0004A\u0013aA;9g\"\u0012qAN\u0001\tMJ|W.\u0016\u001dngR\u0011\u0011\u0007\u001a\u0005\u0006A\"\u0001\r!\u001a\t\u0005Ka[c\u0006\u000b\u0002\tm\u0005)Ao\\\"jgR\u0011\u0011N\u001b\t\u0005K%Zs\nC\u00035\u0013\u0001\u0007\u0011\u0007\u000b\u0002\nm\u0005IAo\\\"TiJ,\u0017-\u001c\u000b\u0003]F\u00042!J8P\u0013\t\u0001\u0018CA\u0002KK:DQ\u0001\u000e\u0006A\u0002EB#A\u0003\u001c\u0002\u000bQ|7)\\:\u0015\u0005U4\b\u0003B\u0013YW=CQ\u0001N\u0006A\u0002EB#a\u0003\u001c\u0002\rQ|W\u000bO5t)\tA#\u0010C\u00035\u0019\u0001\u0007\u0011\u0007\u000b\u0002\rm\u00051Ao\\+9[N$\"!\u001a@\t\u000bQj\u0001\u0019A\u0019)\u000551\u0004&B\u0001\u0002\u0004\u0005%\u0001cA\u0013\u0002\u0006%\u0019\u0011qA\t\u0003\u0007\u0015DH/\r\u0005$c\u0005-\u00111CA\u0007\u0013\u0011\ti!a\u0004\u00027\u0011bWm]:j]&$He\u001a:fCR,\'\u000f\n3fM\u0006,H\u000e\u001e\u00132\u0015\r\t\t\"E\u0001\u0004Kb$\u0018\'C\u0012\u0002\u0016\u0005]\u0011\u0011DA\t\u001d\r)\u0013qC\u0005\u0004\u0003#\t\u0012\'\u0002\u0012&#\u0005m!AB:je\u0016,X\u000eK\u0003\u0001\u0003\u0007\tI\u0001"
    )
  ScalaSig: length = 0x3 (unknown attribute)
   05 02 00
