Classfile /Users/mw/Projects/slang-braindump/.jar/jar11/assemble/slang-braindump/assemble/content/org/sireum/conversions/U28_Ext.class
  Last modified May 29, 2022; size 839 bytes
  SHA-256 checksum 0b40d24b8a2a98653cf0fd82cb986b19f806a22de0de96935e9bdbec2812a32c
  Compiled from "extension.scala"
public final class org.sireum.conversions.U28_Ext
  minor version: 0
  major version: 52
  flags: (0x0031) ACC_PUBLIC, ACC_FINAL, ACC_SUPER
  this_class: #2                          // org/sireum/conversions/U28_Ext
  super_class: #4                         // java/lang/Object
  interfaces: 0, fields: 0, methods: 2, attributes: 3
Constant pool:
   #1 = Utf8               org/sireum/conversions/U28_Ext
   #2 = Class              #1             // org/sireum/conversions/U28_Ext
   #3 = Utf8               java/lang/Object
   #4 = Class              #3             // java/lang/Object
   #5 = Utf8               extension.scala
   #6 = Utf8               Lscala/reflect/ScalaSignature;
   #7 = Utf8               bytes
   #8 = Utf8               \u0006\u0005=:Q!\u0002\u0004\t\u000251Qa\u0004\u0004\t\u0002AAQaF\u0001\u0005\u0002aAQ!G\u0001\u0005\u0002iAQ\u0001K\u0001\u0005\u0002%\nq!\u0016\u001a9?\u0016CHO\u0003\u0002\b\u0011\u0005Y1m\u001c8wKJ\u001c\u0018n\u001c8t\u0015\tI!\"\u0001\u0004tSJ,W/\u001c\u0006\u0002\u0017\u0005\u0019qN]4\u0004\u0001A\u0011a\"A\u0007\u0002\r\t9QK\r\u001d`\u000bb$8CA\u0001\u0012!\t\u0011R#D\u0001\u0014\u0015\u0005!\u0012!B:dC2\f\u0017B\u0001\f\u0014\u0005\u0019\te.\u001f*fM\u00061A(\u001b8jiz\"\u0012!D\u0001\u0006i>,6G\r\u000b\u00037}\u0001\"\u0001H\u000f\u000e\u0003!I!A\b\u0005\u0003\u0007U\u001b$\u0007C\u0003!\u0007\u0001\u0007\u0011%A\u0001o!\ta\"%\u0003\u0002$\u0011\t\u0019QK\r\u001d)\u0005\r)\u0003C\u0001\u000f\'\u0013\t9\u0003B\u0001\u0003qkJ,\u0017!\u0002;p+Z\"DC\u0001\u0016.!\ta2&\u0003\u0002-\u0011\t\u0019QK\u000e\u001b\t\u000b\u0001\"\u0001\u0019A\u0011)\u0005\u0011)\u0003
   #9 = Utf8               toU64
  #10 = Utf8               (I)J
  #11 = Utf8               n
  #12 = Utf8               org/sireum/conversions/U28_Ext$
  #13 = Class              #12            // org/sireum/conversions/U28_Ext$
  #14 = Utf8               MODULE$
  #15 = Utf8               Lorg/sireum/conversions/U28_Ext$;
  #16 = NameAndType        #14:#15        // MODULE$:Lorg/sireum/conversions/U28_Ext$;
  #17 = Fieldref           #13.#16        // org/sireum/conversions/U28_Ext$.MODULE$:Lorg/sireum/conversions/U28_Ext$;
  #18 = NameAndType        #9:#10         // toU64:(I)J
  #19 = Methodref          #13.#18        // org/sireum/conversions/U28_Ext$.toU64:(I)J
  #20 = Utf8               I
  #21 = Utf8               toU32
  #22 = Utf8               (I)I
  #23 = NameAndType        #21:#22        // toU32:(I)I
  #24 = Methodref          #13.#23        // org/sireum/conversions/U28_Ext$.toU32:(I)I
  #25 = Utf8               Code
  #26 = Utf8               LocalVariableTable
  #27 = Utf8               MethodParameters
  #28 = Utf8               SourceFile
  #29 = Utf8               RuntimeVisibleAnnotations
  #30 = Utf8               ScalaSig
{
  public static long toU64(int);
    descriptor: (I)J
    flags: (0x0009) ACC_PUBLIC, ACC_STATIC
    Code:
      stack=2, locals=1, args_size=1
         0: getstatic     #17                 // Field org/sireum/conversions/U28_Ext$.MODULE$:Lorg/sireum/conversions/U28_Ext$;
         3: iload_0
         4: invokevirtual #19                 // Method org/sireum/conversions/U28_Ext$.toU64:(I)J
         7: lreturn
      LocalVariableTable:
        Start  Length  Slot  Name   Signature
            0       8     0     n   I
    MethodParameters:
      Name                           Flags
      n                              final

  public static int toU32(int);
    descriptor: (I)I
    flags: (0x0009) ACC_PUBLIC, ACC_STATIC
    Code:
      stack=2, locals=1, args_size=1
         0: getstatic     #17                 // Field org/sireum/conversions/U28_Ext$.MODULE$:Lorg/sireum/conversions/U28_Ext$;
         3: iload_0
         4: invokevirtual #24                 // Method org/sireum/conversions/U28_Ext$.toU32:(I)I
         7: ireturn
      LocalVariableTable:
        Start  Length  Slot  Name   Signature
            0       8     0     n   I
    MethodParameters:
      Name                           Flags
      n                              final
}
SourceFile: "extension.scala"
RuntimeVisibleAnnotations:
  0: #6(#7=s#8)
    scala.reflect.ScalaSignature(
      bytes="\u0006\u0005=:Q!\u0002\u0004\t\u000251Qa\u0004\u0004\t\u0002AAQaF\u0001\u0005\u0002aAQ!G\u0001\u0005\u0002iAQ\u0001K\u0001\u0005\u0002%\nq!\u0016\u001a9?\u0016CHO\u0003\u0002\b\u0011\u0005Y1m\u001c8wKJ\u001c\u0018n\u001c8t\u0015\tI!\"\u0001\u0004tSJ,W/\u001c\u0006\u0002\u0017\u0005\u0019qN]4\u0004\u0001A\u0011a\"A\u0007\u0002\r\t9QK\r\u001d`\u000bb$8CA\u0001\u0012!\t\u0011R#D\u0001\u0014\u0015\u0005!\u0012!B:dC2\f\u0017B\u0001\f\u0014\u0005\u0019\te.\u001f*fM\u00061A(\u001b8jiz\"\u0012!D\u0001\u0006i>,6G\r\u000b\u00037}\u0001\"\u0001H\u000f\u000e\u0003!I!A\b\u0005\u0003\u0007U\u001b$\u0007C\u0003!\u0007\u0001\u0007\u0011%A\u0001o!\ta\"%\u0003\u0002$\u0011\t\u0019QK\r\u001d)\u0005\r)\u0003C\u0001\u000f\'\u0013\t9\u0003B\u0001\u0003qkJ,\u0017!\u0002;p+Z\"DC\u0001\u0016.!\ta2&\u0003\u0002-\u0011\t\u0019QK\u000e\u001b\t\u000b\u0001\"\u0001\u0019A\u0011)\u0005\u0011)\u0003"
    )
  ScalaSig: length = 0x3 (unknown attribute)
   05 02 00
