Classfile /Users/mw/Projects/slang-braindump/.jar/jar11/assemble/slang-braindump/assemble/content/org/sireum/conversions/U64$.class
  Last modified May 29, 2022; size 6215 bytes
  SHA-256 checksum e7790171d7ff4b383de36f4fb6cfa205df74ee616fdcbfbe68bd4855cd14fc44
  Compiled from "conversions.scala"
public final class org.sireum.conversions.U64$
  minor version: 0
  major version: 52
  flags: (0x0031) ACC_PUBLIC, ACC_FINAL, ACC_SUPER
  this_class: #2                          // org/sireum/conversions/U64$
  super_class: #4                         // java/lang/Object
  interfaces: 0, fields: 1, methods: 54, attributes: 3
Constant pool:
    #1 = Utf8               org/sireum/conversions/U64$
    #2 = Class              #1            // org/sireum/conversions/U64$
    #3 = Utf8               java/lang/Object
    #4 = Class              #3            // java/lang/Object
    #5 = Utf8               conversions.scala
    #6 = Utf8               MODULE$
    #7 = Utf8               Lorg/sireum/conversions/U64$;
    #8 = Utf8               <clinit>
    #9 = Utf8               ()V
   #10 = Utf8               <init>
   #11 = NameAndType        #10:#9        // "<init>":()V
   #12 = Methodref          #2.#11        // org/sireum/conversions/U64$."<init>":()V
   #13 = NameAndType        #6:#7         // MODULE$:Lorg/sireum/conversions/U64$;
   #14 = Fieldref           #2.#13        // org/sireum/conversions/U64$.MODULE$:Lorg/sireum/conversions/U64$;
   #15 = Utf8               toB
   #16 = Utf8               (J)Z
   #17 = Utf8               n
   #18 = Utf8               org/sireum/conversions/U64_Ext$
   #19 = Class              #18           // org/sireum/conversions/U64_Ext$
   #20 = Utf8               Lorg/sireum/conversions/U64_Ext$;
   #21 = NameAndType        #6:#20        // MODULE$:Lorg/sireum/conversions/U64_Ext$;
   #22 = Fieldref           #19.#21       // org/sireum/conversions/U64_Ext$.MODULE$:Lorg/sireum/conversions/U64_Ext$;
   #23 = NameAndType        #15:#16       // toB:(J)Z
   #24 = Methodref          #19.#23       // org/sireum/conversions/U64_Ext$.toB:(J)Z
   #25 = Utf8               this
   #26 = Utf8               J
   #27 = Utf8               toZ
   #28 = Utf8               (J)Lorg/sireum/Z;
   #29 = NameAndType        #27:#28       // toZ:(J)Lorg/sireum/Z;
   #30 = Methodref          #19.#29       // org/sireum/conversions/U64_Ext$.toZ:(J)Lorg/sireum/Z;
   #31 = Utf8               toZ8
   #32 = NameAndType        #31:#28       // toZ8:(J)Lorg/sireum/Z;
   #33 = Methodref          #19.#32       // org/sireum/conversions/U64_Ext$.toZ8:(J)Lorg/sireum/Z;
   #34 = Utf8               toZ16
   #35 = NameAndType        #34:#28       // toZ16:(J)Lorg/sireum/Z;
   #36 = Methodref          #19.#35       // org/sireum/conversions/U64_Ext$.toZ16:(J)Lorg/sireum/Z;
   #37 = Utf8               toZ32
   #38 = NameAndType        #37:#28       // toZ32:(J)Lorg/sireum/Z;
   #39 = Methodref          #19.#38       // org/sireum/conversions/U64_Ext$.toZ32:(J)Lorg/sireum/Z;
   #40 = Utf8               toZ64
   #41 = NameAndType        #40:#28       // toZ64:(J)Lorg/sireum/Z;
   #42 = Methodref          #19.#41       // org/sireum/conversions/U64_Ext$.toZ64:(J)Lorg/sireum/Z;
   #43 = Utf8               toN
   #44 = NameAndType        #43:#28       // toN:(J)Lorg/sireum/Z;
   #45 = Methodref          #19.#44       // org/sireum/conversions/U64_Ext$.toN:(J)Lorg/sireum/Z;
   #46 = Utf8               toN8
   #47 = NameAndType        #46:#28       // toN8:(J)Lorg/sireum/Z;
   #48 = Methodref          #19.#47       // org/sireum/conversions/U64_Ext$.toN8:(J)Lorg/sireum/Z;
   #49 = Utf8               toN16
   #50 = NameAndType        #49:#28       // toN16:(J)Lorg/sireum/Z;
   #51 = Methodref          #19.#50       // org/sireum/conversions/U64_Ext$.toN16:(J)Lorg/sireum/Z;
   #52 = Utf8               toN32
   #53 = NameAndType        #52:#28       // toN32:(J)Lorg/sireum/Z;
   #54 = Methodref          #19.#53       // org/sireum/conversions/U64_Ext$.toN32:(J)Lorg/sireum/Z;
   #55 = Utf8               toN64
   #56 = NameAndType        #55:#28       // toN64:(J)Lorg/sireum/Z;
   #57 = Methodref          #19.#56       // org/sireum/conversions/U64_Ext$.toN64:(J)Lorg/sireum/Z;
   #58 = Utf8               toS8
   #59 = Utf8               (J)B
   #60 = NameAndType        #58:#59       // toS8:(J)B
   #61 = Methodref          #19.#60       // org/sireum/conversions/U64_Ext$.toS8:(J)B
   #62 = Utf8               toS16
   #63 = Utf8               (J)S
   #64 = NameAndType        #62:#63       // toS16:(J)S
   #65 = Methodref          #19.#64       // org/sireum/conversions/U64_Ext$.toS16:(J)S
   #66 = Utf8               toS32
   #67 = Utf8               (J)I
   #68 = NameAndType        #66:#67       // toS32:(J)I
   #69 = Methodref          #19.#68       // org/sireum/conversions/U64_Ext$.toS32:(J)I
   #70 = Utf8               toS64
   #71 = Utf8               (J)J
   #72 = NameAndType        #70:#71       // toS64:(J)J
   #73 = Methodref          #19.#72       // org/sireum/conversions/U64_Ext$.toS64:(J)J
   #74 = Utf8               toRawS64
   #75 = NameAndType        #74:#71       // toRawS64:(J)J
   #76 = Methodref          #19.#75       // org/sireum/conversions/U64_Ext$.toRawS64:(J)J
   #77 = Utf8               toU8
   #78 = NameAndType        #77:#59       // toU8:(J)B
   #79 = Methodref          #19.#78       // org/sireum/conversions/U64_Ext$.toU8:(J)B
   #80 = Utf8               toU16
   #81 = NameAndType        #80:#63       // toU16:(J)S
   #82 = Methodref          #19.#81       // org/sireum/conversions/U64_Ext$.toU16:(J)S
   #83 = Utf8               toU32
   #84 = NameAndType        #83:#67       // toU32:(J)I
   #85 = Methodref          #19.#84       // org/sireum/conversions/U64_Ext$.toU32:(J)I
   #86 = Utf8               toU33
   #87 = NameAndType        #86:#71       // toU33:(J)J
   #88 = Methodref          #19.#87       // org/sireum/conversions/U64_Ext$.toU33:(J)J
   #89 = Utf8               toU34
   #90 = NameAndType        #89:#71       // toU34:(J)J
   #91 = Methodref          #19.#90       // org/sireum/conversions/U64_Ext$.toU34:(J)J
   #92 = Utf8               toU35
   #93 = NameAndType        #92:#71       // toU35:(J)J
   #94 = Methodref          #19.#93       // org/sireum/conversions/U64_Ext$.toU35:(J)J
   #95 = Utf8               toU36
   #96 = NameAndType        #95:#71       // toU36:(J)J
   #97 = Methodref          #19.#96       // org/sireum/conversions/U64_Ext$.toU36:(J)J
   #98 = Utf8               toU37
   #99 = NameAndType        #98:#71       // toU37:(J)J
  #100 = Methodref          #19.#99       // org/sireum/conversions/U64_Ext$.toU37:(J)J
  #101 = Utf8               toU38
  #102 = NameAndType        #101:#71      // toU38:(J)J
  #103 = Methodref          #19.#102      // org/sireum/conversions/U64_Ext$.toU38:(J)J
  #104 = Utf8               toU39
  #105 = NameAndType        #104:#71      // toU39:(J)J
  #106 = Methodref          #19.#105      // org/sireum/conversions/U64_Ext$.toU39:(J)J
  #107 = Utf8               toU40
  #108 = NameAndType        #107:#71      // toU40:(J)J
  #109 = Methodref          #19.#108      // org/sireum/conversions/U64_Ext$.toU40:(J)J
  #110 = Utf8               toU41
  #111 = NameAndType        #110:#71      // toU41:(J)J
  #112 = Methodref          #19.#111      // org/sireum/conversions/U64_Ext$.toU41:(J)J
  #113 = Utf8               toU42
  #114 = NameAndType        #113:#71      // toU42:(J)J
  #115 = Methodref          #19.#114      // org/sireum/conversions/U64_Ext$.toU42:(J)J
  #116 = Utf8               toU43
  #117 = NameAndType        #116:#71      // toU43:(J)J
  #118 = Methodref          #19.#117      // org/sireum/conversions/U64_Ext$.toU43:(J)J
  #119 = Utf8               toU44
  #120 = NameAndType        #119:#71      // toU44:(J)J
  #121 = Methodref          #19.#120      // org/sireum/conversions/U64_Ext$.toU44:(J)J
  #122 = Utf8               toU45
  #123 = NameAndType        #122:#71      // toU45:(J)J
  #124 = Methodref          #19.#123      // org/sireum/conversions/U64_Ext$.toU45:(J)J
  #125 = Utf8               toU46
  #126 = NameAndType        #125:#71      // toU46:(J)J
  #127 = Methodref          #19.#126      // org/sireum/conversions/U64_Ext$.toU46:(J)J
  #128 = Utf8               toU47
  #129 = NameAndType        #128:#71      // toU47:(J)J
  #130 = Methodref          #19.#129      // org/sireum/conversions/U64_Ext$.toU47:(J)J
  #131 = Utf8               toU48
  #132 = NameAndType        #131:#71      // toU48:(J)J
  #133 = Methodref          #19.#132      // org/sireum/conversions/U64_Ext$.toU48:(J)J
  #134 = Utf8               toU49
  #135 = NameAndType        #134:#71      // toU49:(J)J
  #136 = Methodref          #19.#135      // org/sireum/conversions/U64_Ext$.toU49:(J)J
  #137 = Utf8               toU50
  #138 = NameAndType        #137:#71      // toU50:(J)J
  #139 = Methodref          #19.#138      // org/sireum/conversions/U64_Ext$.toU50:(J)J
  #140 = Utf8               toU51
  #141 = NameAndType        #140:#71      // toU51:(J)J
  #142 = Methodref          #19.#141      // org/sireum/conversions/U64_Ext$.toU51:(J)J
  #143 = Utf8               toU52
  #144 = NameAndType        #143:#71      // toU52:(J)J
  #145 = Methodref          #19.#144      // org/sireum/conversions/U64_Ext$.toU52:(J)J
  #146 = Utf8               toU53
  #147 = NameAndType        #146:#71      // toU53:(J)J
  #148 = Methodref          #19.#147      // org/sireum/conversions/U64_Ext$.toU53:(J)J
  #149 = Utf8               toU54
  #150 = NameAndType        #149:#71      // toU54:(J)J
  #151 = Methodref          #19.#150      // org/sireum/conversions/U64_Ext$.toU54:(J)J
  #152 = Utf8               toU55
  #153 = NameAndType        #152:#71      // toU55:(J)J
  #154 = Methodref          #19.#153      // org/sireum/conversions/U64_Ext$.toU55:(J)J
  #155 = Utf8               toU56
  #156 = NameAndType        #155:#71      // toU56:(J)J
  #157 = Methodref          #19.#156      // org/sireum/conversions/U64_Ext$.toU56:(J)J
  #158 = Utf8               toU57
  #159 = NameAndType        #158:#71      // toU57:(J)J
  #160 = Methodref          #19.#159      // org/sireum/conversions/U64_Ext$.toU57:(J)J
  #161 = Utf8               toU58
  #162 = NameAndType        #161:#71      // toU58:(J)J
  #163 = Methodref          #19.#162      // org/sireum/conversions/U64_Ext$.toU58:(J)J
  #164 = Utf8               toU59
  #165 = NameAndType        #164:#71      // toU59:(J)J
  #166 = Methodref          #19.#165      // org/sireum/conversions/U64_Ext$.toU59:(J)J
  #167 = Utf8               toU60
  #168 = NameAndType        #167:#71      // toU60:(J)J
  #169 = Methodref          #19.#168      // org/sireum/conversions/U64_Ext$.toU60:(J)J
  #170 = Utf8               toU61
  #171 = NameAndType        #170:#71      // toU61:(J)J
  #172 = Methodref          #19.#171      // org/sireum/conversions/U64_Ext$.toU61:(J)J
  #173 = Utf8               toU62
  #174 = NameAndType        #173:#71      // toU62:(J)J
  #175 = Methodref          #19.#174      // org/sireum/conversions/U64_Ext$.toU62:(J)J
  #176 = Utf8               toU63
  #177 = NameAndType        #176:#71      // toU63:(J)J
  #178 = Methodref          #19.#177      // org/sireum/conversions/U64_Ext$.toU63:(J)J
  #179 = Utf8               toU64
  #180 = NameAndType        #179:#71      // toU64:(J)J
  #181 = Methodref          #19.#180      // org/sireum/conversions/U64_Ext$.toU64:(J)J
  #182 = Utf8               toRawF64
  #183 = Utf8               (J)D
  #184 = NameAndType        #182:#183     // toRawF64:(J)D
  #185 = Methodref          #19.#184      // org/sireum/conversions/U64_Ext$.toRawF64:(J)D
  #186 = Methodref          #4.#11        // java/lang/Object."<init>":()V
  #187 = Utf8               Code
  #188 = Utf8               LineNumberTable
  #189 = Utf8               LocalVariableTable
  #190 = Utf8               MethodParameters
  #191 = Utf8               SourceFile
  #192 = Utf8               ScalaInlineInfo
  #193 = Utf8               Scala
{
  public static final org.sireum.conversions.U64$ MODULE$;
    descriptor: Lorg/sireum/conversions/U64$;
    flags: (0x0019) ACC_PUBLIC, ACC_STATIC, ACC_FINAL

  public static {};
    descriptor: ()V
    flags: (0x0009) ACC_PUBLIC, ACC_STATIC
    Code:
      stack=2, locals=0, args_size=0
         0: new           #2                  // class org/sireum/conversions/U64$
         3: dup
         4: invokespecial #12                 // Method "<init>":()V
         7: putstatic     #14                 // Field MODULE$:Lorg/sireum/conversions/U64$;
        10: return
      LineNumberTable:
        line 2187: 0

  public boolean toB(long);
    descriptor: (J)Z
    flags: (0x0001) ACC_PUBLIC
    Code:
      stack=3, locals=3, args_size=2
         0: getstatic     #22                 // Field org/sireum/conversions/U64_Ext$.MODULE$:Lorg/sireum/conversions/U64_Ext$;
         3: lload_1
         4: invokevirtual #24                 // Method org/sireum/conversions/U64_Ext$.toB:(J)Z
         7: ireturn
      LineNumberTable:
        line 2189: 0
      LocalVariableTable:
        Start  Length  Slot  Name   Signature
            0       8     0  this   Lorg/sireum/conversions/U64$;
            0       8     1     n   J
    MethodParameters:
      Name                           Flags
      n                              final

  public org.sireum.Z toZ(long);
    descriptor: (J)Lorg/sireum/Z;
    flags: (0x0001) ACC_PUBLIC
    Code:
      stack=3, locals=3, args_size=2
         0: getstatic     #22                 // Field org/sireum/conversions/U64_Ext$.MODULE$:Lorg/sireum/conversions/U64_Ext$;
         3: lload_1
         4: invokevirtual #30                 // Method org/sireum/conversions/U64_Ext$.toZ:(J)Lorg/sireum/Z;
         7: areturn
      LineNumberTable:
        line 2192: 0
      LocalVariableTable:
        Start  Length  Slot  Name   Signature
            0       8     0  this   Lorg/sireum/conversions/U64$;
            0       8     1     n   J
    MethodParameters:
      Name                           Flags
      n                              final

  public org.sireum.Z toZ8(long);
    descriptor: (J)Lorg/sireum/Z;
    flags: (0x0001) ACC_PUBLIC
    Code:
      stack=3, locals=3, args_size=2
         0: getstatic     #22                 // Field org/sireum/conversions/U64_Ext$.MODULE$:Lorg/sireum/conversions/U64_Ext$;
         3: lload_1
         4: invokevirtual #33                 // Method org/sireum/conversions/U64_Ext$.toZ8:(J)Lorg/sireum/Z;
         7: areturn
      LineNumberTable:
        line 2258: 0
      LocalVariableTable:
        Start  Length  Slot  Name   Signature
            0       8     0  this   Lorg/sireum/conversions/U64$;
            0       8     1     n   J
    MethodParameters:
      Name                           Flags
      n                              final

  public org.sireum.Z toZ16(long);
    descriptor: (J)Lorg/sireum/Z;
    flags: (0x0001) ACC_PUBLIC
    Code:
      stack=3, locals=3, args_size=2
         0: getstatic     #22                 // Field org/sireum/conversions/U64_Ext$.MODULE$:Lorg/sireum/conversions/U64_Ext$;
         3: lload_1
         4: invokevirtual #36                 // Method org/sireum/conversions/U64_Ext$.toZ16:(J)Lorg/sireum/Z;
         7: areturn
      LineNumberTable:
        line 2262: 0
      LocalVariableTable:
        Start  Length  Slot  Name   Signature
            0       8     0  this   Lorg/sireum/conversions/U64$;
            0       8     1     n   J
    MethodParameters:
      Name                           Flags
      n                              final

  public org.sireum.Z toZ32(long);
    descriptor: (J)Lorg/sireum/Z;
    flags: (0x0001) ACC_PUBLIC
    Code:
      stack=3, locals=3, args_size=2
         0: getstatic     #22                 // Field org/sireum/conversions/U64_Ext$.MODULE$:Lorg/sireum/conversions/U64_Ext$;
         3: lload_1
         4: invokevirtual #39                 // Method org/sireum/conversions/U64_Ext$.toZ32:(J)Lorg/sireum/Z;
         7: areturn
      LineNumberTable:
        line 2266: 0
      LocalVariableTable:
        Start  Length  Slot  Name   Signature
            0       8     0  this   Lorg/sireum/conversions/U64$;
            0       8     1     n   J
    MethodParameters:
      Name                           Flags
      n                              final

  public org.sireum.Z toZ64(long);
    descriptor: (J)Lorg/sireum/Z;
    flags: (0x0001) ACC_PUBLIC
    Code:
      stack=3, locals=3, args_size=2
         0: getstatic     #22                 // Field org/sireum/conversions/U64_Ext$.MODULE$:Lorg/sireum/conversions/U64_Ext$;
         3: lload_1
         4: invokevirtual #42                 // Method org/sireum/conversions/U64_Ext$.toZ64:(J)Lorg/sireum/Z;
         7: areturn
      LineNumberTable:
        line 2270: 0
      LocalVariableTable:
        Start  Length  Slot  Name   Signature
            0       8     0  this   Lorg/sireum/conversions/U64$;
            0       8     1     n   J
    MethodParameters:
      Name                           Flags
      n                              final

  public org.sireum.Z toN(long);
    descriptor: (J)Lorg/sireum/Z;
    flags: (0x0001) ACC_PUBLIC
    Code:
      stack=3, locals=3, args_size=2
         0: getstatic     #22                 // Field org/sireum/conversions/U64_Ext$.MODULE$:Lorg/sireum/conversions/U64_Ext$;
         3: lload_1
         4: invokevirtual #45                 // Method org/sireum/conversions/U64_Ext$.toN:(J)Lorg/sireum/Z;
         7: areturn
      LineNumberTable:
        line 2274: 0
      LocalVariableTable:
        Start  Length  Slot  Name   Signature
            0       8     0  this   Lorg/sireum/conversions/U64$;
            0       8     1     n   J
    MethodParameters:
      Name                           Flags
      n                              final

  public org.sireum.Z toN8(long);
    descriptor: (J)Lorg/sireum/Z;
    flags: (0x0001) ACC_PUBLIC
    Code:
      stack=3, locals=3, args_size=2
         0: getstatic     #22                 // Field org/sireum/conversions/U64_Ext$.MODULE$:Lorg/sireum/conversions/U64_Ext$;
         3: lload_1
         4: invokevirtual #48                 // Method org/sireum/conversions/U64_Ext$.toN8:(J)Lorg/sireum/Z;
         7: areturn
      LineNumberTable:
        line 2340: 0
      LocalVariableTable:
        Start  Length  Slot  Name   Signature
            0       8     0  this   Lorg/sireum/conversions/U64$;
            0       8     1     n   J
    MethodParameters:
      Name                           Flags
      n                              final

  public org.sireum.Z toN16(long);
    descriptor: (J)Lorg/sireum/Z;
    flags: (0x0001) ACC_PUBLIC
    Code:
      stack=3, locals=3, args_size=2
         0: getstatic     #22                 // Field org/sireum/conversions/U64_Ext$.MODULE$:Lorg/sireum/conversions/U64_Ext$;
         3: lload_1
         4: invokevirtual #51                 // Method org/sireum/conversions/U64_Ext$.toN16:(J)Lorg/sireum/Z;
         7: areturn
      LineNumberTable:
        line 2344: 0
      LocalVariableTable:
        Start  Length  Slot  Name   Signature
            0       8     0  this   Lorg/sireum/conversions/U64$;
            0       8     1     n   J
    MethodParameters:
      Name                           Flags
      n                              final

  public org.sireum.Z toN32(long);
    descriptor: (J)Lorg/sireum/Z;
    flags: (0x0001) ACC_PUBLIC
    Code:
      stack=3, locals=3, args_size=2
         0: getstatic     #22                 // Field org/sireum/conversions/U64_Ext$.MODULE$:Lorg/sireum/conversions/U64_Ext$;
         3: lload_1
         4: invokevirtual #54                 // Method org/sireum/conversions/U64_Ext$.toN32:(J)Lorg/sireum/Z;
         7: areturn
      LineNumberTable:
        line 2348: 0
      LocalVariableTable:
        Start  Length  Slot  Name   Signature
            0       8     0  this   Lorg/sireum/conversions/U64$;
            0       8     1     n   J
    MethodParameters:
      Name                           Flags
      n                              final

  public org.sireum.Z toN64(long);
    descriptor: (J)Lorg/sireum/Z;
    flags: (0x0001) ACC_PUBLIC
    Code:
      stack=3, locals=3, args_size=2
         0: getstatic     #22                 // Field org/sireum/conversions/U64_Ext$.MODULE$:Lorg/sireum/conversions/U64_Ext$;
         3: lload_1
         4: invokevirtual #57                 // Method org/sireum/conversions/U64_Ext$.toN64:(J)Lorg/sireum/Z;
         7: areturn
      LineNumberTable:
        line 2352: 0
      LocalVariableTable:
        Start  Length  Slot  Name   Signature
            0       8     0  this   Lorg/sireum/conversions/U64$;
            0       8     1     n   J
    MethodParameters:
      Name                           Flags
      n                              final

  public byte toS8(long);
    descriptor: (J)B
    flags: (0x0001) ACC_PUBLIC
    Code:
      stack=3, locals=3, args_size=2
         0: getstatic     #22                 // Field org/sireum/conversions/U64_Ext$.MODULE$:Lorg/sireum/conversions/U64_Ext$;
         3: lload_1
         4: invokevirtual #61                 // Method org/sireum/conversions/U64_Ext$.toS8:(J)B
         7: ireturn
      LineNumberTable:
        line 2356: 0
      LocalVariableTable:
        Start  Length  Slot  Name   Signature
            0       8     0  this   Lorg/sireum/conversions/U64$;
            0       8     1     n   J
    MethodParameters:
      Name                           Flags
      n                              final

  public short toS16(long);
    descriptor: (J)S
    flags: (0x0001) ACC_PUBLIC
    Code:
      stack=3, locals=3, args_size=2
         0: getstatic     #22                 // Field org/sireum/conversions/U64_Ext$.MODULE$:Lorg/sireum/conversions/U64_Ext$;
         3: lload_1
         4: invokevirtual #65                 // Method org/sireum/conversions/U64_Ext$.toS16:(J)S
         7: ireturn
      LineNumberTable:
        line 2360: 0
      LocalVariableTable:
        Start  Length  Slot  Name   Signature
            0       8     0  this   Lorg/sireum/conversions/U64$;
            0       8     1     n   J
    MethodParameters:
      Name                           Flags
      n                              final

  public int toS32(long);
    descriptor: (J)I
    flags: (0x0001) ACC_PUBLIC
    Code:
      stack=3, locals=3, args_size=2
         0: getstatic     #22                 // Field org/sireum/conversions/U64_Ext$.MODULE$:Lorg/sireum/conversions/U64_Ext$;
         3: lload_1
         4: invokevirtual #69                 // Method org/sireum/conversions/U64_Ext$.toS32:(J)I
         7: ireturn
      LineNumberTable:
        line 2364: 0
      LocalVariableTable:
        Start  Length  Slot  Name   Signature
            0       8     0  this   Lorg/sireum/conversions/U64$;
            0       8     1     n   J
    MethodParameters:
      Name                           Flags
      n                              final

  public long toS64(long);
    descriptor: (J)J
    flags: (0x0001) ACC_PUBLIC
    Code:
      stack=3, locals=3, args_size=2
         0: getstatic     #22                 // Field org/sireum/conversions/U64_Ext$.MODULE$:Lorg/sireum/conversions/U64_Ext$;
         3: lload_1
         4: invokevirtual #73                 // Method org/sireum/conversions/U64_Ext$.toS64:(J)J
         7: lreturn
      LineNumberTable:
        line 2368: 0
      LocalVariableTable:
        Start  Length  Slot  Name   Signature
            0       8     0  this   Lorg/sireum/conversions/U64$;
            0       8     1     n   J
    MethodParameters:
      Name                           Flags
      n                              final

  public long toRawS64(long);
    descriptor: (J)J
    flags: (0x0001) ACC_PUBLIC
    Code:
      stack=3, locals=3, args_size=2
         0: getstatic     #22                 // Field org/sireum/conversions/U64_Ext$.MODULE$:Lorg/sireum/conversions/U64_Ext$;
         3: lload_1
         4: invokevirtual #76                 // Method org/sireum/conversions/U64_Ext$.toRawS64:(J)J
         7: lreturn
      LineNumberTable:
        line 2372: 0
      LocalVariableTable:
        Start  Length  Slot  Name   Signature
            0       8     0  this   Lorg/sireum/conversions/U64$;
            0       8     1     n   J
    MethodParameters:
      Name                           Flags
      n                              final

  public byte toU8(long);
    descriptor: (J)B
    flags: (0x0001) ACC_PUBLIC
    Code:
      stack=3, locals=3, args_size=2
         0: getstatic     #22                 // Field org/sireum/conversions/U64_Ext$.MODULE$:Lorg/sireum/conversions/U64_Ext$;
         3: lload_1
         4: invokevirtual #79                 // Method org/sireum/conversions/U64_Ext$.toU8:(J)B
         7: ireturn
      LineNumberTable:
        line 2375: 0
      LocalVariableTable:
        Start  Length  Slot  Name   Signature
            0       8     0  this   Lorg/sireum/conversions/U64$;
            0       8     1     n   J
    MethodParameters:
      Name                           Flags
      n                              final

  public short toU16(long);
    descriptor: (J)S
    flags: (0x0001) ACC_PUBLIC
    Code:
      stack=3, locals=3, args_size=2
         0: getstatic     #22                 // Field org/sireum/conversions/U64_Ext$.MODULE$:Lorg/sireum/conversions/U64_Ext$;
         3: lload_1
         4: invokevirtual #82                 // Method org/sireum/conversions/U64_Ext$.toU16:(J)S
         7: ireturn
      LineNumberTable:
        line 2379: 0
      LocalVariableTable:
        Start  Length  Slot  Name   Signature
            0       8     0  this   Lorg/sireum/conversions/U64$;
            0       8     1     n   J
    MethodParameters:
      Name                           Flags
      n                              final

  public int toU32(long);
    descriptor: (J)I
    flags: (0x0001) ACC_PUBLIC
    Code:
      stack=3, locals=3, args_size=2
         0: getstatic     #22                 // Field org/sireum/conversions/U64_Ext$.MODULE$:Lorg/sireum/conversions/U64_Ext$;
         3: lload_1
         4: invokevirtual #85                 // Method org/sireum/conversions/U64_Ext$.toU32:(J)I
         7: ireturn
      LineNumberTable:
        line 2383: 0
      LocalVariableTable:
        Start  Length  Slot  Name   Signature
            0       8     0  this   Lorg/sireum/conversions/U64$;
            0       8     1     n   J
    MethodParameters:
      Name                           Flags
      n                              final

  public long toU33(long);
    descriptor: (J)J
    flags: (0x0001) ACC_PUBLIC
    Code:
      stack=3, locals=3, args_size=2
         0: getstatic     #22                 // Field org/sireum/conversions/U64_Ext$.MODULE$:Lorg/sireum/conversions/U64_Ext$;
         3: lload_1
         4: invokevirtual #88                 // Method org/sireum/conversions/U64_Ext$.toU33:(J)J
         7: lreturn
      LineNumberTable:
        line 2386: 0
      LocalVariableTable:
        Start  Length  Slot  Name   Signature
            0       8     0  this   Lorg/sireum/conversions/U64$;
            0       8     1     n   J
    MethodParameters:
      Name                           Flags
      n                              final

  public long toU34(long);
    descriptor: (J)J
    flags: (0x0001) ACC_PUBLIC
    Code:
      stack=3, locals=3, args_size=2
         0: getstatic     #22                 // Field org/sireum/conversions/U64_Ext$.MODULE$:Lorg/sireum/conversions/U64_Ext$;
         3: lload_1
         4: invokevirtual #91                 // Method org/sireum/conversions/U64_Ext$.toU34:(J)J
         7: lreturn
      LineNumberTable:
        line 2388: 0
      LocalVariableTable:
        Start  Length  Slot  Name   Signature
            0       8     0  this   Lorg/sireum/conversions/U64$;
            0       8     1     n   J
    MethodParameters:
      Name                           Flags
      n                              final

  public long toU35(long);
    descriptor: (J)J
    flags: (0x0001) ACC_PUBLIC
    Code:
      stack=3, locals=3, args_size=2
         0: getstatic     #22                 // Field org/sireum/conversions/U64_Ext$.MODULE$:Lorg/sireum/conversions/U64_Ext$;
         3: lload_1
         4: invokevirtual #94                 // Method org/sireum/conversions/U64_Ext$.toU35:(J)J
         7: lreturn
      LineNumberTable:
        line 2390: 0
      LocalVariableTable:
        Start  Length  Slot  Name   Signature
            0       8     0  this   Lorg/sireum/conversions/U64$;
            0       8     1     n   J
    MethodParameters:
      Name                           Flags
      n                              final

  public long toU36(long);
    descriptor: (J)J
    flags: (0x0001) ACC_PUBLIC
    Code:
      stack=3, locals=3, args_size=2
         0: getstatic     #22                 // Field org/sireum/conversions/U64_Ext$.MODULE$:Lorg/sireum/conversions/U64_Ext$;
         3: lload_1
         4: invokevirtual #97                 // Method org/sireum/conversions/U64_Ext$.toU36:(J)J
         7: lreturn
      LineNumberTable:
        line 2392: 0
      LocalVariableTable:
        Start  Length  Slot  Name   Signature
            0       8     0  this   Lorg/sireum/conversions/U64$;
            0       8     1     n   J
    MethodParameters:
      Name                           Flags
      n                              final

  public long toU37(long);
    descriptor: (J)J
    flags: (0x0001) ACC_PUBLIC
    Code:
      stack=3, locals=3, args_size=2
         0: getstatic     #22                 // Field org/sireum/conversions/U64_Ext$.MODULE$:Lorg/sireum/conversions/U64_Ext$;
         3: lload_1
         4: invokevirtual #100                // Method org/sireum/conversions/U64_Ext$.toU37:(J)J
         7: lreturn
      LineNumberTable:
        line 2394: 0
      LocalVariableTable:
        Start  Length  Slot  Name   Signature
            0       8     0  this   Lorg/sireum/conversions/U64$;
            0       8     1     n   J
    MethodParameters:
      Name                           Flags
      n                              final

  public long toU38(long);
    descriptor: (J)J
    flags: (0x0001) ACC_PUBLIC
    Code:
      stack=3, locals=3, args_size=2
         0: getstatic     #22                 // Field org/sireum/conversions/U64_Ext$.MODULE$:Lorg/sireum/conversions/U64_Ext$;
         3: lload_1
         4: invokevirtual #103                // Method org/sireum/conversions/U64_Ext$.toU38:(J)J
         7: lreturn
      LineNumberTable:
        line 2396: 0
      LocalVariableTable:
        Start  Length  Slot  Name   Signature
            0       8     0  this   Lorg/sireum/conversions/U64$;
            0       8     1     n   J
    MethodParameters:
      Name                           Flags
      n                              final

  public long toU39(long);
    descriptor: (J)J
    flags: (0x0001) ACC_PUBLIC
    Code:
      stack=3, locals=3, args_size=2
         0: getstatic     #22                 // Field org/sireum/conversions/U64_Ext$.MODULE$:Lorg/sireum/conversions/U64_Ext$;
         3: lload_1
         4: invokevirtual #106                // Method org/sireum/conversions/U64_Ext$.toU39:(J)J
         7: lreturn
      LineNumberTable:
        line 2398: 0
      LocalVariableTable:
        Start  Length  Slot  Name   Signature
            0       8     0  this   Lorg/sireum/conversions/U64$;
            0       8     1     n   J
    MethodParameters:
      Name                           Flags
      n                              final

  public long toU40(long);
    descriptor: (J)J
    flags: (0x0001) ACC_PUBLIC
    Code:
      stack=3, locals=3, args_size=2
         0: getstatic     #22                 // Field org/sireum/conversions/U64_Ext$.MODULE$:Lorg/sireum/conversions/U64_Ext$;
         3: lload_1
         4: invokevirtual #109                // Method org/sireum/conversions/U64_Ext$.toU40:(J)J
         7: lreturn
      LineNumberTable:
        line 2400: 0
      LocalVariableTable:
        Start  Length  Slot  Name   Signature
            0       8     0  this   Lorg/sireum/conversions/U64$;
            0       8     1     n   J
    MethodParameters:
      Name                           Flags
      n                              final

  public long toU41(long);
    descriptor: (J)J
    flags: (0x0001) ACC_PUBLIC
    Code:
      stack=3, locals=3, args_size=2
         0: getstatic     #22                 // Field org/sireum/conversions/U64_Ext$.MODULE$:Lorg/sireum/conversions/U64_Ext$;
         3: lload_1
         4: invokevirtual #112                // Method org/sireum/conversions/U64_Ext$.toU41:(J)J
         7: lreturn
      LineNumberTable:
        line 2402: 0
      LocalVariableTable:
        Start  Length  Slot  Name   Signature
            0       8     0  this   Lorg/sireum/conversions/U64$;
            0       8     1     n   J
    MethodParameters:
      Name                           Flags
      n                              final

  public long toU42(long);
    descriptor: (J)J
    flags: (0x0001) ACC_PUBLIC
    Code:
      stack=3, locals=3, args_size=2
         0: getstatic     #22                 // Field org/sireum/conversions/U64_Ext$.MODULE$:Lorg/sireum/conversions/U64_Ext$;
         3: lload_1
         4: invokevirtual #115                // Method org/sireum/conversions/U64_Ext$.toU42:(J)J
         7: lreturn
      LineNumberTable:
        line 2404: 0
      LocalVariableTable:
        Start  Length  Slot  Name   Signature
            0       8     0  this   Lorg/sireum/conversions/U64$;
            0       8     1     n   J
    MethodParameters:
      Name                           Flags
      n                              final

  public long toU43(long);
    descriptor: (J)J
    flags: (0x0001) ACC_PUBLIC
    Code:
      stack=3, locals=3, args_size=2
         0: getstatic     #22                 // Field org/sireum/conversions/U64_Ext$.MODULE$:Lorg/sireum/conversions/U64_Ext$;
         3: lload_1
         4: invokevirtual #118                // Method org/sireum/conversions/U64_Ext$.toU43:(J)J
         7: lreturn
      LineNumberTable:
        line 2406: 0
      LocalVariableTable:
        Start  Length  Slot  Name   Signature
            0       8     0  this   Lorg/sireum/conversions/U64$;
            0       8     1     n   J
    MethodParameters:
      Name                           Flags
      n                              final

  public long toU44(long);
    descriptor: (J)J
    flags: (0x0001) ACC_PUBLIC
    Code:
      stack=3, locals=3, args_size=2
         0: getstatic     #22                 // Field org/sireum/conversions/U64_Ext$.MODULE$:Lorg/sireum/conversions/U64_Ext$;
         3: lload_1
         4: invokevirtual #121                // Method org/sireum/conversions/U64_Ext$.toU44:(J)J
         7: lreturn
      LineNumberTable:
        line 2408: 0
      LocalVariableTable:
        Start  Length  Slot  Name   Signature
            0       8     0  this   Lorg/sireum/conversions/U64$;
            0       8     1     n   J
    MethodParameters:
      Name                           Flags
      n                              final

  public long toU45(long);
    descriptor: (J)J
    flags: (0x0001) ACC_PUBLIC
    Code:
      stack=3, locals=3, args_size=2
         0: getstatic     #22                 // Field org/sireum/conversions/U64_Ext$.MODULE$:Lorg/sireum/conversions/U64_Ext$;
         3: lload_1
         4: invokevirtual #124                // Method org/sireum/conversions/U64_Ext$.toU45:(J)J
         7: lreturn
      LineNumberTable:
        line 2410: 0
      LocalVariableTable:
        Start  Length  Slot  Name   Signature
            0       8     0  this   Lorg/sireum/conversions/U64$;
            0       8     1     n   J
    MethodParameters:
      Name                           Flags
      n                              final

  public long toU46(long);
    descriptor: (J)J
    flags: (0x0001) ACC_PUBLIC
    Code:
      stack=3, locals=3, args_size=2
         0: getstatic     #22                 // Field org/sireum/conversions/U64_Ext$.MODULE$:Lorg/sireum/conversions/U64_Ext$;
         3: lload_1
         4: invokevirtual #127                // Method org/sireum/conversions/U64_Ext$.toU46:(J)J
         7: lreturn
      LineNumberTable:
        line 2412: 0
      LocalVariableTable:
        Start  Length  Slot  Name   Signature
            0       8     0  this   Lorg/sireum/conversions/U64$;
            0       8     1     n   J
    MethodParameters:
      Name                           Flags
      n                              final

  public long toU47(long);
    descriptor: (J)J
    flags: (0x0001) ACC_PUBLIC
    Code:
      stack=3, locals=3, args_size=2
         0: getstatic     #22                 // Field org/sireum/conversions/U64_Ext$.MODULE$:Lorg/sireum/conversions/U64_Ext$;
         3: lload_1
         4: invokevirtual #130                // Method org/sireum/conversions/U64_Ext$.toU47:(J)J
         7: lreturn
      LineNumberTable:
        line 2414: 0
      LocalVariableTable:
        Start  Length  Slot  Name   Signature
            0       8     0  this   Lorg/sireum/conversions/U64$;
            0       8     1     n   J
    MethodParameters:
      Name                           Flags
      n                              final

  public long toU48(long);
    descriptor: (J)J
    flags: (0x0001) ACC_PUBLIC
    Code:
      stack=3, locals=3, args_size=2
         0: getstatic     #22                 // Field org/sireum/conversions/U64_Ext$.MODULE$:Lorg/sireum/conversions/U64_Ext$;
         3: lload_1
         4: invokevirtual #133                // Method org/sireum/conversions/U64_Ext$.toU48:(J)J
         7: lreturn
      LineNumberTable:
        line 2416: 0
      LocalVariableTable:
        Start  Length  Slot  Name   Signature
            0       8     0  this   Lorg/sireum/conversions/U64$;
            0       8     1     n   J
    MethodParameters:
      Name                           Flags
      n                              final

  public long toU49(long);
    descriptor: (J)J
    flags: (0x0001) ACC_PUBLIC
    Code:
      stack=3, locals=3, args_size=2
         0: getstatic     #22                 // Field org/sireum/conversions/U64_Ext$.MODULE$:Lorg/sireum/conversions/U64_Ext$;
         3: lload_1
         4: invokevirtual #136                // Method org/sireum/conversions/U64_Ext$.toU49:(J)J
         7: lreturn
      LineNumberTable:
        line 2418: 0
      LocalVariableTable:
        Start  Length  Slot  Name   Signature
            0       8     0  this   Lorg/sireum/conversions/U64$;
            0       8     1     n   J
    MethodParameters:
      Name                           Flags
      n                              final

  public long toU50(long);
    descriptor: (J)J
    flags: (0x0001) ACC_PUBLIC
    Code:
      stack=3, locals=3, args_size=2
         0: getstatic     #22                 // Field org/sireum/conversions/U64_Ext$.MODULE$:Lorg/sireum/conversions/U64_Ext$;
         3: lload_1
         4: invokevirtual #139                // Method org/sireum/conversions/U64_Ext$.toU50:(J)J
         7: lreturn
      LineNumberTable:
        line 2420: 0
      LocalVariableTable:
        Start  Length  Slot  Name   Signature
            0       8     0  this   Lorg/sireum/conversions/U64$;
            0       8     1     n   J
    MethodParameters:
      Name                           Flags
      n                              final

  public long toU51(long);
    descriptor: (J)J
    flags: (0x0001) ACC_PUBLIC
    Code:
      stack=3, locals=3, args_size=2
         0: getstatic     #22                 // Field org/sireum/conversions/U64_Ext$.MODULE$:Lorg/sireum/conversions/U64_Ext$;
         3: lload_1
         4: invokevirtual #142                // Method org/sireum/conversions/U64_Ext$.toU51:(J)J
         7: lreturn
      LineNumberTable:
        line 2422: 0
      LocalVariableTable:
        Start  Length  Slot  Name   Signature
            0       8     0  this   Lorg/sireum/conversions/U64$;
            0       8     1     n   J
    MethodParameters:
      Name                           Flags
      n                              final

  public long toU52(long);
    descriptor: (J)J
    flags: (0x0001) ACC_PUBLIC
    Code:
      stack=3, locals=3, args_size=2
         0: getstatic     #22                 // Field org/sireum/conversions/U64_Ext$.MODULE$:Lorg/sireum/conversions/U64_Ext$;
         3: lload_1
         4: invokevirtual #145                // Method org/sireum/conversions/U64_Ext$.toU52:(J)J
         7: lreturn
      LineNumberTable:
        line 2424: 0
      LocalVariableTable:
        Start  Length  Slot  Name   Signature
            0       8     0  this   Lorg/sireum/conversions/U64$;
            0       8     1     n   J
    MethodParameters:
      Name                           Flags
      n                              final

  public long toU53(long);
    descriptor: (J)J
    flags: (0x0001) ACC_PUBLIC
    Code:
      stack=3, locals=3, args_size=2
         0: getstatic     #22                 // Field org/sireum/conversions/U64_Ext$.MODULE$:Lorg/sireum/conversions/U64_Ext$;
         3: lload_1
         4: invokevirtual #148                // Method org/sireum/conversions/U64_Ext$.toU53:(J)J
         7: lreturn
      LineNumberTable:
        line 2426: 0
      LocalVariableTable:
        Start  Length  Slot  Name   Signature
            0       8     0  this   Lorg/sireum/conversions/U64$;
            0       8     1     n   J
    MethodParameters:
      Name                           Flags
      n                              final

  public long toU54(long);
    descriptor: (J)J
    flags: (0x0001) ACC_PUBLIC
    Code:
      stack=3, locals=3, args_size=2
         0: getstatic     #22                 // Field org/sireum/conversions/U64_Ext$.MODULE$:Lorg/sireum/conversions/U64_Ext$;
         3: lload_1
         4: invokevirtual #151                // Method org/sireum/conversions/U64_Ext$.toU54:(J)J
         7: lreturn
      LineNumberTable:
        line 2428: 0
      LocalVariableTable:
        Start  Length  Slot  Name   Signature
            0       8     0  this   Lorg/sireum/conversions/U64$;
            0       8     1     n   J
    MethodParameters:
      Name                           Flags
      n                              final

  public long toU55(long);
    descriptor: (J)J
    flags: (0x0001) ACC_PUBLIC
    Code:
      stack=3, locals=3, args_size=2
         0: getstatic     #22                 // Field org/sireum/conversions/U64_Ext$.MODULE$:Lorg/sireum/conversions/U64_Ext$;
         3: lload_1
         4: invokevirtual #154                // Method org/sireum/conversions/U64_Ext$.toU55:(J)J
         7: lreturn
      LineNumberTable:
        line 2430: 0
      LocalVariableTable:
        Start  Length  Slot  Name   Signature
            0       8     0  this   Lorg/sireum/conversions/U64$;
            0       8     1     n   J
    MethodParameters:
      Name                           Flags
      n                              final

  public long toU56(long);
    descriptor: (J)J
    flags: (0x0001) ACC_PUBLIC
    Code:
      stack=3, locals=3, args_size=2
         0: getstatic     #22                 // Field org/sireum/conversions/U64_Ext$.MODULE$:Lorg/sireum/conversions/U64_Ext$;
         3: lload_1
         4: invokevirtual #157                // Method org/sireum/conversions/U64_Ext$.toU56:(J)J
         7: lreturn
      LineNumberTable:
        line 2432: 0
      LocalVariableTable:
        Start  Length  Slot  Name   Signature
            0       8     0  this   Lorg/sireum/conversions/U64$;
            0       8     1     n   J
    MethodParameters:
      Name                           Flags
      n                              final

  public long toU57(long);
    descriptor: (J)J
    flags: (0x0001) ACC_PUBLIC
    Code:
      stack=3, locals=3, args_size=2
         0: getstatic     #22                 // Field org/sireum/conversions/U64_Ext$.MODULE$:Lorg/sireum/conversions/U64_Ext$;
         3: lload_1
         4: invokevirtual #160                // Method org/sireum/conversions/U64_Ext$.toU57:(J)J
         7: lreturn
      LineNumberTable:
        line 2434: 0
      LocalVariableTable:
        Start  Length  Slot  Name   Signature
            0       8     0  this   Lorg/sireum/conversions/U64$;
            0       8     1     n   J
    MethodParameters:
      Name                           Flags
      n                              final

  public long toU58(long);
    descriptor: (J)J
    flags: (0x0001) ACC_PUBLIC
    Code:
      stack=3, locals=3, args_size=2
         0: getstatic     #22                 // Field org/sireum/conversions/U64_Ext$.MODULE$:Lorg/sireum/conversions/U64_Ext$;
         3: lload_1
         4: invokevirtual #163                // Method org/sireum/conversions/U64_Ext$.toU58:(J)J
         7: lreturn
      LineNumberTable:
        line 2436: 0
      LocalVariableTable:
        Start  Length  Slot  Name   Signature
            0       8     0  this   Lorg/sireum/conversions/U64$;
            0       8     1     n   J
    MethodParameters:
      Name                           Flags
      n                              final

  public long toU59(long);
    descriptor: (J)J
    flags: (0x0001) ACC_PUBLIC
    Code:
      stack=3, locals=3, args_size=2
         0: getstatic     #22                 // Field org/sireum/conversions/U64_Ext$.MODULE$:Lorg/sireum/conversions/U64_Ext$;
         3: lload_1
         4: invokevirtual #166                // Method org/sireum/conversions/U64_Ext$.toU59:(J)J
         7: lreturn
      LineNumberTable:
        line 2438: 0
      LocalVariableTable:
        Start  Length  Slot  Name   Signature
            0       8     0  this   Lorg/sireum/conversions/U64$;
            0       8     1     n   J
    MethodParameters:
      Name                           Flags
      n                              final

  public long toU60(long);
    descriptor: (J)J
    flags: (0x0001) ACC_PUBLIC
    Code:
      stack=3, locals=3, args_size=2
         0: getstatic     #22                 // Field org/sireum/conversions/U64_Ext$.MODULE$:Lorg/sireum/conversions/U64_Ext$;
         3: lload_1
         4: invokevirtual #169                // Method org/sireum/conversions/U64_Ext$.toU60:(J)J
         7: lreturn
      LineNumberTable:
        line 2440: 0
      LocalVariableTable:
        Start  Length  Slot  Name   Signature
            0       8     0  this   Lorg/sireum/conversions/U64$;
            0       8     1     n   J
    MethodParameters:
      Name                           Flags
      n                              final

  public long toU61(long);
    descriptor: (J)J
    flags: (0x0001) ACC_PUBLIC
    Code:
      stack=3, locals=3, args_size=2
         0: getstatic     #22                 // Field org/sireum/conversions/U64_Ext$.MODULE$:Lorg/sireum/conversions/U64_Ext$;
         3: lload_1
         4: invokevirtual #172                // Method org/sireum/conversions/U64_Ext$.toU61:(J)J
         7: lreturn
      LineNumberTable:
        line 2442: 0
      LocalVariableTable:
        Start  Length  Slot  Name   Signature
            0       8     0  this   Lorg/sireum/conversions/U64$;
            0       8     1     n   J
    MethodParameters:
      Name                           Flags
      n                              final

  public long toU62(long);
    descriptor: (J)J
    flags: (0x0001) ACC_PUBLIC
    Code:
      stack=3, locals=3, args_size=2
         0: getstatic     #22                 // Field org/sireum/conversions/U64_Ext$.MODULE$:Lorg/sireum/conversions/U64_Ext$;
         3: lload_1
         4: invokevirtual #175                // Method org/sireum/conversions/U64_Ext$.toU62:(J)J
         7: lreturn
      LineNumberTable:
        line 2444: 0
      LocalVariableTable:
        Start  Length  Slot  Name   Signature
            0       8     0  this   Lorg/sireum/conversions/U64$;
            0       8     1     n   J
    MethodParameters:
      Name                           Flags
      n                              final

  public long toU63(long);
    descriptor: (J)J
    flags: (0x0001) ACC_PUBLIC
    Code:
      stack=3, locals=3, args_size=2
         0: getstatic     #22                 // Field org/sireum/conversions/U64_Ext$.MODULE$:Lorg/sireum/conversions/U64_Ext$;
         3: lload_1
         4: invokevirtual #178                // Method org/sireum/conversions/U64_Ext$.toU63:(J)J
         7: lreturn
      LineNumberTable:
        line 2446: 0
      LocalVariableTable:
        Start  Length  Slot  Name   Signature
            0       8     0  this   Lorg/sireum/conversions/U64$;
            0       8     1     n   J
    MethodParameters:
      Name                           Flags
      n                              final

  public long toU64(long);
    descriptor: (J)J
    flags: (0x0001) ACC_PUBLIC
    Code:
      stack=3, locals=3, args_size=2
         0: getstatic     #22                 // Field org/sireum/conversions/U64_Ext$.MODULE$:Lorg/sireum/conversions/U64_Ext$;
         3: lload_1
         4: invokevirtual #181                // Method org/sireum/conversions/U64_Ext$.toU64:(J)J
         7: lreturn
      LineNumberTable:
        line 2449: 0
      LocalVariableTable:
        Start  Length  Slot  Name   Signature
            0       8     0  this   Lorg/sireum/conversions/U64$;
            0       8     1     n   J
    MethodParameters:
      Name                           Flags
      n                              final

  public double toRawF64(long);
    descriptor: (J)D
    flags: (0x0001) ACC_PUBLIC
    Code:
      stack=3, locals=3, args_size=2
         0: getstatic     #22                 // Field org/sireum/conversions/U64_Ext$.MODULE$:Lorg/sireum/conversions/U64_Ext$;
         3: lload_1
         4: invokevirtual #185                // Method org/sireum/conversions/U64_Ext$.toRawF64:(J)D
         7: dreturn
      LineNumberTable:
        line 2453: 0
      LocalVariableTable:
        Start  Length  Slot  Name   Signature
            0       8     0  this   Lorg/sireum/conversions/U64$;
            0       8     1     n   J
    MethodParameters:
      Name                           Flags
      n                              final

  private org.sireum.conversions.U64$();
    descriptor: ()V
    flags: (0x0002) ACC_PRIVATE
    Code:
      stack=1, locals=1, args_size=1
         0: aload_0
         1: invokespecial #186                // Method java/lang/Object."<init>":()V
         4: return
      LineNumberTable:
        line 2187: 0
      LocalVariableTable:
        Start  Length  Slot  Name   Signature
            0       5     0  this   Lorg/sireum/conversions/U64$;
}
SourceFile: "conversions.scala"
  ScalaInlineInfo: length = 0x10D (unknown attribute)
   01 01 00 35 00 0A 00 09 01 00 0F 00 10 01 00 2B
   00 1C 01 00 31 00 1C 01 00 34 00 1C 01 00 37 00
   1C 01 00 2E 00 1C 01 00 B6 00 B7 01 00 4A 00 47
   01 00 3E 00 3F 01 00 42 00 43 01 00 46 00 47 01
   00 3A 00 3B 01 00 50 00 3F 01 00 53 00 43 01 00
   56 00 47 01 00 59 00 47 01 00 5C 00 47 01 00 5F
   00 47 01 00 62 00 47 01 00 65 00 47 01 00 68 00
   47 01 00 6B 00 47 01 00 6E 00 47 01 00 71 00 47
   01 00 74 00 47 01 00 77 00 47 01 00 7A 00 47 01
   00 7D 00 47 01 00 80 00 47 01 00 83 00 47 01 00
   86 00 47 01 00 89 00 47 01 00 8C 00 47 01 00 8F
   00 47 01 00 92 00 47 01 00 95 00 47 01 00 98 00
   47 01 00 9B 00 47 01 00 9E 00 47 01 00 A1 00 47
   01 00 A4 00 47 01 00 A7 00 47 01 00 AA 00 47 01
   00 AD 00 47 01 00 B0 00 47 01 00 B3 00 47 01 00
   4D 00 3B 01 00 1B 00 1C 01 00 22 00 1C 01 00 25
   00 1C 01 00 28 00 1C 01 00 1F 00 1C 01
  Scala: length = 0x0 (unknown attribute)

