Classfile /Users/mw/Projects/slang-braindump/.jar/jar11/assemble/slang-braindump/assemble/content/org/sireum/conversions/U9.class
  Last modified May 29, 2022; size 1079 bytes
  SHA-256 checksum 25e5b5f873d77e76a955f31805f8c8a1361b4cb4ee46d651dfc67bfcb6744659
  Compiled from "conversions.scala"
public final class org.sireum.conversions.U9
  minor version: 0
  major version: 52
  flags: (0x0031) ACC_PUBLIC, ACC_FINAL, ACC_SUPER
  this_class: #2                          // org/sireum/conversions/U9
  super_class: #4                         // java/lang/Object
  interfaces: 0, fields: 0, methods: 3, attributes: 3
Constant pool:
   #1 = Utf8               org/sireum/conversions/U9
   #2 = Class              #1             // org/sireum/conversions/U9
   #3 = Utf8               java/lang/Object
   #4 = Class              #3             // java/lang/Object
   #5 = Utf8               conversions.scala
   #6 = Utf8               Lscala/reflect/ScalaSignature;
   #7 = Utf8               bytes
   #8 = Utf8               \u0006\u0005!;QAB\u0004\t\u000291Q\u0001E\u0004\t\u0002EAQ\u0001G\u0001\u0005\u0002eAQAG\u0001\u0005\u0002mAQ\u0001K\u0001\u0005\u0002%BQaL\u0001\u0005\u0002A\n!!V\u001d\u000b\u0005!I\u0011aC2p]Z,\'o]5p]NT!AC\u0006\u0002\rML\'/Z;n\u0015\u0005a\u0011aA8sO\u000e\u0001\u0001CA\b\u0002\u001b\u00059!AA+:\'\t\t!\u0003\u0005\u0002\u0014-5\tACC\u0001\u0016\u0003\u0015\u00198-\u00197b\u0013\t9BC\u0001\u0004B]f\u0014VMZ\u0001\u0007y%t\u0017\u000e\u001e \u0015\u00039\tQ\u0001^8VcY\"\"\u0001\b\u0011\u0011\u0005uqR\"A\u0005\n\u0005}I!aA+2m!)\u0011e\u0001a\u0001E\u0005\ta\u000e\u0005\u0002\u001eG%\u0011\u0001#\u0003\u0015\u0003\u0007\u0015\u0002\"!\b\u0014\n\u0005\u001dJ!\u0001\u00029ve\u0016\fQ\u0001^8VgI\"\"AK\u0017\u0011\u0005uY\u0013B\u0001\u0017\n\u0005\r)6G\r\u0005\u0006C\u0011\u0001\rA\t\u0015\u0003\t\u0015\nQ\u0001^8VmQ\"\"!\r\u001b\u0011\u0005u\u0011\u0014BA\u001a\n\u0005\r)f\u0007\u000e\u0005\u0006C\u0015\u0001\rA\t\u0015\u0003\u000b\u0015B3!A\u001c;!\ti\u0002(\u0003\u0002:\u0013\t\u0019Q\r\u001f;2\u000b\rZdHQ \u0011\u0005ua\u0014BA\u001f\n\u0005\u0019\u0019FO]5oO&\u0011q\bQ\u0001\u001cI1,7o]5oSR$sM]3bi\u0016\u0014H\u0005Z3gCVdG\u000fJ\u0019\u000b\u0005\u0005K\u0011aA3yiF*1e\u0011#F\u0003:\u0011Q\u0004R\u0005\u0003\u0003&\tDAI\u000f\n\r\n11/\u001b:fk6D3\u0001A\u001c;\u0001
   #9 = Utf8               toU64
  #10 = Utf8               (S)J
  #11 = Utf8               n
  #12 = Utf8               org/sireum/conversions/U9$
  #13 = Class              #12            // org/sireum/conversions/U9$
  #14 = Utf8               MODULE$
  #15 = Utf8               Lorg/sireum/conversions/U9$;
  #16 = NameAndType        #14:#15        // MODULE$:Lorg/sireum/conversions/U9$;
  #17 = Fieldref           #13.#16        // org/sireum/conversions/U9$.MODULE$:Lorg/sireum/conversions/U9$;
  #18 = NameAndType        #9:#10         // toU64:(S)J
  #19 = Methodref          #13.#18        // org/sireum/conversions/U9$.toU64:(S)J
  #20 = Utf8               S
  #21 = Utf8               toU32
  #22 = Utf8               (S)I
  #23 = NameAndType        #21:#22        // toU32:(S)I
  #24 = Methodref          #13.#23        // org/sireum/conversions/U9$.toU32:(S)I
  #25 = Utf8               toU16
  #26 = Utf8               (S)S
  #27 = NameAndType        #25:#26        // toU16:(S)S
  #28 = Methodref          #13.#27        // org/sireum/conversions/U9$.toU16:(S)S
  #29 = Utf8               Code
  #30 = Utf8               LocalVariableTable
  #31 = Utf8               MethodParameters
  #32 = Utf8               SourceFile
  #33 = Utf8               RuntimeVisibleAnnotations
  #34 = Utf8               ScalaSig
{
  public static long toU64(short);
    descriptor: (S)J
    flags: (0x0009) ACC_PUBLIC, ACC_STATIC
    Code:
      stack=2, locals=1, args_size=1
         0: getstatic     #17                 // Field org/sireum/conversions/U9$.MODULE$:Lorg/sireum/conversions/U9$;
         3: iload_0
         4: invokevirtual #19                 // Method org/sireum/conversions/U9$.toU64:(S)J
         7: lreturn
      LocalVariableTable:
        Start  Length  Slot  Name   Signature
            0       8     0     n   S
    MethodParameters:
      Name                           Flags
      n                              final

  public static int toU32(short);
    descriptor: (S)I
    flags: (0x0009) ACC_PUBLIC, ACC_STATIC
    Code:
      stack=2, locals=1, args_size=1
         0: getstatic     #17                 // Field org/sireum/conversions/U9$.MODULE$:Lorg/sireum/conversions/U9$;
         3: iload_0
         4: invokevirtual #24                 // Method org/sireum/conversions/U9$.toU32:(S)I
         7: ireturn
      LocalVariableTable:
        Start  Length  Slot  Name   Signature
            0       8     0     n   S
    MethodParameters:
      Name                           Flags
      n                              final

  public static short toU16(short);
    descriptor: (S)S
    flags: (0x0009) ACC_PUBLIC, ACC_STATIC
    Code:
      stack=2, locals=1, args_size=1
         0: getstatic     #17                 // Field org/sireum/conversions/U9$.MODULE$:Lorg/sireum/conversions/U9$;
         3: iload_0
         4: invokevirtual #28                 // Method org/sireum/conversions/U9$.toU16:(S)S
         7: ireturn
      LocalVariableTable:
        Start  Length  Slot  Name   Signature
            0       8     0     n   S
    MethodParameters:
      Name                           Flags
      n                              final
}
SourceFile: "conversions.scala"
RuntimeVisibleAnnotations:
  0: #6(#7=s#8)
    scala.reflect.ScalaSignature(
      bytes="\u0006\u0005!;QAB\u0004\t\u000291Q\u0001E\u0004\t\u0002EAQ\u0001G\u0001\u0005\u0002eAQAG\u0001\u0005\u0002mAQ\u0001K\u0001\u0005\u0002%BQaL\u0001\u0005\u0002A\n!!V\u001d\u000b\u0005!I\u0011aC2p]Z,\'o]5p]NT!AC\u0006\u0002\rML\'/Z;n\u0015\u0005a\u0011aA8sO\u000e\u0001\u0001CA\b\u0002\u001b\u00059!AA+:\'\t\t!\u0003\u0005\u0002\u0014-5\tACC\u0001\u0016\u0003\u0015\u00198-\u00197b\u0013\t9BC\u0001\u0004B]f\u0014VMZ\u0001\u0007y%t\u0017\u000e\u001e \u0015\u00039\tQ\u0001^8VcY\"\"\u0001\b\u0011\u0011\u0005uqR\"A\u0005\n\u0005}I!aA+2m!)\u0011e\u0001a\u0001E\u0005\ta\u000e\u0005\u0002\u001eG%\u0011\u0001#\u0003\u0015\u0003\u0007\u0015\u0002\"!\b\u0014\n\u0005\u001dJ!\u0001\u00029ve\u0016\fQ\u0001^8VgI\"\"AK\u0017\u0011\u0005uY\u0013B\u0001\u0017\n\u0005\r)6G\r\u0005\u0006C\u0011\u0001\rA\t\u0015\u0003\t\u0015\nQ\u0001^8VmQ\"\"!\r\u001b\u0011\u0005u\u0011\u0014BA\u001a\n\u0005\r)f\u0007\u000e\u0005\u0006C\u0015\u0001\rA\t\u0015\u0003\u000b\u0015B3!A\u001c;!\ti\u0002(\u0003\u0002:\u0013\t\u0019Q\r\u001f;2\u000b\rZdHQ \u0011\u0005ua\u0014BA\u001f\n\u0005\u0019\u0019FO]5oO&\u0011q\bQ\u0001\u001cI1,7o]5oSR$sM]3bi\u0016\u0014H\u0005Z3gCVdG\u000fJ\u0019\u000b\u0005\u0005K\u0011aA3yiF*1e\u0011#F\u0003:\u0011Q\u0004R\u0005\u0003\u0003&\tDAI\u000f\n\r\n11/\u001b:fk6D3\u0001A\u001c;\u0001"
    )
  ScalaSig: length = 0x3 (unknown attribute)
   05 02 00
