Classfile /Users/mw/Projects/slang-braindump/.jar/jar11/assemble/slang-braindump/assemble/content/org/sireum/conversions/Z$.class
  Last modified May 29, 2022; size 4309 bytes
  SHA-256 checksum f0a8a276bba420c1b67bde3a2a6788706bb97a5a7332aa94d0c2628719dfd1c0
  Compiled from "conversions.scala"
public final class org.sireum.conversions.Z$
  minor version: 0
  major version: 52
  flags: (0x0031) ACC_PUBLIC, ACC_FINAL, ACC_SUPER
  this_class: #2                          // org/sireum/conversions/Z$
  super_class: #4                         // java/lang/Object
  interfaces: 0, fields: 1, methods: 32, attributes: 3
Constant pool:
    #1 = Utf8               org/sireum/conversions/Z$
    #2 = Class              #1            // org/sireum/conversions/Z$
    #3 = Utf8               java/lang/Object
    #4 = Class              #3            // java/lang/Object
    #5 = Utf8               conversions.scala
    #6 = Utf8               MODULE$
    #7 = Utf8               Lorg/sireum/conversions/Z$;
    #8 = Utf8               <clinit>
    #9 = Utf8               ()V
   #10 = Utf8               <init>
   #11 = NameAndType        #10:#9        // "<init>":()V
   #12 = Methodref          #2.#11        // org/sireum/conversions/Z$."<init>":()V
   #13 = NameAndType        #6:#7         // MODULE$:Lorg/sireum/conversions/Z$;
   #14 = Fieldref           #2.#13        // org/sireum/conversions/Z$.MODULE$:Lorg/sireum/conversions/Z$;
   #15 = Utf8               isInRangeSigned8
   #16 = Utf8               (Lorg/sireum/Z;)Z
   #17 = Utf8               n
   #18 = Utf8               org/sireum/conversions/Z_Ext$
   #19 = Class              #18           // org/sireum/conversions/Z_Ext$
   #20 = Utf8               Lorg/sireum/conversions/Z_Ext$;
   #21 = NameAndType        #6:#20        // MODULE$:Lorg/sireum/conversions/Z_Ext$;
   #22 = Fieldref           #19.#21       // org/sireum/conversions/Z_Ext$.MODULE$:Lorg/sireum/conversions/Z_Ext$;
   #23 = NameAndType        #15:#16       // isInRangeSigned8:(Lorg/sireum/Z;)Z
   #24 = Methodref          #19.#23       // org/sireum/conversions/Z_Ext$.isInRangeSigned8:(Lorg/sireum/Z;)Z
   #25 = Utf8               this
   #26 = Utf8               Lorg/sireum/Z;
   #27 = Utf8               isInRangeSigned16
   #28 = NameAndType        #27:#16       // isInRangeSigned16:(Lorg/sireum/Z;)Z
   #29 = Methodref          #19.#28       // org/sireum/conversions/Z_Ext$.isInRangeSigned16:(Lorg/sireum/Z;)Z
   #30 = Utf8               isInRangeSigned32
   #31 = NameAndType        #30:#16       // isInRangeSigned32:(Lorg/sireum/Z;)Z
   #32 = Methodref          #19.#31       // org/sireum/conversions/Z_Ext$.isInRangeSigned32:(Lorg/sireum/Z;)Z
   #33 = Utf8               isInRangeSigned64
   #34 = NameAndType        #33:#16       // isInRangeSigned64:(Lorg/sireum/Z;)Z
   #35 = Methodref          #19.#34       // org/sireum/conversions/Z_Ext$.isInRangeSigned64:(Lorg/sireum/Z;)Z
   #36 = Utf8               isInRangeUnsigned8
   #37 = NameAndType        #36:#16       // isInRangeUnsigned8:(Lorg/sireum/Z;)Z
   #38 = Methodref          #19.#37       // org/sireum/conversions/Z_Ext$.isInRangeUnsigned8:(Lorg/sireum/Z;)Z
   #39 = Utf8               isInRangeUnsigned16
   #40 = NameAndType        #39:#16       // isInRangeUnsigned16:(Lorg/sireum/Z;)Z
   #41 = Methodref          #19.#40       // org/sireum/conversions/Z_Ext$.isInRangeUnsigned16:(Lorg/sireum/Z;)Z
   #42 = Utf8               isInRangeUnsigned32
   #43 = NameAndType        #42:#16       // isInRangeUnsigned32:(Lorg/sireum/Z;)Z
   #44 = Methodref          #19.#43       // org/sireum/conversions/Z_Ext$.isInRangeUnsigned32:(Lorg/sireum/Z;)Z
   #45 = Utf8               isInRangeUnsigned64
   #46 = NameAndType        #45:#16       // isInRangeUnsigned64:(Lorg/sireum/Z;)Z
   #47 = Methodref          #19.#46       // org/sireum/conversions/Z_Ext$.isInRangeUnsigned64:(Lorg/sireum/Z;)Z
   #48 = Utf8               toB
   #49 = NameAndType        #48:#16       // toB:(Lorg/sireum/Z;)Z
   #50 = Methodref          #19.#49       // org/sireum/conversions/Z_Ext$.toB:(Lorg/sireum/Z;)Z
   #51 = Utf8               toZ
   #52 = Utf8               (Lorg/sireum/Z;)Lorg/sireum/Z;
   #53 = NameAndType        #51:#52       // toZ:(Lorg/sireum/Z;)Lorg/sireum/Z;
   #54 = Methodref          #19.#53       // org/sireum/conversions/Z_Ext$.toZ:(Lorg/sireum/Z;)Lorg/sireum/Z;
   #55 = Utf8               toZ8
   #56 = NameAndType        #55:#52       // toZ8:(Lorg/sireum/Z;)Lorg/sireum/Z;
   #57 = Methodref          #19.#56       // org/sireum/conversions/Z_Ext$.toZ8:(Lorg/sireum/Z;)Lorg/sireum/Z;
   #58 = Utf8               toZ16
   #59 = NameAndType        #58:#52       // toZ16:(Lorg/sireum/Z;)Lorg/sireum/Z;
   #60 = Methodref          #19.#59       // org/sireum/conversions/Z_Ext$.toZ16:(Lorg/sireum/Z;)Lorg/sireum/Z;
   #61 = Utf8               toZ32
   #62 = NameAndType        #61:#52       // toZ32:(Lorg/sireum/Z;)Lorg/sireum/Z;
   #63 = Methodref          #19.#62       // org/sireum/conversions/Z_Ext$.toZ32:(Lorg/sireum/Z;)Lorg/sireum/Z;
   #64 = Utf8               toZ64
   #65 = NameAndType        #64:#52       // toZ64:(Lorg/sireum/Z;)Lorg/sireum/Z;
   #66 = Methodref          #19.#65       // org/sireum/conversions/Z_Ext$.toZ64:(Lorg/sireum/Z;)Lorg/sireum/Z;
   #67 = Utf8               toN
   #68 = NameAndType        #67:#52       // toN:(Lorg/sireum/Z;)Lorg/sireum/Z;
   #69 = Methodref          #19.#68       // org/sireum/conversions/Z_Ext$.toN:(Lorg/sireum/Z;)Lorg/sireum/Z;
   #70 = Utf8               toN8
   #71 = NameAndType        #70:#52       // toN8:(Lorg/sireum/Z;)Lorg/sireum/Z;
   #72 = Methodref          #19.#71       // org/sireum/conversions/Z_Ext$.toN8:(Lorg/sireum/Z;)Lorg/sireum/Z;
   #73 = Utf8               toN16
   #74 = NameAndType        #73:#52       // toN16:(Lorg/sireum/Z;)Lorg/sireum/Z;
   #75 = Methodref          #19.#74       // org/sireum/conversions/Z_Ext$.toN16:(Lorg/sireum/Z;)Lorg/sireum/Z;
   #76 = Utf8               toN32
   #77 = NameAndType        #76:#52       // toN32:(Lorg/sireum/Z;)Lorg/sireum/Z;
   #78 = Methodref          #19.#77       // org/sireum/conversions/Z_Ext$.toN32:(Lorg/sireum/Z;)Lorg/sireum/Z;
   #79 = Utf8               toN64
   #80 = NameAndType        #79:#52       // toN64:(Lorg/sireum/Z;)Lorg/sireum/Z;
   #81 = Methodref          #19.#80       // org/sireum/conversions/Z_Ext$.toN64:(Lorg/sireum/Z;)Lorg/sireum/Z;
   #82 = Utf8               toS8
   #83 = Utf8               (Lorg/sireum/Z;)B
   #84 = NameAndType        #82:#83       // toS8:(Lorg/sireum/Z;)B
   #85 = Methodref          #19.#84       // org/sireum/conversions/Z_Ext$.toS8:(Lorg/sireum/Z;)B
   #86 = Utf8               toS16
   #87 = Utf8               (Lorg/sireum/Z;)S
   #88 = NameAndType        #86:#87       // toS16:(Lorg/sireum/Z;)S
   #89 = Methodref          #19.#88       // org/sireum/conversions/Z_Ext$.toS16:(Lorg/sireum/Z;)S
   #90 = Utf8               toS32
   #91 = Utf8               (Lorg/sireum/Z;)I
   #92 = NameAndType        #90:#91       // toS32:(Lorg/sireum/Z;)I
   #93 = Methodref          #19.#92       // org/sireum/conversions/Z_Ext$.toS32:(Lorg/sireum/Z;)I
   #94 = Utf8               toS64
   #95 = Utf8               (Lorg/sireum/Z;)J
   #96 = NameAndType        #94:#95       // toS64:(Lorg/sireum/Z;)J
   #97 = Methodref          #19.#96       // org/sireum/conversions/Z_Ext$.toS64:(Lorg/sireum/Z;)J
   #98 = Utf8               toU8
   #99 = NameAndType        #98:#83       // toU8:(Lorg/sireum/Z;)B
  #100 = Methodref          #19.#99       // org/sireum/conversions/Z_Ext$.toU8:(Lorg/sireum/Z;)B
  #101 = Utf8               toU16
  #102 = NameAndType        #101:#87      // toU16:(Lorg/sireum/Z;)S
  #103 = Methodref          #19.#102      // org/sireum/conversions/Z_Ext$.toU16:(Lorg/sireum/Z;)S
  #104 = Utf8               toU32
  #105 = NameAndType        #104:#91      // toU32:(Lorg/sireum/Z;)I
  #106 = Methodref          #19.#105      // org/sireum/conversions/Z_Ext$.toU32:(Lorg/sireum/Z;)I
  #107 = Utf8               toU64
  #108 = NameAndType        #107:#95      // toU64:(Lorg/sireum/Z;)J
  #109 = Methodref          #19.#108      // org/sireum/conversions/Z_Ext$.toU64:(Lorg/sireum/Z;)J
  #110 = Utf8               toR
  #111 = Utf8               (Lorg/sireum/Z;)Lscala/math/BigDecimal;
  #112 = NameAndType        #110:#111     // toR:(Lorg/sireum/Z;)Lscala/math/BigDecimal;
  #113 = Methodref          #19.#112      // org/sireum/conversions/Z_Ext$.toR:(Lorg/sireum/Z;)Lscala/math/BigDecimal;
  #114 = Utf8               toBinary
  #115 = Utf8               (Lorg/sireum/Z;)Lorg/sireum/IS;
  #116 = Utf8               (Lorg/sireum/Z;)Lorg/sireum/IS<Lorg/sireum/Z;Lorg/sireum/U8;>;
  #117 = NameAndType        #114:#115     // toBinary:(Lorg/sireum/Z;)Lorg/sireum/IS;
  #118 = Methodref          #19.#117      // org/sireum/conversions/Z_Ext$.toBinary:(Lorg/sireum/Z;)Lorg/sireum/IS;
  #119 = Utf8               fromBinary
  #120 = Utf8               (Lorg/sireum/IS;)Lorg/sireum/Z;
  #121 = Utf8               (Lorg/sireum/IS<Lorg/sireum/Z;Lorg/sireum/U8;>;)Lorg/sireum/Z;
  #122 = Utf8               bin
  #123 = NameAndType        #119:#120     // fromBinary:(Lorg/sireum/IS;)Lorg/sireum/Z;
  #124 = Methodref          #19.#123      // org/sireum/conversions/Z_Ext$.fromBinary:(Lorg/sireum/IS;)Lorg/sireum/Z;
  #125 = Utf8               Lorg/sireum/IS;
  #126 = Methodref          #4.#11        // java/lang/Object."<init>":()V
  #127 = Utf8               Code
  #128 = Utf8               LineNumberTable
  #129 = Utf8               LocalVariableTable
  #130 = Utf8               MethodParameters
  #131 = Utf8               Signature
  #132 = Utf8               SourceFile
  #133 = Utf8               ScalaInlineInfo
  #134 = Utf8               Scala
{
  public static final org.sireum.conversions.Z$ MODULE$;
    descriptor: Lorg/sireum/conversions/Z$;
    flags: (0x0019) ACC_PUBLIC, ACC_STATIC, ACC_FINAL

  public static {};
    descriptor: ()V
    flags: (0x0009) ACC_PUBLIC, ACC_STATIC
    Code:
      stack=2, locals=0, args_size=0
         0: new           #2                  // class org/sireum/conversions/Z$
         3: dup
         4: invokespecial #12                 // Method "<init>":()V
         7: putstatic     #14                 // Field MODULE$:Lorg/sireum/conversions/Z$;
        10: return
      LineNumberTable:
        line 103: 0

  public boolean isInRangeSigned8(org.sireum.Z);
    descriptor: (Lorg/sireum/Z;)Z
    flags: (0x0001) ACC_PUBLIC
    Code:
      stack=2, locals=2, args_size=2
         0: getstatic     #22                 // Field org/sireum/conversions/Z_Ext$.MODULE$:Lorg/sireum/conversions/Z_Ext$;
         3: aload_1
         4: invokevirtual #24                 // Method org/sireum/conversions/Z_Ext$.isInRangeSigned8:(Lorg/sireum/Z;)Z
         7: ireturn
      LineNumberTable:
        line 105: 0
      LocalVariableTable:
        Start  Length  Slot  Name   Signature
            0       8     0  this   Lorg/sireum/conversions/Z$;
            0       8     1     n   Lorg/sireum/Z;
    MethodParameters:
      Name                           Flags
      n                              final

  public boolean isInRangeSigned16(org.sireum.Z);
    descriptor: (Lorg/sireum/Z;)Z
    flags: (0x0001) ACC_PUBLIC
    Code:
      stack=2, locals=2, args_size=2
         0: getstatic     #22                 // Field org/sireum/conversions/Z_Ext$.MODULE$:Lorg/sireum/conversions/Z_Ext$;
         3: aload_1
         4: invokevirtual #29                 // Method org/sireum/conversions/Z_Ext$.isInRangeSigned16:(Lorg/sireum/Z;)Z
         7: ireturn
      LineNumberTable:
        line 108: 0
      LocalVariableTable:
        Start  Length  Slot  Name   Signature
            0       8     0  this   Lorg/sireum/conversions/Z$;
            0       8     1     n   Lorg/sireum/Z;
    MethodParameters:
      Name                           Flags
      n                              final

  public boolean isInRangeSigned32(org.sireum.Z);
    descriptor: (Lorg/sireum/Z;)Z
    flags: (0x0001) ACC_PUBLIC
    Code:
      stack=2, locals=2, args_size=2
         0: getstatic     #22                 // Field org/sireum/conversions/Z_Ext$.MODULE$:Lorg/sireum/conversions/Z_Ext$;
         3: aload_1
         4: invokevirtual #32                 // Method org/sireum/conversions/Z_Ext$.isInRangeSigned32:(Lorg/sireum/Z;)Z
         7: ireturn
      LineNumberTable:
        line 111: 0
      LocalVariableTable:
        Start  Length  Slot  Name   Signature
            0       8     0  this   Lorg/sireum/conversions/Z$;
            0       8     1     n   Lorg/sireum/Z;
    MethodParameters:
      Name                           Flags
      n                              final

  public boolean isInRangeSigned64(org.sireum.Z);
    descriptor: (Lorg/sireum/Z;)Z
    flags: (0x0001) ACC_PUBLIC
    Code:
      stack=2, locals=2, args_size=2
         0: getstatic     #22                 // Field org/sireum/conversions/Z_Ext$.MODULE$:Lorg/sireum/conversions/Z_Ext$;
         3: aload_1
         4: invokevirtual #35                 // Method org/sireum/conversions/Z_Ext$.isInRangeSigned64:(Lorg/sireum/Z;)Z
         7: ireturn
      LineNumberTable:
        line 114: 0
      LocalVariableTable:
        Start  Length  Slot  Name   Signature
            0       8     0  this   Lorg/sireum/conversions/Z$;
            0       8     1     n   Lorg/sireum/Z;
    MethodParameters:
      Name                           Flags
      n                              final

  public boolean isInRangeUnsigned8(org.sireum.Z);
    descriptor: (Lorg/sireum/Z;)Z
    flags: (0x0001) ACC_PUBLIC
    Code:
      stack=2, locals=2, args_size=2
         0: getstatic     #22                 // Field org/sireum/conversions/Z_Ext$.MODULE$:Lorg/sireum/conversions/Z_Ext$;
         3: aload_1
         4: invokevirtual #38                 // Method org/sireum/conversions/Z_Ext$.isInRangeUnsigned8:(Lorg/sireum/Z;)Z
         7: ireturn
      LineNumberTable:
        line 117: 0
      LocalVariableTable:
        Start  Length  Slot  Name   Signature
            0       8     0  this   Lorg/sireum/conversions/Z$;
            0       8     1     n   Lorg/sireum/Z;
    MethodParameters:
      Name                           Flags
      n                              final

  public boolean isInRangeUnsigned16(org.sireum.Z);
    descriptor: (Lorg/sireum/Z;)Z
    flags: (0x0001) ACC_PUBLIC
    Code:
      stack=2, locals=2, args_size=2
         0: getstatic     #22                 // Field org/sireum/conversions/Z_Ext$.MODULE$:Lorg/sireum/conversions/Z_Ext$;
         3: aload_1
         4: invokevirtual #41                 // Method org/sireum/conversions/Z_Ext$.isInRangeUnsigned16:(Lorg/sireum/Z;)Z
         7: ireturn
      LineNumberTable:
        line 120: 0
      LocalVariableTable:
        Start  Length  Slot  Name   Signature
            0       8     0  this   Lorg/sireum/conversions/Z$;
            0       8     1     n   Lorg/sireum/Z;
    MethodParameters:
      Name                           Flags
      n                              final

  public boolean isInRangeUnsigned32(org.sireum.Z);
    descriptor: (Lorg/sireum/Z;)Z
    flags: (0x0001) ACC_PUBLIC
    Code:
      stack=2, locals=2, args_size=2
         0: getstatic     #22                 // Field org/sireum/conversions/Z_Ext$.MODULE$:Lorg/sireum/conversions/Z_Ext$;
         3: aload_1
         4: invokevirtual #44                 // Method org/sireum/conversions/Z_Ext$.isInRangeUnsigned32:(Lorg/sireum/Z;)Z
         7: ireturn
      LineNumberTable:
        line 123: 0
      LocalVariableTable:
        Start  Length  Slot  Name   Signature
            0       8     0  this   Lorg/sireum/conversions/Z$;
            0       8     1     n   Lorg/sireum/Z;
    MethodParameters:
      Name                           Flags
      n                              final

  public boolean isInRangeUnsigned64(org.sireum.Z);
    descriptor: (Lorg/sireum/Z;)Z
    flags: (0x0001) ACC_PUBLIC
    Code:
      stack=2, locals=2, args_size=2
         0: getstatic     #22                 // Field org/sireum/conversions/Z_Ext$.MODULE$:Lorg/sireum/conversions/Z_Ext$;
         3: aload_1
         4: invokevirtual #47                 // Method org/sireum/conversions/Z_Ext$.isInRangeUnsigned64:(Lorg/sireum/Z;)Z
         7: ireturn
      LineNumberTable:
        line 126: 0
      LocalVariableTable:
        Start  Length  Slot  Name   Signature
            0       8     0  this   Lorg/sireum/conversions/Z$;
            0       8     1     n   Lorg/sireum/Z;
    MethodParameters:
      Name                           Flags
      n                              final

  public boolean toB(org.sireum.Z);
    descriptor: (Lorg/sireum/Z;)Z
    flags: (0x0001) ACC_PUBLIC
    Code:
      stack=2, locals=2, args_size=2
         0: getstatic     #22                 // Field org/sireum/conversions/Z_Ext$.MODULE$:Lorg/sireum/conversions/Z_Ext$;
         3: aload_1
         4: invokevirtual #50                 // Method org/sireum/conversions/Z_Ext$.toB:(Lorg/sireum/Z;)Z
         7: ireturn
      LineNumberTable:
        line 129: 0
      LocalVariableTable:
        Start  Length  Slot  Name   Signature
            0       8     0  this   Lorg/sireum/conversions/Z$;
            0       8     1     n   Lorg/sireum/Z;
    MethodParameters:
      Name                           Flags
      n                              final

  public org.sireum.Z toZ(org.sireum.Z);
    descriptor: (Lorg/sireum/Z;)Lorg/sireum/Z;
    flags: (0x0001) ACC_PUBLIC
    Code:
      stack=2, locals=2, args_size=2
         0: getstatic     #22                 // Field org/sireum/conversions/Z_Ext$.MODULE$:Lorg/sireum/conversions/Z_Ext$;
         3: aload_1
         4: invokevirtual #54                 // Method org/sireum/conversions/Z_Ext$.toZ:(Lorg/sireum/Z;)Lorg/sireum/Z;
         7: areturn
      LineNumberTable:
        line 132: 0
      LocalVariableTable:
        Start  Length  Slot  Name   Signature
            0       8     0  this   Lorg/sireum/conversions/Z$;
            0       8     1     n   Lorg/sireum/Z;
    MethodParameters:
      Name                           Flags
      n                              final

  public org.sireum.Z toZ8(org.sireum.Z);
    descriptor: (Lorg/sireum/Z;)Lorg/sireum/Z;
    flags: (0x0001) ACC_PUBLIC
    Code:
      stack=2, locals=2, args_size=2
         0: getstatic     #22                 // Field org/sireum/conversions/Z_Ext$.MODULE$:Lorg/sireum/conversions/Z_Ext$;
         3: aload_1
         4: invokevirtual #57                 // Method org/sireum/conversions/Z_Ext$.toZ8:(Lorg/sireum/Z;)Lorg/sireum/Z;
         7: areturn
      LineNumberTable:
        line 135: 0
      LocalVariableTable:
        Start  Length  Slot  Name   Signature
            0       8     0  this   Lorg/sireum/conversions/Z$;
            0       8     1     n   Lorg/sireum/Z;
    MethodParameters:
      Name                           Flags
      n                              final

  public org.sireum.Z toZ16(org.sireum.Z);
    descriptor: (Lorg/sireum/Z;)Lorg/sireum/Z;
    flags: (0x0001) ACC_PUBLIC
    Code:
      stack=2, locals=2, args_size=2
         0: getstatic     #22                 // Field org/sireum/conversions/Z_Ext$.MODULE$:Lorg/sireum/conversions/Z_Ext$;
         3: aload_1
         4: invokevirtual #60                 // Method org/sireum/conversions/Z_Ext$.toZ16:(Lorg/sireum/Z;)Lorg/sireum/Z;
         7: areturn
      LineNumberTable:
        line 139: 0
      LocalVariableTable:
        Start  Length  Slot  Name   Signature
            0       8     0  this   Lorg/sireum/conversions/Z$;
            0       8     1     n   Lorg/sireum/Z;
    MethodParameters:
      Name                           Flags
      n                              final

  public org.sireum.Z toZ32(org.sireum.Z);
    descriptor: (Lorg/sireum/Z;)Lorg/sireum/Z;
    flags: (0x0001) ACC_PUBLIC
    Code:
      stack=2, locals=2, args_size=2
         0: getstatic     #22                 // Field org/sireum/conversions/Z_Ext$.MODULE$:Lorg/sireum/conversions/Z_Ext$;
         3: aload_1
         4: invokevirtual #63                 // Method org/sireum/conversions/Z_Ext$.toZ32:(Lorg/sireum/Z;)Lorg/sireum/Z;
         7: areturn
      LineNumberTable:
        line 143: 0
      LocalVariableTable:
        Start  Length  Slot  Name   Signature
            0       8     0  this   Lorg/sireum/conversions/Z$;
            0       8     1     n   Lorg/sireum/Z;
    MethodParameters:
      Name                           Flags
      n                              final

  public org.sireum.Z toZ64(org.sireum.Z);
    descriptor: (Lorg/sireum/Z;)Lorg/sireum/Z;
    flags: (0x0001) ACC_PUBLIC
    Code:
      stack=2, locals=2, args_size=2
         0: getstatic     #22                 // Field org/sireum/conversions/Z_Ext$.MODULE$:Lorg/sireum/conversions/Z_Ext$;
         3: aload_1
         4: invokevirtual #66                 // Method org/sireum/conversions/Z_Ext$.toZ64:(Lorg/sireum/Z;)Lorg/sireum/Z;
         7: areturn
      LineNumberTable:
        line 147: 0
      LocalVariableTable:
        Start  Length  Slot  Name   Signature
            0       8     0  this   Lorg/sireum/conversions/Z$;
            0       8     1     n   Lorg/sireum/Z;
    MethodParameters:
      Name                           Flags
      n                              final

  public org.sireum.Z toN(org.sireum.Z);
    descriptor: (Lorg/sireum/Z;)Lorg/sireum/Z;
    flags: (0x0001) ACC_PUBLIC
    Code:
      stack=2, locals=2, args_size=2
         0: getstatic     #22                 // Field org/sireum/conversions/Z_Ext$.MODULE$:Lorg/sireum/conversions/Z_Ext$;
         3: aload_1
         4: invokevirtual #69                 // Method org/sireum/conversions/Z_Ext$.toN:(Lorg/sireum/Z;)Lorg/sireum/Z;
         7: areturn
      LineNumberTable:
        line 151: 0
      LocalVariableTable:
        Start  Length  Slot  Name   Signature
            0       8     0  this   Lorg/sireum/conversions/Z$;
            0       8     1     n   Lorg/sireum/Z;
    MethodParameters:
      Name                           Flags
      n                              final

  public org.sireum.Z toN8(org.sireum.Z);
    descriptor: (Lorg/sireum/Z;)Lorg/sireum/Z;
    flags: (0x0001) ACC_PUBLIC
    Code:
      stack=2, locals=2, args_size=2
         0: getstatic     #22                 // Field org/sireum/conversions/Z_Ext$.MODULE$:Lorg/sireum/conversions/Z_Ext$;
         3: aload_1
         4: invokevirtual #72                 // Method org/sireum/conversions/Z_Ext$.toN8:(Lorg/sireum/Z;)Lorg/sireum/Z;
         7: areturn
      LineNumberTable:
        line 155: 0
      LocalVariableTable:
        Start  Length  Slot  Name   Signature
            0       8     0  this   Lorg/sireum/conversions/Z$;
            0       8     1     n   Lorg/sireum/Z;
    MethodParameters:
      Name                           Flags
      n                              final

  public org.sireum.Z toN16(org.sireum.Z);
    descriptor: (Lorg/sireum/Z;)Lorg/sireum/Z;
    flags: (0x0001) ACC_PUBLIC
    Code:
      stack=2, locals=2, args_size=2
         0: getstatic     #22                 // Field org/sireum/conversions/Z_Ext$.MODULE$:Lorg/sireum/conversions/Z_Ext$;
         3: aload_1
         4: invokevirtual #75                 // Method org/sireum/conversions/Z_Ext$.toN16:(Lorg/sireum/Z;)Lorg/sireum/Z;
         7: areturn
      LineNumberTable:
        line 159: 0
      LocalVariableTable:
        Start  Length  Slot  Name   Signature
            0       8     0  this   Lorg/sireum/conversions/Z$;
            0       8     1     n   Lorg/sireum/Z;
    MethodParameters:
      Name                           Flags
      n                              final

  public org.sireum.Z toN32(org.sireum.Z);
    descriptor: (Lorg/sireum/Z;)Lorg/sireum/Z;
    flags: (0x0001) ACC_PUBLIC
    Code:
      stack=2, locals=2, args_size=2
         0: getstatic     #22                 // Field org/sireum/conversions/Z_Ext$.MODULE$:Lorg/sireum/conversions/Z_Ext$;
         3: aload_1
         4: invokevirtual #78                 // Method org/sireum/conversions/Z_Ext$.toN32:(Lorg/sireum/Z;)Lorg/sireum/Z;
         7: areturn
      LineNumberTable:
        line 163: 0
      LocalVariableTable:
        Start  Length  Slot  Name   Signature
            0       8     0  this   Lorg/sireum/conversions/Z$;
            0       8     1     n   Lorg/sireum/Z;
    MethodParameters:
      Name                           Flags
      n                              final

  public org.sireum.Z toN64(org.sireum.Z);
    descriptor: (Lorg/sireum/Z;)Lorg/sireum/Z;
    flags: (0x0001) ACC_PUBLIC
    Code:
      stack=2, locals=2, args_size=2
         0: getstatic     #22                 // Field org/sireum/conversions/Z_Ext$.MODULE$:Lorg/sireum/conversions/Z_Ext$;
         3: aload_1
         4: invokevirtual #81                 // Method org/sireum/conversions/Z_Ext$.toN64:(Lorg/sireum/Z;)Lorg/sireum/Z;
         7: areturn
      LineNumberTable:
        line 167: 0
      LocalVariableTable:
        Start  Length  Slot  Name   Signature
            0       8     0  this   Lorg/sireum/conversions/Z$;
            0       8     1     n   Lorg/sireum/Z;
    MethodParameters:
      Name                           Flags
      n                              final

  public byte toS8(org.sireum.Z);
    descriptor: (Lorg/sireum/Z;)B
    flags: (0x0001) ACC_PUBLIC
    Code:
      stack=2, locals=2, args_size=2
         0: getstatic     #22                 // Field org/sireum/conversions/Z_Ext$.MODULE$:Lorg/sireum/conversions/Z_Ext$;
         3: aload_1
         4: invokevirtual #85                 // Method org/sireum/conversions/Z_Ext$.toS8:(Lorg/sireum/Z;)B
         7: ireturn
      LineNumberTable:
        line 171: 0
      LocalVariableTable:
        Start  Length  Slot  Name   Signature
            0       8     0  this   Lorg/sireum/conversions/Z$;
            0       8     1     n   Lorg/sireum/Z;
    MethodParameters:
      Name                           Flags
      n                              final

  public short toS16(org.sireum.Z);
    descriptor: (Lorg/sireum/Z;)S
    flags: (0x0001) ACC_PUBLIC
    Code:
      stack=2, locals=2, args_size=2
         0: getstatic     #22                 // Field org/sireum/conversions/Z_Ext$.MODULE$:Lorg/sireum/conversions/Z_Ext$;
         3: aload_1
         4: invokevirtual #89                 // Method org/sireum/conversions/Z_Ext$.toS16:(Lorg/sireum/Z;)S
         7: ireturn
      LineNumberTable:
        line 175: 0
      LocalVariableTable:
        Start  Length  Slot  Name   Signature
            0       8     0  this   Lorg/sireum/conversions/Z$;
            0       8     1     n   Lorg/sireum/Z;
    MethodParameters:
      Name                           Flags
      n                              final

  public int toS32(org.sireum.Z);
    descriptor: (Lorg/sireum/Z;)I
    flags: (0x0001) ACC_PUBLIC
    Code:
      stack=2, locals=2, args_size=2
         0: getstatic     #22                 // Field org/sireum/conversions/Z_Ext$.MODULE$:Lorg/sireum/conversions/Z_Ext$;
         3: aload_1
         4: invokevirtual #93                 // Method org/sireum/conversions/Z_Ext$.toS32:(Lorg/sireum/Z;)I
         7: ireturn
      LineNumberTable:
        line 179: 0
      LocalVariableTable:
        Start  Length  Slot  Name   Signature
            0       8     0  this   Lorg/sireum/conversions/Z$;
            0       8     1     n   Lorg/sireum/Z;
    MethodParameters:
      Name                           Flags
      n                              final

  public long toS64(org.sireum.Z);
    descriptor: (Lorg/sireum/Z;)J
    flags: (0x0001) ACC_PUBLIC
    Code:
      stack=2, locals=2, args_size=2
         0: getstatic     #22                 // Field org/sireum/conversions/Z_Ext$.MODULE$:Lorg/sireum/conversions/Z_Ext$;
         3: aload_1
         4: invokevirtual #97                 // Method org/sireum/conversions/Z_Ext$.toS64:(Lorg/sireum/Z;)J
         7: lreturn
      LineNumberTable:
        line 183: 0
      LocalVariableTable:
        Start  Length  Slot  Name   Signature
            0       8     0  this   Lorg/sireum/conversions/Z$;
            0       8     1     n   Lorg/sireum/Z;
    MethodParameters:
      Name                           Flags
      n                              final

  public byte toU8(org.sireum.Z);
    descriptor: (Lorg/sireum/Z;)B
    flags: (0x0001) ACC_PUBLIC
    Code:
      stack=2, locals=2, args_size=2
         0: getstatic     #22                 // Field org/sireum/conversions/Z_Ext$.MODULE$:Lorg/sireum/conversions/Z_Ext$;
         3: aload_1
         4: invokevirtual #100                // Method org/sireum/conversions/Z_Ext$.toU8:(Lorg/sireum/Z;)B
         7: ireturn
      LineNumberTable:
        line 187: 0
      LocalVariableTable:
        Start  Length  Slot  Name   Signature
            0       8     0  this   Lorg/sireum/conversions/Z$;
            0       8     1     n   Lorg/sireum/Z;
    MethodParameters:
      Name                           Flags
      n                              final

  public short toU16(org.sireum.Z);
    descriptor: (Lorg/sireum/Z;)S
    flags: (0x0001) ACC_PUBLIC
    Code:
      stack=2, locals=2, args_size=2
         0: getstatic     #22                 // Field org/sireum/conversions/Z_Ext$.MODULE$:Lorg/sireum/conversions/Z_Ext$;
         3: aload_1
         4: invokevirtual #103                // Method org/sireum/conversions/Z_Ext$.toU16:(Lorg/sireum/Z;)S
         7: ireturn
      LineNumberTable:
        line 191: 0
      LocalVariableTable:
        Start  Length  Slot  Name   Signature
            0       8     0  this   Lorg/sireum/conversions/Z$;
            0       8     1     n   Lorg/sireum/Z;
    MethodParameters:
      Name                           Flags
      n                              final

  public int toU32(org.sireum.Z);
    descriptor: (Lorg/sireum/Z;)I
    flags: (0x0001) ACC_PUBLIC
    Code:
      stack=2, locals=2, args_size=2
         0: getstatic     #22                 // Field org/sireum/conversions/Z_Ext$.MODULE$:Lorg/sireum/conversions/Z_Ext$;
         3: aload_1
         4: invokevirtual #106                // Method org/sireum/conversions/Z_Ext$.toU32:(Lorg/sireum/Z;)I
         7: ireturn
      LineNumberTable:
        line 195: 0
      LocalVariableTable:
        Start  Length  Slot  Name   Signature
            0       8     0  this   Lorg/sireum/conversions/Z$;
            0       8     1     n   Lorg/sireum/Z;
    MethodParameters:
      Name                           Flags
      n                              final

  public long toU64(org.sireum.Z);
    descriptor: (Lorg/sireum/Z;)J
    flags: (0x0001) ACC_PUBLIC
    Code:
      stack=2, locals=2, args_size=2
         0: getstatic     #22                 // Field org/sireum/conversions/Z_Ext$.MODULE$:Lorg/sireum/conversions/Z_Ext$;
         3: aload_1
         4: invokevirtual #109                // Method org/sireum/conversions/Z_Ext$.toU64:(Lorg/sireum/Z;)J
         7: lreturn
      LineNumberTable:
        line 199: 0
      LocalVariableTable:
        Start  Length  Slot  Name   Signature
            0       8     0  this   Lorg/sireum/conversions/Z$;
            0       8     1     n   Lorg/sireum/Z;
    MethodParameters:
      Name                           Flags
      n                              final

  public scala.math.BigDecimal toR(org.sireum.Z);
    descriptor: (Lorg/sireum/Z;)Lscala/math/BigDecimal;
    flags: (0x0001) ACC_PUBLIC
    Code:
      stack=2, locals=2, args_size=2
         0: getstatic     #22                 // Field org/sireum/conversions/Z_Ext$.MODULE$:Lorg/sireum/conversions/Z_Ext$;
         3: aload_1
         4: invokevirtual #113                // Method org/sireum/conversions/Z_Ext$.toR:(Lorg/sireum/Z;)Lscala/math/BigDecimal;
         7: areturn
      LineNumberTable:
        line 204: 0
      LocalVariableTable:
        Start  Length  Slot  Name   Signature
            0       8     0  this   Lorg/sireum/conversions/Z$;
            0       8     1     n   Lorg/sireum/Z;
    MethodParameters:
      Name                           Flags
      n                              final

  public org.sireum.IS<org.sireum.Z, org.sireum.U8> toBinary(org.sireum.Z);
    descriptor: (Lorg/sireum/Z;)Lorg/sireum/IS;
    flags: (0x0001) ACC_PUBLIC
    Code:
      stack=2, locals=2, args_size=2
         0: getstatic     #22                 // Field org/sireum/conversions/Z_Ext$.MODULE$:Lorg/sireum/conversions/Z_Ext$;
         3: aload_1
         4: invokevirtual #118                // Method org/sireum/conversions/Z_Ext$.toBinary:(Lorg/sireum/Z;)Lorg/sireum/IS;
         7: areturn
      LineNumberTable:
        line 206: 0
      LocalVariableTable:
        Start  Length  Slot  Name   Signature
            0       8     0  this   Lorg/sireum/conversions/Z$;
            0       8     1     n   Lorg/sireum/Z;
    Signature: #116                         // (Lorg/sireum/Z;)Lorg/sireum/IS<Lorg/sireum/Z;Lorg/sireum/U8;>;
    MethodParameters:
      Name                           Flags
      n                              final

  public org.sireum.Z fromBinary(org.sireum.IS<org.sireum.Z, org.sireum.U8>);
    descriptor: (Lorg/sireum/IS;)Lorg/sireum/Z;
    flags: (0x0001) ACC_PUBLIC
    Code:
      stack=2, locals=2, args_size=2
         0: getstatic     #22                 // Field org/sireum/conversions/Z_Ext$.MODULE$:Lorg/sireum/conversions/Z_Ext$;
         3: aload_1
         4: invokevirtual #124                // Method org/sireum/conversions/Z_Ext$.fromBinary:(Lorg/sireum/IS;)Lorg/sireum/Z;
         7: areturn
      LineNumberTable:
        line 208: 0
      LocalVariableTable:
        Start  Length  Slot  Name   Signature
            0       8     0  this   Lorg/sireum/conversions/Z$;
            0       8     1   bin   Lorg/sireum/IS;
    Signature: #121                         // (Lorg/sireum/IS<Lorg/sireum/Z;Lorg/sireum/U8;>;)Lorg/sireum/Z;
    MethodParameters:
      Name                           Flags
      bin                            final

  private org.sireum.conversions.Z$();
    descriptor: ()V
    flags: (0x0002) ACC_PRIVATE
    Code:
      stack=1, locals=1, args_size=1
         0: aload_0
         1: invokespecial #126                // Method java/lang/Object."<init>":()V
         4: return
      LineNumberTable:
        line 103: 0
      LocalVariableTable:
        Start  Length  Slot  Name   Signature
            0       5     0  this   Lorg/sireum/conversions/Z$;
}
SourceFile: "conversions.scala"
  ScalaInlineInfo: length = 0x9F (unknown attribute)
   01 01 00 1F 00 0A 00 09 01 00 77 00 78 01 00 1B
   00 10 01 00 1E 00 10 01 00 21 00 10 01 00 0F 00
   10 01 00 27 00 10 01 00 2A 00 10 01 00 2D 00 10
   01 00 24 00 10 01 00 30 00 10 01 00 72 00 73 01
   00 43 00 34 01 00 49 00 34 01 00 4C 00 34 01 00
   4F 00 34 01 00 46 00 34 01 00 6E 00 6F 01 00 56
   00 57 01 00 5A 00 5B 01 00 5E 00 5F 01 00 52 00
   53 01 00 65 00 57 01 00 68 00 5B 01 00 6B 00 5F
   01 00 62 00 53 01 00 33 00 34 01 00 3A 00 34 01
   00 3D 00 34 01 00 40 00 34 01 00 37 00 34 01
  Scala: length = 0x0 (unknown attribute)

