Classfile /Users/mw/Projects/slang-braindump/.jar/jar11/assemble/slang-braindump/assemble/content/org/sireum/conversions/Z32_Ext.class
  Last modified May 29, 2022; size 3341 bytes
  SHA-256 checksum db90ed2d5354610e2c1d8177e01ed3558f6b4b00e6ac5936153ab2c511fd1b49
  Compiled from "extension.scala"
public final class org.sireum.conversions.Z32_Ext
  minor version: 0
  major version: 52
  flags: (0x0031) ACC_PUBLIC, ACC_FINAL, ACC_SUPER
  this_class: #2                          // org/sireum/conversions/Z32_Ext
  super_class: #4                         // java/lang/Object
  interfaces: 0, fields: 0, methods: 20, attributes: 3
Constant pool:
   #1 = Utf8               org/sireum/conversions/Z32_Ext
   #2 = Class              #1             // org/sireum/conversions/Z32_Ext
   #3 = Utf8               java/lang/Object
   #4 = Class              #3             // java/lang/Object
   #5 = Utf8               extension.scala
   #6 = Utf8               Lscala/reflect/ScalaSignature;
   #7 = Utf8               bytes
   #8 = Utf8               \u0006\u0005\u0005et!B\f\u0019\u0011\u0003yb!B\u0011\u0019\u0011\u0003\u0011\u0003\"B\u0015\u0002\t\u0003Q\u0003\"B\u0016\u0002\t\u0003a\u0003\"\u0002\u001e\u0002\t\u0003Y\u0004\"B!\u0002\t\u0003\u0011\u0005\"\u0002%\u0002\t\u0003I\u0005\"B(\u0002\t\u0003\u0001\u0006\"B*\u0002\t\u0003!\u0006\"\u0002.\u0002\t\u0003Y\u0006\"B1\u0002\t\u0003\u0011\u0007\"\u00025\u0002\t\u0003I\u0007\"B8\u0002\t\u0003\u0001\b\"\u0002<\u0002\t\u00039\b\"B?\u0002\t\u0003q\bbBA\u0005\u0003\u0011\u0005\u00111\u0002\u0005\b\u0003/\tA\u0011AA\r\u0011\u001d\t)#\u0001C\u0001\u0003OAq!a\r\u0002\t\u0003\t)\u0004C\u0004\u0002B\u0005!\t!a\u0011\t\u000f\u0005=\u0013\u0001\"\u0001\u0002R!9\u0011QL\u0001\u0005\u0002\u0005}\u0003bBA6\u0003\u0011\u0005\u0011QN\u0001\b5N\u0012t,\u0012=u\u0015\tI\"$A\u0006d_:4XM]:j_:\u001c(BA\u000e\u001d\u0003\u0019\u0019\u0018N]3v[*\tQ$A\u0002pe\u001e\u001c\u0001\u0001\u0005\u0002!\u00035\t\u0001DA\u0004[gIzV\t\u001f;\u0014\u0005\u0005\u0019\u0003C\u0001\u0013(\u001b\u0005)#\"\u0001\u0014\u0002\u000bM\u001c\u0017\r\\1\n\u0005!*#AB!osJ+g-\u0001\u0004=S:LGO\u0010\u000b\u0002?\u0005\u0019Ao\u001c\"\u0015\u00055\n\u0004C\u0001\u00180\u001b\u0005Q\u0012B\u0001\u0019\u001b\u0005\u0005\u0011\u0005\"\u0002\u001a\u0004\u0001\u0004\u0019\u0014!\u00018\u0011\u00059\"\u0014BA\u001b\u001b\u0005\rQ6G\r\u0015\u0003\u0007]\u0002\"A\f\u001d\n\u0005eR\"\u0001\u00029ve\u0016\f1\u0001^8[)\tat\b\u0005\u0002/{%\u0011aH\u0007\u0002\u00025\")!\u0007\u0002a\u0001g!\u0012AaN\u0001\u0005i>T\u0006\b\u0006\u0002D\rB\u0011a\u0006R\u0005\u0003\u000bj\u0011!A\u0017\u001d\t\u000bI*\u0001\u0019A\u001a)\u0005\u00159\u0014!\u0002;p5F2DC\u0001&N!\tq3*\u0003\u0002M5\t\u0019!,\r\u001c\t\u000bI2\u0001\u0019A\u001a)\u0005\u00199\u0014!\u0002;p5N\u0012DCA\u001aR\u0011\u0015\u0011t\u00011\u00014Q\t9q\'A\u0003u_j3D\u0007\u0006\u0002V1B\u0011aFV\u0005\u0003/j\u00111A\u0017\u001c5\u0011\u0015\u0011\u0004\u00021\u00014Q\tAq\'A\u0002u_:#\"\u0001X0\u0011\u00059j\u0016B\u00010\u001b\u0005\u0005q\u0005\"\u0002\u001a\n\u0001\u0004\u0019\u0004FA\u00058\u0003\u0011!xN\u0014\u001d\u0015\u0005\r4\u0007C\u0001\u0018e\u0013\t)\'D\u0001\u0002Oq!)!G\u0003a\u0001g!\u0012!bN\u0001\u0006i>t\u0015G\u000e\u000b\u0003U6\u0004\"AL6\n\u00051T\"a\u0001(2m!)!g\u0003a\u0001g!\u00121bN\u0001\u0006i>t5G\r\u000b\u0003cR\u0004\"A\f:\n\u0005MT\"a\u0001(4e!)!\u0007\u0004a\u0001g!\u0012AbN\u0001\u0006i>te\u0007\u000e\u000b\u0003qn\u0004\"AL=\n\u0005iT\"a\u0001(7i!)!\'\u0004a\u0001g!\u0012QbN\u0001\u0005i>\u001c\u0006\bF\u0002\u0000\u0003\u000b\u00012ALA\u0001\u0013\r\t\u0019A\u0007\u0002\u0003\'bBQA\r\bA\u0002MB#AD\u001c\u0002\u000bQ|7+\r\u001c\u0015\t\u00055\u00111\u0003\t\u0004]\u0005=\u0011bAA\t5\t\u00191+\r\u001c\t\u000bIz\u0001\u0019A\u001a)\u0005=9\u0014!\u0002;p\'N\u0012D\u0003BA\u000e\u0003C\u00012ALA\u000f\u0013\r\tyB\u0007\u0002\u0004\'N\u0012\u0004\"\u0002\u001a\u0011\u0001\u0004\u0019\u0004F\u0001\t8\u0003\u0015!xn\u0015\u001c5)\u0011\tI#a\f\u0011\u00079\nY#C\u0002\u0002.i\u00111a\u0015\u001c5\u0011\u0015\u0011\u0014\u00031\u00014Q\t\tr\'\u0001\u0003u_VCD\u0003BA\u001c\u0003{\u00012ALA\u001d\u0013\r\tYD\u0007\u0002\u0003+bBQA\r\nA\u0002MB#AE\u001c\u0002\u000bQ|W+\r\u001c\u0015\t\u0005\u0015\u00131\n\t\u0004]\u0005\u001d\u0013bAA%5\t\u0019Q+\r\u001c\t\u000bI\u001a\u0002\u0019A\u001a)\u0005M9\u0014!\u0002;p+N\u0012D\u0003BA*\u00033\u00022ALA+\u0013\r\t9F\u0007\u0002\u0004+N\u0012\u0004\"\u0002\u001a\u0015\u0001\u0004\u0019\u0004F\u0001\u000b8\u0003\u0015!x.\u0016\u001c5)\u0011\t\t\'a\u001a\u0011\u00079\n\u0019\'C\u0002\u0002fi\u00111!\u0016\u001c5\u0011\u0015\u0011T\u00031\u00014Q\t)r\'A\u0002u_J#B!a\u001c\u0002vA\u0019a&!\u001d\n\u0007\u0005M$DA\u0001S\u0011\u0015\u0011d\u00031\u00014Q\t1r\u0007
   #9 = Utf8               toR
  #10 = Utf8               (Lorg/sireum/Z;)Lscala/math/BigDecimal;
  #11 = Utf8               n
  #12 = Utf8               org/sireum/conversions/Z32_Ext$
  #13 = Class              #12            // org/sireum/conversions/Z32_Ext$
  #14 = Utf8               MODULE$
  #15 = Utf8               Lorg/sireum/conversions/Z32_Ext$;
  #16 = NameAndType        #14:#15        // MODULE$:Lorg/sireum/conversions/Z32_Ext$;
  #17 = Fieldref           #13.#16        // org/sireum/conversions/Z32_Ext$.MODULE$:Lorg/sireum/conversions/Z32_Ext$;
  #18 = NameAndType        #9:#10         // toR:(Lorg/sireum/Z;)Lscala/math/BigDecimal;
  #19 = Methodref          #13.#18        // org/sireum/conversions/Z32_Ext$.toR:(Lorg/sireum/Z;)Lscala/math/BigDecimal;
  #20 = Utf8               Lorg/sireum/Z;
  #21 = Utf8               toU64
  #22 = Utf8               (Lorg/sireum/Z;)J
  #23 = NameAndType        #21:#22        // toU64:(Lorg/sireum/Z;)J
  #24 = Methodref          #13.#23        // org/sireum/conversions/Z32_Ext$.toU64:(Lorg/sireum/Z;)J
  #25 = Utf8               toU32
  #26 = Utf8               (Lorg/sireum/Z;)I
  #27 = NameAndType        #25:#26        // toU32:(Lorg/sireum/Z;)I
  #28 = Methodref          #13.#27        // org/sireum/conversions/Z32_Ext$.toU32:(Lorg/sireum/Z;)I
  #29 = Utf8               toU16
  #30 = Utf8               (Lorg/sireum/Z;)S
  #31 = NameAndType        #29:#30        // toU16:(Lorg/sireum/Z;)S
  #32 = Methodref          #13.#31        // org/sireum/conversions/Z32_Ext$.toU16:(Lorg/sireum/Z;)S
  #33 = Utf8               toU8
  #34 = Utf8               (Lorg/sireum/Z;)B
  #35 = NameAndType        #33:#34        // toU8:(Lorg/sireum/Z;)B
  #36 = Methodref          #13.#35        // org/sireum/conversions/Z32_Ext$.toU8:(Lorg/sireum/Z;)B
  #37 = Utf8               toS64
  #38 = NameAndType        #37:#22        // toS64:(Lorg/sireum/Z;)J
  #39 = Methodref          #13.#38        // org/sireum/conversions/Z32_Ext$.toS64:(Lorg/sireum/Z;)J
  #40 = Utf8               toS32
  #41 = NameAndType        #40:#26        // toS32:(Lorg/sireum/Z;)I
  #42 = Methodref          #13.#41        // org/sireum/conversions/Z32_Ext$.toS32:(Lorg/sireum/Z;)I
  #43 = Utf8               toS16
  #44 = NameAndType        #43:#30        // toS16:(Lorg/sireum/Z;)S
  #45 = Methodref          #13.#44        // org/sireum/conversions/Z32_Ext$.toS16:(Lorg/sireum/Z;)S
  #46 = Utf8               toS8
  #47 = NameAndType        #46:#34        // toS8:(Lorg/sireum/Z;)B
  #48 = Methodref          #13.#47        // org/sireum/conversions/Z32_Ext$.toS8:(Lorg/sireum/Z;)B
  #49 = Utf8               toN64
  #50 = Utf8               (Lorg/sireum/Z;)Lorg/sireum/Z;
  #51 = NameAndType        #49:#50        // toN64:(Lorg/sireum/Z;)Lorg/sireum/Z;
  #52 = Methodref          #13.#51        // org/sireum/conversions/Z32_Ext$.toN64:(Lorg/sireum/Z;)Lorg/sireum/Z;
  #53 = Utf8               toN32
  #54 = NameAndType        #53:#50        // toN32:(Lorg/sireum/Z;)Lorg/sireum/Z;
  #55 = Methodref          #13.#54        // org/sireum/conversions/Z32_Ext$.toN32:(Lorg/sireum/Z;)Lorg/sireum/Z;
  #56 = Utf8               toN16
  #57 = NameAndType        #56:#50        // toN16:(Lorg/sireum/Z;)Lorg/sireum/Z;
  #58 = Methodref          #13.#57        // org/sireum/conversions/Z32_Ext$.toN16:(Lorg/sireum/Z;)Lorg/sireum/Z;
  #59 = Utf8               toN8
  #60 = NameAndType        #59:#50        // toN8:(Lorg/sireum/Z;)Lorg/sireum/Z;
  #61 = Methodref          #13.#60        // org/sireum/conversions/Z32_Ext$.toN8:(Lorg/sireum/Z;)Lorg/sireum/Z;
  #62 = Utf8               toN
  #63 = NameAndType        #62:#50        // toN:(Lorg/sireum/Z;)Lorg/sireum/Z;
  #64 = Methodref          #13.#63        // org/sireum/conversions/Z32_Ext$.toN:(Lorg/sireum/Z;)Lorg/sireum/Z;
  #65 = Utf8               toZ64
  #66 = NameAndType        #65:#50        // toZ64:(Lorg/sireum/Z;)Lorg/sireum/Z;
  #67 = Methodref          #13.#66        // org/sireum/conversions/Z32_Ext$.toZ64:(Lorg/sireum/Z;)Lorg/sireum/Z;
  #68 = Utf8               toZ32
  #69 = NameAndType        #68:#50        // toZ32:(Lorg/sireum/Z;)Lorg/sireum/Z;
  #70 = Methodref          #13.#69        // org/sireum/conversions/Z32_Ext$.toZ32:(Lorg/sireum/Z;)Lorg/sireum/Z;
  #71 = Utf8               toZ16
  #72 = NameAndType        #71:#50        // toZ16:(Lorg/sireum/Z;)Lorg/sireum/Z;
  #73 = Methodref          #13.#72        // org/sireum/conversions/Z32_Ext$.toZ16:(Lorg/sireum/Z;)Lorg/sireum/Z;
  #74 = Utf8               toZ8
  #75 = NameAndType        #74:#50        // toZ8:(Lorg/sireum/Z;)Lorg/sireum/Z;
  #76 = Methodref          #13.#75        // org/sireum/conversions/Z32_Ext$.toZ8:(Lorg/sireum/Z;)Lorg/sireum/Z;
  #77 = Utf8               toZ
  #78 = NameAndType        #77:#50        // toZ:(Lorg/sireum/Z;)Lorg/sireum/Z;
  #79 = Methodref          #13.#78        // org/sireum/conversions/Z32_Ext$.toZ:(Lorg/sireum/Z;)Lorg/sireum/Z;
  #80 = Utf8               toB
  #81 = Utf8               (Lorg/sireum/Z;)Z
  #82 = NameAndType        #80:#81        // toB:(Lorg/sireum/Z;)Z
  #83 = Methodref          #13.#82        // org/sireum/conversions/Z32_Ext$.toB:(Lorg/sireum/Z;)Z
  #84 = Utf8               Code
  #85 = Utf8               LocalVariableTable
  #86 = Utf8               MethodParameters
  #87 = Utf8               SourceFile
  #88 = Utf8               RuntimeVisibleAnnotations
  #89 = Utf8               ScalaSig
{
  public static scala.math.BigDecimal toR(org.sireum.Z);
    descriptor: (Lorg/sireum/Z;)Lscala/math/BigDecimal;
    flags: (0x0009) ACC_PUBLIC, ACC_STATIC
    Code:
      stack=2, locals=1, args_size=1
         0: getstatic     #17                 // Field org/sireum/conversions/Z32_Ext$.MODULE$:Lorg/sireum/conversions/Z32_Ext$;
         3: aload_0
         4: invokevirtual #19                 // Method org/sireum/conversions/Z32_Ext$.toR:(Lorg/sireum/Z;)Lscala/math/BigDecimal;
         7: areturn
      LocalVariableTable:
        Start  Length  Slot  Name   Signature
            0       8     0     n   Lorg/sireum/Z;
    MethodParameters:
      Name                           Flags
      n                              final

  public static long toU64(org.sireum.Z);
    descriptor: (Lorg/sireum/Z;)J
    flags: (0x0009) ACC_PUBLIC, ACC_STATIC
    Code:
      stack=2, locals=1, args_size=1
         0: getstatic     #17                 // Field org/sireum/conversions/Z32_Ext$.MODULE$:Lorg/sireum/conversions/Z32_Ext$;
         3: aload_0
         4: invokevirtual #24                 // Method org/sireum/conversions/Z32_Ext$.toU64:(Lorg/sireum/Z;)J
         7: lreturn
      LocalVariableTable:
        Start  Length  Slot  Name   Signature
            0       8     0     n   Lorg/sireum/Z;
    MethodParameters:
      Name                           Flags
      n                              final

  public static int toU32(org.sireum.Z);
    descriptor: (Lorg/sireum/Z;)I
    flags: (0x0009) ACC_PUBLIC, ACC_STATIC
    Code:
      stack=2, locals=1, args_size=1
         0: getstatic     #17                 // Field org/sireum/conversions/Z32_Ext$.MODULE$:Lorg/sireum/conversions/Z32_Ext$;
         3: aload_0
         4: invokevirtual #28                 // Method org/sireum/conversions/Z32_Ext$.toU32:(Lorg/sireum/Z;)I
         7: ireturn
      LocalVariableTable:
        Start  Length  Slot  Name   Signature
            0       8     0     n   Lorg/sireum/Z;
    MethodParameters:
      Name                           Flags
      n                              final

  public static short toU16(org.sireum.Z);
    descriptor: (Lorg/sireum/Z;)S
    flags: (0x0009) ACC_PUBLIC, ACC_STATIC
    Code:
      stack=2, locals=1, args_size=1
         0: getstatic     #17                 // Field org/sireum/conversions/Z32_Ext$.MODULE$:Lorg/sireum/conversions/Z32_Ext$;
         3: aload_0
         4: invokevirtual #32                 // Method org/sireum/conversions/Z32_Ext$.toU16:(Lorg/sireum/Z;)S
         7: ireturn
      LocalVariableTable:
        Start  Length  Slot  Name   Signature
            0       8     0     n   Lorg/sireum/Z;
    MethodParameters:
      Name                           Flags
      n                              final

  public static byte toU8(org.sireum.Z);
    descriptor: (Lorg/sireum/Z;)B
    flags: (0x0009) ACC_PUBLIC, ACC_STATIC
    Code:
      stack=2, locals=1, args_size=1
         0: getstatic     #17                 // Field org/sireum/conversions/Z32_Ext$.MODULE$:Lorg/sireum/conversions/Z32_Ext$;
         3: aload_0
         4: invokevirtual #36                 // Method org/sireum/conversions/Z32_Ext$.toU8:(Lorg/sireum/Z;)B
         7: ireturn
      LocalVariableTable:
        Start  Length  Slot  Name   Signature
            0       8     0     n   Lorg/sireum/Z;
    MethodParameters:
      Name                           Flags
      n                              final

  public static long toS64(org.sireum.Z);
    descriptor: (Lorg/sireum/Z;)J
    flags: (0x0009) ACC_PUBLIC, ACC_STATIC
    Code:
      stack=2, locals=1, args_size=1
         0: getstatic     #17                 // Field org/sireum/conversions/Z32_Ext$.MODULE$:Lorg/sireum/conversions/Z32_Ext$;
         3: aload_0
         4: invokevirtual #39                 // Method org/sireum/conversions/Z32_Ext$.toS64:(Lorg/sireum/Z;)J
         7: lreturn
      LocalVariableTable:
        Start  Length  Slot  Name   Signature
            0       8     0     n   Lorg/sireum/Z;
    MethodParameters:
      Name                           Flags
      n                              final

  public static int toS32(org.sireum.Z);
    descriptor: (Lorg/sireum/Z;)I
    flags: (0x0009) ACC_PUBLIC, ACC_STATIC
    Code:
      stack=2, locals=1, args_size=1
         0: getstatic     #17                 // Field org/sireum/conversions/Z32_Ext$.MODULE$:Lorg/sireum/conversions/Z32_Ext$;
         3: aload_0
         4: invokevirtual #42                 // Method org/sireum/conversions/Z32_Ext$.toS32:(Lorg/sireum/Z;)I
         7: ireturn
      LocalVariableTable:
        Start  Length  Slot  Name   Signature
            0       8     0     n   Lorg/sireum/Z;
    MethodParameters:
      Name                           Flags
      n                              final

  public static short toS16(org.sireum.Z);
    descriptor: (Lorg/sireum/Z;)S
    flags: (0x0009) ACC_PUBLIC, ACC_STATIC
    Code:
      stack=2, locals=1, args_size=1
         0: getstatic     #17                 // Field org/sireum/conversions/Z32_Ext$.MODULE$:Lorg/sireum/conversions/Z32_Ext$;
         3: aload_0
         4: invokevirtual #45                 // Method org/sireum/conversions/Z32_Ext$.toS16:(Lorg/sireum/Z;)S
         7: ireturn
      LocalVariableTable:
        Start  Length  Slot  Name   Signature
            0       8     0     n   Lorg/sireum/Z;
    MethodParameters:
      Name                           Flags
      n                              final

  public static byte toS8(org.sireum.Z);
    descriptor: (Lorg/sireum/Z;)B
    flags: (0x0009) ACC_PUBLIC, ACC_STATIC
    Code:
      stack=2, locals=1, args_size=1
         0: getstatic     #17                 // Field org/sireum/conversions/Z32_Ext$.MODULE$:Lorg/sireum/conversions/Z32_Ext$;
         3: aload_0
         4: invokevirtual #48                 // Method org/sireum/conversions/Z32_Ext$.toS8:(Lorg/sireum/Z;)B
         7: ireturn
      LocalVariableTable:
        Start  Length  Slot  Name   Signature
            0       8     0     n   Lorg/sireum/Z;
    MethodParameters:
      Name                           Flags
      n                              final

  public static org.sireum.Z toN64(org.sireum.Z);
    descriptor: (Lorg/sireum/Z;)Lorg/sireum/Z;
    flags: (0x0009) ACC_PUBLIC, ACC_STATIC
    Code:
      stack=2, locals=1, args_size=1
         0: getstatic     #17                 // Field org/sireum/conversions/Z32_Ext$.MODULE$:Lorg/sireum/conversions/Z32_Ext$;
         3: aload_0
         4: invokevirtual #52                 // Method org/sireum/conversions/Z32_Ext$.toN64:(Lorg/sireum/Z;)Lorg/sireum/Z;
         7: areturn
      LocalVariableTable:
        Start  Length  Slot  Name   Signature
            0       8     0     n   Lorg/sireum/Z;
    MethodParameters:
      Name                           Flags
      n                              final

  public static org.sireum.Z toN32(org.sireum.Z);
    descriptor: (Lorg/sireum/Z;)Lorg/sireum/Z;
    flags: (0x0009) ACC_PUBLIC, ACC_STATIC
    Code:
      stack=2, locals=1, args_size=1
         0: getstatic     #17                 // Field org/sireum/conversions/Z32_Ext$.MODULE$:Lorg/sireum/conversions/Z32_Ext$;
         3: aload_0
         4: invokevirtual #55                 // Method org/sireum/conversions/Z32_Ext$.toN32:(Lorg/sireum/Z;)Lorg/sireum/Z;
         7: areturn
      LocalVariableTable:
        Start  Length  Slot  Name   Signature
            0       8     0     n   Lorg/sireum/Z;
    MethodParameters:
      Name                           Flags
      n                              final

  public static org.sireum.Z toN16(org.sireum.Z);
    descriptor: (Lorg/sireum/Z;)Lorg/sireum/Z;
    flags: (0x0009) ACC_PUBLIC, ACC_STATIC
    Code:
      stack=2, locals=1, args_size=1
         0: getstatic     #17                 // Field org/sireum/conversions/Z32_Ext$.MODULE$:Lorg/sireum/conversions/Z32_Ext$;
         3: aload_0
         4: invokevirtual #58                 // Method org/sireum/conversions/Z32_Ext$.toN16:(Lorg/sireum/Z;)Lorg/sireum/Z;
         7: areturn
      LocalVariableTable:
        Start  Length  Slot  Name   Signature
            0       8     0     n   Lorg/sireum/Z;
    MethodParameters:
      Name                           Flags
      n                              final

  public static org.sireum.Z toN8(org.sireum.Z);
    descriptor: (Lorg/sireum/Z;)Lorg/sireum/Z;
    flags: (0x0009) ACC_PUBLIC, ACC_STATIC
    Code:
      stack=2, locals=1, args_size=1
         0: getstatic     #17                 // Field org/sireum/conversions/Z32_Ext$.MODULE$:Lorg/sireum/conversions/Z32_Ext$;
         3: aload_0
         4: invokevirtual #61                 // Method org/sireum/conversions/Z32_Ext$.toN8:(Lorg/sireum/Z;)Lorg/sireum/Z;
         7: areturn
      LocalVariableTable:
        Start  Length  Slot  Name   Signature
            0       8     0     n   Lorg/sireum/Z;
    MethodParameters:
      Name                           Flags
      n                              final

  public static org.sireum.Z toN(org.sireum.Z);
    descriptor: (Lorg/sireum/Z;)Lorg/sireum/Z;
    flags: (0x0009) ACC_PUBLIC, ACC_STATIC
    Code:
      stack=2, locals=1, args_size=1
         0: getstatic     #17                 // Field org/sireum/conversions/Z32_Ext$.MODULE$:Lorg/sireum/conversions/Z32_Ext$;
         3: aload_0
         4: invokevirtual #64                 // Method org/sireum/conversions/Z32_Ext$.toN:(Lorg/sireum/Z;)Lorg/sireum/Z;
         7: areturn
      LocalVariableTable:
        Start  Length  Slot  Name   Signature
            0       8     0     n   Lorg/sireum/Z;
    MethodParameters:
      Name                           Flags
      n                              final

  public static org.sireum.Z toZ64(org.sireum.Z);
    descriptor: (Lorg/sireum/Z;)Lorg/sireum/Z;
    flags: (0x0009) ACC_PUBLIC, ACC_STATIC
    Code:
      stack=2, locals=1, args_size=1
         0: getstatic     #17                 // Field org/sireum/conversions/Z32_Ext$.MODULE$:Lorg/sireum/conversions/Z32_Ext$;
         3: aload_0
         4: invokevirtual #67                 // Method org/sireum/conversions/Z32_Ext$.toZ64:(Lorg/sireum/Z;)Lorg/sireum/Z;
         7: areturn
      LocalVariableTable:
        Start  Length  Slot  Name   Signature
            0       8     0     n   Lorg/sireum/Z;
    MethodParameters:
      Name                           Flags
      n                              final

  public static org.sireum.Z toZ32(org.sireum.Z);
    descriptor: (Lorg/sireum/Z;)Lorg/sireum/Z;
    flags: (0x0009) ACC_PUBLIC, ACC_STATIC
    Code:
      stack=2, locals=1, args_size=1
         0: getstatic     #17                 // Field org/sireum/conversions/Z32_Ext$.MODULE$:Lorg/sireum/conversions/Z32_Ext$;
         3: aload_0
         4: invokevirtual #70                 // Method org/sireum/conversions/Z32_Ext$.toZ32:(Lorg/sireum/Z;)Lorg/sireum/Z;
         7: areturn
      LocalVariableTable:
        Start  Length  Slot  Name   Signature
            0       8     0     n   Lorg/sireum/Z;
    MethodParameters:
      Name                           Flags
      n                              final

  public static org.sireum.Z toZ16(org.sireum.Z);
    descriptor: (Lorg/sireum/Z;)Lorg/sireum/Z;
    flags: (0x0009) ACC_PUBLIC, ACC_STATIC
    Code:
      stack=2, locals=1, args_size=1
         0: getstatic     #17                 // Field org/sireum/conversions/Z32_Ext$.MODULE$:Lorg/sireum/conversions/Z32_Ext$;
         3: aload_0
         4: invokevirtual #73                 // Method org/sireum/conversions/Z32_Ext$.toZ16:(Lorg/sireum/Z;)Lorg/sireum/Z;
         7: areturn
      LocalVariableTable:
        Start  Length  Slot  Name   Signature
            0       8     0     n   Lorg/sireum/Z;
    MethodParameters:
      Name                           Flags
      n                              final

  public static org.sireum.Z toZ8(org.sireum.Z);
    descriptor: (Lorg/sireum/Z;)Lorg/sireum/Z;
    flags: (0x0009) ACC_PUBLIC, ACC_STATIC
    Code:
      stack=2, locals=1, args_size=1
         0: getstatic     #17                 // Field org/sireum/conversions/Z32_Ext$.MODULE$:Lorg/sireum/conversions/Z32_Ext$;
         3: aload_0
         4: invokevirtual #76                 // Method org/sireum/conversions/Z32_Ext$.toZ8:(Lorg/sireum/Z;)Lorg/sireum/Z;
         7: areturn
      LocalVariableTable:
        Start  Length  Slot  Name   Signature
            0       8     0     n   Lorg/sireum/Z;
    MethodParameters:
      Name                           Flags
      n                              final

  public static org.sireum.Z toZ(org.sireum.Z);
    descriptor: (Lorg/sireum/Z;)Lorg/sireum/Z;
    flags: (0x0009) ACC_PUBLIC, ACC_STATIC
    Code:
      stack=2, locals=1, args_size=1
         0: getstatic     #17                 // Field org/sireum/conversions/Z32_Ext$.MODULE$:Lorg/sireum/conversions/Z32_Ext$;
         3: aload_0
         4: invokevirtual #79                 // Method org/sireum/conversions/Z32_Ext$.toZ:(Lorg/sireum/Z;)Lorg/sireum/Z;
         7: areturn
      LocalVariableTable:
        Start  Length  Slot  Name   Signature
            0       8     0     n   Lorg/sireum/Z;
    MethodParameters:
      Name                           Flags
      n                              final

  public static boolean toB(org.sireum.Z);
    descriptor: (Lorg/sireum/Z;)Z
    flags: (0x0009) ACC_PUBLIC, ACC_STATIC
    Code:
      stack=2, locals=1, args_size=1
         0: getstatic     #17                 // Field org/sireum/conversions/Z32_Ext$.MODULE$:Lorg/sireum/conversions/Z32_Ext$;
         3: aload_0
         4: invokevirtual #83                 // Method org/sireum/conversions/Z32_Ext$.toB:(Lorg/sireum/Z;)Z
         7: ireturn
      LocalVariableTable:
        Start  Length  Slot  Name   Signature
            0       8     0     n   Lorg/sireum/Z;
    MethodParameters:
      Name                           Flags
      n                              final
}
SourceFile: "extension.scala"
RuntimeVisibleAnnotations:
  0: #6(#7=s#8)
    scala.reflect.ScalaSignature(
      bytes="\u0006\u0005\u0005et!B\f\u0019\u0011\u0003yb!B\u0011\u0019\u0011\u0003\u0011\u0003\"B\u0015\u0002\t\u0003Q\u0003\"B\u0016\u0002\t\u0003a\u0003\"\u0002\u001e\u0002\t\u0003Y\u0004\"B!\u0002\t\u0003\u0011\u0005\"\u0002%\u0002\t\u0003I\u0005\"B(\u0002\t\u0003\u0001\u0006\"B*\u0002\t\u0003!\u0006\"\u0002.\u0002\t\u0003Y\u0006\"B1\u0002\t\u0003\u0011\u0007\"\u00025\u0002\t\u0003I\u0007\"B8\u0002\t\u0003\u0001\b\"\u0002<\u0002\t\u00039\b\"B?\u0002\t\u0003q\bbBA\u0005\u0003\u0011\u0005\u00111\u0002\u0005\b\u0003/\tA\u0011AA\r\u0011\u001d\t)#\u0001C\u0001\u0003OAq!a\r\u0002\t\u0003\t)\u0004C\u0004\u0002B\u0005!\t!a\u0011\t\u000f\u0005=\u0013\u0001\"\u0001\u0002R!9\u0011QL\u0001\u0005\u0002\u0005}\u0003bBA6\u0003\u0011\u0005\u0011QN\u0001\b5N\u0012t,\u0012=u\u0015\tI\"$A\u0006d_:4XM]:j_:\u001c(BA\u000e\u001d\u0003\u0019\u0019\u0018N]3v[*\tQ$A\u0002pe\u001e\u001c\u0001\u0001\u0005\u0002!\u00035\t\u0001DA\u0004[gIzV\t\u001f;\u0014\u0005\u0005\u0019\u0003C\u0001\u0013(\u001b\u0005)#\"\u0001\u0014\u0002\u000bM\u001c\u0017\r\\1\n\u0005!*#AB!osJ+g-\u0001\u0004=S:LGO\u0010\u000b\u0002?\u0005\u0019Ao\u001c\"\u0015\u00055\n\u0004C\u0001\u00180\u001b\u0005Q\u0012B\u0001\u0019\u001b\u0005\u0005\u0011\u0005\"\u0002\u001a\u0004\u0001\u0004\u0019\u0014!\u00018\u0011\u00059\"\u0014BA\u001b\u001b\u0005\rQ6G\r\u0015\u0003\u0007]\u0002\"A\f\u001d\n\u0005eR\"\u0001\u00029ve\u0016\f1\u0001^8[)\tat\b\u0005\u0002/{%\u0011aH\u0007\u0002\u00025\")!\u0007\u0002a\u0001g!\u0012AaN\u0001\u0005i>T\u0006\b\u0006\u0002D\rB\u0011a\u0006R\u0005\u0003\u000bj\u0011!A\u0017\u001d\t\u000bI*\u0001\u0019A\u001a)\u0005\u00159\u0014!\u0002;p5F2DC\u0001&N!\tq3*\u0003\u0002M5\t\u0019!,\r\u001c\t\u000bI2\u0001\u0019A\u001a)\u0005\u00199\u0014!\u0002;p5N\u0012DCA\u001aR\u0011\u0015\u0011t\u00011\u00014Q\t9q\'A\u0003u_j3D\u0007\u0006\u0002V1B\u0011aFV\u0005\u0003/j\u00111A\u0017\u001c5\u0011\u0015\u0011\u0004\u00021\u00014Q\tAq\'A\u0002u_:#\"\u0001X0\u0011\u00059j\u0016B\u00010\u001b\u0005\u0005q\u0005\"\u0002\u001a\n\u0001\u0004\u0019\u0004FA\u00058\u0003\u0011!xN\u0014\u001d\u0015\u0005\r4\u0007C\u0001\u0018e\u0013\t)\'D\u0001\u0002Oq!)!G\u0003a\u0001g!\u0012!bN\u0001\u0006i>t\u0015G\u000e\u000b\u0003U6\u0004\"AL6\n\u00051T\"a\u0001(2m!)!g\u0003a\u0001g!\u00121bN\u0001\u0006i>t5G\r\u000b\u0003cR\u0004\"A\f:\n\u0005MT\"a\u0001(4e!)!\u0007\u0004a\u0001g!\u0012AbN\u0001\u0006i>te\u0007\u000e\u000b\u0003qn\u0004\"AL=\n\u0005iT\"a\u0001(7i!)!\'\u0004a\u0001g!\u0012QbN\u0001\u0005i>\u001c\u0006\bF\u0002\u0000\u0003\u000b\u00012ALA\u0001\u0013\r\t\u0019A\u0007\u0002\u0003\'bBQA\r\bA\u0002MB#AD\u001c\u0002\u000bQ|7+\r\u001c\u0015\t\u00055\u00111\u0003\t\u0004]\u0005=\u0011bAA\t5\t\u00191+\r\u001c\t\u000bIz\u0001\u0019A\u001a)\u0005=9\u0014!\u0002;p\'N\u0012D\u0003BA\u000e\u0003C\u00012ALA\u000f\u0013\r\tyB\u0007\u0002\u0004\'N\u0012\u0004\"\u0002\u001a\u0011\u0001\u0004\u0019\u0004F\u0001\t8\u0003\u0015!xn\u0015\u001c5)\u0011\tI#a\f\u0011\u00079\nY#C\u0002\u0002.i\u00111a\u0015\u001c5\u0011\u0015\u0011\u0014\u00031\u00014Q\t\tr\'\u0001\u0003u_VCD\u0003BA\u001c\u0003{\u00012ALA\u001d\u0013\r\tYD\u0007\u0002\u0003+bBQA\r\nA\u0002MB#AE\u001c\u0002\u000bQ|W+\r\u001c\u0015\t\u0005\u0015\u00131\n\t\u0004]\u0005\u001d\u0013bAA%5\t\u0019Q+\r\u001c\t\u000bI\u001a\u0002\u0019A\u001a)\u0005M9\u0014!\u0002;p+N\u0012D\u0003BA*\u00033\u00022ALA+\u0013\r\t9F\u0007\u0002\u0004+N\u0012\u0004\"\u0002\u001a\u0015\u0001\u0004\u0019\u0004F\u0001\u000b8\u0003\u0015!x.\u0016\u001c5)\u0011\t\t\'a\u001a\u0011\u00079\n\u0019\'C\u0002\u0002fi\u00111!\u0016\u001c5\u0011\u0015\u0011T\u00031\u00014Q\t)r\'A\u0002u_J#B!a\u001c\u0002vA\u0019a&!\u001d\n\u0007\u0005M$DA\u0001S\u0011\u0015\u0011d\u00031\u00014Q\t1r\u0007"
    )
  ScalaSig: length = 0x3 (unknown attribute)
   05 02 00
