Classfile /Users/mw/Projects/slang-braindump/.jar/jar11/assemble/slang-braindump/assemble/content/org/sireum/conversions/Z_Ext.class
  Last modified May 29, 2022; size 5270 bytes
  SHA-256 checksum 41628dfba4bad9ba951c6d4b93682062387cf90bf9847d908720b751d71d1f67
  Compiled from "extension.scala"
public final class org.sireum.conversions.Z_Ext
  minor version: 0
  major version: 52
  flags: (0x0031) ACC_PUBLIC, ACC_FINAL, ACC_SUPER
  this_class: #2                          // org/sireum/conversions/Z_Ext
  super_class: #4                         // java/lang/Object
  interfaces: 0, fields: 0, methods: 31, attributes: 3
Constant pool:
    #1 = Utf8               org/sireum/conversions/Z_Ext
    #2 = Class              #1            // org/sireum/conversions/Z_Ext
    #3 = Utf8               java/lang/Object
    #4 = Class              #3            // java/lang/Object
    #5 = Utf8               extension.scala
    #6 = Utf8               Lscala/reflect/ScalaSignature;
    #7 = Utf8               bytes
    #8 = Utf8               \u0006\u0005\t-q!\u0002\u0012$\u0011\u0003Qc!\u0002\u0017$\u0011\u0003i\u0003\"\u0002\u001b\u0002\t\u0003)\u0004\"\u0002\u001c\u0002\t\u00039\u0004\"B#\u0002\t\u00031\u0005\"B%\u0002\t\u0003Q\u0005\"B\'\u0002\t\u0003q\u0005\"B)\u0002\t\u0003\u0011\u0006\"B+\u0002\t\u00031\u0006\"B-\u0002\t\u0003Q\u0006\"B/\u0002\t\u0003q\u0006\"B1\u0002\t\u0003\u0011\u0007\"B3\u0002\t\u00031\u0007\"B5\u0002\t\u0003Q\u0007\"B7\u0002\t\u0003q\u0007\"\u0002;\u0002\t\u0003)\b\"B>\u0002\t\u0003a\bbBA\u0003\u0003\u0011\u0005\u0011q\u0001\u0005\b\u0003\'\tA\u0011AA\u000b\u0011\u001d\t\t#\u0001C\u0001\u0003GAq!a\f\u0002\t\u0003\t\t\u0004C\u0004\u0002>\u0005!\t!a\u0010\t\u000f\u0005-\u0013\u0001\"\u0001\u0002N!9\u0011\u0011L\u0001\u0005\u0002\u0005m\u0003bBA4\u0003\u0011\u0005\u0011\u0011\u000e\u0005\b\u0003k\nA\u0011AA<\u0011\u001d\t\u0019)\u0001C\u0001\u0003\u000bCq!!%\u0002\t\u0003\t\u0019\nC\u0004\u0002 \u0006!\t!!)\t\u000f\u00055\u0016\u0001\"\u0001\u00020\"9\u00111X\u0001\u0005\u0002\u0005u\u0006bBAe\u0003\u0011\u0005\u00111\u001a\u0005\b\u0003/\fA\u0011AAm\u0011\u001d\u0011\t!\u0001C\u0001\u0005\u0007\tQAW0FqRT!\u0001J\u0013\u0002\u0017\r|gN^3sg&|gn\u001d\u0006\u0003M\u001d\naa]5sKVl\'\"\u0001\u0015\u0002\u0007=\u0014xm\u0001\u0001\u0011\u0005-\nQ\"A\u0012\u0003\u000bi{V\t\u001f;\u0014\u0005\u0005q\u0003CA\u00183\u001b\u0005\u0001$\"A\u0019\u0002\u000bM\u001c\u0017\r\\1\n\u0005M\u0002$AB!osJ+g-\u0001\u0004=S:LGO\u0010\u000b\u0002U\u0005\u0001\u0012n]%o%\u0006tw-Z*jO:,G\r\u000f\u000b\u0003qq\u0002\"!\u000f\u001e\u000e\u0003\u0015J!aO\u0013\u0003\u0003\tCQ!P\u0002A\u0002y\n\u0011A\u001c\t\u0003s}J!\u0001Q\u0013\u0003\u0003iC#a\u0001\"\u0011\u0005e\u001a\u0015B\u0001#&\u0005\u0011\u0001XO]3\u0002#%\u001c\u0018J\u001c*b]\u001e,7+[4oK\u0012\fd\u0007\u0006\u00029\u000f\")Q\b\u0002a\u0001}!\u0012AAQ\u0001\u0012SNLeNU1oO\u0016\u001c\u0016n\u001a8fIN\u0012DC\u0001\u001dL\u0011\u0015iT\u00011\u0001?Q\t)!)A\tjg&s\'+\u00198hKNKwM\\3emQ\"\"\u0001O(\t\u000bu2\u0001\u0019\u0001 )\u0005\u0019\u0011\u0015AC5t\u0013:\u0014\u0016M\\4f\u001dR\u0011\u0001h\u0015\u0005\u0006{\u001d\u0001\rA\u0010\u0015\u0003\u000f\t\u000b!#[:J]J\u000bgnZ3V]NLwM\\3eqQ\u0011\u0001h\u0016\u0005\u0006{!\u0001\rA\u0010\u0015\u0003\u0011\t\u000b1#[:J]J\u000bgnZ3V]NLwM\\3ecY\"\"\u0001O.\t\u000buJ\u0001\u0019\u0001 )\u0005%\u0011\u0015aE5t\u0013:\u0014\u0016M\\4f+:\u001c\u0018n\u001a8fIN\u0012DC\u0001\u001d`\u0011\u0015i$\u00021\u0001?Q\tQ!)A\njg&s\'+\u00198hKVs7/[4oK\u00124D\u0007\u0006\u00029G\")Qh\u0003a\u0001}!\u00121BQ\u0001\u0004i>\u0014EC\u0001\u001dh\u0011\u0015iD\u00021\u0001?Q\ta!)A\u0002u_j#\"AP6\t\u000buj\u0001\u0019\u0001 )\u00055\u0011\u0015\u0001\u0002;p5b\"\"a\u001c:\u0011\u0005e\u0002\u0018BA9&\u0005\tQ\u0006\bC\u0003>\u001d\u0001\u0007a\b\u000b\u0002\u000f\u0005\u0006)Ao\u001c.2mQ\u0011a/\u001f\t\u0003s]L!\u0001_\u0013\u0003\u0007i\u000bd\u0007C\u0003>\u001f\u0001\u0007a\b\u000b\u0002\u0010\u0005\u0006)Ao\u001c.4eQ\u0019Q0!\u0001\u0011\u0005er\u0018BA@&\u0005\rQ6G\r\u0005\u0006{A\u0001\rA\u0010\u0015\u0003!\t\u000bQ\u0001^8[mQ\"B!!\u0003\u0002\u0010A\u0019\u0011(a\u0003\n\u0007\u00055QEA\u0002[mQBQ!P\tA\u0002yB#!\u0005\"\u0002\u0007Q|g\n\u0006\u0003\u0002\u0018\u0005u\u0001cA\u001d\u0002\u001a%\u0019\u00111D\u0013\u0003\u00039CQ!\u0010\nA\u0002yB#A\u0005\"\u0002\tQ|g\n\u000f\u000b\u0005\u0003K\tY\u0003E\u0002:\u0003OI1!!\u000b&\u0005\tq\u0005\bC\u0003>\'\u0001\u0007a\b\u000b\u0002\u0014\u0005\u0006)Ao\u001c(2mQ!\u00111GA\u001d!\rI\u0014QG\u0005\u0004\u0003o)#a\u0001(2m!)Q\b\u0006a\u0001}!\u0012ACQ\u0001\u0006i>t5G\r\u000b\u0005\u0003\u0003\n9\u0005E\u0002:\u0003\u0007J1!!\u0012&\u0005\rq5G\r\u0005\u0006{U\u0001\rA\u0010\u0015\u0003+\t\u000bQ\u0001^8OmQ\"B!a\u0014\u0002VA\u0019\u0011(!\u0015\n\u0007\u0005MSEA\u0002OmQBQ!\u0010\fA\u0002yB#A\u0006\"\u0002\tQ|7\u000b\u000f\u000b\u0005\u0003;\n\u0019\u0007E\u0002:\u0003?J1!!\u0019&\u0005\t\u0019\u0006\bC\u0003>/\u0001\u0007a\b\u000b\u0002\u0018\u0005\u0006)Ao\\*2mQ!\u00111NA9!\rI\u0014QN\u0005\u0004\u0003_*#aA*2m!)Q\b\u0007a\u0001}!\u0012\u0001DQ\u0001\u0006i>\u001c6G\r\u000b\u0005\u0003s\ny\bE\u0002:\u0003wJ1!! &\u0005\r\u00196G\r\u0005\u0006{e\u0001\rA\u0010\u0015\u00033\t\u000bQ\u0001^8TmQ\"B!a\"\u0002\u000eB\u0019\u0011(!#\n\u0007\u0005-UEA\u0002TmQBQ!\u0010\u000eA\u0002yB#A\u0007\"\u0002\tQ|W\u000b\u000f\u000b\u0005\u0003+\u000bY\nE\u0002:\u0003/K1!!\'&\u0005\t)\u0006\bC\u0003>7\u0001\u0007a\b\u000b\u0002\u001c\u0005\u0006)Ao\\+2mQ!\u00111UAU!\rI\u0014QU\u0005\u0004\u0003O+#aA+2m!)Q\b\ba\u0001}!\u0012ADQ\u0001\u0006i>,6G\r\u000b\u0005\u0003c\u000b9\fE\u0002:\u0003gK1!!.&\u0005\r)6G\r\u0005\u0006{u\u0001\rA\u0010\u0015\u0003;\t\u000bQ\u0001^8VmQ\"B!a0\u0002FB\u0019\u0011(!1\n\u0007\u0005\rWEA\u0002VmQBQ!\u0010\u0010A\u0002yB#A\b\"\u0002\u0007Q|\'\u000b\u0006\u0003\u0002N\u0006M\u0007cA\u001d\u0002P&\u0019\u0011\u0011[\u0013\u0003\u0003ICQ!P\u0010A\u0002yB#a\b\"\u0002\u0011Q|\')\u001b8bef$B!a7\u0002~B1\u0011Q\\Ay\u0003+sA!a8\u0002n:!\u0011\u0011]Av\u001d\u0011\t\u0019/!;\u000e\u0005\u0005\u0015(bAAtS\u00051AH]8pizJ\u0011\u0001K\u0005\u0003M\u001dJ1!a<&\u0003\u001d\u0001\u0018mY6bO\u0016LA!a=\u0002v\n\u0019\u0011j\u0015.\n\t\u0005]\u0018\u0011 \u0002\r!\u0006\u001c7.Y4f)J\f\u0017\u000e\u001e\u0006\u0004\u0003w,\u0013!\u0003\u0013j]R,\'O\\1m\u0011\u0015i\u0004\u00051\u0001?Q\t\u0001#)\u0001\u0006ge>l\')\u001b8bef$2A\u0010B\u0003\u0011\u001d\u00119!\ta\u0001\u00037\f1AY5oQ\t\t#\t
    #9 = Utf8               fromBinary
   #10 = Utf8               (Lorg/sireum/IS;)Lorg/sireum/Z;
   #11 = Utf8               (Lorg/sireum/IS<Lorg/sireum/Z;Lorg/sireum/U8;>;)Lorg/sireum/Z;
   #12 = Utf8               bin
   #13 = Utf8               org/sireum/conversions/Z_Ext$
   #14 = Class              #13           // org/sireum/conversions/Z_Ext$
   #15 = Utf8               MODULE$
   #16 = Utf8               Lorg/sireum/conversions/Z_Ext$;
   #17 = NameAndType        #15:#16       // MODULE$:Lorg/sireum/conversions/Z_Ext$;
   #18 = Fieldref           #14.#17       // org/sireum/conversions/Z_Ext$.MODULE$:Lorg/sireum/conversions/Z_Ext$;
   #19 = NameAndType        #9:#10        // fromBinary:(Lorg/sireum/IS;)Lorg/sireum/Z;
   #20 = Methodref          #14.#19       // org/sireum/conversions/Z_Ext$.fromBinary:(Lorg/sireum/IS;)Lorg/sireum/Z;
   #21 = Utf8               Lorg/sireum/IS;
   #22 = Utf8               toBinary
   #23 = Utf8               (Lorg/sireum/Z;)Lorg/sireum/IS;
   #24 = Utf8               (Lorg/sireum/Z;)Lorg/sireum/IS<Lorg/sireum/Z;Lorg/sireum/U8;>;
   #25 = Utf8               n
   #26 = NameAndType        #22:#23       // toBinary:(Lorg/sireum/Z;)Lorg/sireum/IS;
   #27 = Methodref          #14.#26       // org/sireum/conversions/Z_Ext$.toBinary:(Lorg/sireum/Z;)Lorg/sireum/IS;
   #28 = Utf8               Lorg/sireum/Z;
   #29 = Utf8               toR
   #30 = Utf8               (Lorg/sireum/Z;)Lscala/math/BigDecimal;
   #31 = NameAndType        #29:#30       // toR:(Lorg/sireum/Z;)Lscala/math/BigDecimal;
   #32 = Methodref          #14.#31       // org/sireum/conversions/Z_Ext$.toR:(Lorg/sireum/Z;)Lscala/math/BigDecimal;
   #33 = Utf8               toU64
   #34 = Utf8               (Lorg/sireum/Z;)J
   #35 = NameAndType        #33:#34       // toU64:(Lorg/sireum/Z;)J
   #36 = Methodref          #14.#35       // org/sireum/conversions/Z_Ext$.toU64:(Lorg/sireum/Z;)J
   #37 = Utf8               toU32
   #38 = Utf8               (Lorg/sireum/Z;)I
   #39 = NameAndType        #37:#38       // toU32:(Lorg/sireum/Z;)I
   #40 = Methodref          #14.#39       // org/sireum/conversions/Z_Ext$.toU32:(Lorg/sireum/Z;)I
   #41 = Utf8               toU16
   #42 = Utf8               (Lorg/sireum/Z;)S
   #43 = NameAndType        #41:#42       // toU16:(Lorg/sireum/Z;)S
   #44 = Methodref          #14.#43       // org/sireum/conversions/Z_Ext$.toU16:(Lorg/sireum/Z;)S
   #45 = Utf8               toU8
   #46 = Utf8               (Lorg/sireum/Z;)B
   #47 = NameAndType        #45:#46       // toU8:(Lorg/sireum/Z;)B
   #48 = Methodref          #14.#47       // org/sireum/conversions/Z_Ext$.toU8:(Lorg/sireum/Z;)B
   #49 = Utf8               toS64
   #50 = NameAndType        #49:#34       // toS64:(Lorg/sireum/Z;)J
   #51 = Methodref          #14.#50       // org/sireum/conversions/Z_Ext$.toS64:(Lorg/sireum/Z;)J
   #52 = Utf8               toS32
   #53 = NameAndType        #52:#38       // toS32:(Lorg/sireum/Z;)I
   #54 = Methodref          #14.#53       // org/sireum/conversions/Z_Ext$.toS32:(Lorg/sireum/Z;)I
   #55 = Utf8               toS16
   #56 = NameAndType        #55:#42       // toS16:(Lorg/sireum/Z;)S
   #57 = Methodref          #14.#56       // org/sireum/conversions/Z_Ext$.toS16:(Lorg/sireum/Z;)S
   #58 = Utf8               toS8
   #59 = NameAndType        #58:#46       // toS8:(Lorg/sireum/Z;)B
   #60 = Methodref          #14.#59       // org/sireum/conversions/Z_Ext$.toS8:(Lorg/sireum/Z;)B
   #61 = Utf8               toN64
   #62 = Utf8               (Lorg/sireum/Z;)Lorg/sireum/Z;
   #63 = NameAndType        #61:#62       // toN64:(Lorg/sireum/Z;)Lorg/sireum/Z;
   #64 = Methodref          #14.#63       // org/sireum/conversions/Z_Ext$.toN64:(Lorg/sireum/Z;)Lorg/sireum/Z;
   #65 = Utf8               toN32
   #66 = NameAndType        #65:#62       // toN32:(Lorg/sireum/Z;)Lorg/sireum/Z;
   #67 = Methodref          #14.#66       // org/sireum/conversions/Z_Ext$.toN32:(Lorg/sireum/Z;)Lorg/sireum/Z;
   #68 = Utf8               toN16
   #69 = NameAndType        #68:#62       // toN16:(Lorg/sireum/Z;)Lorg/sireum/Z;
   #70 = Methodref          #14.#69       // org/sireum/conversions/Z_Ext$.toN16:(Lorg/sireum/Z;)Lorg/sireum/Z;
   #71 = Utf8               toN8
   #72 = NameAndType        #71:#62       // toN8:(Lorg/sireum/Z;)Lorg/sireum/Z;
   #73 = Methodref          #14.#72       // org/sireum/conversions/Z_Ext$.toN8:(Lorg/sireum/Z;)Lorg/sireum/Z;
   #74 = Utf8               toN
   #75 = NameAndType        #74:#62       // toN:(Lorg/sireum/Z;)Lorg/sireum/Z;
   #76 = Methodref          #14.#75       // org/sireum/conversions/Z_Ext$.toN:(Lorg/sireum/Z;)Lorg/sireum/Z;
   #77 = Utf8               toZ64
   #78 = NameAndType        #77:#62       // toZ64:(Lorg/sireum/Z;)Lorg/sireum/Z;
   #79 = Methodref          #14.#78       // org/sireum/conversions/Z_Ext$.toZ64:(Lorg/sireum/Z;)Lorg/sireum/Z;
   #80 = Utf8               toZ32
   #81 = NameAndType        #80:#62       // toZ32:(Lorg/sireum/Z;)Lorg/sireum/Z;
   #82 = Methodref          #14.#81       // org/sireum/conversions/Z_Ext$.toZ32:(Lorg/sireum/Z;)Lorg/sireum/Z;
   #83 = Utf8               toZ16
   #84 = NameAndType        #83:#62       // toZ16:(Lorg/sireum/Z;)Lorg/sireum/Z;
   #85 = Methodref          #14.#84       // org/sireum/conversions/Z_Ext$.toZ16:(Lorg/sireum/Z;)Lorg/sireum/Z;
   #86 = Utf8               toZ8
   #87 = NameAndType        #86:#62       // toZ8:(Lorg/sireum/Z;)Lorg/sireum/Z;
   #88 = Methodref          #14.#87       // org/sireum/conversions/Z_Ext$.toZ8:(Lorg/sireum/Z;)Lorg/sireum/Z;
   #89 = Utf8               toZ
   #90 = NameAndType        #89:#62       // toZ:(Lorg/sireum/Z;)Lorg/sireum/Z;
   #91 = Methodref          #14.#90       // org/sireum/conversions/Z_Ext$.toZ:(Lorg/sireum/Z;)Lorg/sireum/Z;
   #92 = Utf8               toB
   #93 = Utf8               (Lorg/sireum/Z;)Z
   #94 = NameAndType        #92:#93       // toB:(Lorg/sireum/Z;)Z
   #95 = Methodref          #14.#94       // org/sireum/conversions/Z_Ext$.toB:(Lorg/sireum/Z;)Z
   #96 = Utf8               isInRangeUnsigned64
   #97 = NameAndType        #96:#93       // isInRangeUnsigned64:(Lorg/sireum/Z;)Z
   #98 = Methodref          #14.#97       // org/sireum/conversions/Z_Ext$.isInRangeUnsigned64:(Lorg/sireum/Z;)Z
   #99 = Utf8               isInRangeUnsigned32
  #100 = NameAndType        #99:#93       // isInRangeUnsigned32:(Lorg/sireum/Z;)Z
  #101 = Methodref          #14.#100      // org/sireum/conversions/Z_Ext$.isInRangeUnsigned32:(Lorg/sireum/Z;)Z
  #102 = Utf8               isInRangeUnsigned16
  #103 = NameAndType        #102:#93      // isInRangeUnsigned16:(Lorg/sireum/Z;)Z
  #104 = Methodref          #14.#103      // org/sireum/conversions/Z_Ext$.isInRangeUnsigned16:(Lorg/sireum/Z;)Z
  #105 = Utf8               isInRangeUnsigned8
  #106 = NameAndType        #105:#93      // isInRangeUnsigned8:(Lorg/sireum/Z;)Z
  #107 = Methodref          #14.#106      // org/sireum/conversions/Z_Ext$.isInRangeUnsigned8:(Lorg/sireum/Z;)Z
  #108 = Utf8               isInRangeN
  #109 = NameAndType        #108:#93      // isInRangeN:(Lorg/sireum/Z;)Z
  #110 = Methodref          #14.#109      // org/sireum/conversions/Z_Ext$.isInRangeN:(Lorg/sireum/Z;)Z
  #111 = Utf8               isInRangeSigned64
  #112 = NameAndType        #111:#93      // isInRangeSigned64:(Lorg/sireum/Z;)Z
  #113 = Methodref          #14.#112      // org/sireum/conversions/Z_Ext$.isInRangeSigned64:(Lorg/sireum/Z;)Z
  #114 = Utf8               isInRangeSigned32
  #115 = NameAndType        #114:#93      // isInRangeSigned32:(Lorg/sireum/Z;)Z
  #116 = Methodref          #14.#115      // org/sireum/conversions/Z_Ext$.isInRangeSigned32:(Lorg/sireum/Z;)Z
  #117 = Utf8               isInRangeSigned16
  #118 = NameAndType        #117:#93      // isInRangeSigned16:(Lorg/sireum/Z;)Z
  #119 = Methodref          #14.#118      // org/sireum/conversions/Z_Ext$.isInRangeSigned16:(Lorg/sireum/Z;)Z
  #120 = Utf8               isInRangeSigned8
  #121 = NameAndType        #120:#93      // isInRangeSigned8:(Lorg/sireum/Z;)Z
  #122 = Methodref          #14.#121      // org/sireum/conversions/Z_Ext$.isInRangeSigned8:(Lorg/sireum/Z;)Z
  #123 = Utf8               Code
  #124 = Utf8               LocalVariableTable
  #125 = Utf8               Signature
  #126 = Utf8               MethodParameters
  #127 = Utf8               SourceFile
  #128 = Utf8               RuntimeVisibleAnnotations
  #129 = Utf8               ScalaSig
{
  public static org.sireum.Z fromBinary(org.sireum.IS<org.sireum.Z, org.sireum.U8>);
    descriptor: (Lorg/sireum/IS;)Lorg/sireum/Z;
    flags: (0x0009) ACC_PUBLIC, ACC_STATIC
    Code:
      stack=2, locals=1, args_size=1
         0: getstatic     #18                 // Field org/sireum/conversions/Z_Ext$.MODULE$:Lorg/sireum/conversions/Z_Ext$;
         3: aload_0
         4: invokevirtual #20                 // Method org/sireum/conversions/Z_Ext$.fromBinary:(Lorg/sireum/IS;)Lorg/sireum/Z;
         7: areturn
      LocalVariableTable:
        Start  Length  Slot  Name   Signature
            0       8     0   bin   Lorg/sireum/IS;
    Signature: #11                          // (Lorg/sireum/IS<Lorg/sireum/Z;Lorg/sireum/U8;>;)Lorg/sireum/Z;
    MethodParameters:
      Name                           Flags
      bin                            final

  public static org.sireum.IS<org.sireum.Z, org.sireum.U8> toBinary(org.sireum.Z);
    descriptor: (Lorg/sireum/Z;)Lorg/sireum/IS;
    flags: (0x0009) ACC_PUBLIC, ACC_STATIC
    Code:
      stack=2, locals=1, args_size=1
         0: getstatic     #18                 // Field org/sireum/conversions/Z_Ext$.MODULE$:Lorg/sireum/conversions/Z_Ext$;
         3: aload_0
         4: invokevirtual #27                 // Method org/sireum/conversions/Z_Ext$.toBinary:(Lorg/sireum/Z;)Lorg/sireum/IS;
         7: areturn
      LocalVariableTable:
        Start  Length  Slot  Name   Signature
            0       8     0     n   Lorg/sireum/Z;
    Signature: #24                          // (Lorg/sireum/Z;)Lorg/sireum/IS<Lorg/sireum/Z;Lorg/sireum/U8;>;
    MethodParameters:
      Name                           Flags
      n                              final

  public static scala.math.BigDecimal toR(org.sireum.Z);
    descriptor: (Lorg/sireum/Z;)Lscala/math/BigDecimal;
    flags: (0x0009) ACC_PUBLIC, ACC_STATIC
    Code:
      stack=2, locals=1, args_size=1
         0: getstatic     #18                 // Field org/sireum/conversions/Z_Ext$.MODULE$:Lorg/sireum/conversions/Z_Ext$;
         3: aload_0
         4: invokevirtual #32                 // Method org/sireum/conversions/Z_Ext$.toR:(Lorg/sireum/Z;)Lscala/math/BigDecimal;
         7: areturn
      LocalVariableTable:
        Start  Length  Slot  Name   Signature
            0       8     0     n   Lorg/sireum/Z;
    MethodParameters:
      Name                           Flags
      n                              final

  public static long toU64(org.sireum.Z);
    descriptor: (Lorg/sireum/Z;)J
    flags: (0x0009) ACC_PUBLIC, ACC_STATIC
    Code:
      stack=2, locals=1, args_size=1
         0: getstatic     #18                 // Field org/sireum/conversions/Z_Ext$.MODULE$:Lorg/sireum/conversions/Z_Ext$;
         3: aload_0
         4: invokevirtual #36                 // Method org/sireum/conversions/Z_Ext$.toU64:(Lorg/sireum/Z;)J
         7: lreturn
      LocalVariableTable:
        Start  Length  Slot  Name   Signature
            0       8     0     n   Lorg/sireum/Z;
    MethodParameters:
      Name                           Flags
      n                              final

  public static int toU32(org.sireum.Z);
    descriptor: (Lorg/sireum/Z;)I
    flags: (0x0009) ACC_PUBLIC, ACC_STATIC
    Code:
      stack=2, locals=1, args_size=1
         0: getstatic     #18                 // Field org/sireum/conversions/Z_Ext$.MODULE$:Lorg/sireum/conversions/Z_Ext$;
         3: aload_0
         4: invokevirtual #40                 // Method org/sireum/conversions/Z_Ext$.toU32:(Lorg/sireum/Z;)I
         7: ireturn
      LocalVariableTable:
        Start  Length  Slot  Name   Signature
            0       8     0     n   Lorg/sireum/Z;
    MethodParameters:
      Name                           Flags
      n                              final

  public static short toU16(org.sireum.Z);
    descriptor: (Lorg/sireum/Z;)S
    flags: (0x0009) ACC_PUBLIC, ACC_STATIC
    Code:
      stack=2, locals=1, args_size=1
         0: getstatic     #18                 // Field org/sireum/conversions/Z_Ext$.MODULE$:Lorg/sireum/conversions/Z_Ext$;
         3: aload_0
         4: invokevirtual #44                 // Method org/sireum/conversions/Z_Ext$.toU16:(Lorg/sireum/Z;)S
         7: ireturn
      LocalVariableTable:
        Start  Length  Slot  Name   Signature
            0       8     0     n   Lorg/sireum/Z;
    MethodParameters:
      Name                           Flags
      n                              final

  public static byte toU8(org.sireum.Z);
    descriptor: (Lorg/sireum/Z;)B
    flags: (0x0009) ACC_PUBLIC, ACC_STATIC
    Code:
      stack=2, locals=1, args_size=1
         0: getstatic     #18                 // Field org/sireum/conversions/Z_Ext$.MODULE$:Lorg/sireum/conversions/Z_Ext$;
         3: aload_0
         4: invokevirtual #48                 // Method org/sireum/conversions/Z_Ext$.toU8:(Lorg/sireum/Z;)B
         7: ireturn
      LocalVariableTable:
        Start  Length  Slot  Name   Signature
            0       8     0     n   Lorg/sireum/Z;
    MethodParameters:
      Name                           Flags
      n                              final

  public static long toS64(org.sireum.Z);
    descriptor: (Lorg/sireum/Z;)J
    flags: (0x0009) ACC_PUBLIC, ACC_STATIC
    Code:
      stack=2, locals=1, args_size=1
         0: getstatic     #18                 // Field org/sireum/conversions/Z_Ext$.MODULE$:Lorg/sireum/conversions/Z_Ext$;
         3: aload_0
         4: invokevirtual #51                 // Method org/sireum/conversions/Z_Ext$.toS64:(Lorg/sireum/Z;)J
         7: lreturn
      LocalVariableTable:
        Start  Length  Slot  Name   Signature
            0       8     0     n   Lorg/sireum/Z;
    MethodParameters:
      Name                           Flags
      n                              final

  public static int toS32(org.sireum.Z);
    descriptor: (Lorg/sireum/Z;)I
    flags: (0x0009) ACC_PUBLIC, ACC_STATIC
    Code:
      stack=2, locals=1, args_size=1
         0: getstatic     #18                 // Field org/sireum/conversions/Z_Ext$.MODULE$:Lorg/sireum/conversions/Z_Ext$;
         3: aload_0
         4: invokevirtual #54                 // Method org/sireum/conversions/Z_Ext$.toS32:(Lorg/sireum/Z;)I
         7: ireturn
      LocalVariableTable:
        Start  Length  Slot  Name   Signature
            0       8     0     n   Lorg/sireum/Z;
    MethodParameters:
      Name                           Flags
      n                              final

  public static short toS16(org.sireum.Z);
    descriptor: (Lorg/sireum/Z;)S
    flags: (0x0009) ACC_PUBLIC, ACC_STATIC
    Code:
      stack=2, locals=1, args_size=1
         0: getstatic     #18                 // Field org/sireum/conversions/Z_Ext$.MODULE$:Lorg/sireum/conversions/Z_Ext$;
         3: aload_0
         4: invokevirtual #57                 // Method org/sireum/conversions/Z_Ext$.toS16:(Lorg/sireum/Z;)S
         7: ireturn
      LocalVariableTable:
        Start  Length  Slot  Name   Signature
            0       8     0     n   Lorg/sireum/Z;
    MethodParameters:
      Name                           Flags
      n                              final

  public static byte toS8(org.sireum.Z);
    descriptor: (Lorg/sireum/Z;)B
    flags: (0x0009) ACC_PUBLIC, ACC_STATIC
    Code:
      stack=2, locals=1, args_size=1
         0: getstatic     #18                 // Field org/sireum/conversions/Z_Ext$.MODULE$:Lorg/sireum/conversions/Z_Ext$;
         3: aload_0
         4: invokevirtual #60                 // Method org/sireum/conversions/Z_Ext$.toS8:(Lorg/sireum/Z;)B
         7: ireturn
      LocalVariableTable:
        Start  Length  Slot  Name   Signature
            0       8     0     n   Lorg/sireum/Z;
    MethodParameters:
      Name                           Flags
      n                              final

  public static org.sireum.Z toN64(org.sireum.Z);
    descriptor: (Lorg/sireum/Z;)Lorg/sireum/Z;
    flags: (0x0009) ACC_PUBLIC, ACC_STATIC
    Code:
      stack=2, locals=1, args_size=1
         0: getstatic     #18                 // Field org/sireum/conversions/Z_Ext$.MODULE$:Lorg/sireum/conversions/Z_Ext$;
         3: aload_0
         4: invokevirtual #64                 // Method org/sireum/conversions/Z_Ext$.toN64:(Lorg/sireum/Z;)Lorg/sireum/Z;
         7: areturn
      LocalVariableTable:
        Start  Length  Slot  Name   Signature
            0       8     0     n   Lorg/sireum/Z;
    MethodParameters:
      Name                           Flags
      n                              final

  public static org.sireum.Z toN32(org.sireum.Z);
    descriptor: (Lorg/sireum/Z;)Lorg/sireum/Z;
    flags: (0x0009) ACC_PUBLIC, ACC_STATIC
    Code:
      stack=2, locals=1, args_size=1
         0: getstatic     #18                 // Field org/sireum/conversions/Z_Ext$.MODULE$:Lorg/sireum/conversions/Z_Ext$;
         3: aload_0
         4: invokevirtual #67                 // Method org/sireum/conversions/Z_Ext$.toN32:(Lorg/sireum/Z;)Lorg/sireum/Z;
         7: areturn
      LocalVariableTable:
        Start  Length  Slot  Name   Signature
            0       8     0     n   Lorg/sireum/Z;
    MethodParameters:
      Name                           Flags
      n                              final

  public static org.sireum.Z toN16(org.sireum.Z);
    descriptor: (Lorg/sireum/Z;)Lorg/sireum/Z;
    flags: (0x0009) ACC_PUBLIC, ACC_STATIC
    Code:
      stack=2, locals=1, args_size=1
         0: getstatic     #18                 // Field org/sireum/conversions/Z_Ext$.MODULE$:Lorg/sireum/conversions/Z_Ext$;
         3: aload_0
         4: invokevirtual #70                 // Method org/sireum/conversions/Z_Ext$.toN16:(Lorg/sireum/Z;)Lorg/sireum/Z;
         7: areturn
      LocalVariableTable:
        Start  Length  Slot  Name   Signature
            0       8     0     n   Lorg/sireum/Z;
    MethodParameters:
      Name                           Flags
      n                              final

  public static org.sireum.Z toN8(org.sireum.Z);
    descriptor: (Lorg/sireum/Z;)Lorg/sireum/Z;
    flags: (0x0009) ACC_PUBLIC, ACC_STATIC
    Code:
      stack=2, locals=1, args_size=1
         0: getstatic     #18                 // Field org/sireum/conversions/Z_Ext$.MODULE$:Lorg/sireum/conversions/Z_Ext$;
         3: aload_0
         4: invokevirtual #73                 // Method org/sireum/conversions/Z_Ext$.toN8:(Lorg/sireum/Z;)Lorg/sireum/Z;
         7: areturn
      LocalVariableTable:
        Start  Length  Slot  Name   Signature
            0       8     0     n   Lorg/sireum/Z;
    MethodParameters:
      Name                           Flags
      n                              final

  public static org.sireum.Z toN(org.sireum.Z);
    descriptor: (Lorg/sireum/Z;)Lorg/sireum/Z;
    flags: (0x0009) ACC_PUBLIC, ACC_STATIC
    Code:
      stack=2, locals=1, args_size=1
         0: getstatic     #18                 // Field org/sireum/conversions/Z_Ext$.MODULE$:Lorg/sireum/conversions/Z_Ext$;
         3: aload_0
         4: invokevirtual #76                 // Method org/sireum/conversions/Z_Ext$.toN:(Lorg/sireum/Z;)Lorg/sireum/Z;
         7: areturn
      LocalVariableTable:
        Start  Length  Slot  Name   Signature
            0       8     0     n   Lorg/sireum/Z;
    MethodParameters:
      Name                           Flags
      n                              final

  public static org.sireum.Z toZ64(org.sireum.Z);
    descriptor: (Lorg/sireum/Z;)Lorg/sireum/Z;
    flags: (0x0009) ACC_PUBLIC, ACC_STATIC
    Code:
      stack=2, locals=1, args_size=1
         0: getstatic     #18                 // Field org/sireum/conversions/Z_Ext$.MODULE$:Lorg/sireum/conversions/Z_Ext$;
         3: aload_0
         4: invokevirtual #79                 // Method org/sireum/conversions/Z_Ext$.toZ64:(Lorg/sireum/Z;)Lorg/sireum/Z;
         7: areturn
      LocalVariableTable:
        Start  Length  Slot  Name   Signature
            0       8     0     n   Lorg/sireum/Z;
    MethodParameters:
      Name                           Flags
      n                              final

  public static org.sireum.Z toZ32(org.sireum.Z);
    descriptor: (Lorg/sireum/Z;)Lorg/sireum/Z;
    flags: (0x0009) ACC_PUBLIC, ACC_STATIC
    Code:
      stack=2, locals=1, args_size=1
         0: getstatic     #18                 // Field org/sireum/conversions/Z_Ext$.MODULE$:Lorg/sireum/conversions/Z_Ext$;
         3: aload_0
         4: invokevirtual #82                 // Method org/sireum/conversions/Z_Ext$.toZ32:(Lorg/sireum/Z;)Lorg/sireum/Z;
         7: areturn
      LocalVariableTable:
        Start  Length  Slot  Name   Signature
            0       8     0     n   Lorg/sireum/Z;
    MethodParameters:
      Name                           Flags
      n                              final

  public static org.sireum.Z toZ16(org.sireum.Z);
    descriptor: (Lorg/sireum/Z;)Lorg/sireum/Z;
    flags: (0x0009) ACC_PUBLIC, ACC_STATIC
    Code:
      stack=2, locals=1, args_size=1
         0: getstatic     #18                 // Field org/sireum/conversions/Z_Ext$.MODULE$:Lorg/sireum/conversions/Z_Ext$;
         3: aload_0
         4: invokevirtual #85                 // Method org/sireum/conversions/Z_Ext$.toZ16:(Lorg/sireum/Z;)Lorg/sireum/Z;
         7: areturn
      LocalVariableTable:
        Start  Length  Slot  Name   Signature
            0       8     0     n   Lorg/sireum/Z;
    MethodParameters:
      Name                           Flags
      n                              final

  public static org.sireum.Z toZ8(org.sireum.Z);
    descriptor: (Lorg/sireum/Z;)Lorg/sireum/Z;
    flags: (0x0009) ACC_PUBLIC, ACC_STATIC
    Code:
      stack=2, locals=1, args_size=1
         0: getstatic     #18                 // Field org/sireum/conversions/Z_Ext$.MODULE$:Lorg/sireum/conversions/Z_Ext$;
         3: aload_0
         4: invokevirtual #88                 // Method org/sireum/conversions/Z_Ext$.toZ8:(Lorg/sireum/Z;)Lorg/sireum/Z;
         7: areturn
      LocalVariableTable:
        Start  Length  Slot  Name   Signature
            0       8     0     n   Lorg/sireum/Z;
    MethodParameters:
      Name                           Flags
      n                              final

  public static org.sireum.Z toZ(org.sireum.Z);
    descriptor: (Lorg/sireum/Z;)Lorg/sireum/Z;
    flags: (0x0009) ACC_PUBLIC, ACC_STATIC
    Code:
      stack=2, locals=1, args_size=1
         0: getstatic     #18                 // Field org/sireum/conversions/Z_Ext$.MODULE$:Lorg/sireum/conversions/Z_Ext$;
         3: aload_0
         4: invokevirtual #91                 // Method org/sireum/conversions/Z_Ext$.toZ:(Lorg/sireum/Z;)Lorg/sireum/Z;
         7: areturn
      LocalVariableTable:
        Start  Length  Slot  Name   Signature
            0       8     0     n   Lorg/sireum/Z;
    MethodParameters:
      Name                           Flags
      n                              final

  public static boolean toB(org.sireum.Z);
    descriptor: (Lorg/sireum/Z;)Z
    flags: (0x0009) ACC_PUBLIC, ACC_STATIC
    Code:
      stack=2, locals=1, args_size=1
         0: getstatic     #18                 // Field org/sireum/conversions/Z_Ext$.MODULE$:Lorg/sireum/conversions/Z_Ext$;
         3: aload_0
         4: invokevirtual #95                 // Method org/sireum/conversions/Z_Ext$.toB:(Lorg/sireum/Z;)Z
         7: ireturn
      LocalVariableTable:
        Start  Length  Slot  Name   Signature
            0       8     0     n   Lorg/sireum/Z;
    MethodParameters:
      Name                           Flags
      n                              final

  public static boolean isInRangeUnsigned64(org.sireum.Z);
    descriptor: (Lorg/sireum/Z;)Z
    flags: (0x0009) ACC_PUBLIC, ACC_STATIC
    Code:
      stack=2, locals=1, args_size=1
         0: getstatic     #18                 // Field org/sireum/conversions/Z_Ext$.MODULE$:Lorg/sireum/conversions/Z_Ext$;
         3: aload_0
         4: invokevirtual #98                 // Method org/sireum/conversions/Z_Ext$.isInRangeUnsigned64:(Lorg/sireum/Z;)Z
         7: ireturn
      LocalVariableTable:
        Start  Length  Slot  Name   Signature
            0       8     0     n   Lorg/sireum/Z;
    MethodParameters:
      Name                           Flags
      n                              final

  public static boolean isInRangeUnsigned32(org.sireum.Z);
    descriptor: (Lorg/sireum/Z;)Z
    flags: (0x0009) ACC_PUBLIC, ACC_STATIC
    Code:
      stack=2, locals=1, args_size=1
         0: getstatic     #18                 // Field org/sireum/conversions/Z_Ext$.MODULE$:Lorg/sireum/conversions/Z_Ext$;
         3: aload_0
         4: invokevirtual #101                // Method org/sireum/conversions/Z_Ext$.isInRangeUnsigned32:(Lorg/sireum/Z;)Z
         7: ireturn
      LocalVariableTable:
        Start  Length  Slot  Name   Signature
            0       8     0     n   Lorg/sireum/Z;
    MethodParameters:
      Name                           Flags
      n                              final

  public static boolean isInRangeUnsigned16(org.sireum.Z);
    descriptor: (Lorg/sireum/Z;)Z
    flags: (0x0009) ACC_PUBLIC, ACC_STATIC
    Code:
      stack=2, locals=1, args_size=1
         0: getstatic     #18                 // Field org/sireum/conversions/Z_Ext$.MODULE$:Lorg/sireum/conversions/Z_Ext$;
         3: aload_0
         4: invokevirtual #104                // Method org/sireum/conversions/Z_Ext$.isInRangeUnsigned16:(Lorg/sireum/Z;)Z
         7: ireturn
      LocalVariableTable:
        Start  Length  Slot  Name   Signature
            0       8     0     n   Lorg/sireum/Z;
    MethodParameters:
      Name                           Flags
      n                              final

  public static boolean isInRangeUnsigned8(org.sireum.Z);
    descriptor: (Lorg/sireum/Z;)Z
    flags: (0x0009) ACC_PUBLIC, ACC_STATIC
    Code:
      stack=2, locals=1, args_size=1
         0: getstatic     #18                 // Field org/sireum/conversions/Z_Ext$.MODULE$:Lorg/sireum/conversions/Z_Ext$;
         3: aload_0
         4: invokevirtual #107                // Method org/sireum/conversions/Z_Ext$.isInRangeUnsigned8:(Lorg/sireum/Z;)Z
         7: ireturn
      LocalVariableTable:
        Start  Length  Slot  Name   Signature
            0       8     0     n   Lorg/sireum/Z;
    MethodParameters:
      Name                           Flags
      n                              final

  public static boolean isInRangeN(org.sireum.Z);
    descriptor: (Lorg/sireum/Z;)Z
    flags: (0x0009) ACC_PUBLIC, ACC_STATIC
    Code:
      stack=2, locals=1, args_size=1
         0: getstatic     #18                 // Field org/sireum/conversions/Z_Ext$.MODULE$:Lorg/sireum/conversions/Z_Ext$;
         3: aload_0
         4: invokevirtual #110                // Method org/sireum/conversions/Z_Ext$.isInRangeN:(Lorg/sireum/Z;)Z
         7: ireturn
      LocalVariableTable:
        Start  Length  Slot  Name   Signature
            0       8     0     n   Lorg/sireum/Z;
    MethodParameters:
      Name                           Flags
      n                              final

  public static boolean isInRangeSigned64(org.sireum.Z);
    descriptor: (Lorg/sireum/Z;)Z
    flags: (0x0009) ACC_PUBLIC, ACC_STATIC
    Code:
      stack=2, locals=1, args_size=1
         0: getstatic     #18                 // Field org/sireum/conversions/Z_Ext$.MODULE$:Lorg/sireum/conversions/Z_Ext$;
         3: aload_0
         4: invokevirtual #113                // Method org/sireum/conversions/Z_Ext$.isInRangeSigned64:(Lorg/sireum/Z;)Z
         7: ireturn
      LocalVariableTable:
        Start  Length  Slot  Name   Signature
            0       8     0     n   Lorg/sireum/Z;
    MethodParameters:
      Name                           Flags
      n                              final

  public static boolean isInRangeSigned32(org.sireum.Z);
    descriptor: (Lorg/sireum/Z;)Z
    flags: (0x0009) ACC_PUBLIC, ACC_STATIC
    Code:
      stack=2, locals=1, args_size=1
         0: getstatic     #18                 // Field org/sireum/conversions/Z_Ext$.MODULE$:Lorg/sireum/conversions/Z_Ext$;
         3: aload_0
         4: invokevirtual #116                // Method org/sireum/conversions/Z_Ext$.isInRangeSigned32:(Lorg/sireum/Z;)Z
         7: ireturn
      LocalVariableTable:
        Start  Length  Slot  Name   Signature
            0       8     0     n   Lorg/sireum/Z;
    MethodParameters:
      Name                           Flags
      n                              final

  public static boolean isInRangeSigned16(org.sireum.Z);
    descriptor: (Lorg/sireum/Z;)Z
    flags: (0x0009) ACC_PUBLIC, ACC_STATIC
    Code:
      stack=2, locals=1, args_size=1
         0: getstatic     #18                 // Field org/sireum/conversions/Z_Ext$.MODULE$:Lorg/sireum/conversions/Z_Ext$;
         3: aload_0
         4: invokevirtual #119                // Method org/sireum/conversions/Z_Ext$.isInRangeSigned16:(Lorg/sireum/Z;)Z
         7: ireturn
      LocalVariableTable:
        Start  Length  Slot  Name   Signature
            0       8     0     n   Lorg/sireum/Z;
    MethodParameters:
      Name                           Flags
      n                              final

  public static boolean isInRangeSigned8(org.sireum.Z);
    descriptor: (Lorg/sireum/Z;)Z
    flags: (0x0009) ACC_PUBLIC, ACC_STATIC
    Code:
      stack=2, locals=1, args_size=1
         0: getstatic     #18                 // Field org/sireum/conversions/Z_Ext$.MODULE$:Lorg/sireum/conversions/Z_Ext$;
         3: aload_0
         4: invokevirtual #122                // Method org/sireum/conversions/Z_Ext$.isInRangeSigned8:(Lorg/sireum/Z;)Z
         7: ireturn
      LocalVariableTable:
        Start  Length  Slot  Name   Signature
            0       8     0     n   Lorg/sireum/Z;
    MethodParameters:
      Name                           Flags
      n                              final
}
SourceFile: "extension.scala"
RuntimeVisibleAnnotations:
  0: #6(#7=s#8)
    scala.reflect.ScalaSignature(
      bytes="\u0006\u0005\t-q!\u0002\u0012$\u0011\u0003Qc!\u0002\u0017$\u0011\u0003i\u0003\"\u0002\u001b\u0002\t\u0003)\u0004\"\u0002\u001c\u0002\t\u00039\u0004\"B#\u0002\t\u00031\u0005\"B%\u0002\t\u0003Q\u0005\"B\'\u0002\t\u0003q\u0005\"B)\u0002\t\u0003\u0011\u0006\"B+\u0002\t\u00031\u0006\"B-\u0002\t\u0003Q\u0006\"B/\u0002\t\u0003q\u0006\"B1\u0002\t\u0003\u0011\u0007\"B3\u0002\t\u00031\u0007\"B5\u0002\t\u0003Q\u0007\"B7\u0002\t\u0003q\u0007\"\u0002;\u0002\t\u0003)\b\"B>\u0002\t\u0003a\bbBA\u0003\u0003\u0011\u0005\u0011q\u0001\u0005\b\u0003\'\tA\u0011AA\u000b\u0011\u001d\t\t#\u0001C\u0001\u0003GAq!a\f\u0002\t\u0003\t\t\u0004C\u0004\u0002>\u0005!\t!a\u0010\t\u000f\u0005-\u0013\u0001\"\u0001\u0002N!9\u0011\u0011L\u0001\u0005\u0002\u0005m\u0003bBA4\u0003\u0011\u0005\u0011\u0011\u000e\u0005\b\u0003k\nA\u0011AA<\u0011\u001d\t\u0019)\u0001C\u0001\u0003\u000bCq!!%\u0002\t\u0003\t\u0019\nC\u0004\u0002 \u0006!\t!!)\t\u000f\u00055\u0016\u0001\"\u0001\u00020\"9\u00111X\u0001\u0005\u0002\u0005u\u0006bBAe\u0003\u0011\u0005\u00111\u001a\u0005\b\u0003/\fA\u0011AAm\u0011\u001d\u0011\t!\u0001C\u0001\u0005\u0007\tQAW0FqRT!\u0001J\u0013\u0002\u0017\r|gN^3sg&|gn\u001d\u0006\u0003M\u001d\naa]5sKVl\'\"\u0001\u0015\u0002\u0007=\u0014xm\u0001\u0001\u0011\u0005-\nQ\"A\u0012\u0003\u000bi{V\t\u001f;\u0014\u0005\u0005q\u0003CA\u00183\u001b\u0005\u0001$\"A\u0019\u0002\u000bM\u001c\u0017\r\\1\n\u0005M\u0002$AB!osJ+g-\u0001\u0004=S:LGO\u0010\u000b\u0002U\u0005\u0001\u0012n]%o%\u0006tw-Z*jO:,G\r\u000f\u000b\u0003qq\u0002\"!\u000f\u001e\u000e\u0003\u0015J!aO\u0013\u0003\u0003\tCQ!P\u0002A\u0002y\n\u0011A\u001c\t\u0003s}J!\u0001Q\u0013\u0003\u0003iC#a\u0001\"\u0011\u0005e\u001a\u0015B\u0001#&\u0005\u0011\u0001XO]3\u0002#%\u001c\u0018J\u001c*b]\u001e,7+[4oK\u0012\fd\u0007\u0006\u00029\u000f\")Q\b\u0002a\u0001}!\u0012AAQ\u0001\u0012SNLeNU1oO\u0016\u001c\u0016n\u001a8fIN\u0012DC\u0001\u001dL\u0011\u0015iT\u00011\u0001?Q\t)!)A\tjg&s\'+\u00198hKNKwM\\3emQ\"\"\u0001O(\t\u000bu2\u0001\u0019\u0001 )\u0005\u0019\u0011\u0015AC5t\u0013:\u0014\u0016M\\4f\u001dR\u0011\u0001h\u0015\u0005\u0006{\u001d\u0001\rA\u0010\u0015\u0003\u000f\t\u000b!#[:J]J\u000bgnZ3V]NLwM\\3eqQ\u0011\u0001h\u0016\u0005\u0006{!\u0001\rA\u0010\u0015\u0003\u0011\t\u000b1#[:J]J\u000bgnZ3V]NLwM\\3ecY\"\"\u0001O.\t\u000buJ\u0001\u0019\u0001 )\u0005%\u0011\u0015aE5t\u0013:\u0014\u0016M\\4f+:\u001c\u0018n\u001a8fIN\u0012DC\u0001\u001d`\u0011\u0015i$\u00021\u0001?Q\tQ!)A\njg&s\'+\u00198hKVs7/[4oK\u00124D\u0007\u0006\u00029G\")Qh\u0003a\u0001}!\u00121BQ\u0001\u0004i>\u0014EC\u0001\u001dh\u0011\u0015iD\u00021\u0001?Q\ta!)A\u0002u_j#\"AP6\t\u000buj\u0001\u0019\u0001 )\u00055\u0011\u0015\u0001\u0002;p5b\"\"a\u001c:\u0011\u0005e\u0002\u0018BA9&\u0005\tQ\u0006\bC\u0003>\u001d\u0001\u0007a\b\u000b\u0002\u000f\u0005\u0006)Ao\u001c.2mQ\u0011a/\u001f\t\u0003s]L!\u0001_\u0013\u0003\u0007i\u000bd\u0007C\u0003>\u001f\u0001\u0007a\b\u000b\u0002\u0010\u0005\u0006)Ao\u001c.4eQ\u0019Q0!\u0001\u0011\u0005er\u0018BA@&\u0005\rQ6G\r\u0005\u0006{A\u0001\rA\u0010\u0015\u0003!\t\u000bQ\u0001^8[mQ\"B!!\u0003\u0002\u0010A\u0019\u0011(a\u0003\n\u0007\u00055QEA\u0002[mQBQ!P\tA\u0002yB#!\u0005\"\u0002\u0007Q|g\n\u0006\u0003\u0002\u0018\u0005u\u0001cA\u001d\u0002\u001a%\u0019\u00111D\u0013\u0003\u00039CQ!\u0010\nA\u0002yB#A\u0005\"\u0002\tQ|g\n\u000f\u000b\u0005\u0003K\tY\u0003E\u0002:\u0003OI1!!\u000b&\u0005\tq\u0005\bC\u0003>\'\u0001\u0007a\b\u000b\u0002\u0014\u0005\u0006)Ao\u001c(2mQ!\u00111GA\u001d!\rI\u0014QG\u0005\u0004\u0003o)#a\u0001(2m!)Q\b\u0006a\u0001}!\u0012ACQ\u0001\u0006i>t5G\r\u000b\u0005\u0003\u0003\n9\u0005E\u0002:\u0003\u0007J1!!\u0012&\u0005\rq5G\r\u0005\u0006{U\u0001\rA\u0010\u0015\u0003+\t\u000bQ\u0001^8OmQ\"B!a\u0014\u0002VA\u0019\u0011(!\u0015\n\u0007\u0005MSEA\u0002OmQBQ!\u0010\fA\u0002yB#A\u0006\"\u0002\tQ|7\u000b\u000f\u000b\u0005\u0003;\n\u0019\u0007E\u0002:\u0003?J1!!\u0019&\u0005\t\u0019\u0006\bC\u0003>/\u0001\u0007a\b\u000b\u0002\u0018\u0005\u0006)Ao\\*2mQ!\u00111NA9!\rI\u0014QN\u0005\u0004\u0003_*#aA*2m!)Q\b\u0007a\u0001}!\u0012\u0001DQ\u0001\u0006i>\u001c6G\r\u000b\u0005\u0003s\ny\bE\u0002:\u0003wJ1!! &\u0005\r\u00196G\r\u0005\u0006{e\u0001\rA\u0010\u0015\u00033\t\u000bQ\u0001^8TmQ\"B!a\"\u0002\u000eB\u0019\u0011(!#\n\u0007\u0005-UEA\u0002TmQBQ!\u0010\u000eA\u0002yB#A\u0007\"\u0002\tQ|W\u000b\u000f\u000b\u0005\u0003+\u000bY\nE\u0002:\u0003/K1!!\'&\u0005\t)\u0006\bC\u0003>7\u0001\u0007a\b\u000b\u0002\u001c\u0005\u0006)Ao\\+2mQ!\u00111UAU!\rI\u0014QU\u0005\u0004\u0003O+#aA+2m!)Q\b\ba\u0001}!\u0012ADQ\u0001\u0006i>,6G\r\u000b\u0005\u0003c\u000b9\fE\u0002:\u0003gK1!!.&\u0005\r)6G\r\u0005\u0006{u\u0001\rA\u0010\u0015\u0003;\t\u000bQ\u0001^8VmQ\"B!a0\u0002FB\u0019\u0011(!1\n\u0007\u0005\rWEA\u0002VmQBQ!\u0010\u0010A\u0002yB#A\b\"\u0002\u0007Q|\'\u000b\u0006\u0003\u0002N\u0006M\u0007cA\u001d\u0002P&\u0019\u0011\u0011[\u0013\u0003\u0003ICQ!P\u0010A\u0002yB#a\b\"\u0002\u0011Q|\')\u001b8bef$B!a7\u0002~B1\u0011Q\\Ay\u0003+sA!a8\u0002n:!\u0011\u0011]Av\u001d\u0011\t\u0019/!;\u000e\u0005\u0005\u0015(bAAtS\u00051AH]8pizJ\u0011\u0001K\u0005\u0003M\u001dJ1!a<&\u0003\u001d\u0001\u0018mY6bO\u0016LA!a=\u0002v\n\u0019\u0011j\u0015.\n\t\u0005]\u0018\u0011 \u0002\r!\u0006\u001c7.Y4f)J\f\u0017\u000e\u001e\u0006\u0004\u0003w,\u0013!\u0003\u0013j]R,\'O\\1m\u0011\u0015i\u0004\u00051\u0001?Q\t\u0001#)\u0001\u0006ge>l\')\u001b8bef$2A\u0010B\u0003\u0011\u001d\u00119!\ta\u0001\u00037\f1AY5oQ\t\t#\t"
    )
  ScalaSig: length = 0x3 (unknown attribute)
   05 02 00
