Classfile /Users/mw/Projects/slang-braindump/.jar/jar11/assemble/slang-braindump/assemble/content/org/scalatest/verbs/MustVerb.class
  Last modified May 29, 2022; size 2352 bytes
  SHA-256 checksum e2e980fed379ae9a1feff842885e3da420040808d183bc1471f0225aadb3901d
  Compiled from "MustVerb.scala"
public interface org.scalatest.verbs.MustVerb
  minor version: 0
  major version: 52
  flags: (0x0601) ACC_PUBLIC, ACC_INTERFACE, ACC_ABSTRACT
  this_class: #2                          // org/scalatest/verbs/MustVerb
  super_class: #4                         // java/lang/Object
  interfaces: 0, fields: 0, methods: 3, attributes: 5
Constant pool:
   #1 = Utf8               org/scalatest/verbs/MustVerb
   #2 = Class              #1             // org/scalatest/verbs/MustVerb
   #3 = Utf8               java/lang/Object
   #4 = Class              #3             // java/lang/Object
   #5 = Utf8               MustVerb.scala
   #6 = Utf8               Lscala/reflect/ScalaSignature;
   #7 = Utf8               bytes
   #8 = Utf8               \u0006\u0005E4qa\u0003\u0007\u0011\u0002\u0007\u00051\u0003C\u0003\u001b\u0001\u0011\u00051DB\u0004 \u0001A\u0005\u0019\u0011\u0001\u0011\t\u000bi\u0011A\u0011A\u000e\t\u000f\u0005\u0012!\u0019!D\u0001E!9aF\u0001b\u0001\u000e\u0003y\u0003\"\u0002\u001d\u0003\t\u0003I\u0004\"\u0002\u001d\u0003\t\u00031\u0005\"\u0002\u001d\u0003\t\u0003\t\u0006\"\u0002\u001d\u0003\t\u0003a\u0006\"\u00025\u0001\t\u0007I\'\u0001C\'vgR4VM\u001d2\u000b\u00055q\u0011!\u0002<fe\n\u001c(BA\b\u0011\u0003%\u00198-\u00197bi\u0016\u001cHOC\u0001\u0012\u0003\ry\'oZ\u0002\u0001\'\t\u0001A\u0003\u0005\u0002\u001615\taCC\u0001\u0018\u0003\u0015\u00198-\u00197b\u0013\tIbC\u0001\u0004B]f\u0014VMZ\u0001\u0007I%t\u0017\u000e\u001e\u0013\u0015\u0003q\u0001\"!F\u000f\n\u0005y1\"\u0001B+oSR\u0014\u0001d\u0015;sS:<W*^:u/J\f\u0007\u000f]3s\r>\u0014h+\u001a:c\'\t\u0011A#\u0001\bmK\u001a$8+\u001b3f\'R\u0014\u0018N\\4\u0016\u0003\r\u0002\"\u0001J\u0016\u000f\u0005\u0015J\u0003C\u0001\u0014\u0017\u001b\u00059#B\u0001\u0015\u0013\u0003\u0019a$o\\8u}%\u0011!FF\u0001\u0007!J,G-\u001a4\n\u00051j#AB*ue&twM\u0003\u0002+-\u0005\u0019\u0001o\\:\u0016\u0003A\u0002\"!\r\u001c\u000e\u0003IR!a\r\u001b\u0002\rM|WO]2f\u0015\t)\u0004#A\u0005tG\u0006d\u0017m\u0019;jG&\u0011qG\r\u0002\t!>\u001c\u0018\u000e^5p]\u0006!Q.^:u)\tQD\t\u0006\u0002<\u007fA\u0011A(P\u0007\u0002\u0019%\u0011a\b\u0004\u0002\u001b%\u0016\u001cX\u000f\u001c;PMN#(/\u001b8h!\u0006\u001c8/\u001a3U_Z+\'O\u0019\u0005\u0006\u0001\u001a\u0001\u001d!Q\u0001\u0005gZ\u001c\u0018\u000e\u0005\u0002=\u0005&\u00111\t\u0004\u0002\u001b\'R\u0014\u0018N\\4WKJ\u00147\u000b\u001e:j]\u001eLeN^8dCRLwN\u001c\u0005\u0006\u000b\u001a\u0001\raI\u0001\u0006e&<\u0007\u000e\u001e\u000b\u0003\u000fB#\"\u0001S&\u0011\u0005qJ\u0015B\u0001&\r\u0005)\u0011U\r[1wK^{\'\u000f\u001a\u0005\u0006\u0019\u001e\u0001\u001d!T\u0001\u0006gZ\u0014G.\u001b\t\u0003y9K!a\u0014\u0007\u0003=M#(/\u001b8h-\u0016\u0014(MQ3iCZ,G*[6f\u0013:4xnY1uS>t\u0007\"B#\b\u0001\u0004AEC\u0001*Y)\ta2\u000bC\u0003U\u0011\u0001\u000fQ+A\u0002gk:\u0004\"\u0001\u0010,\n\u0005]c!aG*ue&twMV3sE\ncwnY6SK\u001eL7\u000f\u001e:bi&|g\u000e\u0003\u0004F\u0011\u0011\u0005\r!\u0017\t\u0004+ic\u0012BA.\u0017\u0005!a$-\u001f8b[\u0016tDCA/d)\tab\fC\u0003`\u0013\u0001\u000f\u0001-A\u0003to\u0006<(\u000f\u0005\u0002=C&\u0011!\r\u0004\u0002!\'V\u0014\'.Z2u/&$\b.\u00114uKJ<vN\u001d3SK\u001eL7\u000f\u001e:bi&|g\u000eC\u0003e\u0013\u0001\u0007Q-\u0001\u000fsKN,H\u000e^(g\u0003\u001a$XM],pe\u0012\f\u0005\u000f\u001d7jG\u0006$\u0018n\u001c8\u0011\u0005q2\u0017BA4\r\u0005q\u0011Vm];mi>3\u0017I\u001a;fe^{\'\u000fZ!qa2L7-\u0019;j_:\f\u0011eY8om\u0016\u0014H\u000fV8TiJLgnZ\'vgR<&/\u00199qKJ4uN\u001d,fe\n$\"A[8\u0015\u0005-l\u0007C\u00017\u0003\u001b\u0005\u0001\u0001\"\u00028\u000b\u0001\b\u0001\u0014\u0001\u00039pg&$\u0018n\u001c8\t\u000bAT\u0001\u0019A\u0012\u0002\u0003=\u0004
   #9 = Utf8               org/scalatest/verbs/MustVerb$$anon$1
  #10 = Class              #9             // org/scalatest/verbs/MustVerb$$anon$1
  #11 = Utf8               org/scalatest/verbs/MustVerb$StringMustWrapperForVerb
  #12 = Class              #11            // org/scalatest/verbs/MustVerb$StringMustWrapperForVerb
  #13 = Utf8               StringMustWrapperForVerb
  #14 = Utf8               convertToStringMustWrapperForVerb$
  #15 = Utf8               (Lorg/scalatest/verbs/MustVerb;Ljava/lang/String;Lorg/scalactic/source/Position;)Lorg/scalatest/verbs/MustVerb$StringMustWrapperForVerb;
  #16 = Utf8               $this
  #17 = Utf8               o
  #18 = Utf8               position
  #19 = Utf8               convertToStringMustWrapperForVerb
  #20 = Utf8               (Ljava/lang/String;Lorg/scalactic/source/Position;)Lorg/scalatest/verbs/MustVerb$StringMustWrapperForVerb;
  #21 = NameAndType        #19:#20        // convertToStringMustWrapperForVerb:(Ljava/lang/String;Lorg/scalactic/source/Position;)Lorg/scalatest/verbs/MustVerb$StringMustWrapperForVerb;
  #22 = InterfaceMethodref #2.#21         // org/scalatest/verbs/MustVerb.convertToStringMustWrapperForVerb:(Ljava/lang/String;Lorg/scalactic/source/Position;)Lorg/scalatest/verbs/MustVerb$StringMustWrapperForVerb;
  #23 = Utf8               Lorg/scalatest/verbs/MustVerb;
  #24 = Utf8               Ljava/lang/String;
  #25 = Utf8               Lorg/scalactic/source/Position;
  #26 = Utf8               <init>
  #27 = Utf8               (Lorg/scalatest/verbs/MustVerb;Ljava/lang/String;Lorg/scalactic/source/Position;)V
  #28 = NameAndType        #26:#27        // "<init>":(Lorg/scalatest/verbs/MustVerb;Ljava/lang/String;Lorg/scalactic/source/Position;)V
  #29 = Methodref          #10.#28        // org/scalatest/verbs/MustVerb$$anon$1."<init>":(Lorg/scalatest/verbs/MustVerb;Ljava/lang/String;Lorg/scalactic/source/Position;)V
  #30 = Utf8               this
  #31 = Utf8               $init$
  #32 = Utf8               (Lorg/scalatest/verbs/MustVerb;)V
  #33 = Utf8               Code
  #34 = Utf8               LineNumberTable
  #35 = Utf8               LocalVariableTable
  #36 = Utf8               MethodParameters
  #37 = Utf8               InnerClasses
  #38 = Utf8               SourceFile
  #39 = Utf8               RuntimeVisibleAnnotations
  #40 = Utf8               ScalaInlineInfo
  #41 = Utf8               ScalaSig
{
  public static org.scalatest.verbs.MustVerb$StringMustWrapperForVerb convertToStringMustWrapperForVerb$(org.scalatest.verbs.MustVerb, java.lang.String, org.scalactic.source.Position);
    descriptor: (Lorg/scalatest/verbs/MustVerb;Ljava/lang/String;Lorg/scalactic/source/Position;)Lorg/scalatest/verbs/MustVerb$StringMustWrapperForVerb;
    flags: (0x1009) ACC_PUBLIC, ACC_STATIC, ACC_SYNTHETIC
    Code:
      stack=3, locals=3, args_size=3
         0: aload_0
         1: aload_1
         2: aload_2
         3: invokespecial #22                 // InterfaceMethod convertToStringMustWrapperForVerb:(Ljava/lang/String;Lorg/scalactic/source/Position;)Lorg/scalatest/verbs/MustVerb$StringMustWrapperForVerb;
         6: areturn
      LineNumberTable:
        line 228: 0
      LocalVariableTable:
        Start  Length  Slot  Name   Signature
            0       7     0 $this   Lorg/scalatest/verbs/MustVerb;
            0       7     1     o   Ljava/lang/String;
            0       7     2 position   Lorg/scalactic/source/Position;
    MethodParameters:
      Name                           Flags
      $this                          final synthetic
      o                              final
      position                       final

  public default org.scalatest.verbs.MustVerb$StringMustWrapperForVerb convertToStringMustWrapperForVerb(java.lang.String, org.scalactic.source.Position);
    descriptor: (Ljava/lang/String;Lorg/scalactic/source/Position;)Lorg/scalatest/verbs/MustVerb$StringMustWrapperForVerb;
    flags: (0x0001) ACC_PUBLIC
    Code:
      stack=5, locals=3, args_size=3
         0: new           #10                 // class org/scalatest/verbs/MustVerb$$anon$1
         3: dup
         4: aload_0
         5: aload_1
         6: aload_2
         7: invokespecial #29                 // Method org/scalatest/verbs/MustVerb$$anon$1."<init>":(Lorg/scalatest/verbs/MustVerb;Ljava/lang/String;Lorg/scalactic/source/Position;)V
        10: areturn
      LineNumberTable:
        line 229: 0
      LocalVariableTable:
        Start  Length  Slot  Name   Signature
            0      11     0  this   Lorg/scalatest/verbs/MustVerb;
            0      11     1     o   Ljava/lang/String;
            0      11     2 position   Lorg/scalactic/source/Position;
    MethodParameters:
      Name                           Flags
      o                              final
      position                       final

  public static void $init$(org.scalatest.verbs.MustVerb);
    descriptor: (Lorg/scalatest/verbs/MustVerb;)V
    flags: (0x0009) ACC_PUBLIC, ACC_STATIC
    Code:
      stack=0, locals=1, args_size=1
         0: return
      LineNumberTable:
        line 102: 0
      LocalVariableTable:
        Start  Length  Slot  Name   Signature
            0       1     0 $this   Lorg/scalatest/verbs/MustVerb;
    MethodParameters:
      Name                           Flags
      $this                          final synthetic
}
InnerClasses:
  public final #10;                       // class org/scalatest/verbs/MustVerb$$anon$1
  public #13= #12 of #2;                  // StringMustWrapperForVerb=class org/scalatest/verbs/MustVerb$StringMustWrapperForVerb of class org/scalatest/verbs/MustVerb
SourceFile: "MustVerb.scala"
RuntimeVisibleAnnotations:
  0: #6(#7=s#8)
    scala.reflect.ScalaSignature(
      bytes="\u0006\u0005E4qa\u0003\u0007\u0011\u0002\u0007\u00051\u0003C\u0003\u001b\u0001\u0011\u00051DB\u0004 \u0001A\u0005\u0019\u0011\u0001\u0011\t\u000bi\u0011A\u0011A\u000e\t\u000f\u0005\u0012!\u0019!D\u0001E!9aF\u0001b\u0001\u000e\u0003y\u0003\"\u0002\u001d\u0003\t\u0003I\u0004\"\u0002\u001d\u0003\t\u00031\u0005\"\u0002\u001d\u0003\t\u0003\t\u0006\"\u0002\u001d\u0003\t\u0003a\u0006\"\u00025\u0001\t\u0007I\'\u0001C\'vgR4VM\u001d2\u000b\u00055q\u0011!\u0002<fe\n\u001c(BA\b\u0011\u0003%\u00198-\u00197bi\u0016\u001cHOC\u0001\u0012\u0003\ry\'oZ\u0002\u0001\'\t\u0001A\u0003\u0005\u0002\u001615\taCC\u0001\u0018\u0003\u0015\u00198-\u00197b\u0013\tIbC\u0001\u0004B]f\u0014VMZ\u0001\u0007I%t\u0017\u000e\u001e\u0013\u0015\u0003q\u0001\"!F\u000f\n\u0005y1\"\u0001B+oSR\u0014\u0001d\u0015;sS:<W*^:u/J\f\u0007\u000f]3s\r>\u0014h+\u001a:c\'\t\u0011A#\u0001\bmK\u001a$8+\u001b3f\'R\u0014\u0018N\\4\u0016\u0003\r\u0002\"\u0001J\u0016\u000f\u0005\u0015J\u0003C\u0001\u0014\u0017\u001b\u00059#B\u0001\u0015\u0013\u0003\u0019a$o\\8u}%\u0011!FF\u0001\u0007!J,G-\u001a4\n\u00051j#AB*ue&twM\u0003\u0002+-\u0005\u0019\u0001o\\:\u0016\u0003A\u0002\"!\r\u001c\u000e\u0003IR!a\r\u001b\u0002\rM|WO]2f\u0015\t)\u0004#A\u0005tG\u0006d\u0017m\u0019;jG&\u0011qG\r\u0002\t!>\u001c\u0018\u000e^5p]\u0006!Q.^:u)\tQD\t\u0006\u0002<\u007fA\u0011A(P\u0007\u0002\u0019%\u0011a\b\u0004\u0002\u001b%\u0016\u001cX\u000f\u001c;PMN#(/\u001b8h!\u0006\u001c8/\u001a3U_Z+\'O\u0019\u0005\u0006\u0001\u001a\u0001\u001d!Q\u0001\u0005gZ\u001c\u0018\u000e\u0005\u0002=\u0005&\u00111\t\u0004\u0002\u001b\'R\u0014\u0018N\\4WKJ\u00147\u000b\u001e:j]\u001eLeN^8dCRLwN\u001c\u0005\u0006\u000b\u001a\u0001\raI\u0001\u0006e&<\u0007\u000e\u001e\u000b\u0003\u000fB#\"\u0001S&\u0011\u0005qJ\u0015B\u0001&\r\u0005)\u0011U\r[1wK^{\'\u000f\u001a\u0005\u0006\u0019\u001e\u0001\u001d!T\u0001\u0006gZ\u0014G.\u001b\t\u0003y9K!a\u0014\u0007\u0003=M#(/\u001b8h-\u0016\u0014(MQ3iCZ,G*[6f\u0013:4xnY1uS>t\u0007\"B#\b\u0001\u0004AEC\u0001*Y)\ta2\u000bC\u0003U\u0011\u0001\u000fQ+A\u0002gk:\u0004\"\u0001\u0010,\n\u0005]c!aG*ue&twMV3sE\ncwnY6SK\u001eL7\u000f\u001e:bi&|g\u000e\u0003\u0004F\u0011\u0011\u0005\r!\u0017\t\u0004+ic\u0012BA.\u0017\u0005!a$-\u001f8b[\u0016tDCA/d)\tab\fC\u0003`\u0013\u0001\u000f\u0001-A\u0003to\u0006<(\u000f\u0005\u0002=C&\u0011!\r\u0004\u0002!\'V\u0014\'.Z2u/&$\b.\u00114uKJ<vN\u001d3SK\u001eL7\u000f\u001e:bi&|g\u000eC\u0003e\u0013\u0001\u0007Q-\u0001\u000fsKN,H\u000e^(g\u0003\u001a$XM],pe\u0012\f\u0005\u000f\u001d7jG\u0006$\u0018n\u001c8\u0011\u0005q2\u0017BA4\r\u0005q\u0011Vm];mi>3\u0017I\u001a;fe^{\'\u000fZ!qa2L7-\u0019;j_:\f\u0011eY8om\u0016\u0014H\u000fV8TiJLgnZ\'vgR<&/\u00199qKJ4uN\u001d,fe\n$\"A[8\u0015\u0005-l\u0007C\u00017\u0003\u001b\u0005\u0001\u0001\"\u00028\u000b\u0001\b\u0001\u0014\u0001\u00039pg&$\u0018n\u001c8\t\u000bAT\u0001\u0019A\u0012\u0002\u0003=\u0004"
    )
  ScalaInlineInfo: length = 0x13 (unknown attribute)
   01 00 00 03 00 1F 00 20 01 00 13 00 14 00 00 0E
   00 0F 01
  ScalaSig: length = 0x3 (unknown attribute)
   05 02 00
