Classfile /Users/mw/Projects/slang-braindump/.jar/jar11/assemble/slang-braindump/assemble/content/org/scalatest/verbs/ResultOfAfterWordApplication.class
  Last modified May 29, 2022; size 1528 bytes
  SHA-256 checksum 641f1bc8234ea66d4147a691b9536b1bd826831e0e79694dc093861022307bbe
  Compiled from "ResultOfAfterWordApplication.scala"
public final class org.scalatest.verbs.ResultOfAfterWordApplication
  minor version: 0
  major version: 52
  flags: (0x0031) ACC_PUBLIC, ACC_FINAL, ACC_SUPER
  this_class: #2                          // org/scalatest/verbs/ResultOfAfterWordApplication
  super_class: #4                         // java/lang/Object
  interfaces: 0, fields: 2, methods: 4, attributes: 4
Constant pool:
   #1 = Utf8               org/scalatest/verbs/ResultOfAfterWordApplication
   #2 = Class              #1             // org/scalatest/verbs/ResultOfAfterWordApplication
   #3 = Utf8               java/lang/Object
   #4 = Class              #3             // java/lang/Object
   #5 = Utf8               ResultOfAfterWordApplication.scala
   #6 = Utf8               Lscala/reflect/ScalaSignature;
   #7 = Utf8               bytes
   #8 = Utf8               \u0006\u0005U2Aa\u0002\u0005\u0003\u001f!Aa\u0003\u0001BC\u0002\u0013\u0005q\u0003\u0003\u0005$\u0001\t\u0005\t\u0015!\u0003\u0019\u0011!!\u0003A!b\u0001\n\u0003)\u0003\u0002\u0003\u0017\u0001\u0005\u0003\u0005\u000b\u0011\u0002\u0014\t\u000b5\u0002A\u0011\u0001\u0018\t\u000bM\u0002A\u0011\t\u001b\u00039I+7/\u001e7u\u001f\u001a\fe\r^3s/>\u0014H-\u00119qY&\u001c\u0017\r^5p]*\u0011\u0011BC\u0001\u0006m\u0016\u0014(m\u001d\u0006\u0003\u00171\t\u0011b]2bY\u0006$Xm\u001d;\u000b\u00035\t1a\u001c:h\u0007\u0001\u0019\"\u0001\u0001\t\u0011\u0005E!R\"\u0001\n\u000b\u0003M\tQa]2bY\u0006L!!\u0006\n\u0003\r\u0005s\u0017PU3g\u0003\u0011!X\r\u001f;\u0016\u0003a\u0001\"!\u0007\u0011\u000f\u0005iq\u0002CA\u000e\u0013\u001b\u0005a\"BA\u000f\u000f\u0003\u0019a$o\\8u}%\u0011qDE\u0001\u0007!J,G-\u001a4\n\u0005\u0005\u0012#AB*ue&twM\u0003\u0002 %\u0005)A/\u001a=uA\u0005\ta-F\u0001\'!\r\tr%K\u0005\u0003QI\u0011\u0011BR;oGRLwN\u001c\u0019\u0011\u0005EQ\u0013BA\u0016\u0013\u0005\u0011)f.\u001b;\u0002\u0005\u0019\u0004\u0013A\u0002\u001fj]&$h\bF\u00020cI\u0002\"\u0001\r\u0001\u000e\u0003!AQAF\u0003A\u0002aAQ\u0001J\u0003A\u0002\u0019\n\u0001\u0002^8TiJLgn\u001a\u000b\u00021\u0001
   #9 = Utf8               text
  #10 = Utf8               Ljava/lang/String;
  #11 = Utf8               f
  #12 = Utf8               Lscala/Function0;
  #13 = Utf8               Lscala/Function0<Lscala/runtime/BoxedUnit;>;
  #14 = Utf8               ()Ljava/lang/String;
  #15 = NameAndType        #9:#10         // text:Ljava/lang/String;
  #16 = Fieldref           #2.#15         // org/scalatest/verbs/ResultOfAfterWordApplication.text:Ljava/lang/String;
  #17 = Utf8               this
  #18 = Utf8               Lorg/scalatest/verbs/ResultOfAfterWordApplication;
  #19 = Utf8               ()Lscala/Function0;
  #20 = Utf8               ()Lscala/Function0<Lscala/runtime/BoxedUnit;>;
  #21 = NameAndType        #11:#12        // f:Lscala/Function0;
  #22 = Fieldref           #2.#21         // org/scalatest/verbs/ResultOfAfterWordApplication.f:Lscala/Function0;
  #23 = Utf8               toString
  #24 = NameAndType        #9:#14         // text:()Ljava/lang/String;
  #25 = Methodref          #2.#24         // org/scalatest/verbs/ResultOfAfterWordApplication.text:()Ljava/lang/String;
  #26 = Utf8               <init>
  #27 = Utf8               (Ljava/lang/String;Lscala/Function0;)V
  #28 = Utf8               (Ljava/lang/String;Lscala/Function0<Lscala/runtime/BoxedUnit;>;)V
  #29 = Utf8               ()V
  #30 = NameAndType        #26:#29        // "<init>":()V
  #31 = Methodref          #4.#30         // java/lang/Object."<init>":()V
  #32 = Utf8               Signature
  #33 = Utf8               Code
  #34 = Utf8               LineNumberTable
  #35 = Utf8               LocalVariableTable
  #36 = Utf8               MethodParameters
  #37 = Utf8               SourceFile
  #38 = Utf8               RuntimeVisibleAnnotations
  #39 = Utf8               ScalaInlineInfo
  #40 = Utf8               ScalaSig
{
  private final java.lang.String text;
    descriptor: Ljava/lang/String;
    flags: (0x0012) ACC_PRIVATE, ACC_FINAL

  private final scala.Function0<scala.runtime.BoxedUnit> f;
    descriptor: Lscala/Function0;
    flags: (0x0012) ACC_PRIVATE, ACC_FINAL
    Signature: #13                          // Lscala/Function0<Lscala/runtime/BoxedUnit;>;

  public java.lang.String text();
    descriptor: ()Ljava/lang/String;
    flags: (0x0001) ACC_PUBLIC
    Code:
      stack=1, locals=1, args_size=1
         0: aload_0
         1: getfield      #16                 // Field text:Ljava/lang/String;
         4: areturn
      LineNumberTable:
        line 31: 0
      LocalVariableTable:
        Start  Length  Slot  Name   Signature
            0       5     0  this   Lorg/scalatest/verbs/ResultOfAfterWordApplication;

  public scala.Function0<scala.runtime.BoxedUnit> f();
    descriptor: ()Lscala/Function0;
    flags: (0x0001) ACC_PUBLIC
    Code:
      stack=1, locals=1, args_size=1
         0: aload_0
         1: getfield      #22                 // Field f:Lscala/Function0;
         4: areturn
      LineNumberTable:
        line 31: 0
      LocalVariableTable:
        Start  Length  Slot  Name   Signature
            0       5     0  this   Lorg/scalatest/verbs/ResultOfAfterWordApplication;
    Signature: #20                          // ()Lscala/Function0<Lscala/runtime/BoxedUnit;>;

  public java.lang.String toString();
    descriptor: ()Ljava/lang/String;
    flags: (0x0001) ACC_PUBLIC
    Code:
      stack=1, locals=1, args_size=1
         0: aload_0
         1: invokevirtual #25                 // Method text:()Ljava/lang/String;
         4: areturn
      LineNumberTable:
        line 35: 0
      LocalVariableTable:
        Start  Length  Slot  Name   Signature
            0       5     0  this   Lorg/scalatest/verbs/ResultOfAfterWordApplication;

  public org.scalatest.verbs.ResultOfAfterWordApplication(java.lang.String, scala.Function0<scala.runtime.BoxedUnit>);
    descriptor: (Ljava/lang/String;Lscala/Function0;)V
    flags: (0x0001) ACC_PUBLIC
    Code:
      stack=2, locals=3, args_size=3
         0: aload_0
         1: aload_1
         2: putfield      #16                 // Field text:Ljava/lang/String;
         5: aload_0
         6: aload_2
         7: putfield      #22                 // Field f:Lscala/Function0;
        10: aload_0
        11: invokespecial #31                 // Method java/lang/Object."<init>":()V
        14: return
      LineNumberTable:
        line 31: 0
        line 36: 10
        line 31: 14
      LocalVariableTable:
        Start  Length  Slot  Name   Signature
            0      15     0  this   Lorg/scalatest/verbs/ResultOfAfterWordApplication;
            0      15     1  text   Ljava/lang/String;
            0      15     2     f   Lscala/Function0;
    Signature: #28                          // (Ljava/lang/String;Lscala/Function0<Lscala/runtime/BoxedUnit;>;)V
    MethodParameters:
      Name                           Flags
      text                           final
      f                              final
}
SourceFile: "ResultOfAfterWordApplication.scala"
RuntimeVisibleAnnotations:
  0: #6(#7=s#8)
    scala.reflect.ScalaSignature(
      bytes="\u0006\u0005U2Aa\u0002\u0005\u0003\u001f!Aa\u0003\u0001BC\u0002\u0013\u0005q\u0003\u0003\u0005$\u0001\t\u0005\t\u0015!\u0003\u0019\u0011!!\u0003A!b\u0001\n\u0003)\u0003\u0002\u0003\u0017\u0001\u0005\u0003\u0005\u000b\u0011\u0002\u0014\t\u000b5\u0002A\u0011\u0001\u0018\t\u000bM\u0002A\u0011\t\u001b\u00039I+7/\u001e7u\u001f\u001a\fe\r^3s/>\u0014H-\u00119qY&\u001c\u0017\r^5p]*\u0011\u0011BC\u0001\u0006m\u0016\u0014(m\u001d\u0006\u0003\u00171\t\u0011b]2bY\u0006$Xm\u001d;\u000b\u00035\t1a\u001c:h\u0007\u0001\u0019\"\u0001\u0001\t\u0011\u0005E!R\"\u0001\n\u000b\u0003M\tQa]2bY\u0006L!!\u0006\n\u0003\r\u0005s\u0017PU3g\u0003\u0011!X\r\u001f;\u0016\u0003a\u0001\"!\u0007\u0011\u000f\u0005iq\u0002CA\u000e\u0013\u001b\u0005a\"BA\u000f\u000f\u0003\u0019a$o\\8u}%\u0011qDE\u0001\u0007!J,G-\u001a4\n\u0005\u0005\u0012#AB*ue&twM\u0003\u0002 %\u0005)A/\u001a=uA\u0005\ta-F\u0001\'!\r\tr%K\u0005\u0003QI\u0011\u0011BR;oGRLwN\u001c\u0019\u0011\u0005EQ\u0013BA\u0016\u0013\u0005\u0011)f.\u001b;\u0002\u0005\u0019\u0004\u0013A\u0002\u001fj]&$h\bF\u00020cI\u0002\"\u0001\r\u0001\u000e\u0003!AQAF\u0003A\u0002aAQ\u0001J\u0003A\u0002\u0019\n\u0001\u0002^8TiJLgn\u001a\u000b\u00021\u0001"
    )
  ScalaInlineInfo: length = 0x18 (unknown attribute)
   01 01 00 04 00 1A 00 1B 01 00 0B 00 13 01 00 09
   00 0E 01 00 17 00 0E 01
  ScalaSig: length = 0x3 (unknown attribute)
   05 02 00
