Classfile /Users/mw/Projects/slang-braindump/.jar/jar8/assemble/slang-braindump/assemble/content/com/fasterxml/jackson/databind/type/TypeBase.class
  Last modified May 29, 2022; size 8262 bytes
  SHA-256 checksum b2029b2878abb605cb2fe02d3976045fabd84d246890e8e81f2beef44dc4932f
  Compiled from "TypeBase.java"
public abstract class com.fasterxml.jackson.databind.type.TypeBase extends com.fasterxml.jackson.databind.JavaType implements com.fasterxml.jackson.databind.JsonSerializable
  minor version: 0
  major version: 52
  flags: (0x0421) ACC_PUBLIC, ACC_SUPER, ACC_ABSTRACT
  this_class: #57                         // com/fasterxml/jackson/databind/type/TypeBase
  super_class: #56                        // com/fasterxml/jackson/databind/JavaType
  interfaces: 1, fields: 7, methods: 21, attributes: 1
Constant pool:
    #1 = Methodref          #56.#182      // com/fasterxml/jackson/databind/JavaType."<init>":(Ljava/lang/Class;ILjava/lang/Object;Ljava/lang/Object;Z)V
    #2 = Fieldref           #57.#183      // com/fasterxml/jackson/databind/type/TypeBase.NO_BINDINGS:Lcom/fasterxml/jackson/databind/type/TypeBindings;
    #3 = Fieldref           #57.#184      // com/fasterxml/jackson/databind/type/TypeBase._bindings:Lcom/fasterxml/jackson/databind/type/TypeBindings;
    #4 = Fieldref           #57.#185      // com/fasterxml/jackson/databind/type/TypeBase._superClass:Lcom/fasterxml/jackson/databind/JavaType;
    #5 = Fieldref           #57.#186      // com/fasterxml/jackson/databind/type/TypeBase._superInterfaces:[Lcom/fasterxml/jackson/databind/JavaType;
    #6 = Methodref          #56.#187      // com/fasterxml/jackson/databind/JavaType."<init>":(Lcom/fasterxml/jackson/databind/JavaType;)V
    #7 = Fieldref           #57.#188      // com/fasterxml/jackson/databind/type/TypeBase._canonicalName:Ljava/lang/String;
    #8 = Methodref          #57.#189      // com/fasterxml/jackson/databind/type/TypeBase.buildCanonicalName:()Ljava/lang/String;
    #9 = Fieldref           #57.#190      // com/fasterxml/jackson/databind/type/TypeBase._class:Ljava/lang/Class;
   #10 = Methodref          #191.#192     // java/lang/Class.getName:()Ljava/lang/String;
   #11 = Methodref          #193.#194     // com/fasterxml/jackson/databind/type/TypeBindings.size:()I
   #12 = Methodref          #193.#195     // com/fasterxml/jackson/databind/type/TypeBindings.getBoundType:(I)Lcom/fasterxml/jackson/databind/JavaType;
   #13 = Methodref          #193.#196     // com/fasterxml/jackson/databind/type/TypeBindings.getBoundName:(I)Ljava/lang/String;
   #14 = Methodref          #197.#198     // java/util/Collections.emptyList:()Ljava/util/List;
   #15 = Methodref          #197.#199     // java/util/Collections.singletonList:(Ljava/lang/Object;)Ljava/util/List;
   #16 = Methodref          #200.#201     // java/util/Arrays.asList:([Ljava/lang/Object;)Ljava/util/List;
   #17 = Methodref          #191.#202     // java/lang/Class.isInterface:()Z
   #18 = Methodref          #56.#203      // com/fasterxml/jackson/databind/JavaType.findSuperType:(Ljava/lang/Class;)Lcom/fasterxml/jackson/databind/JavaType;
   #19 = Methodref          #57.#203      // com/fasterxml/jackson/databind/type/TypeBase.findSuperType:(Ljava/lang/Class;)Lcom/fasterxml/jackson/databind/JavaType;
   #20 = Fieldref           #57.#204      // com/fasterxml/jackson/databind/type/TypeBase.NO_TYPES:[Lcom/fasterxml/jackson/databind/JavaType;
   #21 = Methodref          #56.#205      // com/fasterxml/jackson/databind/JavaType.getBindings:()Lcom/fasterxml/jackson/databind/type/TypeBindings;
   #22 = Methodref          #193.#206     // com/fasterxml/jackson/databind/type/TypeBindings.typeParameterArray:()[Lcom/fasterxml/jackson/databind/JavaType;
   #23 = Class              #207          // com/fasterxml/jackson/core/type/WritableTypeId
   #24 = Fieldref           #208.#209     // com/fasterxml/jackson/core/JsonToken.VALUE_STRING:Lcom/fasterxml/jackson/core/JsonToken;
   #25 = Methodref          #23.#210      // com/fasterxml/jackson/core/type/WritableTypeId."<init>":(Ljava/lang/Object;Lcom/fasterxml/jackson/core/JsonToken;)V
   #26 = Methodref          #211.#212     // com/fasterxml/jackson/databind/jsontype/TypeSerializer.writeTypePrefix:(Lcom/fasterxml/jackson/core/JsonGenerator;Lcom/fasterxml/jackson/core/type/WritableTypeId;)Lcom/fasterxml/jackson/core/type/WritableTypeId;
   #27 = Methodref          #57.#213      // com/fasterxml/jackson/databind/type/TypeBase.serialize:(Lcom/fasterxml/jackson/core/JsonGenerator;Lcom/fasterxml/jackson/databind/SerializerProvider;)V
   #28 = Methodref          #211.#214     // com/fasterxml/jackson/databind/jsontype/TypeSerializer.writeTypeSuffix:(Lcom/fasterxml/jackson/core/JsonGenerator;Lcom/fasterxml/jackson/core/type/WritableTypeId;)Lcom/fasterxml/jackson/core/type/WritableTypeId;
   #29 = Methodref          #57.#215      // com/fasterxml/jackson/databind/type/TypeBase.toCanonical:()Ljava/lang/String;
   #30 = Methodref          #216.#217     // com/fasterxml/jackson/core/JsonGenerator.writeString:(Ljava/lang/String;)V
   #31 = Methodref          #191.#218     // java/lang/Class.isPrimitive:()Z
   #32 = Fieldref           #219.#220     // java/lang/Boolean.TYPE:Ljava/lang/Class;
   #33 = Methodref          #43.#221      // java/lang/StringBuilder.append:(C)Ljava/lang/StringBuilder;
   #34 = Fieldref           #222.#220     // java/lang/Byte.TYPE:Ljava/lang/Class;
   #35 = Fieldref           #223.#220     // java/lang/Short.TYPE:Ljava/lang/Class;
   #36 = Fieldref           #224.#220     // java/lang/Character.TYPE:Ljava/lang/Class;
   #37 = Fieldref           #225.#220     // java/lang/Integer.TYPE:Ljava/lang/Class;
   #38 = Fieldref           #226.#220     // java/lang/Long.TYPE:Ljava/lang/Class;
   #39 = Fieldref           #227.#220     // java/lang/Float.TYPE:Ljava/lang/Class;
   #40 = Fieldref           #228.#220     // java/lang/Double.TYPE:Ljava/lang/Class;
   #41 = Fieldref           #229.#220     // java/lang/Void.TYPE:Ljava/lang/Class;
   #42 = Class              #230          // java/lang/IllegalStateException
   #43 = Class              #231          // java/lang/StringBuilder
   #44 = Methodref          #43.#232      // java/lang/StringBuilder."<init>":()V
   #45 = String             #233          // Unrecognized primitive type:
   #46 = Methodref          #43.#234      // java/lang/StringBuilder.append:(Ljava/lang/String;)Ljava/lang/StringBuilder;
   #47 = Methodref          #43.#235      // java/lang/StringBuilder.toString:()Ljava/lang/String;
   #48 = Methodref          #42.#236      // java/lang/IllegalStateException."<init>":(Ljava/lang/String;)V
   #49 = Methodref          #237.#238     // java/lang/String.length:()I
   #50 = Methodref          #237.#239     // java/lang/String.charAt:(I)C
   #51 = Methodref          #191.#240     // java/lang/Class.getSuperclass:()Ljava/lang/Class;
   #52 = Methodref          #241.#242     // com/fasterxml/jackson/databind/type/TypeFactory.unknownType:()Lcom/fasterxml/jackson/databind/JavaType;
   #53 = Methodref          #191.#243     // java/lang/Class.getTypeParameters:()[Ljava/lang/reflect/TypeVariable;
   #54 = Methodref          #57.#244      // com/fasterxml/jackson/databind/type/TypeBase.containedType:(I)Lcom/fasterxml/jackson/databind/JavaType;
   #55 = Methodref          #193.#245     // com/fasterxml/jackson/databind/type/TypeBindings.emptyBindings:()Lcom/fasterxml/jackson/databind/type/TypeBindings;
   #56 = Class              #246          // com/fasterxml/jackson/databind/JavaType
   #57 = Class              #247          // com/fasterxml/jackson/databind/type/TypeBase
   #58 = Class              #248          // com/fasterxml/jackson/databind/JsonSerializable
   #59 = Utf8               serialVersionUID
   #60 = Utf8               J
   #61 = Utf8               ConstantValue
   #62 = Long               1l
   #64 = Utf8               NO_BINDINGS
   #65 = Utf8               Lcom/fasterxml/jackson/databind/type/TypeBindings;
   #66 = Utf8               NO_TYPES
   #67 = Utf8               [Lcom/fasterxml/jackson/databind/JavaType;
   #68 = Utf8               _superClass
   #69 = Utf8               Lcom/fasterxml/jackson/databind/JavaType;
   #70 = Utf8               _superInterfaces
   #71 = Utf8               _bindings
   #72 = Utf8               _canonicalName
   #73 = Utf8               Ljava/lang/String;
   #74 = Utf8               <init>
   #75 = Utf8               (Ljava/lang/Class;Lcom/fasterxml/jackson/databind/type/TypeBindings;Lcom/fasterxml/jackson/databind/JavaType;[Lcom/fasterxml/jackson/databind/JavaType;ILjava/lang/Object;Ljava/lang/Object;Z)V
   #76 = Utf8               Code
   #77 = Utf8               LineNumberTable
   #78 = Utf8               LocalVariableTable
   #79 = Utf8               this
   #80 = Utf8               Lcom/fasterxml/jackson/databind/type/TypeBase;
   #81 = Utf8               raw
   #82 = Utf8               Ljava/lang/Class;
   #83 = Utf8               bindings
   #84 = Utf8               superClass
   #85 = Utf8               superInts
   #86 = Utf8               hash
   #87 = Utf8               I
   #88 = Utf8               valueHandler
   #89 = Utf8               Ljava/lang/Object;
   #90 = Utf8               typeHandler
   #91 = Utf8               asStatic
   #92 = Utf8               Z
   #93 = Utf8               LocalVariableTypeTable
   #94 = Utf8               Ljava/lang/Class<*>;
   #95 = Utf8               StackMapTable
   #96 = Class              #247          // com/fasterxml/jackson/databind/type/TypeBase
   #97 = Class              #249          // java/lang/Class
   #98 = Class              #250          // com/fasterxml/jackson/databind/type/TypeBindings
   #99 = Class              #246          // com/fasterxml/jackson/databind/JavaType
  #100 = Class              #67           // "[Lcom/fasterxml/jackson/databind/JavaType;"
  #101 = Class              #251          // java/lang/Object
  #102 = Utf8               Signature
  #103 = Utf8               (Ljava/lang/Class<*>;Lcom/fasterxml/jackson/databind/type/TypeBindings;Lcom/fasterxml/jackson/databind/JavaType;[Lcom/fasterxml/jackson/databind/JavaType;ILjava/lang/Object;Ljava/lang/Object;Z)V
  #104 = Utf8               (Lcom/fasterxml/jackson/databind/type/TypeBase;)V
  #105 = Utf8               base
  #106 = Utf8               toCanonical
  #107 = Utf8               ()Ljava/lang/String;
  #108 = Utf8               str
  #109 = Class              #252          // java/lang/String
  #110 = Utf8               buildCanonicalName
  #111 = Utf8               getGenericSignature
  #112 = Utf8               (Ljava/lang/StringBuilder;)Ljava/lang/StringBuilder;
  #113 = Utf8               getErasedSignature
  #114 = Utf8               getBindings
  #115 = Utf8               ()Lcom/fasterxml/jackson/databind/type/TypeBindings;
  #116 = Utf8               containedTypeCount
  #117 = Utf8               ()I
  #118 = Utf8               containedType
  #119 = Utf8               (I)Lcom/fasterxml/jackson/databind/JavaType;
  #120 = Utf8               index
  #121 = Utf8               containedTypeName
  #122 = Utf8               (I)Ljava/lang/String;
  #123 = Utf8               Deprecated
  #124 = Utf8               RuntimeVisibleAnnotations
  #125 = Utf8               Ljava/lang/Deprecated;
  #126 = Utf8               getSuperClass
  #127 = Utf8               ()Lcom/fasterxml/jackson/databind/JavaType;
  #128 = Utf8               getInterfaces
  #129 = Utf8               ()Ljava/util/List;
  #130 = Utf8               ()Ljava/util/List<Lcom/fasterxml/jackson/databind/JavaType;>;
  #131 = Utf8               findSuperType
  #132 = Utf8               (Ljava/lang/Class;)Lcom/fasterxml/jackson/databind/JavaType;
  #133 = Utf8               type
  #134 = Utf8               i
  #135 = Utf8               count
  #136 = Utf8               rawTarget
  #137 = Utf8               (Ljava/lang/Class<*>;)Lcom/fasterxml/jackson/databind/JavaType;
  #138 = Utf8               findTypeParameters
  #139 = Utf8               (Ljava/lang/Class;)[Lcom/fasterxml/jackson/databind/JavaType;
  #140 = Utf8               expType
  #141 = Utf8               match
  #142 = Utf8               (Ljava/lang/Class<*>;)[Lcom/fasterxml/jackson/databind/JavaType;
  #143 = Utf8               serializeWithType
  #144 = Utf8               (Lcom/fasterxml/jackson/core/JsonGenerator;Lcom/fasterxml/jackson/databind/SerializerProvider;Lcom/fasterxml/jackson/databind/jsontype/TypeSerializer;)V
  #145 = Utf8               g
  #146 = Utf8               Lcom/fasterxml/jackson/core/JsonGenerator;
  #147 = Utf8               provider
  #148 = Utf8               Lcom/fasterxml/jackson/databind/SerializerProvider;
  #149 = Utf8               typeSer
  #150 = Utf8               Lcom/fasterxml/jackson/databind/jsontype/TypeSerializer;
  #151 = Utf8               typeIdDef
  #152 = Utf8               Lcom/fasterxml/jackson/core/type/WritableTypeId;
  #153 = Utf8               Exceptions
  #154 = Class              #253          // java/io/IOException
  #155 = Utf8               serialize
  #156 = Utf8               (Lcom/fasterxml/jackson/core/JsonGenerator;Lcom/fasterxml/jackson/databind/SerializerProvider;)V
  #157 = Utf8               gen
  #158 = Utf8               _classSignature
  #159 = Utf8               (Ljava/lang/Class;Ljava/lang/StringBuilder;Z)Ljava/lang/StringBuilder;
  #160 = Utf8               c
  #161 = Utf8               C
  #162 = Utf8               len
  #163 = Utf8               name
  #164 = Utf8               cls
  #165 = Utf8               sb
  #166 = Utf8               Ljava/lang/StringBuilder;
  #167 = Utf8               trailingSemicolon
  #168 = Utf8               (Ljava/lang/Class<*>;Ljava/lang/StringBuilder;Z)Ljava/lang/StringBuilder;
  #169 = Utf8               _bogusSuperClass
  #170 = Utf8               parent
  #171 = Utf8               _hasNTypeParameters
  #172 = Utf8               (I)Z
  #173 = Utf8               params
  #174 = Utf8               [Ljava/lang/reflect/TypeVariable;
  #175 = Utf8               [Ljava/lang/reflect/TypeVariable<*>;
  #176 = Class              #174          // "[Ljava/lang/reflect/TypeVariable;"
  #177 = Utf8               (I)Lcom/fasterxml/jackson/core/type/ResolvedType;
  #178 = Utf8               <clinit>
  #179 = Utf8               ()V
  #180 = Utf8               SourceFile
  #181 = Utf8               TypeBase.java
  #182 = NameAndType        #74:#254      // "<init>":(Ljava/lang/Class;ILjava/lang/Object;Ljava/lang/Object;Z)V
  #183 = NameAndType        #64:#65       // NO_BINDINGS:Lcom/fasterxml/jackson/databind/type/TypeBindings;
  #184 = NameAndType        #71:#65       // _bindings:Lcom/fasterxml/jackson/databind/type/TypeBindings;
  #185 = NameAndType        #68:#69       // _superClass:Lcom/fasterxml/jackson/databind/JavaType;
  #186 = NameAndType        #70:#67       // _superInterfaces:[Lcom/fasterxml/jackson/databind/JavaType;
  #187 = NameAndType        #74:#255      // "<init>":(Lcom/fasterxml/jackson/databind/JavaType;)V
  #188 = NameAndType        #72:#73       // _canonicalName:Ljava/lang/String;
  #189 = NameAndType        #110:#107     // buildCanonicalName:()Ljava/lang/String;
  #190 = NameAndType        #256:#82      // _class:Ljava/lang/Class;
  #191 = Class              #249          // java/lang/Class
  #192 = NameAndType        #257:#107     // getName:()Ljava/lang/String;
  #193 = Class              #250          // com/fasterxml/jackson/databind/type/TypeBindings
  #194 = NameAndType        #258:#117     // size:()I
  #195 = NameAndType        #259:#119     // getBoundType:(I)Lcom/fasterxml/jackson/databind/JavaType;
  #196 = NameAndType        #260:#122     // getBoundName:(I)Ljava/lang/String;
  #197 = Class              #261          // java/util/Collections
  #198 = NameAndType        #262:#129     // emptyList:()Ljava/util/List;
  #199 = NameAndType        #263:#264     // singletonList:(Ljava/lang/Object;)Ljava/util/List;
  #200 = Class              #265          // java/util/Arrays
  #201 = NameAndType        #266:#267     // asList:([Ljava/lang/Object;)Ljava/util/List;
  #202 = NameAndType        #268:#269     // isInterface:()Z
  #203 = NameAndType        #131:#132     // findSuperType:(Ljava/lang/Class;)Lcom/fasterxml/jackson/databind/JavaType;
  #204 = NameAndType        #66:#67       // NO_TYPES:[Lcom/fasterxml/jackson/databind/JavaType;
  #205 = NameAndType        #114:#115     // getBindings:()Lcom/fasterxml/jackson/databind/type/TypeBindings;
  #206 = NameAndType        #270:#271     // typeParameterArray:()[Lcom/fasterxml/jackson/databind/JavaType;
  #207 = Utf8               com/fasterxml/jackson/core/type/WritableTypeId
  #208 = Class              #272          // com/fasterxml/jackson/core/JsonToken
  #209 = NameAndType        #273:#274     // VALUE_STRING:Lcom/fasterxml/jackson/core/JsonToken;
  #210 = NameAndType        #74:#275      // "<init>":(Ljava/lang/Object;Lcom/fasterxml/jackson/core/JsonToken;)V
  #211 = Class              #276          // com/fasterxml/jackson/databind/jsontype/TypeSerializer
  #212 = NameAndType        #277:#278     // writeTypePrefix:(Lcom/fasterxml/jackson/core/JsonGenerator;Lcom/fasterxml/jackson/core/type/WritableTypeId;)Lcom/fasterxml/jackson/core/type/WritableTypeId;
  #213 = NameAndType        #155:#156     // serialize:(Lcom/fasterxml/jackson/core/JsonGenerator;Lcom/fasterxml/jackson/databind/SerializerProvider;)V
  #214 = NameAndType        #279:#278     // writeTypeSuffix:(Lcom/fasterxml/jackson/core/JsonGenerator;Lcom/fasterxml/jackson/core/type/WritableTypeId;)Lcom/fasterxml/jackson/core/type/WritableTypeId;
  #215 = NameAndType        #106:#107     // toCanonical:()Ljava/lang/String;
  #216 = Class              #280          // com/fasterxml/jackson/core/JsonGenerator
  #217 = NameAndType        #281:#282     // writeString:(Ljava/lang/String;)V
  #218 = NameAndType        #283:#269     // isPrimitive:()Z
  #219 = Class              #284          // java/lang/Boolean
  #220 = NameAndType        #285:#82      // TYPE:Ljava/lang/Class;
  #221 = NameAndType        #286:#287     // append:(C)Ljava/lang/StringBuilder;
  #222 = Class              #288          // java/lang/Byte
  #223 = Class              #289          // java/lang/Short
  #224 = Class              #290          // java/lang/Character
  #225 = Class              #291          // java/lang/Integer
  #226 = Class              #292          // java/lang/Long
  #227 = Class              #293          // java/lang/Float
  #228 = Class              #294          // java/lang/Double
  #229 = Class              #295          // java/lang/Void
  #230 = Utf8               java/lang/IllegalStateException
  #231 = Utf8               java/lang/StringBuilder
  #232 = NameAndType        #74:#179      // "<init>":()V
  #233 = Utf8               Unrecognized primitive type:
  #234 = NameAndType        #286:#296     // append:(Ljava/lang/String;)Ljava/lang/StringBuilder;
  #235 = NameAndType        #297:#107     // toString:()Ljava/lang/String;
  #236 = NameAndType        #74:#282      // "<init>":(Ljava/lang/String;)V
  #237 = Class              #252          // java/lang/String
  #238 = NameAndType        #298:#117     // length:()I
  #239 = NameAndType        #299:#300     // charAt:(I)C
  #240 = NameAndType        #301:#302     // getSuperclass:()Ljava/lang/Class;
  #241 = Class              #303          // com/fasterxml/jackson/databind/type/TypeFactory
  #242 = NameAndType        #304:#127     // unknownType:()Lcom/fasterxml/jackson/databind/JavaType;
  #243 = NameAndType        #305:#306     // getTypeParameters:()[Ljava/lang/reflect/TypeVariable;
  #244 = NameAndType        #118:#119     // containedType:(I)Lcom/fasterxml/jackson/databind/JavaType;
  #245 = NameAndType        #307:#115     // emptyBindings:()Lcom/fasterxml/jackson/databind/type/TypeBindings;
  #246 = Utf8               com/fasterxml/jackson/databind/JavaType
  #247 = Utf8               com/fasterxml/jackson/databind/type/TypeBase
  #248 = Utf8               com/fasterxml/jackson/databind/JsonSerializable
  #249 = Utf8               java/lang/Class
  #250 = Utf8               com/fasterxml/jackson/databind/type/TypeBindings
  #251 = Utf8               java/lang/Object
  #252 = Utf8               java/lang/String
  #253 = Utf8               java/io/IOException
  #254 = Utf8               (Ljava/lang/Class;ILjava/lang/Object;Ljava/lang/Object;Z)V
  #255 = Utf8               (Lcom/fasterxml/jackson/databind/JavaType;)V
  #256 = Utf8               _class
  #257 = Utf8               getName
  #258 = Utf8               size
  #259 = Utf8               getBoundType
  #260 = Utf8               getBoundName
  #261 = Utf8               java/util/Collections
  #262 = Utf8               emptyList
  #263 = Utf8               singletonList
  #264 = Utf8               (Ljava/lang/Object;)Ljava/util/List;
  #265 = Utf8               java/util/Arrays
  #266 = Utf8               asList
  #267 = Utf8               ([Ljava/lang/Object;)Ljava/util/List;
  #268 = Utf8               isInterface
  #269 = Utf8               ()Z
  #270 = Utf8               typeParameterArray
  #271 = Utf8               ()[Lcom/fasterxml/jackson/databind/JavaType;
  #272 = Utf8               com/fasterxml/jackson/core/JsonToken
  #273 = Utf8               VALUE_STRING
  #274 = Utf8               Lcom/fasterxml/jackson/core/JsonToken;
  #275 = Utf8               (Ljava/lang/Object;Lcom/fasterxml/jackson/core/JsonToken;)V
  #276 = Utf8               com/fasterxml/jackson/databind/jsontype/TypeSerializer
  #277 = Utf8               writeTypePrefix
  #278 = Utf8               (Lcom/fasterxml/jackson/core/JsonGenerator;Lcom/fasterxml/jackson/core/type/WritableTypeId;)Lcom/fasterxml/jackson/core/type/WritableTypeId;
  #279 = Utf8               writeTypeSuffix
  #280 = Utf8               com/fasterxml/jackson/core/JsonGenerator
  #281 = Utf8               writeString
  #282 = Utf8               (Ljava/lang/String;)V
  #283 = Utf8               isPrimitive
  #284 = Utf8               java/lang/Boolean
  #285 = Utf8               TYPE
  #286 = Utf8               append
  #287 = Utf8               (C)Ljava/lang/StringBuilder;
  #288 = Utf8               java/lang/Byte
  #289 = Utf8               java/lang/Short
  #290 = Utf8               java/lang/Character
  #291 = Utf8               java/lang/Integer
  #292 = Utf8               java/lang/Long
  #293 = Utf8               java/lang/Float
  #294 = Utf8               java/lang/Double
  #295 = Utf8               java/lang/Void
  #296 = Utf8               (Ljava/lang/String;)Ljava/lang/StringBuilder;
  #297 = Utf8               toString
  #298 = Utf8               length
  #299 = Utf8               charAt
  #300 = Utf8               (I)C
  #301 = Utf8               getSuperclass
  #302 = Utf8               ()Ljava/lang/Class;
  #303 = Utf8               com/fasterxml/jackson/databind/type/TypeFactory
  #304 = Utf8               unknownType
  #305 = Utf8               getTypeParameters
  #306 = Utf8               ()[Ljava/lang/reflect/TypeVariable;
  #307 = Utf8               emptyBindings
{
  private static final long serialVersionUID;
    descriptor: J
    flags: (0x001a) ACC_PRIVATE, ACC_STATIC, ACC_FINAL
    ConstantValue: long 1l

  private static final com.fasterxml.jackson.databind.type.TypeBindings NO_BINDINGS;
    descriptor: Lcom/fasterxml/jackson/databind/type/TypeBindings;
    flags: (0x001a) ACC_PRIVATE, ACC_STATIC, ACC_FINAL

  private static final com.fasterxml.jackson.databind.JavaType[] NO_TYPES;
    descriptor: [Lcom/fasterxml/jackson/databind/JavaType;
    flags: (0x001a) ACC_PRIVATE, ACC_STATIC, ACC_FINAL

  protected final com.fasterxml.jackson.databind.JavaType _superClass;
    descriptor: Lcom/fasterxml/jackson/databind/JavaType;
    flags: (0x0014) ACC_PROTECTED, ACC_FINAL

  protected final com.fasterxml.jackson.databind.JavaType[] _superInterfaces;
    descriptor: [Lcom/fasterxml/jackson/databind/JavaType;
    flags: (0x0014) ACC_PROTECTED, ACC_FINAL

  protected final com.fasterxml.jackson.databind.type.TypeBindings _bindings;
    descriptor: Lcom/fasterxml/jackson/databind/type/TypeBindings;
    flags: (0x0014) ACC_PROTECTED, ACC_FINAL

  volatile transient java.lang.String _canonicalName;
    descriptor: Ljava/lang/String;
    flags: (0x00c0) ACC_VOLATILE, ACC_TRANSIENT

  protected com.fasterxml.jackson.databind.type.TypeBase(java.lang.Class<?>, com.fasterxml.jackson.databind.type.TypeBindings, com.fasterxml.jackson.databind.JavaType, com.fasterxml.jackson.databind.JavaType[], int, java.lang.Object, java.lang.Object, boolean);
    descriptor: (Ljava/lang/Class;Lcom/fasterxml/jackson/databind/type/TypeBindings;Lcom/fasterxml/jackson/databind/JavaType;[Lcom/fasterxml/jackson/databind/JavaType;ILjava/lang/Object;Ljava/lang/Object;Z)V
    flags: (0x0004) ACC_PROTECTED
    Code:
      stack=6, locals=9, args_size=9
         0: aload_0
         1: aload_1
         2: iload         5
         4: aload         6
         6: aload         7
         8: iload         8
        10: invokespecial #1                  // Method com/fasterxml/jackson/databind/JavaType."<init>":(Ljava/lang/Class;ILjava/lang/Object;Ljava/lang/Object;Z)V
        13: aload_0
        14: aload_2
        15: ifnonnull     24
        18: getstatic     #2                  // Field NO_BINDINGS:Lcom/fasterxml/jackson/databind/type/TypeBindings;
        21: goto          25
        24: aload_2
        25: putfield      #3                  // Field _bindings:Lcom/fasterxml/jackson/databind/type/TypeBindings;
        28: aload_0
        29: aload_3
        30: putfield      #4                  // Field _superClass:Lcom/fasterxml/jackson/databind/JavaType;
        33: aload_0
        34: aload         4
        36: putfield      #5                  // Field _superInterfaces:[Lcom/fasterxml/jackson/databind/JavaType;
        39: return
      LineNumberTable:
        line 49: 0
        line 50: 13
        line 51: 28
        line 52: 33
        line 53: 39
      LocalVariableTable:
        Start  Length  Slot  Name   Signature
            0      40     0  this   Lcom/fasterxml/jackson/databind/type/TypeBase;
            0      40     1   raw   Ljava/lang/Class;
            0      40     2 bindings   Lcom/fasterxml/jackson/databind/type/TypeBindings;
            0      40     3 superClass   Lcom/fasterxml/jackson/databind/JavaType;
            0      40     4 superInts   [Lcom/fasterxml/jackson/databind/JavaType;
            0      40     5  hash   I
            0      40     6 valueHandler   Ljava/lang/Object;
            0      40     7 typeHandler   Ljava/lang/Object;
            0      40     8 asStatic   Z
      LocalVariableTypeTable:
        Start  Length  Slot  Name   Signature
            0      40     1   raw   Ljava/lang/Class<*>;
      StackMapTable: number_of_entries = 2
        frame_type = 255 /* full_frame */
          offset_delta = 24
          locals = [ class com/fasterxml/jackson/databind/type/TypeBase, class java/lang/Class, class com/fasterxml/jackson/databind/type/TypeBindings, class com/fasterxml/jackson/databind/JavaType, class "[Lcom/fasterxml/jackson/databind/JavaType;", int, class java/lang/Object, class java/lang/Object, int ]
          stack = [ class com/fasterxml/jackson/databind/type/TypeBase ]
        frame_type = 255 /* full_frame */
          offset_delta = 0
          locals = [ class com/fasterxml/jackson/databind/type/TypeBase, class java/lang/Class, class com/fasterxml/jackson/databind/type/TypeBindings, class com/fasterxml/jackson/databind/JavaType, class "[Lcom/fasterxml/jackson/databind/JavaType;", int, class java/lang/Object, class java/lang/Object, int ]
          stack = [ class com/fasterxml/jackson/databind/type/TypeBase, class com/fasterxml/jackson/databind/type/TypeBindings ]
    Signature: #103                         // (Ljava/lang/Class<*>;Lcom/fasterxml/jackson/databind/type/TypeBindings;Lcom/fasterxml/jackson/databind/JavaType;[Lcom/fasterxml/jackson/databind/JavaType;ILjava/lang/Object;Ljava/lang/Object;Z)V

  protected com.fasterxml.jackson.databind.type.TypeBase(com.fasterxml.jackson.databind.type.TypeBase);
    descriptor: (Lcom/fasterxml/jackson/databind/type/TypeBase;)V
    flags: (0x0004) ACC_PROTECTED
    Code:
      stack=2, locals=2, args_size=2
         0: aload_0
         1: aload_1
         2: invokespecial #6                  // Method com/fasterxml/jackson/databind/JavaType."<init>":(Lcom/fasterxml/jackson/databind/JavaType;)V
         5: aload_0
         6: aload_1
         7: getfield      #4                  // Field _superClass:Lcom/fasterxml/jackson/databind/JavaType;
        10: putfield      #4                  // Field _superClass:Lcom/fasterxml/jackson/databind/JavaType;
        13: aload_0
        14: aload_1
        15: getfield      #5                  // Field _superInterfaces:[Lcom/fasterxml/jackson/databind/JavaType;
        18: putfield      #5                  // Field _superInterfaces:[Lcom/fasterxml/jackson/databind/JavaType;
        21: aload_0
        22: aload_1
        23: getfield      #3                  // Field _bindings:Lcom/fasterxml/jackson/databind/type/TypeBindings;
        26: putfield      #3                  // Field _bindings:Lcom/fasterxml/jackson/databind/type/TypeBindings;
        29: return
      LineNumberTable:
        line 61: 0
        line 62: 5
        line 63: 13
        line 64: 21
        line 65: 29
      LocalVariableTable:
        Start  Length  Slot  Name   Signature
            0      30     0  this   Lcom/fasterxml/jackson/databind/type/TypeBase;
            0      30     1  base   Lcom/fasterxml/jackson/databind/type/TypeBase;

  public java.lang.String toCanonical();
    descriptor: ()Ljava/lang/String;
    flags: (0x0001) ACC_PUBLIC
    Code:
      stack=1, locals=2, args_size=1
         0: aload_0
         1: getfield      #7                  // Field _canonicalName:Ljava/lang/String;
         4: astore_1
         5: aload_1
         6: ifnonnull     14
         9: aload_0
        10: invokevirtual #8                  // Method buildCanonicalName:()Ljava/lang/String;
        13: astore_1
        14: aload_1
        15: areturn
      LineNumberTable:
        line 70: 0
        line 71: 5
        line 72: 9
        line 74: 14
      LocalVariableTable:
        Start  Length  Slot  Name   Signature
            0      16     0  this   Lcom/fasterxml/jackson/databind/type/TypeBase;
            5      11     1   str   Ljava/lang/String;
      StackMapTable: number_of_entries = 1
        frame_type = 252 /* append */
          offset_delta = 14
          locals = [ class java/lang/String ]

  protected java.lang.String buildCanonicalName();
    descriptor: ()Ljava/lang/String;
    flags: (0x0004) ACC_PROTECTED
    Code:
      stack=1, locals=1, args_size=1
         0: aload_0
         1: getfield      #9                  // Field _class:Ljava/lang/Class;
         4: invokevirtual #10                 // Method java/lang/Class.getName:()Ljava/lang/String;
         7: areturn
      LineNumberTable:
        line 78: 0
      LocalVariableTable:
        Start  Length  Slot  Name   Signature
            0       8     0  this   Lcom/fasterxml/jackson/databind/type/TypeBase;

  public abstract java.lang.StringBuilder getGenericSignature(java.lang.StringBuilder);
    descriptor: (Ljava/lang/StringBuilder;)Ljava/lang/StringBuilder;
    flags: (0x0401) ACC_PUBLIC, ACC_ABSTRACT

  public abstract java.lang.StringBuilder getErasedSignature(java.lang.StringBuilder);
    descriptor: (Ljava/lang/StringBuilder;)Ljava/lang/StringBuilder;
    flags: (0x0401) ACC_PUBLIC, ACC_ABSTRACT

  public com.fasterxml.jackson.databind.type.TypeBindings getBindings();
    descriptor: ()Lcom/fasterxml/jackson/databind/type/TypeBindings;
    flags: (0x0001) ACC_PUBLIC
    Code:
      stack=1, locals=1, args_size=1
         0: aload_0
         1: getfield      #3                  // Field _bindings:Lcom/fasterxml/jackson/databind/type/TypeBindings;
         4: areturn
      LineNumberTable:
        line 89: 0
      LocalVariableTable:
        Start  Length  Slot  Name   Signature
            0       5     0  this   Lcom/fasterxml/jackson/databind/type/TypeBase;

  public int containedTypeCount();
    descriptor: ()I
    flags: (0x0001) ACC_PUBLIC
    Code:
      stack=1, locals=1, args_size=1
         0: aload_0
         1: getfield      #3                  // Field _bindings:Lcom/fasterxml/jackson/databind/type/TypeBindings;
         4: invokevirtual #11                 // Method com/fasterxml/jackson/databind/type/TypeBindings.size:()I
         7: ireturn
      LineNumberTable:
        line 94: 0
      LocalVariableTable:
        Start  Length  Slot  Name   Signature
            0       8     0  this   Lcom/fasterxml/jackson/databind/type/TypeBase;

  public com.fasterxml.jackson.databind.JavaType containedType(int);
    descriptor: (I)Lcom/fasterxml/jackson/databind/JavaType;
    flags: (0x0001) ACC_PUBLIC
    Code:
      stack=2, locals=2, args_size=2
         0: aload_0
         1: getfield      #3                  // Field _bindings:Lcom/fasterxml/jackson/databind/type/TypeBindings;
         4: iload_1
         5: invokevirtual #12                 // Method com/fasterxml/jackson/databind/type/TypeBindings.getBoundType:(I)Lcom/fasterxml/jackson/databind/JavaType;
         8: areturn
      LineNumberTable:
        line 99: 0
      LocalVariableTable:
        Start  Length  Slot  Name   Signature
            0       9     0  this   Lcom/fasterxml/jackson/databind/type/TypeBase;
            0       9     1 index   I

  public java.lang.String containedTypeName(int);
    descriptor: (I)Ljava/lang/String;
    flags: (0x0001) ACC_PUBLIC
    Code:
      stack=2, locals=2, args_size=2
         0: aload_0
         1: getfield      #3                  // Field _bindings:Lcom/fasterxml/jackson/databind/type/TypeBindings;
         4: iload_1
         5: invokevirtual #13                 // Method com/fasterxml/jackson/databind/type/TypeBindings.getBoundName:(I)Ljava/lang/String;
         8: areturn
      LineNumberTable:
        line 105: 0
      LocalVariableTable:
        Start  Length  Slot  Name   Signature
            0       9     0  this   Lcom/fasterxml/jackson/databind/type/TypeBase;
            0       9     1 index   I
    Deprecated: true
    RuntimeVisibleAnnotations:
      0: #125()
        java.lang.Deprecated

  public com.fasterxml.jackson.databind.JavaType getSuperClass();
    descriptor: ()Lcom/fasterxml/jackson/databind/JavaType;
    flags: (0x0001) ACC_PUBLIC
    Code:
      stack=1, locals=1, args_size=1
         0: aload_0
         1: getfield      #4                  // Field _superClass:Lcom/fasterxml/jackson/databind/JavaType;
         4: areturn
      LineNumberTable:
        line 110: 0
      LocalVariableTable:
        Start  Length  Slot  Name   Signature
            0       5     0  this   Lcom/fasterxml/jackson/databind/type/TypeBase;

  public java.util.List<com.fasterxml.jackson.databind.JavaType> getInterfaces();
    descriptor: ()Ljava/util/List;
    flags: (0x0001) ACC_PUBLIC
    Code:
      stack=2, locals=1, args_size=1
         0: aload_0
         1: getfield      #5                  // Field _superInterfaces:[Lcom/fasterxml/jackson/databind/JavaType;
         4: ifnonnull     11
         7: invokestatic  #14                 // Method java/util/Collections.emptyList:()Ljava/util/List;
        10: areturn
        11: aload_0
        12: getfield      #5                  // Field _superInterfaces:[Lcom/fasterxml/jackson/databind/JavaType;
        15: arraylength
        16: lookupswitch  { // 2
                       0: 44
                       1: 48
                 default: 58
            }
        44: invokestatic  #14                 // Method java/util/Collections.emptyList:()Ljava/util/List;
        47: areturn
        48: aload_0
        49: getfield      #5                  // Field _superInterfaces:[Lcom/fasterxml/jackson/databind/JavaType;
        52: iconst_0
        53: aaload
        54: invokestatic  #15                 // Method java/util/Collections.singletonList:(Ljava/lang/Object;)Ljava/util/List;
        57: areturn
        58: aload_0
        59: getfield      #5                  // Field _superInterfaces:[Lcom/fasterxml/jackson/databind/JavaType;
        62: invokestatic  #16                 // Method java/util/Arrays.asList:([Ljava/lang/Object;)Ljava/util/List;
        65: areturn
      LineNumberTable:
        line 115: 0
        line 116: 7
        line 118: 11
        line 120: 44
        line 122: 48
        line 124: 58
      LocalVariableTable:
        Start  Length  Slot  Name   Signature
            0      66     0  this   Lcom/fasterxml/jackson/databind/type/TypeBase;
      StackMapTable: number_of_entries = 4
        frame_type = 11 /* same */
        frame_type = 32 /* same */
        frame_type = 3 /* same */
        frame_type = 9 /* same */
    Signature: #130                         // ()Ljava/util/List<Lcom/fasterxml/jackson/databind/JavaType;>;

  public final com.fasterxml.jackson.databind.JavaType findSuperType(java.lang.Class<?>);
    descriptor: (Ljava/lang/Class;)Lcom/fasterxml/jackson/databind/JavaType;
    flags: (0x0011) ACC_PUBLIC, ACC_FINAL
    Code:
      stack=2, locals=5, args_size=2
         0: aload_1
         1: aload_0
         2: getfield      #9                  // Field _class:Ljava/lang/Class;
         5: if_acmpne     10
         8: aload_0
         9: areturn
        10: aload_1
        11: invokevirtual #17                 // Method java/lang/Class.isInterface:()Z
        14: ifeq          63
        17: aload_0
        18: getfield      #5                  // Field _superInterfaces:[Lcom/fasterxml/jackson/databind/JavaType;
        21: ifnull        63
        24: iconst_0
        25: istore_2
        26: aload_0
        27: getfield      #5                  // Field _superInterfaces:[Lcom/fasterxml/jackson/databind/JavaType;
        30: arraylength
        31: istore_3
        32: iload_2
        33: iload_3
        34: if_icmpge     63
        37: aload_0
        38: getfield      #5                  // Field _superInterfaces:[Lcom/fasterxml/jackson/databind/JavaType;
        41: iload_2
        42: aaload
        43: aload_1
        44: invokevirtual #18                 // Method com/fasterxml/jackson/databind/JavaType.findSuperType:(Ljava/lang/Class;)Lcom/fasterxml/jackson/databind/JavaType;
        47: astore        4
        49: aload         4
        51: ifnull        57
        54: aload         4
        56: areturn
        57: iinc          2, 1
        60: goto          32
        63: aload_0
        64: getfield      #4                  // Field _superClass:Lcom/fasterxml/jackson/databind/JavaType;
        67: ifnull        85
        70: aload_0
        71: getfield      #4                  // Field _superClass:Lcom/fasterxml/jackson/databind/JavaType;
        74: aload_1
        75: invokevirtual #18                 // Method com/fasterxml/jackson/databind/JavaType.findSuperType:(Ljava/lang/Class;)Lcom/fasterxml/jackson/databind/JavaType;
        78: astore_2
        79: aload_2
        80: ifnull        85
        83: aload_2
        84: areturn
        85: aconst_null
        86: areturn
      LineNumberTable:
        line 130: 0
        line 131: 8
        line 134: 10
        line 135: 24
        line 136: 37
        line 137: 49
        line 138: 54
        line 135: 57
        line 143: 63
        line 144: 70
        line 145: 79
        line 146: 83
        line 149: 85
      LocalVariableTable:
        Start  Length  Slot  Name   Signature
           49       8     4  type   Lcom/fasterxml/jackson/databind/JavaType;
           26      37     2     i   I
           32      31     3 count   I
           79       6     2  type   Lcom/fasterxml/jackson/databind/JavaType;
            0      87     0  this   Lcom/fasterxml/jackson/databind/type/TypeBase;
            0      87     1 rawTarget   Ljava/lang/Class;
      LocalVariableTypeTable:
        Start  Length  Slot  Name   Signature
            0      87     1 rawTarget   Ljava/lang/Class<*>;
      StackMapTable: number_of_entries = 5
        frame_type = 10 /* same */
        frame_type = 253 /* append */
          offset_delta = 21
          locals = [ int, int ]
        frame_type = 24 /* same */
        frame_type = 249 /* chop */
          offset_delta = 5
        frame_type = 21 /* same */
    Signature: #137                         // (Ljava/lang/Class<*>;)Lcom/fasterxml/jackson/databind/JavaType;

  public com.fasterxml.jackson.databind.JavaType[] findTypeParameters(java.lang.Class<?>);
    descriptor: (Ljava/lang/Class;)[Lcom/fasterxml/jackson/databind/JavaType;
    flags: (0x0001) ACC_PUBLIC
    Code:
      stack=2, locals=3, args_size=2
         0: aload_0
         1: aload_1
         2: invokevirtual #19                 // Method findSuperType:(Ljava/lang/Class;)Lcom/fasterxml/jackson/databind/JavaType;
         5: astore_2
         6: aload_2
         7: ifnonnull     14
        10: getstatic     #20                 // Field NO_TYPES:[Lcom/fasterxml/jackson/databind/JavaType;
        13: areturn
        14: aload_2
        15: invokevirtual #21                 // Method com/fasterxml/jackson/databind/JavaType.getBindings:()Lcom/fasterxml/jackson/databind/type/TypeBindings;
        18: invokevirtual #22                 // Method com/fasterxml/jackson/databind/type/TypeBindings.typeParameterArray:()[Lcom/fasterxml/jackson/databind/JavaType;
        21: areturn
      LineNumberTable:
        line 155: 0
        line 156: 6
        line 157: 10
        line 159: 14
      LocalVariableTable:
        Start  Length  Slot  Name   Signature
            0      22     0  this   Lcom/fasterxml/jackson/databind/type/TypeBase;
            0      22     1 expType   Ljava/lang/Class;
            6      16     2 match   Lcom/fasterxml/jackson/databind/JavaType;
      LocalVariableTypeTable:
        Start  Length  Slot  Name   Signature
            0      22     1 expType   Ljava/lang/Class<*>;
      StackMapTable: number_of_entries = 1
        frame_type = 252 /* append */
          offset_delta = 14
          locals = [ class com/fasterxml/jackson/databind/JavaType ]
    Signature: #142                         // (Ljava/lang/Class<*>;)[Lcom/fasterxml/jackson/databind/JavaType;

  public void serializeWithType(com.fasterxml.jackson.core.JsonGenerator, com.fasterxml.jackson.databind.SerializerProvider, com.fasterxml.jackson.databind.jsontype.TypeSerializer) throws java.io.IOException;
    descriptor: (Lcom/fasterxml/jackson/core/JsonGenerator;Lcom/fasterxml/jackson/databind/SerializerProvider;Lcom/fasterxml/jackson/databind/jsontype/TypeSerializer;)V
    flags: (0x0001) ACC_PUBLIC
    Code:
      stack=4, locals=5, args_size=4
         0: new           #23                 // class com/fasterxml/jackson/core/type/WritableTypeId
         3: dup
         4: aload_0
         5: getstatic     #24                 // Field com/fasterxml/jackson/core/JsonToken.VALUE_STRING:Lcom/fasterxml/jackson/core/JsonToken;
         8: invokespecial #25                 // Method com/fasterxml/jackson/core/type/WritableTypeId."<init>":(Ljava/lang/Object;Lcom/fasterxml/jackson/core/JsonToken;)V
        11: astore        4
        13: aload_3
        14: aload_1
        15: aload         4
        17: invokevirtual #26                 // Method com/fasterxml/jackson/databind/jsontype/TypeSerializer.writeTypePrefix:(Lcom/fasterxml/jackson/core/JsonGenerator;Lcom/fasterxml/jackson/core/type/WritableTypeId;)Lcom/fasterxml/jackson/core/type/WritableTypeId;
        20: pop
        21: aload_0
        22: aload_1
        23: aload_2
        24: invokevirtual #27                 // Method serialize:(Lcom/fasterxml/jackson/core/JsonGenerator;Lcom/fasterxml/jackson/databind/SerializerProvider;)V
        27: aload_3
        28: aload_1
        29: aload         4
        31: invokevirtual #28                 // Method com/fasterxml/jackson/databind/jsontype/TypeSerializer.writeTypeSuffix:(Lcom/fasterxml/jackson/core/JsonGenerator;Lcom/fasterxml/jackson/core/type/WritableTypeId;)Lcom/fasterxml/jackson/core/type/WritableTypeId;
        34: pop
        35: return
      LineNumberTable:
        line 173: 0
        line 174: 13
        line 175: 21
        line 176: 27
        line 177: 35
      LocalVariableTable:
        Start  Length  Slot  Name   Signature
            0      36     0  this   Lcom/fasterxml/jackson/databind/type/TypeBase;
            0      36     1     g   Lcom/fasterxml/jackson/core/JsonGenerator;
            0      36     2 provider   Lcom/fasterxml/jackson/databind/SerializerProvider;
            0      36     3 typeSer   Lcom/fasterxml/jackson/databind/jsontype/TypeSerializer;
           13      23     4 typeIdDef   Lcom/fasterxml/jackson/core/type/WritableTypeId;
    Exceptions:
      throws java.io.IOException

  public void serialize(com.fasterxml.jackson.core.JsonGenerator, com.fasterxml.jackson.databind.SerializerProvider) throws java.io.IOException;
    descriptor: (Lcom/fasterxml/jackson/core/JsonGenerator;Lcom/fasterxml/jackson/databind/SerializerProvider;)V
    flags: (0x0001) ACC_PUBLIC
    Code:
      stack=2, locals=3, args_size=3
         0: aload_1
         1: aload_0
         2: invokevirtual #29                 // Method toCanonical:()Ljava/lang/String;
         5: invokevirtual #30                 // Method com/fasterxml/jackson/core/JsonGenerator.writeString:(Ljava/lang/String;)V
         8: return
      LineNumberTable:
        line 183: 0
        line 184: 8
      LocalVariableTable:
        Start  Length  Slot  Name   Signature
            0       9     0  this   Lcom/fasterxml/jackson/databind/type/TypeBase;
            0       9     1   gen   Lcom/fasterxml/jackson/core/JsonGenerator;
            0       9     2 provider   Lcom/fasterxml/jackson/databind/SerializerProvider;
    Exceptions:
      throws java.io.IOException

  protected static java.lang.StringBuilder _classSignature(java.lang.Class<?>, java.lang.StringBuilder, boolean);
    descriptor: (Ljava/lang/Class;Ljava/lang/StringBuilder;Z)Ljava/lang/StringBuilder;
    flags: (0x000c) ACC_PROTECTED, ACC_STATIC
    Code:
      stack=4, locals=7, args_size=3
         0: aload_0
         1: invokevirtual #31                 // Method java/lang/Class.isPrimitive:()Z
         4: ifeq          190
         7: aload_0
         8: getstatic     #32                 // Field java/lang/Boolean.TYPE:Ljava/lang/Class;
        11: if_acmpne     24
        14: aload_1
        15: bipush        90
        17: invokevirtual #33                 // Method java/lang/StringBuilder.append:(C)Ljava/lang/StringBuilder;
        20: pop
        21: goto          261
        24: aload_0
        25: getstatic     #34                 // Field java/lang/Byte.TYPE:Ljava/lang/Class;
        28: if_acmpne     41
        31: aload_1
        32: bipush        66
        34: invokevirtual #33                 // Method java/lang/StringBuilder.append:(C)Ljava/lang/StringBuilder;
        37: pop
        38: goto          261
        41: aload_0
        42: getstatic     #35                 // Field java/lang/Short.TYPE:Ljava/lang/Class;
        45: if_acmpne     58
        48: aload_1
        49: bipush        83
        51: invokevirtual #33                 // Method java/lang/StringBuilder.append:(C)Ljava/lang/StringBuilder;
        54: pop
        55: goto          261
        58: aload_0
        59: getstatic     #36                 // Field java/lang/Character.TYPE:Ljava/lang/Class;
        62: if_acmpne     75
        65: aload_1
        66: bipush        67
        68: invokevirtual #33                 // Method java/lang/StringBuilder.append:(C)Ljava/lang/StringBuilder;
        71: pop
        72: goto          261
        75: aload_0
        76: getstatic     #37                 // Field java/lang/Integer.TYPE:Ljava/lang/Class;
        79: if_acmpne     92
        82: aload_1
        83: bipush        73
        85: invokevirtual #33                 // Method java/lang/StringBuilder.append:(C)Ljava/lang/StringBuilder;
        88: pop
        89: goto          261
        92: aload_0
        93: getstatic     #38                 // Field java/lang/Long.TYPE:Ljava/lang/Class;
        96: if_acmpne     109
        99: aload_1
       100: bipush        74
       102: invokevirtual #33                 // Method java/lang/StringBuilder.append:(C)Ljava/lang/StringBuilder;
       105: pop
       106: goto          261
       109: aload_0
       110: getstatic     #39                 // Field java/lang/Float.TYPE:Ljava/lang/Class;
       113: if_acmpne     126
       116: aload_1
       117: bipush        70
       119: invokevirtual #33                 // Method java/lang/StringBuilder.append:(C)Ljava/lang/StringBuilder;
       122: pop
       123: goto          261
       126: aload_0
       127: getstatic     #40                 // Field java/lang/Double.TYPE:Ljava/lang/Class;
       130: if_acmpne     143
       133: aload_1
       134: bipush        68
       136: invokevirtual #33                 // Method java/lang/StringBuilder.append:(C)Ljava/lang/StringBuilder;
       139: pop
       140: goto          261
       143: aload_0
       144: getstatic     #41                 // Field java/lang/Void.TYPE:Ljava/lang/Class;
       147: if_acmpne     160
       150: aload_1
       151: bipush        86
       153: invokevirtual #33                 // Method java/lang/StringBuilder.append:(C)Ljava/lang/StringBuilder;
       156: pop
       157: goto          261
       160: new           #42                 // class java/lang/IllegalStateException
       163: dup
       164: new           #43                 // class java/lang/StringBuilder
       167: dup
       168: invokespecial #44                 // Method java/lang/StringBuilder."<init>":()V
       171: ldc           #45                 // String Unrecognized primitive type:
       173: invokevirtual #46                 // Method java/lang/StringBuilder.append:(Ljava/lang/String;)Ljava/lang/StringBuilder;
       176: aload_0
       177: invokevirtual #10                 // Method java/lang/Class.getName:()Ljava/lang/String;
       180: invokevirtual #46                 // Method java/lang/StringBuilder.append:(Ljava/lang/String;)Ljava/lang/StringBuilder;
       183: invokevirtual #47                 // Method java/lang/StringBuilder.toString:()Ljava/lang/String;
       186: invokespecial #48                 // Method java/lang/IllegalStateException."<init>":(Ljava/lang/String;)V
       189: athrow
       190: aload_1
       191: bipush        76
       193: invokevirtual #33                 // Method java/lang/StringBuilder.append:(C)Ljava/lang/StringBuilder;
       196: pop
       197: aload_0
       198: invokevirtual #10                 // Method java/lang/Class.getName:()Ljava/lang/String;
       201: astore_3
       202: iconst_0
       203: istore        4
       205: aload_3
       206: invokevirtual #49                 // Method java/lang/String.length:()I
       209: istore        5
       211: iload         4
       213: iload         5
       215: if_icmpge     250
       218: aload_3
       219: iload         4
       221: invokevirtual #50                 // Method java/lang/String.charAt:(I)C
       224: istore        6
       226: iload         6
       228: bipush        46
       230: if_icmpne     237
       233: bipush        47
       235: istore        6
       237: aload_1
       238: iload         6
       240: invokevirtual #33                 // Method java/lang/StringBuilder.append:(C)Ljava/lang/StringBuilder;
       243: pop
       244: iinc          4, 1
       247: goto          211
       250: iload_2
       251: ifeq          261
       254: aload_1
       255: bipush        59
       257: invokevirtual #33                 // Method java/lang/StringBuilder.append:(C)Ljava/lang/StringBuilder;
       260: pop
       261: aload_1
       262: areturn
      LineNumberTable:
        line 199: 0
        line 200: 7
        line 201: 14
        line 202: 24
        line 203: 31
        line 205: 41
        line 206: 48
        line 208: 58
        line 209: 65
        line 211: 75
        line 212: 82
        line 214: 92
        line 215: 99
        line 217: 109
        line 218: 116
        line 220: 126
        line 221: 133
        line 223: 143
        line 224: 150
        line 226: 160
        line 229: 190
        line 230: 197
        line 231: 202
        line 232: 218
        line 233: 226
        line 234: 237
        line 231: 244
        line 236: 250
        line 237: 254
        line 240: 261
      LocalVariableTable:
        Start  Length  Slot  Name   Signature
          226      18     6     c   C
          205      45     4     i   I
          211      39     5   len   I
          202      59     3  name   Ljava/lang/String;
            0     263     0   cls   Ljava/lang/Class;
            0     263     1    sb   Ljava/lang/StringBuilder;
            0     263     2 trailingSemicolon   Z
      LocalVariableTypeTable:
        Start  Length  Slot  Name   Signature
            0     263     0   cls   Ljava/lang/Class<*>;
      StackMapTable: number_of_entries = 14
        frame_type = 24 /* same */
        frame_type = 16 /* same */
        frame_type = 16 /* same */
        frame_type = 16 /* same */
        frame_type = 16 /* same */
        frame_type = 16 /* same */
        frame_type = 16 /* same */
        frame_type = 16 /* same */
        frame_type = 16 /* same */
        frame_type = 29 /* same */
        frame_type = 254 /* append */
          offset_delta = 20
          locals = [ class java/lang/String, int, int ]
        frame_type = 252 /* append */
          offset_delta = 25
          locals = [ int ]
        frame_type = 248 /* chop */
          offset_delta = 12
        frame_type = 250 /* chop */
          offset_delta = 10
    Signature: #168                         // (Ljava/lang/Class<*>;Ljava/lang/StringBuilder;Z)Ljava/lang/StringBuilder;

  protected static com.fasterxml.jackson.databind.JavaType _bogusSuperClass(java.lang.Class<?>);
    descriptor: (Ljava/lang/Class;)Lcom/fasterxml/jackson/databind/JavaType;
    flags: (0x000c) ACC_PROTECTED, ACC_STATIC
    Code:
      stack=1, locals=2, args_size=1
         0: aload_0
         1: invokevirtual #51                 // Method java/lang/Class.getSuperclass:()Ljava/lang/Class;
         4: astore_1
         5: aload_1
         6: ifnonnull     11
         9: aconst_null
        10: areturn
        11: invokestatic  #52                 // Method com/fasterxml/jackson/databind/type/TypeFactory.unknownType:()Lcom/fasterxml/jackson/databind/JavaType;
        14: areturn
      LineNumberTable:
        line 253: 0
        line 254: 5
        line 255: 9
        line 257: 11
      LocalVariableTable:
        Start  Length  Slot  Name   Signature
            0      15     0   cls   Ljava/lang/Class;
            5      10     1 parent   Ljava/lang/Class;
      LocalVariableTypeTable:
        Start  Length  Slot  Name   Signature
            0      15     0   cls   Ljava/lang/Class<*>;
            5      10     1 parent   Ljava/lang/Class<*>;
      StackMapTable: number_of_entries = 1
        frame_type = 252 /* append */
          offset_delta = 11
          locals = [ class java/lang/Class ]
    Signature: #137                         // (Ljava/lang/Class<*>;)Lcom/fasterxml/jackson/databind/JavaType;

  protected boolean _hasNTypeParameters(int);
    descriptor: (I)Z
    flags: (0x0004) ACC_PROTECTED
    Code:
      stack=2, locals=3, args_size=2
         0: aload_0
         1: getfield      #9                  // Field _class:Ljava/lang/Class;
         4: invokevirtual #53                 // Method java/lang/Class.getTypeParameters:()[Ljava/lang/reflect/TypeVariable;
         7: astore_2
         8: aload_2
         9: arraylength
        10: iload_1
        11: if_icmpne     18
        14: iconst_1
        15: goto          19
        18: iconst_0
        19: ireturn
      LineNumberTable:
        line 261: 0
        line 262: 8
      LocalVariableTable:
        Start  Length  Slot  Name   Signature
            0      20     0  this   Lcom/fasterxml/jackson/databind/type/TypeBase;
            0      20     1 count   I
            8      12     2 params   [Ljava/lang/reflect/TypeVariable;
      LocalVariableTypeTable:
        Start  Length  Slot  Name   Signature
            8      12     2 params   [Ljava/lang/reflect/TypeVariable<*>;
      StackMapTable: number_of_entries = 2
        frame_type = 252 /* append */
          offset_delta = 18
          locals = [ class "[Ljava/lang/reflect/TypeVariable;" ]
        frame_type = 64 /* same_locals_1_stack_item */
          stack = [ int ]

  public com.fasterxml.jackson.core.type.ResolvedType containedType(int);
    descriptor: (I)Lcom/fasterxml/jackson/core/type/ResolvedType;
    flags: (0x1041) ACC_PUBLIC, ACC_BRIDGE, ACC_SYNTHETIC
    Code:
      stack=2, locals=2, args_size=2
         0: aload_0
         1: iload_1
         2: invokevirtual #54                 // Method containedType:(I)Lcom/fasterxml/jackson/databind/JavaType;
         5: areturn
      LineNumberTable:
        line 15: 0
      LocalVariableTable:
        Start  Length  Slot  Name   Signature
            0       6     0  this   Lcom/fasterxml/jackson/databind/type/TypeBase;

  static {};
    descriptor: ()V
    flags: (0x0008) ACC_STATIC
    Code:
      stack=1, locals=0, args_size=0
         0: invokestatic  #55                 // Method com/fasterxml/jackson/databind/type/TypeBindings.emptyBindings:()Lcom/fasterxml/jackson/databind/type/TypeBindings;
         3: putstatic     #2                  // Field NO_BINDINGS:Lcom/fasterxml/jackson/databind/type/TypeBindings;
         6: iconst_0
         7: anewarray     #56                 // class com/fasterxml/jackson/databind/JavaType
        10: putstatic     #20                 // Field NO_TYPES:[Lcom/fasterxml/jackson/databind/JavaType;
        13: return
      LineNumberTable:
        line 21: 0
        line 22: 6
}
SourceFile: "TypeBase.java"
