Classfile /Users/mw/Projects/slang-braindump/.jar/jar11/assemble/slang-braindump/assemble/content/com/fasterxml/jackson/databind/type/TypeParser$MyTokenizer.class
  Last modified May 29, 2022; size 1386 bytes
  SHA-256 checksum 4f903ee507c9560d4ca71eb08803ac5c332a50576fcdeb527f227f756e22d6c5
  Compiled from "TypeParser.java"
final class com.fasterxml.jackson.databind.type.TypeParser$MyTokenizer extends java.util.StringTokenizer
  minor version: 0
  major version: 52
  flags: (0x0030) ACC_FINAL, ACC_SUPER
  this_class: #11                         // com/fasterxml/jackson/databind/type/TypeParser$MyTokenizer
  super_class: #12                        // java/util/StringTokenizer
  interfaces: 0, fields: 3, methods: 6, attributes: 2
Constant pool:
   #1 = String             #40            // <,>
   #2 = Methodref          #12.#41        // java/util/StringTokenizer."<init>":(Ljava/lang/String;Ljava/lang/String;Z)V
   #3 = Fieldref           #11.#42        // com/fasterxml/jackson/databind/type/TypeParser$MyTokenizer._input:Ljava/lang/String;
   #4 = Fieldref           #11.#43        // com/fasterxml/jackson/databind/type/TypeParser$MyTokenizer._pushbackToken:Ljava/lang/String;
   #5 = Methodref          #12.#44        // java/util/StringTokenizer.hasMoreTokens:()Z
   #6 = Methodref          #12.#45        // java/util/StringTokenizer.nextToken:()Ljava/lang/String;
   #7 = Fieldref           #11.#46        // com/fasterxml/jackson/databind/type/TypeParser$MyTokenizer._index:I
   #8 = Methodref          #47.#48        // java/lang/String.length:()I
   #9 = Methodref          #47.#49        // java/lang/String.trim:()Ljava/lang/String;
  #10 = Methodref          #47.#50        // java/lang/String.substring:(I)Ljava/lang/String;
  #11 = Class              #52            // com/fasterxml/jackson/databind/type/TypeParser$MyTokenizer
  #12 = Class              #53            // java/util/StringTokenizer
  #13 = Utf8               _input
  #14 = Utf8               Ljava/lang/String;
  #15 = Utf8               _index
  #16 = Utf8               I
  #17 = Utf8               _pushbackToken
  #18 = Utf8               <init>
  #19 = Utf8               (Ljava/lang/String;)V
  #20 = Utf8               Code
  #21 = Utf8               LineNumberTable
  #22 = Utf8               LocalVariableTable
  #23 = Utf8               this
  #24 = Utf8               MyTokenizer
  #25 = Utf8               InnerClasses
  #26 = Utf8               Lcom/fasterxml/jackson/databind/type/TypeParser$MyTokenizer;
  #27 = Utf8               str
  #28 = Utf8               hasMoreTokens
  #29 = Utf8               ()Z
  #30 = Utf8               StackMapTable
  #31 = Utf8               nextToken
  #32 = Utf8               ()Ljava/lang/String;
  #33 = Utf8               token
  #34 = Class              #54            // java/lang/String
  #35 = Utf8               pushBack
  #36 = Utf8               getAllInput
  #37 = Utf8               getRemainingInput
  #38 = Utf8               SourceFile
  #39 = Utf8               TypeParser.java
  #40 = Utf8               <,>
  #41 = NameAndType        #18:#55        // "<init>":(Ljava/lang/String;Ljava/lang/String;Z)V
  #42 = NameAndType        #13:#14        // _input:Ljava/lang/String;
  #43 = NameAndType        #17:#14        // _pushbackToken:Ljava/lang/String;
  #44 = NameAndType        #28:#29        // hasMoreTokens:()Z
  #45 = NameAndType        #31:#32        // nextToken:()Ljava/lang/String;
  #46 = NameAndType        #15:#16        // _index:I
  #47 = Class              #54            // java/lang/String
  #48 = NameAndType        #56:#57        // length:()I
  #49 = NameAndType        #58:#32        // trim:()Ljava/lang/String;
  #50 = NameAndType        #59:#60        // substring:(I)Ljava/lang/String;
  #51 = Class              #61            // com/fasterxml/jackson/databind/type/TypeParser
  #52 = Utf8               com/fasterxml/jackson/databind/type/TypeParser$MyTokenizer
  #53 = Utf8               java/util/StringTokenizer
  #54 = Utf8               java/lang/String
  #55 = Utf8               (Ljava/lang/String;Ljava/lang/String;Z)V
  #56 = Utf8               length
  #57 = Utf8               ()I
  #58 = Utf8               trim
  #59 = Utf8               substring
  #60 = Utf8               (I)Ljava/lang/String;
  #61 = Utf8               com/fasterxml/jackson/databind/type/TypeParser
{
  protected final java.lang.String _input;
    descriptor: Ljava/lang/String;
    flags: (0x0014) ACC_PROTECTED, ACC_FINAL

  protected int _index;
    descriptor: I
    flags: (0x0004) ACC_PROTECTED

  protected java.lang.String _pushbackToken;
    descriptor: Ljava/lang/String;
    flags: (0x0004) ACC_PROTECTED

  public com.fasterxml.jackson.databind.type.TypeParser$MyTokenizer(java.lang.String);
    descriptor: (Ljava/lang/String;)V
    flags: (0x0001) ACC_PUBLIC
    Code:
      stack=4, locals=2, args_size=2
         0: aload_0
         1: aload_1
         2: ldc           #1                  // String <,>
         4: iconst_1
         5: invokespecial #2                  // Method java/util/StringTokenizer."<init>":(Ljava/lang/String;Ljava/lang/String;Z)V
         8: aload_0
         9: aload_1
        10: putfield      #3                  // Field _input:Ljava/lang/String;
        13: return
      LineNumberTable:
        line 104: 0
        line 105: 8
        line 106: 13
      LocalVariableTable:
        Start  Length  Slot  Name   Signature
            0      14     0  this   Lcom/fasterxml/jackson/databind/type/TypeParser$MyTokenizer;
            0      14     1   str   Ljava/lang/String;

  public boolean hasMoreTokens();
    descriptor: ()Z
    flags: (0x0001) ACC_PUBLIC
    Code:
      stack=1, locals=1, args_size=1
         0: aload_0
         1: getfield      #4                  // Field _pushbackToken:Ljava/lang/String;
         4: ifnonnull     14
         7: aload_0
         8: invokespecial #5                  // Method java/util/StringTokenizer.hasMoreTokens:()Z
        11: ifeq          18
        14: iconst_1
        15: goto          19
        18: iconst_0
        19: ireturn
      LineNumberTable:
        line 110: 0
      LocalVariableTable:
        Start  Length  Slot  Name   Signature
            0      20     0  this   Lcom/fasterxml/jackson/databind/type/TypeParser$MyTokenizer;
      StackMapTable: number_of_entries = 3
        frame_type = 14 /* same */
        frame_type = 3 /* same */
        frame_type = 64 /* same_locals_1_stack_item */
          stack = [ int ]

  public java.lang.String nextToken();
    descriptor: ()Ljava/lang/String;
    flags: (0x0001) ACC_PUBLIC
    Code:
      stack=3, locals=2, args_size=1
         0: aload_0
         1: getfield      #4                  // Field _pushbackToken:Ljava/lang/String;
         4: ifnull        20
         7: aload_0
         8: getfield      #4                  // Field _pushbackToken:Ljava/lang/String;
        11: astore_1
        12: aload_0
        13: aconst_null
        14: putfield      #4                  // Field _pushbackToken:Ljava/lang/String;
        17: goto          43
        20: aload_0
        21: invokespecial #6                  // Method java/util/StringTokenizer.nextToken:()Ljava/lang/String;
        24: astore_1
        25: aload_0
        26: dup
        27: getfield      #7                  // Field _index:I
        30: aload_1
        31: invokevirtual #8                  // Method java/lang/String.length:()I
        34: iadd
        35: putfield      #7                  // Field _index:I
        38: aload_1
        39: invokevirtual #9                  // Method java/lang/String.trim:()Ljava/lang/String;
        42: astore_1
        43: aload_1
        44: areturn
      LineNumberTable:
        line 116: 0
        line 117: 7
        line 118: 12
        line 120: 20
        line 121: 25
        line 122: 38
        line 124: 43
      LocalVariableTable:
        Start  Length  Slot  Name   Signature
           12       8     1 token   Ljava/lang/String;
            0      45     0  this   Lcom/fasterxml/jackson/databind/type/TypeParser$MyTokenizer;
           25      20     1 token   Ljava/lang/String;
      StackMapTable: number_of_entries = 2
        frame_type = 20 /* same */
        frame_type = 252 /* append */
          offset_delta = 22
          locals = [ class java/lang/String ]

  public void pushBack(java.lang.String);
    descriptor: (Ljava/lang/String;)V
    flags: (0x0001) ACC_PUBLIC
    Code:
      stack=2, locals=2, args_size=2
         0: aload_0
         1: aload_1
         2: putfield      #4                  // Field _pushbackToken:Ljava/lang/String;
         5: return
      LineNumberTable:
        line 128: 0
        line 130: 5
      LocalVariableTable:
        Start  Length  Slot  Name   Signature
            0       6     0  this   Lcom/fasterxml/jackson/databind/type/TypeParser$MyTokenizer;
            0       6     1 token   Ljava/lang/String;

  public java.lang.String getAllInput();
    descriptor: ()Ljava/lang/String;
    flags: (0x0001) ACC_PUBLIC
    Code:
      stack=1, locals=1, args_size=1
         0: aload_0
         1: getfield      #3                  // Field _input:Ljava/lang/String;
         4: areturn
      LineNumberTable:
        line 132: 0
      LocalVariableTable:
        Start  Length  Slot  Name   Signature
            0       5     0  this   Lcom/fasterxml/jackson/databind/type/TypeParser$MyTokenizer;

  public java.lang.String getRemainingInput();
    descriptor: ()Ljava/lang/String;
    flags: (0x0001) ACC_PUBLIC
    Code:
      stack=2, locals=1, args_size=1
         0: aload_0
         1: getfield      #3                  // Field _input:Ljava/lang/String;
         4: aload_0
         5: getfield      #7                  // Field _index:I
         8: invokevirtual #10                 // Method java/lang/String.substring:(I)Ljava/lang/String;
        11: areturn
      LineNumberTable:
        line 134: 0
      LocalVariableTable:
        Start  Length  Slot  Name   Signature
            0      12     0  this   Lcom/fasterxml/jackson/databind/type/TypeParser$MyTokenizer;
}
SourceFile: "TypeParser.java"
InnerClasses:
  static final #24= #11 of #51;           // MyTokenizer=class com/fasterxml/jackson/databind/type/TypeParser$MyTokenizer of class com/fasterxml/jackson/databind/type/TypeParser
