Classfile /Users/mw/Projects/slang-braindump/.jar/jar11/assemble/slang-braindump/assemble/content/org/scalatest/featurespec/FixtureAsyncFeatureSpecLike.class
  Last modified May 29, 2022; size 25400 bytes
  SHA-256 checksum 40ed65282abaaaca2b6bad48d3ecdbae92c533c21cba53c37dd6a7972d0e920c
  Compiled from "FixtureAsyncFeatureSpecLike.scala"
public interface org.scalatest.featurespec.FixtureAsyncFeatureSpecLike extends org.scalatest.FixtureAsyncTestSuite,org.scalatest.FixtureAsyncTestRegistration,org.scalatest.Informing,org.scalatest.Notifying,org.scalatest.Alerting,org.scalatest.Documenting
  minor version: 0
  major version: 52
  flags: (0x0601) ACC_PUBLIC, ACC_INTERFACE, ACC_ABSTRACT
  this_class: #2                          // org/scalatest/featurespec/FixtureAsyncFeatureSpecLike
  super_class: #4                         // java/lang/Object
  interfaces: 6, fields: 0, methods: 63, attributes: 6
Constant pool:
    #1 = Utf8               org/scalatest/featurespec/FixtureAsyncFeatureSpecLike
    #2 = Class              #1            // org/scalatest/featurespec/FixtureAsyncFeatureSpecLike
    #3 = Utf8               java/lang/Object
    #4 = Class              #3            // java/lang/Object
    #5 = Utf8               org/scalatest/FixtureAsyncTestSuite
    #6 = Class              #5            // org/scalatest/FixtureAsyncTestSuite
    #7 = Utf8               org/scalatest/FixtureAsyncTestRegistration
    #8 = Class              #7            // org/scalatest/FixtureAsyncTestRegistration
    #9 = Utf8               org/scalatest/Informing
   #10 = Class              #9            // org/scalatest/Informing
   #11 = Utf8               org/scalatest/Notifying
   #12 = Class              #11           // org/scalatest/Notifying
   #13 = Utf8               org/scalatest/Alerting
   #14 = Class              #13           // org/scalatest/Alerting
   #15 = Utf8               org/scalatest/Documenting
   #16 = Class              #15           // org/scalatest/Documenting
   #17 = Utf8               FixtureAsyncFeatureSpecLike.scala
   #18 = Utf8               Lorg/scalatest/Finders;
   #19 = Utf8               value
   #20 = Utf8               org.scalatest.finders.FeatureSpecFinder
   #21 = Utf8               Lscala/reflect/ScalaSignature;
   #22 = Utf8               bytes
   #23 = Utf8               \u0006\u0005\tmhaB\u0017/!\u0003\r\t!\u000e\u0005\u0006\u001f\u0002!\t\u0001\u0015\u0005\b)\u0002\u0011\r\u0011\"\u0004V\u0011\u0015y\u0006\u0001\"\u0005a\u0011\u0015!\u0007\u0001\"\u0005f\u0011\u0015I\u0007\u0001\"\u0005k\u0011\u0015q\u0007\u0001\"\u0005p\u0011\u0015\u0019\b\u0001\"\u0004u\u0011\u001d\ti\u0005\u0001C\u0003\u0003\u001fBq!!\u0018\u0001\t\u001b\ty\u0006C\u0004\u0002l\u0001!)!!\u001c\u0007\r\u0005m\u0004\u0001AA?\u0011)\tyh\u0003B\u0001B\u0003%\u0011q\u0005\u0005\u000b\u0003\u007fY!\u0011!Q\u0001\n\u0005\u0005\u0003bBAA\u0017\u0011\u0005\u00111\u0011\u0005\b\u0003\u0017[A\u0011AAG\u0011\u001d\t\u0019j\u0003C\u0001\u0003+Cq!a#\f\t\u001b\ti\nC\u0004\u0002\u0014.!\t!!+\t\u000f\u0005E\u0006\u0001\"\u0005\u00024\"9\u0011Q\u001a\u0001\u0005\u0012\u0005=gABAk\u0001\u0001\t9\u000e\u0003\u0006\u0002\u0000U\u0011\t\u0011)A\u0005\u0003OA!\"a\u0010\u0016\u0005\u0003\u0005\u000b\u0011BA!\u0011\u001d\t\t)\u0006C\u0001\u00033Dq!a#\u0016\t\u001b\t\t\u000fC\u0004\u0002\u0014V!\t!a:\t\u000f\u0005-U\u0003\"\u0004\u0002p\"9\u00111S\u000b\u0005\u0002\u0005U\bbBA\u007f\u0001\u0011E\u0011q \u0005\b\u0005\u000b\u0001A\u0011\u0003B\u0004\u0011\u001d\u0011\u0019\u0003\u0001C\u0007\u0005KAqAa\f\u0001\t#\u0011\t\u0004C\u0004\u0003>\u0001!\tEa\u0010\t\u000f\t5\u0003\u0001\"\u0015\u0003P!9!Q\r\u0001\u0005R\t\u001d\u0004b\u0002B:\u0001\u0011\u0005#Q\u000f\u0005\b\u0005o\u0002A\u0011\tB=\u0011\u001d\u0011y\b\u0001C\t\u0005\u0003CqA!$\u0001\t#\u0011y\tC\u0004\u0003\u0014\u0002!\u0019B!&\t\u0013\t\u0015\u0006A1A\u0005F\t\u001d\u0006b\u0002BX\u0001\u0011\u0005#\u0011\u0017\u0005\n\u0005\u000b\u0004\u0011\u0013!C\u0001\u0005\u000fDaB!8\u0001!\u0003\r\t\u0011!C\u0005\u0005?\u0014)OA\u000eGSb$XO]3Bgft7MR3biV\u0014Xm\u00159fG2K7.\u001a\u0006\u0003_A\n1BZ3biV\u0014Xm\u001d9fG*\u0011\u0011GM\u0001\ng\u000e\fG.\u0019;fgRT\u0011aM\u0001\u0004_J<7\u0001A\n\t\u0001Yb\u0004i\u0011$J\u0019B\u0011qGO\u0007\u0002q)\t\u0011(A\u0003tG\u0006d\u0017-\u0003\u0002<q\t1\u0011I\\=SK\u001a\u0004\"!\u0010 \u000e\u0003AJ!a\u0010\u0019\u0003+\u0019K\u0007\u0010^;sK\u0006\u001b\u0018P\\2UKN$8+^5uKB\u0011Q(Q\u0005\u0003\u0005B\u0012ADR5yiV\u0014X-Q:z]\u000e$Vm\u001d;SK\u001eL7\u000f\u001e:bi&|g\u000e\u0005\u0002>\t&\u0011Q\t\r\u0002\n\u0013:4wN]7j]\u001e\u0004\"!P$\n\u0005!\u0003$!\u0003(pi&4\u00170\u001b8h!\ti$*\u0003\u0002La\tA\u0011\t\\3si&tw\r\u0005\u0002>\u001b&\u0011a\n\r\u0002\f\t>\u001cW/\\3oi&tw-\u0001\u0004%S:LG\u000f\n\u000b\u0002#B\u0011qGU\u0005\u0003\'b\u0012A!\u00168ji\u00061QM\\4j]\u0016,\u0012A\u0016\t\u0004{]K\u0016B\u0001-1\u0005I\t5/\u001f8d\r&DH/\u001e:f\u000b:<\u0017N\\3\u0011\u0005i[V\"\u0001\u0001\n\u0005qk&\u0001\u0004$jqR,(/\u001a)be\u0006l\u0017B\u000101\u000511\u0015\u000e\u001f;ve\u0016\u001cV/\u001b;f\u0003\u0011IgNZ8\u0016\u0003\u0005\u0004\"!\u00102\n\u0005\r\u0004$\u0001C%oM>\u0014X.\u001a:\u0002\t9|G/Z\u000b\u0002MB\u0011QhZ\u0005\u0003QB\u0012\u0001BT8uS\u001aLWM]\u0001\u0006C2,\'\u000f^\u000b\u0002WB\u0011Q\b\\\u0005\u0003[B\u0012q!\u00117feR,\'/\u0001\u0004nCJ\\W\u000f]\u000b\u0002aB\u0011Q(]\u0005\u0003eB\u0012!\u0002R8dk6,g\u000e^3s\u0003U\u0011XmZ5ti\u0016\u0014\u0018i]=oGR+7\u000f^%na2$R!^A\u0012\u0003{!B!\u0015<\u0002\u0010!)qo\u0002a\u0001q\u00069A/Z:u\rVt\u0007\u0003B\u001cz3nL!A\u001f\u001d\u0003\u0013\u0019+hn\u0019;j_:\f\u0004\u0003\u0002?\u0000\u0003\u0007i\u0011! \u0006\u0003}b\n!bY8oGV\u0014(/\u001a8u\u0013\r\t\t! \u0002\u0007\rV$XO]3\u0011\t\u0005\u0015\u00111B\u0007\u0003\u0003\u000fQ1!!\u00031\u0003)\u0019w.\u001c9bi&\u0014G.Z\u0005\u0005\u0003\u001b\t9AA\u0005BgN,\'\u000f^5p]\"9\u0011\u0011C\u0004A\u0002\u0005M\u0011a\u00019pgB!\u0011QCA\u0010\u001b\t\t9B\u0003\u0003\u0002\u001a\u0005m\u0011AB:pkJ\u001cWMC\u0002\u0002\u001eI\n\u0011b]2bY\u0006\u001cG/[2\n\t\u0005\u0005\u0012q\u0003\u0002\t!>\u001c\u0018\u000e^5p]\"9\u0011QE\u0004A\u0002\u0005\u001d\u0012\u0001\u0003;fgR$V\r\u001f;\u0011\t\u0005%\u0012q\u0007\b\u0005\u0003W\t\u0019\u0004E\u0002\u0002.aj!!a\f\u000b\u0007\u0005EB\'\u0001\u0004=e>|GOP\u0005\u0004\u0003kA\u0014A\u0002)sK\u0012,g-\u0003\u0003\u0002:\u0005m\"AB*ue&twMC\u0002\u00026aBq!a\u0010\b\u0001\u0004\t\t%\u0001\u0005uKN$H+Y4t!\u00159\u00141IA$\u0013\r\t)\u0005\u000f\u0002\u000byI,\u0007/Z1uK\u0012t\u0004cA\u001f\u0002J%\u0019\u00111\n\u0019\u0003\u0007Q\u000bw-A\tsK\u001eL7\u000f^3s\u0003NLhn\u0019+fgR$b!!\u0015\u0002Z\u0005mC\u0003BA*\u0003/\"2!UA+\u0011\u001d\t\t\u0002\u0003a\u0002\u0003\'AQa\u001e\u0005A\u0002aDq!!\n\t\u0001\u0004\t9\u0003C\u0004\u0002@!\u0001\r!!\u0011\u00029I,w-[:uKJLuM\\8sK\u0012\f5/\u001f8d)\u0016\u001cH/S7qYR1\u0011\u0011MA4\u0003S\"R!UA2\u0003KBQa^\u0005A\u0002aDq!!\u0005\n\u0001\u0004\t\u0019\u0002C\u0004\u0002&%\u0001\r!a\n\t\u000f\u0005}\u0012\u00021\u0001\u0002B\u0005A\"/Z4jgR,\'/S4o_J,G-Q:z]\u000e$Vm\u001d;\u0015\r\u0005=\u0014qOA=)\u0011\t\t(!\u001e\u0015\u0007E\u000b\u0019\bC\u0004\u0002\u0012)\u0001\u001d!a\u0005\t\u000b]T\u0001\u0019\u0001=\t\u000f\u0005\u0015\"\u00021\u0001\u0002(!9\u0011q\b\u0006A\u0002\u0005\u0005#A\u0007*fgVdGo\u00144TG\u0016t\u0017M]5p\u0013:4xnY1uS>t7CA\u00067\u0003!\u0019\b/Z2UKb$\u0018A\u0002\u001fj]&$h\b\u0006\u0004\u0002\u0006\u0006\u001d\u0015\u0011\u0012\t\u00035.Aq!a \u000f\u0001\u0004\t9\u0003C\u0004\u0002@9\u0001\r!!\u0011\u0002\u0013\u0005\u0004\b\u000f\\=J[BdG#B)\u0002\u0010\u0006E\u0005\"B<\u0010\u0001\u0004A\bbBA\t\u001f\u0001\u0007\u00111C\u0001\u0006CB\u0004H.\u001f\u000b\u0005\u0003/\u000bY\nF\u0002R\u00033Cq!!\u0005\u0011\u0001\b\t\u0019\u0002C\u0003x!\u0001\u0007\u0001\u0010F\u0003R\u0003?\u000b9\u000b\u0003\u0004x#\u0001\u0007\u0011\u0011\u0015\t\u0005o\u0005\r60C\u0002\u0002&b\u0012\u0011BR;oGRLwN\u001c\u0019\t\u000f\u0005E\u0011\u00031\u0001\u0002\u0014Q!\u00111VAX)\r\t\u0016Q\u0016\u0005\b\u0003#\u0011\u00029AA\n\u0011\u00199(\u00031\u0001\u0002\"\u0006A1oY3oCJLw\u000e\u0006\u0004\u0002\u0006\u0006U\u0016q\u0017\u0005\b\u0003\u007f\u001a\u0002\u0019AA\u0014\u0011\u001d\tyd\u0005a\u0001\u0003\u0003B3bEA^\u0003\u0003\f\u0019-a2\u0002JB\u0019q\'!0\n\u0007\u0005}\u0006H\u0001\u0006eKB\u0014XmY1uK\u0012\fq!\\3tg\u0006<W-\t\u0002\u0002F\u0006\u0011)\u0005\u00165fAM\u001cWM\\1sS>\u0004\u0003f\u001d;beRLgn\u001a\u0011xSRD\u0007\u0005\\8xKJ\u001c\u0017m]3!OM<\u0013\u0006I7fi\"|G\r\t5bg\u0002\u0012W-\u001a8!I\u0016\u0004(/Z2bi\u0016$\u0007%\u00198eA]LG\u000e\u001c\u0011cK\u0002\u0012X-\\8wK\u0012\u0004\u0013N\u001c\u0011bA\u0019,H/\u001e:fAY,\'o]5p]\u0002zg\rI*dC2\fG+Z:u]\u0001\u0002F.Z1tK\u0002*8/\u001a\u0011TG\u0016t\u0017M]5pA!\u001aH/\u0019:uS:<\u0007e^5uQ\u0002\ng\u000eI;qa\u0016\u00148-Y:fA\u001d\u001av%\u000b\u0011j]N$X-\u00193/AQC\u0017n\u001d\u0011dC:\u0004#-\u001a\u0011sK^\u0014\u0018\u000e\u001e;f]\u0002\nW\u000f^8nCRL7-\u00197ms\u0002:\u0018\u000e\u001e5!CV$xNZ5yu\u0001BG\u000f\u001e9tu=zs-\u001b;ik\nt3m\\70g\u000e\fG.\u0019;fgR|\u0013-\u001e;pM&Dx\u0006\u001e:fK>j\u0017m\u001d;fe>\u001ad&\r\u0018y\u0003\u0015\u0019\u0018N\\2fC\t\tY-A\u00034]Er\u0003\'\u0001\u0005TG\u0016t\u0017M]5p)\u0019\t))!5\u0002T\"9\u0011q\u0010\u000bA\u0002\u0005\u001d\u0002bBA )\u0001\u0007\u0011\u0011\t\u0002\u0019%\u0016\u001cX\u000f\u001c;PM&;gn\u001c:f\u0013:4xnY1uS>t7CA\u000b7)\u0019\tY.!8\u0002`B\u0011!,\u0006\u0005\b\u0003\u007fB\u0002\u0019AA\u0014\u0011\u001d\ty\u0004\u0007a\u0001\u0003\u0003\"R!UAr\u0003KDQa^\rA\u0002aDq!!\u0005\u001a\u0001\u0004\t\u0019\u0002\u0006\u0003\u0002j\u00065HcA)\u0002l\"9\u0011\u0011\u0003\u000eA\u0004\u0005M\u0001\"B<\u001b\u0001\u0004AH#B)\u0002r\u0006M\bBB<\u001c\u0001\u0004\t\t\u000bC\u0004\u0002\u0012m\u0001\r!a\u0005\u0015\t\u0005]\u00181 \u000b\u0004#\u0006e\bbBA\t9\u0001\u000f\u00111\u0003\u0005\u0007or\u0001\r!!)\u0002\r%<gn\u001c:f)\u0019\tYN!\u0001\u0003\u0004!9\u0011qP\u000fA\u0002\u0005\u001d\u0002bBA ;\u0001\u0007\u0011\u0011I\u0001\bM\u0016\fG/\u001e:f)\u0011\u0011IA!\u0007\u0015\t\t-!q\u0002\u000b\u0004#\n5\u0001bBA\t=\u0001\u000f\u00111\u0003\u0005\t\u0005#qB\u00111\u0001\u0003\u0014\u0005\u0019a-\u001e8\u0011\t]\u0012)\"U\u0005\u0004\u0005/A$\u0001\u0003\u001fcs:\fW.\u001a \t\u000f\tma\u00041\u0001\u0002(\u0005YA-Z:de&\u0004H/[8oQ-q\u00121XAa\u0005?\t9-!3\"\u0005\t\u0005\u0012A!\u0011UQ\u0016\u0004c-Z1ukJ,\u0007\u0005K:uCJ$\u0018N\\4!o&$\b\u000e\t7po\u0016\u00148-Y:fA\u001d2w%\u000b\u0011nKRDw\u000e\u001a\u0011iCN\u0004#-Z3oA\u0011,\u0007O]3dCR,G\rI1oI\u0002:\u0018\u000e\u001c7!E\u0016\u0004#/Z7pm\u0016$\u0007%\u001b8!C\u00022W\u000f^;sK\u00022XM]:j_:\u0004sN\u001a\u0011TG\u0006d\u0017\rV3ti:\u0002\u0003\u000b\\3bg\u0016\u0004So]3!\r\u0016\fG/\u001e:fA!\u001aH/\u0019:uS:<\u0007e^5uQ\u0002\ng\u000eI;qa\u0016\u00148-Y:fA\u001d2u%\u000b\u0011j]N$X-\u00193/AQC\u0017n\u001d\u0011dC:\u0004#-\u001a\u0011sK^\u0014\u0018\u000e\u001e;f]\u0002\nW\u000f^8nCRL7-\u00197ms\u0002:\u0018\u000e\u001e5!CV$xNZ5yu\u0001BG\u000f\u001e9tu=zs-\u001b;ik\nt3m\\70g\u000e\fG.\u0019;fgR|\u0013-\u001e;pM&Dx\u0006\u001e:fK>j\u0017m\u001d;fe>\u001ad&\r\u0018y\u0003-1U-\u0019;ve\u0016LU\u000e\u001d7\u0015\t\t\u001d\"Q\u0006\u000b\u0006#\n%\"1\u0006\u0005\t\u0005#yB\u00111\u0001\u0003\u0014!9\u0011\u0011C\u0010A\u0002\u0005M\u0001b\u0002B\u000e?\u0001\u0007\u0011qE\u0001\b\r\u0016\fG/\u001e:f)\u0011\u0011\u0019Da\u000f\u0015\t\tU\"\u0011\b\u000b\u0004#\n]\u0002bBA\tA\u0001\u000f\u00111\u0003\u0005\t\u0005#\u0001C\u00111\u0001\u0003\u0014!9!1\u0004\u0011A\u0002\u0005\u001d\u0012\u0001\u0002;bON,\"A!\u0011\u0011\u0011\u0005%\"1IA\u0014\u0005\u000fJAA!\u0012\u0002<\t\u0019Q*\u00199\u0011\r\u0005%\"\u0011JA\u0014\u0013\u0011\u0011Y%a\u000f\u0003\u0007M+G/A\u0004sk:$Vm\u001d;\u0015\r\tE#q\u000bB.!\ri$1K\u0005\u0004\u0005+\u0002$AB*uCR,8\u000fC\u0004\u0003Z\t\u0002\r!a\n\u0002\u0011Q,7\u000f\u001e(b[\u0016DqA!\u0018#\u0001\u0004\u0011y&\u0001\u0003be\u001e\u001c\bcA\u001f\u0003b%\u0019!1\r\u0019\u0003\t\u0005\u0013xm]\u0001\teVtG+Z:ugR1!\u0011\u000bB5\u0005cBqA!\u0017$\u0001\u0004\u0011Y\u0007E\u00038\u0005[\n9#C\u0002\u0003pa\u0012aa\u00149uS>t\u0007b\u0002B/G\u0001\u0007!qL\u0001\ni\u0016\u001cHOT1nKN,\"Aa\u0012\u0002\u0007I,h\u000e\u0006\u0004\u0003R\tm$Q\u0010\u0005\b\u00053*\u0003\u0019\u0001B6\u0011\u001d\u0011i&\na\u0001\u0005?\nAb]2f]\u0006\u0014\u0018n\\:G_J$2!\u0015BB\u0011\u0019\u0011)I\na\u0001#\u0006!QO\\5uQ-1\u00131XAa\u0005\u0013\u000b9-!3\"\u0005\t-\u0015A!\u0016UQ\u0016\u00043oY3oCJLwn\u001d$pe\u0002B3\u000f^1si&tw\rI<ji\"\u0004Cn\\<fe\u000e\f7/\u001a\u0011(g\u001eJ\u0003%\\3uQ>$\u0007\u0005[1tA\t,WM\u001c\u0011eKB\u0014XmY1uK\u0012\u0004\u0013M\u001c3!o&dG\u000e\t2fAI,Wn\u001c<fI\u0002Jg\u000eI1!MV$XO]3!m\u0016\u00148/[8oA=4\u0007eU2bY\u0006$Vm\u001d;/AAcW-Y:fAU\u001cX\rI*dK:\f\'/[8t\r>\u0014\b\u0005K:uCJ$\u0018N\\4!o&$\b\u000eI1oAU\u0004\b/\u001a:dCN,\u0007eJ*(S\u0001Jgn\u001d;fC\u0012t\u0003\u0005\u00165jg\u0002\u001a\u0017M\u001c\u0011cK\u0002\u0012Xm\u001e:jiR,g\u000eI1vi>l\u0017\r^5dC2d\u0017\u0010I<ji\"\u0004\u0013-\u001e;pM&D(\b\t5uiB\u001c(hL\u0018hSRDWO\u0019\u0018d_6|3oY1mCR,7\u000f^\u0018bkR|g-\u001b=0iJ,WmL7bgR,\'oL\u001a/c9B\u0018\u0001D*dK:\f\'/[8t\r>\u0014HcA)\u0003\u0012\"1!QQ\u0014A\u0002E\u000bqdY8om\u0016\u0014H\u000fU3oI&tw\rV8GSb$XO]3Gk:\u001cG/[8o)\u0011\u00119J!\'\u0011\u000b]J\u0018,a\u0001\t\u0011\tm\u0005\u0006\"a\u0001\u0005;\u000b\u0011A\u001a\t\u0006o\tU!q\u0014\t\u0004{\t\u0005\u0016b\u0001BRa\t\u0001\u0002+\u001a8eS:<7\u000b^1uK6,g\u000e^\u0001\ngRLH.\u001a(b[\u0016,\"!a\n)\u0017%\nY,!1\u0003,\u0006\u001d\u0017\u0011Z\u0011\u0003\u0005[\u000bA\u0010\u00165fAM$\u0018\u0010\\3OC6,\u0007\u0005\\5gK\u000eL8\r\\3![\u0016$\bn\u001c3!Q\u0006\u001c\bEY3f]\u0002\"W\r\u001d:fG\u0006$X\r\u001a\u0011b]\u0012\u0004s/\u001b7mA\t,\u0007E]3n_Z,G\rI5oA\u0005\u0004c-\u001e;ve\u0016\u0004c/\u001a:tS>t\u0007e\u001c4!\'\u000e\fG.\u0019+fgR\u0004s/\u001b;iA9|\u0007E]3qY\u0006\u001cW-\\3oi:\n1\u0002^3ti\u0012\u000bG/\u0019$peR1!1\u0017B]\u0005w\u00032!\u0010B[\u0013\r\u00119\f\r\u0002\t)\u0016\u001cH\u000fR1uC\"9!\u0011\f\u0016A\u0002\u0005\u001d\u0002\"\u0003B_UA\u0005\t\u0019\u0001B`\u00031!\b.Z\"p]\u001aLw-T1q!\ri$\u0011Y\u0005\u0004\u0005\u0007\u0004$!C\"p]\u001aLw-T1q\u0003U!Xm\u001d;ECR\fgi\u001c:%I\u00164\u0017-\u001e7uII*\"A!3+\t\t}&1Z\u0016\u0003\u0005\u001b\u0004BAa4\u0003Z6\u0011!\u0011\u001b\u0006\u0005\u0005\'\u0014).A\u0005v]\u000eDWmY6fI*\u0019!q\u001b\u001d\u0002\u0015\u0005tgn\u001c;bi&|g.\u0003\u0003\u0003\\\nE\'!E;oG\",7m[3e-\u0006\u0014\u0018.\u00198dK\u0006I1/\u001e9fe\u0012\u0012XO\u001c\u000b\u0007\u0005#\u0012\tOa9\t\u000f\teC\u00061\u0001\u0003l!9!Q\f\u0017A\u0002\t}\u0013\u0002\u0002B<\u0005OL1A!;1\u0005\u0015\u0019V/\u001b;fQ\u001d\u0001!Q\u001eBz\u0005k\u00042!\u0010Bx\u0013\r\u0011\t\u0010\r\u0002\b\r&tG-\u001a:t\u0003\u00151\u0018\r\\;fY\t\u001190\t\u0002\u0003z\u00069sN]4/g\u000e\fG.\u0019;fgRtc-\u001b8eKJ\u001chFR3biV\u0014Xm\u00159fG\u001aKg\u000eZ3s\u0001
   #24 = Utf8               java/lang/invoke/MethodHandles$Lookup
   #25 = Class              #24           // java/lang/invoke/MethodHandles$Lookup
   #26 = Utf8               java/lang/invoke/MethodHandles
   #27 = Class              #26           // java/lang/invoke/MethodHandles
   #28 = Utf8               Lookup
   #29 = Utf8               org/scalatest/AsyncSuperEngine$Bundle
   #30 = Class              #29           // org/scalatest/AsyncSuperEngine$Bundle
   #31 = Utf8               org/scalatest/AsyncSuperEngine
   #32 = Class              #31           // org/scalatest/AsyncSuperEngine
   #33 = Utf8               Bundle
   #34 = Utf8               org/scalatest/AsyncSuperEngine$TestLeaf
   #35 = Class              #34           // org/scalatest/AsyncSuperEngine$TestLeaf
   #36 = Utf8               TestLeaf
   #37 = Utf8               org/scalatest/FixtureAsyncTestSuite$OneArgAsyncTest
   #38 = Class              #37           // org/scalatest/FixtureAsyncTestSuite$OneArgAsyncTest
   #39 = Utf8               OneArgAsyncTest
   #40 = Utf8               org/scalatest/featurespec/FixtureAsyncFeatureSpecLike$$anon$1
   #41 = Class              #40           // org/scalatest/featurespec/FixtureAsyncFeatureSpecLike$$anon$1
   #42 = Utf8               org/scalatest/featurespec/FixtureAsyncFeatureSpecLike$ResultOfIgnoreInvocation
   #43 = Class              #42           // org/scalatest/featurespec/FixtureAsyncFeatureSpecLike$ResultOfIgnoreInvocation
   #44 = Utf8               ResultOfIgnoreInvocation
   #45 = Utf8               org/scalatest/featurespec/FixtureAsyncFeatureSpecLike$ResultOfScenarioInvocation
   #46 = Class              #45           // org/scalatest/featurespec/FixtureAsyncFeatureSpecLike$ResultOfScenarioInvocation
   #47 = Utf8               ResultOfScenarioInvocation
   #48 = Utf8               org$scalatest$featurespec$FixtureAsyncFeatureSpecLike$_setter_$org$scalatest$featurespec$FixtureAsyncFeatureSpecLike$$engine_$eq
   #49 = Utf8               (Lorg/scalatest/AsyncFixtureEngine;)V
   #50 = Utf8               (Lorg/scalatest/AsyncFixtureEngine<Ljava/lang/Object;>;)V
   #51 = Utf8               x$1
   #52 = Utf8               org$scalatest$featurespec$FixtureAsyncFeatureSpecLike$_setter_$styleName_$eq
   #53 = Utf8               (Ljava/lang/String;)V
   #54 = Utf8               org$scalatest$featurespec$FixtureAsyncFeatureSpecLike$$super$run
   #55 = Utf8               (Lscala/Option;Lorg/scalatest/Args;)Lorg/scalatest/Status;
   #56 = Utf8               testName
   #57 = Utf8               args
   #58 = Utf8               org$scalatest$featurespec$FixtureAsyncFeatureSpecLike$$engine
   #59 = Utf8               ()Lorg/scalatest/AsyncFixtureEngine;
   #60 = Utf8               ()Lorg/scalatest/AsyncFixtureEngine<Ljava/lang/Object;>;
   #61 = Utf8               info$
   #62 = Utf8               (Lorg/scalatest/featurespec/FixtureAsyncFeatureSpecLike;)Lorg/scalatest/Informer;
   #63 = Utf8               $this
   #64 = Utf8               info
   #65 = Utf8               ()Lorg/scalatest/Informer;
   #66 = NameAndType        #64:#65       // info:()Lorg/scalatest/Informer;
   #67 = InterfaceMethodref #2.#66        // org/scalatest/featurespec/FixtureAsyncFeatureSpecLike.info:()Lorg/scalatest/Informer;
   #68 = Utf8               Lorg/scalatest/featurespec/FixtureAsyncFeatureSpecLike;
   #69 = NameAndType        #58:#59       // org$scalatest$featurespec$FixtureAsyncFeatureSpecLike$$engine:()Lorg/scalatest/AsyncFixtureEngine;
   #70 = InterfaceMethodref #2.#69        // org/scalatest/featurespec/FixtureAsyncFeatureSpecLike.org$scalatest$featurespec$FixtureAsyncFeatureSpecLike$$engine:()Lorg/scalatest/AsyncFixtureEngine;
   #71 = Utf8               org/scalatest/AsyncFixtureEngine
   #72 = Class              #71           // org/scalatest/AsyncFixtureEngine
   #73 = Utf8               atomicInformer
   #74 = Utf8               ()Ljava/util/concurrent/atomic/AtomicReference;
   #75 = NameAndType        #73:#74       // atomicInformer:()Ljava/util/concurrent/atomic/AtomicReference;
   #76 = Methodref          #72.#75       // org/scalatest/AsyncFixtureEngine.atomicInformer:()Ljava/util/concurrent/atomic/AtomicReference;
   #77 = Utf8               java/util/concurrent/atomic/AtomicReference
   #78 = Class              #77           // java/util/concurrent/atomic/AtomicReference
   #79 = Utf8               get
   #80 = Utf8               ()Ljava/lang/Object;
   #81 = NameAndType        #79:#80       // get:()Ljava/lang/Object;
   #82 = Methodref          #78.#81       // java/util/concurrent/atomic/AtomicReference.get:()Ljava/lang/Object;
   #83 = Utf8               org/scalatest/Informer
   #84 = Class              #83           // org/scalatest/Informer
   #85 = Utf8               this
   #86 = Utf8               note$
   #87 = Utf8               (Lorg/scalatest/featurespec/FixtureAsyncFeatureSpecLike;)Lorg/scalatest/Notifier;
   #88 = Utf8               note
   #89 = Utf8               ()Lorg/scalatest/Notifier;
   #90 = NameAndType        #88:#89       // note:()Lorg/scalatest/Notifier;
   #91 = InterfaceMethodref #2.#90        // org/scalatest/featurespec/FixtureAsyncFeatureSpecLike.note:()Lorg/scalatest/Notifier;
   #92 = Utf8               atomicNotifier
   #93 = NameAndType        #92:#74       // atomicNotifier:()Ljava/util/concurrent/atomic/AtomicReference;
   #94 = Methodref          #72.#93       // org/scalatest/AsyncFixtureEngine.atomicNotifier:()Ljava/util/concurrent/atomic/AtomicReference;
   #95 = Utf8               org/scalatest/Notifier
   #96 = Class              #95           // org/scalatest/Notifier
   #97 = Utf8               alert$
   #98 = Utf8               (Lorg/scalatest/featurespec/FixtureAsyncFeatureSpecLike;)Lorg/scalatest/Alerter;
   #99 = Utf8               alert
  #100 = Utf8               ()Lorg/scalatest/Alerter;
  #101 = NameAndType        #99:#100      // alert:()Lorg/scalatest/Alerter;
  #102 = InterfaceMethodref #2.#101       // org/scalatest/featurespec/FixtureAsyncFeatureSpecLike.alert:()Lorg/scalatest/Alerter;
  #103 = Utf8               atomicAlerter
  #104 = NameAndType        #103:#74      // atomicAlerter:()Ljava/util/concurrent/atomic/AtomicReference;
  #105 = Methodref          #72.#104      // org/scalatest/AsyncFixtureEngine.atomicAlerter:()Ljava/util/concurrent/atomic/AtomicReference;
  #106 = Utf8               org/scalatest/Alerter
  #107 = Class              #106          // org/scalatest/Alerter
  #108 = Utf8               markup$
  #109 = Utf8               (Lorg/scalatest/featurespec/FixtureAsyncFeatureSpecLike;)Lorg/scalatest/Documenter;
  #110 = Utf8               markup
  #111 = Utf8               ()Lorg/scalatest/Documenter;
  #112 = NameAndType        #110:#111     // markup:()Lorg/scalatest/Documenter;
  #113 = InterfaceMethodref #2.#112       // org/scalatest/featurespec/FixtureAsyncFeatureSpecLike.markup:()Lorg/scalatest/Documenter;
  #114 = Utf8               atomicDocumenter
  #115 = NameAndType        #114:#74      // atomicDocumenter:()Ljava/util/concurrent/atomic/AtomicReference;
  #116 = Methodref          #72.#115      // org/scalatest/AsyncFixtureEngine.atomicDocumenter:()Ljava/util/concurrent/atomic/AtomicReference;
  #117 = Utf8               org/scalatest/Documenter
  #118 = Class              #117          // org/scalatest/Documenter
  #119 = Utf8               registerAsyncTestImpl
  #120 = Utf8               (Ljava/lang/String;Lscala/collection/immutable/Seq;Lscala/Function1;Lorg/scalactic/source/Position;)V
  #121 = Utf8               (Ljava/lang/String;Lscala/collection/immutable/Seq<Lorg/scalatest/Tag;>;Lscala/Function1<Ljava/lang/Object;Lscala/concurrent/Future<Lorg/scalatest/compatible/Assertion;>;>;Lorg/scalactic/source/Position;)V
  #122 = Utf8               testText
  #123 = Utf8               testTags
  #124 = Utf8               testFun
  #125 = Utf8               pos
  #126 = Utf8               org/scalatest/Resources$
  #127 = Class              #126          // org/scalatest/Resources$
  #128 = Utf8               MODULE$
  #129 = Utf8               Lorg/scalatest/Resources$;
  #130 = NameAndType        #128:#129     // MODULE$:Lorg/scalatest/Resources$;
  #131 = Fieldref           #127.#130     // org/scalatest/Resources$.MODULE$:Lorg/scalatest/Resources$;
  #132 = Utf8               java/lang/String
  #133 = Class              #132          // java/lang/String
  #134 = Utf8               trim
  #135 = Utf8               ()Ljava/lang/String;
  #136 = NameAndType        #134:#135     // trim:()Ljava/lang/String;
  #137 = Methodref          #133.#136     // java/lang/String.trim:()Ljava/lang/String;
  #138 = Utf8               scenario
  #139 = Utf8               (Ljava/lang/Object;)Ljava/lang/String;
  #140 = NameAndType        #138:#139     // scenario:(Ljava/lang/Object;)Ljava/lang/String;
  #141 = Methodref          #127.#140     // org/scalatest/Resources$.scenario:(Ljava/lang/Object;)Ljava/lang/String;
  #142 = Utf8               transformToOutcome
  #143 = Utf8               (Lscala/Function1;)Lscala/Function1;
  #144 = NameAndType        #142:#143     // transformToOutcome:(Lscala/Function1;)Lscala/Function1;
  #145 = InterfaceMethodref #2.#144       // org/scalatest/featurespec/FixtureAsyncFeatureSpecLike.transformToOutcome:(Lscala/Function1;)Lscala/Function1;
  #146 = MethodType         #80           //  ()Ljava/lang/Object;
  #147 = Utf8               $anonfun$registerAsyncTestImpl$1
  #148 = NameAndType        #147:#135     // $anonfun$registerAsyncTestImpl$1:()Ljava/lang/String;
  #149 = InterfaceMethodref #2.#148       // org/scalatest/featurespec/FixtureAsyncFeatureSpecLike.$anonfun$registerAsyncTestImpl$1:()Ljava/lang/String;
  #150 = MethodHandle       6:#149        // REF_invokeStatic org/scalatest/featurespec/FixtureAsyncFeatureSpecLike.$anonfun$registerAsyncTestImpl$1:()Ljava/lang/String;
  #151 = MethodType         #135          //  ()Ljava/lang/String;
  #152 = Integer            5
  #153 = Integer            1
  #154 = Utf8               java/lang/invoke/LambdaMetafactory
  #155 = Class              #154          // java/lang/invoke/LambdaMetafactory
  #156 = Utf8               altMetafactory
  #157 = Utf8               (Ljava/lang/invoke/MethodHandles$Lookup;Ljava/lang/String;Ljava/lang/invoke/MethodType;[Ljava/lang/Object;)Ljava/lang/invoke/CallSite;
  #158 = NameAndType        #156:#157     // altMetafactory:(Ljava/lang/invoke/MethodHandles$Lookup;Ljava/lang/String;Ljava/lang/invoke/MethodType;[Ljava/lang/Object;)Ljava/lang/invoke/CallSite;
  #159 = Methodref          #155.#158     // java/lang/invoke/LambdaMetafactory.altMetafactory:(Ljava/lang/invoke/MethodHandles$Lookup;Ljava/lang/String;Ljava/lang/invoke/MethodType;[Ljava/lang/Object;)Ljava/lang/invoke/CallSite;
  #160 = MethodHandle       6:#159        // REF_invokeStatic java/lang/invoke/LambdaMetafactory.altMetafactory:(Ljava/lang/invoke/MethodHandles$Lookup;Ljava/lang/String;Ljava/lang/invoke/MethodType;[Ljava/lang/Object;)Ljava/lang/invoke/CallSite;
  #161 = Utf8               apply
  #162 = Utf8               ()Lscala/Function0;
  #163 = NameAndType        #161:#162     // apply:()Lscala/Function0;
  #164 = InvokeDynamic      #0:#163       // #0:apply:()Lscala/Function0;
  #165 = Utf8               scala/None$
  #166 = Class              #165          // scala/None$
  #167 = Utf8               Lscala/None$;
  #168 = NameAndType        #128:#167     // MODULE$:Lscala/None$;
  #169 = Fieldref           #166.#168     // scala/None$.MODULE$:Lscala/None$;
  #170 = Utf8               registerAsyncTest
  #171 = Utf8               (Ljava/lang/String;Ljava/lang/Object;Lscala/Function0;Lscala/Option;Lscala/Option;Lorg/scalactic/source/Position;Lscala/collection/immutable/Seq;)Ljava/lang/String;
  #172 = NameAndType        #170:#171     // registerAsyncTest:(Ljava/lang/String;Ljava/lang/Object;Lscala/Function0;Lscala/Option;Lscala/Option;Lorg/scalactic/source/Position;Lscala/collection/immutable/Seq;)Ljava/lang/String;
  #173 = Methodref          #72.#172      // org/scalatest/AsyncFixtureEngine.registerAsyncTest:(Ljava/lang/String;Ljava/lang/Object;Lscala/Function0;Lscala/Option;Lscala/Option;Lorg/scalactic/source/Position;Lscala/collection/immutable/Seq;)Ljava/lang/String;
  #174 = Utf8               Ljava/lang/String;
  #175 = Utf8               Lscala/collection/immutable/Seq;
  #176 = Utf8               Lscala/Function1;
  #177 = Utf8               Lorg/scalactic/source/Position;
  #178 = Utf8               registerAsyncTest$
  #179 = Utf8               (Lorg/scalatest/featurespec/FixtureAsyncFeatureSpecLike;Ljava/lang/String;Lscala/collection/immutable/Seq;Lscala/Function1;Lorg/scalactic/source/Position;)V
  #180 = NameAndType        #170:#120     // registerAsyncTest:(Ljava/lang/String;Lscala/collection/immutable/Seq;Lscala/Function1;Lorg/scalactic/source/Position;)V
  #181 = InterfaceMethodref #2.#180       // org/scalatest/featurespec/FixtureAsyncFeatureSpecLike.registerAsyncTest:(Ljava/lang/String;Lscala/collection/immutable/Seq;Lscala/Function1;Lorg/scalactic/source/Position;)V
  #182 = NameAndType        #119:#120     // registerAsyncTestImpl:(Ljava/lang/String;Lscala/collection/immutable/Seq;Lscala/Function1;Lorg/scalactic/source/Position;)V
  #183 = InterfaceMethodref #2.#182       // org/scalatest/featurespec/FixtureAsyncFeatureSpecLike.registerAsyncTestImpl:(Ljava/lang/String;Lscala/collection/immutable/Seq;Lscala/Function1;Lorg/scalactic/source/Position;)V
  #184 = Utf8               registerIgnoredAsyncTestImpl
  #185 = Utf8               $anonfun$registerIgnoredAsyncTestImpl$1
  #186 = NameAndType        #185:#135     // $anonfun$registerIgnoredAsyncTestImpl$1:()Ljava/lang/String;
  #187 = InterfaceMethodref #2.#186       // org/scalatest/featurespec/FixtureAsyncFeatureSpecLike.$anonfun$registerIgnoredAsyncTestImpl$1:()Ljava/lang/String;
  #188 = MethodHandle       6:#187        // REF_invokeStatic org/scalatest/featurespec/FixtureAsyncFeatureSpecLike.$anonfun$registerIgnoredAsyncTestImpl$1:()Ljava/lang/String;
  #189 = InvokeDynamic      #1:#163       // #1:apply:()Lscala/Function0;
  #190 = Utf8               registerIgnoredAsyncTest
  #191 = Utf8               (Ljava/lang/String;Ljava/lang/Object;Lscala/Function0;Lscala/Option;Lorg/scalactic/source/Position;Lscala/collection/immutable/Seq;)V
  #192 = NameAndType        #190:#191     // registerIgnoredAsyncTest:(Ljava/lang/String;Ljava/lang/Object;Lscala/Function0;Lscala/Option;Lorg/scalactic/source/Position;Lscala/collection/immutable/Seq;)V
  #193 = Methodref          #72.#192      // org/scalatest/AsyncFixtureEngine.registerIgnoredAsyncTest:(Ljava/lang/String;Ljava/lang/Object;Lscala/Function0;Lscala/Option;Lorg/scalactic/source/Position;Lscala/collection/immutable/Seq;)V
  #194 = Utf8               registerIgnoredAsyncTest$
  #195 = NameAndType        #190:#120     // registerIgnoredAsyncTest:(Ljava/lang/String;Lscala/collection/immutable/Seq;Lscala/Function1;Lorg/scalactic/source/Position;)V
  #196 = InterfaceMethodref #2.#195       // org/scalatest/featurespec/FixtureAsyncFeatureSpecLike.registerIgnoredAsyncTest:(Ljava/lang/String;Lscala/collection/immutable/Seq;Lscala/Function1;Lorg/scalactic/source/Position;)V
  #197 = NameAndType        #184:#120     // registerIgnoredAsyncTestImpl:(Ljava/lang/String;Lscala/collection/immutable/Seq;Lscala/Function1;Lorg/scalactic/source/Position;)V
  #198 = InterfaceMethodref #2.#197       // org/scalatest/featurespec/FixtureAsyncFeatureSpecLike.registerIgnoredAsyncTestImpl:(Ljava/lang/String;Lscala/collection/immutable/Seq;Lscala/Function1;Lorg/scalactic/source/Position;)V
  #199 = Utf8               scenario$
  #200 = Utf8               (Lorg/scalatest/featurespec/FixtureAsyncFeatureSpecLike;Ljava/lang/String;Lscala/collection/immutable/Seq;)Lorg/scalatest/featurespec/FixtureAsyncFeatureSpecLike$ResultOfScenarioInvocation;
  #201 = Utf8               specText
  #202 = Utf8               (Ljava/lang/String;Lscala/collection/immutable/Seq;)Lorg/scalatest/featurespec/FixtureAsyncFeatureSpecLike$ResultOfScenarioInvocation;
  #203 = NameAndType        #138:#202     // scenario:(Ljava/lang/String;Lscala/collection/immutable/Seq;)Lorg/scalatest/featurespec/FixtureAsyncFeatureSpecLike$ResultOfScenarioInvocation;
  #204 = InterfaceMethodref #2.#203       // org/scalatest/featurespec/FixtureAsyncFeatureSpecLike.scenario:(Ljava/lang/String;Lscala/collection/immutable/Seq;)Lorg/scalatest/featurespec/FixtureAsyncFeatureSpecLike$ResultOfScenarioInvocation;
  #205 = Utf8               (Ljava/lang/String;Lscala/collection/immutable/Seq<Lorg/scalatest/Tag;>;)Lorg/scalatest/featurespec/FixtureAsyncFeatureSpecLike$ResultOfScenarioInvocation;
  #206 = Utf8               Scenario
  #207 = NameAndType        #206:#202     // Scenario:(Ljava/lang/String;Lscala/collection/immutable/Seq;)Lorg/scalatest/featurespec/FixtureAsyncFeatureSpecLike$ResultOfScenarioInvocation;
  #208 = InterfaceMethodref #2.#207       // org/scalatest/featurespec/FixtureAsyncFeatureSpecLike.Scenario:(Ljava/lang/String;Lscala/collection/immutable/Seq;)Lorg/scalatest/featurespec/FixtureAsyncFeatureSpecLike$ResultOfScenarioInvocation;
  #209 = Utf8               Scenario$
  #210 = Utf8               <init>
  #211 = Utf8               (Lorg/scalatest/featurespec/FixtureAsyncFeatureSpecLike;Ljava/lang/String;Lscala/collection/immutable/Seq;)V
  #212 = NameAndType        #210:#211     // "<init>":(Lorg/scalatest/featurespec/FixtureAsyncFeatureSpecLike;Ljava/lang/String;Lscala/collection/immutable/Seq;)V
  #213 = Methodref          #46.#212      // org/scalatest/featurespec/FixtureAsyncFeatureSpecLike$ResultOfScenarioInvocation."<init>":(Lorg/scalatest/featurespec/FixtureAsyncFeatureSpecLike;Ljava/lang/String;Lscala/collection/immutable/Seq;)V
  #214 = Utf8               ignore$
  #215 = Utf8               (Lorg/scalatest/featurespec/FixtureAsyncFeatureSpecLike;Ljava/lang/String;Lscala/collection/immutable/Seq;)Lorg/scalatest/featurespec/FixtureAsyncFeatureSpecLike$ResultOfIgnoreInvocation;
  #216 = Utf8               ignore
  #217 = Utf8               (Ljava/lang/String;Lscala/collection/immutable/Seq;)Lorg/scalatest/featurespec/FixtureAsyncFeatureSpecLike$ResultOfIgnoreInvocation;
  #218 = NameAndType        #216:#217     // ignore:(Ljava/lang/String;Lscala/collection/immutable/Seq;)Lorg/scalatest/featurespec/FixtureAsyncFeatureSpecLike$ResultOfIgnoreInvocation;
  #219 = InterfaceMethodref #2.#218       // org/scalatest/featurespec/FixtureAsyncFeatureSpecLike.ignore:(Ljava/lang/String;Lscala/collection/immutable/Seq;)Lorg/scalatest/featurespec/FixtureAsyncFeatureSpecLike$ResultOfIgnoreInvocation;
  #220 = Utf8               (Ljava/lang/String;Lscala/collection/immutable/Seq<Lorg/scalatest/Tag;>;)Lorg/scalatest/featurespec/FixtureAsyncFeatureSpecLike$ResultOfIgnoreInvocation;
  #221 = Methodref          #43.#212      // org/scalatest/featurespec/FixtureAsyncFeatureSpecLike$ResultOfIgnoreInvocation."<init>":(Lorg/scalatest/featurespec/FixtureAsyncFeatureSpecLike;Ljava/lang/String;Lscala/collection/immutable/Seq;)V
  #222 = Utf8               feature$
  #223 = Utf8               (Lorg/scalatest/featurespec/FixtureAsyncFeatureSpecLike;Ljava/lang/String;Lscala/Function0;Lorg/scalactic/source/Position;)V
  #224 = Utf8               description
  #225 = Utf8               fun
  #226 = Utf8               feature
  #227 = Utf8               (Ljava/lang/String;Lscala/Function0;Lorg/scalactic/source/Position;)V
  #228 = NameAndType        #226:#227     // feature:(Ljava/lang/String;Lscala/Function0;Lorg/scalactic/source/Position;)V
  #229 = InterfaceMethodref #2.#228       // org/scalatest/featurespec/FixtureAsyncFeatureSpecLike.feature:(Ljava/lang/String;Lscala/Function0;Lorg/scalactic/source/Position;)V
  #230 = Utf8               Lscala/Function0;
  #231 = Utf8               (Ljava/lang/String;Lscala/Function0<Lscala/runtime/BoxedUnit;>;Lorg/scalactic/source/Position;)V
  #232 = Utf8               FeatureImpl
  #233 = NameAndType        #232:#227     // FeatureImpl:(Ljava/lang/String;Lscala/Function0;Lorg/scalactic/source/Position;)V
  #234 = InterfaceMethodref #2.#233       // org/scalatest/featurespec/FixtureAsyncFeatureSpecLike.FeatureImpl:(Ljava/lang/String;Lscala/Function0;Lorg/scalactic/source/Position;)V
  #235 = Utf8               java/lang/Throwable
  #236 = Class              #235          // java/lang/Throwable
  #237 = Utf8               currentBranchIsTrunk
  #238 = Utf8               ()Z
  #239 = NameAndType        #237:#238     // currentBranchIsTrunk:()Z
  #240 = Methodref          #72.#239      // org/scalatest/AsyncFixtureEngine.currentBranchIsTrunk:()Z
  #241 = Utf8               org/scalatest/exceptions/NotAllowedException
  #242 = Class              #241          // org/scalatest/exceptions/NotAllowedException
  #243 = Utf8               cantNestFeatureClauses
  #244 = NameAndType        #243:#135     // cantNestFeatureClauses:()Ljava/lang/String;
  #245 = Methodref          #127.#244     // org/scalatest/Resources$.cantNestFeatureClauses:()Ljava/lang/String;
  #246 = Utf8               (Ljava/lang/String;Lscala/Option;Lorg/scalactic/source/Position;)V
  #247 = NameAndType        #210:#246     // "<init>":(Ljava/lang/String;Lscala/Option;Lorg/scalactic/source/Position;)V
  #248 = Methodref          #242.#247     // org/scalatest/exceptions/NotAllowedException."<init>":(Ljava/lang/String;Lscala/Option;Lorg/scalactic/source/Position;)V
  #249 = NameAndType        #226:#139     // feature:(Ljava/lang/Object;)Ljava/lang/String;
  #250 = Methodref          #127.#249     // org/scalatest/Resources$.feature:(Ljava/lang/Object;)Ljava/lang/String;
  #251 = Utf8               $anonfun$FeatureImpl$1
  #252 = NameAndType        #251:#135     // $anonfun$FeatureImpl$1:()Ljava/lang/String;
  #253 = InterfaceMethodref #2.#252       // org/scalatest/featurespec/FixtureAsyncFeatureSpecLike.$anonfun$FeatureImpl$1:()Ljava/lang/String;
  #254 = MethodHandle       6:#253        // REF_invokeStatic org/scalatest/featurespec/FixtureAsyncFeatureSpecLike.$anonfun$FeatureImpl$1:()Ljava/lang/String;
  #255 = InvokeDynamic      #2:#163       // #2:apply:()Lscala/Function0;
  #256 = Utf8               registerNestedBranch
  #257 = Utf8               (Ljava/lang/String;Lscala/Option;Lscala/Function0;Lscala/Function0;Lscala/Option;Lorg/scalactic/source/Position;)V
  #258 = NameAndType        #256:#257     // registerNestedBranch:(Ljava/lang/String;Lscala/Option;Lscala/Function0;Lscala/Function0;Lscala/Option;Lorg/scalactic/source/Position;)V
  #259 = Methodref          #72.#258      // org/scalatest/AsyncFixtureEngine.registerNestedBranch:(Ljava/lang/String;Lscala/Option;Lscala/Function0;Lscala/Function0;Lscala/Option;Lorg/scalactic/source/Position;)V
  #260 = Utf8               org/scalatest/exceptions/TestFailedException
  #261 = Class              #260          // org/scalatest/exceptions/TestFailedException
  #262 = Utf8               org/scalatest/FailureMessages$
  #263 = Class              #262          // org/scalatest/FailureMessages$
  #264 = Utf8               Lorg/scalatest/FailureMessages$;
  #265 = NameAndType        #128:#264     // MODULE$:Lorg/scalatest/FailureMessages$;
  #266 = Fieldref           #263.#265     // org/scalatest/FailureMessages$.MODULE$:Lorg/scalatest/FailureMessages$;
  #267 = Utf8               assertionShouldBePutInsideScenarioClauseNotFeatureClause
  #268 = NameAndType        #267:#135     // assertionShouldBePutInsideScenarioClauseNotFeatureClause:()Ljava/lang/String;
  #269 = Methodref          #263.#268     // org/scalatest/FailureMessages$.assertionShouldBePutInsideScenarioClauseNotFeatureClause:()Ljava/lang/String;
  #270 = Utf8               scala/Some
  #271 = Class              #270          // scala/Some
  #272 = Utf8               (Ljava/lang/Object;)V
  #273 = NameAndType        #210:#272     // "<init>":(Ljava/lang/Object;)V
  #274 = Methodref          #271.#273     // scala/Some."<init>":(Ljava/lang/Object;)V
  #275 = Utf8               position
  #276 = Utf8               ()Lscala/Option;
  #277 = NameAndType        #275:#276     // position:()Lscala/Option;
  #278 = Methodref          #261.#277     // org/scalatest/exceptions/TestFailedException.position:()Lscala/Option;
  #279 = Utf8               $anonfun$FeatureImpl$2
  #280 = Utf8               (Lorg/scalactic/source/Position;)Lorg/scalactic/source/Position;
  #281 = NameAndType        #279:#280     // $anonfun$FeatureImpl$2:(Lorg/scalactic/source/Position;)Lorg/scalactic/source/Position;
  #282 = InterfaceMethodref #2.#281       // org/scalatest/featurespec/FixtureAsyncFeatureSpecLike.$anonfun$FeatureImpl$2:(Lorg/scalactic/source/Position;)Lorg/scalactic/source/Position;
  #283 = MethodHandle       6:#282        // REF_invokeStatic org/scalatest/featurespec/FixtureAsyncFeatureSpecLike.$anonfun$FeatureImpl$2:(Lorg/scalactic/source/Position;)Lorg/scalactic/source/Position;
  #284 = Utf8               ()Lorg/scalactic/source/Position;
  #285 = MethodType         #284          //  ()Lorg/scalactic/source/Position;
  #286 = Utf8               (Lorg/scalactic/source/Position;)Lscala/Function0;
  #287 = NameAndType        #161:#286     // apply:(Lorg/scalactic/source/Position;)Lscala/Function0;
  #288 = InvokeDynamic      #3:#287       // #3:apply:(Lorg/scalactic/source/Position;)Lscala/Function0;
  #289 = Utf8               scala/Option
  #290 = Class              #289          // scala/Option
  #291 = Utf8               getOrElse
  #292 = Utf8               (Lscala/Function0;)Ljava/lang/Object;
  #293 = NameAndType        #291:#292     // getOrElse:(Lscala/Function0;)Ljava/lang/Object;
  #294 = Methodref          #290.#293     // scala/Option.getOrElse:(Lscala/Function0;)Ljava/lang/Object;
  #295 = Utf8               org/scalactic/source/Position
  #296 = Class              #295          // org/scalactic/source/Position
  #297 = Utf8               org/scalatest/exceptions/TestCanceledException
  #298 = Class              #297          // org/scalatest/exceptions/TestCanceledException
  #299 = Methodref          #298.#277     // org/scalatest/exceptions/TestCanceledException.position:()Lscala/Option;
  #300 = Utf8               $anonfun$FeatureImpl$3
  #301 = NameAndType        #300:#280     // $anonfun$FeatureImpl$3:(Lorg/scalactic/source/Position;)Lorg/scalactic/source/Position;
  #302 = InterfaceMethodref #2.#301       // org/scalatest/featurespec/FixtureAsyncFeatureSpecLike.$anonfun$FeatureImpl$3:(Lorg/scalactic/source/Position;)Lorg/scalactic/source/Position;
  #303 = MethodHandle       6:#302        // REF_invokeStatic org/scalatest/featurespec/FixtureAsyncFeatureSpecLike.$anonfun$FeatureImpl$3:(Lorg/scalactic/source/Position;)Lorg/scalactic/source/Position;
  #304 = InvokeDynamic      #4:#287       // #4:apply:(Lorg/scalactic/source/Position;)Lscala/Function0;
  #305 = Utf8               org/scalatest/Suite$
  #306 = Class              #305          // org/scalatest/Suite$
  #307 = Utf8               Lorg/scalatest/Suite$;
  #308 = NameAndType        #128:#307     // MODULE$:Lorg/scalatest/Suite$;
  #309 = Fieldref           #306.#308     // org/scalatest/Suite$.MODULE$:Lorg/scalatest/Suite$;
  #310 = Utf8               anExceptionThatShouldCauseAnAbort
  #311 = Utf8               (Ljava/lang/Throwable;)Z
  #312 = NameAndType        #310:#311     // anExceptionThatShouldCauseAnAbort:(Ljava/lang/Throwable;)Z
  #313 = Methodref          #306.#312     // org/scalatest/Suite$.anExceptionThatShouldCauseAnAbort:(Ljava/lang/Throwable;)Z
  #314 = Utf8               org/scalactic/Prettifier$
  #315 = Class              #314          // org/scalactic/Prettifier$
  #316 = Utf8               Lorg/scalactic/Prettifier$;
  #317 = NameAndType        #128:#316     // MODULE$:Lorg/scalactic/Prettifier$;
  #318 = Fieldref           #315.#317     // org/scalactic/Prettifier$.MODULE$:Lorg/scalactic/Prettifier$;
  #319 = Utf8               default
  #320 = Utf8               ()Lorg/scalactic/Prettifier;
  #321 = NameAndType        #319:#320     // default:()Lorg/scalactic/Prettifier;
  #322 = Methodref          #315.#321     // org/scalactic/Prettifier$.default:()Lorg/scalactic/Prettifier;
  #323 = Utf8               org/scalatest/UnquotedString$
  #324 = Class              #323          // org/scalatest/UnquotedString$
  #325 = Utf8               Lorg/scalatest/UnquotedString$;
  #326 = NameAndType        #128:#325     // MODULE$:Lorg/scalatest/UnquotedString$;
  #327 = Fieldref           #324.#326     // org/scalatest/UnquotedString$.MODULE$:Lorg/scalatest/UnquotedString$;
  #328 = Utf8               getClass
  #329 = Utf8               ()Ljava/lang/Class;
  #330 = NameAndType        #328:#329     // getClass:()Ljava/lang/Class;
  #331 = Methodref          #236.#330     // java/lang/Throwable.getClass:()Ljava/lang/Class;
  #332 = Utf8               java/lang/Class
  #333 = Class              #332          // java/lang/Class
  #334 = Utf8               getName
  #335 = NameAndType        #334:#135     // getName:()Ljava/lang/String;
  #336 = Methodref          #333.#335     // java/lang/Class.getName:()Ljava/lang/String;
  #337 = Utf8               (Ljava/lang/String;)Lorg/scalatest/UnquotedString;
  #338 = NameAndType        #161:#337     // apply:(Ljava/lang/String;)Lorg/scalatest/UnquotedString;
  #339 = Methodref          #324.#338     // org/scalatest/UnquotedString$.apply:(Ljava/lang/String;)Lorg/scalatest/UnquotedString;
  #340 = Utf8               getMessage
  #341 = NameAndType        #340:#135     // getMessage:()Ljava/lang/String;
  #342 = Methodref          #236.#341     // java/lang/Throwable.getMessage:()Ljava/lang/String;
  #343 = Utf8               exceptionWasThrownInFeatureClause
  #344 = Utf8               (Lorg/scalactic/Prettifier;Ljava/lang/Object;Ljava/lang/Object;Ljava/lang/Object;)Ljava/lang/String;
  #345 = NameAndType        #343:#344     // exceptionWasThrownInFeatureClause:(Lorg/scalactic/Prettifier;Ljava/lang/Object;Ljava/lang/Object;Ljava/lang/Object;)Ljava/lang/String;
  #346 = Methodref          #263.#345     // org/scalatest/FailureMessages$.exceptionWasThrownInFeatureClause:(Lorg/scalactic/Prettifier;Ljava/lang/Object;Ljava/lang/Object;Ljava/lang/Object;)Ljava/lang/String;
  #347 = Utf8               scala/Function0
  #348 = Class              #347          // scala/Function0
  #349 = Utf8               Feature$
  #350 = Utf8               Feature
  #351 = NameAndType        #350:#227     // Feature:(Ljava/lang/String;Lscala/Function0;Lorg/scalactic/source/Position;)V
  #352 = InterfaceMethodref #2.#351       // org/scalatest/featurespec/FixtureAsyncFeatureSpecLike.Feature:(Ljava/lang/String;Lscala/Function0;Lorg/scalactic/source/Position;)V
  #353 = Utf8               tags$
  #354 = Utf8               (Lorg/scalatest/featurespec/FixtureAsyncFeatureSpecLike;)Lscala/collection/immutable/Map;
  #355 = Utf8               tags
  #356 = Utf8               ()Lscala/collection/immutable/Map;
  #357 = NameAndType        #355:#356     // tags:()Lscala/collection/immutable/Map;
  #358 = InterfaceMethodref #2.#357       // org/scalatest/featurespec/FixtureAsyncFeatureSpecLike.tags:()Lscala/collection/immutable/Map;
  #359 = Utf8               ()Lscala/collection/immutable/Map<Ljava/lang/String;Lscala/collection/immutable/Set<Ljava/lang/String;>;>;
  #360 = Utf8               atomic
  #361 = NameAndType        #360:#74      // atomic:()Ljava/util/concurrent/atomic/AtomicReference;
  #362 = Methodref          #72.#361      // org/scalatest/AsyncFixtureEngine.atomic:()Ljava/util/concurrent/atomic/AtomicReference;
  #363 = Utf8               tagsMap
  #364 = NameAndType        #363:#356     // tagsMap:()Lscala/collection/immutable/Map;
  #365 = Methodref          #30.#364      // org/scalatest/AsyncSuperEngine$Bundle.tagsMap:()Lscala/collection/immutable/Map;
  #366 = Utf8               autoTagClassAnnotations
  #367 = Utf8               (Lscala/collection/immutable/Map;Lorg/scalatest/Suite;)Lscala/collection/immutable/Map;
  #368 = NameAndType        #366:#367     // autoTagClassAnnotations:(Lscala/collection/immutable/Map;Lorg/scalatest/Suite;)Lscala/collection/immutable/Map;
  #369 = Methodref          #306.#368     // org/scalatest/Suite$.autoTagClassAnnotations:(Lscala/collection/immutable/Map;Lorg/scalatest/Suite;)Lscala/collection/immutable/Map;
  #370 = Utf8               runTest$
  #371 = Utf8               (Lorg/scalatest/featurespec/FixtureAsyncFeatureSpecLike;Ljava/lang/String;Lorg/scalatest/Args;)Lorg/scalatest/Status;
  #372 = Utf8               runTest
  #373 = Utf8               (Ljava/lang/String;Lorg/scalatest/Args;)Lorg/scalatest/Status;
  #374 = NameAndType        #372:#373     // runTest:(Ljava/lang/String;Lorg/scalatest/Args;)Lorg/scalatest/Status;
  #375 = InterfaceMethodref #2.#374       // org/scalatest/featurespec/FixtureAsyncFeatureSpecLike.runTest:(Ljava/lang/String;Lorg/scalatest/Args;)Lorg/scalatest/Status;
  #376 = Utf8               Lorg/scalatest/Args;
  #377 = Utf8               parallelAsyncTestExecution
  #378 = NameAndType        #377:#238     // parallelAsyncTestExecution:()Z
  #379 = InterfaceMethodref #2.#378       // org/scalatest/featurespec/FixtureAsyncFeatureSpecLike.parallelAsyncTestExecution:()Z
  #380 = Utf8               (Ljava/lang/Object;Ljava/lang/Object;)Ljava/lang/Object;
  #381 = MethodType         #380          //  (Ljava/lang/Object;Ljava/lang/Object;)Ljava/lang/Object;
  #382 = Utf8               $anonfun$runTest$1
  #383 = Utf8               (Lorg/scalatest/featurespec/FixtureAsyncFeatureSpecLike;Lorg/scalatest/Args;Ljava/lang/String;Lorg/scalatest/AsyncSuperEngine$TestLeaf;Lscala/Function1;)Lorg/scalatest/AsyncOutcome;
  #384 = NameAndType        #382:#383     // $anonfun$runTest$1:(Lorg/scalatest/featurespec/FixtureAsyncFeatureSpecLike;Lorg/scalatest/Args;Ljava/lang/String;Lorg/scalatest/AsyncSuperEngine$TestLeaf;Lscala/Function1;)Lorg/scalatest/AsyncOutcome;
  #385 = InterfaceMethodref #2.#384       // org/scalatest/featurespec/FixtureAsyncFeatureSpecLike.$anonfun$runTest$1:(Lorg/scalatest/featurespec/FixtureAsyncFeatureSpecLike;Lorg/scalatest/Args;Ljava/lang/String;Lorg/scalatest/AsyncSuperEngine$TestLeaf;Lscala/Function1;)Lorg/scalatest/AsyncOutcome;
  #386 = MethodHandle       6:#385        // REF_invokeStatic org/scalatest/featurespec/FixtureAsyncFeatureSpecLike.$anonfun$runTest$1:(Lorg/scalatest/featurespec/FixtureAsyncFeatureSpecLike;Lorg/scalatest/Args;Ljava/lang/String;Lorg/scalatest/AsyncSuperEngine$TestLeaf;Lscala/Function1;)Lorg/scalatest/AsyncOutcome;
  #387 = Utf8               (Lorg/scalatest/AsyncSuperEngine$TestLeaf;Lscala/Function1;)Lorg/scalatest/AsyncOutcome;
  #388 = MethodType         #387          //  (Lorg/scalatest/AsyncSuperEngine$TestLeaf;Lscala/Function1;)Lorg/scalatest/AsyncOutcome;
  #389 = Utf8               (Lorg/scalatest/featurespec/FixtureAsyncFeatureSpecLike;Lorg/scalatest/Args;Ljava/lang/String;)Lscala/Function2;
  #390 = NameAndType        #161:#389     // apply:(Lorg/scalatest/featurespec/FixtureAsyncFeatureSpecLike;Lorg/scalatest/Args;Ljava/lang/String;)Lscala/Function2;
  #391 = InvokeDynamic      #5:#390       // #5:apply:(Lorg/scalatest/featurespec/FixtureAsyncFeatureSpecLike;Lorg/scalatest/Args;Ljava/lang/String;)Lscala/Function2;
  #392 = Utf8               executionContext
  #393 = Utf8               ()Lscala/concurrent/ExecutionContext;
  #394 = NameAndType        #392:#393     // executionContext:()Lscala/concurrent/ExecutionContext;
  #395 = InterfaceMethodref #2.#394       // org/scalatest/featurespec/FixtureAsyncFeatureSpecLike.executionContext:()Lscala/concurrent/ExecutionContext;
  #396 = Utf8               runTestImpl
  #397 = Utf8               (Lorg/scalatest/Suite;Ljava/lang/String;Lorg/scalatest/Args;ZZLscala/Function2;Lscala/concurrent/ExecutionContext;)Lorg/scalatest/Status;
  #398 = NameAndType        #396:#397     // runTestImpl:(Lorg/scalatest/Suite;Ljava/lang/String;Lorg/scalatest/Args;ZZLscala/Function2;Lscala/concurrent/ExecutionContext;)Lorg/scalatest/Status;
  #399 = Methodref          #72.#398      // org/scalatest/AsyncFixtureEngine.runTestImpl:(Lorg/scalatest/Suite;Ljava/lang/String;Lorg/scalatest/Args;ZZLscala/Function2;Lscala/concurrent/ExecutionContext;)Lorg/scalatest/Status;
  #400 = Utf8               runTests$
  #401 = Utf8               (Lorg/scalatest/featurespec/FixtureAsyncFeatureSpecLike;Lscala/Option;Lorg/scalatest/Args;)Lorg/scalatest/Status;
  #402 = Utf8               runTests
  #403 = NameAndType        #402:#55      // runTests:(Lscala/Option;Lorg/scalatest/Args;)Lorg/scalatest/Status;
  #404 = InterfaceMethodref #2.#403       // org/scalatest/featurespec/FixtureAsyncFeatureSpecLike.runTests:(Lscala/Option;Lorg/scalatest/Args;)Lorg/scalatest/Status;
  #405 = Utf8               Lscala/Option;
  #406 = Utf8               (Lscala/Option<Ljava/lang/String;>;Lorg/scalatest/Args;)Lorg/scalatest/Status;
  #407 = Utf8               $anonfun$runTests$1
  #408 = NameAndType        #407:#371     // $anonfun$runTests$1:(Lorg/scalatest/featurespec/FixtureAsyncFeatureSpecLike;Ljava/lang/String;Lorg/scalatest/Args;)Lorg/scalatest/Status;
  #409 = InterfaceMethodref #2.#408       // org/scalatest/featurespec/FixtureAsyncFeatureSpecLike.$anonfun$runTests$1:(Lorg/scalatest/featurespec/FixtureAsyncFeatureSpecLike;Ljava/lang/String;Lorg/scalatest/Args;)Lorg/scalatest/Status;
  #410 = MethodHandle       6:#409        // REF_invokeStatic org/scalatest/featurespec/FixtureAsyncFeatureSpecLike.$anonfun$runTests$1:(Lorg/scalatest/featurespec/FixtureAsyncFeatureSpecLike;Ljava/lang/String;Lorg/scalatest/Args;)Lorg/scalatest/Status;
  #411 = MethodType         #373          //  (Ljava/lang/String;Lorg/scalatest/Args;)Lorg/scalatest/Status;
  #412 = Utf8               (Lorg/scalatest/featurespec/FixtureAsyncFeatureSpecLike;)Lscala/Function2;
  #413 = NameAndType        #161:#412     // apply:(Lorg/scalatest/featurespec/FixtureAsyncFeatureSpecLike;)Lscala/Function2;
  #414 = InvokeDynamic      #6:#413       // #6:apply:(Lorg/scalatest/featurespec/FixtureAsyncFeatureSpecLike;)Lscala/Function2;
  #415 = Utf8               runTestsImpl
  #416 = Utf8               (Lorg/scalatest/Suite;Lscala/Option;Lorg/scalatest/Args;ZZLscala/Function2;)Lorg/scalatest/Status;
  #417 = NameAndType        #415:#416     // runTestsImpl:(Lorg/scalatest/Suite;Lscala/Option;Lorg/scalatest/Args;ZZLscala/Function2;)Lorg/scalatest/Status;
  #418 = Methodref          #72.#417      // org/scalatest/AsyncFixtureEngine.runTestsImpl:(Lorg/scalatest/Suite;Lscala/Option;Lorg/scalatest/Args;ZZLscala/Function2;)Lorg/scalatest/Status;
  #419 = Utf8               testNames$
  #420 = Utf8               (Lorg/scalatest/featurespec/FixtureAsyncFeatureSpecLike;)Lscala/collection/immutable/Set;
  #421 = Utf8               testNames
  #422 = Utf8               ()Lscala/collection/immutable/Set;
  #423 = NameAndType        #421:#422     // testNames:()Lscala/collection/immutable/Set;
  #424 = InterfaceMethodref #2.#423       // org/scalatest/featurespec/FixtureAsyncFeatureSpecLike.testNames:()Lscala/collection/immutable/Set;
  #425 = Utf8               ()Lscala/collection/immutable/Set<Ljava/lang/String;>;
  #426 = Utf8               org/scalatest/InsertionOrderSet$
  #427 = Class              #426          // org/scalatest/InsertionOrderSet$
  #428 = Utf8               Lorg/scalatest/InsertionOrderSet$;
  #429 = NameAndType        #128:#428     // MODULE$:Lorg/scalatest/InsertionOrderSet$;
  #430 = Fieldref           #427.#429     // org/scalatest/InsertionOrderSet$.MODULE$:Lorg/scalatest/InsertionOrderSet$;
  #431 = Utf8               testNamesList
  #432 = Utf8               ()Lscala/collection/immutable/List;
  #433 = NameAndType        #431:#432     // testNamesList:()Lscala/collection/immutable/List;
  #434 = Methodref          #30.#433      // org/scalatest/AsyncSuperEngine$Bundle.testNamesList:()Lscala/collection/immutable/List;
  #435 = Utf8               (Lscala/collection/immutable/List;)Lscala/collection/immutable/Set;
  #436 = NameAndType        #161:#435     // apply:(Lscala/collection/immutable/List;)Lscala/collection/immutable/Set;
  #437 = Methodref          #427.#436     // org/scalatest/InsertionOrderSet$.apply:(Lscala/collection/immutable/List;)Lscala/collection/immutable/Set;
  #438 = Utf8               run$
  #439 = Utf8               run
  #440 = NameAndType        #439:#55      // run:(Lscala/Option;Lorg/scalatest/Args;)Lorg/scalatest/Status;
  #441 = InterfaceMethodref #2.#440       // org/scalatest/featurespec/FixtureAsyncFeatureSpecLike.run:(Lscala/Option;Lorg/scalatest/Args;)Lorg/scalatest/Status;
  #442 = Utf8               $anonfun$run$1
  #443 = NameAndType        #442:#401     // $anonfun$run$1:(Lorg/scalatest/featurespec/FixtureAsyncFeatureSpecLike;Lscala/Option;Lorg/scalatest/Args;)Lorg/scalatest/Status;
  #444 = InterfaceMethodref #2.#443       // org/scalatest/featurespec/FixtureAsyncFeatureSpecLike.$anonfun$run$1:(Lorg/scalatest/featurespec/FixtureAsyncFeatureSpecLike;Lscala/Option;Lorg/scalatest/Args;)Lorg/scalatest/Status;
  #445 = MethodHandle       6:#444        // REF_invokeStatic org/scalatest/featurespec/FixtureAsyncFeatureSpecLike.$anonfun$run$1:(Lorg/scalatest/featurespec/FixtureAsyncFeatureSpecLike;Lscala/Option;Lorg/scalatest/Args;)Lorg/scalatest/Status;
  #446 = MethodType         #55           //  (Lscala/Option;Lorg/scalatest/Args;)Lorg/scalatest/Status;
  #447 = InvokeDynamic      #7:#413       // #7:apply:(Lorg/scalatest/featurespec/FixtureAsyncFeatureSpecLike;)Lscala/Function2;
  #448 = Utf8               runImpl
  #449 = Utf8               (Lorg/scalatest/Suite;Lscala/Option;Lorg/scalatest/Args;ZLscala/Function2;)Lorg/scalatest/Status;
  #450 = NameAndType        #448:#449     // runImpl:(Lorg/scalatest/Suite;Lscala/Option;Lorg/scalatest/Args;ZLscala/Function2;)Lorg/scalatest/Status;
  #451 = Methodref          #72.#450      // org/scalatest/AsyncFixtureEngine.runImpl:(Lorg/scalatest/Suite;Lscala/Option;Lorg/scalatest/Args;ZLscala/Function2;)Lorg/scalatest/Status;
  #452 = Utf8               scenariosFor$
  #453 = Utf8               (Lorg/scalatest/featurespec/FixtureAsyncFeatureSpecLike;Lscala/runtime/BoxedUnit;)V
  #454 = Utf8               unit
  #455 = Utf8               scenariosFor
  #456 = Utf8               (Lscala/runtime/BoxedUnit;)V
  #457 = NameAndType        #455:#456     // scenariosFor:(Lscala/runtime/BoxedUnit;)V
  #458 = InterfaceMethodref #2.#457       // org/scalatest/featurespec/FixtureAsyncFeatureSpecLike.scenariosFor:(Lscala/runtime/BoxedUnit;)V
  #459 = Utf8               Lscala/runtime/BoxedUnit;
  #460 = Utf8               ScenariosFor
  #461 = NameAndType        #460:#456     // ScenariosFor:(Lscala/runtime/BoxedUnit;)V
  #462 = InterfaceMethodref #2.#461       // org/scalatest/featurespec/FixtureAsyncFeatureSpecLike.ScenariosFor:(Lscala/runtime/BoxedUnit;)V
  #463 = Utf8               ScenariosFor$
  #464 = Utf8               convertPendingToFixtureFunction$
  #465 = Utf8               (Lorg/scalatest/featurespec/FixtureAsyncFeatureSpecLike;Lscala/Function0;)Lscala/Function1;
  #466 = Utf8               f
  #467 = Utf8               convertPendingToFixtureFunction
  #468 = Utf8               (Lscala/Function0;)Lscala/Function1;
  #469 = NameAndType        #467:#468     // convertPendingToFixtureFunction:(Lscala/Function0;)Lscala/Function1;
  #470 = InterfaceMethodref #2.#469       // org/scalatest/featurespec/FixtureAsyncFeatureSpecLike.convertPendingToFixtureFunction:(Lscala/Function0;)Lscala/Function1;
  #471 = Utf8               (Lscala/Function0<Lorg/scalatest/PendingStatement;>;)Lscala/Function1<Ljava/lang/Object;Lorg/scalatest/compatible/Assertion;>;
  #472 = Utf8               (Ljava/lang/Object;)Ljava/lang/Object;
  #473 = MethodType         #472          //  (Ljava/lang/Object;)Ljava/lang/Object;
  #474 = Utf8               $anonfun$convertPendingToFixtureFunction$1
  #475 = Utf8               (Lscala/Function0;Ljava/lang/Object;)Lorg/scalatest/Succeeded$;
  #476 = NameAndType        #474:#475     // $anonfun$convertPendingToFixtureFunction$1:(Lscala/Function0;Ljava/lang/Object;)Lorg/scalatest/Succeeded$;
  #477 = InterfaceMethodref #2.#476       // org/scalatest/featurespec/FixtureAsyncFeatureSpecLike.$anonfun$convertPendingToFixtureFunction$1:(Lscala/Function0;Ljava/lang/Object;)Lorg/scalatest/Succeeded$;
  #478 = MethodHandle       6:#477        // REF_invokeStatic org/scalatest/featurespec/FixtureAsyncFeatureSpecLike.$anonfun$convertPendingToFixtureFunction$1:(Lscala/Function0;Ljava/lang/Object;)Lorg/scalatest/Succeeded$;
  #479 = Utf8               (Ljava/lang/Object;)Lorg/scalatest/Succeeded$;
  #480 = MethodType         #479          //  (Ljava/lang/Object;)Lorg/scalatest/Succeeded$;
  #481 = NameAndType        #161:#468     // apply:(Lscala/Function0;)Lscala/Function1;
  #482 = InvokeDynamic      #8:#481       // #8:apply:(Lscala/Function0;)Lscala/Function1;
  #483 = Utf8               styleName
  #484 = Utf8               testDataFor$
  #485 = Utf8               (Lorg/scalatest/featurespec/FixtureAsyncFeatureSpecLike;Ljava/lang/String;Lorg/scalatest/ConfigMap;)Lorg/scalatest/TestData;
  #486 = Utf8               theConfigMap
  #487 = Utf8               testDataFor
  #488 = Utf8               (Ljava/lang/String;Lorg/scalatest/ConfigMap;)Lorg/scalatest/TestData;
  #489 = NameAndType        #487:#488     // testDataFor:(Ljava/lang/String;Lorg/scalatest/ConfigMap;)Lorg/scalatest/TestData;
  #490 = InterfaceMethodref #2.#489       // org/scalatest/featurespec/FixtureAsyncFeatureSpecLike.testDataFor:(Ljava/lang/String;Lorg/scalatest/ConfigMap;)Lorg/scalatest/TestData;
  #491 = Utf8               Lorg/scalatest/ConfigMap;
  #492 = Utf8               createTestDataFor
  #493 = Utf8               (Ljava/lang/String;Lorg/scalatest/ConfigMap;Lorg/scalatest/Suite;)Lorg/scalatest/TestData;
  #494 = NameAndType        #492:#493     // createTestDataFor:(Ljava/lang/String;Lorg/scalatest/ConfigMap;Lorg/scalatest/Suite;)Lorg/scalatest/TestData;
  #495 = Methodref          #72.#494      // org/scalatest/AsyncFixtureEngine.createTestDataFor:(Ljava/lang/String;Lorg/scalatest/ConfigMap;Lorg/scalatest/Suite;)Lorg/scalatest/TestData;
  #496 = Utf8               testDataFor$default$2$
  #497 = Utf8               (Lorg/scalatest/featurespec/FixtureAsyncFeatureSpecLike;)Lorg/scalatest/ConfigMap;
  #498 = Utf8               testDataFor$default$2
  #499 = Utf8               ()Lorg/scalatest/ConfigMap;
  #500 = NameAndType        #498:#499     // testDataFor$default$2:()Lorg/scalatest/ConfigMap;
  #501 = InterfaceMethodref #2.#500       // org/scalatest/featurespec/FixtureAsyncFeatureSpecLike.testDataFor$default$2:()Lorg/scalatest/ConfigMap;
  #502 = Utf8               org/scalatest/ConfigMap$
  #503 = Class              #502          // org/scalatest/ConfigMap$
  #504 = Utf8               Lorg/scalatest/ConfigMap$;
  #505 = NameAndType        #128:#504     // MODULE$:Lorg/scalatest/ConfigMap$;
  #506 = Fieldref           #503.#505     // org/scalatest/ConfigMap$.MODULE$:Lorg/scalatest/ConfigMap$;
  #507 = Utf8               empty
  #508 = NameAndType        #507:#499     // empty:()Lorg/scalatest/ConfigMap;
  #509 = Methodref          #503.#508     // org/scalatest/ConfigMap$.empty:()Lorg/scalatest/ConfigMap;
  #510 = Utf8               $anonfun$engine$1
  #511 = Utf8               concurrentFeatureSpecMod
  #512 = NameAndType        #511:#135     // concurrentFeatureSpecMod:()Ljava/lang/String;
  #513 = Methodref          #127.#512     // org/scalatest/Resources$.concurrentFeatureSpecMod:()Ljava/lang/String;
  #514 = Utf8               testCannotBeNestedInsideAnotherTest
  #515 = NameAndType        #514:#135     // testCannotBeNestedInsideAnotherTest:()Ljava/lang/String;
  #516 = Methodref          #127.#515     // org/scalatest/Resources$.testCannotBeNestedInsideAnotherTest:()Ljava/lang/String;
  #517 = Utf8               featureCannotAppearInsideAScenario
  #518 = NameAndType        #517:#135     // featureCannotAppearInsideAScenario:()Ljava/lang/String;
  #519 = Methodref          #127.#518     // org/scalatest/Resources$.featureCannotAppearInsideAScenario:()Ljava/lang/String;
  #520 = Utf8               pos$1
  #521 = Utf8               invokeWithAsyncFixture$1
  #522 = Utf8               (Lorg/scalatest/AsyncSuperEngine$TestLeaf;Lscala/Function1;Lorg/scalatest/Args;Ljava/lang/String;)Lorg/scalatest/AsyncOutcome;
  #523 = Utf8               theTest
  #524 = Utf8               onCompleteFun
  #525 = Utf8               args$1
  #526 = Utf8               testName$1
  #527 = Utf8               org/scalatest/Args
  #528 = Class              #527          // org/scalatest/Args
  #529 = Utf8               configMap
  #530 = NameAndType        #529:#499     // configMap:()Lorg/scalatest/ConfigMap;
  #531 = Methodref          #528.#530     // org/scalatest/Args.configMap:()Lorg/scalatest/ConfigMap;
  #532 = Utf8               org/scalatest/FutureAsyncOutcome
  #533 = Class              #532          // org/scalatest/FutureAsyncOutcome
  #534 = Utf8               (Lorg/scalatest/featurespec/FixtureAsyncFeatureSpecLike;Lorg/scalatest/TestData;Lorg/scalatest/AsyncSuperEngine$TestLeaf;)V
  #535 = NameAndType        #210:#534     // "<init>":(Lorg/scalatest/featurespec/FixtureAsyncFeatureSpecLike;Lorg/scalatest/TestData;Lorg/scalatest/AsyncSuperEngine$TestLeaf;)V
  #536 = Methodref          #41.#535      // org/scalatest/featurespec/FixtureAsyncFeatureSpecLike$$anon$1."<init>":(Lorg/scalatest/featurespec/FixtureAsyncFeatureSpecLike;Lorg/scalatest/TestData;Lorg/scalatest/AsyncSuperEngine$TestLeaf;)V
  #537 = Utf8               withFixture
  #538 = Utf8               (Lorg/scalatest/FixtureAsyncTestSuite$OneArgAsyncTest;)Lorg/scalatest/FutureOutcome;
  #539 = NameAndType        #537:#538     // withFixture:(Lorg/scalatest/FixtureAsyncTestSuite$OneArgAsyncTest;)Lorg/scalatest/FutureOutcome;
  #540 = InterfaceMethodref #2.#539       // org/scalatest/featurespec/FixtureAsyncFeatureSpecLike.withFixture:(Lorg/scalatest/FixtureAsyncTestSuite$OneArgAsyncTest;)Lorg/scalatest/FutureOutcome;
  #541 = Utf8               org/scalatest/FutureOutcome
  #542 = Class              #541          // org/scalatest/FutureOutcome
  #543 = Utf8               underlying
  #544 = Utf8               ()Lscala/concurrent/Future;
  #545 = NameAndType        #543:#544     // underlying:()Lscala/concurrent/Future;
  #546 = Methodref          #542.#545     // org/scalatest/FutureOutcome.underlying:()Lscala/concurrent/Future;
  #547 = Utf8               (Lscala/concurrent/Future;Lscala/Function1;Lscala/concurrent/ExecutionContext;)V
  #548 = NameAndType        #210:#547     // "<init>":(Lscala/concurrent/Future;Lscala/Function1;Lscala/concurrent/ExecutionContext;)V
  #549 = Methodref          #533.#548     // org/scalatest/FutureAsyncOutcome."<init>":(Lscala/concurrent/Future;Lscala/Function1;Lscala/concurrent/ExecutionContext;)V
  #550 = Utf8               testData
  #551 = Utf8               Lorg/scalatest/TestData;
  #552 = Utf8               Lorg/scalatest/AsyncSuperEngine$TestLeaf;
  #553 = NameAndType        #521:#522     // invokeWithAsyncFixture$1:(Lorg/scalatest/AsyncSuperEngine$TestLeaf;Lscala/Function1;Lorg/scalatest/Args;Ljava/lang/String;)Lorg/scalatest/AsyncOutcome;
  #554 = InterfaceMethodref #2.#553       // org/scalatest/featurespec/FixtureAsyncFeatureSpecLike.invokeWithAsyncFixture$1:(Lorg/scalatest/AsyncSuperEngine$TestLeaf;Lscala/Function1;Lorg/scalatest/Args;Ljava/lang/String;)Lorg/scalatest/AsyncOutcome;
  #555 = NameAndType        #54:#55       // org$scalatest$featurespec$FixtureAsyncFeatureSpecLike$$super$run:(Lscala/Option;Lorg/scalatest/Args;)Lorg/scalatest/Status;
  #556 = InterfaceMethodref #2.#555       // org/scalatest/featurespec/FixtureAsyncFeatureSpecLike.org$scalatest$featurespec$FixtureAsyncFeatureSpecLike$$super$run:(Lscala/Option;Lorg/scalatest/Args;)Lorg/scalatest/Status;
  #557 = Utf8               f$1
  #558 = Utf8               fixture
  #559 = NameAndType        #161:#80      // apply:()Ljava/lang/Object;
  #560 = InterfaceMethodref #348.#559     // scala/Function0.apply:()Ljava/lang/Object;
  #561 = Utf8               org/scalatest/Succeeded$
  #562 = Class              #561          // org/scalatest/Succeeded$
  #563 = Utf8               Lorg/scalatest/Succeeded$;
  #564 = NameAndType        #128:#563     // MODULE$:Lorg/scalatest/Succeeded$;
  #565 = Fieldref           #562.#564     // org/scalatest/Succeeded$.MODULE$:Lorg/scalatest/Succeeded$;
  #566 = Utf8               Ljava/lang/Object;
  #567 = Utf8               $init$
  #568 = Utf8               (Lorg/scalatest/featurespec/FixtureAsyncFeatureSpecLike;)V
  #569 = NameAndType        #510:#135     // $anonfun$engine$1:()Ljava/lang/String;
  #570 = InterfaceMethodref #2.#569       // org/scalatest/featurespec/FixtureAsyncFeatureSpecLike.$anonfun$engine$1:()Ljava/lang/String;
  #571 = MethodHandle       6:#570        // REF_invokeStatic org/scalatest/featurespec/FixtureAsyncFeatureSpecLike.$anonfun$engine$1:()Ljava/lang/String;
  #572 = InvokeDynamic      #9:#163       // #9:apply:()Lscala/Function0;
  #573 = Utf8               FixtureFeatureSpec
  #574 = String             #573          // FixtureFeatureSpec
  #575 = Utf8               (Lscala/Function0;Ljava/lang/String;)V
  #576 = NameAndType        #210:#575     // "<init>":(Lscala/Function0;Ljava/lang/String;)V
  #577 = Methodref          #72.#576      // org/scalatest/AsyncFixtureEngine."<init>":(Lscala/Function0;Ljava/lang/String;)V
  #578 = NameAndType        #48:#49       // org$scalatest$featurespec$FixtureAsyncFeatureSpecLike$_setter_$org$scalatest$featurespec$FixtureAsyncFeatureSpecLike$$engine_$eq:(Lorg/scalatest/AsyncFixtureEngine;)V
  #579 = InterfaceMethodref #2.#578       // org/scalatest/featurespec/FixtureAsyncFeatureSpecLike.org$scalatest$featurespec$FixtureAsyncFeatureSpecLike$_setter_$org$scalatest$featurespec$FixtureAsyncFeatureSpecLike$$engine_$eq:(Lorg/scalatest/AsyncFixtureEngine;)V
  #580 = Utf8               org.scalatest.fixture.FeatureSpec
  #581 = String             #580          // org.scalatest.fixture.FeatureSpec
  #582 = NameAndType        #52:#53       // org$scalatest$featurespec$FixtureAsyncFeatureSpecLike$_setter_$styleName_$eq:(Ljava/lang/String;)V
  #583 = InterfaceMethodref #2.#582       // org/scalatest/featurespec/FixtureAsyncFeatureSpecLike.org$scalatest$featurespec$FixtureAsyncFeatureSpecLike$_setter_$styleName_$eq:(Ljava/lang/String;)V
  #584 = Utf8               $deserializeLambda$
  #585 = Utf8               (Ljava/lang/invoke/SerializedLambda;)Ljava/lang/Object;
  #586 = Utf8               scala/runtime/LambdaDeserialize
  #587 = Class              #586          // scala/runtime/LambdaDeserialize
  #588 = Utf8               bootstrap
  #589 = Utf8               (Ljava/lang/invoke/MethodHandles$Lookup;Ljava/lang/String;Ljava/lang/invoke/MethodType;[Ljava/lang/invoke/MethodHandle;)Ljava/lang/invoke/CallSite;
  #590 = NameAndType        #588:#589     // bootstrap:(Ljava/lang/invoke/MethodHandles$Lookup;Ljava/lang/String;Ljava/lang/invoke/MethodType;[Ljava/lang/invoke/MethodHandle;)Ljava/lang/invoke/CallSite;
  #591 = Methodref          #587.#590     // scala/runtime/LambdaDeserialize.bootstrap:(Ljava/lang/invoke/MethodHandles$Lookup;Ljava/lang/String;Ljava/lang/invoke/MethodType;[Ljava/lang/invoke/MethodHandle;)Ljava/lang/invoke/CallSite;
  #592 = MethodHandle       6:#591        // REF_invokeStatic scala/runtime/LambdaDeserialize.bootstrap:(Ljava/lang/invoke/MethodHandles$Lookup;Ljava/lang/String;Ljava/lang/invoke/MethodType;[Ljava/lang/invoke/MethodHandle;)Ljava/lang/invoke/CallSite;
  #593 = Utf8               lambdaDeserialize
  #594 = NameAndType        #593:#585     // lambdaDeserialize:(Ljava/lang/invoke/SerializedLambda;)Ljava/lang/Object;
  #595 = InvokeDynamic      #10:#594      // #10:lambdaDeserialize:(Ljava/lang/invoke/SerializedLambda;)Ljava/lang/Object;
  #596 = Utf8               Signature
  #597 = Utf8               MethodParameters
  #598 = Utf8               Code
  #599 = Utf8               LineNumberTable
  #600 = Utf8               LocalVariableTable
  #601 = Utf8               Deprecated
  #602 = Utf8               StackMapTable
  #603 = Utf8               InnerClasses
  #604 = Utf8               SourceFile
  #605 = Utf8               RuntimeVisibleAnnotations
  #606 = Utf8               BootstrapMethods
  #607 = Utf8               ScalaInlineInfo
  #608 = Utf8               ScalaSig
{
  public abstract void org$scalatest$featurespec$FixtureAsyncFeatureSpecLike$_setter_$org$scalatest$featurespec$FixtureAsyncFeatureSpecLike$$engine_$eq(org.scalatest.AsyncFixtureEngine<java.lang.Object>);
    descriptor: (Lorg/scalatest/AsyncFixtureEngine;)V
    flags: (0x0401) ACC_PUBLIC, ACC_ABSTRACT
    Signature: #50                          // (Lorg/scalatest/AsyncFixtureEngine<Ljava/lang/Object;>;)V
    MethodParameters:
      Name                           Flags
      x$1                            final

  public abstract void org$scalatest$featurespec$FixtureAsyncFeatureSpecLike$_setter_$styleName_$eq(java.lang.String);
    descriptor: (Ljava/lang/String;)V
    flags: (0x0401) ACC_PUBLIC, ACC_ABSTRACT
    MethodParameters:
      Name                           Flags
      x$1                            final

  public abstract org.scalatest.Status org$scalatest$featurespec$FixtureAsyncFeatureSpecLike$$super$run(scala.Option, org.scalatest.Args);
    descriptor: (Lscala/Option;Lorg/scalatest/Args;)Lorg/scalatest/Status;
    flags: (0x1401) ACC_PUBLIC, ACC_ABSTRACT, ACC_SYNTHETIC
    MethodParameters:
      Name                           Flags
      testName                       final
      args                           final

  public abstract org.scalatest.AsyncFixtureEngine<java.lang.Object> org$scalatest$featurespec$FixtureAsyncFeatureSpecLike$$engine();
    descriptor: ()Lorg/scalatest/AsyncFixtureEngine;
    flags: (0x0401) ACC_PUBLIC, ACC_ABSTRACT
    Signature: #60                          // ()Lorg/scalatest/AsyncFixtureEngine<Ljava/lang/Object;>;

  public static org.scalatest.Informer info$(org.scalatest.featurespec.FixtureAsyncFeatureSpecLike);
    descriptor: (Lorg/scalatest/featurespec/FixtureAsyncFeatureSpecLike;)Lorg/scalatest/Informer;
    flags: (0x1009) ACC_PUBLIC, ACC_STATIC, ACC_SYNTHETIC
    Code:
      stack=1, locals=1, args_size=1
         0: aload_0
         1: invokespecial #67                 // InterfaceMethod info:()Lorg/scalatest/Informer;
         4: areturn
      LineNumberTable:
        line 68: 0
      LocalVariableTable:
        Start  Length  Slot  Name   Signature
            0       5     0 $this   Lorg/scalatest/featurespec/FixtureAsyncFeatureSpecLike;
    MethodParameters:
      Name                           Flags
      $this                          final synthetic

  public default org.scalatest.Informer info();
    descriptor: ()Lorg/scalatest/Informer;
    flags: (0x0001) ACC_PUBLIC
    Code:
      stack=1, locals=1, args_size=1
         0: aload_0
         1: invokeinterface #70,  1           // InterfaceMethod org$scalatest$featurespec$FixtureAsyncFeatureSpecLike$$engine:()Lorg/scalatest/AsyncFixtureEngine;
         6: invokevirtual #76                 // Method org/scalatest/AsyncFixtureEngine.atomicInformer:()Ljava/util/concurrent/atomic/AtomicReference;
         9: invokevirtual #82                 // Method java/util/concurrent/atomic/AtomicReference.get:()Ljava/lang/Object;
        12: checkcast     #84                 // class org/scalatest/Informer
        15: areturn
      LineNumberTable:
        line 68: 0
      LocalVariableTable:
        Start  Length  Slot  Name   Signature
            0      16     0  this   Lorg/scalatest/featurespec/FixtureAsyncFeatureSpecLike;

  public static org.scalatest.Notifier note$(org.scalatest.featurespec.FixtureAsyncFeatureSpecLike);
    descriptor: (Lorg/scalatest/featurespec/FixtureAsyncFeatureSpecLike;)Lorg/scalatest/Notifier;
    flags: (0x1009) ACC_PUBLIC, ACC_STATIC, ACC_SYNTHETIC
    Code:
      stack=1, locals=1, args_size=1
         0: aload_0
         1: invokespecial #91                 // InterfaceMethod note:()Lorg/scalatest/Notifier;
         4: areturn
      LineNumberTable:
        line 78: 0
      LocalVariableTable:
        Start  Length  Slot  Name   Signature
            0       5     0 $this   Lorg/scalatest/featurespec/FixtureAsyncFeatureSpecLike;
    MethodParameters:
      Name                           Flags
      $this                          final synthetic

  public default org.scalatest.Notifier note();
    descriptor: ()Lorg/scalatest/Notifier;
    flags: (0x0001) ACC_PUBLIC
    Code:
      stack=1, locals=1, args_size=1
         0: aload_0
         1: invokeinterface #70,  1           // InterfaceMethod org$scalatest$featurespec$FixtureAsyncFeatureSpecLike$$engine:()Lorg/scalatest/AsyncFixtureEngine;
         6: invokevirtual #94                 // Method org/scalatest/AsyncFixtureEngine.atomicNotifier:()Ljava/util/concurrent/atomic/AtomicReference;
         9: invokevirtual #82                 // Method java/util/concurrent/atomic/AtomicReference.get:()Ljava/lang/Object;
        12: checkcast     #96                 // class org/scalatest/Notifier
        15: areturn
      LineNumberTable:
        line 78: 0
      LocalVariableTable:
        Start  Length  Slot  Name   Signature
            0      16     0  this   Lorg/scalatest/featurespec/FixtureAsyncFeatureSpecLike;

  public static org.scalatest.Alerter alert$(org.scalatest.featurespec.FixtureAsyncFeatureSpecLike);
    descriptor: (Lorg/scalatest/featurespec/FixtureAsyncFeatureSpecLike;)Lorg/scalatest/Alerter;
    flags: (0x1009) ACC_PUBLIC, ACC_STATIC, ACC_SYNTHETIC
    Code:
      stack=1, locals=1, args_size=1
         0: aload_0
         1: invokespecial #102                // InterfaceMethod alert:()Lorg/scalatest/Alerter;
         4: areturn
      LineNumberTable:
        line 88: 0
      LocalVariableTable:
        Start  Length  Slot  Name   Signature
            0       5     0 $this   Lorg/scalatest/featurespec/FixtureAsyncFeatureSpecLike;
    MethodParameters:
      Name                           Flags
      $this                          final synthetic

  public default org.scalatest.Alerter alert();
    descriptor: ()Lorg/scalatest/Alerter;
    flags: (0x0001) ACC_PUBLIC
    Code:
      stack=1, locals=1, args_size=1
         0: aload_0
         1: invokeinterface #70,  1           // InterfaceMethod org$scalatest$featurespec$FixtureAsyncFeatureSpecLike$$engine:()Lorg/scalatest/AsyncFixtureEngine;
         6: invokevirtual #105                // Method org/scalatest/AsyncFixtureEngine.atomicAlerter:()Ljava/util/concurrent/atomic/AtomicReference;
         9: invokevirtual #82                 // Method java/util/concurrent/atomic/AtomicReference.get:()Ljava/lang/Object;
        12: checkcast     #107                // class org/scalatest/Alerter
        15: areturn
      LineNumberTable:
        line 88: 0
      LocalVariableTable:
        Start  Length  Slot  Name   Signature
            0      16     0  this   Lorg/scalatest/featurespec/FixtureAsyncFeatureSpecLike;

  public static org.scalatest.Documenter markup$(org.scalatest.featurespec.FixtureAsyncFeatureSpecLike);
    descriptor: (Lorg/scalatest/featurespec/FixtureAsyncFeatureSpecLike;)Lorg/scalatest/Documenter;
    flags: (0x1009) ACC_PUBLIC, ACC_STATIC, ACC_SYNTHETIC
    Code:
      stack=1, locals=1, args_size=1
         0: aload_0
         1: invokespecial #113                // InterfaceMethod markup:()Lorg/scalatest/Documenter;
         4: areturn
      LineNumberTable:
        line 99: 0
      LocalVariableTable:
        Start  Length  Slot  Name   Signature
            0       5     0 $this   Lorg/scalatest/featurespec/FixtureAsyncFeatureSpecLike;
    MethodParameters:
      Name                           Flags
      $this                          final synthetic

  public default org.scalatest.Documenter markup();
    descriptor: ()Lorg/scalatest/Documenter;
    flags: (0x0001) ACC_PUBLIC
    Code:
      stack=1, locals=1, args_size=1
         0: aload_0
         1: invokeinterface #70,  1           // InterfaceMethod org$scalatest$featurespec$FixtureAsyncFeatureSpecLike$$engine:()Lorg/scalatest/AsyncFixtureEngine;
         6: invokevirtual #116                // Method org/scalatest/AsyncFixtureEngine.atomicDocumenter:()Ljava/util/concurrent/atomic/AtomicReference;
         9: invokevirtual #82                 // Method java/util/concurrent/atomic/AtomicReference.get:()Ljava/lang/Object;
        12: checkcast     #118                // class org/scalatest/Documenter
        15: areturn
      LineNumberTable:
        line 99: 0
      LocalVariableTable:
        Start  Length  Slot  Name   Signature
            0      16     0  this   Lorg/scalatest/featurespec/FixtureAsyncFeatureSpecLike;

  private void registerAsyncTestImpl(java.lang.String, scala.collection.immutable.Seq<org.scalatest.Tag>, scala.Function1<java.lang.Object, scala.concurrent.Future<org.scalatest.compatible.Assertion>>, org.scalactic.source.Position);
    descriptor: (Ljava/lang/String;Lscala/collection/immutable/Seq;Lscala/Function1;Lorg/scalactic/source/Position;)V
    flags: (0x0002) ACC_PRIVATE
    Code:
      stack=8, locals=5, args_size=5
         0: aload_0
         1: invokeinterface #70,  1           // InterfaceMethod org$scalatest$featurespec$FixtureAsyncFeatureSpecLike$$engine:()Lorg/scalatest/AsyncFixtureEngine;
         6: getstatic     #131                // Field org/scalatest/Resources$.MODULE$:Lorg/scalatest/Resources$;
         9: aload_1
        10: invokevirtual #137                // Method java/lang/String.trim:()Ljava/lang/String;
        13: invokevirtual #141                // Method org/scalatest/Resources$.scenario:(Ljava/lang/Object;)Ljava/lang/String;
        16: aload_0
        17: aload_3
        18: invokeinterface #145,  2          // InterfaceMethod transformToOutcome:(Lscala/Function1;)Lscala/Function1;
        23: invokedynamic #164,  0            // InvokeDynamic #0:apply:()Lscala/Function0;
        28: getstatic     #169                // Field scala/None$.MODULE$:Lscala/None$;
        31: getstatic     #169                // Field scala/None$.MODULE$:Lscala/None$;
        34: aload         4
        36: aload_2
        37: invokevirtual #173                // Method org/scalatest/AsyncFixtureEngine.registerAsyncTest:(Ljava/lang/String;Ljava/lang/Object;Lscala/Function0;Lscala/Option;Lscala/Option;Lorg/scalactic/source/Position;Lscala/collection/immutable/Seq;)Ljava/lang/String;
        40: pop
        41: return
      LineNumberTable:
        line 102: 0
      LocalVariableTable:
        Start  Length  Slot  Name   Signature
            0      42     0  this   Lorg/scalatest/featurespec/FixtureAsyncFeatureSpecLike;
            0      42     1 testText   Ljava/lang/String;
            0      42     2 testTags   Lscala/collection/immutable/Seq;
            0      42     3 testFun   Lscala/Function1;
            0      42     4   pos   Lorg/scalactic/source/Position;
    Signature: #121                         // (Ljava/lang/String;Lscala/collection/immutable/Seq<Lorg/scalatest/Tag;>;Lscala/Function1<Ljava/lang/Object;Lscala/concurrent/Future<Lorg/scalatest/compatible/Assertion;>;>;Lorg/scalactic/source/Position;)V
    MethodParameters:
      Name                           Flags
      testText                       final
      testTags                       final
      testFun                        final
      pos                            final

  public static void registerAsyncTest$(org.scalatest.featurespec.FixtureAsyncFeatureSpecLike, java.lang.String, scala.collection.immutable.Seq, scala.Function1, org.scalactic.source.Position);
    descriptor: (Lorg/scalatest/featurespec/FixtureAsyncFeatureSpecLike;Ljava/lang/String;Lscala/collection/immutable/Seq;Lscala/Function1;Lorg/scalactic/source/Position;)V
    flags: (0x1009) ACC_PUBLIC, ACC_STATIC, ACC_SYNTHETIC
    Code:
      stack=5, locals=5, args_size=5
         0: aload_0
         1: aload_1
         2: aload_2
         3: aload_3
         4: aload         4
         6: invokespecial #181                // InterfaceMethod registerAsyncTest:(Ljava/lang/String;Lscala/collection/immutable/Seq;Lscala/Function1;Lorg/scalactic/source/Position;)V
         9: return
      LineNumberTable:
        line 106: 0
      LocalVariableTable:
        Start  Length  Slot  Name   Signature
            0      10     0 $this   Lorg/scalatest/featurespec/FixtureAsyncFeatureSpecLike;
            0      10     1 testText   Ljava/lang/String;
            0      10     2 testTags   Lscala/collection/immutable/Seq;
            0      10     3 testFun   Lscala/Function1;
            0      10     4   pos   Lorg/scalactic/source/Position;
    MethodParameters:
      Name                           Flags
      $this                          final synthetic
      testText                       final
      testTags                       final
      testFun                        final
      pos                            final

  public default void registerAsyncTest(java.lang.String, scala.collection.immutable.Seq<org.scalatest.Tag>, scala.Function1<java.lang.Object, scala.concurrent.Future<org.scalatest.compatible.Assertion>>, org.scalactic.source.Position);
    descriptor: (Ljava/lang/String;Lscala/collection/immutable/Seq;Lscala/Function1;Lorg/scalactic/source/Position;)V
    flags: (0x0001) ACC_PUBLIC
    Code:
      stack=5, locals=5, args_size=5
         0: aload_0
         1: aload_1
         2: aload_2
         3: aload_3
         4: aload         4
         6: invokespecial #183                // InterfaceMethod registerAsyncTestImpl:(Ljava/lang/String;Lscala/collection/immutable/Seq;Lscala/Function1;Lorg/scalactic/source/Position;)V
         9: return
      LineNumberTable:
        line 107: 0
      LocalVariableTable:
        Start  Length  Slot  Name   Signature
            0      10     0  this   Lorg/scalatest/featurespec/FixtureAsyncFeatureSpecLike;
            0      10     1 testText   Ljava/lang/String;
            0      10     2 testTags   Lscala/collection/immutable/Seq;
            0      10     3 testFun   Lscala/Function1;
            0      10     4   pos   Lorg/scalactic/source/Position;
    Signature: #121                         // (Ljava/lang/String;Lscala/collection/immutable/Seq<Lorg/scalatest/Tag;>;Lscala/Function1<Ljava/lang/Object;Lscala/concurrent/Future<Lorg/scalatest/compatible/Assertion;>;>;Lorg/scalactic/source/Position;)V
    MethodParameters:
      Name                           Flags
      testText                       final
      testTags                       final
      testFun                        final
      pos                            final

  private void registerIgnoredAsyncTestImpl(java.lang.String, scala.collection.immutable.Seq<org.scalatest.Tag>, scala.Function1<java.lang.Object, scala.concurrent.Future<org.scalatest.compatible.Assertion>>, org.scalactic.source.Position);
    descriptor: (Ljava/lang/String;Lscala/collection/immutable/Seq;Lscala/Function1;Lorg/scalactic/source/Position;)V
    flags: (0x0002) ACC_PRIVATE
    Code:
      stack=7, locals=5, args_size=5
         0: aload_0
         1: invokeinterface #70,  1           // InterfaceMethod org$scalatest$featurespec$FixtureAsyncFeatureSpecLike$$engine:()Lorg/scalatest/AsyncFixtureEngine;
         6: getstatic     #131                // Field org/scalatest/Resources$.MODULE$:Lorg/scalatest/Resources$;
         9: aload_1
        10: invokevirtual #137                // Method java/lang/String.trim:()Ljava/lang/String;
        13: invokevirtual #141                // Method org/scalatest/Resources$.scenario:(Ljava/lang/Object;)Ljava/lang/String;
        16: aload_0
        17: aload_3
        18: invokeinterface #145,  2          // InterfaceMethod transformToOutcome:(Lscala/Function1;)Lscala/Function1;
        23: invokedynamic #189,  0            // InvokeDynamic #1:apply:()Lscala/Function0;
        28: getstatic     #169                // Field scala/None$.MODULE$:Lscala/None$;
        31: aload         4
        33: aload_2
        34: invokevirtual #193                // Method org/scalatest/AsyncFixtureEngine.registerIgnoredAsyncTest:(Ljava/lang/String;Ljava/lang/Object;Lscala/Function0;Lscala/Option;Lorg/scalactic/source/Position;Lscala/collection/immutable/Seq;)V
        37: return
      LineNumberTable:
        line 115: 0
      LocalVariableTable:
        Start  Length  Slot  Name   Signature
            0      38     0  this   Lorg/scalatest/featurespec/FixtureAsyncFeatureSpecLike;
            0      38     1 testText   Ljava/lang/String;
            0      38     2 testTags   Lscala/collection/immutable/Seq;
            0      38     3 testFun   Lscala/Function1;
            0      38     4   pos   Lorg/scalactic/source/Position;
    Signature: #121                         // (Ljava/lang/String;Lscala/collection/immutable/Seq<Lorg/scalatest/Tag;>;Lscala/Function1<Ljava/lang/Object;Lscala/concurrent/Future<Lorg/scalatest/compatible/Assertion;>;>;Lorg/scalactic/source/Position;)V
    MethodParameters:
      Name                           Flags
      testText                       final
      testTags                       final
      testFun                        final
      pos                            final

  public static void registerIgnoredAsyncTest$(org.scalatest.featurespec.FixtureAsyncFeatureSpecLike, java.lang.String, scala.collection.immutable.Seq, scala.Function1, org.scalactic.source.Position);
    descriptor: (Lorg/scalatest/featurespec/FixtureAsyncFeatureSpecLike;Ljava/lang/String;Lscala/collection/immutable/Seq;Lscala/Function1;Lorg/scalactic/source/Position;)V
    flags: (0x1009) ACC_PUBLIC, ACC_STATIC, ACC_SYNTHETIC
    Code:
      stack=5, locals=5, args_size=5
         0: aload_0
         1: aload_1
         2: aload_2
         3: aload_3
         4: aload         4
         6: invokespecial #196                // InterfaceMethod registerIgnoredAsyncTest:(Ljava/lang/String;Lscala/collection/immutable/Seq;Lscala/Function1;Lorg/scalactic/source/Position;)V
         9: return
      LineNumberTable:
        line 119: 0
      LocalVariableTable:
        Start  Length  Slot  Name   Signature
            0      10     0 $this   Lorg/scalatest/featurespec/FixtureAsyncFeatureSpecLike;
            0      10     1 testText   Ljava/lang/String;
            0      10     2 testTags   Lscala/collection/immutable/Seq;
            0      10     3 testFun   Lscala/Function1;
            0      10     4   pos   Lorg/scalactic/source/Position;
    MethodParameters:
      Name                           Flags
      $this                          final synthetic
      testText                       final
      testTags                       final
      testFun                        final
      pos                            final

  public default void registerIgnoredAsyncTest(java.lang.String, scala.collection.immutable.Seq<org.scalatest.Tag>, scala.Function1<java.lang.Object, scala.concurrent.Future<org.scalatest.compatible.Assertion>>, org.scalactic.source.Position);
    descriptor: (Ljava/lang/String;Lscala/collection/immutable/Seq;Lscala/Function1;Lorg/scalactic/source/Position;)V
    flags: (0x0001) ACC_PUBLIC
    Code:
      stack=5, locals=5, args_size=5
         0: aload_0
         1: aload_1
         2: aload_2
         3: aload_3
         4: aload         4
         6: invokespecial #198                // InterfaceMethod registerIgnoredAsyncTestImpl:(Ljava/lang/String;Lscala/collection/immutable/Seq;Lscala/Function1;Lorg/scalactic/source/Position;)V
         9: return
      LineNumberTable:
        line 120: 0
      LocalVariableTable:
        Start  Length  Slot  Name   Signature
            0      10     0  this   Lorg/scalatest/featurespec/FixtureAsyncFeatureSpecLike;
            0      10     1 testText   Ljava/lang/String;
            0      10     2 testTags   Lscala/collection/immutable/Seq;
            0      10     3 testFun   Lscala/Function1;
            0      10     4   pos   Lorg/scalactic/source/Position;
    Signature: #121                         // (Ljava/lang/String;Lscala/collection/immutable/Seq<Lorg/scalatest/Tag;>;Lscala/Function1<Ljava/lang/Object;Lscala/concurrent/Future<Lorg/scalatest/compatible/Assertion;>;>;Lorg/scalactic/source/Position;)V
    MethodParameters:
      Name                           Flags
      testText                       final
      testTags                       final
      testFun                        final
      pos                            final

  public static org.scalatest.featurespec.FixtureAsyncFeatureSpecLike$ResultOfScenarioInvocation scenario$(org.scalatest.featurespec.FixtureAsyncFeatureSpecLike, java.lang.String, scala.collection.immutable.Seq);
    descriptor: (Lorg/scalatest/featurespec/FixtureAsyncFeatureSpecLike;Ljava/lang/String;Lscala/collection/immutable/Seq;)Lorg/scalatest/featurespec/FixtureAsyncFeatureSpecLike$ResultOfScenarioInvocation;
    flags: (0x1009) ACC_PUBLIC, ACC_STATIC, ACC_SYNTHETIC
    Code:
      stack=3, locals=3, args_size=3
         0: aload_0
         1: aload_1
         2: aload_2
         3: invokespecial #204                // InterfaceMethod scenario:(Ljava/lang/String;Lscala/collection/immutable/Seq;)Lorg/scalatest/featurespec/FixtureAsyncFeatureSpecLike$ResultOfScenarioInvocation;
         6: areturn
      LineNumberTable:
        line 165: 0
      LocalVariableTable:
        Start  Length  Slot  Name   Signature
            0       7     0 $this   Lorg/scalatest/featurespec/FixtureAsyncFeatureSpecLike;
            0       7     1 specText   Ljava/lang/String;
            0       7     2 testTags   Lscala/collection/immutable/Seq;
    MethodParameters:
      Name                           Flags
      $this                          final synthetic
      specText                       final
      testTags                       final

  public default org.scalatest.featurespec.FixtureAsyncFeatureSpecLike$ResultOfScenarioInvocation scenario(java.lang.String, scala.collection.immutable.Seq<org.scalatest.Tag>);
    descriptor: (Ljava/lang/String;Lscala/collection/immutable/Seq;)Lorg/scalatest/featurespec/FixtureAsyncFeatureSpecLike$ResultOfScenarioInvocation;
    flags: (0x0001) ACC_PUBLIC
    Code:
      stack=3, locals=3, args_size=3
         0: aload_0
         1: aload_1
         2: aload_2
         3: invokeinterface #208,  3          // InterfaceMethod Scenario:(Ljava/lang/String;Lscala/collection/immutable/Seq;)Lorg/scalatest/featurespec/FixtureAsyncFeatureSpecLike$ResultOfScenarioInvocation;
         8: areturn
      LineNumberTable:
        line 165: 0
      LocalVariableTable:
        Start  Length  Slot  Name   Signature
            0       9     0  this   Lorg/scalatest/featurespec/FixtureAsyncFeatureSpecLike;
            0       9     1 specText   Ljava/lang/String;
            0       9     2 testTags   Lscala/collection/immutable/Seq;
    Signature: #205                         // (Ljava/lang/String;Lscala/collection/immutable/Seq<Lorg/scalatest/Tag;>;)Lorg/scalatest/featurespec/FixtureAsyncFeatureSpecLike$ResultOfScenarioInvocation;
    Deprecated: true
    MethodParameters:
      Name                           Flags
      specText                       final
      testTags                       final

  public static org.scalatest.featurespec.FixtureAsyncFeatureSpecLike$ResultOfScenarioInvocation Scenario$(org.scalatest.featurespec.FixtureAsyncFeatureSpecLike, java.lang.String, scala.collection.immutable.Seq);
    descriptor: (Lorg/scalatest/featurespec/FixtureAsyncFeatureSpecLike;Ljava/lang/String;Lscala/collection/immutable/Seq;)Lorg/scalatest/featurespec/FixtureAsyncFeatureSpecLike$ResultOfScenarioInvocation;
    flags: (0x1009) ACC_PUBLIC, ACC_STATIC, ACC_SYNTHETIC
    Code:
      stack=3, locals=3, args_size=3
         0: aload_0
         1: aload_1
         2: aload_2
         3: invokespecial #208                // InterfaceMethod Scenario:(Ljava/lang/String;Lscala/collection/immutable/Seq;)Lorg/scalatest/featurespec/FixtureAsyncFeatureSpecLike$ResultOfScenarioInvocation;
         6: areturn
      LineNumberTable:
        line 185: 0
      LocalVariableTable:
        Start  Length  Slot  Name   Signature
            0       7     0 $this   Lorg/scalatest/featurespec/FixtureAsyncFeatureSpecLike;
            0       7     1 specText   Ljava/lang/String;
            0       7     2 testTags   Lscala/collection/immutable/Seq;
    MethodParameters:
      Name                           Flags
      $this                          final synthetic
      specText                       final
      testTags                       final

  public default org.scalatest.featurespec.FixtureAsyncFeatureSpecLike$ResultOfScenarioInvocation Scenario(java.lang.String, scala.collection.immutable.Seq<org.scalatest.Tag>);
    descriptor: (Ljava/lang/String;Lscala/collection/immutable/Seq;)Lorg/scalatest/featurespec/FixtureAsyncFeatureSpecLike$ResultOfScenarioInvocation;
    flags: (0x0001) ACC_PUBLIC
    Code:
      stack=5, locals=3, args_size=3
         0: new           #46                 // class org/scalatest/featurespec/FixtureAsyncFeatureSpecLike$ResultOfScenarioInvocation
         3: dup
         4: aload_0
         5: aload_1
         6: aload_2
         7: invokespecial #213                // Method org/scalatest/featurespec/FixtureAsyncFeatureSpecLike$ResultOfScenarioInvocation."<init>":(Lorg/scalatest/featurespec/FixtureAsyncFeatureSpecLike;Ljava/lang/String;Lscala/collection/immutable/Seq;)V
        10: areturn
      LineNumberTable:
        line 186: 0
      LocalVariableTable:
        Start  Length  Slot  Name   Signature
            0      11     0  this   Lorg/scalatest/featurespec/FixtureAsyncFeatureSpecLike;
            0      11     1 specText   Ljava/lang/String;
            0      11     2 testTags   Lscala/collection/immutable/Seq;
    Signature: #205                         // (Ljava/lang/String;Lscala/collection/immutable/Seq<Lorg/scalatest/Tag;>;)Lorg/scalatest/featurespec/FixtureAsyncFeatureSpecLike$ResultOfScenarioInvocation;
    MethodParameters:
      Name                           Flags
      specText                       final
      testTags                       final

  public static org.scalatest.featurespec.FixtureAsyncFeatureSpecLike$ResultOfIgnoreInvocation ignore$(org.scalatest.featurespec.FixtureAsyncFeatureSpecLike, java.lang.String, scala.collection.immutable.Seq);
    descriptor: (Lorg/scalatest/featurespec/FixtureAsyncFeatureSpecLike;Ljava/lang/String;Lscala/collection/immutable/Seq;)Lorg/scalatest/featurespec/FixtureAsyncFeatureSpecLike$ResultOfIgnoreInvocation;
    flags: (0x1009) ACC_PUBLIC, ACC_STATIC, ACC_SYNTHETIC
    Code:
      stack=3, locals=3, args_size=3
         0: aload_0
         1: aload_1
         2: aload_2
         3: invokespecial #219                // InterfaceMethod ignore:(Ljava/lang/String;Lscala/collection/immutable/Seq;)Lorg/scalatest/featurespec/FixtureAsyncFeatureSpecLike$ResultOfIgnoreInvocation;
         6: areturn
      LineNumberTable:
        line 235: 0
      LocalVariableTable:
        Start  Length  Slot  Name   Signature
            0       7     0 $this   Lorg/scalatest/featurespec/FixtureAsyncFeatureSpecLike;
            0       7     1 specText   Ljava/lang/String;
            0       7     2 testTags   Lscala/collection/immutable/Seq;
    MethodParameters:
      Name                           Flags
      $this                          final synthetic
      specText                       final
      testTags                       final

  public default org.scalatest.featurespec.FixtureAsyncFeatureSpecLike$ResultOfIgnoreInvocation ignore(java.lang.String, scala.collection.immutable.Seq<org.scalatest.Tag>);
    descriptor: (Ljava/lang/String;Lscala/collection/immutable/Seq;)Lorg/scalatest/featurespec/FixtureAsyncFeatureSpecLike$ResultOfIgnoreInvocation;
    flags: (0x0001) ACC_PUBLIC
    Code:
      stack=5, locals=3, args_size=3
         0: new           #43                 // class org/scalatest/featurespec/FixtureAsyncFeatureSpecLike$ResultOfIgnoreInvocation
         3: dup
         4: aload_0
         5: aload_1
         6: aload_2
         7: invokespecial #221                // Method org/scalatest/featurespec/FixtureAsyncFeatureSpecLike$ResultOfIgnoreInvocation."<init>":(Lorg/scalatest/featurespec/FixtureAsyncFeatureSpecLike;Ljava/lang/String;Lscala/collection/immutable/Seq;)V
        10: areturn
      LineNumberTable:
        line 236: 0
      LocalVariableTable:
        Start  Length  Slot  Name   Signature
            0      11     0  this   Lorg/scalatest/featurespec/FixtureAsyncFeatureSpecLike;
            0      11     1 specText   Ljava/lang/String;
            0      11     2 testTags   Lscala/collection/immutable/Seq;
    Signature: #220                         // (Ljava/lang/String;Lscala/collection/immutable/Seq<Lorg/scalatest/Tag;>;)Lorg/scalatest/featurespec/FixtureAsyncFeatureSpecLike$ResultOfIgnoreInvocation;
    MethodParameters:
      Name                           Flags
      specText                       final
      testTags                       final

  public static void feature$(org.scalatest.featurespec.FixtureAsyncFeatureSpecLike, java.lang.String, scala.Function0, org.scalactic.source.Position);
    descriptor: (Lorg/scalatest/featurespec/FixtureAsyncFeatureSpecLike;Ljava/lang/String;Lscala/Function0;Lorg/scalactic/source/Position;)V
    flags: (0x1009) ACC_PUBLIC, ACC_STATIC, ACC_SYNTHETIC
    Code:
      stack=4, locals=4, args_size=4
         0: aload_0
         1: aload_1
         2: aload_2
         3: aload_3
         4: invokespecial #229                // InterfaceMethod feature:(Ljava/lang/String;Lscala/Function0;Lorg/scalactic/source/Position;)V
         7: return
      LineNumberTable:
        line 248: 0
      LocalVariableTable:
        Start  Length  Slot  Name   Signature
            0       8     0 $this   Lorg/scalatest/featurespec/FixtureAsyncFeatureSpecLike;
            0       8     1 description   Ljava/lang/String;
            0       8     2   fun   Lscala/Function0;
            0       8     3   pos   Lorg/scalactic/source/Position;
    MethodParameters:
      Name                           Flags
      $this                          final synthetic
      description                    final
      fun                            final
      pos                            final

  public default void feature(java.lang.String, scala.Function0<scala.runtime.BoxedUnit>, org.scalactic.source.Position);
    descriptor: (Ljava/lang/String;Lscala/Function0;Lorg/scalactic/source/Position;)V
    flags: (0x0001) ACC_PUBLIC
    Code:
      stack=4, locals=4, args_size=4
         0: aload_0
         1: aload_1
         2: aload_2
         3: aload_3
         4: invokespecial #234                // InterfaceMethod FeatureImpl:(Ljava/lang/String;Lscala/Function0;Lorg/scalactic/source/Position;)V
         7: return
      LineNumberTable:
        line 248: 0
      LocalVariableTable:
        Start  Length  Slot  Name   Signature
            0       8     0  this   Lorg/scalatest/featurespec/FixtureAsyncFeatureSpecLike;
            0       8     1 description   Ljava/lang/String;
            0       8     2   fun   Lscala/Function0;
            0       8     3   pos   Lorg/scalactic/source/Position;
    Signature: #231                         // (Ljava/lang/String;Lscala/Function0<Lscala/runtime/BoxedUnit;>;Lorg/scalactic/source/Position;)V
    Deprecated: true
    MethodParameters:
      Name                           Flags
      description                    final
      fun                            final
      pos                            final

  private void FeatureImpl(java.lang.String, scala.Function0<scala.runtime.BoxedUnit>, org.scalactic.source.Position);
    descriptor: (Ljava/lang/String;Lscala/Function0;Lorg/scalactic/source/Position;)V
    flags: (0x0002) ACC_PRIVATE
    Code:
      stack=7, locals=12, args_size=4
         0: aload_0
         1: invokeinterface #70,  1           // InterfaceMethod org$scalatest$featurespec$FixtureAsyncFeatureSpecLike$$engine:()Lorg/scalatest/AsyncFixtureEngine;
         6: invokevirtual #240                // Method org/scalatest/AsyncFixtureEngine.currentBranchIsTrunk:()Z
         9: ifne          30
        12: new           #242                // class org/scalatest/exceptions/NotAllowedException
        15: dup
        16: getstatic     #131                // Field org/scalatest/Resources$.MODULE$:Lorg/scalatest/Resources$;
        19: invokevirtual #245                // Method org/scalatest/Resources$.cantNestFeatureClauses:()Ljava/lang/String;
        22: getstatic     #169                // Field scala/None$.MODULE$:Lscala/None$;
        25: aload_3
        26: invokespecial #248                // Method org/scalatest/exceptions/NotAllowedException."<init>":(Ljava/lang/String;Lscala/Option;Lorg/scalactic/source/Position;)V
        29: athrow
        30: aload_0
        31: invokeinterface #70,  1           // InterfaceMethod org$scalatest$featurespec$FixtureAsyncFeatureSpecLike$$engine:()Lorg/scalatest/AsyncFixtureEngine;
        36: getstatic     #131                // Field org/scalatest/Resources$.MODULE$:Lorg/scalatest/Resources$;
        39: aload_1
        40: invokevirtual #137                // Method java/lang/String.trim:()Ljava/lang/String;
        43: invokevirtual #250                // Method org/scalatest/Resources$.feature:(Ljava/lang/Object;)Ljava/lang/String;
        46: getstatic     #169                // Field scala/None$.MODULE$:Lscala/None$;
        49: aload_2
        50: invokedynamic #255,  0            // InvokeDynamic #2:apply:()Lscala/Function0;
        55: getstatic     #169                // Field scala/None$.MODULE$:Lscala/None$;
        58: aload_3
        59: invokevirtual #259                // Method org/scalatest/AsyncFixtureEngine.registerNestedBranch:(Ljava/lang/String;Lscala/Option;Lscala/Function0;Lscala/Function0;Lscala/Option;Lorg/scalactic/source/Position;)V
        62: goto          302
        65: astore        5
        67: aload         5
        69: astore        6
        71: aload         6
        73: instanceof    #261                // class org/scalatest/exceptions/TestFailedException
        76: ifeq          126
        79: aload         6
        81: checkcast     #261                // class org/scalatest/exceptions/TestFailedException
        84: astore        7
        86: new           #242                // class org/scalatest/exceptions/NotAllowedException
        89: dup
        90: getstatic     #266                // Field org/scalatest/FailureMessages$.MODULE$:Lorg/scalatest/FailureMessages$;
        93: invokevirtual #269                // Method org/scalatest/FailureMessages$.assertionShouldBePutInsideScenarioClauseNotFeatureClause:()Ljava/lang/String;
        96: new           #271                // class scala/Some
        99: dup
       100: aload         7
       102: invokespecial #274                // Method scala/Some."<init>":(Ljava/lang/Object;)V
       105: aload         7
       107: invokevirtual #278                // Method org/scalatest/exceptions/TestFailedException.position:()Lscala/Option;
       110: aload_3
       111: invokedynamic #288,  0            // InvokeDynamic #3:apply:(Lorg/scalactic/source/Position;)Lscala/Function0;
       116: invokevirtual #294                // Method scala/Option.getOrElse:(Lscala/Function0;)Ljava/lang/Object;
       119: checkcast     #296                // class org/scalactic/source/Position
       122: invokespecial #248                // Method org/scalatest/exceptions/NotAllowedException."<init>":(Ljava/lang/String;Lscala/Option;Lorg/scalactic/source/Position;)V
       125: athrow
       126: goto          129
       129: aload         6
       131: instanceof    #298                // class org/scalatest/exceptions/TestCanceledException
       134: ifeq          184
       137: aload         6
       139: checkcast     #298                // class org/scalatest/exceptions/TestCanceledException
       142: astore        8
       144: new           #242                // class org/scalatest/exceptions/NotAllowedException
       147: dup
       148: getstatic     #266                // Field org/scalatest/FailureMessages$.MODULE$:Lorg/scalatest/FailureMessages$;
       151: invokevirtual #269                // Method org/scalatest/FailureMessages$.assertionShouldBePutInsideScenarioClauseNotFeatureClause:()Ljava/lang/String;
       154: new           #271                // class scala/Some
       157: dup
       158: aload         8
       160: invokespecial #274                // Method scala/Some."<init>":(Ljava/lang/Object;)V
       163: aload         8
       165: invokevirtual #299                // Method org/scalatest/exceptions/TestCanceledException.position:()Lscala/Option;
       168: aload_3
       169: invokedynamic #304,  0            // InvokeDynamic #4:apply:(Lorg/scalactic/source/Position;)Lscala/Function0;
       174: invokevirtual #294                // Method scala/Option.getOrElse:(Lscala/Function0;)Ljava/lang/Object;
       177: checkcast     #296                // class org/scalactic/source/Position
       180: invokespecial #248                // Method org/scalatest/exceptions/NotAllowedException."<init>":(Ljava/lang/String;Lscala/Option;Lorg/scalactic/source/Position;)V
       183: athrow
       184: goto          187
       187: aload         6
       189: instanceof    #242                // class org/scalatest/exceptions/NotAllowedException
       192: ifeq          205
       195: aload         6
       197: checkcast     #242                // class org/scalatest/exceptions/NotAllowedException
       200: astore        9
       202: aload         9
       204: athrow
       205: goto          208
       208: aload         6
       210: ifnull        281
       213: aload         6
       215: astore        10
       217: getstatic     #309                // Field org/scalatest/Suite$.MODULE$:Lorg/scalatest/Suite$;
       220: aload         10
       222: invokevirtual #313                // Method org/scalatest/Suite$.anExceptionThatShouldCauseAnAbort:(Ljava/lang/Throwable;)Z
       225: ifne          278
       228: new           #242                // class org/scalatest/exceptions/NotAllowedException
       231: dup
       232: getstatic     #266                // Field org/scalatest/FailureMessages$.MODULE$:Lorg/scalatest/FailureMessages$;
       235: getstatic     #318                // Field org/scalactic/Prettifier$.MODULE$:Lorg/scalactic/Prettifier$;
       238: invokevirtual #322                // Method org/scalactic/Prettifier$.default:()Lorg/scalactic/Prettifier;
       241: getstatic     #327                // Field org/scalatest/UnquotedString$.MODULE$:Lorg/scalatest/UnquotedString$;
       244: aload         10
       246: invokevirtual #331                // Method java/lang/Throwable.getClass:()Ljava/lang/Class;
       249: invokevirtual #336                // Method java/lang/Class.getName:()Ljava/lang/String;
       252: invokevirtual #339                // Method org/scalatest/UnquotedString$.apply:(Ljava/lang/String;)Lorg/scalatest/UnquotedString;
       255: aload_1
       256: aload         10
       258: invokevirtual #342                // Method java/lang/Throwable.getMessage:()Ljava/lang/String;
       261: invokevirtual #346                // Method org/scalatest/FailureMessages$.exceptionWasThrownInFeatureClause:(Lorg/scalactic/Prettifier;Ljava/lang/Object;Ljava/lang/Object;Ljava/lang/Object;)Ljava/lang/String;
       264: new           #271                // class scala/Some
       267: dup
       268: aload         10
       270: invokespecial #274                // Method scala/Some."<init>":(Ljava/lang/Object;)V
       273: aload_3
       274: invokespecial #248                // Method org/scalatest/exceptions/NotAllowedException."<init>":(Ljava/lang/String;Lscala/Option;Lorg/scalactic/source/Position;)V
       277: athrow
       278: goto          284
       281: goto          284
       284: aload         6
       286: ifnull        296
       289: aload         6
       291: astore        11
       293: aload         11
       295: athrow
       296: goto          299
       299: aload         5
       301: athrow
       302: return
      Exception table:
         from    to  target type
            30    62    65   Class java/lang/Throwable
      StackMapTable: number_of_entries = 14
        frame_type = 30 /* same */
        frame_type = 98 /* same_locals_1_stack_item */
          stack = [ class java/lang/Throwable ]
        frame_type = 254 /* append */
          offset_delta = 60
          locals = [ top, class java/lang/Throwable, class java/lang/Throwable ]
        frame_type = 2 /* same */
        frame_type = 54 /* same */
        frame_type = 2 /* same */
        frame_type = 17 /* same */
        frame_type = 2 /* same */
        frame_type = 255 /* full_frame */
          offset_delta = 69
          locals = [ class org/scalatest/featurespec/FixtureAsyncFeatureSpecLike, class java/lang/String, class scala/Function0, class org/scalactic/source/Position, top, class java/lang/Throwable, class java/lang/Throwable, top, top, top, class java/lang/Throwable ]
          stack = []
        frame_type = 255 /* full_frame */
          offset_delta = 2
          locals = [ class org/scalatest/featurespec/FixtureAsyncFeatureSpecLike, class java/lang/String, class scala/Function0, class org/scalactic/source/Position, top, class java/lang/Throwable, class java/lang/Throwable ]
          stack = []
        frame_type = 2 /* same */
        frame_type = 11 /* same */
        frame_type = 2 /* same */
        frame_type = 248 /* chop */
          offset_delta = 2
      LineNumberTable:
        line 255: 0
        line 256: 12
        line 259: 30
        line 262: 67
        line 262: 71
        line 263: 129
        line 264: 187
        line 265: 208
        line 266: 284
        line 258: 299
      LocalVariableTable:
        Start  Length  Slot  Name   Signature
            0     303     0  this   Lorg/scalatest/featurespec/FixtureAsyncFeatureSpecLike;
            0     303     1 description   Ljava/lang/String;
            0     303     2   fun   Lscala/Function0;
            0     303     3   pos   Lorg/scalactic/source/Position;
    Signature: #231                         // (Ljava/lang/String;Lscala/Function0<Lscala/runtime/BoxedUnit;>;Lorg/scalactic/source/Position;)V
    MethodParameters:
      Name                           Flags
      description                    final
      fun                            final
      pos                            final

  public static void Feature$(org.scalatest.featurespec.FixtureAsyncFeatureSpecLike, java.lang.String, scala.Function0, org.scalactic.source.Position);
    descriptor: (Lorg/scalatest/featurespec/FixtureAsyncFeatureSpecLike;Ljava/lang/String;Lscala/Function0;Lorg/scalactic/source/Position;)V
    flags: (0x1009) ACC_PUBLIC, ACC_STATIC, ACC_SYNTHETIC
    Code:
      stack=4, locals=4, args_size=4
         0: aload_0
         1: aload_1
         2: aload_2
         3: aload_3
         4: invokespecial #352                // InterfaceMethod Feature:(Ljava/lang/String;Lscala/Function0;Lorg/scalactic/source/Position;)V
         7: return
      LineNumberTable:
        line 279: 0
      LocalVariableTable:
        Start  Length  Slot  Name   Signature
            0       8     0 $this   Lorg/scalatest/featurespec/FixtureAsyncFeatureSpecLike;
            0       8     1 description   Ljava/lang/String;
            0       8     2   fun   Lscala/Function0;
            0       8     3   pos   Lorg/scalactic/source/Position;
    MethodParameters:
      Name                           Flags
      $this                          final synthetic
      description                    final
      fun                            final
      pos                            final

  public default void Feature(java.lang.String, scala.Function0<scala.runtime.BoxedUnit>, org.scalactic.source.Position);
    descriptor: (Ljava/lang/String;Lscala/Function0;Lorg/scalactic/source/Position;)V
    flags: (0x0001) ACC_PUBLIC
    Code:
      stack=4, locals=4, args_size=4
         0: aload_0
         1: aload_1
         2: aload_2
         3: aload_3
         4: invokespecial #234                // InterfaceMethod FeatureImpl:(Ljava/lang/String;Lscala/Function0;Lorg/scalactic/source/Position;)V
         7: return
      LineNumberTable:
        line 280: 0
      LocalVariableTable:
        Start  Length  Slot  Name   Signature
            0       8     0  this   Lorg/scalatest/featurespec/FixtureAsyncFeatureSpecLike;
            0       8     1 description   Ljava/lang/String;
            0       8     2   fun   Lscala/Function0;
            0       8     3   pos   Lorg/scalactic/source/Position;
    Signature: #231                         // (Ljava/lang/String;Lscala/Function0<Lscala/runtime/BoxedUnit;>;Lorg/scalactic/source/Position;)V
    MethodParameters:
      Name                           Flags
      description                    final
      fun                            final
      pos                            final

  public static scala.collection.immutable.Map tags$(org.scalatest.featurespec.FixtureAsyncFeatureSpecLike);
    descriptor: (Lorg/scalatest/featurespec/FixtureAsyncFeatureSpecLike;)Lscala/collection/immutable/Map;
    flags: (0x1009) ACC_PUBLIC, ACC_STATIC, ACC_SYNTHETIC
    Code:
      stack=1, locals=1, args_size=1
         0: aload_0
         1: invokespecial #358                // InterfaceMethod tags:()Lscala/collection/immutable/Map;
         4: areturn
      LineNumberTable:
        line 301: 0
      LocalVariableTable:
        Start  Length  Slot  Name   Signature
            0       5     0 $this   Lorg/scalatest/featurespec/FixtureAsyncFeatureSpecLike;
    MethodParameters:
      Name                           Flags
      $this                          final synthetic

  public default scala.collection.immutable.Map<java.lang.String, scala.collection.immutable.Set<java.lang.String>> tags();
    descriptor: ()Lscala/collection/immutable/Map;
    flags: (0x0001) ACC_PUBLIC
    Code:
      stack=3, locals=1, args_size=1
         0: getstatic     #309                // Field org/scalatest/Suite$.MODULE$:Lorg/scalatest/Suite$;
         3: aload_0
         4: invokeinterface #70,  1           // InterfaceMethod org$scalatest$featurespec$FixtureAsyncFeatureSpecLike$$engine:()Lorg/scalatest/AsyncFixtureEngine;
         9: invokevirtual #362                // Method org/scalatest/AsyncFixtureEngine.atomic:()Ljava/util/concurrent/atomic/AtomicReference;
        12: invokevirtual #82                 // Method java/util/concurrent/atomic/AtomicReference.get:()Ljava/lang/Object;
        15: checkcast     #30                 // class org/scalatest/AsyncSuperEngine$Bundle
        18: invokevirtual #365                // Method org/scalatest/AsyncSuperEngine$Bundle.tagsMap:()Lscala/collection/immutable/Map;
        21: aload_0
        22: invokevirtual #369                // Method org/scalatest/Suite$.autoTagClassAnnotations:(Lscala/collection/immutable/Map;Lorg/scalatest/Suite;)Lscala/collection/immutable/Map;
        25: areturn
      LineNumberTable:
        line 301: 0
      LocalVariableTable:
        Start  Length  Slot  Name   Signature
            0      26     0  this   Lorg/scalatest/featurespec/FixtureAsyncFeatureSpecLike;
    Signature: #359                         // ()Lscala/collection/immutable/Map<Ljava/lang/String;Lscala/collection/immutable/Set<Ljava/lang/String;>;>;

  public static org.scalatest.Status runTest$(org.scalatest.featurespec.FixtureAsyncFeatureSpecLike, java.lang.String, org.scalatest.Args);
    descriptor: (Lorg/scalatest/featurespec/FixtureAsyncFeatureSpecLike;Ljava/lang/String;Lorg/scalatest/Args;)Lorg/scalatest/Status;
    flags: (0x1009) ACC_PUBLIC, ACC_STATIC, ACC_SYNTHETIC
    Code:
      stack=3, locals=3, args_size=3
         0: aload_0
         1: aload_1
         2: aload_2
         3: invokespecial #375                // InterfaceMethod runTest:(Ljava/lang/String;Lorg/scalatest/Args;)Lorg/scalatest/Status;
         6: areturn
      LineNumberTable:
        line 315: 0
      LocalVariableTable:
        Start  Length  Slot  Name   Signature
            0       7     0 $this   Lorg/scalatest/featurespec/FixtureAsyncFeatureSpecLike;
            0       7     1 testName   Ljava/lang/String;
            0       7     2  args   Lorg/scalatest/Args;
    MethodParameters:
      Name                           Flags
      $this                          final synthetic
      testName                       final
      args                           final

  public default org.scalatest.Status runTest(java.lang.String, org.scalatest.Args);
    descriptor: (Ljava/lang/String;Lorg/scalatest/Args;)Lorg/scalatest/Status;
    flags: (0x0001) ACC_PUBLIC
    Code:
      stack=9, locals=3, args_size=3
         0: aload_0
         1: invokeinterface #70,  1           // InterfaceMethod org$scalatest$featurespec$FixtureAsyncFeatureSpecLike$$engine:()Lorg/scalatest/AsyncFixtureEngine;
         6: aload_0
         7: aload_1
         8: aload_2
         9: iconst_1
        10: aload_0
        11: invokeinterface #379,  1          // InterfaceMethod parallelAsyncTestExecution:()Z
        16: aload_0
        17: aload_2
        18: aload_1
        19: invokedynamic #391,  0            // InvokeDynamic #5:apply:(Lorg/scalatest/featurespec/FixtureAsyncFeatureSpecLike;Lorg/scalatest/Args;Ljava/lang/String;)Lscala/Function2;
        24: aload_0
        25: invokeinterface #395,  1          // InterfaceMethod executionContext:()Lscala/concurrent/ExecutionContext;
        30: invokevirtual #399                // Method org/scalatest/AsyncFixtureEngine.runTestImpl:(Lorg/scalatest/Suite;Ljava/lang/String;Lorg/scalatest/Args;ZZLscala/Function2;Lscala/concurrent/ExecutionContext;)Lorg/scalatest/Status;
        33: areturn
      LineNumberTable:
        line 338: 0
      LocalVariableTable:
        Start  Length  Slot  Name   Signature
            0      34     0  this   Lorg/scalatest/featurespec/FixtureAsyncFeatureSpecLike;
            0      34     1 testName   Ljava/lang/String;
            0      34     2  args   Lorg/scalatest/Args;
    MethodParameters:
      Name                           Flags
      testName                       final
      args                           final

  public static org.scalatest.Status runTests$(org.scalatest.featurespec.FixtureAsyncFeatureSpecLike, scala.Option, org.scalatest.Args);
    descriptor: (Lorg/scalatest/featurespec/FixtureAsyncFeatureSpecLike;Lscala/Option;Lorg/scalatest/Args;)Lorg/scalatest/Status;
    flags: (0x1009) ACC_PUBLIC, ACC_STATIC, ACC_SYNTHETIC
    Code:
      stack=3, locals=3, args_size=3
         0: aload_0
         1: aload_1
         2: aload_2
         3: invokespecial #404                // InterfaceMethod runTests:(Lscala/Option;Lorg/scalatest/Args;)Lorg/scalatest/Status;
         6: areturn
      LineNumberTable:
        line 380: 0
      LocalVariableTable:
        Start  Length  Slot  Name   Signature
            0       7     0 $this   Lorg/scalatest/featurespec/FixtureAsyncFeatureSpecLike;
            0       7     1 testName   Lscala/Option;
            0       7     2  args   Lorg/scalatest/Args;
    MethodParameters:
      Name                           Flags
      $this                          final synthetic
      testName                       final
      args                           final

  public default org.scalatest.Status runTests(scala.Option<java.lang.String>, org.scalatest.Args);
    descriptor: (Lscala/Option;Lorg/scalatest/Args;)Lorg/scalatest/Status;
    flags: (0x0001) ACC_PUBLIC
    Code:
      stack=7, locals=3, args_size=3
         0: aload_0
         1: invokeinterface #70,  1           // InterfaceMethod org$scalatest$featurespec$FixtureAsyncFeatureSpecLike$$engine:()Lorg/scalatest/AsyncFixtureEngine;
         6: aload_0
         7: aload_1
         8: aload_2
         9: iconst_0
        10: aload_0
        11: invokeinterface #379,  1          // InterfaceMethod parallelAsyncTestExecution:()Z
        16: aload_0
        17: invokedynamic #414,  0            // InvokeDynamic #6:apply:(Lorg/scalatest/featurespec/FixtureAsyncFeatureSpecLike;)Lscala/Function2;
        22: invokevirtual #418                // Method org/scalatest/AsyncFixtureEngine.runTestsImpl:(Lorg/scalatest/Suite;Lscala/Option;Lorg/scalatest/Args;ZZLscala/Function2;)Lorg/scalatest/Status;
        25: areturn
      LineNumberTable:
        line 381: 0
      LocalVariableTable:
        Start  Length  Slot  Name   Signature
            0      26     0  this   Lorg/scalatest/featurespec/FixtureAsyncFeatureSpecLike;
            0      26     1 testName   Lscala/Option;
            0      26     2  args   Lorg/scalatest/Args;
    Signature: #406                         // (Lscala/Option<Ljava/lang/String;>;Lorg/scalatest/Args;)Lorg/scalatest/Status;
    MethodParameters:
      Name                           Flags
      testName                       final
      args                           final

  public static scala.collection.immutable.Set testNames$(org.scalatest.featurespec.FixtureAsyncFeatureSpecLike);
    descriptor: (Lorg/scalatest/featurespec/FixtureAsyncFeatureSpecLike;)Lscala/collection/immutable/Set;
    flags: (0x1009) ACC_PUBLIC, ACC_STATIC, ACC_SYNTHETIC
    Code:
      stack=1, locals=1, args_size=1
         0: aload_0
         1: invokespecial #424                // InterfaceMethod testNames:()Lscala/collection/immutable/Set;
         4: areturn
      LineNumberTable:
        line 398: 0
      LocalVariableTable:
        Start  Length  Slot  Name   Signature
            0       5     0 $this   Lorg/scalatest/featurespec/FixtureAsyncFeatureSpecLike;
    MethodParameters:
      Name                           Flags
      $this                          final synthetic

  public default scala.collection.immutable.Set<java.lang.String> testNames();
    descriptor: ()Lscala/collection/immutable/Set;
    flags: (0x0001) ACC_PUBLIC
    Code:
      stack=2, locals=1, args_size=1
         0: getstatic     #430                // Field org/scalatest/InsertionOrderSet$.MODULE$:Lorg/scalatest/InsertionOrderSet$;
         3: aload_0
         4: invokeinterface #70,  1           // InterfaceMethod org$scalatest$featurespec$FixtureAsyncFeatureSpecLike$$engine:()Lorg/scalatest/AsyncFixtureEngine;
         9: invokevirtual #362                // Method org/scalatest/AsyncFixtureEngine.atomic:()Ljava/util/concurrent/atomic/AtomicReference;
        12: invokevirtual #82                 // Method java/util/concurrent/atomic/AtomicReference.get:()Ljava/lang/Object;
        15: checkcast     #30                 // class org/scalatest/AsyncSuperEngine$Bundle
        18: invokevirtual #434                // Method org/scalatest/AsyncSuperEngine$Bundle.testNamesList:()Lscala/collection/immutable/List;
        21: invokevirtual #437                // Method org/scalatest/InsertionOrderSet$.apply:(Lscala/collection/immutable/List;)Lscala/collection/immutable/Set;
        24: areturn
      LineNumberTable:
        line 399: 0
      LocalVariableTable:
        Start  Length  Slot  Name   Signature
            0      25     0  this   Lorg/scalatest/featurespec/FixtureAsyncFeatureSpecLike;
    Signature: #425                         // ()Lscala/collection/immutable/Set<Ljava/lang/String;>;

  public static org.scalatest.Status run$(org.scalatest.featurespec.FixtureAsyncFeatureSpecLike, scala.Option, org.scalatest.Args);
    descriptor: (Lorg/scalatest/featurespec/FixtureAsyncFeatureSpecLike;Lscala/Option;Lorg/scalatest/Args;)Lorg/scalatest/Status;
    flags: (0x1009) ACC_PUBLIC, ACC_STATIC, ACC_SYNTHETIC
    Code:
      stack=3, locals=3, args_size=3
         0: aload_0
         1: aload_1
         2: aload_2
         3: invokespecial #441                // InterfaceMethod run:(Lscala/Option;Lorg/scalatest/Args;)Lorg/scalatest/Status;
         6: areturn
      LineNumberTable:
        line 402: 0
      LocalVariableTable:
        Start  Length  Slot  Name   Signature
            0       7     0 $this   Lorg/scalatest/featurespec/FixtureAsyncFeatureSpecLike;
            0       7     1 testName   Lscala/Option;
            0       7     2  args   Lorg/scalatest/Args;
    MethodParameters:
      Name                           Flags
      $this                          final synthetic
      testName                       final
      args                           final

  public default org.scalatest.Status run(scala.Option<java.lang.String>, org.scalatest.Args);
    descriptor: (Lscala/Option;Lorg/scalatest/Args;)Lorg/scalatest/Status;
    flags: (0x0001) ACC_PUBLIC
    Code:
      stack=6, locals=3, args_size=3
         0: aload_0
         1: invokeinterface #70,  1           // InterfaceMethod org$scalatest$featurespec$FixtureAsyncFeatureSpecLike$$engine:()Lorg/scalatest/AsyncFixtureEngine;
         6: aload_0
         7: aload_1
         8: aload_2
         9: aload_0
        10: invokeinterface #379,  1          // InterfaceMethod parallelAsyncTestExecution:()Z
        15: aload_0
        16: invokedynamic #447,  0            // InvokeDynamic #7:apply:(Lorg/scalatest/featurespec/FixtureAsyncFeatureSpecLike;)Lscala/Function2;
        21: invokevirtual #451                // Method org/scalatest/AsyncFixtureEngine.runImpl:(Lorg/scalatest/Suite;Lscala/Option;Lorg/scalatest/Args;ZLscala/Function2;)Lorg/scalatest/Status;
        24: areturn
      LineNumberTable:
        line 403: 0
      LocalVariableTable:
        Start  Length  Slot  Name   Signature
            0      25     0  this   Lorg/scalatest/featurespec/FixtureAsyncFeatureSpecLike;
            0      25     1 testName   Lscala/Option;
            0      25     2  args   Lorg/scalatest/Args;
    Signature: #406                         // (Lscala/Option<Ljava/lang/String;>;Lorg/scalatest/Args;)Lorg/scalatest/Status;
    MethodParameters:
      Name                           Flags
      testName                       final
      args                           final

  public static void scenariosFor$(org.scalatest.featurespec.FixtureAsyncFeatureSpecLike, scala.runtime.BoxedUnit);
    descriptor: (Lorg/scalatest/featurespec/FixtureAsyncFeatureSpecLike;Lscala/runtime/BoxedUnit;)V
    flags: (0x1009) ACC_PUBLIC, ACC_STATIC, ACC_SYNTHETIC
    Code:
      stack=2, locals=2, args_size=2
         0: aload_0
         1: aload_1
         2: invokespecial #458                // InterfaceMethod scenariosFor:(Lscala/runtime/BoxedUnit;)V
         5: return
      LineNumberTable:
        line 415: 0
      LocalVariableTable:
        Start  Length  Slot  Name   Signature
            0       6     0 $this   Lorg/scalatest/featurespec/FixtureAsyncFeatureSpecLike;
            0       6     1  unit   Lscala/runtime/BoxedUnit;
    MethodParameters:
      Name                           Flags
      $this                          final synthetic
      unit                           final

  public default void scenariosFor(scala.runtime.BoxedUnit);
    descriptor: (Lscala/runtime/BoxedUnit;)V
    flags: (0x0001) ACC_PUBLIC
    Code:
      stack=2, locals=2, args_size=2
         0: aload_0
         1: aload_1
         2: invokeinterface #462,  2          // InterfaceMethod ScenariosFor:(Lscala/runtime/BoxedUnit;)V
         7: return
      LineNumberTable:
        line 415: 0
      LocalVariableTable:
        Start  Length  Slot  Name   Signature
            0       8     0  this   Lorg/scalatest/featurespec/FixtureAsyncFeatureSpecLike;
            0       8     1  unit   Lscala/runtime/BoxedUnit;
    Deprecated: true
    MethodParameters:
      Name                           Flags
      unit                           final

  public static void ScenariosFor$(org.scalatest.featurespec.FixtureAsyncFeatureSpecLike, scala.runtime.BoxedUnit);
    descriptor: (Lorg/scalatest/featurespec/FixtureAsyncFeatureSpecLike;Lscala/runtime/BoxedUnit;)V
    flags: (0x1009) ACC_PUBLIC, ACC_STATIC, ACC_SYNTHETIC
    Code:
      stack=2, locals=2, args_size=2
         0: aload_0
         1: aload_1
         2: invokespecial #462                // InterfaceMethod ScenariosFor:(Lscala/runtime/BoxedUnit;)V
         5: return
      LineNumberTable:
        line 437: 0
      LocalVariableTable:
        Start  Length  Slot  Name   Signature
            0       6     0 $this   Lorg/scalatest/featurespec/FixtureAsyncFeatureSpecLike;
            0       6     1  unit   Lscala/runtime/BoxedUnit;
    MethodParameters:
      Name                           Flags
      $this                          final synthetic
      unit                           final

  public default void ScenariosFor(scala.runtime.BoxedUnit);
    descriptor: (Lscala/runtime/BoxedUnit;)V
    flags: (0x0001) ACC_PUBLIC
    Code:
      stack=0, locals=2, args_size=2
         0: return
      LineNumberTable:
        line 437: 0
      LocalVariableTable:
        Start  Length  Slot  Name   Signature
            0       1     0  this   Lorg/scalatest/featurespec/FixtureAsyncFeatureSpecLike;
            0       1     1  unit   Lscala/runtime/BoxedUnit;
    MethodParameters:
      Name                           Flags
      unit                           final

  public static scala.Function1 convertPendingToFixtureFunction$(org.scalatest.featurespec.FixtureAsyncFeatureSpecLike, scala.Function0);
    descriptor: (Lorg/scalatest/featurespec/FixtureAsyncFeatureSpecLike;Lscala/Function0;)Lscala/Function1;
    flags: (0x1009) ACC_PUBLIC, ACC_STATIC, ACC_SYNTHETIC
    Code:
      stack=2, locals=2, args_size=2
         0: aload_0
         1: aload_1
         2: invokespecial #470                // InterfaceMethod convertPendingToFixtureFunction:(Lscala/Function0;)Lscala/Function1;
         5: areturn
      LineNumberTable:
        line 454: 0
      LocalVariableTable:
        Start  Length  Slot  Name   Signature
            0       6     0 $this   Lorg/scalatest/featurespec/FixtureAsyncFeatureSpecLike;
            0       6     1     f   Lscala/Function0;
    MethodParameters:
      Name                           Flags
      $this                          final synthetic
      f                              final

  public default scala.Function1<java.lang.Object, org.scalatest.compatible.Assertion> convertPendingToFixtureFunction(scala.Function0<org.scalatest.PendingStatement>);
    descriptor: (Lscala/Function0;)Lscala/Function1;
    flags: (0x0001) ACC_PUBLIC
    Code:
      stack=1, locals=2, args_size=2
         0: aload_1
         1: invokedynamic #482,  0            // InvokeDynamic #8:apply:(Lscala/Function0;)Lscala/Function1;
         6: areturn
      LineNumberTable:
        line 455: 0
      LocalVariableTable:
        Start  Length  Slot  Name   Signature
            0       7     0  this   Lorg/scalatest/featurespec/FixtureAsyncFeatureSpecLike;
            0       7     1     f   Lscala/Function0;
    Signature: #471                         // (Lscala/Function0<Lorg/scalatest/PendingStatement;>;)Lscala/Function1<Ljava/lang/Object;Lorg/scalatest/compatible/Assertion;>;
    MethodParameters:
      Name                           Flags
      f                              final

  public abstract java.lang.String styleName();
    descriptor: ()Ljava/lang/String;
    flags: (0x0401) ACC_PUBLIC, ACC_ABSTRACT
    Deprecated: true

  public static org.scalatest.TestData testDataFor$(org.scalatest.featurespec.FixtureAsyncFeatureSpecLike, java.lang.String, org.scalatest.ConfigMap);
    descriptor: (Lorg/scalatest/featurespec/FixtureAsyncFeatureSpecLike;Ljava/lang/String;Lorg/scalatest/ConfigMap;)Lorg/scalatest/TestData;
    flags: (0x1009) ACC_PUBLIC, ACC_STATIC, ACC_SYNTHETIC
    Code:
      stack=3, locals=3, args_size=3
         0: aload_0
         1: aload_1
         2: aload_2
         3: invokespecial #490                // InterfaceMethod testDataFor:(Ljava/lang/String;Lorg/scalatest/ConfigMap;)Lorg/scalatest/TestData;
         6: areturn
      LineNumberTable:
        line 483: 0
      LocalVariableTable:
        Start  Length  Slot  Name   Signature
            0       7     0 $this   Lorg/scalatest/featurespec/FixtureAsyncFeatureSpecLike;
            0       7     1 testName   Ljava/lang/String;
            0       7     2 theConfigMap   Lorg/scalatest/ConfigMap;
    MethodParameters:
      Name                           Flags
      $this                          final synthetic
      testName                       final
      theConfigMap                   final

  public default org.scalatest.TestData testDataFor(java.lang.String, org.scalatest.ConfigMap);
    descriptor: (Ljava/lang/String;Lorg/scalatest/ConfigMap;)Lorg/scalatest/TestData;
    flags: (0x0001) ACC_PUBLIC
    Code:
      stack=4, locals=3, args_size=3
         0: aload_0
         1: invokeinterface #70,  1           // InterfaceMethod org$scalatest$featurespec$FixtureAsyncFeatureSpecLike$$engine:()Lorg/scalatest/AsyncFixtureEngine;
         6: aload_1
         7: aload_2
         8: aload_0
         9: invokevirtual #495                // Method org/scalatest/AsyncFixtureEngine.createTestDataFor:(Ljava/lang/String;Lorg/scalatest/ConfigMap;Lorg/scalatest/Suite;)Lorg/scalatest/TestData;
        12: areturn
      LineNumberTable:
        line 483: 0
      LocalVariableTable:
        Start  Length  Slot  Name   Signature
            0      13     0  this   Lorg/scalatest/featurespec/FixtureAsyncFeatureSpecLike;
            0      13     1 testName   Ljava/lang/String;
            0      13     2 theConfigMap   Lorg/scalatest/ConfigMap;
    MethodParameters:
      Name                           Flags
      testName                       final
      theConfigMap                   final

  public static org.scalatest.ConfigMap testDataFor$default$2$(org.scalatest.featurespec.FixtureAsyncFeatureSpecLike);
    descriptor: (Lorg/scalatest/featurespec/FixtureAsyncFeatureSpecLike;)Lorg/scalatest/ConfigMap;
    flags: (0x1009) ACC_PUBLIC, ACC_STATIC, ACC_SYNTHETIC
    Code:
      stack=1, locals=1, args_size=1
         0: aload_0
         1: invokespecial #501                // InterfaceMethod testDataFor$default$2:()Lorg/scalatest/ConfigMap;
         4: areturn
      LineNumberTable:
        line 483: 0
      LocalVariableTable:
        Start  Length  Slot  Name   Signature
            0       5     0 $this   Lorg/scalatest/featurespec/FixtureAsyncFeatureSpecLike;
    MethodParameters:
      Name                           Flags
      $this                          final synthetic

  public default org.scalatest.ConfigMap testDataFor$default$2();
    descriptor: ()Lorg/scalatest/ConfigMap;
    flags: (0x0001) ACC_PUBLIC
    Code:
      stack=1, locals=1, args_size=1
         0: getstatic     #506                // Field org/scalatest/ConfigMap$.MODULE$:Lorg/scalatest/ConfigMap$;
         3: invokevirtual #509                // Method org/scalatest/ConfigMap$.empty:()Lorg/scalatest/ConfigMap;
         6: areturn
      LineNumberTable:
        line 483: 0
      LocalVariableTable:
        Start  Length  Slot  Name   Signature
            0       7     0  this   Lorg/scalatest/featurespec/FixtureAsyncFeatureSpecLike;

  public static java.lang.String $anonfun$engine$1();
    descriptor: ()Ljava/lang/String;
    flags: (0x1009) ACC_PUBLIC, ACC_STATIC, ACC_SYNTHETIC
    Code:
      stack=1, locals=0, args_size=0
         0: getstatic     #131                // Field org/scalatest/Resources$.MODULE$:Lorg/scalatest/Resources$;
         3: invokevirtual #513                // Method org/scalatest/Resources$.concurrentFeatureSpecMod:()Ljava/lang/String;
         6: areturn
      LineNumberTable:
        line 55: 0

  public static java.lang.String $anonfun$registerAsyncTestImpl$1();
    descriptor: ()Ljava/lang/String;
    flags: (0x1009) ACC_PUBLIC, ACC_STATIC, ACC_SYNTHETIC
    Code:
      stack=1, locals=0, args_size=0
         0: getstatic     #131                // Field org/scalatest/Resources$.MODULE$:Lorg/scalatest/Resources$;
         3: invokevirtual #516                // Method org/scalatest/Resources$.testCannotBeNestedInsideAnotherTest:()Ljava/lang/String;
         6: areturn
      LineNumberTable:
        line 102: 0

  public static java.lang.String $anonfun$registerIgnoredAsyncTestImpl$1();
    descriptor: ()Ljava/lang/String;
    flags: (0x1009) ACC_PUBLIC, ACC_STATIC, ACC_SYNTHETIC
    Code:
      stack=1, locals=0, args_size=0
         0: getstatic     #131                // Field org/scalatest/Resources$.MODULE$:Lorg/scalatest/Resources$;
         3: invokevirtual #516                // Method org/scalatest/Resources$.testCannotBeNestedInsideAnotherTest:()Ljava/lang/String;
         6: areturn
      LineNumberTable:
        line 115: 0

  public static java.lang.String $anonfun$FeatureImpl$1();
    descriptor: ()Ljava/lang/String;
    flags: (0x1009) ACC_PUBLIC, ACC_STATIC, ACC_SYNTHETIC
    Code:
      stack=1, locals=0, args_size=0
         0: getstatic     #131                // Field org/scalatest/Resources$.MODULE$:Lorg/scalatest/Resources$;
         3: invokevirtual #519                // Method org/scalatest/Resources$.featureCannotAppearInsideAScenario:()Ljava/lang/String;
         6: areturn
      LineNumberTable:
        line 259: 0

  public static org.scalactic.source.Position $anonfun$FeatureImpl$2(org.scalactic.source.Position);
    descriptor: (Lorg/scalactic/source/Position;)Lorg/scalactic/source/Position;
    flags: (0x1009) ACC_PUBLIC, ACC_STATIC, ACC_SYNTHETIC
    Code:
      stack=1, locals=1, args_size=1
         0: aload_0
         1: areturn
      LineNumberTable:
        line 262: 0
      LocalVariableTable:
        Start  Length  Slot  Name   Signature
            0       2     0 pos$1   Lorg/scalactic/source/Position;
    MethodParameters:
      Name                           Flags
      pos$1                          final

  public static org.scalactic.source.Position $anonfun$FeatureImpl$3(org.scalactic.source.Position);
    descriptor: (Lorg/scalactic/source/Position;)Lorg/scalactic/source/Position;
    flags: (0x1009) ACC_PUBLIC, ACC_STATIC, ACC_SYNTHETIC
    Code:
      stack=1, locals=1, args_size=1
         0: aload_0
         1: areturn
      LineNumberTable:
        line 263: 0
      LocalVariableTable:
        Start  Length  Slot  Name   Signature
            0       2     0 pos$1   Lorg/scalactic/source/Position;
    MethodParameters:
      Name                           Flags
      pos$1                          final

  private org.scalatest.AsyncOutcome invokeWithAsyncFixture$1(org.scalatest.AsyncSuperEngine$TestLeaf, scala.Function1, org.scalatest.Args, java.lang.String);
    descriptor: (Lorg/scalatest/AsyncSuperEngine$TestLeaf;Lscala/Function1;Lorg/scalatest/Args;Ljava/lang/String;)Lorg/scalatest/AsyncOutcome;
    flags: (0x0002) ACC_PRIVATE
    Code:
      stack=8, locals=7, args_size=5
         0: aload_3
         1: invokevirtual #531                // Method org/scalatest/Args.configMap:()Lorg/scalatest/ConfigMap;
         4: astore        5
         6: aload_0
         7: aload         4
         9: aload         5
        11: invokeinterface #490,  3          // InterfaceMethod testDataFor:(Ljava/lang/String;Lorg/scalatest/ConfigMap;)Lorg/scalatest/TestData;
        16: astore        6
        18: new           #533                // class org/scalatest/FutureAsyncOutcome
        21: dup
        22: aload_0
        23: new           #41                 // class org/scalatest/featurespec/FixtureAsyncFeatureSpecLike$$anon$1
        26: dup
        27: aload_0
        28: aload         6
        30: aload_1
        31: invokespecial #536                // Method org/scalatest/featurespec/FixtureAsyncFeatureSpecLike$$anon$1."<init>":(Lorg/scalatest/featurespec/FixtureAsyncFeatureSpecLike;Lorg/scalatest/TestData;Lorg/scalatest/AsyncSuperEngine$TestLeaf;)V
        34: invokeinterface #540,  2          // InterfaceMethod withFixture:(Lorg/scalatest/FixtureAsyncTestSuite$OneArgAsyncTest;)Lorg/scalatest/FutureOutcome;
        39: invokevirtual #546                // Method org/scalatest/FutureOutcome.underlying:()Lscala/concurrent/Future;
        42: aload_2
        43: aload_0
        44: invokeinterface #395,  1          // InterfaceMethod executionContext:()Lscala/concurrent/ExecutionContext;
        49: invokespecial #549                // Method org/scalatest/FutureAsyncOutcome."<init>":(Lscala/concurrent/Future;Lscala/Function1;Lscala/concurrent/ExecutionContext;)V
        52: areturn
      LineNumberTable:
        line 317: 0
        line 318: 6
        line 319: 18
        line 320: 22
        line 321: 23
        line 334: 42
        line 319: 43
      LocalVariableTable:
        Start  Length  Slot  Name   Signature
            6      46     5 theConfigMap   Lorg/scalatest/ConfigMap;
           18      34     6 testData   Lorg/scalatest/TestData;
            0      53     0  this   Lorg/scalatest/featurespec/FixtureAsyncFeatureSpecLike;
            0      53     1 theTest   Lorg/scalatest/AsyncSuperEngine$TestLeaf;
            0      53     2 onCompleteFun   Lscala/Function1;
            0      53     3 args$1   Lorg/scalatest/Args;
            0      53     4 testName$1   Ljava/lang/String;
    MethodParameters:
      Name                           Flags
      theTest                        final
      onCompleteFun                  final
      args$1                         final
      testName$1                     final

  public static org.scalatest.AsyncOutcome $anonfun$runTest$1(org.scalatest.featurespec.FixtureAsyncFeatureSpecLike, org.scalatest.Args, java.lang.String, org.scalatest.AsyncSuperEngine$TestLeaf, scala.Function1);
    descriptor: (Lorg/scalatest/featurespec/FixtureAsyncFeatureSpecLike;Lorg/scalatest/Args;Ljava/lang/String;Lorg/scalatest/AsyncSuperEngine$TestLeaf;Lscala/Function1;)Lorg/scalatest/AsyncOutcome;
    flags: (0x1009) ACC_PUBLIC, ACC_STATIC, ACC_SYNTHETIC
    Code:
      stack=5, locals=5, args_size=5
         0: aload_0
         1: aload_3
         2: aload         4
         4: aload_1
         5: aload_2
         6: invokespecial #554                // InterfaceMethod invokeWithAsyncFixture$1:(Lorg/scalatest/AsyncSuperEngine$TestLeaf;Lscala/Function1;Lorg/scalatest/Args;Ljava/lang/String;)Lorg/scalatest/AsyncOutcome;
         9: areturn
      LineNumberTable:
        line 338: 0
      LocalVariableTable:
        Start  Length  Slot  Name   Signature
            0      10     0 $this   Lorg/scalatest/featurespec/FixtureAsyncFeatureSpecLike;
            0      10     1 args$1   Lorg/scalatest/Args;
            0      10     2 testName$1   Ljava/lang/String;
            0      10     3 theTest   Lorg/scalatest/AsyncSuperEngine$TestLeaf;
            0      10     4 onCompleteFun   Lscala/Function1;
    MethodParameters:
      Name                           Flags
      $this                          final synthetic
      args$1                         final
      testName$1                     final
      theTest                        final
      onCompleteFun                  final

  public static org.scalatest.Status $anonfun$runTests$1(org.scalatest.featurespec.FixtureAsyncFeatureSpecLike, java.lang.String, org.scalatest.Args);
    descriptor: (Lorg/scalatest/featurespec/FixtureAsyncFeatureSpecLike;Ljava/lang/String;Lorg/scalatest/Args;)Lorg/scalatest/Status;
    flags: (0x1009) ACC_PUBLIC, ACC_STATIC, ACC_SYNTHETIC
    Code:
      stack=3, locals=3, args_size=3
         0: aload_0
         1: aload_1
         2: aload_2
         3: invokeinterface #375,  3          // InterfaceMethod runTest:(Ljava/lang/String;Lorg/scalatest/Args;)Lorg/scalatest/Status;
         8: areturn
      LineNumberTable:
        line 381: 0
      LocalVariableTable:
        Start  Length  Slot  Name   Signature
            0       9     0 $this   Lorg/scalatest/featurespec/FixtureAsyncFeatureSpecLike;
            0       9     1 testName   Ljava/lang/String;
            0       9     2  args   Lorg/scalatest/Args;
    MethodParameters:
      Name                           Flags
      $this                          final synthetic
      testName                       final
      args                           final

  public static org.scalatest.Status $anonfun$run$1(org.scalatest.featurespec.FixtureAsyncFeatureSpecLike, scala.Option, org.scalatest.Args);
    descriptor: (Lorg/scalatest/featurespec/FixtureAsyncFeatureSpecLike;Lscala/Option;Lorg/scalatest/Args;)Lorg/scalatest/Status;
    flags: (0x1009) ACC_PUBLIC, ACC_STATIC, ACC_SYNTHETIC
    Code:
      stack=3, locals=3, args_size=3
         0: aload_0
         1: aload_1
         2: aload_2
         3: invokeinterface #556,  3          // InterfaceMethod org$scalatest$featurespec$FixtureAsyncFeatureSpecLike$$super$run:(Lscala/Option;Lorg/scalatest/Args;)Lorg/scalatest/Status;
         8: areturn
      LineNumberTable:
        line 403: 0
      LocalVariableTable:
        Start  Length  Slot  Name   Signature
            0       9     0 $this   Lorg/scalatest/featurespec/FixtureAsyncFeatureSpecLike;
            0       9     1 testName   Lscala/Option;
            0       9     2  args   Lorg/scalatest/Args;
    MethodParameters:
      Name                           Flags
      $this                          final synthetic
      testName                       final
      args                           final

  public static org.scalatest.Succeeded$ $anonfun$convertPendingToFixtureFunction$1(scala.Function0, java.lang.Object);
    descriptor: (Lscala/Function0;Ljava/lang/Object;)Lorg/scalatest/Succeeded$;
    flags: (0x1009) ACC_PUBLIC, ACC_STATIC, ACC_SYNTHETIC
    Code:
      stack=1, locals=2, args_size=2
         0: aload_0
         1: invokeinterface #560,  1          // InterfaceMethod scala/Function0.apply:()Ljava/lang/Object;
         6: pop
         7: getstatic     #565                // Field org/scalatest/Succeeded$.MODULE$:Lorg/scalatest/Succeeded$;
        10: areturn
      LineNumberTable:
        line 455: 0
      LocalVariableTable:
        Start  Length  Slot  Name   Signature
            0      11     0   f$1   Lscala/Function0;
            0      11     1 fixture   Ljava/lang/Object;
    MethodParameters:
      Name                           Flags
      f$1                            final
      fixture                        final

  public static void $init$(org.scalatest.featurespec.FixtureAsyncFeatureSpecLike);
    descriptor: (Lorg/scalatest/featurespec/FixtureAsyncFeatureSpecLike;)V
    flags: (0x0009) ACC_PUBLIC, ACC_STATIC
    Code:
      stack=5, locals=1, args_size=1
         0: aload_0
         1: new           #72                 // class org/scalatest/AsyncFixtureEngine
         4: dup
         5: invokedynamic #572,  0            // InvokeDynamic #9:apply:()Lscala/Function0;
        10: ldc_w         #574                // String FixtureFeatureSpec
        13: invokespecial #577                // Method org/scalatest/AsyncFixtureEngine."<init>":(Lscala/Function0;Ljava/lang/String;)V
        16: invokeinterface #579,  2          // InterfaceMethod org$scalatest$featurespec$FixtureAsyncFeatureSpecLike$_setter_$org$scalatest$featurespec$FixtureAsyncFeatureSpecLike$$engine_$eq:(Lorg/scalatest/AsyncFixtureEngine;)V
        21: aload_0
        22: ldc_w         #581                // String org.scalatest.fixture.FeatureSpec
        25: invokeinterface #583,  2          // InterfaceMethod org$scalatest$featurespec$FixtureAsyncFeatureSpecLike$_setter_$styleName_$eq:(Ljava/lang/String;)V
        30: return
      LineNumberTable:
        line 55: 0
        line 481: 21
        line 53: 30
      LocalVariableTable:
        Start  Length  Slot  Name   Signature
            0      31     0 $this   Lorg/scalatest/featurespec/FixtureAsyncFeatureSpecLike;
    MethodParameters:
      Name                           Flags
      $this                          final synthetic

  private static java.lang.Object $deserializeLambda$(java.lang.invoke.SerializedLambda);
    descriptor: (Ljava/lang/invoke/SerializedLambda;)Ljava/lang/Object;
    flags: (0x100a) ACC_PRIVATE, ACC_STATIC, ACC_SYNTHETIC
    Code:
      stack=1, locals=1, args_size=1
         0: aload_0
         1: invokedynamic #595,  0            // InvokeDynamic #10:lambdaDeserialize:(Ljava/lang/invoke/SerializedLambda;)Ljava/lang/Object;
         6: areturn
}
InnerClasses:
  public static final #28= #25 of #27;    // Lookup=class java/lang/invoke/MethodHandles$Lookup of class java/lang/invoke/MethodHandles
  public #33= #30 of #32;                 // Bundle=class org/scalatest/AsyncSuperEngine$Bundle of class org/scalatest/AsyncSuperEngine
  public #36= #35 of #32;                 // TestLeaf=class org/scalatest/AsyncSuperEngine$TestLeaf of class org/scalatest/AsyncSuperEngine
  public #39= #38 of #6;                  // OneArgAsyncTest=class org/scalatest/FixtureAsyncTestSuite$OneArgAsyncTest of class org/scalatest/FixtureAsyncTestSuite
  public final #41;                       // class org/scalatest/featurespec/FixtureAsyncFeatureSpecLike$$anon$1
  public #44= #43 of #2;                  // ResultOfIgnoreInvocation=class org/scalatest/featurespec/FixtureAsyncFeatureSpecLike$ResultOfIgnoreInvocation of class org/scalatest/featurespec/FixtureAsyncFeatureSpecLike
  public #47= #46 of #2;                  // ResultOfScenarioInvocation=class org/scalatest/featurespec/FixtureAsyncFeatureSpecLike$ResultOfScenarioInvocation of class org/scalatest/featurespec/FixtureAsyncFeatureSpecLike
SourceFile: "FixtureAsyncFeatureSpecLike.scala"
RuntimeVisibleAnnotations:
  0: #18(#19=[s#20])
    org.scalatest.Finders(
      value=["org.scalatest.finders.FeatureSpecFinder"]
    )
  1: #21(#22=s#23)
    scala.reflect.ScalaSignature(
      bytes="\u0006\u0005\tmhaB\u0017/!\u0003\r\t!\u000e\u0005\u0006\u001f\u0002!\t\u0001\u0015\u0005\b)\u0002\u0011\r\u0011\"\u0004V\u0011\u0015y\u0006\u0001\"\u0005a\u0011\u0015!\u0007\u0001\"\u0005f\u0011\u0015I\u0007\u0001\"\u0005k\u0011\u0015q\u0007\u0001\"\u0005p\u0011\u0015\u0019\b\u0001\"\u0004u\u0011\u001d\ti\u0005\u0001C\u0003\u0003\u001fBq!!\u0018\u0001\t\u001b\ty\u0006C\u0004\u0002l\u0001!)!!\u001c\u0007\r\u0005m\u0004\u0001AA?\u0011)\tyh\u0003B\u0001B\u0003%\u0011q\u0005\u0005\u000b\u0003\u007fY!\u0011!Q\u0001\n\u0005\u0005\u0003bBAA\u0017\u0011\u0005\u00111\u0011\u0005\b\u0003\u0017[A\u0011AAG\u0011\u001d\t\u0019j\u0003C\u0001\u0003+Cq!a#\f\t\u001b\ti\nC\u0004\u0002\u0014.!\t!!+\t\u000f\u0005E\u0006\u0001\"\u0005\u00024\"9\u0011Q\u001a\u0001\u0005\u0012\u0005=gABAk\u0001\u0001\t9\u000e\u0003\u0006\u0002\u0000U\u0011\t\u0011)A\u0005\u0003OA!\"a\u0010\u0016\u0005\u0003\u0005\u000b\u0011BA!\u0011\u001d\t\t)\u0006C\u0001\u00033Dq!a#\u0016\t\u001b\t\t\u000fC\u0004\u0002\u0014V!\t!a:\t\u000f\u0005-U\u0003\"\u0004\u0002p\"9\u00111S\u000b\u0005\u0002\u0005U\bbBA\u007f\u0001\u0011E\u0011q \u0005\b\u0005\u000b\u0001A\u0011\u0003B\u0004\u0011\u001d\u0011\u0019\u0003\u0001C\u0007\u0005KAqAa\f\u0001\t#\u0011\t\u0004C\u0004\u0003>\u0001!\tEa\u0010\t\u000f\t5\u0003\u0001\"\u0015\u0003P!9!Q\r\u0001\u0005R\t\u001d\u0004b\u0002B:\u0001\u0011\u0005#Q\u000f\u0005\b\u0005o\u0002A\u0011\tB=\u0011\u001d\u0011y\b\u0001C\t\u0005\u0003CqA!$\u0001\t#\u0011y\tC\u0004\u0003\u0014\u0002!\u0019B!&\t\u0013\t\u0015\u0006A1A\u0005F\t\u001d\u0006b\u0002BX\u0001\u0011\u0005#\u0011\u0017\u0005\n\u0005\u000b\u0004\u0011\u0013!C\u0001\u0005\u000fDaB!8\u0001!\u0003\r\t\u0011!C\u0005\u0005?\u0014)OA\u000eGSb$XO]3Bgft7MR3biV\u0014Xm\u00159fG2K7.\u001a\u0006\u0003_A\n1BZ3biV\u0014Xm\u001d9fG*\u0011\u0011GM\u0001\ng\u000e\fG.\u0019;fgRT\u0011aM\u0001\u0004_J<7\u0001A\n\t\u0001Yb\u0004i\u0011$J\u0019B\u0011qGO\u0007\u0002q)\t\u0011(A\u0003tG\u0006d\u0017-\u0003\u0002<q\t1\u0011I\\=SK\u001a\u0004\"!\u0010 \u000e\u0003AJ!a\u0010\u0019\u0003+\u0019K\u0007\u0010^;sK\u0006\u001b\u0018P\\2UKN$8+^5uKB\u0011Q(Q\u0005\u0003\u0005B\u0012ADR5yiV\u0014X-Q:z]\u000e$Vm\u001d;SK\u001eL7\u000f\u001e:bi&|g\u000e\u0005\u0002>\t&\u0011Q\t\r\u0002\n\u0013:4wN]7j]\u001e\u0004\"!P$\n\u0005!\u0003$!\u0003(pi&4\u00170\u001b8h!\ti$*\u0003\u0002La\tA\u0011\t\\3si&tw\r\u0005\u0002>\u001b&\u0011a\n\r\u0002\f\t>\u001cW/\\3oi&tw-\u0001\u0004%S:LG\u000f\n\u000b\u0002#B\u0011qGU\u0005\u0003\'b\u0012A!\u00168ji\u00061QM\\4j]\u0016,\u0012A\u0016\t\u0004{]K\u0016B\u0001-1\u0005I\t5/\u001f8d\r&DH/\u001e:f\u000b:<\u0017N\\3\u0011\u0005i[V\"\u0001\u0001\n\u0005qk&\u0001\u0004$jqR,(/\u001a)be\u0006l\u0017B\u000101\u000511\u0015\u000e\u001f;ve\u0016\u001cV/\u001b;f\u0003\u0011IgNZ8\u0016\u0003\u0005\u0004\"!\u00102\n\u0005\r\u0004$\u0001C%oM>\u0014X.\u001a:\u0002\t9|G/Z\u000b\u0002MB\u0011QhZ\u0005\u0003QB\u0012\u0001BT8uS\u001aLWM]\u0001\u0006C2,\'\u000f^\u000b\u0002WB\u0011Q\b\\\u0005\u0003[B\u0012q!\u00117feR,\'/\u0001\u0004nCJ\\W\u000f]\u000b\u0002aB\u0011Q(]\u0005\u0003eB\u0012!\u0002R8dk6,g\u000e^3s\u0003U\u0011XmZ5ti\u0016\u0014\u0018i]=oGR+7\u000f^%na2$R!^A\u0012\u0003{!B!\u0015<\u0002\u0010!)qo\u0002a\u0001q\u00069A/Z:u\rVt\u0007\u0003B\u001cz3nL!A\u001f\u001d\u0003\u0013\u0019+hn\u0019;j_:\f\u0004\u0003\u0002?\u0000\u0003\u0007i\u0011! \u0006\u0003}b\n!bY8oGV\u0014(/\u001a8u\u0013\r\t\t! \u0002\u0007\rV$XO]3\u0011\t\u0005\u0015\u00111B\u0007\u0003\u0003\u000fQ1!!\u00031\u0003)\u0019w.\u001c9bi&\u0014G.Z\u0005\u0005\u0003\u001b\t9AA\u0005BgN,\'\u000f^5p]\"9\u0011\u0011C\u0004A\u0002\u0005M\u0011a\u00019pgB!\u0011QCA\u0010\u001b\t\t9B\u0003\u0003\u0002\u001a\u0005m\u0011AB:pkJ\u001cWMC\u0002\u0002\u001eI\n\u0011b]2bY\u0006\u001cG/[2\n\t\u0005\u0005\u0012q\u0003\u0002\t!>\u001c\u0018\u000e^5p]\"9\u0011QE\u0004A\u0002\u0005\u001d\u0012\u0001\u0003;fgR$V\r\u001f;\u0011\t\u0005%\u0012q\u0007\b\u0005\u0003W\t\u0019\u0004E\u0002\u0002.aj!!a\f\u000b\u0007\u0005EB\'\u0001\u0004=e>|GOP\u0005\u0004\u0003kA\u0014A\u0002)sK\u0012,g-\u0003\u0003\u0002:\u0005m\"AB*ue&twMC\u0002\u00026aBq!a\u0010\b\u0001\u0004\t\t%\u0001\u0005uKN$H+Y4t!\u00159\u00141IA$\u0013\r\t)\u0005\u000f\u0002\u000byI,\u0007/Z1uK\u0012t\u0004cA\u001f\u0002J%\u0019\u00111\n\u0019\u0003\u0007Q\u000bw-A\tsK\u001eL7\u000f^3s\u0003NLhn\u0019+fgR$b!!\u0015\u0002Z\u0005mC\u0003BA*\u0003/\"2!UA+\u0011\u001d\t\t\u0002\u0003a\u0002\u0003\'AQa\u001e\u0005A\u0002aDq!!\n\t\u0001\u0004\t9\u0003C\u0004\u0002@!\u0001\r!!\u0011\u00029I,w-[:uKJLuM\\8sK\u0012\f5/\u001f8d)\u0016\u001cH/S7qYR1\u0011\u0011MA4\u0003S\"R!UA2\u0003KBQa^\u0005A\u0002aDq!!\u0005\n\u0001\u0004\t\u0019\u0002C\u0004\u0002&%\u0001\r!a\n\t\u000f\u0005}\u0012\u00021\u0001\u0002B\u0005A\"/Z4jgR,\'/S4o_J,G-Q:z]\u000e$Vm\u001d;\u0015\r\u0005=\u0014qOA=)\u0011\t\t(!\u001e\u0015\u0007E\u000b\u0019\bC\u0004\u0002\u0012)\u0001\u001d!a\u0005\t\u000b]T\u0001\u0019\u0001=\t\u000f\u0005\u0015\"\u00021\u0001\u0002(!9\u0011q\b\u0006A\u0002\u0005\u0005#A\u0007*fgVdGo\u00144TG\u0016t\u0017M]5p\u0013:4xnY1uS>t7CA\u00067\u0003!\u0019\b/Z2UKb$\u0018A\u0002\u001fj]&$h\b\u0006\u0004\u0002\u0006\u0006\u001d\u0015\u0011\u0012\t\u00035.Aq!a \u000f\u0001\u0004\t9\u0003C\u0004\u0002@9\u0001\r!!\u0011\u0002\u0013\u0005\u0004\b\u000f\\=J[BdG#B)\u0002\u0010\u0006E\u0005\"B<\u0010\u0001\u0004A\bbBA\t\u001f\u0001\u0007\u00111C\u0001\u0006CB\u0004H.\u001f\u000b\u0005\u0003/\u000bY\nF\u0002R\u00033Cq!!\u0005\u0011\u0001\b\t\u0019\u0002C\u0003x!\u0001\u0007\u0001\u0010F\u0003R\u0003?\u000b9\u000b\u0003\u0004x#\u0001\u0007\u0011\u0011\u0015\t\u0005o\u0005\r60C\u0002\u0002&b\u0012\u0011BR;oGRLwN\u001c\u0019\t\u000f\u0005E\u0011\u00031\u0001\u0002\u0014Q!\u00111VAX)\r\t\u0016Q\u0016\u0005\b\u0003#\u0011\u00029AA\n\u0011\u00199(\u00031\u0001\u0002\"\u0006A1oY3oCJLw\u000e\u0006\u0004\u0002\u0006\u0006U\u0016q\u0017\u0005\b\u0003\u007f\u001a\u0002\u0019AA\u0014\u0011\u001d\tyd\u0005a\u0001\u0003\u0003B3bEA^\u0003\u0003\f\u0019-a2\u0002JB\u0019q\'!0\n\u0007\u0005}\u0006H\u0001\u0006eKB\u0014XmY1uK\u0012\fq!\\3tg\u0006<W-\t\u0002\u0002F\u0006\u0011)\u0005\u00165fAM\u001cWM\\1sS>\u0004\u0003f\u001d;beRLgn\u001a\u0011xSRD\u0007\u0005\\8xKJ\u001c\u0017m]3!OM<\u0013\u0006I7fi\"|G\r\t5bg\u0002\u0012W-\u001a8!I\u0016\u0004(/Z2bi\u0016$\u0007%\u00198eA]LG\u000e\u001c\u0011cK\u0002\u0012X-\\8wK\u0012\u0004\u0013N\u001c\u0011bA\u0019,H/\u001e:fAY,\'o]5p]\u0002zg\rI*dC2\fG+Z:u]\u0001\u0002F.Z1tK\u0002*8/\u001a\u0011TG\u0016t\u0017M]5pA!\u001aH/\u0019:uS:<\u0007e^5uQ\u0002\ng\u000eI;qa\u0016\u00148-Y:fA\u001d\u001av%\u000b\u0011j]N$X-\u00193/AQC\u0017n\u001d\u0011dC:\u0004#-\u001a\u0011sK^\u0014\u0018\u000e\u001e;f]\u0002\nW\u000f^8nCRL7-\u00197ms\u0002:\u0018\u000e\u001e5!CV$xNZ5yu\u0001BG\u000f\u001e9tu=zs-\u001b;ik\nt3m\\70g\u000e\fG.\u0019;fgR|\u0013-\u001e;pM&Dx\u0006\u001e:fK>j\u0017m\u001d;fe>\u001ad&\r\u0018y\u0003\u0015\u0019\u0018N\\2fC\t\tY-A\u00034]Er\u0003\'\u0001\u0005TG\u0016t\u0017M]5p)\u0019\t))!5\u0002T\"9\u0011q\u0010\u000bA\u0002\u0005\u001d\u0002bBA )\u0001\u0007\u0011\u0011\t\u0002\u0019%\u0016\u001cX\u000f\u001c;PM&;gn\u001c:f\u0013:4xnY1uS>t7CA\u000b7)\u0019\tY.!8\u0002`B\u0011!,\u0006\u0005\b\u0003\u007fB\u0002\u0019AA\u0014\u0011\u001d\ty\u0004\u0007a\u0001\u0003\u0003\"R!UAr\u0003KDQa^\rA\u0002aDq!!\u0005\u001a\u0001\u0004\t\u0019\u0002\u0006\u0003\u0002j\u00065HcA)\u0002l\"9\u0011\u0011\u0003\u000eA\u0004\u0005M\u0001\"B<\u001b\u0001\u0004AH#B)\u0002r\u0006M\bBB<\u001c\u0001\u0004\t\t\u000bC\u0004\u0002\u0012m\u0001\r!a\u0005\u0015\t\u0005]\u00181 \u000b\u0004#\u0006e\bbBA\t9\u0001\u000f\u00111\u0003\u0005\u0007or\u0001\r!!)\u0002\r%<gn\u001c:f)\u0019\tYN!\u0001\u0003\u0004!9\u0011qP\u000fA\u0002\u0005\u001d\u0002bBA ;\u0001\u0007\u0011\u0011I\u0001\bM\u0016\fG/\u001e:f)\u0011\u0011IA!\u0007\u0015\t\t-!q\u0002\u000b\u0004#\n5\u0001bBA\t=\u0001\u000f\u00111\u0003\u0005\t\u0005#qB\u00111\u0001\u0003\u0014\u0005\u0019a-\u001e8\u0011\t]\u0012)\"U\u0005\u0004\u0005/A$\u0001\u0003\u001fcs:\fW.\u001a \t\u000f\tma\u00041\u0001\u0002(\u0005YA-Z:de&\u0004H/[8oQ-q\u00121XAa\u0005?\t9-!3\"\u0005\t\u0005\u0012A!\u0011UQ\u0016\u0004c-Z1ukJ,\u0007\u0005K:uCJ$\u0018N\\4!o&$\b\u000e\t7po\u0016\u00148-Y:fA\u001d2w%\u000b\u0011nKRDw\u000e\u001a\u0011iCN\u0004#-Z3oA\u0011,\u0007O]3dCR,G\rI1oI\u0002:\u0018\u000e\u001c7!E\u0016\u0004#/Z7pm\u0016$\u0007%\u001b8!C\u00022W\u000f^;sK\u00022XM]:j_:\u0004sN\u001a\u0011TG\u0006d\u0017\rV3ti:\u0002\u0003\u000b\\3bg\u0016\u0004So]3!\r\u0016\fG/\u001e:fA!\u001aH/\u0019:uS:<\u0007e^5uQ\u0002\ng\u000eI;qa\u0016\u00148-Y:fA\u001d2u%\u000b\u0011j]N$X-\u00193/AQC\u0017n\u001d\u0011dC:\u0004#-\u001a\u0011sK^\u0014\u0018\u000e\u001e;f]\u0002\nW\u000f^8nCRL7-\u00197ms\u0002:\u0018\u000e\u001e5!CV$xNZ5yu\u0001BG\u000f\u001e9tu=zs-\u001b;ik\nt3m\\70g\u000e\fG.\u0019;fgR|\u0013-\u001e;pM&Dx\u0006\u001e:fK>j\u0017m\u001d;fe>\u001ad&\r\u0018y\u0003-1U-\u0019;ve\u0016LU\u000e\u001d7\u0015\t\t\u001d\"Q\u0006\u000b\u0006#\n%\"1\u0006\u0005\t\u0005#yB\u00111\u0001\u0003\u0014!9\u0011\u0011C\u0010A\u0002\u0005M\u0001b\u0002B\u000e?\u0001\u0007\u0011qE\u0001\b\r\u0016\fG/\u001e:f)\u0011\u0011\u0019Da\u000f\u0015\t\tU\"\u0011\b\u000b\u0004#\n]\u0002bBA\tA\u0001\u000f\u00111\u0003\u0005\t\u0005#\u0001C\u00111\u0001\u0003\u0014!9!1\u0004\u0011A\u0002\u0005\u001d\u0012\u0001\u0002;bON,\"A!\u0011\u0011\u0011\u0005%\"1IA\u0014\u0005\u000fJAA!\u0012\u0002<\t\u0019Q*\u00199\u0011\r\u0005%\"\u0011JA\u0014\u0013\u0011\u0011Y%a\u000f\u0003\u0007M+G/A\u0004sk:$Vm\u001d;\u0015\r\tE#q\u000bB.!\ri$1K\u0005\u0004\u0005+\u0002$AB*uCR,8\u000fC\u0004\u0003Z\t\u0002\r!a\n\u0002\u0011Q,7\u000f\u001e(b[\u0016DqA!\u0018#\u0001\u0004\u0011y&\u0001\u0003be\u001e\u001c\bcA\u001f\u0003b%\u0019!1\r\u0019\u0003\t\u0005\u0013xm]\u0001\teVtG+Z:ugR1!\u0011\u000bB5\u0005cBqA!\u0017$\u0001\u0004\u0011Y\u0007E\u00038\u0005[\n9#C\u0002\u0003pa\u0012aa\u00149uS>t\u0007b\u0002B/G\u0001\u0007!qL\u0001\ni\u0016\u001cHOT1nKN,\"Aa\u0012\u0002\u0007I,h\u000e\u0006\u0004\u0003R\tm$Q\u0010\u0005\b\u00053*\u0003\u0019\u0001B6\u0011\u001d\u0011i&\na\u0001\u0005?\nAb]2f]\u0006\u0014\u0018n\\:G_J$2!\u0015BB\u0011\u0019\u0011)I\na\u0001#\u0006!QO\\5uQ-1\u00131XAa\u0005\u0013\u000b9-!3\"\u0005\t-\u0015A!\u0016UQ\u0016\u00043oY3oCJLwn\u001d$pe\u0002B3\u000f^1si&tw\rI<ji\"\u0004Cn\\<fe\u000e\f7/\u001a\u0011(g\u001eJ\u0003%\\3uQ>$\u0007\u0005[1tA\t,WM\u001c\u0011eKB\u0014XmY1uK\u0012\u0004\u0013M\u001c3!o&dG\u000e\t2fAI,Wn\u001c<fI\u0002Jg\u000eI1!MV$XO]3!m\u0016\u00148/[8oA=4\u0007eU2bY\u0006$Vm\u001d;/AAcW-Y:fAU\u001cX\rI*dK:\f\'/[8t\r>\u0014\b\u0005K:uCJ$\u0018N\\4!o&$\b\u000eI1oAU\u0004\b/\u001a:dCN,\u0007eJ*(S\u0001Jgn\u001d;fC\u0012t\u0003\u0005\u00165jg\u0002\u001a\u0017M\u001c\u0011cK\u0002\u0012Xm\u001e:jiR,g\u000eI1vi>l\u0017\r^5dC2d\u0017\u0010I<ji\"\u0004\u0013-\u001e;pM&D(\b\t5uiB\u001c(hL\u0018hSRDWO\u0019\u0018d_6|3oY1mCR,7\u000f^\u0018bkR|g-\u001b=0iJ,WmL7bgR,\'oL\u001a/c9B\u0018\u0001D*dK:\f\'/[8t\r>\u0014HcA)\u0003\u0012\"1!QQ\u0014A\u0002E\u000bqdY8om\u0016\u0014H\u000fU3oI&tw\rV8GSb$XO]3Gk:\u001cG/[8o)\u0011\u00119J!\'\u0011\u000b]J\u0018,a\u0001\t\u0011\tm\u0005\u0006\"a\u0001\u0005;\u000b\u0011A\u001a\t\u0006o\tU!q\u0014\t\u0004{\t\u0005\u0016b\u0001BRa\t\u0001\u0002+\u001a8eS:<7\u000b^1uK6,g\u000e^\u0001\ngRLH.\u001a(b[\u0016,\"!a\n)\u0017%\nY,!1\u0003,\u0006\u001d\u0017\u0011Z\u0011\u0003\u0005[\u000bA\u0010\u00165fAM$\u0018\u0010\\3OC6,\u0007\u0005\\5gK\u000eL8\r\\3![\u0016$\bn\u001c3!Q\u0006\u001c\bEY3f]\u0002\"W\r\u001d:fG\u0006$X\r\u001a\u0011b]\u0012\u0004s/\u001b7mA\t,\u0007E]3n_Z,G\rI5oA\u0005\u0004c-\u001e;ve\u0016\u0004c/\u001a:tS>t\u0007e\u001c4!\'\u000e\fG.\u0019+fgR\u0004s/\u001b;iA9|\u0007E]3qY\u0006\u001cW-\\3oi:\n1\u0002^3ti\u0012\u000bG/\u0019$peR1!1\u0017B]\u0005w\u00032!\u0010B[\u0013\r\u00119\f\r\u0002\t)\u0016\u001cH\u000fR1uC\"9!\u0011\f\u0016A\u0002\u0005\u001d\u0002\"\u0003B_UA\u0005\t\u0019\u0001B`\u00031!\b.Z\"p]\u001aLw-T1q!\ri$\u0011Y\u0005\u0004\u0005\u0007\u0004$!C\"p]\u001aLw-T1q\u0003U!Xm\u001d;ECR\fgi\u001c:%I\u00164\u0017-\u001e7uII*\"A!3+\t\t}&1Z\u0016\u0003\u0005\u001b\u0004BAa4\u0003Z6\u0011!\u0011\u001b\u0006\u0005\u0005\'\u0014).A\u0005v]\u000eDWmY6fI*\u0019!q\u001b\u001d\u0002\u0015\u0005tgn\u001c;bi&|g.\u0003\u0003\u0003\\\nE\'!E;oG\",7m[3e-\u0006\u0014\u0018.\u00198dK\u0006I1/\u001e9fe\u0012\u0012XO\u001c\u000b\u0007\u0005#\u0012\tOa9\t\u000f\teC\u00061\u0001\u0003l!9!Q\f\u0017A\u0002\t}\u0013\u0002\u0002B<\u0005OL1A!;1\u0005\u0015\u0019V/\u001b;fQ\u001d\u0001!Q\u001eBz\u0005k\u00042!\u0010Bx\u0013\r\u0011\t\u0010\r\u0002\b\r&tG-\u001a:t\u0003\u00151\u0018\r\\;fY\t\u001190\t\u0002\u0003z\u00069sN]4/g\u000e\fG.\u0019;fgRtc-\u001b8eKJ\u001chFR3biV\u0014Xm\u00159fG\u001aKg\u000eZ3s\u0001"
    )
BootstrapMethods:
  0: #160 REF_invokeStatic java/lang/invoke/LambdaMetafactory.altMetafactory:(Ljava/lang/invoke/MethodHandles$Lookup;Ljava/lang/String;Ljava/lang/invoke/MethodType;[Ljava/lang/Object;)Ljava/lang/invoke/CallSite;
    Method arguments:
      #146 ()Ljava/lang/Object;
      #150 REF_invokeStatic org/scalatest/featurespec/FixtureAsyncFeatureSpecLike.$anonfun$registerAsyncTestImpl$1:()Ljava/lang/String;
      #151 ()Ljava/lang/String;
      #152 5
      #153 1
      #151 ()Ljava/lang/String;
  1: #160 REF_invokeStatic java/lang/invoke/LambdaMetafactory.altMetafactory:(Ljava/lang/invoke/MethodHandles$Lookup;Ljava/lang/String;Ljava/lang/invoke/MethodType;[Ljava/lang/Object;)Ljava/lang/invoke/CallSite;
    Method arguments:
      #146 ()Ljava/lang/Object;
      #188 REF_invokeStatic org/scalatest/featurespec/FixtureAsyncFeatureSpecLike.$anonfun$registerIgnoredAsyncTestImpl$1:()Ljava/lang/String;
      #151 ()Ljava/lang/String;
      #152 5
      #153 1
      #151 ()Ljava/lang/String;
  2: #160 REF_invokeStatic java/lang/invoke/LambdaMetafactory.altMetafactory:(Ljava/lang/invoke/MethodHandles$Lookup;Ljava/lang/String;Ljava/lang/invoke/MethodType;[Ljava/lang/Object;)Ljava/lang/invoke/CallSite;
    Method arguments:
      #146 ()Ljava/lang/Object;
      #254 REF_invokeStatic org/scalatest/featurespec/FixtureAsyncFeatureSpecLike.$anonfun$FeatureImpl$1:()Ljava/lang/String;
      #151 ()Ljava/lang/String;
      #152 5
      #153 1
      #151 ()Ljava/lang/String;
  3: #160 REF_invokeStatic java/lang/invoke/LambdaMetafactory.altMetafactory:(Ljava/lang/invoke/MethodHandles$Lookup;Ljava/lang/String;Ljava/lang/invoke/MethodType;[Ljava/lang/Object;)Ljava/lang/invoke/CallSite;
    Method arguments:
      #146 ()Ljava/lang/Object;
      #283 REF_invokeStatic org/scalatest/featurespec/FixtureAsyncFeatureSpecLike.$anonfun$FeatureImpl$2:(Lorg/scalactic/source/Position;)Lorg/scalactic/source/Position;
      #285 ()Lorg/scalactic/source/Position;
      #152 5
      #153 1
      #285 ()Lorg/scalactic/source/Position;
  4: #160 REF_invokeStatic java/lang/invoke/LambdaMetafactory.altMetafactory:(Ljava/lang/invoke/MethodHandles$Lookup;Ljava/lang/String;Ljava/lang/invoke/MethodType;[Ljava/lang/Object;)Ljava/lang/invoke/CallSite;
    Method arguments:
      #146 ()Ljava/lang/Object;
      #303 REF_invokeStatic org/scalatest/featurespec/FixtureAsyncFeatureSpecLike.$anonfun$FeatureImpl$3:(Lorg/scalactic/source/Position;)Lorg/scalactic/source/Position;
      #285 ()Lorg/scalactic/source/Position;
      #152 5
      #153 1
      #285 ()Lorg/scalactic/source/Position;
  5: #160 REF_invokeStatic java/lang/invoke/LambdaMetafactory.altMetafactory:(Ljava/lang/invoke/MethodHandles$Lookup;Ljava/lang/String;Ljava/lang/invoke/MethodType;[Ljava/lang/Object;)Ljava/lang/invoke/CallSite;
    Method arguments:
      #381 (Ljava/lang/Object;Ljava/lang/Object;)Ljava/lang/Object;
      #386 REF_invokeStatic org/scalatest/featurespec/FixtureAsyncFeatureSpecLike.$anonfun$runTest$1:(Lorg/scalatest/featurespec/FixtureAsyncFeatureSpecLike;Lorg/scalatest/Args;Ljava/lang/String;Lorg/scalatest/AsyncSuperEngine$TestLeaf;Lscala/Function1;)Lorg/scalatest/AsyncOutcome;
      #388 (Lorg/scalatest/AsyncSuperEngine$TestLeaf;Lscala/Function1;)Lorg/scalatest/AsyncOutcome;
      #152 5
      #153 1
      #388 (Lorg/scalatest/AsyncSuperEngine$TestLeaf;Lscala/Function1;)Lorg/scalatest/AsyncOutcome;
  6: #160 REF_invokeStatic java/lang/invoke/LambdaMetafactory.altMetafactory:(Ljava/lang/invoke/MethodHandles$Lookup;Ljava/lang/String;Ljava/lang/invoke/MethodType;[Ljava/lang/Object;)Ljava/lang/invoke/CallSite;
    Method arguments:
      #381 (Ljava/lang/Object;Ljava/lang/Object;)Ljava/lang/Object;
      #410 REF_invokeStatic org/scalatest/featurespec/FixtureAsyncFeatureSpecLike.$anonfun$runTests$1:(Lorg/scalatest/featurespec/FixtureAsyncFeatureSpecLike;Ljava/lang/String;Lorg/scalatest/Args;)Lorg/scalatest/Status;
      #411 (Ljava/lang/String;Lorg/scalatest/Args;)Lorg/scalatest/Status;
      #152 5
      #153 1
      #411 (Ljava/lang/String;Lorg/scalatest/Args;)Lorg/scalatest/Status;
  7: #160 REF_invokeStatic java/lang/invoke/LambdaMetafactory.altMetafactory:(Ljava/lang/invoke/MethodHandles$Lookup;Ljava/lang/String;Ljava/lang/invoke/MethodType;[Ljava/lang/Object;)Ljava/lang/invoke/CallSite;
    Method arguments:
      #381 (Ljava/lang/Object;Ljava/lang/Object;)Ljava/lang/Object;
      #445 REF_invokeStatic org/scalatest/featurespec/FixtureAsyncFeatureSpecLike.$anonfun$run$1:(Lorg/scalatest/featurespec/FixtureAsyncFeatureSpecLike;Lscala/Option;Lorg/scalatest/Args;)Lorg/scalatest/Status;
      #446 (Lscala/Option;Lorg/scalatest/Args;)Lorg/scalatest/Status;
      #152 5
      #153 1
      #446 (Lscala/Option;Lorg/scalatest/Args;)Lorg/scalatest/Status;
  8: #160 REF_invokeStatic java/lang/invoke/LambdaMetafactory.altMetafactory:(Ljava/lang/invoke/MethodHandles$Lookup;Ljava/lang/String;Ljava/lang/invoke/MethodType;[Ljava/lang/Object;)Ljava/lang/invoke/CallSite;
    Method arguments:
      #473 (Ljava/lang/Object;)Ljava/lang/Object;
      #478 REF_invokeStatic org/scalatest/featurespec/FixtureAsyncFeatureSpecLike.$anonfun$convertPendingToFixtureFunction$1:(Lscala/Function0;Ljava/lang/Object;)Lorg/scalatest/Succeeded$;
      #480 (Ljava/lang/Object;)Lorg/scalatest/Succeeded$;
      #152 5
      #153 1
      #480 (Ljava/lang/Object;)Lorg/scalatest/Succeeded$;
  9: #160 REF_invokeStatic java/lang/invoke/LambdaMetafactory.altMetafactory:(Ljava/lang/invoke/MethodHandles$Lookup;Ljava/lang/String;Ljava/lang/invoke/MethodType;[Ljava/lang/Object;)Ljava/lang/invoke/CallSite;
    Method arguments:
      #146 ()Ljava/lang/Object;
      #571 REF_invokeStatic org/scalatest/featurespec/FixtureAsyncFeatureSpecLike.$anonfun$engine$1:()Ljava/lang/String;
      #151 ()Ljava/lang/String;
      #152 5
      #153 1
      #151 ()Ljava/lang/String;
  10: #592 REF_invokeStatic scala/runtime/LambdaDeserialize.bootstrap:(Ljava/lang/invoke/MethodHandles$Lookup;Ljava/lang/String;Ljava/lang/invoke/MethodType;[Ljava/lang/invoke/MethodHandle;)Ljava/lang/invoke/CallSite;
    Method arguments:
      #254 REF_invokeStatic org/scalatest/featurespec/FixtureAsyncFeatureSpecLike.$anonfun$FeatureImpl$1:()Ljava/lang/String;
      #283 REF_invokeStatic org/scalatest/featurespec/FixtureAsyncFeatureSpecLike.$anonfun$FeatureImpl$2:(Lorg/scalactic/source/Position;)Lorg/scalactic/source/Position;
      #303 REF_invokeStatic org/scalatest/featurespec/FixtureAsyncFeatureSpecLike.$anonfun$FeatureImpl$3:(Lorg/scalactic/source/Position;)Lorg/scalactic/source/Position;
      #478 REF_invokeStatic org/scalatest/featurespec/FixtureAsyncFeatureSpecLike.$anonfun$convertPendingToFixtureFunction$1:(Lscala/Function0;Ljava/lang/Object;)Lorg/scalatest/Succeeded$;
      #571 REF_invokeStatic org/scalatest/featurespec/FixtureAsyncFeatureSpecLike.$anonfun$engine$1:()Ljava/lang/String;
      #150 REF_invokeStatic org/scalatest/featurespec/FixtureAsyncFeatureSpecLike.$anonfun$registerAsyncTestImpl$1:()Ljava/lang/String;
      #188 REF_invokeStatic org/scalatest/featurespec/FixtureAsyncFeatureSpecLike.$anonfun$registerIgnoredAsyncTestImpl$1:()Ljava/lang/String;
      #445 REF_invokeStatic org/scalatest/featurespec/FixtureAsyncFeatureSpecLike.$anonfun$run$1:(Lorg/scalatest/featurespec/FixtureAsyncFeatureSpecLike;Lscala/Option;Lorg/scalatest/Args;)Lorg/scalatest/Status;
      #386 REF_invokeStatic org/scalatest/featurespec/FixtureAsyncFeatureSpecLike.$anonfun$runTest$1:(Lorg/scalatest/featurespec/FixtureAsyncFeatureSpecLike;Lorg/scalatest/Args;Ljava/lang/String;Lorg/scalatest/AsyncSuperEngine$TestLeaf;Lscala/Function1;)Lorg/scalatest/AsyncOutcome;
      #410 REF_invokeStatic org/scalatest/featurespec/FixtureAsyncFeatureSpecLike.$anonfun$runTests$1:(Lorg/scalatest/featurespec/FixtureAsyncFeatureSpecLike;Ljava/lang/String;Lorg/scalatest/Args;)Lorg/scalatest/Status;
  ScalaInlineInfo: length = 0x13A (unknown attribute)
   01 00 00 3E 00 FB 00 87 01 01 17 01 18 01 01 2C
   01 18 01 01 DA 01 DB 01 01 FE 00 87 01 00 93 00
   87 01 00 B9 00 87 01 01 BA 01 91 01 01 7E 01 7F
   01 01 97 01 73 01 02 37 02 38 01 01 5E 00 E3 00
   01 5D 00 DF 01 00 E8 00 E3 01 00 CE 00 CA 00 00
   D1 00 C8 01 01 CC 01 C8 00 01 CF 01 C5 01 00 63
   00 64 00 00 61 00 62 01 01 D3 01 D4 00 01 D0 01
   D1 01 00 E2 00 E3 00 00 DE 00 DF 01 00 D8 00 D9
   00 00 D6 00 D7 01 00 40 00 41 00 00 3D 00 3E 01
   02 09 02 0A 01 00 6E 00 6F 00 00 6C 00 6D 01 00
   58 00 59 00 00 56 00 57 01 00 3A 00 3B 00 00 36
   00 37 01 00 30 00 31 00 00 34 00 35 00 00 AA 00
   78 01 00 B2 00 B3 01 00 77 00 78 01 00 BE 00 78
   01 00 C2 00 B3 01 00 B8 00 78 01 01 B7 00 37 00
   01 B6 01 91 01 01 74 01 75 00 01 72 01 73 01 01
   92 00 37 00 01 90 01 91 01 00 8A 00 CA 00 00 C7
   00 C8 01 01 C7 01 C8 00 01 C4 01 C5 01 01 E3 00
   87 00 01 63 01 64 00 01 61 01 62 01 01 E7 01 E8
   00 01 E4 01 E5 01 01 F2 01 F3 00 01 F0 01 F1 01
   01 A5 01 A6 00 01 A3 01 A4 01
  ScalaSig: length = 0x3 (unknown attribute)
   05 02 00
