Classfile /Users/mw/Projects/slang-braindump/.jar/jar8/assemble/slang-braindump/assemble/content/org/antlr/runtime/SerializedGrammar$Node.class
  Last modified May 29, 2022; size 558 bytes
  SHA-256 checksum 4a63ed51e7f224e94ae3413323ede3554e8b0dd9a80ea56c87a5a01091403925
  Compiled from "SerializedGrammar.java"
public abstract class org.antlr.runtime.SerializedGrammar$Node
  minor version: 0
  major version: 49
  flags: (0x0421) ACC_PUBLIC, ACC_SUPER, ACC_ABSTRACT
  this_class: #3                          // org/antlr/runtime/SerializedGrammar$Node
  super_class: #4                         // java/lang/Object
  interfaces: 0, fields: 1, methods: 2, attributes: 2
Constant pool:
   #1 = Fieldref           #3.#20         // org/antlr/runtime/SerializedGrammar$Node.this$0:Lorg/antlr/runtime/SerializedGrammar;
   #2 = Methodref          #4.#21         // java/lang/Object."<init>":()V
   #3 = Class              #23            // org/antlr/runtime/SerializedGrammar$Node
   #4 = Class              #24            // java/lang/Object
   #5 = Utf8               this$0
   #6 = Utf8               Lorg/antlr/runtime/SerializedGrammar;
   #7 = Utf8               <init>
   #8 = Utf8               (Lorg/antlr/runtime/SerializedGrammar;)V
   #9 = Utf8               Code
  #10 = Utf8               LineNumberTable
  #11 = Utf8               LocalVariableTable
  #12 = Utf8               this
  #13 = Utf8               Node
  #14 = Utf8               InnerClasses
  #15 = Utf8               Lorg/antlr/runtime/SerializedGrammar$Node;
  #16 = Utf8               toString
  #17 = Utf8               ()Ljava/lang/String;
  #18 = Utf8               SourceFile
  #19 = Utf8               SerializedGrammar.java
  #20 = NameAndType        #5:#6          // this$0:Lorg/antlr/runtime/SerializedGrammar;
  #21 = NameAndType        #7:#25         // "<init>":()V
  #22 = Class              #26            // org/antlr/runtime/SerializedGrammar
  #23 = Utf8               org/antlr/runtime/SerializedGrammar$Node
  #24 = Utf8               java/lang/Object
  #25 = Utf8               ()V
  #26 = Utf8               org/antlr/runtime/SerializedGrammar
{
  final org.antlr.runtime.SerializedGrammar this$0;
    descriptor: Lorg/antlr/runtime/SerializedGrammar;
    flags: (0x1010) ACC_FINAL, ACC_SYNTHETIC

  protected org.antlr.runtime.SerializedGrammar$Node(org.antlr.runtime.SerializedGrammar);
    descriptor: (Lorg/antlr/runtime/SerializedGrammar;)V
    flags: (0x0004) ACC_PROTECTED
    Code:
      stack=2, locals=2, args_size=2
         0: aload_0
         1: aload_1
         2: putfield      #1                  // Field this$0:Lorg/antlr/runtime/SerializedGrammar;
         5: aload_0
         6: invokespecial #2                  // Method java/lang/Object."<init>":()V
         9: return
      LineNumberTable:
        line 60: 0
      LocalVariableTable:
        Start  Length  Slot  Name   Signature
            0      10     0  this   Lorg/antlr/runtime/SerializedGrammar$Node;

  public abstract java.lang.String toString();
    descriptor: ()Ljava/lang/String;
    flags: (0x0401) ACC_PUBLIC, ACC_ABSTRACT
}
SourceFile: "SerializedGrammar.java"
InnerClasses:
  protected abstract #13= #3 of #22;      // Node=class org/antlr/runtime/SerializedGrammar$Node of class org/antlr/runtime/SerializedGrammar
