Classfile /Users/mw/Projects/slang-braindump/.jar/jar8/assemble/slang-braindump/assemble/content/org/antlr/runtime/SerializedGrammar$Block.class
  Last modified May 29, 2022; size 1206 bytes
  SHA-256 checksum 5830eb8fe293527c96af8b6ea430c32717fa124bd13bbdf7f9a867a1fcf3743a
  Compiled from "SerializedGrammar.java"
public class org.antlr.runtime.SerializedGrammar$Block extends org.antlr.runtime.SerializedGrammar$Node
  minor version: 0
  major version: 49
  flags: (0x0021) ACC_PUBLIC, ACC_SUPER
  this_class: #12                         // org/antlr/runtime/SerializedGrammar$Block
  super_class: #13                        // org/antlr/runtime/SerializedGrammar$Node
  interfaces: 0, fields: 2, methods: 2, attributes: 2
Constant pool:
   #1 = Fieldref           #12.#39        // org/antlr/runtime/SerializedGrammar$Block.this$0:Lorg/antlr/runtime/SerializedGrammar;
   #2 = Methodref          #13.#40        // org/antlr/runtime/SerializedGrammar$Node."<init>":(Lorg/antlr/runtime/SerializedGrammar;)V
   #3 = Fieldref           #12.#41        // org/antlr/runtime/SerializedGrammar$Block.alts:[Ljava/util/List;
   #4 = Class              #42            // java/lang/StringBuilder
   #5 = Methodref          #4.#43         // java/lang/StringBuilder."<init>":()V
   #6 = String             #44            // (
   #7 = Methodref          #4.#45         // java/lang/StringBuilder.append:(Ljava/lang/String;)Ljava/lang/StringBuilder;
   #8 = String             #46            // |
   #9 = Methodref          #47.#48        // java/lang/Object.toString:()Ljava/lang/String;
  #10 = String             #49            // )
  #11 = Methodref          #4.#48         // java/lang/StringBuilder.toString:()Ljava/lang/String;
  #12 = Class              #51            // org/antlr/runtime/SerializedGrammar$Block
  #13 = Class              #52            // org/antlr/runtime/SerializedGrammar$Node
  #14 = Utf8               alts
  #15 = Utf8               [Ljava/util/List;
  #16 = Utf8               this$0
  #17 = Utf8               Lorg/antlr/runtime/SerializedGrammar;
  #18 = Utf8               <init>
  #19 = Utf8               (Lorg/antlr/runtime/SerializedGrammar;[Ljava/util/List;)V
  #20 = Utf8               Code
  #21 = Utf8               LineNumberTable
  #22 = Utf8               LocalVariableTable
  #23 = Utf8               this
  #24 = Utf8               Block
  #25 = Utf8               InnerClasses
  #26 = Utf8               Lorg/antlr/runtime/SerializedGrammar$Block;
  #27 = Utf8               toString
  #28 = Utf8               ()Ljava/lang/String;
  #29 = Utf8               alt
  #30 = Utf8               Ljava/util/List;
  #31 = Utf8               i
  #32 = Utf8               I
  #33 = Utf8               buf
  #34 = Utf8               Ljava/lang/StringBuilder;
  #35 = Utf8               LocalVariableTypeTable
  #36 = Utf8               Ljava/util/List<*>;
  #37 = Utf8               SourceFile
  #38 = Utf8               SerializedGrammar.java
  #39 = NameAndType        #16:#17        // this$0:Lorg/antlr/runtime/SerializedGrammar;
  #40 = NameAndType        #18:#54        // "<init>":(Lorg/antlr/runtime/SerializedGrammar;)V
  #41 = NameAndType        #14:#15        // alts:[Ljava/util/List;
  #42 = Utf8               java/lang/StringBuilder
  #43 = NameAndType        #18:#55        // "<init>":()V
  #44 = Utf8               (
  #45 = NameAndType        #56:#57        // append:(Ljava/lang/String;)Ljava/lang/StringBuilder;
  #46 = Utf8               |
  #47 = Class              #58            // java/lang/Object
  #48 = NameAndType        #27:#28        // toString:()Ljava/lang/String;
  #49 = Utf8               )
  #50 = Class              #59            // org/antlr/runtime/SerializedGrammar
  #51 = Utf8               org/antlr/runtime/SerializedGrammar$Block
  #52 = Utf8               org/antlr/runtime/SerializedGrammar$Node
  #53 = Utf8               Node
  #54 = Utf8               (Lorg/antlr/runtime/SerializedGrammar;)V
  #55 = Utf8               ()V
  #56 = Utf8               append
  #57 = Utf8               (Ljava/lang/String;)Ljava/lang/StringBuilder;
  #58 = Utf8               java/lang/Object
  #59 = Utf8               org/antlr/runtime/SerializedGrammar
{
  java.util.List[] alts;
    descriptor: [Ljava/util/List;
    flags: (0x0000)

  final org.antlr.runtime.SerializedGrammar this$0;
    descriptor: Lorg/antlr/runtime/SerializedGrammar;
    flags: (0x1010) ACC_FINAL, ACC_SYNTHETIC

  public org.antlr.runtime.SerializedGrammar$Block(org.antlr.runtime.SerializedGrammar, java.util.List[]);
    descriptor: (Lorg/antlr/runtime/SerializedGrammar;[Ljava/util/List;)V
    flags: (0x0001) ACC_PUBLIC
    Code:
      stack=2, locals=3, args_size=3
         0: aload_0
         1: aload_1
         2: putfield      #1                  // Field this$0:Lorg/antlr/runtime/SerializedGrammar;
         5: aload_0
         6: aload_1
         7: invokespecial #2                  // Method org/antlr/runtime/SerializedGrammar$Node."<init>":(Lorg/antlr/runtime/SerializedGrammar;)V
        10: aload_0
        11: aload_2
        12: putfield      #3                  // Field alts:[Ljava/util/List;
        15: return
      LineNumberTable:
        line 67: 0
        line 68: 10
        line 69: 15
      LocalVariableTable:
        Start  Length  Slot  Name   Signature
            0      16     0  this   Lorg/antlr/runtime/SerializedGrammar$Block;
            0      16     2  alts   [Ljava/util/List;

  public java.lang.String toString();
    descriptor: ()Ljava/lang/String;
    flags: (0x0001) ACC_PUBLIC
    Code:
      stack=2, locals=4, args_size=1
         0: new           #4                  // class java/lang/StringBuilder
         3: dup
         4: invokespecial #5                  // Method java/lang/StringBuilder."<init>":()V
         7: astore_1
         8: aload_1
         9: ldc           #6                  // String (
        11: invokevirtual #7                  // Method java/lang/StringBuilder.append:(Ljava/lang/String;)Ljava/lang/StringBuilder;
        14: pop
        15: iconst_0
        16: istore_2
        17: iload_2
        18: aload_0
        19: getfield      #3                  // Field alts:[Ljava/util/List;
        22: arraylength
        23: if_icmpge     59
        26: aload_0
        27: getfield      #3                  // Field alts:[Ljava/util/List;
        30: iload_2
        31: aaload
        32: astore_3
        33: iload_2
        34: ifle          44
        37: aload_1
        38: ldc           #8                  // String |
        40: invokevirtual #7                  // Method java/lang/StringBuilder.append:(Ljava/lang/String;)Ljava/lang/StringBuilder;
        43: pop
        44: aload_1
        45: aload_3
        46: invokevirtual #9                  // Method java/lang/Object.toString:()Ljava/lang/String;
        49: invokevirtual #7                  // Method java/lang/StringBuilder.append:(Ljava/lang/String;)Ljava/lang/StringBuilder;
        52: pop
        53: iinc          2, 1
        56: goto          17
        59: aload_1
        60: ldc           #10                 // String )
        62: invokevirtual #7                  // Method java/lang/StringBuilder.append:(Ljava/lang/String;)Ljava/lang/StringBuilder;
        65: pop
        66: aload_1
        67: invokevirtual #11                 // Method java/lang/StringBuilder.toString:()Ljava/lang/String;
        70: areturn
      LineNumberTable:
        line 72: 0
        line 73: 8
        line 74: 15
        line 75: 26
        line 76: 33
        line 77: 44
        line 74: 53
        line 79: 59
        line 80: 66
      LocalVariableTable:
        Start  Length  Slot  Name   Signature
           33      20     3   alt   Ljava/util/List;
           17      42     2     i   I
            0      71     0  this   Lorg/antlr/runtime/SerializedGrammar$Block;
            8      63     1   buf   Ljava/lang/StringBuilder;
      LocalVariableTypeTable:
        Start  Length  Slot  Name   Signature
           33      20     3   alt   Ljava/util/List<*>;
}
SourceFile: "SerializedGrammar.java"
InnerClasses:
  protected #24= #12 of #50;              // Block=class org/antlr/runtime/SerializedGrammar$Block of class org/antlr/runtime/SerializedGrammar
  protected abstract #53= #13 of #50;     // Node=class org/antlr/runtime/SerializedGrammar$Node of class org/antlr/runtime/SerializedGrammar
