Classfile /Users/mw/Projects/slang-braindump/.jar/jar8/assemble/slang-braindump/assemble/content/org/scalatest/diagrams/DiagrammedSelectExpr.class
  Last modified May 29, 2022; size 3286 bytes
  SHA-256 checksum b35535608791b8735dfa036fbbdf0d58bbbdf8727acc5a103fcb6faa11728de2
  Compiled from "DiagrammedExpr.scala"
public class org.scalatest.diagrams.DiagrammedSelectExpr<T extends java.lang.Object> extends java.lang.Object implements org.scalatest.diagrams.DiagrammedExpr<T>
  minor version: 0
  major version: 52
  flags: (0x0021) ACC_PUBLIC, ACC_SUPER
  this_class: #2                          // org/scalatest/diagrams/DiagrammedSelectExpr
  super_class: #5                         // java/lang/Object
  interfaces: 1, fields: 3, methods: 5, attributes: 5
Constant pool:
    #1 = Utf8               org/scalatest/diagrams/DiagrammedSelectExpr
    #2 = Class              #1            // org/scalatest/diagrams/DiagrammedSelectExpr
    #3 = Utf8               <T:Ljava/lang/Object;>Ljava/lang/Object;Lorg/scalatest/diagrams/DiagrammedExpr<TT;>;
    #4 = Utf8               java/lang/Object
    #5 = Class              #4            // java/lang/Object
    #6 = Utf8               org/scalatest/diagrams/DiagrammedExpr
    #7 = Class              #6            // org/scalatest/diagrams/DiagrammedExpr
    #8 = Utf8               DiagrammedExpr.scala
    #9 = Utf8               Lscala/reflect/ScalaSignature;
   #10 = Utf8               bytes
   #11 = Utf8               \u0006\u000553Q\u0001C\u0005\u0001\u0013=A\u0001b\n\u0001\u0003\u0002\u0003\u0006I\u0001\u000b\u0005\t[\u0001\u0011)\u0019!C\u0001]!Aq\u0006\u0001B\u0001B\u0003%1\u0004\u0003\u00051\u0001\t\u0015\r\u0011\"\u00012\u0011!)\u0004A!A!\u0002\u0013\u0011\u0004\"\u0002\u001c\u0001\t\u00039\u0004\"\u0002!\u0001\t\u0003\t%\u0001\u0006#jC\u001e\u0014\u0018-\\7fIN+G.Z2u\u000bb\u0004(O\u0003\u0002\u000b\u0017\u0005AA-[1he\u0006l7O\u0003\u0002\r\u001b\u0005I1oY1mCR,7\u000f\u001e\u0006\u0002\u001d\u0005\u0019qN]4\u0016\u0005Ai2c\u0001\u0001\u0012/A\u0011!#F\u0007\u0002\')\tA#A\u0003tG\u0006d\u0017-\u0003\u0002\u0017\'\t1\u0011I\\=SK\u001a\u00042\u0001G\r\u001c\u001b\u0005I\u0011B\u0001\u000e\n\u00059!\u0015.Y4sC6lW\rZ#yaJ\u0004\"\u0001H\u000f\r\u0001\u0011)a\u0004\u0001b\u0001A\t\tAk\u0001\u0001\u0012\u0005\u0005\"\u0003C\u0001\n#\u0013\t\u00193CA\u0004O_RD\u0017N\\4\u0011\u0005I)\u0013B\u0001\u0014\u0014\u0005\r\te._\u0001\ncV\fG.\u001b4jKJ\u0004$!K\u0016\u0011\u0007aI\"\u0006\u0005\u0002\u001dW\u0011IA&AA\u0001\u0002\u0003\u0015\t\u0001\t\u0002\u0004?\u00122\u0014!\u0002<bYV,W#A\u000e\u0002\rY\fG.^3!\u0003\u0019\tgn\u00195peV\t!\u0007\u0005\u0002\u0013g%\u0011Ag\u0005\u0002\u0004\u0013:$\u0018aB1oG\"|\'\u000fI\u0001\u0007y%t\u0017\u000e\u001e \u0015\taJdh\u0010\t\u00041\u0001Y\u0002\"B\u0014\u0007\u0001\u0004Q\u0004GA\u001e>!\rA\u0012\u0004\u0010\t\u00039u\"\u0011\u0002L\u001d\u0002\u0002\u0003\u0005)\u0011\u0001\u0011\t\u000b52\u0001\u0019A\u000e\t\u000bA2\u0001\u0019\u0001\u001a\u0002\u0019\u0005t7\r[8s-\u0006dW/Z:\u0016\u0003\t\u00032a\u0011%K\u001b\u0005!%BA#G\u0003%IW.\\;uC\ndWM\u0003\u0002H\'\u0005Q1m\u001c7mK\u000e$\u0018n\u001c8\n\u0005%#%\u0001\u0002\'jgR\u0004\"\u0001G&\n\u00051K!aC!oG\"|\'OV1mk\u0016\u0004
   #12 = Utf8               qualifier
   #13 = Utf8               Lorg/scalatest/diagrams/DiagrammedExpr;
   #14 = Utf8               Lorg/scalatest/diagrams/DiagrammedExpr<*>;
   #15 = Utf8               value
   #16 = Utf8               Ljava/lang/Object;
   #17 = Utf8               TT;
   #18 = Utf8               anchor
   #19 = Utf8               I
   #20 = Utf8               eliminateDuplicates
   #21 = Utf8               (Lscala/collection/immutable/List;)Lscala/collection/immutable/List;
   #22 = Utf8               (Lscala/collection/immutable/List<Lorg/scalatest/diagrams/AnchorValue;>;)Lscala/collection/immutable/List<Lorg/scalatest/diagrams/AnchorValue;>;
   #23 = Utf8               anchorValues
   #24 = Utf8               eliminateDuplicates$
   #25 = Utf8               (Lorg/scalatest/diagrams/DiagrammedExpr;Lscala/collection/immutable/List;)Lscala/collection/immutable/List;
   #26 = NameAndType        #24:#25       // eliminateDuplicates$:(Lorg/scalatest/diagrams/DiagrammedExpr;Lscala/collection/immutable/List;)Lscala/collection/immutable/List;
   #27 = InterfaceMethodref #7.#26        // org/scalatest/diagrams/DiagrammedExpr.eliminateDuplicates$:(Lorg/scalatest/diagrams/DiagrammedExpr;Lscala/collection/immutable/List;)Lscala/collection/immutable/List;
   #28 = Utf8               this
   #29 = Utf8               Lorg/scalatest/diagrams/DiagrammedSelectExpr;
   #30 = Utf8               Lscala/collection/immutable/List;
   #31 = Utf8               ()Ljava/lang/Object;
   #32 = Utf8               ()TT;
   #33 = NameAndType        #15:#16       // value:Ljava/lang/Object;
   #34 = Fieldref           #2.#33        // org/scalatest/diagrams/DiagrammedSelectExpr.value:Ljava/lang/Object;
   #35 = Utf8               ()I
   #36 = NameAndType        #18:#19       // anchor:I
   #37 = Fieldref           #2.#36        // org/scalatest/diagrams/DiagrammedSelectExpr.anchor:I
   #38 = Utf8               ()Lscala/collection/immutable/List;
   #39 = Utf8               ()Lscala/collection/immutable/List<Lorg/scalatest/diagrams/AnchorValue;>;
   #40 = NameAndType        #12:#13       // qualifier:Lorg/scalatest/diagrams/DiagrammedExpr;
   #41 = Fieldref           #2.#40        // org/scalatest/diagrams/DiagrammedSelectExpr.qualifier:Lorg/scalatest/diagrams/DiagrammedExpr;
   #42 = NameAndType        #23:#38       // anchorValues:()Lscala/collection/immutable/List;
   #43 = InterfaceMethodref #7.#42        // org/scalatest/diagrams/DiagrammedExpr.anchorValues:()Lscala/collection/immutable/List;
   #44 = NameAndType        #20:#21       // eliminateDuplicates:(Lscala/collection/immutable/List;)Lscala/collection/immutable/List;
   #45 = Methodref          #2.#44        // org/scalatest/diagrams/DiagrammedSelectExpr.eliminateDuplicates:(Lscala/collection/immutable/List;)Lscala/collection/immutable/List;
   #46 = Utf8               scala/collection/immutable/List
   #47 = Class              #46           // scala/collection/immutable/List
   #48 = Utf8               toList
   #49 = NameAndType        #48:#38       // toList:()Lscala/collection/immutable/List;
   #50 = Methodref          #47.#49       // scala/collection/immutable/List.toList:()Lscala/collection/immutable/List;
   #51 = Utf8               scala/package$
   #52 = Class              #51           // scala/package$
   #53 = Utf8               MODULE$
   #54 = Utf8               Lscala/package$;
   #55 = NameAndType        #53:#54       // MODULE$:Lscala/package$;
   #56 = Fieldref           #52.#55       // scala/package$.MODULE$:Lscala/package$;
   #57 = Utf8               List
   #58 = Utf8               ()Lscala/collection/immutable/List$;
   #59 = NameAndType        #57:#58       // List:()Lscala/collection/immutable/List$;
   #60 = Methodref          #52.#59       // scala/package$.List:()Lscala/collection/immutable/List$;
   #61 = Utf8               scala/runtime/ScalaRunTime$
   #62 = Class              #61           // scala/runtime/ScalaRunTime$
   #63 = Utf8               Lscala/runtime/ScalaRunTime$;
   #64 = NameAndType        #53:#63       // MODULE$:Lscala/runtime/ScalaRunTime$;
   #65 = Fieldref           #62.#64       // scala/runtime/ScalaRunTime$.MODULE$:Lscala/runtime/ScalaRunTime$;
   #66 = Utf8               org/scalatest/diagrams/AnchorValue
   #67 = Class              #66           // org/scalatest/diagrams/AnchorValue
   #68 = NameAndType        #18:#35       // anchor:()I
   #69 = Methodref          #2.#68        // org/scalatest/diagrams/DiagrammedSelectExpr.anchor:()I
   #70 = NameAndType        #15:#31       // value:()Ljava/lang/Object;
   #71 = Methodref          #2.#70        // org/scalatest/diagrams/DiagrammedSelectExpr.value:()Ljava/lang/Object;
   #72 = Utf8               <init>
   #73 = Utf8               (ILjava/lang/Object;)V
   #74 = NameAndType        #72:#73       // "<init>":(ILjava/lang/Object;)V
   #75 = Methodref          #67.#74       // org/scalatest/diagrams/AnchorValue."<init>":(ILjava/lang/Object;)V
   #76 = Utf8               [Ljava/lang/Object;
   #77 = Class              #76           // "[Ljava/lang/Object;"
   #78 = Utf8               wrapRefArray
   #79 = Utf8               ([Ljava/lang/Object;)Lscala/collection/immutable/ArraySeq;
   #80 = NameAndType        #78:#79       // wrapRefArray:([Ljava/lang/Object;)Lscala/collection/immutable/ArraySeq;
   #81 = Methodref          #62.#80       // scala/runtime/ScalaRunTime$.wrapRefArray:([Ljava/lang/Object;)Lscala/collection/immutable/ArraySeq;
   #82 = Utf8               scala/collection/immutable/List$
   #83 = Class              #82           // scala/collection/immutable/List$
   #84 = Utf8               apply
   #85 = Utf8               (Lscala/collection/immutable/Seq;)Ljava/lang/Object;
   #86 = NameAndType        #84:#85       // apply:(Lscala/collection/immutable/Seq;)Ljava/lang/Object;
   #87 = Methodref          #83.#86       // scala/collection/immutable/List$.apply:(Lscala/collection/immutable/Seq;)Ljava/lang/Object;
   #88 = Utf8               $colon$colon$colon
   #89 = NameAndType        #88:#21       // $colon$colon$colon:(Lscala/collection/immutable/List;)Lscala/collection/immutable/List;
   #90 = Methodref          #47.#89       // scala/collection/immutable/List.$colon$colon$colon:(Lscala/collection/immutable/List;)Lscala/collection/immutable/List;
   #91 = Utf8               quantifierAnchorValues
   #92 = Utf8               (Lorg/scalatest/diagrams/DiagrammedExpr;Ljava/lang/Object;I)V
   #93 = Utf8               (Lorg/scalatest/diagrams/DiagrammedExpr<*>;TT;I)V
   #94 = Utf8               ()V
   #95 = NameAndType        #72:#94       // "<init>":()V
   #96 = Methodref          #5.#95        // java/lang/Object."<init>":()V
   #97 = Utf8               $init$
   #98 = Utf8               (Lorg/scalatest/diagrams/DiagrammedExpr;)V
   #99 = NameAndType        #97:#98       // $init$:(Lorg/scalatest/diagrams/DiagrammedExpr;)V
  #100 = InterfaceMethodref #7.#99        // org/scalatest/diagrams/DiagrammedExpr.$init$:(Lorg/scalatest/diagrams/DiagrammedExpr;)V
  #101 = Utf8               Signature
  #102 = Utf8               Code
  #103 = Utf8               LineNumberTable
  #104 = Utf8               LocalVariableTable
  #105 = Utf8               MethodParameters
  #106 = Utf8               SourceFile
  #107 = Utf8               RuntimeVisibleAnnotations
  #108 = Utf8               ScalaInlineInfo
  #109 = Utf8               ScalaSig
{
  private final org.scalatest.diagrams.DiagrammedExpr<?> qualifier;
    descriptor: Lorg/scalatest/diagrams/DiagrammedExpr;
    flags: (0x0012) ACC_PRIVATE, ACC_FINAL
    Signature: #14                          // Lorg/scalatest/diagrams/DiagrammedExpr<*>;

  private final T value;
    descriptor: Ljava/lang/Object;
    flags: (0x0012) ACC_PRIVATE, ACC_FINAL
    Signature: #17                          // TT;

  private final int anchor;
    descriptor: I
    flags: (0x0012) ACC_PRIVATE, ACC_FINAL

  public scala.collection.immutable.List<org.scalatest.diagrams.AnchorValue> eliminateDuplicates(scala.collection.immutable.List<org.scalatest.diagrams.AnchorValue>);
    descriptor: (Lscala/collection/immutable/List;)Lscala/collection/immutable/List;
    flags: (0x0001) ACC_PUBLIC
    Code:
      stack=2, locals=2, args_size=2
         0: aload_0
         1: aload_1
         2: invokestatic  #27                 // InterfaceMethod org/scalatest/diagrams/DiagrammedExpr.eliminateDuplicates$:(Lorg/scalatest/diagrams/DiagrammedExpr;Lscala/collection/immutable/List;)Lscala/collection/immutable/List;
         5: areturn
      LineNumberTable:
        line 104: 0
      LocalVariableTable:
        Start  Length  Slot  Name   Signature
            0       6     0  this   Lorg/scalatest/diagrams/DiagrammedSelectExpr;
            0       6     1 anchorValues   Lscala/collection/immutable/List;
    Signature: #22                          // (Lscala/collection/immutable/List<Lorg/scalatest/diagrams/AnchorValue;>;)Lscala/collection/immutable/List<Lorg/scalatest/diagrams/AnchorValue;>;
    MethodParameters:
      Name                           Flags
      anchorValues                   final

  public T value();
    descriptor: ()Ljava/lang/Object;
    flags: (0x0001) ACC_PUBLIC
    Code:
      stack=1, locals=1, args_size=1
         0: aload_0
         1: getfield      #34                 // Field value:Ljava/lang/Object;
         4: areturn
      LineNumberTable:
        line 104: 0
      LocalVariableTable:
        Start  Length  Slot  Name   Signature
            0       5     0  this   Lorg/scalatest/diagrams/DiagrammedSelectExpr;
    Signature: #32                          // ()TT;

  public int anchor();
    descriptor: ()I
    flags: (0x0001) ACC_PUBLIC
    Code:
      stack=1, locals=1, args_size=1
         0: aload_0
         1: getfield      #37                 // Field anchor:I
         4: ireturn
      LineNumberTable:
        line 104: 0
      LocalVariableTable:
        Start  Length  Slot  Name   Signature
            0       5     0  this   Lorg/scalatest/diagrams/DiagrammedSelectExpr;

  public scala.collection.immutable.List<org.scalatest.diagrams.AnchorValue> anchorValues();
    descriptor: ()Lscala/collection/immutable/List;
    flags: (0x0001) ACC_PUBLIC
    Code:
      stack=9, locals=3, args_size=1
         0: aload_0
         1: aload_0
         2: getfield      #41                 // Field qualifier:Lorg/scalatest/diagrams/DiagrammedExpr;
         5: invokeinterface #43,  1           // InterfaceMethod org/scalatest/diagrams/DiagrammedExpr.anchorValues:()Lscala/collection/immutable/List;
        10: invokevirtual #45                 // Method eliminateDuplicates:(Lscala/collection/immutable/List;)Lscala/collection/immutable/List;
        13: astore_1
        14: aload_1
        15: invokevirtual #50                 // Method scala/collection/immutable/List.toList:()Lscala/collection/immutable/List;
        18: astore_2
        19: getstatic     #56                 // Field scala/package$.MODULE$:Lscala/package$;
        22: invokevirtual #60                 // Method scala/package$.List:()Lscala/collection/immutable/List$;
        25: getstatic     #65                 // Field scala/runtime/ScalaRunTime$.MODULE$:Lscala/runtime/ScalaRunTime$;
        28: iconst_1
        29: anewarray     #67                 // class org/scalatest/diagrams/AnchorValue
        32: dup
        33: iconst_0
        34: new           #67                 // class org/scalatest/diagrams/AnchorValue
        37: dup
        38: aload_0
        39: invokevirtual #69                 // Method anchor:()I
        42: aload_0
        43: invokevirtual #71                 // Method value:()Ljava/lang/Object;
        46: invokespecial #75                 // Method org/scalatest/diagrams/AnchorValue."<init>":(ILjava/lang/Object;)V
        49: aastore
        50: checkcast     #77                 // class "[Ljava/lang/Object;"
        53: invokevirtual #81                 // Method scala/runtime/ScalaRunTime$.wrapRefArray:([Ljava/lang/Object;)Lscala/collection/immutable/ArraySeq;
        56: invokevirtual #87                 // Method scala/collection/immutable/List$.apply:(Lscala/collection/immutable/Seq;)Ljava/lang/Object;
        59: checkcast     #47                 // class scala/collection/immutable/List
        62: aload_2
        63: invokevirtual #90                 // Method scala/collection/immutable/List.$colon$colon$colon:(Lscala/collection/immutable/List;)Lscala/collection/immutable/List;
        66: areturn
      LineNumberTable:
        line 106: 0
        line 108: 14
      LocalVariableTable:
        Start  Length  Slot  Name   Signature
           14      52     1 quantifierAnchorValues   Lscala/collection/immutable/List;
            0      67     0  this   Lorg/scalatest/diagrams/DiagrammedSelectExpr;
    Signature: #39                          // ()Lscala/collection/immutable/List<Lorg/scalatest/diagrams/AnchorValue;>;

  public org.scalatest.diagrams.DiagrammedSelectExpr(org.scalatest.diagrams.DiagrammedExpr<?>, T, int);
    descriptor: (Lorg/scalatest/diagrams/DiagrammedExpr;Ljava/lang/Object;I)V
    flags: (0x0001) ACC_PUBLIC
    Code:
      stack=2, locals=4, args_size=4
         0: aload_0
         1: aload_1
         2: putfield      #41                 // Field qualifier:Lorg/scalatest/diagrams/DiagrammedExpr;
         5: aload_0
         6: aload_2
         7: putfield      #34                 // Field value:Ljava/lang/Object;
        10: aload_0
        11: iload_3
        12: putfield      #37                 // Field anchor:I
        15: aload_0
        16: invokespecial #96                 // Method java/lang/Object."<init>":()V
        19: aload_0
        20: invokestatic  #100                // InterfaceMethod org/scalatest/diagrams/DiagrammedExpr.$init$:(Lorg/scalatest/diagrams/DiagrammedExpr;)V
        23: return
      LineNumberTable:
        line 104: 0
      LocalVariableTable:
        Start  Length  Slot  Name   Signature
            0      24     0  this   Lorg/scalatest/diagrams/DiagrammedSelectExpr;
            0      24     1 qualifier   Lorg/scalatest/diagrams/DiagrammedExpr;
            0      24     2 value   Ljava/lang/Object;
            0      24     3 anchor   I
    Signature: #93                          // (Lorg/scalatest/diagrams/DiagrammedExpr<*>;TT;I)V
    MethodParameters:
      Name                           Flags
      qualifier                      final
      value                          final
      anchor                         final
}
Signature: #3                           // <T:Ljava/lang/Object;>Ljava/lang/Object;Lorg/scalatest/diagrams/DiagrammedExpr<TT;>;
SourceFile: "DiagrammedExpr.scala"
RuntimeVisibleAnnotations:
  0: #9(#10=s#11)
    scala.reflect.ScalaSignature(
      bytes="\u0006\u000553Q\u0001C\u0005\u0001\u0013=A\u0001b\n\u0001\u0003\u0002\u0003\u0006I\u0001\u000b\u0005\t[\u0001\u0011)\u0019!C\u0001]!Aq\u0006\u0001B\u0001B\u0003%1\u0004\u0003\u00051\u0001\t\u0015\r\u0011\"\u00012\u0011!)\u0004A!A!\u0002\u0013\u0011\u0004\"\u0002\u001c\u0001\t\u00039\u0004\"\u0002!\u0001\t\u0003\t%\u0001\u0006#jC\u001e\u0014\u0018-\\7fIN+G.Z2u\u000bb\u0004(O\u0003\u0002\u000b\u0017\u0005AA-[1he\u0006l7O\u0003\u0002\r\u001b\u0005I1oY1mCR,7\u000f\u001e\u0006\u0002\u001d\u0005\u0019qN]4\u0016\u0005Ai2c\u0001\u0001\u0012/A\u0011!#F\u0007\u0002\')\tA#A\u0003tG\u0006d\u0017-\u0003\u0002\u0017\'\t1\u0011I\\=SK\u001a\u00042\u0001G\r\u001c\u001b\u0005I\u0011B\u0001\u000e\n\u00059!\u0015.Y4sC6lW\rZ#yaJ\u0004\"\u0001H\u000f\r\u0001\u0011)a\u0004\u0001b\u0001A\t\tAk\u0001\u0001\u0012\u0005\u0005\"\u0003C\u0001\n#\u0013\t\u00193CA\u0004O_RD\u0017N\\4\u0011\u0005I)\u0013B\u0001\u0014\u0014\u0005\r\te._\u0001\ncV\fG.\u001b4jKJ\u0004$!K\u0016\u0011\u0007aI\"\u0006\u0005\u0002\u001dW\u0011IA&AA\u0001\u0002\u0003\u0015\t\u0001\t\u0002\u0004?\u00122\u0014!\u0002<bYV,W#A\u000e\u0002\rY\fG.^3!\u0003\u0019\tgn\u00195peV\t!\u0007\u0005\u0002\u0013g%\u0011Ag\u0005\u0002\u0004\u0013:$\u0018aB1oG\"|\'\u000fI\u0001\u0007y%t\u0017\u000e\u001e \u0015\taJdh\u0010\t\u00041\u0001Y\u0002\"B\u0014\u0007\u0001\u0004Q\u0004GA\u001e>!\rA\u0012\u0004\u0010\t\u00039u\"\u0011\u0002L\u001d\u0002\u0002\u0003\u0005)\u0011\u0001\u0011\t\u000b52\u0001\u0019A\u000e\t\u000bA2\u0001\u0019\u0001\u001a\u0002\u0019\u0005t7\r[8s-\u0006dW/Z:\u0016\u0003\t\u00032a\u0011%K\u001b\u0005!%BA#G\u0003%IW.\\;uC\ndWM\u0003\u0002H\'\u0005Q1m\u001c7mK\u000e$\u0018n\u001c8\n\u0005%#%\u0001\u0002\'jgR\u0004\"\u0001G&\n\u00051K!aC!oG\"|\'OV1mk\u0016\u0004"
    )
  ScalaInlineInfo: length = 0x1D (unknown attribute)
   01 00 00 05 00 48 00 5C 00 00 12 00 23 00 00 17
   00 26 00 00 14 00 15 00 00 0F 00 1F 00
  ScalaSig: length = 0x3 (unknown attribute)
   05 02 00
