Classfile /Users/mw/Projects/slang-braindump/.jar/jar11/assemble/slang-braindump/assemble/content/org/apache/commons/lang3/builder/DiffBuilder$12.class
  Last modified May 29, 2022; size 1422 bytes
  SHA-256 checksum de8dfa6a6cf0de16494b1523fee148e2ce6a6dd37e405ac387b4533ccfe56579
  Compiled from "DiffBuilder.java"
class org.apache.commons.lang3.builder.DiffBuilder$12 extends org.apache.commons.lang3.builder.Diff<java.lang.Integer[]>
  minor version: 0
  major version: 52
  flags: (0x0020) ACC_SUPER
  this_class: #8                          // org/apache/commons/lang3/builder/DiffBuilder$12
  super_class: #9                         // org/apache/commons/lang3/builder/Diff
  interfaces: 0, fields: 4, methods: 5, attributes: 4
Constant pool:
   #1 = Fieldref           #8.#41         // org/apache/commons/lang3/builder/DiffBuilder$12.this$0:Lorg/apache/commons/lang3/builder/DiffBuilder;
   #2 = Fieldref           #8.#42         // org/apache/commons/lang3/builder/DiffBuilder$12.val$lhs:[I
   #3 = Fieldref           #8.#43         // org/apache/commons/lang3/builder/DiffBuilder$12.val$rhs:[I
   #4 = Methodref          #9.#44         // org/apache/commons/lang3/builder/Diff."<init>":(Ljava/lang/String;)V
   #5 = Methodref          #45.#46        // org/apache/commons/lang3/ArrayUtils.toObject:([I)[Ljava/lang/Integer;
   #6 = Methodref          #8.#47         // org/apache/commons/lang3/builder/DiffBuilder$12.getRight:()[Ljava/lang/Integer;
   #7 = Methodref          #8.#48         // org/apache/commons/lang3/builder/DiffBuilder$12.getLeft:()[Ljava/lang/Integer;
   #8 = Class              #49            // org/apache/commons/lang3/builder/DiffBuilder$12
   #9 = Class              #50            // org/apache/commons/lang3/builder/Diff
  #10 = Utf8               serialVersionUID
  #11 = Utf8               J
  #12 = Utf8               ConstantValue
  #13 = Long               1l
  #15 = Utf8               val$lhs
  #16 = Utf8               [I
  #17 = Utf8               val$rhs
  #18 = Utf8               this$0
  #19 = Utf8               Lorg/apache/commons/lang3/builder/DiffBuilder;
  #20 = Utf8               <init>
  #21 = Utf8               (Lorg/apache/commons/lang3/builder/DiffBuilder;Ljava/lang/String;[I[I)V
  #22 = Utf8               Code
  #23 = Utf8               LineNumberTable
  #24 = Utf8               LocalVariableTable
  #25 = Utf8               this
  #26 = Utf8               InnerClasses
  #27 = Utf8               Lorg/apache/commons/lang3/builder/DiffBuilder$12;
  #28 = Utf8               fieldName
  #29 = Utf8               Ljava/lang/String;
  #30 = Utf8               getLeft
  #31 = Utf8               ()[Ljava/lang/Integer;
  #32 = Utf8               getRight
  #33 = Utf8               ()Ljava/lang/Object;
  #34 = Utf8               Signature
  #35 = Utf8               Lorg/apache/commons/lang3/builder/Diff<[Ljava/lang/Integer;>;
  #36 = Utf8               SourceFile
  #37 = Utf8               DiffBuilder.java
  #38 = Utf8               EnclosingMethod
  #39 = Class              #51            // org/apache/commons/lang3/builder/DiffBuilder
  #40 = NameAndType        #52:#53        // append:(Ljava/lang/String;[I[I)Lorg/apache/commons/lang3/builder/DiffBuilder;
  #41 = NameAndType        #18:#19        // this$0:Lorg/apache/commons/lang3/builder/DiffBuilder;
  #42 = NameAndType        #15:#16        // val$lhs:[I
  #43 = NameAndType        #17:#16        // val$rhs:[I
  #44 = NameAndType        #20:#54        // "<init>":(Ljava/lang/String;)V
  #45 = Class              #55            // org/apache/commons/lang3/ArrayUtils
  #46 = NameAndType        #56:#57        // toObject:([I)[Ljava/lang/Integer;
  #47 = NameAndType        #32:#31        // getRight:()[Ljava/lang/Integer;
  #48 = NameAndType        #30:#31        // getLeft:()[Ljava/lang/Integer;
  #49 = Utf8               org/apache/commons/lang3/builder/DiffBuilder$12
  #50 = Utf8               org/apache/commons/lang3/builder/Diff
  #51 = Utf8               org/apache/commons/lang3/builder/DiffBuilder
  #52 = Utf8               append
  #53 = Utf8               (Ljava/lang/String;[I[I)Lorg/apache/commons/lang3/builder/DiffBuilder;
  #54 = Utf8               (Ljava/lang/String;)V
  #55 = Utf8               org/apache/commons/lang3/ArrayUtils
  #56 = Utf8               toObject
  #57 = Utf8               ([I)[Ljava/lang/Integer;
{
  private static final long serialVersionUID;
    descriptor: J
    flags: (0x001a) ACC_PRIVATE, ACC_STATIC, ACC_FINAL
    ConstantValue: long 1l

  final int[] val$lhs;
    descriptor: [I
    flags: (0x1010) ACC_FINAL, ACC_SYNTHETIC

  final int[] val$rhs;
    descriptor: [I
    flags: (0x1010) ACC_FINAL, ACC_SYNTHETIC

  final org.apache.commons.lang3.builder.DiffBuilder this$0;
    descriptor: Lorg/apache/commons/lang3/builder/DiffBuilder;
    flags: (0x1010) ACC_FINAL, ACC_SYNTHETIC

  org.apache.commons.lang3.builder.DiffBuilder$12(org.apache.commons.lang3.builder.DiffBuilder, java.lang.String, int[], int[]);
    descriptor: (Lorg/apache/commons/lang3/builder/DiffBuilder;Ljava/lang/String;[I[I)V
    flags: (0x0000)
    Code:
      stack=2, locals=5, args_size=5
         0: aload_0
         1: aload_1
         2: putfield      #1                  // Field this$0:Lorg/apache/commons/lang3/builder/DiffBuilder;
         5: aload_0
         6: aload_3
         7: putfield      #2                  // Field val$lhs:[I
        10: aload_0
        11: aload         4
        13: putfield      #3                  // Field val$rhs:[I
        16: aload_0
        17: aload_2
        18: invokespecial #4                  // Method org/apache/commons/lang3/builder/Diff."<init>":(Ljava/lang/String;)V
        21: return
      LineNumberTable:
        line 611: 0
      LocalVariableTable:
        Start  Length  Slot  Name   Signature
            0      22     0  this   Lorg/apache/commons/lang3/builder/DiffBuilder$12;
            0      22     1 this$0   Lorg/apache/commons/lang3/builder/DiffBuilder;
            0      22     2 fieldName   Ljava/lang/String;

  public java.lang.Integer[] getLeft();
    descriptor: ()[Ljava/lang/Integer;
    flags: (0x0001) ACC_PUBLIC
    Code:
      stack=1, locals=1, args_size=1
         0: aload_0
         1: getfield      #2                  // Field val$lhs:[I
         4: invokestatic  #5                  // Method org/apache/commons/lang3/ArrayUtils.toObject:([I)[Ljava/lang/Integer;
         7: areturn
      LineNumberTable:
        line 616: 0
      LocalVariableTable:
        Start  Length  Slot  Name   Signature
            0       8     0  this   Lorg/apache/commons/lang3/builder/DiffBuilder$12;

  public java.lang.Integer[] getRight();
    descriptor: ()[Ljava/lang/Integer;
    flags: (0x0001) ACC_PUBLIC
    Code:
      stack=1, locals=1, args_size=1
         0: aload_0
         1: getfield      #3                  // Field val$rhs:[I
         4: invokestatic  #5                  // Method org/apache/commons/lang3/ArrayUtils.toObject:([I)[Ljava/lang/Integer;
         7: areturn
      LineNumberTable:
        line 621: 0
      LocalVariableTable:
        Start  Length  Slot  Name   Signature
            0       8     0  this   Lorg/apache/commons/lang3/builder/DiffBuilder$12;

  public java.lang.Object getRight();
    descriptor: ()Ljava/lang/Object;
    flags: (0x1041) ACC_PUBLIC, ACC_BRIDGE, ACC_SYNTHETIC
    Code:
      stack=1, locals=1, args_size=1
         0: aload_0
         1: invokevirtual #6                  // Method getRight:()[Ljava/lang/Integer;
         4: areturn
      LineNumberTable:
        line 611: 0
      LocalVariableTable:
        Start  Length  Slot  Name   Signature
            0       5     0  this   Lorg/apache/commons/lang3/builder/DiffBuilder$12;

  public java.lang.Object getLeft();
    descriptor: ()Ljava/lang/Object;
    flags: (0x1041) ACC_PUBLIC, ACC_BRIDGE, ACC_SYNTHETIC
    Code:
      stack=1, locals=1, args_size=1
         0: aload_0
         1: invokevirtual #7                  // Method getLeft:()[Ljava/lang/Integer;
         4: areturn
      LineNumberTable:
        line 611: 0
      LocalVariableTable:
        Start  Length  Slot  Name   Signature
            0       5     0  this   Lorg/apache/commons/lang3/builder/DiffBuilder$12;
}
Signature: #35                          // Lorg/apache/commons/lang3/builder/Diff<[Ljava/lang/Integer;>;
SourceFile: "DiffBuilder.java"
EnclosingMethod: #39.#40                // org.apache.commons.lang3.builder.DiffBuilder.append
InnerClasses:
  #8;                                     // class org/apache/commons/lang3/builder/DiffBuilder$12
