Classfile /Users/mw/Projects/slang-braindump/.jar/jar11/assemble/slang-braindump/assemble/content/org/apache/commons/lang3/builder/StandardToStringStyle.class
  Last modified May 29, 2022; size 4872 bytes
  SHA-256 checksum 8cee4eaba26c55ea2d010891e2a95f0760f66c93e572ab6e5e8e349ff3da1a50
  Compiled from "StandardToStringStyle.java"
public class org.apache.commons.lang3.builder.StandardToStringStyle extends org.apache.commons.lang3.builder.ToStringStyle
  minor version: 0
  major version: 52
  flags: (0x0021) ACC_PUBLIC, ACC_SUPER
  this_class: #42                         // org/apache/commons/lang3/builder/StandardToStringStyle
  super_class: #43                        // org/apache/commons/lang3/builder/ToStringStyle
  interfaces: 0, fields: 1, methods: 41, attributes: 1
Constant pool:
    #1 = Methodref          #43.#124      // org/apache/commons/lang3/builder/ToStringStyle."<init>":()V
    #2 = Methodref          #43.#125      // org/apache/commons/lang3/builder/ToStringStyle.isUseClassName:()Z
    #3 = Methodref          #43.#126      // org/apache/commons/lang3/builder/ToStringStyle.setUseClassName:(Z)V
    #4 = Methodref          #43.#127      // org/apache/commons/lang3/builder/ToStringStyle.isUseShortClassName:()Z
    #5 = Methodref          #43.#128      // org/apache/commons/lang3/builder/ToStringStyle.setUseShortClassName:(Z)V
    #6 = Methodref          #43.#129      // org/apache/commons/lang3/builder/ToStringStyle.isUseIdentityHashCode:()Z
    #7 = Methodref          #43.#130      // org/apache/commons/lang3/builder/ToStringStyle.setUseIdentityHashCode:(Z)V
    #8 = Methodref          #43.#131      // org/apache/commons/lang3/builder/ToStringStyle.isUseFieldNames:()Z
    #9 = Methodref          #43.#132      // org/apache/commons/lang3/builder/ToStringStyle.setUseFieldNames:(Z)V
   #10 = Methodref          #43.#133      // org/apache/commons/lang3/builder/ToStringStyle.isDefaultFullDetail:()Z
   #11 = Methodref          #43.#134      // org/apache/commons/lang3/builder/ToStringStyle.setDefaultFullDetail:(Z)V
   #12 = Methodref          #43.#135      // org/apache/commons/lang3/builder/ToStringStyle.isArrayContentDetail:()Z
   #13 = Methodref          #43.#136      // org/apache/commons/lang3/builder/ToStringStyle.setArrayContentDetail:(Z)V
   #14 = Methodref          #43.#137      // org/apache/commons/lang3/builder/ToStringStyle.getArrayStart:()Ljava/lang/String;
   #15 = Methodref          #43.#138      // org/apache/commons/lang3/builder/ToStringStyle.setArrayStart:(Ljava/lang/String;)V
   #16 = Methodref          #43.#139      // org/apache/commons/lang3/builder/ToStringStyle.getArrayEnd:()Ljava/lang/String;
   #17 = Methodref          #43.#140      // org/apache/commons/lang3/builder/ToStringStyle.setArrayEnd:(Ljava/lang/String;)V
   #18 = Methodref          #43.#141      // org/apache/commons/lang3/builder/ToStringStyle.getArraySeparator:()Ljava/lang/String;
   #19 = Methodref          #43.#142      // org/apache/commons/lang3/builder/ToStringStyle.setArraySeparator:(Ljava/lang/String;)V
   #20 = Methodref          #43.#143      // org/apache/commons/lang3/builder/ToStringStyle.getContentStart:()Ljava/lang/String;
   #21 = Methodref          #43.#144      // org/apache/commons/lang3/builder/ToStringStyle.setContentStart:(Ljava/lang/String;)V
   #22 = Methodref          #43.#145      // org/apache/commons/lang3/builder/ToStringStyle.getContentEnd:()Ljava/lang/String;
   #23 = Methodref          #43.#146      // org/apache/commons/lang3/builder/ToStringStyle.setContentEnd:(Ljava/lang/String;)V
   #24 = Methodref          #43.#147      // org/apache/commons/lang3/builder/ToStringStyle.getFieldNameValueSeparator:()Ljava/lang/String;
   #25 = Methodref          #43.#148      // org/apache/commons/lang3/builder/ToStringStyle.setFieldNameValueSeparator:(Ljava/lang/String;)V
   #26 = Methodref          #43.#149      // org/apache/commons/lang3/builder/ToStringStyle.getFieldSeparator:()Ljava/lang/String;
   #27 = Methodref          #43.#150      // org/apache/commons/lang3/builder/ToStringStyle.setFieldSeparator:(Ljava/lang/String;)V
   #28 = Methodref          #43.#151      // org/apache/commons/lang3/builder/ToStringStyle.isFieldSeparatorAtStart:()Z
   #29 = Methodref          #43.#152      // org/apache/commons/lang3/builder/ToStringStyle.setFieldSeparatorAtStart:(Z)V
   #30 = Methodref          #43.#153      // org/apache/commons/lang3/builder/ToStringStyle.isFieldSeparatorAtEnd:()Z
   #31 = Methodref          #43.#154      // org/apache/commons/lang3/builder/ToStringStyle.setFieldSeparatorAtEnd:(Z)V
   #32 = Methodref          #43.#155      // org/apache/commons/lang3/builder/ToStringStyle.getNullText:()Ljava/lang/String;
   #33 = Methodref          #43.#156      // org/apache/commons/lang3/builder/ToStringStyle.setNullText:(Ljava/lang/String;)V
   #34 = Methodref          #43.#157      // org/apache/commons/lang3/builder/ToStringStyle.getSizeStartText:()Ljava/lang/String;
   #35 = Methodref          #43.#158      // org/apache/commons/lang3/builder/ToStringStyle.setSizeStartText:(Ljava/lang/String;)V
   #36 = Methodref          #43.#159      // org/apache/commons/lang3/builder/ToStringStyle.getSizeEndText:()Ljava/lang/String;
   #37 = Methodref          #43.#160      // org/apache/commons/lang3/builder/ToStringStyle.setSizeEndText:(Ljava/lang/String;)V
   #38 = Methodref          #43.#161      // org/apache/commons/lang3/builder/ToStringStyle.getSummaryObjectStartText:()Ljava/lang/String;
   #39 = Methodref          #43.#162      // org/apache/commons/lang3/builder/ToStringStyle.setSummaryObjectStartText:(Ljava/lang/String;)V
   #40 = Methodref          #43.#163      // org/apache/commons/lang3/builder/ToStringStyle.getSummaryObjectEndText:()Ljava/lang/String;
   #41 = Methodref          #43.#164      // org/apache/commons/lang3/builder/ToStringStyle.setSummaryObjectEndText:(Ljava/lang/String;)V
   #42 = Class              #165          // org/apache/commons/lang3/builder/StandardToStringStyle
   #43 = Class              #166          // org/apache/commons/lang3/builder/ToStringStyle
   #44 = Utf8               serialVersionUID
   #45 = Utf8               J
   #46 = Utf8               ConstantValue
   #47 = Long               1l
   #49 = Utf8               <init>
   #50 = Utf8               ()V
   #51 = Utf8               Code
   #52 = Utf8               LineNumberTable
   #53 = Utf8               LocalVariableTable
   #54 = Utf8               this
   #55 = Utf8               Lorg/apache/commons/lang3/builder/StandardToStringStyle;
   #56 = Utf8               isUseClassName
   #57 = Utf8               ()Z
   #58 = Utf8               setUseClassName
   #59 = Utf8               (Z)V
   #60 = Utf8               useClassName
   #61 = Utf8               Z
   #62 = Utf8               isUseShortClassName
   #63 = Utf8               setUseShortClassName
   #64 = Utf8               useShortClassName
   #65 = Utf8               isUseIdentityHashCode
   #66 = Utf8               setUseIdentityHashCode
   #67 = Utf8               useIdentityHashCode
   #68 = Utf8               isUseFieldNames
   #69 = Utf8               setUseFieldNames
   #70 = Utf8               useFieldNames
   #71 = Utf8               isDefaultFullDetail
   #72 = Utf8               setDefaultFullDetail
   #73 = Utf8               defaultFullDetail
   #74 = Utf8               isArrayContentDetail
   #75 = Utf8               setArrayContentDetail
   #76 = Utf8               arrayContentDetail
   #77 = Utf8               getArrayStart
   #78 = Utf8               ()Ljava/lang/String;
   #79 = Utf8               setArrayStart
   #80 = Utf8               (Ljava/lang/String;)V
   #81 = Utf8               arrayStart
   #82 = Utf8               Ljava/lang/String;
   #83 = Utf8               getArrayEnd
   #84 = Utf8               setArrayEnd
   #85 = Utf8               arrayEnd
   #86 = Utf8               getArraySeparator
   #87 = Utf8               setArraySeparator
   #88 = Utf8               arraySeparator
   #89 = Utf8               getContentStart
   #90 = Utf8               setContentStart
   #91 = Utf8               contentStart
   #92 = Utf8               getContentEnd
   #93 = Utf8               setContentEnd
   #94 = Utf8               contentEnd
   #95 = Utf8               getFieldNameValueSeparator
   #96 = Utf8               setFieldNameValueSeparator
   #97 = Utf8               fieldNameValueSeparator
   #98 = Utf8               getFieldSeparator
   #99 = Utf8               setFieldSeparator
  #100 = Utf8               fieldSeparator
  #101 = Utf8               isFieldSeparatorAtStart
  #102 = Utf8               setFieldSeparatorAtStart
  #103 = Utf8               fieldSeparatorAtStart
  #104 = Utf8               isFieldSeparatorAtEnd
  #105 = Utf8               setFieldSeparatorAtEnd
  #106 = Utf8               fieldSeparatorAtEnd
  #107 = Utf8               getNullText
  #108 = Utf8               setNullText
  #109 = Utf8               nullText
  #110 = Utf8               getSizeStartText
  #111 = Utf8               setSizeStartText
  #112 = Utf8               sizeStartText
  #113 = Utf8               getSizeEndText
  #114 = Utf8               setSizeEndText
  #115 = Utf8               sizeEndText
  #116 = Utf8               getSummaryObjectStartText
  #117 = Utf8               setSummaryObjectStartText
  #118 = Utf8               summaryObjectStartText
  #119 = Utf8               getSummaryObjectEndText
  #120 = Utf8               setSummaryObjectEndText
  #121 = Utf8               summaryObjectEndText
  #122 = Utf8               SourceFile
  #123 = Utf8               StandardToStringStyle.java
  #124 = NameAndType        #49:#50       // "<init>":()V
  #125 = NameAndType        #56:#57       // isUseClassName:()Z
  #126 = NameAndType        #58:#59       // setUseClassName:(Z)V
  #127 = NameAndType        #62:#57       // isUseShortClassName:()Z
  #128 = NameAndType        #63:#59       // setUseShortClassName:(Z)V
  #129 = NameAndType        #65:#57       // isUseIdentityHashCode:()Z
  #130 = NameAndType        #66:#59       // setUseIdentityHashCode:(Z)V
  #131 = NameAndType        #68:#57       // isUseFieldNames:()Z
  #132 = NameAndType        #69:#59       // setUseFieldNames:(Z)V
  #133 = NameAndType        #71:#57       // isDefaultFullDetail:()Z
  #134 = NameAndType        #72:#59       // setDefaultFullDetail:(Z)V
  #135 = NameAndType        #74:#57       // isArrayContentDetail:()Z
  #136 = NameAndType        #75:#59       // setArrayContentDetail:(Z)V
  #137 = NameAndType        #77:#78       // getArrayStart:()Ljava/lang/String;
  #138 = NameAndType        #79:#80       // setArrayStart:(Ljava/lang/String;)V
  #139 = NameAndType        #83:#78       // getArrayEnd:()Ljava/lang/String;
  #140 = NameAndType        #84:#80       // setArrayEnd:(Ljava/lang/String;)V
  #141 = NameAndType        #86:#78       // getArraySeparator:()Ljava/lang/String;
  #142 = NameAndType        #87:#80       // setArraySeparator:(Ljava/lang/String;)V
  #143 = NameAndType        #89:#78       // getContentStart:()Ljava/lang/String;
  #144 = NameAndType        #90:#80       // setContentStart:(Ljava/lang/String;)V
  #145 = NameAndType        #92:#78       // getContentEnd:()Ljava/lang/String;
  #146 = NameAndType        #93:#80       // setContentEnd:(Ljava/lang/String;)V
  #147 = NameAndType        #95:#78       // getFieldNameValueSeparator:()Ljava/lang/String;
  #148 = NameAndType        #96:#80       // setFieldNameValueSeparator:(Ljava/lang/String;)V
  #149 = NameAndType        #98:#78       // getFieldSeparator:()Ljava/lang/String;
  #150 = NameAndType        #99:#80       // setFieldSeparator:(Ljava/lang/String;)V
  #151 = NameAndType        #101:#57      // isFieldSeparatorAtStart:()Z
  #152 = NameAndType        #102:#59      // setFieldSeparatorAtStart:(Z)V
  #153 = NameAndType        #104:#57      // isFieldSeparatorAtEnd:()Z
  #154 = NameAndType        #105:#59      // setFieldSeparatorAtEnd:(Z)V
  #155 = NameAndType        #107:#78      // getNullText:()Ljava/lang/String;
  #156 = NameAndType        #108:#80      // setNullText:(Ljava/lang/String;)V
  #157 = NameAndType        #110:#78      // getSizeStartText:()Ljava/lang/String;
  #158 = NameAndType        #111:#80      // setSizeStartText:(Ljava/lang/String;)V
  #159 = NameAndType        #113:#78      // getSizeEndText:()Ljava/lang/String;
  #160 = NameAndType        #114:#80      // setSizeEndText:(Ljava/lang/String;)V
  #161 = NameAndType        #116:#78      // getSummaryObjectStartText:()Ljava/lang/String;
  #162 = NameAndType        #117:#80      // setSummaryObjectStartText:(Ljava/lang/String;)V
  #163 = NameAndType        #119:#78      // getSummaryObjectEndText:()Ljava/lang/String;
  #164 = NameAndType        #120:#80      // setSummaryObjectEndText:(Ljava/lang/String;)V
  #165 = Utf8               org/apache/commons/lang3/builder/StandardToStringStyle
  #166 = Utf8               org/apache/commons/lang3/builder/ToStringStyle
{
  private static final long serialVersionUID;
    descriptor: J
    flags: (0x001a) ACC_PRIVATE, ACC_STATIC, ACC_FINAL
    ConstantValue: long 1l

  public org.apache.commons.lang3.builder.StandardToStringStyle();
    descriptor: ()V
    flags: (0x0001) ACC_PUBLIC
    Code:
      stack=1, locals=1, args_size=1
         0: aload_0
         1: invokespecial #1                  // Method org/apache/commons/lang3/builder/ToStringStyle."<init>":()V
         4: return
      LineNumberTable:
        line 43: 0
        line 44: 4
      LocalVariableTable:
        Start  Length  Slot  Name   Signature
            0       5     0  this   Lorg/apache/commons/lang3/builder/StandardToStringStyle;

  public boolean isUseClassName();
    descriptor: ()Z
    flags: (0x0001) ACC_PUBLIC
    Code:
      stack=1, locals=1, args_size=1
         0: aload_0
         1: invokespecial #2                  // Method org/apache/commons/lang3/builder/ToStringStyle.isUseClassName:()Z
         4: ireturn
      LineNumberTable:
        line 55: 0
      LocalVariableTable:
        Start  Length  Slot  Name   Signature
            0       5     0  this   Lorg/apache/commons/lang3/builder/StandardToStringStyle;

  public void setUseClassName(boolean);
    descriptor: (Z)V
    flags: (0x0001) ACC_PUBLIC
    Code:
      stack=2, locals=2, args_size=2
         0: aload_0
         1: iload_1
         2: invokespecial #3                  // Method org/apache/commons/lang3/builder/ToStringStyle.setUseClassName:(Z)V
         5: return
      LineNumberTable:
        line 65: 0
        line 66: 5
      LocalVariableTable:
        Start  Length  Slot  Name   Signature
            0       6     0  this   Lorg/apache/commons/lang3/builder/StandardToStringStyle;
            0       6     1 useClassName   Z

  public boolean isUseShortClassName();
    descriptor: ()Z
    flags: (0x0001) ACC_PUBLIC
    Code:
      stack=1, locals=1, args_size=1
         0: aload_0
         1: invokespecial #4                  // Method org/apache/commons/lang3/builder/ToStringStyle.isUseShortClassName:()Z
         4: ireturn
      LineNumberTable:
        line 78: 0
      LocalVariableTable:
        Start  Length  Slot  Name   Signature
            0       5     0  this   Lorg/apache/commons/lang3/builder/StandardToStringStyle;

  public void setUseShortClassName(boolean);
    descriptor: (Z)V
    flags: (0x0001) ACC_PUBLIC
    Code:
      stack=2, locals=2, args_size=2
         0: aload_0
         1: iload_1
         2: invokespecial #5                  // Method org/apache/commons/lang3/builder/ToStringStyle.setUseShortClassName:(Z)V
         5: return
      LineNumberTable:
        line 89: 0
        line 90: 5
      LocalVariableTable:
        Start  Length  Slot  Name   Signature
            0       6     0  this   Lorg/apache/commons/lang3/builder/StandardToStringStyle;
            0       6     1 useShortClassName   Z

  public boolean isUseIdentityHashCode();
    descriptor: ()Z
    flags: (0x0001) ACC_PUBLIC
    Code:
      stack=1, locals=1, args_size=1
         0: aload_0
         1: invokespecial #6                  // Method org/apache/commons/lang3/builder/ToStringStyle.isUseIdentityHashCode:()Z
         4: ireturn
      LineNumberTable:
        line 100: 0
      LocalVariableTable:
        Start  Length  Slot  Name   Signature
            0       5     0  this   Lorg/apache/commons/lang3/builder/StandardToStringStyle;

  public void setUseIdentityHashCode(boolean);
    descriptor: (Z)V
    flags: (0x0001) ACC_PUBLIC
    Code:
      stack=2, locals=2, args_size=2
         0: aload_0
         1: iload_1
         2: invokespecial #7                  // Method org/apache/commons/lang3/builder/ToStringStyle.setUseIdentityHashCode:(Z)V
         5: return
      LineNumberTable:
        line 110: 0
        line 111: 5
      LocalVariableTable:
        Start  Length  Slot  Name   Signature
            0       6     0  this   Lorg/apache/commons/lang3/builder/StandardToStringStyle;
            0       6     1 useIdentityHashCode   Z

  public boolean isUseFieldNames();
    descriptor: ()Z
    flags: (0x0001) ACC_PUBLIC
    Code:
      stack=1, locals=1, args_size=1
         0: aload_0
         1: invokespecial #8                  // Method org/apache/commons/lang3/builder/ToStringStyle.isUseFieldNames:()Z
         4: ireturn
      LineNumberTable:
        line 122: 0
      LocalVariableTable:
        Start  Length  Slot  Name   Signature
            0       5     0  this   Lorg/apache/commons/lang3/builder/StandardToStringStyle;

  public void setUseFieldNames(boolean);
    descriptor: (Z)V
    flags: (0x0001) ACC_PUBLIC
    Code:
      stack=2, locals=2, args_size=2
         0: aload_0
         1: iload_1
         2: invokespecial #9                  // Method org/apache/commons/lang3/builder/ToStringStyle.setUseFieldNames:(Z)V
         5: return
      LineNumberTable:
        line 132: 0
        line 133: 5
      LocalVariableTable:
        Start  Length  Slot  Name   Signature
            0       6     0  this   Lorg/apache/commons/lang3/builder/StandardToStringStyle;
            0       6     1 useFieldNames   Z

  public boolean isDefaultFullDetail();
    descriptor: ()Z
    flags: (0x0001) ACC_PUBLIC
    Code:
      stack=1, locals=1, args_size=1
         0: aload_0
         1: invokespecial #10                 // Method org/apache/commons/lang3/builder/ToStringStyle.isDefaultFullDetail:()Z
         4: ireturn
      LineNumberTable:
        line 145: 0
      LocalVariableTable:
        Start  Length  Slot  Name   Signature
            0       5     0  this   Lorg/apache/commons/lang3/builder/StandardToStringStyle;

  public void setDefaultFullDetail(boolean);
    descriptor: (Z)V
    flags: (0x0001) ACC_PUBLIC
    Code:
      stack=2, locals=2, args_size=2
         0: aload_0
         1: iload_1
         2: invokespecial #11                 // Method org/apache/commons/lang3/builder/ToStringStyle.setDefaultFullDetail:(Z)V
         5: return
      LineNumberTable:
        line 156: 0
        line 157: 5
      LocalVariableTable:
        Start  Length  Slot  Name   Signature
            0       6     0  this   Lorg/apache/commons/lang3/builder/StandardToStringStyle;
            0       6     1 defaultFullDetail   Z

  public boolean isArrayContentDetail();
    descriptor: ()Z
    flags: (0x0001) ACC_PUBLIC
    Code:
      stack=1, locals=1, args_size=1
         0: aload_0
         1: invokespecial #12                 // Method org/apache/commons/lang3/builder/ToStringStyle.isArrayContentDetail:()Z
         4: ireturn
      LineNumberTable:
        line 168: 0
      LocalVariableTable:
        Start  Length  Slot  Name   Signature
            0       5     0  this   Lorg/apache/commons/lang3/builder/StandardToStringStyle;

  public void setArrayContentDetail(boolean);
    descriptor: (Z)V
    flags: (0x0001) ACC_PUBLIC
    Code:
      stack=2, locals=2, args_size=2
         0: aload_0
         1: iload_1
         2: invokespecial #13                 // Method org/apache/commons/lang3/builder/ToStringStyle.setArrayContentDetail:(Z)V
         5: return
      LineNumberTable:
        line 178: 0
        line 179: 5
      LocalVariableTable:
        Start  Length  Slot  Name   Signature
            0       6     0  this   Lorg/apache/commons/lang3/builder/StandardToStringStyle;
            0       6     1 arrayContentDetail   Z

  public java.lang.String getArrayStart();
    descriptor: ()Ljava/lang/String;
    flags: (0x0001) ACC_PUBLIC
    Code:
      stack=1, locals=1, args_size=1
         0: aload_0
         1: invokespecial #14                 // Method org/apache/commons/lang3/builder/ToStringStyle.getArrayStart:()Ljava/lang/String;
         4: areturn
      LineNumberTable:
        line 190: 0
      LocalVariableTable:
        Start  Length  Slot  Name   Signature
            0       5     0  this   Lorg/apache/commons/lang3/builder/StandardToStringStyle;

  public void setArrayStart(java.lang.String);
    descriptor: (Ljava/lang/String;)V
    flags: (0x0001) ACC_PUBLIC
    Code:
      stack=2, locals=2, args_size=2
         0: aload_0
         1: aload_1
         2: invokespecial #15                 // Method org/apache/commons/lang3/builder/ToStringStyle.setArrayStart:(Ljava/lang/String;)V
         5: return
      LineNumberTable:
        line 203: 0
        line 204: 5
      LocalVariableTable:
        Start  Length  Slot  Name   Signature
            0       6     0  this   Lorg/apache/commons/lang3/builder/StandardToStringStyle;
            0       6     1 arrayStart   Ljava/lang/String;

  public java.lang.String getArrayEnd();
    descriptor: ()Ljava/lang/String;
    flags: (0x0001) ACC_PUBLIC
    Code:
      stack=1, locals=1, args_size=1
         0: aload_0
         1: invokespecial #16                 // Method org/apache/commons/lang3/builder/ToStringStyle.getArrayEnd:()Ljava/lang/String;
         4: areturn
      LineNumberTable:
        line 215: 0
      LocalVariableTable:
        Start  Length  Slot  Name   Signature
            0       5     0  this   Lorg/apache/commons/lang3/builder/StandardToStringStyle;

  public void setArrayEnd(java.lang.String);
    descriptor: (Ljava/lang/String;)V
    flags: (0x0001) ACC_PUBLIC
    Code:
      stack=2, locals=2, args_size=2
         0: aload_0
         1: aload_1
         2: invokespecial #17                 // Method org/apache/commons/lang3/builder/ToStringStyle.setArrayEnd:(Ljava/lang/String;)V
         5: return
      LineNumberTable:
        line 228: 0
        line 229: 5
      LocalVariableTable:
        Start  Length  Slot  Name   Signature
            0       6     0  this   Lorg/apache/commons/lang3/builder/StandardToStringStyle;
            0       6     1 arrayEnd   Ljava/lang/String;

  public java.lang.String getArraySeparator();
    descriptor: ()Ljava/lang/String;
    flags: (0x0001) ACC_PUBLIC
    Code:
      stack=1, locals=1, args_size=1
         0: aload_0
         1: invokespecial #18                 // Method org/apache/commons/lang3/builder/ToStringStyle.getArraySeparator:()Ljava/lang/String;
         4: areturn
      LineNumberTable:
        line 240: 0
      LocalVariableTable:
        Start  Length  Slot  Name   Signature
            0       5     0  this   Lorg/apache/commons/lang3/builder/StandardToStringStyle;

  public void setArraySeparator(java.lang.String);
    descriptor: (Ljava/lang/String;)V
    flags: (0x0001) ACC_PUBLIC
    Code:
      stack=2, locals=2, args_size=2
         0: aload_0
         1: aload_1
         2: invokespecial #19                 // Method org/apache/commons/lang3/builder/ToStringStyle.setArraySeparator:(Ljava/lang/String;)V
         5: return
      LineNumberTable:
        line 253: 0
        line 254: 5
      LocalVariableTable:
        Start  Length  Slot  Name   Signature
            0       6     0  this   Lorg/apache/commons/lang3/builder/StandardToStringStyle;
            0       6     1 arraySeparator   Ljava/lang/String;

  public java.lang.String getContentStart();
    descriptor: ()Ljava/lang/String;
    flags: (0x0001) ACC_PUBLIC
    Code:
      stack=1, locals=1, args_size=1
         0: aload_0
         1: invokespecial #20                 // Method org/apache/commons/lang3/builder/ToStringStyle.getContentStart:()Ljava/lang/String;
         4: areturn
      LineNumberTable:
        line 265: 0
      LocalVariableTable:
        Start  Length  Slot  Name   Signature
            0       5     0  this   Lorg/apache/commons/lang3/builder/StandardToStringStyle;

  public void setContentStart(java.lang.String);
    descriptor: (Ljava/lang/String;)V
    flags: (0x0001) ACC_PUBLIC
    Code:
      stack=2, locals=2, args_size=2
         0: aload_0
         1: aload_1
         2: invokespecial #21                 // Method org/apache/commons/lang3/builder/ToStringStyle.setContentStart:(Ljava/lang/String;)V
         5: return
      LineNumberTable:
        line 278: 0
        line 279: 5
      LocalVariableTable:
        Start  Length  Slot  Name   Signature
            0       6     0  this   Lorg/apache/commons/lang3/builder/StandardToStringStyle;
            0       6     1 contentStart   Ljava/lang/String;

  public java.lang.String getContentEnd();
    descriptor: ()Ljava/lang/String;
    flags: (0x0001) ACC_PUBLIC
    Code:
      stack=1, locals=1, args_size=1
         0: aload_0
         1: invokespecial #22                 // Method org/apache/commons/lang3/builder/ToStringStyle.getContentEnd:()Ljava/lang/String;
         4: areturn
      LineNumberTable:
        line 290: 0
      LocalVariableTable:
        Start  Length  Slot  Name   Signature
            0       5     0  this   Lorg/apache/commons/lang3/builder/StandardToStringStyle;

  public void setContentEnd(java.lang.String);
    descriptor: (Ljava/lang/String;)V
    flags: (0x0001) ACC_PUBLIC
    Code:
      stack=2, locals=2, args_size=2
         0: aload_0
         1: aload_1
         2: invokespecial #23                 // Method org/apache/commons/lang3/builder/ToStringStyle.setContentEnd:(Ljava/lang/String;)V
         5: return
      LineNumberTable:
        line 303: 0
        line 304: 5
      LocalVariableTable:
        Start  Length  Slot  Name   Signature
            0       6     0  this   Lorg/apache/commons/lang3/builder/StandardToStringStyle;
            0       6     1 contentEnd   Ljava/lang/String;

  public java.lang.String getFieldNameValueSeparator();
    descriptor: ()Ljava/lang/String;
    flags: (0x0001) ACC_PUBLIC
    Code:
      stack=1, locals=1, args_size=1
         0: aload_0
         1: invokespecial #24                 // Method org/apache/commons/lang3/builder/ToStringStyle.getFieldNameValueSeparator:()Ljava/lang/String;
         4: areturn
      LineNumberTable:
        line 315: 0
      LocalVariableTable:
        Start  Length  Slot  Name   Signature
            0       5     0  this   Lorg/apache/commons/lang3/builder/StandardToStringStyle;

  public void setFieldNameValueSeparator(java.lang.String);
    descriptor: (Ljava/lang/String;)V
    flags: (0x0001) ACC_PUBLIC
    Code:
      stack=2, locals=2, args_size=2
         0: aload_0
         1: aload_1
         2: invokespecial #25                 // Method org/apache/commons/lang3/builder/ToStringStyle.setFieldNameValueSeparator:(Ljava/lang/String;)V
         5: return
      LineNumberTable:
        line 328: 0
        line 329: 5
      LocalVariableTable:
        Start  Length  Slot  Name   Signature
            0       6     0  this   Lorg/apache/commons/lang3/builder/StandardToStringStyle;
            0       6     1 fieldNameValueSeparator   Ljava/lang/String;

  public java.lang.String getFieldSeparator();
    descriptor: ()Ljava/lang/String;
    flags: (0x0001) ACC_PUBLIC
    Code:
      stack=1, locals=1, args_size=1
         0: aload_0
         1: invokespecial #26                 // Method org/apache/commons/lang3/builder/ToStringStyle.getFieldSeparator:()Ljava/lang/String;
         4: areturn
      LineNumberTable:
        line 340: 0
      LocalVariableTable:
        Start  Length  Slot  Name   Signature
            0       5     0  this   Lorg/apache/commons/lang3/builder/StandardToStringStyle;

  public void setFieldSeparator(java.lang.String);
    descriptor: (Ljava/lang/String;)V
    flags: (0x0001) ACC_PUBLIC
    Code:
      stack=2, locals=2, args_size=2
         0: aload_0
         1: aload_1
         2: invokespecial #27                 // Method org/apache/commons/lang3/builder/ToStringStyle.setFieldSeparator:(Ljava/lang/String;)V
         5: return
      LineNumberTable:
        line 353: 0
        line 354: 5
      LocalVariableTable:
        Start  Length  Slot  Name   Signature
            0       6     0  this   Lorg/apache/commons/lang3/builder/StandardToStringStyle;
            0       6     1 fieldSeparator   Ljava/lang/String;

  public boolean isFieldSeparatorAtStart();
    descriptor: ()Z
    flags: (0x0001) ACC_PUBLIC
    Code:
      stack=1, locals=1, args_size=1
         0: aload_0
         1: invokespecial #28                 // Method org/apache/commons/lang3/builder/ToStringStyle.isFieldSeparatorAtStart:()Z
         4: ireturn
      LineNumberTable:
        line 367: 0
      LocalVariableTable:
        Start  Length  Slot  Name   Signature
            0       5     0  this   Lorg/apache/commons/lang3/builder/StandardToStringStyle;

  public void setFieldSeparatorAtStart(boolean);
    descriptor: (Z)V
    flags: (0x0001) ACC_PUBLIC
    Code:
      stack=2, locals=2, args_size=2
         0: aload_0
         1: iload_1
         2: invokespecial #29                 // Method org/apache/commons/lang3/builder/ToStringStyle.setFieldSeparatorAtStart:(Z)V
         5: return
      LineNumberTable:
        line 379: 0
        line 380: 5
      LocalVariableTable:
        Start  Length  Slot  Name   Signature
            0       6     0  this   Lorg/apache/commons/lang3/builder/StandardToStringStyle;
            0       6     1 fieldSeparatorAtStart   Z

  public boolean isFieldSeparatorAtEnd();
    descriptor: ()Z
    flags: (0x0001) ACC_PUBLIC
    Code:
      stack=1, locals=1, args_size=1
         0: aload_0
         1: invokespecial #30                 // Method org/apache/commons/lang3/builder/ToStringStyle.isFieldSeparatorAtEnd:()Z
         4: ireturn
      LineNumberTable:
        line 393: 0
      LocalVariableTable:
        Start  Length  Slot  Name   Signature
            0       5     0  this   Lorg/apache/commons/lang3/builder/StandardToStringStyle;

  public void setFieldSeparatorAtEnd(boolean);
    descriptor: (Z)V
    flags: (0x0001) ACC_PUBLIC
    Code:
      stack=2, locals=2, args_size=2
         0: aload_0
         1: iload_1
         2: invokespecial #31                 // Method org/apache/commons/lang3/builder/ToStringStyle.setFieldSeparatorAtEnd:(Z)V
         5: return
      LineNumberTable:
        line 405: 0
        line 406: 5
      LocalVariableTable:
        Start  Length  Slot  Name   Signature
            0       6     0  this   Lorg/apache/commons/lang3/builder/StandardToStringStyle;
            0       6     1 fieldSeparatorAtEnd   Z

  public java.lang.String getNullText();
    descriptor: ()Ljava/lang/String;
    flags: (0x0001) ACC_PUBLIC
    Code:
      stack=1, locals=1, args_size=1
         0: aload_0
         1: invokespecial #32                 // Method org/apache/commons/lang3/builder/ToStringStyle.getNullText:()Ljava/lang/String;
         4: areturn
      LineNumberTable:
        line 417: 0
      LocalVariableTable:
        Start  Length  Slot  Name   Signature
            0       5     0  this   Lorg/apache/commons/lang3/builder/StandardToStringStyle;

  public void setNullText(java.lang.String);
    descriptor: (Ljava/lang/String;)V
    flags: (0x0001) ACC_PUBLIC
    Code:
      stack=2, locals=2, args_size=2
         0: aload_0
         1: aload_1
         2: invokespecial #33                 // Method org/apache/commons/lang3/builder/ToStringStyle.setNullText:(Ljava/lang/String;)V
         5: return
      LineNumberTable:
        line 430: 0
        line 431: 5
      LocalVariableTable:
        Start  Length  Slot  Name   Signature
            0       6     0  this   Lorg/apache/commons/lang3/builder/StandardToStringStyle;
            0       6     1 nullText   Ljava/lang/String;

  public java.lang.String getSizeStartText();
    descriptor: ()Ljava/lang/String;
    flags: (0x0001) ACC_PUBLIC
    Code:
      stack=1, locals=1, args_size=1
         0: aload_0
         1: invokespecial #34                 // Method org/apache/commons/lang3/builder/ToStringStyle.getSizeStartText:()Ljava/lang/String;
         4: areturn
      LineNumberTable:
        line 445: 0
      LocalVariableTable:
        Start  Length  Slot  Name   Signature
            0       5     0  this   Lorg/apache/commons/lang3/builder/StandardToStringStyle;

  public void setSizeStartText(java.lang.String);
    descriptor: (Ljava/lang/String;)V
    flags: (0x0001) ACC_PUBLIC
    Code:
      stack=2, locals=2, args_size=2
         0: aload_0
         1: aload_1
         2: invokespecial #35                 // Method org/apache/commons/lang3/builder/ToStringStyle.setSizeStartText:(Ljava/lang/String;)V
         5: return
      LineNumberTable:
        line 461: 0
        line 462: 5
      LocalVariableTable:
        Start  Length  Slot  Name   Signature
            0       6     0  this   Lorg/apache/commons/lang3/builder/StandardToStringStyle;
            0       6     1 sizeStartText   Ljava/lang/String;

  public java.lang.String getSizeEndText();
    descriptor: ()Ljava/lang/String;
    flags: (0x0001) ACC_PUBLIC
    Code:
      stack=1, locals=1, args_size=1
         0: aload_0
         1: invokespecial #36                 // Method org/apache/commons/lang3/builder/ToStringStyle.getSizeEndText:()Ljava/lang/String;
         4: areturn
      LineNumberTable:
        line 476: 0
      LocalVariableTable:
        Start  Length  Slot  Name   Signature
            0       5     0  this   Lorg/apache/commons/lang3/builder/StandardToStringStyle;

  public void setSizeEndText(java.lang.String);
    descriptor: (Ljava/lang/String;)V
    flags: (0x0001) ACC_PUBLIC
    Code:
      stack=2, locals=2, args_size=2
         0: aload_0
         1: aload_1
         2: invokespecial #37                 // Method org/apache/commons/lang3/builder/ToStringStyle.setSizeEndText:(Ljava/lang/String;)V
         5: return
      LineNumberTable:
        line 492: 0
        line 493: 5
      LocalVariableTable:
        Start  Length  Slot  Name   Signature
            0       6     0  this   Lorg/apache/commons/lang3/builder/StandardToStringStyle;
            0       6     1 sizeEndText   Ljava/lang/String;

  public java.lang.String getSummaryObjectStartText();
    descriptor: ()Ljava/lang/String;
    flags: (0x0001) ACC_PUBLIC
    Code:
      stack=1, locals=1, args_size=1
         0: aload_0
         1: invokespecial #38                 // Method org/apache/commons/lang3/builder/ToStringStyle.getSummaryObjectStartText:()Ljava/lang/String;
         4: areturn
      LineNumberTable:
        line 507: 0
      LocalVariableTable:
        Start  Length  Slot  Name   Signature
            0       5     0  this   Lorg/apache/commons/lang3/builder/StandardToStringStyle;

  public void setSummaryObjectStartText(java.lang.String);
    descriptor: (Ljava/lang/String;)V
    flags: (0x0001) ACC_PUBLIC
    Code:
      stack=2, locals=2, args_size=2
         0: aload_0
         1: aload_1
         2: invokespecial #39                 // Method org/apache/commons/lang3/builder/ToStringStyle.setSummaryObjectStartText:(Ljava/lang/String;)V
         5: return
      LineNumberTable:
        line 523: 0
        line 524: 5
      LocalVariableTable:
        Start  Length  Slot  Name   Signature
            0       6     0  this   Lorg/apache/commons/lang3/builder/StandardToStringStyle;
            0       6     1 summaryObjectStartText   Ljava/lang/String;

  public java.lang.String getSummaryObjectEndText();
    descriptor: ()Ljava/lang/String;
    flags: (0x0001) ACC_PUBLIC
    Code:
      stack=1, locals=1, args_size=1
         0: aload_0
         1: invokespecial #40                 // Method org/apache/commons/lang3/builder/ToStringStyle.getSummaryObjectEndText:()Ljava/lang/String;
         4: areturn
      LineNumberTable:
        line 538: 0
      LocalVariableTable:
        Start  Length  Slot  Name   Signature
            0       5     0  this   Lorg/apache/commons/lang3/builder/StandardToStringStyle;

  public void setSummaryObjectEndText(java.lang.String);
    descriptor: (Ljava/lang/String;)V
    flags: (0x0001) ACC_PUBLIC
    Code:
      stack=2, locals=2, args_size=2
         0: aload_0
         1: aload_1
         2: invokespecial #41                 // Method org/apache/commons/lang3/builder/ToStringStyle.setSummaryObjectEndText:(Ljava/lang/String;)V
         5: return
      LineNumberTable:
        line 554: 0
        line 555: 5
      LocalVariableTable:
        Start  Length  Slot  Name   Signature
            0       6     0  this   Lorg/apache/commons/lang3/builder/StandardToStringStyle;
            0       6     1 summaryObjectEndText   Ljava/lang/String;
}
SourceFile: "StandardToStringStyle.java"
