Classfile /Users/mw/Projects/slang-braindump/.jar/jar11/assemble/slang-braindump/assemble/content/org/apache/commons/lang3/builder/ToStringStyle$MultiLineToStringStyle.class
  Last modified May 29, 2022; size 1151 bytes
  SHA-256 checksum dc2ae93984cf6b4c2d8c0a5fd4d960d3242d413d5b90a6b26eba9d983484af4e
  Compiled from "ToStringStyle.java"
final class org.apache.commons.lang3.builder.ToStringStyle$MultiLineToStringStyle extends org.apache.commons.lang3.builder.ToStringStyle
  minor version: 0
  major version: 52
  flags: (0x0030) ACC_FINAL, ACC_SUPER
  this_class: #15                         // org/apache/commons/lang3/builder/ToStringStyle$MultiLineToStringStyle
  super_class: #16                        // org/apache/commons/lang3/builder/ToStringStyle
  interfaces: 0, fields: 1, methods: 2, attributes: 2
Constant pool:
   #1 = Methodref          #16.#35        // org/apache/commons/lang3/builder/ToStringStyle."<init>":()V
   #2 = String             #36            // [
   #3 = Methodref          #15.#37        // org/apache/commons/lang3/builder/ToStringStyle$MultiLineToStringStyle.setContentStart:(Ljava/lang/String;)V
   #4 = Class              #38            // java/lang/StringBuilder
   #5 = Methodref          #4.#35         // java/lang/StringBuilder."<init>":()V
   #6 = Methodref          #39.#40        // java/lang/System.lineSeparator:()Ljava/lang/String;
   #7 = Methodref          #4.#41         // java/lang/StringBuilder.append:(Ljava/lang/String;)Ljava/lang/StringBuilder;
   #8 = String             #42            //
   #9 = Methodref          #4.#43         // java/lang/StringBuilder.toString:()Ljava/lang/String;
  #10 = Methodref          #15.#44        // org/apache/commons/lang3/builder/ToStringStyle$MultiLineToStringStyle.setFieldSeparator:(Ljava/lang/String;)V
  #11 = Methodref          #15.#45        // org/apache/commons/lang3/builder/ToStringStyle$MultiLineToStringStyle.setFieldSeparatorAtStart:(Z)V
  #12 = String             #46            // ]
  #13 = Methodref          #15.#47        // org/apache/commons/lang3/builder/ToStringStyle$MultiLineToStringStyle.setContentEnd:(Ljava/lang/String;)V
  #14 = Fieldref           #15.#48        // org/apache/commons/lang3/builder/ToStringStyle$MultiLineToStringStyle.MULTI_LINE_STYLE:Lorg/apache/commons/lang3/builder/ToStringStyle;
  #15 = Class              #49            // org/apache/commons/lang3/builder/ToStringStyle$MultiLineToStringStyle
  #16 = Class              #50            // org/apache/commons/lang3/builder/ToStringStyle
  #17 = Utf8               serialVersionUID
  #18 = Utf8               J
  #19 = Utf8               ConstantValue
  #20 = Long               1l
  #22 = Utf8               <init>
  #23 = Utf8               ()V
  #24 = Utf8               Code
  #25 = Utf8               LineNumberTable
  #26 = Utf8               LocalVariableTable
  #27 = Utf8               this
  #28 = Utf8               MultiLineToStringStyle
  #29 = Utf8               InnerClasses
  #30 = Utf8               Lorg/apache/commons/lang3/builder/ToStringStyle$MultiLineToStringStyle;
  #31 = Utf8               readResolve
  #32 = Utf8               ()Ljava/lang/Object;
  #33 = Utf8               SourceFile
  #34 = Utf8               ToStringStyle.java
  #35 = NameAndType        #22:#23        // "<init>":()V
  #36 = Utf8               [
  #37 = NameAndType        #51:#52        // setContentStart:(Ljava/lang/String;)V
  #38 = Utf8               java/lang/StringBuilder
  #39 = Class              #53            // java/lang/System
  #40 = NameAndType        #54:#55        // lineSeparator:()Ljava/lang/String;
  #41 = NameAndType        #56:#57        // append:(Ljava/lang/String;)Ljava/lang/StringBuilder;
  #42 = Utf8
  #43 = NameAndType        #58:#55        // toString:()Ljava/lang/String;
  #44 = NameAndType        #59:#52        // setFieldSeparator:(Ljava/lang/String;)V
  #45 = NameAndType        #60:#61        // setFieldSeparatorAtStart:(Z)V
  #46 = Utf8               ]
  #47 = NameAndType        #62:#52        // setContentEnd:(Ljava/lang/String;)V
  #48 = NameAndType        #63:#64        // MULTI_LINE_STYLE:Lorg/apache/commons/lang3/builder/ToStringStyle;
  #49 = Utf8               org/apache/commons/lang3/builder/ToStringStyle$MultiLineToStringStyle
  #50 = Utf8               org/apache/commons/lang3/builder/ToStringStyle
  #51 = Utf8               setContentStart
  #52 = Utf8               (Ljava/lang/String;)V
  #53 = Utf8               java/lang/System
  #54 = Utf8               lineSeparator
  #55 = Utf8               ()Ljava/lang/String;
  #56 = Utf8               append
  #57 = Utf8               (Ljava/lang/String;)Ljava/lang/StringBuilder;
  #58 = Utf8               toString
  #59 = Utf8               setFieldSeparator
  #60 = Utf8               setFieldSeparatorAtStart
  #61 = Utf8               (Z)V
  #62 = Utf8               setContentEnd
  #63 = Utf8               MULTI_LINE_STYLE
  #64 = Utf8               Lorg/apache/commons/lang3/builder/ToStringStyle;
{
  private static final long serialVersionUID;
    descriptor: J
    flags: (0x001a) ACC_PRIVATE, ACC_STATIC, ACC_FINAL
    ConstantValue: long 1l

  org.apache.commons.lang3.builder.ToStringStyle$MultiLineToStringStyle();
    descriptor: ()V
    flags: (0x0000)
    Code:
      stack=3, locals=1, args_size=1
         0: aload_0
         1: invokespecial #1                  // Method org/apache/commons/lang3/builder/ToStringStyle."<init>":()V
         4: aload_0
         5: ldc           #2                  // String [
         7: invokevirtual #3                  // Method setContentStart:(Ljava/lang/String;)V
        10: aload_0
        11: new           #4                  // class java/lang/StringBuilder
        14: dup
        15: invokespecial #5                  // Method java/lang/StringBuilder."<init>":()V
        18: invokestatic  #6                  // Method java/lang/System.lineSeparator:()Ljava/lang/String;
        21: invokevirtual #7                  // Method java/lang/StringBuilder.append:(Ljava/lang/String;)Ljava/lang/StringBuilder;
        24: ldc           #8                  // String
        26: invokevirtual #7                  // Method java/lang/StringBuilder.append:(Ljava/lang/String;)Ljava/lang/StringBuilder;
        29: invokevirtual #9                  // Method java/lang/StringBuilder.toString:()Ljava/lang/String;
        32: invokevirtual #10                 // Method setFieldSeparator:(Ljava/lang/String;)V
        35: aload_0
        36: iconst_1
        37: invokevirtual #11                 // Method setFieldSeparatorAtStart:(Z)V
        40: aload_0
        41: new           #4                  // class java/lang/StringBuilder
        44: dup
        45: invokespecial #5                  // Method java/lang/StringBuilder."<init>":()V
        48: invokestatic  #6                  // Method java/lang/System.lineSeparator:()Ljava/lang/String;
        51: invokevirtual #7                  // Method java/lang/StringBuilder.append:(Ljava/lang/String;)Ljava/lang/StringBuilder;
        54: ldc           #12                 // String ]
        56: invokevirtual #7                  // Method java/lang/StringBuilder.append:(Ljava/lang/String;)Ljava/lang/StringBuilder;
        59: invokevirtual #9                  // Method java/lang/StringBuilder.toString:()Ljava/lang/String;
        62: invokevirtual #13                 // Method setContentEnd:(Ljava/lang/String;)V
        65: return
      LineNumberTable:
        line 2295: 0
        line 2296: 4
        line 2297: 10
        line 2298: 35
        line 2299: 40
        line 2300: 65
      LocalVariableTable:
        Start  Length  Slot  Name   Signature
            0      66     0  this   Lorg/apache/commons/lang3/builder/ToStringStyle$MultiLineToStringStyle;

  private java.lang.Object readResolve();
    descriptor: ()Ljava/lang/Object;
    flags: (0x0002) ACC_PRIVATE
    Code:
      stack=1, locals=1, args_size=1
         0: getstatic     #14                 // Field MULTI_LINE_STYLE:Lorg/apache/commons/lang3/builder/ToStringStyle;
         3: areturn
      LineNumberTable:
        line 2308: 0
      LocalVariableTable:
        Start  Length  Slot  Name   Signature
            0       4     0  this   Lorg/apache/commons/lang3/builder/ToStringStyle$MultiLineToStringStyle;
}
SourceFile: "ToStringStyle.java"
InnerClasses:
  private static final #28= #15 of #16;   // MultiLineToStringStyle=class org/apache/commons/lang3/builder/ToStringStyle$MultiLineToStringStyle of class org/apache/commons/lang3/builder/ToStringStyle
