Classfile /Users/mw/Projects/slang-braindump/.jar/jar11/assemble/slang-braindump/assemble/content/scala/runtime/LambdaDeserialize$.class
  Last modified May 29, 2022; size 2924 bytes
  SHA-256 checksum 4de477b3f1056ce8cde3262aa92eeae68dc749c8a84533c59be70aaf565767a8
  Compiled from "LambdaDeserialize.scala"
public final class scala.runtime.LambdaDeserialize$
  minor version: 0
  major version: 52
  flags: (0x0031) ACC_PUBLIC, ACC_FINAL, ACC_SUPER
  this_class: #2                          // scala/runtime/LambdaDeserialize$
  super_class: #4                         // java/lang/Object
  interfaces: 0, fields: 1, methods: 5, attributes: 4
Constant pool:
    #1 = Utf8               scala/runtime/LambdaDeserialize$
    #2 = Class              #1            // scala/runtime/LambdaDeserialize$
    #3 = Utf8               java/lang/Object
    #4 = Class              #3            // java/lang/Object
    #5 = Utf8               LambdaDeserialize.scala
    #6 = Utf8               java/lang/invoke/MethodHandles$Lookup
    #7 = Class              #6            // java/lang/invoke/MethodHandles$Lookup
    #8 = Utf8               java/lang/invoke/MethodHandles
    #9 = Class              #8            // java/lang/invoke/MethodHandles
   #10 = Utf8               Lookup
   #11 = Utf8               MODULE$
   #12 = Utf8               Lscala/runtime/LambdaDeserialize$;
   #13 = Utf8               <clinit>
   #14 = Utf8               ()V
   #15 = Utf8               <init>
   #16 = NameAndType        #15:#14       // "<init>":()V
   #17 = Methodref          #2.#16        // scala/runtime/LambdaDeserialize$."<init>":()V
   #18 = NameAndType        #11:#12       // MODULE$:Lscala/runtime/LambdaDeserialize$;
   #19 = Fieldref           #2.#18        // scala/runtime/LambdaDeserialize$.MODULE$:Lscala/runtime/LambdaDeserialize$;
   #20 = Utf8               bootstrap
   #21 = Utf8               (Ljava/lang/invoke/MethodHandles$Lookup;Ljava/lang/String;Ljava/lang/invoke/MethodType;[Ljava/lang/invoke/MethodHandle;)Ljava/lang/invoke/CallSite;
   #22 = Utf8               lookup
   #23 = Utf8               invokedName
   #24 = Utf8               invokedType
   #25 = Utf8               targetMethods
   #26 = Utf8               scala/runtime/ScalaRunTime$
   #27 = Class              #26           // scala/runtime/ScalaRunTime$
   #28 = Utf8               Lscala/runtime/ScalaRunTime$;
   #29 = NameAndType        #11:#28       // MODULE$:Lscala/runtime/ScalaRunTime$;
   #30 = Fieldref           #27.#29       // scala/runtime/ScalaRunTime$.MODULE$:Lscala/runtime/ScalaRunTime$;
   #31 = Utf8               wrapRefArray
   #32 = Utf8               ([Ljava/lang/Object;)Lscala/collection/immutable/ArraySeq;
   #33 = NameAndType        #31:#32       // wrapRefArray:([Ljava/lang/Object;)Lscala/collection/immutable/ArraySeq;
   #34 = Methodref          #27.#33       // scala/runtime/ScalaRunTime$.wrapRefArray:([Ljava/lang/Object;)Lscala/collection/immutable/ArraySeq;
   #35 = Utf8               (Ljava/lang/invoke/MethodHandles$Lookup;Ljava/lang/String;Ljava/lang/invoke/MethodType;Lscala/collection/immutable/Seq;)Ljava/lang/invoke/CallSite;
   #36 = NameAndType        #20:#35       // bootstrap:(Ljava/lang/invoke/MethodHandles$Lookup;Ljava/lang/String;Ljava/lang/invoke/MethodType;Lscala/collection/immutable/Seq;)Ljava/lang/invoke/CallSite;
   #37 = Methodref          #2.#36        // scala/runtime/LambdaDeserialize$.bootstrap:(Ljava/lang/invoke/MethodHandles$Lookup;Ljava/lang/String;Ljava/lang/invoke/MethodType;Lscala/collection/immutable/Seq;)Ljava/lang/invoke/CallSite;
   #38 = Utf8               this
   #39 = Utf8               Ljava/lang/invoke/MethodHandles$Lookup;
   #40 = Utf8               Ljava/lang/String;
   #41 = Utf8               Ljava/lang/invoke/MethodType;
   #42 = Utf8               [Ljava/lang/invoke/MethodHandle;
   #43 = Utf8               (Ljava/lang/invoke/MethodHandles$Lookup;Ljava/lang/String;Ljava/lang/invoke/MethodType;Lscala/collection/immutable/Seq<Ljava/lang/invoke/MethodHandle;>;)Ljava/lang/invoke/CallSite;^Ljava/lang/Throwable;
   #44 = Utf8               java/lang/Throwable
   #45 = Class              #44           // java/lang/Throwable
   #46 = Utf8               scala/collection/immutable/ArraySeq
   #47 = Class              #46           // scala/collection/immutable/ArraySeq
   #48 = Utf8               unsafeArray
   #49 = Utf8               ()Ljava/lang/Object;
   #50 = NameAndType        #48:#49       // unsafeArray:()Ljava/lang/Object;
   #51 = Methodref          #47.#50       // scala/collection/immutable/ArraySeq.unsafeArray:()Ljava/lang/Object;
   #52 = Class              #42           // "[Ljava/lang/invoke/MethodHandle;"
   #53 = Utf8               scala/runtime/MethodHandleConstants
   #54 = Class              #53           // scala/runtime/MethodHandleConstants
   #55 = Utf8               LAMBDA_DESERIALIZE_DESERIALIZE_LAMBDA
   #56 = Utf8               Ljava/lang/invoke/MethodHandle;
   #57 = NameAndType        #55:#56       // LAMBDA_DESERIALIZE_DESERIALIZE_LAMBDA:Ljava/lang/invoke/MethodHandle;
   #58 = Fieldref           #54.#57       // scala/runtime/MethodHandleConstants.LAMBDA_DESERIALIZE_DESERIALIZE_LAMBDA:Ljava/lang/invoke/MethodHandle;
   #59 = Utf8               scala/runtime/LambdaDeserialize
   #60 = Class              #59           // scala/runtime/LambdaDeserialize
   #61 = Utf8               (Ljava/lang/invoke/MethodHandles$Lookup;[Ljava/lang/invoke/MethodHandle;)V
   #62 = NameAndType        #15:#61       // "<init>":(Ljava/lang/invoke/MethodHandles$Lookup;[Ljava/lang/invoke/MethodHandle;)V
   #63 = Methodref          #60.#62       // scala/runtime/LambdaDeserialize."<init>":(Ljava/lang/invoke/MethodHandles$Lookup;[Ljava/lang/invoke/MethodHandle;)V
   #64 = Utf8               java/lang/invoke/MethodHandle
   #65 = Class              #64           // java/lang/invoke/MethodHandle
   #66 = Utf8               bindTo
   #67 = Utf8               (Ljava/lang/Object;)Ljava/lang/invoke/MethodHandle;
   #68 = NameAndType        #66:#67       // bindTo:(Ljava/lang/Object;)Ljava/lang/invoke/MethodHandle;
   #69 = Methodref          #65.#68       // java/lang/invoke/MethodHandle.bindTo:(Ljava/lang/Object;)Ljava/lang/invoke/MethodHandle;
   #70 = Utf8               asType
   #71 = Utf8               (Ljava/lang/invoke/MethodType;)Ljava/lang/invoke/MethodHandle;
   #72 = NameAndType        #70:#71       // asType:(Ljava/lang/invoke/MethodType;)Ljava/lang/invoke/MethodHandle;
   #73 = Methodref          #65.#72       // java/lang/invoke/MethodHandle.asType:(Ljava/lang/invoke/MethodType;)Ljava/lang/invoke/MethodHandle;
   #74 = Utf8               java/lang/invoke/ConstantCallSite
   #75 = Class              #74           // java/lang/invoke/ConstantCallSite
   #76 = Utf8               (Ljava/lang/invoke/MethodHandle;)V
   #77 = NameAndType        #15:#76       // "<init>":(Ljava/lang/invoke/MethodHandle;)V
   #78 = Methodref          #75.#77       // java/lang/invoke/ConstantCallSite."<init>":(Ljava/lang/invoke/MethodHandle;)V
   #79 = Utf8               targetMethodsArray
   #80 = Utf8               exact
   #81 = Utf8               Lscala/collection/immutable/Seq;
   #82 = Utf8               nameAndDescriptorKey
   #83 = Utf8               (Ljava/lang/String;Ljava/lang/String;)Ljava/lang/String;
   #84 = Utf8               name
   #85 = Utf8               descriptor
   #86 = Utf8               java/lang/StringBuilder
   #87 = Class              #86           // java/lang/StringBuilder
   #88 = Integer            0
   #89 = Utf8               (I)V
   #90 = NameAndType        #15:#89       // "<init>":(I)V
   #91 = Methodref          #87.#90       // java/lang/StringBuilder."<init>":(I)V
   #92 = Utf8               append
   #93 = Utf8               (Ljava/lang/String;)Ljava/lang/StringBuilder;
   #94 = NameAndType        #92:#93       // append:(Ljava/lang/String;)Ljava/lang/StringBuilder;
   #95 = Methodref          #87.#94       // java/lang/StringBuilder.append:(Ljava/lang/String;)Ljava/lang/StringBuilder;
   #96 = Utf8               toString
   #97 = Utf8               ()Ljava/lang/String;
   #98 = NameAndType        #96:#97       // toString:()Ljava/lang/String;
   #99 = Methodref          #87.#98       // java/lang/StringBuilder.toString:()Ljava/lang/String;
  #100 = Methodref          #4.#16        // java/lang/Object."<init>":()V
  #101 = Utf8               Code
  #102 = Utf8               LineNumberTable
  #103 = Utf8               LocalVariableTable
  #104 = Utf8               MethodParameters
  #105 = Utf8               Exceptions
  #106 = Utf8               Signature
  #107 = Utf8               InnerClasses
  #108 = Utf8               SourceFile
  #109 = Utf8               ScalaInlineInfo
  #110 = Utf8               Scala
{
  public static final scala.runtime.LambdaDeserialize$ MODULE$;
    descriptor: Lscala/runtime/LambdaDeserialize$;
    flags: (0x0019) ACC_PUBLIC, ACC_STATIC, ACC_FINAL

  public static {};
    descriptor: ()V
    flags: (0x0009) ACC_PUBLIC, ACC_STATIC
    Code:
      stack=2, locals=0, args_size=0
         0: new           #2                  // class scala/runtime/LambdaDeserialize$
         3: dup
         4: invokespecial #17                 // Method "<init>":()V
         7: putstatic     #19                 // Field MODULE$:Lscala/runtime/LambdaDeserialize$;
        10: return
      LineNumberTable:
        line 35: 0

  public java.lang.invoke.CallSite bootstrap(java.lang.invoke.MethodHandles$Lookup, java.lang.String, java.lang.invoke.MethodType, java.lang.invoke.MethodHandle...);
    descriptor: (Ljava/lang/invoke/MethodHandles$Lookup;Ljava/lang/String;Ljava/lang/invoke/MethodType;[Ljava/lang/invoke/MethodHandle;)Ljava/lang/invoke/CallSite;
    flags: (0x0081) ACC_PUBLIC, ACC_VARARGS
    Code:
      stack=6, locals=5, args_size=5
         0: aload_0
         1: aload_1
         2: aload_2
         3: aload_3
         4: getstatic     #30                 // Field scala/runtime/ScalaRunTime$.MODULE$:Lscala/runtime/ScalaRunTime$;
         7: aload         4
         9: invokevirtual #34                 // Method scala/runtime/ScalaRunTime$.wrapRefArray:([Ljava/lang/Object;)Lscala/collection/immutable/ArraySeq;
        12: invokevirtual #37                 // Method bootstrap:(Ljava/lang/invoke/MethodHandles$Lookup;Ljava/lang/String;Ljava/lang/invoke/MethodType;Lscala/collection/immutable/Seq;)Ljava/lang/invoke/CallSite;
        15: areturn
      LineNumberTable:
        line 37: 0
      LocalVariableTable:
        Start  Length  Slot  Name   Signature
            0      16     0  this   Lscala/runtime/LambdaDeserialize$;
            0      16     1 lookup   Ljava/lang/invoke/MethodHandles$Lookup;
            0      16     2 invokedName   Ljava/lang/String;
            0      16     3 invokedType   Ljava/lang/invoke/MethodType;
            0      16     4 targetMethods   [Ljava/lang/invoke/MethodHandle;
    MethodParameters:
      Name                           Flags
      lookup                         final
      invokedName                    final
      invokedType                    final
      targetMethods                  final

  public java.lang.invoke.CallSite bootstrap(java.lang.invoke.MethodHandles$Lookup, java.lang.String, java.lang.invoke.MethodType, scala.collection.immutable.Seq<java.lang.invoke.MethodHandle>) throws java/lang/Throwable;
    descriptor: (Ljava/lang/invoke/MethodHandles$Lookup;Ljava/lang/String;Ljava/lang/invoke/MethodType;Lscala/collection/immutable/Seq;)Ljava/lang/invoke/CallSite;
    flags: (0x0001) ACC_PUBLIC
    Code:
      stack=5, locals=7, args_size=5
         0: aload         4
         2: checkcast     #47                 // class scala/collection/immutable/ArraySeq
         5: invokevirtual #51                 // Method scala/collection/immutable/ArraySeq.unsafeArray:()Ljava/lang/Object;
         8: checkcast     #52                 // class "[Ljava/lang/invoke/MethodHandle;"
        11: astore        5
        13: getstatic     #58                 // Field scala/runtime/MethodHandleConstants.LAMBDA_DESERIALIZE_DESERIALIZE_LAMBDA:Ljava/lang/invoke/MethodHandle;
        16: new           #60                 // class scala/runtime/LambdaDeserialize
        19: dup
        20: aload_1
        21: aload         5
        23: invokespecial #63                 // Method scala/runtime/LambdaDeserialize."<init>":(Ljava/lang/invoke/MethodHandles$Lookup;[Ljava/lang/invoke/MethodHandle;)V
        26: invokevirtual #69                 // Method java/lang/invoke/MethodHandle.bindTo:(Ljava/lang/Object;)Ljava/lang/invoke/MethodHandle;
        29: aload_3
        30: invokevirtual #73                 // Method java/lang/invoke/MethodHandle.asType:(Ljava/lang/invoke/MethodType;)Ljava/lang/invoke/MethodHandle;
        33: astore        6
        35: new           #75                 // class java/lang/invoke/ConstantCallSite
        38: dup
        39: aload         6
        41: invokespecial #78                 // Method java/lang/invoke/ConstantCallSite."<init>":(Ljava/lang/invoke/MethodHandle;)V
        44: areturn
      LineNumberTable:
        line 38: 0
        line 39: 13
        line 40: 35
      LocalVariableTable:
        Start  Length  Slot  Name   Signature
           13      31     5 targetMethodsArray   [Ljava/lang/invoke/MethodHandle;
           35       9     6 exact   Ljava/lang/invoke/MethodHandle;
            0      45     0  this   Lscala/runtime/LambdaDeserialize$;
            0      45     1 lookup   Ljava/lang/invoke/MethodHandles$Lookup;
            0      45     2 invokedName   Ljava/lang/String;
            0      45     3 invokedType   Ljava/lang/invoke/MethodType;
            0      45     4 targetMethods   Lscala/collection/immutable/Seq;
    Exceptions:
      throws java.lang.Throwable
    Signature: #43                          // (Ljava/lang/invoke/MethodHandles$Lookup;Ljava/lang/String;Ljava/lang/invoke/MethodType;Lscala/collection/immutable/Seq<Ljava/lang/invoke/MethodHandle;>;)Ljava/lang/invoke/CallSite;^Ljava/lang/Throwable;
    MethodParameters:
      Name                           Flags
      lookup                         final
      invokedName                    final
      invokedType                    final
      targetMethods                  final

  public java.lang.String nameAndDescriptorKey(java.lang.String, java.lang.String);
    descriptor: (Ljava/lang/String;Ljava/lang/String;)Ljava/lang/String;
    flags: (0x0001) ACC_PUBLIC
    Code:
      stack=3, locals=3, args_size=3
         0: new           #87                 // class java/lang/StringBuilder
         3: dup
         4: ldc           #88                 // int 0
         6: invokespecial #91                 // Method java/lang/StringBuilder."<init>":(I)V
         9: aload_1
        10: invokevirtual #95                 // Method java/lang/StringBuilder.append:(Ljava/lang/String;)Ljava/lang/StringBuilder;
        13: aload_2
        14: invokevirtual #95                 // Method java/lang/StringBuilder.append:(Ljava/lang/String;)Ljava/lang/StringBuilder;
        17: invokevirtual #99                 // Method java/lang/StringBuilder.toString:()Ljava/lang/String;
        20: areturn
      LineNumberTable:
        line 43: 0
      LocalVariableTable:
        Start  Length  Slot  Name   Signature
            0      21     0  this   Lscala/runtime/LambdaDeserialize$;
            0      21     1  name   Ljava/lang/String;
            0      21     2 descriptor   Ljava/lang/String;
    MethodParameters:
      Name                           Flags
      name                           final
      descriptor                     final

  private scala.runtime.LambdaDeserialize$();
    descriptor: ()V
    flags: (0x0002) ACC_PRIVATE
    Code:
      stack=1, locals=1, args_size=1
         0: aload_0
         1: invokespecial #100                // Method java/lang/Object."<init>":()V
         4: return
      LineNumberTable:
        line 35: 0
      LocalVariableTable:
        Start  Length  Slot  Name   Signature
            0       5     0  this   Lscala/runtime/LambdaDeserialize$;
}
InnerClasses:
  public static final #10= #7 of #9;      // Lookup=class java/lang/invoke/MethodHandles$Lookup of class java/lang/invoke/MethodHandles
SourceFile: "LambdaDeserialize.scala"
  ScalaInlineInfo: length = 0x18 (unknown attribute)
   01 01 00 04 00 0F 00 0E 01 00 14 00 23 01 00 14
   00 15 01 00 52 00 53 01
  Scala: length = 0x0 (unknown attribute)

