Classfile /Users/mw/Projects/slang-braindump/.jar/jar11/assemble/slang-braindump/assemble/content/scala/runtime/MethodCache.class
  Last modified May 29, 2022; size 1282 bytes
  SHA-256 checksum de87ada2c8364b67f70954de400f56f0d2b0fdcc6424a76cdc370a8a0397d1e2
  Compiled from "MethodCache.scala"
public abstract class scala.runtime.MethodCache
  minor version: 0
  major version: 52
  flags: (0x0421) ACC_PUBLIC, ACC_SUPER, ACC_ABSTRACT
  this_class: #2                          // scala/runtime/MethodCache
  super_class: #4                         // java/lang/Object
  interfaces: 0, fields: 0, methods: 3, attributes: 4
Constant pool:
   #1 = Utf8               scala/runtime/MethodCache
   #2 = Class              #1             // scala/runtime/MethodCache
   #3 = Utf8               java/lang/Object
   #4 = Class              #3             // java/lang/Object
   #5 = Utf8               MethodCache.scala
   #6 = Utf8               Lscala/reflect/ScalaSignature;
   #7 = Utf8               bytes
   #8 = Utf8               \u0006\u0005\t3a\u0001B\u0003\u0002\"\u001dI\u0001\"\u0002\b\u0001\t\u0003\u0001\u0002\"B\n\u0001\r\u0003!\u0002\"B\u0019\u0001\r\u0003\u0011$aC\'fi\"|GmQ1dQ\u0016T!AB\u0004\u0002\u000fI,h\u000e^5nK*\t\u0001\"A\u0003tG\u0006d\u0017m\u0005\u0002\u0001\u0015A\u00111\u0002D\u0007\u0002\u000f%\u0011Qb\u0002\u0002\u0007\u0003:L(+\u001a4\u0002\rqJg.\u001b;?\u0007\u0001!\u0012!\u0005\t\u0003%\u0001i\u0011!B\u0001\u0005M&tG\r\u0006\u0002\u0016?A\u0011a#H\u0007\u0002/)\u0011\u0001$G\u0001\be\u00164G.Z2u\u0015\tQ2$\u0001\u0003mC:<\'\"\u0001\u000f\u0002\t)\fg/Y\u0005\u0003=]\u0011a!T3uQ>$\u0007\"\u0002\u0011\u0003\u0001\u0004\t\u0013a\u00034peJ+7-Z5wKJ\u0004$A\t\u0015\u0011\u0007\r\"c%D\u0001\u001a\u0013\t)\u0013DA\u0003DY\u0006\u001c8\u000f\u0005\u0002(Q1\u0001A!C\u0015 \u0003\u0003\u0005\tQ!\u0001+\u0005\ryF%M\t\u0003W9\u0002\"a\u0003\u0017\n\u00055:!a\u0002(pi\"Lgn\u001a\t\u0003\u0017=J!\u0001M\u0004\u0003\u0007\u0005s\u00170A\u0002bI\u0012$2!E\u001a:\u0011\u0015\u00013\u00011\u00015a\t)t\u0007E\u0002$IY\u0002\"aJ\u001c\u0005\u0013a\u001a\u0014\u0011!A\u0001\u0006\u0003Q#aA0%e!)!h\u0001a\u0001+\u0005Iam\u001c:NKRDw\u000eZ\u0015\u0005\u0001qr\u0004)\u0003\u0002>\u000b\t\u0001R)\u001c9us6+G\u000f[8e\u0007\u0006\u001c\u0007.Z\u0005\u0003\u007f\u0015\u0011q\"T3hC6+G\u000f[8e\u0007\u0006\u001c\u0007.Z\u0005\u0003\u0003\u0016\u0011q\u0002U8ms6+G\u000f[8e\u0007\u0006\u001c\u0007.\u001a
   #9 = Utf8               find
  #10 = Utf8               (Ljava/lang/Class;)Ljava/lang/reflect/Method;
  #11 = Utf8               (Ljava/lang/Class<*>;)Ljava/lang/reflect/Method;
  #12 = Utf8               forReceiver
  #13 = Utf8               add
  #14 = Utf8               (Ljava/lang/Class;Ljava/lang/reflect/Method;)Lscala/runtime/MethodCache;
  #15 = Utf8               (Ljava/lang/Class<*>;Ljava/lang/reflect/Method;)Lscala/runtime/MethodCache;
  #16 = Utf8               forMethod
  #17 = Utf8               <init>
  #18 = Utf8               ()V
  #19 = NameAndType        #17:#18        // "<init>":()V
  #20 = Methodref          #4.#19         // java/lang/Object."<init>":()V
  #21 = Utf8               this
  #22 = Utf8               Lscala/runtime/MethodCache;
  #23 = Utf8               Signature
  #24 = Utf8               MethodParameters
  #25 = Utf8               Code
  #26 = Utf8               LineNumberTable
  #27 = Utf8               LocalVariableTable
  #28 = Utf8               SourceFile
  #29 = Utf8               RuntimeVisibleAnnotations
  #30 = Utf8               ScalaInlineInfo
  #31 = Utf8               ScalaSig
{
  public abstract java.lang.reflect.Method find(java.lang.Class<?>);
    descriptor: (Ljava/lang/Class;)Ljava/lang/reflect/Method;
    flags: (0x0401) ACC_PUBLIC, ACC_ABSTRACT
    Signature: #11                          // (Ljava/lang/Class<*>;)Ljava/lang/reflect/Method;
    MethodParameters:
      Name                           Flags
      forReceiver                    final

  public abstract scala.runtime.MethodCache add(java.lang.Class<?>, java.lang.reflect.Method);
    descriptor: (Ljava/lang/Class;Ljava/lang/reflect/Method;)Lscala/runtime/MethodCache;
    flags: (0x0401) ACC_PUBLIC, ACC_ABSTRACT
    Signature: #15                          // (Ljava/lang/Class<*>;Ljava/lang/reflect/Method;)Lscala/runtime/MethodCache;
    MethodParameters:
      Name                           Flags
      forReceiver                    final
      forMethod                      final

  public scala.runtime.MethodCache();
    descriptor: ()V
    flags: (0x0001) ACC_PUBLIC
    Code:
      stack=1, locals=1, args_size=1
         0: aload_0
         1: invokespecial #20                 // Method java/lang/Object."<init>":()V
         4: return
      LineNumberTable:
        line 29: 0
      LocalVariableTable:
        Start  Length  Slot  Name   Signature
            0       5     0  this   Lscala/runtime/MethodCache;
}
SourceFile: "MethodCache.scala"
RuntimeVisibleAnnotations:
  0: #6(#7=s#8)
    scala.reflect.ScalaSignature(
      bytes="\u0006\u0005\t3a\u0001B\u0003\u0002\"\u001dI\u0001\"\u0002\b\u0001\t\u0003\u0001\u0002\"B\n\u0001\r\u0003!\u0002\"B\u0019\u0001\r\u0003\u0011$aC\'fi\"|GmQ1dQ\u0016T!AB\u0004\u0002\u000fI,h\u000e^5nK*\t\u0001\"A\u0003tG\u0006d\u0017m\u0005\u0002\u0001\u0015A\u00111\u0002D\u0007\u0002\u000f%\u0011Qb\u0002\u0002\u0007\u0003:L(+\u001a4\u0002\rqJg.\u001b;?\u0007\u0001!\u0012!\u0005\t\u0003%\u0001i\u0011!B\u0001\u0005M&tG\r\u0006\u0002\u0016?A\u0011a#H\u0007\u0002/)\u0011\u0001$G\u0001\be\u00164G.Z2u\u0015\tQ2$\u0001\u0003mC:<\'\"\u0001\u000f\u0002\t)\fg/Y\u0005\u0003=]\u0011a!T3uQ>$\u0007\"\u0002\u0011\u0003\u0001\u0004\t\u0013a\u00034peJ+7-Z5wKJ\u0004$A\t\u0015\u0011\u0007\r\"c%D\u0001\u001a\u0013\t)\u0013DA\u0003DY\u0006\u001c8\u000f\u0005\u0002(Q1\u0001A!C\u0015 \u0003\u0003\u0005\tQ!\u0001+\u0005\ryF%M\t\u0003W9\u0002\"a\u0003\u0017\n\u00055:!a\u0002(pi\"Lgn\u001a\t\u0003\u0017=J!\u0001M\u0004\u0003\u0007\u0005s\u00170A\u0002bI\u0012$2!E\u001a:\u0011\u0015\u00013\u00011\u00015a\t)t\u0007E\u0002$IY\u0002\"aJ\u001c\u0005\u0013a\u001a\u0014\u0011!A\u0001\u0006\u0003Q#aA0%e!)!h\u0001a\u0001+\u0005Iam\u001c:NKRDw\u000eZ\u0015\u0005\u0001qr\u0004)\u0003\u0002>\u000b\t\u0001R)\u001c9us6+G\u000f[8e\u0007\u0006\u001c\u0007.Z\u0005\u0003\u007f\u0015\u0011q\"T3hC6+G\u000f[8e\u0007\u0006\u001c\u0007.Z\u0005\u0003\u0003\u0016\u0011q\u0002U8ms6+G\u000f[8e\u0007\u0006\u001c\u0007.\u001a"
    )
  ScalaInlineInfo: length = 0x13 (unknown attribute)
   01 00 00 03 00 11 00 12 01 00 0D 00 0E 00 00 09
   00 0A 00
  ScalaSig: length = 0x3 (unknown attribute)
   05 02 00
