Classfile /Users/mw/Projects/slang-braindump/.jar/jar11/assemble/slang-braindump/assemble/content/scala/runtime/OrderedProxy.class
  Last modified May 29, 2022; size 1600 bytes
  SHA-256 checksum 2fd8c367b6ad2b0168f92cc6179bb766007774af3027fdb3eefb66c43905d84b
  Compiled from "ScalaNumberProxy.scala"
public interface scala.runtime.OrderedProxy<T extends java.lang.Object> extends scala.math.Ordered<T>, scala.Proxy$Typed<T>
  minor version: 0
  major version: 52
  flags: (0x0601) ACC_PUBLIC, ACC_INTERFACE, ACC_ABSTRACT
  this_class: #2                          // scala/runtime/OrderedProxy
  super_class: #5                         // java/lang/Object
  interfaces: 2, fields: 0, methods: 4, attributes: 6
Constant pool:
   #1 = Utf8               scala/runtime/OrderedProxy
   #2 = Class              #1             // scala/runtime/OrderedProxy
   #3 = Utf8               <T:Ljava/lang/Object;>Ljava/lang/Object;Lscala/math/Ordered<TT;>;Lscala/Proxy$Typed<TT;>;
   #4 = Utf8               java/lang/Object
   #5 = Class              #4             // java/lang/Object
   #6 = Utf8               scala/math/Ordered
   #7 = Class              #6             // scala/math/Ordered
   #8 = Utf8               scala/Proxy$Typed
   #9 = Class              #8             // scala/Proxy$Typed
  #10 = Utf8               ScalaNumberProxy.scala
  #11 = Utf8               Lscala/reflect/ScalaSignature;
  #12 = Utf8               bytes
  #13 = Utf8               \u0006\u0005]2q\u0001B\u0003\u0011\u0002\u0007\u0005!\u0002C\u0003\'\u0001\u0011\u0005q\u0005C\u0003,\u0001\u0019EA\u0006C\u00031\u0001\u0011\u0005\u0011G\u0001\u0007Pe\u0012,\'/\u001a3Qe>D\u0018P\u0003\u0002\u0007\u000f\u00059!/\u001e8uS6,\'\"\u0001\u0005\u0002\u000bM\u001c\u0017\r\\1\u0004\u0001U\u00111\"G\n\u0005\u00011\u0001r\u0004\u0005\u0002\u000e\u001d5\tq!\u0003\u0002\u0010\u000f\t\u0019\u0011I\\=\u0011\u0007E!rC\u0004\u0002\u000e%%\u00111cB\u0001\ba\u0006\u001c7.Y4f\u0013\t)bCA\u0004Pe\u0012,\'/\u001a3\u000b\u0005M9\u0001C\u0001\r\u001a\u0019\u0001!QA\u0007\u0001C\u0002m\u0011\u0011\u0001V\t\u000391\u0001\"!D\u000f\n\u0005y9!a\u0002(pi\"Lgn\u001a\t\u0004A\r:bBA\u0007\"\u0013\t\u0011s!A\u0003Qe>D\u00180\u0003\u0002%K\t)A+\u001f9fI*\u0011!eB\u0001\u0007I%t\u0017\u000e\u001e\u0013\u0015\u0003!\u0002\"!D\u0015\n\u0005):!\u0001B+oSR\f1a\u001c:e+\u0005i\u0003cA\t//%\u0011qF\u0006\u0002\t\u001fJ$WM]5oO\u000691m\\7qCJ,GC\u0001\u001a6!\ti1\'\u0003\u00025\u000f\t\u0019\u0011J\u001c;\t\u000bY\u001a\u0001\u0019A\f\u0002\u0003e\u0004
  #14 = Utf8               scala/Proxy
  #15 = Class              #14            // scala/Proxy
  #16 = Utf8               Typed
  #17 = Utf8               ord
  #18 = Utf8               ()Lscala/math/Ordering;
  #19 = Utf8               ()Lscala/math/Ordering<TT;>;
  #20 = Utf8               compare$
  #21 = Utf8               (Lscala/runtime/OrderedProxy;Ljava/lang/Object;)I
  #22 = Utf8               $this
  #23 = Utf8               y
  #24 = Utf8               compare
  #25 = Utf8               (Ljava/lang/Object;)I
  #26 = NameAndType        #24:#25        // compare:(Ljava/lang/Object;)I
  #27 = InterfaceMethodref #2.#26         // scala/runtime/OrderedProxy.compare:(Ljava/lang/Object;)I
  #28 = Utf8               Lscala/runtime/OrderedProxy;
  #29 = Utf8               Ljava/lang/Object;
  #30 = Utf8               (TT;)I
  #31 = NameAndType        #17:#18        // ord:()Lscala/math/Ordering;
  #32 = InterfaceMethodref #2.#31         // scala/runtime/OrderedProxy.ord:()Lscala/math/Ordering;
  #33 = Utf8               self
  #34 = Utf8               ()Ljava/lang/Object;
  #35 = NameAndType        #33:#34        // self:()Ljava/lang/Object;
  #36 = InterfaceMethodref #2.#35         // scala/runtime/OrderedProxy.self:()Ljava/lang/Object;
  #37 = Utf8               scala/math/Ordering
  #38 = Class              #37            // scala/math/Ordering
  #39 = Utf8               (Ljava/lang/Object;Ljava/lang/Object;)I
  #40 = NameAndType        #24:#39        // compare:(Ljava/lang/Object;Ljava/lang/Object;)I
  #41 = InterfaceMethodref #38.#40        // scala/math/Ordering.compare:(Ljava/lang/Object;Ljava/lang/Object;)I
  #42 = Utf8               this
  #43 = Utf8               $init$
  #44 = Utf8               (Lscala/runtime/OrderedProxy;)V
  #45 = Utf8               Signature
  #46 = Utf8               Code
  #47 = Utf8               LineNumberTable
  #48 = Utf8               LocalVariableTable
  #49 = Utf8               MethodParameters
  #50 = Utf8               InnerClasses
  #51 = Utf8               SourceFile
  #52 = Utf8               RuntimeVisibleAnnotations
  #53 = Utf8               ScalaInlineInfo
  #54 = Utf8               ScalaSig
{
  public abstract scala.math.Ordering<T> ord();
    descriptor: ()Lscala/math/Ordering;
    flags: (0x0401) ACC_PUBLIC, ACC_ABSTRACT
    Signature: #19                          // ()Lscala/math/Ordering<TT;>;

  public static int compare$(scala.runtime.OrderedProxy, java.lang.Object);
    descriptor: (Lscala/runtime/OrderedProxy;Ljava/lang/Object;)I
    flags: (0x1009) ACC_PUBLIC, ACC_STATIC, ACC_SYNTHETIC
    Code:
      stack=2, locals=2, args_size=2
         0: aload_0
         1: aload_1
         2: invokespecial #27                 // InterfaceMethod compare:(Ljava/lang/Object;)I
         5: ireturn
      LineNumberTable:
        line 74: 0
      LocalVariableTable:
        Start  Length  Slot  Name   Signature
            0       6     0 $this   Lscala/runtime/OrderedProxy;
            0       6     1     y   Ljava/lang/Object;
    MethodParameters:
      Name                           Flags
      $this                          final synthetic
      y                              final

  public default int compare(T);
    descriptor: (Ljava/lang/Object;)I
    flags: (0x0001) ACC_PUBLIC
    Code:
      stack=3, locals=2, args_size=2
         0: aload_0
         1: invokeinterface #32,  1           // InterfaceMethod ord:()Lscala/math/Ordering;
         6: aload_0
         7: invokeinterface #36,  1           // InterfaceMethod self:()Ljava/lang/Object;
        12: aload_1
        13: invokeinterface #41,  3           // InterfaceMethod scala/math/Ordering.compare:(Ljava/lang/Object;Ljava/lang/Object;)I
        18: ireturn
      LineNumberTable:
        line 74: 0
      LocalVariableTable:
        Start  Length  Slot  Name   Signature
            0      19     0  this   Lscala/runtime/OrderedProxy;
            0      19     1     y   Ljava/lang/Object;
    Signature: #30                          // (TT;)I
    MethodParameters:
      Name                           Flags
      y                              final

  public static void $init$(scala.runtime.OrderedProxy);
    descriptor: (Lscala/runtime/OrderedProxy;)V
    flags: (0x0009) ACC_PUBLIC, ACC_STATIC
    Code:
      stack=0, locals=1, args_size=1
         0: return
      LineNumberTable:
        line 71: 0
      LocalVariableTable:
        Start  Length  Slot  Name   Signature
            0       1     0 $this   Lscala/runtime/OrderedProxy;
    MethodParameters:
      Name                           Flags
      $this                          final synthetic
}
InnerClasses:
  public static #16= #9 of #15;           // Typed=class scala/Proxy$Typed of class scala/Proxy
Signature: #3                           // <T:Ljava/lang/Object;>Ljava/lang/Object;Lscala/math/Ordered<TT;>;Lscala/Proxy$Typed<TT;>;
SourceFile: "ScalaNumberProxy.scala"
RuntimeVisibleAnnotations:
  0: #11(#12=s#13)
    scala.reflect.ScalaSignature(
      bytes="\u0006\u0005]2q\u0001B\u0003\u0011\u0002\u0007\u0005!\u0002C\u0003\'\u0001\u0011\u0005q\u0005C\u0003,\u0001\u0019EA\u0006C\u00031\u0001\u0011\u0005\u0011G\u0001\u0007Pe\u0012,\'/\u001a3Qe>D\u0018P\u0003\u0002\u0007\u000f\u00059!/\u001e8uS6,\'\"\u0001\u0005\u0002\u000bM\u001c\u0017\r\\1\u0004\u0001U\u00111\"G\n\u0005\u00011\u0001r\u0004\u0005\u0002\u000e\u001d5\tq!\u0003\u0002\u0010\u000f\t\u0019\u0011I\\=\u0011\u0007E!rC\u0004\u0002\u000e%%\u00111cB\u0001\ba\u0006\u001c7.Y4f\u0013\t)bCA\u0004Pe\u0012,\'/\u001a3\u000b\u0005M9\u0001C\u0001\r\u001a\u0019\u0001!QA\u0007\u0001C\u0002m\u0011\u0011\u0001V\t\u000391\u0001\"!D\u000f\n\u0005y9!a\u0002(pi\"Lgn\u001a\t\u0004A\r:bBA\u0007\"\u0013\t\u0011s!A\u0003Qe>D\u00180\u0003\u0002%K\t)A+\u001f9fI*\u0011!eB\u0001\u0007I%t\u0017\u000e\u001e\u0013\u0015\u0003!\u0002\"!D\u0015\n\u0005):!\u0001B+oSR\f1a\u001c:e+\u0005i\u0003cA\t//%\u0011qF\u0006\u0002\t\u001fJ$WM]5oO\u000691m\\7qCJ,GC\u0001\u001a6!\ti1\'\u0003\u00025\u000f\t\u0019\u0011J\u001c;\t\u000bY\u001a\u0001\u0019A\f\u0002\u0003e\u0004"
    )
  ScalaInlineInfo: length = 0x18 (unknown attribute)
   01 00 00 04 00 2B 00 2C 01 00 18 00 19 00 00 14
   00 15 01 00 11 00 12 00
  ScalaSig: length = 0x3 (unknown attribute)
   05 02 00
