Classfile /Users/mw/Projects/slang-braindump/.jar/jar11/assemble/slang-braindump/assemble/content/scala/runtime/ScalaWholeNumberProxy.class
  Last modified May 29, 2022; size 1125 bytes
  SHA-256 checksum b05d3c65e7dfa02592238aa0d2a29b6d517a506de1b3832bcf1ee98869705d69
  Compiled from "ScalaNumberProxy.scala"
public interface scala.runtime.ScalaWholeNumberProxy<T extends java.lang.Object> extends scala.runtime.ScalaNumberProxy<T>
  minor version: 0
  major version: 52
  flags: (0x0601) ACC_PUBLIC, ACC_INTERFACE, ACC_ABSTRACT
  this_class: #2                          // scala/runtime/ScalaWholeNumberProxy
  super_class: #5                         // java/lang/Object
  interfaces: 1, fields: 0, methods: 3, attributes: 5
Constant pool:
   #1 = Utf8               scala/runtime/ScalaWholeNumberProxy
   #2 = Class              #1             // scala/runtime/ScalaWholeNumberProxy
   #3 = Utf8               <T:Ljava/lang/Object;>Ljava/lang/Object;Lscala/runtime/ScalaNumberProxy<TT;>;
   #4 = Utf8               java/lang/Object
   #5 = Class              #4             // java/lang/Object
   #6 = Utf8               scala/runtime/ScalaNumberProxy
   #7 = Class              #6             // scala/runtime/ScalaNumberProxy
   #8 = Utf8               ScalaNumberProxy.scala
   #9 = Utf8               Lscala/reflect/ScalaSignature;
  #10 = Utf8               bytes
  #11 = Utf8               \u0006\u0005\u00152qa\u0001\u0003\u0011\u0002\u0007\u0005\u0011\u0002C\u0003\u001c\u0001\u0011\u0005A\u0004C\u0003!\u0001\u0011\u0005\u0011EA\u000bTG\u0006d\u0017m\u00165pY\u0016tU/\u001c2feB\u0013x\u000e_=\u000b\u0005\u00151\u0011a\u0002:v]RLW.\u001a\u0006\u0002\u000f\u0005)1oY1mC\u000e\u0001QC\u0001\u0006\u0016\'\r\u00011b\u0004\t\u0003\u00195i\u0011AB\u0005\u0003\u001d\u0019\u00111!\u00118z!\r\u0001\u0012cE\u0007\u0002\t%\u0011!\u0003\u0002\u0002\u0011\'\u000e\fG.\u0019(v[\n,\'\u000f\u0015:pqf\u0004\"\u0001F\u000b\r\u0001\u0011)a\u0003\u0001b\u0001/\t\tA+\u0005\u0002\u0019\u0017A\u0011A\"G\u0005\u00035\u0019\u0011qAT8uQ&tw-\u0001\u0004%S:LG\u000f\n\u000b\u0002;A\u0011ABH\u0005\u0003?\u0019\u0011A!\u00168ji\u00069\u0011n],i_2,W#\u0001\u0012\u0011\u00051\u0019\u0013B\u0001\u0013\u0007\u0005\u001d\u0011un\u001c7fC:\u0004
  #12 = Utf8               isWhole$
  #13 = Utf8               (Lscala/runtime/ScalaWholeNumberProxy;)Z
  #14 = Utf8               $this
  #15 = Utf8               isWhole
  #16 = Utf8               ()Z
  #17 = NameAndType        #15:#16        // isWhole:()Z
  #18 = InterfaceMethodref #2.#17         // scala/runtime/ScalaWholeNumberProxy.isWhole:()Z
  #19 = Utf8               Lscala/runtime/ScalaWholeNumberProxy;
  #20 = Utf8               this
  #21 = Utf8               $init$
  #22 = Utf8               (Lscala/runtime/ScalaWholeNumberProxy;)V
  #23 = Utf8               Code
  #24 = Utf8               LineNumberTable
  #25 = Utf8               LocalVariableTable
  #26 = Utf8               MethodParameters
  #27 = Utf8               Signature
  #28 = Utf8               SourceFile
  #29 = Utf8               RuntimeVisibleAnnotations
  #30 = Utf8               ScalaInlineInfo
  #31 = Utf8               ScalaSig
{
  public static boolean isWhole$(scala.runtime.ScalaWholeNumberProxy);
    descriptor: (Lscala/runtime/ScalaWholeNumberProxy;)Z
    flags: (0x1009) ACC_PUBLIC, ACC_STATIC, ACC_SYNTHETIC
    Code:
      stack=1, locals=1, args_size=1
         0: aload_0
         1: invokespecial #18                 // InterfaceMethod isWhole:()Z
         4: ireturn
      LineNumberTable:
        line 53: 0
      LocalVariableTable:
        Start  Length  Slot  Name   Signature
            0       5     0 $this   Lscala/runtime/ScalaWholeNumberProxy;
    MethodParameters:
      Name                           Flags
      $this                          final synthetic

  public default boolean isWhole();
    descriptor: ()Z
    flags: (0x0001) ACC_PUBLIC
    Code:
      stack=1, locals=1, args_size=1
         0: iconst_1
         1: ireturn
      LineNumberTable:
        line 53: 0
      LocalVariableTable:
        Start  Length  Slot  Name   Signature
            0       2     0  this   Lscala/runtime/ScalaWholeNumberProxy;

  public static void $init$(scala.runtime.ScalaWholeNumberProxy);
    descriptor: (Lscala/runtime/ScalaWholeNumberProxy;)V
    flags: (0x0009) ACC_PUBLIC, ACC_STATIC
    Code:
      stack=0, locals=1, args_size=1
         0: return
      LineNumberTable:
        line 52: 0
      LocalVariableTable:
        Start  Length  Slot  Name   Signature
            0       1     0 $this   Lscala/runtime/ScalaWholeNumberProxy;
    MethodParameters:
      Name                           Flags
      $this                          final synthetic
}
Signature: #3                           // <T:Ljava/lang/Object;>Ljava/lang/Object;Lscala/runtime/ScalaNumberProxy<TT;>;
SourceFile: "ScalaNumberProxy.scala"
RuntimeVisibleAnnotations:
  0: #9(#10=s#11)
    scala.reflect.ScalaSignature(
      bytes="\u0006\u0005\u00152qa\u0001\u0003\u0011\u0002\u0007\u0005\u0011\u0002C\u0003\u001c\u0001\u0011\u0005A\u0004C\u0003!\u0001\u0011\u0005\u0011EA\u000bTG\u0006d\u0017m\u00165pY\u0016tU/\u001c2feB\u0013x\u000e_=\u000b\u0005\u00151\u0011a\u0002:v]RLW.\u001a\u0006\u0002\u000f\u0005)1oY1mC\u000e\u0001QC\u0001\u0006\u0016\'\r\u00011b\u0004\t\u0003\u00195i\u0011AB\u0005\u0003\u001d\u0019\u00111!\u00118z!\r\u0001\u0012cE\u0007\u0002\t%\u0011!\u0003\u0002\u0002\u0011\'\u000e\fG.\u0019(v[\n,\'\u000f\u0015:pqf\u0004\"\u0001F\u000b\r\u0001\u0011)a\u0003\u0001b\u0001/\t\tA+\u0005\u0002\u0019\u0017A\u0011A\"G\u0005\u00035\u0019\u0011qAT8uQ&tw-\u0001\u0004%S:LG\u000f\n\u000b\u0002;A\u0011ABH\u0005\u0003?\u0019\u0011A!\u00168ji\u00069\u0011n],i_2,W#\u0001\u0012\u0011\u00051\u0019\u0013B\u0001\u0013\u0007\u0005\u001d\u0011un\u001c7fC:\u0004"
    )
  ScalaInlineInfo: length = 0x13 (unknown attribute)
   01 00 00 03 00 15 00 16 01 00 0F 00 10 00 00 0C
   00 0D 01
  ScalaSig: length = 0x3 (unknown attribute)
   05 02 00
