Classfile /Users/mw/Projects/slang-braindump/.jar/jar11/assemble/slang-braindump/assemble/content/scala/runtime/ScalaRunTime$$anon$1.class
  Last modified May 29, 2022; size 1189 bytes
  SHA-256 checksum 2aa67f7ff9e6ba653caaf83abfcba73808413be9dec65e52d1cc7294cc6cecbe
  Compiled from "ScalaRunTime.scala"
public final class scala.runtime.ScalaRunTime$$anon$1 extends scala.collection.AbstractIterator<T>
  minor version: 0
  major version: 52
  flags: (0x0031) ACC_PUBLIC, ACC_FINAL, ACC_SUPER
  this_class: #2                          // scala/runtime/ScalaRunTime$$anon$1
  super_class: #5                         // scala/collection/AbstractIterator
  interfaces: 0, fields: 3, methods: 3, attributes: 6
Constant pool:
   #1 = Utf8               scala/runtime/ScalaRunTime$$anon$1
   #2 = Class              #1             // scala/runtime/ScalaRunTime$$anon$1
   #3 = Utf8               Lscala/collection/AbstractIterator<TT;>;
   #4 = Utf8               scala/collection/AbstractIterator
   #5 = Class              #4             // scala/collection/AbstractIterator
   #6 = Utf8               ScalaRunTime.scala
   #7 = Utf8               scala/runtime/ScalaRunTime$
   #8 = Class              #7             // scala/runtime/ScalaRunTime$
   #9 = Utf8               typedProductIterator
  #10 = Utf8               (Lscala/Product;)Lscala/collection/Iterator;
  #11 = NameAndType        #9:#10         // typedProductIterator:(Lscala/Product;)Lscala/collection/Iterator;
  #12 = Utf8               c
  #13 = Utf8               I
  #14 = Utf8               cmax
  #15 = Utf8               x$2
  #16 = Utf8               Lscala/Product;
  #17 = Utf8               hasNext
  #18 = Utf8               ()Z
  #19 = NameAndType        #12:#13        // c:I
  #20 = Fieldref           #2.#19         // scala/runtime/ScalaRunTime$$anon$1.c:I
  #21 = NameAndType        #14:#13        // cmax:I
  #22 = Fieldref           #2.#21         // scala/runtime/ScalaRunTime$$anon$1.cmax:I
  #23 = Utf8               this
  #24 = Utf8               Lscala/runtime/ScalaRunTime$$anon$1;
  #25 = Utf8               next
  #26 = Utf8               ()Ljava/lang/Object;
  #27 = Utf8               ()TT;
  #28 = NameAndType        #15:#16        // x$2:Lscala/Product;
  #29 = Fieldref           #2.#28         // scala/runtime/ScalaRunTime$$anon$1.x$2:Lscala/Product;
  #30 = Utf8               scala/Product
  #31 = Class              #30            // scala/Product
  #32 = Utf8               productElement
  #33 = Utf8               (I)Ljava/lang/Object;
  #34 = NameAndType        #32:#33        // productElement:(I)Ljava/lang/Object;
  #35 = InterfaceMethodref #31.#34        // scala/Product.productElement:(I)Ljava/lang/Object;
  #36 = Utf8               result
  #37 = Utf8               Ljava/lang/Object;
  #38 = Utf8               <init>
  #39 = Utf8               (Lscala/Product;)V
  #40 = Utf8               ()V
  #41 = NameAndType        #38:#40        // "<init>":()V
  #42 = Methodref          #5.#41         // scala/collection/AbstractIterator."<init>":()V
  #43 = Utf8               productArity
  #44 = Utf8               ()I
  #45 = NameAndType        #43:#44        // productArity:()I
  #46 = InterfaceMethodref #31.#45        // scala/Product.productArity:()I
  #47 = Utf8               Code
  #48 = Utf8               StackMapTable
  #49 = Utf8               LineNumberTable
  #50 = Utf8               LocalVariableTable
  #51 = Utf8               Signature
  #52 = Utf8               MethodParameters
  #53 = Utf8               InnerClasses
  #54 = Utf8               EnclosingMethod
  #55 = Utf8               SourceFile
  #56 = Utf8               ScalaInlineInfo
  #57 = Utf8               Scala
{
  private int c;
    descriptor: I
    flags: (0x0002) ACC_PRIVATE

  private final int cmax;
    descriptor: I
    flags: (0x0012) ACC_PRIVATE, ACC_FINAL

  private final scala.Product x$2;
    descriptor: Lscala/Product;
    flags: (0x0012) ACC_PRIVATE, ACC_FINAL

  public boolean hasNext();
    descriptor: ()Z
    flags: (0x0001) ACC_PUBLIC
    Code:
      stack=2, locals=1, args_size=1
         0: aload_0
         1: getfield      #20                 // Field c:I
         4: aload_0
         5: getfield      #22                 // Field cmax:I
         8: if_icmpge     13
        11: iconst_1
        12: ireturn
        13: iconst_0
        14: ireturn
      StackMapTable: number_of_entries = 1
        frame_type = 13 /* same */
      LineNumberTable:
        line 165: 0
      LocalVariableTable:
        Start  Length  Slot  Name   Signature
            0      15     0  this   Lscala/runtime/ScalaRunTime$$anon$1;

  public T next();
    descriptor: ()Ljava/lang/Object;
    flags: (0x0001) ACC_PUBLIC
    Code:
      stack=3, locals=2, args_size=1
         0: aload_0
         1: getfield      #29                 // Field x$2:Lscala/Product;
         4: aload_0
         5: getfield      #20                 // Field c:I
         8: invokeinterface #35,  2           // InterfaceMethod scala/Product.productElement:(I)Ljava/lang/Object;
        13: astore_1
        14: aload_0
        15: aload_0
        16: getfield      #20                 // Field c:I
        19: iconst_1
        20: iadd
        21: putfield      #20                 // Field c:I
        24: aload_1
        25: areturn
      LineNumberTable:
        line 167: 0
        line 168: 14
        line 169: 24
      LocalVariableTable:
        Start  Length  Slot  Name   Signature
           14      11     1 result   Ljava/lang/Object;
            0      26     0  this   Lscala/runtime/ScalaRunTime$$anon$1;
    Signature: #27                          // ()TT;

  public scala.runtime.ScalaRunTime$$anon$1(scala.Product);
    descriptor: (Lscala/Product;)V
    flags: (0x0001) ACC_PUBLIC
    Code:
      stack=2, locals=2, args_size=2
         0: aload_0
         1: aload_1
         2: putfield      #29                 // Field x$2:Lscala/Product;
         5: aload_0
         6: invokespecial #42                 // Method scala/collection/AbstractIterator."<init>":()V
         9: aload_0
        10: iconst_0
        11: putfield      #20                 // Field c:I
        14: aload_0
        15: aload_1
        16: invokeinterface #46,  1           // InterfaceMethod scala/Product.productArity:()I
        21: putfield      #22                 // Field cmax:I
        24: return
      LineNumberTable:
        line 161: 0
        line 162: 5
        line 163: 9
        line 164: 14
        line 162: 24
      LocalVariableTable:
        Start  Length  Slot  Name   Signature
            0      25     0  this   Lscala/runtime/ScalaRunTime$$anon$1;
            0      25     1   x$2   Lscala/Product;
    MethodParameters:
      Name                           Flags
      x$2                            final
}
InnerClasses:
  public final #2;                        // class scala/runtime/ScalaRunTime$$anon$1
EnclosingMethod: #8.#11                 // scala.runtime.ScalaRunTime$.typedProductIterator
Signature: #3                           // Lscala/collection/AbstractIterator<TT;>;
SourceFile: "ScalaRunTime.scala"
  ScalaInlineInfo: length = 0x13 (unknown attribute)
   01 01 00 03 00 26 00 27 01 00 11 00 12 01 00 19
   00 1A 01
  Scala: length = 0x0 (unknown attribute)

