Classfile /Users/mw/Projects/slang-braindump/.jar/jar11/assemble/slang-braindump/assemble/content/scala/runtime/Static.class
  Last modified May 29, 2022; size 1355 bytes
  SHA-256 checksum 909649673a08f75dc290ddec417cf0e5cf4195fad38e428c726257d7d71c9c53
  Compiled from "Static.java"
public final class scala.runtime.Static
  minor version: 0
  major version: 52
  flags: (0x0031) ACC_PUBLIC, ACC_FINAL, ACC_SUPER
  this_class: #7                          // scala/runtime/Static
  super_class: #8                         // java/lang/Object
  interfaces: 0, fields: 0, methods: 2, attributes: 2
Constant pool:
   #1 = Methodref          #8.#37         // java/lang/Object."<init>":()V
   #2 = Methodref          #38.#39        // java/lang/invoke/MethodHandle.invokeWithArguments:([Ljava/lang/Object;)Ljava/lang/Object;
   #3 = Class              #40            // java/lang/invoke/ConstantCallSite
   #4 = Methodref          #41.#42        // java/lang/invoke/MethodType.returnType:()Ljava/lang/Class;
   #5 = Methodref          #43.#44        // java/lang/invoke/MethodHandles.constant:(Ljava/lang/Class;Ljava/lang/Object;)Ljava/lang/invoke/MethodHandle;
   #6 = Methodref          #3.#45         // java/lang/invoke/ConstantCallSite."<init>":(Ljava/lang/invoke/MethodHandle;)V
   #7 = Class              #46            // scala/runtime/Static
   #8 = Class              #47            // java/lang/Object
   #9 = Utf8               <init>
  #10 = Utf8               ()V
  #11 = Utf8               Code
  #12 = Utf8               LineNumberTable
  #13 = Utf8               LocalVariableTable
  #14 = Utf8               this
  #15 = Utf8               Lscala/runtime/Static;
  #16 = Utf8               bootstrap
  #17 = Class              #48            // java/lang/invoke/MethodHandles$Lookup
  #18 = Utf8               Lookup
  #19 = Utf8               InnerClasses
  #20 = Utf8               (Ljava/lang/invoke/MethodHandles$Lookup;Ljava/lang/String;Ljava/lang/invoke/MethodType;Ljava/lang/invoke/MethodHandle;[Ljava/lang/Object;)Ljava/lang/invoke/CallSite;
  #21 = Utf8               lookup
  #22 = Utf8               Ljava/lang/invoke/MethodHandles$Lookup;
  #23 = Utf8               invokedName
  #24 = Utf8               Ljava/lang/String;
  #25 = Utf8               invokedType
  #26 = Utf8               Ljava/lang/invoke/MethodType;
  #27 = Utf8               handle
  #28 = Utf8               Ljava/lang/invoke/MethodHandle;
  #29 = Utf8               args
  #30 = Utf8               [Ljava/lang/Object;
  #31 = Utf8               value
  #32 = Utf8               Ljava/lang/Object;
  #33 = Utf8               Exceptions
  #34 = Class              #49            // java/lang/Throwable
  #35 = Utf8               SourceFile
  #36 = Utf8               Static.java
  #37 = NameAndType        #9:#10         // "<init>":()V
  #38 = Class              #50            // java/lang/invoke/MethodHandle
  #39 = NameAndType        #51:#52        // invokeWithArguments:([Ljava/lang/Object;)Ljava/lang/Object;
  #40 = Utf8               java/lang/invoke/ConstantCallSite
  #41 = Class              #53            // java/lang/invoke/MethodType
  #42 = NameAndType        #54:#55        // returnType:()Ljava/lang/Class;
  #43 = Class              #56            // java/lang/invoke/MethodHandles
  #44 = NameAndType        #57:#58        // constant:(Ljava/lang/Class;Ljava/lang/Object;)Ljava/lang/invoke/MethodHandle;
  #45 = NameAndType        #9:#59         // "<init>":(Ljava/lang/invoke/MethodHandle;)V
  #46 = Utf8               scala/runtime/Static
  #47 = Utf8               java/lang/Object
  #48 = Utf8               java/lang/invoke/MethodHandles$Lookup
  #49 = Utf8               java/lang/Throwable
  #50 = Utf8               java/lang/invoke/MethodHandle
  #51 = Utf8               invokeWithArguments
  #52 = Utf8               ([Ljava/lang/Object;)Ljava/lang/Object;
  #53 = Utf8               java/lang/invoke/MethodType
  #54 = Utf8               returnType
  #55 = Utf8               ()Ljava/lang/Class;
  #56 = Utf8               java/lang/invoke/MethodHandles
  #57 = Utf8               constant
  #58 = Utf8               (Ljava/lang/Class;Ljava/lang/Object;)Ljava/lang/invoke/MethodHandle;
  #59 = Utf8               (Ljava/lang/invoke/MethodHandle;)V
{
  private scala.runtime.Static();
    descriptor: ()V
    flags: (0x0002) ACC_PRIVATE
    Code:
      stack=1, locals=1, args_size=1
         0: aload_0
         1: invokespecial #1                  // Method java/lang/Object."<init>":()V
         4: return
      LineNumberTable:
        line 18: 0
        line 19: 4
      LocalVariableTable:
        Start  Length  Slot  Name   Signature
            0       5     0  this   Lscala/runtime/Static;

  public static java.lang.invoke.CallSite bootstrap(java.lang.invoke.MethodHandles$Lookup, java.lang.String, java.lang.invoke.MethodType, java.lang.invoke.MethodHandle, java.lang.Object...) throws java.lang.Throwable;
    descriptor: (Ljava/lang/invoke/MethodHandles$Lookup;Ljava/lang/String;Ljava/lang/invoke/MethodType;Ljava/lang/invoke/MethodHandle;[Ljava/lang/Object;)Ljava/lang/invoke/CallSite;
    flags: (0x0089) ACC_PUBLIC, ACC_STATIC, ACC_VARARGS
    Code:
      stack=4, locals=6, args_size=5
         0: aload_3
         1: aload         4
         3: invokevirtual #2                  // Method java/lang/invoke/MethodHandle.invokeWithArguments:([Ljava/lang/Object;)Ljava/lang/Object;
         6: astore        5
         8: new           #3                  // class java/lang/invoke/ConstantCallSite
        11: dup
        12: aload_2
        13: invokevirtual #4                  // Method java/lang/invoke/MethodType.returnType:()Ljava/lang/Class;
        16: aload         5
        18: invokestatic  #5                  // Method java/lang/invoke/MethodHandles.constant:(Ljava/lang/Class;Ljava/lang/Object;)Ljava/lang/invoke/MethodHandle;
        21: invokespecial #6                  // Method java/lang/invoke/ConstantCallSite."<init>":(Ljava/lang/invoke/MethodHandle;)V
        24: areturn
      LineNumberTable:
        line 22: 0
        line 23: 8
      LocalVariableTable:
        Start  Length  Slot  Name   Signature
            0      25     0 lookup   Ljava/lang/invoke/MethodHandles$Lookup;
            0      25     1 invokedName   Ljava/lang/String;
            0      25     2 invokedType   Ljava/lang/invoke/MethodType;
            0      25     3 handle   Ljava/lang/invoke/MethodHandle;
            0      25     4  args   [Ljava/lang/Object;
            8      17     5 value   Ljava/lang/Object;
    Exceptions:
      throws java.lang.Throwable
}
SourceFile: "Static.java"
InnerClasses:
  public static final #18= #17 of #43;    // Lookup=class java/lang/invoke/MethodHandles$Lookup of class java/lang/invoke/MethodHandles
