Classfile /Users/mw/Projects/slang-braindump/.jar/jar11/assemble/slang-braindump/assemble/content/scala/runtime/Tuple2Zipped.class
  Last modified May 29, 2022; size 18770 bytes
  SHA-256 checksum 6245bc000a7011138feb905264cceeda71d59f4cfaec6d2d075598820e3d99dd
  Compiled from "Tuple2Zipped.scala"
public final class scala.runtime.Tuple2Zipped<El1 extends java.lang.Object, It1 extends scala.collection.Iterable<El1>, El2 extends java.lang.Object, It2 extends scala.collection.Iterable<El2>> extends java.lang.Object implements scala.runtime.ZippedIterable2<El1, El2>
  minor version: 0
  major version: 52
  flags: (0x0031) ACC_PUBLIC, ACC_FINAL, ACC_SUPER
  this_class: #2                          // scala/runtime/Tuple2Zipped
  super_class: #5                         // java/lang/Object
  interfaces: 1, fields: 1, methods: 28, attributes: 7
Constant pool:
    #1 = Utf8               scala/runtime/Tuple2Zipped
    #2 = Class              #1            // scala/runtime/Tuple2Zipped
    #3 = Utf8               <El1:Ljava/lang/Object;It1::Lscala/collection/Iterable<TEl1;>;El2:Ljava/lang/Object;It2::Lscala/collection/Iterable<TEl2;>;>Ljava/lang/Object;Lscala/runtime/ZippedIterable2<TEl1;TEl2;>;
    #4 = Utf8               java/lang/Object
    #5 = Class              #4            // java/lang/Object
    #6 = Utf8               scala/runtime/ZippedIterable2
    #7 = Class              #6            // scala/runtime/ZippedIterable2
    #8 = Utf8               Tuple2Zipped.scala
    #9 = Utf8               Lscala/reflect/ScalaSignature;
   #10 = Utf8               bytes
   #11 = Utf8               \u0006\u0005\u0015Ed\u0001\u0002\u00192\u0005YBAB\u0014\u0001\u0005\u0002\u0003\u0015)Q1A\u0005\n=C\u0011b\u0019\u0001\u0003\u0006\u0003\u0005\u000b\u0011\u0002)\t\u000b\u0011\u0004A\u0011A3\t\u000b%\u0004A\u0011\u00026\t\u000b-\u0004A\u0011\u00027\t\u000b5\u0004A\u0011\u00018\t\u000f\u0005%\u0001\u0001\"\u0001\u0002\f!9\u0011q\u0005\u0001\u0005\u0002\u0005%\u0002bBA*\u0001\u0011\u0005\u0011Q\u000b\u0005\b\u00037\u0002A\u0011AA/\u0011\u001d\t\t\u0007\u0001C\u0001\u0003GBq!!\u001c\u0001\t\u0003\ny\u0007C\u0004\u0002r\u0001!\t!a\u001d\t\u000f\u0005\u001d\u0005\u0001\"\u0011\u0002\n\"I\u0011\u0011\u0015\u0001\u0002\u0002\u0013\u0005\u00131\u0015\u0005\n\u0003W\u0003\u0011\u0011!C!\u0003[;q!a22\u0011\u0003\tIM\u0002\u00041c!\u0005\u00111\u001a\u0005\u0007IJ!\t!a5\u0007\r\u0005U\'CAAl\u00119\tY\u000e\u0006C\u0001\u0002\u000b\u0015)\u0019!C\u0005\u0003;D1\"!<\u0015\u0005\u000b\u0005\t\u0015!\u0003\u0002`\"1A\r\u0006C\u0001\u0003_Dq!!?\u0015\t\u0003\tY\u0010C\u0004\u0003HQ!\tA!\u0013\t\u0013\u0005\u0005F#!A\u0005B\u0005\r\u0006\"CAV)\u0005\u0005I\u0011\tBG\u000f%\u0011\tJEA\u0001\u0012\u0003\u0011\u0019JB\u0005\u0002VJ\t\t\u0011#\u0001\u0003\u0016\"1A-\bC\u0001\u0005/CqA!\'\u001e\t\u000b\u0011Y\nC\u0004\u0003hv!)A!;\t\u0013\r-R$!A\u0005\u0006\r5\u0002\"CB\u001f;\u0005\u0005IQAB \u0011\u001d\u0019\u0019F\u0005C\u0003\u0007+Bqa!\u001e\u0013\t\u000b\u00199\bC\u0004\u0004\u0018J!)a!\'\t\u000f\r5\'\u0003\"\u0002\u0004P\"9AQ\u0001\n\u0005\u0006\u0011\u001d\u0001b\u0002C!%\u0011\u0015A1\t\u0005\b\tS\u0012BQ\u0001C6\u0011\u001d!\tJ\u0005C\u0003\t\'Cq\u0001b.\u0013\t\u000b!I\fC\u0004\u0005ZJ!)\u0001b7\t\u000f\u0015\u0015!\u0003\"\u0002\u0006\b!I11\u0006\n\u0002\u0002\u0013\u0015Qq\u0005\u0005\n\u0007{\u0011\u0012\u0011!C\u0003\u000b\u000f\u0012A\u0002V;qY\u0016\u0014$,\u001b9qK\u0012T!AM\u001a\u0002\u000fI,h\u000e^5nK*\tA\'A\u0003tG\u0006d\u0017m\u0001\u0001\u0016\u000b]\u0012E\u000bT0\u0014\u0007\u0001AD\b\u0005\u0002:u5\t1\'\u0003\u0002<g\t1\u0011I\\=WC2\u0004B!\u0010 A\u00176\t\u0011\'\u0003\u0002@c\ty!,\u001b9qK\u0012LE/\u001a:bE2,\'\u0007\u0005\u0002B\u00052\u0001A!B\"\u0001\u0005\u0004!%aA#mcE\u0011Q\t\u0013\t\u0003s\u0019K!aR\u001a\u0003\u000f9{G\u000f[5oOB\u0011\u0011(S\u0005\u0003\u0015N\u00121!\u00118z!\t\tE\nB\u0003N\u0001\t\u0007AIA\u0002FYJ\n\u0011e]2bY\u0006$#/\u001e8uS6,G\u0005V;qY\u0016\u0014$,\u001b9qK\u0012$CeY8mYN,\u0012\u0001\u0015\t\u0005sE\u001bf,\u0003\u0002Sg\t1A+\u001e9mKJ\u0002\"!\u0011+\u0005\u000bU\u0003!\u0019\u0001,\u0003\u0007%#\u0018\'\u0005\u0002F/B\u0019\u0001l\u0017!\u000f\u0005eJ\u0016B\u0001.4\u0003\u001d\u0001\u0018mY6bO\u0016L!\u0001X/\u0003\u0011%#XM]1cY\u0016T!AW\u001a\u0011\u0005\u0005{F!\u00021\u0001\u0005\u0004\t\'aA%ueE\u0011QI\u0019\t\u00041n[\u0015AI:dC2\fGE];oi&lW\r\n+va2,\'GW5qa\u0016$G\u0005J2pY2\u001c\b%\u0001\u0004=S:LGO\u0010\u000b\u0003M\u001e\u0004b!\u0010\u0001A\'.s\u0006\"\u00025\u0004\u0001\u0004\u0001\u0016!B2pY2\u001c\u0018!B2pY2\fT#A*\u0002\u000b\r|G\u000e\u001c\u001a\u0016\u0003y\u000b1!\\1q+\ryWP\u001d\u000b\u0003a~$\"!\u001d;\u0011\u0005\u0005\u0013H!B:\u0007\u0005\u0004!%A\u0001+p\u0011\u0015)h\u0001q\u0001w\u0003\t\u0011g\rE\u0003xuNc\u0018/D\u0001y\u0015\tI8\'\u0001\u0006d_2dWm\u0019;j_:L!a\u001f=\u0003\u0013\t+\u0018\u000e\u001c3Ge>l\u0007CA!~\t\u0015qhA1\u0001E\u0005\u0005\u0011\u0005bBA\u0001\r\u0001\u0007\u00111A\u0001\u0002MB1\u0011(!\u0002A\u0017rL1!a\u00024\u0005%1UO\\2uS>t\'\'A\u0004gY\u0006$X*\u00199\u0016\r\u00055\u00111DA\n)\u0011\ty!!\b\u0015\t\u0005E\u0011Q\u0003\t\u0004\u0003\u0006MA!B:\b\u0005\u0004!\u0005BB;\b\u0001\b\t9\u0002E\u0004xuN\u000bI\"!\u0005\u0011\u0007\u0005\u000bY\u0002B\u0003\u007f\u000f\t\u0007A\tC\u0004\u0002\u0002\u001d\u0001\r!a\b\u0011\u000fe\n)\u0001Q&\u0002\"A)\u0001,a\t\u0002\u001a%\u0019\u0011QE/\u0003\u0019%#XM]1cY\u0016|enY3\u0002\r\u0019LG\u000e^3s+\u0019\tY#a\r\u0002:Q!\u0011QFA%)\u0019\ty#!\u0010\u0002DA1\u0011(UA\u0019\u0003o\u00012!QA\u001a\t\u0019\t)\u0004\u0003b\u0001\t\n\u0019Ak\\\u0019\u0011\u0007\u0005\u000bI\u0004\u0002\u0004\u0002<!\u0011\r\u0001\u0012\u0002\u0004)>\u0014\u0004bBA \u0011\u0001\u000f\u0011\u0011I\u0001\u0004E\u001a\f\u0004CB<{\'\u0002\u000b\t\u0004C\u0004\u0002F!\u0001\u001d!a\u0012\u0002\u0007\t4\'\u0007\u0005\u0004xuz[\u0015q\u0007\u0005\b\u0003\u0003A\u0001\u0019AA&!\u001dI\u0014Q\u0001!L\u0003\u001b\u00022!OA(\u0013\r\t\tf\r\u0002\b\u0005>|G.Z1o\u0003\u0019)\u00070[:ugR!\u0011QJA,\u0011\u001d\tI&\u0003a\u0001\u0003\u0017\n\u0011\u0001]\u0001\u0007M>\u0014\u0018\r\u001c7\u0015\t\u00055\u0013q\f\u0005\b\u00033R\u0001\u0019AA&\u0003!IG/\u001a:bi>\u0014XCAA3!\u0015A\u0016qMA6\u0013\r\tI\'\u0018\u0002\t\u0013R,\'/\u0019;peB!\u0011(\u0015!L\u0003\u001dI7/R7qif,\"!!\u0014\u0002\u000f\u0019|\'/Z1dQV!\u0011QOAB)\u0011\t9(! \u0011\u0007e\nI(C\u0002\u0002|M\u0012A!\u00168ji\"9\u0011\u0011A\u0007A\u0002\u0005}\u0004cB\u001d\u0002\u0006\u0001[\u0015\u0011\u0011\t\u0004\u0003\u0006\rEABAC\u001b\t\u0007AIA\u0001V\u0003!!xn\u0015;sS:<GCAAF!\u0011\ti)a\'\u000f\t\u0005=\u0015q\u0013\t\u0004\u0003#\u001bTBAAJ\u0015\r\t)*N\u0001\u0007yI|w\u000e\u001e \n\u0007\u0005e5\'\u0001\u0004Qe\u0016$WMZ\u0005\u0005\u0003;\u000byJ\u0001\u0004TiJLgn\u001a\u0006\u0004\u00033\u001b\u0014\u0001\u00035bg\"\u001cu\u000eZ3\u0015\u0005\u0005\u0015\u0006cA\u001d\u0002(&\u0019\u0011\u0011V\u001a\u0003\u0007%sG/\u0001\u0004fcV\fGn\u001d\u000b\u0005\u0003\u001b\ny\u000b\u0003\u0005\u00022B\t\t\u00111\u0001I\u0003\rAH%\r\u0015\f\u0001\u0005U\u00161XA_\u0003\u0003\f\u0019\rE\u0002:\u0003oK1!!/4\u0005)!W\r\u001d:fG\u0006$X\rZ\u0001\b[\u0016\u001c8/Y4fC\t\ty,\u0001\u0010Vg\u0016\u00043oY1mC:\u001aw\u000e\u001c7fGRLwN\u001c\u0018MCjL(,\u001b93]\u0005)1/\u001b8dK\u0006\u0012\u0011QY\u0001\u0007e9\n4G\f\u0019\u0002\u0019Q+\b\u000f\\335&\u0004\b/\u001a3\u0011\u0005u\u00122c\u0001\n\u0002NB\u0019\u0011(a4\n\u0007\u0005E7G\u0001\u0004B]f\u0014VM\u001a\u000b\u0003\u0003\u0013\u00141a\u00149t+\u0019\tI.a9\u0002jN\u0011A\u0003O\u0001\"g\u000e\fG.\u0019\u0013sk:$\u0018.\\3%)V\u0004H.\u001a\u001a[SB\u0004X\r\u001a\u0013PaN$C\u0005_\u000b\u0003\u0003?\u0004b!O)\u0002b\u0006\u001d\bcA!\u0002d\u00121\u0011Q\u001d\u000bC\u0002\u0011\u0013!\u0001V\u0019\u0011\u0007\u0005\u000bI\u000f\u0002\u0004\u0002lR\u0011\r\u0001\u0012\u0002\u0003)J\n!e]2bY\u0006$#/\u001e8uS6,G\u0005V;qY\u0016\u0014$,\u001b9qK\u0012$s\n]:%Ia\u0004C\u0003BAy\u0003k\u0004r!a=\u0015\u0003C\f9/D\u0001\u0013\u0011\u001d\t9p\u0006a\u0001\u0003?\f\u0011\u0001_\u0001\u0007S:4XM\u001d;\u0016\u0019\u0005u(\u0011\u0005B\t\u0005s\u0011YC!\u0001\u0015\u0011\u0005}(Q\u0001B\u0012\u0005w\u00012!\u0011B\u0001\t\u0019\u0011\u0019\u0001\u0007b\u0001\t\n!A\u000b[1u\u0011\u001d\u00119\u0001\u0007a\u0002\u0005\u0013\t!a^\u0019\u0011\u000fe\u0012Y!!9\u0003\u0010%\u0019!QB\u001a\u0003!\u0011bWm]:%G>dwN\u001c\u0013mKN\u001c\b#B!\u0003\u0012\t}AAB+\u0019\u0005\u0004\u0011\u0019\"\u0006\u0003\u0003\u0016\tm\u0011cA#\u0003\u0018A!\u0001l\u0017B\r!\r\t%1\u0004\u0003\b\u0005;\u0011\tB1\u0001E\u0005\u0005\t\u0007cA!\u0003\"\u0011)1\t\u0007b\u0001\t\"9!Q\u0005\rA\u0004\t\u001d\u0012AA<3!\u001dI$1BAt\u0005S\u0001R!\u0011B\u0016\u0005o!a\u0001\u0019\rC\u0002\t5R\u0003\u0002B\u0018\u0005k\t2!\u0012B\u0019!\u0011A6La\r\u0011\u0007\u0005\u0013)\u0004B\u0004\u0003\u001e\t-\"\u0019\u0001#\u0011\u0007\u0005\u0013I\u0004B\u0003N1\t\u0007A\t\u0003\u0004v1\u0001\u000f!Q\b\t\toj\f\tOa\u0010\u0002\u0000B1\u0011(\u0015B\u0010\u0005oA3\u0002GA[\u0003w\u0013\u0019%!1\u0002D\u0006\u0012!QI\u0001\u001f+N,\u0007\u0005_:/Y\u0006T\u0018PW5qQeT\u0018FL7ba\"Bs\f\f\u0011`S%\naA_5qa\u0016$WC\u0003B&\u0005#\u0012)F!\u0018\u0003bQ1!Q\nB4\u0005{\u0002\"\"\u0010\u0001\u0003P\tM#1\fB0!\r\t%\u0011\u000b\u0003\u0006\u0007f\u0011\r\u0001\u0012\t\u0004\u0003\nUCAB+\u001a\u0005\u0004\u00119&E\u0002F\u00053\u0002B\u0001W.\u0003PA\u0019\u0011I!\u0018\u0005\u000b5K\"\u0019\u0001#\u0011\u0007\u0005\u0013\t\u0007\u0002\u0004a3\t\u0007!1M\t\u0004\u000b\n\u0015\u0004\u0003\u0002-\\\u00057BqAa\u0002\u001a\u0001\b\u0011I\u0007E\u0004:\u0005W\n\tOa\u001c\n\u0007\t54GA\u0005Gk:\u001cG/[8ocI1!\u0011\u000fB;\u0005\'2aAa\u001d\u0015\u0001\t=$\u0001\u0004\u001fsK\u001aLg.Z7f]Rt\u0004#C<\u0003x\t=#1\u0010B*\u0013\r\u0011I\b\u001f\u0002\f\u0013R,\'/\u00192mK>\u00038\u000f\u0005\u0002Y7\"9!QE\rA\u0004\t}\u0004cB\u001d\u0003l\u0005\u001d(\u0011\u0011\n\u0007\u0005\u0007\u0013)Ia\u0018\u0007\r\tMD\u0003\u0001BA!%9(q\u000fB.\u0005w\u0012y\u0006K\u0006\u001a\u0003k\u000bYL!#\u0002B\u0006\r\u0017E\u0001BF\u0003I)6/\u001a\u0011yg:b\u0017M_=[SBD\u0013p]\u0015\u0015\t\u00055#q\u0012\u0005\t\u0003c[\u0012\u0011!a\u0001\u0011\u0006\u0019q\n]:\u0011\u0007\u0005MXdE\u0002\u001e\u0003\u001b$\"Aa%\u0002!%tg/\u001a:uI\u0015DH/\u001a8tS>tW\u0003\u0005BO\u0005{\u0013yKa6\u0003J\n\r&1\u0016Bc)\u0011\u0011yJa8\u0015\u0011\t\u0005&Q\u0015B`\u00053\u00042!\u0011BR\t\u0019\u0011\u0019a\bb\u0001\t\"9!qA\u0010A\u0004\t\u001d\u0006cB\u001d\u0003\f\t%&Q\u0016\t\u0004\u0003\n-FABAs?\t\u0007A\tE\u0003B\u0005_\u0013Y\f\u0002\u0004V?\t\u0007!\u0011W\u000b\u0005\u0005g\u0013I,E\u0002F\u0005k\u0003B\u0001W.\u00038B\u0019\u0011I!/\u0005\u000f\tu!q\u0016b\u0001\tB\u0019\u0011I!0\u0005\u000b\r{\"\u0019\u0001#\t\u000f\t\u0015r\u0004q\u0001\u0003BB9\u0011Ha\u0003\u0003D\n\u001d\u0007cA!\u0003F\u00121\u00111^\u0010C\u0002\u0011\u0003R!\u0011Be\u0005+$a\u0001Y\u0010C\u0002\t-W\u0003\u0002Bg\u0005\'\f2!\u0012Bh!\u0011A6L!5\u0011\u0007\u0005\u0013\u0019\u000eB\u0004\u0003\u001e\t%\'\u0019\u0001#\u0011\u0007\u0005\u00139\u000eB\u0003N?\t\u0007A\t\u0003\u0004v?\u0001\u000f!1\u001c\t\toj\u0014IK!8\u0003\"B1\u0011(\u0015B^\u0005+DqA!9 \u0001\u0004\u0011\u0019/A\u0003%i\"L7\u000fE\u0004\u0002tR\u0011IKa1)\u0017}\t),a/\u0003D\u0005\u0005\u00171Y\u0001\u0011u&\u0004\b/\u001a3%Kb$XM\\:j_:,bBa;\u0003t\n](q`B\u0002\u0007\u001f\u0019i\u0002\u0006\u0003\u0003n\u000e\u0015BC\u0002Bx\u0007\u0013\u00199\u0002\u0005\u0006>\u0001\tE(Q\u001fB\u007f\u0007\u0003\u00012!\u0011Bz\t\u0015\u0019\u0005E1\u0001E!\r\t%q\u001f\u0003\u0007+\u0002\u0012\rA!?\u0012\u0007\u0015\u0013Y\u0010\u0005\u0003Y7\nE\bcA!\u0003\u0000\u0012)Q\n\tb\u0001\tB\u0019\u0011ia\u0001\u0005\r\u0001\u0004#\u0019AB\u0003#\r)5q\u0001\t\u00051n\u0013i\u0010C\u0004\u0003\b\u0001\u0002\u001daa\u0003\u0011\u000fe\u0012Yg!\u0004\u0004\u0012A\u0019\u0011ia\u0004\u0005\r\u0005\u0015\bE1\u0001E%\u0019\u0019\u0019b!\u0006\u0003v\u001a1!1\u000f\u000b\u0001\u0007#\u0001\u0012b\u001eB<\u0005c\u0014YH!>\t\u000f\t\u0015\u0002\u0005q\u0001\u0004\u001aA9\u0011Ha\u001b\u0004\u001c\r}\u0001cA!\u0004\u001e\u00111\u00111\u001e\u0011C\u0002\u0011\u0013ba!\t\u0004$\r\u0005aA\u0002B:)\u0001\u0019y\u0002E\u0005x\u0005o\u0012iPa\u001f\u0004\u0002!9!\u0011\u001d\u0011A\u0002\r\u001d\u0002cBAz)\r511\u0004\u0015\fA\u0005U\u00161\u0018BE\u0003\u0003\f\u0019-\u0001\niCND7i\u001c3fI\u0015DH/\u001a8tS>tWCBB\u0018\u0007o\u0019Y\u0004\u0006\u0003\u0002$\u000eE\u0002b\u0002BqC\u0001\u000711\u0007\t\b\u0003g$2QGB\u001d!\r\t5q\u0007\u0003\u0007\u0003K\f#\u0019\u0001#\u0011\u0007\u0005\u001bY\u0004\u0002\u0004\u0002l\u0006\u0012\r\u0001R\u0001\u0011KF,\u0018\r\\:%Kb$XM\\:j_:,ba!\u0011\u0004N\rEC\u0003BB\"\u0007\u000f\"B!!\u0014\u0004F!A\u0011\u0011\u0017\u0012\u0002\u0002\u0003\u0007\u0001\nC\u0004\u0003b\n\u0002\ra!\u0013\u0011\u000f\u0005MHca\u0013\u0004PA\u0019\u0011i!\u0014\u0005\r\u0005\u0015(E1\u0001E!\r\t5\u0011\u000b\u0003\u0007\u0003W\u0014#\u0019\u0001#\u0002\u001f\r|G\u000e\\\u0019%Kb$XM\\:j_:,\"ba\u0016\u0004d\rm31NB8)\u0011\u0019If!\u001a\u0011\u0007\u0005\u001bY\u0006\u0002\u0004VG\t\u00071QL\t\u0004\u000b\u000e}\u0003\u0003\u0002-\\\u0007C\u00022!QB2\t\u0015\u00195E1\u0001E\u0011\u001d\u0011\to\ta\u0001\u0007O\u0002\"\"\u0010\u0001\u0004b\re3\u0011NB7!\r\t51\u000e\u0003\u0006\u001b\u000e\u0012\r\u0001\u0012\t\u0004\u0003\u000e=DA\u00021$\u0005\u0004\u0019\t(E\u0002F\u0007g\u0002B\u0001W.\u0004j\u0005y1m\u001c7me\u0011*\u0007\u0010^3og&|g.\u0006\u0006\u0004z\r55\u0011SBC\u0007{\"Baa\u001f\u0004\bB\u0019\u0011i! \u0005\r\u0001$#\u0019AB@#\r)5\u0011\u0011\t\u00051n\u001b\u0019\tE\u0002B\u0007\u000b#Q!\u0014\u0013C\u0002\u0011CqA!9%\u0001\u0004\u0019I\t\u0005\u0006>\u0001\r-5qRBB\u0007w\u00022!QBG\t\u0015\u0019EE1\u0001E!\r\t5\u0011\u0013\u0003\u0007+\u0012\u0012\raa%\u0012\u0007\u0015\u001b)\n\u0005\u0003Y7\u000e-\u0015!D7ba\u0012*\u0007\u0010^3og&|g.\u0006\b\u0004\u001c\u000e]61UBZ\u0007W\u001byla2\u0015\t\ru5\u0011\u0019\u000b\u0005\u0007?\u001bI\f\u0006\u0003\u0004\"\u000e\u0015\u0006cA!\u0004$\u0012)1/\nb\u0001\t\"1Q/\na\u0002\u0007O\u0003\u0002b\u001e>\u0004*\u000eU6\u0011\u0015\t\u0004\u0003\u000e-FAB+&\u0005\u0004\u0019i+E\u0002F\u0007_\u0003B\u0001W.\u00042B\u0019\u0011ia-\u0005\u000b\r+#\u0019\u0001#\u0011\u0007\u0005\u001b9\fB\u0003\u007fK\t\u0007A\tC\u0004\u0002\u0002\u0015\u0002\raa/\u0011\u0013e\n)a!-\u0004>\u000eU\u0006cA!\u0004@\u0012)Q*\nb\u0001\t\"9!\u0011]\u0013A\u0002\r\r\u0007CC\u001f\u0001\u0007c\u001bIk!0\u0004FB\u0019\u0011ia2\u0005\r\u0001,#\u0019ABe#\r)51\u001a\t\u00051n\u001bi,A\tgY\u0006$X*\u00199%Kb$XM\\:j_:,bb!5\u0004n\u000ee7\u0011^Bq\u0007k\u001cy\u0010\u0006\u0003\u0004T\u000eeH\u0003BBk\u0007_$Baa6\u0004\\B\u0019\u0011i!7\u0005\u000bM4#\u0019\u0001#\t\rU4\u00039ABo!!9(pa8\u0004l\u000e]\u0007cA!\u0004b\u00121QK\nb\u0001\u0007G\f2!RBs!\u0011A6la:\u0011\u0007\u0005\u001bI\u000fB\u0003DM\t\u0007A\tE\u0002B\u0007[$QA \u0014C\u0002\u0011Cq!!\u0001\'\u0001\u0004\u0019\t\u0010E\u0005:\u0003\u000b\u00199oa=\u0004xB\u0019\u0011i!>\u0005\u000b53#\u0019\u0001#\u0011\u000ba\u000b\u0019ca;\t\u000f\t\u0005h\u00051\u0001\u0004|BQQ\bABt\u0007?\u001c\u0019p!@\u0011\u0007\u0005\u001by\u0010\u0002\u0004aM\t\u0007A\u0011A\t\u0004\u000b\u0012\r\u0001\u0003\u0002-\\\u0007g\f\u0001CZ5mi\u0016\u0014H%\u001a=uK:\u001c\u0018n\u001c8\u0016\u001d\u0011%A1\u0003C\f\tO!y\u0002b\u000e\u00050Q!A1\u0002C\u001f)\u0011!i\u0001\"\u000f\u0015\r\u0011=A\u0011\u0004C\u0015!\u0019I\u0014\u000b\"\u0005\u0005\u0016A\u0019\u0011\tb\u0005\u0005\r\u0005UrE1\u0001E!\r\tEq\u0003\u0003\u0007\u0003w9#\u0019\u0001#\t\u000f\u0005}r\u0005q\u0001\u0005\u001cAAqO\u001fC\u000f\tK!\t\u0002E\u0002B\t?!a!V\u0014C\u0002\u0011\u0005\u0012cA#\u0005$A!\u0001l\u0017C\u0013!\r\tEq\u0005\u0003\u0006\u0007\u001e\u0012\r\u0001\u0012\u0005\b\u0003\u000b:\u00039\u0001C\u0016!!9(\u0010\"\f\u00056\u0011U\u0001cA!\u00050\u00111\u0001m\nb\u0001\tc\t2!\u0012C\u001a!\u0011A6\f\"\u000e\u0011\u0007\u0005#9\u0004B\u0003NO\t\u0007A\tC\u0004\u0002\u0002\u001d\u0002\r\u0001b\u000f\u0011\u0013e\n)\u0001\"\n\u00056\u00055\u0003b\u0002BqO\u0001\u0007Aq\b\t\u000b{\u0001!)\u0003\"\b\u00056\u00115\u0012\u0001E3ySN$8\u000fJ3yi\u0016t7/[8o+)!)\u0005b\u0014\u0005\\\u0011MC1\r\u000b\u0005\t\u000f\")\u0006\u0006\u0003\u0002N\u0011%\u0003bBA-Q\u0001\u0007A1\n\t\ns\u0005\u0015AQ\nC)\u0003\u001b\u00022!\u0011C(\t\u0015\u0019\u0005F1\u0001E!\r\tE1\u000b\u0003\u0006\u001b\"\u0012\r\u0001\u0012\u0005\b\u0005CD\u0003\u0019\u0001C,!)i\u0004\u0001\"\u0014\u0005Z\u0011EC\u0011\r\t\u0004\u0003\u0012mCAB+)\u0005\u0004!i&E\u0002F\t?\u0002B\u0001W.\u0005NA\u0019\u0011\tb\u0019\u0005\r\u0001D#\u0019\u0001C3#\r)Eq\r\t\u00051n#\t&\u0001\tg_J\fG\u000e\u001c\u0013fqR,gn]5p]VQAQ\u000eC<\t\u0007#Y\bb#\u0015\t\u0011=DQ\u0010\u000b\u0005\u0003\u001b\"\t\bC\u0004\u0002Z%\u0002\r\u0001b\u001d\u0011\u0013e\n)\u0001\"\u001e\u0005z\u00055\u0003cA!\u0005x\u0011)1)\u000bb\u0001\tB\u0019\u0011\tb\u001f\u0005\u000b5K#\u0019\u0001#\t\u000f\t\u0005\u0018\u00061\u0001\u0005\u0000AQQ\b\u0001C;\t\u0003#I\b\"#\u0011\u0007\u0005#\u0019\t\u0002\u0004VS\t\u0007AQQ\t\u0004\u000b\u0012\u001d\u0005\u0003\u0002-\\\tk\u00022!\u0011CF\t\u0019\u0001\u0017F1\u0001\u0005\u000eF\u0019Q\tb$\u0011\ta[F\u0011P\u0001\u0013SR,\'/\u0019;pe\u0012*\u0007\u0010^3og&|g.\u0006\u0006\u0005\u0016\u0012uE\u0011\u0016CQ\tc#B\u0001b&\u0005$B)\u0001,a\u001a\u0005\u001aB1\u0011(\u0015CN\t?\u00032!\u0011CO\t\u0015\u0019%F1\u0001E!\r\tE\u0011\u0015\u0003\u0006\u001b*\u0012\r\u0001\u0012\u0005\b\u0005CT\u0003\u0019\u0001CS!)i\u0004\u0001b\'\u0005(\u0012}Eq\u0016\t\u0004\u0003\u0012%FAB++\u0005\u0004!Y+E\u0002F\t[\u0003B\u0001W.\u0005\u001cB\u0019\u0011\t\"-\u0005\r\u0001T#\u0019\u0001CZ#\r)EQ\u0017\t\u00051n#y*A\tjg\u0016k\u0007\u000f^=%Kb$XM\\:j_:,\"\u0002b/\u0005D\u0012\u001dGq\u001aCj)\u0011\ti\u0005\"0\t\u000f\t\u00058\u00061\u0001\u0005@BQQ\b\u0001Ca\t\u000b$i\r\"5\u0011\u0007\u0005#\u0019\rB\u0003DW\t\u0007A\tE\u0002B\t\u000f$a!V\u0016C\u0002\u0011%\u0017cA#\u0005LB!\u0001l\u0017Ca!\r\tEq\u001a\u0003\u0006\u001b.\u0012\r\u0001\u0012\t\u0004\u0003\u0012MGA\u00021,\u0005\u0004!).E\u0002F\t/\u0004B\u0001W.\u0005N\u0006\tbm\u001c:fC\u000eDG%\u001a=uK:\u001c\u0018n\u001c8\u0016\u0019\u0011uGq\u001eCt\to$Y\u000fb@\u0015\t\u0011}G\u0011\u001f\u000b\u0005\u0003o\"\t\u000fC\u0004\u0002\u00021\u0002\r\u0001b9\u0011\u0013e\n)\u0001\":\u0005j\u00125\bcA!\u0005h\u0012)1\t\fb\u0001\tB\u0019\u0011\tb;\u0005\u000b5c#\u0019\u0001#\u0011\u0007\u0005#y\u000f\u0002\u0004\u0002\u00062\u0012\r\u0001\u0012\u0005\b\u0005Cd\u0003\u0019\u0001Cz!)i\u0004\u0001\":\u0005v\u0012%HQ \t\u0004\u0003\u0012]HAB+-\u0005\u0004!I0E\u0002F\tw\u0004B\u0001W.\u0005fB\u0019\u0011\tb@\u0005\r\u0001d#\u0019AC\u0001#\r)U1\u0001\t\u00051n#I/\u0001\nu_N#(/\u001b8hI\u0015DH/\u001a8tS>tWCCC\u0005\u000b#))\"\"\b\u0006\"Q!\u0011\u0011RC\u0006\u0011\u001d\u0011\t/\fa\u0001\u000b\u001b\u0001\"\"\u0010\u0001\u0006\u0010\u0015MQ1DC\u0010!\r\tU\u0011\u0003\u0003\u0006\u00076\u0012\r\u0001\u0012\t\u0004\u0003\u0016UAAB+.\u0005\u0004)9\"E\u0002F\u000b3\u0001B\u0001W.\u0006\u0010A\u0019\u0011)\"\b\u0005\u000b5k#\u0019\u0001#\u0011\u0007\u0005+\t\u0003\u0002\u0004a[\t\u0007Q1E\t\u0004\u000b\u0016\u0015\u0002\u0003\u0002-\\\u000b7)\"\"\"\u000b\u00062\u0015URQHC!)\u0011\t\u0019+b\u000b\t\u000f\t\u0005h\u00061\u0001\u0006.AQQ\bAC\u0018\u000bg)Y$b\u0010\u0011\u0007\u0005+\t\u0004B\u0003D]\t\u0007A\tE\u0002B\u000bk!a!\u0016\u0018C\u0002\u0015]\u0012cA#\u0006:A!\u0001lWC\u0018!\r\tUQ\b\u0003\u0006\u001b:\u0012\r\u0001\u0012\t\u0004\u0003\u0016\u0005CA\u00021/\u0005\u0004)\u0019%E\u0002F\u000b\u000b\u0002B\u0001W.\u0006<UQQ\u0011JC+\u000b3*\t\'\"\u001a\u0015\t\u0015-Sq\n\u000b\u0005\u0003\u001b*i\u0005\u0003\u0005\u00022>\n\t\u00111\u0001I\u0011\u001d\u0011\to\fa\u0001\u000b#\u0002\"\"\u0010\u0001\u0006T\u0015]SqLC2!\r\tUQ\u000b\u0003\u0006\u0007>\u0012\r\u0001\u0012\t\u0004\u0003\u0016eCAB+0\u0005\u0004)Y&E\u0002F\u000b;\u0002B\u0001W.\u0006TA\u0019\u0011)\"\u0019\u0005\u000b5{#\u0019\u0001#\u0011\u0007\u0005+)\u0007\u0002\u0004a_\t\u0007QqM\t\u0004\u000b\u0016%\u0004\u0003\u0002-\\\u000b?B3BEA[\u0003w\u000bi,!1\u0002D\"\u001a!#!.)\u0017E\t),a/\u0002>\u0006\u0005\u00171\u0019
   #12 = Utf8               scala/runtime/Tuple2Zipped$Ops
   #13 = Class              #12           // scala/runtime/Tuple2Zipped$Ops
   #14 = Utf8               Ops
   #15 = Utf8               scala/runtime/Tuple2Zipped$Ops$
   #16 = Class              #15           // scala/runtime/Tuple2Zipped$Ops$
   #17 = Utf8               Ops$
   #18 = Utf8               scala$runtime$Tuple2Zipped$$colls
   #19 = Utf8               Lscala/Tuple2;
   #20 = Utf8               Lscala/Tuple2<TIt1;TIt2;>;
   #21 = Utf8               equals$extension
   #22 = Utf8               (Lscala/Tuple2;Ljava/lang/Object;)Z
   #23 = Utf8               <El1:Ljava/lang/Object;It1::Lscala/collection/Iterable<TEl1;>;El2:Ljava/lang/Object;It2::Lscala/collection/Iterable<TEl2;>;>(Lscala/Tuple2<TIt1;TIt2;>;Ljava/lang/Object;)Z
   #24 = Utf8               $this
   #25 = Utf8               x$1
   #26 = Utf8               scala/runtime/Tuple2Zipped$
   #27 = Class              #26           // scala/runtime/Tuple2Zipped$
   #28 = Utf8               MODULE$
   #29 = Utf8               Lscala/runtime/Tuple2Zipped$;
   #30 = NameAndType        #28:#29       // MODULE$:Lscala/runtime/Tuple2Zipped$;
   #31 = Fieldref           #27.#30       // scala/runtime/Tuple2Zipped$.MODULE$:Lscala/runtime/Tuple2Zipped$;
   #32 = NameAndType        #21:#22       // equals$extension:(Lscala/Tuple2;Ljava/lang/Object;)Z
   #33 = Methodref          #27.#32       // scala/runtime/Tuple2Zipped$.equals$extension:(Lscala/Tuple2;Ljava/lang/Object;)Z
   #34 = Utf8               Ljava/lang/Object;
   #35 = Utf8               hashCode$extension
   #36 = Utf8               (Lscala/Tuple2;)I
   #37 = Utf8               <El1:Ljava/lang/Object;It1::Lscala/collection/Iterable<TEl1;>;El2:Ljava/lang/Object;It2::Lscala/collection/Iterable<TEl2;>;>(Lscala/Tuple2<TIt1;TIt2;>;)I
   #38 = Utf8               scala/Tuple2
   #39 = Class              #38           // scala/Tuple2
   #40 = Utf8               hashCode
   #41 = Utf8               ()I
   #42 = NameAndType        #40:#41       // hashCode:()I
   #43 = Methodref          #39.#42       // scala/Tuple2.hashCode:()I
   #44 = Utf8               toString$extension
   #45 = Utf8               (Lscala/Tuple2;)Ljava/lang/String;
   #46 = Utf8               <El1:Ljava/lang/Object;It1::Lscala/collection/Iterable<TEl1;>;El2:Ljava/lang/Object;It2::Lscala/collection/Iterable<TEl2;>;>(Lscala/Tuple2<TIt1;TIt2;>;)Ljava/lang/String;
   #47 = NameAndType        #44:#45       // toString$extension:(Lscala/Tuple2;)Ljava/lang/String;
   #48 = Methodref          #27.#47       // scala/runtime/Tuple2Zipped$.toString$extension:(Lscala/Tuple2;)Ljava/lang/String;
   #49 = Utf8               foreach$extension
   #50 = Utf8               (Lscala/Tuple2;Lscala/Function2;)V
   #51 = Utf8               <U:Ljava/lang/Object;El1:Ljava/lang/Object;It1::Lscala/collection/Iterable<TEl1;>;El2:Ljava/lang/Object;It2::Lscala/collection/Iterable<TEl2;>;>(Lscala/Tuple2<TIt1;TIt2;>;Lscala/Function2<TEl1;TEl2;TU;>;)V
   #52 = Utf8               f
   #53 = Utf8               _1
   #54 = Utf8               ()Ljava/lang/Object;
   #55 = NameAndType        #53:#54       // _1:()Ljava/lang/Object;
   #56 = Methodref          #39.#55       // scala/Tuple2._1:()Ljava/lang/Object;
   #57 = Utf8               scala/collection/Iterable
   #58 = Class              #57           // scala/collection/Iterable
   #59 = Utf8               iterator
   #60 = Utf8               ()Lscala/collection/Iterator;
   #61 = NameAndType        #59:#60       // iterator:()Lscala/collection/Iterator;
   #62 = InterfaceMethodref #58.#61       // scala/collection/Iterable.iterator:()Lscala/collection/Iterator;
   #63 = Utf8               _2
   #64 = NameAndType        #63:#54       // _2:()Ljava/lang/Object;
   #65 = Methodref          #39.#64       // scala/Tuple2._2:()Ljava/lang/Object;
   #66 = Utf8               scala/collection/Iterator
   #67 = Class              #66           // scala/collection/Iterator
   #68 = Utf8               hasNext
   #69 = Utf8               ()Z
   #70 = NameAndType        #68:#69       // hasNext:()Z
   #71 = InterfaceMethodref #67.#70       // scala/collection/Iterator.hasNext:()Z
   #72 = Utf8               next
   #73 = NameAndType        #72:#54       // next:()Ljava/lang/Object;
   #74 = InterfaceMethodref #67.#73       // scala/collection/Iterator.next:()Ljava/lang/Object;
   #75 = Utf8               scala/Function2
   #76 = Class              #75           // scala/Function2
   #77 = Utf8               apply
   #78 = Utf8               (Ljava/lang/Object;Ljava/lang/Object;)Ljava/lang/Object;
   #79 = NameAndType        #77:#78       // apply:(Ljava/lang/Object;Ljava/lang/Object;)Ljava/lang/Object;
   #80 = InterfaceMethodref #76.#79       // scala/Function2.apply:(Ljava/lang/Object;Ljava/lang/Object;)Ljava/lang/Object;
   #81 = Utf8               Lscala/Function2;
   #82 = Utf8               foreach$extension_elems1
   #83 = Utf8               Lscala/collection/Iterator;
   #84 = Utf8               foreach$extension_elems2
   #85 = Utf8               isEmpty$extension
   #86 = Utf8               (Lscala/Tuple2;)Z
   #87 = Utf8               <El1:Ljava/lang/Object;It1::Lscala/collection/Iterable<TEl1;>;El2:Ljava/lang/Object;It2::Lscala/collection/Iterable<TEl2;>;>(Lscala/Tuple2<TIt1;TIt2;>;)Z
   #88 = NameAndType        #85:#86       // isEmpty$extension:(Lscala/Tuple2;)Z
   #89 = Methodref          #27.#88       // scala/runtime/Tuple2Zipped$.isEmpty$extension:(Lscala/Tuple2;)Z
   #90 = Utf8               iterator$extension
   #91 = Utf8               (Lscala/Tuple2;)Lscala/collection/Iterator;
   #92 = Utf8               <El1:Ljava/lang/Object;It1::Lscala/collection/Iterable<TEl1;>;El2:Ljava/lang/Object;It2::Lscala/collection/Iterable<TEl2;>;>(Lscala/Tuple2<TIt1;TIt2;>;)Lscala/collection/Iterator<Lscala/Tuple2<TEl1;TEl2;>;>;
   #93 = NameAndType        #90:#91       // iterator$extension:(Lscala/Tuple2;)Lscala/collection/Iterator;
   #94 = Methodref          #27.#93       // scala/runtime/Tuple2Zipped$.iterator$extension:(Lscala/Tuple2;)Lscala/collection/Iterator;
   #95 = Utf8               forall$extension
   #96 = Utf8               (Lscala/Tuple2;Lscala/Function2;)Z
   #97 = Utf8               <El1:Ljava/lang/Object;It1::Lscala/collection/Iterable<TEl1;>;El2:Ljava/lang/Object;It2::Lscala/collection/Iterable<TEl2;>;>(Lscala/Tuple2<TIt1;TIt2;>;Lscala/Function2<TEl1;TEl2;Ljava/lang/Object;>;)Z
   #98 = Utf8               p
   #99 = Utf8               scala/runtime/BoxesRunTime
  #100 = Class              #99           // scala/runtime/BoxesRunTime
  #101 = Utf8               unboxToBoolean
  #102 = Utf8               (Ljava/lang/Object;)Z
  #103 = NameAndType        #101:#102     // unboxToBoolean:(Ljava/lang/Object;)Z
  #104 = Methodref          #100.#103     // scala/runtime/BoxesRunTime.unboxToBoolean:(Ljava/lang/Object;)Z
  #105 = Utf8               forall$extension_exists$extension_elems1
  #106 = Utf8               forall$extension_exists$extension_elems2
  #107 = Utf8               exists$extension
  #108 = Utf8               exists$extension_elems1
  #109 = Utf8               exists$extension_elems2
  #110 = Utf8               filter$extension
  #111 = Utf8               (Lscala/Tuple2;Lscala/Function2;Lscala/collection/BuildFrom;Lscala/collection/BuildFrom;)Lscala/Tuple2;
  #112 = Utf8               <To1:Ljava/lang/Object;To2:Ljava/lang/Object;El1:Ljava/lang/Object;It1::Lscala/collection/Iterable<TEl1;>;El2:Ljava/lang/Object;It2::Lscala/collection/Iterable<TEl2;>;>(Lscala/Tuple2<TIt1;TIt2;>;Lscala/Function2<TEl1;TEl2;Ljava/lang/Object;>;Lscala/collection/BuildFrom<TIt1;TEl1;TTo1;>;Lscala/collection/BuildFrom<TIt2;TEl2;TTo2;>;)Lscala/Tuple2<TTo1;TTo2;>;
  #113 = Utf8               bf1
  #114 = Utf8               bf2
  #115 = Utf8               scala/collection/BuildFrom
  #116 = Class              #115          // scala/collection/BuildFrom
  #117 = Utf8               newBuilder
  #118 = Utf8               (Ljava/lang/Object;)Lscala/collection/mutable/Builder;
  #119 = NameAndType        #117:#118     // newBuilder:(Ljava/lang/Object;)Lscala/collection/mutable/Builder;
  #120 = InterfaceMethodref #116.#119     // scala/collection/BuildFrom.newBuilder:(Ljava/lang/Object;)Lscala/collection/mutable/Builder;
  #121 = Utf8               scala/collection/mutable/Growable
  #122 = Class              #121          // scala/collection/mutable/Growable
  #123 = Utf8               addOne
  #124 = Utf8               (Ljava/lang/Object;)Lscala/collection/mutable/Growable;
  #125 = NameAndType        #123:#124     // addOne:(Ljava/lang/Object;)Lscala/collection/mutable/Growable;
  #126 = InterfaceMethodref #122.#125     // scala/collection/mutable/Growable.addOne:(Ljava/lang/Object;)Lscala/collection/mutable/Growable;
  #127 = Utf8               scala/collection/mutable/Builder
  #128 = Class              #127          // scala/collection/mutable/Builder
  #129 = Utf8               result
  #130 = NameAndType        #129:#54      // result:()Ljava/lang/Object;
  #131 = InterfaceMethodref #128.#130     // scala/collection/mutable/Builder.result:()Ljava/lang/Object;
  #132 = Utf8               <init>
  #133 = Utf8               (Ljava/lang/Object;Ljava/lang/Object;)V
  #134 = NameAndType        #132:#133     // "<init>":(Ljava/lang/Object;Ljava/lang/Object;)V
  #135 = Methodref          #39.#134      // scala/Tuple2."<init>":(Ljava/lang/Object;Ljava/lang/Object;)V
  #136 = Utf8               Lscala/collection/BuildFrom;
  #137 = Utf8               filter$extension_el1
  #138 = Utf8               filter$extension_el2
  #139 = Utf8               filter$extension_b1
  #140 = Utf8               Lscala/collection/mutable/Builder;
  #141 = Utf8               filter$extension_b2
  #142 = Utf8               filter$extension_elems1
  #143 = Utf8               filter$extension_elems2
  #144 = Utf8               flatMap$extension
  #145 = Utf8               (Lscala/Tuple2;Lscala/Function2;Lscala/collection/BuildFrom;)Ljava/lang/Object;
  #146 = Utf8               <B:Ljava/lang/Object;To:Ljava/lang/Object;El1:Ljava/lang/Object;It1::Lscala/collection/Iterable<TEl1;>;El2:Ljava/lang/Object;It2::Lscala/collection/Iterable<TEl2;>;>(Lscala/Tuple2<TIt1;TIt2;>;Lscala/Function2<TEl1;TEl2;Lscala/collection/IterableOnce<TB;>;>;Lscala/collection/BuildFrom<TIt1;TB;TTo;>;)TTo;
  #147 = Utf8               bf
  #148 = Utf8               scala/collection/IterableOnce
  #149 = Class              #148          // scala/collection/IterableOnce
  #150 = Utf8               addAll
  #151 = Utf8               (Lscala/collection/IterableOnce;)Lscala/collection/mutable/Growable;
  #152 = NameAndType        #150:#151     // addAll:(Lscala/collection/IterableOnce;)Lscala/collection/mutable/Growable;
  #153 = InterfaceMethodref #122.#152     // scala/collection/mutable/Growable.addAll:(Lscala/collection/IterableOnce;)Lscala/collection/mutable/Growable;
  #154 = Utf8               flatMap$extension_b
  #155 = Utf8               flatMap$extension_elems1
  #156 = Utf8               flatMap$extension_elems2
  #157 = Utf8               flatMap$extension_$plus$plus$eq_xs
  #158 = Utf8               Lscala/collection/IterableOnce;
  #159 = Utf8               map$extension
  #160 = Utf8               <B:Ljava/lang/Object;To:Ljava/lang/Object;El1:Ljava/lang/Object;It1::Lscala/collection/Iterable<TEl1;>;El2:Ljava/lang/Object;It2::Lscala/collection/Iterable<TEl2;>;>(Lscala/Tuple2<TIt1;TIt2;>;Lscala/Function2<TEl1;TEl2;TB;>;Lscala/collection/BuildFrom<TIt1;TB;TTo;>;)TTo;
  #161 = Utf8               sizeHint
  #162 = Utf8               (Lscala/collection/IterableOnce;I)V
  #163 = NameAndType        #161:#162     // sizeHint:(Lscala/collection/IterableOnce;I)V
  #164 = InterfaceMethodref #128.#163     // scala/collection/mutable/Builder.sizeHint:(Lscala/collection/IterableOnce;I)V
  #165 = Utf8               map$extension_b
  #166 = Utf8               map$extension_elems1
  #167 = Utf8               map$extension_elems2
  #168 = Utf8               map$extension_$plus$eq_elem
  #169 = Utf8               coll2$extension
  #170 = Utf8               (Lscala/Tuple2;)Lscala/collection/Iterable;
  #171 = Utf8               <El1:Ljava/lang/Object;It1::Lscala/collection/Iterable<TEl1;>;El2:Ljava/lang/Object;It2::Lscala/collection/Iterable<TEl2;>;>(Lscala/Tuple2<TIt1;TIt2;>;)TIt2;
  #172 = Utf8               coll1$extension
  #173 = Utf8               <El1:Ljava/lang/Object;It1::Lscala/collection/Iterable<TEl1;>;El2:Ljava/lang/Object;It2::Lscala/collection/Iterable<TEl2;>;>(Lscala/Tuple2<TIt1;TIt2;>;)TIt1;
  #174 = Utf8               ()Lscala/Tuple2;
  #175 = Utf8               ()Lscala/Tuple2<TIt1;TIt2;>;
  #176 = NameAndType        #18:#19       // scala$runtime$Tuple2Zipped$$colls:Lscala/Tuple2;
  #177 = Fieldref           #2.#176       // scala/runtime/Tuple2Zipped.scala$runtime$Tuple2Zipped$$colls:Lscala/Tuple2;
  #178 = Utf8               this
  #179 = Utf8               Lscala/runtime/Tuple2Zipped;
  #180 = Utf8               coll1
  #181 = Utf8               ()Lscala/collection/Iterable;
  #182 = Utf8               ()TIt1;
  #183 = NameAndType        #18:#174      // scala$runtime$Tuple2Zipped$$colls:()Lscala/Tuple2;
  #184 = Methodref          #2.#183       // scala/runtime/Tuple2Zipped.scala$runtime$Tuple2Zipped$$colls:()Lscala/Tuple2;
  #185 = Utf8               coll2
  #186 = Utf8               ()TIt2;
  #187 = Utf8               map
  #188 = Utf8               (Lscala/Function2;Lscala/collection/BuildFrom;)Ljava/lang/Object;
  #189 = Utf8               <B:Ljava/lang/Object;To:Ljava/lang/Object;>(Lscala/Function2<TEl1;TEl2;TB;>;Lscala/collection/BuildFrom<TIt1;TB;TTo;>;)TTo;
  #190 = Utf8               map$extension_$this
  #191 = Utf8               flatMap
  #192 = Utf8               <B:Ljava/lang/Object;To:Ljava/lang/Object;>(Lscala/Function2<TEl1;TEl2;Lscala/collection/IterableOnce<TB;>;>;Lscala/collection/BuildFrom<TIt1;TB;TTo;>;)TTo;
  #193 = Utf8               flatMap$extension_$this
  #194 = Utf8               filter
  #195 = Utf8               (Lscala/Function2;Lscala/collection/BuildFrom;Lscala/collection/BuildFrom;)Lscala/Tuple2;
  #196 = Utf8               <To1:Ljava/lang/Object;To2:Ljava/lang/Object;>(Lscala/Function2<TEl1;TEl2;Ljava/lang/Object;>;Lscala/collection/BuildFrom<TIt1;TEl1;TTo1;>;Lscala/collection/BuildFrom<TIt2;TEl2;TTo2;>;)Lscala/Tuple2<TTo1;TTo2;>;
  #197 = Utf8               filter$extension_$this
  #198 = Utf8               exists
  #199 = Utf8               (Lscala/Function2;)Z
  #200 = Utf8               (Lscala/Function2<TEl1;TEl2;Ljava/lang/Object;>;)Z
  #201 = Utf8               exists$extension_$this
  #202 = Utf8               forall
  #203 = Utf8               forall$extension_$this
  #204 = Utf8               ()Lscala/collection/Iterator<Lscala/Tuple2<TEl1;TEl2;>;>;
  #205 = Utf8               isEmpty
  #206 = Utf8               foreach
  #207 = Utf8               (Lscala/Function2;)V
  #208 = Utf8               <U:Ljava/lang/Object;>(Lscala/Function2<TEl1;TEl2;TU;>;)V
  #209 = Utf8               foreach$extension_$this
  #210 = Utf8               toString
  #211 = Utf8               ()Ljava/lang/String;
  #212 = Utf8               equals
  #213 = Utf8               (Lscala/Tuple2;)V
  #214 = Utf8               (Lscala/Tuple2<TIt1;TIt2;>;)V
  #215 = Utf8               colls
  #216 = Utf8               ()V
  #217 = NameAndType        #132:#216     // "<init>":()V
  #218 = Methodref          #5.#217       // java/lang/Object."<init>":()V
  #219 = Utf8               Signature
  #220 = Utf8               Code
  #221 = Utf8               LocalVariableTable
  #222 = Utf8               MethodParameters
  #223 = Utf8               LineNumberTable
  #224 = Utf8               StackMapTable
  #225 = Utf8               InnerClasses
  #226 = Utf8               SourceFile
  #227 = Utf8               Deprecated
  #228 = Utf8               RuntimeVisibleAnnotations
  #229 = Utf8               ScalaInlineInfo
  #230 = Utf8               ScalaSig
{
  private final scala.Tuple2<It1, It2> scala$runtime$Tuple2Zipped$$colls;
    descriptor: Lscala/Tuple2;
    flags: (0x0012) ACC_PRIVATE, ACC_FINAL
    Signature: #20                          // Lscala/Tuple2<TIt1;TIt2;>;

  public static <El1 extends java.lang.Object, It1 extends scala.collection.Iterable<El1>, El2 extends java.lang.Object, It2 extends scala.collection.Iterable<El2>> boolean equals$extension(scala.Tuple2<It1, It2>, java.lang.Object);
    descriptor: (Lscala/Tuple2;Ljava/lang/Object;)Z
    flags: (0x0009) ACC_PUBLIC, ACC_STATIC
    Code:
      stack=3, locals=2, args_size=2
         0: getstatic     #31                 // Field scala/runtime/Tuple2Zipped$.MODULE$:Lscala/runtime/Tuple2Zipped$;
         3: aload_0
         4: aload_1
         5: invokevirtual #33                 // Method scala/runtime/Tuple2Zipped$.equals$extension:(Lscala/Tuple2;Ljava/lang/Object;)Z
         8: ireturn
      LocalVariableTable:
        Start  Length  Slot  Name   Signature
            0       9     0 $this   Lscala/Tuple2;
            0       9     1   x$1   Ljava/lang/Object;
    Signature: #23                          // <El1:Ljava/lang/Object;It1::Lscala/collection/Iterable<TEl1;>;El2:Ljava/lang/Object;It2::Lscala/collection/Iterable<TEl2;>;>(Lscala/Tuple2<TIt1;TIt2;>;Ljava/lang/Object;)Z
    MethodParameters:
      Name                           Flags
      $this                          final
      x$1                            final

  public static <El1 extends java.lang.Object, It1 extends scala.collection.Iterable<El1>, El2 extends java.lang.Object, It2 extends scala.collection.Iterable<El2>> int hashCode$extension(scala.Tuple2<It1, It2>);
    descriptor: (Lscala/Tuple2;)I
    flags: (0x0009) ACC_PUBLIC, ACC_STATIC
    Code:
      stack=1, locals=1, args_size=1
         0: getstatic     #31                 // Field scala/runtime/Tuple2Zipped$.MODULE$:Lscala/runtime/Tuple2Zipped$;
         3: pop
         4: aload_0
         5: invokevirtual #43                 // Method scala/Tuple2.hashCode:()I
         8: ireturn
      LineNumberTable:
        line 44: 4
      LocalVariableTable:
        Start  Length  Slot  Name   Signature
            0       9     0 $this   Lscala/Tuple2;
    Signature: #37                          // <El1:Ljava/lang/Object;It1::Lscala/collection/Iterable<TEl1;>;El2:Ljava/lang/Object;It2::Lscala/collection/Iterable<TEl2;>;>(Lscala/Tuple2<TIt1;TIt2;>;)I
    MethodParameters:
      Name                           Flags
      $this                          final

  public static <El1 extends java.lang.Object, It1 extends scala.collection.Iterable<El1>, El2 extends java.lang.Object, It2 extends scala.collection.Iterable<El2>> java.lang.String toString$extension(scala.Tuple2<It1, It2>);
    descriptor: (Lscala/Tuple2;)Ljava/lang/String;
    flags: (0x0009) ACC_PUBLIC, ACC_STATIC
    Code:
      stack=2, locals=1, args_size=1
         0: getstatic     #31                 // Field scala/runtime/Tuple2Zipped$.MODULE$:Lscala/runtime/Tuple2Zipped$;
         3: aload_0
         4: invokevirtual #48                 // Method scala/runtime/Tuple2Zipped$.toString$extension:(Lscala/Tuple2;)Ljava/lang/String;
         7: areturn
      LocalVariableTable:
        Start  Length  Slot  Name   Signature
            0       8     0 $this   Lscala/Tuple2;
    Signature: #46                          // <El1:Ljava/lang/Object;It1::Lscala/collection/Iterable<TEl1;>;El2:Ljava/lang/Object;It2::Lscala/collection/Iterable<TEl2;>;>(Lscala/Tuple2<TIt1;TIt2;>;)Ljava/lang/String;
    MethodParameters:
      Name                           Flags
      $this                          final

  public static <U extends java.lang.Object, El1 extends java.lang.Object, It1 extends scala.collection.Iterable<El1>, El2 extends java.lang.Object, It2 extends scala.collection.Iterable<El2>> void foreach$extension(scala.Tuple2<It1, It2>, scala.Function2<El1, El2, U>);
    descriptor: (Lscala/Tuple2;Lscala/Function2;)V
    flags: (0x0009) ACC_PUBLIC, ACC_STATIC
    Code:
      stack=3, locals=4, args_size=2
         0: getstatic     #31                 // Field scala/runtime/Tuple2Zipped$.MODULE$:Lscala/runtime/Tuple2Zipped$;
         3: pop
         4: aload_0
         5: invokevirtual #56                 // Method scala/Tuple2._1:()Ljava/lang/Object;
         8: checkcast     #58                 // class scala/collection/Iterable
        11: invokeinterface #62,  1           // InterfaceMethod scala/collection/Iterable.iterator:()Lscala/collection/Iterator;
        16: astore_2
        17: aload_0
        18: invokevirtual #65                 // Method scala/Tuple2._2:()Ljava/lang/Object;
        21: checkcast     #58                 // class scala/collection/Iterable
        24: invokeinterface #62,  1           // InterfaceMethod scala/collection/Iterable.iterator:()Lscala/collection/Iterator;
        29: astore_3
        30: aload_2
        31: invokeinterface #71,  1           // InterfaceMethod scala/collection/Iterator.hasNext:()Z
        36: ifeq          70
        39: aload_3
        40: invokeinterface #71,  1           // InterfaceMethod scala/collection/Iterator.hasNext:()Z
        45: ifeq          70
        48: aload_1
        49: aload_2
        50: invokeinterface #74,  1           // InterfaceMethod scala/collection/Iterator.next:()Ljava/lang/Object;
        55: aload_3
        56: invokeinterface #74,  1           // InterfaceMethod scala/collection/Iterator.next:()Ljava/lang/Object;
        61: invokeinterface #80,  3           // InterfaceMethod scala/Function2.apply:(Ljava/lang/Object;Ljava/lang/Object;)Ljava/lang/Object;
        66: pop
        67: goto          30
        70: return
      StackMapTable: number_of_entries = 2
        frame_type = 253 /* append */
          offset_delta = 30
          locals = [ class scala/collection/Iterator, class scala/collection/Iterator ]
        frame_type = 39 /* same */
      LineNumberTable:
        line 45: 4
        line 109: 11
        line 46: 17
        line 110: 24
        line 112: 30
        line 113: 48
        line 112: 70
      LocalVariableTable:
        Start  Length  Slot  Name   Signature
            0      71     0 $this   Lscala/Tuple2;
            0      71     1     f   Lscala/Function2;
           17      53     2 foreach$extension_elems1   Lscala/collection/Iterator;
           30      40     3 foreach$extension_elems2   Lscala/collection/Iterator;
    Signature: #51                          // <U:Ljava/lang/Object;El1:Ljava/lang/Object;It1::Lscala/collection/Iterable<TEl1;>;El2:Ljava/lang/Object;It2::Lscala/collection/Iterable<TEl2;>;>(Lscala/Tuple2<TIt1;TIt2;>;Lscala/Function2<TEl1;TEl2;TU;>;)V
    MethodParameters:
      Name                           Flags
      $this                          final
      f                              final

  public static <El1 extends java.lang.Object, It1 extends scala.collection.Iterable<El1>, El2 extends java.lang.Object, It2 extends scala.collection.Iterable<El2>> boolean isEmpty$extension(scala.Tuple2<It1, It2>);
    descriptor: (Lscala/Tuple2;)Z
    flags: (0x0009) ACC_PUBLIC, ACC_STATIC
    Code:
      stack=2, locals=1, args_size=1
         0: getstatic     #31                 // Field scala/runtime/Tuple2Zipped$.MODULE$:Lscala/runtime/Tuple2Zipped$;
         3: aload_0
         4: invokevirtual #89                 // Method scala/runtime/Tuple2Zipped$.isEmpty$extension:(Lscala/Tuple2;)Z
         7: ireturn
      LocalVariableTable:
        Start  Length  Slot  Name   Signature
            0       8     0 $this   Lscala/Tuple2;
    Signature: #87                          // <El1:Ljava/lang/Object;It1::Lscala/collection/Iterable<TEl1;>;El2:Ljava/lang/Object;It2::Lscala/collection/Iterable<TEl2;>;>(Lscala/Tuple2<TIt1;TIt2;>;)Z
    MethodParameters:
      Name                           Flags
      $this                          final

  public static <El1 extends java.lang.Object, It1 extends scala.collection.Iterable<El1>, El2 extends java.lang.Object, It2 extends scala.collection.Iterable<El2>> scala.collection.Iterator<scala.Tuple2<El1, El2>> iterator$extension(scala.Tuple2<It1, It2>);
    descriptor: (Lscala/Tuple2;)Lscala/collection/Iterator;
    flags: (0x0009) ACC_PUBLIC, ACC_STATIC
    Code:
      stack=2, locals=1, args_size=1
         0: getstatic     #31                 // Field scala/runtime/Tuple2Zipped$.MODULE$:Lscala/runtime/Tuple2Zipped$;
         3: aload_0
         4: invokevirtual #94                 // Method scala/runtime/Tuple2Zipped$.iterator$extension:(Lscala/Tuple2;)Lscala/collection/Iterator;
         7: areturn
      LocalVariableTable:
        Start  Length  Slot  Name   Signature
            0       8     0 $this   Lscala/Tuple2;
    Signature: #92                          // <El1:Ljava/lang/Object;It1::Lscala/collection/Iterable<TEl1;>;El2:Ljava/lang/Object;It2::Lscala/collection/Iterable<TEl2;>;>(Lscala/Tuple2<TIt1;TIt2;>;)Lscala/collection/Iterator<Lscala/Tuple2<TEl1;TEl2;>;>;
    MethodParameters:
      Name                           Flags
      $this                          final

  public static <El1 extends java.lang.Object, It1 extends scala.collection.Iterable<El1>, El2 extends java.lang.Object, It2 extends scala.collection.Iterable<El2>> boolean forall$extension(scala.Tuple2<It1, It2>, scala.Function2<El1, El2, java.lang.Object>);
    descriptor: (Lscala/Tuple2;Lscala/Function2;)Z
    flags: (0x0009) ACC_PUBLIC, ACC_STATIC
    Code:
      stack=3, locals=7, args_size=2
         0: getstatic     #31                 // Field scala/runtime/Tuple2Zipped$.MODULE$:Lscala/runtime/Tuple2Zipped$;
         3: pop
         4: aload_0
         5: invokevirtual #56                 // Method scala/Tuple2._1:()Ljava/lang/Object;
         8: checkcast     #58                 // class scala/collection/Iterable
        11: invokeinterface #62,  1           // InterfaceMethod scala/collection/Iterable.iterator:()Lscala/collection/Iterator;
        16: astore_2
        17: aload_0
        18: invokevirtual #65                 // Method scala/Tuple2._2:()Ljava/lang/Object;
        21: checkcast     #58                 // class scala/collection/Iterable
        24: invokeinterface #62,  1           // InterfaceMethod scala/collection/Iterable.iterator:()Lscala/collection/Iterator;
        29: astore_3
        30: aload_2
        31: invokeinterface #71,  1           // InterfaceMethod scala/collection/Iterator.hasNext:()Z
        36: ifeq          94
        39: aload_3
        40: invokeinterface #71,  1           // InterfaceMethod scala/collection/Iterator.hasNext:()Z
        45: ifeq          94
        48: aload_2
        49: invokeinterface #74,  1           // InterfaceMethod scala/collection/Iterator.next:()Ljava/lang/Object;
        54: aload_3
        55: invokeinterface #74,  1           // InterfaceMethod scala/collection/Iterator.next:()Ljava/lang/Object;
        60: astore        6
        62: astore        5
        64: aload_1
        65: aload         5
        67: aload         6
        69: invokeinterface #80,  3           // InterfaceMethod scala/Function2.apply:(Ljava/lang/Object;Ljava/lang/Object;)Ljava/lang/Object;
        74: invokestatic  #104                // Method scala/runtime/BoxesRunTime.unboxToBoolean:(Ljava/lang/Object;)Z
        77: ifne          84
        80: iconst_1
        81: goto          85
        84: iconst_0
        85: ifeq          30
        88: iconst_1
        89: istore        4
        91: goto          97
        94: iconst_0
        95: istore        4
        97: iload         4
        99: aconst_null
       100: astore_2
       101: aconst_null
       102: astore_3
       103: ifne          108
       106: iconst_1
       107: ireturn
       108: iconst_0
       109: ireturn
      StackMapTable: number_of_entries = 6
        frame_type = 253 /* append */
          offset_delta = 30
          locals = [ class scala/collection/Iterator, class scala/collection/Iterator ]
        frame_type = 254 /* append */
          offset_delta = 53
          locals = [ top, class java/lang/Object, class java/lang/Object ]
        frame_type = 64 /* same_locals_1_stack_item */
          stack = [ int ]
        frame_type = 248 /* chop */
          offset_delta = 8
        frame_type = 252 /* append */
          offset_delta = 2
          locals = [ int ]
        frame_type = 255 /* full_frame */
          offset_delta = 10
          locals = [ class scala/Tuple2, class scala/Function2, null, null, int ]
          stack = []
      LineNumberTable:
        line 45: 4
        line 92: 11
        line 46: 17
        line 93: 24
        line 95: 30
        line 96: 48
        line 104: 64
        line 96: 85
        line 97: 88
        line 100: 94
        line 104: 97
      LocalVariableTable:
        Start  Length  Slot  Name   Signature
            0     110     0 $this   Lscala/Tuple2;
            0     110     1     p   Lscala/Function2;
           17      78     2 forall$extension_exists$extension_elems1   Lscala/collection/Iterator;
           30      65     3 forall$extension_exists$extension_elems2   Lscala/collection/Iterator;
    Signature: #97                          // <El1:Ljava/lang/Object;It1::Lscala/collection/Iterable<TEl1;>;El2:Ljava/lang/Object;It2::Lscala/collection/Iterable<TEl2;>;>(Lscala/Tuple2<TIt1;TIt2;>;Lscala/Function2<TEl1;TEl2;Ljava/lang/Object;>;)Z
    MethodParameters:
      Name                           Flags
      $this                          final
      p                              final

  public static <El1 extends java.lang.Object, It1 extends scala.collection.Iterable<El1>, El2 extends java.lang.Object, It2 extends scala.collection.Iterable<El2>> boolean exists$extension(scala.Tuple2<It1, It2>, scala.Function2<El1, El2, java.lang.Object>);
    descriptor: (Lscala/Tuple2;Lscala/Function2;)Z
    flags: (0x0009) ACC_PUBLIC, ACC_STATIC
    Code:
      stack=3, locals=5, args_size=2
         0: getstatic     #31                 // Field scala/runtime/Tuple2Zipped$.MODULE$:Lscala/runtime/Tuple2Zipped$;
         3: pop
         4: aload_0
         5: invokevirtual #56                 // Method scala/Tuple2._1:()Ljava/lang/Object;
         8: checkcast     #58                 // class scala/collection/Iterable
        11: invokeinterface #62,  1           // InterfaceMethod scala/collection/Iterable.iterator:()Lscala/collection/Iterator;
        16: astore_2
        17: aload_0
        18: invokevirtual #65                 // Method scala/Tuple2._2:()Ljava/lang/Object;
        21: checkcast     #58                 // class scala/collection/Iterable
        24: invokeinterface #62,  1           // InterfaceMethod scala/collection/Iterable.iterator:()Lscala/collection/Iterator;
        29: astore_3
        30: aload_2
        31: invokeinterface #71,  1           // InterfaceMethod scala/collection/Iterator.hasNext:()Z
        36: ifeq          78
        39: aload_3
        40: invokeinterface #71,  1           // InterfaceMethod scala/collection/Iterator.hasNext:()Z
        45: ifeq          78
        48: aload_1
        49: aload_2
        50: invokeinterface #74,  1           // InterfaceMethod scala/collection/Iterator.next:()Ljava/lang/Object;
        55: aload_3
        56: invokeinterface #74,  1           // InterfaceMethod scala/collection/Iterator.next:()Ljava/lang/Object;
        61: invokeinterface #80,  3           // InterfaceMethod scala/Function2.apply:(Ljava/lang/Object;Ljava/lang/Object;)Ljava/lang/Object;
        66: invokestatic  #104                // Method scala/runtime/BoxesRunTime.unboxToBoolean:(Ljava/lang/Object;)Z
        69: ifeq          30
        72: iconst_1
        73: istore        4
        75: goto          81
        78: iconst_0
        79: istore        4
        81: iload         4
        83: ireturn
      StackMapTable: number_of_entries = 3
        frame_type = 253 /* append */
          offset_delta = 30
          locals = [ class scala/collection/Iterator, class scala/collection/Iterator ]
        frame_type = 47 /* same */
        frame_type = 252 /* append */
          offset_delta = 2
          locals = [ int ]
      LineNumberTable:
        line 45: 4
        line 92: 11
        line 46: 17
        line 93: 24
        line 95: 30
        line 96: 48
        line 97: 72
        line 100: 78
      LocalVariableTable:
        Start  Length  Slot  Name   Signature
            0      84     0 $this   Lscala/Tuple2;
            0      84     1     p   Lscala/Function2;
           17      62     2 exists$extension_elems1   Lscala/collection/Iterator;
           30      49     3 exists$extension_elems2   Lscala/collection/Iterator;
    Signature: #97                          // <El1:Ljava/lang/Object;It1::Lscala/collection/Iterable<TEl1;>;El2:Ljava/lang/Object;It2::Lscala/collection/Iterable<TEl2;>;>(Lscala/Tuple2<TIt1;TIt2;>;Lscala/Function2<TEl1;TEl2;Ljava/lang/Object;>;)Z
    MethodParameters:
      Name                           Flags
      $this                          final
      p                              final

  public static <To1 extends java.lang.Object, To2 extends java.lang.Object, El1 extends java.lang.Object, It1 extends scala.collection.Iterable<El1>, El2 extends java.lang.Object, It2 extends scala.collection.Iterable<El2>> scala.Tuple2<To1, To2> filter$extension(scala.Tuple2<It1, It2>, scala.Function2<El1, El2, java.lang.Object>, scala.collection.BuildFrom<It1, El1, To1>, scala.collection.BuildFrom<It2, El2, To2>);
    descriptor: (Lscala/Tuple2;Lscala/Function2;Lscala/collection/BuildFrom;Lscala/collection/BuildFrom;)Lscala/Tuple2;
    flags: (0x0009) ACC_PUBLIC, ACC_STATIC
    Code:
      stack=4, locals=10, args_size=4
         0: getstatic     #31                 // Field scala/runtime/Tuple2Zipped$.MODULE$:Lscala/runtime/Tuple2Zipped$;
         3: pop
         4: aload_2
         5: aload_0
         6: invokevirtual #56                 // Method scala/Tuple2._1:()Ljava/lang/Object;
         9: checkcast     #58                 // class scala/collection/Iterable
        12: invokeinterface #120,  2          // InterfaceMethod scala/collection/BuildFrom.newBuilder:(Ljava/lang/Object;)Lscala/collection/mutable/Builder;
        17: astore        4
        19: aload_3
        20: aload_0
        21: invokevirtual #65                 // Method scala/Tuple2._2:()Ljava/lang/Object;
        24: checkcast     #58                 // class scala/collection/Iterable
        27: invokeinterface #120,  2          // InterfaceMethod scala/collection/BuildFrom.newBuilder:(Ljava/lang/Object;)Lscala/collection/mutable/Builder;
        32: astore        5
        34: aload_0
        35: invokevirtual #56                 // Method scala/Tuple2._1:()Ljava/lang/Object;
        38: checkcast     #58                 // class scala/collection/Iterable
        41: invokeinterface #62,  1           // InterfaceMethod scala/collection/Iterable.iterator:()Lscala/collection/Iterator;
        46: astore        6
        48: aload_0
        49: invokevirtual #65                 // Method scala/Tuple2._2:()Ljava/lang/Object;
        52: checkcast     #58                 // class scala/collection/Iterable
        55: invokeinterface #62,  1           // InterfaceMethod scala/collection/Iterable.iterator:()Lscala/collection/Iterator;
        60: astore        7
        62: aload         6
        64: invokeinterface #71,  1           // InterfaceMethod scala/collection/Iterator.hasNext:()Z
        69: ifeq          153
        72: aload         7
        74: invokeinterface #71,  1           // InterfaceMethod scala/collection/Iterator.hasNext:()Z
        79: ifeq          153
        82: aload         6
        84: invokeinterface #74,  1           // InterfaceMethod scala/collection/Iterator.next:()Ljava/lang/Object;
        89: astore        8
        91: aload         7
        93: invokeinterface #74,  1           // InterfaceMethod scala/collection/Iterator.next:()Ljava/lang/Object;
        98: astore        9
       100: aload_1
       101: aload         8
       103: aload         9
       105: invokeinterface #80,  3           // InterfaceMethod scala/Function2.apply:(Ljava/lang/Object;Ljava/lang/Object;)Ljava/lang/Object;
       110: invokestatic  #104                // Method scala/runtime/BoxesRunTime.unboxToBoolean:(Ljava/lang/Object;)Z
       113: ifeq          62
       116: aload         4
       118: ifnonnull     123
       121: aconst_null
       122: athrow
       123: aload         4
       125: aload         8
       127: invokeinterface #126,  2          // InterfaceMethod scala/collection/mutable/Growable.addOne:(Ljava/lang/Object;)Lscala/collection/mutable/Growable;
       132: pop
       133: aload         5
       135: ifnonnull     140
       138: aconst_null
       139: athrow
       140: aload         5
       142: aload         9
       144: invokeinterface #126,  2          // InterfaceMethod scala/collection/mutable/Growable.addOne:(Ljava/lang/Object;)Lscala/collection/mutable/Growable;
       149: pop
       150: goto          62
       153: new           #39                 // class scala/Tuple2
       156: dup
       157: aload         4
       159: invokeinterface #131,  1          // InterfaceMethod scala/collection/mutable/Builder.result:()Ljava/lang/Object;
       164: aload         5
       166: invokeinterface #131,  1          // InterfaceMethod scala/collection/mutable/Builder.result:()Ljava/lang/Object;
       171: invokespecial #135                // Method scala/Tuple2."<init>":(Ljava/lang/Object;Ljava/lang/Object;)V
       174: areturn
      StackMapTable: number_of_entries = 4
        frame_type = 255 /* full_frame */
          offset_delta = 62
          locals = [ class scala/Tuple2, class scala/Function2, class scala/collection/BuildFrom, class scala/collection/BuildFrom, class scala/collection/mutable/Builder, class scala/collection/mutable/Builder, class scala/collection/Iterator, class scala/collection/Iterator ]
          stack = []
        frame_type = 253 /* append */
          offset_delta = 60
          locals = [ class java/lang/Object, class java/lang/Object ]
        frame_type = 16 /* same */
        frame_type = 249 /* chop */
          offset_delta = 12
      LineNumberTable:
        line 74: 4
        line 45: 5
        line 74: 12
        line 75: 19
        line 46: 20
        line 75: 27
        line 45: 34
        line 76: 41
        line 46: 48
        line 77: 55
        line 79: 62
        line 80: 82
        line 81: 91
        line 82: 100
        line 83: 116
        line 84: 133
        line 88: 153
      LocalVariableTable:
        Start  Length  Slot  Name   Signature
            0     175     0 $this   Lscala/Tuple2;
            0     175     1     f   Lscala/Function2;
            0     175     2   bf1   Lscala/collection/BuildFrom;
            0     175     3   bf2   Lscala/collection/BuildFrom;
           91      62     8 filter$extension_el1   Ljava/lang/Object;
          100      53     9 filter$extension_el2   Ljava/lang/Object;
           19     155     4 filter$extension_b1   Lscala/collection/mutable/Builder;
           34     140     5 filter$extension_b2   Lscala/collection/mutable/Builder;
           48     126     6 filter$extension_elems1   Lscala/collection/Iterator;
           62     112     7 filter$extension_elems2   Lscala/collection/Iterator;
    Signature: #112                         // <To1:Ljava/lang/Object;To2:Ljava/lang/Object;El1:Ljava/lang/Object;It1::Lscala/collection/Iterable<TEl1;>;El2:Ljava/lang/Object;It2::Lscala/collection/Iterable<TEl2;>;>(Lscala/Tuple2<TIt1;TIt2;>;Lscala/Function2<TEl1;TEl2;Ljava/lang/Object;>;Lscala/collection/BuildFrom<TIt1;TEl1;TTo1;>;Lscala/collection/BuildFrom<TIt2;TEl2;TTo2;>;)Lscala/Tuple2<TTo1;TTo2;>;
    MethodParameters:
      Name                           Flags
      $this                          final
      f                              final
      bf1                            final
      bf2                            final

  public static <B extends java.lang.Object, To extends java.lang.Object, El1 extends java.lang.Object, It1 extends scala.collection.Iterable<El1>, El2 extends java.lang.Object, It2 extends scala.collection.Iterable<El2>> To flatMap$extension(scala.Tuple2<It1, It2>, scala.Function2<El1, El2, scala.collection.IterableOnce<B>>, scala.collection.BuildFrom<It1, B, To>);
    descriptor: (Lscala/Tuple2;Lscala/Function2;Lscala/collection/BuildFrom;)Ljava/lang/Object;
    flags: (0x0009) ACC_PUBLIC, ACC_STATIC
    Code:
      stack=4, locals=7, args_size=3
         0: getstatic     #31                 // Field scala/runtime/Tuple2Zipped$.MODULE$:Lscala/runtime/Tuple2Zipped$;
         3: pop
         4: aload_2
         5: aload_0
         6: invokevirtual #56                 // Method scala/Tuple2._1:()Ljava/lang/Object;
         9: checkcast     #58                 // class scala/collection/Iterable
        12: invokeinterface #120,  2          // InterfaceMethod scala/collection/BuildFrom.newBuilder:(Ljava/lang/Object;)Lscala/collection/mutable/Builder;
        17: astore_3
        18: aload_0
        19: invokevirtual #56                 // Method scala/Tuple2._1:()Ljava/lang/Object;
        22: checkcast     #58                 // class scala/collection/Iterable
        25: invokeinterface #62,  1           // InterfaceMethod scala/collection/Iterable.iterator:()Lscala/collection/Iterator;
        30: astore        4
        32: aload_0
        33: invokevirtual #65                 // Method scala/Tuple2._2:()Ljava/lang/Object;
        36: checkcast     #58                 // class scala/collection/Iterable
        39: invokeinterface #62,  1           // InterfaceMethod scala/collection/Iterable.iterator:()Lscala/collection/Iterator;
        44: astore        5
        46: aload         4
        48: invokeinterface #71,  1           // InterfaceMethod scala/collection/Iterator.hasNext:()Z
        53: ifeq          112
        56: aload         5
        58: invokeinterface #71,  1           // InterfaceMethod scala/collection/Iterator.hasNext:()Z
        63: ifeq          112
        66: aload_3
        67: aload_1
        68: aload         4
        70: invokeinterface #74,  1           // InterfaceMethod scala/collection/Iterator.next:()Ljava/lang/Object;
        75: aload         5
        77: invokeinterface #74,  1           // InterfaceMethod scala/collection/Iterator.next:()Ljava/lang/Object;
        82: invokeinterface #80,  3           // InterfaceMethod scala/Function2.apply:(Ljava/lang/Object;Ljava/lang/Object;)Ljava/lang/Object;
        87: checkcast     #149                // class scala/collection/IterableOnce
        90: astore        6
        92: ifnonnull     97
        95: aconst_null
        96: athrow
        97: aload_3
        98: aload         6
       100: invokeinterface #153,  2          // InterfaceMethod scala/collection/mutable/Growable.addAll:(Lscala/collection/IterableOnce;)Lscala/collection/mutable/Growable;
       105: pop
       106: aconst_null
       107: astore        6
       109: goto          46
       112: aload_3
       113: invokeinterface #131,  1          // InterfaceMethod scala/collection/mutable/Builder.result:()Ljava/lang/Object;
       118: areturn
      StackMapTable: number_of_entries = 3
        frame_type = 254 /* append */
          offset_delta = 46
          locals = [ class scala/collection/mutable/Builder, class scala/collection/Iterator, class scala/collection/Iterator ]
        frame_type = 252 /* append */
          offset_delta = 50
          locals = [ class scala/collection/IterableOnce ]
        frame_type = 250 /* chop */
          offset_delta = 14
      LineNumberTable:
        line 62: 4
        line 45: 5
        line 62: 12
        line 45: 18
        line 63: 25
        line 46: 32
        line 64: 39
        line 66: 46
        line 67: 66
        line 70: 112
      LocalVariableTable:
        Start  Length  Slot  Name   Signature
            0     119     0 $this   Lscala/Tuple2;
            0     119     1     f   Lscala/Function2;
            0     119     2    bf   Lscala/collection/BuildFrom;
           18     100     3 flatMap$extension_b   Lscala/collection/mutable/Builder;
           32      86     4 flatMap$extension_elems1   Lscala/collection/Iterator;
           46      72     5 flatMap$extension_elems2   Lscala/collection/Iterator;
           97       9     6 flatMap$extension_$plus$plus$eq_xs   Lscala/collection/IterableOnce;
    Signature: #146                         // <B:Ljava/lang/Object;To:Ljava/lang/Object;El1:Ljava/lang/Object;It1::Lscala/collection/Iterable<TEl1;>;El2:Ljava/lang/Object;It2::Lscala/collection/Iterable<TEl2;>;>(Lscala/Tuple2<TIt1;TIt2;>;Lscala/Function2<TEl1;TEl2;Lscala/collection/IterableOnce<TB;>;>;Lscala/collection/BuildFrom<TIt1;TB;TTo;>;)TTo;
    MethodParameters:
      Name                           Flags
      $this                          final
      f                              final
      bf                             final

  public static <B extends java.lang.Object, To extends java.lang.Object, El1 extends java.lang.Object, It1 extends scala.collection.Iterable<El1>, El2 extends java.lang.Object, It2 extends scala.collection.Iterable<El2>> To map$extension(scala.Tuple2<It1, It2>, scala.Function2<El1, El2, B>, scala.collection.BuildFrom<It1, B, To>);
    descriptor: (Lscala/Tuple2;Lscala/Function2;Lscala/collection/BuildFrom;)Ljava/lang/Object;
    flags: (0x0009) ACC_PUBLIC, ACC_STATIC
    Code:
      stack=3, locals=7, args_size=3
         0: getstatic     #31                 // Field scala/runtime/Tuple2Zipped$.MODULE$:Lscala/runtime/Tuple2Zipped$;
         3: pop
         4: aload_2
         5: aload_0
         6: invokevirtual #56                 // Method scala/Tuple2._1:()Ljava/lang/Object;
         9: checkcast     #58                 // class scala/collection/Iterable
        12: invokeinterface #120,  2          // InterfaceMethod scala/collection/BuildFrom.newBuilder:(Ljava/lang/Object;)Lscala/collection/mutable/Builder;
        17: astore_3
        18: aload_3
        19: aload_0
        20: invokevirtual #56                 // Method scala/Tuple2._1:()Ljava/lang/Object;
        23: checkcast     #58                 // class scala/collection/Iterable
        26: iconst_0
        27: invokeinterface #164,  3          // InterfaceMethod scala/collection/mutable/Builder.sizeHint:(Lscala/collection/IterableOnce;I)V
        32: aload_0
        33: invokevirtual #56                 // Method scala/Tuple2._1:()Ljava/lang/Object;
        36: checkcast     #58                 // class scala/collection/Iterable
        39: invokeinterface #62,  1           // InterfaceMethod scala/collection/Iterable.iterator:()Lscala/collection/Iterator;
        44: astore        4
        46: aload_0
        47: invokevirtual #65                 // Method scala/Tuple2._2:()Ljava/lang/Object;
        50: checkcast     #58                 // class scala/collection/Iterable
        53: invokeinterface #62,  1           // InterfaceMethod scala/collection/Iterable.iterator:()Lscala/collection/Iterator;
        58: astore        5
        60: aload         4
        62: invokeinterface #71,  1           // InterfaceMethod scala/collection/Iterator.hasNext:()Z
        67: ifeq          117
        70: aload         5
        72: invokeinterface #71,  1           // InterfaceMethod scala/collection/Iterator.hasNext:()Z
        77: ifeq          117
        80: aload_1
        81: aload         4
        83: invokeinterface #74,  1           // InterfaceMethod scala/collection/Iterator.next:()Ljava/lang/Object;
        88: aload         5
        90: invokeinterface #74,  1           // InterfaceMethod scala/collection/Iterator.next:()Ljava/lang/Object;
        95: invokeinterface #80,  3           // InterfaceMethod scala/Function2.apply:(Ljava/lang/Object;Ljava/lang/Object;)Ljava/lang/Object;
       100: astore        6
       102: aload_3
       103: aload         6
       105: invokeinterface #126,  2          // InterfaceMethod scala/collection/mutable/Growable.addOne:(Ljava/lang/Object;)Lscala/collection/mutable/Growable;
       110: pop
       111: aconst_null
       112: astore        6
       114: goto          60
       117: aload_3
       118: invokeinterface #131,  1          // InterfaceMethod scala/collection/mutable/Builder.result:()Ljava/lang/Object;
       123: areturn
      StackMapTable: number_of_entries = 2
        frame_type = 254 /* append */
          offset_delta = 60
          locals = [ class scala/collection/mutable/Builder, class scala/collection/Iterator, class scala/collection/Iterator ]
        frame_type = 56 /* same */
      LineNumberTable:
        line 49: 4
        line 45: 5
        line 49: 12
        line 50: 18
        line 45: 19
        line 50: 26
        line 45: 32
        line 51: 39
        line 46: 46
        line 52: 53
        line 54: 60
        line 55: 80
        line 58: 117
      LocalVariableTable:
        Start  Length  Slot  Name   Signature
            0     124     0 $this   Lscala/Tuple2;
            0     124     1     f   Lscala/Function2;
            0     124     2    bf   Lscala/collection/BuildFrom;
           18     105     3 map$extension_b   Lscala/collection/mutable/Builder;
           46      77     4 map$extension_elems1   Lscala/collection/Iterator;
           60      63     5 map$extension_elems2   Lscala/collection/Iterator;
          102       9     6 map$extension_$plus$eq_elem   Ljava/lang/Object;
    Signature: #160                         // <B:Ljava/lang/Object;To:Ljava/lang/Object;El1:Ljava/lang/Object;It1::Lscala/collection/Iterable<TEl1;>;El2:Ljava/lang/Object;It2::Lscala/collection/Iterable<TEl2;>;>(Lscala/Tuple2<TIt1;TIt2;>;Lscala/Function2<TEl1;TEl2;TB;>;Lscala/collection/BuildFrom<TIt1;TB;TTo;>;)TTo;
    MethodParameters:
      Name                           Flags
      $this                          final
      f                              final
      bf                             final

  public static <El1 extends java.lang.Object, It1 extends scala.collection.Iterable<El1>, El2 extends java.lang.Object, It2 extends scala.collection.Iterable<El2>> It2 coll2$extension(scala.Tuple2<It1, It2>);
    descriptor: (Lscala/Tuple2;)Lscala/collection/Iterable;
    flags: (0x0009) ACC_PUBLIC, ACC_STATIC
    Code:
      stack=1, locals=1, args_size=1
         0: getstatic     #31                 // Field scala/runtime/Tuple2Zipped$.MODULE$:Lscala/runtime/Tuple2Zipped$;
         3: pop
         4: aload_0
         5: invokevirtual #65                 // Method scala/Tuple2._2:()Ljava/lang/Object;
         8: checkcast     #58                 // class scala/collection/Iterable
        11: areturn
      LineNumberTable:
        line 46: 4
      LocalVariableTable:
        Start  Length  Slot  Name   Signature
            0      12     0 $this   Lscala/Tuple2;
    Signature: #171                         // <El1:Ljava/lang/Object;It1::Lscala/collection/Iterable<TEl1;>;El2:Ljava/lang/Object;It2::Lscala/collection/Iterable<TEl2;>;>(Lscala/Tuple2<TIt1;TIt2;>;)TIt2;
    MethodParameters:
      Name                           Flags
      $this                          final

  public static <El1 extends java.lang.Object, It1 extends scala.collection.Iterable<El1>, El2 extends java.lang.Object, It2 extends scala.collection.Iterable<El2>> It1 coll1$extension(scala.Tuple2<It1, It2>);
    descriptor: (Lscala/Tuple2;)Lscala/collection/Iterable;
    flags: (0x0009) ACC_PUBLIC, ACC_STATIC
    Code:
      stack=1, locals=1, args_size=1
         0: getstatic     #31                 // Field scala/runtime/Tuple2Zipped$.MODULE$:Lscala/runtime/Tuple2Zipped$;
         3: pop
         4: aload_0
         5: invokevirtual #56                 // Method scala/Tuple2._1:()Ljava/lang/Object;
         8: checkcast     #58                 // class scala/collection/Iterable
        11: areturn
      LineNumberTable:
        line 45: 4
      LocalVariableTable:
        Start  Length  Slot  Name   Signature
            0      12     0 $this   Lscala/Tuple2;
    Signature: #173                         // <El1:Ljava/lang/Object;It1::Lscala/collection/Iterable<TEl1;>;El2:Ljava/lang/Object;It2::Lscala/collection/Iterable<TEl2;>;>(Lscala/Tuple2<TIt1;TIt2;>;)TIt1;
    MethodParameters:
      Name                           Flags
      $this                          final

  public scala.Tuple2<It1, It2> scala$runtime$Tuple2Zipped$$colls();
    descriptor: ()Lscala/Tuple2;
    flags: (0x0001) ACC_PUBLIC
    Code:
      stack=1, locals=1, args_size=1
         0: aload_0
         1: getfield      #177                // Field scala$runtime$Tuple2Zipped$$colls:Lscala/Tuple2;
         4: areturn
      LineNumberTable:
        line 44: 0
      LocalVariableTable:
        Start  Length  Slot  Name   Signature
            0       5     0  this   Lscala/runtime/Tuple2Zipped;
    Signature: #175                         // ()Lscala/Tuple2<TIt1;TIt2;>;

  private It1 coll1();
    descriptor: ()Lscala/collection/Iterable;
    flags: (0x0002) ACC_PRIVATE
    Code:
      stack=1, locals=1, args_size=1
         0: getstatic     #31                 // Field scala/runtime/Tuple2Zipped$.MODULE$:Lscala/runtime/Tuple2Zipped$;
         3: pop
         4: aload_0
         5: invokevirtual #184                // Method scala$runtime$Tuple2Zipped$$colls:()Lscala/Tuple2;
         8: invokevirtual #56                 // Method scala/Tuple2._1:()Ljava/lang/Object;
        11: checkcast     #58                 // class scala/collection/Iterable
        14: areturn
      LineNumberTable:
        line 45: 0
        line 45: 8
        line 45: 14
      LocalVariableTable:
        Start  Length  Slot  Name   Signature
            0      15     0  this   Lscala/runtime/Tuple2Zipped;
    Signature: #182                         // ()TIt1;

  private It2 coll2();
    descriptor: ()Lscala/collection/Iterable;
    flags: (0x0002) ACC_PRIVATE
    Code:
      stack=1, locals=1, args_size=1
         0: getstatic     #31                 // Field scala/runtime/Tuple2Zipped$.MODULE$:Lscala/runtime/Tuple2Zipped$;
         3: pop
         4: aload_0
         5: invokevirtual #184                // Method scala$runtime$Tuple2Zipped$$colls:()Lscala/Tuple2;
         8: invokevirtual #65                 // Method scala/Tuple2._2:()Ljava/lang/Object;
        11: checkcast     #58                 // class scala/collection/Iterable
        14: areturn
      LineNumberTable:
        line 46: 0
        line 46: 8
        line 46: 14
      LocalVariableTable:
        Start  Length  Slot  Name   Signature
            0      15     0  this   Lscala/runtime/Tuple2Zipped;
    Signature: #186                         // ()TIt2;

  public <B extends java.lang.Object, To extends java.lang.Object> To map(scala.Function2<El1, El2, B>, scala.collection.BuildFrom<It1, B, To>);
    descriptor: (Lscala/Function2;Lscala/collection/BuildFrom;)Ljava/lang/Object;
    flags: (0x0001) ACC_PUBLIC
    Code:
      stack=3, locals=8, args_size=3
         0: getstatic     #31                 // Field scala/runtime/Tuple2Zipped$.MODULE$:Lscala/runtime/Tuple2Zipped$;
         3: pop
         4: aload_0
         5: invokevirtual #184                // Method scala$runtime$Tuple2Zipped$$colls:()Lscala/Tuple2;
         8: astore_3
         9: aload_2
        10: aload_3
        11: invokevirtual #56                 // Method scala/Tuple2._1:()Ljava/lang/Object;
        14: checkcast     #58                 // class scala/collection/Iterable
        17: invokeinterface #120,  2          // InterfaceMethod scala/collection/BuildFrom.newBuilder:(Ljava/lang/Object;)Lscala/collection/mutable/Builder;
        22: astore        4
        24: aload         4
        26: aload_3
        27: invokevirtual #56                 // Method scala/Tuple2._1:()Ljava/lang/Object;
        30: checkcast     #58                 // class scala/collection/Iterable
        33: iconst_0
        34: invokeinterface #164,  3          // InterfaceMethod scala/collection/mutable/Builder.sizeHint:(Lscala/collection/IterableOnce;I)V
        39: aload_3
        40: invokevirtual #56                 // Method scala/Tuple2._1:()Ljava/lang/Object;
        43: checkcast     #58                 // class scala/collection/Iterable
        46: invokeinterface #62,  1           // InterfaceMethod scala/collection/Iterable.iterator:()Lscala/collection/Iterator;
        51: astore        5
        53: aload_3
        54: invokevirtual #65                 // Method scala/Tuple2._2:()Ljava/lang/Object;
        57: checkcast     #58                 // class scala/collection/Iterable
        60: invokeinterface #62,  1           // InterfaceMethod scala/collection/Iterable.iterator:()Lscala/collection/Iterator;
        65: astore        6
        67: aload         5
        69: invokeinterface #71,  1           // InterfaceMethod scala/collection/Iterator.hasNext:()Z
        74: ifeq          125
        77: aload         6
        79: invokeinterface #71,  1           // InterfaceMethod scala/collection/Iterator.hasNext:()Z
        84: ifeq          125
        87: aload_1
        88: aload         5
        90: invokeinterface #74,  1           // InterfaceMethod scala/collection/Iterator.next:()Ljava/lang/Object;
        95: aload         6
        97: invokeinterface #74,  1           // InterfaceMethod scala/collection/Iterator.next:()Ljava/lang/Object;
       102: invokeinterface #80,  3           // InterfaceMethod scala/Function2.apply:(Ljava/lang/Object;Ljava/lang/Object;)Ljava/lang/Object;
       107: astore        7
       109: aload         4
       111: aload         7
       113: invokeinterface #126,  2          // InterfaceMethod scala/collection/mutable/Growable.addOne:(Ljava/lang/Object;)Lscala/collection/mutable/Growable;
       118: pop
       119: aconst_null
       120: astore        7
       122: goto          67
       125: aload         4
       127: invokeinterface #131,  1          // InterfaceMethod scala/collection/mutable/Builder.result:()Ljava/lang/Object;
       132: areturn
      StackMapTable: number_of_entries = 2
        frame_type = 255 /* full_frame */
          offset_delta = 67
          locals = [ class scala/runtime/Tuple2Zipped, class scala/Function2, class scala/collection/BuildFrom, class scala/Tuple2, class scala/collection/mutable/Builder, class scala/collection/Iterator, class scala/collection/Iterator ]
          stack = []
        frame_type = 57 /* same */
      LineNumberTable:
        line 48: 0
        line 49: 9
        line 45: 10
        line 49: 17
        line 50: 24
        line 45: 26
        line 50: 33
        line 45: 39
        line 51: 46
        line 46: 53
        line 52: 60
        line 54: 67
        line 55: 87
        line 58: 125
        line 48: 132
      LocalVariableTable:
        Start  Length  Slot  Name   Signature
            0     133     0  this   Lscala/runtime/Tuple2Zipped;
            0     133     1     f   Lscala/Function2;
            0     133     2    bf   Lscala/collection/BuildFrom;
           24     108     4 map$extension_b   Lscala/collection/mutable/Builder;
           53      79     5 map$extension_elems1   Lscala/collection/Iterator;
           67      65     6 map$extension_elems2   Lscala/collection/Iterator;
            9     123     3 map$extension_$this   Lscala/Tuple2;
          109      10     7 map$extension_$plus$eq_elem   Ljava/lang/Object;
    Signature: #189                         // <B:Ljava/lang/Object;To:Ljava/lang/Object;>(Lscala/Function2<TEl1;TEl2;TB;>;Lscala/collection/BuildFrom<TIt1;TB;TTo;>;)TTo;
    MethodParameters:
      Name                           Flags
      f                              final
      bf                             final

  public <B extends java.lang.Object, To extends java.lang.Object> To flatMap(scala.Function2<El1, El2, scala.collection.IterableOnce<B>>, scala.collection.BuildFrom<It1, B, To>);
    descriptor: (Lscala/Function2;Lscala/collection/BuildFrom;)Ljava/lang/Object;
    flags: (0x0001) ACC_PUBLIC
    Code:
      stack=4, locals=8, args_size=3
         0: getstatic     #31                 // Field scala/runtime/Tuple2Zipped$.MODULE$:Lscala/runtime/Tuple2Zipped$;
         3: pop
         4: aload_0
         5: invokevirtual #184                // Method scala$runtime$Tuple2Zipped$$colls:()Lscala/Tuple2;
         8: astore_3
         9: aload_2
        10: aload_3
        11: invokevirtual #56                 // Method scala/Tuple2._1:()Ljava/lang/Object;
        14: checkcast     #58                 // class scala/collection/Iterable
        17: invokeinterface #120,  2          // InterfaceMethod scala/collection/BuildFrom.newBuilder:(Ljava/lang/Object;)Lscala/collection/mutable/Builder;
        22: astore        4
        24: aload_3
        25: invokevirtual #56                 // Method scala/Tuple2._1:()Ljava/lang/Object;
        28: checkcast     #58                 // class scala/collection/Iterable
        31: invokeinterface #62,  1           // InterfaceMethod scala/collection/Iterable.iterator:()Lscala/collection/Iterator;
        36: astore        5
        38: aload_3
        39: invokevirtual #65                 // Method scala/Tuple2._2:()Ljava/lang/Object;
        42: checkcast     #58                 // class scala/collection/Iterable
        45: invokeinterface #62,  1           // InterfaceMethod scala/collection/Iterable.iterator:()Lscala/collection/Iterator;
        50: astore        6
        52: aload         5
        54: invokeinterface #71,  1           // InterfaceMethod scala/collection/Iterator.hasNext:()Z
        59: ifeq          120
        62: aload         6
        64: invokeinterface #71,  1           // InterfaceMethod scala/collection/Iterator.hasNext:()Z
        69: ifeq          120
        72: aload         4
        74: aload_1
        75: aload         5
        77: invokeinterface #74,  1           // InterfaceMethod scala/collection/Iterator.next:()Ljava/lang/Object;
        82: aload         6
        84: invokeinterface #74,  1           // InterfaceMethod scala/collection/Iterator.next:()Ljava/lang/Object;
        89: invokeinterface #80,  3           // InterfaceMethod scala/Function2.apply:(Ljava/lang/Object;Ljava/lang/Object;)Ljava/lang/Object;
        94: checkcast     #149                // class scala/collection/IterableOnce
        97: astore        7
        99: ifnonnull     104
       102: aconst_null
       103: athrow
       104: aload         4
       106: aload         7
       108: invokeinterface #153,  2          // InterfaceMethod scala/collection/mutable/Growable.addAll:(Lscala/collection/IterableOnce;)Lscala/collection/mutable/Growable;
       113: pop
       114: aconst_null
       115: astore        7
       117: goto          52
       120: aload         4
       122: invokeinterface #131,  1          // InterfaceMethod scala/collection/mutable/Builder.result:()Ljava/lang/Object;
       127: areturn
      StackMapTable: number_of_entries = 3
        frame_type = 255 /* full_frame */
          offset_delta = 52
          locals = [ class scala/runtime/Tuple2Zipped, class scala/Function2, class scala/collection/BuildFrom, class scala/Tuple2, class scala/collection/mutable/Builder, class scala/collection/Iterator, class scala/collection/Iterator ]
          stack = []
        frame_type = 252 /* append */
          offset_delta = 51
          locals = [ class scala/collection/IterableOnce ]
        frame_type = 250 /* chop */
          offset_delta = 15
      LineNumberTable:
        line 61: 0
        line 62: 9
        line 45: 10
        line 62: 17
        line 45: 24
        line 63: 31
        line 46: 38
        line 64: 45
        line 66: 52
        line 67: 72
        line 70: 120
        line 61: 127
      LocalVariableTable:
        Start  Length  Slot  Name   Signature
            0     128     0  this   Lscala/runtime/Tuple2Zipped;
            0     128     1     f   Lscala/Function2;
            0     128     2    bf   Lscala/collection/BuildFrom;
           24     103     4 flatMap$extension_b   Lscala/collection/mutable/Builder;
           38      89     5 flatMap$extension_elems1   Lscala/collection/Iterator;
           52      75     6 flatMap$extension_elems2   Lscala/collection/Iterator;
            9     118     3 flatMap$extension_$this   Lscala/Tuple2;
          104      10     7 flatMap$extension_$plus$plus$eq_xs   Lscala/collection/IterableOnce;
    Signature: #192                         // <B:Ljava/lang/Object;To:Ljava/lang/Object;>(Lscala/Function2<TEl1;TEl2;Lscala/collection/IterableOnce<TB;>;>;Lscala/collection/BuildFrom<TIt1;TB;TTo;>;)TTo;
    MethodParameters:
      Name                           Flags
      f                              final
      bf                             final

  public <To1 extends java.lang.Object, To2 extends java.lang.Object> scala.Tuple2<To1, To2> filter(scala.Function2<El1, El2, java.lang.Object>, scala.collection.BuildFrom<It1, El1, To1>, scala.collection.BuildFrom<It2, El2, To2>);
    descriptor: (Lscala/Function2;Lscala/collection/BuildFrom;Lscala/collection/BuildFrom;)Lscala/Tuple2;
    flags: (0x0001) ACC_PUBLIC
    Code:
      stack=4, locals=11, args_size=4
         0: getstatic     #31                 // Field scala/runtime/Tuple2Zipped$.MODULE$:Lscala/runtime/Tuple2Zipped$;
         3: pop
         4: aload_0
         5: invokevirtual #184                // Method scala$runtime$Tuple2Zipped$$colls:()Lscala/Tuple2;
         8: astore        4
        10: aload_2
        11: aload         4
        13: invokevirtual #56                 // Method scala/Tuple2._1:()Ljava/lang/Object;
        16: checkcast     #58                 // class scala/collection/Iterable
        19: invokeinterface #120,  2          // InterfaceMethod scala/collection/BuildFrom.newBuilder:(Ljava/lang/Object;)Lscala/collection/mutable/Builder;
        24: astore        5
        26: aload_3
        27: aload         4
        29: invokevirtual #65                 // Method scala/Tuple2._2:()Ljava/lang/Object;
        32: checkcast     #58                 // class scala/collection/Iterable
        35: invokeinterface #120,  2          // InterfaceMethod scala/collection/BuildFrom.newBuilder:(Ljava/lang/Object;)Lscala/collection/mutable/Builder;
        40: astore        6
        42: aload         4
        44: invokevirtual #56                 // Method scala/Tuple2._1:()Ljava/lang/Object;
        47: checkcast     #58                 // class scala/collection/Iterable
        50: invokeinterface #62,  1           // InterfaceMethod scala/collection/Iterable.iterator:()Lscala/collection/Iterator;
        55: astore        7
        57: aload         4
        59: invokevirtual #65                 // Method scala/Tuple2._2:()Ljava/lang/Object;
        62: checkcast     #58                 // class scala/collection/Iterable
        65: invokeinterface #62,  1           // InterfaceMethod scala/collection/Iterable.iterator:()Lscala/collection/Iterator;
        70: astore        8
        72: aload         7
        74: invokeinterface #71,  1           // InterfaceMethod scala/collection/Iterator.hasNext:()Z
        79: ifeq          163
        82: aload         8
        84: invokeinterface #71,  1           // InterfaceMethod scala/collection/Iterator.hasNext:()Z
        89: ifeq          163
        92: aload         7
        94: invokeinterface #74,  1           // InterfaceMethod scala/collection/Iterator.next:()Ljava/lang/Object;
        99: astore        9
       101: aload         8
       103: invokeinterface #74,  1           // InterfaceMethod scala/collection/Iterator.next:()Ljava/lang/Object;
       108: astore        10
       110: aload_1
       111: aload         9
       113: aload         10
       115: invokeinterface #80,  3           // InterfaceMethod scala/Function2.apply:(Ljava/lang/Object;Ljava/lang/Object;)Ljava/lang/Object;
       120: invokestatic  #104                // Method scala/runtime/BoxesRunTime.unboxToBoolean:(Ljava/lang/Object;)Z
       123: ifeq          72
       126: aload         5
       128: ifnonnull     133
       131: aconst_null
       132: athrow
       133: aload         5
       135: aload         9
       137: invokeinterface #126,  2          // InterfaceMethod scala/collection/mutable/Growable.addOne:(Ljava/lang/Object;)Lscala/collection/mutable/Growable;
       142: pop
       143: aload         6
       145: ifnonnull     150
       148: aconst_null
       149: athrow
       150: aload         6
       152: aload         10
       154: invokeinterface #126,  2          // InterfaceMethod scala/collection/mutable/Growable.addOne:(Ljava/lang/Object;)Lscala/collection/mutable/Growable;
       159: pop
       160: goto          72
       163: new           #39                 // class scala/Tuple2
       166: dup
       167: aload         5
       169: invokeinterface #131,  1          // InterfaceMethod scala/collection/mutable/Builder.result:()Ljava/lang/Object;
       174: aload         6
       176: invokeinterface #131,  1          // InterfaceMethod scala/collection/mutable/Builder.result:()Ljava/lang/Object;
       181: invokespecial #135                // Method scala/Tuple2."<init>":(Ljava/lang/Object;Ljava/lang/Object;)V
       184: areturn
      StackMapTable: number_of_entries = 4
        frame_type = 255 /* full_frame */
          offset_delta = 72
          locals = [ class scala/runtime/Tuple2Zipped, class scala/Function2, class scala/collection/BuildFrom, class scala/collection/BuildFrom, class scala/Tuple2, class scala/collection/mutable/Builder, class scala/collection/mutable/Builder, class scala/collection/Iterator, class scala/collection/Iterator ]
          stack = []
        frame_type = 253 /* append */
          offset_delta = 60
          locals = [ class java/lang/Object, class java/lang/Object ]
        frame_type = 16 /* same */
        frame_type = 249 /* chop */
          offset_delta = 12
      LineNumberTable:
        line 73: 0
        line 74: 10
        line 45: 11
        line 74: 19
        line 75: 26
        line 46: 27
        line 75: 35
        line 45: 42
        line 76: 50
        line 46: 57
        line 77: 65
        line 79: 72
        line 80: 92
        line 81: 101
        line 82: 110
        line 83: 126
        line 84: 143
        line 88: 163
        line 73: 184
      LocalVariableTable:
        Start  Length  Slot  Name   Signature
            0     185     0  this   Lscala/runtime/Tuple2Zipped;
            0     185     1     f   Lscala/Function2;
            0     185     2   bf1   Lscala/collection/BuildFrom;
            0     185     3   bf2   Lscala/collection/BuildFrom;
          101      62     9 filter$extension_el1   Ljava/lang/Object;
          110      53    10 filter$extension_el2   Ljava/lang/Object;
           26     158     5 filter$extension_b1   Lscala/collection/mutable/Builder;
           42     142     6 filter$extension_b2   Lscala/collection/mutable/Builder;
           57     127     7 filter$extension_elems1   Lscala/collection/Iterator;
           72     112     8 filter$extension_elems2   Lscala/collection/Iterator;
           10     174     4 filter$extension_$this   Lscala/Tuple2;
    Signature: #196                         // <To1:Ljava/lang/Object;To2:Ljava/lang/Object;>(Lscala/Function2<TEl1;TEl2;Ljava/lang/Object;>;Lscala/collection/BuildFrom<TIt1;TEl1;TTo1;>;Lscala/collection/BuildFrom<TIt2;TEl2;TTo2;>;)Lscala/Tuple2<TTo1;TTo2;>;
    MethodParameters:
      Name                           Flags
      f                              final
      bf1                            final
      bf2                            final

  public boolean exists(scala.Function2<El1, El2, java.lang.Object>);
    descriptor: (Lscala/Function2;)Z
    flags: (0x0001) ACC_PUBLIC
    Code:
      stack=3, locals=6, args_size=2
         0: getstatic     #31                 // Field scala/runtime/Tuple2Zipped$.MODULE$:Lscala/runtime/Tuple2Zipped$;
         3: pop
         4: aload_0
         5: invokevirtual #184                // Method scala$runtime$Tuple2Zipped$$colls:()Lscala/Tuple2;
         8: astore_2
         9: aload_2
        10: invokevirtual #56                 // Method scala/Tuple2._1:()Ljava/lang/Object;
        13: checkcast     #58                 // class scala/collection/Iterable
        16: invokeinterface #62,  1           // InterfaceMethod scala/collection/Iterable.iterator:()Lscala/collection/Iterator;
        21: astore_3
        22: aload_2
        23: invokevirtual #65                 // Method scala/Tuple2._2:()Ljava/lang/Object;
        26: checkcast     #58                 // class scala/collection/Iterable
        29: invokeinterface #62,  1           // InterfaceMethod scala/collection/Iterable.iterator:()Lscala/collection/Iterator;
        34: astore        4
        36: aload_3
        37: invokeinterface #71,  1           // InterfaceMethod scala/collection/Iterator.hasNext:()Z
        42: ifeq          86
        45: aload         4
        47: invokeinterface #71,  1           // InterfaceMethod scala/collection/Iterator.hasNext:()Z
        52: ifeq          86
        55: aload_1
        56: aload_3
        57: invokeinterface #74,  1           // InterfaceMethod scala/collection/Iterator.next:()Ljava/lang/Object;
        62: aload         4
        64: invokeinterface #74,  1           // InterfaceMethod scala/collection/Iterator.next:()Ljava/lang/Object;
        69: invokeinterface #80,  3           // InterfaceMethod scala/Function2.apply:(Ljava/lang/Object;Ljava/lang/Object;)Ljava/lang/Object;
        74: invokestatic  #104                // Method scala/runtime/BoxesRunTime.unboxToBoolean:(Ljava/lang/Object;)Z
        77: ifeq          36
        80: iconst_1
        81: istore        5
        83: goto          89
        86: iconst_0
        87: istore        5
        89: iload         5
        91: ireturn
      StackMapTable: number_of_entries = 3
        frame_type = 254 /* append */
          offset_delta = 36
          locals = [ class scala/Tuple2, class scala/collection/Iterator, class scala/collection/Iterator ]
        frame_type = 49 /* same */
        frame_type = 252 /* append */
          offset_delta = 2
          locals = [ int ]
      LineNumberTable:
        line 91: 0
        line 45: 9
        line 92: 16
        line 46: 22
        line 93: 29
        line 95: 36
        line 96: 55
        line 97: 80
        line 100: 86
        line 91: 89
      LocalVariableTable:
        Start  Length  Slot  Name   Signature
            0      92     0  this   Lscala/runtime/Tuple2Zipped;
            0      92     1     p   Lscala/Function2;
           22      65     3 exists$extension_elems1   Lscala/collection/Iterator;
           36      51     4 exists$extension_elems2   Lscala/collection/Iterator;
            9      80     2 exists$extension_$this   Lscala/Tuple2;
    Signature: #200                         // (Lscala/Function2<TEl1;TEl2;Ljava/lang/Object;>;)Z
    MethodParameters:
      Name                           Flags
      p                              final

  public boolean forall(scala.Function2<El1, El2, java.lang.Object>);
    descriptor: (Lscala/Function2;)Z
    flags: (0x0001) ACC_PUBLIC
    Code:
      stack=3, locals=8, args_size=2
         0: getstatic     #31                 // Field scala/runtime/Tuple2Zipped$.MODULE$:Lscala/runtime/Tuple2Zipped$;
         3: pop
         4: aload_0
         5: invokevirtual #184                // Method scala$runtime$Tuple2Zipped$$colls:()Lscala/Tuple2;
         8: astore_2
         9: aload_2
        10: invokevirtual #56                 // Method scala/Tuple2._1:()Ljava/lang/Object;
        13: checkcast     #58                 // class scala/collection/Iterable
        16: invokeinterface #62,  1           // InterfaceMethod scala/collection/Iterable.iterator:()Lscala/collection/Iterator;
        21: astore_3
        22: aload_2
        23: invokevirtual #65                 // Method scala/Tuple2._2:()Ljava/lang/Object;
        26: checkcast     #58                 // class scala/collection/Iterable
        29: invokeinterface #62,  1           // InterfaceMethod scala/collection/Iterable.iterator:()Lscala/collection/Iterator;
        34: astore        4
        36: aload_3
        37: invokeinterface #71,  1           // InterfaceMethod scala/collection/Iterator.hasNext:()Z
        42: ifeq          102
        45: aload         4
        47: invokeinterface #71,  1           // InterfaceMethod scala/collection/Iterator.hasNext:()Z
        52: ifeq          102
        55: aload_3
        56: invokeinterface #74,  1           // InterfaceMethod scala/collection/Iterator.next:()Ljava/lang/Object;
        61: aload         4
        63: invokeinterface #74,  1           // InterfaceMethod scala/collection/Iterator.next:()Ljava/lang/Object;
        68: astore        7
        70: astore        6
        72: aload_1
        73: aload         6
        75: aload         7
        77: invokeinterface #80,  3           // InterfaceMethod scala/Function2.apply:(Ljava/lang/Object;Ljava/lang/Object;)Ljava/lang/Object;
        82: invokestatic  #104                // Method scala/runtime/BoxesRunTime.unboxToBoolean:(Ljava/lang/Object;)Z
        85: ifne          92
        88: iconst_1
        89: goto          93
        92: iconst_0
        93: ifeq          36
        96: iconst_1
        97: istore        5
        99: goto          105
       102: iconst_0
       103: istore        5
       105: iload         5
       107: aconst_null
       108: astore_3
       109: aconst_null
       110: astore        4
       112: ifne          117
       115: iconst_1
       116: ireturn
       117: iconst_0
       118: ireturn
      StackMapTable: number_of_entries = 6
        frame_type = 254 /* append */
          offset_delta = 36
          locals = [ class scala/Tuple2, class scala/collection/Iterator, class scala/collection/Iterator ]
        frame_type = 254 /* append */
          offset_delta = 55
          locals = [ top, class java/lang/Object, class java/lang/Object ]
        frame_type = 64 /* same_locals_1_stack_item */
          stack = [ int ]
        frame_type = 248 /* chop */
          offset_delta = 8
        frame_type = 252 /* append */
          offset_delta = 2
          locals = [ int ]
        frame_type = 255 /* full_frame */
          offset_delta = 11
          locals = [ class scala/runtime/Tuple2Zipped, class scala/Function2, class scala/Tuple2, null, null, int ]
          stack = []
      LineNumberTable:
        line 104: 0
        line 45: 9
        line 92: 16
        line 46: 22
        line 93: 29
        line 95: 36
        line 96: 55
        line 104: 72
        line 96: 93
        line 97: 96
        line 100: 102
        line 104: 105
        line 104: 118
      LocalVariableTable:
        Start  Length  Slot  Name   Signature
            0     119     0  this   Lscala/runtime/Tuple2Zipped;
            0     119     1     p   Lscala/Function2;
            9     109     2 forall$extension_$this   Lscala/Tuple2;
           22      81     3 forall$extension_exists$extension_elems1   Lscala/collection/Iterator;
           36      67     4 forall$extension_exists$extension_elems2   Lscala/collection/Iterator;
    Signature: #200                         // (Lscala/Function2<TEl1;TEl2;Ljava/lang/Object;>;)Z
    MethodParameters:
      Name                           Flags
      p                              final

  public scala.collection.Iterator<scala.Tuple2<El1, El2>> iterator();
    descriptor: ()Lscala/collection/Iterator;
    flags: (0x0001) ACC_PUBLIC
    Code:
      stack=2, locals=1, args_size=1
         0: getstatic     #31                 // Field scala/runtime/Tuple2Zipped$.MODULE$:Lscala/runtime/Tuple2Zipped$;
         3: aload_0
         4: invokevirtual #184                // Method scala$runtime$Tuple2Zipped$$colls:()Lscala/Tuple2;
         7: invokevirtual #94                 // Method scala/runtime/Tuple2Zipped$.iterator$extension:(Lscala/Tuple2;)Lscala/collection/Iterator;
        10: areturn
      LineNumberTable:
        line 106: 0
      LocalVariableTable:
        Start  Length  Slot  Name   Signature
            0      11     0  this   Lscala/runtime/Tuple2Zipped;
    Signature: #204                         // ()Lscala/collection/Iterator<Lscala/Tuple2<TEl1;TEl2;>;>;

  public boolean isEmpty();
    descriptor: ()Z
    flags: (0x0001) ACC_PUBLIC
    Code:
      stack=2, locals=1, args_size=1
         0: getstatic     #31                 // Field scala/runtime/Tuple2Zipped$.MODULE$:Lscala/runtime/Tuple2Zipped$;
         3: aload_0
         4: invokevirtual #184                // Method scala$runtime$Tuple2Zipped$$colls:()Lscala/Tuple2;
         7: invokevirtual #89                 // Method scala/runtime/Tuple2Zipped$.isEmpty$extension:(Lscala/Tuple2;)Z
        10: ireturn
      LineNumberTable:
        line 107: 0
      LocalVariableTable:
        Start  Length  Slot  Name   Signature
            0      11     0  this   Lscala/runtime/Tuple2Zipped;

  public <U extends java.lang.Object> void foreach(scala.Function2<El1, El2, U>);
    descriptor: (Lscala/Function2;)V
    flags: (0x0001) ACC_PUBLIC
    Code:
      stack=3, locals=5, args_size=2
         0: getstatic     #31                 // Field scala/runtime/Tuple2Zipped$.MODULE$:Lscala/runtime/Tuple2Zipped$;
         3: pop
         4: aload_0
         5: invokevirtual #184                // Method scala$runtime$Tuple2Zipped$$colls:()Lscala/Tuple2;
         8: astore_2
         9: aload_2
        10: invokevirtual #56                 // Method scala/Tuple2._1:()Ljava/lang/Object;
        13: checkcast     #58                 // class scala/collection/Iterable
        16: invokeinterface #62,  1           // InterfaceMethod scala/collection/Iterable.iterator:()Lscala/collection/Iterator;
        21: astore_3
        22: aload_2
        23: invokevirtual #65                 // Method scala/Tuple2._2:()Ljava/lang/Object;
        26: checkcast     #58                 // class scala/collection/Iterable
        29: invokeinterface #62,  1           // InterfaceMethod scala/collection/Iterable.iterator:()Lscala/collection/Iterator;
        34: astore        4
        36: aload_3
        37: invokeinterface #71,  1           // InterfaceMethod scala/collection/Iterator.hasNext:()Z
        42: ifeq          78
        45: aload         4
        47: invokeinterface #71,  1           // InterfaceMethod scala/collection/Iterator.hasNext:()Z
        52: ifeq          78
        55: aload_1
        56: aload_3
        57: invokeinterface #74,  1           // InterfaceMethod scala/collection/Iterator.next:()Ljava/lang/Object;
        62: aload         4
        64: invokeinterface #74,  1           // InterfaceMethod scala/collection/Iterator.next:()Ljava/lang/Object;
        69: invokeinterface #80,  3           // InterfaceMethod scala/Function2.apply:(Ljava/lang/Object;Ljava/lang/Object;)Ljava/lang/Object;
        74: pop
        75: goto          36
        78: return
      StackMapTable: number_of_entries = 2
        frame_type = 254 /* append */
          offset_delta = 36
          locals = [ class scala/Tuple2, class scala/collection/Iterator, class scala/collection/Iterator ]
        frame_type = 41 /* same */
      LineNumberTable:
        line 108: 0
        line 45: 9
        line 109: 16
        line 46: 22
        line 110: 29
        line 112: 36
        line 113: 55
        line 108: 78
      LocalVariableTable:
        Start  Length  Slot  Name   Signature
            0      79     0  this   Lscala/runtime/Tuple2Zipped;
            0      79     1     f   Lscala/Function2;
           22      56     3 foreach$extension_elems1   Lscala/collection/Iterator;
           36      42     4 foreach$extension_elems2   Lscala/collection/Iterator;
            9      69     2 foreach$extension_$this   Lscala/Tuple2;
    Signature: #208                         // <U:Ljava/lang/Object;>(Lscala/Function2<TEl1;TEl2;TU;>;)V
    MethodParameters:
      Name                           Flags
      f                              final

  public java.lang.String toString();
    descriptor: ()Ljava/lang/String;
    flags: (0x0001) ACC_PUBLIC
    Code:
      stack=2, locals=1, args_size=1
         0: getstatic     #31                 // Field scala/runtime/Tuple2Zipped$.MODULE$:Lscala/runtime/Tuple2Zipped$;
         3: aload_0
         4: invokevirtual #184                // Method scala$runtime$Tuple2Zipped$$colls:()Lscala/Tuple2;
         7: invokevirtual #48                 // Method scala/runtime/Tuple2Zipped$.toString$extension:(Lscala/Tuple2;)Ljava/lang/String;
        10: areturn
      LineNumberTable:
        line 117: 0
      LocalVariableTable:
        Start  Length  Slot  Name   Signature
            0      11     0  this   Lscala/runtime/Tuple2Zipped;

  public int hashCode();
    descriptor: ()I
    flags: (0x0001) ACC_PUBLIC
    Code:
      stack=1, locals=1, args_size=1
         0: getstatic     #31                 // Field scala/runtime/Tuple2Zipped$.MODULE$:Lscala/runtime/Tuple2Zipped$;
         3: pop
         4: aload_0
         5: invokevirtual #184                // Method scala$runtime$Tuple2Zipped$$colls:()Lscala/Tuple2;
         8: invokevirtual #43                 // Method scala/Tuple2.hashCode:()I
        11: ireturn
      LineNumberTable:
        line 44: 0
        line 44: 8
        line 44: 11
      LocalVariableTable:
        Start  Length  Slot  Name   Signature
            0      12     0  this   Lscala/runtime/Tuple2Zipped;

  public boolean equals(java.lang.Object);
    descriptor: (Ljava/lang/Object;)Z
    flags: (0x0001) ACC_PUBLIC
    Code:
      stack=3, locals=2, args_size=2
         0: getstatic     #31                 // Field scala/runtime/Tuple2Zipped$.MODULE$:Lscala/runtime/Tuple2Zipped$;
         3: aload_0
         4: invokevirtual #184                // Method scala$runtime$Tuple2Zipped$$colls:()Lscala/Tuple2;
         7: aload_1
         8: invokevirtual #33                 // Method scala/runtime/Tuple2Zipped$.equals$extension:(Lscala/Tuple2;Ljava/lang/Object;)Z
        11: ireturn
      LineNumberTable:
        line 44: 0
      LocalVariableTable:
        Start  Length  Slot  Name   Signature
            0      12     0  this   Lscala/runtime/Tuple2Zipped;
            0      12     1   x$1   Ljava/lang/Object;
    MethodParameters:
      Name                           Flags
      x$1                            final

  public scala.runtime.Tuple2Zipped(scala.Tuple2<It1, It2>);
    descriptor: (Lscala/Tuple2;)V
    flags: (0x0001) ACC_PUBLIC
    Code:
      stack=2, locals=2, args_size=2
         0: aload_0
         1: aload_1
         2: putfield      #177                // Field scala$runtime$Tuple2Zipped$$colls:Lscala/Tuple2;
         5: aload_0
         6: invokespecial #218                // Method java/lang/Object."<init>":()V
         9: return
      LineNumberTable:
        line 44: 0
      LocalVariableTable:
        Start  Length  Slot  Name   Signature
            0      10     0  this   Lscala/runtime/Tuple2Zipped;
            0      10     1 colls   Lscala/Tuple2;
    Signature: #214                         // (Lscala/Tuple2<TIt1;TIt2;>;)V
    MethodParameters:
      Name                           Flags
      colls                          final
}
InnerClasses:
  public static final #14= #13 of #2;     // Ops=class scala/runtime/Tuple2Zipped$Ops of class scala/runtime/Tuple2Zipped
  public static #17= #16 of #2;           // Ops$=class scala/runtime/Tuple2Zipped$Ops$ of class scala/runtime/Tuple2Zipped
Signature: #3                           // <El1:Ljava/lang/Object;It1::Lscala/collection/Iterable<TEl1;>;El2:Ljava/lang/Object;It2::Lscala/collection/Iterable<TEl2;>;>Ljava/lang/Object;Lscala/runtime/ZippedIterable2<TEl1;TEl2;>;
SourceFile: "Tuple2Zipped.scala"
Deprecated: true
RuntimeVisibleAnnotations:
  0: #9(#10=s#11)
    scala.reflect.ScalaSignature(
      bytes="\u0006\u0005\u0015Ed\u0001\u0002\u00192\u0005YBAB\u0014\u0001\u0005\u0002\u0003\u0015)Q1A\u0005\n=C\u0011b\u0019\u0001\u0003\u0006\u0003\u0005\u000b\u0011\u0002)\t\u000b\u0011\u0004A\u0011A3\t\u000b%\u0004A\u0011\u00026\t\u000b-\u0004A\u0011\u00027\t\u000b5\u0004A\u0011\u00018\t\u000f\u0005%\u0001\u0001\"\u0001\u0002\f!9\u0011q\u0005\u0001\u0005\u0002\u0005%\u0002bBA*\u0001\u0011\u0005\u0011Q\u000b\u0005\b\u00037\u0002A\u0011AA/\u0011\u001d\t\t\u0007\u0001C\u0001\u0003GBq!!\u001c\u0001\t\u0003\ny\u0007C\u0004\u0002r\u0001!\t!a\u001d\t\u000f\u0005\u001d\u0005\u0001\"\u0011\u0002\n\"I\u0011\u0011\u0015\u0001\u0002\u0002\u0013\u0005\u00131\u0015\u0005\n\u0003W\u0003\u0011\u0011!C!\u0003[;q!a22\u0011\u0003\tIM\u0002\u00041c!\u0005\u00111\u001a\u0005\u0007IJ!\t!a5\u0007\r\u0005U\'CAAl\u00119\tY\u000e\u0006C\u0001\u0002\u000b\u0015)\u0019!C\u0005\u0003;D1\"!<\u0015\u0005\u000b\u0005\t\u0015!\u0003\u0002`\"1A\r\u0006C\u0001\u0003_Dq!!?\u0015\t\u0003\tY\u0010C\u0004\u0003HQ!\tA!\u0013\t\u0013\u0005\u0005F#!A\u0005B\u0005\r\u0006\"CAV)\u0005\u0005I\u0011\tBG\u000f%\u0011\tJEA\u0001\u0012\u0003\u0011\u0019JB\u0005\u0002VJ\t\t\u0011#\u0001\u0003\u0016\"1A-\bC\u0001\u0005/CqA!\'\u001e\t\u000b\u0011Y\nC\u0004\u0003hv!)A!;\t\u0013\r-R$!A\u0005\u0006\r5\u0002\"CB\u001f;\u0005\u0005IQAB \u0011\u001d\u0019\u0019F\u0005C\u0003\u0007+Bqa!\u001e\u0013\t\u000b\u00199\bC\u0004\u0004\u0018J!)a!\'\t\u000f\r5\'\u0003\"\u0002\u0004P\"9AQ\u0001\n\u0005\u0006\u0011\u001d\u0001b\u0002C!%\u0011\u0015A1\t\u0005\b\tS\u0012BQ\u0001C6\u0011\u001d!\tJ\u0005C\u0003\t\'Cq\u0001b.\u0013\t\u000b!I\fC\u0004\u0005ZJ!)\u0001b7\t\u000f\u0015\u0015!\u0003\"\u0002\u0006\b!I11\u0006\n\u0002\u0002\u0013\u0015Qq\u0005\u0005\n\u0007{\u0011\u0012\u0011!C\u0003\u000b\u000f\u0012A\u0002V;qY\u0016\u0014$,\u001b9qK\u0012T!AM\u001a\u0002\u000fI,h\u000e^5nK*\tA\'A\u0003tG\u0006d\u0017m\u0001\u0001\u0016\u000b]\u0012E\u000bT0\u0014\u0007\u0001AD\b\u0005\u0002:u5\t1\'\u0003\u0002<g\t1\u0011I\\=WC2\u0004B!\u0010 A\u00176\t\u0011\'\u0003\u0002@c\ty!,\u001b9qK\u0012LE/\u001a:bE2,\'\u0007\u0005\u0002B\u00052\u0001A!B\"\u0001\u0005\u0004!%aA#mcE\u0011Q\t\u0013\t\u0003s\u0019K!aR\u001a\u0003\u000f9{G\u000f[5oOB\u0011\u0011(S\u0005\u0003\u0015N\u00121!\u00118z!\t\tE\nB\u0003N\u0001\t\u0007AIA\u0002FYJ\n\u0011e]2bY\u0006$#/\u001e8uS6,G\u0005V;qY\u0016\u0014$,\u001b9qK\u0012$CeY8mYN,\u0012\u0001\u0015\t\u0005sE\u001bf,\u0003\u0002Sg\t1A+\u001e9mKJ\u0002\"!\u0011+\u0005\u000bU\u0003!\u0019\u0001,\u0003\u0007%#\u0018\'\u0005\u0002F/B\u0019\u0001l\u0017!\u000f\u0005eJ\u0016B\u0001.4\u0003\u001d\u0001\u0018mY6bO\u0016L!\u0001X/\u0003\u0011%#XM]1cY\u0016T!AW\u001a\u0011\u0005\u0005{F!\u00021\u0001\u0005\u0004\t\'aA%ueE\u0011QI\u0019\t\u00041n[\u0015AI:dC2\fGE];oi&lW\r\n+va2,\'GW5qa\u0016$G\u0005J2pY2\u001c\b%\u0001\u0004=S:LGO\u0010\u000b\u0003M\u001e\u0004b!\u0010\u0001A\'.s\u0006\"\u00025\u0004\u0001\u0004\u0001\u0016!B2pY2\u001c\u0018!B2pY2\fT#A*\u0002\u000b\r|G\u000e\u001c\u001a\u0016\u0003y\u000b1!\\1q+\ryWP\u001d\u000b\u0003a~$\"!\u001d;\u0011\u0005\u0005\u0013H!B:\u0007\u0005\u0004!%A\u0001+p\u0011\u0015)h\u0001q\u0001w\u0003\t\u0011g\rE\u0003xuNc\u0018/D\u0001y\u0015\tI8\'\u0001\u0006d_2dWm\u0019;j_:L!a\u001f=\u0003\u0013\t+\u0018\u000e\u001c3Ge>l\u0007CA!~\t\u0015qhA1\u0001E\u0005\u0005\u0011\u0005bBA\u0001\r\u0001\u0007\u00111A\u0001\u0002MB1\u0011(!\u0002A\u0017rL1!a\u00024\u0005%1UO\\2uS>t\'\'A\u0004gY\u0006$X*\u00199\u0016\r\u00055\u00111DA\n)\u0011\ty!!\b\u0015\t\u0005E\u0011Q\u0003\t\u0004\u0003\u0006MA!B:\b\u0005\u0004!\u0005BB;\b\u0001\b\t9\u0002E\u0004xuN\u000bI\"!\u0005\u0011\u0007\u0005\u000bY\u0002B\u0003\u007f\u000f\t\u0007A\tC\u0004\u0002\u0002\u001d\u0001\r!a\b\u0011\u000fe\n)\u0001Q&\u0002\"A)\u0001,a\t\u0002\u001a%\u0019\u0011QE/\u0003\u0019%#XM]1cY\u0016|enY3\u0002\r\u0019LG\u000e^3s+\u0019\tY#a\r\u0002:Q!\u0011QFA%)\u0019\ty#!\u0010\u0002DA1\u0011(UA\u0019\u0003o\u00012!QA\u001a\t\u0019\t)\u0004\u0003b\u0001\t\n\u0019Ak\\\u0019\u0011\u0007\u0005\u000bI\u0004\u0002\u0004\u0002<!\u0011\r\u0001\u0012\u0002\u0004)>\u0014\u0004bBA \u0011\u0001\u000f\u0011\u0011I\u0001\u0004E\u001a\f\u0004CB<{\'\u0002\u000b\t\u0004C\u0004\u0002F!\u0001\u001d!a\u0012\u0002\u0007\t4\'\u0007\u0005\u0004xuz[\u0015q\u0007\u0005\b\u0003\u0003A\u0001\u0019AA&!\u001dI\u0014Q\u0001!L\u0003\u001b\u00022!OA(\u0013\r\t\tf\r\u0002\b\u0005>|G.Z1o\u0003\u0019)\u00070[:ugR!\u0011QJA,\u0011\u001d\tI&\u0003a\u0001\u0003\u0017\n\u0011\u0001]\u0001\u0007M>\u0014\u0018\r\u001c7\u0015\t\u00055\u0013q\f\u0005\b\u00033R\u0001\u0019AA&\u0003!IG/\u001a:bi>\u0014XCAA3!\u0015A\u0016qMA6\u0013\r\tI\'\u0018\u0002\t\u0013R,\'/\u0019;peB!\u0011(\u0015!L\u0003\u001dI7/R7qif,\"!!\u0014\u0002\u000f\u0019|\'/Z1dQV!\u0011QOAB)\u0011\t9(! \u0011\u0007e\nI(C\u0002\u0002|M\u0012A!\u00168ji\"9\u0011\u0011A\u0007A\u0002\u0005}\u0004cB\u001d\u0002\u0006\u0001[\u0015\u0011\u0011\t\u0004\u0003\u0006\rEABAC\u001b\t\u0007AIA\u0001V\u0003!!xn\u0015;sS:<GCAAF!\u0011\ti)a\'\u000f\t\u0005=\u0015q\u0013\t\u0004\u0003#\u001bTBAAJ\u0015\r\t)*N\u0001\u0007yI|w\u000e\u001e \n\u0007\u0005e5\'\u0001\u0004Qe\u0016$WMZ\u0005\u0005\u0003;\u000byJ\u0001\u0004TiJLgn\u001a\u0006\u0004\u00033\u001b\u0014\u0001\u00035bg\"\u001cu\u000eZ3\u0015\u0005\u0005\u0015\u0006cA\u001d\u0002(&\u0019\u0011\u0011V\u001a\u0003\u0007%sG/\u0001\u0004fcV\fGn\u001d\u000b\u0005\u0003\u001b\ny\u000b\u0003\u0005\u00022B\t\t\u00111\u0001I\u0003\rAH%\r\u0015\f\u0001\u0005U\u00161XA_\u0003\u0003\f\u0019\rE\u0002:\u0003oK1!!/4\u0005)!W\r\u001d:fG\u0006$X\rZ\u0001\b[\u0016\u001c8/Y4fC\t\ty,\u0001\u0010Vg\u0016\u00043oY1mC:\u001aw\u000e\u001c7fGRLwN\u001c\u0018MCjL(,\u001b93]\u0005)1/\u001b8dK\u0006\u0012\u0011QY\u0001\u0007e9\n4G\f\u0019\u0002\u0019Q+\b\u000f\\335&\u0004\b/\u001a3\u0011\u0005u\u00122c\u0001\n\u0002NB\u0019\u0011(a4\n\u0007\u0005E7G\u0001\u0004B]f\u0014VM\u001a\u000b\u0003\u0003\u0013\u00141a\u00149t+\u0019\tI.a9\u0002jN\u0011A\u0003O\u0001\"g\u000e\fG.\u0019\u0013sk:$\u0018.\\3%)V\u0004H.\u001a\u001a[SB\u0004X\r\u001a\u0013PaN$C\u0005_\u000b\u0003\u0003?\u0004b!O)\u0002b\u0006\u001d\bcA!\u0002d\u00121\u0011Q\u001d\u000bC\u0002\u0011\u0013!\u0001V\u0019\u0011\u0007\u0005\u000bI\u000f\u0002\u0004\u0002lR\u0011\r\u0001\u0012\u0002\u0003)J\n!e]2bY\u0006$#/\u001e8uS6,G\u0005V;qY\u0016\u0014$,\u001b9qK\u0012$s\n]:%Ia\u0004C\u0003BAy\u0003k\u0004r!a=\u0015\u0003C\f9/D\u0001\u0013\u0011\u001d\t9p\u0006a\u0001\u0003?\f\u0011\u0001_\u0001\u0007S:4XM\u001d;\u0016\u0019\u0005u(\u0011\u0005B\t\u0005s\u0011YC!\u0001\u0015\u0011\u0005}(Q\u0001B\u0012\u0005w\u00012!\u0011B\u0001\t\u0019\u0011\u0019\u0001\u0007b\u0001\t\n!A\u000b[1u\u0011\u001d\u00119\u0001\u0007a\u0002\u0005\u0013\t!a^\u0019\u0011\u000fe\u0012Y!!9\u0003\u0010%\u0019!QB\u001a\u0003!\u0011bWm]:%G>dwN\u001c\u0013mKN\u001c\b#B!\u0003\u0012\t}AAB+\u0019\u0005\u0004\u0011\u0019\"\u0006\u0003\u0003\u0016\tm\u0011cA#\u0003\u0018A!\u0001l\u0017B\r!\r\t%1\u0004\u0003\b\u0005;\u0011\tB1\u0001E\u0005\u0005\t\u0007cA!\u0003\"\u0011)1\t\u0007b\u0001\t\"9!Q\u0005\rA\u0004\t\u001d\u0012AA<3!\u001dI$1BAt\u0005S\u0001R!\u0011B\u0016\u0005o!a\u0001\u0019\rC\u0002\t5R\u0003\u0002B\u0018\u0005k\t2!\u0012B\u0019!\u0011A6La\r\u0011\u0007\u0005\u0013)\u0004B\u0004\u0003\u001e\t-\"\u0019\u0001#\u0011\u0007\u0005\u0013I\u0004B\u0003N1\t\u0007A\t\u0003\u0004v1\u0001\u000f!Q\b\t\toj\f\tOa\u0010\u0002\u0000B1\u0011(\u0015B\u0010\u0005oA3\u0002GA[\u0003w\u0013\u0019%!1\u0002D\u0006\u0012!QI\u0001\u001f+N,\u0007\u0005_:/Y\u0006T\u0018PW5qQeT\u0018FL7ba\"Bs\f\f\u0011`S%\naA_5qa\u0016$WC\u0003B&\u0005#\u0012)F!\u0018\u0003bQ1!Q\nB4\u0005{\u0002\"\"\u0010\u0001\u0003P\tM#1\fB0!\r\t%\u0011\u000b\u0003\u0006\u0007f\u0011\r\u0001\u0012\t\u0004\u0003\nUCAB+\u001a\u0005\u0004\u00119&E\u0002F\u00053\u0002B\u0001W.\u0003PA\u0019\u0011I!\u0018\u0005\u000b5K\"\u0019\u0001#\u0011\u0007\u0005\u0013\t\u0007\u0002\u0004a3\t\u0007!1M\t\u0004\u000b\n\u0015\u0004\u0003\u0002-\\\u00057BqAa\u0002\u001a\u0001\b\u0011I\u0007E\u0004:\u0005W\n\tOa\u001c\n\u0007\t54GA\u0005Gk:\u001cG/[8ocI1!\u0011\u000fB;\u0005\'2aAa\u001d\u0015\u0001\t=$\u0001\u0004\u001fsK\u001aLg.Z7f]Rt\u0004#C<\u0003x\t=#1\u0010B*\u0013\r\u0011I\b\u001f\u0002\f\u0013R,\'/\u00192mK>\u00038\u000f\u0005\u0002Y7\"9!QE\rA\u0004\t}\u0004cB\u001d\u0003l\u0005\u001d(\u0011\u0011\n\u0007\u0005\u0007\u0013)Ia\u0018\u0007\r\tMD\u0003\u0001BA!%9(q\u000fB.\u0005w\u0012y\u0006K\u0006\u001a\u0003k\u000bYL!#\u0002B\u0006\r\u0017E\u0001BF\u0003I)6/\u001a\u0011yg:b\u0017M_=[SBD\u0013p]\u0015\u0015\t\u00055#q\u0012\u0005\t\u0003c[\u0012\u0011!a\u0001\u0011\u0006\u0019q\n]:\u0011\u0007\u0005MXdE\u0002\u001e\u0003\u001b$\"Aa%\u0002!%tg/\u001a:uI\u0015DH/\u001a8tS>tW\u0003\u0005BO\u0005{\u0013yKa6\u0003J\n\r&1\u0016Bc)\u0011\u0011yJa8\u0015\u0011\t\u0005&Q\u0015B`\u00053\u00042!\u0011BR\t\u0019\u0011\u0019a\bb\u0001\t\"9!qA\u0010A\u0004\t\u001d\u0006cB\u001d\u0003\f\t%&Q\u0016\t\u0004\u0003\n-FABAs?\t\u0007A\tE\u0003B\u0005_\u0013Y\f\u0002\u0004V?\t\u0007!\u0011W\u000b\u0005\u0005g\u0013I,E\u0002F\u0005k\u0003B\u0001W.\u00038B\u0019\u0011I!/\u0005\u000f\tu!q\u0016b\u0001\tB\u0019\u0011I!0\u0005\u000b\r{\"\u0019\u0001#\t\u000f\t\u0015r\u0004q\u0001\u0003BB9\u0011Ha\u0003\u0003D\n\u001d\u0007cA!\u0003F\u00121\u00111^\u0010C\u0002\u0011\u0003R!\u0011Be\u0005+$a\u0001Y\u0010C\u0002\t-W\u0003\u0002Bg\u0005\'\f2!\u0012Bh!\u0011A6L!5\u0011\u0007\u0005\u0013\u0019\u000eB\u0004\u0003\u001e\t%\'\u0019\u0001#\u0011\u0007\u0005\u00139\u000eB\u0003N?\t\u0007A\t\u0003\u0004v?\u0001\u000f!1\u001c\t\toj\u0014IK!8\u0003\"B1\u0011(\u0015B^\u0005+DqA!9 \u0001\u0004\u0011\u0019/A\u0003%i\"L7\u000fE\u0004\u0002tR\u0011IKa1)\u0017}\t),a/\u0003D\u0005\u0005\u00171Y\u0001\u0011u&\u0004\b/\u001a3%Kb$XM\\:j_:,bBa;\u0003t\n](q`B\u0002\u0007\u001f\u0019i\u0002\u0006\u0003\u0003n\u000e\u0015BC\u0002Bx\u0007\u0013\u00199\u0002\u0005\u0006>\u0001\tE(Q\u001fB\u007f\u0007\u0003\u00012!\u0011Bz\t\u0015\u0019\u0005E1\u0001E!\r\t%q\u001f\u0003\u0007+\u0002\u0012\rA!?\u0012\u0007\u0015\u0013Y\u0010\u0005\u0003Y7\nE\bcA!\u0003\u0000\u0012)Q\n\tb\u0001\tB\u0019\u0011ia\u0001\u0005\r\u0001\u0004#\u0019AB\u0003#\r)5q\u0001\t\u00051n\u0013i\u0010C\u0004\u0003\b\u0001\u0002\u001daa\u0003\u0011\u000fe\u0012Yg!\u0004\u0004\u0012A\u0019\u0011ia\u0004\u0005\r\u0005\u0015\bE1\u0001E%\u0019\u0019\u0019b!\u0006\u0003v\u001a1!1\u000f\u000b\u0001\u0007#\u0001\u0012b\u001eB<\u0005c\u0014YH!>\t\u000f\t\u0015\u0002\u0005q\u0001\u0004\u001aA9\u0011Ha\u001b\u0004\u001c\r}\u0001cA!\u0004\u001e\u00111\u00111\u001e\u0011C\u0002\u0011\u0013ba!\t\u0004$\r\u0005aA\u0002B:)\u0001\u0019y\u0002E\u0005x\u0005o\u0012iPa\u001f\u0004\u0002!9!\u0011\u001d\u0011A\u0002\r\u001d\u0002cBAz)\r511\u0004\u0015\fA\u0005U\u00161\u0018BE\u0003\u0003\f\u0019-\u0001\niCND7i\u001c3fI\u0015DH/\u001a8tS>tWCBB\u0018\u0007o\u0019Y\u0004\u0006\u0003\u0002$\u000eE\u0002b\u0002BqC\u0001\u000711\u0007\t\b\u0003g$2QGB\u001d!\r\t5q\u0007\u0003\u0007\u0003K\f#\u0019\u0001#\u0011\u0007\u0005\u001bY\u0004\u0002\u0004\u0002l\u0006\u0012\r\u0001R\u0001\u0011KF,\u0018\r\\:%Kb$XM\\:j_:,ba!\u0011\u0004N\rEC\u0003BB\"\u0007\u000f\"B!!\u0014\u0004F!A\u0011\u0011\u0017\u0012\u0002\u0002\u0003\u0007\u0001\nC\u0004\u0003b\n\u0002\ra!\u0013\u0011\u000f\u0005MHca\u0013\u0004PA\u0019\u0011i!\u0014\u0005\r\u0005\u0015(E1\u0001E!\r\t5\u0011\u000b\u0003\u0007\u0003W\u0014#\u0019\u0001#\u0002\u001f\r|G\u000e\\\u0019%Kb$XM\\:j_:,\"ba\u0016\u0004d\rm31NB8)\u0011\u0019If!\u001a\u0011\u0007\u0005\u001bY\u0006\u0002\u0004VG\t\u00071QL\t\u0004\u000b\u000e}\u0003\u0003\u0002-\\\u0007C\u00022!QB2\t\u0015\u00195E1\u0001E\u0011\u001d\u0011\to\ta\u0001\u0007O\u0002\"\"\u0010\u0001\u0004b\re3\u0011NB7!\r\t51\u000e\u0003\u0006\u001b\u000e\u0012\r\u0001\u0012\t\u0004\u0003\u000e=DA\u00021$\u0005\u0004\u0019\t(E\u0002F\u0007g\u0002B\u0001W.\u0004j\u0005y1m\u001c7me\u0011*\u0007\u0010^3og&|g.\u0006\u0006\u0004z\r55\u0011SBC\u0007{\"Baa\u001f\u0004\bB\u0019\u0011i! \u0005\r\u0001$#\u0019AB@#\r)5\u0011\u0011\t\u00051n\u001b\u0019\tE\u0002B\u0007\u000b#Q!\u0014\u0013C\u0002\u0011CqA!9%\u0001\u0004\u0019I\t\u0005\u0006>\u0001\r-5qRBB\u0007w\u00022!QBG\t\u0015\u0019EE1\u0001E!\r\t5\u0011\u0013\u0003\u0007+\u0012\u0012\raa%\u0012\u0007\u0015\u001b)\n\u0005\u0003Y7\u000e-\u0015!D7ba\u0012*\u0007\u0010^3og&|g.\u0006\b\u0004\u001c\u000e]61UBZ\u0007W\u001byla2\u0015\t\ru5\u0011\u0019\u000b\u0005\u0007?\u001bI\f\u0006\u0003\u0004\"\u000e\u0015\u0006cA!\u0004$\u0012)1/\nb\u0001\t\"1Q/\na\u0002\u0007O\u0003\u0002b\u001e>\u0004*\u000eU6\u0011\u0015\t\u0004\u0003\u000e-FAB+&\u0005\u0004\u0019i+E\u0002F\u0007_\u0003B\u0001W.\u00042B\u0019\u0011ia-\u0005\u000b\r+#\u0019\u0001#\u0011\u0007\u0005\u001b9\fB\u0003\u007fK\t\u0007A\tC\u0004\u0002\u0002\u0015\u0002\raa/\u0011\u0013e\n)a!-\u0004>\u000eU\u0006cA!\u0004@\u0012)Q*\nb\u0001\t\"9!\u0011]\u0013A\u0002\r\r\u0007CC\u001f\u0001\u0007c\u001bIk!0\u0004FB\u0019\u0011ia2\u0005\r\u0001,#\u0019ABe#\r)51\u001a\t\u00051n\u001bi,A\tgY\u0006$X*\u00199%Kb$XM\\:j_:,bb!5\u0004n\u000ee7\u0011^Bq\u0007k\u001cy\u0010\u0006\u0003\u0004T\u000eeH\u0003BBk\u0007_$Baa6\u0004\\B\u0019\u0011i!7\u0005\u000bM4#\u0019\u0001#\t\rU4\u00039ABo!!9(pa8\u0004l\u000e]\u0007cA!\u0004b\u00121QK\nb\u0001\u0007G\f2!RBs!\u0011A6la:\u0011\u0007\u0005\u001bI\u000fB\u0003DM\t\u0007A\tE\u0002B\u0007[$QA \u0014C\u0002\u0011Cq!!\u0001\'\u0001\u0004\u0019\t\u0010E\u0005:\u0003\u000b\u00199oa=\u0004xB\u0019\u0011i!>\u0005\u000b53#\u0019\u0001#\u0011\u000ba\u000b\u0019ca;\t\u000f\t\u0005h\u00051\u0001\u0004|BQQ\bABt\u0007?\u001c\u0019p!@\u0011\u0007\u0005\u001by\u0010\u0002\u0004aM\t\u0007A\u0011A\t\u0004\u000b\u0012\r\u0001\u0003\u0002-\\\u0007g\f\u0001CZ5mi\u0016\u0014H%\u001a=uK:\u001c\u0018n\u001c8\u0016\u001d\u0011%A1\u0003C\f\tO!y\u0002b\u000e\u00050Q!A1\u0002C\u001f)\u0011!i\u0001\"\u000f\u0015\r\u0011=A\u0011\u0004C\u0015!\u0019I\u0014\u000b\"\u0005\u0005\u0016A\u0019\u0011\tb\u0005\u0005\r\u0005UrE1\u0001E!\r\tEq\u0003\u0003\u0007\u0003w9#\u0019\u0001#\t\u000f\u0005}r\u0005q\u0001\u0005\u001cAAqO\u001fC\u000f\tK!\t\u0002E\u0002B\t?!a!V\u0014C\u0002\u0011\u0005\u0012cA#\u0005$A!\u0001l\u0017C\u0013!\r\tEq\u0005\u0003\u0006\u0007\u001e\u0012\r\u0001\u0012\u0005\b\u0003\u000b:\u00039\u0001C\u0016!!9(\u0010\"\f\u00056\u0011U\u0001cA!\u00050\u00111\u0001m\nb\u0001\tc\t2!\u0012C\u001a!\u0011A6\f\"\u000e\u0011\u0007\u0005#9\u0004B\u0003NO\t\u0007A\tC\u0004\u0002\u0002\u001d\u0002\r\u0001b\u000f\u0011\u0013e\n)\u0001\"\n\u00056\u00055\u0003b\u0002BqO\u0001\u0007Aq\b\t\u000b{\u0001!)\u0003\"\b\u00056\u00115\u0012\u0001E3ySN$8\u000fJ3yi\u0016t7/[8o+)!)\u0005b\u0014\u0005\\\u0011MC1\r\u000b\u0005\t\u000f\")\u0006\u0006\u0003\u0002N\u0011%\u0003bBA-Q\u0001\u0007A1\n\t\ns\u0005\u0015AQ\nC)\u0003\u001b\u00022!\u0011C(\t\u0015\u0019\u0005F1\u0001E!\r\tE1\u000b\u0003\u0006\u001b\"\u0012\r\u0001\u0012\u0005\b\u0005CD\u0003\u0019\u0001C,!)i\u0004\u0001\"\u0014\u0005Z\u0011EC\u0011\r\t\u0004\u0003\u0012mCAB+)\u0005\u0004!i&E\u0002F\t?\u0002B\u0001W.\u0005NA\u0019\u0011\tb\u0019\u0005\r\u0001D#\u0019\u0001C3#\r)Eq\r\t\u00051n#\t&\u0001\tg_J\fG\u000e\u001c\u0013fqR,gn]5p]VQAQ\u000eC<\t\u0007#Y\bb#\u0015\t\u0011=DQ\u0010\u000b\u0005\u0003\u001b\"\t\bC\u0004\u0002Z%\u0002\r\u0001b\u001d\u0011\u0013e\n)\u0001\"\u001e\u0005z\u00055\u0003cA!\u0005x\u0011)1)\u000bb\u0001\tB\u0019\u0011\tb\u001f\u0005\u000b5K#\u0019\u0001#\t\u000f\t\u0005\u0018\u00061\u0001\u0005\u0000AQQ\b\u0001C;\t\u0003#I\b\"#\u0011\u0007\u0005#\u0019\t\u0002\u0004VS\t\u0007AQQ\t\u0004\u000b\u0012\u001d\u0005\u0003\u0002-\\\tk\u00022!\u0011CF\t\u0019\u0001\u0017F1\u0001\u0005\u000eF\u0019Q\tb$\u0011\ta[F\u0011P\u0001\u0013SR,\'/\u0019;pe\u0012*\u0007\u0010^3og&|g.\u0006\u0006\u0005\u0016\u0012uE\u0011\u0016CQ\tc#B\u0001b&\u0005$B)\u0001,a\u001a\u0005\u001aB1\u0011(\u0015CN\t?\u00032!\u0011CO\t\u0015\u0019%F1\u0001E!\r\tE\u0011\u0015\u0003\u0006\u001b*\u0012\r\u0001\u0012\u0005\b\u0005CT\u0003\u0019\u0001CS!)i\u0004\u0001b\'\u0005(\u0012}Eq\u0016\t\u0004\u0003\u0012%FAB++\u0005\u0004!Y+E\u0002F\t[\u0003B\u0001W.\u0005\u001cB\u0019\u0011\t\"-\u0005\r\u0001T#\u0019\u0001CZ#\r)EQ\u0017\t\u00051n#y*A\tjg\u0016k\u0007\u000f^=%Kb$XM\\:j_:,\"\u0002b/\u0005D\u0012\u001dGq\u001aCj)\u0011\ti\u0005\"0\t\u000f\t\u00058\u00061\u0001\u0005@BQQ\b\u0001Ca\t\u000b$i\r\"5\u0011\u0007\u0005#\u0019\rB\u0003DW\t\u0007A\tE\u0002B\t\u000f$a!V\u0016C\u0002\u0011%\u0017cA#\u0005LB!\u0001l\u0017Ca!\r\tEq\u001a\u0003\u0006\u001b.\u0012\r\u0001\u0012\t\u0004\u0003\u0012MGA\u00021,\u0005\u0004!).E\u0002F\t/\u0004B\u0001W.\u0005N\u0006\tbm\u001c:fC\u000eDG%\u001a=uK:\u001c\u0018n\u001c8\u0016\u0019\u0011uGq\u001eCt\to$Y\u000fb@\u0015\t\u0011}G\u0011\u001f\u000b\u0005\u0003o\"\t\u000fC\u0004\u0002\u00021\u0002\r\u0001b9\u0011\u0013e\n)\u0001\":\u0005j\u00125\bcA!\u0005h\u0012)1\t\fb\u0001\tB\u0019\u0011\tb;\u0005\u000b5c#\u0019\u0001#\u0011\u0007\u0005#y\u000f\u0002\u0004\u0002\u00062\u0012\r\u0001\u0012\u0005\b\u0005Cd\u0003\u0019\u0001Cz!)i\u0004\u0001\":\u0005v\u0012%HQ \t\u0004\u0003\u0012]HAB+-\u0005\u0004!I0E\u0002F\tw\u0004B\u0001W.\u0005fB\u0019\u0011\tb@\u0005\r\u0001d#\u0019AC\u0001#\r)U1\u0001\t\u00051n#I/\u0001\nu_N#(/\u001b8hI\u0015DH/\u001a8tS>tWCCC\u0005\u000b#))\"\"\b\u0006\"Q!\u0011\u0011RC\u0006\u0011\u001d\u0011\t/\fa\u0001\u000b\u001b\u0001\"\"\u0010\u0001\u0006\u0010\u0015MQ1DC\u0010!\r\tU\u0011\u0003\u0003\u0006\u00076\u0012\r\u0001\u0012\t\u0004\u0003\u0016UAAB+.\u0005\u0004)9\"E\u0002F\u000b3\u0001B\u0001W.\u0006\u0010A\u0019\u0011)\"\b\u0005\u000b5k#\u0019\u0001#\u0011\u0007\u0005+\t\u0003\u0002\u0004a[\t\u0007Q1E\t\u0004\u000b\u0016\u0015\u0002\u0003\u0002-\\\u000b7)\"\"\"\u000b\u00062\u0015URQHC!)\u0011\t\u0019+b\u000b\t\u000f\t\u0005h\u00061\u0001\u0006.AQQ\bAC\u0018\u000bg)Y$b\u0010\u0011\u0007\u0005+\t\u0004B\u0003D]\t\u0007A\tE\u0002B\u000bk!a!\u0016\u0018C\u0002\u0015]\u0012cA#\u0006:A!\u0001lWC\u0018!\r\tUQ\b\u0003\u0006\u001b:\u0012\r\u0001\u0012\t\u0004\u0003\u0016\u0005CA\u00021/\u0005\u0004)\u0019%E\u0002F\u000b\u000b\u0002B\u0001W.\u0006<UQQ\u0011JC+\u000b3*\t\'\"\u001a\u0015\t\u0015-Sq\n\u000b\u0005\u0003\u001b*i\u0005\u0003\u0005\u00022>\n\t\u00111\u0001I\u0011\u001d\u0011\to\fa\u0001\u000b#\u0002\"\"\u0010\u0001\u0006T\u0015]SqLC2!\r\tUQ\u000b\u0003\u0006\u0007>\u0012\r\u0001\u0012\t\u0004\u0003\u0016eCAB+0\u0005\u0004)Y&E\u0002F\u000b;\u0002B\u0001W.\u0006TA\u0019\u0011)\"\u0019\u0005\u000b5{#\u0019\u0001#\u0011\u0007\u0005+)\u0007\u0002\u0004a_\t\u0007QqM\t\u0004\u000b\u0016%\u0004\u0003\u0002-\\\u000b?B3BEA[\u0003w\u000bi,!1\u0002D\"\u001a!#!.)\u0017E\t),a/\u0002>\u0006\u0005\u00171\u0019"
    )
  ScalaInlineInfo: length = 0x4F (unknown attribute)
   01 01 00 0F 00 84 00 D5 01 00 B4 00 B5 01 00 B9
   00 B5 01 00 D4 00 66 01 00 C6 00 C7 01 00 C2 00
   C3 01 00 BF 00 BC 01 00 CA 00 C7 01 00 CE 00 CF
   01 00 28 00 29 01 00 CD 00 45 01 00 3B 00 3C 01
   00 BB 00 BC 01 00 12 00 AE 01 00 D2 00 D3 01
  ScalaSig: length = 0x3 (unknown attribute)
   05 02 00
