Classfile /Users/mw/Projects/slang-braindump/.jar/jar11/assemble/slang-braindump/assemble/content/scala/runtime/ZippedIterable3.class
  Last modified May 29, 2022; size 1885 bytes
  SHA-256 checksum c4d7f4fd83f6d35e27730ac3485e2c642c960d7916365fcf670aea447fdf360c
  Compiled from "Tuple3Zipped.scala"
public interface scala.runtime.ZippedIterable3<El1 extends java.lang.Object, El2 extends java.lang.Object, El3 extends java.lang.Object>
  minor version: 0
  major version: 52
  flags: (0x0601) ACC_PUBLIC, ACC_INTERFACE, ACC_ABSTRACT
  this_class: #2                          // scala/runtime/ZippedIterable3
  super_class: #5                         // java/lang/Object
  interfaces: 0, fields: 0, methods: 3, attributes: 7
Constant pool:
   #1 = Utf8               scala/runtime/ZippedIterable3
   #2 = Class              #1             // scala/runtime/ZippedIterable3
   #3 = Utf8               <El1:Ljava/lang/Object;El2:Ljava/lang/Object;El3:Ljava/lang/Object;>Ljava/lang/Object;
   #4 = Utf8               java/lang/Object
   #5 = Class              #4             // java/lang/Object
   #6 = Utf8               Tuple3Zipped.scala
   #7 = Utf8               Lscala/reflect/ScalaSignature;
   #8 = Utf8               bytes
   #9 = Utf8               \u0006\u0005]3qa\u0002\u0005\u0011\u0002G\u0005Q\u0002C\u0003\u0014\u0001\u0019\u0005A\u0003C\u0003.\u0001\u0019\u0005afB\u0003=\u0011!\u0005QHB\u0003\b\u0011!\u0005q\bC\u0003D\t\u0011\u0005A\tC\u0003F\t\u0011\raIA\b[SB\u0004X\rZ%uKJ\f\'\r\\34\u0015\tI!\"A\u0004sk:$\u0018.\\3\u000b\u0003-\tQa]2bY\u0006\u001c\u0001!\u0006\u0003\u000fC!Z3C\u0001\u0001\u0010!\t\u0001\u0012#D\u0001\u000b\u0013\t\u0011\"BA\u0002B]f\f\u0001\"\u001b;fe\u0006$xN]\u000b\u0002+A\u0019a#\u0007\u000f\u000f\u0005A9\u0012B\u0001\r\u000b\u0003\u001d\u0001\u0018mY6bO\u0016L!AG\u000e\u0003\u0011%#XM]1u_JT!\u0001\u0007\u0006\u0011\u000bAird\n\u0016\n\u0005yQ!A\u0002+va2,7\u0007\u0005\u0002!C1\u0001AA\u0002\u0012\u0001\t\u000b\u00071EA\u0002FYF\n\"\u0001J\b\u0011\u0005A)\u0013B\u0001\u0014\u000b\u0005\u001dqu\u000e\u001e5j]\u001e\u0004\"\u0001\t\u0015\u0005\r%\u0002AQ1\u0001$\u0005\r)EN\r\t\u0003A-\"a\u0001\f\u0001\u0005\u0006\u0004\u0019#aA#mg\u00059\u0011n]#naRLX#A\u0018\u0011\u0005A\u0001\u0014BA\u0019\u000b\u0005\u001d\u0011un\u001c7fC:Dc\u0001A\u001a7oeR\u0004C\u0001\t5\u0013\t)$B\u0001\u0006eKB\u0014XmY1uK\u0012\fq!\\3tg\u0006<W-I\u00019\u0003y)6/\u001a\u0011tG\u0006d\u0017ML2pY2,7\r^5p]:b\u0015M_=[SB\u001cd&A\u0003tS:\u001cW-I\u0001<\u0003\u0019\u0011d&M\u001a/a\u0005y!,\u001b9qK\u0012LE/\u001a:bE2,7\u0007\u0005\u0002?\t5\t\u0001b\u0005\u0002\u0005\u0001B\u0011\u0001#Q\u0005\u0003\u0005*\u0011a!\u00118z%\u00164\u0017A\u0002\u001fj]&$h\bF\u0001>\u0003eQ\u0018\u000e\u001d9fI&#XM]1cY\u0016\u001cDk\\%uKJ\f\'\r\\3\u0016\t\u001dku*\u0015\u000b\u0003\u0011J\u00032AF%L\u0013\tQ5D\u0001\u0005Ji\u0016\u0014\u0018M\u00197f!\u0015\u0001R\u0004\u0014(Q!\t\u0001S\nB\u0003#\r\t\u00071\u0005\u0005\u0002!\u001f\u0012)\u0011F\u0002b\u0001GA\u0011\u0001%\u0015\u0003\u0006Y\u0019\u0011\ra\t\u0005\u0006\'\u001a\u0001\r\u0001V\u0001\u0003uj\u0004RA\u0010\u0001M\u001dBCc\u0001B\u001a7oeR\u0004FB\u00024m]J$\b
  #10 = Utf8               scala/runtime/ZippedIterable3$$anon$1
  #11 = Class              #10            // scala/runtime/ZippedIterable3$$anon$1
  #12 = Utf8               zippedIterable3ToIterable
  #13 = Utf8               (Lscala/runtime/ZippedIterable3;)Lscala/collection/Iterable;
  #14 = Utf8               <El1:Ljava/lang/Object;El2:Ljava/lang/Object;El3:Ljava/lang/Object;>(Lscala/runtime/ZippedIterable3<TEl1;TEl2;TEl3;>;)Lscala/collection/Iterable<Lscala/Tuple3<TEl1;TEl2;TEl3;>;>;
  #15 = Utf8               zz
  #16 = Utf8               scala/runtime/ZippedIterable3$
  #17 = Class              #16            // scala/runtime/ZippedIterable3$
  #18 = Utf8               MODULE$
  #19 = Utf8               Lscala/runtime/ZippedIterable3$;
  #20 = NameAndType        #18:#19        // MODULE$:Lscala/runtime/ZippedIterable3$;
  #21 = Fieldref           #17.#20        // scala/runtime/ZippedIterable3$.MODULE$:Lscala/runtime/ZippedIterable3$;
  #22 = Utf8               <init>
  #23 = Utf8               (Lscala/runtime/ZippedIterable3;)V
  #24 = NameAndType        #22:#23        // "<init>":(Lscala/runtime/ZippedIterable3;)V
  #25 = Methodref          #11.#24        // scala/runtime/ZippedIterable3$$anon$1."<init>":(Lscala/runtime/ZippedIterable3;)V
  #26 = Utf8               Lscala/runtime/ZippedIterable3;
  #27 = Utf8               iterator
  #28 = Utf8               ()Lscala/collection/Iterator;
  #29 = Utf8               ()Lscala/collection/Iterator<Lscala/Tuple3<TEl1;TEl2;TEl3;>;>;
  #30 = Utf8               isEmpty
  #31 = Utf8               ()Z
  #32 = Utf8               Code
  #33 = Utf8               LineNumberTable
  #34 = Utf8               LocalVariableTable
  #35 = Utf8               Signature
  #36 = Utf8               MethodParameters
  #37 = Utf8               InnerClasses
  #38 = Utf8               SourceFile
  #39 = Utf8               Deprecated
  #40 = Utf8               RuntimeVisibleAnnotations
  #41 = Utf8               ScalaInlineInfo
  #42 = Utf8               ScalaSig
{
  public static <El1 extends java.lang.Object, El2 extends java.lang.Object, El3 extends java.lang.Object> scala.collection.Iterable<scala.Tuple3<El1, El2, El3>> zippedIterable3ToIterable(scala.runtime.ZippedIterable3<El1, El2, El3>);
    descriptor: (Lscala/runtime/ZippedIterable3;)Lscala/collection/Iterable;
    flags: (0x0009) ACC_PUBLIC, ACC_STATIC
    Code:
      stack=3, locals=1, args_size=1
         0: getstatic     #21                 // Field scala/runtime/ZippedIterable3$.MODULE$:Lscala/runtime/ZippedIterable3$;
         3: pop
         4: new           #11                 // class scala/runtime/ZippedIterable3$$anon$1
         7: dup
         8: aload_0
         9: invokespecial #25                 // Method scala/runtime/ZippedIterable3$$anon$1."<init>":(Lscala/runtime/ZippedIterable3;)V
        12: areturn
      LineNumberTable:
        line 34: 4
      LocalVariableTable:
        Start  Length  Slot  Name   Signature
            0      13     0    zz   Lscala/runtime/ZippedIterable3;
    Signature: #14                          // <El1:Ljava/lang/Object;El2:Ljava/lang/Object;El3:Ljava/lang/Object;>(Lscala/runtime/ZippedIterable3<TEl1;TEl2;TEl3;>;)Lscala/collection/Iterable<Lscala/Tuple3<TEl1;TEl2;TEl3;>;>;
    MethodParameters:
      Name                           Flags
      zz                             final

  public abstract scala.collection.Iterator<scala.Tuple3<El1, El2, El3>> iterator();
    descriptor: ()Lscala/collection/Iterator;
    flags: (0x0401) ACC_PUBLIC, ACC_ABSTRACT
    Signature: #29                          // ()Lscala/collection/Iterator<Lscala/Tuple3<TEl1;TEl2;TEl3;>;>;

  public abstract boolean isEmpty();
    descriptor: ()Z
    flags: (0x0401) ACC_PUBLIC, ACC_ABSTRACT
}
InnerClasses:
  public final #11;                       // class scala/runtime/ZippedIterable3$$anon$1
Signature: #3                           // <El1:Ljava/lang/Object;El2:Ljava/lang/Object;El3:Ljava/lang/Object;>Ljava/lang/Object;
SourceFile: "Tuple3Zipped.scala"
Deprecated: true
RuntimeVisibleAnnotations:
  0: #7(#8=s#9)
    scala.reflect.ScalaSignature(
      bytes="\u0006\u0005]3qa\u0002\u0005\u0011\u0002G\u0005Q\u0002C\u0003\u0014\u0001\u0019\u0005A\u0003C\u0003.\u0001\u0019\u0005afB\u0003=\u0011!\u0005QHB\u0003\b\u0011!\u0005q\bC\u0003D\t\u0011\u0005A\tC\u0003F\t\u0011\raIA\b[SB\u0004X\rZ%uKJ\f\'\r\\34\u0015\tI!\"A\u0004sk:$\u0018.\\3\u000b\u0003-\tQa]2bY\u0006\u001c\u0001!\u0006\u0003\u000fC!Z3C\u0001\u0001\u0010!\t\u0001\u0012#D\u0001\u000b\u0013\t\u0011\"BA\u0002B]f\f\u0001\"\u001b;fe\u0006$xN]\u000b\u0002+A\u0019a#\u0007\u000f\u000f\u0005A9\u0012B\u0001\r\u000b\u0003\u001d\u0001\u0018mY6bO\u0016L!AG\u000e\u0003\u0011%#XM]1u_JT!\u0001\u0007\u0006\u0011\u000bAird\n\u0016\n\u0005yQ!A\u0002+va2,7\u0007\u0005\u0002!C1\u0001AA\u0002\u0012\u0001\t\u000b\u00071EA\u0002FYF\n\"\u0001J\b\u0011\u0005A)\u0013B\u0001\u0014\u000b\u0005\u001dqu\u000e\u001e5j]\u001e\u0004\"\u0001\t\u0015\u0005\r%\u0002AQ1\u0001$\u0005\r)EN\r\t\u0003A-\"a\u0001\f\u0001\u0005\u0006\u0004\u0019#aA#mg\u00059\u0011n]#naRLX#A\u0018\u0011\u0005A\u0001\u0014BA\u0019\u000b\u0005\u001d\u0011un\u001c7fC:Dc\u0001A\u001a7oeR\u0004C\u0001\t5\u0013\t)$B\u0001\u0006eKB\u0014XmY1uK\u0012\fq!\\3tg\u0006<W-I\u00019\u0003y)6/\u001a\u0011tG\u0006d\u0017ML2pY2,7\r^5p]:b\u0015M_=[SB\u001cd&A\u0003tS:\u001cW-I\u0001<\u0003\u0019\u0011d&M\u001a/a\u0005y!,\u001b9qK\u0012LE/\u001a:bE2,7\u0007\u0005\u0002?\t5\t\u0001b\u0005\u0002\u0005\u0001B\u0011\u0001#Q\u0005\u0003\u0005*\u0011a!\u00118z%\u00164\u0017A\u0002\u001fj]&$h\bF\u0001>\u0003eQ\u0018\u000e\u001d9fI&#XM]1cY\u0016\u001cDk\\%uKJ\f\'\r\\3\u0016\t\u001dku*\u0015\u000b\u0003\u0011J\u00032AF%L\u0013\tQ5D\u0001\u0005Ji\u0016\u0014\u0018M\u00197f!\u0015\u0001R\u0004\u0014(Q!\t\u0001S\nB\u0003#\r\t\u00071\u0005\u0005\u0002!\u001f\u0012)\u0011F\u0002b\u0001GA\u0011\u0001%\u0015\u0003\u0006Y\u0019\u0011\ra\t\u0005\u0006\'\u001a\u0001\r\u0001V\u0001\u0003uj\u0004RA\u0010\u0001M\u001dBCc\u0001B\u001a7oeR\u0004FB\u00024m]J$\b"
    )
  ScalaInlineInfo: length = 0xE (unknown attribute)
   01 00 00 02 00 1E 00 1F 00 00 1B 00 1C 00
  ScalaSig: length = 0x3 (unknown attribute)
   05 02 00
