Classfile /Users/mw/Projects/slang-braindump/.jar/jar11/assemble/slang-braindump/assemble/content/com/fasterxml/jackson/databind/exc/InvalidFormatException.class
  Last modified May 29, 2022; size 2578 bytes
  SHA-256 checksum d11cc7b9e7a359bf9c6e81b6a02bb32066cccb29f945d162fcab75cbab300cd0
  Compiled from "InvalidFormatException.java"
public class com.fasterxml.jackson.databind.exc.InvalidFormatException extends com.fasterxml.jackson.databind.exc.MismatchedInputException
  minor version: 0
  major version: 52
  flags: (0x0021) ACC_PUBLIC, ACC_SUPER
  this_class: #6                          // com/fasterxml/jackson/databind/exc/InvalidFormatException
  super_class: #8                         // com/fasterxml/jackson/databind/exc/MismatchedInputException
  interfaces: 0, fields: 2, methods: 5, attributes: 1
Constant pool:
   #1 = Methodref          #8.#50         // com/fasterxml/jackson/databind/exc/MismatchedInputException."<init>":(Lcom/fasterxml/jackson/core/JsonParser;Ljava/lang/String;)V
   #2 = Fieldref           #6.#51         // com/fasterxml/jackson/databind/exc/InvalidFormatException._value:Ljava/lang/Object;
   #3 = Fieldref           #6.#52         // com/fasterxml/jackson/databind/exc/InvalidFormatException._targetType:Ljava/lang/Class;
   #4 = Methodref          #8.#53         // com/fasterxml/jackson/databind/exc/MismatchedInputException."<init>":(Lcom/fasterxml/jackson/core/JsonParser;Ljava/lang/String;Lcom/fasterxml/jackson/core/JsonLocation;)V
   #5 = Methodref          #8.#54         // com/fasterxml/jackson/databind/exc/MismatchedInputException."<init>":(Lcom/fasterxml/jackson/core/JsonParser;Ljava/lang/String;Ljava/lang/Class;)V
   #6 = Class              #55            // com/fasterxml/jackson/databind/exc/InvalidFormatException
   #7 = Methodref          #6.#56         // com/fasterxml/jackson/databind/exc/InvalidFormatException."<init>":(Lcom/fasterxml/jackson/core/JsonParser;Ljava/lang/String;Ljava/lang/Object;Ljava/lang/Class;)V
   #8 = Class              #57            // com/fasterxml/jackson/databind/exc/MismatchedInputException
   #9 = Utf8               serialVersionUID
  #10 = Utf8               J
  #11 = Utf8               ConstantValue
  #12 = Long               1l
  #14 = Utf8               _value
  #15 = Utf8               Ljava/lang/Object;
  #16 = Utf8               <init>
  #17 = Utf8               (Ljava/lang/String;Ljava/lang/Object;Ljava/lang/Class;)V
  #18 = Utf8               Code
  #19 = Utf8               LineNumberTable
  #20 = Utf8               LocalVariableTable
  #21 = Utf8               this
  #22 = Utf8               Lcom/fasterxml/jackson/databind/exc/InvalidFormatException;
  #23 = Utf8               msg
  #24 = Utf8               Ljava/lang/String;
  #25 = Utf8               value
  #26 = Utf8               targetType
  #27 = Utf8               Ljava/lang/Class;
  #28 = Utf8               LocalVariableTypeTable
  #29 = Utf8               Ljava/lang/Class<*>;
  #30 = Utf8               Deprecated
  #31 = Utf8               Signature
  #32 = Utf8               (Ljava/lang/String;Ljava/lang/Object;Ljava/lang/Class<*>;)V
  #33 = Utf8               RuntimeVisibleAnnotations
  #34 = Utf8               Ljava/lang/Deprecated;
  #35 = Utf8               (Ljava/lang/String;Lcom/fasterxml/jackson/core/JsonLocation;Ljava/lang/Object;Ljava/lang/Class;)V
  #36 = Utf8               loc
  #37 = Utf8               Lcom/fasterxml/jackson/core/JsonLocation;
  #38 = Utf8               (Ljava/lang/String;Lcom/fasterxml/jackson/core/JsonLocation;Ljava/lang/Object;Ljava/lang/Class<*>;)V
  #39 = Utf8               (Lcom/fasterxml/jackson/core/JsonParser;Ljava/lang/String;Ljava/lang/Object;Ljava/lang/Class;)V
  #40 = Utf8               p
  #41 = Utf8               Lcom/fasterxml/jackson/core/JsonParser;
  #42 = Utf8               (Lcom/fasterxml/jackson/core/JsonParser;Ljava/lang/String;Ljava/lang/Object;Ljava/lang/Class<*>;)V
  #43 = Utf8               from
  #44 = Utf8               (Lcom/fasterxml/jackson/core/JsonParser;Ljava/lang/String;Ljava/lang/Object;Ljava/lang/Class;)Lcom/fasterxml/jackson/databind/exc/InvalidFormatException;
  #45 = Utf8               (Lcom/fasterxml/jackson/core/JsonParser;Ljava/lang/String;Ljava/lang/Object;Ljava/lang/Class<*>;)Lcom/fasterxml/jackson/databind/exc/InvalidFormatException;
  #46 = Utf8               getValue
  #47 = Utf8               ()Ljava/lang/Object;
  #48 = Utf8               SourceFile
  #49 = Utf8               InvalidFormatException.java
  #50 = NameAndType        #16:#58        // "<init>":(Lcom/fasterxml/jackson/core/JsonParser;Ljava/lang/String;)V
  #51 = NameAndType        #14:#15        // _value:Ljava/lang/Object;
  #52 = NameAndType        #59:#27        // _targetType:Ljava/lang/Class;
  #53 = NameAndType        #16:#60        // "<init>":(Lcom/fasterxml/jackson/core/JsonParser;Ljava/lang/String;Lcom/fasterxml/jackson/core/JsonLocation;)V
  #54 = NameAndType        #16:#61        // "<init>":(Lcom/fasterxml/jackson/core/JsonParser;Ljava/lang/String;Ljava/lang/Class;)V
  #55 = Utf8               com/fasterxml/jackson/databind/exc/InvalidFormatException
  #56 = NameAndType        #16:#39        // "<init>":(Lcom/fasterxml/jackson/core/JsonParser;Ljava/lang/String;Ljava/lang/Object;Ljava/lang/Class;)V
  #57 = Utf8               com/fasterxml/jackson/databind/exc/MismatchedInputException
  #58 = Utf8               (Lcom/fasterxml/jackson/core/JsonParser;Ljava/lang/String;)V
  #59 = Utf8               _targetType
  #60 = Utf8               (Lcom/fasterxml/jackson/core/JsonParser;Ljava/lang/String;Lcom/fasterxml/jackson/core/JsonLocation;)V
  #61 = Utf8               (Lcom/fasterxml/jackson/core/JsonParser;Ljava/lang/String;Ljava/lang/Class;)V
{
  private static final long serialVersionUID;
    descriptor: J
    flags: (0x001a) ACC_PRIVATE, ACC_STATIC, ACC_FINAL
    ConstantValue: long 1l

  protected final java.lang.Object _value;
    descriptor: Ljava/lang/Object;
    flags: (0x0014) ACC_PROTECTED, ACC_FINAL

  public com.fasterxml.jackson.databind.exc.InvalidFormatException(java.lang.String, java.lang.Object, java.lang.Class<?>);
    descriptor: (Ljava/lang/String;Ljava/lang/Object;Ljava/lang/Class;)V
    flags: (0x0001) ACC_PUBLIC
    Code:
      stack=3, locals=4, args_size=4
         0: aload_0
         1: aconst_null
         2: aload_1
         3: invokespecial #1                  // Method com/fasterxml/jackson/databind/exc/MismatchedInputException."<init>":(Lcom/fasterxml/jackson/core/JsonParser;Ljava/lang/String;)V
         6: aload_0
         7: aload_2
         8: putfield      #2                  // Field _value:Ljava/lang/Object;
        11: aload_0
        12: aload_3
        13: putfield      #3                  // Field _targetType:Ljava/lang/Class;
        16: return
      LineNumberTable:
        line 37: 0
        line 38: 6
        line 39: 11
        line 40: 16
      LocalVariableTable:
        Start  Length  Slot  Name   Signature
            0      17     0  this   Lcom/fasterxml/jackson/databind/exc/InvalidFormatException;
            0      17     1   msg   Ljava/lang/String;
            0      17     2 value   Ljava/lang/Object;
            0      17     3 targetType   Ljava/lang/Class;
      LocalVariableTypeTable:
        Start  Length  Slot  Name   Signature
            0      17     3 targetType   Ljava/lang/Class<*>;
    Deprecated: true
    Signature: #32                          // (Ljava/lang/String;Ljava/lang/Object;Ljava/lang/Class<*>;)V
    RuntimeVisibleAnnotations:
      0: #34()
        java.lang.Deprecated

  public com.fasterxml.jackson.databind.exc.InvalidFormatException(java.lang.String, com.fasterxml.jackson.core.JsonLocation, java.lang.Object, java.lang.Class<?>);
    descriptor: (Ljava/lang/String;Lcom/fasterxml/jackson/core/JsonLocation;Ljava/lang/Object;Ljava/lang/Class;)V
    flags: (0x0001) ACC_PUBLIC
    Code:
      stack=4, locals=5, args_size=5
         0: aload_0
         1: aconst_null
         2: aload_1
         3: aload_2
         4: invokespecial #4                  // Method com/fasterxml/jackson/databind/exc/MismatchedInputException."<init>":(Lcom/fasterxml/jackson/core/JsonParser;Ljava/lang/String;Lcom/fasterxml/jackson/core/JsonLocation;)V
         7: aload_0
         8: aload_3
         9: putfield      #2                  // Field _value:Ljava/lang/Object;
        12: aload_0
        13: aload         4
        15: putfield      #3                  // Field _targetType:Ljava/lang/Class;
        18: return
      LineNumberTable:
        line 49: 0
        line 50: 7
        line 51: 12
        line 52: 18
      LocalVariableTable:
        Start  Length  Slot  Name   Signature
            0      19     0  this   Lcom/fasterxml/jackson/databind/exc/InvalidFormatException;
            0      19     1   msg   Ljava/lang/String;
            0      19     2   loc   Lcom/fasterxml/jackson/core/JsonLocation;
            0      19     3 value   Ljava/lang/Object;
            0      19     4 targetType   Ljava/lang/Class;
      LocalVariableTypeTable:
        Start  Length  Slot  Name   Signature
            0      19     4 targetType   Ljava/lang/Class<*>;
    Deprecated: true
    Signature: #38                          // (Ljava/lang/String;Lcom/fasterxml/jackson/core/JsonLocation;Ljava/lang/Object;Ljava/lang/Class<*>;)V
    RuntimeVisibleAnnotations:
      0: #34()
        java.lang.Deprecated

  public com.fasterxml.jackson.databind.exc.InvalidFormatException(com.fasterxml.jackson.core.JsonParser, java.lang.String, java.lang.Object, java.lang.Class<?>);
    descriptor: (Lcom/fasterxml/jackson/core/JsonParser;Ljava/lang/String;Ljava/lang/Object;Ljava/lang/Class;)V
    flags: (0x0001) ACC_PUBLIC
    Code:
      stack=4, locals=5, args_size=5
         0: aload_0
         1: aload_1
         2: aload_2
         3: aload         4
         5: invokespecial #5                  // Method com/fasterxml/jackson/databind/exc/MismatchedInputException."<init>":(Lcom/fasterxml/jackson/core/JsonParser;Ljava/lang/String;Ljava/lang/Class;)V
         8: aload_0
         9: aload_3
        10: putfield      #2                  // Field _value:Ljava/lang/Object;
        13: return
      LineNumberTable:
        line 60: 0
        line 61: 8
        line 62: 13
      LocalVariableTable:
        Start  Length  Slot  Name   Signature
            0      14     0  this   Lcom/fasterxml/jackson/databind/exc/InvalidFormatException;
            0      14     1     p   Lcom/fasterxml/jackson/core/JsonParser;
            0      14     2   msg   Ljava/lang/String;
            0      14     3 value   Ljava/lang/Object;
            0      14     4 targetType   Ljava/lang/Class;
      LocalVariableTypeTable:
        Start  Length  Slot  Name   Signature
            0      14     4 targetType   Ljava/lang/Class<*>;
    Signature: #42                          // (Lcom/fasterxml/jackson/core/JsonParser;Ljava/lang/String;Ljava/lang/Object;Ljava/lang/Class<*>;)V

  public static com.fasterxml.jackson.databind.exc.InvalidFormatException from(com.fasterxml.jackson.core.JsonParser, java.lang.String, java.lang.Object, java.lang.Class<?>);
    descriptor: (Lcom/fasterxml/jackson/core/JsonParser;Ljava/lang/String;Ljava/lang/Object;Ljava/lang/Class;)Lcom/fasterxml/jackson/databind/exc/InvalidFormatException;
    flags: (0x0009) ACC_PUBLIC, ACC_STATIC
    Code:
      stack=6, locals=4, args_size=4
         0: new           #6                  // class com/fasterxml/jackson/databind/exc/InvalidFormatException
         3: dup
         4: aload_0
         5: aload_1
         6: aload_2
         7: aload_3
         8: invokespecial #7                  // Method "<init>":(Lcom/fasterxml/jackson/core/JsonParser;Ljava/lang/String;Ljava/lang/Object;Ljava/lang/Class;)V
        11: areturn
      LineNumberTable:
        line 67: 0
      LocalVariableTable:
        Start  Length  Slot  Name   Signature
            0      12     0     p   Lcom/fasterxml/jackson/core/JsonParser;
            0      12     1   msg   Ljava/lang/String;
            0      12     2 value   Ljava/lang/Object;
            0      12     3 targetType   Ljava/lang/Class;
      LocalVariableTypeTable:
        Start  Length  Slot  Name   Signature
            0      12     3 targetType   Ljava/lang/Class<*>;
    Signature: #45                          // (Lcom/fasterxml/jackson/core/JsonParser;Ljava/lang/String;Ljava/lang/Object;Ljava/lang/Class<*>;)Lcom/fasterxml/jackson/databind/exc/InvalidFormatException;

  public java.lang.Object getValue();
    descriptor: ()Ljava/lang/Object;
    flags: (0x0001) ACC_PUBLIC
    Code:
      stack=1, locals=1, args_size=1
         0: aload_0
         1: getfield      #2                  // Field _value:Ljava/lang/Object;
         4: areturn
      LineNumberTable:
        line 83: 0
      LocalVariableTable:
        Start  Length  Slot  Name   Signature
            0       5     0  this   Lcom/fasterxml/jackson/databind/exc/InvalidFormatException;
}
SourceFile: "InvalidFormatException.java"
