Classfile /Users/mw/Projects/slang-braindump/.jar/jar8/assemble/slang-braindump/assemble/content/com/fasterxml/jackson/databind/ser/AnyGetterWriter.class
  Last modified May 29, 2022; size 4871 bytes
  SHA-256 checksum a3bb8a207e99a86d0f12871dadb581630a060aa10af3e7e022c6a081577971a8
  Compiled from "AnyGetterWriter.java"
public class com.fasterxml.jackson.databind.ser.AnyGetterWriter
  minor version: 0
  major version: 52
  flags: (0x0021) ACC_PUBLIC, ACC_SUPER
  this_class: #26                         // com/fasterxml/jackson/databind/ser/AnyGetterWriter
  super_class: #14                        // java/lang/Object
  interfaces: 0, fields: 4, methods: 5, attributes: 1
Constant pool:
    #1 = Methodref          #14.#81       // java/lang/Object."<init>":()V
    #2 = Fieldref           #26.#82       // com/fasterxml/jackson/databind/ser/AnyGetterWriter._accessor:Lcom/fasterxml/jackson/databind/introspect/AnnotatedMember;
    #3 = Fieldref           #26.#83       // com/fasterxml/jackson/databind/ser/AnyGetterWriter._property:Lcom/fasterxml/jackson/databind/BeanProperty;
    #4 = Fieldref           #26.#84       // com/fasterxml/jackson/databind/ser/AnyGetterWriter._serializer:Lcom/fasterxml/jackson/databind/JsonSerializer;
    #5 = Class              #85           // com/fasterxml/jackson/databind/ser/std/MapSerializer
    #6 = Fieldref           #26.#86       // com/fasterxml/jackson/databind/ser/AnyGetterWriter._mapSerializer:Lcom/fasterxml/jackson/databind/ser/std/MapSerializer;
    #7 = Fieldref           #87.#88       // com/fasterxml/jackson/databind/MapperFeature.OVERRIDE_PUBLIC_ACCESS_MODIFIERS:Lcom/fasterxml/jackson/databind/MapperFeature;
    #8 = Methodref          #89.#90       // com/fasterxml/jackson/databind/SerializationConfig.isEnabled:(Lcom/fasterxml/jackson/databind/MapperFeature;)Z
    #9 = Methodref          #91.#92       // com/fasterxml/jackson/databind/introspect/AnnotatedMember.fixAccess:(Z)V
   #10 = Methodref          #91.#93       // com/fasterxml/jackson/databind/introspect/AnnotatedMember.getValue:(Ljava/lang/Object;)Ljava/lang/Object;
   #11 = Class              #94           // java/util/Map
   #12 = InterfaceMethodref #95.#96       // com/fasterxml/jackson/databind/BeanProperty.getType:()Lcom/fasterxml/jackson/databind/JavaType;
   #13 = String             #97           // Value returned by \'any-getter\' %s() not java.util.Map but %s
   #14 = Class              #98           // java/lang/Object
   #15 = Methodref          #91.#99       // com/fasterxml/jackson/databind/introspect/AnnotatedMember.getName:()Ljava/lang/String;
   #16 = Methodref          #14.#100      // java/lang/Object.getClass:()Ljava/lang/Class;
   #17 = Methodref          #101.#99      // java/lang/Class.getName:()Ljava/lang/String;
   #18 = Methodref          #102.#103     // java/lang/String.format:(Ljava/lang/String;[Ljava/lang/Object;)Ljava/lang/String;
   #19 = Methodref          #104.#105     // com/fasterxml/jackson/databind/SerializerProvider.reportBadDefinition:(Lcom/fasterxml/jackson/databind/JavaType;Ljava/lang/String;)Ljava/lang/Object;
   #20 = Methodref          #5.#106       // com/fasterxml/jackson/databind/ser/std/MapSerializer.serializeWithoutTypeInfo:(Ljava/util/Map;Lcom/fasterxml/jackson/core/JsonGenerator;Lcom/fasterxml/jackson/databind/SerializerProvider;)V
   #21 = Methodref          #107.#108     // com/fasterxml/jackson/databind/JsonSerializer.serialize:(Ljava/lang/Object;Lcom/fasterxml/jackson/core/JsonGenerator;Lcom/fasterxml/jackson/databind/SerializerProvider;)V
   #22 = String             #109          // Value returned by \'any-getter\' (%s()) not java.util.Map but %s
   #23 = Methodref          #5.#110       // com/fasterxml/jackson/databind/ser/std/MapSerializer.serializeFilteredAnyProperties:(Lcom/fasterxml/jackson/databind/SerializerProvider;Lcom/fasterxml/jackson/core/JsonGenerator;Ljava/lang/Object;Ljava/util/Map;Lcom/fasterxml/jackson/databind/ser/PropertyFilter;Ljava/lang/Object;)V
   #24 = Class              #111          // com/fasterxml/jackson/databind/ser/ContextualSerializer
   #25 = Methodref          #104.#112     // com/fasterxml/jackson/databind/SerializerProvider.handlePrimaryContextualization:(Lcom/fasterxml/jackson/databind/JsonSerializer;Lcom/fasterxml/jackson/databind/BeanProperty;)Lcom/fasterxml/jackson/databind/JsonSerializer;
   #26 = Class              #113          // com/fasterxml/jackson/databind/ser/AnyGetterWriter
   #27 = Utf8               _property
   #28 = Utf8               Lcom/fasterxml/jackson/databind/BeanProperty;
   #29 = Utf8               _accessor
   #30 = Utf8               Lcom/fasterxml/jackson/databind/introspect/AnnotatedMember;
   #31 = Utf8               _serializer
   #32 = Utf8               Lcom/fasterxml/jackson/databind/JsonSerializer;
   #33 = Utf8               Signature
   #34 = Utf8               Lcom/fasterxml/jackson/databind/JsonSerializer<Ljava/lang/Object;>;
   #35 = Utf8               _mapSerializer
   #36 = Utf8               Lcom/fasterxml/jackson/databind/ser/std/MapSerializer;
   #37 = Utf8               <init>
   #38 = Utf8               (Lcom/fasterxml/jackson/databind/BeanProperty;Lcom/fasterxml/jackson/databind/introspect/AnnotatedMember;Lcom/fasterxml/jackson/databind/JsonSerializer;)V
   #39 = Utf8               Code
   #40 = Utf8               LineNumberTable
   #41 = Utf8               LocalVariableTable
   #42 = Utf8               this
   #43 = Utf8               Lcom/fasterxml/jackson/databind/ser/AnyGetterWriter;
   #44 = Utf8               property
   #45 = Utf8               accessor
   #46 = Utf8               serializer
   #47 = Utf8               LocalVariableTypeTable
   #48 = Utf8               Lcom/fasterxml/jackson/databind/JsonSerializer<*>;
   #49 = Utf8               StackMapTable
   #50 = Class              #113          // com/fasterxml/jackson/databind/ser/AnyGetterWriter
   #51 = Class              #114          // com/fasterxml/jackson/databind/BeanProperty
   #52 = Class              #115          // com/fasterxml/jackson/databind/introspect/AnnotatedMember
   #53 = Class              #116          // com/fasterxml/jackson/databind/JsonSerializer
   #54 = Utf8               (Lcom/fasterxml/jackson/databind/BeanProperty;Lcom/fasterxml/jackson/databind/introspect/AnnotatedMember;Lcom/fasterxml/jackson/databind/JsonSerializer<*>;)V
   #55 = Utf8               fixAccess
   #56 = Utf8               (Lcom/fasterxml/jackson/databind/SerializationConfig;)V
   #57 = Utf8               config
   #58 = Utf8               Lcom/fasterxml/jackson/databind/SerializationConfig;
   #59 = Utf8               getAndSerialize
   #60 = Utf8               (Ljava/lang/Object;Lcom/fasterxml/jackson/core/JsonGenerator;Lcom/fasterxml/jackson/databind/SerializerProvider;)V
   #61 = Utf8               bean
   #62 = Utf8               Ljava/lang/Object;
   #63 = Utf8               gen
   #64 = Utf8               Lcom/fasterxml/jackson/core/JsonGenerator;
   #65 = Utf8               provider
   #66 = Utf8               Lcom/fasterxml/jackson/databind/SerializerProvider;
   #67 = Utf8               value
   #68 = Class              #98           // java/lang/Object
   #69 = Utf8               Exceptions
   #70 = Class              #117          // java/lang/Exception
   #71 = Utf8               getAndFilter
   #72 = Utf8               (Ljava/lang/Object;Lcom/fasterxml/jackson/core/JsonGenerator;Lcom/fasterxml/jackson/databind/SerializerProvider;Lcom/fasterxml/jackson/databind/ser/PropertyFilter;)V
   #73 = Utf8               filter
   #74 = Utf8               Lcom/fasterxml/jackson/databind/ser/PropertyFilter;
   #75 = Utf8               resolve
   #76 = Utf8               (Lcom/fasterxml/jackson/databind/SerializerProvider;)V
   #77 = Utf8               ser
   #78 = Class              #118          // com/fasterxml/jackson/databind/JsonMappingException
   #79 = Utf8               SourceFile
   #80 = Utf8               AnyGetterWriter.java
   #81 = NameAndType        #37:#119      // "<init>":()V
   #82 = NameAndType        #29:#30       // _accessor:Lcom/fasterxml/jackson/databind/introspect/AnnotatedMember;
   #83 = NameAndType        #27:#28       // _property:Lcom/fasterxml/jackson/databind/BeanProperty;
   #84 = NameAndType        #31:#32       // _serializer:Lcom/fasterxml/jackson/databind/JsonSerializer;
   #85 = Utf8               com/fasterxml/jackson/databind/ser/std/MapSerializer
   #86 = NameAndType        #35:#36       // _mapSerializer:Lcom/fasterxml/jackson/databind/ser/std/MapSerializer;
   #87 = Class              #120          // com/fasterxml/jackson/databind/MapperFeature
   #88 = NameAndType        #121:#122     // OVERRIDE_PUBLIC_ACCESS_MODIFIERS:Lcom/fasterxml/jackson/databind/MapperFeature;
   #89 = Class              #123          // com/fasterxml/jackson/databind/SerializationConfig
   #90 = NameAndType        #124:#125     // isEnabled:(Lcom/fasterxml/jackson/databind/MapperFeature;)Z
   #91 = Class              #115          // com/fasterxml/jackson/databind/introspect/AnnotatedMember
   #92 = NameAndType        #55:#126      // fixAccess:(Z)V
   #93 = NameAndType        #127:#128     // getValue:(Ljava/lang/Object;)Ljava/lang/Object;
   #94 = Utf8               java/util/Map
   #95 = Class              #114          // com/fasterxml/jackson/databind/BeanProperty
   #96 = NameAndType        #129:#130     // getType:()Lcom/fasterxml/jackson/databind/JavaType;
   #97 = Utf8               Value returned by \'any-getter\' %s() not java.util.Map but %s
   #98 = Utf8               java/lang/Object
   #99 = NameAndType        #131:#132     // getName:()Ljava/lang/String;
  #100 = NameAndType        #133:#134     // getClass:()Ljava/lang/Class;
  #101 = Class              #135          // java/lang/Class
  #102 = Class              #136          // java/lang/String
  #103 = NameAndType        #137:#138     // format:(Ljava/lang/String;[Ljava/lang/Object;)Ljava/lang/String;
  #104 = Class              #139          // com/fasterxml/jackson/databind/SerializerProvider
  #105 = NameAndType        #140:#141     // reportBadDefinition:(Lcom/fasterxml/jackson/databind/JavaType;Ljava/lang/String;)Ljava/lang/Object;
  #106 = NameAndType        #142:#143     // serializeWithoutTypeInfo:(Ljava/util/Map;Lcom/fasterxml/jackson/core/JsonGenerator;Lcom/fasterxml/jackson/databind/SerializerProvider;)V
  #107 = Class              #116          // com/fasterxml/jackson/databind/JsonSerializer
  #108 = NameAndType        #144:#60      // serialize:(Ljava/lang/Object;Lcom/fasterxml/jackson/core/JsonGenerator;Lcom/fasterxml/jackson/databind/SerializerProvider;)V
  #109 = Utf8               Value returned by \'any-getter\' (%s()) not java.util.Map but %s
  #110 = NameAndType        #145:#146     // serializeFilteredAnyProperties:(Lcom/fasterxml/jackson/databind/SerializerProvider;Lcom/fasterxml/jackson/core/JsonGenerator;Ljava/lang/Object;Ljava/util/Map;Lcom/fasterxml/jackson/databind/ser/PropertyFilter;Ljava/lang/Object;)V
  #111 = Utf8               com/fasterxml/jackson/databind/ser/ContextualSerializer
  #112 = NameAndType        #147:#148     // handlePrimaryContextualization:(Lcom/fasterxml/jackson/databind/JsonSerializer;Lcom/fasterxml/jackson/databind/BeanProperty;)Lcom/fasterxml/jackson/databind/JsonSerializer;
  #113 = Utf8               com/fasterxml/jackson/databind/ser/AnyGetterWriter
  #114 = Utf8               com/fasterxml/jackson/databind/BeanProperty
  #115 = Utf8               com/fasterxml/jackson/databind/introspect/AnnotatedMember
  #116 = Utf8               com/fasterxml/jackson/databind/JsonSerializer
  #117 = Utf8               java/lang/Exception
  #118 = Utf8               com/fasterxml/jackson/databind/JsonMappingException
  #119 = Utf8               ()V
  #120 = Utf8               com/fasterxml/jackson/databind/MapperFeature
  #121 = Utf8               OVERRIDE_PUBLIC_ACCESS_MODIFIERS
  #122 = Utf8               Lcom/fasterxml/jackson/databind/MapperFeature;
  #123 = Utf8               com/fasterxml/jackson/databind/SerializationConfig
  #124 = Utf8               isEnabled
  #125 = Utf8               (Lcom/fasterxml/jackson/databind/MapperFeature;)Z
  #126 = Utf8               (Z)V
  #127 = Utf8               getValue
  #128 = Utf8               (Ljava/lang/Object;)Ljava/lang/Object;
  #129 = Utf8               getType
  #130 = Utf8               ()Lcom/fasterxml/jackson/databind/JavaType;
  #131 = Utf8               getName
  #132 = Utf8               ()Ljava/lang/String;
  #133 = Utf8               getClass
  #134 = Utf8               ()Ljava/lang/Class;
  #135 = Utf8               java/lang/Class
  #136 = Utf8               java/lang/String
  #137 = Utf8               format
  #138 = Utf8               (Ljava/lang/String;[Ljava/lang/Object;)Ljava/lang/String;
  #139 = Utf8               com/fasterxml/jackson/databind/SerializerProvider
  #140 = Utf8               reportBadDefinition
  #141 = Utf8               (Lcom/fasterxml/jackson/databind/JavaType;Ljava/lang/String;)Ljava/lang/Object;
  #142 = Utf8               serializeWithoutTypeInfo
  #143 = Utf8               (Ljava/util/Map;Lcom/fasterxml/jackson/core/JsonGenerator;Lcom/fasterxml/jackson/databind/SerializerProvider;)V
  #144 = Utf8               serialize
  #145 = Utf8               serializeFilteredAnyProperties
  #146 = Utf8               (Lcom/fasterxml/jackson/databind/SerializerProvider;Lcom/fasterxml/jackson/core/JsonGenerator;Ljava/lang/Object;Ljava/util/Map;Lcom/fasterxml/jackson/databind/ser/PropertyFilter;Ljava/lang/Object;)V
  #147 = Utf8               handlePrimaryContextualization
  #148 = Utf8               (Lcom/fasterxml/jackson/databind/JsonSerializer;Lcom/fasterxml/jackson/databind/BeanProperty;)Lcom/fasterxml/jackson/databind/JsonSerializer;
{
  protected final com.fasterxml.jackson.databind.BeanProperty _property;
    descriptor: Lcom/fasterxml/jackson/databind/BeanProperty;
    flags: (0x0014) ACC_PROTECTED, ACC_FINAL

  protected final com.fasterxml.jackson.databind.introspect.AnnotatedMember _accessor;
    descriptor: Lcom/fasterxml/jackson/databind/introspect/AnnotatedMember;
    flags: (0x0014) ACC_PROTECTED, ACC_FINAL

  protected com.fasterxml.jackson.databind.JsonSerializer<java.lang.Object> _serializer;
    descriptor: Lcom/fasterxml/jackson/databind/JsonSerializer;
    flags: (0x0004) ACC_PROTECTED
    Signature: #34                          // Lcom/fasterxml/jackson/databind/JsonSerializer<Ljava/lang/Object;>;

  protected com.fasterxml.jackson.databind.ser.std.MapSerializer _mapSerializer;
    descriptor: Lcom/fasterxml/jackson/databind/ser/std/MapSerializer;
    flags: (0x0004) ACC_PROTECTED

  public com.fasterxml.jackson.databind.ser.AnyGetterWriter(com.fasterxml.jackson.databind.BeanProperty, com.fasterxml.jackson.databind.introspect.AnnotatedMember, com.fasterxml.jackson.databind.JsonSerializer<?>);
    descriptor: (Lcom/fasterxml/jackson/databind/BeanProperty;Lcom/fasterxml/jackson/databind/introspect/AnnotatedMember;Lcom/fasterxml/jackson/databind/JsonSerializer;)V
    flags: (0x0001) ACC_PUBLIC
    Code:
      stack=2, locals=4, args_size=4
         0: aload_0
         1: invokespecial #1                  // Method java/lang/Object."<init>":()V
         4: aload_0
         5: aload_2
         6: putfield      #2                  // Field _accessor:Lcom/fasterxml/jackson/databind/introspect/AnnotatedMember;
         9: aload_0
        10: aload_1
        11: putfield      #3                  // Field _property:Lcom/fasterxml/jackson/databind/BeanProperty;
        14: aload_0
        15: aload_3
        16: putfield      #4                  // Field _serializer:Lcom/fasterxml/jackson/databind/JsonSerializer;
        19: aload_3
        20: instanceof    #5                  // class com/fasterxml/jackson/databind/ser/std/MapSerializer
        23: ifeq          34
        26: aload_0
        27: aload_3
        28: checkcast     #5                  // class com/fasterxml/jackson/databind/ser/std/MapSerializer
        31: putfield      #6                  // Field _mapSerializer:Lcom/fasterxml/jackson/databind/ser/std/MapSerializer;
        34: return
      LineNumberTable:
        line 31: 0
        line 32: 4
        line 33: 9
        line 34: 14
        line 35: 19
        line 36: 26
        line 38: 34
      LocalVariableTable:
        Start  Length  Slot  Name   Signature
            0      35     0  this   Lcom/fasterxml/jackson/databind/ser/AnyGetterWriter;
            0      35     1 property   Lcom/fasterxml/jackson/databind/BeanProperty;
            0      35     2 accessor   Lcom/fasterxml/jackson/databind/introspect/AnnotatedMember;
            0      35     3 serializer   Lcom/fasterxml/jackson/databind/JsonSerializer;
      LocalVariableTypeTable:
        Start  Length  Slot  Name   Signature
            0      35     3 serializer   Lcom/fasterxml/jackson/databind/JsonSerializer<*>;
      StackMapTable: number_of_entries = 1
        frame_type = 255 /* full_frame */
          offset_delta = 34
          locals = [ class com/fasterxml/jackson/databind/ser/AnyGetterWriter, class com/fasterxml/jackson/databind/BeanProperty, class com/fasterxml/jackson/databind/introspect/AnnotatedMember, class com/fasterxml/jackson/databind/JsonSerializer ]
          stack = []
    Signature: #54                          // (Lcom/fasterxml/jackson/databind/BeanProperty;Lcom/fasterxml/jackson/databind/introspect/AnnotatedMember;Lcom/fasterxml/jackson/databind/JsonSerializer<*>;)V

  public void fixAccess(com.fasterxml.jackson.databind.SerializationConfig);
    descriptor: (Lcom/fasterxml/jackson/databind/SerializationConfig;)V
    flags: (0x0001) ACC_PUBLIC
    Code:
      stack=3, locals=2, args_size=2
         0: aload_0
         1: getfield      #2                  // Field _accessor:Lcom/fasterxml/jackson/databind/introspect/AnnotatedMember;
         4: aload_1
         5: getstatic     #7                  // Field com/fasterxml/jackson/databind/MapperFeature.OVERRIDE_PUBLIC_ACCESS_MODIFIERS:Lcom/fasterxml/jackson/databind/MapperFeature;
         8: invokevirtual #8                  // Method com/fasterxml/jackson/databind/SerializationConfig.isEnabled:(Lcom/fasterxml/jackson/databind/MapperFeature;)Z
        11: invokevirtual #9                  // Method com/fasterxml/jackson/databind/introspect/AnnotatedMember.fixAccess:(Z)V
        14: return
      LineNumberTable:
        line 44: 0
        line 45: 8
        line 44: 11
        line 46: 14
      LocalVariableTable:
        Start  Length  Slot  Name   Signature
            0      15     0  this   Lcom/fasterxml/jackson/databind/ser/AnyGetterWriter;
            0      15     1 config   Lcom/fasterxml/jackson/databind/SerializationConfig;

  public void getAndSerialize(java.lang.Object, com.fasterxml.jackson.core.JsonGenerator, com.fasterxml.jackson.databind.SerializerProvider) throws java.lang.Exception;
    descriptor: (Ljava/lang/Object;Lcom/fasterxml/jackson/core/JsonGenerator;Lcom/fasterxml/jackson/databind/SerializerProvider;)V
    flags: (0x0001) ACC_PUBLIC
    Code:
      stack=7, locals=5, args_size=4
         0: aload_0
         1: getfield      #2                  // Field _accessor:Lcom/fasterxml/jackson/databind/introspect/AnnotatedMember;
         4: aload_1
         5: invokevirtual #10                 // Method com/fasterxml/jackson/databind/introspect/AnnotatedMember.getValue:(Ljava/lang/Object;)Ljava/lang/Object;
         8: astore        4
        10: aload         4
        12: ifnonnull     16
        15: return
        16: aload         4
        18: instanceof    #11                 // class java/util/Map
        21: ifne          68
        24: aload_3
        25: aload_0
        26: getfield      #3                  // Field _property:Lcom/fasterxml/jackson/databind/BeanProperty;
        29: invokeinterface #12,  1           // InterfaceMethod com/fasterxml/jackson/databind/BeanProperty.getType:()Lcom/fasterxml/jackson/databind/JavaType;
        34: ldc           #13                 // String Value returned by \'any-getter\' %s() not java.util.Map but %s
        36: iconst_2
        37: anewarray     #14                 // class java/lang/Object
        40: dup
        41: iconst_0
        42: aload_0
        43: getfield      #2                  // Field _accessor:Lcom/fasterxml/jackson/databind/introspect/AnnotatedMember;
        46: invokevirtual #15                 // Method com/fasterxml/jackson/databind/introspect/AnnotatedMember.getName:()Ljava/lang/String;
        49: aastore
        50: dup
        51: iconst_1
        52: aload         4
        54: invokevirtual #16                 // Method java/lang/Object.getClass:()Ljava/lang/Class;
        57: invokevirtual #17                 // Method java/lang/Class.getName:()Ljava/lang/String;
        60: aastore
        61: invokestatic  #18                 // Method java/lang/String.format:(Ljava/lang/String;[Ljava/lang/Object;)Ljava/lang/String;
        64: invokevirtual #19                 // Method com/fasterxml/jackson/databind/SerializerProvider.reportBadDefinition:(Lcom/fasterxml/jackson/databind/JavaType;Ljava/lang/String;)Ljava/lang/Object;
        67: pop
        68: aload_0
        69: getfield      #6                  // Field _mapSerializer:Lcom/fasterxml/jackson/databind/ser/std/MapSerializer;
        72: ifnull        90
        75: aload_0
        76: getfield      #6                  // Field _mapSerializer:Lcom/fasterxml/jackson/databind/ser/std/MapSerializer;
        79: aload         4
        81: checkcast     #11                 // class java/util/Map
        84: aload_2
        85: aload_3
        86: invokevirtual #20                 // Method com/fasterxml/jackson/databind/ser/std/MapSerializer.serializeWithoutTypeInfo:(Ljava/util/Map;Lcom/fasterxml/jackson/core/JsonGenerator;Lcom/fasterxml/jackson/databind/SerializerProvider;)V
        89: return
        90: aload_0
        91: getfield      #4                  // Field _serializer:Lcom/fasterxml/jackson/databind/JsonSerializer;
        94: aload         4
        96: aload_2
        97: aload_3
        98: invokevirtual #21                 // Method com/fasterxml/jackson/databind/JsonSerializer.serialize:(Ljava/lang/Object;Lcom/fasterxml/jackson/core/JsonGenerator;Lcom/fasterxml/jackson/databind/SerializerProvider;)V
       101: return
      LineNumberTable:
        line 51: 0
        line 52: 10
        line 53: 15
        line 55: 16
        line 56: 24
        line 58: 46
        line 56: 61
        line 61: 68
        line 62: 75
        line 63: 89
        line 65: 90
        line 66: 101
      LocalVariableTable:
        Start  Length  Slot  Name   Signature
            0     102     0  this   Lcom/fasterxml/jackson/databind/ser/AnyGetterWriter;
            0     102     1  bean   Ljava/lang/Object;
            0     102     2   gen   Lcom/fasterxml/jackson/core/JsonGenerator;
            0     102     3 provider   Lcom/fasterxml/jackson/databind/SerializerProvider;
           10      92     4 value   Ljava/lang/Object;
      StackMapTable: number_of_entries = 3
        frame_type = 252 /* append */
          offset_delta = 16
          locals = [ class java/lang/Object ]
        frame_type = 51 /* same */
        frame_type = 21 /* same */
    Exceptions:
      throws java.lang.Exception

  public void getAndFilter(java.lang.Object, com.fasterxml.jackson.core.JsonGenerator, com.fasterxml.jackson.databind.SerializerProvider, com.fasterxml.jackson.databind.ser.PropertyFilter) throws java.lang.Exception;
    descriptor: (Ljava/lang/Object;Lcom/fasterxml/jackson/core/JsonGenerator;Lcom/fasterxml/jackson/databind/SerializerProvider;Lcom/fasterxml/jackson/databind/ser/PropertyFilter;)V
    flags: (0x0001) ACC_PUBLIC
    Code:
      stack=7, locals=6, args_size=5
         0: aload_0
         1: getfield      #2                  // Field _accessor:Lcom/fasterxml/jackson/databind/introspect/AnnotatedMember;
         4: aload_1
         5: invokevirtual #10                 // Method com/fasterxml/jackson/databind/introspect/AnnotatedMember.getValue:(Ljava/lang/Object;)Ljava/lang/Object;
         8: astore        5
        10: aload         5
        12: ifnonnull     16
        15: return
        16: aload         5
        18: instanceof    #11                 // class java/util/Map
        21: ifne          68
        24: aload_3
        25: aload_0
        26: getfield      #3                  // Field _property:Lcom/fasterxml/jackson/databind/BeanProperty;
        29: invokeinterface #12,  1           // InterfaceMethod com/fasterxml/jackson/databind/BeanProperty.getType:()Lcom/fasterxml/jackson/databind/JavaType;
        34: ldc           #22                 // String Value returned by \'any-getter\' (%s()) not java.util.Map but %s
        36: iconst_2
        37: anewarray     #14                 // class java/lang/Object
        40: dup
        41: iconst_0
        42: aload_0
        43: getfield      #2                  // Field _accessor:Lcom/fasterxml/jackson/databind/introspect/AnnotatedMember;
        46: invokevirtual #15                 // Method com/fasterxml/jackson/databind/introspect/AnnotatedMember.getName:()Ljava/lang/String;
        49: aastore
        50: dup
        51: iconst_1
        52: aload         5
        54: invokevirtual #16                 // Method java/lang/Object.getClass:()Ljava/lang/Class;
        57: invokevirtual #17                 // Method java/lang/Class.getName:()Ljava/lang/String;
        60: aastore
        61: invokestatic  #18                 // Method java/lang/String.format:(Ljava/lang/String;[Ljava/lang/Object;)Ljava/lang/String;
        64: invokevirtual #19                 // Method com/fasterxml/jackson/databind/SerializerProvider.reportBadDefinition:(Lcom/fasterxml/jackson/databind/JavaType;Ljava/lang/String;)Ljava/lang/Object;
        67: pop
        68: aload_0
        69: getfield      #6                  // Field _mapSerializer:Lcom/fasterxml/jackson/databind/ser/std/MapSerializer;
        72: ifnull        94
        75: aload_0
        76: getfield      #6                  // Field _mapSerializer:Lcom/fasterxml/jackson/databind/ser/std/MapSerializer;
        79: aload_3
        80: aload_2
        81: aload_1
        82: aload         5
        84: checkcast     #11                 // class java/util/Map
        87: aload         4
        89: aconst_null
        90: invokevirtual #23                 // Method com/fasterxml/jackson/databind/ser/std/MapSerializer.serializeFilteredAnyProperties:(Lcom/fasterxml/jackson/databind/SerializerProvider;Lcom/fasterxml/jackson/core/JsonGenerator;Ljava/lang/Object;Ljava/util/Map;Lcom/fasterxml/jackson/databind/ser/PropertyFilter;Ljava/lang/Object;)V
        93: return
        94: aload_0
        95: getfield      #4                  // Field _serializer:Lcom/fasterxml/jackson/databind/JsonSerializer;
        98: aload         5
       100: aload_2
       101: aload_3
       102: invokevirtual #21                 // Method com/fasterxml/jackson/databind/JsonSerializer.serialize:(Ljava/lang/Object;Lcom/fasterxml/jackson/core/JsonGenerator;Lcom/fasterxml/jackson/databind/SerializerProvider;)V
       105: return
      LineNumberTable:
        line 75: 0
        line 76: 10
        line 77: 15
        line 79: 16
        line 80: 24
        line 82: 46
        line 81: 61
        line 80: 64
        line 85: 68
        line 86: 75
        line 88: 93
        line 91: 94
        line 92: 105
      LocalVariableTable:
        Start  Length  Slot  Name   Signature
            0     106     0  this   Lcom/fasterxml/jackson/databind/ser/AnyGetterWriter;
            0     106     1  bean   Ljava/lang/Object;
            0     106     2   gen   Lcom/fasterxml/jackson/core/JsonGenerator;
            0     106     3 provider   Lcom/fasterxml/jackson/databind/SerializerProvider;
            0     106     4 filter   Lcom/fasterxml/jackson/databind/ser/PropertyFilter;
           10      96     5 value   Ljava/lang/Object;
      StackMapTable: number_of_entries = 3
        frame_type = 252 /* append */
          offset_delta = 16
          locals = [ class java/lang/Object ]
        frame_type = 51 /* same */
        frame_type = 25 /* same */
    Exceptions:
      throws java.lang.Exception

  public void resolve(com.fasterxml.jackson.databind.SerializerProvider) throws com.fasterxml.jackson.databind.JsonMappingException;
    descriptor: (Lcom/fasterxml/jackson/databind/SerializerProvider;)V
    flags: (0x0001) ACC_PUBLIC
    Code:
      stack=3, locals=3, args_size=2
         0: aload_0
         1: getfield      #4                  // Field _serializer:Lcom/fasterxml/jackson/databind/JsonSerializer;
         4: instanceof    #24                 // class com/fasterxml/jackson/databind/ser/ContextualSerializer
         7: ifeq          43
        10: aload_1
        11: aload_0
        12: getfield      #4                  // Field _serializer:Lcom/fasterxml/jackson/databind/JsonSerializer;
        15: aload_0
        16: getfield      #3                  // Field _property:Lcom/fasterxml/jackson/databind/BeanProperty;
        19: invokevirtual #25                 // Method com/fasterxml/jackson/databind/SerializerProvider.handlePrimaryContextualization:(Lcom/fasterxml/jackson/databind/JsonSerializer;Lcom/fasterxml/jackson/databind/BeanProperty;)Lcom/fasterxml/jackson/databind/JsonSerializer;
        22: astore_2
        23: aload_0
        24: aload_2
        25: putfield      #4                  // Field _serializer:Lcom/fasterxml/jackson/databind/JsonSerializer;
        28: aload_2
        29: instanceof    #5                  // class com/fasterxml/jackson/databind/ser/std/MapSerializer
        32: ifeq          43
        35: aload_0
        36: aload_2
        37: checkcast     #5                  // class com/fasterxml/jackson/databind/ser/std/MapSerializer
        40: putfield      #6                  // Field _mapSerializer:Lcom/fasterxml/jackson/databind/ser/std/MapSerializer;
        43: return
      LineNumberTable:
        line 99: 0
        line 100: 10
        line 101: 23
        line 102: 28
        line 103: 35
        line 106: 43
      LocalVariableTable:
        Start  Length  Slot  Name   Signature
           23      20     2   ser   Lcom/fasterxml/jackson/databind/JsonSerializer;
            0      44     0  this   Lcom/fasterxml/jackson/databind/ser/AnyGetterWriter;
            0      44     1 provider   Lcom/fasterxml/jackson/databind/SerializerProvider;
      LocalVariableTypeTable:
        Start  Length  Slot  Name   Signature
           23      20     2   ser   Lcom/fasterxml/jackson/databind/JsonSerializer<*>;
      StackMapTable: number_of_entries = 1
        frame_type = 43 /* same */
    Exceptions:
      throws com.fasterxml.jackson.databind.JsonMappingException
}
SourceFile: "AnyGetterWriter.java"
