Classfile /Users/mw/Projects/slang-braindump/.jar/jar8/assemble/slang-braindump/assemble/content/org/kohsuke/github/AbstractBuilder.class
  Last modified May 29, 2022; size 3172 bytes
  SHA-256 checksum b67298350455998fd22a3e1a06d94b0efd14f33752af6f6a6b7c523ce7bc19b1
  Compiled from "AbstractBuilder.java"
abstract class org.kohsuke.github.AbstractBuilder<R extends java.lang.Object, S extends java.lang.Object> extends org.kohsuke.github.GitHubInteractiveObject
  minor version: 0
  major version: 52
  flags: (0x0420) ACC_SUPER, ACC_ABSTRACT
  this_class: #18                         // org/kohsuke/github/AbstractBuilder
  super_class: #19                        // org/kohsuke/github/GitHubInteractiveObject
  interfaces: 0, fields: 5, methods: 4, attributes: 3
Constant pool:
    #1 = Methodref          #19.#73       // org/kohsuke/github/GitHubInteractiveObject."<init>":(Lorg/kohsuke/github/GitHub;)V
    #2 = Methodref          #51.#74       // org/kohsuke/github/GitHub.createRequest:()Lorg/kohsuke/github/Requester;
    #3 = Fieldref           #18.#75       // org/kohsuke/github/AbstractBuilder.requester:Lorg/kohsuke/github/Requester;
    #4 = Fieldref           #18.#76       // org/kohsuke/github/AbstractBuilder.returnType:Ljava/lang/Class;
    #5 = Methodref          #52.#77       // java/lang/Object.equals:(Ljava/lang/Object;)Z
    #6 = Fieldref           #18.#78       // org/kohsuke/github/AbstractBuilder.commitChangesImmediately:Z
    #7 = Methodref          #50.#79       // java/lang/Class.isInstance:(Ljava/lang/Object;)Z
    #8 = Class              #80           // java/lang/IllegalArgumentException
    #9 = String             #81           // Argument \"intermediateReturnType\": This instance must be castable to intermediateReturnType or finalReturnType must be equal to intermediateReturnType.
   #10 = Methodref          #8.#82        // java/lang/IllegalArgumentException."<init>":(Ljava/lang/String;)V
   #11 = Fieldref           #18.#83       // org/kohsuke/github/AbstractBuilder.baseInstance:Ljava/lang/Object;
   #12 = Fieldref           #18.#84       // org/kohsuke/github/AbstractBuilder.updateInPlace:Z
   #13 = Methodref          #85.#86       // org/kohsuke/github/Requester.fetchInto:(Ljava/lang/Object;)Ljava/lang/Object;
   #14 = Methodref          #85.#87       // org/kohsuke/github/Requester.fetch:(Ljava/lang/Class;)Ljava/lang/Object;
   #15 = Methodref          #85.#88       // org/kohsuke/github/Requester.with:(Ljava/lang/String;Ljava/lang/Object;)Lorg/kohsuke/github/GitHubRequest$Builder;
   #16 = Methodref          #18.#89       // org/kohsuke/github/AbstractBuilder.continueOrDone:()Ljava/lang/Object;
   #17 = Methodref          #18.#90       // org/kohsuke/github/AbstractBuilder.done:()Ljava/lang/Object;
   #18 = Class              #91           // org/kohsuke/github/AbstractBuilder
   #19 = Class              #92           // org/kohsuke/github/GitHubInteractiveObject
   #20 = Utf8               returnType
   #21 = Utf8               Ljava/lang/Class;
   #22 = Utf8               Signature
   #23 = Utf8               Ljava/lang/Class<TR;>;
   #24 = Utf8               RuntimeVisibleAnnotations
   #25 = Utf8               Ljavax/annotation/Nonnull;
   #26 = Utf8               commitChangesImmediately
   #27 = Utf8               Z
   #28 = Utf8               baseInstance
   #29 = Utf8               Ljava/lang/Object;
   #30 = Utf8               TR;
   #31 = Utf8               Ljavax/annotation/CheckForNull;
   #32 = Utf8               requester
   #33 = Utf8               Lorg/kohsuke/github/Requester;
   #34 = Utf8               updateInPlace
   #35 = Utf8               <init>
   #36 = Utf8               (Ljava/lang/Class;Ljava/lang/Class;Lorg/kohsuke/github/GitHub;Ljava/lang/Object;)V
   #37 = Utf8               Code
   #38 = Utf8               LineNumberTable
   #39 = Utf8               LocalVariableTable
   #40 = Utf8               this
   #41 = Utf8               Lorg/kohsuke/github/AbstractBuilder;
   #42 = Utf8               finalReturnType
   #43 = Utf8               intermediateReturnType
   #44 = Utf8               root
   #45 = Utf8               Lorg/kohsuke/github/GitHub;
   #46 = Utf8               LocalVariableTypeTable
   #47 = Utf8               Lorg/kohsuke/github/AbstractBuilder<TR;TS;>;
   #48 = Utf8               Ljava/lang/Class<TS;>;
   #49 = Utf8               StackMapTable
   #50 = Class              #93           // java/lang/Class
   #51 = Class              #94           // org/kohsuke/github/GitHub
   #52 = Class              #95           // java/lang/Object
   #53 = Utf8               (Ljava/lang/Class<TR;>;Ljava/lang/Class<TS;>;Lorg/kohsuke/github/GitHub;TR;)V
   #54 = Utf8               RuntimeVisibleParameterAnnotations
   #55 = Utf8               done
   #56 = Utf8               ()Ljava/lang/Object;
   #57 = Utf8               result
   #58 = Utf8               Exceptions
   #59 = Class              #96           // java/io/IOException
   #60 = Utf8               ()TR;
   #61 = Utf8               Lorg/kohsuke/github/BetaApi;
   #62 = Utf8               with
   #63 = Utf8               (Ljava/lang/String;Ljava/lang/Object;)Ljava/lang/Object;
   #64 = Utf8               name
   #65 = Utf8               Ljava/lang/String;
   #66 = Utf8               value
   #67 = Utf8               (Ljava/lang/String;Ljava/lang/Object;)TS;
   #68 = Utf8               continueOrDone
   #69 = Utf8               ()TS;
   #70 = Utf8               <R:Ljava/lang/Object;S:Ljava/lang/Object;>Lorg/kohsuke/github/GitHubInteractiveObject;
   #71 = Utf8               SourceFile
   #72 = Utf8               AbstractBuilder.java
   #73 = NameAndType        #35:#97       // "<init>":(Lorg/kohsuke/github/GitHub;)V
   #74 = NameAndType        #98:#99       // createRequest:()Lorg/kohsuke/github/Requester;
   #75 = NameAndType        #32:#33       // requester:Lorg/kohsuke/github/Requester;
   #76 = NameAndType        #20:#21       // returnType:Ljava/lang/Class;
   #77 = NameAndType        #100:#101     // equals:(Ljava/lang/Object;)Z
   #78 = NameAndType        #26:#27       // commitChangesImmediately:Z
   #79 = NameAndType        #102:#101     // isInstance:(Ljava/lang/Object;)Z
   #80 = Utf8               java/lang/IllegalArgumentException
   #81 = Utf8               Argument \"intermediateReturnType\": This instance must be castable to intermediateReturnType or finalReturnType must be equal to intermediateReturnType.
   #82 = NameAndType        #35:#103      // "<init>":(Ljava/lang/String;)V
   #83 = NameAndType        #28:#29       // baseInstance:Ljava/lang/Object;
   #84 = NameAndType        #34:#27       // updateInPlace:Z
   #85 = Class              #104          // org/kohsuke/github/Requester
   #86 = NameAndType        #105:#106     // fetchInto:(Ljava/lang/Object;)Ljava/lang/Object;
   #87 = NameAndType        #107:#108     // fetch:(Ljava/lang/Class;)Ljava/lang/Object;
   #88 = NameAndType        #62:#112      // with:(Ljava/lang/String;Ljava/lang/Object;)Lorg/kohsuke/github/GitHubRequest$Builder;
   #89 = NameAndType        #68:#56       // continueOrDone:()Ljava/lang/Object;
   #90 = NameAndType        #55:#56       // done:()Ljava/lang/Object;
   #91 = Utf8               org/kohsuke/github/AbstractBuilder
   #92 = Utf8               org/kohsuke/github/GitHubInteractiveObject
   #93 = Utf8               java/lang/Class
   #94 = Utf8               org/kohsuke/github/GitHub
   #95 = Utf8               java/lang/Object
   #96 = Utf8               java/io/IOException
   #97 = Utf8               (Lorg/kohsuke/github/GitHub;)V
   #98 = Utf8               createRequest
   #99 = Utf8               ()Lorg/kohsuke/github/Requester;
  #100 = Utf8               equals
  #101 = Utf8               (Ljava/lang/Object;)Z
  #102 = Utf8               isInstance
  #103 = Utf8               (Ljava/lang/String;)V
  #104 = Utf8               org/kohsuke/github/Requester
  #105 = Utf8               fetchInto
  #106 = Utf8               (Ljava/lang/Object;)Ljava/lang/Object;
  #107 = Utf8               fetch
  #108 = Utf8               (Ljava/lang/Class;)Ljava/lang/Object;
  #109 = Class              #114          // org/kohsuke/github/GitHubRequest$Builder
  #110 = Utf8               Builder
  #111 = Utf8               InnerClasses
  #112 = Utf8               (Ljava/lang/String;Ljava/lang/Object;)Lorg/kohsuke/github/GitHubRequest$Builder;
  #113 = Class              #115          // org/kohsuke/github/GitHubRequest
  #114 = Utf8               org/kohsuke/github/GitHubRequest$Builder
  #115 = Utf8               org/kohsuke/github/GitHubRequest
{
  private final java.lang.Class<R> returnType;
    descriptor: Ljava/lang/Class;
    flags: (0x0012) ACC_PRIVATE, ACC_FINAL
    Signature: #23                          // Ljava/lang/Class<TR;>;
    RuntimeVisibleAnnotations:
      0: #25()
        javax.annotation.Nonnull

  private final boolean commitChangesImmediately;
    descriptor: Z
    flags: (0x0012) ACC_PRIVATE, ACC_FINAL

  private final R baseInstance;
    descriptor: Ljava/lang/Object;
    flags: (0x0012) ACC_PRIVATE, ACC_FINAL
    Signature: #30                          // TR;
    RuntimeVisibleAnnotations:
      0: #31()
        javax.annotation.CheckForNull

  protected final org.kohsuke.github.Requester requester;
    descriptor: Lorg/kohsuke/github/Requester;
    flags: (0x0014) ACC_PROTECTED, ACC_FINAL
    RuntimeVisibleAnnotations:
      0: #25()
        javax.annotation.Nonnull

  protected boolean updateInPlace;
    descriptor: Z
    flags: (0x0004) ACC_PROTECTED

  protected org.kohsuke.github.AbstractBuilder(java.lang.Class<R>, java.lang.Class<S>, org.kohsuke.github.GitHub, R);
    descriptor: (Ljava/lang/Class;Ljava/lang/Class;Lorg/kohsuke/github/GitHub;Ljava/lang/Object;)V
    flags: (0x0004) ACC_PROTECTED
    Code:
      stack=3, locals=5, args_size=5
         0: aload_0
         1: aload_3
         2: invokespecial #1                  // Method org/kohsuke/github/GitHubInteractiveObject."<init>":(Lorg/kohsuke/github/GitHub;)V
         5: aload_0
         6: aload_3
         7: invokevirtual #2                  // Method org/kohsuke/github/GitHub.createRequest:()Lorg/kohsuke/github/Requester;
        10: putfield      #3                  // Field requester:Lorg/kohsuke/github/Requester;
        13: aload_0
        14: aload_1
        15: putfield      #4                  // Field returnType:Ljava/lang/Class;
        18: aload_0
        19: aload_0
        20: getfield      #4                  // Field returnType:Ljava/lang/Class;
        23: aload_2
        24: invokevirtual #5                  // Method java/lang/Object.equals:(Ljava/lang/Object;)Z
        27: putfield      #6                  // Field commitChangesImmediately:Z
        30: aload_0
        31: getfield      #6                  // Field commitChangesImmediately:Z
        34: ifne          55
        37: aload_2
        38: aload_0
        39: invokevirtual #7                  // Method java/lang/Class.isInstance:(Ljava/lang/Object;)Z
        42: ifne          55
        45: new           #8                  // class java/lang/IllegalArgumentException
        48: dup
        49: ldc           #9                  // String Argument \"intermediateReturnType\": This instance must be castable to intermediateReturnType or finalReturnType must be equal to intermediateReturnType.
        51: invokespecial #10                 // Method java/lang/IllegalArgumentException."<init>":(Ljava/lang/String;)V
        54: athrow
        55: aload_0
        56: aload         4
        58: putfield      #11                 // Field baseInstance:Ljava/lang/Object;
        61: aload_0
        62: iconst_0
        63: putfield      #12                 // Field updateInPlace:Z
        66: return
      LineNumberTable:
        line 80: 0
        line 81: 5
        line 82: 13
        line 83: 18
        line 84: 30
        line 85: 45
        line 89: 55
        line 90: 61
        line 91: 66
      LocalVariableTable:
        Start  Length  Slot  Name   Signature
            0      67     0  this   Lorg/kohsuke/github/AbstractBuilder;
            0      67     1 finalReturnType   Ljava/lang/Class;
            0      67     2 intermediateReturnType   Ljava/lang/Class;
            0      67     3  root   Lorg/kohsuke/github/GitHub;
            0      67     4 baseInstance   Ljava/lang/Object;
      LocalVariableTypeTable:
        Start  Length  Slot  Name   Signature
            0      67     0  this   Lorg/kohsuke/github/AbstractBuilder<TR;TS;>;
            0      67     1 finalReturnType   Ljava/lang/Class<TR;>;
            0      67     2 intermediateReturnType   Ljava/lang/Class<TS;>;
            0      67     4 baseInstance   TR;
      StackMapTable: number_of_entries = 1
        frame_type = 255 /* full_frame */
          offset_delta = 55
          locals = [ class org/kohsuke/github/AbstractBuilder, class java/lang/Class, class java/lang/Class, class org/kohsuke/github/GitHub, class java/lang/Object ]
          stack = []
    Signature: #53                          // (Ljava/lang/Class<TR;>;Ljava/lang/Class<TS;>;Lorg/kohsuke/github/GitHub;TR;)V
    RuntimeVisibleParameterAnnotations:
      parameter 0:
        0: #25()
          javax.annotation.Nonnull
      parameter 1:
        0: #25()
          javax.annotation.Nonnull
      parameter 2:
        0: #25()
          javax.annotation.Nonnull
      parameter 3:
        0: #31()
          javax.annotation.CheckForNull

  public R done() throws java.io.IOException;
    descriptor: ()Ljava/lang/Object;
    flags: (0x0001) ACC_PUBLIC
    Code:
      stack=2, locals=2, args_size=1
         0: aload_0
         1: getfield      #12                 // Field updateInPlace:Z
         4: ifeq          29
         7: aload_0
         8: getfield      #11                 // Field baseInstance:Ljava/lang/Object;
        11: ifnull        29
        14: aload_0
        15: getfield      #3                  // Field requester:Lorg/kohsuke/github/Requester;
        18: aload_0
        19: getfield      #11                 // Field baseInstance:Ljava/lang/Object;
        22: invokevirtual #13                 // Method org/kohsuke/github/Requester.fetchInto:(Ljava/lang/Object;)Ljava/lang/Object;
        25: astore_1
        26: goto          41
        29: aload_0
        30: getfield      #3                  // Field requester:Lorg/kohsuke/github/Requester;
        33: aload_0
        34: getfield      #4                  // Field returnType:Ljava/lang/Class;
        37: invokevirtual #14                 // Method org/kohsuke/github/Requester.fetch:(Ljava/lang/Class;)Ljava/lang/Object;
        40: astore_1
        41: aload_1
        42: areturn
      LineNumberTable:
        line 106: 0
        line 107: 14
        line 109: 29
        line 111: 41
      LocalVariableTable:
        Start  Length  Slot  Name   Signature
           26       3     1 result   Ljava/lang/Object;
            0      43     0  this   Lorg/kohsuke/github/AbstractBuilder;
           41       2     1 result   Ljava/lang/Object;
      LocalVariableTypeTable:
        Start  Length  Slot  Name   Signature
           26       3     1 result   TR;
            0      43     0  this   Lorg/kohsuke/github/AbstractBuilder<TR;TS;>;
           41       2     1 result   TR;
      StackMapTable: number_of_entries = 2
        frame_type = 29 /* same */
        frame_type = 252 /* append */
          offset_delta = 11
          locals = [ class java/lang/Object ]
    Exceptions:
      throws java.io.IOException
    Signature: #60                          // ()TR;
    RuntimeVisibleAnnotations:
      0: #25()
        javax.annotation.Nonnull
      1: #61()
        org.kohsuke.github.BetaApi

  protected S with(java.lang.String, java.lang.Object) throws java.io.IOException;
    descriptor: (Ljava/lang/String;Ljava/lang/Object;)Ljava/lang/Object;
    flags: (0x0004) ACC_PROTECTED
    Code:
      stack=3, locals=3, args_size=3
         0: aload_0
         1: getfield      #3                  // Field requester:Lorg/kohsuke/github/Requester;
         4: aload_1
         5: aload_2
         6: invokevirtual #15                 // Method org/kohsuke/github/Requester.with:(Ljava/lang/String;Ljava/lang/Object;)Lorg/kohsuke/github/GitHubRequest$Builder;
         9: pop
        10: aload_0
        11: invokevirtual #16                 // Method continueOrDone:()Ljava/lang/Object;
        14: areturn
      LineNumberTable:
        line 134: 0
        line 135: 10
      LocalVariableTable:
        Start  Length  Slot  Name   Signature
            0      15     0  this   Lorg/kohsuke/github/AbstractBuilder;
            0      15     1  name   Ljava/lang/String;
            0      15     2 value   Ljava/lang/Object;
      LocalVariableTypeTable:
        Start  Length  Slot  Name   Signature
            0      15     0  this   Lorg/kohsuke/github/AbstractBuilder<TR;TS;>;
    Exceptions:
      throws java.io.IOException
    Signature: #67                          // (Ljava/lang/String;Ljava/lang/Object;)TS;
    RuntimeVisibleAnnotations:
      0: #25()
        javax.annotation.Nonnull
      1: #61()
        org.kohsuke.github.BetaApi
    RuntimeVisibleParameterAnnotations:
      parameter 0:
        0: #25()
          javax.annotation.Nonnull
      parameter 1:

  protected S continueOrDone() throws java.io.IOException;
    descriptor: ()Ljava/lang/Object;
    flags: (0x0004) ACC_PROTECTED
    Code:
      stack=1, locals=1, args_size=1
         0: aload_0
         1: getfield      #6                  // Field commitChangesImmediately:Z
         4: ifeq          12
         7: aload_0
         8: invokevirtual #17                 // Method done:()Ljava/lang/Object;
        11: areturn
        12: aload_0
        13: areturn
      LineNumberTable:
        line 157: 0
        line 160: 7
        line 162: 12
      LocalVariableTable:
        Start  Length  Slot  Name   Signature
            0      14     0  this   Lorg/kohsuke/github/AbstractBuilder;
      LocalVariableTypeTable:
        Start  Length  Slot  Name   Signature
            0      14     0  this   Lorg/kohsuke/github/AbstractBuilder<TR;TS;>;
      StackMapTable: number_of_entries = 1
        frame_type = 12 /* same */
    Exceptions:
      throws java.io.IOException
    Signature: #69                          // ()TS;
    RuntimeVisibleAnnotations:
      0: #25()
        javax.annotation.Nonnull
      1: #61()
        org.kohsuke.github.BetaApi
}
Signature: #70                          // <R:Ljava/lang/Object;S:Ljava/lang/Object;>Lorg/kohsuke/github/GitHubInteractiveObject;
SourceFile: "AbstractBuilder.java"
InnerClasses:
  static #110= #109 of #113;              // Builder=class org/kohsuke/github/GitHubRequest$Builder of class org/kohsuke/github/GitHubRequest
