Classfile /Users/mw/Projects/slang-braindump/.jar/jar8/assemble/slang-braindump/assemble/content/org/kohsuke/github/AbuseLimitHandler$2.class
  Last modified May 29, 2022; size 652 bytes
  SHA-256 checksum 1bc136ee0ef64276af3ab741c1d67c97df6495c7c0a361d5ccd0fd09985fb53a
  Compiled from "AbuseLimitHandler.java"
class org.kohsuke.github.AbuseLimitHandler$2 extends org.kohsuke.github.AbuseLimitHandler
  minor version: 0
  major version: 52
  flags: (0x0020) ACC_SUPER
  this_class: #2                          // org/kohsuke/github/AbuseLimitHandler$2
  super_class: #3                         // org/kohsuke/github/AbuseLimitHandler
  interfaces: 0, fields: 0, methods: 2, attributes: 3
Constant pool:
   #1 = Methodref          #3.#23         // org/kohsuke/github/AbuseLimitHandler."<init>":()V
   #2 = Class              #24            // org/kohsuke/github/AbuseLimitHandler$2
   #3 = Class              #25            // org/kohsuke/github/AbuseLimitHandler
   #4 = Utf8               <init>
   #5 = Utf8               ()V
   #6 = Utf8               Code
   #7 = Utf8               LineNumberTable
   #8 = Utf8               LocalVariableTable
   #9 = Utf8               this
  #10 = Utf8               InnerClasses
  #11 = Utf8               Lorg/kohsuke/github/AbuseLimitHandler$2;
  #12 = Utf8               onError
  #13 = Utf8               (Ljava/io/IOException;Ljava/net/HttpURLConnection;)V
  #14 = Utf8               e
  #15 = Utf8               Ljava/io/IOException;
  #16 = Utf8               uc
  #17 = Utf8               Ljava/net/HttpURLConnection;
  #18 = Utf8               Exceptions
  #19 = Class              #26            // java/io/IOException
  #20 = Utf8               SourceFile
  #21 = Utf8               AbuseLimitHandler.java
  #22 = Utf8               EnclosingMethod
  #23 = NameAndType        #4:#5          // "<init>":()V
  #24 = Utf8               org/kohsuke/github/AbuseLimitHandler$2
  #25 = Utf8               org/kohsuke/github/AbuseLimitHandler
  #26 = Utf8               java/io/IOException
{
  org.kohsuke.github.AbuseLimitHandler$2();
    descriptor: ()V
    flags: (0x0000)
    Code:
      stack=1, locals=1, args_size=1
         0: aload_0
         1: invokespecial #1                  // Method org/kohsuke/github/AbuseLimitHandler."<init>":()V
         4: return
      LineNumberTable:
        line 101: 0
      LocalVariableTable:
        Start  Length  Slot  Name   Signature
            0       5     0  this   Lorg/kohsuke/github/AbuseLimitHandler$2;

  public void onError(java.io.IOException, java.net.HttpURLConnection) throws java.io.IOException;
    descriptor: (Ljava/io/IOException;Ljava/net/HttpURLConnection;)V
    flags: (0x0001) ACC_PUBLIC
    Code:
      stack=1, locals=3, args_size=3
         0: aload_1
         1: athrow
      LineNumberTable:
        line 104: 0
      LocalVariableTable:
        Start  Length  Slot  Name   Signature
            0       2     0  this   Lorg/kohsuke/github/AbuseLimitHandler$2;
            0       2     1     e   Ljava/io/IOException;
            0       2     2    uc   Ljava/net/HttpURLConnection;
    Exceptions:
      throws java.io.IOException
}
SourceFile: "AbuseLimitHandler.java"
EnclosingMethod: #3.#0                  // org.kohsuke.github.AbuseLimitHandler
InnerClasses:
  #2;                                     // class org/kohsuke/github/AbuseLimitHandler$2
