Classfile /Users/mw/Projects/slang-braindump/.jar/jar8/assemble/slang-braindump/assemble/content/org/kohsuke/github/GHAppInstallationsPage.class
  Last modified May 29, 2022; size 648 bytes
  SHA-256 checksum 08ffcdc7362f7a481df5df53cbfa746b9abfb32c8656c242af23fe4d829aa1e6
  Compiled from "GHAppInstallationsPage.java"
class org.kohsuke.github.GHAppInstallationsPage
  minor version: 0
  major version: 52
  flags: (0x0020) ACC_SUPER
  this_class: #4                          // org/kohsuke/github/GHAppInstallationsPage
  super_class: #5                         // java/lang/Object
  interfaces: 0, fields: 2, methods: 3, attributes: 1
Constant pool:
   #1 = Methodref          #5.#23         // java/lang/Object."<init>":()V
   #2 = Fieldref           #4.#24         // org/kohsuke/github/GHAppInstallationsPage.total_count:I
   #3 = Fieldref           #4.#25         // org/kohsuke/github/GHAppInstallationsPage.installations:[Lorg/kohsuke/github/GHAppInstallation;
   #4 = Class              #26            // org/kohsuke/github/GHAppInstallationsPage
   #5 = Class              #27            // java/lang/Object
   #6 = Utf8               total_count
   #7 = Utf8               I
   #8 = Utf8               installations
   #9 = Utf8               [Lorg/kohsuke/github/GHAppInstallation;
  #10 = Utf8               <init>
  #11 = Utf8               ()V
  #12 = Utf8               Code
  #13 = Utf8               LineNumberTable
  #14 = Utf8               LocalVariableTable
  #15 = Utf8               this
  #16 = Utf8               Lorg/kohsuke/github/GHAppInstallationsPage;
  #17 = Utf8               getTotalCount
  #18 = Utf8               ()I
  #19 = Utf8               getInstallations
  #20 = Utf8               ()[Lorg/kohsuke/github/GHAppInstallation;
  #21 = Utf8               SourceFile
  #22 = Utf8               GHAppInstallationsPage.java
  #23 = NameAndType        #10:#11        // "<init>":()V
  #24 = NameAndType        #6:#7          // total_count:I
  #25 = NameAndType        #8:#9          // installations:[Lorg/kohsuke/github/GHAppInstallation;
  #26 = Utf8               org/kohsuke/github/GHAppInstallationsPage
  #27 = Utf8               java/lang/Object
{
  private int total_count;
    descriptor: I
    flags: (0x0002) ACC_PRIVATE

  private org.kohsuke.github.GHAppInstallation[] installations;
    descriptor: [Lorg/kohsuke/github/GHAppInstallation;
    flags: (0x0002) ACC_PRIVATE

  org.kohsuke.github.GHAppInstallationsPage();
    descriptor: ()V
    flags: (0x0000)
    Code:
      stack=1, locals=1, args_size=1
         0: aload_0
         1: invokespecial #1                  // Method java/lang/Object."<init>":()V
         4: return
      LineNumberTable:
        line 6: 0
      LocalVariableTable:
        Start  Length  Slot  Name   Signature
            0       5     0  this   Lorg/kohsuke/github/GHAppInstallationsPage;

  public int getTotalCount();
    descriptor: ()I
    flags: (0x0001) ACC_PUBLIC
    Code:
      stack=1, locals=1, args_size=1
         0: aload_0
         1: getfield      #2                  // Field total_count:I
         4: ireturn
      LineNumberTable:
        line 11: 0
      LocalVariableTable:
        Start  Length  Slot  Name   Signature
            0       5     0  this   Lorg/kohsuke/github/GHAppInstallationsPage;

  org.kohsuke.github.GHAppInstallation[] getInstallations();
    descriptor: ()[Lorg/kohsuke/github/GHAppInstallation;
    flags: (0x0000)
    Code:
      stack=1, locals=1, args_size=1
         0: aload_0
         1: getfield      #3                  // Field installations:[Lorg/kohsuke/github/GHAppInstallation;
         4: areturn
      LineNumberTable:
        line 15: 0
      LocalVariableTable:
        Start  Length  Slot  Name   Signature
            0       5     0  this   Lorg/kohsuke/github/GHAppInstallationsPage;
}
SourceFile: "GHAppInstallationsPage.java"
