Classfile /Users/mw/Projects/slang-braindump/.jar/jar8/assemble/slang-braindump/assemble/content/org/kohsuke/github/GHBranchProtectionBuilder$StatusChecks.class
  Last modified May 29, 2022; size 879 bytes
  SHA-256 checksum 0cfe2d9e4c2277b9ff201bf1bb85fe2b95cfff2643e2e4c22dfd7564411e0dce
  Compiled from "GHBranchProtectionBuilder.java"
class org.kohsuke.github.GHBranchProtectionBuilder$StatusChecks
  minor version: 0
  major version: 52
  flags: (0x0020) ACC_SUPER
  this_class: #6                          // org/kohsuke/github/GHBranchProtectionBuilder$StatusChecks
  super_class: #7                         // java/lang/Object
  interfaces: 0, fields: 2, methods: 2, attributes: 2
Constant pool:
   #1 = Methodref          #6.#29         // org/kohsuke/github/GHBranchProtectionBuilder$StatusChecks."<init>":()V
   #2 = Methodref          #7.#29         // java/lang/Object."<init>":()V
   #3 = Class              #30            // java/util/ArrayList
   #4 = Methodref          #3.#29         // java/util/ArrayList."<init>":()V
   #5 = Fieldref           #6.#31         // org/kohsuke/github/GHBranchProtectionBuilder$StatusChecks.contexts:Ljava/util/List;
   #6 = Class              #33            // org/kohsuke/github/GHBranchProtectionBuilder$StatusChecks
   #7 = Class              #34            // java/lang/Object
   #8 = Utf8               contexts
   #9 = Utf8               Ljava/util/List;
  #10 = Utf8               Signature
  #11 = Utf8               Ljava/util/List<Ljava/lang/String;>;
  #12 = Utf8               strict
  #13 = Utf8               Z
  #14 = Utf8               <init>
  #15 = Utf8               ()V
  #16 = Utf8               Code
  #17 = Utf8               LineNumberTable
  #18 = Utf8               LocalVariableTable
  #19 = Utf8               this
  #20 = Utf8               StatusChecks
  #21 = Utf8               InnerClasses
  #22 = Utf8               Lorg/kohsuke/github/GHBranchProtectionBuilder$StatusChecks;
  #23 = Class              #35            // org/kohsuke/github/GHBranchProtectionBuilder$1
  #24 = Utf8               (Lorg/kohsuke/github/GHBranchProtectionBuilder$1;)V
  #25 = Utf8               x0
  #26 = Utf8               Lorg/kohsuke/github/GHBranchProtectionBuilder$1;
  #27 = Utf8               SourceFile
  #28 = Utf8               GHBranchProtectionBuilder.java
  #29 = NameAndType        #14:#15        // "<init>":()V
  #30 = Utf8               java/util/ArrayList
  #31 = NameAndType        #8:#9          // contexts:Ljava/util/List;
  #32 = Class              #36            // org/kohsuke/github/GHBranchProtectionBuilder
  #33 = Utf8               org/kohsuke/github/GHBranchProtectionBuilder$StatusChecks
  #34 = Utf8               java/lang/Object
  #35 = Utf8               org/kohsuke/github/GHBranchProtectionBuilder$1
  #36 = Utf8               org/kohsuke/github/GHBranchProtectionBuilder
{
  final java.util.List<java.lang.String> contexts;
    descriptor: Ljava/util/List;
    flags: (0x0010) ACC_FINAL
    Signature: #11                          // Ljava/util/List<Ljava/lang/String;>;

  boolean strict;
    descriptor: Z
    flags: (0x0000)

  private org.kohsuke.github.GHBranchProtectionBuilder$StatusChecks();
    descriptor: ()V
    flags: (0x0002) ACC_PRIVATE
    Code:
      stack=3, locals=1, args_size=1
         0: aload_0
         1: invokespecial #2                  // Method java/lang/Object."<init>":()V
         4: aload_0
         5: new           #3                  // class java/util/ArrayList
         8: dup
         9: invokespecial #4                  // Method java/util/ArrayList."<init>":()V
        12: putfield      #5                  // Field contexts:Ljava/util/List;
        15: return
      LineNumberTable:
        line 363: 0
        line 364: 4
      LocalVariableTable:
        Start  Length  Slot  Name   Signature
            0      16     0  this   Lorg/kohsuke/github/GHBranchProtectionBuilder$StatusChecks;

  org.kohsuke.github.GHBranchProtectionBuilder$StatusChecks(org.kohsuke.github.GHBranchProtectionBuilder$1);
    descriptor: (Lorg/kohsuke/github/GHBranchProtectionBuilder$1;)V
    flags: (0x1000) ACC_SYNTHETIC
    Code:
      stack=1, locals=2, args_size=2
         0: aload_0
         1: invokespecial #1                  // Method "<init>":()V
         4: return
      LineNumberTable:
        line 363: 0
      LocalVariableTable:
        Start  Length  Slot  Name   Signature
            0       5     0  this   Lorg/kohsuke/github/GHBranchProtectionBuilder$StatusChecks;
            0       5     1    x0   Lorg/kohsuke/github/GHBranchProtectionBuilder$1;
}
SourceFile: "GHBranchProtectionBuilder.java"
InnerClasses:
  private static #20= #6 of #32;          // StatusChecks=class org/kohsuke/github/GHBranchProtectionBuilder$StatusChecks of class org/kohsuke/github/GHBranchProtectionBuilder
  static #23;                             // class org/kohsuke/github/GHBranchProtectionBuilder$1
