Classfile /Users/mw/Projects/slang-braindump/.jar/jar8/assemble/slang-braindump/assemble/content/org/kohsuke/github/GHBranchProtection$RequiredSignatures.class
  Last modified May 29, 2022; size 944 bytes
  SHA-256 checksum bcc18049edd20a9912288861205a6489861f367b509b0497061b5c55316fd04e
  Compiled from "GHBranchProtection.java"
class org.kohsuke.github.GHBranchProtection$RequiredSignatures
  minor version: 0
  major version: 52
  flags: (0x0020) ACC_SUPER
  this_class: #4                          // org/kohsuke/github/GHBranchProtection$RequiredSignatures
  super_class: #5                         // java/lang/Object
  interfaces: 0, fields: 2, methods: 4, attributes: 2
Constant pool:
   #1 = Fieldref           #4.#30         // org/kohsuke/github/GHBranchProtection$RequiredSignatures.enabled:Z
   #2 = Methodref          #5.#31         // java/lang/Object."<init>":()V
   #3 = Fieldref           #4.#32         // org/kohsuke/github/GHBranchProtection$RequiredSignatures.url:Ljava/lang/String;
   #4 = Class              #34            // org/kohsuke/github/GHBranchProtection$RequiredSignatures
   #5 = Class              #35            // java/lang/Object
   #6 = Utf8               enabled
   #7 = Utf8               Z
   #8 = Utf8               RuntimeVisibleAnnotations
   #9 = Utf8               Lcom/fasterxml/jackson/annotation/JsonProperty;
  #10 = Utf8               url
  #11 = Utf8               Ljava/lang/String;
  #12 = Utf8               <init>
  #13 = Utf8               ()V
  #14 = Utf8               Code
  #15 = Utf8               LineNumberTable
  #16 = Utf8               LocalVariableTable
  #17 = Utf8               this
  #18 = Utf8               RequiredSignatures
  #19 = Utf8               InnerClasses
  #20 = Utf8               Lorg/kohsuke/github/GHBranchProtection$RequiredSignatures;
  #21 = Utf8               getUrl
  #22 = Utf8               ()Ljava/lang/String;
  #23 = Utf8               isEnabled
  #24 = Utf8               ()Z
  #25 = Utf8               access$000
  #26 = Utf8               (Lorg/kohsuke/github/GHBranchProtection$RequiredSignatures;)Z
  #27 = Utf8               x0
  #28 = Utf8               SourceFile
  #29 = Utf8               GHBranchProtection.java
  #30 = NameAndType        #6:#7          // enabled:Z
  #31 = NameAndType        #12:#13        // "<init>":()V
  #32 = NameAndType        #10:#11        // url:Ljava/lang/String;
  #33 = Class              #36            // org/kohsuke/github/GHBranchProtection
  #34 = Utf8               org/kohsuke/github/GHBranchProtection$RequiredSignatures
  #35 = Utf8               java/lang/Object
  #36 = Utf8               org/kohsuke/github/GHBranchProtection
{
  private boolean enabled;
    descriptor: Z
    flags: (0x0002) ACC_PRIVATE
    RuntimeVisibleAnnotations:
      0: #9()
        com.fasterxml.jackson.annotation.JsonProperty

  private java.lang.String url;
    descriptor: Ljava/lang/String;
    flags: (0x0002) ACC_PRIVATE
    RuntimeVisibleAnnotations:
      0: #9()
        com.fasterxml.jackson.annotation.JsonProperty

  private org.kohsuke.github.GHBranchProtection$RequiredSignatures();
    descriptor: ()V
    flags: (0x0002) ACC_PRIVATE
    Code:
      stack=1, locals=1, args_size=1
         0: aload_0
         1: invokespecial #2                  // Method java/lang/Object."<init>":()V
         4: return
      LineNumberTable:
        line 214: 0
      LocalVariableTable:
        Start  Length  Slot  Name   Signature
            0       5     0  this   Lorg/kohsuke/github/GHBranchProtection$RequiredSignatures;

  public java.lang.String getUrl();
    descriptor: ()Ljava/lang/String;
    flags: (0x0001) ACC_PUBLIC
    Code:
      stack=1, locals=1, args_size=1
         0: aload_0
         1: getfield      #3                  // Field url:Ljava/lang/String;
         4: areturn
      LineNumberTable:
        line 227: 0
      LocalVariableTable:
        Start  Length  Slot  Name   Signature
            0       5     0  this   Lorg/kohsuke/github/GHBranchProtection$RequiredSignatures;

  public boolean isEnabled();
    descriptor: ()Z
    flags: (0x0001) ACC_PUBLIC
    Code:
      stack=1, locals=1, args_size=1
         0: aload_0
         1: getfield      #1                  // Field enabled:Z
         4: ireturn
      LineNumberTable:
        line 236: 0
      LocalVariableTable:
        Start  Length  Slot  Name   Signature
            0       5     0  this   Lorg/kohsuke/github/GHBranchProtection$RequiredSignatures;

  static boolean access$000(org.kohsuke.github.GHBranchProtection$RequiredSignatures);
    descriptor: (Lorg/kohsuke/github/GHBranchProtection$RequiredSignatures;)Z
    flags: (0x1008) ACC_STATIC, ACC_SYNTHETIC
    Code:
      stack=1, locals=1, args_size=1
         0: aload_0
         1: getfield      #1                  // Field enabled:Z
         4: ireturn
      LineNumberTable:
        line 214: 0
      LocalVariableTable:
        Start  Length  Slot  Name   Signature
            0       5     0    x0   Lorg/kohsuke/github/GHBranchProtection$RequiredSignatures;
}
SourceFile: "GHBranchProtection.java"
InnerClasses:
  private static #18= #4 of #33;          // RequiredSignatures=class org/kohsuke/github/GHBranchProtection$RequiredSignatures of class org/kohsuke/github/GHBranchProtection
