Classfile /Users/mw/Projects/slang-braindump/.jar/jar8/assemble/slang-braindump/assemble/content/org/kohsuke/github/GHBranchProtection$RequiredStatusChecks.class
  Last modified May 29, 2022; size 1223 bytes
  SHA-256 checksum a5de258e69ea2a92301c3423faaf4bcdef3fac0a0c92e01622165b3867a6e7aa
  Compiled from "GHBranchProtection.java"
public class org.kohsuke.github.GHBranchProtection$RequiredStatusChecks
  minor version: 0
  major version: 52
  flags: (0x0021) ACC_PUBLIC, ACC_SUPER
  this_class: #6                          // org/kohsuke/github/GHBranchProtection$RequiredStatusChecks
  super_class: #7                         // java/lang/Object
  interfaces: 0, fields: 3, methods: 4, attributes: 2
Constant pool:
   #1 = Methodref          #7.#36         // java/lang/Object."<init>":()V
   #2 = Fieldref           #6.#37         // org/kohsuke/github/GHBranchProtection$RequiredStatusChecks.contexts:Ljava/util/Collection;
   #3 = Methodref          #38.#39        // java/util/Collections.unmodifiableCollection:(Ljava/util/Collection;)Ljava/util/Collection;
   #4 = Fieldref           #6.#40         // org/kohsuke/github/GHBranchProtection$RequiredStatusChecks.url:Ljava/lang/String;
   #5 = Fieldref           #6.#41         // org/kohsuke/github/GHBranchProtection$RequiredStatusChecks.strict:Z
   #6 = Class              #43            // org/kohsuke/github/GHBranchProtection$RequiredStatusChecks
   #7 = Class              #44            // java/lang/Object
   #8 = Utf8               contexts
   #9 = Utf8               Ljava/util/Collection;
  #10 = Utf8               Signature
  #11 = Utf8               Ljava/util/Collection<Ljava/lang/String;>;
  #12 = Utf8               RuntimeVisibleAnnotations
  #13 = Utf8               Lcom/fasterxml/jackson/annotation/JsonProperty;
  #14 = Utf8               strict
  #15 = Utf8               Z
  #16 = Utf8               url
  #17 = Utf8               Ljava/lang/String;
  #18 = Utf8               <init>
  #19 = Utf8               ()V
  #20 = Utf8               Code
  #21 = Utf8               LineNumberTable
  #22 = Utf8               LocalVariableTable
  #23 = Utf8               this
  #24 = Utf8               RequiredStatusChecks
  #25 = Utf8               InnerClasses
  #26 = Utf8               Lorg/kohsuke/github/GHBranchProtection$RequiredStatusChecks;
  #27 = Utf8               getContexts
  #28 = Utf8               ()Ljava/util/Collection;
  #29 = Utf8               ()Ljava/util/Collection<Ljava/lang/String;>;
  #30 = Utf8               getUrl
  #31 = Utf8               ()Ljava/lang/String;
  #32 = Utf8               isRequiresBranchUpToDate
  #33 = Utf8               ()Z
  #34 = Utf8               SourceFile
  #35 = Utf8               GHBranchProtection.java
  #36 = NameAndType        #18:#19        // "<init>":()V
  #37 = NameAndType        #8:#9          // contexts:Ljava/util/Collection;
  #38 = Class              #45            // java/util/Collections
  #39 = NameAndType        #46:#47        // unmodifiableCollection:(Ljava/util/Collection;)Ljava/util/Collection;
  #40 = NameAndType        #16:#17        // url:Ljava/lang/String;
  #41 = NameAndType        #14:#15        // strict:Z
  #42 = Class              #48            // org/kohsuke/github/GHBranchProtection
  #43 = Utf8               org/kohsuke/github/GHBranchProtection$RequiredStatusChecks
  #44 = Utf8               java/lang/Object
  #45 = Utf8               java/util/Collections
  #46 = Utf8               unmodifiableCollection
  #47 = Utf8               (Ljava/util/Collection;)Ljava/util/Collection;
  #48 = Utf8               org/kohsuke/github/GHBranchProtection
{
  private java.util.Collection<java.lang.String> contexts;
    descriptor: Ljava/util/Collection;
    flags: (0x0002) ACC_PRIVATE
    Signature: #11                          // Ljava/util/Collection<Ljava/lang/String;>;
    RuntimeVisibleAnnotations:
      0: #13()
        com.fasterxml.jackson.annotation.JsonProperty

  private boolean strict;
    descriptor: Z
    flags: (0x0002) ACC_PRIVATE
    RuntimeVisibleAnnotations:
      0: #13()
        com.fasterxml.jackson.annotation.JsonProperty

  private java.lang.String url;
    descriptor: Ljava/lang/String;
    flags: (0x0002) ACC_PRIVATE
    RuntimeVisibleAnnotations:
      0: #13()
        com.fasterxml.jackson.annotation.JsonProperty

  public org.kohsuke.github.GHBranchProtection$RequiredStatusChecks();
    descriptor: ()V
    flags: (0x0001) ACC_PUBLIC
    Code:
      stack=1, locals=1, args_size=1
         0: aload_0
         1: invokespecial #1                  // Method java/lang/Object."<init>":()V
         4: return
      LineNumberTable:
        line 243: 0
      LocalVariableTable:
        Start  Length  Slot  Name   Signature
            0       5     0  this   Lorg/kohsuke/github/GHBranchProtection$RequiredStatusChecks;

  public java.util.Collection<java.lang.String> getContexts();
    descriptor: ()Ljava/util/Collection;
    flags: (0x0001) ACC_PUBLIC
    Code:
      stack=1, locals=1, args_size=1
         0: aload_0
         1: getfield      #2                  // Field contexts:Ljava/util/Collection;
         4: invokestatic  #3                  // Method java/util/Collections.unmodifiableCollection:(Ljava/util/Collection;)Ljava/util/Collection;
         7: areturn
      LineNumberTable:
        line 259: 0
      LocalVariableTable:
        Start  Length  Slot  Name   Signature
            0       8     0  this   Lorg/kohsuke/github/GHBranchProtection$RequiredStatusChecks;
    Signature: #29                          // ()Ljava/util/Collection<Ljava/lang/String;>;

  public java.lang.String getUrl();
    descriptor: ()Ljava/lang/String;
    flags: (0x0001) ACC_PUBLIC
    Code:
      stack=1, locals=1, args_size=1
         0: aload_0
         1: getfield      #4                  // Field url:Ljava/lang/String;
         4: areturn
      LineNumberTable:
        line 268: 0
      LocalVariableTable:
        Start  Length  Slot  Name   Signature
            0       5     0  this   Lorg/kohsuke/github/GHBranchProtection$RequiredStatusChecks;

  public boolean isRequiresBranchUpToDate();
    descriptor: ()Z
    flags: (0x0001) ACC_PUBLIC
    Code:
      stack=1, locals=1, args_size=1
         0: aload_0
         1: getfield      #5                  // Field strict:Z
         4: ireturn
      LineNumberTable:
        line 277: 0
      LocalVariableTable:
        Start  Length  Slot  Name   Signature
            0       5     0  this   Lorg/kohsuke/github/GHBranchProtection$RequiredStatusChecks;
}
SourceFile: "GHBranchProtection.java"
InnerClasses:
  public static #24= #6 of #42;           // RequiredStatusChecks=class org/kohsuke/github/GHBranchProtection$RequiredStatusChecks of class org/kohsuke/github/GHBranchProtection
