Classfile /Users/mw/Projects/slang-braindump/.jar/jar8/assemble/slang-braindump/assemble/content/org/kohsuke/github/GHCommitStatus.class
  Last modified May 29, 2022; size 1920 bytes
  SHA-256 checksum 3b0f1fd70b6c4ecb9e3aa0bf5b519c71c8b73fe7483c15eb5590b2f9d0984d89
  Compiled from "GHCommitStatus.java"
public class org.kohsuke.github.GHCommitStatus extends org.kohsuke.github.GHObject
  minor version: 0
  major version: 52
  flags: (0x0021) ACC_PUBLIC, ACC_SUPER
  this_class: #19                         // org/kohsuke/github/GHCommitStatus
  super_class: #20                        // org/kohsuke/github/GHObject
  interfaces: 0, fields: 5, methods: 7, attributes: 1
Constant pool:
   #1 = Methodref          #20.#54        // org/kohsuke/github/GHObject."<init>":()V
   #2 = Methodref          #55.#56        // org/kohsuke/github/GHCommitState.values:()[Lorg/kohsuke/github/GHCommitState;
   #3 = Methodref          #55.#57        // org/kohsuke/github/GHCommitState.name:()Ljava/lang/String;
   #4 = Fieldref           #19.#58        // org/kohsuke/github/GHCommitStatus.state:Ljava/lang/String;
   #5 = Methodref          #59.#60        // java/lang/String.equalsIgnoreCase:(Ljava/lang/String;)Z
   #6 = Class              #61            // java/lang/IllegalStateException
   #7 = Class              #62            // java/lang/StringBuilder
   #8 = Methodref          #7.#54         // java/lang/StringBuilder."<init>":()V
   #9 = String             #63            // Unexpected state:
  #10 = Methodref          #7.#64         // java/lang/StringBuilder.append:(Ljava/lang/String;)Ljava/lang/StringBuilder;
  #11 = Methodref          #7.#65         // java/lang/StringBuilder.toString:()Ljava/lang/String;
  #12 = Methodref          #6.#66         // java/lang/IllegalStateException."<init>":(Ljava/lang/String;)V
  #13 = Fieldref           #19.#67        // org/kohsuke/github/GHCommitStatus.target_url:Ljava/lang/String;
  #14 = Fieldref           #19.#68        // org/kohsuke/github/GHCommitStatus.description:Ljava/lang/String;
  #15 = Methodref          #19.#69        // org/kohsuke/github/GHCommitStatus.root:()Lorg/kohsuke/github/GitHub;
  #16 = Fieldref           #19.#70        // org/kohsuke/github/GHCommitStatus.creator:Lorg/kohsuke/github/GHUser;
  #17 = Methodref          #71.#72        // org/kohsuke/github/GitHub.intern:(Lorg/kohsuke/github/GHUser;)Lorg/kohsuke/github/GHUser;
  #18 = Fieldref           #19.#73        // org/kohsuke/github/GHCommitStatus.context:Ljava/lang/String;
  #19 = Class              #74            // org/kohsuke/github/GHCommitStatus
  #20 = Class              #75            // org/kohsuke/github/GHObject
  #21 = Utf8               state
  #22 = Utf8               Ljava/lang/String;
  #23 = Utf8               target_url
  #24 = Utf8               description
  #25 = Utf8               context
  #26 = Utf8               creator
  #27 = Utf8               Lorg/kohsuke/github/GHUser;
  #28 = Utf8               <init>
  #29 = Utf8               ()V
  #30 = Utf8               Code
  #31 = Utf8               LineNumberTable
  #32 = Utf8               LocalVariableTable
  #33 = Utf8               this
  #34 = Utf8               Lorg/kohsuke/github/GHCommitStatus;
  #35 = Utf8               getState
  #36 = Utf8               ()Lorg/kohsuke/github/GHCommitState;
  #37 = Utf8               s
  #38 = Utf8               Lorg/kohsuke/github/GHCommitState;
  #39 = Utf8               StackMapTable
  #40 = Class              #76            // "[Lorg/kohsuke/github/GHCommitState;"
  #41 = Utf8               getTargetUrl
  #42 = Utf8               ()Ljava/lang/String;
  #43 = Utf8               getDescription
  #44 = Utf8               getCreator
  #45 = Utf8               ()Lorg/kohsuke/github/GHUser;
  #46 = Utf8               Exceptions
  #47 = Class              #77            // java/io/IOException
  #48 = Utf8               getContext
  #49 = Utf8               getHtmlUrl
  #50 = Utf8               ()Ljava/net/URL;
  #51 = Utf8               Deprecated
  #52 = Utf8               SourceFile
  #53 = Utf8               GHCommitStatus.java
  #54 = NameAndType        #28:#29        // "<init>":()V
  #55 = Class              #78            // org/kohsuke/github/GHCommitState
  #56 = NameAndType        #79:#80        // values:()[Lorg/kohsuke/github/GHCommitState;
  #57 = NameAndType        #81:#42        // name:()Ljava/lang/String;
  #58 = NameAndType        #21:#22        // state:Ljava/lang/String;
  #59 = Class              #82            // java/lang/String
  #60 = NameAndType        #83:#84        // equalsIgnoreCase:(Ljava/lang/String;)Z
  #61 = Utf8               java/lang/IllegalStateException
  #62 = Utf8               java/lang/StringBuilder
  #63 = Utf8               Unexpected state:
  #64 = NameAndType        #85:#86        // append:(Ljava/lang/String;)Ljava/lang/StringBuilder;
  #65 = NameAndType        #87:#42        // toString:()Ljava/lang/String;
  #66 = NameAndType        #28:#88        // "<init>":(Ljava/lang/String;)V
  #67 = NameAndType        #23:#22        // target_url:Ljava/lang/String;
  #68 = NameAndType        #24:#22        // description:Ljava/lang/String;
  #69 = NameAndType        #89:#90        // root:()Lorg/kohsuke/github/GitHub;
  #70 = NameAndType        #26:#27        // creator:Lorg/kohsuke/github/GHUser;
  #71 = Class              #91            // org/kohsuke/github/GitHub
  #72 = NameAndType        #92:#93        // intern:(Lorg/kohsuke/github/GHUser;)Lorg/kohsuke/github/GHUser;
  #73 = NameAndType        #25:#22        // context:Ljava/lang/String;
  #74 = Utf8               org/kohsuke/github/GHCommitStatus
  #75 = Utf8               org/kohsuke/github/GHObject
  #76 = Utf8               [Lorg/kohsuke/github/GHCommitState;
  #77 = Utf8               java/io/IOException
  #78 = Utf8               org/kohsuke/github/GHCommitState
  #79 = Utf8               values
  #80 = Utf8               ()[Lorg/kohsuke/github/GHCommitState;
  #81 = Utf8               name
  #82 = Utf8               java/lang/String
  #83 = Utf8               equalsIgnoreCase
  #84 = Utf8               (Ljava/lang/String;)Z
  #85 = Utf8               append
  #86 = Utf8               (Ljava/lang/String;)Ljava/lang/StringBuilder;
  #87 = Utf8               toString
  #88 = Utf8               (Ljava/lang/String;)V
  #89 = Utf8               root
  #90 = Utf8               ()Lorg/kohsuke/github/GitHub;
  #91 = Utf8               org/kohsuke/github/GitHub
  #92 = Utf8               intern
  #93 = Utf8               (Lorg/kohsuke/github/GHUser;)Lorg/kohsuke/github/GHUser;
{
  java.lang.String state;
    descriptor: Ljava/lang/String;
    flags: (0x0000)

  java.lang.String target_url;
    descriptor: Ljava/lang/String;
    flags: (0x0000)

  java.lang.String description;
    descriptor: Ljava/lang/String;
    flags: (0x0000)

  java.lang.String context;
    descriptor: Ljava/lang/String;
    flags: (0x0000)

  org.kohsuke.github.GHUser creator;
    descriptor: Lorg/kohsuke/github/GHUser;
    flags: (0x0000)

  public org.kohsuke.github.GHCommitStatus();
    descriptor: ()V
    flags: (0x0001) ACC_PUBLIC
    Code:
      stack=1, locals=1, args_size=1
         0: aload_0
         1: invokespecial #1                  // Method org/kohsuke/github/GHObject."<init>":()V
         4: return
      LineNumberTable:
        line 15: 0
      LocalVariableTable:
        Start  Length  Slot  Name   Signature
            0       5     0  this   Lorg/kohsuke/github/GHCommitStatus;

  public org.kohsuke.github.GHCommitState getState();
    descriptor: ()Lorg/kohsuke/github/GHCommitState;
    flags: (0x0001) ACC_PUBLIC
    Code:
      stack=4, locals=5, args_size=1
         0: invokestatic  #2                  // Method org/kohsuke/github/GHCommitState.values:()[Lorg/kohsuke/github/GHCommitState;
         3: astore_1
         4: aload_1
         5: arraylength
         6: istore_2
         7: iconst_0
         8: istore_3
         9: iload_3
        10: iload_2
        11: if_icmpge     43
        14: aload_1
        15: iload_3
        16: aaload
        17: astore        4
        19: aload         4
        21: invokevirtual #3                  // Method org/kohsuke/github/GHCommitState.name:()Ljava/lang/String;
        24: aload_0
        25: getfield      #4                  // Field state:Ljava/lang/String;
        28: invokevirtual #5                  // Method java/lang/String.equalsIgnoreCase:(Ljava/lang/String;)Z
        31: ifeq          37
        34: aload         4
        36: areturn
        37: iinc          3, 1
        40: goto          9
        43: new           #6                  // class java/lang/IllegalStateException
        46: dup
        47: new           #7                  // class java/lang/StringBuilder
        50: dup
        51: invokespecial #8                  // Method java/lang/StringBuilder."<init>":()V
        54: ldc           #9                  // String Unexpected state:
        56: invokevirtual #10                 // Method java/lang/StringBuilder.append:(Ljava/lang/String;)Ljava/lang/StringBuilder;
        59: aload_0
        60: getfield      #4                  // Field state:Ljava/lang/String;
        63: invokevirtual #10                 // Method java/lang/StringBuilder.append:(Ljava/lang/String;)Ljava/lang/StringBuilder;
        66: invokevirtual #11                 // Method java/lang/StringBuilder.toString:()Ljava/lang/String;
        69: invokespecial #12                 // Method java/lang/IllegalStateException."<init>":(Ljava/lang/String;)V
        72: athrow
      LineNumberTable:
        line 27: 0
        line 28: 19
        line 29: 34
        line 27: 37
        line 31: 43
      LocalVariableTable:
        Start  Length  Slot  Name   Signature
           19      18     4     s   Lorg/kohsuke/github/GHCommitState;
            0      73     0  this   Lorg/kohsuke/github/GHCommitStatus;
      StackMapTable: number_of_entries = 3
        frame_type = 254 /* append */
          offset_delta = 9
          locals = [ class "[Lorg/kohsuke/github/GHCommitState;", int, int ]
        frame_type = 27 /* same */
        frame_type = 248 /* chop */
          offset_delta = 5

  public java.lang.String getTargetUrl();
    descriptor: ()Ljava/lang/String;
    flags: (0x0001) ACC_PUBLIC
    Code:
      stack=1, locals=1, args_size=1
         0: aload_0
         1: getfield      #13                 // Field target_url:Ljava/lang/String;
         4: areturn
      LineNumberTable:
        line 42: 0
      LocalVariableTable:
        Start  Length  Slot  Name   Signature
            0       5     0  this   Lorg/kohsuke/github/GHCommitStatus;

  public java.lang.String getDescription();
    descriptor: ()Ljava/lang/String;
    flags: (0x0001) ACC_PUBLIC
    Code:
      stack=1, locals=1, args_size=1
         0: aload_0
         1: getfield      #14                 // Field description:Ljava/lang/String;
         4: areturn
      LineNumberTable:
        line 51: 0
      LocalVariableTable:
        Start  Length  Slot  Name   Signature
            0       5     0  this   Lorg/kohsuke/github/GHCommitStatus;

  public org.kohsuke.github.GHUser getCreator() throws java.io.IOException;
    descriptor: ()Lorg/kohsuke/github/GHUser;
    flags: (0x0001) ACC_PUBLIC
    Code:
      stack=2, locals=1, args_size=1
         0: aload_0
         1: invokevirtual #15                 // Method root:()Lorg/kohsuke/github/GitHub;
         4: aload_0
         5: getfield      #16                 // Field creator:Lorg/kohsuke/github/GHUser;
         8: invokevirtual #17                 // Method org/kohsuke/github/GitHub.intern:(Lorg/kohsuke/github/GHUser;)Lorg/kohsuke/github/GHUser;
        11: areturn
      LineNumberTable:
        line 62: 0
      LocalVariableTable:
        Start  Length  Slot  Name   Signature
            0      12     0  this   Lorg/kohsuke/github/GHCommitStatus;
    Exceptions:
      throws java.io.IOException

  public java.lang.String getContext();
    descriptor: ()Ljava/lang/String;
    flags: (0x0001) ACC_PUBLIC
    Code:
      stack=1, locals=1, args_size=1
         0: aload_0
         1: getfield      #18                 // Field context:Ljava/lang/String;
         4: areturn
      LineNumberTable:
        line 71: 0
      LocalVariableTable:
        Start  Length  Slot  Name   Signature
            0       5     0  this   Lorg/kohsuke/github/GHCommitStatus;

  public java.net.URL getHtmlUrl();
    descriptor: ()Ljava/net/URL;
    flags: (0x0001) ACC_PUBLIC
    Code:
      stack=1, locals=1, args_size=1
         0: aconst_null
         1: areturn
      LineNumberTable:
        line 79: 0
      LocalVariableTable:
        Start  Length  Slot  Name   Signature
            0       2     0  this   Lorg/kohsuke/github/GHCommitStatus;
    Deprecated: true
}
SourceFile: "GHCommitStatus.java"
