Classfile /Users/mw/Projects/slang-braindump/.jar/jar8/assemble/slang-braindump/assemble/content/org/kohsuke/github/GHContentBuilder.class
  Last modified May 29, 2022; size 3091 bytes
  SHA-256 checksum 31aa2598964d9093bad544fa5b76531a0bd73e2da436ec0dd63c9854ecdf353c
  Compiled from "GHContentBuilder.java"
public final class org.kohsuke.github.GHContentBuilder
  minor version: 0
  major version: 52
  flags: (0x0031) ACC_PUBLIC, ACC_FINAL, ACC_SUPER
  this_class: #30                         // org/kohsuke/github/GHContentBuilder
  super_class: #31                        // java/lang/Object
  interfaces: 0, fields: 3, methods: 8, attributes: 2
Constant pool:
    #1 = Methodref          #31.#61       // java/lang/Object."<init>":()V
    #2 = Fieldref           #30.#62       // org/kohsuke/github/GHContentBuilder.repo:Lorg/kohsuke/github/GHRepository;
    #3 = Methodref          #63.#64       // org/kohsuke/github/GHRepository.root:()Lorg/kohsuke/github/GitHub;
    #4 = Methodref          #65.#66       // org/kohsuke/github/GitHub.createRequest:()Lorg/kohsuke/github/Requester;
    #5 = String             #67           // PUT
    #6 = Methodref          #7.#68        // org/kohsuke/github/Requester.method:(Ljava/lang/String;)Lorg/kohsuke/github/GitHubRequest$Builder;
    #7 = Class              #69           // org/kohsuke/github/Requester
    #8 = Fieldref           #30.#70       // org/kohsuke/github/GHContentBuilder.req:Lorg/kohsuke/github/Requester;
    #9 = Fieldref           #30.#71       // org/kohsuke/github/GHContentBuilder.path:Ljava/lang/String;
   #10 = String             #36           // path
   #11 = Methodref          #7.#72        // org/kohsuke/github/Requester.with:(Ljava/lang/String;Ljava/lang/String;)Lorg/kohsuke/github/GitHubRequest$Builder;
   #12 = String             #46           // branch
   #13 = String             #47           // sha
   #14 = String             #48           // content
   #15 = Methodref          #73.#74       // java/util/Base64.getEncoder:()Ljava/util/Base64$Encoder;
   #16 = Methodref          #75.#76       // java/util/Base64$Encoder.encodeToString:([B)Ljava/lang/String;
   #17 = Fieldref           #77.#78       // java/nio/charset/StandardCharsets.UTF_8:Ljava/nio/charset/Charset;
   #18 = Methodref          #22.#79       // java/lang/String.getBytes:(Ljava/nio/charset/Charset;)[B
   #19 = Methodref          #30.#80       // org/kohsuke/github/GHContentBuilder.content:([B)Lorg/kohsuke/github/GHContentBuilder;
   #20 = String             #51           // message
   #21 = Methodref          #81.#82       // org/kohsuke/github/GHContent.getApiRoute:(Lorg/kohsuke/github/GHRepository;Ljava/lang/String;)Ljava/lang/String;
   #22 = Class              #83           // java/lang/String
   #23 = Methodref          #7.#84        // org/kohsuke/github/Requester.withUrlPath:(Ljava/lang/String;[Ljava/lang/String;)Lorg/kohsuke/github/GitHubRequest$Builder;
   #24 = Class              #85           // org/kohsuke/github/GHContentUpdateResponse
   #25 = Methodref          #7.#86        // org/kohsuke/github/Requester.fetch:(Ljava/lang/Class;)Ljava/lang/Object;
   #26 = Methodref          #24.#87       // org/kohsuke/github/GHContentUpdateResponse.getContent:()Lorg/kohsuke/github/GHContent;
   #27 = Methodref          #81.#88       // org/kohsuke/github/GHContent.wrap:(Lorg/kohsuke/github/GHRepository;)Lorg/kohsuke/github/GHContent;
   #28 = Methodref          #24.#89       // org/kohsuke/github/GHContentUpdateResponse.getCommit:()Lorg/kohsuke/github/GHCommit;
   #29 = Methodref          #90.#91       // org/kohsuke/github/GHCommit.wrapUp:(Lorg/kohsuke/github/GHRepository;)Lorg/kohsuke/github/GHCommit;
   #30 = Class              #92           // org/kohsuke/github/GHContentBuilder
   #31 = Class              #93           // java/lang/Object
   #32 = Utf8               repo
   #33 = Utf8               Lorg/kohsuke/github/GHRepository;
   #34 = Utf8               req
   #35 = Utf8               Lorg/kohsuke/github/Requester;
   #36 = Utf8               path
   #37 = Utf8               Ljava/lang/String;
   #38 = Utf8               <init>
   #39 = Utf8               (Lorg/kohsuke/github/GHRepository;)V
   #40 = Utf8               Code
   #41 = Utf8               LineNumberTable
   #42 = Utf8               LocalVariableTable
   #43 = Utf8               this
   #44 = Utf8               Lorg/kohsuke/github/GHContentBuilder;
   #45 = Utf8               (Ljava/lang/String;)Lorg/kohsuke/github/GHContentBuilder;
   #46 = Utf8               branch
   #47 = Utf8               sha
   #48 = Utf8               content
   #49 = Utf8               ([B)Lorg/kohsuke/github/GHContentBuilder;
   #50 = Utf8               [B
   #51 = Utf8               message
   #52 = Utf8               commitMessage
   #53 = Utf8               commit
   #54 = Utf8               ()Lorg/kohsuke/github/GHContentUpdateResponse;
   #55 = Utf8               response
   #56 = Utf8               Lorg/kohsuke/github/GHContentUpdateResponse;
   #57 = Utf8               Exceptions
   #58 = Class              #94           // java/io/IOException
   #59 = Utf8               SourceFile
   #60 = Utf8               GHContentBuilder.java
   #61 = NameAndType        #38:#95       // "<init>":()V
   #62 = NameAndType        #32:#33       // repo:Lorg/kohsuke/github/GHRepository;
   #63 = Class              #96           // org/kohsuke/github/GHRepository
   #64 = NameAndType        #97:#98       // root:()Lorg/kohsuke/github/GitHub;
   #65 = Class              #99           // org/kohsuke/github/GitHub
   #66 = NameAndType        #100:#101     // createRequest:()Lorg/kohsuke/github/Requester;
   #67 = Utf8               PUT
   #68 = NameAndType        #102:#106     // method:(Ljava/lang/String;)Lorg/kohsuke/github/GitHubRequest$Builder;
   #69 = Utf8               org/kohsuke/github/Requester
   #70 = NameAndType        #34:#35       // req:Lorg/kohsuke/github/Requester;
   #71 = NameAndType        #36:#37       // path:Ljava/lang/String;
   #72 = NameAndType        #107:#108     // with:(Ljava/lang/String;Ljava/lang/String;)Lorg/kohsuke/github/GitHubRequest$Builder;
   #73 = Class              #109          // java/util/Base64
   #74 = NameAndType        #110:#112     // getEncoder:()Ljava/util/Base64$Encoder;
   #75 = Class              #113          // java/util/Base64$Encoder
   #76 = NameAndType        #114:#115     // encodeToString:([B)Ljava/lang/String;
   #77 = Class              #116          // java/nio/charset/StandardCharsets
   #78 = NameAndType        #117:#118     // UTF_8:Ljava/nio/charset/Charset;
   #79 = NameAndType        #119:#120     // getBytes:(Ljava/nio/charset/Charset;)[B
   #80 = NameAndType        #48:#49       // content:([B)Lorg/kohsuke/github/GHContentBuilder;
   #81 = Class              #121          // org/kohsuke/github/GHContent
   #82 = NameAndType        #122:#123     // getApiRoute:(Lorg/kohsuke/github/GHRepository;Ljava/lang/String;)Ljava/lang/String;
   #83 = Utf8               java/lang/String
   #84 = NameAndType        #124:#125     // withUrlPath:(Ljava/lang/String;[Ljava/lang/String;)Lorg/kohsuke/github/GitHubRequest$Builder;
   #85 = Utf8               org/kohsuke/github/GHContentUpdateResponse
   #86 = NameAndType        #126:#127     // fetch:(Ljava/lang/Class;)Ljava/lang/Object;
   #87 = NameAndType        #128:#129     // getContent:()Lorg/kohsuke/github/GHContent;
   #88 = NameAndType        #130:#131     // wrap:(Lorg/kohsuke/github/GHRepository;)Lorg/kohsuke/github/GHContent;
   #89 = NameAndType        #132:#133     // getCommit:()Lorg/kohsuke/github/GHCommit;
   #90 = Class              #134          // org/kohsuke/github/GHCommit
   #91 = NameAndType        #135:#136     // wrapUp:(Lorg/kohsuke/github/GHRepository;)Lorg/kohsuke/github/GHCommit;
   #92 = Utf8               org/kohsuke/github/GHContentBuilder
   #93 = Utf8               java/lang/Object
   #94 = Utf8               java/io/IOException
   #95 = Utf8               ()V
   #96 = Utf8               org/kohsuke/github/GHRepository
   #97 = Utf8               root
   #98 = Utf8               ()Lorg/kohsuke/github/GitHub;
   #99 = Utf8               org/kohsuke/github/GitHub
  #100 = Utf8               createRequest
  #101 = Utf8               ()Lorg/kohsuke/github/Requester;
  #102 = Utf8               method
  #103 = Class              #138          // org/kohsuke/github/GitHubRequest$Builder
  #104 = Utf8               Builder
  #105 = Utf8               InnerClasses
  #106 = Utf8               (Ljava/lang/String;)Lorg/kohsuke/github/GitHubRequest$Builder;
  #107 = Utf8               with
  #108 = Utf8               (Ljava/lang/String;Ljava/lang/String;)Lorg/kohsuke/github/GitHubRequest$Builder;
  #109 = Utf8               java/util/Base64
  #110 = Utf8               getEncoder
  #111 = Utf8               Encoder
  #112 = Utf8               ()Ljava/util/Base64$Encoder;
  #113 = Utf8               java/util/Base64$Encoder
  #114 = Utf8               encodeToString
  #115 = Utf8               ([B)Ljava/lang/String;
  #116 = Utf8               java/nio/charset/StandardCharsets
  #117 = Utf8               UTF_8
  #118 = Utf8               Ljava/nio/charset/Charset;
  #119 = Utf8               getBytes
  #120 = Utf8               (Ljava/nio/charset/Charset;)[B
  #121 = Utf8               org/kohsuke/github/GHContent
  #122 = Utf8               getApiRoute
  #123 = Utf8               (Lorg/kohsuke/github/GHRepository;Ljava/lang/String;)Ljava/lang/String;
  #124 = Utf8               withUrlPath
  #125 = Utf8               (Ljava/lang/String;[Ljava/lang/String;)Lorg/kohsuke/github/GitHubRequest$Builder;
  #126 = Utf8               fetch
  #127 = Utf8               (Ljava/lang/Class;)Ljava/lang/Object;
  #128 = Utf8               getContent
  #129 = Utf8               ()Lorg/kohsuke/github/GHContent;
  #130 = Utf8               wrap
  #131 = Utf8               (Lorg/kohsuke/github/GHRepository;)Lorg/kohsuke/github/GHContent;
  #132 = Utf8               getCommit
  #133 = Utf8               ()Lorg/kohsuke/github/GHCommit;
  #134 = Utf8               org/kohsuke/github/GHCommit
  #135 = Utf8               wrapUp
  #136 = Utf8               (Lorg/kohsuke/github/GHRepository;)Lorg/kohsuke/github/GHCommit;
  #137 = Class              #139          // org/kohsuke/github/GitHubRequest
  #138 = Utf8               org/kohsuke/github/GitHubRequest$Builder
  #139 = Utf8               org/kohsuke/github/GitHubRequest
{
  private final org.kohsuke.github.GHRepository repo;
    descriptor: Lorg/kohsuke/github/GHRepository;
    flags: (0x0012) ACC_PRIVATE, ACC_FINAL

  private final org.kohsuke.github.Requester req;
    descriptor: Lorg/kohsuke/github/Requester;
    flags: (0x0012) ACC_PRIVATE, ACC_FINAL

  private java.lang.String path;
    descriptor: Ljava/lang/String;
    flags: (0x0002) ACC_PRIVATE

  org.kohsuke.github.GHContentBuilder(org.kohsuke.github.GHRepository);
    descriptor: (Lorg/kohsuke/github/GHRepository;)V
    flags: (0x0000)
    Code:
      stack=3, locals=2, args_size=2
         0: aload_0
         1: invokespecial #1                  // Method java/lang/Object."<init>":()V
         4: aload_0
         5: aload_1
         6: putfield      #2                  // Field repo:Lorg/kohsuke/github/GHRepository;
         9: aload_0
        10: aload_1
        11: invokevirtual #3                  // Method org/kohsuke/github/GHRepository.root:()Lorg/kohsuke/github/GitHub;
        14: invokevirtual #4                  // Method org/kohsuke/github/GitHub.createRequest:()Lorg/kohsuke/github/Requester;
        17: ldc           #5                  // String PUT
        19: invokevirtual #6                  // Method org/kohsuke/github/Requester.method:(Ljava/lang/String;)Lorg/kohsuke/github/GitHubRequest$Builder;
        22: checkcast     #7                  // class org/kohsuke/github/Requester
        25: putfield      #8                  // Field req:Lorg/kohsuke/github/Requester;
        28: return
      LineNumberTable:
        line 21: 0
        line 22: 4
        line 23: 9
        line 24: 28
      LocalVariableTable:
        Start  Length  Slot  Name   Signature
            0      29     0  this   Lorg/kohsuke/github/GHContentBuilder;
            0      29     1  repo   Lorg/kohsuke/github/GHRepository;

  public org.kohsuke.github.GHContentBuilder path(java.lang.String);
    descriptor: (Ljava/lang/String;)Lorg/kohsuke/github/GHContentBuilder;
    flags: (0x0001) ACC_PUBLIC
    Code:
      stack=3, locals=2, args_size=2
         0: aload_0
         1: aload_1
         2: putfield      #9                  // Field path:Ljava/lang/String;
         5: aload_0
         6: getfield      #8                  // Field req:Lorg/kohsuke/github/Requester;
         9: ldc           #10                 // String path
        11: aload_1
        12: invokevirtual #11                 // Method org/kohsuke/github/Requester.with:(Ljava/lang/String;Ljava/lang/String;)Lorg/kohsuke/github/GitHubRequest$Builder;
        15: pop
        16: aload_0
        17: areturn
      LineNumberTable:
        line 34: 0
        line 35: 5
        line 36: 16
      LocalVariableTable:
        Start  Length  Slot  Name   Signature
            0      18     0  this   Lorg/kohsuke/github/GHContentBuilder;
            0      18     1  path   Ljava/lang/String;

  public org.kohsuke.github.GHContentBuilder branch(java.lang.String);
    descriptor: (Ljava/lang/String;)Lorg/kohsuke/github/GHContentBuilder;
    flags: (0x0001) ACC_PUBLIC
    Code:
      stack=3, locals=2, args_size=2
         0: aload_0
         1: getfield      #8                  // Field req:Lorg/kohsuke/github/Requester;
         4: ldc           #12                 // String branch
         6: aload_1
         7: invokevirtual #11                 // Method org/kohsuke/github/Requester.with:(Ljava/lang/String;Ljava/lang/String;)Lorg/kohsuke/github/GitHubRequest$Builder;
        10: pop
        11: aload_0
        12: areturn
      LineNumberTable:
        line 47: 0
        line 48: 11
      LocalVariableTable:
        Start  Length  Slot  Name   Signature
            0      13     0  this   Lorg/kohsuke/github/GHContentBuilder;
            0      13     1 branch   Ljava/lang/String;

  public org.kohsuke.github.GHContentBuilder sha(java.lang.String);
    descriptor: (Ljava/lang/String;)Lorg/kohsuke/github/GHContentBuilder;
    flags: (0x0001) ACC_PUBLIC
    Code:
      stack=3, locals=2, args_size=2
         0: aload_0
         1: getfield      #8                  // Field req:Lorg/kohsuke/github/Requester;
         4: ldc           #13                 // String sha
         6: aload_1
         7: invokevirtual #11                 // Method org/kohsuke/github/Requester.with:(Ljava/lang/String;Ljava/lang/String;)Lorg/kohsuke/github/GitHubRequest$Builder;
        10: pop
        11: aload_0
        12: areturn
      LineNumberTable:
        line 59: 0
        line 60: 11
      LocalVariableTable:
        Start  Length  Slot  Name   Signature
            0      13     0  this   Lorg/kohsuke/github/GHContentBuilder;
            0      13     1   sha   Ljava/lang/String;

  public org.kohsuke.github.GHContentBuilder content(byte[]);
    descriptor: ([B)Lorg/kohsuke/github/GHContentBuilder;
    flags: (0x0001) ACC_PUBLIC
    Code:
      stack=4, locals=2, args_size=2
         0: aload_0
         1: getfield      #8                  // Field req:Lorg/kohsuke/github/Requester;
         4: ldc           #14                 // String content
         6: invokestatic  #15                 // Method java/util/Base64.getEncoder:()Ljava/util/Base64$Encoder;
         9: aload_1
        10: invokevirtual #16                 // Method java/util/Base64$Encoder.encodeToString:([B)Ljava/lang/String;
        13: invokevirtual #11                 // Method org/kohsuke/github/Requester.with:(Ljava/lang/String;Ljava/lang/String;)Lorg/kohsuke/github/GitHubRequest$Builder;
        16: pop
        17: aload_0
        18: areturn
      LineNumberTable:
        line 71: 0
        line 72: 17
      LocalVariableTable:
        Start  Length  Slot  Name   Signature
            0      19     0  this   Lorg/kohsuke/github/GHContentBuilder;
            0      19     1 content   [B

  public org.kohsuke.github.GHContentBuilder content(java.lang.String);
    descriptor: (Ljava/lang/String;)Lorg/kohsuke/github/GHContentBuilder;
    flags: (0x0001) ACC_PUBLIC
    Code:
      stack=3, locals=2, args_size=2
         0: aload_0
         1: aload_1
         2: getstatic     #17                 // Field java/nio/charset/StandardCharsets.UTF_8:Ljava/nio/charset/Charset;
         5: invokevirtual #18                 // Method java/lang/String.getBytes:(Ljava/nio/charset/Charset;)[B
         8: invokevirtual #19                 // Method content:([B)Lorg/kohsuke/github/GHContentBuilder;
        11: areturn
      LineNumberTable:
        line 83: 0
      LocalVariableTable:
        Start  Length  Slot  Name   Signature
            0      12     0  this   Lorg/kohsuke/github/GHContentBuilder;
            0      12     1 content   Ljava/lang/String;

  public org.kohsuke.github.GHContentBuilder message(java.lang.String);
    descriptor: (Ljava/lang/String;)Lorg/kohsuke/github/GHContentBuilder;
    flags: (0x0001) ACC_PUBLIC
    Code:
      stack=3, locals=2, args_size=2
         0: aload_0
         1: getfield      #8                  // Field req:Lorg/kohsuke/github/Requester;
         4: ldc           #20                 // String message
         6: aload_1
         7: invokevirtual #11                 // Method org/kohsuke/github/Requester.with:(Ljava/lang/String;Ljava/lang/String;)Lorg/kohsuke/github/GitHubRequest$Builder;
        10: pop
        11: aload_0
        12: areturn
      LineNumberTable:
        line 94: 0
        line 95: 11
      LocalVariableTable:
        Start  Length  Slot  Name   Signature
            0      13     0  this   Lorg/kohsuke/github/GHContentBuilder;
            0      13     1 commitMessage   Ljava/lang/String;

  public org.kohsuke.github.GHContentUpdateResponse commit() throws java.io.IOException;
    descriptor: ()Lorg/kohsuke/github/GHContentUpdateResponse;
    flags: (0x0001) ACC_PUBLIC
    Code:
      stack=3, locals=2, args_size=1
         0: aload_0
         1: getfield      #8                  // Field req:Lorg/kohsuke/github/Requester;
         4: aload_0
         5: getfield      #2                  // Field repo:Lorg/kohsuke/github/GHRepository;
         8: aload_0
         9: getfield      #9                  // Field path:Ljava/lang/String;
        12: invokestatic  #21                 // Method org/kohsuke/github/GHContent.getApiRoute:(Lorg/kohsuke/github/GHRepository;Ljava/lang/String;)Ljava/lang/String;
        15: iconst_0
        16: anewarray     #22                 // class java/lang/String
        19: invokevirtual #23                 // Method org/kohsuke/github/Requester.withUrlPath:(Ljava/lang/String;[Ljava/lang/String;)Lorg/kohsuke/github/GitHubRequest$Builder;
        22: checkcast     #7                  // class org/kohsuke/github/Requester
        25: ldc           #24                 // class org/kohsuke/github/GHContentUpdateResponse
        27: invokevirtual #25                 // Method org/kohsuke/github/Requester.fetch:(Ljava/lang/Class;)Ljava/lang/Object;
        30: checkcast     #24                 // class org/kohsuke/github/GHContentUpdateResponse
        33: astore_1
        34: aload_1
        35: invokevirtual #26                 // Method org/kohsuke/github/GHContentUpdateResponse.getContent:()Lorg/kohsuke/github/GHContent;
        38: aload_0
        39: getfield      #2                  // Field repo:Lorg/kohsuke/github/GHRepository;
        42: invokevirtual #27                 // Method org/kohsuke/github/GHContent.wrap:(Lorg/kohsuke/github/GHRepository;)Lorg/kohsuke/github/GHContent;
        45: pop
        46: aload_1
        47: invokevirtual #28                 // Method org/kohsuke/github/GHContentUpdateResponse.getCommit:()Lorg/kohsuke/github/GHCommit;
        50: aload_0
        51: getfield      #2                  // Field repo:Lorg/kohsuke/github/GHRepository;
        54: invokevirtual #29                 // Method org/kohsuke/github/GHCommit.wrapUp:(Lorg/kohsuke/github/GHRepository;)Lorg/kohsuke/github/GHCommit;
        57: pop
        58: aload_1
        59: areturn
      LineNumberTable:
        line 106: 0
        line 107: 27
        line 109: 34
        line 110: 46
        line 112: 58
      LocalVariableTable:
        Start  Length  Slot  Name   Signature
            0      60     0  this   Lorg/kohsuke/github/GHContentBuilder;
           34      26     1 response   Lorg/kohsuke/github/GHContentUpdateResponse;
    Exceptions:
      throws java.io.IOException
}
SourceFile: "GHContentBuilder.java"
InnerClasses:
  static #104= #103 of #137;              // Builder=class org/kohsuke/github/GitHubRequest$Builder of class org/kohsuke/github/GitHubRequest
  public static #111= #75 of #73;         // Encoder=class java/util/Base64$Encoder of class java/util/Base64
