Classfile /Users/mw/Projects/slang-braindump/.jar/jar8/assemble/slang-braindump/assemble/content/org/kohsuke/github/GHCompare$Commit.class
  Last modified May 29, 2022; size 861 bytes
  SHA-256 checksum 03ca2d5149e301eb81d6bda72b2e819cdc2315ead8c73bc01f1b8fce6738f4e6
  Compiled from "GHCompare.java"
public class org.kohsuke.github.GHCompare$Commit extends org.kohsuke.github.GHCommit
  minor version: 0
  major version: 52
  flags: (0x0021) ACC_PUBLIC, ACC_SUPER
  this_class: #3                          // org/kohsuke/github/GHCompare$Commit
  super_class: #4                         // org/kohsuke/github/GHCommit
  interfaces: 0, fields: 1, methods: 2, attributes: 3
Constant pool:
   #1 = Methodref          #4.#29         // org/kohsuke/github/GHCommit."<init>":()V
   #2 = Fieldref           #3.#30         // org/kohsuke/github/GHCompare$Commit.commit:Lorg/kohsuke/github/GHCompare$InnerCommit;
   #3 = Class              #32            // org/kohsuke/github/GHCompare$Commit
   #4 = Class              #33            // org/kohsuke/github/GHCommit
   #5 = Utf8               commit
   #6 = Class              #34            // org/kohsuke/github/GHCompare$InnerCommit
   #7 = Utf8               InnerCommit
   #8 = Utf8               InnerClasses
   #9 = Utf8               Lorg/kohsuke/github/GHCompare$InnerCommit;
  #10 = Utf8               <init>
  #11 = Utf8               ()V
  #12 = Utf8               Code
  #13 = Utf8               LineNumberTable
  #14 = Utf8               LocalVariableTable
  #15 = Utf8               this
  #16 = Utf8               Commit
  #17 = Utf8               Lorg/kohsuke/github/GHCompare$Commit;
  #18 = Utf8               getCommit
  #19 = Utf8               ()Lorg/kohsuke/github/GHCompare$InnerCommit;
  #20 = Utf8               SourceFile
  #21 = Utf8               GHCompare.java
  #22 = Utf8               RuntimeInvisibleAnnotations
  #23 = Utf8               Ledu/umd/cs/findbugs/annotations/SuppressFBWarnings;
  #24 = Utf8               value
  #25 = Utf8               UWF_UNWRITTEN_PUBLIC_OR_PROTECTED_FIELD
  #26 = Utf8               UWF_UNWRITTEN_FIELD
  #27 = Utf8               justification
  #28 = Utf8               JSON API
  #29 = NameAndType        #10:#11        // "<init>":()V
  #30 = NameAndType        #5:#9          // commit:Lorg/kohsuke/github/GHCompare$InnerCommit;
  #31 = Class              #35            // org/kohsuke/github/GHCompare
  #32 = Utf8               org/kohsuke/github/GHCompare$Commit
  #33 = Utf8               org/kohsuke/github/GHCommit
  #34 = Utf8               org/kohsuke/github/GHCompare$InnerCommit
  #35 = Utf8               org/kohsuke/github/GHCompare
{
  private org.kohsuke.github.GHCompare$InnerCommit commit;
    descriptor: Lorg/kohsuke/github/GHCompare$InnerCommit;
    flags: (0x0002) ACC_PRIVATE

  public org.kohsuke.github.GHCompare$Commit();
    descriptor: ()V
    flags: (0x0001) ACC_PUBLIC
    Code:
      stack=1, locals=1, args_size=1
         0: aload_0
         1: invokespecial #1                  // Method org/kohsuke/github/GHCommit."<init>":()V
         4: return
      LineNumberTable:
        line 231: 0
      LocalVariableTable:
        Start  Length  Slot  Name   Signature
            0       5     0  this   Lorg/kohsuke/github/GHCompare$Commit;

  public org.kohsuke.github.GHCompare$InnerCommit getCommit();
    descriptor: ()Lorg/kohsuke/github/GHCompare$InnerCommit;
    flags: (0x0001) ACC_PUBLIC
    Code:
      stack=1, locals=1, args_size=1
         0: aload_0
         1: getfield      #2                  // Field commit:Lorg/kohsuke/github/GHCompare$InnerCommit;
         4: areturn
      LineNumberTable:
        line 241: 0
      LocalVariableTable:
        Start  Length  Slot  Name   Signature
            0       5     0  this   Lorg/kohsuke/github/GHCompare$Commit;
}
SourceFile: "GHCompare.java"
RuntimeInvisibleAnnotations:
  0: #23(#24=[s#25,s#26],#27=s#28)
    edu.umd.cs.findbugs.annotations.SuppressFBWarnings(
      value=["UWF_UNWRITTEN_PUBLIC_OR_PROTECTED_FIELD","UWF_UNWRITTEN_FIELD"]
      justification="JSON API"
    )
InnerClasses:
  public static #7= #6 of #31;            // InnerCommit=class org/kohsuke/github/GHCompare$InnerCommit of class org/kohsuke/github/GHCompare
  public static #16= #3 of #31;           // Commit=class org/kohsuke/github/GHCompare$Commit of class org/kohsuke/github/GHCompare
