Classfile /Users/mw/Projects/slang-braindump/.jar/jar8/assemble/slang-braindump/assemble/content/org/kohsuke/github/GHEventPayload$PullRequestReviewComment.class
  Last modified May 29, 2022; size 2327 bytes
  SHA-256 checksum ada2c30fc3bd3d8f2834e9a60571ea72e6dc13e3bfb919f6fe7d7a088ea886cb
  Compiled from "GHEventPayload.java"
public class org.kohsuke.github.GHEventPayload$PullRequestReviewComment extends org.kohsuke.github.GHEventPayload
  minor version: 0
  major version: 52
  flags: (0x0021) ACC_PUBLIC, ACC_SUPER
  this_class: #13                         // org/kohsuke/github/GHEventPayload$PullRequestReviewComment
  super_class: #14                        // org/kohsuke/github/GHEventPayload
  interfaces: 0, fields: 3, methods: 6, attributes: 2
Constant pool:
   #1 = Methodref          #14.#56        // org/kohsuke/github/GHEventPayload."<init>":()V
   #2 = Fieldref           #13.#57        // org/kohsuke/github/GHEventPayload$PullRequestReviewComment.comment:Lorg/kohsuke/github/GHPullRequestReviewComment;
   #3 = Fieldref           #13.#58        // org/kohsuke/github/GHEventPayload$PullRequestReviewComment.changes:Lorg/kohsuke/github/GHEventPayload$CommentChanges;
   #4 = Fieldref           #13.#59        // org/kohsuke/github/GHEventPayload$PullRequestReviewComment.pullRequest:Lorg/kohsuke/github/GHPullRequest;
   #5 = Class              #60            // java/lang/IllegalStateException
   #6 = String             #61            // Expected pull_request_review_comment payload, but got something else. Maybe we\'ve got another type of event?
   #7 = Methodref          #5.#62         // java/lang/IllegalStateException."<init>":(Ljava/lang/String;)V
   #8 = Methodref          #14.#63        // org/kohsuke/github/GHEventPayload.lateBind:()V
   #9 = Methodref          #64.#65        // org/kohsuke/github/GHPullRequestReviewComment.wrapUp:(Lorg/kohsuke/github/GHPullRequest;)Lorg/kohsuke/github/GHPullRequestReviewComment;
  #10 = Methodref          #13.#66        // org/kohsuke/github/GHEventPayload$PullRequestReviewComment.getRepository:()Lorg/kohsuke/github/GHRepository;
  #11 = Methodref          #67.#68        // org/kohsuke/github/GHPullRequest.wrapUp:(Lorg/kohsuke/github/GHRepository;)Lorg/kohsuke/github/GHPullRequest;
  #12 = Methodref          #14.#69        // org/kohsuke/github/GHEventPayload.getRoot:()Lorg/kohsuke/github/GitHub;
  #13 = Class              #70            // org/kohsuke/github/GHEventPayload$PullRequestReviewComment
  #14 = Class              #71            // org/kohsuke/github/GHEventPayload
  #15 = Utf8               comment
  #16 = Utf8               Lorg/kohsuke/github/GHPullRequestReviewComment;
  #17 = Utf8               pullRequest
  #18 = Utf8               Lorg/kohsuke/github/GHPullRequest;
  #19 = Utf8               changes
  #20 = Class              #72            // org/kohsuke/github/GHEventPayload$CommentChanges
  #21 = Utf8               CommentChanges
  #22 = Utf8               InnerClasses
  #23 = Utf8               Lorg/kohsuke/github/GHEventPayload$CommentChanges;
  #24 = Utf8               <init>
  #25 = Utf8               ()V
  #26 = Utf8               Code
  #27 = Utf8               LineNumberTable
  #28 = Utf8               LocalVariableTable
  #29 = Utf8               this
  #30 = Utf8               PullRequestReviewComment
  #31 = Utf8               Lorg/kohsuke/github/GHEventPayload$PullRequestReviewComment;
  #32 = Utf8               getComment
  #33 = Utf8               ()Lorg/kohsuke/github/GHPullRequestReviewComment;
  #34 = Utf8               RuntimeInvisibleAnnotations
  #35 = Utf8               Ledu/umd/cs/findbugs/annotations/SuppressFBWarnings;
  #36 = Utf8               value
  #37 = Utf8               EI_EXPOSE_REP
  #38 = Utf8               justification
  #39 = Utf8               Expected
  #40 = Utf8               getChanges
  #41 = Utf8               ()Lorg/kohsuke/github/GHEventPayload$CommentChanges;
  #42 = Utf8               getPullRequest
  #43 = Utf8               ()Lorg/kohsuke/github/GHPullRequest;
  #44 = Utf8               lateBind
  #45 = Utf8               repository
  #46 = Utf8               Lorg/kohsuke/github/GHRepository;
  #47 = Utf8               StackMapTable
  #48 = Class              #73            // org/kohsuke/github/GHRepository
  #49 = Utf8               getRoot
  #50 = Utf8               ()Lorg/kohsuke/github/GitHub;
  #51 = Utf8               RuntimeVisibleAnnotations
  #52 = Utf8               Ljava/lang/Deprecated;
  #53 = Utf8               Expected behavior
  #54 = Utf8               SourceFile
  #55 = Utf8               GHEventPayload.java
  #56 = NameAndType        #24:#25        // "<init>":()V
  #57 = NameAndType        #15:#16        // comment:Lorg/kohsuke/github/GHPullRequestReviewComment;
  #58 = NameAndType        #19:#23        // changes:Lorg/kohsuke/github/GHEventPayload$CommentChanges;
  #59 = NameAndType        #17:#18        // pullRequest:Lorg/kohsuke/github/GHPullRequest;
  #60 = Utf8               java/lang/IllegalStateException
  #61 = Utf8               Expected pull_request_review_comment payload, but got something else. Maybe we\'ve got another type of event?
  #62 = NameAndType        #24:#74        // "<init>":(Ljava/lang/String;)V
  #63 = NameAndType        #44:#25        // lateBind:()V
  #64 = Class              #75            // org/kohsuke/github/GHPullRequestReviewComment
  #65 = NameAndType        #76:#77        // wrapUp:(Lorg/kohsuke/github/GHPullRequest;)Lorg/kohsuke/github/GHPullRequestReviewComment;
  #66 = NameAndType        #78:#79        // getRepository:()Lorg/kohsuke/github/GHRepository;
  #67 = Class              #80            // org/kohsuke/github/GHPullRequest
  #68 = NameAndType        #76:#81        // wrapUp:(Lorg/kohsuke/github/GHRepository;)Lorg/kohsuke/github/GHPullRequest;
  #69 = NameAndType        #49:#50        // getRoot:()Lorg/kohsuke/github/GitHub;
  #70 = Utf8               org/kohsuke/github/GHEventPayload$PullRequestReviewComment
  #71 = Utf8               org/kohsuke/github/GHEventPayload
  #72 = Utf8               org/kohsuke/github/GHEventPayload$CommentChanges
  #73 = Utf8               org/kohsuke/github/GHRepository
  #74 = Utf8               (Ljava/lang/String;)V
  #75 = Utf8               org/kohsuke/github/GHPullRequestReviewComment
  #76 = Utf8               wrapUp
  #77 = Utf8               (Lorg/kohsuke/github/GHPullRequest;)Lorg/kohsuke/github/GHPullRequestReviewComment;
  #78 = Utf8               getRepository
  #79 = Utf8               ()Lorg/kohsuke/github/GHRepository;
  #80 = Utf8               org/kohsuke/github/GHPullRequest
  #81 = Utf8               (Lorg/kohsuke/github/GHRepository;)Lorg/kohsuke/github/GHPullRequest;
{
  private org.kohsuke.github.GHPullRequestReviewComment comment;
    descriptor: Lorg/kohsuke/github/GHPullRequestReviewComment;
    flags: (0x0002) ACC_PRIVATE

  private org.kohsuke.github.GHPullRequest pullRequest;
    descriptor: Lorg/kohsuke/github/GHPullRequest;
    flags: (0x0002) ACC_PRIVATE

  private org.kohsuke.github.GHEventPayload$CommentChanges changes;
    descriptor: Lorg/kohsuke/github/GHEventPayload$CommentChanges;
    flags: (0x0002) ACC_PRIVATE

  public org.kohsuke.github.GHEventPayload$PullRequestReviewComment();
    descriptor: ()V
    flags: (0x0001) ACC_PUBLIC
    Code:
      stack=1, locals=1, args_size=1
         0: aload_0
         1: invokespecial #1                  // Method org/kohsuke/github/GHEventPayload."<init>":()V
         4: return
      LineNumberTable:
        line 513: 0
      LocalVariableTable:
        Start  Length  Slot  Name   Signature
            0       5     0  this   Lorg/kohsuke/github/GHEventPayload$PullRequestReviewComment;

  public org.kohsuke.github.GHPullRequestReviewComment getComment();
    descriptor: ()Lorg/kohsuke/github/GHPullRequestReviewComment;
    flags: (0x0001) ACC_PUBLIC
    Code:
      stack=1, locals=1, args_size=1
         0: aload_0
         1: getfield      #2                  // Field comment:Lorg/kohsuke/github/GHPullRequestReviewComment;
         4: areturn
      LineNumberTable:
        line 525: 0
      LocalVariableTable:
        Start  Length  Slot  Name   Signature
            0       5     0  this   Lorg/kohsuke/github/GHEventPayload$PullRequestReviewComment;
    RuntimeInvisibleAnnotations:
      0: #35(#36=[s#37],#38=s#39)
        edu.umd.cs.findbugs.annotations.SuppressFBWarnings(
          value=["EI_EXPOSE_REP"]
          justification="Expected"
        )

  public org.kohsuke.github.GHEventPayload$CommentChanges getChanges();
    descriptor: ()Lorg/kohsuke/github/GHEventPayload$CommentChanges;
    flags: (0x0001) ACC_PUBLIC
    Code:
      stack=1, locals=1, args_size=1
         0: aload_0
         1: getfield      #3                  // Field changes:Lorg/kohsuke/github/GHEventPayload$CommentChanges;
         4: areturn
      LineNumberTable:
        line 534: 0
      LocalVariableTable:
        Start  Length  Slot  Name   Signature
            0       5     0  this   Lorg/kohsuke/github/GHEventPayload$PullRequestReviewComment;

  public org.kohsuke.github.GHPullRequest getPullRequest();
    descriptor: ()Lorg/kohsuke/github/GHPullRequest;
    flags: (0x0001) ACC_PUBLIC
    Code:
      stack=1, locals=1, args_size=1
         0: aload_0
         1: getfield      #4                  // Field pullRequest:Lorg/kohsuke/github/GHPullRequest;
         4: areturn
      LineNumberTable:
        line 544: 0
      LocalVariableTable:
        Start  Length  Slot  Name   Signature
            0       5     0  this   Lorg/kohsuke/github/GHEventPayload$PullRequestReviewComment;
    RuntimeInvisibleAnnotations:
      0: #35(#36=[s#37],#38=s#39)
        edu.umd.cs.findbugs.annotations.SuppressFBWarnings(
          value=["EI_EXPOSE_REP"]
          justification="Expected"
        )

  void lateBind();
    descriptor: ()V
    flags: (0x0000)
    Code:
      stack=3, locals=2, args_size=1
         0: aload_0
         1: getfield      #2                  // Field comment:Lorg/kohsuke/github/GHPullRequestReviewComment;
         4: ifnonnull     17
         7: new           #5                  // class java/lang/IllegalStateException
        10: dup
        11: ldc           #6                  // String Expected pull_request_review_comment payload, but got something else. Maybe we\'ve got another type of event?
        13: invokespecial #7                  // Method java/lang/IllegalStateException."<init>":(Ljava/lang/String;)V
        16: athrow
        17: aload_0
        18: invokespecial #8                  // Method org/kohsuke/github/GHEventPayload.lateBind:()V
        21: aload_0
        22: getfield      #2                  // Field comment:Lorg/kohsuke/github/GHPullRequestReviewComment;
        25: aload_0
        26: getfield      #4                  // Field pullRequest:Lorg/kohsuke/github/GHPullRequest;
        29: invokevirtual #9                  // Method org/kohsuke/github/GHPullRequestReviewComment.wrapUp:(Lorg/kohsuke/github/GHPullRequest;)Lorg/kohsuke/github/GHPullRequestReviewComment;
        32: pop
        33: aload_0
        34: invokevirtual #10                 // Method getRepository:()Lorg/kohsuke/github/GHRepository;
        37: astore_1
        38: aload_1
        39: ifnull        51
        42: aload_0
        43: getfield      #4                  // Field pullRequest:Lorg/kohsuke/github/GHPullRequest;
        46: aload_1
        47: invokevirtual #11                 // Method org/kohsuke/github/GHPullRequest.wrapUp:(Lorg/kohsuke/github/GHRepository;)Lorg/kohsuke/github/GHPullRequest;
        50: pop
        51: return
      LineNumberTable:
        line 549: 0
        line 550: 7
        line 552: 17
        line 553: 21
        line 555: 33
        line 556: 38
        line 557: 42
        line 559: 51
      LocalVariableTable:
        Start  Length  Slot  Name   Signature
            0      52     0  this   Lorg/kohsuke/github/GHEventPayload$PullRequestReviewComment;
           38      14     1 repository   Lorg/kohsuke/github/GHRepository;
      StackMapTable: number_of_entries = 2
        frame_type = 17 /* same */
        frame_type = 252 /* append */
          offset_delta = 33
          locals = [ class org/kohsuke/github/GHRepository ]

  public org.kohsuke.github.GitHub getRoot();
    descriptor: ()Lorg/kohsuke/github/GitHub;
    flags: (0x1041) ACC_PUBLIC, ACC_BRIDGE, ACC_SYNTHETIC
    Code:
      stack=1, locals=1, args_size=1
         0: aload_0
         1: invokespecial #12                 // Method org/kohsuke/github/GHEventPayload.getRoot:()Lorg/kohsuke/github/GitHub;
         4: areturn
      LineNumberTable:
        line 513: 0
      LocalVariableTable:
        Start  Length  Slot  Name   Signature
            0       5     0  this   Lorg/kohsuke/github/GHEventPayload$PullRequestReviewComment;
    RuntimeVisibleAnnotations:
      0: #52()
        java.lang.Deprecated
    RuntimeInvisibleAnnotations:
      0: #35(#36=[s#37],#38=s#53)
        edu.umd.cs.findbugs.annotations.SuppressFBWarnings(
          value=["EI_EXPOSE_REP"]
          justification="Expected behavior"
        )
}
SourceFile: "GHEventPayload.java"
InnerClasses:
  public static #21= #20 of #14;          // CommentChanges=class org/kohsuke/github/GHEventPayload$CommentChanges of class org/kohsuke/github/GHEventPayload
  public static #30= #13 of #14;          // PullRequestReviewComment=class org/kohsuke/github/GHEventPayload$PullRequestReviewComment of class org/kohsuke/github/GHEventPayload
