Classfile /Users/mw/Projects/slang-braindump/.jar/jar8/assemble/slang-braindump/assemble/content/org/kohsuke/github/GHEventPayload$CheckRun.class
  Last modified May 29, 2022; size 2433 bytes
  SHA-256 checksum 15b9aaf99026c9a1430a773d25c0c3ebfdaf71d592ccb44f2b98f45038ad57e3
  Compiled from "GHEventPayload.java"
public class org.kohsuke.github.GHEventPayload$CheckRun extends org.kohsuke.github.GHEventPayload
  minor version: 0
  major version: 52
  flags: (0x0021) ACC_PUBLIC, ACC_SUPER
  this_class: #17                         // org/kohsuke/github/GHEventPayload$CheckRun
  super_class: #18                        // org/kohsuke/github/GHEventPayload
  interfaces: 0, fields: 3, methods: 8, attributes: 2
Constant pool:
   #1 = Methodref          #18.#65        // org/kohsuke/github/GHEventPayload."<init>":()V
   #2 = Fieldref           #17.#66        // org/kohsuke/github/GHEventPayload$CheckRun.number:I
   #3 = Class              #67            // java/lang/RuntimeException
   #4 = String             #68            // Do not use this method.
   #5 = Methodref          #3.#69         // java/lang/RuntimeException."<init>":(Ljava/lang/String;)V
   #6 = Fieldref           #17.#70        // org/kohsuke/github/GHEventPayload$CheckRun.checkRun:Lorg/kohsuke/github/GHCheckRun;
   #7 = Fieldref           #17.#71        // org/kohsuke/github/GHEventPayload$CheckRun.requestedAction:Lorg/kohsuke/github/GHRequestedAction;
   #8 = Class              #72            // java/lang/IllegalStateException
   #9 = String             #73            // Expected check_run payload, but got something else. Maybe we\'ve got another type of event?
  #10 = Methodref          #8.#69         // java/lang/IllegalStateException."<init>":(Ljava/lang/String;)V
  #11 = Methodref          #18.#74        // org/kohsuke/github/GHEventPayload.lateBind:()V
  #12 = Methodref          #17.#75        // org/kohsuke/github/GHEventPayload$CheckRun.getRepository:()Lorg/kohsuke/github/GHRepository;
  #13 = Methodref          #76.#77        // org/kohsuke/github/GHCheckRun.wrap:(Lorg/kohsuke/github/GHRepository;)Lorg/kohsuke/github/GHCheckRun;
  #14 = Methodref          #17.#78        // org/kohsuke/github/GHEventPayload$CheckRun.root:()Lorg/kohsuke/github/GitHub;
  #15 = Methodref          #76.#79        // org/kohsuke/github/GHCheckRun.wrap:(Lorg/kohsuke/github/GitHub;)Lorg/kohsuke/github/GHCheckRun;
  #16 = Methodref          #18.#80        // org/kohsuke/github/GHEventPayload.getRoot:()Lorg/kohsuke/github/GitHub;
  #17 = Class              #81            // org/kohsuke/github/GHEventPayload$CheckRun
  #18 = Class              #82            // org/kohsuke/github/GHEventPayload
  #19 = Utf8               number
  #20 = Utf8               I
  #21 = Utf8               checkRun
  #22 = Utf8               Lorg/kohsuke/github/GHCheckRun;
  #23 = Utf8               requestedAction
  #24 = Utf8               Lorg/kohsuke/github/GHRequestedAction;
  #25 = Utf8               <init>
  #26 = Utf8               ()V
  #27 = Utf8               Code
  #28 = Utf8               LineNumberTable
  #29 = Utf8               LocalVariableTable
  #30 = Utf8               this
  #31 = Utf8               CheckRun
  #32 = Utf8               InnerClasses
  #33 = Utf8               Lorg/kohsuke/github/GHEventPayload$CheckRun;
  #34 = Utf8               getNumber
  #35 = Utf8               ()I
  #36 = Utf8               setCheckRun
  #37 = Utf8               (Lorg/kohsuke/github/GHCheckRun;)V
  #38 = Utf8               currentCheckRun
  #39 = Utf8               Deprecated
  #40 = Utf8               RuntimeVisibleAnnotations
  #41 = Utf8               Ljava/lang/Deprecated;
  #42 = Utf8               getCheckRun
  #43 = Utf8               ()Lorg/kohsuke/github/GHCheckRun;
  #44 = Utf8               RuntimeInvisibleAnnotations
  #45 = Utf8               Ledu/umd/cs/findbugs/annotations/SuppressFBWarnings;
  #46 = Utf8               value
  #47 = Utf8               EI_EXPOSE_REP
  #48 = Utf8               justification
  #49 = Utf8               Expected
  #50 = Utf8               setRequestedAction
  #51 = Utf8               (Lorg/kohsuke/github/GHRequestedAction;)V
  #52 = Utf8               currentRequestedAction
  #53 = Utf8               getRequestedAction
  #54 = Utf8               ()Lorg/kohsuke/github/GHRequestedAction;
  #55 = Utf8               lateBind
  #56 = Utf8               repository
  #57 = Utf8               Lorg/kohsuke/github/GHRepository;
  #58 = Utf8               StackMapTable
  #59 = Class              #83            // org/kohsuke/github/GHRepository
  #60 = Utf8               getRoot
  #61 = Utf8               ()Lorg/kohsuke/github/GitHub;
  #62 = Utf8               Expected behavior
  #63 = Utf8               SourceFile
  #64 = Utf8               GHEventPayload.java
  #65 = NameAndType        #25:#26        // "<init>":()V
  #66 = NameAndType        #19:#20        // number:I
  #67 = Utf8               java/lang/RuntimeException
  #68 = Utf8               Do not use this method.
  #69 = NameAndType        #25:#84        // "<init>":(Ljava/lang/String;)V
  #70 = NameAndType        #21:#22        // checkRun:Lorg/kohsuke/github/GHCheckRun;
  #71 = NameAndType        #23:#24        // requestedAction:Lorg/kohsuke/github/GHRequestedAction;
  #72 = Utf8               java/lang/IllegalStateException
  #73 = Utf8               Expected check_run payload, but got something else. Maybe we\'ve got another type of event?
  #74 = NameAndType        #55:#26        // lateBind:()V
  #75 = NameAndType        #85:#86        // getRepository:()Lorg/kohsuke/github/GHRepository;
  #76 = Class              #87            // org/kohsuke/github/GHCheckRun
  #77 = NameAndType        #88:#89        // wrap:(Lorg/kohsuke/github/GHRepository;)Lorg/kohsuke/github/GHCheckRun;
  #78 = NameAndType        #90:#61        // root:()Lorg/kohsuke/github/GitHub;
  #79 = NameAndType        #88:#91        // wrap:(Lorg/kohsuke/github/GitHub;)Lorg/kohsuke/github/GHCheckRun;
  #80 = NameAndType        #60:#61        // getRoot:()Lorg/kohsuke/github/GitHub;
  #81 = Utf8               org/kohsuke/github/GHEventPayload$CheckRun
  #82 = Utf8               org/kohsuke/github/GHEventPayload
  #83 = Utf8               org/kohsuke/github/GHRepository
  #84 = Utf8               (Ljava/lang/String;)V
  #85 = Utf8               getRepository
  #86 = Utf8               ()Lorg/kohsuke/github/GHRepository;
  #87 = Utf8               org/kohsuke/github/GHCheckRun
  #88 = Utf8               wrap
  #89 = Utf8               (Lorg/kohsuke/github/GHRepository;)Lorg/kohsuke/github/GHCheckRun;
  #90 = Utf8               root
  #91 = Utf8               (Lorg/kohsuke/github/GitHub;)Lorg/kohsuke/github/GHCheckRun;
{
  private int number;
    descriptor: I
    flags: (0x0002) ACC_PRIVATE

  private org.kohsuke.github.GHCheckRun checkRun;
    descriptor: Lorg/kohsuke/github/GHCheckRun;
    flags: (0x0002) ACC_PRIVATE

  private org.kohsuke.github.GHRequestedAction requestedAction;
    descriptor: Lorg/kohsuke/github/GHRequestedAction;
    flags: (0x0002) ACC_PRIVATE

  public org.kohsuke.github.GHEventPayload$CheckRun();
    descriptor: ()V
    flags: (0x0001) ACC_PUBLIC
    Code:
      stack=1, locals=1, args_size=1
         0: aload_0
         1: invokespecial #1                  // Method org/kohsuke/github/GHEventPayload."<init>":()V
         4: return
      LineNumberTable:
        line 138: 0
      LocalVariableTable:
        Start  Length  Slot  Name   Signature
            0       5     0  this   Lorg/kohsuke/github/GHEventPayload$CheckRun;

  public int getNumber();
    descriptor: ()I
    flags: (0x0001) ACC_PUBLIC
    Code:
      stack=1, locals=1, args_size=1
         0: aload_0
         1: getfield      #2                  // Field number:I
         4: ireturn
      LineNumberTable:
        line 149: 0
      LocalVariableTable:
        Start  Length  Slot  Name   Signature
            0       5     0  this   Lorg/kohsuke/github/GHEventPayload$CheckRun;

  public void setCheckRun(org.kohsuke.github.GHCheckRun);
    descriptor: (Lorg/kohsuke/github/GHCheckRun;)V
    flags: (0x0001) ACC_PUBLIC
    Code:
      stack=3, locals=2, args_size=2
         0: new           #3                  // class java/lang/RuntimeException
         3: dup
         4: ldc           #4                  // String Do not use this method.
         6: invokespecial #5                  // Method java/lang/RuntimeException."<init>":(Ljava/lang/String;)V
         9: athrow
      LineNumberTable:
        line 161: 0
      LocalVariableTable:
        Start  Length  Slot  Name   Signature
            0      10     0  this   Lorg/kohsuke/github/GHEventPayload$CheckRun;
            0      10     1 currentCheckRun   Lorg/kohsuke/github/GHCheckRun;
    Deprecated: true
    RuntimeVisibleAnnotations:
      0: #41()
        java.lang.Deprecated

  public org.kohsuke.github.GHCheckRun getCheckRun();
    descriptor: ()Lorg/kohsuke/github/GHCheckRun;
    flags: (0x0001) ACC_PUBLIC
    Code:
      stack=1, locals=1, args_size=1
         0: aload_0
         1: getfield      #6                  // Field checkRun:Lorg/kohsuke/github/GHCheckRun;
         4: areturn
      LineNumberTable:
        line 171: 0
      LocalVariableTable:
        Start  Length  Slot  Name   Signature
            0       5     0  this   Lorg/kohsuke/github/GHEventPayload$CheckRun;
    RuntimeInvisibleAnnotations:
      0: #45(#46=[s#47],#48=s#49)
        edu.umd.cs.findbugs.annotations.SuppressFBWarnings(
          value=["EI_EXPOSE_REP"]
          justification="Expected"
        )

  public void setRequestedAction(org.kohsuke.github.GHRequestedAction);
    descriptor: (Lorg/kohsuke/github/GHRequestedAction;)V
    flags: (0x0001) ACC_PUBLIC
    Code:
      stack=3, locals=2, args_size=2
         0: new           #3                  // class java/lang/RuntimeException
         3: dup
         4: ldc           #4                  // String Do not use this method.
         6: invokespecial #5                  // Method java/lang/RuntimeException."<init>":(Ljava/lang/String;)V
         9: athrow
      LineNumberTable:
        line 183: 0
      LocalVariableTable:
        Start  Length  Slot  Name   Signature
            0      10     0  this   Lorg/kohsuke/github/GHEventPayload$CheckRun;
            0      10     1 currentRequestedAction   Lorg/kohsuke/github/GHRequestedAction;
    Deprecated: true
    RuntimeVisibleAnnotations:
      0: #41()
        java.lang.Deprecated

  public org.kohsuke.github.GHRequestedAction getRequestedAction();
    descriptor: ()Lorg/kohsuke/github/GHRequestedAction;
    flags: (0x0001) ACC_PUBLIC
    Code:
      stack=1, locals=1, args_size=1
         0: aload_0
         1: getfield      #7                  // Field requestedAction:Lorg/kohsuke/github/GHRequestedAction;
         4: areturn
      LineNumberTable:
        line 193: 0
      LocalVariableTable:
        Start  Length  Slot  Name   Signature
            0       5     0  this   Lorg/kohsuke/github/GHEventPayload$CheckRun;
    RuntimeInvisibleAnnotations:
      0: #45(#46=[s#47],#48=s#49)
        edu.umd.cs.findbugs.annotations.SuppressFBWarnings(
          value=["EI_EXPOSE_REP"]
          justification="Expected"
        )

  void lateBind();
    descriptor: ()V
    flags: (0x0000)
    Code:
      stack=3, locals=2, args_size=1
         0: aload_0
         1: getfield      #6                  // Field checkRun:Lorg/kohsuke/github/GHCheckRun;
         4: ifnonnull     17
         7: new           #8                  // class java/lang/IllegalStateException
        10: dup
        11: ldc           #9                  // String Expected check_run payload, but got something else. Maybe we\'ve got another type of event?
        13: invokespecial #10                 // Method java/lang/IllegalStateException."<init>":(Ljava/lang/String;)V
        16: athrow
        17: aload_0
        18: invokespecial #11                 // Method org/kohsuke/github/GHEventPayload.lateBind:()V
        21: aload_0
        22: invokevirtual #12                 // Method getRepository:()Lorg/kohsuke/github/GHRepository;
        25: astore_1
        26: aload_1
        27: ifnull        42
        30: aload_0
        31: getfield      #6                  // Field checkRun:Lorg/kohsuke/github/GHCheckRun;
        34: aload_1
        35: invokevirtual #13                 // Method org/kohsuke/github/GHCheckRun.wrap:(Lorg/kohsuke/github/GHRepository;)Lorg/kohsuke/github/GHCheckRun;
        38: pop
        39: goto          54
        42: aload_0
        43: getfield      #6                  // Field checkRun:Lorg/kohsuke/github/GHCheckRun;
        46: aload_0
        47: invokevirtual #14                 // Method root:()Lorg/kohsuke/github/GitHub;
        50: invokevirtual #15                 // Method org/kohsuke/github/GHCheckRun.wrap:(Lorg/kohsuke/github/GitHub;)Lorg/kohsuke/github/GHCheckRun;
        53: pop
        54: return
      LineNumberTable:
        line 198: 0
        line 199: 7
        line 201: 17
        line 202: 21
        line 203: 26
        line 204: 30
        line 206: 42
        line 208: 54
      LocalVariableTable:
        Start  Length  Slot  Name   Signature
            0      55     0  this   Lorg/kohsuke/github/GHEventPayload$CheckRun;
           26      29     1 repository   Lorg/kohsuke/github/GHRepository;
      StackMapTable: number_of_entries = 3
        frame_type = 17 /* same */
        frame_type = 252 /* append */
          offset_delta = 24
          locals = [ class org/kohsuke/github/GHRepository ]
        frame_type = 11 /* same */

  public org.kohsuke.github.GitHub getRoot();
    descriptor: ()Lorg/kohsuke/github/GitHub;
    flags: (0x1041) ACC_PUBLIC, ACC_BRIDGE, ACC_SYNTHETIC
    Code:
      stack=1, locals=1, args_size=1
         0: aload_0
         1: invokespecial #16                 // Method org/kohsuke/github/GHEventPayload.getRoot:()Lorg/kohsuke/github/GitHub;
         4: areturn
      LineNumberTable:
        line 138: 0
      LocalVariableTable:
        Start  Length  Slot  Name   Signature
            0       5     0  this   Lorg/kohsuke/github/GHEventPayload$CheckRun;
    RuntimeVisibleAnnotations:
      0: #41()
        java.lang.Deprecated
    RuntimeInvisibleAnnotations:
      0: #45(#46=[s#47],#48=s#62)
        edu.umd.cs.findbugs.annotations.SuppressFBWarnings(
          value=["EI_EXPOSE_REP"]
          justification="Expected behavior"
        )
}
SourceFile: "GHEventPayload.java"
InnerClasses:
  public static #31= #17 of #18;          // CheckRun=class org/kohsuke/github/GHEventPayload$CheckRun of class org/kohsuke/github/GHEventPayload
