Classfile /Users/mw/Projects/slang-braindump/.jar/jar8/assemble/slang-braindump/assemble/content/org/kohsuke/github/GHEventPayload$DeploymentStatus.class
  Last modified May 29, 2022; size 2195 bytes
  SHA-256 checksum 16059a12879d10b5a4ba5a9021d6f8ada87f41b982da81b367af489ae0b68d2c
  Compiled from "GHEventPayload.java"
public class org.kohsuke.github.GHEventPayload$DeploymentStatus extends org.kohsuke.github.GHEventPayload
  minor version: 0
  major version: 52
  flags: (0x0021) ACC_PUBLIC, ACC_SUPER
  this_class: #12                         // org/kohsuke/github/GHEventPayload$DeploymentStatus
  super_class: #13                        // org/kohsuke/github/GHEventPayload
  interfaces: 0, fields: 2, methods: 7, attributes: 2
Constant pool:
   #1 = Methodref          #13.#54        // org/kohsuke/github/GHEventPayload."<init>":()V
   #2 = Fieldref           #12.#55        // org/kohsuke/github/GHEventPayload$DeploymentStatus.deploymentStatus:Lorg/kohsuke/github/GHDeploymentStatus;
   #3 = Class              #56            // java/lang/RuntimeException
   #4 = String             #57            // Do not use this method.
   #5 = Methodref          #3.#58         // java/lang/RuntimeException."<init>":(Ljava/lang/String;)V
   #6 = Fieldref           #12.#59        // org/kohsuke/github/GHEventPayload$DeploymentStatus.deployment:Lorg/kohsuke/github/GHDeployment;
   #7 = Methodref          #13.#60        // org/kohsuke/github/GHEventPayload.lateBind:()V
   #8 = Methodref          #12.#61        // org/kohsuke/github/GHEventPayload$DeploymentStatus.getRepository:()Lorg/kohsuke/github/GHRepository;
   #9 = Methodref          #62.#63        // org/kohsuke/github/GHDeployment.wrap:(Lorg/kohsuke/github/GHRepository;)Lorg/kohsuke/github/GHDeployment;
  #10 = Methodref          #64.#65        // org/kohsuke/github/GHDeploymentStatus.lateBind:(Lorg/kohsuke/github/GHRepository;)Lorg/kohsuke/github/GHDeploymentStatus;
  #11 = Methodref          #13.#66        // org/kohsuke/github/GHEventPayload.getRoot:()Lorg/kohsuke/github/GitHub;
  #12 = Class              #67            // org/kohsuke/github/GHEventPayload$DeploymentStatus
  #13 = Class              #68            // org/kohsuke/github/GHEventPayload
  #14 = Utf8               deploymentStatus
  #15 = Utf8               Lorg/kohsuke/github/GHDeploymentStatus;
  #16 = Utf8               deployment
  #17 = Utf8               Lorg/kohsuke/github/GHDeployment;
  #18 = Utf8               <init>
  #19 = Utf8               ()V
  #20 = Utf8               Code
  #21 = Utf8               LineNumberTable
  #22 = Utf8               LocalVariableTable
  #23 = Utf8               this
  #24 = Utf8               DeploymentStatus
  #25 = Utf8               InnerClasses
  #26 = Utf8               Lorg/kohsuke/github/GHEventPayload$DeploymentStatus;
  #27 = Utf8               getDeploymentStatus
  #28 = Utf8               ()Lorg/kohsuke/github/GHDeploymentStatus;
  #29 = Utf8               RuntimeInvisibleAnnotations
  #30 = Utf8               Ledu/umd/cs/findbugs/annotations/SuppressFBWarnings;
  #31 = Utf8               value
  #32 = Utf8               EI_EXPOSE_REP
  #33 = Utf8               justification
  #34 = Utf8               Expected
  #35 = Utf8               setDeploymentStatus
  #36 = Utf8               (Lorg/kohsuke/github/GHDeploymentStatus;)V
  #37 = Utf8               Deprecated
  #38 = Utf8               RuntimeVisibleAnnotations
  #39 = Utf8               Ljava/lang/Deprecated;
  #40 = Utf8               getDeployment
  #41 = Utf8               ()Lorg/kohsuke/github/GHDeployment;
  #42 = Utf8               setDeployment
  #43 = Utf8               (Lorg/kohsuke/github/GHDeployment;)V
  #44 = Utf8               lateBind
  #45 = Utf8               repository
  #46 = Utf8               Lorg/kohsuke/github/GHRepository;
  #47 = Utf8               StackMapTable
  #48 = Class              #69            // org/kohsuke/github/GHRepository
  #49 = Utf8               getRoot
  #50 = Utf8               ()Lorg/kohsuke/github/GitHub;
  #51 = Utf8               Expected behavior
  #52 = Utf8               SourceFile
  #53 = Utf8               GHEventPayload.java
  #54 = NameAndType        #18:#19        // "<init>":()V
  #55 = NameAndType        #14:#15        // deploymentStatus:Lorg/kohsuke/github/GHDeploymentStatus;
  #56 = Utf8               java/lang/RuntimeException
  #57 = Utf8               Do not use this method.
  #58 = NameAndType        #18:#70        // "<init>":(Ljava/lang/String;)V
  #59 = NameAndType        #16:#17        // deployment:Lorg/kohsuke/github/GHDeployment;
  #60 = NameAndType        #44:#19        // lateBind:()V
  #61 = NameAndType        #71:#72        // getRepository:()Lorg/kohsuke/github/GHRepository;
  #62 = Class              #73            // org/kohsuke/github/GHDeployment
  #63 = NameAndType        #74:#75        // wrap:(Lorg/kohsuke/github/GHRepository;)Lorg/kohsuke/github/GHDeployment;
  #64 = Class              #76            // org/kohsuke/github/GHDeploymentStatus
  #65 = NameAndType        #44:#77        // lateBind:(Lorg/kohsuke/github/GHRepository;)Lorg/kohsuke/github/GHDeploymentStatus;
  #66 = NameAndType        #49:#50        // getRoot:()Lorg/kohsuke/github/GitHub;
  #67 = Utf8               org/kohsuke/github/GHEventPayload$DeploymentStatus
  #68 = Utf8               org/kohsuke/github/GHEventPayload
  #69 = Utf8               org/kohsuke/github/GHRepository
  #70 = Utf8               (Ljava/lang/String;)V
  #71 = Utf8               getRepository
  #72 = Utf8               ()Lorg/kohsuke/github/GHRepository;
  #73 = Utf8               org/kohsuke/github/GHDeployment
  #74 = Utf8               wrap
  #75 = Utf8               (Lorg/kohsuke/github/GHRepository;)Lorg/kohsuke/github/GHDeployment;
  #76 = Utf8               org/kohsuke/github/GHDeploymentStatus
  #77 = Utf8               (Lorg/kohsuke/github/GHRepository;)Lorg/kohsuke/github/GHDeploymentStatus;
{
  private org.kohsuke.github.GHDeploymentStatus deploymentStatus;
    descriptor: Lorg/kohsuke/github/GHDeploymentStatus;
    flags: (0x0002) ACC_PRIVATE

  private org.kohsuke.github.GHDeployment deployment;
    descriptor: Lorg/kohsuke/github/GHDeployment;
    flags: (0x0002) ACC_PRIVATE

  public org.kohsuke.github.GHEventPayload$DeploymentStatus();
    descriptor: ()V
    flags: (0x0001) ACC_PUBLIC
    Code:
      stack=1, locals=1, args_size=1
         0: aload_0
         1: invokespecial #1                  // Method org/kohsuke/github/GHEventPayload."<init>":()V
         4: return
      LineNumberTable:
        line 881: 0
      LocalVariableTable:
        Start  Length  Slot  Name   Signature
            0       5     0  this   Lorg/kohsuke/github/GHEventPayload$DeploymentStatus;

  public org.kohsuke.github.GHDeploymentStatus getDeploymentStatus();
    descriptor: ()Lorg/kohsuke/github/GHDeploymentStatus;
    flags: (0x0001) ACC_PUBLIC
    Code:
      stack=1, locals=1, args_size=1
         0: aload_0
         1: getfield      #2                  // Field deploymentStatus:Lorg/kohsuke/github/GHDeploymentStatus;
         4: areturn
      LineNumberTable:
        line 892: 0
      LocalVariableTable:
        Start  Length  Slot  Name   Signature
            0       5     0  this   Lorg/kohsuke/github/GHEventPayload$DeploymentStatus;
    RuntimeInvisibleAnnotations:
      0: #30(#31=[s#32],#33=s#34)
        edu.umd.cs.findbugs.annotations.SuppressFBWarnings(
          value=["EI_EXPOSE_REP"]
          justification="Expected"
        )

  public void setDeploymentStatus(org.kohsuke.github.GHDeploymentStatus);
    descriptor: (Lorg/kohsuke/github/GHDeploymentStatus;)V
    flags: (0x0001) ACC_PUBLIC
    Code:
      stack=3, locals=2, args_size=2
         0: new           #3                  // class java/lang/RuntimeException
         3: dup
         4: ldc           #4                  // String Do not use this method.
         6: invokespecial #5                  // Method java/lang/RuntimeException."<init>":(Ljava/lang/String;)V
         9: athrow
      LineNumberTable:
        line 904: 0
      LocalVariableTable:
        Start  Length  Slot  Name   Signature
            0      10     0  this   Lorg/kohsuke/github/GHEventPayload$DeploymentStatus;
            0      10     1 deploymentStatus   Lorg/kohsuke/github/GHDeploymentStatus;
    Deprecated: true
    RuntimeVisibleAnnotations:
      0: #39()
        java.lang.Deprecated

  public org.kohsuke.github.GHDeployment getDeployment();
    descriptor: ()Lorg/kohsuke/github/GHDeployment;
    flags: (0x0001) ACC_PUBLIC
    Code:
      stack=1, locals=1, args_size=1
         0: aload_0
         1: getfield      #6                  // Field deployment:Lorg/kohsuke/github/GHDeployment;
         4: areturn
      LineNumberTable:
        line 914: 0
      LocalVariableTable:
        Start  Length  Slot  Name   Signature
            0       5     0  this   Lorg/kohsuke/github/GHEventPayload$DeploymentStatus;
    RuntimeInvisibleAnnotations:
      0: #30(#31=[s#32],#33=s#34)
        edu.umd.cs.findbugs.annotations.SuppressFBWarnings(
          value=["EI_EXPOSE_REP"]
          justification="Expected"
        )

  public void setDeployment(org.kohsuke.github.GHDeployment);
    descriptor: (Lorg/kohsuke/github/GHDeployment;)V
    flags: (0x0001) ACC_PUBLIC
    Code:
      stack=3, locals=2, args_size=2
         0: new           #3                  // class java/lang/RuntimeException
         3: dup
         4: ldc           #4                  // String Do not use this method.
         6: invokespecial #5                  // Method java/lang/RuntimeException."<init>":(Ljava/lang/String;)V
         9: athrow
      LineNumberTable:
        line 926: 0
      LocalVariableTable:
        Start  Length  Slot  Name   Signature
            0      10     0  this   Lorg/kohsuke/github/GHEventPayload$DeploymentStatus;
            0      10     1 deployment   Lorg/kohsuke/github/GHDeployment;
    Deprecated: true
    RuntimeVisibleAnnotations:
      0: #39()
        java.lang.Deprecated

  void lateBind();
    descriptor: ()V
    flags: (0x0000)
    Code:
      stack=2, locals=2, args_size=1
         0: aload_0
         1: invokespecial #7                  // Method org/kohsuke/github/GHEventPayload.lateBind:()V
         4: aload_0
         5: invokevirtual #8                  // Method getRepository:()Lorg/kohsuke/github/GHRepository;
         8: astore_1
         9: aload_1
        10: ifnull        31
        13: aload_0
        14: getfield      #6                  // Field deployment:Lorg/kohsuke/github/GHDeployment;
        17: aload_1
        18: invokevirtual #9                  // Method org/kohsuke/github/GHDeployment.wrap:(Lorg/kohsuke/github/GHRepository;)Lorg/kohsuke/github/GHDeployment;
        21: pop
        22: aload_0
        23: getfield      #2                  // Field deploymentStatus:Lorg/kohsuke/github/GHDeploymentStatus;
        26: aload_1
        27: invokevirtual #10                 // Method org/kohsuke/github/GHDeploymentStatus.lateBind:(Lorg/kohsuke/github/GHRepository;)Lorg/kohsuke/github/GHDeploymentStatus;
        30: pop
        31: return
      LineNumberTable:
        line 931: 0
        line 932: 4
        line 933: 9
        line 934: 13
        line 935: 22
        line 937: 31
      LocalVariableTable:
        Start  Length  Slot  Name   Signature
            0      32     0  this   Lorg/kohsuke/github/GHEventPayload$DeploymentStatus;
            9      23     1 repository   Lorg/kohsuke/github/GHRepository;
      StackMapTable: number_of_entries = 1
        frame_type = 252 /* append */
          offset_delta = 31
          locals = [ class org/kohsuke/github/GHRepository ]

  public org.kohsuke.github.GitHub getRoot();
    descriptor: ()Lorg/kohsuke/github/GitHub;
    flags: (0x1041) ACC_PUBLIC, ACC_BRIDGE, ACC_SYNTHETIC
    Code:
      stack=1, locals=1, args_size=1
         0: aload_0
         1: invokespecial #11                 // Method org/kohsuke/github/GHEventPayload.getRoot:()Lorg/kohsuke/github/GitHub;
         4: areturn
      LineNumberTable:
        line 881: 0
      LocalVariableTable:
        Start  Length  Slot  Name   Signature
            0       5     0  this   Lorg/kohsuke/github/GHEventPayload$DeploymentStatus;
    RuntimeVisibleAnnotations:
      0: #39()
        java.lang.Deprecated
    RuntimeInvisibleAnnotations:
      0: #30(#31=[s#32],#33=s#51)
        edu.umd.cs.findbugs.annotations.SuppressFBWarnings(
          value=["EI_EXPOSE_REP"]
          justification="Expected behavior"
        )
}
SourceFile: "GHEventPayload.java"
InnerClasses:
  public static #24= #12 of #13;          // DeploymentStatus=class org/kohsuke/github/GHEventPayload$DeploymentStatus of class org/kohsuke/github/GHEventPayload
