Classfile /Users/mw/Projects/slang-braindump/.jar/jar8/assemble/slang-braindump/assemble/content/org/kohsuke/github/GHException.class
  Last modified May 29, 2022; size 544 bytes
  SHA-256 checksum 918bc291564a7bd46547caf0bdb6c521806485ead5abc2bb4336d99d2342558b
  Compiled from "GHException.java"
public class org.kohsuke.github.GHException extends java.lang.RuntimeException
  minor version: 0
  major version: 52
  flags: (0x0021) ACC_PUBLIC, ACC_SUPER
  this_class: #3                          // org/kohsuke/github/GHException
  super_class: #4                         // java/lang/RuntimeException
  interfaces: 0, fields: 0, methods: 2, attributes: 1
Constant pool:
   #1 = Methodref          #4.#19         // java/lang/RuntimeException."<init>":(Ljava/lang/String;)V
   #2 = Methodref          #4.#20         // java/lang/RuntimeException."<init>":(Ljava/lang/String;Ljava/lang/Throwable;)V
   #3 = Class              #21            // org/kohsuke/github/GHException
   #4 = Class              #22            // java/lang/RuntimeException
   #5 = Utf8               <init>
   #6 = Utf8               (Ljava/lang/String;)V
   #7 = Utf8               Code
   #8 = Utf8               LineNumberTable
   #9 = Utf8               LocalVariableTable
  #10 = Utf8               this
  #11 = Utf8               Lorg/kohsuke/github/GHException;
  #12 = Utf8               message
  #13 = Utf8               Ljava/lang/String;
  #14 = Utf8               (Ljava/lang/String;Ljava/lang/Throwable;)V
  #15 = Utf8               cause
  #16 = Utf8               Ljava/lang/Throwable;
  #17 = Utf8               SourceFile
  #18 = Utf8               GHException.java
  #19 = NameAndType        #5:#6          // "<init>":(Ljava/lang/String;)V
  #20 = NameAndType        #5:#14         // "<init>":(Ljava/lang/String;Ljava/lang/Throwable;)V
  #21 = Utf8               org/kohsuke/github/GHException
  #22 = Utf8               java/lang/RuntimeException
{
  public org.kohsuke.github.GHException(java.lang.String);
    descriptor: (Ljava/lang/String;)V
    flags: (0x0001) ACC_PUBLIC
    Code:
      stack=2, locals=2, args_size=2
         0: aload_0
         1: aload_1
         2: invokespecial #1                  // Method java/lang/RuntimeException."<init>":(Ljava/lang/String;)V
         5: return
      LineNumberTable:
        line 16: 0
        line 17: 5
      LocalVariableTable:
        Start  Length  Slot  Name   Signature
            0       6     0  this   Lorg/kohsuke/github/GHException;
            0       6     1 message   Ljava/lang/String;

  public org.kohsuke.github.GHException(java.lang.String, java.lang.Throwable);
    descriptor: (Ljava/lang/String;Ljava/lang/Throwable;)V
    flags: (0x0001) ACC_PUBLIC
    Code:
      stack=3, locals=3, args_size=3
         0: aload_0
         1: aload_1
         2: aload_2
         3: invokespecial #2                  // Method java/lang/RuntimeException."<init>":(Ljava/lang/String;Ljava/lang/Throwable;)V
         6: return
      LineNumberTable:
        line 28: 0
        line 29: 6
      LocalVariableTable:
        Start  Length  Slot  Name   Signature
            0       7     0  this   Lorg/kohsuke/github/GHException;
            0       7     1 message   Ljava/lang/String;
            0       7     2 cause   Ljava/lang/Throwable;
}
SourceFile: "GHException.java"
