Classfile /Users/mw/Projects/slang-braindump/.jar/jar8/assemble/slang-braindump/assemble/content/org/kohsuke/github/GHGistUpdater.class
  Last modified May 29, 2022; size 4317 bytes
  SHA-256 checksum b376db2da1086dd7620ed055c7311ae3489c97b6fb85326337519979c141054e
  Compiled from "GHGistUpdater.java"
public class org.kohsuke.github.GHGistUpdater
  minor version: 0
  major version: 52
  flags: (0x0021) ACC_PUBLIC, ACC_SUPER
  this_class: #34                         // org/kohsuke/github/GHGistUpdater
  super_class: #35                        // java/lang/Object
  interfaces: 0, fields: 3, methods: 11, attributes: 3
Constant pool:
    #1 = Methodref          #35.#81       // java/lang/Object."<init>":()V
    #2 = Fieldref           #34.#82       // org/kohsuke/github/GHGistUpdater.base:Lorg/kohsuke/github/GHGist;
    #3 = Methodref          #30.#83       // org/kohsuke/github/GHGist.root:()Lorg/kohsuke/github/GitHub;
    #4 = Methodref          #84.#85       // org/kohsuke/github/GitHub.createRequest:()Lorg/kohsuke/github/Requester;
    #5 = Fieldref           #34.#86       // org/kohsuke/github/GHGistUpdater.builder:Lorg/kohsuke/github/Requester;
    #6 = Class              #87           // java/util/LinkedHashMap
    #7 = Methodref          #6.#81        // java/util/LinkedHashMap."<init>":()V
    #8 = Fieldref           #34.#88       // org/kohsuke/github/GHGistUpdater.files:Ljava/util/LinkedHashMap;
    #9 = Methodref          #34.#89       // org/kohsuke/github/GHGistUpdater.updateFile:(Ljava/lang/String;Ljava/lang/String;)Lorg/kohsuke/github/GHGistUpdater;
   #10 = Methodref          #6.#90        // java/util/LinkedHashMap.put:(Ljava/lang/Object;Ljava/lang/Object;)Ljava/lang/Object;
   #11 = InvokeDynamic      #0:#96        // #0:apply:()Ljava/util/function/Function;
   #12 = Methodref          #6.#97        // java/util/LinkedHashMap.computeIfAbsent:(Ljava/lang/Object;Ljava/util/function/Function;)Ljava/lang/Object;
   #13 = Class              #98           // java/util/Map
   #14 = String             #99           // filename
   #15 = InterfaceMethodref #13.#90       // java/util/Map.put:(Ljava/lang/Object;Ljava/lang/Object;)Ljava/lang/Object;
   #16 = InvokeDynamic      #1:#96        // #1:apply:()Ljava/util/function/Function;
   #17 = String             #55           // content
   #18 = InvokeDynamic      #2:#96        // #2:apply:()Ljava/util/function/Function;
   #19 = String             #70           // description
   #20 = Methodref          #25.#102      // org/kohsuke/github/Requester.with:(Ljava/lang/String;Ljava/lang/String;)Lorg/kohsuke/github/GitHubRequest$Builder;
   #21 = String             #40           // files
   #22 = Methodref          #25.#103      // org/kohsuke/github/Requester.with:(Ljava/lang/String;Ljava/util/Map;)Lorg/kohsuke/github/GitHubRequest$Builder;
   #23 = String             #104          // PATCH
   #24 = Methodref          #25.#105      // org/kohsuke/github/Requester.method:(Ljava/lang/String;)Lorg/kohsuke/github/GitHubRequest$Builder;
   #25 = Class              #106          // org/kohsuke/github/Requester
   #26 = String             #107          //
   #27 = Methodref          #30.#108      // org/kohsuke/github/GHGist.getApiTailUrl:(Ljava/lang/String;)Ljava/lang/String;
   #28 = Class              #109          // java/lang/String
   #29 = Methodref          #25.#110      // org/kohsuke/github/Requester.withUrlPath:(Ljava/lang/String;[Ljava/lang/String;)Lorg/kohsuke/github/GitHubRequest$Builder;
   #30 = Class              #111          // org/kohsuke/github/GHGist
   #31 = Methodref          #25.#112      // org/kohsuke/github/Requester.fetch:(Ljava/lang/Class;)Ljava/lang/Object;
   #32 = Class              #113          // java/util/HashMap
   #33 = Methodref          #32.#81       // java/util/HashMap."<init>":()V
   #34 = Class              #114          // org/kohsuke/github/GHGistUpdater
   #35 = Class              #115          // java/lang/Object
   #36 = Utf8               base
   #37 = Utf8               Lorg/kohsuke/github/GHGist;
   #38 = Utf8               builder
   #39 = Utf8               Lorg/kohsuke/github/Requester;
   #40 = Utf8               files
   #41 = Utf8               Ljava/util/LinkedHashMap;
   #42 = Utf8               Signature
   #43 = Utf8               Ljava/util/LinkedHashMap<Ljava/lang/String;Ljava/util/Map<Ljava/lang/String;Ljava/lang/String;>;>;
   #44 = Utf8               <init>
   #45 = Utf8               (Lorg/kohsuke/github/GHGist;)V
   #46 = Utf8               Code
   #47 = Utf8               LineNumberTable
   #48 = Utf8               LocalVariableTable
   #49 = Utf8               this
   #50 = Utf8               Lorg/kohsuke/github/GHGistUpdater;
   #51 = Utf8               addFile
   #52 = Utf8               (Ljava/lang/String;Ljava/lang/String;)Lorg/kohsuke/github/GHGistUpdater;
   #53 = Utf8               fileName
   #54 = Utf8               Ljava/lang/String;
   #55 = Utf8               content
   #56 = Utf8               Exceptions
   #57 = Class              #116          // java/io/IOException
   #58 = Utf8               RuntimeVisibleParameterAnnotations
   #59 = Utf8               Ljavax/annotation/Nonnull;
   #60 = Utf8               deleteFile
   #61 = Utf8               (Ljava/lang/String;)Lorg/kohsuke/github/GHGistUpdater;
   #62 = Utf8               renameFile
   #63 = Utf8               newFileName
   #64 = Utf8               file
   #65 = Utf8               Ljava/util/Map;
   #66 = Utf8               LocalVariableTypeTable
   #67 = Utf8               Ljava/util/Map<Ljava/lang/String;Ljava/lang/String;>;
   #68 = Utf8               updateFile
   #69 = Utf8               (Ljava/lang/String;Ljava/lang/String;Ljava/lang/String;)Lorg/kohsuke/github/GHGistUpdater;
   #70 = Utf8               description
   #71 = Utf8               desc
   #72 = Utf8               update
   #73 = Utf8               ()Lorg/kohsuke/github/GHGist;
   #74 = Utf8               lambda$updateFile$2
   #75 = Utf8               (Ljava/lang/String;)Ljava/util/Map;
   #76 = Utf8               d
   #77 = Utf8               lambda$updateFile$1
   #78 = Utf8               lambda$renameFile$0
   #79 = Utf8               SourceFile
   #80 = Utf8               GHGistUpdater.java
   #81 = NameAndType        #44:#117      // "<init>":()V
   #82 = NameAndType        #36:#37       // base:Lorg/kohsuke/github/GHGist;
   #83 = NameAndType        #118:#119     // root:()Lorg/kohsuke/github/GitHub;
   #84 = Class              #120          // org/kohsuke/github/GitHub
   #85 = NameAndType        #121:#122     // createRequest:()Lorg/kohsuke/github/Requester;
   #86 = NameAndType        #38:#39       // builder:Lorg/kohsuke/github/Requester;
   #87 = Utf8               java/util/LinkedHashMap
   #88 = NameAndType        #40:#41       // files:Ljava/util/LinkedHashMap;
   #89 = NameAndType        #68:#52       // updateFile:(Ljava/lang/String;Ljava/lang/String;)Lorg/kohsuke/github/GHGistUpdater;
   #90 = NameAndType        #123:#124     // put:(Ljava/lang/Object;Ljava/lang/Object;)Ljava/lang/Object;
   #91 = Utf8               BootstrapMethods
   #92 = MethodHandle       6:#125        // REF_invokeStatic java/lang/invoke/LambdaMetafactory.metafactory:(Ljava/lang/invoke/MethodHandles$Lookup;Ljava/lang/String;Ljava/lang/invoke/MethodType;Ljava/lang/invoke/MethodType;Ljava/lang/invoke/MethodHandle;Ljava/lang/invoke/MethodType;)Ljava/lang/invoke/CallSite;
   #93 = MethodType         #126          //  (Ljava/lang/Object;)Ljava/lang/Object;
   #94 = MethodHandle       6:#127        // REF_invokeStatic org/kohsuke/github/GHGistUpdater.lambda$renameFile$0:(Ljava/lang/String;)Ljava/util/Map;
   #95 = MethodType         #75           //  (Ljava/lang/String;)Ljava/util/Map;
   #96 = NameAndType        #128:#129     // apply:()Ljava/util/function/Function;
   #97 = NameAndType        #130:#131     // computeIfAbsent:(Ljava/lang/Object;Ljava/util/function/Function;)Ljava/lang/Object;
   #98 = Utf8               java/util/Map
   #99 = Utf8               filename
  #100 = MethodHandle       6:#132        // REF_invokeStatic org/kohsuke/github/GHGistUpdater.lambda$updateFile$1:(Ljava/lang/String;)Ljava/util/Map;
  #101 = MethodHandle       6:#133        // REF_invokeStatic org/kohsuke/github/GHGistUpdater.lambda$updateFile$2:(Ljava/lang/String;)Ljava/util/Map;
  #102 = NameAndType        #134:#138     // with:(Ljava/lang/String;Ljava/lang/String;)Lorg/kohsuke/github/GitHubRequest$Builder;
  #103 = NameAndType        #134:#139     // with:(Ljava/lang/String;Ljava/util/Map;)Lorg/kohsuke/github/GitHubRequest$Builder;
  #104 = Utf8               PATCH
  #105 = NameAndType        #140:#141     // method:(Ljava/lang/String;)Lorg/kohsuke/github/GitHubRequest$Builder;
  #106 = Utf8               org/kohsuke/github/Requester
  #107 = Utf8
  #108 = NameAndType        #142:#143     // getApiTailUrl:(Ljava/lang/String;)Ljava/lang/String;
  #109 = Utf8               java/lang/String
  #110 = NameAndType        #144:#145     // withUrlPath:(Ljava/lang/String;[Ljava/lang/String;)Lorg/kohsuke/github/GitHubRequest$Builder;
  #111 = Utf8               org/kohsuke/github/GHGist
  #112 = NameAndType        #146:#147     // fetch:(Ljava/lang/Class;)Ljava/lang/Object;
  #113 = Utf8               java/util/HashMap
  #114 = Utf8               org/kohsuke/github/GHGistUpdater
  #115 = Utf8               java/lang/Object
  #116 = Utf8               java/io/IOException
  #117 = Utf8               ()V
  #118 = Utf8               root
  #119 = Utf8               ()Lorg/kohsuke/github/GitHub;
  #120 = Utf8               org/kohsuke/github/GitHub
  #121 = Utf8               createRequest
  #122 = Utf8               ()Lorg/kohsuke/github/Requester;
  #123 = Utf8               put
  #124 = Utf8               (Ljava/lang/Object;Ljava/lang/Object;)Ljava/lang/Object;
  #125 = Methodref          #148.#149     // java/lang/invoke/LambdaMetafactory.metafactory:(Ljava/lang/invoke/MethodHandles$Lookup;Ljava/lang/String;Ljava/lang/invoke/MethodType;Ljava/lang/invoke/MethodType;Ljava/lang/invoke/MethodHandle;Ljava/lang/invoke/MethodType;)Ljava/lang/invoke/CallSite;
  #126 = Utf8               (Ljava/lang/Object;)Ljava/lang/Object;
  #127 = Methodref          #34.#150      // org/kohsuke/github/GHGistUpdater.lambda$renameFile$0:(Ljava/lang/String;)Ljava/util/Map;
  #128 = Utf8               apply
  #129 = Utf8               ()Ljava/util/function/Function;
  #130 = Utf8               computeIfAbsent
  #131 = Utf8               (Ljava/lang/Object;Ljava/util/function/Function;)Ljava/lang/Object;
  #132 = Methodref          #34.#151      // org/kohsuke/github/GHGistUpdater.lambda$updateFile$1:(Ljava/lang/String;)Ljava/util/Map;
  #133 = Methodref          #34.#152      // org/kohsuke/github/GHGistUpdater.lambda$updateFile$2:(Ljava/lang/String;)Ljava/util/Map;
  #134 = Utf8               with
  #135 = Class              #154          // org/kohsuke/github/GitHubRequest$Builder
  #136 = Utf8               Builder
  #137 = Utf8               InnerClasses
  #138 = Utf8               (Ljava/lang/String;Ljava/lang/String;)Lorg/kohsuke/github/GitHubRequest$Builder;
  #139 = Utf8               (Ljava/lang/String;Ljava/util/Map;)Lorg/kohsuke/github/GitHubRequest$Builder;
  #140 = Utf8               method
  #141 = Utf8               (Ljava/lang/String;)Lorg/kohsuke/github/GitHubRequest$Builder;
  #142 = Utf8               getApiTailUrl
  #143 = Utf8               (Ljava/lang/String;)Ljava/lang/String;
  #144 = Utf8               withUrlPath
  #145 = Utf8               (Ljava/lang/String;[Ljava/lang/String;)Lorg/kohsuke/github/GitHubRequest$Builder;
  #146 = Utf8               fetch
  #147 = Utf8               (Ljava/lang/Class;)Ljava/lang/Object;
  #148 = Class              #155          // java/lang/invoke/LambdaMetafactory
  #149 = NameAndType        #156:#159     // metafactory:(Ljava/lang/invoke/MethodHandles$Lookup;Ljava/lang/String;Ljava/lang/invoke/MethodType;Ljava/lang/invoke/MethodType;Ljava/lang/invoke/MethodHandle;Ljava/lang/invoke/MethodType;)Ljava/lang/invoke/CallSite;
  #150 = NameAndType        #78:#75       // lambda$renameFile$0:(Ljava/lang/String;)Ljava/util/Map;
  #151 = NameAndType        #77:#75       // lambda$updateFile$1:(Ljava/lang/String;)Ljava/util/Map;
  #152 = NameAndType        #74:#75       // lambda$updateFile$2:(Ljava/lang/String;)Ljava/util/Map;
  #153 = Class              #160          // org/kohsuke/github/GitHubRequest
  #154 = Utf8               org/kohsuke/github/GitHubRequest$Builder
  #155 = Utf8               java/lang/invoke/LambdaMetafactory
  #156 = Utf8               metafactory
  #157 = Class              #162          // java/lang/invoke/MethodHandles$Lookup
  #158 = Utf8               Lookup
  #159 = Utf8               (Ljava/lang/invoke/MethodHandles$Lookup;Ljava/lang/String;Ljava/lang/invoke/MethodType;Ljava/lang/invoke/MethodType;Ljava/lang/invoke/MethodHandle;Ljava/lang/invoke/MethodType;)Ljava/lang/invoke/CallSite;
  #160 = Utf8               org/kohsuke/github/GitHubRequest
  #161 = Class              #163          // java/lang/invoke/MethodHandles
  #162 = Utf8               java/lang/invoke/MethodHandles$Lookup
  #163 = Utf8               java/lang/invoke/MethodHandles
{
  private final org.kohsuke.github.GHGist base;
    descriptor: Lorg/kohsuke/github/GHGist;
    flags: (0x0012) ACC_PRIVATE, ACC_FINAL

  private final org.kohsuke.github.Requester builder;
    descriptor: Lorg/kohsuke/github/Requester;
    flags: (0x0012) ACC_PRIVATE, ACC_FINAL

  java.util.LinkedHashMap<java.lang.String, java.util.Map<java.lang.String, java.lang.String>> files;
    descriptor: Ljava/util/LinkedHashMap;
    flags: (0x0000)
    Signature: #43                          // Ljava/util/LinkedHashMap<Ljava/lang/String;Ljava/util/Map<Ljava/lang/String;Ljava/lang/String;>;>;

  org.kohsuke.github.GHGistUpdater(org.kohsuke.github.GHGist);
    descriptor: (Lorg/kohsuke/github/GHGist;)V
    flags: (0x0000)
    Code:
      stack=3, locals=2, args_size=2
         0: aload_0
         1: invokespecial #1                  // Method java/lang/Object."<init>":()V
         4: aload_0
         5: aload_1
         6: putfield      #2                  // Field base:Lorg/kohsuke/github/GHGist;
         9: aload_0
        10: aload_1
        11: invokevirtual #3                  // Method org/kohsuke/github/GHGist.root:()Lorg/kohsuke/github/GitHub;
        14: invokevirtual #4                  // Method org/kohsuke/github/GitHub.createRequest:()Lorg/kohsuke/github/Requester;
        17: putfield      #5                  // Field builder:Lorg/kohsuke/github/Requester;
        20: aload_0
        21: new           #6                  // class java/util/LinkedHashMap
        24: dup
        25: invokespecial #7                  // Method java/util/LinkedHashMap."<init>":()V
        28: putfield      #8                  // Field files:Ljava/util/LinkedHashMap;
        31: return
      LineNumberTable:
        line 20: 0
        line 21: 4
        line 22: 9
        line 24: 20
        line 25: 31
      LocalVariableTable:
        Start  Length  Slot  Name   Signature
            0      32     0  this   Lorg/kohsuke/github/GHGistUpdater;
            0      32     1  base   Lorg/kohsuke/github/GHGist;

  public org.kohsuke.github.GHGistUpdater addFile(java.lang.String, java.lang.String) throws java.io.IOException;
    descriptor: (Ljava/lang/String;Ljava/lang/String;)Lorg/kohsuke/github/GHGistUpdater;
    flags: (0x0001) ACC_PUBLIC
    Code:
      stack=3, locals=3, args_size=3
         0: aload_0
         1: aload_1
         2: aload_2
         3: invokevirtual #9                  // Method updateFile:(Ljava/lang/String;Ljava/lang/String;)Lorg/kohsuke/github/GHGistUpdater;
         6: pop
         7: aload_0
         8: areturn
      LineNumberTable:
        line 39: 0
        line 40: 7
      LocalVariableTable:
        Start  Length  Slot  Name   Signature
            0       9     0  this   Lorg/kohsuke/github/GHGistUpdater;
            0       9     1 fileName   Ljava/lang/String;
            0       9     2 content   Ljava/lang/String;
    Exceptions:
      throws java.io.IOException
    RuntimeVisibleParameterAnnotations:
      parameter 0:
        0: #59()
          javax.annotation.Nonnull
      parameter 1:
        0: #59()
          javax.annotation.Nonnull

  public org.kohsuke.github.GHGistUpdater deleteFile(java.lang.String) throws java.io.IOException;
    descriptor: (Ljava/lang/String;)Lorg/kohsuke/github/GHGistUpdater;
    flags: (0x0001) ACC_PUBLIC
    Code:
      stack=3, locals=2, args_size=2
         0: aload_0
         1: getfield      #8                  // Field files:Ljava/util/LinkedHashMap;
         4: aload_1
         5: aconst_null
         6: invokevirtual #10                 // Method java/util/LinkedHashMap.put:(Ljava/lang/Object;Ljava/lang/Object;)Ljava/lang/Object;
         9: pop
        10: aload_0
        11: areturn
      LineNumberTable:
        line 44: 0
        line 45: 10
      LocalVariableTable:
        Start  Length  Slot  Name   Signature
            0      12     0  this   Lorg/kohsuke/github/GHGistUpdater;
            0      12     1 fileName   Ljava/lang/String;
    Exceptions:
      throws java.io.IOException
    RuntimeVisibleParameterAnnotations:
      parameter 0:
        0: #59()
          javax.annotation.Nonnull

  public org.kohsuke.github.GHGistUpdater renameFile(java.lang.String, java.lang.String) throws java.io.IOException;
    descriptor: (Ljava/lang/String;Ljava/lang/String;)Lorg/kohsuke/github/GHGistUpdater;
    flags: (0x0001) ACC_PUBLIC
    Code:
      stack=3, locals=4, args_size=3
         0: aload_0
         1: getfield      #8                  // Field files:Ljava/util/LinkedHashMap;
         4: aload_1
         5: invokedynamic #11,  0             // InvokeDynamic #0:apply:()Ljava/util/function/Function;
        10: invokevirtual #12                 // Method java/util/LinkedHashMap.computeIfAbsent:(Ljava/lang/Object;Ljava/util/function/Function;)Ljava/lang/Object;
        13: checkcast     #13                 // class java/util/Map
        16: astore_3
        17: aload_3
        18: ldc           #14                 // String filename
        20: aload_2
        21: invokeinterface #15,  3           // InterfaceMethod java/util/Map.put:(Ljava/lang/Object;Ljava/lang/Object;)Ljava/lang/Object;
        26: pop
        27: aload_0
        28: areturn
      LineNumberTable:
        line 60: 0
        line 61: 17
        line 62: 27
      LocalVariableTable:
        Start  Length  Slot  Name   Signature
            0      29     0  this   Lorg/kohsuke/github/GHGistUpdater;
            0      29     1 fileName   Ljava/lang/String;
            0      29     2 newFileName   Ljava/lang/String;
           17      12     3  file   Ljava/util/Map;
      LocalVariableTypeTable:
        Start  Length  Slot  Name   Signature
           17      12     3  file   Ljava/util/Map<Ljava/lang/String;Ljava/lang/String;>;
    Exceptions:
      throws java.io.IOException
    RuntimeVisibleParameterAnnotations:
      parameter 0:
        0: #59()
          javax.annotation.Nonnull
      parameter 1:
        0: #59()
          javax.annotation.Nonnull

  public org.kohsuke.github.GHGistUpdater updateFile(java.lang.String, java.lang.String) throws java.io.IOException;
    descriptor: (Ljava/lang/String;Ljava/lang/String;)Lorg/kohsuke/github/GHGistUpdater;
    flags: (0x0001) ACC_PUBLIC
    Code:
      stack=3, locals=4, args_size=3
         0: aload_0
         1: getfield      #8                  // Field files:Ljava/util/LinkedHashMap;
         4: aload_1
         5: invokedynamic #16,  0             // InvokeDynamic #1:apply:()Ljava/util/function/Function;
        10: invokevirtual #12                 // Method java/util/LinkedHashMap.computeIfAbsent:(Ljava/lang/Object;Ljava/util/function/Function;)Ljava/lang/Object;
        13: checkcast     #13                 // class java/util/Map
        16: astore_3
        17: aload_3
        18: ldc           #17                 // String content
        20: aload_2
        21: invokeinterface #15,  3           // InterfaceMethod java/util/Map.put:(Ljava/lang/Object;Ljava/lang/Object;)Ljava/lang/Object;
        26: pop
        27: aload_0
        28: areturn
      LineNumberTable:
        line 77: 0
        line 78: 17
        line 79: 27
      LocalVariableTable:
        Start  Length  Slot  Name   Signature
            0      29     0  this   Lorg/kohsuke/github/GHGistUpdater;
            0      29     1 fileName   Ljava/lang/String;
            0      29     2 content   Ljava/lang/String;
           17      12     3  file   Ljava/util/Map;
      LocalVariableTypeTable:
        Start  Length  Slot  Name   Signature
           17      12     3  file   Ljava/util/Map<Ljava/lang/String;Ljava/lang/String;>;
    Exceptions:
      throws java.io.IOException
    RuntimeVisibleParameterAnnotations:
      parameter 0:
        0: #59()
          javax.annotation.Nonnull
      parameter 1:
        0: #59()
          javax.annotation.Nonnull

  public org.kohsuke.github.GHGistUpdater updateFile(java.lang.String, java.lang.String, java.lang.String) throws java.io.IOException;
    descriptor: (Ljava/lang/String;Ljava/lang/String;Ljava/lang/String;)Lorg/kohsuke/github/GHGistUpdater;
    flags: (0x0001) ACC_PUBLIC
    Code:
      stack=3, locals=5, args_size=4
         0: aload_0
         1: getfield      #8                  // Field files:Ljava/util/LinkedHashMap;
         4: aload_1
         5: invokedynamic #18,  0             // InvokeDynamic #2:apply:()Ljava/util/function/Function;
        10: invokevirtual #12                 // Method java/util/LinkedHashMap.computeIfAbsent:(Ljava/lang/Object;Ljava/util/function/Function;)Ljava/lang/Object;
        13: checkcast     #13                 // class java/util/Map
        16: astore        4
        18: aload         4
        20: ldc           #17                 // String content
        22: aload_3
        23: invokeinterface #15,  3           // InterfaceMethod java/util/Map.put:(Ljava/lang/Object;Ljava/lang/Object;)Ljava/lang/Object;
        28: pop
        29: aload         4
        31: ldc           #14                 // String filename
        33: aload_2
        34: invokeinterface #15,  3           // InterfaceMethod java/util/Map.put:(Ljava/lang/Object;Ljava/lang/Object;)Ljava/lang/Object;
        39: pop
        40: aload_0
        41: getfield      #8                  // Field files:Ljava/util/LinkedHashMap;
        44: aload_1
        45: aload         4
        47: invokevirtual #10                 // Method java/util/LinkedHashMap.put:(Ljava/lang/Object;Ljava/lang/Object;)Ljava/lang/Object;
        50: pop
        51: aload_0
        52: areturn
      LineNumberTable:
        line 97: 0
        line 98: 18
        line 99: 29
        line 100: 40
        line 101: 51
      LocalVariableTable:
        Start  Length  Slot  Name   Signature
            0      53     0  this   Lorg/kohsuke/github/GHGistUpdater;
            0      53     1 fileName   Ljava/lang/String;
            0      53     2 newFileName   Ljava/lang/String;
            0      53     3 content   Ljava/lang/String;
           18      35     4  file   Ljava/util/Map;
      LocalVariableTypeTable:
        Start  Length  Slot  Name   Signature
           18      35     4  file   Ljava/util/Map<Ljava/lang/String;Ljava/lang/String;>;
    Exceptions:
      throws java.io.IOException
    RuntimeVisibleParameterAnnotations:
      parameter 0:
        0: #59()
          javax.annotation.Nonnull
      parameter 1:
        0: #59()
          javax.annotation.Nonnull
      parameter 2:
        0: #59()
          javax.annotation.Nonnull

  public org.kohsuke.github.GHGistUpdater description(java.lang.String);
    descriptor: (Ljava/lang/String;)Lorg/kohsuke/github/GHGistUpdater;
    flags: (0x0001) ACC_PUBLIC
    Code:
      stack=3, locals=2, args_size=2
         0: aload_0
         1: getfield      #5                  // Field builder:Lorg/kohsuke/github/Requester;
         4: ldc           #19                 // String description
         6: aload_1
         7: invokevirtual #20                 // Method org/kohsuke/github/Requester.with:(Ljava/lang/String;Ljava/lang/String;)Lorg/kohsuke/github/GitHubRequest$Builder;
        10: pop
        11: aload_0
        12: areturn
      LineNumberTable:
        line 112: 0
        line 113: 11
      LocalVariableTable:
        Start  Length  Slot  Name   Signature
            0      13     0  this   Lorg/kohsuke/github/GHGistUpdater;
            0      13     1  desc   Ljava/lang/String;

  public org.kohsuke.github.GHGist update() throws java.io.IOException;
    descriptor: ()Lorg/kohsuke/github/GHGist;
    flags: (0x0001) ACC_PUBLIC
    Code:
      stack=3, locals=1, args_size=1
         0: aload_0
         1: getfield      #5                  // Field builder:Lorg/kohsuke/github/Requester;
         4: ldc           #21                 // String files
         6: aload_0
         7: getfield      #8                  // Field files:Ljava/util/LinkedHashMap;
        10: invokevirtual #22                 // Method org/kohsuke/github/Requester.with:(Ljava/lang/String;Ljava/util/Map;)Lorg/kohsuke/github/GitHubRequest$Builder;
        13: pop
        14: aload_0
        15: getfield      #5                  // Field builder:Lorg/kohsuke/github/Requester;
        18: ldc           #23                 // String PATCH
        20: invokevirtual #24                 // Method org/kohsuke/github/Requester.method:(Ljava/lang/String;)Lorg/kohsuke/github/GitHubRequest$Builder;
        23: checkcast     #25                 // class org/kohsuke/github/Requester
        26: aload_0
        27: getfield      #2                  // Field base:Lorg/kohsuke/github/GHGist;
        30: ldc           #26                 // String
        32: invokevirtual #27                 // Method org/kohsuke/github/GHGist.getApiTailUrl:(Ljava/lang/String;)Ljava/lang/String;
        35: iconst_0
        36: anewarray     #28                 // class java/lang/String
        39: invokevirtual #29                 // Method org/kohsuke/github/Requester.withUrlPath:(Ljava/lang/String;[Ljava/lang/String;)Lorg/kohsuke/github/GitHubRequest$Builder;
        42: checkcast     #25                 // class org/kohsuke/github/Requester
        45: ldc           #30                 // class org/kohsuke/github/GHGist
        47: invokevirtual #31                 // Method org/kohsuke/github/Requester.fetch:(Ljava/lang/Class;)Ljava/lang/Object;
        50: checkcast     #30                 // class org/kohsuke/github/GHGist
        53: areturn
      LineNumberTable:
        line 124: 0
        line 125: 14
      LocalVariableTable:
        Start  Length  Slot  Name   Signature
            0      54     0  this   Lorg/kohsuke/github/GHGistUpdater;
    Exceptions:
      throws java.io.IOException

  private static java.util.Map lambda$updateFile$2(java.lang.String);
    descriptor: (Ljava/lang/String;)Ljava/util/Map;
    flags: (0x100a) ACC_PRIVATE, ACC_STATIC, ACC_SYNTHETIC
    Code:
      stack=2, locals=1, args_size=1
         0: new           #32                 // class java/util/HashMap
         3: dup
         4: invokespecial #33                 // Method java/util/HashMap."<init>":()V
         7: areturn
      LineNumberTable:
        line 97: 0
      LocalVariableTable:
        Start  Length  Slot  Name   Signature
            0       8     0     d   Ljava/lang/String;

  private static java.util.Map lambda$updateFile$1(java.lang.String);
    descriptor: (Ljava/lang/String;)Ljava/util/Map;
    flags: (0x100a) ACC_PRIVATE, ACC_STATIC, ACC_SYNTHETIC
    Code:
      stack=2, locals=1, args_size=1
         0: new           #32                 // class java/util/HashMap
         3: dup
         4: invokespecial #33                 // Method java/util/HashMap."<init>":()V
         7: areturn
      LineNumberTable:
        line 77: 0
      LocalVariableTable:
        Start  Length  Slot  Name   Signature
            0       8     0     d   Ljava/lang/String;

  private static java.util.Map lambda$renameFile$0(java.lang.String);
    descriptor: (Ljava/lang/String;)Ljava/util/Map;
    flags: (0x100a) ACC_PRIVATE, ACC_STATIC, ACC_SYNTHETIC
    Code:
      stack=2, locals=1, args_size=1
         0: new           #32                 // class java/util/HashMap
         3: dup
         4: invokespecial #33                 // Method java/util/HashMap."<init>":()V
         7: areturn
      LineNumberTable:
        line 60: 0
      LocalVariableTable:
        Start  Length  Slot  Name   Signature
            0       8     0     d   Ljava/lang/String;
}
SourceFile: "GHGistUpdater.java"
InnerClasses:
  static #136= #135 of #153;              // Builder=class org/kohsuke/github/GitHubRequest$Builder of class org/kohsuke/github/GitHubRequest
  public static final #158= #157 of #161; // Lookup=class java/lang/invoke/MethodHandles$Lookup of class java/lang/invoke/MethodHandles
BootstrapMethods:
  0: #92 REF_invokeStatic java/lang/invoke/LambdaMetafactory.metafactory:(Ljava/lang/invoke/MethodHandles$Lookup;Ljava/lang/String;Ljava/lang/invoke/MethodType;Ljava/lang/invoke/MethodType;Ljava/lang/invoke/MethodHandle;Ljava/lang/invoke/MethodType;)Ljava/lang/invoke/CallSite;
    Method arguments:
      #93 (Ljava/lang/Object;)Ljava/lang/Object;
      #94 REF_invokeStatic org/kohsuke/github/GHGistUpdater.lambda$renameFile$0:(Ljava/lang/String;)Ljava/util/Map;
      #95 (Ljava/lang/String;)Ljava/util/Map;
  1: #92 REF_invokeStatic java/lang/invoke/LambdaMetafactory.metafactory:(Ljava/lang/invoke/MethodHandles$Lookup;Ljava/lang/String;Ljava/lang/invoke/MethodType;Ljava/lang/invoke/MethodType;Ljava/lang/invoke/MethodHandle;Ljava/lang/invoke/MethodType;)Ljava/lang/invoke/CallSite;
    Method arguments:
      #93 (Ljava/lang/Object;)Ljava/lang/Object;
      #100 REF_invokeStatic org/kohsuke/github/GHGistUpdater.lambda$updateFile$1:(Ljava/lang/String;)Ljava/util/Map;
      #95 (Ljava/lang/String;)Ljava/util/Map;
  2: #92 REF_invokeStatic java/lang/invoke/LambdaMetafactory.metafactory:(Ljava/lang/invoke/MethodHandles$Lookup;Ljava/lang/String;Ljava/lang/invoke/MethodType;Ljava/lang/invoke/MethodType;Ljava/lang/invoke/MethodHandle;Ljava/lang/invoke/MethodType;)Ljava/lang/invoke/CallSite;
    Method arguments:
      #93 (Ljava/lang/Object;)Ljava/lang/Object;
      #101 REF_invokeStatic org/kohsuke/github/GHGistUpdater.lambda$updateFile$2:(Ljava/lang/String;)Ljava/util/Map;
      #95 (Ljava/lang/String;)Ljava/util/Map;
