Classfile /Users/mw/Projects/slang-braindump/.jar/jar8/assemble/slang-braindump/assemble/content/org/kohsuke/github/GHInvitation.class
  Last modified May 29, 2022; size 2055 bytes
  SHA-256 checksum 6911cd69a25863680ec3453494e5e79abfba2df0e93730a4b9eeeaaa1428b483
  Compiled from "GHInvitation.java"
public class org.kohsuke.github.GHInvitation extends org.kohsuke.github.GHObject
  minor version: 0
  major version: 52
  flags: (0x0021) ACC_PUBLIC, ACC_SUPER
  this_class: #20                         // org/kohsuke/github/GHInvitation
  super_class: #21                        // org/kohsuke/github/GHObject
  interfaces: 0, fields: 6, methods: 4, attributes: 3
Constant pool:
    #1 = Methodref          #21.#56       // org/kohsuke/github/GHObject."<init>":()V
    #2 = Methodref          #20.#57       // org/kohsuke/github/GHInvitation.root:()Lorg/kohsuke/github/GitHub;
    #3 = Methodref          #58.#59       // org/kohsuke/github/GitHub.createRequest:()Lorg/kohsuke/github/Requester;
    #4 = String             #60           // PATCH
    #5 = Methodref          #6.#61        // org/kohsuke/github/Requester.method:(Ljava/lang/String;)Lorg/kohsuke/github/GitHubRequest$Builder;
    #6 = Class              #62           // org/kohsuke/github/Requester
    #7 = Class              #63           // java/lang/StringBuilder
    #8 = Methodref          #7.#56        // java/lang/StringBuilder."<init>":()V
    #9 = String             #64           // /user/repository_invitations/
   #10 = Methodref          #7.#65        // java/lang/StringBuilder.append:(Ljava/lang/String;)Ljava/lang/StringBuilder;
   #11 = Fieldref           #20.#66       // org/kohsuke/github/GHInvitation.id:I
   #12 = Methodref          #7.#67        // java/lang/StringBuilder.append:(I)Ljava/lang/StringBuilder;
   #13 = Methodref          #7.#68        // java/lang/StringBuilder.toString:()Ljava/lang/String;
   #14 = Class              #69           // java/lang/String
   #15 = Methodref          #6.#70        // org/kohsuke/github/Requester.withUrlPath:(Ljava/lang/String;[Ljava/lang/String;)Lorg/kohsuke/github/GitHubRequest$Builder;
   #16 = Methodref          #6.#71        // org/kohsuke/github/Requester.send:()V
   #17 = String             #72           // DELETE
   #18 = Fieldref           #20.#73       // org/kohsuke/github/GHInvitation.html_url:Ljava/lang/String;
   #19 = Methodref          #74.#75       // org/kohsuke/github/GitHubClient.parseURL:(Ljava/lang/String;)Ljava/net/URL;
   #20 = Class              #76           // org/kohsuke/github/GHInvitation
   #21 = Class              #77           // org/kohsuke/github/GHObject
   #22 = Utf8               id
   #23 = Utf8               I
   #24 = Utf8               repository
   #25 = Utf8               Lorg/kohsuke/github/GHRepository;
   #26 = Utf8               invitee
   #27 = Utf8               Lorg/kohsuke/github/GHUser;
   #28 = Utf8               inviter
   #29 = Utf8               permissions
   #30 = Utf8               Ljava/lang/String;
   #31 = Utf8               html_url
   #32 = Utf8               <init>
   #33 = Utf8               ()V
   #34 = Utf8               Code
   #35 = Utf8               LineNumberTable
   #36 = Utf8               LocalVariableTable
   #37 = Utf8               this
   #38 = Utf8               Lorg/kohsuke/github/GHInvitation;
   #39 = Utf8               accept
   #40 = Utf8               Exceptions
   #41 = Class              #78           // java/io/IOException
   #42 = Utf8               decline
   #43 = Utf8               getHtmlUrl
   #44 = Utf8               ()Ljava/net/URL;
   #45 = Utf8               SourceFile
   #46 = Utf8               GHInvitation.java
   #47 = Utf8               RuntimeInvisibleAnnotations
   #48 = Utf8               Ledu/umd/cs/findbugs/annotations/SuppressFBWarnings;
   #49 = Utf8               value
   #50 = Utf8               UWF_UNWRITTEN_PUBLIC_OR_PROTECTED_FIELD
   #51 = Utf8               UWF_UNWRITTEN_FIELD
   #52 = Utf8               NP_UNWRITTEN_FIELD
   #53 = Utf8               UUF_UNUSED_FIELD
   #54 = Utf8               justification
   #55 = Utf8               JSON API
   #56 = NameAndType        #32:#33       // "<init>":()V
   #57 = NameAndType        #79:#80       // root:()Lorg/kohsuke/github/GitHub;
   #58 = Class              #81           // org/kohsuke/github/GitHub
   #59 = NameAndType        #82:#83       // createRequest:()Lorg/kohsuke/github/Requester;
   #60 = Utf8               PATCH
   #61 = NameAndType        #84:#88       // method:(Ljava/lang/String;)Lorg/kohsuke/github/GitHubRequest$Builder;
   #62 = Utf8               org/kohsuke/github/Requester
   #63 = Utf8               java/lang/StringBuilder
   #64 = Utf8               /user/repository_invitations/
   #65 = NameAndType        #89:#90       // append:(Ljava/lang/String;)Ljava/lang/StringBuilder;
   #66 = NameAndType        #22:#23       // id:I
   #67 = NameAndType        #89:#91       // append:(I)Ljava/lang/StringBuilder;
   #68 = NameAndType        #92:#93       // toString:()Ljava/lang/String;
   #69 = Utf8               java/lang/String
   #70 = NameAndType        #94:#95       // withUrlPath:(Ljava/lang/String;[Ljava/lang/String;)Lorg/kohsuke/github/GitHubRequest$Builder;
   #71 = NameAndType        #96:#33       // send:()V
   #72 = Utf8               DELETE
   #73 = NameAndType        #31:#30       // html_url:Ljava/lang/String;
   #74 = Class              #97           // org/kohsuke/github/GitHubClient
   #75 = NameAndType        #98:#99       // parseURL:(Ljava/lang/String;)Ljava/net/URL;
   #76 = Utf8               org/kohsuke/github/GHInvitation
   #77 = Utf8               org/kohsuke/github/GHObject
   #78 = Utf8               java/io/IOException
   #79 = Utf8               root
   #80 = Utf8               ()Lorg/kohsuke/github/GitHub;
   #81 = Utf8               org/kohsuke/github/GitHub
   #82 = Utf8               createRequest
   #83 = Utf8               ()Lorg/kohsuke/github/Requester;
   #84 = Utf8               method
   #85 = Class              #101          // org/kohsuke/github/GitHubRequest$Builder
   #86 = Utf8               Builder
   #87 = Utf8               InnerClasses
   #88 = Utf8               (Ljava/lang/String;)Lorg/kohsuke/github/GitHubRequest$Builder;
   #89 = Utf8               append
   #90 = Utf8               (Ljava/lang/String;)Ljava/lang/StringBuilder;
   #91 = Utf8               (I)Ljava/lang/StringBuilder;
   #92 = Utf8               toString
   #93 = Utf8               ()Ljava/lang/String;
   #94 = Utf8               withUrlPath
   #95 = Utf8               (Ljava/lang/String;[Ljava/lang/String;)Lorg/kohsuke/github/GitHubRequest$Builder;
   #96 = Utf8               send
   #97 = Utf8               org/kohsuke/github/GitHubClient
   #98 = Utf8               parseURL
   #99 = Utf8               (Ljava/lang/String;)Ljava/net/URL;
  #100 = Class              #102          // org/kohsuke/github/GitHubRequest
  #101 = Utf8               org/kohsuke/github/GitHubRequest$Builder
  #102 = Utf8               org/kohsuke/github/GitHubRequest
{
  private int id;
    descriptor: I
    flags: (0x0002) ACC_PRIVATE

  private org.kohsuke.github.GHRepository repository;
    descriptor: Lorg/kohsuke/github/GHRepository;
    flags: (0x0002) ACC_PRIVATE

  private org.kohsuke.github.GHUser invitee;
    descriptor: Lorg/kohsuke/github/GHUser;
    flags: (0x0002) ACC_PRIVATE

  private org.kohsuke.github.GHUser inviter;
    descriptor: Lorg/kohsuke/github/GHUser;
    flags: (0x0002) ACC_PRIVATE

  private java.lang.String permissions;
    descriptor: Ljava/lang/String;
    flags: (0x0002) ACC_PRIVATE

  private java.lang.String html_url;
    descriptor: Ljava/lang/String;
    flags: (0x0002) ACC_PRIVATE

  public org.kohsuke.github.GHInvitation();
    descriptor: ()V
    flags: (0x0001) ACC_PUBLIC
    Code:
      stack=1, locals=1, args_size=1
         0: aload_0
         1: invokespecial #1                  // Method org/kohsuke/github/GHObject."<init>":()V
         4: return
      LineNumberTable:
        line 18: 0
      LocalVariableTable:
        Start  Length  Slot  Name   Signature
            0       5     0  this   Lorg/kohsuke/github/GHInvitation;

  public void accept() throws java.io.IOException;
    descriptor: ()V
    flags: (0x0001) ACC_PUBLIC
    Code:
      stack=3, locals=1, args_size=1
         0: aload_0
         1: invokevirtual #2                  // Method root:()Lorg/kohsuke/github/GitHub;
         4: invokevirtual #3                  // Method org/kohsuke/github/GitHub.createRequest:()Lorg/kohsuke/github/Requester;
         7: ldc           #4                  // String PATCH
         9: invokevirtual #5                  // Method org/kohsuke/github/Requester.method:(Ljava/lang/String;)Lorg/kohsuke/github/GitHubRequest$Builder;
        12: checkcast     #6                  // class org/kohsuke/github/Requester
        15: new           #7                  // class java/lang/StringBuilder
        18: dup
        19: invokespecial #8                  // Method java/lang/StringBuilder."<init>":()V
        22: ldc           #9                  // String /user/repository_invitations/
        24: invokevirtual #10                 // Method java/lang/StringBuilder.append:(Ljava/lang/String;)Ljava/lang/StringBuilder;
        27: aload_0
        28: getfield      #11                 // Field id:I
        31: invokevirtual #12                 // Method java/lang/StringBuilder.append:(I)Ljava/lang/StringBuilder;
        34: invokevirtual #13                 // Method java/lang/StringBuilder.toString:()Ljava/lang/String;
        37: iconst_0
        38: anewarray     #14                 // class java/lang/String
        41: invokevirtual #15                 // Method org/kohsuke/github/Requester.withUrlPath:(Ljava/lang/String;[Ljava/lang/String;)Lorg/kohsuke/github/GitHubRequest$Builder;
        44: checkcast     #6                  // class org/kohsuke/github/Requester
        47: invokevirtual #16                 // Method org/kohsuke/github/Requester.send:()V
        50: return
      LineNumberTable:
        line 33: 0
        line 34: 50
      LocalVariableTable:
        Start  Length  Slot  Name   Signature
            0      51     0  this   Lorg/kohsuke/github/GHInvitation;
    Exceptions:
      throws java.io.IOException

  public void decline() throws java.io.IOException;
    descriptor: ()V
    flags: (0x0001) ACC_PUBLIC
    Code:
      stack=3, locals=1, args_size=1
         0: aload_0
         1: invokevirtual #2                  // Method root:()Lorg/kohsuke/github/GitHub;
         4: invokevirtual #3                  // Method org/kohsuke/github/GitHub.createRequest:()Lorg/kohsuke/github/Requester;
         7: ldc           #17                 // String DELETE
         9: invokevirtual #5                  // Method org/kohsuke/github/Requester.method:(Ljava/lang/String;)Lorg/kohsuke/github/GitHubRequest$Builder;
        12: checkcast     #6                  // class org/kohsuke/github/Requester
        15: new           #7                  // class java/lang/StringBuilder
        18: dup
        19: invokespecial #8                  // Method java/lang/StringBuilder."<init>":()V
        22: ldc           #9                  // String /user/repository_invitations/
        24: invokevirtual #10                 // Method java/lang/StringBuilder.append:(Ljava/lang/String;)Ljava/lang/StringBuilder;
        27: aload_0
        28: getfield      #11                 // Field id:I
        31: invokevirtual #12                 // Method java/lang/StringBuilder.append:(I)Ljava/lang/StringBuilder;
        34: invokevirtual #13                 // Method java/lang/StringBuilder.toString:()Ljava/lang/String;
        37: iconst_0
        38: anewarray     #14                 // class java/lang/String
        41: invokevirtual #15                 // Method org/kohsuke/github/Requester.withUrlPath:(Ljava/lang/String;[Ljava/lang/String;)Lorg/kohsuke/github/GitHubRequest$Builder;
        44: checkcast     #6                  // class org/kohsuke/github/Requester
        47: invokevirtual #16                 // Method org/kohsuke/github/Requester.send:()V
        50: return
      LineNumberTable:
        line 43: 0
        line 44: 50
      LocalVariableTable:
        Start  Length  Slot  Name   Signature
            0      51     0  this   Lorg/kohsuke/github/GHInvitation;
    Exceptions:
      throws java.io.IOException

  public java.net.URL getHtmlUrl();
    descriptor: ()Ljava/net/URL;
    flags: (0x0001) ACC_PUBLIC
    Code:
      stack=1, locals=1, args_size=1
         0: aload_0
         1: getfield      #18                 // Field html_url:Ljava/lang/String;
         4: invokestatic  #19                 // Method org/kohsuke/github/GitHubClient.parseURL:(Ljava/lang/String;)Ljava/net/URL;
         7: areturn
      LineNumberTable:
        line 48: 0
      LocalVariableTable:
        Start  Length  Slot  Name   Signature
            0       8     0  this   Lorg/kohsuke/github/GHInvitation;
}
SourceFile: "GHInvitation.java"
RuntimeInvisibleAnnotations:
  0: #48(#49=[s#50,s#51,s#52,s#53],#54=s#55)
    edu.umd.cs.findbugs.annotations.SuppressFBWarnings(
      value=["UWF_UNWRITTEN_PUBLIC_OR_PROTECTED_FIELD","UWF_UNWRITTEN_FIELD","NP_UNWRITTEN_FIELD","UUF_UNUSED_FIELD"]
      justification="JSON API"
    )
InnerClasses:
  static #86= #85 of #100;                // Builder=class org/kohsuke/github/GitHubRequest$Builder of class org/kohsuke/github/GitHubRequest
