Classfile /Users/mw/Projects/slang-braindump/.jar/jar8/assemble/slang-braindump/assemble/content/org/kohsuke/github/GHIssueQueryBuilder.class
  Last modified May 29, 2022; size 3054 bytes
  SHA-256 checksum ad9a8d9d64cb57daf89cf0c2b9cf67c5066c81346e7ce7d66052614e14d5c23a
  Compiled from "GHIssueQueryBuilder.java"
public abstract class org.kohsuke.github.GHIssueQueryBuilder extends org.kohsuke.github.GHQueryBuilder<org.kohsuke.github.GHIssue>
  minor version: 0
  major version: 52
  flags: (0x0421) ACC_PUBLIC, ACC_SUPER, ACC_ABSTRACT
  this_class: #24                         // org/kohsuke/github/GHIssueQueryBuilder
  super_class: #25                        // org/kohsuke/github/GHQueryBuilder
  interfaces: 0, fields: 1, methods: 9, attributes: 3
Constant pool:
    #1 = Methodref          #25.#72       // org/kohsuke/github/GHQueryBuilder."<init>":(Lorg/kohsuke/github/GitHub;)V
    #2 = Class              #73           // java/util/ArrayList
    #3 = Methodref          #2.#74        // java/util/ArrayList."<init>":()V
    #4 = Fieldref           #24.#75       // org/kohsuke/github/GHIssueQueryBuilder.labels:Ljava/util/List;
    #5 = Fieldref           #24.#76       // org/kohsuke/github/GHIssueQueryBuilder.req:Lorg/kohsuke/github/Requester;
    #6 = String             #44           // state
    #7 = Methodref          #77.#78       // org/kohsuke/github/Requester.with:(Ljava/lang/String;Ljava/lang/Enum;)Lorg/kohsuke/github/GitHubRequest$Builder;
    #8 = Methodref          #79.#80       // java/lang/String.trim:()Ljava/lang/String;
    #9 = Methodref          #79.#81       // java/lang/String.isEmpty:()Z
   #10 = InterfaceMethodref #82.#83       // java/util/List.add:(Ljava/lang/Object;)Z
   #11 = String             #31           // labels
   #12 = String             #84           // ,
   #13 = Methodref          #79.#85       // java/lang/String.join:(Ljava/lang/CharSequence;Ljava/lang/Iterable;)Ljava/lang/String;
   #14 = Methodref          #77.#86       // org/kohsuke/github/Requester.with:(Ljava/lang/String;Ljava/lang/String;)Lorg/kohsuke/github/GitHubRequest$Builder;
   #15 = String             #51           // sort
   #16 = String             #54           // direction
   #17 = String             #57           // since
   #18 = Methodref          #87.#88       // org/kohsuke/github/GitHubClient.printDate:(Ljava/util/Date;)Ljava/lang/String;
   #19 = Class              #89           // java/util/Date
   #20 = Methodref          #19.#90       // java/util/Date."<init>":(J)V
   #21 = Methodref          #24.#91       // org/kohsuke/github/GHIssueQueryBuilder.since:(Ljava/util/Date;)Lorg/kohsuke/github/GHIssueQueryBuilder;
   #22 = String             #92           // per_page
   #23 = Methodref          #77.#93       // org/kohsuke/github/Requester.with:(Ljava/lang/String;I)Lorg/kohsuke/github/GitHubRequest$Builder;
   #24 = Class              #94           // org/kohsuke/github/GHIssueQueryBuilder
   #25 = Class              #95           // org/kohsuke/github/GHQueryBuilder
   #26 = Class              #96           // org/kohsuke/github/GHIssueQueryBuilder$ForRepository
   #27 = Utf8               ForRepository
   #28 = Utf8               InnerClasses
   #29 = Class              #97           // org/kohsuke/github/GHIssueQueryBuilder$Sort
   #30 = Utf8               Sort
   #31 = Utf8               labels
   #32 = Utf8               Ljava/util/List;
   #33 = Utf8               Signature
   #34 = Utf8               Ljava/util/List<Ljava/lang/String;>;
   #35 = Utf8               <init>
   #36 = Utf8               (Lorg/kohsuke/github/GitHub;)V
   #37 = Utf8               Code
   #38 = Utf8               LineNumberTable
   #39 = Utf8               LocalVariableTable
   #40 = Utf8               this
   #41 = Utf8               Lorg/kohsuke/github/GHIssueQueryBuilder;
   #42 = Utf8               root
   #43 = Utf8               Lorg/kohsuke/github/GitHub;
   #44 = Utf8               state
   #45 = Utf8               (Lorg/kohsuke/github/GHIssueState;)Lorg/kohsuke/github/GHIssueQueryBuilder;
   #46 = Utf8               Lorg/kohsuke/github/GHIssueState;
   #47 = Utf8               label
   #48 = Utf8               (Ljava/lang/String;)Lorg/kohsuke/github/GHIssueQueryBuilder;
   #49 = Utf8               Ljava/lang/String;
   #50 = Utf8               StackMapTable
   #51 = Utf8               sort
   #52 = Utf8               (Lorg/kohsuke/github/GHIssueQueryBuilder$Sort;)Lorg/kohsuke/github/GHIssueQueryBuilder;
   #53 = Utf8               Lorg/kohsuke/github/GHIssueQueryBuilder$Sort;
   #54 = Utf8               direction
   #55 = Utf8               (Lorg/kohsuke/github/GHDirection;)Lorg/kohsuke/github/GHIssueQueryBuilder;
   #56 = Utf8               Lorg/kohsuke/github/GHDirection;
   #57 = Utf8               since
   #58 = Utf8               (Ljava/util/Date;)Lorg/kohsuke/github/GHIssueQueryBuilder;
   #59 = Utf8               date
   #60 = Utf8               Ljava/util/Date;
   #61 = Utf8               (J)Lorg/kohsuke/github/GHIssueQueryBuilder;
   #62 = Utf8               timestamp
   #63 = Utf8               J
   #64 = Utf8               pageSize
   #65 = Utf8               (I)Lorg/kohsuke/github/GHIssueQueryBuilder;
   #66 = Utf8               I
   #67 = Utf8               getApiUrl
   #68 = Utf8               ()Ljava/lang/String;
   #69 = Utf8               Lorg/kohsuke/github/GHQueryBuilder<Lorg/kohsuke/github/GHIssue;>;
   #70 = Utf8               SourceFile
   #71 = Utf8               GHIssueQueryBuilder.java
   #72 = NameAndType        #35:#36       // "<init>":(Lorg/kohsuke/github/GitHub;)V
   #73 = Utf8               java/util/ArrayList
   #74 = NameAndType        #35:#98       // "<init>":()V
   #75 = NameAndType        #31:#32       // labels:Ljava/util/List;
   #76 = NameAndType        #99:#100      // req:Lorg/kohsuke/github/Requester;
   #77 = Class              #101          // org/kohsuke/github/Requester
   #78 = NameAndType        #102:#105     // with:(Ljava/lang/String;Ljava/lang/Enum;)Lorg/kohsuke/github/GitHubRequest$Builder;
   #79 = Class              #106          // java/lang/String
   #80 = NameAndType        #107:#68      // trim:()Ljava/lang/String;
   #81 = NameAndType        #108:#109     // isEmpty:()Z
   #82 = Class              #110          // java/util/List
   #83 = NameAndType        #111:#112     // add:(Ljava/lang/Object;)Z
   #84 = Utf8               ,
   #85 = NameAndType        #113:#114     // join:(Ljava/lang/CharSequence;Ljava/lang/Iterable;)Ljava/lang/String;
   #86 = NameAndType        #102:#115     // with:(Ljava/lang/String;Ljava/lang/String;)Lorg/kohsuke/github/GitHubRequest$Builder;
   #87 = Class              #116          // org/kohsuke/github/GitHubClient
   #88 = NameAndType        #117:#118     // printDate:(Ljava/util/Date;)Ljava/lang/String;
   #89 = Utf8               java/util/Date
   #90 = NameAndType        #35:#119      // "<init>":(J)V
   #91 = NameAndType        #57:#58       // since:(Ljava/util/Date;)Lorg/kohsuke/github/GHIssueQueryBuilder;
   #92 = Utf8               per_page
   #93 = NameAndType        #102:#120     // with:(Ljava/lang/String;I)Lorg/kohsuke/github/GitHubRequest$Builder;
   #94 = Utf8               org/kohsuke/github/GHIssueQueryBuilder
   #95 = Utf8               org/kohsuke/github/GHQueryBuilder
   #96 = Utf8               org/kohsuke/github/GHIssueQueryBuilder$ForRepository
   #97 = Utf8               org/kohsuke/github/GHIssueQueryBuilder$Sort
   #98 = Utf8               ()V
   #99 = Utf8               req
  #100 = Utf8               Lorg/kohsuke/github/Requester;
  #101 = Utf8               org/kohsuke/github/Requester
  #102 = Utf8               with
  #103 = Class              #122          // org/kohsuke/github/GitHubRequest$Builder
  #104 = Utf8               Builder
  #105 = Utf8               (Ljava/lang/String;Ljava/lang/Enum;)Lorg/kohsuke/github/GitHubRequest$Builder;
  #106 = Utf8               java/lang/String
  #107 = Utf8               trim
  #108 = Utf8               isEmpty
  #109 = Utf8               ()Z
  #110 = Utf8               java/util/List
  #111 = Utf8               add
  #112 = Utf8               (Ljava/lang/Object;)Z
  #113 = Utf8               join
  #114 = Utf8               (Ljava/lang/CharSequence;Ljava/lang/Iterable;)Ljava/lang/String;
  #115 = Utf8               (Ljava/lang/String;Ljava/lang/String;)Lorg/kohsuke/github/GitHubRequest$Builder;
  #116 = Utf8               org/kohsuke/github/GitHubClient
  #117 = Utf8               printDate
  #118 = Utf8               (Ljava/util/Date;)Ljava/lang/String;
  #119 = Utf8               (J)V
  #120 = Utf8               (Ljava/lang/String;I)Lorg/kohsuke/github/GitHubRequest$Builder;
  #121 = Class              #123          // org/kohsuke/github/GitHubRequest
  #122 = Utf8               org/kohsuke/github/GitHubRequest$Builder
  #123 = Utf8               org/kohsuke/github/GitHubRequest
{
  private final java.util.List<java.lang.String> labels;
    descriptor: Ljava/util/List;
    flags: (0x0012) ACC_PRIVATE, ACC_FINAL
    Signature: #34                          // Ljava/util/List<Ljava/lang/String;>;

  org.kohsuke.github.GHIssueQueryBuilder(org.kohsuke.github.GitHub);
    descriptor: (Lorg/kohsuke/github/GitHub;)V
    flags: (0x0000)
    Code:
      stack=3, locals=2, args_size=2
         0: aload_0
         1: aload_1
         2: invokespecial #1                  // Method org/kohsuke/github/GHQueryBuilder."<init>":(Lorg/kohsuke/github/GitHub;)V
         5: aload_0
         6: new           #2                  // class java/util/ArrayList
         9: dup
        10: invokespecial #3                  // Method java/util/ArrayList."<init>":()V
        13: putfield      #4                  // Field labels:Ljava/util/List;
        16: return
      LineNumberTable:
        line 11: 0
        line 8: 5
        line 12: 16
      LocalVariableTable:
        Start  Length  Slot  Name   Signature
            0      17     0  this   Lorg/kohsuke/github/GHIssueQueryBuilder;
            0      17     1  root   Lorg/kohsuke/github/GitHub;

  public org.kohsuke.github.GHIssueQueryBuilder state(org.kohsuke.github.GHIssueState);
    descriptor: (Lorg/kohsuke/github/GHIssueState;)Lorg/kohsuke/github/GHIssueQueryBuilder;
    flags: (0x0001) ACC_PUBLIC
    Code:
      stack=3, locals=2, args_size=2
         0: aload_0
         1: getfield      #5                  // Field req:Lorg/kohsuke/github/Requester;
         4: ldc           #6                  // String state
         6: aload_1
         7: invokevirtual #7                  // Method org/kohsuke/github/Requester.with:(Ljava/lang/String;Ljava/lang/Enum;)Lorg/kohsuke/github/GitHubRequest$Builder;
        10: pop
        11: aload_0
        12: areturn
      LineNumberTable:
        line 22: 0
        line 23: 11
      LocalVariableTable:
        Start  Length  Slot  Name   Signature
            0      13     0  this   Lorg/kohsuke/github/GHIssueQueryBuilder;
            0      13     1 state   Lorg/kohsuke/github/GHIssueState;

  public org.kohsuke.github.GHIssueQueryBuilder label(java.lang.String);
    descriptor: (Ljava/lang/String;)Lorg/kohsuke/github/GHIssueQueryBuilder;
    flags: (0x0001) ACC_PUBLIC
    Code:
      stack=4, locals=2, args_size=2
         0: aload_1
         1: ifnull        44
         4: aload_1
         5: invokevirtual #8                  // Method java/lang/String.trim:()Ljava/lang/String;
         8: invokevirtual #9                  // Method java/lang/String.isEmpty:()Z
        11: ifne          44
        14: aload_0
        15: getfield      #4                  // Field labels:Ljava/util/List;
        18: aload_1
        19: invokeinterface #10,  2           // InterfaceMethod java/util/List.add:(Ljava/lang/Object;)Z
        24: pop
        25: aload_0
        26: getfield      #5                  // Field req:Lorg/kohsuke/github/Requester;
        29: ldc           #11                 // String labels
        31: ldc           #12                 // String ,
        33: aload_0
        34: getfield      #4                  // Field labels:Ljava/util/List;
        37: invokestatic  #13                 // Method java/lang/String.join:(Ljava/lang/CharSequence;Ljava/lang/Iterable;)Ljava/lang/String;
        40: invokevirtual #14                 // Method org/kohsuke/github/Requester.with:(Ljava/lang/String;Ljava/lang/String;)Lorg/kohsuke/github/GitHubRequest$Builder;
        43: pop
        44: aload_0
        45: areturn
      LineNumberTable:
        line 34: 0
        line 35: 14
        line 36: 25
        line 38: 44
      LocalVariableTable:
        Start  Length  Slot  Name   Signature
            0      46     0  this   Lorg/kohsuke/github/GHIssueQueryBuilder;
            0      46     1 label   Ljava/lang/String;
      StackMapTable: number_of_entries = 1
        frame_type = 44 /* same */

  public org.kohsuke.github.GHIssueQueryBuilder sort(org.kohsuke.github.GHIssueQueryBuilder$Sort);
    descriptor: (Lorg/kohsuke/github/GHIssueQueryBuilder$Sort;)Lorg/kohsuke/github/GHIssueQueryBuilder;
    flags: (0x0001) ACC_PUBLIC
    Code:
      stack=3, locals=2, args_size=2
         0: aload_0
         1: getfield      #5                  // Field req:Lorg/kohsuke/github/Requester;
         4: ldc           #15                 // String sort
         6: aload_1
         7: invokevirtual #7                  // Method org/kohsuke/github/Requester.with:(Ljava/lang/String;Ljava/lang/Enum;)Lorg/kohsuke/github/GitHubRequest$Builder;
        10: pop
        11: aload_0
        12: areturn
      LineNumberTable:
        line 49: 0
        line 50: 11
      LocalVariableTable:
        Start  Length  Slot  Name   Signature
            0      13     0  this   Lorg/kohsuke/github/GHIssueQueryBuilder;
            0      13     1  sort   Lorg/kohsuke/github/GHIssueQueryBuilder$Sort;

  public org.kohsuke.github.GHIssueQueryBuilder direction(org.kohsuke.github.GHDirection);
    descriptor: (Lorg/kohsuke/github/GHDirection;)Lorg/kohsuke/github/GHIssueQueryBuilder;
    flags: (0x0001) ACC_PUBLIC
    Code:
      stack=3, locals=2, args_size=2
         0: aload_0
         1: getfield      #5                  // Field req:Lorg/kohsuke/github/Requester;
         4: ldc           #16                 // String direction
         6: aload_1
         7: invokevirtual #7                  // Method org/kohsuke/github/Requester.with:(Ljava/lang/String;Ljava/lang/Enum;)Lorg/kohsuke/github/GitHubRequest$Builder;
        10: pop
        11: aload_0
        12: areturn
      LineNumberTable:
        line 61: 0
        line 62: 11
      LocalVariableTable:
        Start  Length  Slot  Name   Signature
            0      13     0  this   Lorg/kohsuke/github/GHIssueQueryBuilder;
            0      13     1 direction   Lorg/kohsuke/github/GHDirection;

  public org.kohsuke.github.GHIssueQueryBuilder since(java.util.Date);
    descriptor: (Ljava/util/Date;)Lorg/kohsuke/github/GHIssueQueryBuilder;
    flags: (0x0001) ACC_PUBLIC
    Code:
      stack=3, locals=2, args_size=2
         0: aload_0
         1: getfield      #5                  // Field req:Lorg/kohsuke/github/Requester;
         4: ldc           #17                 // String since
         6: aload_1
         7: invokestatic  #18                 // Method org/kohsuke/github/GitHubClient.printDate:(Ljava/util/Date;)Ljava/lang/String;
        10: invokevirtual #14                 // Method org/kohsuke/github/Requester.with:(Ljava/lang/String;Ljava/lang/String;)Lorg/kohsuke/github/GitHubRequest$Builder;
        13: pop
        14: aload_0
        15: areturn
      LineNumberTable:
        line 73: 0
        line 74: 14
      LocalVariableTable:
        Start  Length  Slot  Name   Signature
            0      16     0  this   Lorg/kohsuke/github/GHIssueQueryBuilder;
            0      16     1  date   Ljava/util/Date;

  public org.kohsuke.github.GHIssueQueryBuilder since(long);
    descriptor: (J)Lorg/kohsuke/github/GHIssueQueryBuilder;
    flags: (0x0001) ACC_PUBLIC
    Code:
      stack=5, locals=3, args_size=2
         0: aload_0
         1: new           #19                 // class java/util/Date
         4: dup
         5: lload_1
         6: invokespecial #20                 // Method java/util/Date."<init>":(J)V
         9: invokevirtual #21                 // Method since:(Ljava/util/Date;)Lorg/kohsuke/github/GHIssueQueryBuilder;
        12: areturn
      LineNumberTable:
        line 85: 0
      LocalVariableTable:
        Start  Length  Slot  Name   Signature
            0      13     0  this   Lorg/kohsuke/github/GHIssueQueryBuilder;
            0      13     1 timestamp   J

  public org.kohsuke.github.GHIssueQueryBuilder pageSize(int);
    descriptor: (I)Lorg/kohsuke/github/GHIssueQueryBuilder;
    flags: (0x0001) ACC_PUBLIC
    Code:
      stack=3, locals=2, args_size=2
         0: aload_0
         1: getfield      #5                  // Field req:Lorg/kohsuke/github/Requester;
         4: ldc           #22                 // String per_page
         6: iload_1
         7: invokevirtual #23                 // Method org/kohsuke/github/Requester.with:(Ljava/lang/String;I)Lorg/kohsuke/github/GitHubRequest$Builder;
        10: pop
        11: aload_0
        12: areturn
      LineNumberTable:
        line 96: 0
        line 97: 11
      LocalVariableTable:
        Start  Length  Slot  Name   Signature
            0      13     0  this   Lorg/kohsuke/github/GHIssueQueryBuilder;
            0      13     1 pageSize   I

  public abstract java.lang.String getApiUrl();
    descriptor: ()Ljava/lang/String;
    flags: (0x0401) ACC_PUBLIC, ACC_ABSTRACT
}
Signature: #69                          // Lorg/kohsuke/github/GHQueryBuilder<Lorg/kohsuke/github/GHIssue;>;
SourceFile: "GHIssueQueryBuilder.java"
InnerClasses:
  public static #27= #26 of #24;          // ForRepository=class org/kohsuke/github/GHIssueQueryBuilder$ForRepository of class org/kohsuke/github/GHIssueQueryBuilder
  public static final #30= #29 of #24;    // Sort=class org/kohsuke/github/GHIssueQueryBuilder$Sort of class org/kohsuke/github/GHIssueQueryBuilder
  static #104= #103 of #121;              // Builder=class org/kohsuke/github/GitHubRequest$Builder of class org/kohsuke/github/GitHubRequest
