Classfile /Users/mw/Projects/slang-braindump/.jar/jar8/assemble/slang-braindump/assemble/content/org/kohsuke/github/GHIssueSearchBuilder.class
  Last modified May 29, 2022; size 2706 bytes
  SHA-256 checksum ecc8281c93fc199c6f9cba1e32cbea9d5c33868cafafb9c3c5d7c34bd3a43490
  Compiled from "GHIssueSearchBuilder.java"
public class org.kohsuke.github.GHIssueSearchBuilder extends org.kohsuke.github.GHSearchBuilder<org.kohsuke.github.GHIssue>
  minor version: 0
  major version: 52
  flags: (0x0021) ACC_PUBLIC, ACC_SUPER
  this_class: #20                         // org/kohsuke/github/GHIssueSearchBuilder
  super_class: #21                        // org/kohsuke/github/GHSearchBuilder
  interfaces: 0, fields: 0, methods: 11, attributes: 3
Constant pool:
    #1 = Class              #62           // org/kohsuke/github/GHIssueSearchBuilder$IssueSearchResult
    #2 = Methodref          #21.#63       // org/kohsuke/github/GHSearchBuilder."<init>":(Lorg/kohsuke/github/GitHub;Ljava/lang/Class;)V
    #3 = Methodref          #21.#64       // org/kohsuke/github/GHSearchBuilder.q:(Ljava/lang/String;)Lorg/kohsuke/github/GHQueryBuilder;
    #4 = Methodref          #65.#66       // org/kohsuke/github/GHUser.getLogin:()Ljava/lang/String;
    #5 = Methodref          #20.#67       // org/kohsuke/github/GHIssueSearchBuilder.mentions:(Ljava/lang/String;)Lorg/kohsuke/github/GHIssueSearchBuilder;
    #6 = Class              #68           // java/lang/StringBuilder
    #7 = Methodref          #6.#69        // java/lang/StringBuilder."<init>":()V
    #8 = String             #70           // mentions:
    #9 = Methodref          #6.#71        // java/lang/StringBuilder.append:(Ljava/lang/String;)Ljava/lang/StringBuilder;
   #10 = Methodref          #6.#72        // java/lang/StringBuilder.toString:()Ljava/lang/String;
   #11 = Methodref          #20.#73       // org/kohsuke/github/GHIssueSearchBuilder.q:(Ljava/lang/String;)Lorg/kohsuke/github/GHIssueSearchBuilder;
   #12 = String             #74           // is:open
   #13 = String             #75           // is:closed
   #14 = String             #76           // is:merged
   #15 = Fieldref           #20.#77       // org/kohsuke/github/GHIssueSearchBuilder.req:Lorg/kohsuke/github/Requester;
   #16 = String             #48           // order
   #17 = Methodref          #78.#79       // org/kohsuke/github/Requester.with:(Ljava/lang/String;Ljava/lang/Enum;)Lorg/kohsuke/github/GitHubRequest$Builder;
   #18 = String             #52           // sort
   #19 = String             #80           // /search/issues
   #20 = Class              #81           // org/kohsuke/github/GHIssueSearchBuilder
   #21 = Class              #82           // org/kohsuke/github/GHSearchBuilder
   #22 = Utf8               IssueSearchResult
   #23 = Utf8               InnerClasses
   #24 = Class              #83           // org/kohsuke/github/GHIssueSearchBuilder$Sort
   #25 = Utf8               Sort
   #26 = Utf8               <init>
   #27 = Utf8               (Lorg/kohsuke/github/GitHub;)V
   #28 = Utf8               Code
   #29 = Utf8               LineNumberTable
   #30 = Utf8               LocalVariableTable
   #31 = Utf8               this
   #32 = Utf8               Lorg/kohsuke/github/GHIssueSearchBuilder;
   #33 = Utf8               root
   #34 = Utf8               Lorg/kohsuke/github/GitHub;
   #35 = Utf8               q
   #36 = Utf8               (Ljava/lang/String;)Lorg/kohsuke/github/GHIssueSearchBuilder;
   #37 = Utf8               term
   #38 = Utf8               Ljava/lang/String;
   #39 = Utf8               mentions
   #40 = Utf8               (Lorg/kohsuke/github/GHUser;)Lorg/kohsuke/github/GHIssueSearchBuilder;
   #41 = Utf8               u
   #42 = Utf8               Lorg/kohsuke/github/GHUser;
   #43 = Utf8               login
   #44 = Utf8               isOpen
   #45 = Utf8               ()Lorg/kohsuke/github/GHIssueSearchBuilder;
   #46 = Utf8               isClosed
   #47 = Utf8               isMerged
   #48 = Utf8               order
   #49 = Utf8               (Lorg/kohsuke/github/GHDirection;)Lorg/kohsuke/github/GHIssueSearchBuilder;
   #50 = Utf8               v
   #51 = Utf8               Lorg/kohsuke/github/GHDirection;
   #52 = Utf8               sort
   #53 = Utf8               (Lorg/kohsuke/github/GHIssueSearchBuilder$Sort;)Lorg/kohsuke/github/GHIssueSearchBuilder;
   #54 = Utf8               Lorg/kohsuke/github/GHIssueSearchBuilder$Sort;
   #55 = Utf8               getApiUrl
   #56 = Utf8               ()Ljava/lang/String;
   #57 = Utf8               (Ljava/lang/String;)Lorg/kohsuke/github/GHQueryBuilder;
   #58 = Utf8               Signature
   #59 = Utf8               Lorg/kohsuke/github/GHSearchBuilder<Lorg/kohsuke/github/GHIssue;>;
   #60 = Utf8               SourceFile
   #61 = Utf8               GHIssueSearchBuilder.java
   #62 = Utf8               org/kohsuke/github/GHIssueSearchBuilder$IssueSearchResult
   #63 = NameAndType        #26:#84       // "<init>":(Lorg/kohsuke/github/GitHub;Ljava/lang/Class;)V
   #64 = NameAndType        #35:#57       // q:(Ljava/lang/String;)Lorg/kohsuke/github/GHQueryBuilder;
   #65 = Class              #85           // org/kohsuke/github/GHUser
   #66 = NameAndType        #86:#56       // getLogin:()Ljava/lang/String;
   #67 = NameAndType        #39:#36       // mentions:(Ljava/lang/String;)Lorg/kohsuke/github/GHIssueSearchBuilder;
   #68 = Utf8               java/lang/StringBuilder
   #69 = NameAndType        #26:#87       // "<init>":()V
   #70 = Utf8               mentions:
   #71 = NameAndType        #88:#89       // append:(Ljava/lang/String;)Ljava/lang/StringBuilder;
   #72 = NameAndType        #90:#56       // toString:()Ljava/lang/String;
   #73 = NameAndType        #35:#36       // q:(Ljava/lang/String;)Lorg/kohsuke/github/GHIssueSearchBuilder;
   #74 = Utf8               is:open
   #75 = Utf8               is:closed
   #76 = Utf8               is:merged
   #77 = NameAndType        #91:#92       // req:Lorg/kohsuke/github/Requester;
   #78 = Class              #93           // org/kohsuke/github/Requester
   #79 = NameAndType        #94:#97       // with:(Ljava/lang/String;Ljava/lang/Enum;)Lorg/kohsuke/github/GitHubRequest$Builder;
   #80 = Utf8               /search/issues
   #81 = Utf8               org/kohsuke/github/GHIssueSearchBuilder
   #82 = Utf8               org/kohsuke/github/GHSearchBuilder
   #83 = Utf8               org/kohsuke/github/GHIssueSearchBuilder$Sort
   #84 = Utf8               (Lorg/kohsuke/github/GitHub;Ljava/lang/Class;)V
   #85 = Utf8               org/kohsuke/github/GHUser
   #86 = Utf8               getLogin
   #87 = Utf8               ()V
   #88 = Utf8               append
   #89 = Utf8               (Ljava/lang/String;)Ljava/lang/StringBuilder;
   #90 = Utf8               toString
   #91 = Utf8               req
   #92 = Utf8               Lorg/kohsuke/github/Requester;
   #93 = Utf8               org/kohsuke/github/Requester
   #94 = Utf8               with
   #95 = Class              #99           // org/kohsuke/github/GitHubRequest$Builder
   #96 = Utf8               Builder
   #97 = Utf8               (Ljava/lang/String;Ljava/lang/Enum;)Lorg/kohsuke/github/GitHubRequest$Builder;
   #98 = Class              #100          // org/kohsuke/github/GitHubRequest
   #99 = Utf8               org/kohsuke/github/GitHubRequest$Builder
  #100 = Utf8               org/kohsuke/github/GitHubRequest
{
  org.kohsuke.github.GHIssueSearchBuilder(org.kohsuke.github.GitHub);
    descriptor: (Lorg/kohsuke/github/GitHub;)V
    flags: (0x0000)
    Code:
      stack=3, locals=2, args_size=2
         0: aload_0
         1: aload_1
         2: ldc           #1                  // class org/kohsuke/github/GHIssueSearchBuilder$IssueSearchResult
         4: invokespecial #2                  // Method org/kohsuke/github/GHSearchBuilder."<init>":(Lorg/kohsuke/github/GitHub;Ljava/lang/Class;)V
         7: return
      LineNumberTable:
        line 11: 0
        line 12: 7
      LocalVariableTable:
        Start  Length  Slot  Name   Signature
            0       8     0  this   Lorg/kohsuke/github/GHIssueSearchBuilder;
            0       8     1  root   Lorg/kohsuke/github/GitHub;

  public org.kohsuke.github.GHIssueSearchBuilder q(java.lang.String);
    descriptor: (Ljava/lang/String;)Lorg/kohsuke/github/GHIssueSearchBuilder;
    flags: (0x0001) ACC_PUBLIC
    Code:
      stack=2, locals=2, args_size=2
         0: aload_0
         1: aload_1
         2: invokespecial #3                  // Method org/kohsuke/github/GHSearchBuilder.q:(Ljava/lang/String;)Lorg/kohsuke/github/GHQueryBuilder;
         5: pop
         6: aload_0
         7: areturn
      LineNumberTable:
        line 18: 0
        line 19: 6
      LocalVariableTable:
        Start  Length  Slot  Name   Signature
            0       8     0  this   Lorg/kohsuke/github/GHIssueSearchBuilder;
            0       8     1  term   Ljava/lang/String;

  public org.kohsuke.github.GHIssueSearchBuilder mentions(org.kohsuke.github.GHUser);
    descriptor: (Lorg/kohsuke/github/GHUser;)Lorg/kohsuke/github/GHIssueSearchBuilder;
    flags: (0x0001) ACC_PUBLIC
    Code:
      stack=2, locals=2, args_size=2
         0: aload_0
         1: aload_1
         2: invokevirtual #4                  // Method org/kohsuke/github/GHUser.getLogin:()Ljava/lang/String;
         5: invokevirtual #5                  // Method mentions:(Ljava/lang/String;)Lorg/kohsuke/github/GHIssueSearchBuilder;
         8: areturn
      LineNumberTable:
        line 30: 0
      LocalVariableTable:
        Start  Length  Slot  Name   Signature
            0       9     0  this   Lorg/kohsuke/github/GHIssueSearchBuilder;
            0       9     1     u   Lorg/kohsuke/github/GHUser;

  public org.kohsuke.github.GHIssueSearchBuilder mentions(java.lang.String);
    descriptor: (Ljava/lang/String;)Lorg/kohsuke/github/GHIssueSearchBuilder;
    flags: (0x0001) ACC_PUBLIC
    Code:
      stack=3, locals=2, args_size=2
         0: aload_0
         1: new           #6                  // class java/lang/StringBuilder
         4: dup
         5: invokespecial #7                  // Method java/lang/StringBuilder."<init>":()V
         8: ldc           #8                  // String mentions:
        10: invokevirtual #9                  // Method java/lang/StringBuilder.append:(Ljava/lang/String;)Ljava/lang/StringBuilder;
        13: aload_1
        14: invokevirtual #9                  // Method java/lang/StringBuilder.append:(Ljava/lang/String;)Ljava/lang/StringBuilder;
        17: invokevirtual #10                 // Method java/lang/StringBuilder.toString:()Ljava/lang/String;
        20: invokevirtual #11                 // Method q:(Ljava/lang/String;)Lorg/kohsuke/github/GHIssueSearchBuilder;
        23: areturn
      LineNumberTable:
        line 41: 0
      LocalVariableTable:
        Start  Length  Slot  Name   Signature
            0      24     0  this   Lorg/kohsuke/github/GHIssueSearchBuilder;
            0      24     1 login   Ljava/lang/String;

  public org.kohsuke.github.GHIssueSearchBuilder isOpen();
    descriptor: ()Lorg/kohsuke/github/GHIssueSearchBuilder;
    flags: (0x0001) ACC_PUBLIC
    Code:
      stack=2, locals=1, args_size=1
         0: aload_0
         1: ldc           #12                 // String is:open
         3: invokevirtual #11                 // Method q:(Ljava/lang/String;)Lorg/kohsuke/github/GHIssueSearchBuilder;
         6: areturn
      LineNumberTable:
        line 50: 0
      LocalVariableTable:
        Start  Length  Slot  Name   Signature
            0       7     0  this   Lorg/kohsuke/github/GHIssueSearchBuilder;

  public org.kohsuke.github.GHIssueSearchBuilder isClosed();
    descriptor: ()Lorg/kohsuke/github/GHIssueSearchBuilder;
    flags: (0x0001) ACC_PUBLIC
    Code:
      stack=2, locals=1, args_size=1
         0: aload_0
         1: ldc           #13                 // String is:closed
         3: invokevirtual #11                 // Method q:(Ljava/lang/String;)Lorg/kohsuke/github/GHIssueSearchBuilder;
         6: areturn
      LineNumberTable:
        line 59: 0
      LocalVariableTable:
        Start  Length  Slot  Name   Signature
            0       7     0  this   Lorg/kohsuke/github/GHIssueSearchBuilder;

  public org.kohsuke.github.GHIssueSearchBuilder isMerged();
    descriptor: ()Lorg/kohsuke/github/GHIssueSearchBuilder;
    flags: (0x0001) ACC_PUBLIC
    Code:
      stack=2, locals=1, args_size=1
         0: aload_0
         1: ldc           #14                 // String is:merged
         3: invokevirtual #11                 // Method q:(Ljava/lang/String;)Lorg/kohsuke/github/GHIssueSearchBuilder;
         6: areturn
      LineNumberTable:
        line 68: 0
      LocalVariableTable:
        Start  Length  Slot  Name   Signature
            0       7     0  this   Lorg/kohsuke/github/GHIssueSearchBuilder;

  public org.kohsuke.github.GHIssueSearchBuilder order(org.kohsuke.github.GHDirection);
    descriptor: (Lorg/kohsuke/github/GHDirection;)Lorg/kohsuke/github/GHIssueSearchBuilder;
    flags: (0x0001) ACC_PUBLIC
    Code:
      stack=3, locals=2, args_size=2
         0: aload_0
         1: getfield      #15                 // Field req:Lorg/kohsuke/github/Requester;
         4: ldc           #16                 // String order
         6: aload_1
         7: invokevirtual #17                 // Method org/kohsuke/github/Requester.with:(Ljava/lang/String;Ljava/lang/Enum;)Lorg/kohsuke/github/GitHubRequest$Builder;
        10: pop
        11: aload_0
        12: areturn
      LineNumberTable:
        line 79: 0
        line 80: 11
      LocalVariableTable:
        Start  Length  Slot  Name   Signature
            0      13     0  this   Lorg/kohsuke/github/GHIssueSearchBuilder;
            0      13     1     v   Lorg/kohsuke/github/GHDirection;

  public org.kohsuke.github.GHIssueSearchBuilder sort(org.kohsuke.github.GHIssueSearchBuilder$Sort);
    descriptor: (Lorg/kohsuke/github/GHIssueSearchBuilder$Sort;)Lorg/kohsuke/github/GHIssueSearchBuilder;
    flags: (0x0001) ACC_PUBLIC
    Code:
      stack=3, locals=2, args_size=2
         0: aload_0
         1: getfield      #15                 // Field req:Lorg/kohsuke/github/Requester;
         4: ldc           #18                 // String sort
         6: aload_1
         7: invokevirtual #17                 // Method org/kohsuke/github/Requester.with:(Ljava/lang/String;Ljava/lang/Enum;)Lorg/kohsuke/github/GitHubRequest$Builder;
        10: pop
        11: aload_0
        12: areturn
      LineNumberTable:
        line 91: 0
        line 92: 11
      LocalVariableTable:
        Start  Length  Slot  Name   Signature
            0      13     0  this   Lorg/kohsuke/github/GHIssueSearchBuilder;
            0      13     1  sort   Lorg/kohsuke/github/GHIssueSearchBuilder$Sort;

  protected java.lang.String getApiUrl();
    descriptor: ()Ljava/lang/String;
    flags: (0x0004) ACC_PROTECTED
    Code:
      stack=1, locals=1, args_size=1
         0: ldc           #19                 // String /search/issues
         2: areturn
      LineNumberTable:
        line 115: 0
      LocalVariableTable:
        Start  Length  Slot  Name   Signature
            0       3     0  this   Lorg/kohsuke/github/GHIssueSearchBuilder;

  public org.kohsuke.github.GHQueryBuilder q(java.lang.String);
    descriptor: (Ljava/lang/String;)Lorg/kohsuke/github/GHQueryBuilder;
    flags: (0x1041) ACC_PUBLIC, ACC_BRIDGE, ACC_SYNTHETIC
    Code:
      stack=2, locals=2, args_size=2
         0: aload_0
         1: aload_1
         2: invokevirtual #11                 // Method q:(Ljava/lang/String;)Lorg/kohsuke/github/GHIssueSearchBuilder;
         5: areturn
      LineNumberTable:
        line 9: 0
      LocalVariableTable:
        Start  Length  Slot  Name   Signature
            0       6     0  this   Lorg/kohsuke/github/GHIssueSearchBuilder;
}
Signature: #59                          // Lorg/kohsuke/github/GHSearchBuilder<Lorg/kohsuke/github/GHIssue;>;
SourceFile: "GHIssueSearchBuilder.java"
InnerClasses:
  private static #22= #1 of #20;          // IssueSearchResult=class org/kohsuke/github/GHIssueSearchBuilder$IssueSearchResult of class org/kohsuke/github/GHIssueSearchBuilder
  public static final #25= #24 of #20;    // Sort=class org/kohsuke/github/GHIssueSearchBuilder$Sort of class org/kohsuke/github/GHIssueSearchBuilder
  static #96= #95 of #98;                 // Builder=class org/kohsuke/github/GitHubRequest$Builder of class org/kohsuke/github/GitHubRequest
