Classfile /Users/mw/Projects/slang-braindump/.jar/jar8/assemble/slang-braindump/assemble/content/org/kohsuke/github/GHKey.class
  Last modified May 29, 2022; size 1682 bytes
  SHA-256 checksum 211044c1aaa09ab46c9750efbe01e0684037438d780428411b282055fc4195c5
  Compiled from "GHKey.java"
public class org.kohsuke.github.GHKey extends org.kohsuke.github.GitHubInteractiveObject
  minor version: 0
  major version: 52
  flags: (0x0021) ACC_PUBLIC, ACC_SUPER
  this_class: #16                         // org/kohsuke/github/GHKey
  super_class: #17                        // org/kohsuke/github/GitHubInteractiveObject
  interfaces: 0, fields: 5, methods: 8, attributes: 2
Constant pool:
   #1 = Methodref          #17.#56        // org/kohsuke/github/GitHubInteractiveObject."<init>":()V
   #2 = Fieldref           #16.#57        // org/kohsuke/github/GHKey.id:I
   #3 = Fieldref           #16.#58        // org/kohsuke/github/GHKey.key:Ljava/lang/String;
   #4 = Fieldref           #16.#59        // org/kohsuke/github/GHKey.title:Ljava/lang/String;
   #5 = Fieldref           #16.#60        // org/kohsuke/github/GHKey.url:Ljava/lang/String;
   #6 = Fieldref           #16.#61        // org/kohsuke/github/GHKey.verified:Z
   #7 = Class              #62            // org/apache/commons/lang3/builder/ToStringBuilder
   #8 = Methodref          #7.#63         // org/apache/commons/lang3/builder/ToStringBuilder."<init>":(Ljava/lang/Object;)V
   #9 = String             #21            // title
  #10 = Methodref          #7.#64         // org/apache/commons/lang3/builder/ToStringBuilder.append:(Ljava/lang/String;Ljava/lang/Object;)Lorg/apache/commons/lang3/builder/ToStringBuilder;
  #11 = String             #24            // id
  #12 = Methodref          #7.#65         // org/apache/commons/lang3/builder/ToStringBuilder.append:(Ljava/lang/String;I)Lorg/apache/commons/lang3/builder/ToStringBuilder;
  #13 = String             #20            // key
  #14 = Methodref          #7.#66         // org/apache/commons/lang3/builder/ToStringBuilder.toString:()Ljava/lang/String;
  #15 = Methodref          #17.#67        // org/kohsuke/github/GitHubInteractiveObject.getRoot:()Lorg/kohsuke/github/GitHub;
  #16 = Class              #68            // org/kohsuke/github/GHKey
  #17 = Class              #69            // org/kohsuke/github/GitHubInteractiveObject
  #18 = Utf8               url
  #19 = Utf8               Ljava/lang/String;
  #20 = Utf8               key
  #21 = Utf8               title
  #22 = Utf8               verified
  #23 = Utf8               Z
  #24 = Utf8               id
  #25 = Utf8               I
  #26 = Utf8               <init>
  #27 = Utf8               ()V
  #28 = Utf8               Code
  #29 = Utf8               LineNumberTable
  #30 = Utf8               LocalVariableTable
  #31 = Utf8               this
  #32 = Utf8               Lorg/kohsuke/github/GHKey;
  #33 = Utf8               getId
  #34 = Utf8               ()I
  #35 = Utf8               getKey
  #36 = Utf8               ()Ljava/lang/String;
  #37 = Utf8               getTitle
  #38 = Utf8               getUrl
  #39 = Utf8               isVerified
  #40 = Utf8               ()Z
  #41 = Utf8               toString
  #42 = Utf8               getRoot
  #43 = Utf8               ()Lorg/kohsuke/github/GitHub;
  #44 = Utf8               RuntimeVisibleAnnotations
  #45 = Utf8               Ljava/lang/Deprecated;
  #46 = Utf8               RuntimeInvisibleAnnotations
  #47 = Utf8               Ledu/umd/cs/findbugs/annotations/SuppressFBWarnings;
  #48 = Utf8               value
  #49 = Utf8               EI_EXPOSE_REP
  #50 = Utf8               justification
  #51 = Utf8               Expected behavior
  #52 = Utf8               SourceFile
  #53 = Utf8               GHKey.java
  #54 = Utf8               UWF_UNWRITTEN_PUBLIC_OR_PROTECTED_FIELD
  #55 = Utf8               JSON API
  #56 = NameAndType        #26:#27        // "<init>":()V
  #57 = NameAndType        #24:#25        // id:I
  #58 = NameAndType        #20:#19        // key:Ljava/lang/String;
  #59 = NameAndType        #21:#19        // title:Ljava/lang/String;
  #60 = NameAndType        #18:#19        // url:Ljava/lang/String;
  #61 = NameAndType        #22:#23        // verified:Z
  #62 = Utf8               org/apache/commons/lang3/builder/ToStringBuilder
  #63 = NameAndType        #26:#70        // "<init>":(Ljava/lang/Object;)V
  #64 = NameAndType        #71:#72        // append:(Ljava/lang/String;Ljava/lang/Object;)Lorg/apache/commons/lang3/builder/ToStringBuilder;
  #65 = NameAndType        #71:#73        // append:(Ljava/lang/String;I)Lorg/apache/commons/lang3/builder/ToStringBuilder;
  #66 = NameAndType        #41:#36        // toString:()Ljava/lang/String;
  #67 = NameAndType        #42:#43        // getRoot:()Lorg/kohsuke/github/GitHub;
  #68 = Utf8               org/kohsuke/github/GHKey
  #69 = Utf8               org/kohsuke/github/GitHubInteractiveObject
  #70 = Utf8               (Ljava/lang/Object;)V
  #71 = Utf8               append
  #72 = Utf8               (Ljava/lang/String;Ljava/lang/Object;)Lorg/apache/commons/lang3/builder/ToStringBuilder;
  #73 = Utf8               (Ljava/lang/String;I)Lorg/apache/commons/lang3/builder/ToStringBuilder;
{
  protected java.lang.String url;
    descriptor: Ljava/lang/String;
    flags: (0x0004) ACC_PROTECTED

  protected java.lang.String key;
    descriptor: Ljava/lang/String;
    flags: (0x0004) ACC_PROTECTED

  protected java.lang.String title;
    descriptor: Ljava/lang/String;
    flags: (0x0004) ACC_PROTECTED

  protected boolean verified;
    descriptor: Z
    flags: (0x0004) ACC_PROTECTED

  protected int id;
    descriptor: I
    flags: (0x0004) ACC_PROTECTED

  public org.kohsuke.github.GHKey();
    descriptor: ()V
    flags: (0x0001) ACC_PUBLIC
    Code:
      stack=1, locals=1, args_size=1
         0: aload_0
         1: invokespecial #1                  // Method org/kohsuke/github/GitHubInteractiveObject."<init>":()V
         4: return
      LineNumberTable:
        line 12: 0
      LocalVariableTable:
        Start  Length  Slot  Name   Signature
            0       5     0  this   Lorg/kohsuke/github/GHKey;

  public int getId();
    descriptor: ()I
    flags: (0x0001) ACC_PUBLIC
    Code:
      stack=1, locals=1, args_size=1
         0: aload_0
         1: getfield      #2                  // Field id:I
         4: ireturn
      LineNumberTable:
        line 23: 0
      LocalVariableTable:
        Start  Length  Slot  Name   Signature
            0       5     0  this   Lorg/kohsuke/github/GHKey;

  public java.lang.String getKey();
    descriptor: ()Ljava/lang/String;
    flags: (0x0001) ACC_PUBLIC
    Code:
      stack=1, locals=1, args_size=1
         0: aload_0
         1: getfield      #3                  // Field key:Ljava/lang/String;
         4: areturn
      LineNumberTable:
        line 32: 0
      LocalVariableTable:
        Start  Length  Slot  Name   Signature
            0       5     0  this   Lorg/kohsuke/github/GHKey;

  public java.lang.String getTitle();
    descriptor: ()Ljava/lang/String;
    flags: (0x0001) ACC_PUBLIC
    Code:
      stack=1, locals=1, args_size=1
         0: aload_0
         1: getfield      #4                  // Field title:Ljava/lang/String;
         4: areturn
      LineNumberTable:
        line 41: 0
      LocalVariableTable:
        Start  Length  Slot  Name   Signature
            0       5     0  this   Lorg/kohsuke/github/GHKey;

  public java.lang.String getUrl();
    descriptor: ()Ljava/lang/String;
    flags: (0x0001) ACC_PUBLIC
    Code:
      stack=1, locals=1, args_size=1
         0: aload_0
         1: getfield      #5                  // Field url:Ljava/lang/String;
         4: areturn
      LineNumberTable:
        line 50: 0
      LocalVariableTable:
        Start  Length  Slot  Name   Signature
            0       5     0  this   Lorg/kohsuke/github/GHKey;

  public boolean isVerified();
    descriptor: ()Z
    flags: (0x0001) ACC_PUBLIC
    Code:
      stack=1, locals=1, args_size=1
         0: aload_0
         1: getfield      #6                  // Field verified:Z
         4: ireturn
      LineNumberTable:
        line 59: 0
      LocalVariableTable:
        Start  Length  Slot  Name   Signature
            0       5     0  this   Lorg/kohsuke/github/GHKey;

  public java.lang.String toString();
    descriptor: ()Ljava/lang/String;
    flags: (0x0001) ACC_PUBLIC
    Code:
      stack=3, locals=1, args_size=1
         0: new           #7                  // class org/apache/commons/lang3/builder/ToStringBuilder
         3: dup
         4: aload_0
         5: invokespecial #8                  // Method org/apache/commons/lang3/builder/ToStringBuilder."<init>":(Ljava/lang/Object;)V
         8: ldc           #9                  // String title
        10: aload_0
        11: getfield      #4                  // Field title:Ljava/lang/String;
        14: invokevirtual #10                 // Method org/apache/commons/lang3/builder/ToStringBuilder.append:(Ljava/lang/String;Ljava/lang/Object;)Lorg/apache/commons/lang3/builder/ToStringBuilder;
        17: ldc           #11                 // String id
        19: aload_0
        20: getfield      #2                  // Field id:I
        23: invokevirtual #12                 // Method org/apache/commons/lang3/builder/ToStringBuilder.append:(Ljava/lang/String;I)Lorg/apache/commons/lang3/builder/ToStringBuilder;
        26: ldc           #13                 // String key
        28: aload_0
        29: getfield      #3                  // Field key:Ljava/lang/String;
        32: invokevirtual #10                 // Method org/apache/commons/lang3/builder/ToStringBuilder.append:(Ljava/lang/String;Ljava/lang/Object;)Lorg/apache/commons/lang3/builder/ToStringBuilder;
        35: invokevirtual #14                 // Method org/apache/commons/lang3/builder/ToStringBuilder.toString:()Ljava/lang/String;
        38: areturn
      LineNumberTable:
        line 63: 0
      LocalVariableTable:
        Start  Length  Slot  Name   Signature
            0      39     0  this   Lorg/kohsuke/github/GHKey;

  public org.kohsuke.github.GitHub getRoot();
    descriptor: ()Lorg/kohsuke/github/GitHub;
    flags: (0x1041) ACC_PUBLIC, ACC_BRIDGE, ACC_SYNTHETIC
    Code:
      stack=1, locals=1, args_size=1
         0: aload_0
         1: invokespecial #15                 // Method org/kohsuke/github/GitHubInteractiveObject.getRoot:()Lorg/kohsuke/github/GitHub;
         4: areturn
      LineNumberTable:
        line 11: 0
      LocalVariableTable:
        Start  Length  Slot  Name   Signature
            0       5     0  this   Lorg/kohsuke/github/GHKey;
    RuntimeVisibleAnnotations:
      0: #45()
        java.lang.Deprecated
    RuntimeInvisibleAnnotations:
      0: #47(#48=[s#49],#50=s#51)
        edu.umd.cs.findbugs.annotations.SuppressFBWarnings(
          value=["EI_EXPOSE_REP"]
          justification="Expected behavior"
        )
}
SourceFile: "GHKey.java"
RuntimeInvisibleAnnotations:
  0: #47(#48=[s#54],#50=s#55)
    edu.umd.cs.findbugs.annotations.SuppressFBWarnings(
      value=["UWF_UNWRITTEN_PUBLIC_OR_PROTECTED_FIELD"]
      justification="JSON API"
    )
