Classfile /Users/mw/Projects/slang-braindump/.jar/jar8/assemble/slang-braindump/assemble/content/org/kohsuke/github/GHLabelBuilder.class
  Last modified May 29, 2022; size 2370 bytes
  SHA-256 checksum b111c4ed0752cd8014e6974c90be6043210bfc954b0f5d40834a83b28ef10aa3
  Compiled from "GHLabelBuilder.java"
class org.kohsuke.github.GHLabelBuilder<S extends java.lang.Object> extends org.kohsuke.github.AbstractBuilder<org.kohsuke.github.GHLabel, S>
  minor version: 0
  major version: 52
  flags: (0x0020) ACC_SUPER
  this_class: #12                         // org/kohsuke/github/GHLabelBuilder
  super_class: #13                        // org/kohsuke/github/AbstractBuilder
  interfaces: 0, fields: 0, methods: 4, attributes: 3
Constant pool:
   #1 = Class              #52            // org/kohsuke/github/GHLabel
   #2 = Methodref          #13.#53        // org/kohsuke/github/AbstractBuilder."<init>":(Ljava/lang/Class;Ljava/lang/Class;Lorg/kohsuke/github/GitHub;Ljava/lang/Object;)V
   #3 = Fieldref           #12.#54        // org/kohsuke/github/GHLabelBuilder.requester:Lorg/kohsuke/github/Requester;
   #4 = String             #38            // name
   #5 = Methodref          #1.#55         // org/kohsuke/github/GHLabel.getName:()Ljava/lang/String;
   #6 = Methodref          #56.#57        // org/kohsuke/github/Requester.with:(Ljava/lang/String;Ljava/lang/String;)Lorg/kohsuke/github/GitHubRequest$Builder;
   #7 = String             #47            // color
   #8 = Methodref          #1.#58         // org/kohsuke/github/GHLabel.getColor:()Ljava/lang/String;
   #9 = String             #48            // description
  #10 = Methodref          #1.#59         // org/kohsuke/github/GHLabel.getDescription:()Ljava/lang/String;
  #11 = Methodref          #12.#60        // org/kohsuke/github/GHLabelBuilder.with:(Ljava/lang/String;Ljava/lang/Object;)Ljava/lang/Object;
  #12 = Class              #61            // org/kohsuke/github/GHLabelBuilder
  #13 = Class              #62            // org/kohsuke/github/AbstractBuilder
  #14 = Utf8               <init>
  #15 = Utf8               (Ljava/lang/Class;Lorg/kohsuke/github/GitHub;Lorg/kohsuke/github/GHLabel;)V
  #16 = Utf8               Code
  #17 = Utf8               LineNumberTable
  #18 = Utf8               LocalVariableTable
  #19 = Utf8               this
  #20 = Utf8               Lorg/kohsuke/github/GHLabelBuilder;
  #21 = Utf8               intermediateReturnType
  #22 = Utf8               Ljava/lang/Class;
  #23 = Utf8               root
  #24 = Utf8               Lorg/kohsuke/github/GitHub;
  #25 = Utf8               baseInstance
  #26 = Utf8               Lorg/kohsuke/github/GHLabel;
  #27 = Utf8               LocalVariableTypeTable
  #28 = Utf8               Lorg/kohsuke/github/GHLabelBuilder<TS;>;
  #29 = Utf8               Ljava/lang/Class<TS;>;
  #30 = Utf8               StackMapTable
  #31 = Class              #63            // java/lang/Class
  #32 = Class              #64            // org/kohsuke/github/GitHub
  #33 = Utf8               Signature
  #34 = Utf8               (Ljava/lang/Class<TS;>;Lorg/kohsuke/github/GitHub;Lorg/kohsuke/github/GHLabel;)V
  #35 = Utf8               RuntimeVisibleParameterAnnotations
  #36 = Utf8               Ljavax/annotation/Nonnull;
  #37 = Utf8               Ljavax/annotation/CheckForNull;
  #38 = Utf8               name
  #39 = Utf8               (Ljava/lang/String;)Ljava/lang/Object;
  #40 = Utf8               value
  #41 = Utf8               Ljava/lang/String;
  #42 = Utf8               Exceptions
  #43 = Class              #65            // java/io/IOException
  #44 = Utf8               (Ljava/lang/String;)TS;
  #45 = Utf8               RuntimeVisibleAnnotations
  #46 = Utf8               Lorg/kohsuke/github/BetaApi;
  #47 = Utf8               color
  #48 = Utf8               description
  #49 = Utf8               <S:Ljava/lang/Object;>Lorg/kohsuke/github/AbstractBuilder<Lorg/kohsuke/github/GHLabel;TS;>;
  #50 = Utf8               SourceFile
  #51 = Utf8               GHLabelBuilder.java
  #52 = Utf8               org/kohsuke/github/GHLabel
  #53 = NameAndType        #14:#66        // "<init>":(Ljava/lang/Class;Ljava/lang/Class;Lorg/kohsuke/github/GitHub;Ljava/lang/Object;)V
  #54 = NameAndType        #67:#68        // requester:Lorg/kohsuke/github/Requester;
  #55 = NameAndType        #69:#70        // getName:()Ljava/lang/String;
  #56 = Class              #71            // org/kohsuke/github/Requester
  #57 = NameAndType        #72:#76        // with:(Ljava/lang/String;Ljava/lang/String;)Lorg/kohsuke/github/GitHubRequest$Builder;
  #58 = NameAndType        #77:#70        // getColor:()Ljava/lang/String;
  #59 = NameAndType        #78:#70        // getDescription:()Ljava/lang/String;
  #60 = NameAndType        #72:#79        // with:(Ljava/lang/String;Ljava/lang/Object;)Ljava/lang/Object;
  #61 = Utf8               org/kohsuke/github/GHLabelBuilder
  #62 = Utf8               org/kohsuke/github/AbstractBuilder
  #63 = Utf8               java/lang/Class
  #64 = Utf8               org/kohsuke/github/GitHub
  #65 = Utf8               java/io/IOException
  #66 = Utf8               (Ljava/lang/Class;Ljava/lang/Class;Lorg/kohsuke/github/GitHub;Ljava/lang/Object;)V
  #67 = Utf8               requester
  #68 = Utf8               Lorg/kohsuke/github/Requester;
  #69 = Utf8               getName
  #70 = Utf8               ()Ljava/lang/String;
  #71 = Utf8               org/kohsuke/github/Requester
  #72 = Utf8               with
  #73 = Class              #81            // org/kohsuke/github/GitHubRequest$Builder
  #74 = Utf8               Builder
  #75 = Utf8               InnerClasses
  #76 = Utf8               (Ljava/lang/String;Ljava/lang/String;)Lorg/kohsuke/github/GitHubRequest$Builder;
  #77 = Utf8               getColor
  #78 = Utf8               getDescription
  #79 = Utf8               (Ljava/lang/String;Ljava/lang/Object;)Ljava/lang/Object;
  #80 = Class              #82            // org/kohsuke/github/GitHubRequest
  #81 = Utf8               org/kohsuke/github/GitHubRequest$Builder
  #82 = Utf8               org/kohsuke/github/GitHubRequest
{
  protected org.kohsuke.github.GHLabelBuilder(java.lang.Class<S>, org.kohsuke.github.GitHub, org.kohsuke.github.GHLabel);
    descriptor: (Ljava/lang/Class;Lorg/kohsuke/github/GitHub;Lorg/kohsuke/github/GHLabel;)V
    flags: (0x0004) ACC_PROTECTED
    Code:
      stack=5, locals=4, args_size=4
         0: aload_0
         1: ldc           #1                  // class org/kohsuke/github/GHLabel
         3: aload_1
         4: aload_2
         5: aload_3
         6: invokespecial #2                  // Method org/kohsuke/github/AbstractBuilder."<init>":(Ljava/lang/Class;Ljava/lang/Class;Lorg/kohsuke/github/GitHub;Ljava/lang/Object;)V
         9: aload_3
        10: ifnull        55
        13: aload_0
        14: getfield      #3                  // Field requester:Lorg/kohsuke/github/Requester;
        17: ldc           #4                  // String name
        19: aload_3
        20: invokevirtual #5                  // Method org/kohsuke/github/GHLabel.getName:()Ljava/lang/String;
        23: invokevirtual #6                  // Method org/kohsuke/github/Requester.with:(Ljava/lang/String;Ljava/lang/String;)Lorg/kohsuke/github/GitHubRequest$Builder;
        26: pop
        27: aload_0
        28: getfield      #3                  // Field requester:Lorg/kohsuke/github/Requester;
        31: ldc           #7                  // String color
        33: aload_3
        34: invokevirtual #8                  // Method org/kohsuke/github/GHLabel.getColor:()Ljava/lang/String;
        37: invokevirtual #6                  // Method org/kohsuke/github/Requester.with:(Ljava/lang/String;Ljava/lang/String;)Lorg/kohsuke/github/GitHubRequest$Builder;
        40: pop
        41: aload_0
        42: getfield      #3                  // Field requester:Lorg/kohsuke/github/Requester;
        45: ldc           #9                  // String description
        47: aload_3
        48: invokevirtual #10                 // Method org/kohsuke/github/GHLabel.getDescription:()Ljava/lang/String;
        51: invokevirtual #6                  // Method org/kohsuke/github/Requester.with:(Ljava/lang/String;Ljava/lang/String;)Lorg/kohsuke/github/GitHubRequest$Builder;
        54: pop
        55: return
      LineNumberTable:
        line 31: 0
        line 33: 9
        line 34: 13
        line 35: 27
        line 36: 41
        line 38: 55
      LocalVariableTable:
        Start  Length  Slot  Name   Signature
            0      56     0  this   Lorg/kohsuke/github/GHLabelBuilder;
            0      56     1 intermediateReturnType   Ljava/lang/Class;
            0      56     2  root   Lorg/kohsuke/github/GitHub;
            0      56     3 baseInstance   Lorg/kohsuke/github/GHLabel;
      LocalVariableTypeTable:
        Start  Length  Slot  Name   Signature
            0      56     0  this   Lorg/kohsuke/github/GHLabelBuilder<TS;>;
            0      56     1 intermediateReturnType   Ljava/lang/Class<TS;>;
      StackMapTable: number_of_entries = 1
        frame_type = 255 /* full_frame */
          offset_delta = 55
          locals = [ class org/kohsuke/github/GHLabelBuilder, class java/lang/Class, class org/kohsuke/github/GitHub, class org/kohsuke/github/GHLabel ]
          stack = []
    Signature: #34                          // (Ljava/lang/Class<TS;>;Lorg/kohsuke/github/GitHub;Lorg/kohsuke/github/GHLabel;)V
    RuntimeVisibleParameterAnnotations:
      parameter 0:
        0: #36()
          javax.annotation.Nonnull
      parameter 1:
        0: #36()
          javax.annotation.Nonnull
      parameter 2:
        0: #37()
          javax.annotation.CheckForNull

  public S name(java.lang.String) throws java.io.IOException;
    descriptor: (Ljava/lang/String;)Ljava/lang/Object;
    flags: (0x0001) ACC_PUBLIC
    Code:
      stack=3, locals=2, args_size=2
         0: aload_0
         1: ldc           #4                  // String name
         3: aload_1
         4: invokevirtual #11                 // Method with:(Ljava/lang/String;Ljava/lang/Object;)Ljava/lang/Object;
         7: areturn
      LineNumberTable:
        line 43: 0
      LocalVariableTable:
        Start  Length  Slot  Name   Signature
            0       8     0  this   Lorg/kohsuke/github/GHLabelBuilder;
            0       8     1 value   Ljava/lang/String;
      LocalVariableTypeTable:
        Start  Length  Slot  Name   Signature
            0       8     0  this   Lorg/kohsuke/github/GHLabelBuilder<TS;>;
    Exceptions:
      throws java.io.IOException
    Signature: #44                          // (Ljava/lang/String;)TS;
    RuntimeVisibleAnnotations:
      0: #36()
        javax.annotation.Nonnull
      1: #46()
        org.kohsuke.github.BetaApi

  public S color(java.lang.String) throws java.io.IOException;
    descriptor: (Ljava/lang/String;)Ljava/lang/Object;
    flags: (0x0001) ACC_PUBLIC
    Code:
      stack=3, locals=2, args_size=2
         0: aload_0
         1: ldc           #7                  // String color
         3: aload_1
         4: invokevirtual #11                 // Method with:(Ljava/lang/String;Ljava/lang/Object;)Ljava/lang/Object;
         7: areturn
      LineNumberTable:
        line 49: 0
      LocalVariableTable:
        Start  Length  Slot  Name   Signature
            0       8     0  this   Lorg/kohsuke/github/GHLabelBuilder;
            0       8     1 value   Ljava/lang/String;
      LocalVariableTypeTable:
        Start  Length  Slot  Name   Signature
            0       8     0  this   Lorg/kohsuke/github/GHLabelBuilder<TS;>;
    Exceptions:
      throws java.io.IOException
    Signature: #44                          // (Ljava/lang/String;)TS;
    RuntimeVisibleAnnotations:
      0: #36()
        javax.annotation.Nonnull
      1: #46()
        org.kohsuke.github.BetaApi

  public S description(java.lang.String) throws java.io.IOException;
    descriptor: (Ljava/lang/String;)Ljava/lang/Object;
    flags: (0x0001) ACC_PUBLIC
    Code:
      stack=3, locals=2, args_size=2
         0: aload_0
         1: ldc           #9                  // String description
         3: aload_1
         4: invokevirtual #11                 // Method with:(Ljava/lang/String;Ljava/lang/Object;)Ljava/lang/Object;
         7: areturn
      LineNumberTable:
        line 55: 0
      LocalVariableTable:
        Start  Length  Slot  Name   Signature
            0       8     0  this   Lorg/kohsuke/github/GHLabelBuilder;
            0       8     1 value   Ljava/lang/String;
      LocalVariableTypeTable:
        Start  Length  Slot  Name   Signature
            0       8     0  this   Lorg/kohsuke/github/GHLabelBuilder<TS;>;
    Exceptions:
      throws java.io.IOException
    Signature: #44                          // (Ljava/lang/String;)TS;
    RuntimeVisibleAnnotations:
      0: #36()
        javax.annotation.Nonnull
      1: #46()
        org.kohsuke.github.BetaApi
}
Signature: #49                          // <S:Ljava/lang/Object;>Lorg/kohsuke/github/AbstractBuilder<Lorg/kohsuke/github/GHLabel;TS;>;
SourceFile: "GHLabelBuilder.java"
InnerClasses:
  static #74= #73 of #80;                 // Builder=class org/kohsuke/github/GitHubRequest$Builder of class org/kohsuke/github/GitHubRequest
