Classfile /Users/mw/Projects/slang-braindump/.jar/jar8/assemble/slang-braindump/assemble/content/org/kohsuke/github/GHLabel$Creator.class
  Last modified May 29, 2022; size 2490 bytes
  SHA-256 checksum 7ba0df6b280cfce4148bbf37dd2d2a8e03ab0785d23b4c910c86acfb885ed484
  Compiled from "GHLabel.java"
public class org.kohsuke.github.GHLabel$Creator extends org.kohsuke.github.GHLabelBuilder<org.kohsuke.github.GHLabel$Creator>
  minor version: 0
  major version: 52
  flags: (0x0021) ACC_PUBLIC, ACC_SUPER
  this_class: #2                          // org/kohsuke/github/GHLabel$Creator
  super_class: #18                        // org/kohsuke/github/GHLabelBuilder
  interfaces: 0, fields: 0, methods: 7, attributes: 4
Constant pool:
   #1 = Methodref          #2.#60         // org/kohsuke/github/GHLabel$Creator."<init>":(Lorg/kohsuke/github/GHRepository;)V
   #2 = Class              #62            // org/kohsuke/github/GHLabel$Creator
   #3 = Methodref          #63.#64        // org/kohsuke/github/GHRepository.root:()Lorg/kohsuke/github/GitHub;
   #4 = Methodref          #18.#65        // org/kohsuke/github/GHLabelBuilder."<init>":(Ljava/lang/Class;Lorg/kohsuke/github/GitHub;Lorg/kohsuke/github/GHLabel;)V
   #5 = Fieldref           #2.#66         // org/kohsuke/github/GHLabel$Creator.requester:Lorg/kohsuke/github/Requester;
   #6 = String             #67            // POST
   #7 = Methodref          #8.#68         // org/kohsuke/github/Requester.method:(Ljava/lang/String;)Lorg/kohsuke/github/GitHubRequest$Builder;
   #8 = Class              #69            // org/kohsuke/github/Requester
   #9 = String             #70            // labels
  #10 = Methodref          #63.#71        // org/kohsuke/github/GHRepository.getApiTailUrl:(Ljava/lang/String;)Ljava/lang/String;
  #11 = Class              #72            // java/lang/String
  #12 = Methodref          #8.#73         // org/kohsuke/github/Requester.withUrlPath:(Ljava/lang/String;[Ljava/lang/String;)Lorg/kohsuke/github/GitHubRequest$Builder;
  #13 = Methodref          #18.#74        // org/kohsuke/github/GHLabelBuilder.description:(Ljava/lang/String;)Ljava/lang/Object;
  #14 = Methodref          #18.#75        // org/kohsuke/github/GHLabelBuilder.color:(Ljava/lang/String;)Ljava/lang/Object;
  #15 = Methodref          #18.#76        // org/kohsuke/github/GHLabelBuilder.name:(Ljava/lang/String;)Ljava/lang/Object;
  #16 = Methodref          #18.#77        // org/kohsuke/github/GHLabelBuilder.done:()Ljava/lang/Object;
  #17 = Methodref          #18.#78        // org/kohsuke/github/GHLabelBuilder.getRoot:()Lorg/kohsuke/github/GitHub;
  #18 = Class              #79            // org/kohsuke/github/GHLabelBuilder
  #19 = Utf8               <init>
  #20 = Utf8               (Lorg/kohsuke/github/GHRepository;)V
  #21 = Utf8               Code
  #22 = Utf8               LineNumberTable
  #23 = Utf8               LocalVariableTable
  #24 = Utf8               this
  #25 = Utf8               Creator
  #26 = Utf8               InnerClasses
  #27 = Utf8               Lorg/kohsuke/github/GHLabel$Creator;
  #28 = Utf8               repository
  #29 = Utf8               Lorg/kohsuke/github/GHRepository;
  #30 = Utf8               RuntimeVisibleParameterAnnotations
  #31 = Utf8               Ljavax/annotation/Nonnull;
  #32 = Utf8               description
  #33 = Utf8               (Ljava/lang/String;)Ljava/lang/Object;
  #34 = Utf8               Exceptions
  #35 = Class              #80            // java/io/IOException
  #36 = Utf8               RuntimeVisibleAnnotations
  #37 = Utf8               Lorg/kohsuke/github/BetaApi;
  #38 = Utf8               color
  #39 = Utf8               name
  #40 = Utf8               done
  #41 = Utf8               ()Ljava/lang/Object;
  #42 = Utf8               getRoot
  #43 = Utf8               ()Lorg/kohsuke/github/GitHub;
  #44 = Utf8               Ljava/lang/Deprecated;
  #45 = Utf8               RuntimeInvisibleAnnotations
  #46 = Utf8               Ledu/umd/cs/findbugs/annotations/SuppressFBWarnings;
  #47 = Utf8               value
  #48 = Utf8               EI_EXPOSE_REP
  #49 = Utf8               justification
  #50 = Utf8               Expected behavior
  #51 = Class              #81            // org/kohsuke/github/GHLabel$1
  #52 = Utf8               (Lorg/kohsuke/github/GHRepository;Lorg/kohsuke/github/GHLabel$1;)V
  #53 = Utf8               x0
  #54 = Utf8               x1
  #55 = Utf8               Lorg/kohsuke/github/GHLabel$1;
  #56 = Utf8               Signature
  #57 = Utf8               Lorg/kohsuke/github/GHLabelBuilder<Lorg/kohsuke/github/GHLabel$Creator;>;
  #58 = Utf8               SourceFile
  #59 = Utf8               GHLabel.java
  #60 = NameAndType        #19:#20        // "<init>":(Lorg/kohsuke/github/GHRepository;)V
  #61 = Class              #82            // org/kohsuke/github/GHLabel
  #62 = Utf8               org/kohsuke/github/GHLabel$Creator
  #63 = Class              #83            // org/kohsuke/github/GHRepository
  #64 = NameAndType        #84:#43        // root:()Lorg/kohsuke/github/GitHub;
  #65 = NameAndType        #19:#85        // "<init>":(Ljava/lang/Class;Lorg/kohsuke/github/GitHub;Lorg/kohsuke/github/GHLabel;)V
  #66 = NameAndType        #86:#87        // requester:Lorg/kohsuke/github/Requester;
  #67 = Utf8               POST
  #68 = NameAndType        #88:#91        // method:(Ljava/lang/String;)Lorg/kohsuke/github/GitHubRequest$Builder;
  #69 = Utf8               org/kohsuke/github/Requester
  #70 = Utf8               labels
  #71 = NameAndType        #92:#93        // getApiTailUrl:(Ljava/lang/String;)Ljava/lang/String;
  #72 = Utf8               java/lang/String
  #73 = NameAndType        #94:#95        // withUrlPath:(Ljava/lang/String;[Ljava/lang/String;)Lorg/kohsuke/github/GitHubRequest$Builder;
  #74 = NameAndType        #32:#33        // description:(Ljava/lang/String;)Ljava/lang/Object;
  #75 = NameAndType        #38:#33        // color:(Ljava/lang/String;)Ljava/lang/Object;
  #76 = NameAndType        #39:#33        // name:(Ljava/lang/String;)Ljava/lang/Object;
  #77 = NameAndType        #40:#41        // done:()Ljava/lang/Object;
  #78 = NameAndType        #42:#43        // getRoot:()Lorg/kohsuke/github/GitHub;
  #79 = Utf8               org/kohsuke/github/GHLabelBuilder
  #80 = Utf8               java/io/IOException
  #81 = Utf8               org/kohsuke/github/GHLabel$1
  #82 = Utf8               org/kohsuke/github/GHLabel
  #83 = Utf8               org/kohsuke/github/GHRepository
  #84 = Utf8               root
  #85 = Utf8               (Ljava/lang/Class;Lorg/kohsuke/github/GitHub;Lorg/kohsuke/github/GHLabel;)V
  #86 = Utf8               requester
  #87 = Utf8               Lorg/kohsuke/github/Requester;
  #88 = Utf8               method
  #89 = Class              #97            // org/kohsuke/github/GitHubRequest$Builder
  #90 = Utf8               Builder
  #91 = Utf8               (Ljava/lang/String;)Lorg/kohsuke/github/GitHubRequest$Builder;
  #92 = Utf8               getApiTailUrl
  #93 = Utf8               (Ljava/lang/String;)Ljava/lang/String;
  #94 = Utf8               withUrlPath
  #95 = Utf8               (Ljava/lang/String;[Ljava/lang/String;)Lorg/kohsuke/github/GitHubRequest$Builder;
  #96 = Class              #98            // org/kohsuke/github/GitHubRequest
  #97 = Utf8               org/kohsuke/github/GitHubRequest$Builder
  #98 = Utf8               org/kohsuke/github/GitHubRequest
{
  private org.kohsuke.github.GHLabel$Creator(org.kohsuke.github.GHRepository);
    descriptor: (Lorg/kohsuke/github/GHRepository;)V
    flags: (0x0002) ACC_PRIVATE
    Code:
      stack=4, locals=2, args_size=2
         0: aload_0
         1: ldc           #2                  // class org/kohsuke/github/GHLabel$Creator
         3: aload_1
         4: invokevirtual #3                  // Method org/kohsuke/github/GHRepository.root:()Lorg/kohsuke/github/GitHub;
         7: aconst_null
         8: invokespecial #4                  // Method org/kohsuke/github/GHLabelBuilder."<init>":(Ljava/lang/Class;Lorg/kohsuke/github/GitHub;Lorg/kohsuke/github/GHLabel;)V
        11: aload_0
        12: getfield      #5                  // Field requester:Lorg/kohsuke/github/Requester;
        15: ldc           #6                  // String POST
        17: invokevirtual #7                  // Method org/kohsuke/github/Requester.method:(Ljava/lang/String;)Lorg/kohsuke/github/GitHubRequest$Builder;
        20: checkcast     #8                  // class org/kohsuke/github/Requester
        23: aload_1
        24: ldc           #9                  // String labels
        26: invokevirtual #10                 // Method org/kohsuke/github/GHRepository.getApiTailUrl:(Ljava/lang/String;)Ljava/lang/String;
        29: iconst_0
        30: anewarray     #11                 // class java/lang/String
        33: invokevirtual #12                 // Method org/kohsuke/github/Requester.withUrlPath:(Ljava/lang/String;[Ljava/lang/String;)Lorg/kohsuke/github/GitHubRequest$Builder;
        36: pop
        37: return
      LineNumberTable:
        line 287: 0
        line 288: 11
        line 289: 37
      LocalVariableTable:
        Start  Length  Slot  Name   Signature
            0      38     0  this   Lorg/kohsuke/github/GHLabel$Creator;
            0      38     1 repository   Lorg/kohsuke/github/GHRepository;
    RuntimeVisibleParameterAnnotations:
      parameter 0:
        0: #31()
          javax.annotation.Nonnull

  public java.lang.Object description(java.lang.String) throws java.io.IOException;
    descriptor: (Ljava/lang/String;)Ljava/lang/Object;
    flags: (0x1041) ACC_PUBLIC, ACC_BRIDGE, ACC_SYNTHETIC
    Code:
      stack=2, locals=2, args_size=2
         0: aload_0
         1: aload_1
         2: invokespecial #13                 // Method org/kohsuke/github/GHLabelBuilder.description:(Ljava/lang/String;)Ljava/lang/Object;
         5: areturn
      LineNumberTable:
        line 284: 0
      LocalVariableTable:
        Start  Length  Slot  Name   Signature
            0       6     0  this   Lorg/kohsuke/github/GHLabel$Creator;
    Exceptions:
      throws java.io.IOException
    RuntimeVisibleAnnotations:
      0: #31()
        javax.annotation.Nonnull
      1: #37()
        org.kohsuke.github.BetaApi

  public java.lang.Object color(java.lang.String) throws java.io.IOException;
    descriptor: (Ljava/lang/String;)Ljava/lang/Object;
    flags: (0x1041) ACC_PUBLIC, ACC_BRIDGE, ACC_SYNTHETIC
    Code:
      stack=2, locals=2, args_size=2
         0: aload_0
         1: aload_1
         2: invokespecial #14                 // Method org/kohsuke/github/GHLabelBuilder.color:(Ljava/lang/String;)Ljava/lang/Object;
         5: areturn
      LineNumberTable:
        line 284: 0
      LocalVariableTable:
        Start  Length  Slot  Name   Signature
            0       6     0  this   Lorg/kohsuke/github/GHLabel$Creator;
    Exceptions:
      throws java.io.IOException
    RuntimeVisibleAnnotations:
      0: #31()
        javax.annotation.Nonnull
      1: #37()
        org.kohsuke.github.BetaApi

  public java.lang.Object name(java.lang.String) throws java.io.IOException;
    descriptor: (Ljava/lang/String;)Ljava/lang/Object;
    flags: (0x1041) ACC_PUBLIC, ACC_BRIDGE, ACC_SYNTHETIC
    Code:
      stack=2, locals=2, args_size=2
         0: aload_0
         1: aload_1
         2: invokespecial #15                 // Method org/kohsuke/github/GHLabelBuilder.name:(Ljava/lang/String;)Ljava/lang/Object;
         5: areturn
      LineNumberTable:
        line 284: 0
      LocalVariableTable:
        Start  Length  Slot  Name   Signature
            0       6     0  this   Lorg/kohsuke/github/GHLabel$Creator;
    Exceptions:
      throws java.io.IOException
    RuntimeVisibleAnnotations:
      0: #31()
        javax.annotation.Nonnull
      1: #37()
        org.kohsuke.github.BetaApi

  public java.lang.Object done() throws java.io.IOException;
    descriptor: ()Ljava/lang/Object;
    flags: (0x1041) ACC_PUBLIC, ACC_BRIDGE, ACC_SYNTHETIC
    Code:
      stack=1, locals=1, args_size=1
         0: aload_0
         1: invokespecial #16                 // Method org/kohsuke/github/GHLabelBuilder.done:()Ljava/lang/Object;
         4: areturn
      LineNumberTable:
        line 284: 0
      LocalVariableTable:
        Start  Length  Slot  Name   Signature
            0       5     0  this   Lorg/kohsuke/github/GHLabel$Creator;
    Exceptions:
      throws java.io.IOException
    RuntimeVisibleAnnotations:
      0: #31()
        javax.annotation.Nonnull
      1: #37()
        org.kohsuke.github.BetaApi

  public org.kohsuke.github.GitHub getRoot();
    descriptor: ()Lorg/kohsuke/github/GitHub;
    flags: (0x1041) ACC_PUBLIC, ACC_BRIDGE, ACC_SYNTHETIC
    Code:
      stack=1, locals=1, args_size=1
         0: aload_0
         1: invokespecial #17                 // Method org/kohsuke/github/GHLabelBuilder.getRoot:()Lorg/kohsuke/github/GitHub;
         4: areturn
      LineNumberTable:
        line 284: 0
      LocalVariableTable:
        Start  Length  Slot  Name   Signature
            0       5     0  this   Lorg/kohsuke/github/GHLabel$Creator;
    RuntimeVisibleAnnotations:
      0: #44()
        java.lang.Deprecated
    RuntimeInvisibleAnnotations:
      0: #46(#47=[s#48],#49=s#50)
        edu.umd.cs.findbugs.annotations.SuppressFBWarnings(
          value=["EI_EXPOSE_REP"]
          justification="Expected behavior"
        )

  org.kohsuke.github.GHLabel$Creator(org.kohsuke.github.GHRepository, org.kohsuke.github.GHLabel$1);
    descriptor: (Lorg/kohsuke/github/GHRepository;Lorg/kohsuke/github/GHLabel$1;)V
    flags: (0x1000) ACC_SYNTHETIC
    Code:
      stack=2, locals=3, args_size=3
         0: aload_0
         1: aload_1
         2: invokespecial #1                  // Method "<init>":(Lorg/kohsuke/github/GHRepository;)V
         5: return
      LineNumberTable:
        line 285: 0
      LocalVariableTable:
        Start  Length  Slot  Name   Signature
            0       6     0  this   Lorg/kohsuke/github/GHLabel$Creator;
            0       6     1    x0   Lorg/kohsuke/github/GHRepository;
            0       6     2    x1   Lorg/kohsuke/github/GHLabel$1;
}
Signature: #57                          // Lorg/kohsuke/github/GHLabelBuilder<Lorg/kohsuke/github/GHLabel$Creator;>;
SourceFile: "GHLabel.java"
RuntimeVisibleAnnotations:
  0: #37()
    org.kohsuke.github.BetaApi
InnerClasses:
  public static #25= #2 of #61;           // Creator=class org/kohsuke/github/GHLabel$Creator of class org/kohsuke/github/GHLabel
  static #51;                             // class org/kohsuke/github/GHLabel$1
  static #90= #89 of #96;                 // Builder=class org/kohsuke/github/GitHubRequest$Builder of class org/kohsuke/github/GitHubRequest
