Classfile /Users/mw/Projects/slang-braindump/.jar/jar8/assemble/slang-braindump/assemble/content/org/kohsuke/github/GHMilestone.class
  Last modified May 29, 2022; size 4964 bytes
  SHA-256 checksum 4f8931193ced44120b27c85309bf0d733b30df8035e0fcd00cda871693333c8f
  Compiled from "GHMilestone.java"
public class org.kohsuke.github.GHMilestone extends org.kohsuke.github.GHObject
  minor version: 0
  major version: 52
  flags: (0x0021) ACC_PUBLIC, ACC_SUPER
  this_class: #52                         // org/kohsuke/github/GHMilestone
  super_class: #53                        // org/kohsuke/github/GHObject
  interfaces: 0, fields: 11, methods: 22, attributes: 2
Constant pool:
    #1 = Methodref          #53.#127      // org/kohsuke/github/GHObject."<init>":()V
    #2 = Fieldref           #52.#128      // org/kohsuke/github/GHMilestone.owner:Lorg/kohsuke/github/GHRepository;
    #3 = Methodref          #52.#129      // org/kohsuke/github/GHMilestone.root:()Lorg/kohsuke/github/GitHub;
    #4 = Fieldref           #52.#130      // org/kohsuke/github/GHMilestone.creator:Lorg/kohsuke/github/GHUser;
    #5 = Methodref          #131.#132     // org/kohsuke/github/GitHub.intern:(Lorg/kohsuke/github/GHUser;)Lorg/kohsuke/github/GHUser;
    #6 = Fieldref           #52.#133      // org/kohsuke/github/GHMilestone.due_on:Ljava/lang/String;
    #7 = Methodref          #134.#135     // org/kohsuke/github/GitHubClient.parseDate:(Ljava/lang/String;)Ljava/util/Date;
    #8 = Fieldref           #52.#136      // org/kohsuke/github/GHMilestone.closed_at:Ljava/lang/String;
    #9 = Fieldref           #52.#137      // org/kohsuke/github/GHMilestone.title:Ljava/lang/String;
   #10 = Fieldref           #52.#138      // org/kohsuke/github/GHMilestone.description:Ljava/lang/String;
   #11 = Fieldref           #52.#139      // org/kohsuke/github/GHMilestone.closed_issues:I
   #12 = Fieldref           #52.#140      // org/kohsuke/github/GHMilestone.open_issues:I
   #13 = Fieldref           #52.#141      // org/kohsuke/github/GHMilestone.number:I
   #14 = Fieldref           #52.#142      // org/kohsuke/github/GHMilestone.html_url:Ljava/lang/String;
   #15 = Methodref          #134.#143     // org/kohsuke/github/GitHubClient.parseURL:(Ljava/lang/String;)Ljava/net/URL;
   #16 = Class              #144          // org/kohsuke/github/GHMilestoneState
   #17 = Fieldref           #52.#145      // org/kohsuke/github/GHMilestone.state:Ljava/lang/String;
   #18 = Fieldref           #146.#147     // java/util/Locale.ENGLISH:Ljava/util/Locale;
   #19 = Methodref          #30.#148      // java/lang/String.toUpperCase:(Ljava/util/Locale;)Ljava/lang/String;
   #20 = Methodref          #149.#150     // java/lang/Enum.valueOf:(Ljava/lang/Class;Ljava/lang/String;)Ljava/lang/Enum;
   #21 = String             #58           // state
   #22 = String             #151          // closed
   #23 = Methodref          #52.#152      // org/kohsuke/github/GHMilestone.edit:(Ljava/lang/String;Ljava/lang/Object;)V
   #24 = String             #153          // open
   #25 = Methodref          #131.#154     // org/kohsuke/github/GitHub.createRequest:()Lorg/kohsuke/github/Requester;
   #26 = String             #155          // DELETE
   #27 = Methodref          #28.#156      // org/kohsuke/github/Requester.method:(Ljava/lang/String;)Lorg/kohsuke/github/GitHubRequest$Builder;
   #28 = Class              #157          // org/kohsuke/github/Requester
   #29 = Methodref          #52.#158      // org/kohsuke/github/GHMilestone.getApiRoute:()Ljava/lang/String;
   #30 = Class              #159          // java/lang/String
   #31 = Methodref          #28.#160      // org/kohsuke/github/Requester.withUrlPath:(Ljava/lang/String;[Ljava/lang/String;)Lorg/kohsuke/github/GitHubRequest$Builder;
   #32 = Methodref          #28.#161      // org/kohsuke/github/Requester.send:()V
   #33 = Methodref          #28.#162      // org/kohsuke/github/Requester.with:(Ljava/lang/String;Ljava/lang/Object;)Lorg/kohsuke/github/GitHubRequest$Builder;
   #34 = String             #163          // PATCH
   #35 = String             #61           // title
   #36 = String             #62           // description
   #37 = String             #60           // due_on
   #38 = Methodref          #134.#164     // org/kohsuke/github/GitHubClient.printDate:(Ljava/util/Date;)Ljava/lang/String;
   #39 = Class              #165          // java/lang/StringBuilder
   #40 = Methodref          #39.#127      // java/lang/StringBuilder."<init>":()V
   #41 = String             #166          // /repos/
   #42 = Methodref          #39.#167      // java/lang/StringBuilder.append:(Ljava/lang/String;)Ljava/lang/StringBuilder;
   #43 = Methodref          #168.#169     // org/kohsuke/github/GHRepository.getOwnerName:()Ljava/lang/String;
   #44 = String             #170          // /
   #45 = Methodref          #168.#171     // org/kohsuke/github/GHRepository.getName:()Ljava/lang/String;
   #46 = String             #172          // /milestones/
   #47 = Methodref          #39.#173      // java/lang/StringBuilder.append:(I)Ljava/lang/StringBuilder;
   #48 = Methodref          #39.#174      // java/lang/StringBuilder.toString:()Ljava/lang/String;
   #49 = Class              #175          // java/lang/RuntimeException
   #50 = String             #176          // Do not use this method.
   #51 = Methodref          #49.#177      // java/lang/RuntimeException."<init>":(Ljava/lang/String;)V
   #52 = Class              #178          // org/kohsuke/github/GHMilestone
   #53 = Class              #179          // org/kohsuke/github/GHObject
   #54 = Utf8               owner
   #55 = Utf8               Lorg/kohsuke/github/GHRepository;
   #56 = Utf8               creator
   #57 = Utf8               Lorg/kohsuke/github/GHUser;
   #58 = Utf8               state
   #59 = Utf8               Ljava/lang/String;
   #60 = Utf8               due_on
   #61 = Utf8               title
   #62 = Utf8               description
   #63 = Utf8               html_url
   #64 = Utf8               closed_issues
   #65 = Utf8               I
   #66 = Utf8               open_issues
   #67 = Utf8               number
   #68 = Utf8               closed_at
   #69 = Utf8               <init>
   #70 = Utf8               ()V
   #71 = Utf8               Code
   #72 = Utf8               LineNumberTable
   #73 = Utf8               LocalVariableTable
   #74 = Utf8               this
   #75 = Utf8               Lorg/kohsuke/github/GHMilestone;
   #76 = Utf8               getOwner
   #77 = Utf8               ()Lorg/kohsuke/github/GHRepository;
   #78 = Utf8               RuntimeInvisibleAnnotations
   #79 = Utf8               Ledu/umd/cs/findbugs/annotations/SuppressFBWarnings;
   #80 = Utf8               value
   #81 = Utf8               EI_EXPOSE_REP
   #82 = Utf8               justification
   #83 = Utf8               Expected behavior
   #84 = Utf8               getCreator
   #85 = Utf8               ()Lorg/kohsuke/github/GHUser;
   #86 = Utf8               Exceptions
   #87 = Class              #180          // java/io/IOException
   #88 = Utf8               getDueOn
   #89 = Utf8               ()Ljava/util/Date;
   #90 = Utf8               StackMapTable
   #91 = Utf8               getClosedAt
   #92 = Utf8               getTitle
   #93 = Utf8               ()Ljava/lang/String;
   #94 = Utf8               getDescription
   #95 = Utf8               getClosedIssues
   #96 = Utf8               ()I
   #97 = Utf8               getOpenIssues
   #98 = Utf8               getNumber
   #99 = Utf8               getHtmlUrl
  #100 = Utf8               ()Ljava/net/URL;
  #101 = Utf8               getState
  #102 = Utf8               ()Lorg/kohsuke/github/GHMilestoneState;
  #103 = Utf8               close
  #104 = Utf8               reopen
  #105 = Utf8               delete
  #106 = Utf8               edit
  #107 = Utf8               (Ljava/lang/String;Ljava/lang/Object;)V
  #108 = Utf8               key
  #109 = Utf8               Ljava/lang/Object;
  #110 = Utf8               setTitle
  #111 = Utf8               (Ljava/lang/String;)V
  #112 = Utf8               setDescription
  #113 = Utf8               setDueOn
  #114 = Utf8               (Ljava/util/Date;)V
  #115 = Utf8               dueOn
  #116 = Utf8               Ljava/util/Date;
  #117 = Utf8               getApiRoute
  #118 = Utf8               wrap
  #119 = Utf8               (Lorg/kohsuke/github/GHRepository;)Lorg/kohsuke/github/GHMilestone;
  #120 = Utf8               repo
  #121 = Utf8               Deprecated
  #122 = Utf8               RuntimeVisibleAnnotations
  #123 = Utf8               Ljava/lang/Deprecated;
  #124 = Utf8               lateBind
  #125 = Utf8               SourceFile
  #126 = Utf8               GHMilestone.java
  #127 = NameAndType        #69:#70       // "<init>":()V
  #128 = NameAndType        #54:#55       // owner:Lorg/kohsuke/github/GHRepository;
  #129 = NameAndType        #181:#182     // root:()Lorg/kohsuke/github/GitHub;
  #130 = NameAndType        #56:#57       // creator:Lorg/kohsuke/github/GHUser;
  #131 = Class              #183          // org/kohsuke/github/GitHub
  #132 = NameAndType        #184:#185     // intern:(Lorg/kohsuke/github/GHUser;)Lorg/kohsuke/github/GHUser;
  #133 = NameAndType        #60:#59       // due_on:Ljava/lang/String;
  #134 = Class              #186          // org/kohsuke/github/GitHubClient
  #135 = NameAndType        #187:#188     // parseDate:(Ljava/lang/String;)Ljava/util/Date;
  #136 = NameAndType        #68:#59       // closed_at:Ljava/lang/String;
  #137 = NameAndType        #61:#59       // title:Ljava/lang/String;
  #138 = NameAndType        #62:#59       // description:Ljava/lang/String;
  #139 = NameAndType        #64:#65       // closed_issues:I
  #140 = NameAndType        #66:#65       // open_issues:I
  #141 = NameAndType        #67:#65       // number:I
  #142 = NameAndType        #63:#59       // html_url:Ljava/lang/String;
  #143 = NameAndType        #189:#190     // parseURL:(Ljava/lang/String;)Ljava/net/URL;
  #144 = Utf8               org/kohsuke/github/GHMilestoneState
  #145 = NameAndType        #58:#59       // state:Ljava/lang/String;
  #146 = Class              #191          // java/util/Locale
  #147 = NameAndType        #192:#193     // ENGLISH:Ljava/util/Locale;
  #148 = NameAndType        #194:#195     // toUpperCase:(Ljava/util/Locale;)Ljava/lang/String;
  #149 = Class              #196          // java/lang/Enum
  #150 = NameAndType        #197:#198     // valueOf:(Ljava/lang/Class;Ljava/lang/String;)Ljava/lang/Enum;
  #151 = Utf8               closed
  #152 = NameAndType        #106:#107     // edit:(Ljava/lang/String;Ljava/lang/Object;)V
  #153 = Utf8               open
  #154 = NameAndType        #199:#200     // createRequest:()Lorg/kohsuke/github/Requester;
  #155 = Utf8               DELETE
  #156 = NameAndType        #201:#205     // method:(Ljava/lang/String;)Lorg/kohsuke/github/GitHubRequest$Builder;
  #157 = Utf8               org/kohsuke/github/Requester
  #158 = NameAndType        #117:#93      // getApiRoute:()Ljava/lang/String;
  #159 = Utf8               java/lang/String
  #160 = NameAndType        #206:#207     // withUrlPath:(Ljava/lang/String;[Ljava/lang/String;)Lorg/kohsuke/github/GitHubRequest$Builder;
  #161 = NameAndType        #208:#70      // send:()V
  #162 = NameAndType        #209:#210     // with:(Ljava/lang/String;Ljava/lang/Object;)Lorg/kohsuke/github/GitHubRequest$Builder;
  #163 = Utf8               PATCH
  #164 = NameAndType        #211:#212     // printDate:(Ljava/util/Date;)Ljava/lang/String;
  #165 = Utf8               java/lang/StringBuilder
  #166 = Utf8               /repos/
  #167 = NameAndType        #213:#214     // append:(Ljava/lang/String;)Ljava/lang/StringBuilder;
  #168 = Class              #215          // org/kohsuke/github/GHRepository
  #169 = NameAndType        #216:#93      // getOwnerName:()Ljava/lang/String;
  #170 = Utf8               /
  #171 = NameAndType        #217:#93      // getName:()Ljava/lang/String;
  #172 = Utf8               /milestones/
  #173 = NameAndType        #213:#218     // append:(I)Ljava/lang/StringBuilder;
  #174 = NameAndType        #219:#93      // toString:()Ljava/lang/String;
  #175 = Utf8               java/lang/RuntimeException
  #176 = Utf8               Do not use this method.
  #177 = NameAndType        #69:#111      // "<init>":(Ljava/lang/String;)V
  #178 = Utf8               org/kohsuke/github/GHMilestone
  #179 = Utf8               org/kohsuke/github/GHObject
  #180 = Utf8               java/io/IOException
  #181 = Utf8               root
  #182 = Utf8               ()Lorg/kohsuke/github/GitHub;
  #183 = Utf8               org/kohsuke/github/GitHub
  #184 = Utf8               intern
  #185 = Utf8               (Lorg/kohsuke/github/GHUser;)Lorg/kohsuke/github/GHUser;
  #186 = Utf8               org/kohsuke/github/GitHubClient
  #187 = Utf8               parseDate
  #188 = Utf8               (Ljava/lang/String;)Ljava/util/Date;
  #189 = Utf8               parseURL
  #190 = Utf8               (Ljava/lang/String;)Ljava/net/URL;
  #191 = Utf8               java/util/Locale
  #192 = Utf8               ENGLISH
  #193 = Utf8               Ljava/util/Locale;
  #194 = Utf8               toUpperCase
  #195 = Utf8               (Ljava/util/Locale;)Ljava/lang/String;
  #196 = Utf8               java/lang/Enum
  #197 = Utf8               valueOf
  #198 = Utf8               (Ljava/lang/Class;Ljava/lang/String;)Ljava/lang/Enum;
  #199 = Utf8               createRequest
  #200 = Utf8               ()Lorg/kohsuke/github/Requester;
  #201 = Utf8               method
  #202 = Class              #221          // org/kohsuke/github/GitHubRequest$Builder
  #203 = Utf8               Builder
  #204 = Utf8               InnerClasses
  #205 = Utf8               (Ljava/lang/String;)Lorg/kohsuke/github/GitHubRequest$Builder;
  #206 = Utf8               withUrlPath
  #207 = Utf8               (Ljava/lang/String;[Ljava/lang/String;)Lorg/kohsuke/github/GitHubRequest$Builder;
  #208 = Utf8               send
  #209 = Utf8               with
  #210 = Utf8               (Ljava/lang/String;Ljava/lang/Object;)Lorg/kohsuke/github/GitHubRequest$Builder;
  #211 = Utf8               printDate
  #212 = Utf8               (Ljava/util/Date;)Ljava/lang/String;
  #213 = Utf8               append
  #214 = Utf8               (Ljava/lang/String;)Ljava/lang/StringBuilder;
  #215 = Utf8               org/kohsuke/github/GHRepository
  #216 = Utf8               getOwnerName
  #217 = Utf8               getName
  #218 = Utf8               (I)Ljava/lang/StringBuilder;
  #219 = Utf8               toString
  #220 = Class              #222          // org/kohsuke/github/GitHubRequest
  #221 = Utf8               org/kohsuke/github/GitHubRequest$Builder
  #222 = Utf8               org/kohsuke/github/GitHubRequest
{
  org.kohsuke.github.GHRepository owner;
    descriptor: Lorg/kohsuke/github/GHRepository;
    flags: (0x0000)

  org.kohsuke.github.GHUser creator;
    descriptor: Lorg/kohsuke/github/GHUser;
    flags: (0x0000)

  private java.lang.String state;
    descriptor: Ljava/lang/String;
    flags: (0x0002) ACC_PRIVATE

  private java.lang.String due_on;
    descriptor: Ljava/lang/String;
    flags: (0x0002) ACC_PRIVATE

  private java.lang.String title;
    descriptor: Ljava/lang/String;
    flags: (0x0002) ACC_PRIVATE

  private java.lang.String description;
    descriptor: Ljava/lang/String;
    flags: (0x0002) ACC_PRIVATE

  private java.lang.String html_url;
    descriptor: Ljava/lang/String;
    flags: (0x0002) ACC_PRIVATE

  private int closed_issues;
    descriptor: I
    flags: (0x0002) ACC_PRIVATE

  private int open_issues;
    descriptor: I
    flags: (0x0002) ACC_PRIVATE

  private int number;
    descriptor: I
    flags: (0x0002) ACC_PRIVATE

  protected java.lang.String closed_at;
    descriptor: Ljava/lang/String;
    flags: (0x0004) ACC_PROTECTED

  public org.kohsuke.github.GHMilestone();
    descriptor: ()V
    flags: (0x0001) ACC_PUBLIC
    Code:
      stack=1, locals=1, args_size=1
         0: aload_0
         1: invokespecial #1                  // Method org/kohsuke/github/GHObject."<init>":()V
         4: return
      LineNumberTable:
        line 15: 0
      LocalVariableTable:
        Start  Length  Slot  Name   Signature
            0       5     0  this   Lorg/kohsuke/github/GHMilestone;

  public org.kohsuke.github.GHRepository getOwner();
    descriptor: ()Lorg/kohsuke/github/GHRepository;
    flags: (0x0001) ACC_PUBLIC
    Code:
      stack=1, locals=1, args_size=1
         0: aload_0
         1: getfield      #2                  // Field owner:Lorg/kohsuke/github/GHRepository;
         4: areturn
      LineNumberTable:
        line 30: 0
      LocalVariableTable:
        Start  Length  Slot  Name   Signature
            0       5     0  this   Lorg/kohsuke/github/GHMilestone;
    RuntimeInvisibleAnnotations:
      0: #79(#80=[s#81],#82=s#83)
        edu.umd.cs.findbugs.annotations.SuppressFBWarnings(
          value=["EI_EXPOSE_REP"]
          justification="Expected behavior"
        )

  public org.kohsuke.github.GHUser getCreator() throws java.io.IOException;
    descriptor: ()Lorg/kohsuke/github/GHUser;
    flags: (0x0001) ACC_PUBLIC
    Code:
      stack=2, locals=1, args_size=1
         0: aload_0
         1: invokevirtual #3                  // Method root:()Lorg/kohsuke/github/GitHub;
         4: aload_0
         5: getfield      #4                  // Field creator:Lorg/kohsuke/github/GHUser;
         8: invokevirtual #5                  // Method org/kohsuke/github/GitHub.intern:(Lorg/kohsuke/github/GHUser;)Lorg/kohsuke/github/GHUser;
        11: areturn
      LineNumberTable:
        line 41: 0
      LocalVariableTable:
        Start  Length  Slot  Name   Signature
            0      12     0  this   Lorg/kohsuke/github/GHMilestone;
    Exceptions:
      throws java.io.IOException

  public java.util.Date getDueOn();
    descriptor: ()Ljava/util/Date;
    flags: (0x0001) ACC_PUBLIC
    Code:
      stack=1, locals=1, args_size=1
         0: aload_0
         1: getfield      #6                  // Field due_on:Ljava/lang/String;
         4: ifnonnull     9
         7: aconst_null
         8: areturn
         9: aload_0
        10: getfield      #6                  // Field due_on:Ljava/lang/String;
        13: invokestatic  #7                  // Method org/kohsuke/github/GitHubClient.parseDate:(Ljava/lang/String;)Ljava/util/Date;
        16: areturn
      LineNumberTable:
        line 50: 0
        line 51: 7
        line 52: 9
      LocalVariableTable:
        Start  Length  Slot  Name   Signature
            0      17     0  this   Lorg/kohsuke/github/GHMilestone;
      StackMapTable: number_of_entries = 1
        frame_type = 9 /* same */

  public java.util.Date getClosedAt() throws java.io.IOException;
    descriptor: ()Ljava/util/Date;
    flags: (0x0001) ACC_PUBLIC
    Code:
      stack=1, locals=1, args_size=1
         0: aload_0
         1: getfield      #8                  // Field closed_at:Ljava/lang/String;
         4: invokestatic  #7                  // Method org/kohsuke/github/GitHubClient.parseDate:(Ljava/lang/String;)Ljava/util/Date;
         7: areturn
      LineNumberTable:
        line 63: 0
      LocalVariableTable:
        Start  Length  Slot  Name   Signature
            0       8     0  this   Lorg/kohsuke/github/GHMilestone;
    Exceptions:
      throws java.io.IOException

  public java.lang.String getTitle();
    descriptor: ()Ljava/lang/String;
    flags: (0x0001) ACC_PUBLIC
    Code:
      stack=1, locals=1, args_size=1
         0: aload_0
         1: getfield      #9                  // Field title:Ljava/lang/String;
         4: areturn
      LineNumberTable:
        line 72: 0
      LocalVariableTable:
        Start  Length  Slot  Name   Signature
            0       5     0  this   Lorg/kohsuke/github/GHMilestone;

  public java.lang.String getDescription();
    descriptor: ()Ljava/lang/String;
    flags: (0x0001) ACC_PUBLIC
    Code:
      stack=1, locals=1, args_size=1
         0: aload_0
         1: getfield      #10                 // Field description:Ljava/lang/String;
         4: areturn
      LineNumberTable:
        line 81: 0
      LocalVariableTable:
        Start  Length  Slot  Name   Signature
            0       5     0  this   Lorg/kohsuke/github/GHMilestone;

  public int getClosedIssues();
    descriptor: ()I
    flags: (0x0001) ACC_PUBLIC
    Code:
      stack=1, locals=1, args_size=1
         0: aload_0
         1: getfield      #11                 // Field closed_issues:I
         4: ireturn
      LineNumberTable:
        line 90: 0
      LocalVariableTable:
        Start  Length  Slot  Name   Signature
            0       5     0  this   Lorg/kohsuke/github/GHMilestone;

  public int getOpenIssues();
    descriptor: ()I
    flags: (0x0001) ACC_PUBLIC
    Code:
      stack=1, locals=1, args_size=1
         0: aload_0
         1: getfield      #12                 // Field open_issues:I
         4: ireturn
      LineNumberTable:
        line 99: 0
      LocalVariableTable:
        Start  Length  Slot  Name   Signature
            0       5     0  this   Lorg/kohsuke/github/GHMilestone;

  public int getNumber();
    descriptor: ()I
    flags: (0x0001) ACC_PUBLIC
    Code:
      stack=1, locals=1, args_size=1
         0: aload_0
         1: getfield      #13                 // Field number:I
         4: ireturn
      LineNumberTable:
        line 108: 0
      LocalVariableTable:
        Start  Length  Slot  Name   Signature
            0       5     0  this   Lorg/kohsuke/github/GHMilestone;

  public java.net.URL getHtmlUrl();
    descriptor: ()Ljava/net/URL;
    flags: (0x0001) ACC_PUBLIC
    Code:
      stack=1, locals=1, args_size=1
         0: aload_0
         1: getfield      #14                 // Field html_url:Ljava/lang/String;
         4: invokestatic  #15                 // Method org/kohsuke/github/GitHubClient.parseURL:(Ljava/lang/String;)Ljava/net/URL;
         7: areturn
      LineNumberTable:
        line 112: 0
      LocalVariableTable:
        Start  Length  Slot  Name   Signature
            0       8     0  this   Lorg/kohsuke/github/GHMilestone;

  public org.kohsuke.github.GHMilestoneState getState();
    descriptor: ()Lorg/kohsuke/github/GHMilestoneState;
    flags: (0x0001) ACC_PUBLIC
    Code:
      stack=3, locals=1, args_size=1
         0: ldc           #16                 // class org/kohsuke/github/GHMilestoneState
         2: aload_0
         3: getfield      #17                 // Field state:Ljava/lang/String;
         6: getstatic     #18                 // Field java/util/Locale.ENGLISH:Ljava/util/Locale;
         9: invokevirtual #19                 // Method java/lang/String.toUpperCase:(Ljava/util/Locale;)Ljava/lang/String;
        12: invokestatic  #20                 // Method java/lang/Enum.valueOf:(Ljava/lang/Class;Ljava/lang/String;)Ljava/lang/Enum;
        15: checkcast     #16                 // class org/kohsuke/github/GHMilestoneState
        18: areturn
      LineNumberTable:
        line 121: 0
      LocalVariableTable:
        Start  Length  Slot  Name   Signature
            0      19     0  this   Lorg/kohsuke/github/GHMilestone;

  public void close() throws java.io.IOException;
    descriptor: ()V
    flags: (0x0001) ACC_PUBLIC
    Code:
      stack=3, locals=1, args_size=1
         0: aload_0
         1: ldc           #21                 // String state
         3: ldc           #22                 // String closed
         5: invokespecial #23                 // Method edit:(Ljava/lang/String;Ljava/lang/Object;)V
         8: return
      LineNumberTable:
        line 131: 0
        line 132: 8
      LocalVariableTable:
        Start  Length  Slot  Name   Signature
            0       9     0  this   Lorg/kohsuke/github/GHMilestone;
    Exceptions:
      throws java.io.IOException

  public void reopen() throws java.io.IOException;
    descriptor: ()V
    flags: (0x0001) ACC_PUBLIC
    Code:
      stack=3, locals=1, args_size=1
         0: aload_0
         1: ldc           #21                 // String state
         3: ldc           #24                 // String open
         5: invokespecial #23                 // Method edit:(Ljava/lang/String;Ljava/lang/Object;)V
         8: return
      LineNumberTable:
        line 141: 0
        line 142: 8
      LocalVariableTable:
        Start  Length  Slot  Name   Signature
            0       9     0  this   Lorg/kohsuke/github/GHMilestone;
    Exceptions:
      throws java.io.IOException

  public void delete() throws java.io.IOException;
    descriptor: ()V
    flags: (0x0001) ACC_PUBLIC
    Code:
      stack=3, locals=1, args_size=1
         0: aload_0
         1: invokevirtual #3                  // Method root:()Lorg/kohsuke/github/GitHub;
         4: invokevirtual #25                 // Method org/kohsuke/github/GitHub.createRequest:()Lorg/kohsuke/github/Requester;
         7: ldc           #26                 // String DELETE
         9: invokevirtual #27                 // Method org/kohsuke/github/Requester.method:(Ljava/lang/String;)Lorg/kohsuke/github/GitHubRequest$Builder;
        12: checkcast     #28                 // class org/kohsuke/github/Requester
        15: aload_0
        16: invokevirtual #29                 // Method getApiRoute:()Ljava/lang/String;
        19: iconst_0
        20: anewarray     #30                 // class java/lang/String
        23: invokevirtual #31                 // Method org/kohsuke/github/Requester.withUrlPath:(Ljava/lang/String;[Ljava/lang/String;)Lorg/kohsuke/github/GitHubRequest$Builder;
        26: checkcast     #28                 // class org/kohsuke/github/Requester
        29: invokevirtual #32                 // Method org/kohsuke/github/Requester.send:()V
        32: return
      LineNumberTable:
        line 151: 0
        line 152: 32
      LocalVariableTable:
        Start  Length  Slot  Name   Signature
            0      33     0  this   Lorg/kohsuke/github/GHMilestone;
    Exceptions:
      throws java.io.IOException

  private void edit(java.lang.String, java.lang.Object) throws java.io.IOException;
    descriptor: (Ljava/lang/String;Ljava/lang/Object;)V
    flags: (0x0002) ACC_PRIVATE
    Code:
      stack=3, locals=3, args_size=3
         0: aload_0
         1: invokevirtual #3                  // Method root:()Lorg/kohsuke/github/GitHub;
         4: invokevirtual #25                 // Method org/kohsuke/github/GitHub.createRequest:()Lorg/kohsuke/github/Requester;
         7: aload_1
         8: aload_2
         9: invokevirtual #33                 // Method org/kohsuke/github/Requester.with:(Ljava/lang/String;Ljava/lang/Object;)Lorg/kohsuke/github/GitHubRequest$Builder;
        12: checkcast     #28                 // class org/kohsuke/github/Requester
        15: ldc           #34                 // String PATCH
        17: invokevirtual #27                 // Method org/kohsuke/github/Requester.method:(Ljava/lang/String;)Lorg/kohsuke/github/GitHubRequest$Builder;
        20: checkcast     #28                 // class org/kohsuke/github/Requester
        23: aload_0
        24: invokevirtual #29                 // Method getApiRoute:()Ljava/lang/String;
        27: iconst_0
        28: anewarray     #30                 // class java/lang/String
        31: invokevirtual #31                 // Method org/kohsuke/github/Requester.withUrlPath:(Ljava/lang/String;[Ljava/lang/String;)Lorg/kohsuke/github/GitHubRequest$Builder;
        34: checkcast     #28                 // class org/kohsuke/github/Requester
        37: invokevirtual #32                 // Method org/kohsuke/github/Requester.send:()V
        40: return
      LineNumberTable:
        line 155: 0
        line 156: 40
      LocalVariableTable:
        Start  Length  Slot  Name   Signature
            0      41     0  this   Lorg/kohsuke/github/GHMilestone;
            0      41     1   key   Ljava/lang/String;
            0      41     2 value   Ljava/lang/Object;
    Exceptions:
      throws java.io.IOException

  public void setTitle(java.lang.String) throws java.io.IOException;
    descriptor: (Ljava/lang/String;)V
    flags: (0x0001) ACC_PUBLIC
    Code:
      stack=3, locals=2, args_size=2
         0: aload_0
         1: ldc           #35                 // String title
         3: aload_1
         4: invokespecial #23                 // Method edit:(Ljava/lang/String;Ljava/lang/Object;)V
         7: return
      LineNumberTable:
        line 167: 0
        line 168: 7
      LocalVariableTable:
        Start  Length  Slot  Name   Signature
            0       8     0  this   Lorg/kohsuke/github/GHMilestone;
            0       8     1 title   Ljava/lang/String;
    Exceptions:
      throws java.io.IOException

  public void setDescription(java.lang.String) throws java.io.IOException;
    descriptor: (Ljava/lang/String;)V
    flags: (0x0001) ACC_PUBLIC
    Code:
      stack=3, locals=2, args_size=2
         0: aload_0
         1: ldc           #36                 // String description
         3: aload_1
         4: invokespecial #23                 // Method edit:(Ljava/lang/String;Ljava/lang/Object;)V
         7: return
      LineNumberTable:
        line 179: 0
        line 180: 7
      LocalVariableTable:
        Start  Length  Slot  Name   Signature
            0       8     0  this   Lorg/kohsuke/github/GHMilestone;
            0       8     1 description   Ljava/lang/String;
    Exceptions:
      throws java.io.IOException

  public void setDueOn(java.util.Date) throws java.io.IOException;
    descriptor: (Ljava/util/Date;)V
    flags: (0x0001) ACC_PUBLIC
    Code:
      stack=3, locals=2, args_size=2
         0: aload_0
         1: ldc           #37                 // String due_on
         3: aload_1
         4: invokestatic  #38                 // Method org/kohsuke/github/GitHubClient.printDate:(Ljava/util/Date;)Ljava/lang/String;
         7: invokespecial #23                 // Method edit:(Ljava/lang/String;Ljava/lang/Object;)V
        10: return
      LineNumberTable:
        line 191: 0
        line 192: 10
      LocalVariableTable:
        Start  Length  Slot  Name   Signature
            0      11     0  this   Lorg/kohsuke/github/GHMilestone;
            0      11     1 dueOn   Ljava/util/Date;
    Exceptions:
      throws java.io.IOException

  protected java.lang.String getApiRoute();
    descriptor: ()Ljava/lang/String;
    flags: (0x0004) ACC_PROTECTED
    Code:
      stack=2, locals=1, args_size=1
         0: new           #39                 // class java/lang/StringBuilder
         3: dup
         4: invokespecial #40                 // Method java/lang/StringBuilder."<init>":()V
         7: ldc           #41                 // String /repos/
         9: invokevirtual #42                 // Method java/lang/StringBuilder.append:(Ljava/lang/String;)Ljava/lang/StringBuilder;
        12: aload_0
        13: getfield      #2                  // Field owner:Lorg/kohsuke/github/GHRepository;
        16: invokevirtual #43                 // Method org/kohsuke/github/GHRepository.getOwnerName:()Ljava/lang/String;
        19: invokevirtual #42                 // Method java/lang/StringBuilder.append:(Ljava/lang/String;)Ljava/lang/StringBuilder;
        22: ldc           #44                 // String /
        24: invokevirtual #42                 // Method java/lang/StringBuilder.append:(Ljava/lang/String;)Ljava/lang/StringBuilder;
        27: aload_0
        28: getfield      #2                  // Field owner:Lorg/kohsuke/github/GHRepository;
        31: invokevirtual #45                 // Method org/kohsuke/github/GHRepository.getName:()Ljava/lang/String;
        34: invokevirtual #42                 // Method java/lang/StringBuilder.append:(Ljava/lang/String;)Ljava/lang/StringBuilder;
        37: ldc           #46                 // String /milestones/
        39: invokevirtual #42                 // Method java/lang/StringBuilder.append:(Ljava/lang/String;)Ljava/lang/StringBuilder;
        42: aload_0
        43: getfield      #13                 // Field number:I
        46: invokevirtual #47                 // Method java/lang/StringBuilder.append:(I)Ljava/lang/StringBuilder;
        49: invokevirtual #48                 // Method java/lang/StringBuilder.toString:()Ljava/lang/String;
        52: areturn
      LineNumberTable:
        line 200: 0
      LocalVariableTable:
        Start  Length  Slot  Name   Signature
            0      53     0  this   Lorg/kohsuke/github/GHMilestone;

  public org.kohsuke.github.GHMilestone wrap(org.kohsuke.github.GHRepository);
    descriptor: (Lorg/kohsuke/github/GHRepository;)Lorg/kohsuke/github/GHMilestone;
    flags: (0x0001) ACC_PUBLIC
    Code:
      stack=3, locals=2, args_size=2
         0: new           #49                 // class java/lang/RuntimeException
         3: dup
         4: ldc           #50                 // String Do not use this method.
         6: invokespecial #51                 // Method java/lang/RuntimeException."<init>":(Ljava/lang/String;)V
         9: athrow
      LineNumberTable:
        line 212: 0
      LocalVariableTable:
        Start  Length  Slot  Name   Signature
            0      10     0  this   Lorg/kohsuke/github/GHMilestone;
            0      10     1  repo   Lorg/kohsuke/github/GHRepository;
    Deprecated: true
    RuntimeVisibleAnnotations:
      0: #123()
        java.lang.Deprecated

  org.kohsuke.github.GHMilestone lateBind(org.kohsuke.github.GHRepository);
    descriptor: (Lorg/kohsuke/github/GHRepository;)Lorg/kohsuke/github/GHMilestone;
    flags: (0x0000)
    Code:
      stack=2, locals=2, args_size=2
         0: aload_0
         1: aload_1
         2: putfield      #2                  // Field owner:Lorg/kohsuke/github/GHRepository;
         5: aload_0
         6: areturn
      LineNumberTable:
        line 223: 0
        line 224: 5
      LocalVariableTable:
        Start  Length  Slot  Name   Signature
            0       7     0  this   Lorg/kohsuke/github/GHMilestone;
            0       7     1  repo   Lorg/kohsuke/github/GHRepository;
}
SourceFile: "GHMilestone.java"
InnerClasses:
  static #203= #202 of #220;              // Builder=class org/kohsuke/github/GitHubRequest$Builder of class org/kohsuke/github/GitHubRequest
