Classfile /Users/mw/Projects/slang-braindump/.jar/jar8/assemble/slang-braindump/assemble/content/org/kohsuke/github/GHObject$1.class
  Last modified May 29, 2022; size 1476 bytes
  SHA-256 checksum 8260c78d4769bdbabe41fc7047810db4163c9c6574b4937ec744cd505585d27a
  Compiled from "GHObject.java"
class org.kohsuke.github.GHObject$1 extends org.apache.commons.lang3.builder.ReflectionToStringBuilder
  minor version: 0
  major version: 52
  flags: (0x0020) ACC_SUPER
  this_class: #6                          // org/kohsuke/github/GHObject$1
  super_class: #7                         // org/apache/commons/lang3/builder/ReflectionToStringBuilder
  interfaces: 0, fields: 1, methods: 2, attributes: 3
Constant pool:
   #1 = Fieldref           #6.#42         // org/kohsuke/github/GHObject$1.this$0:Lorg/kohsuke/github/GHObject;
   #2 = Methodref          #7.#43         // org/apache/commons/lang3/builder/ReflectionToStringBuilder."<init>":(Ljava/lang/Object;Lorg/apache/commons/lang3/builder/ToStringStyle;Ljava/lang/StringBuffer;Ljava/lang/Class;ZZ)V
   #3 = Methodref          #7.#44         // org/apache/commons/lang3/builder/ReflectionToStringBuilder.accept:(Ljava/lang/reflect/Field;)Z
   #4 = Class              #45            // org/kohsuke/github/SkipFromToString
   #5 = Methodref          #46.#47        // java/lang/reflect/Field.isAnnotationPresent:(Ljava/lang/Class;)Z
   #6 = Class              #48            // org/kohsuke/github/GHObject$1
   #7 = Class              #49            // org/apache/commons/lang3/builder/ReflectionToStringBuilder
   #8 = Utf8               this$0
   #9 = Utf8               Lorg/kohsuke/github/GHObject;
  #10 = Utf8               <init>
  #11 = Utf8               (Lorg/kohsuke/github/GHObject;Ljava/lang/Object;Lorg/apache/commons/lang3/builder/ToStringStyle;Ljava/lang/StringBuffer;Ljava/lang/Class;ZZ)V
  #12 = Utf8               Code
  #13 = Utf8               LineNumberTable
  #14 = Utf8               LocalVariableTable
  #15 = Utf8               this
  #16 = Utf8               InnerClasses
  #17 = Utf8               Lorg/kohsuke/github/GHObject$1;
  #18 = Utf8               object
  #19 = Utf8               Ljava/lang/Object;
  #20 = Utf8               style
  #21 = Utf8               Lorg/apache/commons/lang3/builder/ToStringStyle;
  #22 = Utf8               buffer
  #23 = Utf8               Ljava/lang/StringBuffer;
  #24 = Utf8               reflectUpToClass
  #25 = Utf8               Ljava/lang/Class;
  #26 = Utf8               outputTransients
  #27 = Utf8               Z
  #28 = Utf8               outputStatics
  #29 = Utf8               LocalVariableTypeTable
  #30 = Utf8               TT;
  #31 = Utf8               Ljava/lang/Class<-TT;>;
  #32 = Utf8               accept
  #33 = Utf8               (Ljava/lang/reflect/Field;)Z
  #34 = Utf8               field
  #35 = Utf8               Ljava/lang/reflect/Field;
  #36 = Utf8               StackMapTable
  #37 = Utf8               SourceFile
  #38 = Utf8               GHObject.java
  #39 = Utf8               EnclosingMethod
  #40 = Class              #50            // org/kohsuke/github/GHObject
  #41 = NameAndType        #51:#52        // toString:()Ljava/lang/String;
  #42 = NameAndType        #8:#9          // this$0:Lorg/kohsuke/github/GHObject;
  #43 = NameAndType        #10:#53        // "<init>":(Ljava/lang/Object;Lorg/apache/commons/lang3/builder/ToStringStyle;Ljava/lang/StringBuffer;Ljava/lang/Class;ZZ)V
  #44 = NameAndType        #32:#33        // accept:(Ljava/lang/reflect/Field;)Z
  #45 = Utf8               org/kohsuke/github/SkipFromToString
  #46 = Class              #54            // java/lang/reflect/Field
  #47 = NameAndType        #55:#56        // isAnnotationPresent:(Ljava/lang/Class;)Z
  #48 = Utf8               org/kohsuke/github/GHObject$1
  #49 = Utf8               org/apache/commons/lang3/builder/ReflectionToStringBuilder
  #50 = Utf8               org/kohsuke/github/GHObject
  #51 = Utf8               toString
  #52 = Utf8               ()Ljava/lang/String;
  #53 = Utf8               (Ljava/lang/Object;Lorg/apache/commons/lang3/builder/ToStringStyle;Ljava/lang/StringBuffer;Ljava/lang/Class;ZZ)V
  #54 = Utf8               java/lang/reflect/Field
  #55 = Utf8               isAnnotationPresent
  #56 = Utf8               (Ljava/lang/Class;)Z
{
  final org.kohsuke.github.GHObject this$0;
    descriptor: Lorg/kohsuke/github/GHObject;
    flags: (0x1010) ACC_FINAL, ACC_SYNTHETIC

  org.kohsuke.github.GHObject$1(org.kohsuke.github.GHObject, java.lang.Object, org.apache.commons.lang3.builder.ToStringStyle, java.lang.StringBuffer, java.lang.Class, boolean, boolean);
    descriptor: (Lorg/kohsuke/github/GHObject;Ljava/lang/Object;Lorg/apache/commons/lang3/builder/ToStringStyle;Ljava/lang/StringBuffer;Ljava/lang/Class;ZZ)V
    flags: (0x0000)
    Code:
      stack=7, locals=8, args_size=8
         0: aload_0
         1: aload_1
         2: putfield      #1                  // Field this$0:Lorg/kohsuke/github/GHObject;
         5: aload_0
         6: aload_2
         7: aload_3
         8: aload         4
        10: aload         5
        12: iload         6
        14: iload         7
        16: invokespecial #2                  // Method org/apache/commons/lang3/builder/ReflectionToStringBuilder."<init>":(Ljava/lang/Object;Lorg/apache/commons/lang3/builder/ToStringStyle;Ljava/lang/StringBuffer;Ljava/lang/Class;ZZ)V
        19: return
      LineNumberTable:
        line 160: 0
      LocalVariableTable:
        Start  Length  Slot  Name   Signature
            0      20     0  this   Lorg/kohsuke/github/GHObject$1;
            0      20     1 this$0   Lorg/kohsuke/github/GHObject;
            0      20     2 object   Ljava/lang/Object;
            0      20     3 style   Lorg/apache/commons/lang3/builder/ToStringStyle;
            0      20     4 buffer   Ljava/lang/StringBuffer;
            0      20     5 reflectUpToClass   Ljava/lang/Class;
            0      20     6 outputTransients   Z
            0      20     7 outputStatics   Z
      LocalVariableTypeTable:
        Start  Length  Slot  Name   Signature
            0      20     2 object   TT;
            0      20     5 reflectUpToClass   Ljava/lang/Class<-TT;>;

  protected boolean accept(java.lang.reflect.Field);
    descriptor: (Ljava/lang/reflect/Field;)Z
    flags: (0x0004) ACC_PROTECTED
    Code:
      stack=2, locals=2, args_size=2
         0: aload_0
         1: aload_1
         2: invokespecial #3                  // Method org/apache/commons/lang3/builder/ReflectionToStringBuilder.accept:(Ljava/lang/reflect/Field;)Z
         5: ifeq          21
         8: aload_1
         9: ldc           #4                  // class org/kohsuke/github/SkipFromToString
        11: invokevirtual #5                  // Method java/lang/reflect/Field.isAnnotationPresent:(Ljava/lang/Class;)Z
        14: ifne          21
        17: iconst_1
        18: goto          22
        21: iconst_0
        22: ireturn
      LineNumberTable:
        line 163: 0
      LocalVariableTable:
        Start  Length  Slot  Name   Signature
            0      23     0  this   Lorg/kohsuke/github/GHObject$1;
            0      23     1 field   Ljava/lang/reflect/Field;
      StackMapTable: number_of_entries = 2
        frame_type = 21 /* same */
        frame_type = 64 /* same_locals_1_stack_item */
          stack = [ int ]
}
SourceFile: "GHObject.java"
EnclosingMethod: #40.#41                // org.kohsuke.github.GHObject.toString
InnerClasses:
  #6;                                     // class org/kohsuke/github/GHObject$1
