Classfile /Users/mw/Projects/slang-braindump/.jar/jar8/assemble/slang-braindump/assemble/content/org/kohsuke/github/GHPersonSet.class
  Last modified May 29, 2022; size 1968 bytes
  SHA-256 checksum 4adea8903b1d3a7ad5b3c7674cc00979b984041edc4825fa1495a19e47a4cade
  Compiled from "GHPersonSet.java"
public class org.kohsuke.github.GHPersonSet<T extends org.kohsuke.github.GHPerson> extends java.util.HashSet<T>
  minor version: 0
  major version: 52
  flags: (0x0021) ACC_PUBLIC, ACC_SUPER
  this_class: #12                         // org/kohsuke/github/GHPersonSet
  super_class: #13                        // java/util/HashSet
  interfaces: 0, fields: 1, methods: 6, attributes: 2
Constant pool:
   #1 = Methodref          #13.#57        // java/util/HashSet."<init>":()V
   #2 = Methodref          #13.#58        // java/util/HashSet."<init>":(Ljava/util/Collection;)V
   #3 = Methodref          #59.#60        // java/util/Arrays.asList:([Ljava/lang/Object;)Ljava/util/List;
   #4 = Methodref          #13.#61        // java/util/HashSet."<init>":(IF)V
   #5 = Methodref          #13.#62        // java/util/HashSet."<init>":(I)V
   #6 = Methodref          #12.#63        // org/kohsuke/github/GHPersonSet.iterator:()Ljava/util/Iterator;
   #7 = InterfaceMethodref #52.#64        // java/util/Iterator.hasNext:()Z
   #8 = InterfaceMethodref #52.#65        // java/util/Iterator.next:()Ljava/lang/Object;
   #9 = Class              #66            // org/kohsuke/github/GHPerson
  #10 = Methodref          #9.#67         // org/kohsuke/github/GHPerson.getLogin:()Ljava/lang/String;
  #11 = Methodref          #68.#69        // java/lang/String.equals:(Ljava/lang/Object;)Z
  #12 = Class              #70            // org/kohsuke/github/GHPersonSet
  #13 = Class              #71            // java/util/HashSet
  #14 = Utf8               serialVersionUID
  #15 = Utf8               J
  #16 = Utf8               ConstantValue
  #17 = Long               1l
  #19 = Utf8               <init>
  #20 = Utf8               ()V
  #21 = Utf8               Code
  #22 = Utf8               LineNumberTable
  #23 = Utf8               LocalVariableTable
  #24 = Utf8               this
  #25 = Utf8               Lorg/kohsuke/github/GHPersonSet;
  #26 = Utf8               LocalVariableTypeTable
  #27 = Utf8               Lorg/kohsuke/github/GHPersonSet<TT;>;
  #28 = Utf8               (Ljava/util/Collection;)V
  #29 = Utf8               c
  #30 = Utf8               Ljava/util/Collection;
  #31 = Utf8               Ljava/util/Collection<+TT;>;
  #32 = Utf8               Signature
  #33 = Utf8               (Ljava/util/Collection<+TT;>;)V
  #34 = Utf8               ([Lorg/kohsuke/github/GHPerson;)V
  #35 = Utf8               [Lorg/kohsuke/github/GHPerson;
  #36 = Utf8               [TT;
  #37 = Utf8               ([TT;)V
  #38 = Utf8               (IF)V
  #39 = Utf8               initialCapacity
  #40 = Utf8               I
  #41 = Utf8               loadFactor
  #42 = Utf8               F
  #43 = Utf8               (I)V
  #44 = Utf8               byLogin
  #45 = Utf8               (Ljava/lang/String;)Lorg/kohsuke/github/GHPerson;
  #46 = Utf8               t
  #47 = Utf8               Lorg/kohsuke/github/GHPerson;
  #48 = Utf8               login
  #49 = Utf8               Ljava/lang/String;
  #50 = Utf8               TT;
  #51 = Utf8               StackMapTable
  #52 = Class              #72            // java/util/Iterator
  #53 = Utf8               (Ljava/lang/String;)TT;
  #54 = Utf8               <T:Lorg/kohsuke/github/GHPerson;>Ljava/util/HashSet<TT;>;
  #55 = Utf8               SourceFile
  #56 = Utf8               GHPersonSet.java
  #57 = NameAndType        #19:#20        // "<init>":()V
  #58 = NameAndType        #19:#28        // "<init>":(Ljava/util/Collection;)V
  #59 = Class              #73            // java/util/Arrays
  #60 = NameAndType        #74:#75        // asList:([Ljava/lang/Object;)Ljava/util/List;
  #61 = NameAndType        #19:#38        // "<init>":(IF)V
  #62 = NameAndType        #19:#43        // "<init>":(I)V
  #63 = NameAndType        #76:#77        // iterator:()Ljava/util/Iterator;
  #64 = NameAndType        #78:#79        // hasNext:()Z
  #65 = NameAndType        #80:#81        // next:()Ljava/lang/Object;
  #66 = Utf8               org/kohsuke/github/GHPerson
  #67 = NameAndType        #82:#83        // getLogin:()Ljava/lang/String;
  #68 = Class              #84            // java/lang/String
  #69 = NameAndType        #85:#86        // equals:(Ljava/lang/Object;)Z
  #70 = Utf8               org/kohsuke/github/GHPersonSet
  #71 = Utf8               java/util/HashSet
  #72 = Utf8               java/util/Iterator
  #73 = Utf8               java/util/Arrays
  #74 = Utf8               asList
  #75 = Utf8               ([Ljava/lang/Object;)Ljava/util/List;
  #76 = Utf8               iterator
  #77 = Utf8               ()Ljava/util/Iterator;
  #78 = Utf8               hasNext
  #79 = Utf8               ()Z
  #80 = Utf8               next
  #81 = Utf8               ()Ljava/lang/Object;
  #82 = Utf8               getLogin
  #83 = Utf8               ()Ljava/lang/String;
  #84 = Utf8               java/lang/String
  #85 = Utf8               equals
  #86 = Utf8               (Ljava/lang/Object;)Z
{
  private static final long serialVersionUID;
    descriptor: J
    flags: (0x001a) ACC_PRIVATE, ACC_STATIC, ACC_FINAL
    ConstantValue: long 1l

  public org.kohsuke.github.GHPersonSet();
    descriptor: ()V
    flags: (0x0001) ACC_PUBLIC
    Code:
      stack=1, locals=1, args_size=1
         0: aload_0
         1: invokespecial #1                  // Method java/util/HashSet."<init>":()V
         4: return
      LineNumberTable:
        line 20: 0
        line 21: 4
      LocalVariableTable:
        Start  Length  Slot  Name   Signature
            0       5     0  this   Lorg/kohsuke/github/GHPersonSet;
      LocalVariableTypeTable:
        Start  Length  Slot  Name   Signature
            0       5     0  this   Lorg/kohsuke/github/GHPersonSet<TT;>;

  public org.kohsuke.github.GHPersonSet(java.util.Collection<? extends T>);
    descriptor: (Ljava/util/Collection;)V
    flags: (0x0001) ACC_PUBLIC
    Code:
      stack=2, locals=2, args_size=2
         0: aload_0
         1: aload_1
         2: invokespecial #2                  // Method java/util/HashSet."<init>":(Ljava/util/Collection;)V
         5: return
      LineNumberTable:
        line 30: 0
        line 31: 5
      LocalVariableTable:
        Start  Length  Slot  Name   Signature
            0       6     0  this   Lorg/kohsuke/github/GHPersonSet;
            0       6     1     c   Ljava/util/Collection;
      LocalVariableTypeTable:
        Start  Length  Slot  Name   Signature
            0       6     0  this   Lorg/kohsuke/github/GHPersonSet<TT;>;
            0       6     1     c   Ljava/util/Collection<+TT;>;
    Signature: #33                          // (Ljava/util/Collection<+TT;>;)V

  public org.kohsuke.github.GHPersonSet(T...);
    descriptor: ([Lorg/kohsuke/github/GHPerson;)V
    flags: (0x0081) ACC_PUBLIC, ACC_VARARGS
    Code:
      stack=2, locals=2, args_size=2
         0: aload_0
         1: aload_1
         2: invokestatic  #3                  // Method java/util/Arrays.asList:([Ljava/lang/Object;)Ljava/util/List;
         5: invokespecial #2                  // Method java/util/HashSet."<init>":(Ljava/util/Collection;)V
         8: return
      LineNumberTable:
        line 40: 0
        line 41: 8
      LocalVariableTable:
        Start  Length  Slot  Name   Signature
            0       9     0  this   Lorg/kohsuke/github/GHPersonSet;
            0       9     1     c   [Lorg/kohsuke/github/GHPerson;
      LocalVariableTypeTable:
        Start  Length  Slot  Name   Signature
            0       9     0  this   Lorg/kohsuke/github/GHPersonSet<TT;>;
            0       9     1     c   [TT;
    Signature: #37                          // ([TT;)V

  public org.kohsuke.github.GHPersonSet(int, float);
    descriptor: (IF)V
    flags: (0x0001) ACC_PUBLIC
    Code:
      stack=3, locals=3, args_size=3
         0: aload_0
         1: iload_1
         2: fload_2
         3: invokespecial #4                  // Method java/util/HashSet."<init>":(IF)V
         6: return
      LineNumberTable:
        line 52: 0
        line 53: 6
      LocalVariableTable:
        Start  Length  Slot  Name   Signature
            0       7     0  this   Lorg/kohsuke/github/GHPersonSet;
            0       7     1 initialCapacity   I
            0       7     2 loadFactor   F
      LocalVariableTypeTable:
        Start  Length  Slot  Name   Signature
            0       7     0  this   Lorg/kohsuke/github/GHPersonSet<TT;>;

  public org.kohsuke.github.GHPersonSet(int);
    descriptor: (I)V
    flags: (0x0001) ACC_PUBLIC
    Code:
      stack=2, locals=2, args_size=2
         0: aload_0
         1: iload_1
         2: invokespecial #5                  // Method java/util/HashSet."<init>":(I)V
         5: return
      LineNumberTable:
        line 62: 0
        line 63: 5
      LocalVariableTable:
        Start  Length  Slot  Name   Signature
            0       6     0  this   Lorg/kohsuke/github/GHPersonSet;
            0       6     1 initialCapacity   I
      LocalVariableTypeTable:
        Start  Length  Slot  Name   Signature
            0       6     0  this   Lorg/kohsuke/github/GHPersonSet<TT;>;

  public T byLogin(java.lang.String);
    descriptor: (Ljava/lang/String;)Lorg/kohsuke/github/GHPerson;
    flags: (0x0001) ACC_PUBLIC
    Code:
      stack=2, locals=4, args_size=2
         0: aload_0
         1: invokevirtual #6                  // Method iterator:()Ljava/util/Iterator;
         4: astore_2
         5: aload_2
         6: invokeinterface #7,  1            // InterfaceMethod java/util/Iterator.hasNext:()Z
        11: ifeq          40
        14: aload_2
        15: invokeinterface #8,  1            // InterfaceMethod java/util/Iterator.next:()Ljava/lang/Object;
        20: checkcast     #9                  // class org/kohsuke/github/GHPerson
        23: astore_3
        24: aload_3
        25: invokevirtual #10                 // Method org/kohsuke/github/GHPerson.getLogin:()Ljava/lang/String;
        28: aload_1
        29: invokevirtual #11                 // Method java/lang/String.equals:(Ljava/lang/Object;)Z
        32: ifeq          37
        35: aload_3
        36: areturn
        37: goto          5
        40: aconst_null
        41: areturn
      LineNumberTable:
        line 73: 0
        line 74: 24
        line 75: 35
        line 74: 37
        line 76: 40
      LocalVariableTable:
        Start  Length  Slot  Name   Signature
           24      13     3     t   Lorg/kohsuke/github/GHPerson;
            0      42     0  this   Lorg/kohsuke/github/GHPersonSet;
            0      42     1 login   Ljava/lang/String;
      LocalVariableTypeTable:
        Start  Length  Slot  Name   Signature
           24      13     3     t   TT;
            0      42     0  this   Lorg/kohsuke/github/GHPersonSet<TT;>;
      StackMapTable: number_of_entries = 3
        frame_type = 252 /* append */
          offset_delta = 5
          locals = [ class java/util/Iterator ]
        frame_type = 31 /* same */
        frame_type = 250 /* chop */
          offset_delta = 2
    Signature: #53                          // (Ljava/lang/String;)TT;
}
Signature: #54                          // <T:Lorg/kohsuke/github/GHPerson;>Ljava/util/HashSet<TT;>;
SourceFile: "GHPersonSet.java"
