Classfile /Users/mw/Projects/slang-braindump/.jar/jar8/assemble/slang-braindump/assemble/content/org/kohsuke/github/GHPerson.class
  Last modified May 29, 2022; size 7989 bytes
  SHA-256 checksum 4f185b107ad54ad02309eb65151f5247508c83b4f751faaca5ff9e04efa52e65
  Compiled from "GHPerson.java"
public abstract class org.kohsuke.github.GHPerson extends org.kohsuke.github.GHObject
  minor version: 0
  major version: 52
  flags: (0x0421) ACC_PUBLIC, ACC_SUPER, ACC_ABSTRACT
  this_class: #65                         // org/kohsuke/github/GHPerson
  super_class: #66                        // org/kohsuke/github/GHObject
  interfaces: 0, fields: 18, methods: 28, attributes: 3
Constant pool:
    #1 = Methodref          #66.#170      // org/kohsuke/github/GHObject."<init>":()V
    #2 = Methodref          #66.#171      // org/kohsuke/github/GHObject.getCreatedAt:()Ljava/util/Date;
    #3 = Methodref          #65.#172      // org/kohsuke/github/GHPerson.isOffline:()Z
    #4 = Methodref          #65.#173      // org/kohsuke/github/GHPerson.getUrl:()Ljava/net/URL;
    #5 = Methodref          #65.#174      // org/kohsuke/github/GHPerson.root:()Lorg/kohsuke/github/GitHub;
    #6 = Methodref          #175.#176     // org/kohsuke/github/GitHub.createRequest:()Lorg/kohsuke/github/Requester;
    #7 = Methodref          #101.#177     // java/net/URL.toString:()Ljava/lang/String;
    #8 = Methodref          #9.#178       // org/kohsuke/github/Requester.setRawUrlPath:(Ljava/lang/String;)Lorg/kohsuke/github/GitHubRequest$Builder;
    #9 = Class              #179          // org/kohsuke/github/Requester
   #10 = Methodref          #9.#180       // org/kohsuke/github/Requester.fetchInto:(Ljava/lang/Object;)Ljava/lang/Object;
   #11 = Class              #181          // java/util/TreeMap
   #12 = Methodref          #11.#170      // java/util/TreeMap."<init>":()V
   #13 = Methodref          #65.#182      // org/kohsuke/github/GHPerson.listRepositories:(I)Lorg/kohsuke/github/PagedIterable;
   #14 = Methodref          #183.#184     // org/kohsuke/github/PagedIterable.iterator:()Lorg/kohsuke/github/PagedIterator;
   #15 = InterfaceMethodref #113.#185     // java/util/Iterator.hasNext:()Z
   #16 = InterfaceMethodref #113.#186     // java/util/Iterator.next:()Ljava/lang/Object;
   #17 = Class              #187          // org/kohsuke/github/GHRepository
   #18 = Methodref          #17.#188      // org/kohsuke/github/GHRepository.getName:()Ljava/lang/String;
   #19 = InterfaceMethodref #112.#189     // java/util/Map.put:(Ljava/lang/Object;Ljava/lang/Object;)Ljava/lang/Object;
   #20 = Methodref          #190.#191     // java/util/Collections.unmodifiableMap:(Ljava/util/Map;)Ljava/util/Map;
   #21 = Class              #192          // java/lang/StringBuilder
   #22 = Methodref          #21.#170      // java/lang/StringBuilder."<init>":()V
   #23 = String             #193          // /users/
   #24 = Methodref          #21.#194      // java/lang/StringBuilder.append:(Ljava/lang/String;)Ljava/lang/StringBuilder;
   #25 = Fieldref           #65.#195      // org/kohsuke/github/GHPerson.login:Ljava/lang/String;
   #26 = String             #196          // /repos
   #27 = Methodref          #21.#177      // java/lang/StringBuilder.toString:()Ljava/lang/String;
   #28 = Class              #197          // java/lang/String
   #29 = Methodref          #9.#198       // org/kohsuke/github/Requester.withUrlPath:(Ljava/lang/String;[Ljava/lang/String;)Lorg/kohsuke/github/GitHubRequest$Builder;
   #30 = Class              #199          // "[Lorg/kohsuke/github/GHRepository;"
   #31 = Methodref          #9.#200       // org/kohsuke/github/Requester.toIterable:(Ljava/lang/Class;Ljava/util/function/Consumer;)Lorg/kohsuke/github/PagedIterable;
   #32 = Methodref          #183.#201     // org/kohsuke/github/PagedIterable.withPageSize:(I)Lorg/kohsuke/github/PagedIterable;
   #33 = InvokeDynamic      #0:#206       // #0:iterator:(Lorg/kohsuke/github/GHPerson;I)Ljava/lang/Iterable;
   #34 = Methodref          #17.#207      // org/kohsuke/github/GHRepository.read:(Lorg/kohsuke/github/GitHub;Ljava/lang/String;Ljava/lang/String;)Lorg/kohsuke/github/GHRepository;
   #35 = Class              #208          // java/io/FileNotFoundException
   #36 = String             #209          //
   #37 = Fieldref           #65.#210      // org/kohsuke/github/GHPerson.avatar_url:Ljava/lang/String;
   #38 = Methodref          #65.#211      // org/kohsuke/github/GHPerson.populate:()V
   #39 = Fieldref           #65.#212      // org/kohsuke/github/GHPerson.name:Ljava/lang/String;
   #40 = Fieldref           #65.#213      // org/kohsuke/github/GHPerson.company:Ljava/lang/String;
   #41 = Fieldref           #65.#214      // org/kohsuke/github/GHPerson.location:Ljava/lang/String;
   #42 = Fieldref           #65.#215      // org/kohsuke/github/GHPerson.twitter_username:Ljava/lang/String;
   #43 = Methodref          #66.#216      // org/kohsuke/github/GHObject.getUpdatedAt:()Ljava/util/Date;
   #44 = Fieldref           #65.#217      // org/kohsuke/github/GHPerson.blog:Ljava/lang/String;
   #45 = Fieldref           #65.#218      // org/kohsuke/github/GHPerson.html_url:Ljava/lang/String;
   #46 = Methodref          #219.#220     // org/kohsuke/github/GitHubClient.parseURL:(Ljava/lang/String;)Ljava/net/URL;
   #47 = Fieldref           #65.#221      // org/kohsuke/github/GHPerson.email:Ljava/lang/String;
   #48 = Fieldref           #65.#222      // org/kohsuke/github/GHPerson.public_gists:I
   #49 = Fieldref           #65.#223      // org/kohsuke/github/GHPerson.public_repos:I
   #50 = Fieldref           #65.#224      // org/kohsuke/github/GHPerson.following:I
   #51 = Fieldref           #65.#225      // org/kohsuke/github/GHPerson.followers:I
   #52 = Fieldref           #65.#226      // org/kohsuke/github/GHPerson.type:Ljava/lang/String;
   #53 = Fieldref           #65.#227      // org/kohsuke/github/GHPerson.site_admin:Z
   #54 = Fieldref           #65.#228      // org/kohsuke/github/GHPerson.total_private_repos:Ljava/lang/Integer;
   #55 = Methodref          #229.#230     // java/util/Optional.ofNullable:(Ljava/lang/Object;)Ljava/util/Optional;
   #56 = Methodref          #175.#231     // org/kohsuke/github/GitHub.getClient:()Lorg/kohsuke/github/GitHubClient;
   #57 = String             #232          // users
   #58 = String             #233          // repos
   #59 = Methodref          #9.#234       // org/kohsuke/github/Requester.build:()Lorg/kohsuke/github/GitHubRequest;
   #60 = Methodref          #235.#236     // org/kohsuke/github/GitHubPageIterator.create:(Lorg/kohsuke/github/GitHubClient;Ljava/lang/Class;Lorg/kohsuke/github/GitHubRequest;I)Lorg/kohsuke/github/GitHubPageIterator;
   #61 = Class              #237          // org/kohsuke/github/PagedIterator
   #62 = Methodref          #61.#238      // org/kohsuke/github/PagedIterator."<init>":(Ljava/util/Iterator;Ljava/util/function/Consumer;)V
   #63 = Class              #239          // org/kohsuke/github/GHPerson$1
   #64 = Methodref          #63.#240      // org/kohsuke/github/GHPerson$1."<init>":(Lorg/kohsuke/github/GHPerson;Lorg/kohsuke/github/PagedIterator;)V
   #65 = Class              #241          // org/kohsuke/github/GHPerson
   #66 = Class              #242          // org/kohsuke/github/GHObject
   #67 = Utf8               InnerClasses
   #68 = Utf8               login
   #69 = Utf8               Ljava/lang/String;
   #70 = Utf8               avatar_url
   #71 = Utf8               location
   #72 = Utf8               blog
   #73 = Utf8               email
   #74 = Utf8               bio
   #75 = Utf8               name
   #76 = Utf8               company
   #77 = Utf8               type
   #78 = Utf8               twitter_username
   #79 = Utf8               html_url
   #80 = Utf8               followers
   #81 = Utf8               I
   #82 = Utf8               following
   #83 = Utf8               public_repos
   #84 = Utf8               public_gists
   #85 = Utf8               site_admin
   #86 = Utf8               Z
   #87 = Utf8               hireable
   #88 = Utf8               total_private_repos
   #89 = Utf8               Ljava/lang/Integer;
   #90 = Utf8               <init>
   #91 = Utf8               ()V
   #92 = Utf8               Code
   #93 = Utf8               LineNumberTable
   #94 = Utf8               LocalVariableTable
   #95 = Utf8               this
   #96 = Utf8               Lorg/kohsuke/github/GHPerson;
   #97 = Utf8               populate
   #98 = Utf8               url
   #99 = Utf8               Ljava/net/URL;
  #100 = Utf8               StackMapTable
  #101 = Class              #243          // java/net/URL
  #102 = Utf8               Exceptions
  #103 = Class              #244          // java/io/IOException
  #104 = Utf8               getRepositories
  #105 = Utf8               ()Ljava/util/Map;
  #106 = Utf8               r
  #107 = Utf8               Lorg/kohsuke/github/GHRepository;
  #108 = Utf8               repositories
  #109 = Utf8               Ljava/util/Map;
  #110 = Utf8               LocalVariableTypeTable
  #111 = Utf8               Ljava/util/Map<Ljava/lang/String;Lorg/kohsuke/github/GHRepository;>;
  #112 = Class              #245          // java/util/Map
  #113 = Class              #246          // java/util/Iterator
  #114 = Utf8               Signature
  #115 = Utf8               ()Ljava/util/Map<Ljava/lang/String;Lorg/kohsuke/github/GHRepository;>;
  #116 = Utf8               listRepositories
  #117 = Utf8               ()Lorg/kohsuke/github/PagedIterable;
  #118 = Utf8               ()Lorg/kohsuke/github/PagedIterable<Lorg/kohsuke/github/GHRepository;>;
  #119 = Utf8               (I)Lorg/kohsuke/github/PagedIterable;
  #120 = Utf8               pageSize
  #121 = Utf8               (I)Lorg/kohsuke/github/PagedIterable<Lorg/kohsuke/github/GHRepository;>;
  #122 = Utf8               iterateRepositories
  #123 = Utf8               (I)Ljava/lang/Iterable;
  #124 = Utf8               Deprecated
  #125 = Utf8               (I)Ljava/lang/Iterable<Ljava/util/List<Lorg/kohsuke/github/GHRepository;>;>;
  #126 = Utf8               RuntimeVisibleAnnotations
  #127 = Utf8               Ljava/lang/Deprecated;
  #128 = Utf8               getRepository
  #129 = Utf8               (Ljava/lang/String;)Lorg/kohsuke/github/GHRepository;
  #130 = Utf8               e
  #131 = Utf8               Ljava/io/FileNotFoundException;
  #132 = Utf8               listEvents
  #133 = Utf8               ()Lorg/kohsuke/github/PagedIterable<Lorg/kohsuke/github/GHEventInfo;>;
  #134 = Utf8               getGravatarId
  #135 = Utf8               ()Ljava/lang/String;
  #136 = Utf8               getAvatarUrl
  #137 = Utf8               getLogin
  #138 = Utf8               getName
  #139 = Utf8               getCompany
  #140 = Utf8               getLocation
  #141 = Utf8               getTwitterUsername
  #142 = Utf8               getCreatedAt
  #143 = Utf8               ()Ljava/util/Date;
  #144 = Utf8               getUpdatedAt
  #145 = Utf8               getBlog
  #146 = Utf8               getHtmlUrl
  #147 = Utf8               ()Ljava/net/URL;
  #148 = Utf8               getEmail
  #149 = Utf8               getPublicGistCount
  #150 = Utf8               ()I
  #151 = Utf8               getPublicRepoCount
  #152 = Utf8               getFollowingCount
  #153 = Utf8               getFollowersCount
  #154 = Utf8               getType
  #155 = Utf8               isSiteAdmin
  #156 = Utf8               ()Z
  #157 = Utf8               getTotalPrivateRepoCount
  #158 = Utf8               ()Ljava/util/Optional;
  #159 = Utf8               ()Ljava/util/Optional<Ljava/lang/Integer;>;
  #160 = Utf8               lambda$iterateRepositories$0
  #161 = Utf8               (I)Ljava/util/Iterator;
  #162 = Utf8               pager
  #163 = Utf8               Lorg/kohsuke/github/PagedIterator;
  #164 = Utf8               iterator
  #165 = Utf8               Lorg/kohsuke/github/GitHubPageIterator;
  #166 = Utf8               Lorg/kohsuke/github/PagedIterator<Lorg/kohsuke/github/GHRepository;>;
  #167 = Utf8               Lorg/kohsuke/github/GitHubPageIterator<[Lorg/kohsuke/github/GHRepository;>;
  #168 = Utf8               SourceFile
  #169 = Utf8               GHPerson.java
  #170 = NameAndType        #90:#91       // "<init>":()V
  #171 = NameAndType        #142:#143     // getCreatedAt:()Ljava/util/Date;
  #172 = NameAndType        #247:#156     // isOffline:()Z
  #173 = NameAndType        #248:#147     // getUrl:()Ljava/net/URL;
  #174 = NameAndType        #249:#250     // root:()Lorg/kohsuke/github/GitHub;
  #175 = Class              #251          // org/kohsuke/github/GitHub
  #176 = NameAndType        #252:#253     // createRequest:()Lorg/kohsuke/github/Requester;
  #177 = NameAndType        #254:#135     // toString:()Ljava/lang/String;
  #178 = NameAndType        #255:#258     // setRawUrlPath:(Ljava/lang/String;)Lorg/kohsuke/github/GitHubRequest$Builder;
  #179 = Utf8               org/kohsuke/github/Requester
  #180 = NameAndType        #259:#260     // fetchInto:(Ljava/lang/Object;)Ljava/lang/Object;
  #181 = Utf8               java/util/TreeMap
  #182 = NameAndType        #116:#119     // listRepositories:(I)Lorg/kohsuke/github/PagedIterable;
  #183 = Class              #261          // org/kohsuke/github/PagedIterable
  #184 = NameAndType        #164:#262     // iterator:()Lorg/kohsuke/github/PagedIterator;
  #185 = NameAndType        #263:#156     // hasNext:()Z
  #186 = NameAndType        #264:#265     // next:()Ljava/lang/Object;
  #187 = Utf8               org/kohsuke/github/GHRepository
  #188 = NameAndType        #138:#135     // getName:()Ljava/lang/String;
  #189 = NameAndType        #266:#267     // put:(Ljava/lang/Object;Ljava/lang/Object;)Ljava/lang/Object;
  #190 = Class              #268          // java/util/Collections
  #191 = NameAndType        #269:#270     // unmodifiableMap:(Ljava/util/Map;)Ljava/util/Map;
  #192 = Utf8               java/lang/StringBuilder
  #193 = Utf8               /users/
  #194 = NameAndType        #271:#272     // append:(Ljava/lang/String;)Ljava/lang/StringBuilder;
  #195 = NameAndType        #68:#69       // login:Ljava/lang/String;
  #196 = Utf8               /repos
  #197 = Utf8               java/lang/String
  #198 = NameAndType        #273:#274     // withUrlPath:(Ljava/lang/String;[Ljava/lang/String;)Lorg/kohsuke/github/GitHubRequest$Builder;
  #199 = Utf8               [Lorg/kohsuke/github/GHRepository;
  #200 = NameAndType        #275:#276     // toIterable:(Ljava/lang/Class;Ljava/util/function/Consumer;)Lorg/kohsuke/github/PagedIterable;
  #201 = NameAndType        #277:#119     // withPageSize:(I)Lorg/kohsuke/github/PagedIterable;
  #202 = Utf8               BootstrapMethods
  #203 = MethodHandle       6:#278        // REF_invokeStatic java/lang/invoke/LambdaMetafactory.metafactory:(Ljava/lang/invoke/MethodHandles$Lookup;Ljava/lang/String;Ljava/lang/invoke/MethodType;Ljava/lang/invoke/MethodType;Ljava/lang/invoke/MethodHandle;Ljava/lang/invoke/MethodType;)Ljava/lang/invoke/CallSite;
  #204 = MethodType         #279          //  ()Ljava/util/Iterator;
  #205 = MethodHandle       7:#280        // REF_invokeSpecial org/kohsuke/github/GHPerson.lambda$iterateRepositories$0:(I)Ljava/util/Iterator;
  #206 = NameAndType        #164:#281     // iterator:(Lorg/kohsuke/github/GHPerson;I)Ljava/lang/Iterable;
  #207 = NameAndType        #282:#283     // read:(Lorg/kohsuke/github/GitHub;Ljava/lang/String;Ljava/lang/String;)Lorg/kohsuke/github/GHRepository;
  #208 = Utf8               java/io/FileNotFoundException
  #209 = Utf8
  #210 = NameAndType        #70:#69       // avatar_url:Ljava/lang/String;
  #211 = NameAndType        #97:#91       // populate:()V
  #212 = NameAndType        #75:#69       // name:Ljava/lang/String;
  #213 = NameAndType        #76:#69       // company:Ljava/lang/String;
  #214 = NameAndType        #71:#69       // location:Ljava/lang/String;
  #215 = NameAndType        #78:#69       // twitter_username:Ljava/lang/String;
  #216 = NameAndType        #144:#143     // getUpdatedAt:()Ljava/util/Date;
  #217 = NameAndType        #72:#69       // blog:Ljava/lang/String;
  #218 = NameAndType        #79:#69       // html_url:Ljava/lang/String;
  #219 = Class              #284          // org/kohsuke/github/GitHubClient
  #220 = NameAndType        #285:#286     // parseURL:(Ljava/lang/String;)Ljava/net/URL;
  #221 = NameAndType        #73:#69       // email:Ljava/lang/String;
  #222 = NameAndType        #84:#81       // public_gists:I
  #223 = NameAndType        #83:#81       // public_repos:I
  #224 = NameAndType        #82:#81       // following:I
  #225 = NameAndType        #80:#81       // followers:I
  #226 = NameAndType        #77:#69       // type:Ljava/lang/String;
  #227 = NameAndType        #85:#86       // site_admin:Z
  #228 = NameAndType        #88:#89       // total_private_repos:Ljava/lang/Integer;
  #229 = Class              #287          // java/util/Optional
  #230 = NameAndType        #288:#289     // ofNullable:(Ljava/lang/Object;)Ljava/util/Optional;
  #231 = NameAndType        #290:#291     // getClient:()Lorg/kohsuke/github/GitHubClient;
  #232 = Utf8               users
  #233 = Utf8               repos
  #234 = NameAndType        #292:#293     // build:()Lorg/kohsuke/github/GitHubRequest;
  #235 = Class              #294          // org/kohsuke/github/GitHubPageIterator
  #236 = NameAndType        #295:#296     // create:(Lorg/kohsuke/github/GitHubClient;Ljava/lang/Class;Lorg/kohsuke/github/GitHubRequest;I)Lorg/kohsuke/github/GitHubPageIterator;
  #237 = Utf8               org/kohsuke/github/PagedIterator
  #238 = NameAndType        #90:#297      // "<init>":(Ljava/util/Iterator;Ljava/util/function/Consumer;)V
  #239 = Utf8               org/kohsuke/github/GHPerson$1
  #240 = NameAndType        #90:#298      // "<init>":(Lorg/kohsuke/github/GHPerson;Lorg/kohsuke/github/PagedIterator;)V
  #241 = Utf8               org/kohsuke/github/GHPerson
  #242 = Utf8               org/kohsuke/github/GHObject
  #243 = Utf8               java/net/URL
  #244 = Utf8               java/io/IOException
  #245 = Utf8               java/util/Map
  #246 = Utf8               java/util/Iterator
  #247 = Utf8               isOffline
  #248 = Utf8               getUrl
  #249 = Utf8               root
  #250 = Utf8               ()Lorg/kohsuke/github/GitHub;
  #251 = Utf8               org/kohsuke/github/GitHub
  #252 = Utf8               createRequest
  #253 = Utf8               ()Lorg/kohsuke/github/Requester;
  #254 = Utf8               toString
  #255 = Utf8               setRawUrlPath
  #256 = Class              #300          // org/kohsuke/github/GitHubRequest$Builder
  #257 = Utf8               Builder
  #258 = Utf8               (Ljava/lang/String;)Lorg/kohsuke/github/GitHubRequest$Builder;
  #259 = Utf8               fetchInto
  #260 = Utf8               (Ljava/lang/Object;)Ljava/lang/Object;
  #261 = Utf8               org/kohsuke/github/PagedIterable
  #262 = Utf8               ()Lorg/kohsuke/github/PagedIterator;
  #263 = Utf8               hasNext
  #264 = Utf8               next
  #265 = Utf8               ()Ljava/lang/Object;
  #266 = Utf8               put
  #267 = Utf8               (Ljava/lang/Object;Ljava/lang/Object;)Ljava/lang/Object;
  #268 = Utf8               java/util/Collections
  #269 = Utf8               unmodifiableMap
  #270 = Utf8               (Ljava/util/Map;)Ljava/util/Map;
  #271 = Utf8               append
  #272 = Utf8               (Ljava/lang/String;)Ljava/lang/StringBuilder;
  #273 = Utf8               withUrlPath
  #274 = Utf8               (Ljava/lang/String;[Ljava/lang/String;)Lorg/kohsuke/github/GitHubRequest$Builder;
  #275 = Utf8               toIterable
  #276 = Utf8               (Ljava/lang/Class;Ljava/util/function/Consumer;)Lorg/kohsuke/github/PagedIterable;
  #277 = Utf8               withPageSize
  #278 = Methodref          #301.#302     // java/lang/invoke/LambdaMetafactory.metafactory:(Ljava/lang/invoke/MethodHandles$Lookup;Ljava/lang/String;Ljava/lang/invoke/MethodType;Ljava/lang/invoke/MethodType;Ljava/lang/invoke/MethodHandle;Ljava/lang/invoke/MethodType;)Ljava/lang/invoke/CallSite;
  #279 = Utf8               ()Ljava/util/Iterator;
  #280 = Methodref          #65.#303      // org/kohsuke/github/GHPerson.lambda$iterateRepositories$0:(I)Ljava/util/Iterator;
  #281 = Utf8               (Lorg/kohsuke/github/GHPerson;I)Ljava/lang/Iterable;
  #282 = Utf8               read
  #283 = Utf8               (Lorg/kohsuke/github/GitHub;Ljava/lang/String;Ljava/lang/String;)Lorg/kohsuke/github/GHRepository;
  #284 = Utf8               org/kohsuke/github/GitHubClient
  #285 = Utf8               parseURL
  #286 = Utf8               (Ljava/lang/String;)Ljava/net/URL;
  #287 = Utf8               java/util/Optional
  #288 = Utf8               ofNullable
  #289 = Utf8               (Ljava/lang/Object;)Ljava/util/Optional;
  #290 = Utf8               getClient
  #291 = Utf8               ()Lorg/kohsuke/github/GitHubClient;
  #292 = Utf8               build
  #293 = Utf8               ()Lorg/kohsuke/github/GitHubRequest;
  #294 = Utf8               org/kohsuke/github/GitHubPageIterator
  #295 = Utf8               create
  #296 = Utf8               (Lorg/kohsuke/github/GitHubClient;Ljava/lang/Class;Lorg/kohsuke/github/GitHubRequest;I)Lorg/kohsuke/github/GitHubPageIterator;
  #297 = Utf8               (Ljava/util/Iterator;Ljava/util/function/Consumer;)V
  #298 = Utf8               (Lorg/kohsuke/github/GHPerson;Lorg/kohsuke/github/PagedIterator;)V
  #299 = Class              #304          // org/kohsuke/github/GitHubRequest
  #300 = Utf8               org/kohsuke/github/GitHubRequest$Builder
  #301 = Class              #305          // java/lang/invoke/LambdaMetafactory
  #302 = NameAndType        #306:#309     // metafactory:(Ljava/lang/invoke/MethodHandles$Lookup;Ljava/lang/String;Ljava/lang/invoke/MethodType;Ljava/lang/invoke/MethodType;Ljava/lang/invoke/MethodHandle;Ljava/lang/invoke/MethodType;)Ljava/lang/invoke/CallSite;
  #303 = NameAndType        #160:#161     // lambda$iterateRepositories$0:(I)Ljava/util/Iterator;
  #304 = Utf8               org/kohsuke/github/GitHubRequest
  #305 = Utf8               java/lang/invoke/LambdaMetafactory
  #306 = Utf8               metafactory
  #307 = Class              #311          // java/lang/invoke/MethodHandles$Lookup
  #308 = Utf8               Lookup
  #309 = Utf8               (Ljava/lang/invoke/MethodHandles$Lookup;Ljava/lang/String;Ljava/lang/invoke/MethodType;Ljava/lang/invoke/MethodType;Ljava/lang/invoke/MethodHandle;Ljava/lang/invoke/MethodType;)Ljava/lang/invoke/CallSite;
  #310 = Class              #312          // java/lang/invoke/MethodHandles
  #311 = Utf8               java/lang/invoke/MethodHandles$Lookup
  #312 = Utf8               java/lang/invoke/MethodHandles
{
  protected java.lang.String login;
    descriptor: Ljava/lang/String;
    flags: (0x0004) ACC_PROTECTED

  protected java.lang.String avatar_url;
    descriptor: Ljava/lang/String;
    flags: (0x0004) ACC_PROTECTED

  protected java.lang.String location;
    descriptor: Ljava/lang/String;
    flags: (0x0004) ACC_PROTECTED

  protected java.lang.String blog;
    descriptor: Ljava/lang/String;
    flags: (0x0004) ACC_PROTECTED

  protected java.lang.String email;
    descriptor: Ljava/lang/String;
    flags: (0x0004) ACC_PROTECTED

  protected java.lang.String bio;
    descriptor: Ljava/lang/String;
    flags: (0x0004) ACC_PROTECTED

  protected java.lang.String name;
    descriptor: Ljava/lang/String;
    flags: (0x0004) ACC_PROTECTED

  protected java.lang.String company;
    descriptor: Ljava/lang/String;
    flags: (0x0004) ACC_PROTECTED

  protected java.lang.String type;
    descriptor: Ljava/lang/String;
    flags: (0x0004) ACC_PROTECTED

  protected java.lang.String twitter_username;
    descriptor: Ljava/lang/String;
    flags: (0x0004) ACC_PROTECTED

  protected java.lang.String html_url;
    descriptor: Ljava/lang/String;
    flags: (0x0004) ACC_PROTECTED

  protected int followers;
    descriptor: I
    flags: (0x0004) ACC_PROTECTED

  protected int following;
    descriptor: I
    flags: (0x0004) ACC_PROTECTED

  protected int public_repos;
    descriptor: I
    flags: (0x0004) ACC_PROTECTED

  protected int public_gists;
    descriptor: I
    flags: (0x0004) ACC_PROTECTED

  protected boolean site_admin;
    descriptor: Z
    flags: (0x0004) ACC_PROTECTED

  protected boolean hireable;
    descriptor: Z
    flags: (0x0004) ACC_PROTECTED

  protected java.lang.Integer total_private_repos;
    descriptor: Ljava/lang/Integer;
    flags: (0x0004) ACC_PROTECTED

  public org.kohsuke.github.GHPerson();
    descriptor: ()V
    flags: (0x0001) ACC_PUBLIC
    Code:
      stack=1, locals=1, args_size=1
         0: aload_0
         1: invokespecial #1                  // Method org/kohsuke/github/GHObject."<init>":()V
         4: return
      LineNumberTable:
        line 19: 0
      LocalVariableTable:
        Start  Length  Slot  Name   Signature
            0       5     0  this   Lorg/kohsuke/github/GHPerson;

  protected synchronized void populate() throws java.io.IOException;
    descriptor: ()V
    flags: (0x0024) ACC_PROTECTED, ACC_SYNCHRONIZED
    Code:
      stack=2, locals=2, args_size=1
         0: aload_0
         1: invokespecial #2                  // Method org/kohsuke/github/GHObject.getCreatedAt:()Ljava/util/Date;
         4: ifnull        8
         7: return
         8: aload_0
         9: invokevirtual #3                  // Method isOffline:()Z
        12: ifeq          16
        15: return
        16: aload_0
        17: invokevirtual #4                  // Method getUrl:()Ljava/net/URL;
        20: astore_1
        21: aload_1
        22: ifnull        47
        25: aload_0
        26: invokevirtual #5                  // Method root:()Lorg/kohsuke/github/GitHub;
        29: invokevirtual #6                  // Method org/kohsuke/github/GitHub.createRequest:()Lorg/kohsuke/github/Requester;
        32: aload_1
        33: invokevirtual #7                  // Method java/net/URL.toString:()Ljava/lang/String;
        36: invokevirtual #8                  // Method org/kohsuke/github/Requester.setRawUrlPath:(Ljava/lang/String;)Lorg/kohsuke/github/GitHubRequest$Builder;
        39: checkcast     #9                  // class org/kohsuke/github/Requester
        42: aload_0
        43: invokevirtual #10                 // Method org/kohsuke/github/Requester.fetchInto:(Ljava/lang/Object;)Ljava/lang/Object;
        46: pop
        47: return
      LineNumberTable:
        line 42: 0
        line 43: 7
        line 45: 8
        line 46: 15
        line 48: 16
        line 49: 21
        line 50: 25
        line 52: 47
      LocalVariableTable:
        Start  Length  Slot  Name   Signature
            0      48     0  this   Lorg/kohsuke/github/GHPerson;
           21      27     1   url   Ljava/net/URL;
      StackMapTable: number_of_entries = 3
        frame_type = 8 /* same */
        frame_type = 7 /* same */
        frame_type = 252 /* append */
          offset_delta = 30
          locals = [ class java/net/URL ]
    Exceptions:
      throws java.io.IOException

  public synchronized java.util.Map<java.lang.String, org.kohsuke.github.GHRepository> getRepositories() throws java.io.IOException;
    descriptor: ()Ljava/util/Map;
    flags: (0x0021) ACC_PUBLIC, ACC_SYNCHRONIZED
    Code:
      stack=3, locals=4, args_size=1
         0: new           #11                 // class java/util/TreeMap
         3: dup
         4: invokespecial #12                 // Method java/util/TreeMap."<init>":()V
         7: astore_1
         8: aload_0
         9: bipush        100
        11: invokevirtual #13                 // Method listRepositories:(I)Lorg/kohsuke/github/PagedIterable;
        14: invokevirtual #14                 // Method org/kohsuke/github/PagedIterable.iterator:()Lorg/kohsuke/github/PagedIterator;
        17: astore_2
        18: aload_2
        19: invokeinterface #15,  1           // InterfaceMethod java/util/Iterator.hasNext:()Z
        24: ifeq          52
        27: aload_2
        28: invokeinterface #16,  1           // InterfaceMethod java/util/Iterator.next:()Ljava/lang/Object;
        33: checkcast     #17                 // class org/kohsuke/github/GHRepository
        36: astore_3
        37: aload_1
        38: aload_3
        39: invokevirtual #18                 // Method org/kohsuke/github/GHRepository.getName:()Ljava/lang/String;
        42: aload_3
        43: invokeinterface #19,  3           // InterfaceMethod java/util/Map.put:(Ljava/lang/Object;Ljava/lang/Object;)Ljava/lang/Object;
        48: pop
        49: goto          18
        52: aload_1
        53: invokestatic  #20                 // Method java/util/Collections.unmodifiableMap:(Ljava/util/Map;)Ljava/util/Map;
        56: areturn
      LineNumberTable:
        line 65: 0
        line 66: 8
        line 67: 37
        line 68: 49
        line 69: 52
      LocalVariableTable:
        Start  Length  Slot  Name   Signature
           37      12     3     r   Lorg/kohsuke/github/GHRepository;
            0      57     0  this   Lorg/kohsuke/github/GHPerson;
            8      49     1 repositories   Ljava/util/Map;
      LocalVariableTypeTable:
        Start  Length  Slot  Name   Signature
            8      49     1 repositories   Ljava/util/Map<Ljava/lang/String;Lorg/kohsuke/github/GHRepository;>;
      StackMapTable: number_of_entries = 2
        frame_type = 253 /* append */
          offset_delta = 18
          locals = [ class java/util/Map, class java/util/Iterator ]
        frame_type = 250 /* chop */
          offset_delta = 33
    Exceptions:
      throws java.io.IOException
    Signature: #115                         // ()Ljava/util/Map<Ljava/lang/String;Lorg/kohsuke/github/GHRepository;>;

  public org.kohsuke.github.PagedIterable<org.kohsuke.github.GHRepository> listRepositories();
    descriptor: ()Lorg/kohsuke/github/PagedIterable;
    flags: (0x0001) ACC_PUBLIC
    Code:
      stack=2, locals=1, args_size=1
         0: aload_0
         1: bipush        30
         3: invokevirtual #13                 // Method listRepositories:(I)Lorg/kohsuke/github/PagedIterable;
         6: areturn
      LineNumberTable:
        line 80: 0
      LocalVariableTable:
        Start  Length  Slot  Name   Signature
            0       7     0  this   Lorg/kohsuke/github/GHPerson;
    Signature: #118                         // ()Lorg/kohsuke/github/PagedIterable<Lorg/kohsuke/github/GHRepository;>;

  public org.kohsuke.github.PagedIterable<org.kohsuke.github.GHRepository> listRepositories(int);
    descriptor: (I)Lorg/kohsuke/github/PagedIterable;
    flags: (0x0001) ACC_PUBLIC
    Code:
      stack=3, locals=2, args_size=2
         0: aload_0
         1: invokevirtual #5                  // Method root:()Lorg/kohsuke/github/GitHub;
         4: invokevirtual #6                  // Method org/kohsuke/github/GitHub.createRequest:()Lorg/kohsuke/github/Requester;
         7: new           #21                 // class java/lang/StringBuilder
        10: dup
        11: invokespecial #22                 // Method java/lang/StringBuilder."<init>":()V
        14: ldc           #23                 // String /users/
        16: invokevirtual #24                 // Method java/lang/StringBuilder.append:(Ljava/lang/String;)Ljava/lang/StringBuilder;
        19: aload_0
        20: getfield      #25                 // Field login:Ljava/lang/String;
        23: invokevirtual #24                 // Method java/lang/StringBuilder.append:(Ljava/lang/String;)Ljava/lang/StringBuilder;
        26: ldc           #26                 // String /repos
        28: invokevirtual #24                 // Method java/lang/StringBuilder.append:(Ljava/lang/String;)Ljava/lang/StringBuilder;
        31: invokevirtual #27                 // Method java/lang/StringBuilder.toString:()Ljava/lang/String;
        34: iconst_0
        35: anewarray     #28                 // class java/lang/String
        38: invokevirtual #29                 // Method org/kohsuke/github/Requester.withUrlPath:(Ljava/lang/String;[Ljava/lang/String;)Lorg/kohsuke/github/GitHubRequest$Builder;
        41: checkcast     #9                  // class org/kohsuke/github/Requester
        44: ldc           #30                 // class "[Lorg/kohsuke/github/GHRepository;"
        46: aconst_null
        47: invokevirtual #31                 // Method org/kohsuke/github/Requester.toIterable:(Ljava/lang/Class;Ljava/util/function/Consumer;)Lorg/kohsuke/github/PagedIterable;
        50: iload_1
        51: invokevirtual #32                 // Method org/kohsuke/github/PagedIterable.withPageSize:(I)Lorg/kohsuke/github/PagedIterable;
        54: areturn
      LineNumberTable:
        line 92: 0
        line 93: 38
        line 94: 47
        line 95: 51
        line 92: 54
      LocalVariableTable:
        Start  Length  Slot  Name   Signature
            0      55     0  this   Lorg/kohsuke/github/GHPerson;
            0      55     1 pageSize   I
    Signature: #121                         // (I)Lorg/kohsuke/github/PagedIterable<Lorg/kohsuke/github/GHRepository;>;

  public synchronized java.lang.Iterable<java.util.List<org.kohsuke.github.GHRepository>> iterateRepositories(int);
    descriptor: (I)Ljava/lang/Iterable;
    flags: (0x0021) ACC_PUBLIC, ACC_SYNCHRONIZED
    Code:
      stack=2, locals=2, args_size=2
         0: aload_0
         1: iload_1
         2: invokedynamic #33,  0             // InvokeDynamic #0:iterator:(Lorg/kohsuke/github/GHPerson;I)Ljava/lang/Iterable;
         7: areturn
      LineNumberTable:
        line 115: 0
      LocalVariableTable:
        Start  Length  Slot  Name   Signature
            0       8     0  this   Lorg/kohsuke/github/GHPerson;
            0       8     1 pageSize   I
    Deprecated: true
    Signature: #125                         // (I)Ljava/lang/Iterable<Ljava/util/List<Lorg/kohsuke/github/GHRepository;>;>;
    RuntimeVisibleAnnotations:
      0: #127()
        java.lang.Deprecated

  public org.kohsuke.github.GHRepository getRepository(java.lang.String) throws java.io.IOException;
    descriptor: (Ljava/lang/String;)Lorg/kohsuke/github/GHRepository;
    flags: (0x0001) ACC_PUBLIC
    Code:
      stack=3, locals=3, args_size=2
         0: aload_0
         1: invokevirtual #5                  // Method root:()Lorg/kohsuke/github/GitHub;
         4: aload_0
         5: getfield      #25                 // Field login:Ljava/lang/String;
         8: aload_1
         9: invokestatic  #34                 // Method org/kohsuke/github/GHRepository.read:(Lorg/kohsuke/github/GitHub;Ljava/lang/String;Ljava/lang/String;)Lorg/kohsuke/github/GHRepository;
        12: areturn
        13: astore_2
        14: aconst_null
        15: areturn
      Exception table:
         from    to  target type
             0    12    13   Class java/io/FileNotFoundException
      LineNumberTable:
        line 146: 0
        line 147: 13
        line 148: 14
      LocalVariableTable:
        Start  Length  Slot  Name   Signature
           14       2     2     e   Ljava/io/FileNotFoundException;
            0      16     0  this   Lorg/kohsuke/github/GHPerson;
            0      16     1  name   Ljava/lang/String;
      StackMapTable: number_of_entries = 1
        frame_type = 77 /* same_locals_1_stack_item */
          stack = [ class java/io/FileNotFoundException ]
    Exceptions:
      throws java.io.IOException

  public abstract org.kohsuke.github.PagedIterable<org.kohsuke.github.GHEventInfo> listEvents() throws java.io.IOException;
    descriptor: ()Lorg/kohsuke/github/PagedIterable;
    flags: (0x0401) ACC_PUBLIC, ACC_ABSTRACT
    Exceptions:
      throws java.io.IOException
    Signature: #133                         // ()Lorg/kohsuke/github/PagedIterable<Lorg/kohsuke/github/GHEventInfo;>;

  public java.lang.String getGravatarId();
    descriptor: ()Ljava/lang/String;
    flags: (0x0001) ACC_PUBLIC
    Code:
      stack=1, locals=1, args_size=1
         0: ldc           #36                 // String
         2: areturn
      LineNumberTable:
        line 169: 0
      LocalVariableTable:
        Start  Length  Slot  Name   Signature
            0       3     0  this   Lorg/kohsuke/github/GHPerson;
    Deprecated: true
    RuntimeVisibleAnnotations:
      0: #127()
        java.lang.Deprecated

  public java.lang.String getAvatarUrl();
    descriptor: ()Ljava/lang/String;
    flags: (0x0001) ACC_PUBLIC
    Code:
      stack=1, locals=1, args_size=1
         0: aload_0
         1: getfield      #37                 // Field avatar_url:Ljava/lang/String;
         4: areturn
      LineNumberTable:
        line 178: 0
      LocalVariableTable:
        Start  Length  Slot  Name   Signature
            0       5     0  this   Lorg/kohsuke/github/GHPerson;

  public java.lang.String getLogin();
    descriptor: ()Ljava/lang/String;
    flags: (0x0001) ACC_PUBLIC
    Code:
      stack=1, locals=1, args_size=1
         0: aload_0
         1: getfield      #25                 // Field login:Ljava/lang/String;
         4: areturn
      LineNumberTable:
        line 187: 0
      LocalVariableTable:
        Start  Length  Slot  Name   Signature
            0       5     0  this   Lorg/kohsuke/github/GHPerson;

  public java.lang.String getName() throws java.io.IOException;
    descriptor: ()Ljava/lang/String;
    flags: (0x0001) ACC_PUBLIC
    Code:
      stack=1, locals=1, args_size=1
         0: aload_0
         1: invokevirtual #38                 // Method populate:()V
         4: aload_0
         5: getfield      #39                 // Field name:Ljava/lang/String;
         8: areturn
      LineNumberTable:
        line 198: 0
        line 199: 4
      LocalVariableTable:
        Start  Length  Slot  Name   Signature
            0       9     0  this   Lorg/kohsuke/github/GHPerson;
    Exceptions:
      throws java.io.IOException

  public java.lang.String getCompany() throws java.io.IOException;
    descriptor: ()Ljava/lang/String;
    flags: (0x0001) ACC_PUBLIC
    Code:
      stack=1, locals=1, args_size=1
         0: aload_0
         1: invokevirtual #38                 // Method populate:()V
         4: aload_0
         5: getfield      #40                 // Field company:Ljava/lang/String;
         8: areturn
      LineNumberTable:
        line 210: 0
        line 211: 4
      LocalVariableTable:
        Start  Length  Slot  Name   Signature
            0       9     0  this   Lorg/kohsuke/github/GHPerson;
    Exceptions:
      throws java.io.IOException

  public java.lang.String getLocation() throws java.io.IOException;
    descriptor: ()Ljava/lang/String;
    flags: (0x0001) ACC_PUBLIC
    Code:
      stack=1, locals=1, args_size=1
         0: aload_0
         1: invokevirtual #38                 // Method populate:()V
         4: aload_0
         5: getfield      #41                 // Field location:Ljava/lang/String;
         8: areturn
      LineNumberTable:
        line 222: 0
        line 223: 4
      LocalVariableTable:
        Start  Length  Slot  Name   Signature
            0       9     0  this   Lorg/kohsuke/github/GHPerson;
    Exceptions:
      throws java.io.IOException

  public java.lang.String getTwitterUsername() throws java.io.IOException;
    descriptor: ()Ljava/lang/String;
    flags: (0x0001) ACC_PUBLIC
    Code:
      stack=1, locals=1, args_size=1
         0: aload_0
         1: invokevirtual #38                 // Method populate:()V
         4: aload_0
         5: getfield      #42                 // Field twitter_username:Ljava/lang/String;
         8: areturn
      LineNumberTable:
        line 234: 0
        line 235: 4
      LocalVariableTable:
        Start  Length  Slot  Name   Signature
            0       9     0  this   Lorg/kohsuke/github/GHPerson;
    Exceptions:
      throws java.io.IOException

  public java.util.Date getCreatedAt() throws java.io.IOException;
    descriptor: ()Ljava/util/Date;
    flags: (0x0001) ACC_PUBLIC
    Code:
      stack=1, locals=1, args_size=1
         0: aload_0
         1: invokevirtual #38                 // Method populate:()V
         4: aload_0
         5: invokespecial #2                  // Method org/kohsuke/github/GHObject.getCreatedAt:()Ljava/util/Date;
         8: areturn
      LineNumberTable:
        line 239: 0
        line 240: 4
      LocalVariableTable:
        Start  Length  Slot  Name   Signature
            0       9     0  this   Lorg/kohsuke/github/GHPerson;
    Exceptions:
      throws java.io.IOException

  public java.util.Date getUpdatedAt() throws java.io.IOException;
    descriptor: ()Ljava/util/Date;
    flags: (0x0001) ACC_PUBLIC
    Code:
      stack=1, locals=1, args_size=1
         0: aload_0
         1: invokevirtual #38                 // Method populate:()V
         4: aload_0
         5: invokespecial #43                 // Method org/kohsuke/github/GHObject.getUpdatedAt:()Ljava/util/Date;
         8: areturn
      LineNumberTable:
        line 244: 0
        line 245: 4
      LocalVariableTable:
        Start  Length  Slot  Name   Signature
            0       9     0  this   Lorg/kohsuke/github/GHPerson;
    Exceptions:
      throws java.io.IOException

  public java.lang.String getBlog() throws java.io.IOException;
    descriptor: ()Ljava/lang/String;
    flags: (0x0001) ACC_PUBLIC
    Code:
      stack=1, locals=1, args_size=1
         0: aload_0
         1: invokevirtual #38                 // Method populate:()V
         4: aload_0
         5: getfield      #44                 // Field blog:Ljava/lang/String;
         8: areturn
      LineNumberTable:
        line 256: 0
        line 257: 4
      LocalVariableTable:
        Start  Length  Slot  Name   Signature
            0       9     0  this   Lorg/kohsuke/github/GHPerson;
    Exceptions:
      throws java.io.IOException

  public java.net.URL getHtmlUrl();
    descriptor: ()Ljava/net/URL;
    flags: (0x0001) ACC_PUBLIC
    Code:
      stack=1, locals=1, args_size=1
         0: aload_0
         1: getfield      #45                 // Field html_url:Ljava/lang/String;
         4: invokestatic  #46                 // Method org/kohsuke/github/GitHubClient.parseURL:(Ljava/lang/String;)Ljava/net/URL;
         7: areturn
      LineNumberTable:
        line 262: 0
      LocalVariableTable:
        Start  Length  Slot  Name   Signature
            0       8     0  this   Lorg/kohsuke/github/GHPerson;

  public java.lang.String getEmail() throws java.io.IOException;
    descriptor: ()Ljava/lang/String;
    flags: (0x0001) ACC_PUBLIC
    Code:
      stack=1, locals=1, args_size=1
         0: aload_0
         1: invokevirtual #38                 // Method populate:()V
         4: aload_0
         5: getfield      #47                 // Field email:Ljava/lang/String;
         8: areturn
      LineNumberTable:
        line 273: 0
        line 274: 4
      LocalVariableTable:
        Start  Length  Slot  Name   Signature
            0       9     0  this   Lorg/kohsuke/github/GHPerson;
    Exceptions:
      throws java.io.IOException

  public int getPublicGistCount() throws java.io.IOException;
    descriptor: ()I
    flags: (0x0001) ACC_PUBLIC
    Code:
      stack=1, locals=1, args_size=1
         0: aload_0
         1: invokevirtual #38                 // Method populate:()V
         4: aload_0
         5: getfield      #48                 // Field public_gists:I
         8: ireturn
      LineNumberTable:
        line 285: 0
        line 286: 4
      LocalVariableTable:
        Start  Length  Slot  Name   Signature
            0       9     0  this   Lorg/kohsuke/github/GHPerson;
    Exceptions:
      throws java.io.IOException

  public int getPublicRepoCount() throws java.io.IOException;
    descriptor: ()I
    flags: (0x0001) ACC_PUBLIC
    Code:
      stack=1, locals=1, args_size=1
         0: aload_0
         1: invokevirtual #38                 // Method populate:()V
         4: aload_0
         5: getfield      #49                 // Field public_repos:I
         8: ireturn
      LineNumberTable:
        line 297: 0
        line 298: 4
      LocalVariableTable:
        Start  Length  Slot  Name   Signature
            0       9     0  this   Lorg/kohsuke/github/GHPerson;
    Exceptions:
      throws java.io.IOException

  public int getFollowingCount() throws java.io.IOException;
    descriptor: ()I
    flags: (0x0001) ACC_PUBLIC
    Code:
      stack=1, locals=1, args_size=1
         0: aload_0
         1: invokevirtual #38                 // Method populate:()V
         4: aload_0
         5: getfield      #50                 // Field following:I
         8: ireturn
      LineNumberTable:
        line 309: 0
        line 310: 4
      LocalVariableTable:
        Start  Length  Slot  Name   Signature
            0       9     0  this   Lorg/kohsuke/github/GHPerson;
    Exceptions:
      throws java.io.IOException

  public int getFollowersCount() throws java.io.IOException;
    descriptor: ()I
    flags: (0x0001) ACC_PUBLIC
    Code:
      stack=1, locals=1, args_size=1
         0: aload_0
         1: invokevirtual #38                 // Method populate:()V
         4: aload_0
         5: getfield      #51                 // Field followers:I
         8: ireturn
      LineNumberTable:
        line 321: 0
        line 322: 4
      LocalVariableTable:
        Start  Length  Slot  Name   Signature
            0       9     0  this   Lorg/kohsuke/github/GHPerson;
    Exceptions:
      throws java.io.IOException

  public java.lang.String getType() throws java.io.IOException;
    descriptor: ()Ljava/lang/String;
    flags: (0x0001) ACC_PUBLIC
    Code:
      stack=1, locals=1, args_size=1
         0: aload_0
         1: invokevirtual #38                 // Method populate:()V
         4: aload_0
         5: getfield      #52                 // Field type:Ljava/lang/String;
         8: areturn
      LineNumberTable:
        line 333: 0
        line 334: 4
      LocalVariableTable:
        Start  Length  Slot  Name   Signature
            0       9     0  this   Lorg/kohsuke/github/GHPerson;
    Exceptions:
      throws java.io.IOException

  public boolean isSiteAdmin() throws java.io.IOException;
    descriptor: ()Z
    flags: (0x0001) ACC_PUBLIC
    Code:
      stack=1, locals=1, args_size=1
         0: aload_0
         1: invokevirtual #38                 // Method populate:()V
         4: aload_0
         5: getfield      #53                 // Field site_admin:Z
         8: ireturn
      LineNumberTable:
        line 345: 0
        line 346: 4
      LocalVariableTable:
        Start  Length  Slot  Name   Signature
            0       9     0  this   Lorg/kohsuke/github/GHPerson;
    Exceptions:
      throws java.io.IOException

  public java.util.Optional<java.lang.Integer> getTotalPrivateRepoCount() throws java.io.IOException;
    descriptor: ()Ljava/util/Optional;
    flags: (0x0001) ACC_PUBLIC
    Code:
      stack=1, locals=1, args_size=1
         0: aload_0
         1: invokevirtual #38                 // Method populate:()V
         4: aload_0
         5: getfield      #54                 // Field total_private_repos:Ljava/lang/Integer;
         8: invokestatic  #55                 // Method java/util/Optional.ofNullable:(Ljava/lang/Object;)Ljava/util/Optional;
        11: areturn
      LineNumberTable:
        line 357: 0
        line 358: 4
      LocalVariableTable:
        Start  Length  Slot  Name   Signature
            0      12     0  this   Lorg/kohsuke/github/GHPerson;
    Exceptions:
      throws java.io.IOException
    Signature: #159                         // ()Ljava/util/Optional<Ljava/lang/Integer;>;

  private java.util.Iterator lambda$iterateRepositories$0(int);
    descriptor: (I)Ljava/util/Iterator;
    flags: (0x1002) ACC_PRIVATE, ACC_SYNTHETIC
    Code:
      stack=8, locals=4, args_size=2
         0: aload_0
         1: invokevirtual #5                  // Method root:()Lorg/kohsuke/github/GitHub;
         4: invokevirtual #56                 // Method org/kohsuke/github/GitHub.getClient:()Lorg/kohsuke/github/GitHubClient;
         7: ldc           #30                 // class "[Lorg/kohsuke/github/GHRepository;"
         9: aload_0
        10: invokevirtual #5                  // Method root:()Lorg/kohsuke/github/GitHub;
        13: invokevirtual #6                  // Method org/kohsuke/github/GitHub.createRequest:()Lorg/kohsuke/github/Requester;
        16: ldc           #57                 // String users
        18: iconst_2
        19: anewarray     #28                 // class java/lang/String
        22: dup
        23: iconst_0
        24: aload_0
        25: getfield      #25                 // Field login:Ljava/lang/String;
        28: aastore
        29: dup
        30: iconst_1
        31: ldc           #58                 // String repos
        33: aastore
        34: invokevirtual #29                 // Method org/kohsuke/github/Requester.withUrlPath:(Ljava/lang/String;[Ljava/lang/String;)Lorg/kohsuke/github/GitHubRequest$Builder;
        37: checkcast     #9                  // class org/kohsuke/github/Requester
        40: invokevirtual #59                 // Method org/kohsuke/github/Requester.build:()Lorg/kohsuke/github/GitHubRequest;
        43: iload_1
        44: invokestatic  #60                 // Method org/kohsuke/github/GitHubPageIterator.create:(Lorg/kohsuke/github/GitHubClient;Ljava/lang/Class;Lorg/kohsuke/github/GitHubRequest;I)Lorg/kohsuke/github/GitHubPageIterator;
        47: astore_3
        48: new           #61                 // class org/kohsuke/github/PagedIterator
        51: dup
        52: aload_3
        53: aconst_null
        54: invokespecial #62                 // Method org/kohsuke/github/PagedIterator."<init>":(Ljava/util/Iterator;Ljava/util/function/Consumer;)V
        57: astore_2
        58: new           #63                 // class org/kohsuke/github/GHPerson$1
        61: dup
        62: aload_0
        63: aload_2
        64: invokespecial #64                 // Method org/kohsuke/github/GHPerson$1."<init>":(Lorg/kohsuke/github/GHPerson;Lorg/kohsuke/github/PagedIterator;)V
        67: areturn
      LineNumberTable:
        line 117: 0
        line 119: 10
        line 117: 44
        line 121: 48
        line 123: 58
      LocalVariableTable:
        Start  Length  Slot  Name   Signature
            0      68     0  this   Lorg/kohsuke/github/GHPerson;
            0      68     1 pageSize   I
           58      10     2 pager   Lorg/kohsuke/github/PagedIterator;
           48      20     3 iterator   Lorg/kohsuke/github/GitHubPageIterator;
      LocalVariableTypeTable:
        Start  Length  Slot  Name   Signature
           58      10     2 pager   Lorg/kohsuke/github/PagedIterator<Lorg/kohsuke/github/GHRepository;>;
           48      20     3 iterator   Lorg/kohsuke/github/GitHubPageIterator<[Lorg/kohsuke/github/GHRepository;>;
}
SourceFile: "GHPerson.java"
InnerClasses:
  #63;                                    // class org/kohsuke/github/GHPerson$1
  static #257= #256 of #299;              // Builder=class org/kohsuke/github/GitHubRequest$Builder of class org/kohsuke/github/GitHubRequest
  public static final #308= #307 of #310; // Lookup=class java/lang/invoke/MethodHandles$Lookup of class java/lang/invoke/MethodHandles
BootstrapMethods:
  0: #203 REF_invokeStatic java/lang/invoke/LambdaMetafactory.metafactory:(Ljava/lang/invoke/MethodHandles$Lookup;Ljava/lang/String;Ljava/lang/invoke/MethodType;Ljava/lang/invoke/MethodType;Ljava/lang/invoke/MethodHandle;Ljava/lang/invoke/MethodType;)Ljava/lang/invoke/CallSite;
    Method arguments:
      #204 ()Ljava/util/Iterator;
      #205 REF_invokeSpecial org/kohsuke/github/GHPerson.lambda$iterateRepositories$0:(I)Ljava/util/Iterator;
      #204 ()Ljava/util/Iterator;
