Classfile /Users/mw/Projects/slang-braindump/.jar/jar8/assemble/slang-braindump/assemble/content/org/kohsuke/github/GHPullRequestCommitDetail.class
  Last modified May 29, 2022; size 2274 bytes
  SHA-256 checksum 12b6a1e7410d02d0b7ae38ca4d24ce39bb2088bf0c32aacb6d566ca4c960cb03
  Compiled from "GHPullRequestCommitDetail.java"
public class org.kohsuke.github.GHPullRequestCommitDetail
  minor version: 0
  major version: 52
  flags: (0x0021) ACC_PUBLIC, ACC_SUPER
  this_class: #12                         // org/kohsuke/github/GHPullRequestCommitDetail
  super_class: #13                        // java/lang/Object
  interfaces: 0, fields: 7, methods: 8, attributes: 3
Constant pool:
   #1 = Methodref          #13.#64        // java/lang/Object."<init>":()V
   #2 = Fieldref           #12.#65        // org/kohsuke/github/GHPullRequestCommitDetail.owner:Lorg/kohsuke/github/GHPullRequest;
   #3 = Fieldref           #12.#66        // org/kohsuke/github/GHPullRequestCommitDetail.sha:Ljava/lang/String;
   #4 = Fieldref           #12.#67        // org/kohsuke/github/GHPullRequestCommitDetail.commit:Lorg/kohsuke/github/GHPullRequestCommitDetail$Commit;
   #5 = Fieldref           #12.#68        // org/kohsuke/github/GHPullRequestCommitDetail.url:Ljava/lang/String;
   #6 = Methodref          #69.#70        // org/kohsuke/github/GitHubClient.parseURL:(Ljava/lang/String;)Ljava/net/URL;
   #7 = Fieldref           #12.#71        // org/kohsuke/github/GHPullRequestCommitDetail.html_url:Ljava/lang/String;
   #8 = Fieldref           #12.#72        // org/kohsuke/github/GHPullRequestCommitDetail.comments_url:Ljava/lang/String;
   #9 = Fieldref           #12.#73        // org/kohsuke/github/GHPullRequestCommitDetail.parents:[Lorg/kohsuke/github/GHPullRequestCommitDetail$CommitPointer;
  #10 = Class              #74            // org/kohsuke/github/GHPullRequestCommitDetail$CommitPointer
  #11 = Methodref          #75.#76        // java/lang/System.arraycopy:(Ljava/lang/Object;ILjava/lang/Object;II)V
  #12 = Class              #77            // org/kohsuke/github/GHPullRequestCommitDetail
  #13 = Class              #78            // java/lang/Object
  #14 = Utf8               CommitPointer
  #15 = Utf8               InnerClasses
  #16 = Class              #79            // org/kohsuke/github/GHPullRequestCommitDetail$Commit
  #17 = Utf8               Commit
  #18 = Class              #80            // org/kohsuke/github/GHPullRequestCommitDetail$Tree
  #19 = Utf8               Tree
  #20 = Class              #81            // org/kohsuke/github/GHPullRequestCommitDetail$Authorship
  #21 = Utf8               Authorship
  #22 = Utf8               owner
  #23 = Utf8               Lorg/kohsuke/github/GHPullRequest;
  #24 = Utf8               sha
  #25 = Utf8               Ljava/lang/String;
  #26 = Utf8               commit
  #27 = Utf8               Lorg/kohsuke/github/GHPullRequestCommitDetail$Commit;
  #28 = Utf8               url
  #29 = Utf8               html_url
  #30 = Utf8               comments_url
  #31 = Utf8               parents
  #32 = Utf8               [Lorg/kohsuke/github/GHPullRequestCommitDetail$CommitPointer;
  #33 = Utf8               <init>
  #34 = Utf8               ()V
  #35 = Utf8               Code
  #36 = Utf8               LineNumberTable
  #37 = Utf8               LocalVariableTable
  #38 = Utf8               this
  #39 = Utf8               Lorg/kohsuke/github/GHPullRequestCommitDetail;
  #40 = Utf8               wrapUp
  #41 = Utf8               (Lorg/kohsuke/github/GHPullRequest;)V
  #42 = Utf8               getSha
  #43 = Utf8               ()Ljava/lang/String;
  #44 = Utf8               getCommit
  #45 = Utf8               ()Lorg/kohsuke/github/GHPullRequestCommitDetail$Commit;
  #46 = Utf8               getApiUrl
  #47 = Utf8               ()Ljava/net/URL;
  #48 = Utf8               getUrl
  #49 = Utf8               getCommentsUrl
  #50 = Utf8               getParents
  #51 = Utf8               ()[Lorg/kohsuke/github/GHPullRequestCommitDetail$CommitPointer;
  #52 = Utf8               newValue
  #53 = Utf8               SourceFile
  #54 = Utf8               GHPullRequestCommitDetail.java
  #55 = Utf8               RuntimeInvisibleAnnotations
  #56 = Utf8               Ledu/umd/cs/findbugs/annotations/SuppressFBWarnings;
  #57 = Utf8               value
  #58 = Utf8               UWF_UNWRITTEN_PUBLIC_OR_PROTECTED_FIELD
  #59 = Utf8               UWF_UNWRITTEN_FIELD
  #60 = Utf8               NP_UNWRITTEN_FIELD
  #61 = Utf8               URF_UNREAD_FIELD
  #62 = Utf8               justification
  #63 = Utf8               JSON API
  #64 = NameAndType        #33:#34        // "<init>":()V
  #65 = NameAndType        #22:#23        // owner:Lorg/kohsuke/github/GHPullRequest;
  #66 = NameAndType        #24:#25        // sha:Ljava/lang/String;
  #67 = NameAndType        #26:#27        // commit:Lorg/kohsuke/github/GHPullRequestCommitDetail$Commit;
  #68 = NameAndType        #28:#25        // url:Ljava/lang/String;
  #69 = Class              #82            // org/kohsuke/github/GitHubClient
  #70 = NameAndType        #83:#84        // parseURL:(Ljava/lang/String;)Ljava/net/URL;
  #71 = NameAndType        #29:#25        // html_url:Ljava/lang/String;
  #72 = NameAndType        #30:#25        // comments_url:Ljava/lang/String;
  #73 = NameAndType        #31:#32        // parents:[Lorg/kohsuke/github/GHPullRequestCommitDetail$CommitPointer;
  #74 = Utf8               org/kohsuke/github/GHPullRequestCommitDetail$CommitPointer
  #75 = Class              #85            // java/lang/System
  #76 = NameAndType        #86:#87        // arraycopy:(Ljava/lang/Object;ILjava/lang/Object;II)V
  #77 = Utf8               org/kohsuke/github/GHPullRequestCommitDetail
  #78 = Utf8               java/lang/Object
  #79 = Utf8               org/kohsuke/github/GHPullRequestCommitDetail$Commit
  #80 = Utf8               org/kohsuke/github/GHPullRequestCommitDetail$Tree
  #81 = Utf8               org/kohsuke/github/GHPullRequestCommitDetail$Authorship
  #82 = Utf8               org/kohsuke/github/GitHubClient
  #83 = Utf8               parseURL
  #84 = Utf8               (Ljava/lang/String;)Ljava/net/URL;
  #85 = Utf8               java/lang/System
  #86 = Utf8               arraycopy
  #87 = Utf8               (Ljava/lang/Object;ILjava/lang/Object;II)V
{
  private org.kohsuke.github.GHPullRequest owner;
    descriptor: Lorg/kohsuke/github/GHPullRequest;
    flags: (0x0002) ACC_PRIVATE

  java.lang.String sha;
    descriptor: Ljava/lang/String;
    flags: (0x0000)

  org.kohsuke.github.GHPullRequestCommitDetail$Commit commit;
    descriptor: Lorg/kohsuke/github/GHPullRequestCommitDetail$Commit;
    flags: (0x0000)

  java.lang.String url;
    descriptor: Ljava/lang/String;
    flags: (0x0000)

  java.lang.String html_url;
    descriptor: Ljava/lang/String;
    flags: (0x0000)

  java.lang.String comments_url;
    descriptor: Ljava/lang/String;
    flags: (0x0000)

  org.kohsuke.github.GHPullRequestCommitDetail$CommitPointer[] parents;
    descriptor: [Lorg/kohsuke/github/GHPullRequestCommitDetail$CommitPointer;
    flags: (0x0000)

  public org.kohsuke.github.GHPullRequestCommitDetail();
    descriptor: ()V
    flags: (0x0001) ACC_PUBLIC
    Code:
      stack=1, locals=1, args_size=1
         0: aload_0
         1: invokespecial #1                  // Method java/lang/Object."<init>":()V
         4: return
      LineNumberTable:
        line 41: 0
      LocalVariableTable:
        Start  Length  Slot  Name   Signature
            0       5     0  this   Lorg/kohsuke/github/GHPullRequestCommitDetail;

  void wrapUp(org.kohsuke.github.GHPullRequest);
    descriptor: (Lorg/kohsuke/github/GHPullRequest;)V
    flags: (0x0000)
    Code:
      stack=2, locals=2, args_size=2
         0: aload_0
         1: aload_1
         2: putfield      #2                  // Field owner:Lorg/kohsuke/github/GHPullRequest;
         5: return
      LineNumberTable:
        line 45: 0
        line 46: 5
      LocalVariableTable:
        Start  Length  Slot  Name   Signature
            0       6     0  this   Lorg/kohsuke/github/GHPullRequestCommitDetail;
            0       6     1 owner   Lorg/kohsuke/github/GHPullRequest;

  public java.lang.String getSha();
    descriptor: ()Ljava/lang/String;
    flags: (0x0001) ACC_PUBLIC
    Code:
      stack=1, locals=1, args_size=1
         0: aload_0
         1: getfield      #3                  // Field sha:Ljava/lang/String;
         4: areturn
      LineNumberTable:
        line 199: 0
      LocalVariableTable:
        Start  Length  Slot  Name   Signature
            0       5     0  this   Lorg/kohsuke/github/GHPullRequestCommitDetail;

  public org.kohsuke.github.GHPullRequestCommitDetail$Commit getCommit();
    descriptor: ()Lorg/kohsuke/github/GHPullRequestCommitDetail$Commit;
    flags: (0x0001) ACC_PUBLIC
    Code:
      stack=1, locals=1, args_size=1
         0: aload_0
         1: getfield      #4                  // Field commit:Lorg/kohsuke/github/GHPullRequestCommitDetail$Commit;
         4: areturn
      LineNumberTable:
        line 208: 0
      LocalVariableTable:
        Start  Length  Slot  Name   Signature
            0       5     0  this   Lorg/kohsuke/github/GHPullRequestCommitDetail;

  public java.net.URL getApiUrl();
    descriptor: ()Ljava/net/URL;
    flags: (0x0001) ACC_PUBLIC
    Code:
      stack=1, locals=1, args_size=1
         0: aload_0
         1: getfield      #5                  // Field url:Ljava/lang/String;
         4: invokestatic  #6                  // Method org/kohsuke/github/GitHubClient.parseURL:(Ljava/lang/String;)Ljava/net/URL;
         7: areturn
      LineNumberTable:
        line 217: 0
      LocalVariableTable:
        Start  Length  Slot  Name   Signature
            0       8     0  this   Lorg/kohsuke/github/GHPullRequestCommitDetail;

  public java.net.URL getUrl();
    descriptor: ()Ljava/net/URL;
    flags: (0x0001) ACC_PUBLIC
    Code:
      stack=1, locals=1, args_size=1
         0: aload_0
         1: getfield      #7                  // Field html_url:Ljava/lang/String;
         4: invokestatic  #6                  // Method org/kohsuke/github/GitHubClient.parseURL:(Ljava/lang/String;)Ljava/net/URL;
         7: areturn
      LineNumberTable:
        line 226: 0
      LocalVariableTable:
        Start  Length  Slot  Name   Signature
            0       8     0  this   Lorg/kohsuke/github/GHPullRequestCommitDetail;

  public java.net.URL getCommentsUrl();
    descriptor: ()Ljava/net/URL;
    flags: (0x0001) ACC_PUBLIC
    Code:
      stack=1, locals=1, args_size=1
         0: aload_0
         1: getfield      #8                  // Field comments_url:Ljava/lang/String;
         4: invokestatic  #6                  // Method org/kohsuke/github/GitHubClient.parseURL:(Ljava/lang/String;)Ljava/net/URL;
         7: areturn
      LineNumberTable:
        line 235: 0
      LocalVariableTable:
        Start  Length  Slot  Name   Signature
            0       8     0  this   Lorg/kohsuke/github/GHPullRequestCommitDetail;

  public org.kohsuke.github.GHPullRequestCommitDetail$CommitPointer[] getParents();
    descriptor: ()[Lorg/kohsuke/github/GHPullRequestCommitDetail$CommitPointer;
    flags: (0x0001) ACC_PUBLIC
    Code:
      stack=5, locals=2, args_size=1
         0: aload_0
         1: getfield      #9                  // Field parents:[Lorg/kohsuke/github/GHPullRequestCommitDetail$CommitPointer;
         4: arraylength
         5: anewarray     #10                 // class org/kohsuke/github/GHPullRequestCommitDetail$CommitPointer
         8: astore_1
         9: aload_0
        10: getfield      #9                  // Field parents:[Lorg/kohsuke/github/GHPullRequestCommitDetail$CommitPointer;
        13: iconst_0
        14: aload_1
        15: iconst_0
        16: aload_0
        17: getfield      #9                  // Field parents:[Lorg/kohsuke/github/GHPullRequestCommitDetail$CommitPointer;
        20: arraylength
        21: invokestatic  #11                 // Method java/lang/System.arraycopy:(Ljava/lang/Object;ILjava/lang/Object;II)V
        24: aload_1
        25: areturn
      LineNumberTable:
        line 244: 0
        line 245: 9
        line 246: 24
      LocalVariableTable:
        Start  Length  Slot  Name   Signature
            0      26     0  this   Lorg/kohsuke/github/GHPullRequestCommitDetail;
            9      17     1 newValue   [Lorg/kohsuke/github/GHPullRequestCommitDetail$CommitPointer;
}
SourceFile: "GHPullRequestCommitDetail.java"
RuntimeInvisibleAnnotations:
  0: #56(#57=[s#58,s#59,s#60,s#61],#62=s#63)
    edu.umd.cs.findbugs.annotations.SuppressFBWarnings(
      value=["UWF_UNWRITTEN_PUBLIC_OR_PROTECTED_FIELD","UWF_UNWRITTEN_FIELD","NP_UNWRITTEN_FIELD","URF_UNREAD_FIELD"]
      justification="JSON API"
    )
InnerClasses:
  public static #14= #10 of #12;          // CommitPointer=class org/kohsuke/github/GHPullRequestCommitDetail$CommitPointer of class org/kohsuke/github/GHPullRequestCommitDetail
  public static #17= #16 of #12;          // Commit=class org/kohsuke/github/GHPullRequestCommitDetail$Commit of class org/kohsuke/github/GHPullRequestCommitDetail
  public static #19= #18 of #12;          // Tree=class org/kohsuke/github/GHPullRequestCommitDetail$Tree of class org/kohsuke/github/GHPullRequestCommitDetail
  public static #21= #20 of #12;          // Authorship=class org/kohsuke/github/GHPullRequestCommitDetail$Authorship of class org/kohsuke/github/GHPullRequestCommitDetail
