Classfile /Users/mw/Projects/slang-braindump/.jar/jar8/assemble/slang-braindump/assemble/content/org/kohsuke/github/GHPullRequestQueryBuilder.class
  Last modified May 29, 2022; size 4101 bytes
  SHA-256 checksum dde205e531985b854ff3ca4d06dc8963c5df07a0c5fff3ea5487346c8cb00e1d
  Compiled from "GHPullRequestQueryBuilder.java"
public class org.kohsuke.github.GHPullRequestQueryBuilder extends org.kohsuke.github.GHQueryBuilder<org.kohsuke.github.GHPullRequest>
  minor version: 0
  major version: 52
  flags: (0x0021) ACC_PUBLIC, ACC_SUPER
  this_class: #30                         // org/kohsuke/github/GHPullRequestQueryBuilder
  super_class: #31                        // org/kohsuke/github/GHQueryBuilder
  interfaces: 0, fields: 1, methods: 8, attributes: 4
Constant pool:
    #1 = Methodref          #70.#71       // org/kohsuke/github/GHRepository.root:()Lorg/kohsuke/github/GitHub;
    #2 = Methodref          #31.#72       // org/kohsuke/github/GHQueryBuilder."<init>":(Lorg/kohsuke/github/GitHub;)V
    #3 = Fieldref           #30.#73       // org/kohsuke/github/GHPullRequestQueryBuilder.repo:Lorg/kohsuke/github/GHRepository;
    #4 = Fieldref           #30.#74       // org/kohsuke/github/GHPullRequestQueryBuilder.req:Lorg/kohsuke/github/Requester;
    #5 = String             #44           // state
    #6 = Methodref          #21.#75       // org/kohsuke/github/Requester.with:(Ljava/lang/String;Ljava/lang/Enum;)Lorg/kohsuke/github/GitHubRequest$Builder;
    #7 = String             #76           // :
    #8 = Methodref          #24.#77       // java/lang/String.contains:(Ljava/lang/CharSequence;)Z
    #9 = Class              #78           // java/lang/StringBuilder
   #10 = Methodref          #9.#79        // java/lang/StringBuilder."<init>":()V
   #11 = Methodref          #70.#80       // org/kohsuke/github/GHRepository.getOwnerName:()Ljava/lang/String;
   #12 = Methodref          #9.#81        // java/lang/StringBuilder.append:(Ljava/lang/String;)Ljava/lang/StringBuilder;
   #13 = Methodref          #9.#82        // java/lang/StringBuilder.toString:()Ljava/lang/String;
   #14 = String             #47           // head
   #15 = Methodref          #21.#83       // org/kohsuke/github/Requester.with:(Ljava/lang/String;Ljava/lang/String;)Lorg/kohsuke/github/GitHubRequest$Builder;
   #16 = String             #51           // base
   #17 = String             #52           // sort
   #18 = String             #55           // direction
   #19 = Fieldref           #84.#85       // org/kohsuke/github/internal/Previews.SHADOW_CAT:Lorg/kohsuke/github/internal/Previews;
   #20 = Methodref          #21.#86       // org/kohsuke/github/Requester.withPreview:(Lorg/kohsuke/github/internal/Previews;)Lorg/kohsuke/github/GitHubRequest$Builder;
   #21 = Class              #87           // org/kohsuke/github/Requester
   #22 = String             #88           // pulls
   #23 = Methodref          #70.#89       // org/kohsuke/github/GHRepository.getApiTailUrl:(Ljava/lang/String;)Ljava/lang/String;
   #24 = Class              #90           // java/lang/String
   #25 = Methodref          #21.#91       // org/kohsuke/github/Requester.withUrlPath:(Ljava/lang/String;[Ljava/lang/String;)Lorg/kohsuke/github/GitHubRequest$Builder;
   #26 = Class              #92           // "[Lorg/kohsuke/github/GHPullRequest;"
   #27 = InvokeDynamic      #0:#98        // #0:accept:(Lorg/kohsuke/github/GHPullRequestQueryBuilder;)Ljava/util/function/Consumer;
   #28 = Methodref          #21.#99       // org/kohsuke/github/Requester.toIterable:(Ljava/lang/Class;Ljava/util/function/Consumer;)Lorg/kohsuke/github/PagedIterable;
   #29 = Methodref          #100.#101     // org/kohsuke/github/GHPullRequest.wrapUp:(Lorg/kohsuke/github/GHRepository;)Lorg/kohsuke/github/GHPullRequest;
   #30 = Class              #102          // org/kohsuke/github/GHPullRequestQueryBuilder
   #31 = Class              #103          // org/kohsuke/github/GHQueryBuilder
   #32 = Class              #104          // org/kohsuke/github/GHPullRequestQueryBuilder$Sort
   #33 = Utf8               Sort
   #34 = Utf8               InnerClasses
   #35 = Utf8               repo
   #36 = Utf8               Lorg/kohsuke/github/GHRepository;
   #37 = Utf8               <init>
   #38 = Utf8               (Lorg/kohsuke/github/GHRepository;)V
   #39 = Utf8               Code
   #40 = Utf8               LineNumberTable
   #41 = Utf8               LocalVariableTable
   #42 = Utf8               this
   #43 = Utf8               Lorg/kohsuke/github/GHPullRequestQueryBuilder;
   #44 = Utf8               state
   #45 = Utf8               (Lorg/kohsuke/github/GHIssueState;)Lorg/kohsuke/github/GHPullRequestQueryBuilder;
   #46 = Utf8               Lorg/kohsuke/github/GHIssueState;
   #47 = Utf8               head
   #48 = Utf8               (Ljava/lang/String;)Lorg/kohsuke/github/GHPullRequestQueryBuilder;
   #49 = Utf8               Ljava/lang/String;
   #50 = Utf8               StackMapTable
   #51 = Utf8               base
   #52 = Utf8               sort
   #53 = Utf8               (Lorg/kohsuke/github/GHPullRequestQueryBuilder$Sort;)Lorg/kohsuke/github/GHPullRequestQueryBuilder;
   #54 = Utf8               Lorg/kohsuke/github/GHPullRequestQueryBuilder$Sort;
   #55 = Utf8               direction
   #56 = Utf8               (Lorg/kohsuke/github/GHDirection;)Lorg/kohsuke/github/GHPullRequestQueryBuilder;
   #57 = Utf8               d
   #58 = Utf8               Lorg/kohsuke/github/GHDirection;
   #59 = Utf8               list
   #60 = Utf8               ()Lorg/kohsuke/github/PagedIterable;
   #61 = Utf8               Signature
   #62 = Utf8               ()Lorg/kohsuke/github/PagedIterable<Lorg/kohsuke/github/GHPullRequest;>;
   #63 = Utf8               lambda$list$0
   #64 = Utf8               (Lorg/kohsuke/github/GHPullRequest;)V
   #65 = Utf8               item
   #66 = Utf8               Lorg/kohsuke/github/GHPullRequest;
   #67 = Utf8               Lorg/kohsuke/github/GHQueryBuilder<Lorg/kohsuke/github/GHPullRequest;>;
   #68 = Utf8               SourceFile
   #69 = Utf8               GHPullRequestQueryBuilder.java
   #70 = Class              #105          // org/kohsuke/github/GHRepository
   #71 = NameAndType        #106:#107     // root:()Lorg/kohsuke/github/GitHub;
   #72 = NameAndType        #37:#108      // "<init>":(Lorg/kohsuke/github/GitHub;)V
   #73 = NameAndType        #35:#36       // repo:Lorg/kohsuke/github/GHRepository;
   #74 = NameAndType        #109:#110     // req:Lorg/kohsuke/github/Requester;
   #75 = NameAndType        #111:#114     // with:(Ljava/lang/String;Ljava/lang/Enum;)Lorg/kohsuke/github/GitHubRequest$Builder;
   #76 = Utf8               :
   #77 = NameAndType        #115:#116     // contains:(Ljava/lang/CharSequence;)Z
   #78 = Utf8               java/lang/StringBuilder
   #79 = NameAndType        #37:#117      // "<init>":()V
   #80 = NameAndType        #118:#119     // getOwnerName:()Ljava/lang/String;
   #81 = NameAndType        #120:#121     // append:(Ljava/lang/String;)Ljava/lang/StringBuilder;
   #82 = NameAndType        #122:#119     // toString:()Ljava/lang/String;
   #83 = NameAndType        #111:#123     // with:(Ljava/lang/String;Ljava/lang/String;)Lorg/kohsuke/github/GitHubRequest$Builder;
   #84 = Class              #124          // org/kohsuke/github/internal/Previews
   #85 = NameAndType        #125:#126     // SHADOW_CAT:Lorg/kohsuke/github/internal/Previews;
   #86 = NameAndType        #127:#128     // withPreview:(Lorg/kohsuke/github/internal/Previews;)Lorg/kohsuke/github/GitHubRequest$Builder;
   #87 = Utf8               org/kohsuke/github/Requester
   #88 = Utf8               pulls
   #89 = NameAndType        #129:#130     // getApiTailUrl:(Ljava/lang/String;)Ljava/lang/String;
   #90 = Utf8               java/lang/String
   #91 = NameAndType        #131:#132     // withUrlPath:(Ljava/lang/String;[Ljava/lang/String;)Lorg/kohsuke/github/GitHubRequest$Builder;
   #92 = Utf8               [Lorg/kohsuke/github/GHPullRequest;
   #93 = Utf8               BootstrapMethods
   #94 = MethodHandle       6:#133        // REF_invokeStatic java/lang/invoke/LambdaMetafactory.metafactory:(Ljava/lang/invoke/MethodHandles$Lookup;Ljava/lang/String;Ljava/lang/invoke/MethodType;Ljava/lang/invoke/MethodType;Ljava/lang/invoke/MethodHandle;Ljava/lang/invoke/MethodType;)Ljava/lang/invoke/CallSite;
   #95 = MethodType         #134          //  (Ljava/lang/Object;)V
   #96 = MethodHandle       7:#135        // REF_invokeSpecial org/kohsuke/github/GHPullRequestQueryBuilder.lambda$list$0:(Lorg/kohsuke/github/GHPullRequest;)V
   #97 = MethodType         #64           //  (Lorg/kohsuke/github/GHPullRequest;)V
   #98 = NameAndType        #136:#137     // accept:(Lorg/kohsuke/github/GHPullRequestQueryBuilder;)Ljava/util/function/Consumer;
   #99 = NameAndType        #138:#139     // toIterable:(Ljava/lang/Class;Ljava/util/function/Consumer;)Lorg/kohsuke/github/PagedIterable;
  #100 = Class              #140          // org/kohsuke/github/GHPullRequest
  #101 = NameAndType        #141:#142     // wrapUp:(Lorg/kohsuke/github/GHRepository;)Lorg/kohsuke/github/GHPullRequest;
  #102 = Utf8               org/kohsuke/github/GHPullRequestQueryBuilder
  #103 = Utf8               org/kohsuke/github/GHQueryBuilder
  #104 = Utf8               org/kohsuke/github/GHPullRequestQueryBuilder$Sort
  #105 = Utf8               org/kohsuke/github/GHRepository
  #106 = Utf8               root
  #107 = Utf8               ()Lorg/kohsuke/github/GitHub;
  #108 = Utf8               (Lorg/kohsuke/github/GitHub;)V
  #109 = Utf8               req
  #110 = Utf8               Lorg/kohsuke/github/Requester;
  #111 = Utf8               with
  #112 = Class              #144          // org/kohsuke/github/GitHubRequest$Builder
  #113 = Utf8               Builder
  #114 = Utf8               (Ljava/lang/String;Ljava/lang/Enum;)Lorg/kohsuke/github/GitHubRequest$Builder;
  #115 = Utf8               contains
  #116 = Utf8               (Ljava/lang/CharSequence;)Z
  #117 = Utf8               ()V
  #118 = Utf8               getOwnerName
  #119 = Utf8               ()Ljava/lang/String;
  #120 = Utf8               append
  #121 = Utf8               (Ljava/lang/String;)Ljava/lang/StringBuilder;
  #122 = Utf8               toString
  #123 = Utf8               (Ljava/lang/String;Ljava/lang/String;)Lorg/kohsuke/github/GitHubRequest$Builder;
  #124 = Utf8               org/kohsuke/github/internal/Previews
  #125 = Utf8               SHADOW_CAT
  #126 = Utf8               Lorg/kohsuke/github/internal/Previews;
  #127 = Utf8               withPreview
  #128 = Utf8               (Lorg/kohsuke/github/internal/Previews;)Lorg/kohsuke/github/GitHubRequest$Builder;
  #129 = Utf8               getApiTailUrl
  #130 = Utf8               (Ljava/lang/String;)Ljava/lang/String;
  #131 = Utf8               withUrlPath
  #132 = Utf8               (Ljava/lang/String;[Ljava/lang/String;)Lorg/kohsuke/github/GitHubRequest$Builder;
  #133 = Methodref          #145.#146     // java/lang/invoke/LambdaMetafactory.metafactory:(Ljava/lang/invoke/MethodHandles$Lookup;Ljava/lang/String;Ljava/lang/invoke/MethodType;Ljava/lang/invoke/MethodType;Ljava/lang/invoke/MethodHandle;Ljava/lang/invoke/MethodType;)Ljava/lang/invoke/CallSite;
  #134 = Utf8               (Ljava/lang/Object;)V
  #135 = Methodref          #30.#147      // org/kohsuke/github/GHPullRequestQueryBuilder.lambda$list$0:(Lorg/kohsuke/github/GHPullRequest;)V
  #136 = Utf8               accept
  #137 = Utf8               (Lorg/kohsuke/github/GHPullRequestQueryBuilder;)Ljava/util/function/Consumer;
  #138 = Utf8               toIterable
  #139 = Utf8               (Ljava/lang/Class;Ljava/util/function/Consumer;)Lorg/kohsuke/github/PagedIterable;
  #140 = Utf8               org/kohsuke/github/GHPullRequest
  #141 = Utf8               wrapUp
  #142 = Utf8               (Lorg/kohsuke/github/GHRepository;)Lorg/kohsuke/github/GHPullRequest;
  #143 = Class              #148          // org/kohsuke/github/GitHubRequest
  #144 = Utf8               org/kohsuke/github/GitHubRequest$Builder
  #145 = Class              #149          // java/lang/invoke/LambdaMetafactory
  #146 = NameAndType        #150:#153     // metafactory:(Ljava/lang/invoke/MethodHandles$Lookup;Ljava/lang/String;Ljava/lang/invoke/MethodType;Ljava/lang/invoke/MethodType;Ljava/lang/invoke/MethodHandle;Ljava/lang/invoke/MethodType;)Ljava/lang/invoke/CallSite;
  #147 = NameAndType        #63:#64       // lambda$list$0:(Lorg/kohsuke/github/GHPullRequest;)V
  #148 = Utf8               org/kohsuke/github/GitHubRequest
  #149 = Utf8               java/lang/invoke/LambdaMetafactory
  #150 = Utf8               metafactory
  #151 = Class              #155          // java/lang/invoke/MethodHandles$Lookup
  #152 = Utf8               Lookup
  #153 = Utf8               (Ljava/lang/invoke/MethodHandles$Lookup;Ljava/lang/String;Ljava/lang/invoke/MethodType;Ljava/lang/invoke/MethodType;Ljava/lang/invoke/MethodHandle;Ljava/lang/invoke/MethodType;)Ljava/lang/invoke/CallSite;
  #154 = Class              #156          // java/lang/invoke/MethodHandles
  #155 = Utf8               java/lang/invoke/MethodHandles$Lookup
  #156 = Utf8               java/lang/invoke/MethodHandles
{
  private final org.kohsuke.github.GHRepository repo;
    descriptor: Lorg/kohsuke/github/GHRepository;
    flags: (0x0012) ACC_PRIVATE, ACC_FINAL

  org.kohsuke.github.GHPullRequestQueryBuilder(org.kohsuke.github.GHRepository);
    descriptor: (Lorg/kohsuke/github/GHRepository;)V
    flags: (0x0000)
    Code:
      stack=2, locals=2, args_size=2
         0: aload_0
         1: aload_1
         2: invokevirtual #1                  // Method org/kohsuke/github/GHRepository.root:()Lorg/kohsuke/github/GitHub;
         5: invokespecial #2                  // Method org/kohsuke/github/GHQueryBuilder."<init>":(Lorg/kohsuke/github/GitHub;)V
         8: aload_0
         9: aload_1
        10: putfield      #3                  // Field repo:Lorg/kohsuke/github/GHRepository;
        13: return
      LineNumberTable:
        line 15: 0
        line 16: 8
        line 17: 13
      LocalVariableTable:
        Start  Length  Slot  Name   Signature
            0      14     0  this   Lorg/kohsuke/github/GHPullRequestQueryBuilder;
            0      14     1  repo   Lorg/kohsuke/github/GHRepository;

  public org.kohsuke.github.GHPullRequestQueryBuilder state(org.kohsuke.github.GHIssueState);
    descriptor: (Lorg/kohsuke/github/GHIssueState;)Lorg/kohsuke/github/GHPullRequestQueryBuilder;
    flags: (0x0001) ACC_PUBLIC
    Code:
      stack=3, locals=2, args_size=2
         0: aload_0
         1: getfield      #4                  // Field req:Lorg/kohsuke/github/Requester;
         4: ldc           #5                  // String state
         6: aload_1
         7: invokevirtual #6                  // Method org/kohsuke/github/Requester.with:(Ljava/lang/String;Ljava/lang/Enum;)Lorg/kohsuke/github/GitHubRequest$Builder;
        10: pop
        11: aload_0
        12: areturn
      LineNumberTable:
        line 27: 0
        line 28: 11
      LocalVariableTable:
        Start  Length  Slot  Name   Signature
            0      13     0  this   Lorg/kohsuke/github/GHPullRequestQueryBuilder;
            0      13     1 state   Lorg/kohsuke/github/GHIssueState;

  public org.kohsuke.github.GHPullRequestQueryBuilder head(java.lang.String);
    descriptor: (Ljava/lang/String;)Lorg/kohsuke/github/GHPullRequestQueryBuilder;
    flags: (0x0001) ACC_PUBLIC
    Code:
      stack=3, locals=2, args_size=2
         0: aload_1
         1: ifnull        43
         4: aload_1
         5: ldc           #7                  // String :
         7: invokevirtual #8                  // Method java/lang/String.contains:(Ljava/lang/CharSequence;)Z
        10: ifne          43
        13: new           #9                  // class java/lang/StringBuilder
        16: dup
        17: invokespecial #10                 // Method java/lang/StringBuilder."<init>":()V
        20: aload_0
        21: getfield      #3                  // Field repo:Lorg/kohsuke/github/GHRepository;
        24: invokevirtual #11                 // Method org/kohsuke/github/GHRepository.getOwnerName:()Ljava/lang/String;
        27: invokevirtual #12                 // Method java/lang/StringBuilder.append:(Ljava/lang/String;)Ljava/lang/StringBuilder;
        30: ldc           #7                  // String :
        32: invokevirtual #12                 // Method java/lang/StringBuilder.append:(Ljava/lang/String;)Ljava/lang/StringBuilder;
        35: aload_1
        36: invokevirtual #12                 // Method java/lang/StringBuilder.append:(Ljava/lang/String;)Ljava/lang/StringBuilder;
        39: invokevirtual #13                 // Method java/lang/StringBuilder.toString:()Ljava/lang/String;
        42: astore_1
        43: aload_0
        44: getfield      #4                  // Field req:Lorg/kohsuke/github/Requester;
        47: ldc           #14                 // String head
        49: aload_1
        50: invokevirtual #15                 // Method org/kohsuke/github/Requester.with:(Ljava/lang/String;Ljava/lang/String;)Lorg/kohsuke/github/GitHubRequest$Builder;
        53: pop
        54: aload_0
        55: areturn
      LineNumberTable:
        line 39: 0
        line 40: 13
        line 42: 43
        line 43: 54
      LocalVariableTable:
        Start  Length  Slot  Name   Signature
            0      56     0  this   Lorg/kohsuke/github/GHPullRequestQueryBuilder;
            0      56     1  head   Ljava/lang/String;
      StackMapTable: number_of_entries = 1
        frame_type = 43 /* same */

  public org.kohsuke.github.GHPullRequestQueryBuilder base(java.lang.String);
    descriptor: (Ljava/lang/String;)Lorg/kohsuke/github/GHPullRequestQueryBuilder;
    flags: (0x0001) ACC_PUBLIC
    Code:
      stack=3, locals=2, args_size=2
         0: aload_0
         1: getfield      #4                  // Field req:Lorg/kohsuke/github/Requester;
         4: ldc           #16                 // String base
         6: aload_1
         7: invokevirtual #15                 // Method org/kohsuke/github/Requester.with:(Ljava/lang/String;Ljava/lang/String;)Lorg/kohsuke/github/GitHubRequest$Builder;
        10: pop
        11: aload_0
        12: areturn
      LineNumberTable:
        line 54: 0
        line 55: 11
      LocalVariableTable:
        Start  Length  Slot  Name   Signature
            0      13     0  this   Lorg/kohsuke/github/GHPullRequestQueryBuilder;
            0      13     1  base   Ljava/lang/String;

  public org.kohsuke.github.GHPullRequestQueryBuilder sort(org.kohsuke.github.GHPullRequestQueryBuilder$Sort);
    descriptor: (Lorg/kohsuke/github/GHPullRequestQueryBuilder$Sort;)Lorg/kohsuke/github/GHPullRequestQueryBuilder;
    flags: (0x0001) ACC_PUBLIC
    Code:
      stack=3, locals=2, args_size=2
         0: aload_0
         1: getfield      #4                  // Field req:Lorg/kohsuke/github/Requester;
         4: ldc           #17                 // String sort
         6: aload_1
         7: invokevirtual #6                  // Method org/kohsuke/github/Requester.with:(Ljava/lang/String;Ljava/lang/Enum;)Lorg/kohsuke/github/GitHubRequest$Builder;
        10: pop
        11: aload_0
        12: areturn
      LineNumberTable:
        line 66: 0
        line 67: 11
      LocalVariableTable:
        Start  Length  Slot  Name   Signature
            0      13     0  this   Lorg/kohsuke/github/GHPullRequestQueryBuilder;
            0      13     1  sort   Lorg/kohsuke/github/GHPullRequestQueryBuilder$Sort;

  public org.kohsuke.github.GHPullRequestQueryBuilder direction(org.kohsuke.github.GHDirection);
    descriptor: (Lorg/kohsuke/github/GHDirection;)Lorg/kohsuke/github/GHPullRequestQueryBuilder;
    flags: (0x0001) ACC_PUBLIC
    Code:
      stack=3, locals=2, args_size=2
         0: aload_0
         1: getfield      #4                  // Field req:Lorg/kohsuke/github/Requester;
         4: ldc           #18                 // String direction
         6: aload_1
         7: invokevirtual #6                  // Method org/kohsuke/github/Requester.with:(Ljava/lang/String;Ljava/lang/Enum;)Lorg/kohsuke/github/GitHubRequest$Builder;
        10: pop
        11: aload_0
        12: areturn
      LineNumberTable:
        line 85: 0
        line 86: 11
      LocalVariableTable:
        Start  Length  Slot  Name   Signature
            0      13     0  this   Lorg/kohsuke/github/GHPullRequestQueryBuilder;
            0      13     1     d   Lorg/kohsuke/github/GHDirection;

  public org.kohsuke.github.PagedIterable<org.kohsuke.github.GHPullRequest> list();
    descriptor: ()Lorg/kohsuke/github/PagedIterable;
    flags: (0x0001) ACC_PUBLIC
    Code:
      stack=3, locals=1, args_size=1
         0: aload_0
         1: getfield      #4                  // Field req:Lorg/kohsuke/github/Requester;
         4: getstatic     #19                 // Field org/kohsuke/github/internal/Previews.SHADOW_CAT:Lorg/kohsuke/github/internal/Previews;
         7: invokevirtual #20                 // Method org/kohsuke/github/Requester.withPreview:(Lorg/kohsuke/github/internal/Previews;)Lorg/kohsuke/github/GitHubRequest$Builder;
        10: checkcast     #21                 // class org/kohsuke/github/Requester
        13: aload_0
        14: getfield      #3                  // Field repo:Lorg/kohsuke/github/GHRepository;
        17: ldc           #22                 // String pulls
        19: invokevirtual #23                 // Method org/kohsuke/github/GHRepository.getApiTailUrl:(Ljava/lang/String;)Ljava/lang/String;
        22: iconst_0
        23: anewarray     #24                 // class java/lang/String
        26: invokevirtual #25                 // Method org/kohsuke/github/Requester.withUrlPath:(Ljava/lang/String;[Ljava/lang/String;)Lorg/kohsuke/github/GitHubRequest$Builder;
        29: checkcast     #21                 // class org/kohsuke/github/Requester
        32: ldc           #26                 // class "[Lorg/kohsuke/github/GHPullRequest;"
        34: aload_0
        35: invokedynamic #27,  0             // InvokeDynamic #0:accept:(Lorg/kohsuke/github/GHPullRequestQueryBuilder;)Ljava/util/function/Consumer;
        40: invokevirtual #28                 // Method org/kohsuke/github/Requester.toIterable:(Ljava/lang/Class;Ljava/util/function/Consumer;)Lorg/kohsuke/github/PagedIterable;
        43: areturn
      LineNumberTable:
        line 91: 0
        line 92: 19
        line 93: 40
        line 91: 43
      LocalVariableTable:
        Start  Length  Slot  Name   Signature
            0      44     0  this   Lorg/kohsuke/github/GHPullRequestQueryBuilder;
    Signature: #62                          // ()Lorg/kohsuke/github/PagedIterable<Lorg/kohsuke/github/GHPullRequest;>;

  private void lambda$list$0(org.kohsuke.github.GHPullRequest);
    descriptor: (Lorg/kohsuke/github/GHPullRequest;)V
    flags: (0x1002) ACC_PRIVATE, ACC_SYNTHETIC
    Code:
      stack=2, locals=2, args_size=2
         0: aload_1
         1: aload_0
         2: getfield      #3                  // Field repo:Lorg/kohsuke/github/GHRepository;
         5: invokevirtual #29                 // Method org/kohsuke/github/GHPullRequest.wrapUp:(Lorg/kohsuke/github/GHRepository;)Lorg/kohsuke/github/GHPullRequest;
         8: pop
         9: return
      LineNumberTable:
        line 93: 0
      LocalVariableTable:
        Start  Length  Slot  Name   Signature
            0      10     0  this   Lorg/kohsuke/github/GHPullRequestQueryBuilder;
            0      10     1  item   Lorg/kohsuke/github/GHPullRequest;
}
Signature: #67                          // Lorg/kohsuke/github/GHQueryBuilder<Lorg/kohsuke/github/GHPullRequest;>;
SourceFile: "GHPullRequestQueryBuilder.java"
InnerClasses:
  public static final #33= #32 of #30;    // Sort=class org/kohsuke/github/GHPullRequestQueryBuilder$Sort of class org/kohsuke/github/GHPullRequestQueryBuilder
  static #113= #112 of #143;              // Builder=class org/kohsuke/github/GitHubRequest$Builder of class org/kohsuke/github/GitHubRequest
  public static final #152= #151 of #154; // Lookup=class java/lang/invoke/MethodHandles$Lookup of class java/lang/invoke/MethodHandles
BootstrapMethods:
  0: #94 REF_invokeStatic java/lang/invoke/LambdaMetafactory.metafactory:(Ljava/lang/invoke/MethodHandles$Lookup;Ljava/lang/String;Ljava/lang/invoke/MethodType;Ljava/lang/invoke/MethodType;Ljava/lang/invoke/MethodHandle;Ljava/lang/invoke/MethodType;)Ljava/lang/invoke/CallSite;
    Method arguments:
      #95 (Ljava/lang/Object;)V
      #96 REF_invokeSpecial org/kohsuke/github/GHPullRequestQueryBuilder.lambda$list$0:(Lorg/kohsuke/github/GHPullRequest;)V
      #97 (Lorg/kohsuke/github/GHPullRequest;)V
