Classfile /Users/mw/Projects/slang-braindump/.jar/jar8/assemble/slang-braindump/assemble/content/org/kohsuke/github/GHQueryBuilder.class
  Last modified May 29, 2022; size 1218 bytes
  SHA-256 checksum b5a09bf5ed695fa2c93c7c772b80b2911603a87265788eeb15cc810234436ce0
  Compiled from "GHQueryBuilder.java"
public abstract class org.kohsuke.github.GHQueryBuilder<T extends java.lang.Object> extends org.kohsuke.github.GitHubInteractiveObject
  minor version: 0
  major version: 52
  flags: (0x0421) ACC_PUBLIC, ACC_SUPER, ACC_ABSTRACT
  this_class: #5                          // org/kohsuke/github/GHQueryBuilder
  super_class: #6                         // org/kohsuke/github/GitHubInteractiveObject
  interfaces: 0, fields: 1, methods: 3, attributes: 2
Constant pool:
   #1 = Methodref          #6.#37         // org/kohsuke/github/GitHubInteractiveObject."<init>":(Lorg/kohsuke/github/GitHub;)V
   #2 = Methodref          #38.#39        // org/kohsuke/github/GitHub.createRequest:()Lorg/kohsuke/github/Requester;
   #3 = Fieldref           #5.#40         // org/kohsuke/github/GHQueryBuilder.req:Lorg/kohsuke/github/Requester;
   #4 = Methodref          #6.#41         // org/kohsuke/github/GitHubInteractiveObject.getRoot:()Lorg/kohsuke/github/GitHub;
   #5 = Class              #42            // org/kohsuke/github/GHQueryBuilder
   #6 = Class              #43            // org/kohsuke/github/GitHubInteractiveObject
   #7 = Utf8               req
   #8 = Utf8               Lorg/kohsuke/github/Requester;
   #9 = Utf8               <init>
  #10 = Utf8               (Lorg/kohsuke/github/GitHub;)V
  #11 = Utf8               Code
  #12 = Utf8               LineNumberTable
  #13 = Utf8               LocalVariableTable
  #14 = Utf8               this
  #15 = Utf8               Lorg/kohsuke/github/GHQueryBuilder;
  #16 = Utf8               root
  #17 = Utf8               Lorg/kohsuke/github/GitHub;
  #18 = Utf8               LocalVariableTypeTable
  #19 = Utf8               Lorg/kohsuke/github/GHQueryBuilder<TT;>;
  #20 = Utf8               list
  #21 = Utf8               ()Lorg/kohsuke/github/PagedIterable;
  #22 = Utf8               Signature
  #23 = Utf8               ()Lorg/kohsuke/github/PagedIterable<TT;>;
  #24 = Utf8               getRoot
  #25 = Utf8               ()Lorg/kohsuke/github/GitHub;
  #26 = Utf8               RuntimeVisibleAnnotations
  #27 = Utf8               Ljava/lang/Deprecated;
  #28 = Utf8               RuntimeInvisibleAnnotations
  #29 = Utf8               Ledu/umd/cs/findbugs/annotations/SuppressFBWarnings;
  #30 = Utf8               value
  #31 = Utf8               EI_EXPOSE_REP
  #32 = Utf8               justification
  #33 = Utf8               Expected behavior
  #34 = Utf8               <T:Ljava/lang/Object;>Lorg/kohsuke/github/GitHubInteractiveObject;
  #35 = Utf8               SourceFile
  #36 = Utf8               GHQueryBuilder.java
  #37 = NameAndType        #9:#10         // "<init>":(Lorg/kohsuke/github/GitHub;)V
  #38 = Class              #44            // org/kohsuke/github/GitHub
  #39 = NameAndType        #45:#46        // createRequest:()Lorg/kohsuke/github/Requester;
  #40 = NameAndType        #7:#8          // req:Lorg/kohsuke/github/Requester;
  #41 = NameAndType        #24:#25        // getRoot:()Lorg/kohsuke/github/GitHub;
  #42 = Utf8               org/kohsuke/github/GHQueryBuilder
  #43 = Utf8               org/kohsuke/github/GitHubInteractiveObject
  #44 = Utf8               org/kohsuke/github/GitHub
  #45 = Utf8               createRequest
  #46 = Utf8               ()Lorg/kohsuke/github/Requester;
{
  protected final org.kohsuke.github.Requester req;
    descriptor: Lorg/kohsuke/github/Requester;
    flags: (0x0014) ACC_PROTECTED, ACC_FINAL

  org.kohsuke.github.GHQueryBuilder(org.kohsuke.github.GitHub);
    descriptor: (Lorg/kohsuke/github/GitHub;)V
    flags: (0x0000)
    Code:
      stack=2, locals=2, args_size=2
         0: aload_0
         1: aload_1
         2: invokespecial #1                  // Method org/kohsuke/github/GitHubInteractiveObject."<init>":(Lorg/kohsuke/github/GitHub;)V
         5: aload_0
         6: aload_1
         7: invokevirtual #2                  // Method org/kohsuke/github/GitHub.createRequest:()Lorg/kohsuke/github/Requester;
        10: putfield      #3                  // Field req:Lorg/kohsuke/github/Requester;
        13: return
      LineNumberTable:
        line 14: 0
        line 15: 5
        line 16: 13
      LocalVariableTable:
        Start  Length  Slot  Name   Signature
            0      14     0  this   Lorg/kohsuke/github/GHQueryBuilder;
            0      14     1  root   Lorg/kohsuke/github/GitHub;
      LocalVariableTypeTable:
        Start  Length  Slot  Name   Signature
            0      14     0  this   Lorg/kohsuke/github/GHQueryBuilder<TT;>;

  public abstract org.kohsuke.github.PagedIterable<T> list();
    descriptor: ()Lorg/kohsuke/github/PagedIterable;
    flags: (0x0401) ACC_PUBLIC, ACC_ABSTRACT
    Signature: #23                          // ()Lorg/kohsuke/github/PagedIterable<TT;>;

  public org.kohsuke.github.GitHub getRoot();
    descriptor: ()Lorg/kohsuke/github/GitHub;
    flags: (0x1041) ACC_PUBLIC, ACC_BRIDGE, ACC_SYNTHETIC
    Code:
      stack=1, locals=1, args_size=1
         0: aload_0
         1: invokespecial #4                  // Method org/kohsuke/github/GitHubInteractiveObject.getRoot:()Lorg/kohsuke/github/GitHub;
         4: areturn
      LineNumberTable:
        line 10: 0
      LocalVariableTable:
        Start  Length  Slot  Name   Signature
            0       5     0  this   Lorg/kohsuke/github/GHQueryBuilder;
      LocalVariableTypeTable:
        Start  Length  Slot  Name   Signature
            0       5     0  this   Lorg/kohsuke/github/GHQueryBuilder<TT;>;
    RuntimeVisibleAnnotations:
      0: #27()
        java.lang.Deprecated
    RuntimeInvisibleAnnotations:
      0: #29(#30=[s#31],#32=s#33)
        edu.umd.cs.findbugs.annotations.SuppressFBWarnings(
          value=["EI_EXPOSE_REP"]
          justification="Expected behavior"
        )
}
Signature: #34                          // <T:Ljava/lang/Object;>Lorg/kohsuke/github/GitHubInteractiveObject;
SourceFile: "GHQueryBuilder.java"
