Classfile /Users/mw/Projects/slang-braindump/.jar/jar8/assemble/slang-braindump/assemble/content/org/kohsuke/github/GHRepositorySearchBuilder$Fork.class
  Last modified May 29, 2022; size 1633 bytes
  SHA-256 checksum 6d47874bcbd96d26f94528f58f323419848a18d751c6a6a583d98151c8a089f8
  Compiled from "GHRepositorySearchBuilder.java"
public final class org.kohsuke.github.GHRepositorySearchBuilder$Fork extends java.lang.Enum<org.kohsuke.github.GHRepositorySearchBuilder$Fork>
  minor version: 0
  major version: 52
  flags: (0x4031) ACC_PUBLIC, ACC_FINAL, ACC_SUPER, ACC_ENUM
  this_class: #4                          // org/kohsuke/github/GHRepositorySearchBuilder$Fork
  super_class: #18                        // java/lang/Enum
  interfaces: 0, fields: 5, methods: 5, attributes: 5
Constant pool:
   #1 = Fieldref           #4.#53         // org/kohsuke/github/GHRepositorySearchBuilder$Fork.$VALUES:[Lorg/kohsuke/github/GHRepositorySearchBuilder$Fork;
   #2 = Methodref          #54.#55        // "[Lorg/kohsuke/github/GHRepositorySearchBuilder$Fork;".clone:()Ljava/lang/Object;
   #3 = Class              #28            // "[Lorg/kohsuke/github/GHRepositorySearchBuilder$Fork;"
   #4 = Class              #57            // org/kohsuke/github/GHRepositorySearchBuilder$Fork
   #5 = Methodref          #18.#58        // java/lang/Enum.valueOf:(Ljava/lang/Class;Ljava/lang/String;)Ljava/lang/Enum;
   #6 = Methodref          #18.#59        // java/lang/Enum."<init>":(Ljava/lang/String;I)V
   #7 = Fieldref           #4.#60         // org/kohsuke/github/GHRepositorySearchBuilder$Fork.filterMode:Ljava/lang/String;
   #8 = String             #19            // PARENT_AND_FORKS
   #9 = String             #61            // true
  #10 = Methodref          #4.#62         // org/kohsuke/github/GHRepositorySearchBuilder$Fork."<init>":(Ljava/lang/String;ILjava/lang/String;)V
  #11 = Fieldref           #4.#63         // org/kohsuke/github/GHRepositorySearchBuilder$Fork.PARENT_AND_FORKS:Lorg/kohsuke/github/GHRepositorySearchBuilder$Fork;
  #12 = String             #23            // FORKS_ONLY
  #13 = String             #64            // only
  #14 = Fieldref           #4.#65         // org/kohsuke/github/GHRepositorySearchBuilder$Fork.FORKS_ONLY:Lorg/kohsuke/github/GHRepositorySearchBuilder$Fork;
  #15 = String             #24            // PARENT_ONLY
  #16 = String             #66            //
  #17 = Fieldref           #4.#67         // org/kohsuke/github/GHRepositorySearchBuilder$Fork.PARENT_ONLY:Lorg/kohsuke/github/GHRepositorySearchBuilder$Fork;
  #18 = Class              #68            // java/lang/Enum
  #19 = Utf8               PARENT_AND_FORKS
  #20 = Utf8               Fork
  #21 = Utf8               InnerClasses
  #22 = Utf8               Lorg/kohsuke/github/GHRepositorySearchBuilder$Fork;
  #23 = Utf8               FORKS_ONLY
  #24 = Utf8               PARENT_ONLY
  #25 = Utf8               filterMode
  #26 = Utf8               Ljava/lang/String;
  #27 = Utf8               $VALUES
  #28 = Utf8               [Lorg/kohsuke/github/GHRepositorySearchBuilder$Fork;
  #29 = Utf8               values
  #30 = Utf8               ()[Lorg/kohsuke/github/GHRepositorySearchBuilder$Fork;
  #31 = Utf8               Code
  #32 = Utf8               LineNumberTable
  #33 = Utf8               valueOf
  #34 = Utf8               (Ljava/lang/String;)Lorg/kohsuke/github/GHRepositorySearchBuilder$Fork;
  #35 = Utf8               LocalVariableTable
  #36 = Utf8               name
  #37 = Utf8               <init>
  #38 = Utf8               (Ljava/lang/String;ILjava/lang/String;)V
  #39 = Utf8               this
  #40 = Utf8               mode
  #41 = Utf8               Signature
  #42 = Utf8               (Ljava/lang/String;)V
  #43 = Utf8               toString
  #44 = Utf8               ()Ljava/lang/String;
  #45 = Utf8               <clinit>
  #46 = Utf8               ()V
  #47 = Utf8               Ljava/lang/Enum<Lorg/kohsuke/github/GHRepositorySearchBuilder$Fork;>;
  #48 = Utf8               SourceFile
  #49 = Utf8               GHRepositorySearchBuilder.java
  #50 = Utf8               Deprecated
  #51 = Utf8               RuntimeVisibleAnnotations
  #52 = Utf8               Ljava/lang/Deprecated;
  #53 = NameAndType        #27:#28        // $VALUES:[Lorg/kohsuke/github/GHRepositorySearchBuilder$Fork;
  #54 = Class              #28            // "[Lorg/kohsuke/github/GHRepositorySearchBuilder$Fork;"
  #55 = NameAndType        #69:#70        // clone:()Ljava/lang/Object;
  #56 = Class              #71            // org/kohsuke/github/GHRepositorySearchBuilder
  #57 = Utf8               org/kohsuke/github/GHRepositorySearchBuilder$Fork
  #58 = NameAndType        #33:#72        // valueOf:(Ljava/lang/Class;Ljava/lang/String;)Ljava/lang/Enum;
  #59 = NameAndType        #37:#73        // "<init>":(Ljava/lang/String;I)V
  #60 = NameAndType        #25:#26        // filterMode:Ljava/lang/String;
  #61 = Utf8               true
  #62 = NameAndType        #37:#38        // "<init>":(Ljava/lang/String;ILjava/lang/String;)V
  #63 = NameAndType        #19:#22        // PARENT_AND_FORKS:Lorg/kohsuke/github/GHRepositorySearchBuilder$Fork;
  #64 = Utf8               only
  #65 = NameAndType        #23:#22        // FORKS_ONLY:Lorg/kohsuke/github/GHRepositorySearchBuilder$Fork;
  #66 = Utf8
  #67 = NameAndType        #24:#22        // PARENT_ONLY:Lorg/kohsuke/github/GHRepositorySearchBuilder$Fork;
  #68 = Utf8               java/lang/Enum
  #69 = Utf8               clone
  #70 = Utf8               ()Ljava/lang/Object;
  #71 = Utf8               org/kohsuke/github/GHRepositorySearchBuilder
  #72 = Utf8               (Ljava/lang/Class;Ljava/lang/String;)Ljava/lang/Enum;
  #73 = Utf8               (Ljava/lang/String;I)V
{
  public static final org.kohsuke.github.GHRepositorySearchBuilder$Fork PARENT_AND_FORKS;
    descriptor: Lorg/kohsuke/github/GHRepositorySearchBuilder$Fork;
    flags: (0x4019) ACC_PUBLIC, ACC_STATIC, ACC_FINAL, ACC_ENUM

  public static final org.kohsuke.github.GHRepositorySearchBuilder$Fork FORKS_ONLY;
    descriptor: Lorg/kohsuke/github/GHRepositorySearchBuilder$Fork;
    flags: (0x4019) ACC_PUBLIC, ACC_STATIC, ACC_FINAL, ACC_ENUM

  public static final org.kohsuke.github.GHRepositorySearchBuilder$Fork PARENT_ONLY;
    descriptor: Lorg/kohsuke/github/GHRepositorySearchBuilder$Fork;
    flags: (0x4019) ACC_PUBLIC, ACC_STATIC, ACC_FINAL, ACC_ENUM

  private java.lang.String filterMode;
    descriptor: Ljava/lang/String;
    flags: (0x0002) ACC_PRIVATE

  private static final org.kohsuke.github.GHRepositorySearchBuilder$Fork[] $VALUES;
    descriptor: [Lorg/kohsuke/github/GHRepositorySearchBuilder$Fork;
    flags: (0x101a) ACC_PRIVATE, ACC_STATIC, ACC_FINAL, ACC_SYNTHETIC

  public static org.kohsuke.github.GHRepositorySearchBuilder$Fork[] values();
    descriptor: ()[Lorg/kohsuke/github/GHRepositorySearchBuilder$Fork;
    flags: (0x0009) ACC_PUBLIC, ACC_STATIC
    Code:
      stack=1, locals=0, args_size=0
         0: getstatic     #1                  // Field $VALUES:[Lorg/kohsuke/github/GHRepositorySearchBuilder$Fork;
         3: invokevirtual #2                  // Method "[Lorg/kohsuke/github/GHRepositorySearchBuilder$Fork;".clone:()Ljava/lang/Object;
         6: checkcast     #3                  // class "[Lorg/kohsuke/github/GHRepositorySearchBuilder$Fork;"
         9: areturn
      LineNumberTable:
        line 271: 0

  public static org.kohsuke.github.GHRepositorySearchBuilder$Fork valueOf(java.lang.String);
    descriptor: (Ljava/lang/String;)Lorg/kohsuke/github/GHRepositorySearchBuilder$Fork;
    flags: (0x0009) ACC_PUBLIC, ACC_STATIC
    Code:
      stack=2, locals=1, args_size=1
         0: ldc           #4                  // class org/kohsuke/github/GHRepositorySearchBuilder$Fork
         2: aload_0
         3: invokestatic  #5                  // Method java/lang/Enum.valueOf:(Ljava/lang/Class;Ljava/lang/String;)Ljava/lang/Enum;
         6: checkcast     #4                  // class org/kohsuke/github/GHRepositorySearchBuilder$Fork
         9: areturn
      LineNumberTable:
        line 271: 0
      LocalVariableTable:
        Start  Length  Slot  Name   Signature
            0      10     0  name   Ljava/lang/String;

  private org.kohsuke.github.GHRepositorySearchBuilder$Fork(java.lang.String);
    descriptor: (Ljava/lang/String;ILjava/lang/String;)V
    flags: (0x0002) ACC_PRIVATE
    Code:
      stack=3, locals=4, args_size=4
         0: aload_0
         1: aload_1
         2: iload_2
         3: invokespecial #6                  // Method java/lang/Enum."<init>":(Ljava/lang/String;I)V
         6: aload_0
         7: aload_3
         8: putfield      #7                  // Field filterMode:Ljava/lang/String;
        11: return
      LineNumberTable:
        line 296: 0
        line 297: 6
        line 298: 11
      LocalVariableTable:
        Start  Length  Slot  Name   Signature
            0      12     0  this   Lorg/kohsuke/github/GHRepositorySearchBuilder$Fork;
            0      12     3  mode   Ljava/lang/String;
    Signature: #42                          // (Ljava/lang/String;)V

  public java.lang.String toString();
    descriptor: ()Ljava/lang/String;
    flags: (0x0001) ACC_PUBLIC
    Code:
      stack=1, locals=1, args_size=1
         0: aload_0
         1: getfield      #7                  // Field filterMode:Ljava/lang/String;
         4: areturn
      LineNumberTable:
        line 302: 0
      LocalVariableTable:
        Start  Length  Slot  Name   Signature
            0       5     0  this   Lorg/kohsuke/github/GHRepositorySearchBuilder$Fork;

  static {};
    descriptor: ()V
    flags: (0x0008) ACC_STATIC
    Code:
      stack=5, locals=0, args_size=0
         0: new           #4                  // class org/kohsuke/github/GHRepositorySearchBuilder$Fork
         3: dup
         4: ldc           #8                  // String PARENT_AND_FORKS
         6: iconst_0
         7: ldc           #9                  // String true
         9: invokespecial #10                 // Method "<init>":(Ljava/lang/String;ILjava/lang/String;)V
        12: putstatic     #11                 // Field PARENT_AND_FORKS:Lorg/kohsuke/github/GHRepositorySearchBuilder$Fork;
        15: new           #4                  // class org/kohsuke/github/GHRepositorySearchBuilder$Fork
        18: dup
        19: ldc           #12                 // String FORKS_ONLY
        21: iconst_1
        22: ldc           #13                 // String only
        24: invokespecial #10                 // Method "<init>":(Ljava/lang/String;ILjava/lang/String;)V
        27: putstatic     #14                 // Field FORKS_ONLY:Lorg/kohsuke/github/GHRepositorySearchBuilder$Fork;
        30: new           #4                  // class org/kohsuke/github/GHRepositorySearchBuilder$Fork
        33: dup
        34: ldc           #15                 // String PARENT_ONLY
        36: iconst_2
        37: ldc           #16                 // String
        39: invokespecial #10                 // Method "<init>":(Ljava/lang/String;ILjava/lang/String;)V
        42: putstatic     #17                 // Field PARENT_ONLY:Lorg/kohsuke/github/GHRepositorySearchBuilder$Fork;
        45: iconst_3
        46: anewarray     #4                  // class org/kohsuke/github/GHRepositorySearchBuilder$Fork
        49: dup
        50: iconst_0
        51: getstatic     #11                 // Field PARENT_AND_FORKS:Lorg/kohsuke/github/GHRepositorySearchBuilder$Fork;
        54: aastore
        55: dup
        56: iconst_1
        57: getstatic     #14                 // Field FORKS_ONLY:Lorg/kohsuke/github/GHRepositorySearchBuilder$Fork;
        60: aastore
        61: dup
        62: iconst_2
        63: getstatic     #17                 // Field PARENT_ONLY:Lorg/kohsuke/github/GHRepositorySearchBuilder$Fork;
        66: aastore
        67: putstatic     #1                  // Field $VALUES:[Lorg/kohsuke/github/GHRepositorySearchBuilder$Fork;
        70: return
      LineNumberTable:
        line 279: 0
        line 286: 15
        line 293: 30
        line 271: 45
}
Signature: #47                          // Ljava/lang/Enum<Lorg/kohsuke/github/GHRepositorySearchBuilder$Fork;>;
SourceFile: "GHRepositorySearchBuilder.java"
Deprecated: true
RuntimeVisibleAnnotations:
  0: #52()
    java.lang.Deprecated
InnerClasses:
  public static final #20= #4 of #56;     // Fork=class org/kohsuke/github/GHRepositorySearchBuilder$Fork of class org/kohsuke/github/GHRepositorySearchBuilder
