Classfile /Users/mw/Projects/slang-braindump/.jar/jar8/assemble/slang-braindump/assemble/content/org/kohsuke/github/GHRepositoryDiscussion$Category.class
  Last modified May 29, 2022; size 1635 bytes
  SHA-256 checksum aa613ae2e6864d9157d43308058e083e0e6295896b96b50e3aa2ce5a1d1a9092
  Compiled from "GHRepositoryDiscussion.java"
public class org.kohsuke.github.GHRepositoryDiscussion$Category
  minor version: 0
  major version: 52
  flags: (0x0021) ACC_PUBLIC, ACC_SUPER
  this_class: #13                         // org/kohsuke/github/GHRepositoryDiscussion$Category
  super_class: #14                        // java/lang/Object
  interfaces: 0, fields: 10, methods: 11, attributes: 2
Constant pool:
   #1 = Methodref          #14.#52        // java/lang/Object."<init>":()V
   #2 = Fieldref           #13.#53        // org/kohsuke/github/GHRepositoryDiscussion$Category.id:J
   #3 = Fieldref           #13.#54        // org/kohsuke/github/GHRepositoryDiscussion$Category.nodeId:Ljava/lang/String;
   #4 = Fieldref           #13.#55        // org/kohsuke/github/GHRepositoryDiscussion$Category.repositoryId:J
   #5 = Fieldref           #13.#56        // org/kohsuke/github/GHRepositoryDiscussion$Category.emoji:Ljava/lang/String;
   #6 = Fieldref           #13.#57        // org/kohsuke/github/GHRepositoryDiscussion$Category.name:Ljava/lang/String;
   #7 = Fieldref           #13.#58        // org/kohsuke/github/GHRepositoryDiscussion$Category.description:Ljava/lang/String;
   #8 = Fieldref           #13.#59        // org/kohsuke/github/GHRepositoryDiscussion$Category.createdAt:Ljava/lang/String;
   #9 = Methodref          #60.#61        // org/kohsuke/github/GitHubClient.parseDate:(Ljava/lang/String;)Ljava/util/Date;
  #10 = Fieldref           #13.#62        // org/kohsuke/github/GHRepositoryDiscussion$Category.updatedAt:Ljava/lang/String;
  #11 = Fieldref           #13.#63        // org/kohsuke/github/GHRepositoryDiscussion$Category.slug:Ljava/lang/String;
  #12 = Fieldref           #13.#64        // org/kohsuke/github/GHRepositoryDiscussion$Category.isAnswerable:Z
  #13 = Class              #66            // org/kohsuke/github/GHRepositoryDiscussion$Category
  #14 = Class              #67            // java/lang/Object
  #15 = Utf8               id
  #16 = Utf8               J
  #17 = Utf8               nodeId
  #18 = Utf8               Ljava/lang/String;
  #19 = Utf8               repositoryId
  #20 = Utf8               emoji
  #21 = Utf8               name
  #22 = Utf8               description
  #23 = Utf8               createdAt
  #24 = Utf8               updatedAt
  #25 = Utf8               slug
  #26 = Utf8               isAnswerable
  #27 = Utf8               Z
  #28 = Utf8               <init>
  #29 = Utf8               ()V
  #30 = Utf8               Code
  #31 = Utf8               LineNumberTable
  #32 = Utf8               LocalVariableTable
  #33 = Utf8               this
  #34 = Utf8               Category
  #35 = Utf8               InnerClasses
  #36 = Utf8               Lorg/kohsuke/github/GHRepositoryDiscussion$Category;
  #37 = Utf8               getId
  #38 = Utf8               ()J
  #39 = Utf8               getNodeId
  #40 = Utf8               ()Ljava/lang/String;
  #41 = Utf8               getRepositoryId
  #42 = Utf8               getEmoji
  #43 = Utf8               getName
  #44 = Utf8               getDescription
  #45 = Utf8               getCreatedAt
  #46 = Utf8               ()Ljava/util/Date;
  #47 = Utf8               getUpdatedAt
  #48 = Utf8               getSlug
  #49 = Utf8               ()Z
  #50 = Utf8               SourceFile
  #51 = Utf8               GHRepositoryDiscussion.java
  #52 = NameAndType        #28:#29        // "<init>":()V
  #53 = NameAndType        #15:#16        // id:J
  #54 = NameAndType        #17:#18        // nodeId:Ljava/lang/String;
  #55 = NameAndType        #19:#16        // repositoryId:J
  #56 = NameAndType        #20:#18        // emoji:Ljava/lang/String;
  #57 = NameAndType        #21:#18        // name:Ljava/lang/String;
  #58 = NameAndType        #22:#18        // description:Ljava/lang/String;
  #59 = NameAndType        #23:#18        // createdAt:Ljava/lang/String;
  #60 = Class              #68            // org/kohsuke/github/GitHubClient
  #61 = NameAndType        #69:#70        // parseDate:(Ljava/lang/String;)Ljava/util/Date;
  #62 = NameAndType        #24:#18        // updatedAt:Ljava/lang/String;
  #63 = NameAndType        #25:#18        // slug:Ljava/lang/String;
  #64 = NameAndType        #26:#27        // isAnswerable:Z
  #65 = Class              #71            // org/kohsuke/github/GHRepositoryDiscussion
  #66 = Utf8               org/kohsuke/github/GHRepositoryDiscussion$Category
  #67 = Utf8               java/lang/Object
  #68 = Utf8               org/kohsuke/github/GitHubClient
  #69 = Utf8               parseDate
  #70 = Utf8               (Ljava/lang/String;)Ljava/util/Date;
  #71 = Utf8               org/kohsuke/github/GHRepositoryDiscussion
{
  private long id;
    descriptor: J
    flags: (0x0002) ACC_PRIVATE

  private java.lang.String nodeId;
    descriptor: Ljava/lang/String;
    flags: (0x0002) ACC_PRIVATE

  private long repositoryId;
    descriptor: J
    flags: (0x0002) ACC_PRIVATE

  private java.lang.String emoji;
    descriptor: Ljava/lang/String;
    flags: (0x0002) ACC_PRIVATE

  private java.lang.String name;
    descriptor: Ljava/lang/String;
    flags: (0x0002) ACC_PRIVATE

  private java.lang.String description;
    descriptor: Ljava/lang/String;
    flags: (0x0002) ACC_PRIVATE

  private java.lang.String createdAt;
    descriptor: Ljava/lang/String;
    flags: (0x0002) ACC_PRIVATE

  private java.lang.String updatedAt;
    descriptor: Ljava/lang/String;
    flags: (0x0002) ACC_PRIVATE

  private java.lang.String slug;
    descriptor: Ljava/lang/String;
    flags: (0x0002) ACC_PRIVATE

  private boolean isAnswerable;
    descriptor: Z
    flags: (0x0002) ACC_PRIVATE

  public org.kohsuke.github.GHRepositoryDiscussion$Category();
    descriptor: ()V
    flags: (0x0001) ACC_PUBLIC
    Code:
      stack=1, locals=1, args_size=1
         0: aload_0
         1: invokespecial #1                  // Method java/lang/Object."<init>":()V
         4: return
      LineNumberTable:
        line 113: 0
      LocalVariableTable:
        Start  Length  Slot  Name   Signature
            0       5     0  this   Lorg/kohsuke/github/GHRepositoryDiscussion$Category;

  public long getId();
    descriptor: ()J
    flags: (0x0001) ACC_PUBLIC
    Code:
      stack=2, locals=1, args_size=1
         0: aload_0
         1: getfield      #2                  // Field id:J
         4: lreturn
      LineNumberTable:
        line 127: 0
      LocalVariableTable:
        Start  Length  Slot  Name   Signature
            0       5     0  this   Lorg/kohsuke/github/GHRepositoryDiscussion$Category;

  public java.lang.String getNodeId();
    descriptor: ()Ljava/lang/String;
    flags: (0x0001) ACC_PUBLIC
    Code:
      stack=1, locals=1, args_size=1
         0: aload_0
         1: getfield      #3                  // Field nodeId:Ljava/lang/String;
         4: areturn
      LineNumberTable:
        line 131: 0
      LocalVariableTable:
        Start  Length  Slot  Name   Signature
            0       5     0  this   Lorg/kohsuke/github/GHRepositoryDiscussion$Category;

  public long getRepositoryId();
    descriptor: ()J
    flags: (0x0001) ACC_PUBLIC
    Code:
      stack=2, locals=1, args_size=1
         0: aload_0
         1: getfield      #4                  // Field repositoryId:J
         4: lreturn
      LineNumberTable:
        line 135: 0
      LocalVariableTable:
        Start  Length  Slot  Name   Signature
            0       5     0  this   Lorg/kohsuke/github/GHRepositoryDiscussion$Category;

  public java.lang.String getEmoji();
    descriptor: ()Ljava/lang/String;
    flags: (0x0001) ACC_PUBLIC
    Code:
      stack=1, locals=1, args_size=1
         0: aload_0
         1: getfield      #5                  // Field emoji:Ljava/lang/String;
         4: areturn
      LineNumberTable:
        line 139: 0
      LocalVariableTable:
        Start  Length  Slot  Name   Signature
            0       5     0  this   Lorg/kohsuke/github/GHRepositoryDiscussion$Category;

  public java.lang.String getName();
    descriptor: ()Ljava/lang/String;
    flags: (0x0001) ACC_PUBLIC
    Code:
      stack=1, locals=1, args_size=1
         0: aload_0
         1: getfield      #6                  // Field name:Ljava/lang/String;
         4: areturn
      LineNumberTable:
        line 143: 0
      LocalVariableTable:
        Start  Length  Slot  Name   Signature
            0       5     0  this   Lorg/kohsuke/github/GHRepositoryDiscussion$Category;

  public java.lang.String getDescription();
    descriptor: ()Ljava/lang/String;
    flags: (0x0001) ACC_PUBLIC
    Code:
      stack=1, locals=1, args_size=1
         0: aload_0
         1: getfield      #7                  // Field description:Ljava/lang/String;
         4: areturn
      LineNumberTable:
        line 147: 0
      LocalVariableTable:
        Start  Length  Slot  Name   Signature
            0       5     0  this   Lorg/kohsuke/github/GHRepositoryDiscussion$Category;

  public java.util.Date getCreatedAt();
    descriptor: ()Ljava/util/Date;
    flags: (0x0001) ACC_PUBLIC
    Code:
      stack=1, locals=1, args_size=1
         0: aload_0
         1: getfield      #8                  // Field createdAt:Ljava/lang/String;
         4: invokestatic  #9                  // Method org/kohsuke/github/GitHubClient.parseDate:(Ljava/lang/String;)Ljava/util/Date;
         7: areturn
      LineNumberTable:
        line 151: 0
      LocalVariableTable:
        Start  Length  Slot  Name   Signature
            0       8     0  this   Lorg/kohsuke/github/GHRepositoryDiscussion$Category;

  public java.util.Date getUpdatedAt();
    descriptor: ()Ljava/util/Date;
    flags: (0x0001) ACC_PUBLIC
    Code:
      stack=1, locals=1, args_size=1
         0: aload_0
         1: getfield      #10                 // Field updatedAt:Ljava/lang/String;
         4: invokestatic  #9                  // Method org/kohsuke/github/GitHubClient.parseDate:(Ljava/lang/String;)Ljava/util/Date;
         7: areturn
      LineNumberTable:
        line 155: 0
      LocalVariableTable:
        Start  Length  Slot  Name   Signature
            0       8     0  this   Lorg/kohsuke/github/GHRepositoryDiscussion$Category;

  public java.lang.String getSlug();
    descriptor: ()Ljava/lang/String;
    flags: (0x0001) ACC_PUBLIC
    Code:
      stack=1, locals=1, args_size=1
         0: aload_0
         1: getfield      #11                 // Field slug:Ljava/lang/String;
         4: areturn
      LineNumberTable:
        line 159: 0
      LocalVariableTable:
        Start  Length  Slot  Name   Signature
            0       5     0  this   Lorg/kohsuke/github/GHRepositoryDiscussion$Category;

  public boolean isAnswerable();
    descriptor: ()Z
    flags: (0x0001) ACC_PUBLIC
    Code:
      stack=1, locals=1, args_size=1
         0: aload_0
         1: getfield      #12                 // Field isAnswerable:Z
         4: ireturn
      LineNumberTable:
        line 163: 0
      LocalVariableTable:
        Start  Length  Slot  Name   Signature
            0       5     0  this   Lorg/kohsuke/github/GHRepositoryDiscussion$Category;
}
SourceFile: "GHRepositoryDiscussion.java"
InnerClasses:
  public static #34= #13 of #65;          // Category=class org/kohsuke/github/GHRepositoryDiscussion$Category of class org/kohsuke/github/GHRepositoryDiscussion
