Classfile /Users/mw/Projects/slang-braindump/.jar/jar8/assemble/slang-braindump/assemble/content/org/kohsuke/github/GHReleaseUpdater.class
  Last modified May 29, 2022; size 2860 bytes
  SHA-256 checksum d267ce5469bf82dd9efbb025c5c7b5ee1f5f854046a302a70a9720914ea061af
  Compiled from "GHReleaseUpdater.java"
public class org.kohsuke.github.GHReleaseUpdater
  minor version: 0
  major version: 52
  flags: (0x0021) ACC_PUBLIC, ACC_SUPER
  this_class: #32                         // org/kohsuke/github/GHReleaseUpdater
  super_class: #33                        // java/lang/Object
  interfaces: 0, fields: 2, methods: 9, attributes: 2
Constant pool:
    #1 = Methodref          #33.#62       // java/lang/Object."<init>":()V
    #2 = Fieldref           #32.#63       // org/kohsuke/github/GHReleaseUpdater.base:Lorg/kohsuke/github/GHRelease;
    #3 = Methodref          #29.#64       // org/kohsuke/github/GHRelease.root:()Lorg/kohsuke/github/GitHub;
    #4 = Methodref          #65.#66       // org/kohsuke/github/GitHub.createRequest:()Lorg/kohsuke/github/Requester;
    #5 = Fieldref           #32.#67       // org/kohsuke/github/GHReleaseUpdater.builder:Lorg/kohsuke/github/Requester;
    #6 = String             #68           // tag_name
    #7 = Methodref          #17.#69       // org/kohsuke/github/Requester.with:(Ljava/lang/String;Ljava/lang/String;)Lorg/kohsuke/github/GitHubRequest$Builder;
    #8 = String             #48           // body
    #9 = String             #70           // target_commitish
   #10 = String             #50           // draft
   #11 = Methodref          #17.#71       // org/kohsuke/github/Requester.with:(Ljava/lang/String;Z)Lorg/kohsuke/github/GitHubRequest$Builder;
   #12 = String             #53           // name
   #13 = String             #54           // prerelease
   #14 = String             #72           // discussion_category_name
   #15 = String             #73           // PATCH
   #16 = Methodref          #17.#74       // org/kohsuke/github/Requester.method:(Ljava/lang/String;)Lorg/kohsuke/github/GitHubRequest$Builder;
   #17 = Class              #75           // org/kohsuke/github/Requester
   #18 = Fieldref           #29.#76       // org/kohsuke/github/GHRelease.owner:Lorg/kohsuke/github/GHRepository;
   #19 = Class              #77           // java/lang/StringBuilder
   #20 = Methodref          #19.#62       // java/lang/StringBuilder."<init>":()V
   #21 = String             #78           // releases/
   #22 = Methodref          #19.#79       // java/lang/StringBuilder.append:(Ljava/lang/String;)Ljava/lang/StringBuilder;
   #23 = Methodref          #29.#80       // org/kohsuke/github/GHRelease.getId:()J
   #24 = Methodref          #19.#81       // java/lang/StringBuilder.append:(J)Ljava/lang/StringBuilder;
   #25 = Methodref          #19.#82       // java/lang/StringBuilder.toString:()Ljava/lang/String;
   #26 = Methodref          #83.#84       // org/kohsuke/github/GHRepository.getApiTailUrl:(Ljava/lang/String;)Ljava/lang/String;
   #27 = Class              #85           // java/lang/String
   #28 = Methodref          #17.#86       // org/kohsuke/github/Requester.withUrlPath:(Ljava/lang/String;[Ljava/lang/String;)Lorg/kohsuke/github/GitHubRequest$Builder;
   #29 = Class              #87           // org/kohsuke/github/GHRelease
   #30 = Methodref          #17.#88       // org/kohsuke/github/Requester.fetch:(Ljava/lang/Class;)Ljava/lang/Object;
   #31 = Methodref          #29.#89       // org/kohsuke/github/GHRelease.wrap:(Lorg/kohsuke/github/GHRepository;)Lorg/kohsuke/github/GHRelease;
   #32 = Class              #90           // org/kohsuke/github/GHReleaseUpdater
   #33 = Class              #91           // java/lang/Object
   #34 = Utf8               base
   #35 = Utf8               Lorg/kohsuke/github/GHRelease;
   #36 = Utf8               builder
   #37 = Utf8               Lorg/kohsuke/github/Requester;
   #38 = Utf8               <init>
   #39 = Utf8               (Lorg/kohsuke/github/GHRelease;)V
   #40 = Utf8               Code
   #41 = Utf8               LineNumberTable
   #42 = Utf8               LocalVariableTable
   #43 = Utf8               this
   #44 = Utf8               Lorg/kohsuke/github/GHReleaseUpdater;
   #45 = Utf8               tag
   #46 = Utf8               (Ljava/lang/String;)Lorg/kohsuke/github/GHReleaseUpdater;
   #47 = Utf8               Ljava/lang/String;
   #48 = Utf8               body
   #49 = Utf8               commitish
   #50 = Utf8               draft
   #51 = Utf8               (Z)Lorg/kohsuke/github/GHReleaseUpdater;
   #52 = Utf8               Z
   #53 = Utf8               name
   #54 = Utf8               prerelease
   #55 = Utf8               categoryName
   #56 = Utf8               update
   #57 = Utf8               ()Lorg/kohsuke/github/GHRelease;
   #58 = Utf8               Exceptions
   #59 = Class              #92           // java/io/IOException
   #60 = Utf8               SourceFile
   #61 = Utf8               GHReleaseUpdater.java
   #62 = NameAndType        #38:#93       // "<init>":()V
   #63 = NameAndType        #34:#35       // base:Lorg/kohsuke/github/GHRelease;
   #64 = NameAndType        #94:#95       // root:()Lorg/kohsuke/github/GitHub;
   #65 = Class              #96           // org/kohsuke/github/GitHub
   #66 = NameAndType        #97:#98       // createRequest:()Lorg/kohsuke/github/Requester;
   #67 = NameAndType        #36:#37       // builder:Lorg/kohsuke/github/Requester;
   #68 = Utf8               tag_name
   #69 = NameAndType        #99:#103      // with:(Ljava/lang/String;Ljava/lang/String;)Lorg/kohsuke/github/GitHubRequest$Builder;
   #70 = Utf8               target_commitish
   #71 = NameAndType        #99:#104      // with:(Ljava/lang/String;Z)Lorg/kohsuke/github/GitHubRequest$Builder;
   #72 = Utf8               discussion_category_name
   #73 = Utf8               PATCH
   #74 = NameAndType        #105:#106     // method:(Ljava/lang/String;)Lorg/kohsuke/github/GitHubRequest$Builder;
   #75 = Utf8               org/kohsuke/github/Requester
   #76 = NameAndType        #107:#108     // owner:Lorg/kohsuke/github/GHRepository;
   #77 = Utf8               java/lang/StringBuilder
   #78 = Utf8               releases/
   #79 = NameAndType        #109:#110     // append:(Ljava/lang/String;)Ljava/lang/StringBuilder;
   #80 = NameAndType        #111:#112     // getId:()J
   #81 = NameAndType        #109:#113     // append:(J)Ljava/lang/StringBuilder;
   #82 = NameAndType        #114:#115     // toString:()Ljava/lang/String;
   #83 = Class              #116          // org/kohsuke/github/GHRepository
   #84 = NameAndType        #117:#118     // getApiTailUrl:(Ljava/lang/String;)Ljava/lang/String;
   #85 = Utf8               java/lang/String
   #86 = NameAndType        #119:#120     // withUrlPath:(Ljava/lang/String;[Ljava/lang/String;)Lorg/kohsuke/github/GitHubRequest$Builder;
   #87 = Utf8               org/kohsuke/github/GHRelease
   #88 = NameAndType        #121:#122     // fetch:(Ljava/lang/Class;)Ljava/lang/Object;
   #89 = NameAndType        #123:#124     // wrap:(Lorg/kohsuke/github/GHRepository;)Lorg/kohsuke/github/GHRelease;
   #90 = Utf8               org/kohsuke/github/GHReleaseUpdater
   #91 = Utf8               java/lang/Object
   #92 = Utf8               java/io/IOException
   #93 = Utf8               ()V
   #94 = Utf8               root
   #95 = Utf8               ()Lorg/kohsuke/github/GitHub;
   #96 = Utf8               org/kohsuke/github/GitHub
   #97 = Utf8               createRequest
   #98 = Utf8               ()Lorg/kohsuke/github/Requester;
   #99 = Utf8               with
  #100 = Class              #126          // org/kohsuke/github/GitHubRequest$Builder
  #101 = Utf8               Builder
  #102 = Utf8               InnerClasses
  #103 = Utf8               (Ljava/lang/String;Ljava/lang/String;)Lorg/kohsuke/github/GitHubRequest$Builder;
  #104 = Utf8               (Ljava/lang/String;Z)Lorg/kohsuke/github/GitHubRequest$Builder;
  #105 = Utf8               method
  #106 = Utf8               (Ljava/lang/String;)Lorg/kohsuke/github/GitHubRequest$Builder;
  #107 = Utf8               owner
  #108 = Utf8               Lorg/kohsuke/github/GHRepository;
  #109 = Utf8               append
  #110 = Utf8               (Ljava/lang/String;)Ljava/lang/StringBuilder;
  #111 = Utf8               getId
  #112 = Utf8               ()J
  #113 = Utf8               (J)Ljava/lang/StringBuilder;
  #114 = Utf8               toString
  #115 = Utf8               ()Ljava/lang/String;
  #116 = Utf8               org/kohsuke/github/GHRepository
  #117 = Utf8               getApiTailUrl
  #118 = Utf8               (Ljava/lang/String;)Ljava/lang/String;
  #119 = Utf8               withUrlPath
  #120 = Utf8               (Ljava/lang/String;[Ljava/lang/String;)Lorg/kohsuke/github/GitHubRequest$Builder;
  #121 = Utf8               fetch
  #122 = Utf8               (Ljava/lang/Class;)Ljava/lang/Object;
  #123 = Utf8               wrap
  #124 = Utf8               (Lorg/kohsuke/github/GHRepository;)Lorg/kohsuke/github/GHRelease;
  #125 = Class              #127          // org/kohsuke/github/GitHubRequest
  #126 = Utf8               org/kohsuke/github/GitHubRequest$Builder
  #127 = Utf8               org/kohsuke/github/GitHubRequest
{
  private final org.kohsuke.github.GHRelease base;
    descriptor: Lorg/kohsuke/github/GHRelease;
    flags: (0x0012) ACC_PRIVATE, ACC_FINAL

  private final org.kohsuke.github.Requester builder;
    descriptor: Lorg/kohsuke/github/Requester;
    flags: (0x0012) ACC_PRIVATE, ACC_FINAL

  org.kohsuke.github.GHReleaseUpdater(org.kohsuke.github.GHRelease);
    descriptor: (Lorg/kohsuke/github/GHRelease;)V
    flags: (0x0000)
    Code:
      stack=2, locals=2, args_size=2
         0: aload_0
         1: invokespecial #1                  // Method java/lang/Object."<init>":()V
         4: aload_0
         5: aload_1
         6: putfield      #2                  // Field base:Lorg/kohsuke/github/GHRelease;
         9: aload_0
        10: aload_1
        11: invokevirtual #3                  // Method org/kohsuke/github/GHRelease.root:()Lorg/kohsuke/github/GitHub;
        14: invokevirtual #4                  // Method org/kohsuke/github/GitHub.createRequest:()Lorg/kohsuke/github/Requester;
        17: putfield      #5                  // Field builder:Lorg/kohsuke/github/Requester;
        20: return
      LineNumberTable:
        line 15: 0
        line 16: 4
        line 17: 9
        line 18: 20
      LocalVariableTable:
        Start  Length  Slot  Name   Signature
            0      21     0  this   Lorg/kohsuke/github/GHReleaseUpdater;
            0      21     1  base   Lorg/kohsuke/github/GHRelease;

  public org.kohsuke.github.GHReleaseUpdater tag(java.lang.String);
    descriptor: (Ljava/lang/String;)Lorg/kohsuke/github/GHReleaseUpdater;
    flags: (0x0001) ACC_PUBLIC
    Code:
      stack=3, locals=2, args_size=2
         0: aload_0
         1: getfield      #5                  // Field builder:Lorg/kohsuke/github/Requester;
         4: ldc           #6                  // String tag_name
         6: aload_1
         7: invokevirtual #7                  // Method org/kohsuke/github/Requester.with:(Ljava/lang/String;Ljava/lang/String;)Lorg/kohsuke/github/GitHubRequest$Builder;
        10: pop
        11: aload_0
        12: areturn
      LineNumberTable:
        line 28: 0
        line 29: 11
      LocalVariableTable:
        Start  Length  Slot  Name   Signature
            0      13     0  this   Lorg/kohsuke/github/GHReleaseUpdater;
            0      13     1   tag   Ljava/lang/String;

  public org.kohsuke.github.GHReleaseUpdater body(java.lang.String);
    descriptor: (Ljava/lang/String;)Lorg/kohsuke/github/GHReleaseUpdater;
    flags: (0x0001) ACC_PUBLIC
    Code:
      stack=3, locals=2, args_size=2
         0: aload_0
         1: getfield      #5                  // Field builder:Lorg/kohsuke/github/Requester;
         4: ldc           #8                  // String body
         6: aload_1
         7: invokevirtual #7                  // Method org/kohsuke/github/Requester.with:(Ljava/lang/String;Ljava/lang/String;)Lorg/kohsuke/github/GitHubRequest$Builder;
        10: pop
        11: aload_0
        12: areturn
      LineNumberTable:
        line 40: 0
        line 41: 11
      LocalVariableTable:
        Start  Length  Slot  Name   Signature
            0      13     0  this   Lorg/kohsuke/github/GHReleaseUpdater;
            0      13     1  body   Ljava/lang/String;

  public org.kohsuke.github.GHReleaseUpdater commitish(java.lang.String);
    descriptor: (Ljava/lang/String;)Lorg/kohsuke/github/GHReleaseUpdater;
    flags: (0x0001) ACC_PUBLIC
    Code:
      stack=3, locals=2, args_size=2
         0: aload_0
         1: getfield      #5                  // Field builder:Lorg/kohsuke/github/Requester;
         4: ldc           #9                  // String target_commitish
         6: aload_1
         7: invokevirtual #7                  // Method org/kohsuke/github/Requester.with:(Ljava/lang/String;Ljava/lang/String;)Lorg/kohsuke/github/GitHubRequest$Builder;
        10: pop
        11: aload_0
        12: areturn
      LineNumberTable:
        line 52: 0
        line 53: 11
      LocalVariableTable:
        Start  Length  Slot  Name   Signature
            0      13     0  this   Lorg/kohsuke/github/GHReleaseUpdater;
            0      13     1 commitish   Ljava/lang/String;

  public org.kohsuke.github.GHReleaseUpdater draft(boolean);
    descriptor: (Z)Lorg/kohsuke/github/GHReleaseUpdater;
    flags: (0x0001) ACC_PUBLIC
    Code:
      stack=3, locals=2, args_size=2
         0: aload_0
         1: getfield      #5                  // Field builder:Lorg/kohsuke/github/Requester;
         4: ldc           #10                 // String draft
         6: iload_1
         7: invokevirtual #11                 // Method org/kohsuke/github/Requester.with:(Ljava/lang/String;Z)Lorg/kohsuke/github/GitHubRequest$Builder;
        10: pop
        11: aload_0
        12: areturn
      LineNumberTable:
        line 65: 0
        line 66: 11
      LocalVariableTable:
        Start  Length  Slot  Name   Signature
            0      13     0  this   Lorg/kohsuke/github/GHReleaseUpdater;
            0      13     1 draft   Z

  public org.kohsuke.github.GHReleaseUpdater name(java.lang.String);
    descriptor: (Ljava/lang/String;)Lorg/kohsuke/github/GHReleaseUpdater;
    flags: (0x0001) ACC_PUBLIC
    Code:
      stack=3, locals=2, args_size=2
         0: aload_0
         1: getfield      #5                  // Field builder:Lorg/kohsuke/github/Requester;
         4: ldc           #12                 // String name
         6: aload_1
         7: invokevirtual #7                  // Method org/kohsuke/github/Requester.with:(Ljava/lang/String;Ljava/lang/String;)Lorg/kohsuke/github/GitHubRequest$Builder;
        10: pop
        11: aload_0
        12: areturn
      LineNumberTable:
        line 77: 0
        line 78: 11
      LocalVariableTable:
        Start  Length  Slot  Name   Signature
            0      13     0  this   Lorg/kohsuke/github/GHReleaseUpdater;
            0      13     1  name   Ljava/lang/String;

  public org.kohsuke.github.GHReleaseUpdater prerelease(boolean);
    descriptor: (Z)Lorg/kohsuke/github/GHReleaseUpdater;
    flags: (0x0001) ACC_PUBLIC
    Code:
      stack=3, locals=2, args_size=2
         0: aload_0
         1: getfield      #5                  // Field builder:Lorg/kohsuke/github/Requester;
         4: ldc           #13                 // String prerelease
         6: iload_1
         7: invokevirtual #11                 // Method org/kohsuke/github/Requester.with:(Ljava/lang/String;Z)Lorg/kohsuke/github/GitHubRequest$Builder;
        10: pop
        11: aload_0
        12: areturn
      LineNumberTable:
        line 90: 0
        line 91: 11
      LocalVariableTable:
        Start  Length  Slot  Name   Signature
            0      13     0  this   Lorg/kohsuke/github/GHReleaseUpdater;
            0      13     1 prerelease   Z

  public org.kohsuke.github.GHReleaseUpdater categoryName(java.lang.String);
    descriptor: (Ljava/lang/String;)Lorg/kohsuke/github/GHReleaseUpdater;
    flags: (0x0001) ACC_PUBLIC
    Code:
      stack=3, locals=2, args_size=2
         0: aload_0
         1: getfield      #5                  // Field builder:Lorg/kohsuke/github/Requester;
         4: ldc           #14                 // String discussion_category_name
         6: aload_1
         7: invokevirtual #7                  // Method org/kohsuke/github/Requester.with:(Ljava/lang/String;Ljava/lang/String;)Lorg/kohsuke/github/GitHubRequest$Builder;
        10: pop
        11: aload_0
        12: areturn
      LineNumberTable:
        line 102: 0
        line 103: 11
      LocalVariableTable:
        Start  Length  Slot  Name   Signature
            0      13     0  this   Lorg/kohsuke/github/GHReleaseUpdater;
            0      13     1 categoryName   Ljava/lang/String;

  public org.kohsuke.github.GHRelease update() throws java.io.IOException;
    descriptor: ()Lorg/kohsuke/github/GHRelease;
    flags: (0x0001) ACC_PUBLIC
    Code:
      stack=5, locals=1, args_size=1
         0: aload_0
         1: getfield      #5                  // Field builder:Lorg/kohsuke/github/Requester;
         4: ldc           #15                 // String PATCH
         6: invokevirtual #16                 // Method org/kohsuke/github/Requester.method:(Ljava/lang/String;)Lorg/kohsuke/github/GitHubRequest$Builder;
         9: checkcast     #17                 // class org/kohsuke/github/Requester
        12: aload_0
        13: getfield      #2                  // Field base:Lorg/kohsuke/github/GHRelease;
        16: getfield      #18                 // Field org/kohsuke/github/GHRelease.owner:Lorg/kohsuke/github/GHRepository;
        19: new           #19                 // class java/lang/StringBuilder
        22: dup
        23: invokespecial #20                 // Method java/lang/StringBuilder."<init>":()V
        26: ldc           #21                 // String releases/
        28: invokevirtual #22                 // Method java/lang/StringBuilder.append:(Ljava/lang/String;)Ljava/lang/StringBuilder;
        31: aload_0
        32: getfield      #2                  // Field base:Lorg/kohsuke/github/GHRelease;
        35: invokevirtual #23                 // Method org/kohsuke/github/GHRelease.getId:()J
        38: invokevirtual #24                 // Method java/lang/StringBuilder.append:(J)Ljava/lang/StringBuilder;
        41: invokevirtual #25                 // Method java/lang/StringBuilder.toString:()Ljava/lang/String;
        44: invokevirtual #26                 // Method org/kohsuke/github/GHRepository.getApiTailUrl:(Ljava/lang/String;)Ljava/lang/String;
        47: iconst_0
        48: anewarray     #27                 // class java/lang/String
        51: invokevirtual #28                 // Method org/kohsuke/github/Requester.withUrlPath:(Ljava/lang/String;[Ljava/lang/String;)Lorg/kohsuke/github/GitHubRequest$Builder;
        54: checkcast     #17                 // class org/kohsuke/github/Requester
        57: ldc           #29                 // class org/kohsuke/github/GHRelease
        59: invokevirtual #30                 // Method org/kohsuke/github/Requester.fetch:(Ljava/lang/Class;)Ljava/lang/Object;
        62: checkcast     #29                 // class org/kohsuke/github/GHRelease
        65: aload_0
        66: getfield      #2                  // Field base:Lorg/kohsuke/github/GHRelease;
        69: getfield      #18                 // Field org/kohsuke/github/GHRelease.owner:Lorg/kohsuke/github/GHRepository;
        72: invokevirtual #31                 // Method org/kohsuke/github/GHRelease.wrap:(Lorg/kohsuke/github/GHRepository;)Lorg/kohsuke/github/GHRelease;
        75: areturn
      LineNumberTable:
        line 114: 0
        line 115: 35
        line 116: 59
        line 117: 72
        line 114: 75
      LocalVariableTable:
        Start  Length  Slot  Name   Signature
            0      76     0  this   Lorg/kohsuke/github/GHReleaseUpdater;
    Exceptions:
      throws java.io.IOException
}
SourceFile: "GHReleaseUpdater.java"
InnerClasses:
  static #101= #100 of #125;              // Builder=class org/kohsuke/github/GitHubRequest$Builder of class org/kohsuke/github/GitHubRequest
