Classfile /Users/mw/Projects/slang-braindump/.jar/jar8/assemble/slang-braindump/assemble/content/org/kohsuke/github/GHRepositoryStatistics$PunchCardItem.class
  Last modified May 29, 2022; size 1873 bytes
  SHA-256 checksum f658a4c95eb0e553a12abe5b19c01aff3210c3cbcb7b439a24fa8eba179da18e
  Compiled from "GHRepositoryStatistics.java"
public class org.kohsuke.github.GHRepositoryStatistics$PunchCardItem
  minor version: 0
  major version: 52
  flags: (0x0021) ACC_PUBLIC, ACC_SUPER
  this_class: #21                         // org/kohsuke/github/GHRepositoryStatistics$PunchCardItem
  super_class: #22                        // java/lang/Object
  interfaces: 0, fields: 3, methods: 5, attributes: 2
Constant pool:
   #1 = Methodref          #22.#58        // java/lang/Object."<init>":()V
   #2 = InterfaceMethodref #59.#60        // java/util/List.get:(I)Ljava/lang/Object;
   #3 = Class              #61            // java/lang/Integer
   #4 = Methodref          #3.#62         // java/lang/Integer.intValue:()I
   #5 = Fieldref           #21.#63        // org/kohsuke/github/GHRepositoryStatistics$PunchCardItem.dayOfWeek:I
   #6 = Fieldref           #21.#64        // org/kohsuke/github/GHRepositoryStatistics$PunchCardItem.hourOfDay:I
   #7 = Fieldref           #21.#65        // org/kohsuke/github/GHRepositoryStatistics$PunchCardItem.numberOfCommits:I
   #8 = Class              #66            // java/lang/StringBuilder
   #9 = Methodref          #8.#58         // java/lang/StringBuilder."<init>":()V
  #10 = String             #67            // Day
  #11 = Methodref          #8.#68         // java/lang/StringBuilder.append:(Ljava/lang/String;)Ljava/lang/StringBuilder;
  #12 = Methodref          #21.#69        // org/kohsuke/github/GHRepositoryStatistics$PunchCardItem.getDayOfWeek:()I
  #13 = Methodref          #8.#70         // java/lang/StringBuilder.append:(I)Ljava/lang/StringBuilder;
  #14 = String             #71            //  Hour
  #15 = Methodref          #21.#72        // org/kohsuke/github/GHRepositoryStatistics$PunchCardItem.getHourOfDay:()J
  #16 = Methodref          #8.#73         // java/lang/StringBuilder.append:(J)Ljava/lang/StringBuilder;
  #17 = String             #74            // :
  #18 = Methodref          #21.#75        // org/kohsuke/github/GHRepositoryStatistics$PunchCardItem.getNumberOfCommits:()J
  #19 = String             #76            //  commits
  #20 = Methodref          #8.#77         // java/lang/StringBuilder.toString:()Ljava/lang/String;
  #21 = Class              #79            // org/kohsuke/github/GHRepositoryStatistics$PunchCardItem
  #22 = Class              #80            // java/lang/Object
  #23 = Utf8               dayOfWeek
  #24 = Utf8               I
  #25 = Utf8               hourOfDay
  #26 = Utf8               numberOfCommits
  #27 = Utf8               <init>
  #28 = Utf8               (Ljava/util/List;)V
  #29 = Utf8               Code
  #30 = Utf8               LineNumberTable
  #31 = Utf8               LocalVariableTable
  #32 = Utf8               this
  #33 = Utf8               PunchCardItem
  #34 = Utf8               InnerClasses
  #35 = Utf8               Lorg/kohsuke/github/GHRepositoryStatistics$PunchCardItem;
  #36 = Utf8               item
  #37 = Utf8               Ljava/util/List;
  #38 = Utf8               LocalVariableTypeTable
  #39 = Utf8               Ljava/util/List<Ljava/lang/Integer;>;
  #40 = Utf8               Signature
  #41 = Utf8               (Ljava/util/List<Ljava/lang/Integer;>;)V
  #42 = Utf8               RuntimeVisibleAnnotations
  #43 = Utf8               Lcom/fasterxml/jackson/annotation/JsonCreator;
  #44 = Utf8               mode
  #45 = Class              #82            // com/fasterxml/jackson/annotation/JsonCreator$Mode
  #46 = Utf8               Mode
  #47 = Utf8               Lcom/fasterxml/jackson/annotation/JsonCreator$Mode;
  #48 = Utf8               DELEGATING
  #49 = Utf8               getDayOfWeek
  #50 = Utf8               ()I
  #51 = Utf8               getHourOfDay
  #52 = Utf8               ()J
  #53 = Utf8               getNumberOfCommits
  #54 = Utf8               toString
  #55 = Utf8               ()Ljava/lang/String;
  #56 = Utf8               SourceFile
  #57 = Utf8               GHRepositoryStatistics.java
  #58 = NameAndType        #27:#83        // "<init>":()V
  #59 = Class              #84            // java/util/List
  #60 = NameAndType        #85:#86        // get:(I)Ljava/lang/Object;
  #61 = Utf8               java/lang/Integer
  #62 = NameAndType        #87:#50        // intValue:()I
  #63 = NameAndType        #23:#24        // dayOfWeek:I
  #64 = NameAndType        #25:#24        // hourOfDay:I
  #65 = NameAndType        #26:#24        // numberOfCommits:I
  #66 = Utf8               java/lang/StringBuilder
  #67 = Utf8               Day
  #68 = NameAndType        #88:#89        // append:(Ljava/lang/String;)Ljava/lang/StringBuilder;
  #69 = NameAndType        #49:#50        // getDayOfWeek:()I
  #70 = NameAndType        #88:#90        // append:(I)Ljava/lang/StringBuilder;
  #71 = Utf8                Hour
  #72 = NameAndType        #51:#52        // getHourOfDay:()J
  #73 = NameAndType        #88:#91        // append:(J)Ljava/lang/StringBuilder;
  #74 = Utf8               :
  #75 = NameAndType        #53:#52        // getNumberOfCommits:()J
  #76 = Utf8                commits
  #77 = NameAndType        #54:#55        // toString:()Ljava/lang/String;
  #78 = Class              #92            // org/kohsuke/github/GHRepositoryStatistics
  #79 = Utf8               org/kohsuke/github/GHRepositoryStatistics$PunchCardItem
  #80 = Utf8               java/lang/Object
  #81 = Class              #93            // com/fasterxml/jackson/annotation/JsonCreator
  #82 = Utf8               com/fasterxml/jackson/annotation/JsonCreator$Mode
  #83 = Utf8               ()V
  #84 = Utf8               java/util/List
  #85 = Utf8               get
  #86 = Utf8               (I)Ljava/lang/Object;
  #87 = Utf8               intValue
  #88 = Utf8               append
  #89 = Utf8               (Ljava/lang/String;)Ljava/lang/StringBuilder;
  #90 = Utf8               (I)Ljava/lang/StringBuilder;
  #91 = Utf8               (J)Ljava/lang/StringBuilder;
  #92 = Utf8               org/kohsuke/github/GHRepositoryStatistics
  #93 = Utf8               com/fasterxml/jackson/annotation/JsonCreator
{
  private final int dayOfWeek;
    descriptor: I
    flags: (0x0012) ACC_PRIVATE, ACC_FINAL

  private final int hourOfDay;
    descriptor: I
    flags: (0x0012) ACC_PRIVATE, ACC_FINAL

  private final int numberOfCommits;
    descriptor: I
    flags: (0x0012) ACC_PRIVATE, ACC_FINAL

  private org.kohsuke.github.GHRepositoryStatistics$PunchCardItem(java.util.List<java.lang.Integer>);
    descriptor: (Ljava/util/List;)V
    flags: (0x0002) ACC_PRIVATE
    Code:
      stack=3, locals=2, args_size=2
         0: aload_0
         1: invokespecial #1                  // Method java/lang/Object."<init>":()V
         4: aload_0
         5: aload_1
         6: iconst_0
         7: invokeinterface #2,  2            // InterfaceMethod java/util/List.get:(I)Ljava/lang/Object;
        12: checkcast     #3                  // class java/lang/Integer
        15: invokevirtual #4                  // Method java/lang/Integer.intValue:()I
        18: putfield      #5                  // Field dayOfWeek:I
        21: aload_0
        22: aload_1
        23: iconst_1
        24: invokeinterface #2,  2            // InterfaceMethod java/util/List.get:(I)Ljava/lang/Object;
        29: checkcast     #3                  // class java/lang/Integer
        32: invokevirtual #4                  // Method java/lang/Integer.intValue:()I
        35: putfield      #6                  // Field hourOfDay:I
        38: aload_0
        39: aload_1
        40: iconst_2
        41: invokeinterface #2,  2            // InterfaceMethod java/util/List.get:(I)Ljava/lang/Object;
        46: checkcast     #3                  // class java/lang/Integer
        49: invokevirtual #4                  // Method java/lang/Integer.intValue:()I
        52: putfield      #7                  // Field numberOfCommits:I
        55: return
      LineNumberTable:
        line 423: 0
        line 424: 4
        line 425: 21
        line 426: 38
        line 427: 55
      LocalVariableTable:
        Start  Length  Slot  Name   Signature
            0      56     0  this   Lorg/kohsuke/github/GHRepositoryStatistics$PunchCardItem;
            0      56     1  item   Ljava/util/List;
      LocalVariableTypeTable:
        Start  Length  Slot  Name   Signature
            0      56     1  item   Ljava/util/List<Ljava/lang/Integer;>;
    Signature: #41                          // (Ljava/util/List<Ljava/lang/Integer;>;)V
    RuntimeVisibleAnnotations:
      0: #43(#44=e#47.#48)
        com.fasterxml.jackson.annotation.JsonCreator(
          mode=Lcom/fasterxml/jackson/annotation/JsonCreator$Mode;.DELEGATING
        )

  public int getDayOfWeek();
    descriptor: ()I
    flags: (0x0001) ACC_PUBLIC
    Code:
      stack=1, locals=1, args_size=1
         0: aload_0
         1: getfield      #5                  // Field dayOfWeek:I
         4: ireturn
      LineNumberTable:
        line 435: 0
      LocalVariableTable:
        Start  Length  Slot  Name   Signature
            0       5     0  this   Lorg/kohsuke/github/GHRepositoryStatistics$PunchCardItem;

  public long getHourOfDay();
    descriptor: ()J
    flags: (0x0001) ACC_PUBLIC
    Code:
      stack=2, locals=1, args_size=1
         0: aload_0
         1: getfield      #6                  // Field hourOfDay:I
         4: i2l
         5: lreturn
      LineNumberTable:
        line 444: 0
      LocalVariableTable:
        Start  Length  Slot  Name   Signature
            0       6     0  this   Lorg/kohsuke/github/GHRepositoryStatistics$PunchCardItem;

  public long getNumberOfCommits();
    descriptor: ()J
    flags: (0x0001) ACC_PUBLIC
    Code:
      stack=2, locals=1, args_size=1
         0: aload_0
         1: getfield      #7                  // Field numberOfCommits:I
         4: i2l
         5: lreturn
      LineNumberTable:
        line 453: 0
      LocalVariableTable:
        Start  Length  Slot  Name   Signature
            0       6     0  this   Lorg/kohsuke/github/GHRepositoryStatistics$PunchCardItem;

  public java.lang.String toString();
    descriptor: ()Ljava/lang/String;
    flags: (0x0001) ACC_PUBLIC
    Code:
      stack=3, locals=1, args_size=1
         0: new           #8                  // class java/lang/StringBuilder
         3: dup
         4: invokespecial #9                  // Method java/lang/StringBuilder."<init>":()V
         7: ldc           #10                 // String Day
         9: invokevirtual #11                 // Method java/lang/StringBuilder.append:(Ljava/lang/String;)Ljava/lang/StringBuilder;
        12: aload_0
        13: invokevirtual #12                 // Method getDayOfWeek:()I
        16: invokevirtual #13                 // Method java/lang/StringBuilder.append:(I)Ljava/lang/StringBuilder;
        19: ldc           #14                 // String  Hour
        21: invokevirtual #11                 // Method java/lang/StringBuilder.append:(Ljava/lang/String;)Ljava/lang/StringBuilder;
        24: aload_0
        25: invokevirtual #15                 // Method getHourOfDay:()J
        28: invokevirtual #16                 // Method java/lang/StringBuilder.append:(J)Ljava/lang/StringBuilder;
        31: ldc           #17                 // String :
        33: invokevirtual #11                 // Method java/lang/StringBuilder.append:(Ljava/lang/String;)Ljava/lang/StringBuilder;
        36: aload_0
        37: invokevirtual #18                 // Method getNumberOfCommits:()J
        40: invokevirtual #16                 // Method java/lang/StringBuilder.append:(J)Ljava/lang/StringBuilder;
        43: ldc           #19                 // String  commits
        45: invokevirtual #11                 // Method java/lang/StringBuilder.append:(Ljava/lang/String;)Ljava/lang/StringBuilder;
        48: invokevirtual #20                 // Method java/lang/StringBuilder.toString:()Ljava/lang/String;
        51: areturn
      LineNumberTable:
        line 457: 0
      LocalVariableTable:
        Start  Length  Slot  Name   Signature
            0      52     0  this   Lorg/kohsuke/github/GHRepositoryStatistics$PunchCardItem;
}
SourceFile: "GHRepositoryStatistics.java"
InnerClasses:
  public static #33= #21 of #78;          // PunchCardItem=class org/kohsuke/github/GHRepositoryStatistics$PunchCardItem of class org/kohsuke/github/GHRepositoryStatistics
  public static final #46= #45 of #81;    // Mode=class com/fasterxml/jackson/annotation/JsonCreator$Mode of class com/fasterxml/jackson/annotation/JsonCreator
