Classfile /Users/mw/Projects/slang-braindump/.jar/jar8/assemble/slang-braindump/assemble/content/org/kohsuke/github/GHRelease.class
  Last modified May 29, 2022; size 7994 bytes
  SHA-256 checksum 494fec56392fa3b97e483b55f3b593e983426f3b06a4456e9b4361ee1fcce4bc
  Compiled from "GHRelease.java"
public class org.kohsuke.github.GHRelease extends org.kohsuke.github.GHObject
  minor version: 0
  major version: 52
  flags: (0x0021) ACC_PUBLIC, ACC_SUPER
  this_class: #76                         // org/kohsuke/github/GHRelease
  super_class: #77                        // org/kohsuke/github/GHObject
  interfaces: 0, fields: 15, methods: 29, attributes: 3
Constant pool:
    #1 = Methodref          #77.#185      // org/kohsuke/github/GHObject."<init>":()V
    #2 = Fieldref           #76.#186      // org/kohsuke/github/GHRelease.discussion_url:Ljava/lang/String;
    #3 = Fieldref           #76.#187      // org/kohsuke/github/GHRelease.assets_url:Ljava/lang/String;
    #4 = Fieldref           #76.#188      // org/kohsuke/github/GHRelease.body:Ljava/lang/String;
    #5 = Fieldref           #76.#189      // org/kohsuke/github/GHRelease.draft:Z
    #6 = Methodref          #76.#190      // org/kohsuke/github/GHRelease.update:()Lorg/kohsuke/github/GHReleaseUpdater;
    #7 = Methodref          #70.#191      // org/kohsuke/github/GHReleaseUpdater.draft:(Z)Lorg/kohsuke/github/GHReleaseUpdater;
    #8 = Methodref          #70.#192      // org/kohsuke/github/GHReleaseUpdater.update:()Lorg/kohsuke/github/GHRelease;
    #9 = Fieldref           #76.#193      // org/kohsuke/github/GHRelease.html_url:Ljava/lang/String;
   #10 = Methodref          #194.#195     // org/kohsuke/github/GitHubClient.parseURL:(Ljava/lang/String;)Ljava/net/URL;
   #11 = Fieldref           #76.#196      // org/kohsuke/github/GHRelease.name:Ljava/lang/String;
   #12 = Fieldref           #76.#197      // org/kohsuke/github/GHRelease.owner:Lorg/kohsuke/github/GHRepository;
   #13 = Class              #198          // java/lang/RuntimeException
   #14 = String             #199          // Do not use this method.
   #15 = Methodref          #13.#200      // java/lang/RuntimeException."<init>":(Ljava/lang/String;)V
   #16 = Fieldref           #76.#201      // org/kohsuke/github/GHRelease.prerelease:Z
   #17 = Class              #202          // java/util/Date
   #18 = Fieldref           #76.#203      // org/kohsuke/github/GHRelease.published_at:Ljava/util/Date;
   #19 = Methodref          #17.#204      // java/util/Date.getTime:()J
   #20 = Methodref          #17.#205      // java/util/Date."<init>":(J)V
   #21 = Fieldref           #76.#206      // org/kohsuke/github/GHRelease.tag_name:Ljava/lang/String;
   #22 = Fieldref           #76.#207      // org/kohsuke/github/GHRelease.target_commitish:Ljava/lang/String;
   #23 = Fieldref           #76.#208      // org/kohsuke/github/GHRelease.upload_url:Ljava/lang/String;
   #24 = Fieldref           #76.#209      // org/kohsuke/github/GHRelease.zipball_url:Ljava/lang/String;
   #25 = Fieldref           #76.#210      // org/kohsuke/github/GHRelease.tarball_url:Ljava/lang/String;
   #26 = Methodref          #76.#211      // org/kohsuke/github/GHRelease.wrap:(Lorg/kohsuke/github/GHRepository;)Lorg/kohsuke/github/GHRelease;
   #27 = Class              #212          // java/io/FileInputStream
   #28 = Methodref          #27.#213      // java/io/FileInputStream."<init>":(Ljava/io/File;)V
   #29 = Methodref          #158.#214     // java/io/File.getName:()Ljava/lang/String;
   #30 = Methodref          #76.#215      // org/kohsuke/github/GHRelease.uploadAsset:(Ljava/lang/String;Ljava/io/InputStream;Ljava/lang/String;)Lorg/kohsuke/github/GHAsset;
   #31 = Methodref          #27.#216      // java/io/FileInputStream.close:()V
   #32 = Methodref          #217.#218     // org/kohsuke/github/GHRepository.root:()Lorg/kohsuke/github/GitHub;
   #33 = Methodref          #219.#220     // org/kohsuke/github/GitHub.createRequest:()Lorg/kohsuke/github/Requester;
   #34 = String             #221          // POST
   #35 = Methodref          #36.#222      // org/kohsuke/github/Requester.method:(Ljava/lang/String;)Lorg/kohsuke/github/GitHubRequest$Builder;
   #36 = Class              #223          // org/kohsuke/github/Requester
   #37 = Methodref          #76.#224      // org/kohsuke/github/GHRelease.getUploadUrl:()Ljava/lang/String;
   #38 = Methodref          #49.#225      // java/lang/String.indexOf:(I)I
   #39 = Methodref          #49.#226      // java/lang/String.substring:(II)Ljava/lang/String;
   #40 = Class              #227          // java/lang/StringBuilder
   #41 = Methodref          #40.#185      // java/lang/StringBuilder."<init>":()V
   #42 = Methodref          #40.#228      // java/lang/StringBuilder.append:(Ljava/lang/String;)Ljava/lang/StringBuilder;
   #43 = String             #229          // ?name=
   #44 = String             #230          // UTF-8
   #45 = Methodref          #231.#232     // java/net/URLEncoder.encode:(Ljava/lang/String;Ljava/lang/String;)Ljava/lang/String;
   #46 = Methodref          #40.#233      // java/lang/StringBuilder.toString:()Ljava/lang/String;
   #47 = Methodref          #36.#234      // org/kohsuke/github/Requester.contentType:(Ljava/lang/String;)Lorg/kohsuke/github/GitHubRequest$Builder;
   #48 = Methodref          #36.#235      // org/kohsuke/github/Requester.with:(Ljava/io/InputStream;)Lorg/kohsuke/github/GitHubRequest$Builder;
   #49 = Class              #236          // java/lang/String
   #50 = Methodref          #36.#237      // org/kohsuke/github/Requester.withUrlPath:(Ljava/lang/String;[Ljava/lang/String;)Lorg/kohsuke/github/GitHubRequest$Builder;
   #51 = Class              #238          // org/kohsuke/github/GHAsset
   #52 = Methodref          #36.#239      // org/kohsuke/github/Requester.fetch:(Ljava/lang/Class;)Ljava/lang/Object;
   #53 = Methodref          #51.#240      // org/kohsuke/github/GHAsset.wrap:(Lorg/kohsuke/github/GHRelease;)Lorg/kohsuke/github/GHAsset;
   #54 = Fieldref           #76.#241      // org/kohsuke/github/GHRelease.assets:Ljava/util/List;
   #55 = Methodref          #242.#243     // java/util/Collections.unmodifiableList:(Ljava/util/List;)Ljava/util/List;
   #56 = Methodref          #76.#244      // org/kohsuke/github/GHRelease.listAssets:()Lorg/kohsuke/github/PagedIterable;
   #57 = Methodref          #245.#246     // org/kohsuke/github/PagedIterable.toList:()Ljava/util/List;
   #58 = String             #83           // assets
   #59 = Methodref          #76.#247      // org/kohsuke/github/GHRelease.getApiTailUrl:(Ljava/lang/String;)Ljava/lang/String;
   #60 = Class              #248          // "[Lorg/kohsuke/github/GHAsset;"
   #61 = InvokeDynamic      #0:#254       // #0:accept:(Lorg/kohsuke/github/GHRelease;)Ljava/util/function/Consumer;
   #62 = Methodref          #36.#255      // org/kohsuke/github/Requester.toIterable:(Ljava/lang/Class;Ljava/util/function/Consumer;)Lorg/kohsuke/github/PagedIterable;
   #63 = Methodref          #76.#218      // org/kohsuke/github/GHRelease.root:()Lorg/kohsuke/github/GitHub;
   #64 = String             #256          // DELETE
   #65 = String             #257          // releases/
   #66 = Methodref          #76.#258      // org/kohsuke/github/GHRelease.getId:()J
   #67 = Methodref          #40.#259      // java/lang/StringBuilder.append:(J)Ljava/lang/StringBuilder;
   #68 = Methodref          #217.#247     // org/kohsuke/github/GHRepository.getApiTailUrl:(Ljava/lang/String;)Ljava/lang/String;
   #69 = Methodref          #36.#260      // org/kohsuke/github/Requester.send:()V
   #70 = Class              #261          // org/kohsuke/github/GHReleaseUpdater
   #71 = Methodref          #70.#262      // org/kohsuke/github/GHReleaseUpdater."<init>":(Lorg/kohsuke/github/GHRelease;)V
   #72 = String             #263          // releases/%s/%s
   #73 = Class              #264          // java/lang/Object
   #74 = Methodref          #265.#266     // java/lang/Long.valueOf:(J)Ljava/lang/Long;
   #75 = Methodref          #49.#267      // java/lang/String.format:(Ljava/lang/String;[Ljava/lang/Object;)Ljava/lang/String;
   #76 = Class              #268          // org/kohsuke/github/GHRelease
   #77 = Class              #269          // org/kohsuke/github/GHObject
   #78 = Utf8               owner
   #79 = Utf8               Lorg/kohsuke/github/GHRepository;
   #80 = Utf8               html_url
   #81 = Utf8               Ljava/lang/String;
   #82 = Utf8               assets_url
   #83 = Utf8               assets
   #84 = Utf8               Ljava/util/List;
   #85 = Utf8               Signature
   #86 = Utf8               Ljava/util/List<Lorg/kohsuke/github/GHAsset;>;
   #87 = Utf8               upload_url
   #88 = Utf8               tag_name
   #89 = Utf8               target_commitish
   #90 = Utf8               name
   #91 = Utf8               body
   #92 = Utf8               draft
   #93 = Utf8               Z
   #94 = Utf8               prerelease
   #95 = Utf8               published_at
   #96 = Utf8               Ljava/util/Date;
   #97 = Utf8               tarball_url
   #98 = Utf8               zipball_url
   #99 = Utf8               discussion_url
  #100 = Utf8               <init>
  #101 = Utf8               ()V
  #102 = Utf8               Code
  #103 = Utf8               LineNumberTable
  #104 = Utf8               LocalVariableTable
  #105 = Utf8               this
  #106 = Utf8               Lorg/kohsuke/github/GHRelease;
  #107 = Utf8               getDiscussionUrl
  #108 = Utf8               ()Ljava/lang/String;
  #109 = Utf8               getAssetsUrl
  #110 = Utf8               getBody
  #111 = Utf8               isDraft
  #112 = Utf8               ()Z
  #113 = Utf8               setDraft
  #114 = Utf8               (Z)Lorg/kohsuke/github/GHRelease;
  #115 = Utf8               Exceptions
  #116 = Class              #270          // java/io/IOException
  #117 = Utf8               Deprecated
  #118 = Utf8               RuntimeVisibleAnnotations
  #119 = Utf8               Ljava/lang/Deprecated;
  #120 = Utf8               getHtmlUrl
  #121 = Utf8               ()Ljava/net/URL;
  #122 = Utf8               getName
  #123 = Utf8               setName
  #124 = Utf8               (Ljava/lang/String;)V
  #125 = Utf8               getOwner
  #126 = Utf8               ()Lorg/kohsuke/github/GHRepository;
  #127 = Utf8               RuntimeInvisibleAnnotations
  #128 = Utf8               Ledu/umd/cs/findbugs/annotations/SuppressFBWarnings;
  #129 = Utf8               value
  #130 = Utf8               EI_EXPOSE_REP
  #131 = Utf8               justification
  #132 = Utf8               Expected behavior
  #133 = Utf8               setOwner
  #134 = Utf8               (Lorg/kohsuke/github/GHRepository;)V
  #135 = Utf8               isPrerelease
  #136 = Utf8               getPublished_at
  #137 = Utf8               ()Ljava/util/Date;
  #138 = Utf8               getTagName
  #139 = Utf8               getTargetCommitish
  #140 = Utf8               getUploadUrl
  #141 = Utf8               getZipballUrl
  #142 = Utf8               getTarballUrl
  #143 = Utf8               wrap
  #144 = Utf8               (Lorg/kohsuke/github/GHRepository;)Lorg/kohsuke/github/GHRelease;
  #145 = Utf8               ([Lorg/kohsuke/github/GHRelease;Lorg/kohsuke/github/GHRepository;)[Lorg/kohsuke/github/GHRelease;
  #146 = Utf8               release
  #147 = Utf8               releases
  #148 = Utf8               [Lorg/kohsuke/github/GHRelease;
  #149 = Utf8               StackMapTable
  #150 = Class              #148          // "[Lorg/kohsuke/github/GHRelease;"
  #151 = Utf8               uploadAsset
  #152 = Utf8               (Ljava/io/File;Ljava/lang/String;)Lorg/kohsuke/github/GHAsset;
  #153 = Utf8               file
  #154 = Utf8               Ljava/io/File;
  #155 = Utf8               contentType
  #156 = Utf8               s
  #157 = Utf8               Ljava/io/FileInputStream;
  #158 = Class              #271          // java/io/File
  #159 = Class              #272          // java/lang/Throwable
  #160 = Utf8               (Ljava/lang/String;Ljava/io/InputStream;Ljava/lang/String;)Lorg/kohsuke/github/GHAsset;
  #161 = Utf8               filename
  #162 = Utf8               stream
  #163 = Utf8               Ljava/io/InputStream;
  #164 = Utf8               builder
  #165 = Utf8               Lorg/kohsuke/github/Requester;
  #166 = Utf8               url
  #167 = Utf8               ()Ljava/util/List;
  #168 = Utf8               ()Ljava/util/List<Lorg/kohsuke/github/GHAsset;>;
  #169 = Utf8               getAssets
  #170 = Utf8               listAssets
  #171 = Utf8               ()Lorg/kohsuke/github/PagedIterable;
  #172 = Utf8               ()Lorg/kohsuke/github/PagedIterable<Lorg/kohsuke/github/GHAsset;>;
  #173 = Utf8               delete
  #174 = Utf8               update
  #175 = Utf8               ()Lorg/kohsuke/github/GHReleaseUpdater;
  #176 = Utf8               getApiTailUrl
  #177 = Utf8               (Ljava/lang/String;)Ljava/lang/String;
  #178 = Utf8               end
  #179 = Utf8               lambda$listAssets$0
  #180 = Utf8               (Lorg/kohsuke/github/GHAsset;)V
  #181 = Utf8               item
  #182 = Utf8               Lorg/kohsuke/github/GHAsset;
  #183 = Utf8               SourceFile
  #184 = Utf8               GHRelease.java
  #185 = NameAndType        #100:#101     // "<init>":()V
  #186 = NameAndType        #99:#81       // discussion_url:Ljava/lang/String;
  #187 = NameAndType        #82:#81       // assets_url:Ljava/lang/String;
  #188 = NameAndType        #91:#81       // body:Ljava/lang/String;
  #189 = NameAndType        #92:#93       // draft:Z
  #190 = NameAndType        #174:#175     // update:()Lorg/kohsuke/github/GHReleaseUpdater;
  #191 = NameAndType        #92:#273      // draft:(Z)Lorg/kohsuke/github/GHReleaseUpdater;
  #192 = NameAndType        #174:#274     // update:()Lorg/kohsuke/github/GHRelease;
  #193 = NameAndType        #80:#81       // html_url:Ljava/lang/String;
  #194 = Class              #275          // org/kohsuke/github/GitHubClient
  #195 = NameAndType        #276:#277     // parseURL:(Ljava/lang/String;)Ljava/net/URL;
  #196 = NameAndType        #90:#81       // name:Ljava/lang/String;
  #197 = NameAndType        #78:#79       // owner:Lorg/kohsuke/github/GHRepository;
  #198 = Utf8               java/lang/RuntimeException
  #199 = Utf8               Do not use this method.
  #200 = NameAndType        #100:#124     // "<init>":(Ljava/lang/String;)V
  #201 = NameAndType        #94:#93       // prerelease:Z
  #202 = Utf8               java/util/Date
  #203 = NameAndType        #95:#96       // published_at:Ljava/util/Date;
  #204 = NameAndType        #278:#279     // getTime:()J
  #205 = NameAndType        #100:#280     // "<init>":(J)V
  #206 = NameAndType        #88:#81       // tag_name:Ljava/lang/String;
  #207 = NameAndType        #89:#81       // target_commitish:Ljava/lang/String;
  #208 = NameAndType        #87:#81       // upload_url:Ljava/lang/String;
  #209 = NameAndType        #98:#81       // zipball_url:Ljava/lang/String;
  #210 = NameAndType        #97:#81       // tarball_url:Ljava/lang/String;
  #211 = NameAndType        #143:#144     // wrap:(Lorg/kohsuke/github/GHRepository;)Lorg/kohsuke/github/GHRelease;
  #212 = Utf8               java/io/FileInputStream
  #213 = NameAndType        #100:#281     // "<init>":(Ljava/io/File;)V
  #214 = NameAndType        #122:#108     // getName:()Ljava/lang/String;
  #215 = NameAndType        #151:#160     // uploadAsset:(Ljava/lang/String;Ljava/io/InputStream;Ljava/lang/String;)Lorg/kohsuke/github/GHAsset;
  #216 = NameAndType        #282:#101     // close:()V
  #217 = Class              #283          // org/kohsuke/github/GHRepository
  #218 = NameAndType        #284:#285     // root:()Lorg/kohsuke/github/GitHub;
  #219 = Class              #286          // org/kohsuke/github/GitHub
  #220 = NameAndType        #287:#288     // createRequest:()Lorg/kohsuke/github/Requester;
  #221 = Utf8               POST
  #222 = NameAndType        #289:#293     // method:(Ljava/lang/String;)Lorg/kohsuke/github/GitHubRequest$Builder;
  #223 = Utf8               org/kohsuke/github/Requester
  #224 = NameAndType        #140:#108     // getUploadUrl:()Ljava/lang/String;
  #225 = NameAndType        #294:#295     // indexOf:(I)I
  #226 = NameAndType        #296:#297     // substring:(II)Ljava/lang/String;
  #227 = Utf8               java/lang/StringBuilder
  #228 = NameAndType        #298:#299     // append:(Ljava/lang/String;)Ljava/lang/StringBuilder;
  #229 = Utf8               ?name=
  #230 = Utf8               UTF-8
  #231 = Class              #300          // java/net/URLEncoder
  #232 = NameAndType        #301:#302     // encode:(Ljava/lang/String;Ljava/lang/String;)Ljava/lang/String;
  #233 = NameAndType        #303:#108     // toString:()Ljava/lang/String;
  #234 = NameAndType        #155:#293     // contentType:(Ljava/lang/String;)Lorg/kohsuke/github/GitHubRequest$Builder;
  #235 = NameAndType        #304:#305     // with:(Ljava/io/InputStream;)Lorg/kohsuke/github/GitHubRequest$Builder;
  #236 = Utf8               java/lang/String
  #237 = NameAndType        #306:#307     // withUrlPath:(Ljava/lang/String;[Ljava/lang/String;)Lorg/kohsuke/github/GitHubRequest$Builder;
  #238 = Utf8               org/kohsuke/github/GHAsset
  #239 = NameAndType        #308:#309     // fetch:(Ljava/lang/Class;)Ljava/lang/Object;
  #240 = NameAndType        #143:#310     // wrap:(Lorg/kohsuke/github/GHRelease;)Lorg/kohsuke/github/GHAsset;
  #241 = NameAndType        #83:#84       // assets:Ljava/util/List;
  #242 = Class              #311          // java/util/Collections
  #243 = NameAndType        #312:#313     // unmodifiableList:(Ljava/util/List;)Ljava/util/List;
  #244 = NameAndType        #170:#171     // listAssets:()Lorg/kohsuke/github/PagedIterable;
  #245 = Class              #314          // org/kohsuke/github/PagedIterable
  #246 = NameAndType        #315:#167     // toList:()Ljava/util/List;
  #247 = NameAndType        #176:#177     // getApiTailUrl:(Ljava/lang/String;)Ljava/lang/String;
  #248 = Utf8               [Lorg/kohsuke/github/GHAsset;
  #249 = Utf8               BootstrapMethods
  #250 = MethodHandle       6:#316        // REF_invokeStatic java/lang/invoke/LambdaMetafactory.metafactory:(Ljava/lang/invoke/MethodHandles$Lookup;Ljava/lang/String;Ljava/lang/invoke/MethodType;Ljava/lang/invoke/MethodType;Ljava/lang/invoke/MethodHandle;Ljava/lang/invoke/MethodType;)Ljava/lang/invoke/CallSite;
  #251 = MethodType         #317          //  (Ljava/lang/Object;)V
  #252 = MethodHandle       7:#318        // REF_invokeSpecial org/kohsuke/github/GHRelease.lambda$listAssets$0:(Lorg/kohsuke/github/GHAsset;)V
  #253 = MethodType         #180          //  (Lorg/kohsuke/github/GHAsset;)V
  #254 = NameAndType        #319:#320     // accept:(Lorg/kohsuke/github/GHRelease;)Ljava/util/function/Consumer;
  #255 = NameAndType        #321:#322     // toIterable:(Ljava/lang/Class;Ljava/util/function/Consumer;)Lorg/kohsuke/github/PagedIterable;
  #256 = Utf8               DELETE
  #257 = Utf8               releases/
  #258 = NameAndType        #323:#279     // getId:()J
  #259 = NameAndType        #298:#324     // append:(J)Ljava/lang/StringBuilder;
  #260 = NameAndType        #325:#101     // send:()V
  #261 = Utf8               org/kohsuke/github/GHReleaseUpdater
  #262 = NameAndType        #100:#326     // "<init>":(Lorg/kohsuke/github/GHRelease;)V
  #263 = Utf8               releases/%s/%s
  #264 = Utf8               java/lang/Object
  #265 = Class              #327          // java/lang/Long
  #266 = NameAndType        #328:#329     // valueOf:(J)Ljava/lang/Long;
  #267 = NameAndType        #330:#331     // format:(Ljava/lang/String;[Ljava/lang/Object;)Ljava/lang/String;
  #268 = Utf8               org/kohsuke/github/GHRelease
  #269 = Utf8               org/kohsuke/github/GHObject
  #270 = Utf8               java/io/IOException
  #271 = Utf8               java/io/File
  #272 = Utf8               java/lang/Throwable
  #273 = Utf8               (Z)Lorg/kohsuke/github/GHReleaseUpdater;
  #274 = Utf8               ()Lorg/kohsuke/github/GHRelease;
  #275 = Utf8               org/kohsuke/github/GitHubClient
  #276 = Utf8               parseURL
  #277 = Utf8               (Ljava/lang/String;)Ljava/net/URL;
  #278 = Utf8               getTime
  #279 = Utf8               ()J
  #280 = Utf8               (J)V
  #281 = Utf8               (Ljava/io/File;)V
  #282 = Utf8               close
  #283 = Utf8               org/kohsuke/github/GHRepository
  #284 = Utf8               root
  #285 = Utf8               ()Lorg/kohsuke/github/GitHub;
  #286 = Utf8               org/kohsuke/github/GitHub
  #287 = Utf8               createRequest
  #288 = Utf8               ()Lorg/kohsuke/github/Requester;
  #289 = Utf8               method
  #290 = Class              #333          // org/kohsuke/github/GitHubRequest$Builder
  #291 = Utf8               Builder
  #292 = Utf8               InnerClasses
  #293 = Utf8               (Ljava/lang/String;)Lorg/kohsuke/github/GitHubRequest$Builder;
  #294 = Utf8               indexOf
  #295 = Utf8               (I)I
  #296 = Utf8               substring
  #297 = Utf8               (II)Ljava/lang/String;
  #298 = Utf8               append
  #299 = Utf8               (Ljava/lang/String;)Ljava/lang/StringBuilder;
  #300 = Utf8               java/net/URLEncoder
  #301 = Utf8               encode
  #302 = Utf8               (Ljava/lang/String;Ljava/lang/String;)Ljava/lang/String;
  #303 = Utf8               toString
  #304 = Utf8               with
  #305 = Utf8               (Ljava/io/InputStream;)Lorg/kohsuke/github/GitHubRequest$Builder;
  #306 = Utf8               withUrlPath
  #307 = Utf8               (Ljava/lang/String;[Ljava/lang/String;)Lorg/kohsuke/github/GitHubRequest$Builder;
  #308 = Utf8               fetch
  #309 = Utf8               (Ljava/lang/Class;)Ljava/lang/Object;
  #310 = Utf8               (Lorg/kohsuke/github/GHRelease;)Lorg/kohsuke/github/GHAsset;
  #311 = Utf8               java/util/Collections
  #312 = Utf8               unmodifiableList
  #313 = Utf8               (Ljava/util/List;)Ljava/util/List;
  #314 = Utf8               org/kohsuke/github/PagedIterable
  #315 = Utf8               toList
  #316 = Methodref          #334.#335     // java/lang/invoke/LambdaMetafactory.metafactory:(Ljava/lang/invoke/MethodHandles$Lookup;Ljava/lang/String;Ljava/lang/invoke/MethodType;Ljava/lang/invoke/MethodType;Ljava/lang/invoke/MethodHandle;Ljava/lang/invoke/MethodType;)Ljava/lang/invoke/CallSite;
  #317 = Utf8               (Ljava/lang/Object;)V
  #318 = Methodref          #76.#336      // org/kohsuke/github/GHRelease.lambda$listAssets$0:(Lorg/kohsuke/github/GHAsset;)V
  #319 = Utf8               accept
  #320 = Utf8               (Lorg/kohsuke/github/GHRelease;)Ljava/util/function/Consumer;
  #321 = Utf8               toIterable
  #322 = Utf8               (Ljava/lang/Class;Ljava/util/function/Consumer;)Lorg/kohsuke/github/PagedIterable;
  #323 = Utf8               getId
  #324 = Utf8               (J)Ljava/lang/StringBuilder;
  #325 = Utf8               send
  #326 = Utf8               (Lorg/kohsuke/github/GHRelease;)V
  #327 = Utf8               java/lang/Long
  #328 = Utf8               valueOf
  #329 = Utf8               (J)Ljava/lang/Long;
  #330 = Utf8               format
  #331 = Utf8               (Ljava/lang/String;[Ljava/lang/Object;)Ljava/lang/String;
  #332 = Class              #337          // org/kohsuke/github/GitHubRequest
  #333 = Utf8               org/kohsuke/github/GitHubRequest$Builder
  #334 = Class              #338          // java/lang/invoke/LambdaMetafactory
  #335 = NameAndType        #339:#342     // metafactory:(Ljava/lang/invoke/MethodHandles$Lookup;Ljava/lang/String;Ljava/lang/invoke/MethodType;Ljava/lang/invoke/MethodType;Ljava/lang/invoke/MethodHandle;Ljava/lang/invoke/MethodType;)Ljava/lang/invoke/CallSite;
  #336 = NameAndType        #179:#180     // lambda$listAssets$0:(Lorg/kohsuke/github/GHAsset;)V
  #337 = Utf8               org/kohsuke/github/GitHubRequest
  #338 = Utf8               java/lang/invoke/LambdaMetafactory
  #339 = Utf8               metafactory
  #340 = Class              #344          // java/lang/invoke/MethodHandles$Lookup
  #341 = Utf8               Lookup
  #342 = Utf8               (Ljava/lang/invoke/MethodHandles$Lookup;Ljava/lang/String;Ljava/lang/invoke/MethodType;Ljava/lang/invoke/MethodType;Ljava/lang/invoke/MethodHandle;Ljava/lang/invoke/MethodType;)Ljava/lang/invoke/CallSite;
  #343 = Class              #345          // java/lang/invoke/MethodHandles
  #344 = Utf8               java/lang/invoke/MethodHandles$Lookup
  #345 = Utf8               java/lang/invoke/MethodHandles
{
  org.kohsuke.github.GHRepository owner;
    descriptor: Lorg/kohsuke/github/GHRepository;
    flags: (0x0000)

  private java.lang.String html_url;
    descriptor: Ljava/lang/String;
    flags: (0x0002) ACC_PRIVATE

  private java.lang.String assets_url;
    descriptor: Ljava/lang/String;
    flags: (0x0002) ACC_PRIVATE

  private java.util.List<org.kohsuke.github.GHAsset> assets;
    descriptor: Ljava/util/List;
    flags: (0x0002) ACC_PRIVATE
    Signature: #86                          // Ljava/util/List<Lorg/kohsuke/github/GHAsset;>;

  private java.lang.String upload_url;
    descriptor: Ljava/lang/String;
    flags: (0x0002) ACC_PRIVATE

  private java.lang.String tag_name;
    descriptor: Ljava/lang/String;
    flags: (0x0002) ACC_PRIVATE

  private java.lang.String target_commitish;
    descriptor: Ljava/lang/String;
    flags: (0x0002) ACC_PRIVATE

  private java.lang.String name;
    descriptor: Ljava/lang/String;
    flags: (0x0002) ACC_PRIVATE

  private java.lang.String body;
    descriptor: Ljava/lang/String;
    flags: (0x0002) ACC_PRIVATE

  private boolean draft;
    descriptor: Z
    flags: (0x0002) ACC_PRIVATE

  private boolean prerelease;
    descriptor: Z
    flags: (0x0002) ACC_PRIVATE

  private java.util.Date published_at;
    descriptor: Ljava/util/Date;
    flags: (0x0002) ACC_PRIVATE

  private java.lang.String tarball_url;
    descriptor: Ljava/lang/String;
    flags: (0x0002) ACC_PRIVATE

  private java.lang.String zipball_url;
    descriptor: Ljava/lang/String;
    flags: (0x0002) ACC_PRIVATE

  private java.lang.String discussion_url;
    descriptor: Ljava/lang/String;
    flags: (0x0002) ACC_PRIVATE

  public org.kohsuke.github.GHRelease();
    descriptor: ()V
    flags: (0x0001) ACC_PUBLIC
    Code:
      stack=1, locals=1, args_size=1
         0: aload_0
         1: invokespecial #1                  // Method org/kohsuke/github/GHObject."<init>":()V
         4: return
      LineNumberTable:
        line 24: 0
      LocalVariableTable:
        Start  Length  Slot  Name   Signature
            0       5     0  this   Lorg/kohsuke/github/GHRelease;

  public java.lang.String getDiscussionUrl();
    descriptor: ()Ljava/lang/String;
    flags: (0x0001) ACC_PUBLIC
    Code:
      stack=1, locals=1, args_size=1
         0: aload_0
         1: getfield      #2                  // Field discussion_url:Ljava/lang/String;
         4: areturn
      LineNumberTable:
        line 48: 0
      LocalVariableTable:
        Start  Length  Slot  Name   Signature
            0       5     0  this   Lorg/kohsuke/github/GHRelease;

  public java.lang.String getAssetsUrl();
    descriptor: ()Ljava/lang/String;
    flags: (0x0001) ACC_PUBLIC
    Code:
      stack=1, locals=1, args_size=1
         0: aload_0
         1: getfield      #3                  // Field assets_url:Ljava/lang/String;
         4: areturn
      LineNumberTable:
        line 57: 0
      LocalVariableTable:
        Start  Length  Slot  Name   Signature
            0       5     0  this   Lorg/kohsuke/github/GHRelease;

  public java.lang.String getBody();
    descriptor: ()Ljava/lang/String;
    flags: (0x0001) ACC_PUBLIC
    Code:
      stack=1, locals=1, args_size=1
         0: aload_0
         1: getfield      #4                  // Field body:Ljava/lang/String;
         4: areturn
      LineNumberTable:
        line 66: 0
      LocalVariableTable:
        Start  Length  Slot  Name   Signature
            0       5     0  this   Lorg/kohsuke/github/GHRelease;

  public boolean isDraft();
    descriptor: ()Z
    flags: (0x0001) ACC_PUBLIC
    Code:
      stack=1, locals=1, args_size=1
         0: aload_0
         1: getfield      #5                  // Field draft:Z
         4: ireturn
      LineNumberTable:
        line 75: 0
      LocalVariableTable:
        Start  Length  Slot  Name   Signature
            0       5     0  this   Lorg/kohsuke/github/GHRelease;

  public org.kohsuke.github.GHRelease setDraft(boolean) throws java.io.IOException;
    descriptor: (Z)Lorg/kohsuke/github/GHRelease;
    flags: (0x0001) ACC_PUBLIC
    Code:
      stack=2, locals=2, args_size=2
         0: aload_0
         1: invokevirtual #6                  // Method update:()Lorg/kohsuke/github/GHReleaseUpdater;
         4: iload_1
         5: invokevirtual #7                  // Method org/kohsuke/github/GHReleaseUpdater.draft:(Z)Lorg/kohsuke/github/GHReleaseUpdater;
         8: invokevirtual #8                  // Method org/kohsuke/github/GHReleaseUpdater.update:()Lorg/kohsuke/github/GHRelease;
        11: areturn
      LineNumberTable:
        line 90: 0
      LocalVariableTable:
        Start  Length  Slot  Name   Signature
            0      12     0  this   Lorg/kohsuke/github/GHRelease;
            0      12     1 draft   Z
    Exceptions:
      throws java.io.IOException
    Deprecated: true
    RuntimeVisibleAnnotations:
      0: #119()
        java.lang.Deprecated

  public java.net.URL getHtmlUrl();
    descriptor: ()Ljava/net/URL;
    flags: (0x0001) ACC_PUBLIC
    Code:
      stack=1, locals=1, args_size=1
         0: aload_0
         1: getfield      #9                  // Field html_url:Ljava/lang/String;
         4: invokestatic  #10                 // Method org/kohsuke/github/GitHubClient.parseURL:(Ljava/lang/String;)Ljava/net/URL;
         7: areturn
      LineNumberTable:
        line 94: 0
      LocalVariableTable:
        Start  Length  Slot  Name   Signature
            0       8     0  this   Lorg/kohsuke/github/GHRelease;

  public java.lang.String getName();
    descriptor: ()Ljava/lang/String;
    flags: (0x0001) ACC_PUBLIC
    Code:
      stack=1, locals=1, args_size=1
         0: aload_0
         1: getfield      #11                 // Field name:Ljava/lang/String;
         4: areturn
      LineNumberTable:
        line 103: 0
      LocalVariableTable:
        Start  Length  Slot  Name   Signature
            0       5     0  this   Lorg/kohsuke/github/GHRelease;

  public void setName(java.lang.String);
    descriptor: (Ljava/lang/String;)V
    flags: (0x0001) ACC_PUBLIC
    Code:
      stack=2, locals=2, args_size=2
         0: aload_0
         1: aload_1
         2: putfield      #11                 // Field name:Ljava/lang/String;
         5: return
      LineNumberTable:
        line 113: 0
        line 114: 5
      LocalVariableTable:
        Start  Length  Slot  Name   Signature
            0       6     0  this   Lorg/kohsuke/github/GHRelease;
            0       6     1  name   Ljava/lang/String;

  public org.kohsuke.github.GHRepository getOwner();
    descriptor: ()Lorg/kohsuke/github/GHRepository;
    flags: (0x0001) ACC_PUBLIC
    Code:
      stack=1, locals=1, args_size=1
         0: aload_0
         1: getfield      #12                 // Field owner:Lorg/kohsuke/github/GHRepository;
         4: areturn
      LineNumberTable:
        line 123: 0
      LocalVariableTable:
        Start  Length  Slot  Name   Signature
            0       5     0  this   Lorg/kohsuke/github/GHRelease;
    RuntimeInvisibleAnnotations:
      0: #128(#129=[s#130],#131=s#132)
        edu.umd.cs.findbugs.annotations.SuppressFBWarnings(
          value=["EI_EXPOSE_REP"]
          justification="Expected behavior"
        )

  public void setOwner(org.kohsuke.github.GHRepository);
    descriptor: (Lorg/kohsuke/github/GHRepository;)V
    flags: (0x0001) ACC_PUBLIC
    Code:
      stack=3, locals=2, args_size=2
         0: new           #13                 // class java/lang/RuntimeException
         3: dup
         4: ldc           #14                 // String Do not use this method.
         6: invokespecial #15                 // Method java/lang/RuntimeException."<init>":(Ljava/lang/String;)V
         9: athrow
      LineNumberTable:
        line 135: 0
      LocalVariableTable:
        Start  Length  Slot  Name   Signature
            0      10     0  this   Lorg/kohsuke/github/GHRelease;
            0      10     1 owner   Lorg/kohsuke/github/GHRepository;
    Deprecated: true
    RuntimeVisibleAnnotations:
      0: #119()
        java.lang.Deprecated

  public boolean isPrerelease();
    descriptor: ()Z
    flags: (0x0001) ACC_PUBLIC
    Code:
      stack=1, locals=1, args_size=1
         0: aload_0
         1: getfield      #16                 // Field prerelease:Z
         4: ireturn
      LineNumberTable:
        line 144: 0
      LocalVariableTable:
        Start  Length  Slot  Name   Signature
            0       5     0  this   Lorg/kohsuke/github/GHRelease;

  public java.util.Date getPublished_at();
    descriptor: ()Ljava/util/Date;
    flags: (0x0001) ACC_PUBLIC
    Code:
      stack=4, locals=1, args_size=1
         0: new           #17                 // class java/util/Date
         3: dup
         4: aload_0
         5: getfield      #18                 // Field published_at:Ljava/util/Date;
         8: invokevirtual #19                 // Method java/util/Date.getTime:()J
        11: invokespecial #20                 // Method java/util/Date."<init>":(J)V
        14: areturn
      LineNumberTable:
        line 153: 0
      LocalVariableTable:
        Start  Length  Slot  Name   Signature
            0      15     0  this   Lorg/kohsuke/github/GHRelease;

  public java.lang.String getTagName();
    descriptor: ()Ljava/lang/String;
    flags: (0x0001) ACC_PUBLIC
    Code:
      stack=1, locals=1, args_size=1
         0: aload_0
         1: getfield      #21                 // Field tag_name:Ljava/lang/String;
         4: areturn
      LineNumberTable:
        line 162: 0
      LocalVariableTable:
        Start  Length  Slot  Name   Signature
            0       5     0  this   Lorg/kohsuke/github/GHRelease;

  public java.lang.String getTargetCommitish();
    descriptor: ()Ljava/lang/String;
    flags: (0x0001) ACC_PUBLIC
    Code:
      stack=1, locals=1, args_size=1
         0: aload_0
         1: getfield      #22                 // Field target_commitish:Ljava/lang/String;
         4: areturn
      LineNumberTable:
        line 171: 0
      LocalVariableTable:
        Start  Length  Slot  Name   Signature
            0       5     0  this   Lorg/kohsuke/github/GHRelease;

  public java.lang.String getUploadUrl();
    descriptor: ()Ljava/lang/String;
    flags: (0x0001) ACC_PUBLIC
    Code:
      stack=1, locals=1, args_size=1
         0: aload_0
         1: getfield      #23                 // Field upload_url:Ljava/lang/String;
         4: areturn
      LineNumberTable:
        line 180: 0
      LocalVariableTable:
        Start  Length  Slot  Name   Signature
            0       5     0  this   Lorg/kohsuke/github/GHRelease;

  public java.lang.String getZipballUrl();
    descriptor: ()Ljava/lang/String;
    flags: (0x0001) ACC_PUBLIC
    Code:
      stack=1, locals=1, args_size=1
         0: aload_0
         1: getfield      #24                 // Field zipball_url:Ljava/lang/String;
         4: areturn
      LineNumberTable:
        line 189: 0
      LocalVariableTable:
        Start  Length  Slot  Name   Signature
            0       5     0  this   Lorg/kohsuke/github/GHRelease;

  public java.lang.String getTarballUrl();
    descriptor: ()Ljava/lang/String;
    flags: (0x0001) ACC_PUBLIC
    Code:
      stack=1, locals=1, args_size=1
         0: aload_0
         1: getfield      #25                 // Field tarball_url:Ljava/lang/String;
         4: areturn
      LineNumberTable:
        line 198: 0
      LocalVariableTable:
        Start  Length  Slot  Name   Signature
            0       5     0  this   Lorg/kohsuke/github/GHRelease;

  org.kohsuke.github.GHRelease wrap(org.kohsuke.github.GHRepository);
    descriptor: (Lorg/kohsuke/github/GHRepository;)Lorg/kohsuke/github/GHRelease;
    flags: (0x0000)
    Code:
      stack=2, locals=2, args_size=2
         0: aload_0
         1: aload_1
         2: putfield      #12                 // Field owner:Lorg/kohsuke/github/GHRepository;
         5: aload_0
         6: areturn
      LineNumberTable:
        line 202: 0
        line 203: 5
      LocalVariableTable:
        Start  Length  Slot  Name   Signature
            0       7     0  this   Lorg/kohsuke/github/GHRelease;
            0       7     1 owner   Lorg/kohsuke/github/GHRepository;

  static org.kohsuke.github.GHRelease[] wrap(org.kohsuke.github.GHRelease[], org.kohsuke.github.GHRepository);
    descriptor: ([Lorg/kohsuke/github/GHRelease;Lorg/kohsuke/github/GHRepository;)[Lorg/kohsuke/github/GHRelease;
    flags: (0x0008) ACC_STATIC
    Code:
      stack=2, locals=6, args_size=2
         0: aload_0
         1: astore_2
         2: aload_2
         3: arraylength
         4: istore_3
         5: iconst_0
         6: istore        4
         8: iload         4
        10: iload_3
        11: if_icmpge     33
        14: aload_2
        15: iload         4
        17: aaload
        18: astore        5
        20: aload         5
        22: aload_1
        23: invokevirtual #26                 // Method wrap:(Lorg/kohsuke/github/GHRepository;)Lorg/kohsuke/github/GHRelease;
        26: pop
        27: iinc          4, 1
        30: goto          8
        33: aload_0
        34: areturn
      LineNumberTable:
        line 207: 0
        line 208: 20
        line 207: 27
        line 210: 33
      LocalVariableTable:
        Start  Length  Slot  Name   Signature
           20       7     5 release   Lorg/kohsuke/github/GHRelease;
            0      35     0 releases   [Lorg/kohsuke/github/GHRelease;
            0      35     1 owner   Lorg/kohsuke/github/GHRepository;
      StackMapTable: number_of_entries = 2
        frame_type = 254 /* append */
          offset_delta = 8
          locals = [ class "[Lorg/kohsuke/github/GHRelease;", int, int ]
        frame_type = 248 /* chop */
          offset_delta = 24

  public org.kohsuke.github.GHAsset uploadAsset(java.io.File, java.lang.String) throws java.io.IOException;
    descriptor: (Ljava/io/File;Ljava/lang/String;)Lorg/kohsuke/github/GHAsset;
    flags: (0x0001) ACC_PUBLIC
    Code:
      stack=4, locals=6, args_size=3
         0: new           #27                 // class java/io/FileInputStream
         3: dup
         4: aload_1
         5: invokespecial #28                 // Method java/io/FileInputStream."<init>":(Ljava/io/File;)V
         8: astore_3
         9: aload_0
        10: aload_1
        11: invokevirtual #29                 // Method java/io/File.getName:()Ljava/lang/String;
        14: aload_3
        15: aload_2
        16: invokevirtual #30                 // Method uploadAsset:(Ljava/lang/String;Ljava/io/InputStream;Ljava/lang/String;)Lorg/kohsuke/github/GHAsset;
        19: astore        4
        21: aload_3
        22: invokevirtual #31                 // Method java/io/FileInputStream.close:()V
        25: aload         4
        27: areturn
        28: astore        5
        30: aload_3
        31: invokevirtual #31                 // Method java/io/FileInputStream.close:()V
        34: aload         5
        36: athrow
      Exception table:
         from    to  target type
             9    21    28   any
            28    30    28   any
      LineNumberTable:
        line 228: 0
        line 230: 9
        line 232: 21
        line 230: 25
        line 232: 28
        line 233: 34
      LocalVariableTable:
        Start  Length  Slot  Name   Signature
            0      37     0  this   Lorg/kohsuke/github/GHRelease;
            0      37     1  file   Ljava/io/File;
            0      37     2 contentType   Ljava/lang/String;
            9      28     3     s   Ljava/io/FileInputStream;
      StackMapTable: number_of_entries = 1
        frame_type = 255 /* full_frame */
          offset_delta = 28
          locals = [ class org/kohsuke/github/GHRelease, class java/io/File, class java/lang/String, class java/io/FileInputStream ]
          stack = [ class java/lang/Throwable ]
    Exceptions:
      throws java.io.IOException

  public org.kohsuke.github.GHAsset uploadAsset(java.lang.String, java.io.InputStream, java.lang.String) throws java.io.IOException;
    descriptor: (Ljava/lang/String;Ljava/io/InputStream;Ljava/lang/String;)Lorg/kohsuke/github/GHAsset;
    flags: (0x0001) ACC_PUBLIC
    Code:
      stack=4, locals=6, args_size=4
         0: aload_0
         1: getfield      #12                 // Field owner:Lorg/kohsuke/github/GHRepository;
         4: invokevirtual #32                 // Method org/kohsuke/github/GHRepository.root:()Lorg/kohsuke/github/GitHub;
         7: invokevirtual #33                 // Method org/kohsuke/github/GitHub.createRequest:()Lorg/kohsuke/github/Requester;
        10: ldc           #34                 // String POST
        12: invokevirtual #35                 // Method org/kohsuke/github/Requester.method:(Ljava/lang/String;)Lorg/kohsuke/github/GitHubRequest$Builder;
        15: checkcast     #36                 // class org/kohsuke/github/Requester
        18: astore        4
        20: aload_0
        21: invokevirtual #37                 // Method getUploadUrl:()Ljava/lang/String;
        24: astore        5
        26: aload         5
        28: iconst_0
        29: aload         5
        31: bipush        123
        33: invokevirtual #38                 // Method java/lang/String.indexOf:(I)I
        36: invokevirtual #39                 // Method java/lang/String.substring:(II)Ljava/lang/String;
        39: astore        5
        41: new           #40                 // class java/lang/StringBuilder
        44: dup
        45: invokespecial #41                 // Method java/lang/StringBuilder."<init>":()V
        48: aload         5
        50: invokevirtual #42                 // Method java/lang/StringBuilder.append:(Ljava/lang/String;)Ljava/lang/StringBuilder;
        53: ldc           #43                 // String ?name=
        55: invokevirtual #42                 // Method java/lang/StringBuilder.append:(Ljava/lang/String;)Ljava/lang/StringBuilder;
        58: aload_1
        59: ldc           #44                 // String UTF-8
        61: invokestatic  #45                 // Method java/net/URLEncoder.encode:(Ljava/lang/String;Ljava/lang/String;)Ljava/lang/String;
        64: invokevirtual #42                 // Method java/lang/StringBuilder.append:(Ljava/lang/String;)Ljava/lang/StringBuilder;
        67: invokevirtual #46                 // Method java/lang/StringBuilder.toString:()Ljava/lang/String;
        70: astore        5
        72: aload         4
        74: aload_3
        75: invokevirtual #47                 // Method org/kohsuke/github/Requester.contentType:(Ljava/lang/String;)Lorg/kohsuke/github/GitHubRequest$Builder;
        78: checkcast     #36                 // class org/kohsuke/github/Requester
        81: aload_2
        82: invokevirtual #48                 // Method org/kohsuke/github/Requester.with:(Ljava/io/InputStream;)Lorg/kohsuke/github/GitHubRequest$Builder;
        85: checkcast     #36                 // class org/kohsuke/github/Requester
        88: aload         5
        90: iconst_0
        91: anewarray     #49                 // class java/lang/String
        94: invokevirtual #50                 // Method org/kohsuke/github/Requester.withUrlPath:(Ljava/lang/String;[Ljava/lang/String;)Lorg/kohsuke/github/GitHubRequest$Builder;
        97: checkcast     #36                 // class org/kohsuke/github/Requester
       100: ldc           #51                 // class org/kohsuke/github/GHAsset
       102: invokevirtual #52                 // Method org/kohsuke/github/Requester.fetch:(Ljava/lang/Class;)Ljava/lang/Object;
       105: checkcast     #51                 // class org/kohsuke/github/GHAsset
       108: aload_0
       109: invokevirtual #53                 // Method org/kohsuke/github/GHAsset.wrap:(Lorg/kohsuke/github/GHRelease;)Lorg/kohsuke/github/GHAsset;
       112: areturn
      LineNumberTable:
        line 250: 0
        line 251: 20
        line 253: 26
        line 254: 41
        line 255: 72
      LocalVariableTable:
        Start  Length  Slot  Name   Signature
            0     113     0  this   Lorg/kohsuke/github/GHRelease;
            0     113     1 filename   Ljava/lang/String;
            0     113     2 stream   Ljava/io/InputStream;
            0     113     3 contentType   Ljava/lang/String;
           20      93     4 builder   Lorg/kohsuke/github/Requester;
           26      87     5   url   Ljava/lang/String;
    Exceptions:
      throws java.io.IOException

  public java.util.List<org.kohsuke.github.GHAsset> assets();
    descriptor: ()Ljava/util/List;
    flags: (0x0001) ACC_PUBLIC
    Code:
      stack=1, locals=1, args_size=1
         0: aload_0
         1: getfield      #54                 // Field assets:Ljava/util/List;
         4: invokestatic  #55                 // Method java/util/Collections.unmodifiableList:(Ljava/util/List;)Ljava/util/List;
         7: areturn
      LineNumberTable:
        line 269: 0
      LocalVariableTable:
        Start  Length  Slot  Name   Signature
            0       8     0  this   Lorg/kohsuke/github/GHRelease;
    Deprecated: true
    Signature: #168                         // ()Ljava/util/List<Lorg/kohsuke/github/GHAsset;>;
    RuntimeVisibleAnnotations:
      0: #119()
        java.lang.Deprecated

  public java.util.List<org.kohsuke.github.GHAsset> getAssets() throws java.io.IOException;
    descriptor: ()Ljava/util/List;
    flags: (0x0001) ACC_PUBLIC
    Code:
      stack=1, locals=1, args_size=1
         0: aload_0
         1: invokevirtual #56                 // Method listAssets:()Lorg/kohsuke/github/PagedIterable;
         4: invokevirtual #57                 // Method org/kohsuke/github/PagedIterable.toList:()Ljava/util/List;
         7: areturn
      LineNumberTable:
        line 284: 0
      LocalVariableTable:
        Start  Length  Slot  Name   Signature
            0       8     0  this   Lorg/kohsuke/github/GHRelease;
    Exceptions:
      throws java.io.IOException
    Deprecated: true
    Signature: #168                         // ()Ljava/util/List<Lorg/kohsuke/github/GHAsset;>;
    RuntimeVisibleAnnotations:
      0: #119()
        java.lang.Deprecated

  public org.kohsuke.github.PagedIterable<org.kohsuke.github.GHAsset> listAssets() throws java.io.IOException;
    descriptor: ()Lorg/kohsuke/github/PagedIterable;
    flags: (0x0001) ACC_PUBLIC
    Code:
      stack=3, locals=2, args_size=1
         0: aload_0
         1: getfield      #12                 // Field owner:Lorg/kohsuke/github/GHRepository;
         4: invokevirtual #32                 // Method org/kohsuke/github/GHRepository.root:()Lorg/kohsuke/github/GitHub;
         7: invokevirtual #33                 // Method org/kohsuke/github/GitHub.createRequest:()Lorg/kohsuke/github/Requester;
        10: astore_1
        11: aload_1
        12: aload_0
        13: ldc           #58                 // String assets
        15: invokespecial #59                 // Method getApiTailUrl:(Ljava/lang/String;)Ljava/lang/String;
        18: iconst_0
        19: anewarray     #49                 // class java/lang/String
        22: invokevirtual #50                 // Method org/kohsuke/github/Requester.withUrlPath:(Ljava/lang/String;[Ljava/lang/String;)Lorg/kohsuke/github/GitHubRequest$Builder;
        25: checkcast     #36                 // class org/kohsuke/github/Requester
        28: ldc           #60                 // class "[Lorg/kohsuke/github/GHAsset;"
        30: aload_0
        31: invokedynamic #61,  0             // InvokeDynamic #0:accept:(Lorg/kohsuke/github/GHRelease;)Ljava/util/function/Consumer;
        36: invokevirtual #62                 // Method org/kohsuke/github/Requester.toIterable:(Ljava/lang/Class;Ljava/util/function/Consumer;)Lorg/kohsuke/github/PagedIterable;
        39: areturn
      LineNumberTable:
        line 295: 0
        line 296: 11
      LocalVariableTable:
        Start  Length  Slot  Name   Signature
            0      40     0  this   Lorg/kohsuke/github/GHRelease;
           11      29     1 builder   Lorg/kohsuke/github/Requester;
    Exceptions:
      throws java.io.IOException
    Signature: #172                         // ()Lorg/kohsuke/github/PagedIterable<Lorg/kohsuke/github/GHAsset;>;

  public void delete() throws java.io.IOException;
    descriptor: ()V
    flags: (0x0001) ACC_PUBLIC
    Code:
      stack=5, locals=1, args_size=1
         0: aload_0
         1: invokevirtual #63                 // Method root:()Lorg/kohsuke/github/GitHub;
         4: invokevirtual #33                 // Method org/kohsuke/github/GitHub.createRequest:()Lorg/kohsuke/github/Requester;
         7: ldc           #64                 // String DELETE
         9: invokevirtual #35                 // Method org/kohsuke/github/Requester.method:(Ljava/lang/String;)Lorg/kohsuke/github/GitHubRequest$Builder;
        12: checkcast     #36                 // class org/kohsuke/github/Requester
        15: aload_0
        16: getfield      #12                 // Field owner:Lorg/kohsuke/github/GHRepository;
        19: new           #40                 // class java/lang/StringBuilder
        22: dup
        23: invokespecial #41                 // Method java/lang/StringBuilder."<init>":()V
        26: ldc           #65                 // String releases/
        28: invokevirtual #42                 // Method java/lang/StringBuilder.append:(Ljava/lang/String;)Ljava/lang/StringBuilder;
        31: aload_0
        32: invokevirtual #66                 // Method getId:()J
        35: invokevirtual #67                 // Method java/lang/StringBuilder.append:(J)Ljava/lang/StringBuilder;
        38: invokevirtual #46                 // Method java/lang/StringBuilder.toString:()Ljava/lang/String;
        41: invokevirtual #68                 // Method org/kohsuke/github/GHRepository.getApiTailUrl:(Ljava/lang/String;)Ljava/lang/String;
        44: iconst_0
        45: anewarray     #49                 // class java/lang/String
        48: invokevirtual #50                 // Method org/kohsuke/github/Requester.withUrlPath:(Ljava/lang/String;[Ljava/lang/String;)Lorg/kohsuke/github/GitHubRequest$Builder;
        51: checkcast     #36                 // class org/kohsuke/github/Requester
        54: invokevirtual #69                 // Method org/kohsuke/github/Requester.send:()V
        57: return
      LineNumberTable:
        line 306: 0
        line 307: 57
      LocalVariableTable:
        Start  Length  Slot  Name   Signature
            0      58     0  this   Lorg/kohsuke/github/GHRelease;
    Exceptions:
      throws java.io.IOException

  public org.kohsuke.github.GHReleaseUpdater update();
    descriptor: ()Lorg/kohsuke/github/GHReleaseUpdater;
    flags: (0x0001) ACC_PUBLIC
    Code:
      stack=3, locals=1, args_size=1
         0: new           #70                 // class org/kohsuke/github/GHReleaseUpdater
         3: dup
         4: aload_0
         5: invokespecial #71                 // Method org/kohsuke/github/GHReleaseUpdater."<init>":(Lorg/kohsuke/github/GHRelease;)V
         8: areturn
      LineNumberTable:
        line 315: 0
      LocalVariableTable:
        Start  Length  Slot  Name   Signature
            0       9     0  this   Lorg/kohsuke/github/GHRelease;

  private java.lang.String getApiTailUrl(java.lang.String);
    descriptor: (Ljava/lang/String;)Ljava/lang/String;
    flags: (0x0002) ACC_PRIVATE
    Code:
      stack=7, locals=2, args_size=2
         0: aload_0
         1: getfield      #12                 // Field owner:Lorg/kohsuke/github/GHRepository;
         4: ldc           #72                 // String releases/%s/%s
         6: iconst_2
         7: anewarray     #73                 // class java/lang/Object
        10: dup
        11: iconst_0
        12: aload_0
        13: invokevirtual #66                 // Method getId:()J
        16: invokestatic  #74                 // Method java/lang/Long.valueOf:(J)Ljava/lang/Long;
        19: aastore
        20: dup
        21: iconst_1
        22: aload_1
        23: aastore
        24: invokestatic  #75                 // Method java/lang/String.format:(Ljava/lang/String;[Ljava/lang/Object;)Ljava/lang/String;
        27: invokevirtual #68                 // Method org/kohsuke/github/GHRepository.getApiTailUrl:(Ljava/lang/String;)Ljava/lang/String;
        30: areturn
      LineNumberTable:
        line 319: 0
      LocalVariableTable:
        Start  Length  Slot  Name   Signature
            0      31     0  this   Lorg/kohsuke/github/GHRelease;
            0      31     1   end   Ljava/lang/String;

  private void lambda$listAssets$0(org.kohsuke.github.GHAsset);
    descriptor: (Lorg/kohsuke/github/GHAsset;)V
    flags: (0x1002) ACC_PRIVATE, ACC_SYNTHETIC
    Code:
      stack=2, locals=2, args_size=2
         0: aload_1
         1: aload_0
         2: invokevirtual #53                 // Method org/kohsuke/github/GHAsset.wrap:(Lorg/kohsuke/github/GHRelease;)Lorg/kohsuke/github/GHAsset;
         5: pop
         6: return
      LineNumberTable:
        line 296: 0
      LocalVariableTable:
        Start  Length  Slot  Name   Signature
            0       7     0  this   Lorg/kohsuke/github/GHRelease;
            0       7     1  item   Lorg/kohsuke/github/GHAsset;
}
SourceFile: "GHRelease.java"
InnerClasses:
  static #291= #290 of #332;              // Builder=class org/kohsuke/github/GitHubRequest$Builder of class org/kohsuke/github/GitHubRequest
  public static final #341= #340 of #343; // Lookup=class java/lang/invoke/MethodHandles$Lookup of class java/lang/invoke/MethodHandles
BootstrapMethods:
  0: #250 REF_invokeStatic java/lang/invoke/LambdaMetafactory.metafactory:(Ljava/lang/invoke/MethodHandles$Lookup;Ljava/lang/String;Ljava/lang/invoke/MethodType;Ljava/lang/invoke/MethodType;Ljava/lang/invoke/MethodHandle;Ljava/lang/invoke/MethodType;)Ljava/lang/invoke/CallSite;
    Method arguments:
      #251 (Ljava/lang/Object;)V
      #252 REF_invokeSpecial org/kohsuke/github/GHRelease.lambda$listAssets$0:(Lorg/kohsuke/github/GHAsset;)V
      #253 (Lorg/kohsuke/github/GHAsset;)V
