Classfile /Users/mw/Projects/slang-braindump/.jar/jar8/assemble/slang-braindump/assemble/content/org/kohsuke/github/GHRepositoryDiscussion.class
  Last modified May 29, 2022; size 3158 bytes
  SHA-256 checksum a794a958458afe0ef3cbf0f3866c8675779c911437fbd6501e01e3ed1241f4df
  Compiled from "GHRepositoryDiscussion.java"
public class org.kohsuke.github.GHRepositoryDiscussion extends org.kohsuke.github.GHObject
  minor version: 0
  major version: 52
  flags: (0x0021) ACC_PUBLIC, ACC_SUPER
  this_class: #24                         // org/kohsuke/github/GHRepositoryDiscussion
  super_class: #25                        // org/kohsuke/github/GHObject
  interfaces: 0, fields: 15, methods: 16, attributes: 2
Constant pool:
    #1 = Methodref          #25.#86       // org/kohsuke/github/GHObject."<init>":()V
    #2 = Fieldref           #24.#87       // org/kohsuke/github/GHRepositoryDiscussion.category:Lorg/kohsuke/github/GHRepositoryDiscussion$Category;
    #3 = Fieldref           #24.#88       // org/kohsuke/github/GHRepositoryDiscussion.answerHtmlUrl:Ljava/lang/String;
    #4 = Methodref          #89.#90       // org/kohsuke/github/GitHubClient.parseURL:(Ljava/lang/String;)Ljava/net/URL;
    #5 = Fieldref           #24.#91       // org/kohsuke/github/GHRepositoryDiscussion.answerChosenAt:Ljava/lang/String;
    #6 = Methodref          #89.#92       // org/kohsuke/github/GitHubClient.parseDate:(Ljava/lang/String;)Ljava/util/Date;
    #7 = Methodref          #24.#93       // org/kohsuke/github/GHRepositoryDiscussion.root:()Lorg/kohsuke/github/GitHub;
    #8 = Fieldref           #24.#94       // org/kohsuke/github/GHRepositoryDiscussion.answerChosenBy:Lorg/kohsuke/github/GHUser;
    #9 = Methodref          #95.#96       // org/kohsuke/github/GitHub.intern:(Lorg/kohsuke/github/GHUser;)Lorg/kohsuke/github/GHUser;
   #10 = Fieldref           #24.#97       // org/kohsuke/github/GHRepositoryDiscussion.htmlUrl:Ljava/lang/String;
   #11 = Fieldref           #24.#98       // org/kohsuke/github/GHRepositoryDiscussion.number:I
   #12 = Fieldref           #24.#99       // org/kohsuke/github/GHRepositoryDiscussion.title:Ljava/lang/String;
   #13 = Fieldref           #24.#100      // org/kohsuke/github/GHRepositoryDiscussion.user:Lorg/kohsuke/github/GHUser;
   #14 = Class              #101          // org/kohsuke/github/GHRepositoryDiscussion$State
   #15 = Fieldref           #24.#102      // org/kohsuke/github/GHRepositoryDiscussion.state:Ljava/lang/String;
   #16 = Fieldref           #14.#103      // org/kohsuke/github/GHRepositoryDiscussion$State.UNKNOWN:Lorg/kohsuke/github/GHRepositoryDiscussion$State;
   #17 = Methodref          #104.#105     // org/kohsuke/github/internal/EnumUtils.getEnumOrDefault:(Ljava/lang/Class;Ljava/lang/String;Ljava/lang/Enum;)Ljava/lang/Enum;
   #18 = Fieldref           #24.#106      // org/kohsuke/github/GHRepositoryDiscussion.locked:Z
   #19 = Fieldref           #24.#107      // org/kohsuke/github/GHRepositoryDiscussion.comments:I
   #20 = Fieldref           #24.#108      // org/kohsuke/github/GHRepositoryDiscussion.authorAssociation:Lorg/kohsuke/github/GHCommentAuthorAssociation;
   #21 = Fieldref           #24.#109      // org/kohsuke/github/GHRepositoryDiscussion.activeLockReason:Ljava/lang/String;
   #22 = Fieldref           #24.#110      // org/kohsuke/github/GHRepositoryDiscussion.body:Ljava/lang/String;
   #23 = Fieldref           #24.#111      // org/kohsuke/github/GHRepositoryDiscussion.timelineUrl:Ljava/lang/String;
   #24 = Class              #112          // org/kohsuke/github/GHRepositoryDiscussion
   #25 = Class              #113          // org/kohsuke/github/GHObject
   #26 = Utf8               State
   #27 = Utf8               InnerClasses
   #28 = Class              #114          // org/kohsuke/github/GHRepositoryDiscussion$Category
   #29 = Utf8               Category
   #30 = Utf8               category
   #31 = Utf8               Lorg/kohsuke/github/GHRepositoryDiscussion$Category;
   #32 = Utf8               answerHtmlUrl
   #33 = Utf8               Ljava/lang/String;
   #34 = Utf8               answerChosenAt
   #35 = Utf8               answerChosenBy
   #36 = Utf8               Lorg/kohsuke/github/GHUser;
   #37 = Utf8               htmlUrl
   #38 = Utf8               number
   #39 = Utf8               I
   #40 = Utf8               title
   #41 = Utf8               user
   #42 = Utf8               state
   #43 = Utf8               locked
   #44 = Utf8               Z
   #45 = Utf8               comments
   #46 = Utf8               authorAssociation
   #47 = Utf8               Lorg/kohsuke/github/GHCommentAuthorAssociation;
   #48 = Utf8               activeLockReason
   #49 = Utf8               body
   #50 = Utf8               timelineUrl
   #51 = Utf8               <init>
   #52 = Utf8               ()V
   #53 = Utf8               Code
   #54 = Utf8               LineNumberTable
   #55 = Utf8               LocalVariableTable
   #56 = Utf8               this
   #57 = Utf8               Lorg/kohsuke/github/GHRepositoryDiscussion;
   #58 = Utf8               getCategory
   #59 = Utf8               ()Lorg/kohsuke/github/GHRepositoryDiscussion$Category;
   #60 = Utf8               getAnswerHtmlUrl
   #61 = Utf8               ()Ljava/net/URL;
   #62 = Utf8               getAnswerChosenAt
   #63 = Utf8               ()Ljava/util/Date;
   #64 = Utf8               getAnswerChosenBy
   #65 = Utf8               ()Lorg/kohsuke/github/GHUser;
   #66 = Utf8               Exceptions
   #67 = Class              #115          // java/io/IOException
   #68 = Utf8               getHtmlUrl
   #69 = Utf8               getNumber
   #70 = Utf8               ()I
   #71 = Utf8               getTitle
   #72 = Utf8               ()Ljava/lang/String;
   #73 = Utf8               getUser
   #74 = Utf8               getState
   #75 = Utf8               ()Lorg/kohsuke/github/GHRepositoryDiscussion$State;
   #76 = Utf8               isLocked
   #77 = Utf8               ()Z
   #78 = Utf8               getComments
   #79 = Utf8               getAuthorAssociation
   #80 = Utf8               ()Lorg/kohsuke/github/GHCommentAuthorAssociation;
   #81 = Utf8               getActiveLockReason
   #82 = Utf8               getBody
   #83 = Utf8               getTimelineUrl
   #84 = Utf8               SourceFile
   #85 = Utf8               GHRepositoryDiscussion.java
   #86 = NameAndType        #51:#52       // "<init>":()V
   #87 = NameAndType        #30:#31       // category:Lorg/kohsuke/github/GHRepositoryDiscussion$Category;
   #88 = NameAndType        #32:#33       // answerHtmlUrl:Ljava/lang/String;
   #89 = Class              #116          // org/kohsuke/github/GitHubClient
   #90 = NameAndType        #117:#118     // parseURL:(Ljava/lang/String;)Ljava/net/URL;
   #91 = NameAndType        #34:#33       // answerChosenAt:Ljava/lang/String;
   #92 = NameAndType        #119:#120     // parseDate:(Ljava/lang/String;)Ljava/util/Date;
   #93 = NameAndType        #121:#122     // root:()Lorg/kohsuke/github/GitHub;
   #94 = NameAndType        #35:#36       // answerChosenBy:Lorg/kohsuke/github/GHUser;
   #95 = Class              #123          // org/kohsuke/github/GitHub
   #96 = NameAndType        #124:#125     // intern:(Lorg/kohsuke/github/GHUser;)Lorg/kohsuke/github/GHUser;
   #97 = NameAndType        #37:#33       // htmlUrl:Ljava/lang/String;
   #98 = NameAndType        #38:#39       // number:I
   #99 = NameAndType        #40:#33       // title:Ljava/lang/String;
  #100 = NameAndType        #41:#36       // user:Lorg/kohsuke/github/GHUser;
  #101 = Utf8               org/kohsuke/github/GHRepositoryDiscussion$State
  #102 = NameAndType        #42:#33       // state:Ljava/lang/String;
  #103 = NameAndType        #126:#127     // UNKNOWN:Lorg/kohsuke/github/GHRepositoryDiscussion$State;
  #104 = Class              #128          // org/kohsuke/github/internal/EnumUtils
  #105 = NameAndType        #129:#130     // getEnumOrDefault:(Ljava/lang/Class;Ljava/lang/String;Ljava/lang/Enum;)Ljava/lang/Enum;
  #106 = NameAndType        #43:#44       // locked:Z
  #107 = NameAndType        #45:#39       // comments:I
  #108 = NameAndType        #46:#47       // authorAssociation:Lorg/kohsuke/github/GHCommentAuthorAssociation;
  #109 = NameAndType        #48:#33       // activeLockReason:Ljava/lang/String;
  #110 = NameAndType        #49:#33       // body:Ljava/lang/String;
  #111 = NameAndType        #50:#33       // timelineUrl:Ljava/lang/String;
  #112 = Utf8               org/kohsuke/github/GHRepositoryDiscussion
  #113 = Utf8               org/kohsuke/github/GHObject
  #114 = Utf8               org/kohsuke/github/GHRepositoryDiscussion$Category
  #115 = Utf8               java/io/IOException
  #116 = Utf8               org/kohsuke/github/GitHubClient
  #117 = Utf8               parseURL
  #118 = Utf8               (Ljava/lang/String;)Ljava/net/URL;
  #119 = Utf8               parseDate
  #120 = Utf8               (Ljava/lang/String;)Ljava/util/Date;
  #121 = Utf8               root
  #122 = Utf8               ()Lorg/kohsuke/github/GitHub;
  #123 = Utf8               org/kohsuke/github/GitHub
  #124 = Utf8               intern
  #125 = Utf8               (Lorg/kohsuke/github/GHUser;)Lorg/kohsuke/github/GHUser;
  #126 = Utf8               UNKNOWN
  #127 = Utf8               Lorg/kohsuke/github/GHRepositoryDiscussion$State;
  #128 = Utf8               org/kohsuke/github/internal/EnumUtils
  #129 = Utf8               getEnumOrDefault
  #130 = Utf8               (Ljava/lang/Class;Ljava/lang/String;Ljava/lang/Enum;)Ljava/lang/Enum;
{
  private org.kohsuke.github.GHRepositoryDiscussion$Category category;
    descriptor: Lorg/kohsuke/github/GHRepositoryDiscussion$Category;
    flags: (0x0002) ACC_PRIVATE

  private java.lang.String answerHtmlUrl;
    descriptor: Ljava/lang/String;
    flags: (0x0002) ACC_PRIVATE

  private java.lang.String answerChosenAt;
    descriptor: Ljava/lang/String;
    flags: (0x0002) ACC_PRIVATE

  private org.kohsuke.github.GHUser answerChosenBy;
    descriptor: Lorg/kohsuke/github/GHUser;
    flags: (0x0002) ACC_PRIVATE

  private java.lang.String htmlUrl;
    descriptor: Ljava/lang/String;
    flags: (0x0002) ACC_PRIVATE

  private int number;
    descriptor: I
    flags: (0x0002) ACC_PRIVATE

  private java.lang.String title;
    descriptor: Ljava/lang/String;
    flags: (0x0002) ACC_PRIVATE

  private org.kohsuke.github.GHUser user;
    descriptor: Lorg/kohsuke/github/GHUser;
    flags: (0x0002) ACC_PRIVATE

  private java.lang.String state;
    descriptor: Ljava/lang/String;
    flags: (0x0002) ACC_PRIVATE

  private boolean locked;
    descriptor: Z
    flags: (0x0002) ACC_PRIVATE

  private int comments;
    descriptor: I
    flags: (0x0002) ACC_PRIVATE

  private org.kohsuke.github.GHCommentAuthorAssociation authorAssociation;
    descriptor: Lorg/kohsuke/github/GHCommentAuthorAssociation;
    flags: (0x0002) ACC_PRIVATE

  private java.lang.String activeLockReason;
    descriptor: Ljava/lang/String;
    flags: (0x0002) ACC_PRIVATE

  private java.lang.String body;
    descriptor: Ljava/lang/String;
    flags: (0x0002) ACC_PRIVATE

  private java.lang.String timelineUrl;
    descriptor: Ljava/lang/String;
    flags: (0x0002) ACC_PRIVATE

  public org.kohsuke.github.GHRepositoryDiscussion();
    descriptor: ()V
    flags: (0x0001) ACC_PUBLIC
    Code:
      stack=1, locals=1, args_size=1
         0: aload_0
         1: invokespecial #1                  // Method org/kohsuke/github/GHObject."<init>":()V
         4: return
      LineNumberTable:
        line 22: 0
      LocalVariableTable:
        Start  Length  Slot  Name   Signature
            0       5     0  this   Lorg/kohsuke/github/GHRepositoryDiscussion;

  public org.kohsuke.github.GHRepositoryDiscussion$Category getCategory();
    descriptor: ()Lorg/kohsuke/github/GHRepositoryDiscussion$Category;
    flags: (0x0001) ACC_PUBLIC
    Code:
      stack=1, locals=1, args_size=1
         0: aload_0
         1: getfield      #2                  // Field category:Lorg/kohsuke/github/GHRepositoryDiscussion$Category;
         4: areturn
      LineNumberTable:
        line 44: 0
      LocalVariableTable:
        Start  Length  Slot  Name   Signature
            0       5     0  this   Lorg/kohsuke/github/GHRepositoryDiscussion;

  public java.net.URL getAnswerHtmlUrl();
    descriptor: ()Ljava/net/URL;
    flags: (0x0001) ACC_PUBLIC
    Code:
      stack=1, locals=1, args_size=1
         0: aload_0
         1: getfield      #3                  // Field answerHtmlUrl:Ljava/lang/String;
         4: invokestatic  #4                  // Method org/kohsuke/github/GitHubClient.parseURL:(Ljava/lang/String;)Ljava/net/URL;
         7: areturn
      LineNumberTable:
        line 48: 0
      LocalVariableTable:
        Start  Length  Slot  Name   Signature
            0       8     0  this   Lorg/kohsuke/github/GHRepositoryDiscussion;

  public java.util.Date getAnswerChosenAt();
    descriptor: ()Ljava/util/Date;
    flags: (0x0001) ACC_PUBLIC
    Code:
      stack=1, locals=1, args_size=1
         0: aload_0
         1: getfield      #5                  // Field answerChosenAt:Ljava/lang/String;
         4: invokestatic  #6                  // Method org/kohsuke/github/GitHubClient.parseDate:(Ljava/lang/String;)Ljava/util/Date;
         7: areturn
      LineNumberTable:
        line 52: 0
      LocalVariableTable:
        Start  Length  Slot  Name   Signature
            0       8     0  this   Lorg/kohsuke/github/GHRepositoryDiscussion;

  public org.kohsuke.github.GHUser getAnswerChosenBy() throws java.io.IOException;
    descriptor: ()Lorg/kohsuke/github/GHUser;
    flags: (0x0001) ACC_PUBLIC
    Code:
      stack=2, locals=1, args_size=1
         0: aload_0
         1: invokevirtual #7                  // Method root:()Lorg/kohsuke/github/GitHub;
         4: aload_0
         5: getfield      #8                  // Field answerChosenBy:Lorg/kohsuke/github/GHUser;
         8: invokevirtual #9                  // Method org/kohsuke/github/GitHub.intern:(Lorg/kohsuke/github/GHUser;)Lorg/kohsuke/github/GHUser;
        11: areturn
      LineNumberTable:
        line 56: 0
      LocalVariableTable:
        Start  Length  Slot  Name   Signature
            0      12     0  this   Lorg/kohsuke/github/GHRepositoryDiscussion;
    Exceptions:
      throws java.io.IOException

  public java.net.URL getHtmlUrl();
    descriptor: ()Ljava/net/URL;
    flags: (0x0001) ACC_PUBLIC
    Code:
      stack=1, locals=1, args_size=1
         0: aload_0
         1: getfield      #10                 // Field htmlUrl:Ljava/lang/String;
         4: invokestatic  #4                  // Method org/kohsuke/github/GitHubClient.parseURL:(Ljava/lang/String;)Ljava/net/URL;
         7: areturn
      LineNumberTable:
        line 60: 0
      LocalVariableTable:
        Start  Length  Slot  Name   Signature
            0       8     0  this   Lorg/kohsuke/github/GHRepositoryDiscussion;

  public int getNumber();
    descriptor: ()I
    flags: (0x0001) ACC_PUBLIC
    Code:
      stack=1, locals=1, args_size=1
         0: aload_0
         1: getfield      #11                 // Field number:I
         4: ireturn
      LineNumberTable:
        line 64: 0
      LocalVariableTable:
        Start  Length  Slot  Name   Signature
            0       5     0  this   Lorg/kohsuke/github/GHRepositoryDiscussion;

  public java.lang.String getTitle();
    descriptor: ()Ljava/lang/String;
    flags: (0x0001) ACC_PUBLIC
    Code:
      stack=1, locals=1, args_size=1
         0: aload_0
         1: getfield      #12                 // Field title:Ljava/lang/String;
         4: areturn
      LineNumberTable:
        line 68: 0
      LocalVariableTable:
        Start  Length  Slot  Name   Signature
            0       5     0  this   Lorg/kohsuke/github/GHRepositoryDiscussion;

  public org.kohsuke.github.GHUser getUser() throws java.io.IOException;
    descriptor: ()Lorg/kohsuke/github/GHUser;
    flags: (0x0001) ACC_PUBLIC
    Code:
      stack=2, locals=1, args_size=1
         0: aload_0
         1: invokevirtual #7                  // Method root:()Lorg/kohsuke/github/GitHub;
         4: aload_0
         5: getfield      #13                 // Field user:Lorg/kohsuke/github/GHUser;
         8: invokevirtual #9                  // Method org/kohsuke/github/GitHub.intern:(Lorg/kohsuke/github/GHUser;)Lorg/kohsuke/github/GHUser;
        11: areturn
      LineNumberTable:
        line 72: 0
      LocalVariableTable:
        Start  Length  Slot  Name   Signature
            0      12     0  this   Lorg/kohsuke/github/GHRepositoryDiscussion;
    Exceptions:
      throws java.io.IOException

  public org.kohsuke.github.GHRepositoryDiscussion$State getState();
    descriptor: ()Lorg/kohsuke/github/GHRepositoryDiscussion$State;
    flags: (0x0001) ACC_PUBLIC
    Code:
      stack=3, locals=1, args_size=1
         0: ldc           #14                 // class org/kohsuke/github/GHRepositoryDiscussion$State
         2: aload_0
         3: getfield      #15                 // Field state:Ljava/lang/String;
         6: getstatic     #16                 // Field org/kohsuke/github/GHRepositoryDiscussion$State.UNKNOWN:Lorg/kohsuke/github/GHRepositoryDiscussion$State;
         9: invokestatic  #17                 // Method org/kohsuke/github/internal/EnumUtils.getEnumOrDefault:(Ljava/lang/Class;Ljava/lang/String;Ljava/lang/Enum;)Ljava/lang/Enum;
        12: checkcast     #14                 // class org/kohsuke/github/GHRepositoryDiscussion$State
        15: areturn
      LineNumberTable:
        line 76: 0
      LocalVariableTable:
        Start  Length  Slot  Name   Signature
            0      16     0  this   Lorg/kohsuke/github/GHRepositoryDiscussion;

  public boolean isLocked();
    descriptor: ()Z
    flags: (0x0001) ACC_PUBLIC
    Code:
      stack=1, locals=1, args_size=1
         0: aload_0
         1: getfield      #18                 // Field locked:Z
         4: ireturn
      LineNumberTable:
        line 80: 0
      LocalVariableTable:
        Start  Length  Slot  Name   Signature
            0       5     0  this   Lorg/kohsuke/github/GHRepositoryDiscussion;

  public int getComments();
    descriptor: ()I
    flags: (0x0001) ACC_PUBLIC
    Code:
      stack=1, locals=1, args_size=1
         0: aload_0
         1: getfield      #19                 // Field comments:I
         4: ireturn
      LineNumberTable:
        line 84: 0
      LocalVariableTable:
        Start  Length  Slot  Name   Signature
            0       5     0  this   Lorg/kohsuke/github/GHRepositoryDiscussion;

  public org.kohsuke.github.GHCommentAuthorAssociation getAuthorAssociation();
    descriptor: ()Lorg/kohsuke/github/GHCommentAuthorAssociation;
    flags: (0x0001) ACC_PUBLIC
    Code:
      stack=1, locals=1, args_size=1
         0: aload_0
         1: getfield      #20                 // Field authorAssociation:Lorg/kohsuke/github/GHCommentAuthorAssociation;
         4: areturn
      LineNumberTable:
        line 88: 0
      LocalVariableTable:
        Start  Length  Slot  Name   Signature
            0       5     0  this   Lorg/kohsuke/github/GHRepositoryDiscussion;

  public java.lang.String getActiveLockReason();
    descriptor: ()Ljava/lang/String;
    flags: (0x0001) ACC_PUBLIC
    Code:
      stack=1, locals=1, args_size=1
         0: aload_0
         1: getfield      #21                 // Field activeLockReason:Ljava/lang/String;
         4: areturn
      LineNumberTable:
        line 92: 0
      LocalVariableTable:
        Start  Length  Slot  Name   Signature
            0       5     0  this   Lorg/kohsuke/github/GHRepositoryDiscussion;

  public java.lang.String getBody();
    descriptor: ()Ljava/lang/String;
    flags: (0x0001) ACC_PUBLIC
    Code:
      stack=1, locals=1, args_size=1
         0: aload_0
         1: getfield      #22                 // Field body:Ljava/lang/String;
         4: areturn
      LineNumberTable:
        line 96: 0
      LocalVariableTable:
        Start  Length  Slot  Name   Signature
            0       5     0  this   Lorg/kohsuke/github/GHRepositoryDiscussion;

  public java.lang.String getTimelineUrl();
    descriptor: ()Ljava/lang/String;
    flags: (0x0001) ACC_PUBLIC
    Code:
      stack=1, locals=1, args_size=1
         0: aload_0
         1: getfield      #23                 // Field timelineUrl:Ljava/lang/String;
         4: areturn
      LineNumberTable:
        line 100: 0
      LocalVariableTable:
        Start  Length  Slot  Name   Signature
            0       5     0  this   Lorg/kohsuke/github/GHRepositoryDiscussion;
}
SourceFile: "GHRepositoryDiscussion.java"
InnerClasses:
  public static final #26= #14 of #24;    // State=class org/kohsuke/github/GHRepositoryDiscussion$State of class org/kohsuke/github/GHRepositoryDiscussion
  public static #29= #28 of #24;          // Category=class org/kohsuke/github/GHRepositoryDiscussion$Category of class org/kohsuke/github/GHRepositoryDiscussion
