Classfile /Users/mw/Projects/slang-braindump/.jar/jar8/assemble/slang-braindump/assemble/content/org/kohsuke/github/GHRepositoryStatistics$ContributorStats$Week.class
  Last modified May 29, 2022; size 1672 bytes
  SHA-256 checksum c9f6f64747c9e501df1248fbd4f77412703d6cf652528fee71fbb61b5c366999
  Compiled from "GHRepositoryStatistics.java"
public class org.kohsuke.github.GHRepositoryStatistics$ContributorStats$Week
  minor version: 0
  major version: 52
  flags: (0x0021) ACC_PUBLIC, ACC_SUPER
  this_class: #11                         // org/kohsuke/github/GHRepositoryStatistics$ContributorStats$Week
  super_class: #7                         // java/lang/Object
  interfaces: 0, fields: 4, methods: 6, attributes: 3
Constant pool:
   #1 = Methodref          #7.#48         // java/lang/Object."<init>":()V
   #2 = Fieldref           #11.#49        // org/kohsuke/github/GHRepositoryStatistics$ContributorStats$Week.w:J
   #3 = Fieldref           #11.#50        // org/kohsuke/github/GHRepositoryStatistics$ContributorStats$Week.a:I
   #4 = Fieldref           #11.#51        // org/kohsuke/github/GHRepositoryStatistics$ContributorStats$Week.d:I
   #5 = Fieldref           #11.#52        // org/kohsuke/github/GHRepositoryStatistics$ContributorStats$Week.c:I
   #6 = String             #53            // Week starting %d - Additions: %d, Deletions: %d, Commits: %d
   #7 = Class              #54            // java/lang/Object
   #8 = Methodref          #55.#56        // java/lang/Long.valueOf:(J)Ljava/lang/Long;
   #9 = Methodref          #57.#58        // java/lang/Integer.valueOf:(I)Ljava/lang/Integer;
  #10 = Methodref          #59.#60        // java/lang/String.format:(Ljava/lang/String;[Ljava/lang/Object;)Ljava/lang/String;
  #11 = Class              #61            // org/kohsuke/github/GHRepositoryStatistics$ContributorStats$Week
  #12 = Utf8               w
  #13 = Utf8               J
  #14 = Utf8               a
  #15 = Utf8               I
  #16 = Utf8               d
  #17 = Utf8               c
  #18 = Utf8               <init>
  #19 = Utf8               ()V
  #20 = Utf8               Code
  #21 = Utf8               LineNumberTable
  #22 = Utf8               LocalVariableTable
  #23 = Utf8               this
  #24 = Class              #63            // org/kohsuke/github/GHRepositoryStatistics$ContributorStats
  #25 = Utf8               ContributorStats
  #26 = Utf8               InnerClasses
  #27 = Utf8               Week
  #28 = Utf8               Lorg/kohsuke/github/GHRepositoryStatistics$ContributorStats$Week;
  #29 = Utf8               getWeekTimestamp
  #30 = Utf8               ()J
  #31 = Utf8               getNumberOfAdditions
  #32 = Utf8               ()I
  #33 = Utf8               getNumberOfDeletions
  #34 = Utf8               getNumberOfCommits
  #35 = Utf8               toString
  #36 = Utf8               ()Ljava/lang/String;
  #37 = Utf8               SourceFile
  #38 = Utf8               GHRepositoryStatistics.java
  #39 = Utf8               RuntimeInvisibleAnnotations
  #40 = Utf8               Ledu/umd/cs/findbugs/annotations/SuppressFBWarnings;
  #41 = Utf8               value
  #42 = Utf8               UWF_UNWRITTEN_PUBLIC_OR_PROTECTED_FIELD
  #43 = Utf8               UWF_UNWRITTEN_FIELD
  #44 = Utf8               NP_UNWRITTEN_FIELD
  #45 = Utf8               URF_UNREAD_FIELD
  #46 = Utf8               justification
  #47 = Utf8               JSON API
  #48 = NameAndType        #18:#19        // "<init>":()V
  #49 = NameAndType        #12:#13        // w:J
  #50 = NameAndType        #14:#15        // a:I
  #51 = NameAndType        #16:#15        // d:I
  #52 = NameAndType        #17:#15        // c:I
  #53 = Utf8               Week starting %d - Additions: %d, Deletions: %d, Commits: %d
  #54 = Utf8               java/lang/Object
  #55 = Class              #64            // java/lang/Long
  #56 = NameAndType        #65:#66        // valueOf:(J)Ljava/lang/Long;
  #57 = Class              #67            // java/lang/Integer
  #58 = NameAndType        #65:#68        // valueOf:(I)Ljava/lang/Integer;
  #59 = Class              #69            // java/lang/String
  #60 = NameAndType        #70:#71        // format:(Ljava/lang/String;[Ljava/lang/Object;)Ljava/lang/String;
  #61 = Utf8               org/kohsuke/github/GHRepositoryStatistics$ContributorStats$Week
  #62 = Class              #72            // org/kohsuke/github/GHRepositoryStatistics
  #63 = Utf8               org/kohsuke/github/GHRepositoryStatistics$ContributorStats
  #64 = Utf8               java/lang/Long
  #65 = Utf8               valueOf
  #66 = Utf8               (J)Ljava/lang/Long;
  #67 = Utf8               java/lang/Integer
  #68 = Utf8               (I)Ljava/lang/Integer;
  #69 = Utf8               java/lang/String
  #70 = Utf8               format
  #71 = Utf8               (Ljava/lang/String;[Ljava/lang/Object;)Ljava/lang/String;
  #72 = Utf8               org/kohsuke/github/GHRepositoryStatistics
{
  private long w;
    descriptor: J
    flags: (0x0002) ACC_PRIVATE

  private int a;
    descriptor: I
    flags: (0x0002) ACC_PRIVATE

  private int d;
    descriptor: I
    flags: (0x0002) ACC_PRIVATE

  private int c;
    descriptor: I
    flags: (0x0002) ACC_PRIVATE

  public org.kohsuke.github.GHRepositoryStatistics$ContributorStats$Week();
    descriptor: ()V
    flags: (0x0001) ACC_PUBLIC
    Code:
      stack=1, locals=1, args_size=1
         0: aload_0
         1: invokespecial #1                  // Method java/lang/Object."<init>":()V
         4: return
      LineNumberTable:
        line 172: 0
      LocalVariableTable:
        Start  Length  Slot  Name   Signature
            0       5     0  this   Lorg/kohsuke/github/GHRepositoryStatistics$ContributorStats$Week;

  public long getWeekTimestamp();
    descriptor: ()J
    flags: (0x0001) ACC_PUBLIC
    Code:
      stack=2, locals=1, args_size=1
         0: aload_0
         1: getfield      #2                  // Field w:J
         4: lreturn
      LineNumberTable:
        line 185: 0
      LocalVariableTable:
        Start  Length  Slot  Name   Signature
            0       5     0  this   Lorg/kohsuke/github/GHRepositoryStatistics$ContributorStats$Week;

  public int getNumberOfAdditions();
    descriptor: ()I
    flags: (0x0001) ACC_PUBLIC
    Code:
      stack=1, locals=1, args_size=1
         0: aload_0
         1: getfield      #3                  // Field a:I
         4: ireturn
      LineNumberTable:
        line 194: 0
      LocalVariableTable:
        Start  Length  Slot  Name   Signature
            0       5     0  this   Lorg/kohsuke/github/GHRepositoryStatistics$ContributorStats$Week;

  public int getNumberOfDeletions();
    descriptor: ()I
    flags: (0x0001) ACC_PUBLIC
    Code:
      stack=1, locals=1, args_size=1
         0: aload_0
         1: getfield      #4                  // Field d:I
         4: ireturn
      LineNumberTable:
        line 203: 0
      LocalVariableTable:
        Start  Length  Slot  Name   Signature
            0       5     0  this   Lorg/kohsuke/github/GHRepositoryStatistics$ContributorStats$Week;

  public int getNumberOfCommits();
    descriptor: ()I
    flags: (0x0001) ACC_PUBLIC
    Code:
      stack=1, locals=1, args_size=1
         0: aload_0
         1: getfield      #5                  // Field c:I
         4: ireturn
      LineNumberTable:
        line 212: 0
      LocalVariableTable:
        Start  Length  Slot  Name   Signature
            0       5     0  this   Lorg/kohsuke/github/GHRepositoryStatistics$ContributorStats$Week;

  public java.lang.String toString();
    descriptor: ()Ljava/lang/String;
    flags: (0x0001) ACC_PUBLIC
    Code:
      stack=6, locals=1, args_size=1
         0: ldc           #6                  // String Week starting %d - Additions: %d, Deletions: %d, Commits: %d
         2: iconst_4
         3: anewarray     #7                  // class java/lang/Object
         6: dup
         7: iconst_0
         8: aload_0
         9: getfield      #2                  // Field w:J
        12: invokestatic  #8                  // Method java/lang/Long.valueOf:(J)Ljava/lang/Long;
        15: aastore
        16: dup
        17: iconst_1
        18: aload_0
        19: getfield      #3                  // Field a:I
        22: invokestatic  #9                  // Method java/lang/Integer.valueOf:(I)Ljava/lang/Integer;
        25: aastore
        26: dup
        27: iconst_2
        28: aload_0
        29: getfield      #4                  // Field d:I
        32: invokestatic  #9                  // Method java/lang/Integer.valueOf:(I)Ljava/lang/Integer;
        35: aastore
        36: dup
        37: iconst_3
        38: aload_0
        39: getfield      #5                  // Field c:I
        42: invokestatic  #9                  // Method java/lang/Integer.valueOf:(I)Ljava/lang/Integer;
        45: aastore
        46: invokestatic  #10                 // Method java/lang/String.format:(Ljava/lang/String;[Ljava/lang/Object;)Ljava/lang/String;
        49: areturn
      LineNumberTable:
        line 217: 0
      LocalVariableTable:
        Start  Length  Slot  Name   Signature
            0      50     0  this   Lorg/kohsuke/github/GHRepositoryStatistics$ContributorStats$Week;
}
SourceFile: "GHRepositoryStatistics.java"
RuntimeInvisibleAnnotations:
  0: #40(#41=[s#42,s#43,s#44,s#45],#46=s#47)
    edu.umd.cs.findbugs.annotations.SuppressFBWarnings(
      value=["UWF_UNWRITTEN_PUBLIC_OR_PROTECTED_FIELD","UWF_UNWRITTEN_FIELD","NP_UNWRITTEN_FIELD","URF_UNREAD_FIELD"]
      justification="JSON API"
    )
InnerClasses:
  public static #25= #24 of #62;          // ContributorStats=class org/kohsuke/github/GHRepositoryStatistics$ContributorStats of class org/kohsuke/github/GHRepositoryStatistics
  public static #27= #11 of #24;          // Week=class org/kohsuke/github/GHRepositoryStatistics$ContributorStats$Week of class org/kohsuke/github/GHRepositoryStatistics$ContributorStats
