Classfile /Users/mw/Projects/slang-braindump/.jar/jar8/assemble/slang-braindump/assemble/content/org/kohsuke/github/GHSearchBuilder.class
  Last modified May 29, 2022; size 4399 bytes
  SHA-256 checksum 185d877f4bf320ab4034676720d835b6db94edad08dcb7c3fb8dc9ba54e7d635
  Compiled from "GHSearchBuilder.java"
public abstract class org.kohsuke.github.GHSearchBuilder<T extends java.lang.Object> extends org.kohsuke.github.GHQueryBuilder<T>
  minor version: 0
  major version: 52
  flags: (0x0421) ACC_PUBLIC, ACC_SUPER, ACC_ABSTRACT
  this_class: #34                         // org/kohsuke/github/GHSearchBuilder
  super_class: #35                        // org/kohsuke/github/GHQueryBuilder
  interfaces: 0, fields: 2, methods: 7, attributes: 4
Constant pool:
    #1 = Methodref          #35.#80       // org/kohsuke/github/GHQueryBuilder."<init>":(Lorg/kohsuke/github/GitHub;)V
    #2 = Class              #81           // java/util/ArrayList
    #3 = Methodref          #2.#82        // java/util/ArrayList."<init>":()V
    #4 = Fieldref           #34.#83       // org/kohsuke/github/GHSearchBuilder.terms:Ljava/util/List;
    #5 = Fieldref           #34.#84       // org/kohsuke/github/GHSearchBuilder.receiverType:Ljava/lang/Class;
    #6 = Fieldref           #34.#85       // org/kohsuke/github/GHSearchBuilder.req:Lorg/kohsuke/github/Requester;
    #7 = Methodref          #34.#86       // org/kohsuke/github/GHSearchBuilder.getApiUrl:()Ljava/lang/String;
    #8 = Class              #87           // java/lang/String
    #9 = Methodref          #88.#89       // org/kohsuke/github/Requester.withUrlPath:(Ljava/lang/String;[Ljava/lang/String;)Lorg/kohsuke/github/GitHubRequest$Builder;
   #10 = Fieldref           #90.#91       // org/kohsuke/github/RateLimitTarget.SEARCH:Lorg/kohsuke/github/RateLimitTarget;
   #11 = Methodref          #88.#92       // org/kohsuke/github/Requester.rateLimit:(Lorg/kohsuke/github/RateLimitTarget;)Lorg/kohsuke/github/GitHubRequest$Builder;
   #12 = InterfaceMethodref #93.#94       // java/util/List.add:(Ljava/lang/Object;)Z
   #13 = Methodref          #95.#96       // org/apache/commons/lang3/StringUtils.isEmpty:(Ljava/lang/CharSequence;)Z
   #14 = Class              #97           // java/lang/IllegalArgumentException
   #15 = String             #98           // qualifier cannot be null or empty
   #16 = Methodref          #14.#99       // java/lang/IllegalArgumentException."<init>":(Ljava/lang/String;)V
   #17 = Class              #100          // java/lang/StringBuilder
   #18 = Methodref          #17.#82       // java/lang/StringBuilder."<init>":()V
   #19 = Methodref          #17.#101      // java/lang/StringBuilder.append:(Ljava/lang/String;)Ljava/lang/StringBuilder;
   #20 = String             #102          // :
   #21 = Methodref          #17.#103      // java/lang/StringBuilder.toString:()Ljava/lang/String;
   #22 = InvokeDynamic      #0:#109       // #0:test:(Ljava/lang/String;)Ljava/util/function/Predicate;
   #23 = InterfaceMethodref #93.#110      // java/util/List.removeIf:(Ljava/util/function/Predicate;)Z
   #24 = String             #55           // q
   #25 = String             #111          //
   #26 = Methodref          #95.#112      // org/apache/commons/lang3/StringUtils.join:(Ljava/lang/Iterable;Ljava/lang/String;)Ljava/lang/String;
   #27 = Methodref          #88.#113      // org/kohsuke/github/Requester.set:(Ljava/lang/String;Ljava/lang/Object;)Lorg/kohsuke/github/GitHubRequest$Builder;
   #28 = Class              #114          // org/kohsuke/github/PagedSearchIterable
   #29 = Methodref          #34.#115      // org/kohsuke/github/GHSearchBuilder.root:()Lorg/kohsuke/github/GitHub;
   #30 = Methodref          #88.#116      // org/kohsuke/github/Requester.build:()Lorg/kohsuke/github/GitHubRequest;
   #31 = Methodref          #28.#117      // org/kohsuke/github/PagedSearchIterable."<init>":(Lorg/kohsuke/github/GitHub;Lorg/kohsuke/github/GitHubRequest;Ljava/lang/Class;)V
   #32 = Methodref          #34.#118      // org/kohsuke/github/GHSearchBuilder.list:()Lorg/kohsuke/github/PagedSearchIterable;
   #33 = Methodref          #8.#119       // java/lang/String.startsWith:(Ljava/lang/String;)Z
   #34 = Class              #120          // org/kohsuke/github/GHSearchBuilder
   #35 = Class              #121          // org/kohsuke/github/GHQueryBuilder
   #36 = Utf8               terms
   #37 = Utf8               Ljava/util/List;
   #38 = Utf8               Signature
   #39 = Utf8               Ljava/util/List<Ljava/lang/String;>;
   #40 = Utf8               receiverType
   #41 = Utf8               Ljava/lang/Class;
   #42 = Utf8               Ljava/lang/Class<+Lorg/kohsuke/github/SearchResult<TT;>;>;
   #43 = Utf8               <init>
   #44 = Utf8               (Lorg/kohsuke/github/GitHub;Ljava/lang/Class;)V
   #45 = Utf8               Code
   #46 = Utf8               LineNumberTable
   #47 = Utf8               LocalVariableTable
   #48 = Utf8               this
   #49 = Utf8               Lorg/kohsuke/github/GHSearchBuilder;
   #50 = Utf8               root
   #51 = Utf8               Lorg/kohsuke/github/GitHub;
   #52 = Utf8               LocalVariableTypeTable
   #53 = Utf8               Lorg/kohsuke/github/GHSearchBuilder<TT;>;
   #54 = Utf8               (Lorg/kohsuke/github/GitHub;Ljava/lang/Class<+Lorg/kohsuke/github/SearchResult<TT;>;>;)V
   #55 = Utf8               q
   #56 = Utf8               (Ljava/lang/String;)Lorg/kohsuke/github/GHQueryBuilder;
   #57 = Utf8               term
   #58 = Utf8               Ljava/lang/String;
   #59 = Utf8               (Ljava/lang/String;)Lorg/kohsuke/github/GHQueryBuilder<TT;>;
   #60 = Utf8               (Ljava/lang/String;Ljava/lang/String;)Lorg/kohsuke/github/GHQueryBuilder;
   #61 = Utf8               removeQualifier
   #62 = Utf8               qualifier
   #63 = Utf8               value
   #64 = Utf8               StackMapTable
   #65 = Utf8               (Ljava/lang/String;Ljava/lang/String;)Lorg/kohsuke/github/GHQueryBuilder<TT;>;
   #66 = Utf8               RuntimeVisibleParameterAnnotations
   #67 = Utf8               Ljavax/annotation/Nonnull;
   #68 = Utf8               Ljavax/annotation/CheckForNull;
   #69 = Utf8               list
   #70 = Utf8               ()Lorg/kohsuke/github/PagedSearchIterable;
   #71 = Utf8               ()Lorg/kohsuke/github/PagedSearchIterable<TT;>;
   #72 = Utf8               getApiUrl
   #73 = Utf8               ()Ljava/lang/String;
   #74 = Utf8               ()Lorg/kohsuke/github/PagedIterable;
   #75 = Utf8               lambda$q$0
   #76 = Utf8               (Ljava/lang/String;Ljava/lang/String;)Z
   #77 = Utf8               <T:Ljava/lang/Object;>Lorg/kohsuke/github/GHQueryBuilder<TT;>;
   #78 = Utf8               SourceFile
   #79 = Utf8               GHSearchBuilder.java
   #80 = NameAndType        #43:#122      // "<init>":(Lorg/kohsuke/github/GitHub;)V
   #81 = Utf8               java/util/ArrayList
   #82 = NameAndType        #43:#123      // "<init>":()V
   #83 = NameAndType        #36:#37       // terms:Ljava/util/List;
   #84 = NameAndType        #40:#41       // receiverType:Ljava/lang/Class;
   #85 = NameAndType        #124:#125     // req:Lorg/kohsuke/github/Requester;
   #86 = NameAndType        #72:#73       // getApiUrl:()Ljava/lang/String;
   #87 = Utf8               java/lang/String
   #88 = Class              #126          // org/kohsuke/github/Requester
   #89 = NameAndType        #127:#131     // withUrlPath:(Ljava/lang/String;[Ljava/lang/String;)Lorg/kohsuke/github/GitHubRequest$Builder;
   #90 = Class              #132          // org/kohsuke/github/RateLimitTarget
   #91 = NameAndType        #133:#134     // SEARCH:Lorg/kohsuke/github/RateLimitTarget;
   #92 = NameAndType        #135:#136     // rateLimit:(Lorg/kohsuke/github/RateLimitTarget;)Lorg/kohsuke/github/GitHubRequest$Builder;
   #93 = Class              #137          // java/util/List
   #94 = NameAndType        #138:#139     // add:(Ljava/lang/Object;)Z
   #95 = Class              #140          // org/apache/commons/lang3/StringUtils
   #96 = NameAndType        #141:#142     // isEmpty:(Ljava/lang/CharSequence;)Z
   #97 = Utf8               java/lang/IllegalArgumentException
   #98 = Utf8               qualifier cannot be null or empty
   #99 = NameAndType        #43:#143      // "<init>":(Ljava/lang/String;)V
  #100 = Utf8               java/lang/StringBuilder
  #101 = NameAndType        #144:#145     // append:(Ljava/lang/String;)Ljava/lang/StringBuilder;
  #102 = Utf8               :
  #103 = NameAndType        #146:#73      // toString:()Ljava/lang/String;
  #104 = Utf8               BootstrapMethods
  #105 = MethodHandle       6:#147        // REF_invokeStatic java/lang/invoke/LambdaMetafactory.metafactory:(Ljava/lang/invoke/MethodHandles$Lookup;Ljava/lang/String;Ljava/lang/invoke/MethodType;Ljava/lang/invoke/MethodType;Ljava/lang/invoke/MethodHandle;Ljava/lang/invoke/MethodType;)Ljava/lang/invoke/CallSite;
  #106 = MethodType         #139          //  (Ljava/lang/Object;)Z
  #107 = MethodHandle       6:#148        // REF_invokeStatic org/kohsuke/github/GHSearchBuilder.lambda$q$0:(Ljava/lang/String;Ljava/lang/String;)Z
  #108 = MethodType         #149          //  (Ljava/lang/String;)Z
  #109 = NameAndType        #150:#151     // test:(Ljava/lang/String;)Ljava/util/function/Predicate;
  #110 = NameAndType        #152:#153     // removeIf:(Ljava/util/function/Predicate;)Z
  #111 = Utf8
  #112 = NameAndType        #154:#155     // join:(Ljava/lang/Iterable;Ljava/lang/String;)Ljava/lang/String;
  #113 = NameAndType        #156:#157     // set:(Ljava/lang/String;Ljava/lang/Object;)Lorg/kohsuke/github/GitHubRequest$Builder;
  #114 = Utf8               org/kohsuke/github/PagedSearchIterable
  #115 = NameAndType        #50:#158      // root:()Lorg/kohsuke/github/GitHub;
  #116 = NameAndType        #159:#160     // build:()Lorg/kohsuke/github/GitHubRequest;
  #117 = NameAndType        #43:#161      // "<init>":(Lorg/kohsuke/github/GitHub;Lorg/kohsuke/github/GitHubRequest;Ljava/lang/Class;)V
  #118 = NameAndType        #69:#70       // list:()Lorg/kohsuke/github/PagedSearchIterable;
  #119 = NameAndType        #162:#149     // startsWith:(Ljava/lang/String;)Z
  #120 = Utf8               org/kohsuke/github/GHSearchBuilder
  #121 = Utf8               org/kohsuke/github/GHQueryBuilder
  #122 = Utf8               (Lorg/kohsuke/github/GitHub;)V
  #123 = Utf8               ()V
  #124 = Utf8               req
  #125 = Utf8               Lorg/kohsuke/github/Requester;
  #126 = Utf8               org/kohsuke/github/Requester
  #127 = Utf8               withUrlPath
  #128 = Class              #164          // org/kohsuke/github/GitHubRequest$Builder
  #129 = Utf8               Builder
  #130 = Utf8               InnerClasses
  #131 = Utf8               (Ljava/lang/String;[Ljava/lang/String;)Lorg/kohsuke/github/GitHubRequest$Builder;
  #132 = Utf8               org/kohsuke/github/RateLimitTarget
  #133 = Utf8               SEARCH
  #134 = Utf8               Lorg/kohsuke/github/RateLimitTarget;
  #135 = Utf8               rateLimit
  #136 = Utf8               (Lorg/kohsuke/github/RateLimitTarget;)Lorg/kohsuke/github/GitHubRequest$Builder;
  #137 = Utf8               java/util/List
  #138 = Utf8               add
  #139 = Utf8               (Ljava/lang/Object;)Z
  #140 = Utf8               org/apache/commons/lang3/StringUtils
  #141 = Utf8               isEmpty
  #142 = Utf8               (Ljava/lang/CharSequence;)Z
  #143 = Utf8               (Ljava/lang/String;)V
  #144 = Utf8               append
  #145 = Utf8               (Ljava/lang/String;)Ljava/lang/StringBuilder;
  #146 = Utf8               toString
  #147 = Methodref          #165.#166     // java/lang/invoke/LambdaMetafactory.metafactory:(Ljava/lang/invoke/MethodHandles$Lookup;Ljava/lang/String;Ljava/lang/invoke/MethodType;Ljava/lang/invoke/MethodType;Ljava/lang/invoke/MethodHandle;Ljava/lang/invoke/MethodType;)Ljava/lang/invoke/CallSite;
  #148 = Methodref          #34.#167      // org/kohsuke/github/GHSearchBuilder.lambda$q$0:(Ljava/lang/String;Ljava/lang/String;)Z
  #149 = Utf8               (Ljava/lang/String;)Z
  #150 = Utf8               test
  #151 = Utf8               (Ljava/lang/String;)Ljava/util/function/Predicate;
  #152 = Utf8               removeIf
  #153 = Utf8               (Ljava/util/function/Predicate;)Z
  #154 = Utf8               join
  #155 = Utf8               (Ljava/lang/Iterable;Ljava/lang/String;)Ljava/lang/String;
  #156 = Utf8               set
  #157 = Utf8               (Ljava/lang/String;Ljava/lang/Object;)Lorg/kohsuke/github/GitHubRequest$Builder;
  #158 = Utf8               ()Lorg/kohsuke/github/GitHub;
  #159 = Utf8               build
  #160 = Utf8               ()Lorg/kohsuke/github/GitHubRequest;
  #161 = Utf8               (Lorg/kohsuke/github/GitHub;Lorg/kohsuke/github/GitHubRequest;Ljava/lang/Class;)V
  #162 = Utf8               startsWith
  #163 = Class              #168          // org/kohsuke/github/GitHubRequest
  #164 = Utf8               org/kohsuke/github/GitHubRequest$Builder
  #165 = Class              #169          // java/lang/invoke/LambdaMetafactory
  #166 = NameAndType        #170:#173     // metafactory:(Ljava/lang/invoke/MethodHandles$Lookup;Ljava/lang/String;Ljava/lang/invoke/MethodType;Ljava/lang/invoke/MethodType;Ljava/lang/invoke/MethodHandle;Ljava/lang/invoke/MethodType;)Ljava/lang/invoke/CallSite;
  #167 = NameAndType        #75:#76       // lambda$q$0:(Ljava/lang/String;Ljava/lang/String;)Z
  #168 = Utf8               org/kohsuke/github/GitHubRequest
  #169 = Utf8               java/lang/invoke/LambdaMetafactory
  #170 = Utf8               metafactory
  #171 = Class              #175          // java/lang/invoke/MethodHandles$Lookup
  #172 = Utf8               Lookup
  #173 = Utf8               (Ljava/lang/invoke/MethodHandles$Lookup;Ljava/lang/String;Ljava/lang/invoke/MethodType;Ljava/lang/invoke/MethodType;Ljava/lang/invoke/MethodHandle;Ljava/lang/invoke/MethodType;)Ljava/lang/invoke/CallSite;
  #174 = Class              #176          // java/lang/invoke/MethodHandles
  #175 = Utf8               java/lang/invoke/MethodHandles$Lookup
  #176 = Utf8               java/lang/invoke/MethodHandles
{
  protected final java.util.List<java.lang.String> terms;
    descriptor: Ljava/util/List;
    flags: (0x0014) ACC_PROTECTED, ACC_FINAL
    Signature: #39                          // Ljava/util/List<Ljava/lang/String;>;

  private final java.lang.Class<? extends org.kohsuke.github.SearchResult<T>> receiverType;
    descriptor: Ljava/lang/Class;
    flags: (0x0012) ACC_PRIVATE, ACC_FINAL
    Signature: #42                          // Ljava/lang/Class<+Lorg/kohsuke/github/SearchResult<TT;>;>;

  org.kohsuke.github.GHSearchBuilder(org.kohsuke.github.GitHub, java.lang.Class<? extends org.kohsuke.github.SearchResult<T>>);
    descriptor: (Lorg/kohsuke/github/GitHub;Ljava/lang/Class;)V
    flags: (0x0000)
    Code:
      stack=3, locals=3, args_size=3
         0: aload_0
         1: aload_1
         2: invokespecial #1                  // Method org/kohsuke/github/GHQueryBuilder."<init>":(Lorg/kohsuke/github/GitHub;)V
         5: aload_0
         6: new           #2                  // class java/util/ArrayList
         9: dup
        10: invokespecial #3                  // Method java/util/ArrayList."<init>":()V
        13: putfield      #4                  // Field terms:Ljava/util/List;
        16: aload_0
        17: aload_2
        18: putfield      #5                  // Field receiverType:Ljava/lang/Class;
        21: aload_0
        22: getfield      #6                  // Field req:Lorg/kohsuke/github/Requester;
        25: aload_0
        26: invokevirtual #7                  // Method getApiUrl:()Ljava/lang/String;
        29: iconst_0
        30: anewarray     #8                  // class java/lang/String
        33: invokevirtual #9                  // Method org/kohsuke/github/Requester.withUrlPath:(Ljava/lang/String;[Ljava/lang/String;)Lorg/kohsuke/github/GitHubRequest$Builder;
        36: pop
        37: aload_0
        38: getfield      #6                  // Field req:Lorg/kohsuke/github/Requester;
        41: getstatic     #10                 // Field org/kohsuke/github/RateLimitTarget.SEARCH:Lorg/kohsuke/github/RateLimitTarget;
        44: invokevirtual #11                 // Method org/kohsuke/github/Requester.rateLimit:(Lorg/kohsuke/github/RateLimitTarget;)Lorg/kohsuke/github/GitHubRequest$Builder;
        47: pop
        48: return
      LineNumberTable:
        line 27: 0
        line 19: 5
        line 28: 16
        line 29: 21
        line 30: 37
        line 31: 48
      LocalVariableTable:
        Start  Length  Slot  Name   Signature
            0      49     0  this   Lorg/kohsuke/github/GHSearchBuilder;
            0      49     1  root   Lorg/kohsuke/github/GitHub;
            0      49     2 receiverType   Ljava/lang/Class;
      LocalVariableTypeTable:
        Start  Length  Slot  Name   Signature
            0      49     0  this   Lorg/kohsuke/github/GHSearchBuilder<TT;>;
            0      49     2 receiverType   Ljava/lang/Class<+Lorg/kohsuke/github/SearchResult<TT;>;>;
    Signature: #54                          // (Lorg/kohsuke/github/GitHub;Ljava/lang/Class<+Lorg/kohsuke/github/SearchResult<TT;>;>;)V

  public org.kohsuke.github.GHQueryBuilder<T> q(java.lang.String);
    descriptor: (Ljava/lang/String;)Lorg/kohsuke/github/GHQueryBuilder;
    flags: (0x0001) ACC_PUBLIC
    Code:
      stack=2, locals=2, args_size=2
         0: aload_0
         1: getfield      #4                  // Field terms:Ljava/util/List;
         4: aload_1
         5: invokeinterface #12,  2           // InterfaceMethod java/util/List.add:(Ljava/lang/Object;)Z
        10: pop
        11: aload_0
        12: areturn
      LineNumberTable:
        line 41: 0
        line 42: 11
      LocalVariableTable:
        Start  Length  Slot  Name   Signature
            0      13     0  this   Lorg/kohsuke/github/GHSearchBuilder;
            0      13     1  term   Ljava/lang/String;
      LocalVariableTypeTable:
        Start  Length  Slot  Name   Signature
            0      13     0  this   Lorg/kohsuke/github/GHSearchBuilder<TT;>;
    Signature: #59                          // (Ljava/lang/String;)Lorg/kohsuke/github/GHQueryBuilder<TT;>;

  org.kohsuke.github.GHQueryBuilder<T> q(java.lang.String, java.lang.String);
    descriptor: (Ljava/lang/String;Ljava/lang/String;)Lorg/kohsuke/github/GHQueryBuilder;
    flags: (0x0000)
    Code:
      stack=3, locals=4, args_size=3
         0: aload_1
         1: invokestatic  #13                 // Method org/apache/commons/lang3/StringUtils.isEmpty:(Ljava/lang/CharSequence;)Z
         4: ifeq          17
         7: new           #14                 // class java/lang/IllegalArgumentException
        10: dup
        11: ldc           #15                 // String qualifier cannot be null or empty
        13: invokespecial #16                 // Method java/lang/IllegalArgumentException."<init>":(Ljava/lang/String;)V
        16: athrow
        17: aload_2
        18: invokestatic  #13                 // Method org/apache/commons/lang3/StringUtils.isEmpty:(Ljava/lang/CharSequence;)Z
        21: ifeq          63
        24: new           #17                 // class java/lang/StringBuilder
        27: dup
        28: invokespecial #18                 // Method java/lang/StringBuilder."<init>":()V
        31: aload_1
        32: invokevirtual #19                 // Method java/lang/StringBuilder.append:(Ljava/lang/String;)Ljava/lang/StringBuilder;
        35: ldc           #20                 // String :
        37: invokevirtual #19                 // Method java/lang/StringBuilder.append:(Ljava/lang/String;)Ljava/lang/StringBuilder;
        40: invokevirtual #21                 // Method java/lang/StringBuilder.toString:()Ljava/lang/String;
        43: astore_3
        44: aload_0
        45: getfield      #4                  // Field terms:Ljava/util/List;
        48: aload_3
        49: invokedynamic #22,  0             // InvokeDynamic #0:test:(Ljava/lang/String;)Ljava/util/function/Predicate;
        54: invokeinterface #23,  2           // InterfaceMethod java/util/List.removeIf:(Ljava/util/function/Predicate;)Z
        59: pop
        60: goto          96
        63: aload_0
        64: getfield      #4                  // Field terms:Ljava/util/List;
        67: new           #17                 // class java/lang/StringBuilder
        70: dup
        71: invokespecial #18                 // Method java/lang/StringBuilder."<init>":()V
        74: aload_1
        75: invokevirtual #19                 // Method java/lang/StringBuilder.append:(Ljava/lang/String;)Ljava/lang/StringBuilder;
        78: ldc           #20                 // String :
        80: invokevirtual #19                 // Method java/lang/StringBuilder.append:(Ljava/lang/String;)Ljava/lang/StringBuilder;
        83: aload_2
        84: invokevirtual #19                 // Method java/lang/StringBuilder.append:(Ljava/lang/String;)Ljava/lang/StringBuilder;
        87: invokevirtual #21                 // Method java/lang/StringBuilder.toString:()Ljava/lang/String;
        90: invokeinterface #12,  2           // InterfaceMethod java/util/List.add:(Ljava/lang/Object;)Z
        95: pop
        96: aload_0
        97: areturn
      LineNumberTable:
        line 57: 0
        line 58: 7
        line 60: 17
        line 61: 24
        line 62: 44
        line 63: 60
        line 64: 63
        line 66: 96
      LocalVariableTable:
        Start  Length  Slot  Name   Signature
           44      16     3 removeQualifier   Ljava/lang/String;
            0      98     0  this   Lorg/kohsuke/github/GHSearchBuilder;
            0      98     1 qualifier   Ljava/lang/String;
            0      98     2 value   Ljava/lang/String;
      LocalVariableTypeTable:
        Start  Length  Slot  Name   Signature
            0      98     0  this   Lorg/kohsuke/github/GHSearchBuilder<TT;>;
      StackMapTable: number_of_entries = 3
        frame_type = 17 /* same */
        frame_type = 45 /* same */
        frame_type = 32 /* same */
    Signature: #65                          // (Ljava/lang/String;Ljava/lang/String;)Lorg/kohsuke/github/GHQueryBuilder<TT;>;
    RuntimeVisibleParameterAnnotations:
      parameter 0:
        0: #67()
          javax.annotation.Nonnull
      parameter 1:
        0: #68()
          javax.annotation.CheckForNull

  public org.kohsuke.github.PagedSearchIterable<T> list();
    descriptor: ()Lorg/kohsuke/github/PagedSearchIterable;
    flags: (0x0001) ACC_PUBLIC
    Code:
      stack=5, locals=1, args_size=1
         0: aload_0
         1: getfield      #6                  // Field req:Lorg/kohsuke/github/Requester;
         4: ldc           #24                 // String q
         6: aload_0
         7: getfield      #4                  // Field terms:Ljava/util/List;
        10: ldc           #25                 // String
        12: invokestatic  #26                 // Method org/apache/commons/lang3/StringUtils.join:(Ljava/lang/Iterable;Ljava/lang/String;)Ljava/lang/String;
        15: invokevirtual #27                 // Method org/kohsuke/github/Requester.set:(Ljava/lang/String;Ljava/lang/Object;)Lorg/kohsuke/github/GitHubRequest$Builder;
        18: pop
        19: new           #28                 // class org/kohsuke/github/PagedSearchIterable
        22: dup
        23: aload_0
        24: invokevirtual #29                 // Method root:()Lorg/kohsuke/github/GitHub;
        27: aload_0
        28: getfield      #6                  // Field req:Lorg/kohsuke/github/Requester;
        31: invokevirtual #30                 // Method org/kohsuke/github/Requester.build:()Lorg/kohsuke/github/GitHubRequest;
        34: aload_0
        35: getfield      #5                  // Field receiverType:Ljava/lang/Class;
        38: invokespecial #31                 // Method org/kohsuke/github/PagedSearchIterable."<init>":(Lorg/kohsuke/github/GitHub;Lorg/kohsuke/github/GitHubRequest;Ljava/lang/Class;)V
        41: areturn
      LineNumberTable:
        line 75: 0
        line 76: 19
      LocalVariableTable:
        Start  Length  Slot  Name   Signature
            0      42     0  this   Lorg/kohsuke/github/GHSearchBuilder;
      LocalVariableTypeTable:
        Start  Length  Slot  Name   Signature
            0      42     0  this   Lorg/kohsuke/github/GHSearchBuilder<TT;>;
    Signature: #71                          // ()Lorg/kohsuke/github/PagedSearchIterable<TT;>;

  protected abstract java.lang.String getApiUrl();
    descriptor: ()Ljava/lang/String;
    flags: (0x0404) ACC_PROTECTED, ACC_ABSTRACT

  public org.kohsuke.github.PagedIterable list();
    descriptor: ()Lorg/kohsuke/github/PagedIterable;
    flags: (0x1041) ACC_PUBLIC, ACC_BRIDGE, ACC_SYNTHETIC
    Code:
      stack=1, locals=1, args_size=1
         0: aload_0
         1: invokevirtual #32                 // Method list:()Lorg/kohsuke/github/PagedSearchIterable;
         4: areturn
      LineNumberTable:
        line 18: 0
      LocalVariableTable:
        Start  Length  Slot  Name   Signature
            0       5     0  this   Lorg/kohsuke/github/GHSearchBuilder;
      LocalVariableTypeTable:
        Start  Length  Slot  Name   Signature
            0       5     0  this   Lorg/kohsuke/github/GHSearchBuilder<TT;>;

  private static boolean lambda$q$0(java.lang.String, java.lang.String);
    descriptor: (Ljava/lang/String;Ljava/lang/String;)Z
    flags: (0x100a) ACC_PRIVATE, ACC_STATIC, ACC_SYNTHETIC
    Code:
      stack=2, locals=2, args_size=2
         0: aload_1
         1: aload_0
         2: invokevirtual #33                 // Method java/lang/String.startsWith:(Ljava/lang/String;)Z
         5: ireturn
      LineNumberTable:
        line 62: 0
      LocalVariableTable:
        Start  Length  Slot  Name   Signature
            0       6     0 removeQualifier   Ljava/lang/String;
            0       6     1  term   Ljava/lang/String;
}
Signature: #77                          // <T:Ljava/lang/Object;>Lorg/kohsuke/github/GHQueryBuilder<TT;>;
SourceFile: "GHSearchBuilder.java"
InnerClasses:
  static #129= #128 of #163;              // Builder=class org/kohsuke/github/GitHubRequest$Builder of class org/kohsuke/github/GitHubRequest
  public static final #172= #171 of #174; // Lookup=class java/lang/invoke/MethodHandles$Lookup of class java/lang/invoke/MethodHandles
BootstrapMethods:
  0: #105 REF_invokeStatic java/lang/invoke/LambdaMetafactory.metafactory:(Ljava/lang/invoke/MethodHandles$Lookup;Ljava/lang/String;Ljava/lang/invoke/MethodType;Ljava/lang/invoke/MethodType;Ljava/lang/invoke/MethodHandle;Ljava/lang/invoke/MethodType;)Ljava/lang/invoke/CallSite;
    Method arguments:
      #106 (Ljava/lang/Object;)Z
      #107 REF_invokeStatic org/kohsuke/github/GHSearchBuilder.lambda$q$0:(Ljava/lang/String;Ljava/lang/String;)Z
      #108 (Ljava/lang/String;)Z
