Classfile /Users/mw/Projects/slang-braindump/.jar/jar8/assemble/slang-braindump/assemble/content/org/kohsuke/github/GHSubscription.class
  Last modified May 29, 2022; size 2627 bytes
  SHA-256 checksum e42126731e213c99ef35049fadd74bad4e9f613a885088daa9a087e591d7251f
  Compiled from "GHSubscription.java"
public class org.kohsuke.github.GHSubscription extends org.kohsuke.github.GitHubInteractiveObject
  minor version: 0
  major version: 52
  flags: (0x0021) ACC_PUBLIC, ACC_SUPER
  this_class: #21                         // org/kohsuke/github/GHSubscription
  super_class: #22                        // org/kohsuke/github/GitHubInteractiveObject
  interfaces: 0, fields: 7, methods: 11, attributes: 2
Constant pool:
    #1 = Methodref          #22.#68       // org/kohsuke/github/GitHubInteractiveObject."<init>":()V
    #2 = Fieldref           #21.#69       // org/kohsuke/github/GHSubscription.created_at:Ljava/lang/String;
    #3 = Methodref          #70.#71       // org/kohsuke/github/GitHubClient.parseDate:(Ljava/lang/String;)Ljava/util/Date;
    #4 = Fieldref           #21.#72       // org/kohsuke/github/GHSubscription.url:Ljava/lang/String;
    #5 = Fieldref           #21.#73       // org/kohsuke/github/GHSubscription.repository_url:Ljava/lang/String;
    #6 = Fieldref           #21.#74       // org/kohsuke/github/GHSubscription.reason:Ljava/lang/String;
    #7 = Fieldref           #21.#75       // org/kohsuke/github/GHSubscription.subscribed:Z
    #8 = Fieldref           #21.#76       // org/kohsuke/github/GHSubscription.ignored:Z
    #9 = Fieldref           #21.#77       // org/kohsuke/github/GHSubscription.repo:Lorg/kohsuke/github/GHRepository;
   #10 = Methodref          #21.#78       // org/kohsuke/github/GHSubscription.root:()Lorg/kohsuke/github/GitHub;
   #11 = Methodref          #79.#80       // org/kohsuke/github/GitHub.createRequest:()Lorg/kohsuke/github/Requester;
   #12 = String             #81           // DELETE
   #13 = Methodref          #14.#82       // org/kohsuke/github/Requester.method:(Ljava/lang/String;)Lorg/kohsuke/github/GitHubRequest$Builder;
   #14 = Class              #83           // org/kohsuke/github/Requester
   #15 = String             #84           // subscription
   #16 = Methodref          #85.#86       // org/kohsuke/github/GHRepository.getApiTailUrl:(Ljava/lang/String;)Ljava/lang/String;
   #17 = Class              #87           // java/lang/String
   #18 = Methodref          #14.#88       // org/kohsuke/github/Requester.withUrlPath:(Ljava/lang/String;[Ljava/lang/String;)Lorg/kohsuke/github/GitHubRequest$Builder;
   #19 = Methodref          #14.#89       // org/kohsuke/github/Requester.send:()V
   #20 = Methodref          #22.#90       // org/kohsuke/github/GitHubInteractiveObject.getRoot:()Lorg/kohsuke/github/GitHub;
   #21 = Class              #91           // org/kohsuke/github/GHSubscription
   #22 = Class              #92           // org/kohsuke/github/GitHubInteractiveObject
   #23 = Utf8               created_at
   #24 = Utf8               Ljava/lang/String;
   #25 = Utf8               url
   #26 = Utf8               repository_url
   #27 = Utf8               reason
   #28 = Utf8               subscribed
   #29 = Utf8               Z
   #30 = Utf8               ignored
   #31 = Utf8               repo
   #32 = Utf8               Lorg/kohsuke/github/GHRepository;
   #33 = Utf8               <init>
   #34 = Utf8               ()V
   #35 = Utf8               Code
   #36 = Utf8               LineNumberTable
   #37 = Utf8               LocalVariableTable
   #38 = Utf8               this
   #39 = Utf8               Lorg/kohsuke/github/GHSubscription;
   #40 = Utf8               getCreatedAt
   #41 = Utf8               ()Ljava/util/Date;
   #42 = Utf8               getUrl
   #43 = Utf8               ()Ljava/lang/String;
   #44 = Utf8               getRepositoryUrl
   #45 = Utf8               getReason
   #46 = Utf8               isSubscribed
   #47 = Utf8               ()Z
   #48 = Utf8               isIgnored
   #49 = Utf8               getRepository
   #50 = Utf8               ()Lorg/kohsuke/github/GHRepository;
   #51 = Utf8               RuntimeInvisibleAnnotations
   #52 = Utf8               Ledu/umd/cs/findbugs/annotations/SuppressFBWarnings;
   #53 = Utf8               value
   #54 = Utf8               EI_EXPOSE_REP
   #55 = Utf8               justification
   #56 = Utf8               Expected behavior
   #57 = Utf8               delete
   #58 = Utf8               Exceptions
   #59 = Class              #93           // java/io/IOException
   #60 = Utf8               wrapUp
   #61 = Utf8               (Lorg/kohsuke/github/GHRepository;)Lorg/kohsuke/github/GHSubscription;
   #62 = Utf8               getRoot
   #63 = Utf8               ()Lorg/kohsuke/github/GitHub;
   #64 = Utf8               RuntimeVisibleAnnotations
   #65 = Utf8               Ljava/lang/Deprecated;
   #66 = Utf8               SourceFile
   #67 = Utf8               GHSubscription.java
   #68 = NameAndType        #33:#34       // "<init>":()V
   #69 = NameAndType        #23:#24       // created_at:Ljava/lang/String;
   #70 = Class              #94           // org/kohsuke/github/GitHubClient
   #71 = NameAndType        #95:#96       // parseDate:(Ljava/lang/String;)Ljava/util/Date;
   #72 = NameAndType        #25:#24       // url:Ljava/lang/String;
   #73 = NameAndType        #26:#24       // repository_url:Ljava/lang/String;
   #74 = NameAndType        #27:#24       // reason:Ljava/lang/String;
   #75 = NameAndType        #28:#29       // subscribed:Z
   #76 = NameAndType        #30:#29       // ignored:Z
   #77 = NameAndType        #31:#32       // repo:Lorg/kohsuke/github/GHRepository;
   #78 = NameAndType        #97:#63       // root:()Lorg/kohsuke/github/GitHub;
   #79 = Class              #98           // org/kohsuke/github/GitHub
   #80 = NameAndType        #99:#100      // createRequest:()Lorg/kohsuke/github/Requester;
   #81 = Utf8               DELETE
   #82 = NameAndType        #101:#105     // method:(Ljava/lang/String;)Lorg/kohsuke/github/GitHubRequest$Builder;
   #83 = Utf8               org/kohsuke/github/Requester
   #84 = Utf8               subscription
   #85 = Class              #106          // org/kohsuke/github/GHRepository
   #86 = NameAndType        #107:#108     // getApiTailUrl:(Ljava/lang/String;)Ljava/lang/String;
   #87 = Utf8               java/lang/String
   #88 = NameAndType        #109:#110     // withUrlPath:(Ljava/lang/String;[Ljava/lang/String;)Lorg/kohsuke/github/GitHubRequest$Builder;
   #89 = NameAndType        #111:#34      // send:()V
   #90 = NameAndType        #62:#63       // getRoot:()Lorg/kohsuke/github/GitHub;
   #91 = Utf8               org/kohsuke/github/GHSubscription
   #92 = Utf8               org/kohsuke/github/GitHubInteractiveObject
   #93 = Utf8               java/io/IOException
   #94 = Utf8               org/kohsuke/github/GitHubClient
   #95 = Utf8               parseDate
   #96 = Utf8               (Ljava/lang/String;)Ljava/util/Date;
   #97 = Utf8               root
   #98 = Utf8               org/kohsuke/github/GitHub
   #99 = Utf8               createRequest
  #100 = Utf8               ()Lorg/kohsuke/github/Requester;
  #101 = Utf8               method
  #102 = Class              #113          // org/kohsuke/github/GitHubRequest$Builder
  #103 = Utf8               Builder
  #104 = Utf8               InnerClasses
  #105 = Utf8               (Ljava/lang/String;)Lorg/kohsuke/github/GitHubRequest$Builder;
  #106 = Utf8               org/kohsuke/github/GHRepository
  #107 = Utf8               getApiTailUrl
  #108 = Utf8               (Ljava/lang/String;)Ljava/lang/String;
  #109 = Utf8               withUrlPath
  #110 = Utf8               (Ljava/lang/String;[Ljava/lang/String;)Lorg/kohsuke/github/GitHubRequest$Builder;
  #111 = Utf8               send
  #112 = Class              #114          // org/kohsuke/github/GitHubRequest
  #113 = Utf8               org/kohsuke/github/GitHubRequest$Builder
  #114 = Utf8               org/kohsuke/github/GitHubRequest
{
  private java.lang.String created_at;
    descriptor: Ljava/lang/String;
    flags: (0x0002) ACC_PRIVATE

  private java.lang.String url;
    descriptor: Ljava/lang/String;
    flags: (0x0002) ACC_PRIVATE

  private java.lang.String repository_url;
    descriptor: Ljava/lang/String;
    flags: (0x0002) ACC_PRIVATE

  private java.lang.String reason;
    descriptor: Ljava/lang/String;
    flags: (0x0002) ACC_PRIVATE

  private boolean subscribed;
    descriptor: Z
    flags: (0x0002) ACC_PRIVATE

  private boolean ignored;
    descriptor: Z
    flags: (0x0002) ACC_PRIVATE

  private org.kohsuke.github.GHRepository repo;
    descriptor: Lorg/kohsuke/github/GHRepository;
    flags: (0x0002) ACC_PRIVATE

  public org.kohsuke.github.GHSubscription();
    descriptor: ()V
    flags: (0x0001) ACC_PUBLIC
    Code:
      stack=1, locals=1, args_size=1
         0: aload_0
         1: invokespecial #1                  // Method org/kohsuke/github/GitHubInteractiveObject."<init>":()V
         4: return
      LineNumberTable:
        line 15: 0
      LocalVariableTable:
        Start  Length  Slot  Name   Signature
            0       5     0  this   Lorg/kohsuke/github/GHSubscription;

  public java.util.Date getCreatedAt();
    descriptor: ()Ljava/util/Date;
    flags: (0x0001) ACC_PUBLIC
    Code:
      stack=1, locals=1, args_size=1
         0: aload_0
         1: getfield      #2                  // Field created_at:Ljava/lang/String;
         4: invokestatic  #3                  // Method org/kohsuke/github/GitHubClient.parseDate:(Ljava/lang/String;)Ljava/util/Date;
         7: areturn
      LineNumberTable:
        line 27: 0
      LocalVariableTable:
        Start  Length  Slot  Name   Signature
            0       8     0  this   Lorg/kohsuke/github/GHSubscription;

  public java.lang.String getUrl();
    descriptor: ()Ljava/lang/String;
    flags: (0x0001) ACC_PUBLIC
    Code:
      stack=1, locals=1, args_size=1
         0: aload_0
         1: getfield      #4                  // Field url:Ljava/lang/String;
         4: areturn
      LineNumberTable:
        line 36: 0
      LocalVariableTable:
        Start  Length  Slot  Name   Signature
            0       5     0  this   Lorg/kohsuke/github/GHSubscription;

  public java.lang.String getRepositoryUrl();
    descriptor: ()Ljava/lang/String;
    flags: (0x0001) ACC_PUBLIC
    Code:
      stack=1, locals=1, args_size=1
         0: aload_0
         1: getfield      #5                  // Field repository_url:Ljava/lang/String;
         4: areturn
      LineNumberTable:
        line 45: 0
      LocalVariableTable:
        Start  Length  Slot  Name   Signature
            0       5     0  this   Lorg/kohsuke/github/GHSubscription;

  public java.lang.String getReason();
    descriptor: ()Ljava/lang/String;
    flags: (0x0001) ACC_PUBLIC
    Code:
      stack=1, locals=1, args_size=1
         0: aload_0
         1: getfield      #6                  // Field reason:Ljava/lang/String;
         4: areturn
      LineNumberTable:
        line 54: 0
      LocalVariableTable:
        Start  Length  Slot  Name   Signature
            0       5     0  this   Lorg/kohsuke/github/GHSubscription;

  public boolean isSubscribed();
    descriptor: ()Z
    flags: (0x0001) ACC_PUBLIC
    Code:
      stack=1, locals=1, args_size=1
         0: aload_0
         1: getfield      #7                  // Field subscribed:Z
         4: ireturn
      LineNumberTable:
        line 63: 0
      LocalVariableTable:
        Start  Length  Slot  Name   Signature
            0       5     0  this   Lorg/kohsuke/github/GHSubscription;

  public boolean isIgnored();
    descriptor: ()Z
    flags: (0x0001) ACC_PUBLIC
    Code:
      stack=1, locals=1, args_size=1
         0: aload_0
         1: getfield      #8                  // Field ignored:Z
         4: ireturn
      LineNumberTable:
        line 72: 0
      LocalVariableTable:
        Start  Length  Slot  Name   Signature
            0       5     0  this   Lorg/kohsuke/github/GHSubscription;

  public org.kohsuke.github.GHRepository getRepository();
    descriptor: ()Lorg/kohsuke/github/GHRepository;
    flags: (0x0001) ACC_PUBLIC
    Code:
      stack=1, locals=1, args_size=1
         0: aload_0
         1: getfield      #9                  // Field repo:Lorg/kohsuke/github/GHRepository;
         4: areturn
      LineNumberTable:
        line 82: 0
      LocalVariableTable:
        Start  Length  Slot  Name   Signature
            0       5     0  this   Lorg/kohsuke/github/GHSubscription;
    RuntimeInvisibleAnnotations:
      0: #52(#53=[s#54],#55=s#56)
        edu.umd.cs.findbugs.annotations.SuppressFBWarnings(
          value=["EI_EXPOSE_REP"]
          justification="Expected behavior"
        )

  public void delete() throws java.io.IOException;
    descriptor: ()V
    flags: (0x0001) ACC_PUBLIC
    Code:
      stack=3, locals=1, args_size=1
         0: aload_0
         1: invokevirtual #10                 // Method root:()Lorg/kohsuke/github/GitHub;
         4: invokevirtual #11                 // Method org/kohsuke/github/GitHub.createRequest:()Lorg/kohsuke/github/Requester;
         7: ldc           #12                 // String DELETE
         9: invokevirtual #13                 // Method org/kohsuke/github/Requester.method:(Ljava/lang/String;)Lorg/kohsuke/github/GitHubRequest$Builder;
        12: checkcast     #14                 // class org/kohsuke/github/Requester
        15: aload_0
        16: getfield      #9                  // Field repo:Lorg/kohsuke/github/GHRepository;
        19: ldc           #15                 // String subscription
        21: invokevirtual #16                 // Method org/kohsuke/github/GHRepository.getApiTailUrl:(Ljava/lang/String;)Ljava/lang/String;
        24: iconst_0
        25: anewarray     #17                 // class java/lang/String
        28: invokevirtual #18                 // Method org/kohsuke/github/Requester.withUrlPath:(Ljava/lang/String;[Ljava/lang/String;)Lorg/kohsuke/github/GitHubRequest$Builder;
        31: checkcast     #14                 // class org/kohsuke/github/Requester
        34: invokevirtual #19                 // Method org/kohsuke/github/Requester.send:()V
        37: return
      LineNumberTable:
        line 92: 0
        line 93: 37
      LocalVariableTable:
        Start  Length  Slot  Name   Signature
            0      38     0  this   Lorg/kohsuke/github/GHSubscription;
    Exceptions:
      throws java.io.IOException

  org.kohsuke.github.GHSubscription wrapUp(org.kohsuke.github.GHRepository);
    descriptor: (Lorg/kohsuke/github/GHRepository;)Lorg/kohsuke/github/GHSubscription;
    flags: (0x0000)
    Code:
      stack=2, locals=2, args_size=2
         0: aload_0
         1: aload_1
         2: putfield      #9                  // Field repo:Lorg/kohsuke/github/GHRepository;
         5: aload_0
         6: areturn
      LineNumberTable:
        line 96: 0
        line 97: 5
      LocalVariableTable:
        Start  Length  Slot  Name   Signature
            0       7     0  this   Lorg/kohsuke/github/GHSubscription;
            0       7     1  repo   Lorg/kohsuke/github/GHRepository;

  public org.kohsuke.github.GitHub getRoot();
    descriptor: ()Lorg/kohsuke/github/GitHub;
    flags: (0x1041) ACC_PUBLIC, ACC_BRIDGE, ACC_SYNTHETIC
    Code:
      stack=1, locals=1, args_size=1
         0: aload_0
         1: invokespecial #20                 // Method org/kohsuke/github/GitHubInteractiveObject.getRoot:()Lorg/kohsuke/github/GitHub;
         4: areturn
      LineNumberTable:
        line 15: 0
      LocalVariableTable:
        Start  Length  Slot  Name   Signature
            0       5     0  this   Lorg/kohsuke/github/GHSubscription;
    RuntimeVisibleAnnotations:
      0: #65()
        java.lang.Deprecated
    RuntimeInvisibleAnnotations:
      0: #52(#53=[s#54],#55=s#56)
        edu.umd.cs.findbugs.annotations.SuppressFBWarnings(
          value=["EI_EXPOSE_REP"]
          justification="Expected behavior"
        )
}
SourceFile: "GHSubscription.java"
InnerClasses:
  static #103= #102 of #112;              // Builder=class org/kohsuke/github/GitHubRequest$Builder of class org/kohsuke/github/GitHubRequest
