Classfile /Users/mw/Projects/slang-braindump/.jar/jar8/assemble/slang-braindump/assemble/content/org/kohsuke/github/GHTag.class
  Last modified May 29, 2022; size 1623 bytes
  SHA-256 checksum ed0e454af854900c762a3757f572365c21f2ddf5a9a94829f98da319bb90ee16
  Compiled from "GHTag.java"
public class org.kohsuke.github.GHTag extends org.kohsuke.github.GitHubInteractiveObject
  minor version: 0
  major version: 52
  flags: (0x0021) ACC_PUBLIC, ACC_SUPER
  this_class: #7                          // org/kohsuke/github/GHTag
  super_class: #8                         // org/kohsuke/github/GitHubInteractiveObject
  interfaces: 0, fields: 3, methods: 6, attributes: 2
Constant pool:
   #1 = Methodref          #8.#47         // org/kohsuke/github/GitHubInteractiveObject."<init>":()V
   #2 = Fieldref           #7.#48         // org/kohsuke/github/GHTag.owner:Lorg/kohsuke/github/GHRepository;
   #3 = Fieldref           #7.#49         // org/kohsuke/github/GHTag.commit:Lorg/kohsuke/github/GHCommit;
   #4 = Methodref          #50.#51        // org/kohsuke/github/GHCommit.wrapUp:(Lorg/kohsuke/github/GHRepository;)Lorg/kohsuke/github/GHCommit;
   #5 = Fieldref           #7.#52         // org/kohsuke/github/GHTag.name:Ljava/lang/String;
   #6 = Methodref          #8.#53         // org/kohsuke/github/GitHubInteractiveObject.getRoot:()Lorg/kohsuke/github/GitHub;
   #7 = Class              #54            // org/kohsuke/github/GHTag
   #8 = Class              #55            // org/kohsuke/github/GitHubInteractiveObject
   #9 = Utf8               owner
  #10 = Utf8               Lorg/kohsuke/github/GHRepository;
  #11 = Utf8               name
  #12 = Utf8               Ljava/lang/String;
  #13 = Utf8               commit
  #14 = Utf8               Lorg/kohsuke/github/GHCommit;
  #15 = Utf8               <init>
  #16 = Utf8               ()V
  #17 = Utf8               Code
  #18 = Utf8               LineNumberTable
  #19 = Utf8               LocalVariableTable
  #20 = Utf8               this
  #21 = Utf8               Lorg/kohsuke/github/GHTag;
  #22 = Utf8               wrap
  #23 = Utf8               (Lorg/kohsuke/github/GHRepository;)Lorg/kohsuke/github/GHTag;
  #24 = Utf8               StackMapTable
  #25 = Utf8               getOwner
  #26 = Utf8               ()Lorg/kohsuke/github/GHRepository;
  #27 = Utf8               RuntimeInvisibleAnnotations
  #28 = Utf8               Ledu/umd/cs/findbugs/annotations/SuppressFBWarnings;
  #29 = Utf8               value
  #30 = Utf8               EI_EXPOSE_REP
  #31 = Utf8               justification
  #32 = Utf8               Expected behavior
  #33 = Utf8               getName
  #34 = Utf8               ()Ljava/lang/String;
  #35 = Utf8               getCommit
  #36 = Utf8               ()Lorg/kohsuke/github/GHCommit;
  #37 = Utf8               getRoot
  #38 = Utf8               ()Lorg/kohsuke/github/GitHub;
  #39 = Utf8               RuntimeVisibleAnnotations
  #40 = Utf8               Ljava/lang/Deprecated;
  #41 = Utf8               SourceFile
  #42 = Utf8               GHTag.java
  #43 = Utf8               UWF_UNWRITTEN_PUBLIC_OR_PROTECTED_FIELD
  #44 = Utf8               UWF_UNWRITTEN_FIELD
  #45 = Utf8               NP_UNWRITTEN_FIELD
  #46 = Utf8               JSON API
  #47 = NameAndType        #15:#16        // "<init>":()V
  #48 = NameAndType        #9:#10         // owner:Lorg/kohsuke/github/GHRepository;
  #49 = NameAndType        #13:#14        // commit:Lorg/kohsuke/github/GHCommit;
  #50 = Class              #56            // org/kohsuke/github/GHCommit
  #51 = NameAndType        #57:#58        // wrapUp:(Lorg/kohsuke/github/GHRepository;)Lorg/kohsuke/github/GHCommit;
  #52 = NameAndType        #11:#12        // name:Ljava/lang/String;
  #53 = NameAndType        #37:#38        // getRoot:()Lorg/kohsuke/github/GitHub;
  #54 = Utf8               org/kohsuke/github/GHTag
  #55 = Utf8               org/kohsuke/github/GitHubInteractiveObject
  #56 = Utf8               org/kohsuke/github/GHCommit
  #57 = Utf8               wrapUp
  #58 = Utf8               (Lorg/kohsuke/github/GHRepository;)Lorg/kohsuke/github/GHCommit;
{
  private org.kohsuke.github.GHRepository owner;
    descriptor: Lorg/kohsuke/github/GHRepository;
    flags: (0x0002) ACC_PRIVATE

  private java.lang.String name;
    descriptor: Ljava/lang/String;
    flags: (0x0002) ACC_PRIVATE

  private org.kohsuke.github.GHCommit commit;
    descriptor: Lorg/kohsuke/github/GHCommit;
    flags: (0x0002) ACC_PRIVATE

  public org.kohsuke.github.GHTag();
    descriptor: ()V
    flags: (0x0001) ACC_PUBLIC
    Code:
      stack=1, locals=1, args_size=1
         0: aload_0
         1: invokespecial #1                  // Method org/kohsuke/github/GitHubInteractiveObject."<init>":()V
         4: return
      LineNumberTable:
        line 12: 0
      LocalVariableTable:
        Start  Length  Slot  Name   Signature
            0       5     0  this   Lorg/kohsuke/github/GHTag;

  org.kohsuke.github.GHTag wrap(org.kohsuke.github.GHRepository);
    descriptor: (Lorg/kohsuke/github/GHRepository;)Lorg/kohsuke/github/GHTag;
    flags: (0x0000)
    Code:
      stack=2, locals=2, args_size=2
         0: aload_0
         1: aload_1
         2: putfield      #2                  // Field owner:Lorg/kohsuke/github/GHRepository;
         5: aload_0
         6: getfield      #3                  // Field commit:Lorg/kohsuke/github/GHCommit;
         9: ifnull        21
        12: aload_0
        13: getfield      #3                  // Field commit:Lorg/kohsuke/github/GHCommit;
        16: aload_1
        17: invokevirtual #4                  // Method org/kohsuke/github/GHCommit.wrapUp:(Lorg/kohsuke/github/GHRepository;)Lorg/kohsuke/github/GHCommit;
        20: pop
        21: aload_0
        22: areturn
      LineNumberTable:
        line 19: 0
        line 20: 5
        line 21: 12
        line 22: 21
      LocalVariableTable:
        Start  Length  Slot  Name   Signature
            0      23     0  this   Lorg/kohsuke/github/GHTag;
            0      23     1 owner   Lorg/kohsuke/github/GHRepository;
      StackMapTable: number_of_entries = 1
        frame_type = 21 /* same */

  public org.kohsuke.github.GHRepository getOwner();
    descriptor: ()Lorg/kohsuke/github/GHRepository;
    flags: (0x0001) ACC_PUBLIC
    Code:
      stack=1, locals=1, args_size=1
         0: aload_0
         1: getfield      #2                  // Field owner:Lorg/kohsuke/github/GHRepository;
         4: areturn
      LineNumberTable:
        line 32: 0
      LocalVariableTable:
        Start  Length  Slot  Name   Signature
            0       5     0  this   Lorg/kohsuke/github/GHTag;
    RuntimeInvisibleAnnotations:
      0: #28(#29=[s#30],#31=s#32)
        edu.umd.cs.findbugs.annotations.SuppressFBWarnings(
          value=["EI_EXPOSE_REP"]
          justification="Expected behavior"
        )

  public java.lang.String getName();
    descriptor: ()Ljava/lang/String;
    flags: (0x0001) ACC_PUBLIC
    Code:
      stack=1, locals=1, args_size=1
         0: aload_0
         1: getfield      #5                  // Field name:Ljava/lang/String;
         4: areturn
      LineNumberTable:
        line 41: 0
      LocalVariableTable:
        Start  Length  Slot  Name   Signature
            0       5     0  this   Lorg/kohsuke/github/GHTag;

  public org.kohsuke.github.GHCommit getCommit();
    descriptor: ()Lorg/kohsuke/github/GHCommit;
    flags: (0x0001) ACC_PUBLIC
    Code:
      stack=1, locals=1, args_size=1
         0: aload_0
         1: getfield      #3                  // Field commit:Lorg/kohsuke/github/GHCommit;
         4: areturn
      LineNumberTable:
        line 51: 0
      LocalVariableTable:
        Start  Length  Slot  Name   Signature
            0       5     0  this   Lorg/kohsuke/github/GHTag;
    RuntimeInvisibleAnnotations:
      0: #28(#29=[s#30],#31=s#32)
        edu.umd.cs.findbugs.annotations.SuppressFBWarnings(
          value=["EI_EXPOSE_REP"]
          justification="Expected behavior"
        )

  public org.kohsuke.github.GitHub getRoot();
    descriptor: ()Lorg/kohsuke/github/GitHub;
    flags: (0x1041) ACC_PUBLIC, ACC_BRIDGE, ACC_SYNTHETIC
    Code:
      stack=1, locals=1, args_size=1
         0: aload_0
         1: invokespecial #6                  // Method org/kohsuke/github/GitHubInteractiveObject.getRoot:()Lorg/kohsuke/github/GitHub;
         4: areturn
      LineNumberTable:
        line 10: 0
      LocalVariableTable:
        Start  Length  Slot  Name   Signature
            0       5     0  this   Lorg/kohsuke/github/GHTag;
    RuntimeVisibleAnnotations:
      0: #40()
        java.lang.Deprecated
    RuntimeInvisibleAnnotations:
      0: #28(#29=[s#30],#31=s#32)
        edu.umd.cs.findbugs.annotations.SuppressFBWarnings(
          value=["EI_EXPOSE_REP"]
          justification="Expected behavior"
        )
}
SourceFile: "GHTag.java"
RuntimeInvisibleAnnotations:
  0: #28(#29=[s#43,s#44,s#45],#31=s#46)
    edu.umd.cs.findbugs.annotations.SuppressFBWarnings(
      value=["UWF_UNWRITTEN_PUBLIC_OR_PROTECTED_FIELD","UWF_UNWRITTEN_FIELD","NP_UNWRITTEN_FIELD"]
      justification="JSON API"
    )
