Classfile /Users/mw/Projects/slang-braindump/.jar/jar8/assemble/slang-braindump/assemble/content/org/kohsuke/github/GHWorkflow.class
  Last modified May 29, 2022; size 4804 bytes
  SHA-256 checksum f679387f6fd3f58acceb1413b044f80bb7b66b50054cc106c46bac0c57016939
  Compiled from "GHWorkflow.java"
public class org.kohsuke.github.GHWorkflow extends org.kohsuke.github.GHObject
  minor version: 0
  major version: 52
  flags: (0x0021) ACC_PUBLIC, ACC_SUPER
  this_class: #53                         // org/kohsuke/github/GHWorkflow
  super_class: #54                        // org/kohsuke/github/GHObject
  interfaces: 0, fields: 6, methods: 14, attributes: 2
Constant pool:
    #1 = Methodref          #54.#114      // org/kohsuke/github/GHObject."<init>":()V
    #2 = Fieldref           #53.#115      // org/kohsuke/github/GHWorkflow.name:Ljava/lang/String;
    #3 = Fieldref           #53.#116      // org/kohsuke/github/GHWorkflow.path:Ljava/lang/String;
    #4 = Fieldref           #53.#117      // org/kohsuke/github/GHWorkflow.state:Ljava/lang/String;
    #5 = Fieldref           #53.#118      // org/kohsuke/github/GHWorkflow.htmlUrl:Ljava/lang/String;
    #6 = Methodref          #119.#120     // org/kohsuke/github/GitHubClient.parseURL:(Ljava/lang/String;)Ljava/net/URL;
    #7 = Fieldref           #53.#121      // org/kohsuke/github/GHWorkflow.owner:Lorg/kohsuke/github/GHRepository;
    #8 = Fieldref           #53.#122      // org/kohsuke/github/GHWorkflow.badgeUrl:Ljava/lang/String;
    #9 = Methodref          #53.#123      // org/kohsuke/github/GHWorkflow.root:()Lorg/kohsuke/github/GitHub;
   #10 = Methodref          #124.#125     // org/kohsuke/github/GitHub.createRequest:()Lorg/kohsuke/github/Requester;
   #11 = String             #126          // PUT
   #12 = Methodref          #13.#127      // org/kohsuke/github/Requester.method:(Ljava/lang/String;)Lorg/kohsuke/github/GitHubRequest$Builder;
   #13 = Class              #128          // org/kohsuke/github/Requester
   #14 = Methodref          #53.#129      // org/kohsuke/github/GHWorkflow.getApiRoute:()Ljava/lang/String;
   #15 = Class              #130          // java/lang/String
   #16 = String             #89           // disable
   #17 = Methodref          #13.#131      // org/kohsuke/github/Requester.withUrlPath:(Ljava/lang/String;[Ljava/lang/String;)Lorg/kohsuke/github/GitHubRequest$Builder;
   #18 = Methodref          #13.#132      // org/kohsuke/github/Requester.fetchHttpStatusCode:()I
   #19 = String             #90           // enable
   #20 = Methodref          #133.#134     // java/util/Collections.emptyMap:()Ljava/util/Map;
   #21 = Methodref          #53.#135      // org/kohsuke/github/GHWorkflow.dispatch:(Ljava/lang/String;Ljava/util/Map;)V
   #22 = String             #136          // POST
   #23 = String             #137          // dispatches
   #24 = String             #93           // ref
   #25 = Methodref          #13.#138      // org/kohsuke/github/Requester.with:(Ljava/lang/String;Ljava/lang/String;)Lorg/kohsuke/github/GitHubRequest$Builder;
   #26 = InterfaceMethodref #139.#140     // java/util/Map.isEmpty:()Z
   #27 = String             #95           // inputs
   #28 = Methodref          #13.#141      // org/kohsuke/github/Requester.with:(Ljava/lang/String;Ljava/util/Map;)Lorg/kohsuke/github/GitHubRequest$Builder;
   #29 = Class              #142          // org/kohsuke/github/GHWorkflowRunsIterable
   #30 = String             #143          // runs
   #31 = Methodref          #29.#144      // org/kohsuke/github/GHWorkflowRunsIterable."<init>":(Lorg/kohsuke/github/GHRepository;Lorg/kohsuke/github/GitHubRequest$Builder;)V
   #32 = Methodref          #53.#145      // org/kohsuke/github/GHWorkflow.getUrl:()Ljava/net/URL;
   #33 = String             #146          // Missing instance URL!
   #34 = Methodref          #147.#148     // java/util/Objects.requireNonNull:(Ljava/lang/Object;Ljava/lang/String;)Ljava/lang/Object;
   #35 = Class              #149          // java/net/URL
   #36 = Methodref          #35.#150      // java/net/URL.toString:()Ljava/lang/String;
   #37 = Methodref          #124.#151     // org/kohsuke/github/GitHub.getApiUrl:()Ljava/lang/String;
   #38 = String             #152          //
   #39 = Methodref          #15.#153      // java/lang/String.replace:(Ljava/lang/CharSequence;Ljava/lang/CharSequence;)Ljava/lang/String;
   #40 = String             #154          // /
   #41 = Class              #155          // java/lang/CharSequence
   #42 = Methodref          #156.#157     // org/apache/commons/lang3/StringUtils.prependIfMissing:(Ljava/lang/String;Ljava/lang/CharSequence;[Ljava/lang/CharSequence;)Ljava/lang/String;
   #43 = Class              #158          // java/lang/StringBuilder
   #44 = Methodref          #43.#114      // java/lang/StringBuilder."<init>":()V
   #45 = String             #159          // /repos/
   #46 = Methodref          #43.#160      // java/lang/StringBuilder.append:(Ljava/lang/String;)Ljava/lang/StringBuilder;
   #47 = Methodref          #161.#162     // org/kohsuke/github/GHRepository.getOwnerName:()Ljava/lang/String;
   #48 = Methodref          #161.#163     // org/kohsuke/github/GHRepository.getName:()Ljava/lang/String;
   #49 = String             #164          // /actions/workflows/
   #50 = Methodref          #53.#165      // org/kohsuke/github/GHWorkflow.getId:()J
   #51 = Methodref          #43.#166      // java/lang/StringBuilder.append:(J)Ljava/lang/StringBuilder;
   #52 = Methodref          #43.#150      // java/lang/StringBuilder.toString:()Ljava/lang/String;
   #53 = Class              #167          // org/kohsuke/github/GHWorkflow
   #54 = Class              #168          // org/kohsuke/github/GHObject
   #55 = Utf8               owner
   #56 = Utf8               Lorg/kohsuke/github/GHRepository;
   #57 = Utf8               RuntimeVisibleAnnotations
   #58 = Utf8               Lcom/fasterxml/jackson/annotation/JsonIgnore;
   #59 = Utf8               name
   #60 = Utf8               Ljava/lang/String;
   #61 = Utf8               path
   #62 = Utf8               state
   #63 = Utf8               htmlUrl
   #64 = Utf8               badgeUrl
   #65 = Utf8               <init>
   #66 = Utf8               ()V
   #67 = Utf8               Code
   #68 = Utf8               LineNumberTable
   #69 = Utf8               LocalVariableTable
   #70 = Utf8               this
   #71 = Utf8               Lorg/kohsuke/github/GHWorkflow;
   #72 = Utf8               getName
   #73 = Utf8               ()Ljava/lang/String;
   #74 = Utf8               getPath
   #75 = Utf8               getState
   #76 = Utf8               getHtmlUrl
   #77 = Utf8               ()Ljava/net/URL;
   #78 = Utf8               Exceptions
   #79 = Class              #169          // java/io/IOException
   #80 = Utf8               getRepository
   #81 = Utf8               ()Lorg/kohsuke/github/GHRepository;
   #82 = Utf8               RuntimeInvisibleAnnotations
   #83 = Utf8               Ledu/umd/cs/findbugs/annotations/SuppressFBWarnings;
   #84 = Utf8               value
   #85 = Utf8               EI_EXPOSE_REP
   #86 = Utf8               justification
   #87 = Utf8               Expected behavior
   #88 = Utf8               getBadgeUrl
   #89 = Utf8               disable
   #90 = Utf8               enable
   #91 = Utf8               dispatch
   #92 = Utf8               (Ljava/lang/String;)V
   #93 = Utf8               ref
   #94 = Utf8               (Ljava/lang/String;Ljava/util/Map;)V
   #95 = Utf8               inputs
   #96 = Utf8               Ljava/util/Map;
   #97 = Utf8               requester
   #98 = Utf8               Lorg/kohsuke/github/Requester;
   #99 = Utf8               LocalVariableTypeTable
  #100 = Utf8               Ljava/util/Map<Ljava/lang/String;Ljava/lang/Object;>;
  #101 = Utf8               StackMapTable
  #102 = Utf8               Signature
  #103 = Utf8               (Ljava/lang/String;Ljava/util/Map<Ljava/lang/String;Ljava/lang/Object;>;)V
  #104 = Utf8               listRuns
  #105 = Utf8               ()Lorg/kohsuke/github/PagedIterable;
  #106 = Utf8               ()Lorg/kohsuke/github/PagedIterable<Lorg/kohsuke/github/GHWorkflowRun;>;
  #107 = Utf8               getApiRoute
  #108 = Utf8               url
  #109 = Utf8               Ljava/net/URL;
  #110 = Utf8               wrapUp
  #111 = Utf8               (Lorg/kohsuke/github/GHRepository;)Lorg/kohsuke/github/GHWorkflow;
  #112 = Utf8               SourceFile
  #113 = Utf8               GHWorkflow.java
  #114 = NameAndType        #65:#66       // "<init>":()V
  #115 = NameAndType        #59:#60       // name:Ljava/lang/String;
  #116 = NameAndType        #61:#60       // path:Ljava/lang/String;
  #117 = NameAndType        #62:#60       // state:Ljava/lang/String;
  #118 = NameAndType        #63:#60       // htmlUrl:Ljava/lang/String;
  #119 = Class              #170          // org/kohsuke/github/GitHubClient
  #120 = NameAndType        #171:#172     // parseURL:(Ljava/lang/String;)Ljava/net/URL;
  #121 = NameAndType        #55:#56       // owner:Lorg/kohsuke/github/GHRepository;
  #122 = NameAndType        #64:#60       // badgeUrl:Ljava/lang/String;
  #123 = NameAndType        #173:#174     // root:()Lorg/kohsuke/github/GitHub;
  #124 = Class              #175          // org/kohsuke/github/GitHub
  #125 = NameAndType        #176:#177     // createRequest:()Lorg/kohsuke/github/Requester;
  #126 = Utf8               PUT
  #127 = NameAndType        #178:#182     // method:(Ljava/lang/String;)Lorg/kohsuke/github/GitHubRequest$Builder;
  #128 = Utf8               org/kohsuke/github/Requester
  #129 = NameAndType        #107:#73      // getApiRoute:()Ljava/lang/String;
  #130 = Utf8               java/lang/String
  #131 = NameAndType        #183:#184     // withUrlPath:(Ljava/lang/String;[Ljava/lang/String;)Lorg/kohsuke/github/GitHubRequest$Builder;
  #132 = NameAndType        #185:#186     // fetchHttpStatusCode:()I
  #133 = Class              #187          // java/util/Collections
  #134 = NameAndType        #188:#189     // emptyMap:()Ljava/util/Map;
  #135 = NameAndType        #91:#94       // dispatch:(Ljava/lang/String;Ljava/util/Map;)V
  #136 = Utf8               POST
  #137 = Utf8               dispatches
  #138 = NameAndType        #190:#191     // with:(Ljava/lang/String;Ljava/lang/String;)Lorg/kohsuke/github/GitHubRequest$Builder;
  #139 = Class              #192          // java/util/Map
  #140 = NameAndType        #193:#194     // isEmpty:()Z
  #141 = NameAndType        #190:#195     // with:(Ljava/lang/String;Ljava/util/Map;)Lorg/kohsuke/github/GitHubRequest$Builder;
  #142 = Utf8               org/kohsuke/github/GHWorkflowRunsIterable
  #143 = Utf8               runs
  #144 = NameAndType        #65:#196      // "<init>":(Lorg/kohsuke/github/GHRepository;Lorg/kohsuke/github/GitHubRequest$Builder;)V
  #145 = NameAndType        #197:#77      // getUrl:()Ljava/net/URL;
  #146 = Utf8               Missing instance URL!
  #147 = Class              #198          // java/util/Objects
  #148 = NameAndType        #199:#200     // requireNonNull:(Ljava/lang/Object;Ljava/lang/String;)Ljava/lang/Object;
  #149 = Utf8               java/net/URL
  #150 = NameAndType        #201:#73      // toString:()Ljava/lang/String;
  #151 = NameAndType        #202:#73      // getApiUrl:()Ljava/lang/String;
  #152 = Utf8
  #153 = NameAndType        #203:#204     // replace:(Ljava/lang/CharSequence;Ljava/lang/CharSequence;)Ljava/lang/String;
  #154 = Utf8               /
  #155 = Utf8               java/lang/CharSequence
  #156 = Class              #205          // org/apache/commons/lang3/StringUtils
  #157 = NameAndType        #206:#207     // prependIfMissing:(Ljava/lang/String;Ljava/lang/CharSequence;[Ljava/lang/CharSequence;)Ljava/lang/String;
  #158 = Utf8               java/lang/StringBuilder
  #159 = Utf8               /repos/
  #160 = NameAndType        #208:#209     // append:(Ljava/lang/String;)Ljava/lang/StringBuilder;
  #161 = Class              #210          // org/kohsuke/github/GHRepository
  #162 = NameAndType        #211:#73      // getOwnerName:()Ljava/lang/String;
  #163 = NameAndType        #72:#73       // getName:()Ljava/lang/String;
  #164 = Utf8               /actions/workflows/
  #165 = NameAndType        #212:#213     // getId:()J
  #166 = NameAndType        #208:#214     // append:(J)Ljava/lang/StringBuilder;
  #167 = Utf8               org/kohsuke/github/GHWorkflow
  #168 = Utf8               org/kohsuke/github/GHObject
  #169 = Utf8               java/io/IOException
  #170 = Utf8               org/kohsuke/github/GitHubClient
  #171 = Utf8               parseURL
  #172 = Utf8               (Ljava/lang/String;)Ljava/net/URL;
  #173 = Utf8               root
  #174 = Utf8               ()Lorg/kohsuke/github/GitHub;
  #175 = Utf8               org/kohsuke/github/GitHub
  #176 = Utf8               createRequest
  #177 = Utf8               ()Lorg/kohsuke/github/Requester;
  #178 = Utf8               method
  #179 = Class              #216          // org/kohsuke/github/GitHubRequest$Builder
  #180 = Utf8               Builder
  #181 = Utf8               InnerClasses
  #182 = Utf8               (Ljava/lang/String;)Lorg/kohsuke/github/GitHubRequest$Builder;
  #183 = Utf8               withUrlPath
  #184 = Utf8               (Ljava/lang/String;[Ljava/lang/String;)Lorg/kohsuke/github/GitHubRequest$Builder;
  #185 = Utf8               fetchHttpStatusCode
  #186 = Utf8               ()I
  #187 = Utf8               java/util/Collections
  #188 = Utf8               emptyMap
  #189 = Utf8               ()Ljava/util/Map;
  #190 = Utf8               with
  #191 = Utf8               (Ljava/lang/String;Ljava/lang/String;)Lorg/kohsuke/github/GitHubRequest$Builder;
  #192 = Utf8               java/util/Map
  #193 = Utf8               isEmpty
  #194 = Utf8               ()Z
  #195 = Utf8               (Ljava/lang/String;Ljava/util/Map;)Lorg/kohsuke/github/GitHubRequest$Builder;
  #196 = Utf8               (Lorg/kohsuke/github/GHRepository;Lorg/kohsuke/github/GitHubRequest$Builder;)V
  #197 = Utf8               getUrl
  #198 = Utf8               java/util/Objects
  #199 = Utf8               requireNonNull
  #200 = Utf8               (Ljava/lang/Object;Ljava/lang/String;)Ljava/lang/Object;
  #201 = Utf8               toString
  #202 = Utf8               getApiUrl
  #203 = Utf8               replace
  #204 = Utf8               (Ljava/lang/CharSequence;Ljava/lang/CharSequence;)Ljava/lang/String;
  #205 = Utf8               org/apache/commons/lang3/StringUtils
  #206 = Utf8               prependIfMissing
  #207 = Utf8               (Ljava/lang/String;Ljava/lang/CharSequence;[Ljava/lang/CharSequence;)Ljava/lang/String;
  #208 = Utf8               append
  #209 = Utf8               (Ljava/lang/String;)Ljava/lang/StringBuilder;
  #210 = Utf8               org/kohsuke/github/GHRepository
  #211 = Utf8               getOwnerName
  #212 = Utf8               getId
  #213 = Utf8               ()J
  #214 = Utf8               (J)Ljava/lang/StringBuilder;
  #215 = Class              #217          // org/kohsuke/github/GitHubRequest
  #216 = Utf8               org/kohsuke/github/GitHubRequest$Builder
  #217 = Utf8               org/kohsuke/github/GitHubRequest
{
  private org.kohsuke.github.GHRepository owner;
    descriptor: Lorg/kohsuke/github/GHRepository;
    flags: (0x0002) ACC_PRIVATE
    RuntimeVisibleAnnotations:
      0: #58()
        com.fasterxml.jackson.annotation.JsonIgnore

  private java.lang.String name;
    descriptor: Ljava/lang/String;
    flags: (0x0002) ACC_PRIVATE

  private java.lang.String path;
    descriptor: Ljava/lang/String;
    flags: (0x0002) ACC_PRIVATE

  private java.lang.String state;
    descriptor: Ljava/lang/String;
    flags: (0x0002) ACC_PRIVATE

  private java.lang.String htmlUrl;
    descriptor: Ljava/lang/String;
    flags: (0x0002) ACC_PRIVATE

  private java.lang.String badgeUrl;
    descriptor: Ljava/lang/String;
    flags: (0x0002) ACC_PRIVATE

  public org.kohsuke.github.GHWorkflow();
    descriptor: ()V
    flags: (0x0001) ACC_PUBLIC
    Code:
      stack=1, locals=1, args_size=1
         0: aload_0
         1: invokespecial #1                  // Method org/kohsuke/github/GHObject."<init>":()V
         4: return
      LineNumberTable:
        line 19: 0
      LocalVariableTable:
        Start  Length  Slot  Name   Signature
            0       5     0  this   Lorg/kohsuke/github/GHWorkflow;

  public java.lang.String getName();
    descriptor: ()Ljava/lang/String;
    flags: (0x0001) ACC_PUBLIC
    Code:
      stack=1, locals=1, args_size=1
         0: aload_0
         1: getfield      #2                  // Field name:Ljava/lang/String;
         4: areturn
      LineNumberTable:
        line 38: 0
      LocalVariableTable:
        Start  Length  Slot  Name   Signature
            0       5     0  this   Lorg/kohsuke/github/GHWorkflow;

  public java.lang.String getPath();
    descriptor: ()Ljava/lang/String;
    flags: (0x0001) ACC_PUBLIC
    Code:
      stack=1, locals=1, args_size=1
         0: aload_0
         1: getfield      #3                  // Field path:Ljava/lang/String;
         4: areturn
      LineNumberTable:
        line 47: 0
      LocalVariableTable:
        Start  Length  Slot  Name   Signature
            0       5     0  this   Lorg/kohsuke/github/GHWorkflow;

  public java.lang.String getState();
    descriptor: ()Ljava/lang/String;
    flags: (0x0001) ACC_PUBLIC
    Code:
      stack=1, locals=1, args_size=1
         0: aload_0
         1: getfield      #4                  // Field state:Ljava/lang/String;
         4: areturn
      LineNumberTable:
        line 56: 0
      LocalVariableTable:
        Start  Length  Slot  Name   Signature
            0       5     0  this   Lorg/kohsuke/github/GHWorkflow;

  public java.net.URL getHtmlUrl() throws java.io.IOException;
    descriptor: ()Ljava/net/URL;
    flags: (0x0001) ACC_PUBLIC
    Code:
      stack=1, locals=1, args_size=1
         0: aload_0
         1: getfield      #5                  // Field htmlUrl:Ljava/lang/String;
         4: invokestatic  #6                  // Method org/kohsuke/github/GitHubClient.parseURL:(Ljava/lang/String;)Ljava/net/URL;
         7: areturn
      LineNumberTable:
        line 61: 0
      LocalVariableTable:
        Start  Length  Slot  Name   Signature
            0       8     0  this   Lorg/kohsuke/github/GHWorkflow;
    Exceptions:
      throws java.io.IOException

  public org.kohsuke.github.GHRepository getRepository();
    descriptor: ()Lorg/kohsuke/github/GHRepository;
    flags: (0x0001) ACC_PUBLIC
    Code:
      stack=1, locals=1, args_size=1
         0: aload_0
         1: getfield      #7                  // Field owner:Lorg/kohsuke/github/GHRepository;
         4: areturn
      LineNumberTable:
        line 71: 0
      LocalVariableTable:
        Start  Length  Slot  Name   Signature
            0       5     0  this   Lorg/kohsuke/github/GHWorkflow;
    RuntimeInvisibleAnnotations:
      0: #83(#84=[s#85],#86=s#87)
        edu.umd.cs.findbugs.annotations.SuppressFBWarnings(
          value=["EI_EXPOSE_REP"]
          justification="Expected behavior"
        )

  public java.net.URL getBadgeUrl();
    descriptor: ()Ljava/net/URL;
    flags: (0x0001) ACC_PUBLIC
    Code:
      stack=1, locals=1, args_size=1
         0: aload_0
         1: getfield      #8                  // Field badgeUrl:Ljava/lang/String;
         4: invokestatic  #6                  // Method org/kohsuke/github/GitHubClient.parseURL:(Ljava/lang/String;)Ljava/net/URL;
         7: areturn
      LineNumberTable:
        line 80: 0
      LocalVariableTable:
        Start  Length  Slot  Name   Signature
            0       8     0  this   Lorg/kohsuke/github/GHWorkflow;

  public void disable() throws java.io.IOException;
    descriptor: ()V
    flags: (0x0001) ACC_PUBLIC
    Code:
      stack=6, locals=1, args_size=1
         0: aload_0
         1: invokevirtual #9                  // Method root:()Lorg/kohsuke/github/GitHub;
         4: invokevirtual #10                 // Method org/kohsuke/github/GitHub.createRequest:()Lorg/kohsuke/github/Requester;
         7: ldc           #11                 // String PUT
         9: invokevirtual #12                 // Method org/kohsuke/github/Requester.method:(Ljava/lang/String;)Lorg/kohsuke/github/GitHubRequest$Builder;
        12: checkcast     #13                 // class org/kohsuke/github/Requester
        15: aload_0
        16: invokespecial #14                 // Method getApiRoute:()Ljava/lang/String;
        19: iconst_1
        20: anewarray     #15                 // class java/lang/String
        23: dup
        24: iconst_0
        25: ldc           #16                 // String disable
        27: aastore
        28: invokevirtual #17                 // Method org/kohsuke/github/Requester.withUrlPath:(Ljava/lang/String;[Ljava/lang/String;)Lorg/kohsuke/github/GitHubRequest$Builder;
        31: checkcast     #13                 // class org/kohsuke/github/Requester
        34: invokevirtual #18                 // Method org/kohsuke/github/Requester.fetchHttpStatusCode:()I
        37: pop
        38: return
      LineNumberTable:
        line 90: 0
        line 91: 38
      LocalVariableTable:
        Start  Length  Slot  Name   Signature
            0      39     0  this   Lorg/kohsuke/github/GHWorkflow;
    Exceptions:
      throws java.io.IOException

  public void enable() throws java.io.IOException;
    descriptor: ()V
    flags: (0x0001) ACC_PUBLIC
    Code:
      stack=6, locals=1, args_size=1
         0: aload_0
         1: invokevirtual #9                  // Method root:()Lorg/kohsuke/github/GitHub;
         4: invokevirtual #10                 // Method org/kohsuke/github/GitHub.createRequest:()Lorg/kohsuke/github/Requester;
         7: ldc           #11                 // String PUT
         9: invokevirtual #12                 // Method org/kohsuke/github/Requester.method:(Ljava/lang/String;)Lorg/kohsuke/github/GitHubRequest$Builder;
        12: checkcast     #13                 // class org/kohsuke/github/Requester
        15: aload_0
        16: invokespecial #14                 // Method getApiRoute:()Ljava/lang/String;
        19: iconst_1
        20: anewarray     #15                 // class java/lang/String
        23: dup
        24: iconst_0
        25: ldc           #19                 // String enable
        27: aastore
        28: invokevirtual #17                 // Method org/kohsuke/github/Requester.withUrlPath:(Ljava/lang/String;[Ljava/lang/String;)Lorg/kohsuke/github/GitHubRequest$Builder;
        31: checkcast     #13                 // class org/kohsuke/github/Requester
        34: invokevirtual #18                 // Method org/kohsuke/github/Requester.fetchHttpStatusCode:()I
        37: pop
        38: return
      LineNumberTable:
        line 100: 0
        line 101: 38
      LocalVariableTable:
        Start  Length  Slot  Name   Signature
            0      39     0  this   Lorg/kohsuke/github/GHWorkflow;
    Exceptions:
      throws java.io.IOException

  public void dispatch(java.lang.String) throws java.io.IOException;
    descriptor: (Ljava/lang/String;)V
    flags: (0x0001) ACC_PUBLIC
    Code:
      stack=3, locals=2, args_size=2
         0: aload_0
         1: aload_1
         2: invokestatic  #20                 // Method java/util/Collections.emptyMap:()Ljava/util/Map;
         5: invokevirtual #21                 // Method dispatch:(Ljava/lang/String;Ljava/util/Map;)V
         8: return
      LineNumberTable:
        line 112: 0
        line 113: 8
      LocalVariableTable:
        Start  Length  Slot  Name   Signature
            0       9     0  this   Lorg/kohsuke/github/GHWorkflow;
            0       9     1   ref   Ljava/lang/String;
    Exceptions:
      throws java.io.IOException

  public void dispatch(java.lang.String, java.util.Map<java.lang.String, java.lang.Object>) throws java.io.IOException;
    descriptor: (Ljava/lang/String;Ljava/util/Map;)V
    flags: (0x0001) ACC_PUBLIC
    Code:
      stack=6, locals=4, args_size=3
         0: aload_0
         1: invokevirtual #9                  // Method root:()Lorg/kohsuke/github/GitHub;
         4: invokevirtual #10                 // Method org/kohsuke/github/GitHub.createRequest:()Lorg/kohsuke/github/Requester;
         7: ldc           #22                 // String POST
         9: invokevirtual #12                 // Method org/kohsuke/github/Requester.method:(Ljava/lang/String;)Lorg/kohsuke/github/GitHubRequest$Builder;
        12: checkcast     #13                 // class org/kohsuke/github/Requester
        15: aload_0
        16: invokespecial #14                 // Method getApiRoute:()Ljava/lang/String;
        19: iconst_1
        20: anewarray     #15                 // class java/lang/String
        23: dup
        24: iconst_0
        25: ldc           #23                 // String dispatches
        27: aastore
        28: invokevirtual #17                 // Method org/kohsuke/github/Requester.withUrlPath:(Ljava/lang/String;[Ljava/lang/String;)Lorg/kohsuke/github/GitHubRequest$Builder;
        31: checkcast     #13                 // class org/kohsuke/github/Requester
        34: ldc           #24                 // String ref
        36: aload_1
        37: invokevirtual #25                 // Method org/kohsuke/github/Requester.with:(Ljava/lang/String;Ljava/lang/String;)Lorg/kohsuke/github/GitHubRequest$Builder;
        40: checkcast     #13                 // class org/kohsuke/github/Requester
        43: astore_3
        44: aload_2
        45: invokeinterface #26,  1           // InterfaceMethod java/util/Map.isEmpty:()Z
        50: ifne          61
        53: aload_3
        54: ldc           #27                 // String inputs
        56: aload_2
        57: invokevirtual #28                 // Method org/kohsuke/github/Requester.with:(Ljava/lang/String;Ljava/util/Map;)Lorg/kohsuke/github/GitHubRequest$Builder;
        60: pop
        61: aload_3
        62: invokevirtual #18                 // Method org/kohsuke/github/Requester.fetchHttpStatusCode:()I
        65: pop
        66: return
      LineNumberTable:
        line 127: 0
        line 128: 9
        line 129: 16
        line 130: 37
        line 132: 44
        line 133: 53
        line 136: 61
        line 137: 66
      LocalVariableTable:
        Start  Length  Slot  Name   Signature
            0      67     0  this   Lorg/kohsuke/github/GHWorkflow;
            0      67     1   ref   Ljava/lang/String;
            0      67     2 inputs   Ljava/util/Map;
           44      23     3 requester   Lorg/kohsuke/github/Requester;
      LocalVariableTypeTable:
        Start  Length  Slot  Name   Signature
            0      67     2 inputs   Ljava/util/Map<Ljava/lang/String;Ljava/lang/Object;>;
      StackMapTable: number_of_entries = 1
        frame_type = 252 /* append */
          offset_delta = 61
          locals = [ class org/kohsuke/github/Requester ]
    Exceptions:
      throws java.io.IOException
    Signature: #103                         // (Ljava/lang/String;Ljava/util/Map<Ljava/lang/String;Ljava/lang/Object;>;)V

  public org.kohsuke.github.PagedIterable<org.kohsuke.github.GHWorkflowRun> listRuns();
    descriptor: ()Lorg/kohsuke/github/PagedIterable;
    flags: (0x0001) ACC_PUBLIC
    Code:
      stack=9, locals=1, args_size=1
         0: new           #29                 // class org/kohsuke/github/GHWorkflowRunsIterable
         3: dup
         4: aload_0
         5: getfield      #7                  // Field owner:Lorg/kohsuke/github/GHRepository;
         8: aload_0
         9: invokevirtual #9                  // Method root:()Lorg/kohsuke/github/GitHub;
        12: invokevirtual #10                 // Method org/kohsuke/github/GitHub.createRequest:()Lorg/kohsuke/github/Requester;
        15: aload_0
        16: invokespecial #14                 // Method getApiRoute:()Ljava/lang/String;
        19: iconst_1
        20: anewarray     #15                 // class java/lang/String
        23: dup
        24: iconst_0
        25: ldc           #30                 // String runs
        27: aastore
        28: invokevirtual #17                 // Method org/kohsuke/github/Requester.withUrlPath:(Ljava/lang/String;[Ljava/lang/String;)Lorg/kohsuke/github/GitHubRequest$Builder;
        31: invokespecial #31                 // Method org/kohsuke/github/GHWorkflowRunsIterable."<init>":(Lorg/kohsuke/github/GHRepository;Lorg/kohsuke/github/GitHubRequest$Builder;)V
        34: areturn
      LineNumberTable:
        line 145: 0
      LocalVariableTable:
        Start  Length  Slot  Name   Signature
            0      35     0  this   Lorg/kohsuke/github/GHWorkflow;
    Signature: #106                         // ()Lorg/kohsuke/github/PagedIterable<Lorg/kohsuke/github/GHWorkflowRun;>;

  private java.lang.String getApiRoute();
    descriptor: ()Ljava/lang/String;
    flags: (0x0002) ACC_PRIVATE
    Code:
      stack=3, locals=2, args_size=1
         0: aload_0
         1: getfield      #7                  // Field owner:Lorg/kohsuke/github/GHRepository;
         4: ifnonnull     46
         7: aload_0
         8: invokevirtual #32                 // Method getUrl:()Ljava/net/URL;
        11: ldc           #33                 // String Missing instance URL!
        13: invokestatic  #34                 // Method java/util/Objects.requireNonNull:(Ljava/lang/Object;Ljava/lang/String;)Ljava/lang/Object;
        16: checkcast     #35                 // class java/net/URL
        19: astore_1
        20: aload_1
        21: invokevirtual #36                 // Method java/net/URL.toString:()Ljava/lang/String;
        24: aload_0
        25: invokevirtual #9                  // Method root:()Lorg/kohsuke/github/GitHub;
        28: invokevirtual #37                 // Method org/kohsuke/github/GitHub.getApiUrl:()Ljava/lang/String;
        31: ldc           #38                 // String
        33: invokevirtual #39                 // Method java/lang/String.replace:(Ljava/lang/CharSequence;Ljava/lang/CharSequence;)Ljava/lang/String;
        36: ldc           #40                 // String /
        38: iconst_0
        39: anewarray     #41                 // class java/lang/CharSequence
        42: invokestatic  #42                 // Method org/apache/commons/lang3/StringUtils.prependIfMissing:(Ljava/lang/String;Ljava/lang/CharSequence;[Ljava/lang/CharSequence;)Ljava/lang/String;
        45: areturn
        46: new           #43                 // class java/lang/StringBuilder
        49: dup
        50: invokespecial #44                 // Method java/lang/StringBuilder."<init>":()V
        53: ldc           #45                 // String /repos/
        55: invokevirtual #46                 // Method java/lang/StringBuilder.append:(Ljava/lang/String;)Ljava/lang/StringBuilder;
        58: aload_0
        59: getfield      #7                  // Field owner:Lorg/kohsuke/github/GHRepository;
        62: invokevirtual #47                 // Method org/kohsuke/github/GHRepository.getOwnerName:()Ljava/lang/String;
        65: invokevirtual #46                 // Method java/lang/StringBuilder.append:(Ljava/lang/String;)Ljava/lang/StringBuilder;
        68: ldc           #40                 // String /
        70: invokevirtual #46                 // Method java/lang/StringBuilder.append:(Ljava/lang/String;)Ljava/lang/StringBuilder;
        73: aload_0
        74: getfield      #7                  // Field owner:Lorg/kohsuke/github/GHRepository;
        77: invokevirtual #48                 // Method org/kohsuke/github/GHRepository.getName:()Ljava/lang/String;
        80: invokevirtual #46                 // Method java/lang/StringBuilder.append:(Ljava/lang/String;)Ljava/lang/StringBuilder;
        83: ldc           #49                 // String /actions/workflows/
        85: invokevirtual #46                 // Method java/lang/StringBuilder.append:(Ljava/lang/String;)Ljava/lang/StringBuilder;
        88: aload_0
        89: invokevirtual #50                 // Method getId:()J
        92: invokevirtual #51                 // Method java/lang/StringBuilder.append:(J)Ljava/lang/StringBuilder;
        95: invokevirtual #52                 // Method java/lang/StringBuilder.toString:()Ljava/lang/String;
        98: areturn
      LineNumberTable:
        line 149: 0
        line 151: 7
        line 152: 20
        line 155: 46
      LocalVariableTable:
        Start  Length  Slot  Name   Signature
           20      26     1   url   Ljava/net/URL;
            0      99     0  this   Lorg/kohsuke/github/GHWorkflow;
      StackMapTable: number_of_entries = 1
        frame_type = 46 /* same */

  org.kohsuke.github.GHWorkflow wrapUp(org.kohsuke.github.GHRepository);
    descriptor: (Lorg/kohsuke/github/GHRepository;)Lorg/kohsuke/github/GHWorkflow;
    flags: (0x0000)
    Code:
      stack=2, locals=2, args_size=2
         0: aload_0
         1: aload_1
         2: putfield      #7                  // Field owner:Lorg/kohsuke/github/GHRepository;
         5: aload_0
         6: areturn
      LineNumberTable:
        line 159: 0
        line 160: 5
      LocalVariableTable:
        Start  Length  Slot  Name   Signature
            0       7     0  this   Lorg/kohsuke/github/GHWorkflow;
            0       7     1 owner   Lorg/kohsuke/github/GHRepository;
}
SourceFile: "GHWorkflow.java"
InnerClasses:
  static #180= #179 of #215;              // Builder=class org/kohsuke/github/GitHubRequest$Builder of class org/kohsuke/github/GitHubRequest
