Classfile /Users/mw/Projects/slang-braindump/.jar/jar8/assemble/slang-braindump/assemble/content/org/kohsuke/github/GitHubConnectorResponseErrorHandler$1.class
  Last modified May 29, 2022; size 1546 bytes
  SHA-256 checksum a1d21885f9925891d7f462683803e916101c62688a764068411144cf2fda2a7d
  Compiled from "GitHubConnectorResponseErrorHandler.java"
class org.kohsuke.github.GitHubConnectorResponseErrorHandler$1 extends org.kohsuke.github.GitHubConnectorResponseErrorHandler
  minor version: 0
  major version: 52
  flags: (0x0020) ACC_SUPER
  this_class: #11                         // org/kohsuke/github/GitHubConnectorResponseErrorHandler$1
  super_class: #12                        // org/kohsuke/github/GitHubConnectorResponseErrorHandler
  interfaces: 0, fields: 0, methods: 3, attributes: 3
Constant pool:
   #1 = Class              #35            // java/net/HttpURLConnection
   #2 = Methodref          #12.#36        // org/kohsuke/github/GitHubConnectorResponseErrorHandler."<init>":()V
   #3 = Methodref          #37.#38        // org/kohsuke/github/connector/GitHubConnectorResponse.statusCode:()I
   #4 = Class              #39            // java/io/FileNotFoundException
   #5 = Methodref          #37.#40        // org/kohsuke/github/connector/GitHubConnectorResponse.request:()Lorg/kohsuke/github/connector/GitHubConnectorRequest;
   #6 = InterfaceMethodref #41.#42        // org/kohsuke/github/connector/GitHubConnectorRequest.url:()Ljava/net/URL;
   #7 = Methodref          #43.#44        // java/net/URL.toString:()Ljava/lang/String;
   #8 = Methodref          #4.#45         // java/io/FileNotFoundException."<init>":(Ljava/lang/String;)V
   #9 = Class              #46            // org/kohsuke/github/HttpException
  #10 = Methodref          #9.#47         // org/kohsuke/github/HttpException."<init>":(Lorg/kohsuke/github/connector/GitHubConnectorResponse;)V
  #11 = Class              #48            // org/kohsuke/github/GitHubConnectorResponseErrorHandler$1
  #12 = Class              #49            // org/kohsuke/github/GitHubConnectorResponseErrorHandler
  #13 = Utf8               <init>
  #14 = Utf8               ()V
  #15 = Utf8               Code
  #16 = Utf8               LineNumberTable
  #17 = Utf8               LocalVariableTable
  #18 = Utf8               this
  #19 = Utf8               InnerClasses
  #20 = Utf8               Lorg/kohsuke/github/GitHubConnectorResponseErrorHandler$1;
  #21 = Utf8               isError
  #22 = Utf8               (Lorg/kohsuke/github/connector/GitHubConnectorResponse;)Z
  #23 = Utf8               connectorResponse
  #24 = Utf8               Lorg/kohsuke/github/connector/GitHubConnectorResponse;
  #25 = Utf8               StackMapTable
  #26 = Utf8               Exceptions
  #27 = Class              #50            // java/io/IOException
  #28 = Utf8               RuntimeInvisibleParameterAnnotations
  #29 = Utf8               Lorg/jetbrains/annotations/NotNull;
  #30 = Utf8               onError
  #31 = Utf8               (Lorg/kohsuke/github/connector/GitHubConnectorResponse;)V
  #32 = Utf8               SourceFile
  #33 = Utf8               GitHubConnectorResponseErrorHandler.java
  #34 = Utf8               EnclosingMethod
  #35 = Utf8               java/net/HttpURLConnection
  #36 = NameAndType        #13:#14        // "<init>":()V
  #37 = Class              #51            // org/kohsuke/github/connector/GitHubConnectorResponse
  #38 = NameAndType        #52:#53        // statusCode:()I
  #39 = Utf8               java/io/FileNotFoundException
  #40 = NameAndType        #54:#55        // request:()Lorg/kohsuke/github/connector/GitHubConnectorRequest;
  #41 = Class              #56            // org/kohsuke/github/connector/GitHubConnectorRequest
  #42 = NameAndType        #57:#58        // url:()Ljava/net/URL;
  #43 = Class              #59            // java/net/URL
  #44 = NameAndType        #60:#61        // toString:()Ljava/lang/String;
  #45 = NameAndType        #13:#62        // "<init>":(Ljava/lang/String;)V
  #46 = Utf8               org/kohsuke/github/HttpException
  #47 = NameAndType        #13:#31        // "<init>":(Lorg/kohsuke/github/connector/GitHubConnectorResponse;)V
  #48 = Utf8               org/kohsuke/github/GitHubConnectorResponseErrorHandler$1
  #49 = Utf8               org/kohsuke/github/GitHubConnectorResponseErrorHandler
  #50 = Utf8               java/io/IOException
  #51 = Utf8               org/kohsuke/github/connector/GitHubConnectorResponse
  #52 = Utf8               statusCode
  #53 = Utf8               ()I
  #54 = Utf8               request
  #55 = Utf8               ()Lorg/kohsuke/github/connector/GitHubConnectorRequest;
  #56 = Utf8               org/kohsuke/github/connector/GitHubConnectorRequest
  #57 = Utf8               url
  #58 = Utf8               ()Ljava/net/URL;
  #59 = Utf8               java/net/URL
  #60 = Utf8               toString
  #61 = Utf8               ()Ljava/lang/String;
  #62 = Utf8               (Ljava/lang/String;)V
{
  org.kohsuke.github.GitHubConnectorResponseErrorHandler$1();
    descriptor: ()V
    flags: (0x0000)
    Code:
      stack=1, locals=1, args_size=1
         0: aload_0
         1: invokespecial #2                  // Method org/kohsuke/github/GitHubConnectorResponseErrorHandler."<init>":()V
         4: return
      LineNumberTable:
        line 45: 0
      LocalVariableTable:
        Start  Length  Slot  Name   Signature
            0       5     0  this   Lorg/kohsuke/github/GitHubConnectorResponseErrorHandler$1;

  public boolean isError(org.kohsuke.github.connector.GitHubConnectorResponse) throws java.io.IOException;
    descriptor: (Lorg/kohsuke/github/connector/GitHubConnectorResponse;)Z
    flags: (0x0001) ACC_PUBLIC
    Code:
      stack=2, locals=2, args_size=2
         0: aload_1
         1: invokevirtual #3                  // Method org/kohsuke/github/connector/GitHubConnectorResponse.statusCode:()I
         4: sipush        400
         7: if_icmplt     14
        10: iconst_1
        11: goto          15
        14: iconst_0
        15: ireturn
      LineNumberTable:
        line 48: 0
      LocalVariableTable:
        Start  Length  Slot  Name   Signature
            0      16     0  this   Lorg/kohsuke/github/GitHubConnectorResponseErrorHandler$1;
            0      16     1 connectorResponse   Lorg/kohsuke/github/connector/GitHubConnectorResponse;
      StackMapTable: number_of_entries = 2
        frame_type = 14 /* same */
        frame_type = 64 /* same_locals_1_stack_item */
          stack = [ int ]
    Exceptions:
      throws java.io.IOException
    RuntimeInvisibleParameterAnnotations:
      parameter 0:
        0: #29()
          org.jetbrains.annotations.NotNull

  public void onError(org.kohsuke.github.connector.GitHubConnectorResponse) throws java.io.IOException;
    descriptor: (Lorg/kohsuke/github/connector/GitHubConnectorResponse;)V
    flags: (0x0001) ACC_PUBLIC
    Code:
      stack=3, locals=2, args_size=2
         0: aload_1
         1: invokevirtual #3                  // Method org/kohsuke/github/connector/GitHubConnectorResponse.statusCode:()I
         4: sipush        404
         7: if_icmpne     30
        10: new           #4                  // class java/io/FileNotFoundException
        13: dup
        14: aload_1
        15: invokevirtual #5                  // Method org/kohsuke/github/connector/GitHubConnectorResponse.request:()Lorg/kohsuke/github/connector/GitHubConnectorRequest;
        18: invokeinterface #6,  1            // InterfaceMethod org/kohsuke/github/connector/GitHubConnectorRequest.url:()Ljava/net/URL;
        23: invokevirtual #7                  // Method java/net/URL.toString:()Ljava/lang/String;
        26: invokespecial #8                  // Method java/io/FileNotFoundException."<init>":(Ljava/lang/String;)V
        29: athrow
        30: new           #9                  // class org/kohsuke/github/HttpException
        33: dup
        34: aload_1
        35: invokespecial #10                 // Method org/kohsuke/github/HttpException."<init>":(Lorg/kohsuke/github/connector/GitHubConnectorResponse;)V
        38: athrow
      LineNumberTable:
        line 53: 0
        line 54: 10
        line 56: 30
      LocalVariableTable:
        Start  Length  Slot  Name   Signature
            0      39     0  this   Lorg/kohsuke/github/GitHubConnectorResponseErrorHandler$1;
            0      39     1 connectorResponse   Lorg/kohsuke/github/connector/GitHubConnectorResponse;
      StackMapTable: number_of_entries = 1
        frame_type = 30 /* same */
    Exceptions:
      throws java.io.IOException
    RuntimeInvisibleParameterAnnotations:
      parameter 0:
        0: #29()
          org.jetbrains.annotations.NotNull
}
SourceFile: "GitHubConnectorResponseErrorHandler.java"
EnclosingMethod: #12.#0                 // org.kohsuke.github.GitHubConnectorResponseErrorHandler
InnerClasses:
  #11;                                    // class org/kohsuke/github/GitHubConnectorResponseErrorHandler$1
