Classfile /Users/mw/Projects/slang-braindump/.jar/jar8/assemble/slang-braindump/assemble/content/org/kohsuke/github/GitHubRequest$Entry.class
  Last modified May 29, 2022; size 567 bytes
  SHA-256 checksum 818d629d35796ee29c2400028b098ad162c0a768c871432deed70f8566e4aeb8
  Compiled from "GitHubRequest.java"
public class org.kohsuke.github.GitHubRequest$Entry
  minor version: 0
  major version: 52
  flags: (0x0021) ACC_PUBLIC, ACC_SUPER
  this_class: #4                          // org/kohsuke/github/GitHubRequest$Entry
  super_class: #5                         // java/lang/Object
  interfaces: 0, fields: 2, methods: 1, attributes: 2
Constant pool:
   #1 = Methodref          #5.#21         // java/lang/Object."<init>":()V
   #2 = Fieldref           #4.#22         // org/kohsuke/github/GitHubRequest$Entry.key:Ljava/lang/String;
   #3 = Fieldref           #4.#23         // org/kohsuke/github/GitHubRequest$Entry.value:Ljava/lang/Object;
   #4 = Class              #25            // org/kohsuke/github/GitHubRequest$Entry
   #5 = Class              #26            // java/lang/Object
   #6 = Utf8               key
   #7 = Utf8               Ljava/lang/String;
   #8 = Utf8               value
   #9 = Utf8               Ljava/lang/Object;
  #10 = Utf8               <init>
  #11 = Utf8               (Ljava/lang/String;Ljava/lang/Object;)V
  #12 = Utf8               Code
  #13 = Utf8               LineNumberTable
  #14 = Utf8               LocalVariableTable
  #15 = Utf8               this
  #16 = Utf8               Entry
  #17 = Utf8               InnerClasses
  #18 = Utf8               Lorg/kohsuke/github/GitHubRequest$Entry;
  #19 = Utf8               SourceFile
  #20 = Utf8               GitHubRequest.java
  #21 = NameAndType        #10:#27        // "<init>":()V
  #22 = NameAndType        #6:#7          // key:Ljava/lang/String;
  #23 = NameAndType        #8:#9          // value:Ljava/lang/Object;
  #24 = Class              #28            // org/kohsuke/github/GitHubRequest
  #25 = Utf8               org/kohsuke/github/GitHubRequest$Entry
  #26 = Utf8               java/lang/Object
  #27 = Utf8               ()V
  #28 = Utf8               org/kohsuke/github/GitHubRequest
{
  final java.lang.String key;
    descriptor: Ljava/lang/String;
    flags: (0x0010) ACC_FINAL

  final java.lang.Object value;
    descriptor: Ljava/lang/Object;
    flags: (0x0010) ACC_FINAL

  protected org.kohsuke.github.GitHubRequest$Entry(java.lang.String, java.lang.Object);
    descriptor: (Ljava/lang/String;Ljava/lang/Object;)V
    flags: (0x0004) ACC_PROTECTED
    Code:
      stack=2, locals=3, args_size=3
         0: aload_0
         1: invokespecial #1                  // Method java/lang/Object."<init>":()V
         4: aload_0
         5: aload_1
         6: putfield      #2                  // Field key:Ljava/lang/String;
         9: aload_0
        10: aload_2
        11: putfield      #3                  // Field value:Ljava/lang/Object;
        14: return
      LineNumberTable:
        line 784: 0
        line 785: 4
        line 786: 9
        line 787: 14
      LocalVariableTable:
        Start  Length  Slot  Name   Signature
            0      15     0  this   Lorg/kohsuke/github/GitHubRequest$Entry;
            0      15     1   key   Ljava/lang/String;
            0      15     2 value   Ljava/lang/Object;
}
SourceFile: "GitHubRequest.java"
InnerClasses:
  protected static #16= #4 of #24;        // Entry=class org/kohsuke/github/GitHubRequest$Entry of class org/kohsuke/github/GitHubRequest
