Classfile /Users/mw/Projects/slang-braindump/.jar/jar8/assemble/slang-braindump/assemble/content/org/kohsuke/github/GitUser.class
  Last modified May 29, 2022; size 1154 bytes
  SHA-256 checksum b2499e894a801b5e9a1c9b0377a86c1e529de215f2d632c373e9a8346f1bde8b
  Compiled from "GitUser.java"
public class org.kohsuke.github.GitUser
  minor version: 0
  major version: 52
  flags: (0x0021) ACC_PUBLIC, ACC_SUPER
  this_class: #7                          // org/kohsuke/github/GitUser
  super_class: #8                         // java/lang/Object
  interfaces: 0, fields: 4, methods: 5, attributes: 2
Constant pool:
   #1 = Methodref          #8.#39         // java/lang/Object."<init>":()V
   #2 = Fieldref           #7.#40         // org/kohsuke/github/GitUser.name:Ljava/lang/String;
   #3 = Fieldref           #7.#41         // org/kohsuke/github/GitUser.email:Ljava/lang/String;
   #4 = Fieldref           #7.#42         // org/kohsuke/github/GitUser.username:Ljava/lang/String;
   #5 = Fieldref           #7.#43         // org/kohsuke/github/GitUser.date:Ljava/lang/String;
   #6 = Methodref          #44.#45        // org/kohsuke/github/GitHubClient.parseDate:(Ljava/lang/String;)Ljava/util/Date;
   #7 = Class              #46            // org/kohsuke/github/GitUser
   #8 = Class              #47            // java/lang/Object
   #9 = Utf8               name
  #10 = Utf8               Ljava/lang/String;
  #11 = Utf8               email
  #12 = Utf8               date
  #13 = Utf8               username
  #14 = Utf8               <init>
  #15 = Utf8               ()V
  #16 = Utf8               Code
  #17 = Utf8               LineNumberTable
  #18 = Utf8               LocalVariableTable
  #19 = Utf8               this
  #20 = Utf8               Lorg/kohsuke/github/GitUser;
  #21 = Utf8               getName
  #22 = Utf8               ()Ljava/lang/String;
  #23 = Utf8               getEmail
  #24 = Utf8               getUsername
  #25 = Utf8               RuntimeVisibleAnnotations
  #26 = Utf8               Ljavax/annotation/CheckForNull;
  #27 = Utf8               getDate
  #28 = Utf8               ()Ljava/util/Date;
  #29 = Utf8               SourceFile
  #30 = Utf8               GitUser.java
  #31 = Utf8               RuntimeInvisibleAnnotations
  #32 = Utf8               Ledu/umd/cs/findbugs/annotations/SuppressFBWarnings;
  #33 = Utf8               value
  #34 = Utf8               UWF_UNWRITTEN_PUBLIC_OR_PROTECTED_FIELD
  #35 = Utf8               UWF_UNWRITTEN_FIELD
  #36 = Utf8               NP_UNWRITTEN_FIELD
  #37 = Utf8               justification
  #38 = Utf8               JSON API
  #39 = NameAndType        #14:#15        // "<init>":()V
  #40 = NameAndType        #9:#10         // name:Ljava/lang/String;
  #41 = NameAndType        #11:#10        // email:Ljava/lang/String;
  #42 = NameAndType        #13:#10        // username:Ljava/lang/String;
  #43 = NameAndType        #12:#10        // date:Ljava/lang/String;
  #44 = Class              #48            // org/kohsuke/github/GitHubClient
  #45 = NameAndType        #49:#50        // parseDate:(Ljava/lang/String;)Ljava/util/Date;
  #46 = Utf8               org/kohsuke/github/GitUser
  #47 = Utf8               java/lang/Object
  #48 = Utf8               org/kohsuke/github/GitHubClient
  #49 = Utf8               parseDate
  #50 = Utf8               (Ljava/lang/String;)Ljava/util/Date;
{
  private java.lang.String name;
    descriptor: Ljava/lang/String;
    flags: (0x0002) ACC_PRIVATE

  private java.lang.String email;
    descriptor: Ljava/lang/String;
    flags: (0x0002) ACC_PRIVATE

  private java.lang.String date;
    descriptor: Ljava/lang/String;
    flags: (0x0002) ACC_PRIVATE

  private java.lang.String username;
    descriptor: Ljava/lang/String;
    flags: (0x0002) ACC_PRIVATE

  public org.kohsuke.github.GitUser();
    descriptor: ()V
    flags: (0x0001) ACC_PUBLIC
    Code:
      stack=1, locals=1, args_size=1
         0: aload_0
         1: invokespecial #1                  // Method java/lang/Object."<init>":()V
         4: return
      LineNumberTable:
        line 19: 0
      LocalVariableTable:
        Start  Length  Slot  Name   Signature
            0       5     0  this   Lorg/kohsuke/github/GitUser;

  public java.lang.String getName();
    descriptor: ()Ljava/lang/String;
    flags: (0x0001) ACC_PUBLIC
    Code:
      stack=1, locals=1, args_size=1
         0: aload_0
         1: getfield      #2                  // Field name:Ljava/lang/String;
         4: areturn
      LineNumberTable:
        line 28: 0
      LocalVariableTable:
        Start  Length  Slot  Name   Signature
            0       5     0  this   Lorg/kohsuke/github/GitUser;

  public java.lang.String getEmail();
    descriptor: ()Ljava/lang/String;
    flags: (0x0001) ACC_PUBLIC
    Code:
      stack=1, locals=1, args_size=1
         0: aload_0
         1: getfield      #3                  // Field email:Ljava/lang/String;
         4: areturn
      LineNumberTable:
        line 37: 0
      LocalVariableTable:
        Start  Length  Slot  Name   Signature
            0       5     0  this   Lorg/kohsuke/github/GitUser;

  public java.lang.String getUsername();
    descriptor: ()Ljava/lang/String;
    flags: (0x0001) ACC_PUBLIC
    Code:
      stack=1, locals=1, args_size=1
         0: aload_0
         1: getfield      #4                  // Field username:Ljava/lang/String;
         4: areturn
      LineNumberTable:
        line 47: 0
      LocalVariableTable:
        Start  Length  Slot  Name   Signature
            0       5     0  this   Lorg/kohsuke/github/GitUser;
    RuntimeVisibleAnnotations:
      0: #26()
        javax.annotation.CheckForNull

  public java.util.Date getDate();
    descriptor: ()Ljava/util/Date;
    flags: (0x0001) ACC_PUBLIC
    Code:
      stack=1, locals=1, args_size=1
         0: aload_0
         1: getfield      #5                  // Field date:Ljava/lang/String;
         4: invokestatic  #6                  // Method org/kohsuke/github/GitHubClient.parseDate:(Ljava/lang/String;)Ljava/util/Date;
         7: areturn
      LineNumberTable:
        line 56: 0
      LocalVariableTable:
        Start  Length  Slot  Name   Signature
            0       8     0  this   Lorg/kohsuke/github/GitUser;
}
SourceFile: "GitUser.java"
RuntimeInvisibleAnnotations:
  0: #32(#33=[s#34,s#35,s#36],#37=s#38)
    edu.umd.cs.findbugs.annotations.SuppressFBWarnings(
      value=["UWF_UNWRITTEN_PUBLIC_OR_PROTECTED_FIELD","UWF_UNWRITTEN_FIELD","NP_UNWRITTEN_FIELD"]
      justification="JSON API"
    )
