Classfile /Users/mw/Projects/slang-braindump/.jar/jar8/assemble/slang-braindump/assemble/content/org/kohsuke/github/PagedIterable.class
  Last modified May 29, 2022; size 4893 bytes
  SHA-256 checksum f2ecbc2f38ee284670b0a086ba37877bef753c070c1e6a1d2b8ac3acb07b3025
  Compiled from "PagedIterable.java"
public abstract class org.kohsuke.github.PagedIterable<T extends java.lang.Object> extends java.lang.Object implements java.lang.Iterable<T>
  minor version: 0
  major version: 52
  flags: (0x0421) ACC_PUBLIC, ACC_SUPER, ACC_ABSTRACT
  this_class: #40                         // org/kohsuke/github/PagedIterable
  super_class: #41                        // java/lang/Object
  interfaces: 1, fields: 1, methods: 12, attributes: 2
Constant pool:
    #1 = Methodref          #41.#115      // java/lang/Object."<init>":()V
    #2 = Fieldref           #40.#116      // org/kohsuke/github/PagedIterable.pageSize:I
    #3 = Methodref          #40.#117      // org/kohsuke/github/PagedIterable._iterator:(I)Lorg/kohsuke/github/PagedIterator;
    #4 = Class              #118          // java/util/ArrayList
    #5 = Methodref          #4.#115       // java/util/ArrayList."<init>":()V
    #6 = Methodref          #84.#119      // org/kohsuke/github/PagedIterator.nextPageArray:()[Ljava/lang/Object;
    #7 = Methodref          #120.#121     // java/lang/reflect/Array.getLength:(Ljava/lang/Object;)I
    #8 = Methodref          #4.#122       // java/util/ArrayList.add:(Ljava/lang/Object;)Z
    #9 = Methodref          #84.#123      // org/kohsuke/github/PagedIterator.hasNext:()Z
   #10 = Methodref          #41.#124      // java/lang/Object.getClass:()Ljava/lang/Class;
   #11 = Methodref          #40.#125      // org/kohsuke/github/PagedIterable.concatenatePages:(Ljava/lang/Class;Ljava/util/List;I)[Ljava/lang/Object;
   #12 = Class              #126          // org/kohsuke/github/GHException
   #13 = Methodref          #12.#127      // org/kohsuke/github/GHException.getCause:()Ljava/lang/Throwable;
   #14 = Class              #128          // java/io/IOException
   #15 = Methodref          #40.#129      // org/kohsuke/github/PagedIterable.iterator:()Lorg/kohsuke/github/PagedIterator;
   #16 = Methodref          #40.#130      // org/kohsuke/github/PagedIterable.toArray:(Lorg/kohsuke/github/PagedIterator;)[Ljava/lang/Object;
   #17 = Methodref          #40.#131      // org/kohsuke/github/PagedIterable.toArray:()[Ljava/lang/Object;
   #18 = Methodref          #132.#133     // java/util/Arrays.asList:([Ljava/lang/Object;)Ljava/util/List;
   #19 = Methodref          #134.#135     // java/util/Collections.unmodifiableList:(Ljava/util/List;)Ljava/util/List;
   #20 = Class              #136          // java/util/LinkedHashSet
   #21 = Methodref          #20.#137      // java/util/LinkedHashSet."<init>":(Ljava/util/Collection;)V
   #22 = Methodref          #134.#138     // java/util/Collections.unmodifiableSet:(Ljava/util/Set;)Ljava/util/Set;
   #23 = Methodref          #40.#139      // org/kohsuke/github/PagedIterable.toList:()Ljava/util/List;
   #24 = Class              #140          // java/lang/StringBuilder
   #25 = Methodref          #24.#115      // java/lang/StringBuilder."<init>":()V
   #26 = String             #141          // Failed to retrieve list:
   #27 = Methodref          #24.#142      // java/lang/StringBuilder.append:(Ljava/lang/String;)Ljava/lang/StringBuilder;
   #28 = Methodref          #14.#143      // java/io/IOException.getMessage:()Ljava/lang/String;
   #29 = Methodref          #24.#144      // java/lang/StringBuilder.toString:()Ljava/lang/String;
   #30 = Methodref          #12.#145      // org/kohsuke/github/GHException."<init>":(Ljava/lang/String;Ljava/lang/Throwable;)V
   #31 = Methodref          #40.#146      // org/kohsuke/github/PagedIterable.toSet:()Ljava/util/Set;
   #32 = Methodref          #147.#148     // java/lang/Class.getComponentType:()Ljava/lang/Class;
   #33 = Methodref          #120.#149     // java/lang/reflect/Array.newInstance:(Ljava/lang/Class;I)Ljava/lang/Object;
   #34 = Methodref          #147.#150     // java/lang/Class.cast:(Ljava/lang/Object;)Ljava/lang/Object;
   #35 = Class              #73           // "[Ljava/lang/Object;"
   #36 = InterfaceMethodref #151.#152     // java/util/List.iterator:()Ljava/util/Iterator;
   #37 = InterfaceMethodref #109.#123     // java/util/Iterator.hasNext:()Z
   #38 = InterfaceMethodref #109.#153     // java/util/Iterator.next:()Ljava/lang/Object;
   #39 = Methodref          #154.#155     // java/lang/System.arraycopy:(Ljava/lang/Object;ILjava/lang/Object;II)V
   #40 = Class              #156          // org/kohsuke/github/PagedIterable
   #41 = Class              #157          // java/lang/Object
   #42 = Class              #158          // java/lang/Iterable
   #43 = Utf8               pageSize
   #44 = Utf8               I
   #45 = Utf8               <init>
   #46 = Utf8               ()V
   #47 = Utf8               Code
   #48 = Utf8               LineNumberTable
   #49 = Utf8               LocalVariableTable
   #50 = Utf8               this
   #51 = Utf8               Lorg/kohsuke/github/PagedIterable;
   #52 = Utf8               LocalVariableTypeTable
   #53 = Utf8               Lorg/kohsuke/github/PagedIterable<TT;>;
   #54 = Utf8               withPageSize
   #55 = Utf8               (I)Lorg/kohsuke/github/PagedIterable;
   #56 = Utf8               size
   #57 = Utf8               Signature
   #58 = Utf8               (I)Lorg/kohsuke/github/PagedIterable<TT;>;
   #59 = Utf8               iterator
   #60 = Utf8               ()Lorg/kohsuke/github/PagedIterator;
   #61 = Utf8               ()Lorg/kohsuke/github/PagedIterator<TT;>;
   #62 = Utf8               RuntimeVisibleAnnotations
   #63 = Utf8               Ljavax/annotation/Nonnull;
   #64 = Utf8               _iterator
   #65 = Utf8               (I)Lorg/kohsuke/github/PagedIterator;
   #66 = Utf8               (I)Lorg/kohsuke/github/PagedIterator<TT;>;
   #67 = Utf8               toArray
   #68 = Utf8               (Lorg/kohsuke/github/PagedIterator;)[Ljava/lang/Object;
   #69 = Utf8               pages
   #70 = Utf8               Ljava/util/ArrayList;
   #71 = Utf8               totalSize
   #72 = Utf8               item
   #73 = Utf8               [Ljava/lang/Object;
   #74 = Utf8               type
   #75 = Utf8               Ljava/lang/Class;
   #76 = Utf8               e
   #77 = Utf8               Lorg/kohsuke/github/GHException;
   #78 = Utf8               Lorg/kohsuke/github/PagedIterator;
   #79 = Utf8               Ljava/util/ArrayList<[TT;>;
   #80 = Utf8               [TT;
   #81 = Utf8               Ljava/lang/Class<[TT;>;
   #82 = Utf8               Lorg/kohsuke/github/PagedIterator<TT;>;
   #83 = Utf8               StackMapTable
   #84 = Class              #159          // org/kohsuke/github/PagedIterator
   #85 = Utf8               Exceptions
   #86 = Utf8               (Lorg/kohsuke/github/PagedIterator<TT;>;)[TT;
   #87 = Utf8               ()[Ljava/lang/Object;
   #88 = Utf8               ()[TT;
   #89 = Utf8               toList
   #90 = Utf8               ()Ljava/util/List;
   #91 = Utf8               ()Ljava/util/List<TT;>;
   #92 = Utf8               toSet
   #93 = Utf8               ()Ljava/util/Set;
   #94 = Utf8               ()Ljava/util/Set<TT;>;
   #95 = Utf8               asList
   #96 = Utf8               Ljava/io/IOException;
   #97 = Utf8               Deprecated
   #98 = Utf8               Ljava/lang/Deprecated;
   #99 = Utf8               asSet
  #100 = Utf8               concatenatePages
  #101 = Utf8               (Ljava/lang/Class;Ljava/util/List;I)[Ljava/lang/Object;
  #102 = Utf8               pageLength
  #103 = Utf8               page
  #104 = Utf8               Ljava/util/List;
  #105 = Utf8               totalLength
  #106 = Utf8               result
  #107 = Utf8               position
  #108 = Utf8               Ljava/util/List<[TT;>;
  #109 = Class              #160          // java/util/Iterator
  #110 = Utf8               (Ljava/lang/Class<[TT;>;Ljava/util/List<[TT;>;I)[TT;
  #111 = Utf8               ()Ljava/util/Iterator;
  #112 = Utf8               <T:Ljava/lang/Object;>Ljava/lang/Object;Ljava/lang/Iterable<TT;>;
  #113 = Utf8               SourceFile
  #114 = Utf8               PagedIterable.java
  #115 = NameAndType        #45:#46       // "<init>":()V
  #116 = NameAndType        #43:#44       // pageSize:I
  #117 = NameAndType        #64:#65       // _iterator:(I)Lorg/kohsuke/github/PagedIterator;
  #118 = Utf8               java/util/ArrayList
  #119 = NameAndType        #161:#87      // nextPageArray:()[Ljava/lang/Object;
  #120 = Class              #162          // java/lang/reflect/Array
  #121 = NameAndType        #163:#164     // getLength:(Ljava/lang/Object;)I
  #122 = NameAndType        #165:#166     // add:(Ljava/lang/Object;)Z
  #123 = NameAndType        #167:#168     // hasNext:()Z
  #124 = NameAndType        #169:#170     // getClass:()Ljava/lang/Class;
  #125 = NameAndType        #100:#101     // concatenatePages:(Ljava/lang/Class;Ljava/util/List;I)[Ljava/lang/Object;
  #126 = Utf8               org/kohsuke/github/GHException
  #127 = NameAndType        #171:#172     // getCause:()Ljava/lang/Throwable;
  #128 = Utf8               java/io/IOException
  #129 = NameAndType        #59:#60       // iterator:()Lorg/kohsuke/github/PagedIterator;
  #130 = NameAndType        #67:#68       // toArray:(Lorg/kohsuke/github/PagedIterator;)[Ljava/lang/Object;
  #131 = NameAndType        #67:#87       // toArray:()[Ljava/lang/Object;
  #132 = Class              #173          // java/util/Arrays
  #133 = NameAndType        #95:#174      // asList:([Ljava/lang/Object;)Ljava/util/List;
  #134 = Class              #175          // java/util/Collections
  #135 = NameAndType        #176:#177     // unmodifiableList:(Ljava/util/List;)Ljava/util/List;
  #136 = Utf8               java/util/LinkedHashSet
  #137 = NameAndType        #45:#178      // "<init>":(Ljava/util/Collection;)V
  #138 = NameAndType        #179:#180     // unmodifiableSet:(Ljava/util/Set;)Ljava/util/Set;
  #139 = NameAndType        #89:#90       // toList:()Ljava/util/List;
  #140 = Utf8               java/lang/StringBuilder
  #141 = Utf8               Failed to retrieve list:
  #142 = NameAndType        #181:#182     // append:(Ljava/lang/String;)Ljava/lang/StringBuilder;
  #143 = NameAndType        #183:#184     // getMessage:()Ljava/lang/String;
  #144 = NameAndType        #185:#184     // toString:()Ljava/lang/String;
  #145 = NameAndType        #45:#186      // "<init>":(Ljava/lang/String;Ljava/lang/Throwable;)V
  #146 = NameAndType        #92:#93       // toSet:()Ljava/util/Set;
  #147 = Class              #187          // java/lang/Class
  #148 = NameAndType        #188:#170     // getComponentType:()Ljava/lang/Class;
  #149 = NameAndType        #189:#190     // newInstance:(Ljava/lang/Class;I)Ljava/lang/Object;
  #150 = NameAndType        #191:#192     // cast:(Ljava/lang/Object;)Ljava/lang/Object;
  #151 = Class              #193          // java/util/List
  #152 = NameAndType        #59:#111      // iterator:()Ljava/util/Iterator;
  #153 = NameAndType        #194:#195     // next:()Ljava/lang/Object;
  #154 = Class              #196          // java/lang/System
  #155 = NameAndType        #197:#198     // arraycopy:(Ljava/lang/Object;ILjava/lang/Object;II)V
  #156 = Utf8               org/kohsuke/github/PagedIterable
  #157 = Utf8               java/lang/Object
  #158 = Utf8               java/lang/Iterable
  #159 = Utf8               org/kohsuke/github/PagedIterator
  #160 = Utf8               java/util/Iterator
  #161 = Utf8               nextPageArray
  #162 = Utf8               java/lang/reflect/Array
  #163 = Utf8               getLength
  #164 = Utf8               (Ljava/lang/Object;)I
  #165 = Utf8               add
  #166 = Utf8               (Ljava/lang/Object;)Z
  #167 = Utf8               hasNext
  #168 = Utf8               ()Z
  #169 = Utf8               getClass
  #170 = Utf8               ()Ljava/lang/Class;
  #171 = Utf8               getCause
  #172 = Utf8               ()Ljava/lang/Throwable;
  #173 = Utf8               java/util/Arrays
  #174 = Utf8               ([Ljava/lang/Object;)Ljava/util/List;
  #175 = Utf8               java/util/Collections
  #176 = Utf8               unmodifiableList
  #177 = Utf8               (Ljava/util/List;)Ljava/util/List;
  #178 = Utf8               (Ljava/util/Collection;)V
  #179 = Utf8               unmodifiableSet
  #180 = Utf8               (Ljava/util/Set;)Ljava/util/Set;
  #181 = Utf8               append
  #182 = Utf8               (Ljava/lang/String;)Ljava/lang/StringBuilder;
  #183 = Utf8               getMessage
  #184 = Utf8               ()Ljava/lang/String;
  #185 = Utf8               toString
  #186 = Utf8               (Ljava/lang/String;Ljava/lang/Throwable;)V
  #187 = Utf8               java/lang/Class
  #188 = Utf8               getComponentType
  #189 = Utf8               newInstance
  #190 = Utf8               (Ljava/lang/Class;I)Ljava/lang/Object;
  #191 = Utf8               cast
  #192 = Utf8               (Ljava/lang/Object;)Ljava/lang/Object;
  #193 = Utf8               java/util/List
  #194 = Utf8               next
  #195 = Utf8               ()Ljava/lang/Object;
  #196 = Utf8               java/lang/System
  #197 = Utf8               arraycopy
  #198 = Utf8               (Ljava/lang/Object;ILjava/lang/Object;II)V
{
  private int pageSize;
    descriptor: I
    flags: (0x0002) ACC_PRIVATE

  public org.kohsuke.github.PagedIterable();
    descriptor: ()V
    flags: (0x0001) ACC_PUBLIC
    Code:
      stack=2, locals=1, args_size=1
         0: aload_0
         1: invokespecial #1                  // Method java/lang/Object."<init>":()V
         4: aload_0
         5: iconst_0
         6: putfield      #2                  // Field pageSize:I
         9: return
      LineNumberTable:
        line 22: 0
        line 26: 4
      LocalVariableTable:
        Start  Length  Slot  Name   Signature
            0      10     0  this   Lorg/kohsuke/github/PagedIterable;
      LocalVariableTypeTable:
        Start  Length  Slot  Name   Signature
            0      10     0  this   Lorg/kohsuke/github/PagedIterable<TT;>;

  public org.kohsuke.github.PagedIterable<T> withPageSize(int);
    descriptor: (I)Lorg/kohsuke/github/PagedIterable;
    flags: (0x0001) ACC_PUBLIC
    Code:
      stack=2, locals=2, args_size=2
         0: aload_0
         1: iload_1
         2: putfield      #2                  // Field pageSize:I
         5: aload_0
         6: areturn
      LineNumberTable:
        line 39: 0
        line 40: 5
      LocalVariableTable:
        Start  Length  Slot  Name   Signature
            0       7     0  this   Lorg/kohsuke/github/PagedIterable;
            0       7     1  size   I
      LocalVariableTypeTable:
        Start  Length  Slot  Name   Signature
            0       7     0  this   Lorg/kohsuke/github/PagedIterable<TT;>;
    Signature: #58                          // (I)Lorg/kohsuke/github/PagedIterable<TT;>;

  public final org.kohsuke.github.PagedIterator<T> iterator();
    descriptor: ()Lorg/kohsuke/github/PagedIterator;
    flags: (0x0011) ACC_PUBLIC, ACC_FINAL
    Code:
      stack=2, locals=1, args_size=1
         0: aload_0
         1: aload_0
         2: getfield      #2                  // Field pageSize:I
         5: invokevirtual #3                  // Method _iterator:(I)Lorg/kohsuke/github/PagedIterator;
         8: areturn
      LineNumberTable:
        line 50: 0
      LocalVariableTable:
        Start  Length  Slot  Name   Signature
            0       9     0  this   Lorg/kohsuke/github/PagedIterable;
      LocalVariableTypeTable:
        Start  Length  Slot  Name   Signature
            0       9     0  this   Lorg/kohsuke/github/PagedIterable<TT;>;
    Signature: #61                          // ()Lorg/kohsuke/github/PagedIterator<TT;>;
    RuntimeVisibleAnnotations:
      0: #63()
        javax.annotation.Nonnull

  public abstract org.kohsuke.github.PagedIterator<T> _iterator(int);
    descriptor: (I)Lorg/kohsuke/github/PagedIterator;
    flags: (0x0401) ACC_PUBLIC, ACC_ABSTRACT
    Signature: #66                          // (I)Lorg/kohsuke/github/PagedIterator<TT;>;
    RuntimeVisibleAnnotations:
      0: #63()
        javax.annotation.Nonnull

  protected T[] toArray(org.kohsuke.github.PagedIterator<T>) throws java.io.IOException;
    descriptor: (Lorg/kohsuke/github/PagedIterator;)[Ljava/lang/Object;
    flags: (0x0004) ACC_PROTECTED
    Code:
      stack=4, locals=6, args_size=2
         0: new           #4                  // class java/util/ArrayList
         3: dup
         4: invokespecial #5                  // Method java/util/ArrayList."<init>":()V
         7: astore_2
         8: iconst_0
         9: istore_3
        10: aload_1
        11: invokevirtual #6                  // Method org/kohsuke/github/PagedIterator.nextPageArray:()[Ljava/lang/Object;
        14: astore        4
        16: iload_3
        17: aload         4
        19: invokestatic  #7                  // Method java/lang/reflect/Array.getLength:(Ljava/lang/Object;)I
        22: iadd
        23: istore_3
        24: aload_2
        25: aload         4
        27: invokevirtual #8                  // Method java/util/ArrayList.add:(Ljava/lang/Object;)Z
        30: pop
        31: aload_1
        32: invokevirtual #9                  // Method org/kohsuke/github/PagedIterator.hasNext:()Z
        35: ifne          10
        38: aload         4
        40: invokevirtual #10                 // Method java/lang/Object.getClass:()Ljava/lang/Class;
        43: astore        5
        45: aload_0
        46: aload         5
        48: aload_2
        49: iload_3
        50: invokespecial #11                 // Method concatenatePages:(Ljava/lang/Class;Ljava/util/List;I)[Ljava/lang/Object;
        53: areturn
        54: astore_2
        55: aload_2
        56: invokevirtual #13                 // Method org/kohsuke/github/GHException.getCause:()Ljava/lang/Throwable;
        59: instanceof    #14                 // class java/io/IOException
        62: ifeq          73
        65: aload_2
        66: invokevirtual #13                 // Method org/kohsuke/github/GHException.getCause:()Ljava/lang/Throwable;
        69: checkcast     #14                 // class java/io/IOException
        72: athrow
        73: aload_2
        74: athrow
      Exception table:
         from    to  target type
             0    53    54   Class org/kohsuke/github/GHException
      LineNumberTable:
        line 74: 0
        line 75: 8
        line 78: 10
        line 79: 16
        line 80: 24
        line 81: 31
        line 83: 38
        line 85: 45
        line 86: 54
        line 89: 55
        line 90: 65
        line 92: 73
      LocalVariableTable:
        Start  Length  Slot  Name   Signature
            8      46     2 pages   Ljava/util/ArrayList;
           10      44     3 totalSize   I
           16      38     4  item   [Ljava/lang/Object;
           45       9     5  type   Ljava/lang/Class;
           55      20     2     e   Lorg/kohsuke/github/GHException;
            0      75     0  this   Lorg/kohsuke/github/PagedIterable;
            0      75     1 iterator   Lorg/kohsuke/github/PagedIterator;
      LocalVariableTypeTable:
        Start  Length  Slot  Name   Signature
            8      46     2 pages   Ljava/util/ArrayList<[TT;>;
           16      38     4  item   [TT;
           45       9     5  type   Ljava/lang/Class<[TT;>;
            0      75     0  this   Lorg/kohsuke/github/PagedIterable<TT;>;
            0      75     1 iterator   Lorg/kohsuke/github/PagedIterator<TT;>;
      StackMapTable: number_of_entries = 3
        frame_type = 253 /* append */
          offset_delta = 10
          locals = [ class java/util/ArrayList, int ]
        frame_type = 255 /* full_frame */
          offset_delta = 43
          locals = [ class org/kohsuke/github/PagedIterable, class org/kohsuke/github/PagedIterator ]
          stack = [ class org/kohsuke/github/GHException ]
        frame_type = 252 /* append */
          offset_delta = 18
          locals = [ class org/kohsuke/github/GHException ]
    Exceptions:
      throws java.io.IOException
    Signature: #86                          // (Lorg/kohsuke/github/PagedIterator<TT;>;)[TT;

  public T[] toArray() throws java.io.IOException;
    descriptor: ()[Ljava/lang/Object;
    flags: (0x0001) ACC_PUBLIC
    Code:
      stack=2, locals=1, args_size=1
         0: aload_0
         1: aload_0
         2: invokevirtual #15                 // Method iterator:()Lorg/kohsuke/github/PagedIterator;
         5: invokevirtual #16                 // Method toArray:(Lorg/kohsuke/github/PagedIterator;)[Ljava/lang/Object;
         8: areturn
      LineNumberTable:
        line 106: 0
      LocalVariableTable:
        Start  Length  Slot  Name   Signature
            0       9     0  this   Lorg/kohsuke/github/PagedIterable;
      LocalVariableTypeTable:
        Start  Length  Slot  Name   Signature
            0       9     0  this   Lorg/kohsuke/github/PagedIterable<TT;>;
    Exceptions:
      throws java.io.IOException
    Signature: #88                          // ()[TT;
    RuntimeVisibleAnnotations:
      0: #63()
        javax.annotation.Nonnull

  public java.util.List<T> toList() throws java.io.IOException;
    descriptor: ()Ljava/util/List;
    flags: (0x0001) ACC_PUBLIC
    Code:
      stack=1, locals=1, args_size=1
         0: aload_0
         1: invokevirtual #17                 // Method toArray:()[Ljava/lang/Object;
         4: invokestatic  #18                 // Method java/util/Arrays.asList:([Ljava/lang/Object;)Ljava/util/List;
         7: invokestatic  #19                 // Method java/util/Collections.unmodifiableList:(Ljava/util/List;)Ljava/util/List;
        10: areturn
      LineNumberTable:
        line 118: 0
      LocalVariableTable:
        Start  Length  Slot  Name   Signature
            0      11     0  this   Lorg/kohsuke/github/PagedIterable;
      LocalVariableTypeTable:
        Start  Length  Slot  Name   Signature
            0      11     0  this   Lorg/kohsuke/github/PagedIterable<TT;>;
    Exceptions:
      throws java.io.IOException
    Signature: #91                          // ()Ljava/util/List<TT;>;
    RuntimeVisibleAnnotations:
      0: #63()
        javax.annotation.Nonnull

  public java.util.Set<T> toSet() throws java.io.IOException;
    descriptor: ()Ljava/util/Set;
    flags: (0x0001) ACC_PUBLIC
    Code:
      stack=3, locals=1, args_size=1
         0: new           #20                 // class java/util/LinkedHashSet
         3: dup
         4: aload_0
         5: invokevirtual #17                 // Method toArray:()[Ljava/lang/Object;
         8: invokestatic  #18                 // Method java/util/Arrays.asList:([Ljava/lang/Object;)Ljava/util/List;
        11: invokespecial #21                 // Method java/util/LinkedHashSet."<init>":(Ljava/util/Collection;)V
        14: invokestatic  #22                 // Method java/util/Collections.unmodifiableSet:(Ljava/util/Set;)Ljava/util/Set;
        17: areturn
      LineNumberTable:
        line 130: 0
      LocalVariableTable:
        Start  Length  Slot  Name   Signature
            0      18     0  this   Lorg/kohsuke/github/PagedIterable;
      LocalVariableTypeTable:
        Start  Length  Slot  Name   Signature
            0      18     0  this   Lorg/kohsuke/github/PagedIterable<TT;>;
    Exceptions:
      throws java.io.IOException
    Signature: #94                          // ()Ljava/util/Set<TT;>;
    RuntimeVisibleAnnotations:
      0: #63()
        javax.annotation.Nonnull

  public java.util.List<T> asList();
    descriptor: ()Ljava/util/List;
    flags: (0x0001) ACC_PUBLIC
    Code:
      stack=4, locals=2, args_size=1
         0: aload_0
         1: invokevirtual #23                 // Method toList:()Ljava/util/List;
         4: areturn
         5: astore_1
         6: new           #12                 // class org/kohsuke/github/GHException
         9: dup
        10: new           #24                 // class java/lang/StringBuilder
        13: dup
        14: invokespecial #25                 // Method java/lang/StringBuilder."<init>":()V
        17: ldc           #26                 // String Failed to retrieve list:
        19: invokevirtual #27                 // Method java/lang/StringBuilder.append:(Ljava/lang/String;)Ljava/lang/StringBuilder;
        22: aload_1
        23: invokevirtual #28                 // Method java/io/IOException.getMessage:()Ljava/lang/String;
        26: invokevirtual #27                 // Method java/lang/StringBuilder.append:(Ljava/lang/String;)Ljava/lang/StringBuilder;
        29: invokevirtual #29                 // Method java/lang/StringBuilder.toString:()Ljava/lang/String;
        32: aload_1
        33: invokespecial #30                 // Method org/kohsuke/github/GHException."<init>":(Ljava/lang/String;Ljava/lang/Throwable;)V
        36: athrow
      Exception table:
         from    to  target type
             0     4     5   Class java/io/IOException
      LineNumberTable:
        line 143: 0
        line 144: 5
        line 145: 6
      LocalVariableTable:
        Start  Length  Slot  Name   Signature
            6      31     1     e   Ljava/io/IOException;
            0      37     0  this   Lorg/kohsuke/github/PagedIterable;
      LocalVariableTypeTable:
        Start  Length  Slot  Name   Signature
            0      37     0  this   Lorg/kohsuke/github/PagedIterable<TT;>;
      StackMapTable: number_of_entries = 1
        frame_type = 69 /* same_locals_1_stack_item */
          stack = [ class java/io/IOException ]
    Deprecated: true
    Signature: #91                          // ()Ljava/util/List<TT;>;
    RuntimeVisibleAnnotations:
      0: #63()
        javax.annotation.Nonnull
      1: #98()
        java.lang.Deprecated

  public java.util.Set<T> asSet();
    descriptor: ()Ljava/util/Set;
    flags: (0x0001) ACC_PUBLIC
    Code:
      stack=4, locals=2, args_size=1
         0: aload_0
         1: invokevirtual #31                 // Method toSet:()Ljava/util/Set;
         4: areturn
         5: astore_1
         6: new           #12                 // class org/kohsuke/github/GHException
         9: dup
        10: new           #24                 // class java/lang/StringBuilder
        13: dup
        14: invokespecial #25                 // Method java/lang/StringBuilder."<init>":()V
        17: ldc           #26                 // String Failed to retrieve list:
        19: invokevirtual #27                 // Method java/lang/StringBuilder.append:(Ljava/lang/String;)Ljava/lang/StringBuilder;
        22: aload_1
        23: invokevirtual #28                 // Method java/io/IOException.getMessage:()Ljava/lang/String;
        26: invokevirtual #27                 // Method java/lang/StringBuilder.append:(Ljava/lang/String;)Ljava/lang/StringBuilder;
        29: invokevirtual #29                 // Method java/lang/StringBuilder.toString:()Ljava/lang/String;
        32: aload_1
        33: invokespecial #30                 // Method org/kohsuke/github/GHException."<init>":(Ljava/lang/String;Ljava/lang/Throwable;)V
        36: athrow
      Exception table:
         from    to  target type
             0     4     5   Class java/io/IOException
      LineNumberTable:
        line 159: 0
        line 160: 5
        line 161: 6
      LocalVariableTable:
        Start  Length  Slot  Name   Signature
            6      31     1     e   Ljava/io/IOException;
            0      37     0  this   Lorg/kohsuke/github/PagedIterable;
      LocalVariableTypeTable:
        Start  Length  Slot  Name   Signature
            0      37     0  this   Lorg/kohsuke/github/PagedIterable<TT;>;
      StackMapTable: number_of_entries = 1
        frame_type = 69 /* same_locals_1_stack_item */
          stack = [ class java/io/IOException ]
    Deprecated: true
    Signature: #94                          // ()Ljava/util/Set<TT;>;
    RuntimeVisibleAnnotations:
      0: #63()
        javax.annotation.Nonnull
      1: #98()
        java.lang.Deprecated

  private T[] concatenatePages(java.lang.Class<T[]>, java.util.List<T[]>, int);
    descriptor: (Ljava/lang/Class;Ljava/util/List;I)[Ljava/lang/Object;
    flags: (0x0002) ACC_PRIVATE
    Code:
      stack=5, locals=9, args_size=4
         0: aload_1
         1: aload_1
         2: invokevirtual #32                 // Method java/lang/Class.getComponentType:()Ljava/lang/Class;
         5: iload_3
         6: invokestatic  #33                 // Method java/lang/reflect/Array.newInstance:(Ljava/lang/Class;I)Ljava/lang/Object;
         9: invokevirtual #34                 // Method java/lang/Class.cast:(Ljava/lang/Object;)Ljava/lang/Object;
        12: checkcast     #35                 // class "[Ljava/lang/Object;"
        15: astore        4
        17: iconst_0
        18: istore        5
        20: aload_2
        21: invokeinterface #36,  1           // InterfaceMethod java/util/List.iterator:()Ljava/util/Iterator;
        26: astore        6
        28: aload         6
        30: invokeinterface #37,  1           // InterfaceMethod java/util/Iterator.hasNext:()Z
        35: ifeq          79
        38: aload         6
        40: invokeinterface #38,  1           // InterfaceMethod java/util/Iterator.next:()Ljava/lang/Object;
        45: checkcast     #35                 // class "[Ljava/lang/Object;"
        48: astore        7
        50: aload         7
        52: invokestatic  #7                  // Method java/lang/reflect/Array.getLength:(Ljava/lang/Object;)I
        55: istore        8
        57: aload         7
        59: iconst_0
        60: aload         4
        62: iload         5
        64: iload         8
        66: invokestatic  #39                 // Method java/lang/System.arraycopy:(Ljava/lang/Object;ILjava/lang/Object;II)V
        69: iload         5
        71: iload         8
        73: iadd
        74: istore        5
        76: goto          28
        79: aload         4
        81: areturn
      LineNumberTable:
        line 179: 0
        line 181: 17
        line 182: 20
        line 183: 50
        line 184: 57
        line 185: 69
        line 186: 76
        line 187: 79
      LocalVariableTable:
        Start  Length  Slot  Name   Signature
           57      19     8 pageLength   I
           50      26     7  page   [Ljava/lang/Object;
            0      82     0  this   Lorg/kohsuke/github/PagedIterable;
            0      82     1  type   Ljava/lang/Class;
            0      82     2 pages   Ljava/util/List;
            0      82     3 totalLength   I
           17      65     4 result   [Ljava/lang/Object;
           20      62     5 position   I
      LocalVariableTypeTable:
        Start  Length  Slot  Name   Signature
           50      26     7  page   [TT;
            0      82     0  this   Lorg/kohsuke/github/PagedIterable<TT;>;
            0      82     1  type   Ljava/lang/Class<[TT;>;
            0      82     2 pages   Ljava/util/List<[TT;>;
           17      65     4 result   [TT;
      StackMapTable: number_of_entries = 2
        frame_type = 254 /* append */
          offset_delta = 28
          locals = [ class "[Ljava/lang/Object;", int, class java/util/Iterator ]
        frame_type = 250 /* chop */
          offset_delta = 50
    Signature: #110                         // (Ljava/lang/Class<[TT;>;Ljava/util/List<[TT;>;I)[TT;
    RuntimeVisibleAnnotations:
      0: #63()
        javax.annotation.Nonnull

  public java.util.Iterator iterator();
    descriptor: ()Ljava/util/Iterator;
    flags: (0x1041) ACC_PUBLIC, ACC_BRIDGE, ACC_SYNTHETIC
    Code:
      stack=1, locals=1, args_size=1
         0: aload_0
         1: invokevirtual #15                 // Method iterator:()Lorg/kohsuke/github/PagedIterator;
         4: areturn
      LineNumberTable:
        line 22: 0
      LocalVariableTable:
        Start  Length  Slot  Name   Signature
            0       5     0  this   Lorg/kohsuke/github/PagedIterable;
      LocalVariableTypeTable:
        Start  Length  Slot  Name   Signature
            0       5     0  this   Lorg/kohsuke/github/PagedIterable<TT;>;
    RuntimeVisibleAnnotations:
      0: #63()
        javax.annotation.Nonnull
}
Signature: #112                         // <T:Ljava/lang/Object;>Ljava/lang/Object;Ljava/lang/Iterable<TT;>;
SourceFile: "PagedIterable.java"
