Classfile /Users/mw/Projects/slang-braindump/.jar/jar8/assemble/slang-braindump/assemble/content/org/kohsuke/github/PagedSearchIterable.class
  Last modified May 29, 2022; size 4111 bytes
  SHA-256 checksum 1d97e88ccbdd1c8148db9671f526aab54afa01a163f52299d69a5eaea1526ca0
  Compiled from "PagedSearchIterable.java"
public class org.kohsuke.github.PagedSearchIterable<T extends java.lang.Object> extends org.kohsuke.github.PagedIterable<T>
  minor version: 0
  major version: 52
  flags: (0x0021) ACC_PUBLIC, ACC_SUPER
  this_class: #7                          // org/kohsuke/github/PagedSearchIterable
  super_class: #21                        // org/kohsuke/github/PagedIterable
  interfaces: 0, fields: 4, methods: 11, attributes: 4
Constant pool:
    #1 = Fieldref           #7.#90        // org/kohsuke/github/PagedSearchIterable.root:Lorg/kohsuke/github/GitHub;
    #2 = Fieldref           #7.#91        // org/kohsuke/github/PagedSearchIterable.result:Lorg/kohsuke/github/SearchResult;
    #3 = Methodref          #21.#92       // org/kohsuke/github/PagedIterable."<init>":()V
    #4 = Fieldref           #7.#93        // org/kohsuke/github/PagedSearchIterable.request:Lorg/kohsuke/github/GitHubRequest;
    #5 = Fieldref           #7.#94        // org/kohsuke/github/PagedSearchIterable.receiverType:Ljava/lang/Class;
    #6 = Methodref          #21.#95       // org/kohsuke/github/PagedIterable.withPageSize:(I)Lorg/kohsuke/github/PagedIterable;
    #7 = Class              #96           // org/kohsuke/github/PagedSearchIterable
    #8 = Methodref          #7.#97        // org/kohsuke/github/PagedSearchIterable.populate:()V
    #9 = Fieldref           #98.#99       // org/kohsuke/github/SearchResult.total_count:I
   #10 = Fieldref           #98.#100      // org/kohsuke/github/SearchResult.incomplete_results:Z
   #11 = Methodref          #7.#101       // org/kohsuke/github/PagedSearchIterable.iterator:()Lorg/kohsuke/github/PagedIterator;
   #12 = Methodref          #16.#102      // org/kohsuke/github/PagedIterator.hasNext:()Z
   #13 = Methodref          #103.#104     // org/kohsuke/github/GitHub.getClient:()Lorg/kohsuke/github/GitHubClient;
   #14 = Methodref          #105.#106     // org/kohsuke/github/GitHubPageIterator.create:(Lorg/kohsuke/github/GitHubClient;Ljava/lang/Class;Lorg/kohsuke/github/GitHubRequest;I)Lorg/kohsuke/github/GitHubPageIterator;
   #15 = Methodref          #7.#107       // org/kohsuke/github/PagedSearchIterable.adapt:(Ljava/util/Iterator;)Ljava/util/Iterator;
   #16 = Class              #108          // org/kohsuke/github/PagedIterator
   #17 = Methodref          #16.#109      // org/kohsuke/github/PagedIterator."<init>":(Ljava/util/Iterator;Ljava/util/function/Consumer;)V
   #18 = Class              #110          // org/kohsuke/github/PagedSearchIterable$1
   #19 = Methodref          #18.#111      // org/kohsuke/github/PagedSearchIterable$1."<init>":(Lorg/kohsuke/github/PagedSearchIterable;Ljava/util/Iterator;)V
   #20 = Methodref          #7.#112       // org/kohsuke/github/PagedSearchIterable.withPageSize:(I)Lorg/kohsuke/github/PagedSearchIterable;
   #21 = Class              #113          // org/kohsuke/github/PagedIterable
   #22 = Utf8               InnerClasses
   #23 = Utf8               root
   #24 = Utf8               Lorg/kohsuke/github/GitHub;
   #25 = Utf8               request
   #26 = Utf8               Lorg/kohsuke/github/GitHubRequest;
   #27 = Utf8               receiverType
   #28 = Utf8               Ljava/lang/Class;
   #29 = Utf8               Signature
   #30 = Utf8               Ljava/lang/Class<+Lorg/kohsuke/github/SearchResult<TT;>;>;
   #31 = Utf8               result
   #32 = Utf8               Lorg/kohsuke/github/SearchResult;
   #33 = Utf8               Lorg/kohsuke/github/SearchResult<TT;>;
   #34 = Utf8               <init>
   #35 = Utf8               (Lorg/kohsuke/github/GitHub;Lorg/kohsuke/github/GitHubRequest;Ljava/lang/Class;)V
   #36 = Utf8               Code
   #37 = Utf8               LineNumberTable
   #38 = Utf8               LocalVariableTable
   #39 = Utf8               this
   #40 = Utf8               Lorg/kohsuke/github/PagedSearchIterable;
   #41 = Utf8               LocalVariableTypeTable
   #42 = Utf8               Lorg/kohsuke/github/PagedSearchIterable<TT;>;
   #43 = Utf8               (Lorg/kohsuke/github/GitHub;Lorg/kohsuke/github/GitHubRequest;Ljava/lang/Class<+Lorg/kohsuke/github/SearchResult<TT;>;>;)V
   #44 = Utf8               withPageSize
   #45 = Utf8               (I)Lorg/kohsuke/github/PagedSearchIterable;
   #46 = Utf8               size
   #47 = Utf8               I
   #48 = Utf8               (I)Lorg/kohsuke/github/PagedSearchIterable<TT;>;
   #49 = Utf8               getTotalCount
   #50 = Utf8               ()I
   #51 = Utf8               isIncomplete
   #52 = Utf8               ()Z
   #53 = Utf8               populate
   #54 = Utf8               ()V
   #55 = Utf8               StackMapTable
   #56 = Utf8               _iterator
   #57 = Utf8               (I)Lorg/kohsuke/github/PagedIterator;
   #58 = Utf8               pageSize
   #59 = Utf8               adapter
   #60 = Utf8               Ljava/util/Iterator;
   #61 = Utf8               Ljava/util/Iterator<[TT;>;
   #62 = Utf8               (I)Lorg/kohsuke/github/PagedIterator<TT;>;
   #63 = Utf8               RuntimeVisibleAnnotations
   #64 = Utf8               Ljavax/annotation/Nonnull;
   #65 = Utf8               adapt
   #66 = Utf8               (Ljava/util/Iterator;)Ljava/util/Iterator;
   #67 = Utf8               base
   #68 = Utf8               Ljava/util/Iterator<+Lorg/kohsuke/github/SearchResult<TT;>;>;
   #69 = Utf8               (Ljava/util/Iterator<+Lorg/kohsuke/github/SearchResult<TT;>;>;)Ljava/util/Iterator<[TT;>;
   #70 = Utf8               (I)Lorg/kohsuke/github/PagedIterable;
   #71 = Utf8               access$000
   #72 = Utf8               (Lorg/kohsuke/github/PagedSearchIterable;)Lorg/kohsuke/github/SearchResult;
   #73 = Utf8               x0
   #74 = Utf8               access$002
   #75 = Utf8               (Lorg/kohsuke/github/PagedSearchIterable;Lorg/kohsuke/github/SearchResult;)Lorg/kohsuke/github/SearchResult;
   #76 = Utf8               x1
   #77 = Utf8               access$100
   #78 = Utf8               (Lorg/kohsuke/github/PagedSearchIterable;)Lorg/kohsuke/github/GitHub;
   #79 = Utf8               <T:Ljava/lang/Object;>Lorg/kohsuke/github/PagedIterable<TT;>;
   #80 = Utf8               SourceFile
   #81 = Utf8               PagedSearchIterable.java
   #82 = Utf8               RuntimeInvisibleAnnotations
   #83 = Utf8               Ledu/umd/cs/findbugs/annotations/SuppressFBWarnings;
   #84 = Utf8               value
   #85 = Utf8               UWF_UNWRITTEN_PUBLIC_OR_PROTECTED_FIELD
   #86 = Utf8               UWF_UNWRITTEN_FIELD
   #87 = Utf8               UWF_FIELD_NOT_INITIALIZED_IN_CONSTRUCTOR
   #88 = Utf8               justification
   #89 = Utf8               Constructed by JSON API
   #90 = NameAndType        #23:#24       // root:Lorg/kohsuke/github/GitHub;
   #91 = NameAndType        #31:#32       // result:Lorg/kohsuke/github/SearchResult;
   #92 = NameAndType        #34:#54       // "<init>":()V
   #93 = NameAndType        #25:#26       // request:Lorg/kohsuke/github/GitHubRequest;
   #94 = NameAndType        #27:#28       // receiverType:Ljava/lang/Class;
   #95 = NameAndType        #44:#70       // withPageSize:(I)Lorg/kohsuke/github/PagedIterable;
   #96 = Utf8               org/kohsuke/github/PagedSearchIterable
   #97 = NameAndType        #53:#54       // populate:()V
   #98 = Class              #114          // org/kohsuke/github/SearchResult
   #99 = NameAndType        #115:#47      // total_count:I
  #100 = NameAndType        #116:#117     // incomplete_results:Z
  #101 = NameAndType        #118:#119     // iterator:()Lorg/kohsuke/github/PagedIterator;
  #102 = NameAndType        #120:#52      // hasNext:()Z
  #103 = Class              #121          // org/kohsuke/github/GitHub
  #104 = NameAndType        #122:#123     // getClient:()Lorg/kohsuke/github/GitHubClient;
  #105 = Class              #124          // org/kohsuke/github/GitHubPageIterator
  #106 = NameAndType        #125:#126     // create:(Lorg/kohsuke/github/GitHubClient;Ljava/lang/Class;Lorg/kohsuke/github/GitHubRequest;I)Lorg/kohsuke/github/GitHubPageIterator;
  #107 = NameAndType        #65:#66       // adapt:(Ljava/util/Iterator;)Ljava/util/Iterator;
  #108 = Utf8               org/kohsuke/github/PagedIterator
  #109 = NameAndType        #34:#127      // "<init>":(Ljava/util/Iterator;Ljava/util/function/Consumer;)V
  #110 = Utf8               org/kohsuke/github/PagedSearchIterable$1
  #111 = NameAndType        #34:#128      // "<init>":(Lorg/kohsuke/github/PagedSearchIterable;Ljava/util/Iterator;)V
  #112 = NameAndType        #44:#45       // withPageSize:(I)Lorg/kohsuke/github/PagedSearchIterable;
  #113 = Utf8               org/kohsuke/github/PagedIterable
  #114 = Utf8               org/kohsuke/github/SearchResult
  #115 = Utf8               total_count
  #116 = Utf8               incomplete_results
  #117 = Utf8               Z
  #118 = Utf8               iterator
  #119 = Utf8               ()Lorg/kohsuke/github/PagedIterator;
  #120 = Utf8               hasNext
  #121 = Utf8               org/kohsuke/github/GitHub
  #122 = Utf8               getClient
  #123 = Utf8               ()Lorg/kohsuke/github/GitHubClient;
  #124 = Utf8               org/kohsuke/github/GitHubPageIterator
  #125 = Utf8               create
  #126 = Utf8               (Lorg/kohsuke/github/GitHubClient;Ljava/lang/Class;Lorg/kohsuke/github/GitHubRequest;I)Lorg/kohsuke/github/GitHubPageIterator;
  #127 = Utf8               (Ljava/util/Iterator;Ljava/util/function/Consumer;)V
  #128 = Utf8               (Lorg/kohsuke/github/PagedSearchIterable;Ljava/util/Iterator;)V
{
  private final transient org.kohsuke.github.GitHub root;
    descriptor: Lorg/kohsuke/github/GitHub;
    flags: (0x0092) ACC_PRIVATE, ACC_FINAL, ACC_TRANSIENT

  private final org.kohsuke.github.GitHubRequest request;
    descriptor: Lorg/kohsuke/github/GitHubRequest;
    flags: (0x0012) ACC_PRIVATE, ACC_FINAL

  private final java.lang.Class<? extends org.kohsuke.github.SearchResult<T>> receiverType;
    descriptor: Ljava/lang/Class;
    flags: (0x0012) ACC_PRIVATE, ACC_FINAL
    Signature: #30                          // Ljava/lang/Class<+Lorg/kohsuke/github/SearchResult<TT;>;>;

  private org.kohsuke.github.SearchResult<T> result;
    descriptor: Lorg/kohsuke/github/SearchResult;
    flags: (0x0002) ACC_PRIVATE
    Signature: #33                          // Lorg/kohsuke/github/SearchResult<TT;>;

  org.kohsuke.github.PagedSearchIterable(org.kohsuke.github.GitHub, org.kohsuke.github.GitHubRequest, java.lang.Class<? extends org.kohsuke.github.SearchResult<T>>);
    descriptor: (Lorg/kohsuke/github/GitHub;Lorg/kohsuke/github/GitHubRequest;Ljava/lang/Class;)V
    flags: (0x0000)
    Code:
      stack=2, locals=4, args_size=4
         0: aload_0
         1: invokespecial #3                  // Method org/kohsuke/github/PagedIterable."<init>":()V
         4: aload_0
         5: aload_1
         6: putfield      #1                  // Field root:Lorg/kohsuke/github/GitHub;
         9: aload_0
        10: aload_2
        11: putfield      #4                  // Field request:Lorg/kohsuke/github/GitHubRequest;
        14: aload_0
        15: aload_3
        16: putfield      #5                  // Field receiverType:Ljava/lang/Class;
        19: return
      LineNumberTable:
        line 32: 0
        line 33: 4
        line 34: 9
        line 35: 14
        line 36: 19
      LocalVariableTable:
        Start  Length  Slot  Name   Signature
            0      20     0  this   Lorg/kohsuke/github/PagedSearchIterable;
            0      20     1  root   Lorg/kohsuke/github/GitHub;
            0      20     2 request   Lorg/kohsuke/github/GitHubRequest;
            0      20     3 receiverType   Ljava/lang/Class;
      LocalVariableTypeTable:
        Start  Length  Slot  Name   Signature
            0      20     0  this   Lorg/kohsuke/github/PagedSearchIterable<TT;>;
            0      20     3 receiverType   Ljava/lang/Class<+Lorg/kohsuke/github/SearchResult<TT;>;>;
    Signature: #43                          // (Lorg/kohsuke/github/GitHub;Lorg/kohsuke/github/GitHubRequest;Ljava/lang/Class<+Lorg/kohsuke/github/SearchResult<TT;>;>;)V

  public org.kohsuke.github.PagedSearchIterable<T> withPageSize(int);
    descriptor: (I)Lorg/kohsuke/github/PagedSearchIterable;
    flags: (0x0001) ACC_PUBLIC
    Code:
      stack=2, locals=2, args_size=2
         0: aload_0
         1: iload_1
         2: invokespecial #6                  // Method org/kohsuke/github/PagedIterable.withPageSize:(I)Lorg/kohsuke/github/PagedIterable;
         5: checkcast     #7                  // class org/kohsuke/github/PagedSearchIterable
         8: areturn
      LineNumberTable:
        line 40: 0
      LocalVariableTable:
        Start  Length  Slot  Name   Signature
            0       9     0  this   Lorg/kohsuke/github/PagedSearchIterable;
            0       9     1  size   I
      LocalVariableTypeTable:
        Start  Length  Slot  Name   Signature
            0       9     0  this   Lorg/kohsuke/github/PagedSearchIterable<TT;>;
    Signature: #48                          // (I)Lorg/kohsuke/github/PagedSearchIterable<TT;>;

  public int getTotalCount();
    descriptor: ()I
    flags: (0x0001) ACC_PUBLIC
    Code:
      stack=1, locals=1, args_size=1
         0: aload_0
         1: invokespecial #8                  // Method populate:()V
         4: aload_0
         5: getfield      #2                  // Field result:Lorg/kohsuke/github/SearchResult;
         8: getfield      #9                  // Field org/kohsuke/github/SearchResult.total_count:I
        11: ireturn
      LineNumberTable:
        line 49: 0
        line 50: 4
      LocalVariableTable:
        Start  Length  Slot  Name   Signature
            0      12     0  this   Lorg/kohsuke/github/PagedSearchIterable;
      LocalVariableTypeTable:
        Start  Length  Slot  Name   Signature
            0      12     0  this   Lorg/kohsuke/github/PagedSearchIterable<TT;>;

  public boolean isIncomplete();
    descriptor: ()Z
    flags: (0x0001) ACC_PUBLIC
    Code:
      stack=1, locals=1, args_size=1
         0: aload_0
         1: invokespecial #8                  // Method populate:()V
         4: aload_0
         5: getfield      #2                  // Field result:Lorg/kohsuke/github/SearchResult;
         8: getfield      #10                 // Field org/kohsuke/github/SearchResult.incomplete_results:Z
        11: ireturn
      LineNumberTable:
        line 59: 0
        line 60: 4
      LocalVariableTable:
        Start  Length  Slot  Name   Signature
            0      12     0  this   Lorg/kohsuke/github/PagedSearchIterable;
      LocalVariableTypeTable:
        Start  Length  Slot  Name   Signature
            0      12     0  this   Lorg/kohsuke/github/PagedSearchIterable<TT;>;

  private void populate();
    descriptor: ()V
    flags: (0x0002) ACC_PRIVATE
    Code:
      stack=1, locals=1, args_size=1
         0: aload_0
         1: getfield      #2                  // Field result:Lorg/kohsuke/github/SearchResult;
         4: ifnonnull     15
         7: aload_0
         8: invokevirtual #11                 // Method iterator:()Lorg/kohsuke/github/PagedIterator;
        11: invokevirtual #12                 // Method org/kohsuke/github/PagedIterator.hasNext:()Z
        14: pop
        15: return
      LineNumberTable:
        line 64: 0
        line 65: 7
        line 66: 15
      LocalVariableTable:
        Start  Length  Slot  Name   Signature
            0      16     0  this   Lorg/kohsuke/github/PagedSearchIterable;
      LocalVariableTypeTable:
        Start  Length  Slot  Name   Signature
            0      16     0  this   Lorg/kohsuke/github/PagedSearchIterable<TT;>;
      StackMapTable: number_of_entries = 1
        frame_type = 15 /* same */

  public org.kohsuke.github.PagedIterator<T> _iterator(int);
    descriptor: (I)Lorg/kohsuke/github/PagedIterator;
    flags: (0x0001) ACC_PUBLIC
    Code:
      stack=5, locals=3, args_size=2
         0: aload_0
         1: aload_0
         2: getfield      #1                  // Field root:Lorg/kohsuke/github/GitHub;
         5: invokevirtual #13                 // Method org/kohsuke/github/GitHub.getClient:()Lorg/kohsuke/github/GitHubClient;
         8: aload_0
         9: getfield      #5                  // Field receiverType:Ljava/lang/Class;
        12: aload_0
        13: getfield      #4                  // Field request:Lorg/kohsuke/github/GitHubRequest;
        16: iload_1
        17: invokestatic  #14                 // Method org/kohsuke/github/GitHubPageIterator.create:(Lorg/kohsuke/github/GitHubClient;Ljava/lang/Class;Lorg/kohsuke/github/GitHubRequest;I)Lorg/kohsuke/github/GitHubPageIterator;
        20: invokevirtual #15                 // Method adapt:(Ljava/util/Iterator;)Ljava/util/Iterator;
        23: astore_2
        24: new           #16                 // class org/kohsuke/github/PagedIterator
        27: dup
        28: aload_2
        29: aconst_null
        30: invokespecial #17                 // Method org/kohsuke/github/PagedIterator."<init>":(Ljava/util/Iterator;Ljava/util/function/Consumer;)V
        33: areturn
      LineNumberTable:
        line 71: 0
        line 72: 5
        line 71: 20
        line 73: 24
      LocalVariableTable:
        Start  Length  Slot  Name   Signature
            0      34     0  this   Lorg/kohsuke/github/PagedSearchIterable;
            0      34     1 pageSize   I
           24      10     2 adapter   Ljava/util/Iterator;
      LocalVariableTypeTable:
        Start  Length  Slot  Name   Signature
            0      34     0  this   Lorg/kohsuke/github/PagedSearchIterable<TT;>;
           24      10     2 adapter   Ljava/util/Iterator<[TT;>;
    Signature: #62                          // (I)Lorg/kohsuke/github/PagedIterator<TT;>;
    RuntimeVisibleAnnotations:
      0: #64()
        javax.annotation.Nonnull

  protected java.util.Iterator<T[]> adapt(java.util.Iterator<? extends org.kohsuke.github.SearchResult<T>>);
    descriptor: (Ljava/util/Iterator;)Ljava/util/Iterator;
    flags: (0x0004) ACC_PROTECTED
    Code:
      stack=4, locals=2, args_size=2
         0: new           #18                 // class org/kohsuke/github/PagedSearchIterable$1
         3: dup
         4: aload_0
         5: aload_1
         6: invokespecial #19                 // Method org/kohsuke/github/PagedSearchIterable$1."<init>":(Lorg/kohsuke/github/PagedSearchIterable;Ljava/util/Iterator;)V
         9: areturn
      LineNumberTable:
        line 84: 0
      LocalVariableTable:
        Start  Length  Slot  Name   Signature
            0      10     0  this   Lorg/kohsuke/github/PagedSearchIterable;
            0      10     1  base   Ljava/util/Iterator;
      LocalVariableTypeTable:
        Start  Length  Slot  Name   Signature
            0      10     0  this   Lorg/kohsuke/github/PagedSearchIterable<TT;>;
            0      10     1  base   Ljava/util/Iterator<+Lorg/kohsuke/github/SearchResult<TT;>;>;
    Signature: #69                          // (Ljava/util/Iterator<+Lorg/kohsuke/github/SearchResult<TT;>;>;)Ljava/util/Iterator<[TT;>;

  public org.kohsuke.github.PagedIterable withPageSize(int);
    descriptor: (I)Lorg/kohsuke/github/PagedIterable;
    flags: (0x1041) ACC_PUBLIC, ACC_BRIDGE, ACC_SYNTHETIC
    Code:
      stack=2, locals=2, args_size=2
         0: aload_0
         1: iload_1
         2: invokevirtual #20                 // Method withPageSize:(I)Lorg/kohsuke/github/PagedSearchIterable;
         5: areturn
      LineNumberTable:
        line 16: 0
      LocalVariableTable:
        Start  Length  Slot  Name   Signature
            0       6     0  this   Lorg/kohsuke/github/PagedSearchIterable;
      LocalVariableTypeTable:
        Start  Length  Slot  Name   Signature
            0       6     0  this   Lorg/kohsuke/github/PagedSearchIterable<TT;>;

  static org.kohsuke.github.SearchResult access$000(org.kohsuke.github.PagedSearchIterable);
    descriptor: (Lorg/kohsuke/github/PagedSearchIterable;)Lorg/kohsuke/github/SearchResult;
    flags: (0x1008) ACC_STATIC, ACC_SYNTHETIC
    Code:
      stack=1, locals=1, args_size=1
         0: aload_0
         1: getfield      #2                  // Field result:Lorg/kohsuke/github/SearchResult;
         4: areturn
      LineNumberTable:
        line 20: 0
      LocalVariableTable:
        Start  Length  Slot  Name   Signature
            0       5     0    x0   Lorg/kohsuke/github/PagedSearchIterable;

  static org.kohsuke.github.SearchResult access$002(org.kohsuke.github.PagedSearchIterable, org.kohsuke.github.SearchResult);
    descriptor: (Lorg/kohsuke/github/PagedSearchIterable;Lorg/kohsuke/github/SearchResult;)Lorg/kohsuke/github/SearchResult;
    flags: (0x1008) ACC_STATIC, ACC_SYNTHETIC
    Code:
      stack=3, locals=2, args_size=2
         0: aload_0
         1: aload_1
         2: dup_x1
         3: putfield      #2                  // Field result:Lorg/kohsuke/github/SearchResult;
         6: areturn
      LineNumberTable:
        line 20: 0
      LocalVariableTable:
        Start  Length  Slot  Name   Signature
            0       7     0    x0   Lorg/kohsuke/github/PagedSearchIterable;
            0       7     1    x1   Lorg/kohsuke/github/SearchResult;

  static org.kohsuke.github.GitHub access$100(org.kohsuke.github.PagedSearchIterable);
    descriptor: (Lorg/kohsuke/github/PagedSearchIterable;)Lorg/kohsuke/github/GitHub;
    flags: (0x1008) ACC_STATIC, ACC_SYNTHETIC
    Code:
      stack=1, locals=1, args_size=1
         0: aload_0
         1: getfield      #1                  // Field root:Lorg/kohsuke/github/GitHub;
         4: areturn
      LineNumberTable:
        line 20: 0
      LocalVariableTable:
        Start  Length  Slot  Name   Signature
            0       5     0    x0   Lorg/kohsuke/github/PagedSearchIterable;
}
Signature: #79                          // <T:Ljava/lang/Object;>Lorg/kohsuke/github/PagedIterable<TT;>;
SourceFile: "PagedSearchIterable.java"
RuntimeInvisibleAnnotations:
  0: #83(#84=[s#85,s#86,s#87],#88=s#89)
    edu.umd.cs.findbugs.annotations.SuppressFBWarnings(
      value=["UWF_UNWRITTEN_PUBLIC_OR_PROTECTED_FIELD","UWF_UNWRITTEN_FIELD","UWF_FIELD_NOT_INITIALIZED_IN_CONSTRUCTOR"]
      justification="Constructed by JSON API"
    )
InnerClasses:
  #18;                                    // class org/kohsuke/github/PagedSearchIterable$1
