Classfile /Users/mw/Projects/slang-braindump/.jar/jar8/assemble/slang-braindump/assemble/content/org/kohsuke/github/RateLimitChecker$1.class
  Last modified May 29, 2022; size 393 bytes
  SHA-256 checksum afa6a67ef6f7c5d2c5bfb8d47e484489865a872af6e9e0a0aeb29d548d39623d
  Compiled from "RateLimitChecker.java"
class org.kohsuke.github.RateLimitChecker$1 extends org.kohsuke.github.RateLimitChecker
  minor version: 0
  major version: 52
  flags: (0x0020) ACC_SUPER
  this_class: #2                          // org/kohsuke/github/RateLimitChecker$1
  super_class: #3                         // org/kohsuke/github/RateLimitChecker
  interfaces: 0, fields: 0, methods: 1, attributes: 3
Constant pool:
   #1 = Methodref          #3.#15         // org/kohsuke/github/RateLimitChecker."<init>":()V
   #2 = Class              #16            // org/kohsuke/github/RateLimitChecker$1
   #3 = Class              #17            // org/kohsuke/github/RateLimitChecker
   #4 = Utf8               <init>
   #5 = Utf8               ()V
   #6 = Utf8               Code
   #7 = Utf8               LineNumberTable
   #8 = Utf8               LocalVariableTable
   #9 = Utf8               this
  #10 = Utf8               InnerClasses
  #11 = Utf8               Lorg/kohsuke/github/RateLimitChecker$1;
  #12 = Utf8               SourceFile
  #13 = Utf8               RateLimitChecker.java
  #14 = Utf8               EnclosingMethod
  #15 = NameAndType        #4:#5          // "<init>":()V
  #16 = Utf8               org/kohsuke/github/RateLimitChecker$1
  #17 = Utf8               org/kohsuke/github/RateLimitChecker
{
  org.kohsuke.github.RateLimitChecker$1();
    descriptor: ()V
    flags: (0x0000)
    Code:
      stack=1, locals=1, args_size=1
         0: aload_0
         1: invokespecial #1                  // Method org/kohsuke/github/RateLimitChecker."<init>":()V
         4: return
      LineNumberTable:
        line 26: 0
      LocalVariableTable:
        Start  Length  Slot  Name   Signature
            0       5     0  this   Lorg/kohsuke/github/RateLimitChecker$1;
}
SourceFile: "RateLimitChecker.java"
EnclosingMethod: #3.#0                  // org.kohsuke.github.RateLimitChecker
InnerClasses:
  #2;                                     // class org/kohsuke/github/RateLimitChecker$1
