Classfile /Users/mw/Projects/slang-braindump/.jar/jar8/assemble/slang-braindump/assemble/content/scala/collection/compat/immutable/package$.class
  Last modified May 29, 2022; size 945 bytes
  SHA-256 checksum f776ebf2c3d1f6f2fe033f647f5cbc0059c4ac752079df01424bfac0a3992781
  Compiled from "package.scala"
public final class scala.collection.compat.immutable.package$
  minor version: 0
  major version: 52
  flags: (0x0031) ACC_PUBLIC, ACC_FINAL, ACC_SUPER
  this_class: #2                          // scala/collection/compat/immutable/package$
  super_class: #4                         // java/lang/Object
  interfaces: 0, fields: 3, methods: 4, attributes: 3
Constant pool:
   #1 = Utf8               scala/collection/compat/immutable/package$
   #2 = Class              #1             // scala/collection/compat/immutable/package$
   #3 = Utf8               java/lang/Object
   #4 = Class              #3             // java/lang/Object
   #5 = Utf8               package.scala
   #6 = Utf8               MODULE$
   #7 = Utf8               Lscala/collection/compat/immutable/package$;
   #8 = Utf8               ArraySeq
   #9 = Utf8               Lscala/collection/immutable/ArraySeq$;
  #10 = Utf8               LazyList
  #11 = Utf8               Lscala/collection/immutable/LazyList$;
  #12 = Utf8               <clinit>
  #13 = Utf8               ()V
  #14 = Utf8               <init>
  #15 = NameAndType        #14:#13        // "<init>":()V
  #16 = Methodref          #2.#15         // scala/collection/compat/immutable/package$."<init>":()V
  #17 = NameAndType        #6:#7          // MODULE$:Lscala/collection/compat/immutable/package$;
  #18 = Fieldref           #2.#17         // scala/collection/compat/immutable/package$.MODULE$:Lscala/collection/compat/immutable/package$;
  #19 = Utf8               scala/collection/immutable/ArraySeq$
  #20 = Class              #19            // scala/collection/immutable/ArraySeq$
  #21 = NameAndType        #6:#9          // MODULE$:Lscala/collection/immutable/ArraySeq$;
  #22 = Fieldref           #20.#21        // scala/collection/immutable/ArraySeq$.MODULE$:Lscala/collection/immutable/ArraySeq$;
  #23 = NameAndType        #8:#9          // ArraySeq:Lscala/collection/immutable/ArraySeq$;
  #24 = Fieldref           #2.#23         // scala/collection/compat/immutable/package$.ArraySeq:Lscala/collection/immutable/ArraySeq$;
  #25 = Utf8               scala/collection/immutable/LazyList$
  #26 = Class              #25            // scala/collection/immutable/LazyList$
  #27 = NameAndType        #6:#11         // MODULE$:Lscala/collection/immutable/LazyList$;
  #28 = Fieldref           #26.#27        // scala/collection/immutable/LazyList$.MODULE$:Lscala/collection/immutable/LazyList$;
  #29 = NameAndType        #10:#11        // LazyList:Lscala/collection/immutable/LazyList$;
  #30 = Fieldref           #2.#29         // scala/collection/compat/immutable/package$.LazyList:Lscala/collection/immutable/LazyList$;
  #31 = Utf8               ()Lscala/collection/immutable/ArraySeq$;
  #32 = Utf8               this
  #33 = Utf8               ()Lscala/collection/immutable/LazyList$;
  #34 = Methodref          #4.#15         // java/lang/Object."<init>":()V
  #35 = Utf8               Code
  #36 = Utf8               LineNumberTable
  #37 = Utf8               LocalVariableTable
  #38 = Utf8               SourceFile
  #39 = Utf8               ScalaInlineInfo
  #40 = Utf8               Scala
{
  public static final scala.collection.compat.immutable.package$ MODULE$;
    descriptor: Lscala/collection/compat/immutable/package$;
    flags: (0x0019) ACC_PUBLIC, ACC_STATIC, ACC_FINAL

  private static final scala.collection.immutable.ArraySeq$ ArraySeq;
    descriptor: Lscala/collection/immutable/ArraySeq$;
    flags: (0x001a) ACC_PRIVATE, ACC_STATIC, ACC_FINAL

  private static final scala.collection.immutable.LazyList$ LazyList;
    descriptor: Lscala/collection/immutable/LazyList$;
    flags: (0x001a) ACC_PRIVATE, ACC_STATIC, ACC_FINAL

  public static {};
    descriptor: ()V
    flags: (0x0009) ACC_PUBLIC, ACC_STATIC
    Code:
      stack=2, locals=0, args_size=0
         0: new           #2                  // class scala/collection/compat/immutable/package$
         3: dup
         4: invokespecial #16                 // Method "<init>":()V
         7: putstatic     #18                 // Field MODULE$:Lscala/collection/compat/immutable/package$;
        10: getstatic     #22                 // Field scala/collection/immutable/ArraySeq$.MODULE$:Lscala/collection/immutable/ArraySeq$;
        13: putstatic     #24                 // Field ArraySeq:Lscala/collection/immutable/ArraySeq$;
        16: getstatic     #28                 // Field scala/collection/immutable/LazyList$.MODULE$:Lscala/collection/immutable/LazyList$;
        19: putstatic     #30                 // Field LazyList:Lscala/collection/immutable/LazyList$;
        22: return
      LineNumberTable:
        line 15: 0
        line 17: 10
        line 20: 16
        line 15: 22

  public scala.collection.immutable.ArraySeq$ ArraySeq();
    descriptor: ()Lscala/collection/immutable/ArraySeq$;
    flags: (0x0001) ACC_PUBLIC
    Code:
      stack=1, locals=1, args_size=1
         0: getstatic     #24                 // Field ArraySeq:Lscala/collection/immutable/ArraySeq$;
         3: areturn
      LineNumberTable:
        line 17: 0
      LocalVariableTable:
        Start  Length  Slot  Name   Signature
            0       4     0  this   Lscala/collection/compat/immutable/package$;

  public scala.collection.immutable.LazyList$ LazyList();
    descriptor: ()Lscala/collection/immutable/LazyList$;
    flags: (0x0001) ACC_PUBLIC
    Code:
      stack=1, locals=1, args_size=1
         0: getstatic     #30                 // Field LazyList:Lscala/collection/immutable/LazyList$;
         3: areturn
      LineNumberTable:
        line 20: 0
      LocalVariableTable:
        Start  Length  Slot  Name   Signature
            0       4     0  this   Lscala/collection/compat/immutable/package$;

  private scala.collection.compat.immutable.package$();
    descriptor: ()V
    flags: (0x0002) ACC_PRIVATE
    Code:
      stack=1, locals=1, args_size=1
         0: aload_0
         1: invokespecial #34                 // Method java/lang/Object."<init>":()V
         4: return
      LineNumberTable:
        line 21: 0
        line 15: 4
      LocalVariableTable:
        Start  Length  Slot  Name   Signature
            0       5     0  this   Lscala/collection/compat/immutable/package$;
}
SourceFile: "package.scala"
  ScalaInlineInfo: length = 0x13 (unknown attribute)
   01 01 00 03 00 0E 00 0D 01 00 08 00 1F 01 00 0A
   00 21 01
  Scala: length = 0x0 (unknown attribute)

