Classfile /Users/mw/Projects/slang-braindump/.jar/jar8/assemble/slang-braindump/assemble/content/coursier/complete/Complete$Result.class
  Last modified May 29, 2022; size 6577 bytes
  SHA-256 checksum 6ef93095775ce451d3bbbaa968da7e5a5b938b031eb9d3127a6a79d39b13c78c
  Compiled from "Complete.scala"
public final class coursier.complete.Complete$Result implements scala.Product,java.io.Serializable
  minor version: 0
  major version: 52
  flags: (0x0031) ACC_PUBLIC, ACC_FINAL, ACC_SUPER
  this_class: #2                          // coursier/complete/Complete$Result
  super_class: #4                         // java/lang/Object
  interfaces: 2, fields: 2, methods: 20, attributes: 5
Constant pool:
    #1 = Utf8               coursier/complete/Complete$Result
    #2 = Class              #1            // coursier/complete/Complete$Result
    #3 = Utf8               java/lang/Object
    #4 = Class              #3            // java/lang/Object
    #5 = Utf8               scala/Product
    #6 = Class              #5            // scala/Product
    #7 = Utf8               java/io/Serializable
    #8 = Class              #7            // java/io/Serializable
    #9 = Utf8               Complete.scala
   #10 = Utf8               coursier/complete/Complete
   #11 = Class              #10           // coursier/complete/Complete
   #12 = Utf8               Result
   #13 = Utf8               coursier/core/Repository$Complete$
   #14 = Class              #13           // coursier/core/Repository$Complete$
   #15 = Utf8               coursier/core/Repository
   #16 = Class              #15           // coursier/core/Repository
   #17 = Utf8
   #18 = Utf8               coursier/core/Repository$Complete$Input
   #19 = Class              #18           // coursier/core/Repository$Complete$Input
   #20 = Utf8               Input
   #21 = Utf8               java/lang/invoke/MethodHandles$Lookup
   #22 = Class              #21           // java/lang/invoke/MethodHandles$Lookup
   #23 = Utf8               java/lang/invoke/MethodHandles
   #24 = Class              #23           // java/lang/invoke/MethodHandles
   #25 = Utf8               Lookup
   #26 = Utf8               input
   #27 = Utf8               Lcoursier/core/Repository$Complete$Input;
   #28 = Utf8               results
   #29 = Utf8               Lscala/collection/immutable/Seq;
   #30 = Utf8               Lscala/collection/immutable/Seq<Lscala/Tuple2<Lcoursier/core/Repository;Lscala/util/Either<Ljava/lang/Throwable;Lscala/collection/immutable/Seq<Ljava/lang/String;>;>;>;>;
   #31 = Utf8               productIterator
   #32 = Utf8               ()Lscala/collection/Iterator;
   #33 = Utf8               ()Lscala/collection/Iterator<Ljava/lang/Object;>;
   #34 = Utf8               productIterator$
   #35 = Utf8               (Lscala/Product;)Lscala/collection/Iterator;
   #36 = NameAndType        #34:#35       // productIterator$:(Lscala/Product;)Lscala/collection/Iterator;
   #37 = InterfaceMethodref #6.#36        // scala/Product.productIterator$:(Lscala/Product;)Lscala/collection/Iterator;
   #38 = Utf8               this
   #39 = Utf8               Lcoursier/complete/Complete$Result;
   #40 = Utf8               productElementNames
   #41 = Utf8               ()Lscala/collection/Iterator<Ljava/lang/String;>;
   #42 = Utf8               productElementNames$
   #43 = NameAndType        #42:#35       // productElementNames$:(Lscala/Product;)Lscala/collection/Iterator;
   #44 = InterfaceMethodref #6.#43        // scala/Product.productElementNames$:(Lscala/Product;)Lscala/collection/Iterator;
   #45 = Utf8               ()Lcoursier/core/Repository$Complete$Input;
   #46 = NameAndType        #26:#27       // input:Lcoursier/core/Repository$Complete$Input;
   #47 = Fieldref           #2.#46        // coursier/complete/Complete$Result.input:Lcoursier/core/Repository$Complete$Input;
   #48 = Utf8               ()Lscala/collection/immutable/Seq;
   #49 = Utf8               ()Lscala/collection/immutable/Seq<Lscala/Tuple2<Lcoursier/core/Repository;Lscala/util/Either<Ljava/lang/Throwable;Lscala/collection/immutable/Seq<Ljava/lang/String;>;>;>;>;
   #50 = NameAndType        #28:#29       // results:Lscala/collection/immutable/Seq;
   #51 = Fieldref           #2.#50        // coursier/complete/Complete$Result.results:Lscala/collection/immutable/Seq;
   #52 = Utf8               from
   #53 = Utf8               ()I
   #54 = NameAndType        #26:#45       // input:()Lcoursier/core/Repository$Complete$Input;
   #55 = Methodref          #2.#54        // coursier/complete/Complete$Result.input:()Lcoursier/core/Repository$Complete$Input;
   #56 = NameAndType        #52:#53       // from:()I
   #57 = Methodref          #19.#56       // coursier/core/Repository$Complete$Input.from:()I
   #58 = Utf8               completions
   #59 = Utf8               ()Lscala/collection/immutable/Seq<Ljava/lang/String;>;
   #60 = NameAndType        #28:#48       // results:()Lscala/collection/immutable/Seq;
   #61 = Methodref          #2.#60        // coursier/complete/Complete$Result.results:()Lscala/collection/immutable/Seq;
   #62 = Utf8               (Ljava/lang/Object;)Ljava/lang/Object;
   #63 = MethodType         #62           //  (Ljava/lang/Object;)Ljava/lang/Object;
   #64 = Utf8               $anonfun$completions$1
   #65 = Utf8               (Lscala/Tuple2;)Lscala/collection/immutable/Seq;
   #66 = NameAndType        #64:#65       // $anonfun$completions$1:(Lscala/Tuple2;)Lscala/collection/immutable/Seq;
   #67 = Methodref          #2.#66        // coursier/complete/Complete$Result.$anonfun$completions$1:(Lscala/Tuple2;)Lscala/collection/immutable/Seq;
   #68 = MethodHandle       6:#67         // REF_invokeStatic coursier/complete/Complete$Result.$anonfun$completions$1:(Lscala/Tuple2;)Lscala/collection/immutable/Seq;
   #69 = MethodType         #65           //  (Lscala/Tuple2;)Lscala/collection/immutable/Seq;
   #70 = Integer            5
   #71 = Integer            1
   #72 = Utf8               java/lang/invoke/LambdaMetafactory
   #73 = Class              #72           // java/lang/invoke/LambdaMetafactory
   #74 = Utf8               altMetafactory
   #75 = Utf8               (Ljava/lang/invoke/MethodHandles$Lookup;Ljava/lang/String;Ljava/lang/invoke/MethodType;[Ljava/lang/Object;)Ljava/lang/invoke/CallSite;
   #76 = NameAndType        #74:#75       // altMetafactory:(Ljava/lang/invoke/MethodHandles$Lookup;Ljava/lang/String;Ljava/lang/invoke/MethodType;[Ljava/lang/Object;)Ljava/lang/invoke/CallSite;
   #77 = Methodref          #73.#76       // java/lang/invoke/LambdaMetafactory.altMetafactory:(Ljava/lang/invoke/MethodHandles$Lookup;Ljava/lang/String;Ljava/lang/invoke/MethodType;[Ljava/lang/Object;)Ljava/lang/invoke/CallSite;
   #78 = MethodHandle       6:#77         // REF_invokeStatic java/lang/invoke/LambdaMetafactory.altMetafactory:(Ljava/lang/invoke/MethodHandles$Lookup;Ljava/lang/String;Ljava/lang/invoke/MethodType;[Ljava/lang/Object;)Ljava/lang/invoke/CallSite;
   #79 = Utf8               apply
   #80 = Utf8               ()Lscala/Function1;
   #81 = NameAndType        #79:#80       // apply:()Lscala/Function1;
   #82 = InvokeDynamic      #0:#81        // #0:apply:()Lscala/Function1;
   #83 = Utf8               scala/collection/immutable/Seq
   #84 = Class              #83           // scala/collection/immutable/Seq
   #85 = Utf8               flatMap
   #86 = Utf8               (Lscala/Function1;)Ljava/lang/Object;
   #87 = NameAndType        #85:#86       // flatMap:(Lscala/Function1;)Ljava/lang/Object;
   #88 = InterfaceMethodref #84.#87       // scala/collection/immutable/Seq.flatMap:(Lscala/Function1;)Ljava/lang/Object;
   #89 = Utf8               withInput
   #90 = Utf8               (Lcoursier/core/Repository$Complete$Input;)Lcoursier/complete/Complete$Result;
   #91 = Utf8               <init>
   #92 = Utf8               (Lcoursier/core/Repository$Complete$Input;Lscala/collection/immutable/Seq;)V
   #93 = NameAndType        #91:#92       // "<init>":(Lcoursier/core/Repository$Complete$Input;Lscala/collection/immutable/Seq;)V
   #94 = Methodref          #2.#93        // coursier/complete/Complete$Result."<init>":(Lcoursier/core/Repository$Complete$Input;Lscala/collection/immutable/Seq;)V
   #95 = Utf8               withResults
   #96 = Utf8               (Lscala/collection/immutable/Seq;)Lcoursier/complete/Complete$Result;
   #97 = Utf8               (Lscala/collection/immutable/Seq<Lscala/Tuple2<Lcoursier/core/Repository;Lscala/util/Either<Ljava/lang/Throwable;Lscala/collection/immutable/Seq<Ljava/lang/String;>;>;>;>;)Lcoursier/complete/Complete$Result;
   #98 = Utf8               toString
   #99 = Utf8               ()Ljava/lang/String;
  #100 = Utf8               java/lang/StringBuilder
  #101 = Class              #100          // java/lang/StringBuilder
  #102 = Utf8               Result(
  #103 = String             #102          // Result(
  #104 = Utf8               (Ljava/lang/String;)V
  #105 = NameAndType        #91:#104      // "<init>":(Ljava/lang/String;)V
  #106 = Methodref          #101.#105     // java/lang/StringBuilder."<init>":(Ljava/lang/String;)V
  #107 = Utf8               java/lang/String
  #108 = Class              #107          // java/lang/String
  #109 = Utf8               valueOf
  #110 = Utf8               (Ljava/lang/Object;)Ljava/lang/String;
  #111 = NameAndType        #109:#110     // valueOf:(Ljava/lang/Object;)Ljava/lang/String;
  #112 = Methodref          #108.#111     // java/lang/String.valueOf:(Ljava/lang/Object;)Ljava/lang/String;
  #113 = Utf8               append
  #114 = Utf8               (Ljava/lang/String;)Ljava/lang/StringBuilder;
  #115 = NameAndType        #113:#114     // append:(Ljava/lang/String;)Ljava/lang/StringBuilder;
  #116 = Methodref          #101.#115     // java/lang/StringBuilder.append:(Ljava/lang/String;)Ljava/lang/StringBuilder;
  #117 = Utf8               ,
  #118 = String             #117          // ,
  #119 = Utf8               )
  #120 = String             #119          // )
  #121 = NameAndType        #98:#99       // toString:()Ljava/lang/String;
  #122 = Methodref          #101.#121     // java/lang/StringBuilder.toString:()Ljava/lang/String;
  #123 = Utf8               b
  #124 = Utf8               Ljava/lang/StringBuilder;
  #125 = Utf8               canEqual
  #126 = Utf8               (Ljava/lang/Object;)Z
  #127 = Utf8               obj
  #128 = Utf8               Ljava/lang/Object;
  #129 = Utf8               equals
  #130 = NameAndType        #125:#126     // canEqual:(Ljava/lang/Object;)Z
  #131 = Methodref          #2.#130       // coursier/complete/Complete$Result.canEqual:(Ljava/lang/Object;)Z
  #132 = NameAndType        #129:#126     // equals:(Ljava/lang/Object;)Z
  #133 = Methodref          #4.#132       // java/lang/Object.equals:(Ljava/lang/Object;)Z
  #134 = Utf8               other
  #135 = Utf8               hashCode
  #136 = String             #12           // Result
  #137 = Utf8               scala/runtime/Statics
  #138 = Class              #137          // scala/runtime/Statics
  #139 = Utf8               anyHash
  #140 = Utf8               (Ljava/lang/Object;)I
  #141 = NameAndType        #139:#140     // anyHash:(Ljava/lang/Object;)I
  #142 = Methodref          #138.#141     // scala/runtime/Statics.anyHash:(Ljava/lang/Object;)I
  #143 = Utf8               code
  #144 = Utf8               I
  #145 = Utf8               tuple
  #146 = Utf8               ()Lscala/Tuple2;
  #147 = Utf8               ()Lscala/Tuple2<Lcoursier/core/Repository$Complete$Input;Lscala/collection/immutable/Seq<Lscala/Tuple2<Lcoursier/core/Repository;Lscala/util/Either<Ljava/lang/Throwable;Lscala/collection/immutable/Seq<Ljava/lang/String;>;>;>;>;>;
  #148 = Utf8               scala/Tuple2
  #149 = Class              #148          // scala/Tuple2
  #150 = Utf8               (Ljava/lang/Object;Ljava/lang/Object;)V
  #151 = NameAndType        #91:#150      // "<init>":(Ljava/lang/Object;Ljava/lang/Object;)V
  #152 = Methodref          #149.#151     // scala/Tuple2."<init>":(Ljava/lang/Object;Ljava/lang/Object;)V
  #153 = Utf8               productPrefix
  #154 = Utf8               productArity
  #155 = Utf8               productElement
  #156 = Utf8               (I)Ljava/lang/Object;
  #157 = Utf8               n
  #158 = Utf8               java/lang/IndexOutOfBoundsException
  #159 = Class              #158          // java/lang/IndexOutOfBoundsException
  #160 = Utf8               scala/runtime/BoxesRunTime
  #161 = Class              #160          // scala/runtime/BoxesRunTime
  #162 = Utf8               boxToInteger
  #163 = Utf8               (I)Ljava/lang/Integer;
  #164 = NameAndType        #162:#163     // boxToInteger:(I)Ljava/lang/Integer;
  #165 = Methodref          #161.#164     // scala/runtime/BoxesRunTime.boxToInteger:(I)Ljava/lang/Integer;
  #166 = Methodref          #4.#121       // java/lang/Object.toString:()Ljava/lang/String;
  #167 = Methodref          #159.#105     // java/lang/IndexOutOfBoundsException."<init>":(Ljava/lang/String;)V
  #168 = Utf8               productElementName
  #169 = Utf8               (I)Ljava/lang/String;
  #170 = String             #26           // input
  #171 = String             #28           // results
  #172 = Utf8               x$4
  #173 = Utf8               _2
  #174 = Utf8               ()Ljava/lang/Object;
  #175 = NameAndType        #173:#174     // _2:()Ljava/lang/Object;
  #176 = Methodref          #149.#175     // scala/Tuple2._2:()Ljava/lang/Object;
  #177 = Utf8               scala/util/Either
  #178 = Class              #177          // scala/util/Either
  #179 = Utf8               toSeq
  #180 = NameAndType        #179:#48      // toSeq:()Lscala/collection/immutable/Seq;
  #181 = Methodref          #178.#180     // scala/util/Either.toSeq:()Lscala/collection/immutable/Seq;
  #182 = Utf8               scala/Predef$
  #183 = Class              #182          // scala/Predef$
  #184 = Utf8               MODULE$
  #185 = Utf8               Lscala/Predef$;
  #186 = NameAndType        #184:#185     // MODULE$:Lscala/Predef$;
  #187 = Fieldref           #183.#186     // scala/Predef$.MODULE$:Lscala/Predef$;
  #188 = Utf8               $conforms
  #189 = NameAndType        #188:#80      // $conforms:()Lscala/Function1;
  #190 = Methodref          #183.#189     // scala/Predef$.$conforms:()Lscala/Function1;
  #191 = Utf8               flatten
  #192 = NameAndType        #191:#86      // flatten:(Lscala/Function1;)Ljava/lang/Object;
  #193 = InterfaceMethodref #84.#192      // scala/collection/immutable/Seq.flatten:(Lscala/Function1;)Ljava/lang/Object;
  #194 = Utf8               Lscala/Tuple2;
  #195 = Utf8               (Lcoursier/core/Repository$Complete$Input;Lscala/collection/immutable/Seq<Lscala/Tuple2<Lcoursier/core/Repository;Lscala/util/Either<Ljava/lang/Throwable;Lscala/collection/immutable/Seq<Ljava/lang/String;>;>;>;>;)V
  #196 = Utf8               ()V
  #197 = NameAndType        #91:#196      // "<init>":()V
  #198 = Methodref          #4.#197       // java/lang/Object."<init>":()V
  #199 = Utf8               $init$
  #200 = Utf8               (Lscala/Product;)V
  #201 = NameAndType        #199:#200     // $init$:(Lscala/Product;)V
  #202 = InterfaceMethodref #6.#201       // scala/Product.$init$:(Lscala/Product;)V
  #203 = Utf8               $deserializeLambda$
  #204 = Utf8               (Ljava/lang/invoke/SerializedLambda;)Ljava/lang/Object;
  #205 = Utf8               scala/runtime/LambdaDeserialize
  #206 = Class              #205          // scala/runtime/LambdaDeserialize
  #207 = Utf8               bootstrap
  #208 = Utf8               (Ljava/lang/invoke/MethodHandles$Lookup;Ljava/lang/String;Ljava/lang/invoke/MethodType;[Ljava/lang/invoke/MethodHandle;)Ljava/lang/invoke/CallSite;
  #209 = NameAndType        #207:#208     // bootstrap:(Ljava/lang/invoke/MethodHandles$Lookup;Ljava/lang/String;Ljava/lang/invoke/MethodType;[Ljava/lang/invoke/MethodHandle;)Ljava/lang/invoke/CallSite;
  #210 = Methodref          #206.#209     // scala/runtime/LambdaDeserialize.bootstrap:(Ljava/lang/invoke/MethodHandles$Lookup;Ljava/lang/String;Ljava/lang/invoke/MethodType;[Ljava/lang/invoke/MethodHandle;)Ljava/lang/invoke/CallSite;
  #211 = MethodHandle       6:#210        // REF_invokeStatic scala/runtime/LambdaDeserialize.bootstrap:(Ljava/lang/invoke/MethodHandles$Lookup;Ljava/lang/String;Ljava/lang/invoke/MethodType;[Ljava/lang/invoke/MethodHandle;)Ljava/lang/invoke/CallSite;
  #212 = Utf8               lambdaDeserialize
  #213 = NameAndType        #212:#204     // lambdaDeserialize:(Ljava/lang/invoke/SerializedLambda;)Ljava/lang/Object;
  #214 = InvokeDynamic      #1:#213       // #1:lambdaDeserialize:(Ljava/lang/invoke/SerializedLambda;)Ljava/lang/Object;
  #215 = Utf8               Signature
  #216 = Utf8               Code
  #217 = Utf8               LineNumberTable
  #218 = Utf8               LocalVariableTable
  #219 = Utf8               MethodParameters
  #220 = Utf8               StackMapTable
  #221 = Utf8               InnerClasses
  #222 = Utf8               SourceFile
  #223 = Utf8               BootstrapMethods
  #224 = Utf8               ScalaInlineInfo
  #225 = Utf8               Scala
{
  private final coursier.core.Repository$Complete$Input input;
    descriptor: Lcoursier/core/Repository$Complete$Input;
    flags: (0x0012) ACC_PRIVATE, ACC_FINAL

  private final scala.collection.immutable.Seq<scala.Tuple2<coursier.core.Repository, scala.util.Either<java.lang.Throwable, scala.collection.immutable.Seq<java.lang.String>>>> results;
    descriptor: Lscala/collection/immutable/Seq;
    flags: (0x0012) ACC_PRIVATE, ACC_FINAL
    Signature: #30                          // Lscala/collection/immutable/Seq<Lscala/Tuple2<Lcoursier/core/Repository;Lscala/util/Either<Ljava/lang/Throwable;Lscala/collection/immutable/Seq<Ljava/lang/String;>;>;>;>;

  public scala.collection.Iterator<java.lang.Object> productIterator();
    descriptor: ()Lscala/collection/Iterator;
    flags: (0x0001) ACC_PUBLIC
    Code:
      stack=1, locals=1, args_size=1
         0: aload_0
         1: invokestatic  #37                 // InterfaceMethod scala/Product.productIterator$:(Lscala/Product;)Lscala/collection/Iterator;
         4: areturn
      LineNumberTable:
        line 84: 0
      LocalVariableTable:
        Start  Length  Slot  Name   Signature
            0       5     0  this   Lcoursier/complete/Complete$Result;
    Signature: #33                          // ()Lscala/collection/Iterator<Ljava/lang/Object;>;

  public scala.collection.Iterator<java.lang.String> productElementNames();
    descriptor: ()Lscala/collection/Iterator;
    flags: (0x0001) ACC_PUBLIC
    Code:
      stack=1, locals=1, args_size=1
         0: aload_0
         1: invokestatic  #44                 // InterfaceMethod scala/Product.productElementNames$:(Lscala/Product;)Lscala/collection/Iterator;
         4: areturn
      LineNumberTable:
        line 84: 0
      LocalVariableTable:
        Start  Length  Slot  Name   Signature
            0       5     0  this   Lcoursier/complete/Complete$Result;
    Signature: #41                          // ()Lscala/collection/Iterator<Ljava/lang/String;>;

  public coursier.core.Repository$Complete$Input input();
    descriptor: ()Lcoursier/core/Repository$Complete$Input;
    flags: (0x0001) ACC_PUBLIC
    Code:
      stack=1, locals=1, args_size=1
         0: aload_0
         1: getfield      #47                 // Field input:Lcoursier/core/Repository$Complete$Input;
         4: areturn
      LineNumberTable:
        line 84: 0
      LocalVariableTable:
        Start  Length  Slot  Name   Signature
            0       5     0  this   Lcoursier/complete/Complete$Result;

  public scala.collection.immutable.Seq<scala.Tuple2<coursier.core.Repository, scala.util.Either<java.lang.Throwable, scala.collection.immutable.Seq<java.lang.String>>>> results();
    descriptor: ()Lscala/collection/immutable/Seq;
    flags: (0x0001) ACC_PUBLIC
    Code:
      stack=1, locals=1, args_size=1
         0: aload_0
         1: getfield      #51                 // Field results:Lscala/collection/immutable/Seq;
         4: areturn
      LineNumberTable:
        line 84: 0
      LocalVariableTable:
        Start  Length  Slot  Name   Signature
            0       5     0  this   Lcoursier/complete/Complete$Result;
    Signature: #49                          // ()Lscala/collection/immutable/Seq<Lscala/Tuple2<Lcoursier/core/Repository;Lscala/util/Either<Ljava/lang/Throwable;Lscala/collection/immutable/Seq<Ljava/lang/String;>;>;>;>;

  public int from();
    descriptor: ()I
    flags: (0x0001) ACC_PUBLIC
    Code:
      stack=1, locals=1, args_size=1
         0: aload_0
         1: invokevirtual #55                 // Method input:()Lcoursier/core/Repository$Complete$Input;
         4: invokevirtual #57                 // Method coursier/core/Repository$Complete$Input.from:()I
         7: ireturn
      LineNumberTable:
        line 88: 0
      LocalVariableTable:
        Start  Length  Slot  Name   Signature
            0       8     0  this   Lcoursier/complete/Complete$Result;

  public scala.collection.immutable.Seq<java.lang.String> completions();
    descriptor: ()Lscala/collection/immutable/Seq;
    flags: (0x0001) ACC_PUBLIC
    Code:
      stack=2, locals=1, args_size=1
         0: aload_0
         1: invokevirtual #61                 // Method results:()Lscala/collection/immutable/Seq;
         4: invokedynamic #82,  0             // InvokeDynamic #0:apply:()Lscala/Function1;
         9: invokeinterface #88,  2           // InterfaceMethod scala/collection/immutable/Seq.flatMap:(Lscala/Function1;)Ljava/lang/Object;
        14: checkcast     #84                 // class scala/collection/immutable/Seq
        17: areturn
      LineNumberTable:
        line 90: 0
      LocalVariableTable:
        Start  Length  Slot  Name   Signature
            0      18     0  this   Lcoursier/complete/Complete$Result;
    Signature: #59                          // ()Lscala/collection/immutable/Seq<Ljava/lang/String;>;

  public coursier.complete.Complete$Result withInput(coursier.core.Repository$Complete$Input);
    descriptor: (Lcoursier/core/Repository$Complete$Input;)Lcoursier/complete/Complete$Result;
    flags: (0x0001) ACC_PUBLIC
    Code:
      stack=4, locals=2, args_size=2
         0: new           #2                  // class coursier/complete/Complete$Result
         3: dup
         4: aload_1
         5: aload_0
         6: invokevirtual #61                 // Method results:()Lscala/collection/immutable/Seq;
         9: invokespecial #94                 // Method "<init>":(Lcoursier/core/Repository$Complete$Input;Lscala/collection/immutable/Seq;)V
        12: areturn
      LineNumberTable:
        line 84: 0
      LocalVariableTable:
        Start  Length  Slot  Name   Signature
            0      13     0  this   Lcoursier/complete/Complete$Result;
            0      13     1 input   Lcoursier/core/Repository$Complete$Input;
    MethodParameters:
      Name                           Flags
      input                          final

  public coursier.complete.Complete$Result withResults(scala.collection.immutable.Seq<scala.Tuple2<coursier.core.Repository, scala.util.Either<java.lang.Throwable, scala.collection.immutable.Seq<java.lang.String>>>>);
    descriptor: (Lscala/collection/immutable/Seq;)Lcoursier/complete/Complete$Result;
    flags: (0x0001) ACC_PUBLIC
    Code:
      stack=4, locals=2, args_size=2
         0: new           #2                  // class coursier/complete/Complete$Result
         3: dup
         4: aload_0
         5: invokevirtual #55                 // Method input:()Lcoursier/core/Repository$Complete$Input;
         8: aload_1
         9: invokespecial #94                 // Method "<init>":(Lcoursier/core/Repository$Complete$Input;Lscala/collection/immutable/Seq;)V
        12: areturn
      LineNumberTable:
        line 84: 0
      LocalVariableTable:
        Start  Length  Slot  Name   Signature
            0      13     0  this   Lcoursier/complete/Complete$Result;
            0      13     1 results   Lscala/collection/immutable/Seq;
    Signature: #97                          // (Lscala/collection/immutable/Seq<Lscala/Tuple2<Lcoursier/core/Repository;Lscala/util/Either<Ljava/lang/Throwable;Lscala/collection/immutable/Seq<Ljava/lang/String;>;>;>;>;)Lcoursier/complete/Complete$Result;
    MethodParameters:
      Name                           Flags
      results                        final

  public java.lang.String toString();
    descriptor: ()Ljava/lang/String;
    flags: (0x0001) ACC_PUBLIC
    Code:
      stack=3, locals=2, args_size=1
         0: new           #101                // class java/lang/StringBuilder
         3: dup
         4: ldc           #103                // String Result(
         6: invokespecial #106                // Method java/lang/StringBuilder."<init>":(Ljava/lang/String;)V
         9: astore_1
        10: aload_1
        11: aload_0
        12: invokevirtual #55                 // Method input:()Lcoursier/core/Repository$Complete$Input;
        15: invokestatic  #112                // Method java/lang/String.valueOf:(Ljava/lang/Object;)Ljava/lang/String;
        18: invokevirtual #116                // Method java/lang/StringBuilder.append:(Ljava/lang/String;)Ljava/lang/StringBuilder;
        21: pop
        22: aload_1
        23: ldc           #118                // String ,
        25: invokevirtual #116                // Method java/lang/StringBuilder.append:(Ljava/lang/String;)Ljava/lang/StringBuilder;
        28: pop
        29: aload_1
        30: aload_0
        31: invokevirtual #61                 // Method results:()Lscala/collection/immutable/Seq;
        34: invokestatic  #112                // Method java/lang/String.valueOf:(Ljava/lang/Object;)Ljava/lang/String;
        37: invokevirtual #116                // Method java/lang/StringBuilder.append:(Ljava/lang/String;)Ljava/lang/StringBuilder;
        40: pop
        41: aload_1
        42: ldc           #120                // String )
        44: invokevirtual #116                // Method java/lang/StringBuilder.append:(Ljava/lang/String;)Ljava/lang/StringBuilder;
        47: pop
        48: aload_1
        49: invokevirtual #122                // Method java/lang/StringBuilder.toString:()Ljava/lang/String;
        52: areturn
      LineNumberTable:
        line 84: 0
      LocalVariableTable:
        Start  Length  Slot  Name   Signature
           10      42     1     b   Ljava/lang/StringBuilder;
            0      53     0  this   Lcoursier/complete/Complete$Result;

  public boolean canEqual(java.lang.Object);
    descriptor: (Ljava/lang/Object;)Z
    flags: (0x0001) ACC_PUBLIC
    Code:
      stack=1, locals=2, args_size=2
         0: aload_1
         1: ifnull        15
         4: aload_1
         5: instanceof    #2                  // class coursier/complete/Complete$Result
         8: ifeq          15
        11: iconst_1
        12: goto          16
        15: iconst_0
        16: ireturn
      StackMapTable: number_of_entries = 2
        frame_type = 15 /* same */
        frame_type = 64 /* same_locals_1_stack_item */
          stack = [ int ]
      LineNumberTable:
        line 84: 0
      LocalVariableTable:
        Start  Length  Slot  Name   Signature
            0      17     0  this   Lcoursier/complete/Complete$Result;
            0      17     1   obj   Ljava/lang/Object;
    MethodParameters:
      Name                           Flags
      obj                            final

  public boolean equals(java.lang.Object);
    descriptor: (Ljava/lang/Object;)Z
    flags: (0x0001) ACC_PUBLIC
    Code:
      stack=2, locals=5, args_size=2
         0: aload_0
         1: aload_1
         2: if_acmpeq     89
         5: aload_0
         6: aload_1
         7: invokevirtual #131                // Method canEqual:(Ljava/lang/Object;)Z
        10: ifeq          93
        13: aload_1
        14: checkcast     #2                  // class coursier/complete/Complete$Result
        17: astore_2
        18: iconst_1
        19: ifeq          85
        22: aload_0
        23: invokevirtual #55                 // Method input:()Lcoursier/core/Repository$Complete$Input;
        26: aload_2
        27: invokevirtual #55                 // Method input:()Lcoursier/core/Repository$Complete$Input;
        30: astore_3
        31: dup
        32: ifnonnull     43
        35: pop
        36: aload_3
        37: ifnull        50
        40: goto          85
        43: aload_3
        44: invokevirtual #133                // Method java/lang/Object.equals:(Ljava/lang/Object;)Z
        47: ifeq          85
        50: aload_0
        51: invokevirtual #61                 // Method results:()Lscala/collection/immutable/Seq;
        54: aload_2
        55: invokevirtual #61                 // Method results:()Lscala/collection/immutable/Seq;
        58: astore        4
        60: dup
        61: ifnonnull     73
        64: pop
        65: aload         4
        67: ifnull        81
        70: goto          85
        73: aload         4
        75: invokevirtual #133                // Method java/lang/Object.equals:(Ljava/lang/Object;)Z
        78: ifeq          85
        81: iconst_1
        82: goto          86
        85: iconst_0
        86: ifeq          93
        89: iconst_1
        90: goto          94
        93: iconst_0
        94: ireturn
      StackMapTable: number_of_entries = 9
        frame_type = 255 /* full_frame */
          offset_delta = 43
          locals = [ class coursier/complete/Complete$Result, class java/lang/Object, class coursier/complete/Complete$Result, class coursier/core/Repository$Complete$Input ]
          stack = [ class coursier/core/Repository$Complete$Input ]
        frame_type = 6 /* same */
        frame_type = 255 /* full_frame */
          offset_delta = 22
          locals = [ class coursier/complete/Complete$Result, class java/lang/Object, class coursier/complete/Complete$Result, class coursier/core/Repository$Complete$Input, class scala/collection/immutable/Seq ]
          stack = [ class scala/collection/immutable/Seq ]
        frame_type = 7 /* same */
        frame_type = 249 /* chop */
          offset_delta = 3
        frame_type = 64 /* same_locals_1_stack_item */
          stack = [ int ]
        frame_type = 250 /* chop */
          offset_delta = 2
        frame_type = 3 /* same */
        frame_type = 64 /* same_locals_1_stack_item */
          stack = [ int ]
      LineNumberTable:
        line 84: 0
      LocalVariableTable:
        Start  Length  Slot  Name   Signature
           18      68     2 other   Lcoursier/complete/Complete$Result;
            0      95     0  this   Lcoursier/complete/Complete$Result;
            0      95     1   obj   Ljava/lang/Object;
    MethodParameters:
      Name                           Flags
      obj                            final

  public int hashCode();
    descriptor: ()I
    flags: (0x0001) ACC_PUBLIC
    Code:
      stack=2, locals=2, args_size=1
         0: bipush        17
         2: ldc           #136                // String Result
         4: invokestatic  #142                // Method scala/runtime/Statics.anyHash:(Ljava/lang/Object;)I
         7: iadd
         8: istore_1
         9: bipush        37
        11: iload_1
        12: imul
        13: aload_0
        14: invokevirtual #55                 // Method input:()Lcoursier/core/Repository$Complete$Input;
        17: invokestatic  #142                // Method scala/runtime/Statics.anyHash:(Ljava/lang/Object;)I
        20: iadd
        21: istore_1
        22: bipush        37
        24: iload_1
        25: imul
        26: aload_0
        27: invokevirtual #61                 // Method results:()Lscala/collection/immutable/Seq;
        30: invokestatic  #142                // Method scala/runtime/Statics.anyHash:(Ljava/lang/Object;)I
        33: iadd
        34: istore_1
        35: bipush        37
        37: iload_1
        38: imul
        39: ireturn
      LineNumberTable:
        line 84: 0
      LocalVariableTable:
        Start  Length  Slot  Name   Signature
            9      30     1  code   I
            0      40     0  this   Lcoursier/complete/Complete$Result;

  private scala.Tuple2<coursier.core.Repository$Complete$Input, scala.collection.immutable.Seq<scala.Tuple2<coursier.core.Repository, scala.util.Either<java.lang.Throwable, scala.collection.immutable.Seq<java.lang.String>>>>> tuple();
    descriptor: ()Lscala/Tuple2;
    flags: (0x0002) ACC_PRIVATE
    Code:
      stack=4, locals=1, args_size=1
         0: new           #149                // class scala/Tuple2
         3: dup
         4: aload_0
         5: invokevirtual #55                 // Method input:()Lcoursier/core/Repository$Complete$Input;
         8: aload_0
         9: invokevirtual #61                 // Method results:()Lscala/collection/immutable/Seq;
        12: invokespecial #152                // Method scala/Tuple2."<init>":(Ljava/lang/Object;Ljava/lang/Object;)V
        15: areturn
      LineNumberTable:
        line 84: 0
      LocalVariableTable:
        Start  Length  Slot  Name   Signature
            0      16     0  this   Lcoursier/complete/Complete$Result;
    Signature: #147                         // ()Lscala/Tuple2<Lcoursier/core/Repository$Complete$Input;Lscala/collection/immutable/Seq<Lscala/Tuple2<Lcoursier/core/Repository;Lscala/util/Either<Ljava/lang/Throwable;Lscala/collection/immutable/Seq<Ljava/lang/String;>;>;>;>;>;

  public java.lang.String productPrefix();
    descriptor: ()Ljava/lang/String;
    flags: (0x0001) ACC_PUBLIC
    Code:
      stack=1, locals=1, args_size=1
         0: ldc           #136                // String Result
         2: areturn
      LineNumberTable:
        line 84: 0
      LocalVariableTable:
        Start  Length  Slot  Name   Signature
            0       3     0  this   Lcoursier/complete/Complete$Result;

  public int productArity();
    descriptor: ()I
    flags: (0x0001) ACC_PUBLIC
    Code:
      stack=1, locals=1, args_size=1
         0: iconst_2
         1: ireturn
      LineNumberTable:
        line 84: 0
      LocalVariableTable:
        Start  Length  Slot  Name   Signature
            0       2     0  this   Lcoursier/complete/Complete$Result;

  public java.lang.Object productElement(int);
    descriptor: (I)Ljava/lang/Object;
    flags: (0x0001) ACC_PUBLIC
    Code:
      stack=3, locals=3, args_size=2
         0: iload_1
         1: istore_2
         2: iload_2
         3: tableswitch   { // 0 to 1
                       0: 24
                       1: 31
                 default: 38
            }
        24: aload_0
        25: invokevirtual #55                 // Method input:()Lcoursier/core/Repository$Complete$Input;
        28: goto          53
        31: aload_0
        32: invokevirtual #61                 // Method results:()Lscala/collection/immutable/Seq;
        35: goto          53
        38: new           #159                // class java/lang/IndexOutOfBoundsException
        41: dup
        42: iload_2
        43: invokestatic  #165                // Method scala/runtime/BoxesRunTime.boxToInteger:(I)Ljava/lang/Integer;
        46: invokevirtual #166                // Method java/lang/Object.toString:()Ljava/lang/String;
        49: invokespecial #167                // Method java/lang/IndexOutOfBoundsException."<init>":(Ljava/lang/String;)V
        52: athrow
        53: areturn
      StackMapTable: number_of_entries = 4
        frame_type = 252 /* append */
          offset_delta = 24
          locals = [ int ]
        frame_type = 6 /* same */
        frame_type = 6 /* same */
        frame_type = 78 /* same_locals_1_stack_item */
          stack = [ class java/lang/Object ]
      LineNumberTable:
        line 84: 0
      LocalVariableTable:
        Start  Length  Slot  Name   Signature
            0      54     0  this   Lcoursier/complete/Complete$Result;
            0      54     1     n   I
    MethodParameters:
      Name                           Flags
      n                              final

  public java.lang.String productElementName(int);
    descriptor: (I)Ljava/lang/String;
    flags: (0x0001) ACC_PUBLIC
    Code:
      stack=3, locals=3, args_size=2
         0: iload_1
         1: istore_2
         2: iload_2
         3: tableswitch   { // 0 to 1
                       0: 24
                       1: 29
                 default: 34
            }
        24: ldc           #170                // String input
        26: goto          49
        29: ldc           #171                // String results
        31: goto          49
        34: new           #159                // class java/lang/IndexOutOfBoundsException
        37: dup
        38: iload_2
        39: invokestatic  #165                // Method scala/runtime/BoxesRunTime.boxToInteger:(I)Ljava/lang/Integer;
        42: invokevirtual #166                // Method java/lang/Object.toString:()Ljava/lang/String;
        45: invokespecial #167                // Method java/lang/IndexOutOfBoundsException."<init>":(Ljava/lang/String;)V
        48: athrow
        49: areturn
      StackMapTable: number_of_entries = 4
        frame_type = 252 /* append */
          offset_delta = 24
          locals = [ int ]
        frame_type = 4 /* same */
        frame_type = 4 /* same */
        frame_type = 78 /* same_locals_1_stack_item */
          stack = [ class java/lang/String ]
      LineNumberTable:
        line 84: 0
      LocalVariableTable:
        Start  Length  Slot  Name   Signature
            0      50     0  this   Lcoursier/complete/Complete$Result;
            0      50     1     n   I
    MethodParameters:
      Name                           Flags
      n                              final

  public static final scala.collection.immutable.Seq $anonfun$completions$1(scala.Tuple2);
    descriptor: (Lscala/Tuple2;)Lscala/collection/immutable/Seq;
    flags: (0x1019) ACC_PUBLIC, ACC_STATIC, ACC_FINAL, ACC_SYNTHETIC
    Code:
      stack=2, locals=1, args_size=1
         0: aload_0
         1: invokevirtual #176                // Method scala/Tuple2._2:()Ljava/lang/Object;
         4: checkcast     #178                // class scala/util/Either
         7: invokevirtual #181                // Method scala/util/Either.toSeq:()Lscala/collection/immutable/Seq;
        10: getstatic     #187                // Field scala/Predef$.MODULE$:Lscala/Predef$;
        13: invokevirtual #190                // Method scala/Predef$.$conforms:()Lscala/Function1;
        16: invokeinterface #193,  2          // InterfaceMethod scala/collection/immutable/Seq.flatten:(Lscala/Function1;)Ljava/lang/Object;
        21: checkcast     #84                 // class scala/collection/immutable/Seq
        24: areturn
      LineNumberTable:
        line 90: 0
      LocalVariableTable:
        Start  Length  Slot  Name   Signature
            0      25     0   x$4   Lscala/Tuple2;
    MethodParameters:
      Name                           Flags
      x$4                            final

  public coursier.complete.Complete$Result(coursier.core.Repository$Complete$Input, scala.collection.immutable.Seq<scala.Tuple2<coursier.core.Repository, scala.util.Either<java.lang.Throwable, scala.collection.immutable.Seq<java.lang.String>>>>);
    descriptor: (Lcoursier/core/Repository$Complete$Input;Lscala/collection/immutable/Seq;)V
    flags: (0x0001) ACC_PUBLIC
    Code:
      stack=2, locals=3, args_size=3
         0: aload_0
         1: aload_1
         2: putfield      #47                 // Field input:Lcoursier/core/Repository$Complete$Input;
         5: aload_0
         6: aload_2
         7: putfield      #51                 // Field results:Lscala/collection/immutable/Seq;
        10: aload_0
        11: invokespecial #198                // Method java/lang/Object."<init>":()V
        14: aload_0
        15: invokestatic  #202                // InterfaceMethod scala/Product.$init$:(Lscala/Product;)V
        18: return
      LineNumberTable:
        line 84: 0
        line 92: 10
        line 84: 18
      LocalVariableTable:
        Start  Length  Slot  Name   Signature
            0      19     0  this   Lcoursier/complete/Complete$Result;
            0      19     1 input   Lcoursier/core/Repository$Complete$Input;
            0      19     2 results   Lscala/collection/immutable/Seq;
    Signature: #195                         // (Lcoursier/core/Repository$Complete$Input;Lscala/collection/immutable/Seq<Lscala/Tuple2<Lcoursier/core/Repository;Lscala/util/Either<Ljava/lang/Throwable;Lscala/collection/immutable/Seq<Ljava/lang/String;>;>;>;>;)V
    MethodParameters:
      Name                           Flags
      input                          final
      results                        final

  private static java.lang.Object $deserializeLambda$(java.lang.invoke.SerializedLambda);
    descriptor: (Ljava/lang/invoke/SerializedLambda;)Ljava/lang/Object;
    flags: (0x100a) ACC_PRIVATE, ACC_STATIC, ACC_SYNTHETIC
    Code:
      stack=1, locals=1, args_size=1
         0: aload_0
         1: invokedynamic #214,  0            // InvokeDynamic #1:lambdaDeserialize:(Ljava/lang/invoke/SerializedLambda;)Ljava/lang/Object;
         6: areturn
}
InnerClasses:
  public static final #12= #2 of #11;     // Result=class coursier/complete/Complete$Result of class coursier/complete/Complete
  public static #17= #14 of #16;          // =class coursier/core/Repository$Complete$ of class coursier/core/Repository
  public static abstract #20= #19 of #14; // Input=class coursier/core/Repository$Complete$Input of class coursier/core/Repository$Complete$
  public static final #25= #22 of #24;    // Lookup=class java/lang/invoke/MethodHandles$Lookup of class java/lang/invoke/MethodHandles
SourceFile: "Complete.scala"
BootstrapMethods:
  0: #78 REF_invokeStatic java/lang/invoke/LambdaMetafactory.altMetafactory:(Ljava/lang/invoke/MethodHandles$Lookup;Ljava/lang/String;Ljava/lang/invoke/MethodType;[Ljava/lang/Object;)Ljava/lang/invoke/CallSite;
    Method arguments:
      #63 (Ljava/lang/Object;)Ljava/lang/Object;
      #68 REF_invokeStatic coursier/complete/Complete$Result.$anonfun$completions$1:(Lscala/Tuple2;)Lscala/collection/immutable/Seq;
      #69 (Lscala/Tuple2;)Lscala/collection/immutable/Seq;
      #70 5
      #71 1
      #69 (Lscala/Tuple2;)Lscala/collection/immutable/Seq;
  1: #211 REF_invokeStatic scala/runtime/LambdaDeserialize.bootstrap:(Ljava/lang/invoke/MethodHandles$Lookup;Ljava/lang/String;Ljava/lang/invoke/MethodType;[Ljava/lang/invoke/MethodHandle;)Ljava/lang/invoke/CallSite;
    Method arguments:
      #68 REF_invokeStatic coursier/complete/Complete$Result.$anonfun$completions$1:(Lscala/Tuple2;)Lscala/collection/immutable/Seq;
  ScalaInlineInfo: length = 0x63 (unknown attribute)
   01 01 00 13 00 40 00 41 01 00 5B 00 5C 01 00 7D
   00 7E 01 00 3A 00 30 01 00 81 00 7E 01 00 34 00
   35 01 00 87 00 35 01 00 1A 00 2D 01 00 9A 00 35
   01 00 9B 00 9C 01 00 A8 00 A9 01 00 28 00 20 01
   00 1F 00 20 01 00 99 00 63 01 00 1C 00 30 01 00
   62 00 63 01 00 91 00 92 01 00 59 00 5A 01 00 5F
   00 60 01
  Scala: length = 0x0 (unknown attribute)

