Classfile /Users/mw/Projects/slang-braindump/.jar/jar8/assemble/slang-braindump/assemble/content/com/zaxxer/nuprocess/codec/NuCharsetEncoder.class
  Last modified May 29, 2022; size 2092 bytes
  SHA-256 checksum 981ba3fc84ef09c8862b3adcf74f99001777ba3f8fb105ed2f1e971b526372fa
  Compiled from "NuCharsetEncoder.java"
public final class com.zaxxer.nuprocess.codec.NuCharsetEncoder
  minor version: 0
  major version: 51
  flags: (0x0031) ACC_PUBLIC, ACC_FINAL, ACC_SUPER
  this_class: #18                         // com/zaxxer/nuprocess/codec/NuCharsetEncoder
  super_class: #19                        // java/lang/Object
  interfaces: 0, fields: 3, methods: 3, attributes: 1
Constant pool:
   #1 = Methodref          #49.#50        // java/nio/charset/Charset.newEncoder:()Ljava/nio/charset/CharsetEncoder;
   #2 = Methodref          #18.#51        // com/zaxxer/nuprocess/codec/NuCharsetEncoder."<init>":(Lcom/zaxxer/nuprocess/codec/NuCharsetEncoderHandler;Ljava/nio/charset/CharsetEncoder;)V
   #3 = Methodref          #19.#52        // java/lang/Object."<init>":()V
   #4 = Fieldref           #18.#53        // com/zaxxer/nuprocess/codec/NuCharsetEncoder.handler:Lcom/zaxxer/nuprocess/codec/NuCharsetEncoderHandler;
   #5 = Fieldref           #18.#54        // com/zaxxer/nuprocess/codec/NuCharsetEncoder.encoder:Ljava/nio/charset/CharsetEncoder;
   #6 = Class              #55            // com/zaxxer/nuprocess/NuProcess
   #7 = Integer            65536
   #8 = Methodref          #56.#57        // java/nio/CharBuffer.allocate:(I)Ljava/nio/CharBuffer;
   #9 = Fieldref           #18.#58        // com/zaxxer/nuprocess/codec/NuCharsetEncoder.charBuffer:Ljava/nio/CharBuffer;
  #10 = InterfaceMethodref #59.#60        // com/zaxxer/nuprocess/codec/NuCharsetEncoderHandler.onStdinReady:(Ljava/nio/CharBuffer;)Z
  #11 = Methodref          #61.#62        // java/nio/charset/CharsetEncoder.encode:(Ljava/nio/CharBuffer;Ljava/nio/ByteBuffer;Z)Ljava/nio/charset/CoderResult;
  #12 = Methodref          #63.#64        // java/nio/ByteBuffer.flip:()Ljava/nio/ByteBuffer;
  #13 = Methodref          #56.#65        // java/nio/CharBuffer.compact:()Ljava/nio/CharBuffer;
  #14 = Methodref          #46.#66        // java/nio/charset/CoderResult.isError:()Z
  #15 = InterfaceMethodref #59.#67        // com/zaxxer/nuprocess/codec/NuCharsetEncoderHandler.onEncoderError:(Ljava/nio/charset/CoderResult;)V
  #16 = Methodref          #46.#68        // java/nio/charset/CoderResult.isOverflow:()Z
  #17 = Methodref          #61.#69        // java/nio/charset/CharsetEncoder.flush:(Ljava/nio/ByteBuffer;)Ljava/nio/charset/CoderResult;
  #18 = Class              #70            // com/zaxxer/nuprocess/codec/NuCharsetEncoder
  #19 = Class              #71            // java/lang/Object
  #20 = Utf8               handler
  #21 = Utf8               Lcom/zaxxer/nuprocess/codec/NuCharsetEncoderHandler;
  #22 = Utf8               encoder
  #23 = Utf8               Ljava/nio/charset/CharsetEncoder;
  #24 = Utf8               charBuffer
  #25 = Utf8               Ljava/nio/CharBuffer;
  #26 = Utf8               <init>
  #27 = Utf8               (Lcom/zaxxer/nuprocess/codec/NuCharsetEncoderHandler;Ljava/nio/charset/Charset;)V
  #28 = Utf8               Code
  #29 = Utf8               LineNumberTable
  #30 = Utf8               LocalVariableTable
  #31 = Utf8               this
  #32 = Utf8               Lcom/zaxxer/nuprocess/codec/NuCharsetEncoder;
  #33 = Utf8               charset
  #34 = Utf8               Ljava/nio/charset/Charset;
  #35 = Utf8               (Lcom/zaxxer/nuprocess/codec/NuCharsetEncoderHandler;Ljava/nio/charset/CharsetEncoder;)V
  #36 = Utf8               onStdinReady
  #37 = Utf8               (Ljava/nio/ByteBuffer;)Z
  #38 = Utf8               flushResult
  #39 = Utf8               Ljava/nio/charset/CoderResult;
  #40 = Utf8               buffer
  #41 = Utf8               Ljava/nio/ByteBuffer;
  #42 = Utf8               endOfInput
  #43 = Utf8               Z
  #44 = Utf8               encoderResult
  #45 = Utf8               StackMapTable
  #46 = Class              #72            // java/nio/charset/CoderResult
  #47 = Utf8               SourceFile
  #48 = Utf8               NuCharsetEncoder.java
  #49 = Class              #73            // java/nio/charset/Charset
  #50 = NameAndType        #74:#75        // newEncoder:()Ljava/nio/charset/CharsetEncoder;
  #51 = NameAndType        #26:#35        // "<init>":(Lcom/zaxxer/nuprocess/codec/NuCharsetEncoderHandler;Ljava/nio/charset/CharsetEncoder;)V
  #52 = NameAndType        #26:#76        // "<init>":()V
  #53 = NameAndType        #20:#21        // handler:Lcom/zaxxer/nuprocess/codec/NuCharsetEncoderHandler;
  #54 = NameAndType        #22:#23        // encoder:Ljava/nio/charset/CharsetEncoder;
  #55 = Utf8               com/zaxxer/nuprocess/NuProcess
  #56 = Class              #77            // java/nio/CharBuffer
  #57 = NameAndType        #78:#79        // allocate:(I)Ljava/nio/CharBuffer;
  #58 = NameAndType        #24:#25        // charBuffer:Ljava/nio/CharBuffer;
  #59 = Class              #80            // com/zaxxer/nuprocess/codec/NuCharsetEncoderHandler
  #60 = NameAndType        #36:#81        // onStdinReady:(Ljava/nio/CharBuffer;)Z
  #61 = Class              #82            // java/nio/charset/CharsetEncoder
  #62 = NameAndType        #83:#84        // encode:(Ljava/nio/CharBuffer;Ljava/nio/ByteBuffer;Z)Ljava/nio/charset/CoderResult;
  #63 = Class              #85            // java/nio/ByteBuffer
  #64 = NameAndType        #86:#87        // flip:()Ljava/nio/ByteBuffer;
  #65 = NameAndType        #88:#89        // compact:()Ljava/nio/CharBuffer;
  #66 = NameAndType        #90:#91        // isError:()Z
  #67 = NameAndType        #92:#93        // onEncoderError:(Ljava/nio/charset/CoderResult;)V
  #68 = NameAndType        #94:#91        // isOverflow:()Z
  #69 = NameAndType        #95:#96        // flush:(Ljava/nio/ByteBuffer;)Ljava/nio/charset/CoderResult;
  #70 = Utf8               com/zaxxer/nuprocess/codec/NuCharsetEncoder
  #71 = Utf8               java/lang/Object
  #72 = Utf8               java/nio/charset/CoderResult
  #73 = Utf8               java/nio/charset/Charset
  #74 = Utf8               newEncoder
  #75 = Utf8               ()Ljava/nio/charset/CharsetEncoder;
  #76 = Utf8               ()V
  #77 = Utf8               java/nio/CharBuffer
  #78 = Utf8               allocate
  #79 = Utf8               (I)Ljava/nio/CharBuffer;
  #80 = Utf8               com/zaxxer/nuprocess/codec/NuCharsetEncoderHandler
  #81 = Utf8               (Ljava/nio/CharBuffer;)Z
  #82 = Utf8               java/nio/charset/CharsetEncoder
  #83 = Utf8               encode
  #84 = Utf8               (Ljava/nio/CharBuffer;Ljava/nio/ByteBuffer;Z)Ljava/nio/charset/CoderResult;
  #85 = Utf8               java/nio/ByteBuffer
  #86 = Utf8               flip
  #87 = Utf8               ()Ljava/nio/ByteBuffer;
  #88 = Utf8               compact
  #89 = Utf8               ()Ljava/nio/CharBuffer;
  #90 = Utf8               isError
  #91 = Utf8               ()Z
  #92 = Utf8               onEncoderError
  #93 = Utf8               (Ljava/nio/charset/CoderResult;)V
  #94 = Utf8               isOverflow
  #95 = Utf8               flush
  #96 = Utf8               (Ljava/nio/ByteBuffer;)Ljava/nio/charset/CoderResult;
{
  private final com.zaxxer.nuprocess.codec.NuCharsetEncoderHandler handler;
    descriptor: Lcom/zaxxer/nuprocess/codec/NuCharsetEncoderHandler;
    flags: (0x0012) ACC_PRIVATE, ACC_FINAL

  private final java.nio.charset.CharsetEncoder encoder;
    descriptor: Ljava/nio/charset/CharsetEncoder;
    flags: (0x0012) ACC_PRIVATE, ACC_FINAL

  private final java.nio.CharBuffer charBuffer;
    descriptor: Ljava/nio/CharBuffer;
    flags: (0x0012) ACC_PRIVATE, ACC_FINAL

  public com.zaxxer.nuprocess.codec.NuCharsetEncoder(com.zaxxer.nuprocess.codec.NuCharsetEncoderHandler, java.nio.charset.Charset);
    descriptor: (Lcom/zaxxer/nuprocess/codec/NuCharsetEncoderHandler;Ljava/nio/charset/Charset;)V
    flags: (0x0001) ACC_PUBLIC
    Code:
      stack=3, locals=3, args_size=3
         0: aload_0
         1: aload_1
         2: aload_2
         3: invokevirtual #1                  // Method java/nio/charset/Charset.newEncoder:()Ljava/nio/charset/CharsetEncoder;
         6: invokespecial #2                  // Method "<init>":(Lcom/zaxxer/nuprocess/codec/NuCharsetEncoderHandler;Ljava/nio/charset/CharsetEncoder;)V
         9: return
      LineNumberTable:
        line 56: 0
        line 57: 9
      LocalVariableTable:
        Start  Length  Slot  Name   Signature
            0      10     0  this   Lcom/zaxxer/nuprocess/codec/NuCharsetEncoder;
            0      10     1 handler   Lcom/zaxxer/nuprocess/codec/NuCharsetEncoderHandler;
            0      10     2 charset   Ljava/nio/charset/Charset;

  public com.zaxxer.nuprocess.codec.NuCharsetEncoder(com.zaxxer.nuprocess.codec.NuCharsetEncoderHandler, java.nio.charset.CharsetEncoder);
    descriptor: (Lcom/zaxxer/nuprocess/codec/NuCharsetEncoderHandler;Ljava/nio/charset/CharsetEncoder;)V
    flags: (0x0001) ACC_PUBLIC
    Code:
      stack=2, locals=3, args_size=3
         0: aload_0
         1: invokespecial #3                  // Method java/lang/Object."<init>":()V
         4: aload_0
         5: aload_1
         6: putfield      #4                  // Field handler:Lcom/zaxxer/nuprocess/codec/NuCharsetEncoderHandler;
         9: aload_0
        10: aload_2
        11: putfield      #5                  // Field encoder:Ljava/nio/charset/CharsetEncoder;
        14: aload_0
        15: ldc           #7                  // int 65536
        17: invokestatic  #8                  // Method java/nio/CharBuffer.allocate:(I)Ljava/nio/CharBuffer;
        20: putfield      #9                  // Field charBuffer:Ljava/nio/CharBuffer;
        23: return
      LineNumberTable:
        line 70: 0
        line 71: 4
        line 72: 9
        line 73: 14
        line 74: 23
      LocalVariableTable:
        Start  Length  Slot  Name   Signature
            0      24     0  this   Lcom/zaxxer/nuprocess/codec/NuCharsetEncoder;
            0      24     1 handler   Lcom/zaxxer/nuprocess/codec/NuCharsetEncoderHandler;
            0      24     2 encoder   Ljava/nio/charset/CharsetEncoder;

  public boolean onStdinReady(java.nio.ByteBuffer);
    descriptor: (Ljava/nio/ByteBuffer;)Z
    flags: (0x0001) ACC_PUBLIC
    Code:
      stack=4, locals=5, args_size=2
         0: aload_0
         1: getfield      #4                  // Field handler:Lcom/zaxxer/nuprocess/codec/NuCharsetEncoderHandler;
         4: aload_0
         5: getfield      #9                  // Field charBuffer:Ljava/nio/CharBuffer;
         8: invokeinterface #10,  2           // InterfaceMethod com/zaxxer/nuprocess/codec/NuCharsetEncoderHandler.onStdinReady:(Ljava/nio/CharBuffer;)Z
        13: ifne          20
        16: iconst_1
        17: goto          21
        20: iconst_0
        21: istore_2
        22: aload_0
        23: getfield      #5                  // Field encoder:Ljava/nio/charset/CharsetEncoder;
        26: aload_0
        27: getfield      #9                  // Field charBuffer:Ljava/nio/CharBuffer;
        30: aload_1
        31: iload_2
        32: invokevirtual #11                 // Method java/nio/charset/CharsetEncoder.encode:(Ljava/nio/CharBuffer;Ljava/nio/ByteBuffer;Z)Ljava/nio/charset/CoderResult;
        35: astore_3
        36: aload_1
        37: invokevirtual #12                 // Method java/nio/ByteBuffer.flip:()Ljava/nio/ByteBuffer;
        40: pop
        41: aload_0
        42: getfield      #9                  // Field charBuffer:Ljava/nio/CharBuffer;
        45: invokevirtual #13                 // Method java/nio/CharBuffer.compact:()Ljava/nio/CharBuffer;
        48: pop
        49: aload_3
        50: invokevirtual #14                 // Method java/nio/charset/CoderResult.isError:()Z
        53: ifeq          66
        56: aload_0
        57: getfield      #4                  // Field handler:Lcom/zaxxer/nuprocess/codec/NuCharsetEncoderHandler;
        60: aload_3
        61: invokeinterface #15,  2           // InterfaceMethod com/zaxxer/nuprocess/codec/NuCharsetEncoderHandler.onEncoderError:(Ljava/nio/charset/CoderResult;)V
        66: aload_3
        67: invokevirtual #16                 // Method java/nio/charset/CoderResult.isOverflow:()Z
        70: ifeq          75
        73: iconst_1
        74: ireturn
        75: iload_2
        76: ifeq          95
        79: aload_0
        80: getfield      #5                  // Field encoder:Ljava/nio/charset/CharsetEncoder;
        83: aload_1
        84: invokevirtual #17                 // Method java/nio/charset/CharsetEncoder.flush:(Ljava/nio/ByteBuffer;)Ljava/nio/charset/CoderResult;
        87: astore        4
        89: aload         4
        91: invokevirtual #16                 // Method java/nio/charset/CoderResult.isOverflow:()Z
        94: ireturn
        95: iconst_1
        96: ireturn
      LineNumberTable:
        line 88: 0
        line 89: 22
        line 90: 36
        line 91: 41
        line 92: 49
        line 93: 56
        line 95: 66
        line 96: 73
        line 98: 75
        line 99: 79
        line 100: 89
        line 103: 95
      LocalVariableTable:
        Start  Length  Slot  Name   Signature
           89       6     4 flushResult   Ljava/nio/charset/CoderResult;
            0      97     0  this   Lcom/zaxxer/nuprocess/codec/NuCharsetEncoder;
            0      97     1 buffer   Ljava/nio/ByteBuffer;
           22      75     2 endOfInput   Z
           36      61     3 encoderResult   Ljava/nio/charset/CoderResult;
      StackMapTable: number_of_entries = 5
        frame_type = 20 /* same */
        frame_type = 64 /* same_locals_1_stack_item */
          stack = [ int ]
        frame_type = 253 /* append */
          offset_delta = 44
          locals = [ int, class java/nio/charset/CoderResult ]
        frame_type = 8 /* same */
        frame_type = 19 /* same */
}
SourceFile: "NuCharsetEncoder.java"
