Classfile /Users/mw/Projects/slang-braindump/.jar/jar8/assemble/slang-braindump/assemble/content/coursier/error/CoursierError.class
  Last modified May 29, 2022; size 1406 bytes
  SHA-256 checksum acdbf77474a5bc217524557097f77e6a10bf1a0bc0c3f5e7b0eb28c858a57e28
  Compiled from "CoursierError.scala"
public abstract class coursier.error.CoursierError extends java.lang.Exception
  minor version: 0
  major version: 52
  flags: (0x0421) ACC_PUBLIC, ACC_SUPER, ACC_ABSTRACT
  this_class: #2                          // coursier/error/CoursierError
  super_class: #4                         // java/lang/Exception
  interfaces: 0, fields: 0, methods: 2, attributes: 4
Constant pool:
   #1 = Utf8               coursier/error/CoursierError
   #2 = Class              #1             // coursier/error/CoursierError
   #3 = Utf8               java/lang/Exception
   #4 = Class              #3             // java/lang/Exception
   #5 = Utf8               CoursierError.scala
   #6 = Utf8               Lscala/reflect/ScalaSignature;
   #7 = Utf8               bytes
   #8 = Utf8               \u0006\u0005U3Q!\u0003\u0006\u0002\u0002=A\u0001B\b\u0001\u0003\u0002\u0003\u0006Ia\b\u0005\tO\u0001\u0011\t\u0011)A\u0005Q!)1\u0006\u0001C\u0001Y\u001d9\u0011GCA\u0001\u0012\u0003\u0011daB\u0005\u000b\u0003\u0003E\ta\r\u0005\u0006W\u0015!\t\u0001\u0011\u0005\b\u0003\u0016\t\n\u0011\"\u0001C\u0011\u001diU!!A\u0005\n9\u0013QbQ8veNLWM]#se>\u0014(BA\u0006\r\u0003\u0015)\'O]8s\u0015\u0005i\u0011\u0001C2pkJ\u001c\u0018.\u001a:\u0004\u0001M\u0011\u0001\u0001\u0005\t\u0003#mq!A\u0005\r\u000f\u0005M1R\"\u0001\u000b\u000b\u0005Uq\u0011A\u0002\u001fs_>$h(C\u0001\u0018\u0003\u0015\u00198-\u00197b\u0013\tI\"$A\u0004qC\u000e\\\u0017mZ3\u000b\u0003]I!\u0001H\u000f\u0003\u0013\u0015C8-\u001a9uS>t\'BA\r\u001b\u0003\u001diWm]:bO\u0016\u0004\"\u0001\t\u0013\u000f\u0005\u0005\u0012\u0003CA\n\u001b\u0013\t\u0019#$\u0001\u0004Qe\u0016$WMZ\u0005\u0003K\u0019\u0012aa\u0015;sS:<\'BA\u0012\u001b\u0003\u0015\u0019\u0017-^:f!\t\t\u0012&\u0003\u0002+;\tIA\u000b\u001b:po\u0006\u0014G.Z\u0001\u0007y%t\u0017\u000e\u001e \u0015\u00075z\u0003\u0007\u0005\u0002/\u00015\t!\u0002C\u0003\u001f\u0007\u0001\u0007q\u0004C\u0004(\u0007A\u0005\t\u0019\u0001\u0015\u0002\u001b\r{WO]:jKJ,%O]8s!\tqSaE\u0002\u0006ia\u0002\"!\u000e\u001c\u000e\u0003iI!a\u000e\u000e\u0003\r\u0005s\u0017PU3g!\tId(D\u0001;\u0015\tYD(\u0001\u0002j_*\tQ(\u0001\u0003kCZ\f\u0017BA ;\u00051\u0019VM]5bY&T\u0018M\u00197f)\u0005\u0011\u0014a\u0007\u0013mKN\u001c\u0018N\\5uI\u001d\u0014X-\u0019;fe\u0012\"WMZ1vYR$#\'F\u0001DU\tACiK\u0001F!\t15*D\u0001H\u0015\tA\u0015*A\u0005v]\u000eDWmY6fI*\u0011!JG\u0001\u000bC:tw\u000e^1uS>t\u0017B\u0001\'H\u0005E)hn\u00195fG.,GMV1sS\u0006t7-Z\u0001\roJLG/\u001a*fa2\f7-\u001a\u000b\u0002\u001fB\u0011\u0001kU\u0007\u0002#*\u0011!\u000bP\u0001\u0005Y\u0006tw-\u0003\u0002U#\n1qJ\u00196fGR\u0004
   #9 = Utf8               $lessinit$greater$default$2
  #10 = Utf8               ()Ljava/lang/Throwable;
  #11 = Utf8               coursier/error/CoursierError$
  #12 = Class              #11            // coursier/error/CoursierError$
  #13 = Utf8               MODULE$
  #14 = Utf8               Lcoursier/error/CoursierError$;
  #15 = NameAndType        #13:#14        // MODULE$:Lcoursier/error/CoursierError$;
  #16 = Fieldref           #12.#15        // coursier/error/CoursierError$.MODULE$:Lcoursier/error/CoursierError$;
  #17 = NameAndType        #9:#10         // $lessinit$greater$default$2:()Ljava/lang/Throwable;
  #18 = Methodref          #12.#17        // coursier/error/CoursierError$.$lessinit$greater$default$2:()Ljava/lang/Throwable;
  #19 = Utf8               <init>
  #20 = Utf8               (Ljava/lang/String;Ljava/lang/Throwable;)V
  #21 = Utf8               message
  #22 = Utf8               cause
  #23 = NameAndType        #19:#20        // "<init>":(Ljava/lang/String;Ljava/lang/Throwable;)V
  #24 = Methodref          #4.#23         // java/lang/Exception."<init>":(Ljava/lang/String;Ljava/lang/Throwable;)V
  #25 = Utf8               this
  #26 = Utf8               Lcoursier/error/CoursierError;
  #27 = Utf8               Ljava/lang/String;
  #28 = Utf8               Ljava/lang/Throwable;
  #29 = Utf8               Code
  #30 = Utf8               LineNumberTable
  #31 = Utf8               LocalVariableTable
  #32 = Utf8               MethodParameters
  #33 = Utf8               SourceFile
  #34 = Utf8               RuntimeVisibleAnnotations
  #35 = Utf8               ScalaInlineInfo
  #36 = Utf8               ScalaSig
{
  public static java.lang.Throwable $lessinit$greater$default$2();
    descriptor: ()Ljava/lang/Throwable;
    flags: (0x0009) ACC_PUBLIC, ACC_STATIC
    Code:
      stack=1, locals=0, args_size=0
         0: getstatic     #16                 // Field coursier/error/CoursierError$.MODULE$:Lcoursier/error/CoursierError$;
         3: invokevirtual #18                 // Method coursier/error/CoursierError$.$lessinit$greater$default$2:()Ljava/lang/Throwable;
         6: areturn

  public coursier.error.CoursierError(java.lang.String, java.lang.Throwable);
    descriptor: (Ljava/lang/String;Ljava/lang/Throwable;)V
    flags: (0x0001) ACC_PUBLIC
    Code:
      stack=3, locals=3, args_size=3
         0: aload_0
         1: aload_1
         2: aload_2
         3: invokespecial #24                 // Method java/lang/Exception."<init>":(Ljava/lang/String;Ljava/lang/Throwable;)V
         6: return
      LineNumberTable:
        line 4: 0
      LocalVariableTable:
        Start  Length  Slot  Name   Signature
            0       7     0  this   Lcoursier/error/CoursierError;
            0       7     1 message   Ljava/lang/String;
            0       7     2 cause   Ljava/lang/Throwable;
    MethodParameters:
      Name                           Flags
      message                        final
      cause                          final
}
SourceFile: "CoursierError.scala"
RuntimeVisibleAnnotations:
  0: #6(#7=s#8)
    scala.reflect.ScalaSignature(
      bytes="\u0006\u0005U3Q!\u0003\u0006\u0002\u0002=A\u0001B\b\u0001\u0003\u0002\u0003\u0006Ia\b\u0005\tO\u0001\u0011\t\u0011)A\u0005Q!)1\u0006\u0001C\u0001Y\u001d9\u0011GCA\u0001\u0012\u0003\u0011daB\u0005\u000b\u0003\u0003E\ta\r\u0005\u0006W\u0015!\t\u0001\u0011\u0005\b\u0003\u0016\t\n\u0011\"\u0001C\u0011\u001diU!!A\u0005\n9\u0013QbQ8veNLWM]#se>\u0014(BA\u0006\r\u0003\u0015)\'O]8s\u0015\u0005i\u0011\u0001C2pkJ\u001c\u0018.\u001a:\u0004\u0001M\u0011\u0001\u0001\u0005\t\u0003#mq!A\u0005\r\u000f\u0005M1R\"\u0001\u000b\u000b\u0005Uq\u0011A\u0002\u001fs_>$h(C\u0001\u0018\u0003\u0015\u00198-\u00197b\u0013\tI\"$A\u0004qC\u000e\\\u0017mZ3\u000b\u0003]I!\u0001H\u000f\u0003\u0013\u0015C8-\u001a9uS>t\'BA\r\u001b\u0003\u001diWm]:bO\u0016\u0004\"\u0001\t\u0013\u000f\u0005\u0005\u0012\u0003CA\n\u001b\u0013\t\u0019#$\u0001\u0004Qe\u0016$WMZ\u0005\u0003K\u0019\u0012aa\u0015;sS:<\'BA\u0012\u001b\u0003\u0015\u0019\u0017-^:f!\t\t\u0012&\u0003\u0002+;\tIA\u000b\u001b:po\u0006\u0014G.Z\u0001\u0007y%t\u0017\u000e\u001e \u0015\u00075z\u0003\u0007\u0005\u0002/\u00015\t!\u0002C\u0003\u001f\u0007\u0001\u0007q\u0004C\u0004(\u0007A\u0005\t\u0019\u0001\u0015\u0002\u001b\r{WO]:jKJ,%O]8s!\tqSaE\u0002\u0006ia\u0002\"!\u000e\u001c\u000e\u0003iI!a\u000e\u000e\u0003\r\u0005s\u0017PU3g!\tId(D\u0001;\u0015\tYD(\u0001\u0002j_*\tQ(\u0001\u0003kCZ\f\u0017BA ;\u00051\u0019VM]5bY&T\u0018M\u00197f)\u0005\u0011\u0014a\u0007\u0013mKN\u001c\u0018N\\5uI\u001d\u0014X-\u0019;fe\u0012\"WMZ1vYR$#\'F\u0001DU\tACiK\u0001F!\t15*D\u0001H\u0015\tA\u0015*A\u0005v]\u000eDWmY6fI*\u0011!JG\u0001\u000bC:tw\u000e^1uS>t\u0017B\u0001\'H\u0005E)hn\u00195fG.,GMV1sS\u0006t7-Z\u0001\roJLG/\u001a*fa2\f7-\u001a\u000b\u0002\u001fB\u0011\u0001kU\u0007\u0002#*\u0011!\u000bP\u0001\u0005Y\u0006tw-\u0003\u0002U#\n1qJ\u00196fGR\u0004"
    )
  ScalaInlineInfo: length = 0x9 (unknown attribute)
   01 00 00 01 00 13 00 14 00
  ScalaSig: length = 0x3 (unknown attribute)
   05 02 00
