Classfile /Users/mw/Projects/slang-braindump/.jar/jar8/assemble/slang-braindump/assemble/content/coursier/error/FetchError$DownloadingArtifacts$$anonfun$$lessinit$greater$2.class
  Last modified May 29, 2022; size 1496 bytes
  SHA-256 checksum 084bc726e3df456f7d1847e59d07489aec28519cf67bbbade1f2bbdfab5bac55
  Compiled from "FetchError.scala"
public final class coursier.error.FetchError$DownloadingArtifacts$$anonfun$$lessinit$greater$2 extends scala.runtime.AbstractFunction1<scala.Tuple2<coursier.util.Artifact, coursier.cache.ArtifactError>, coursier.cache.ArtifactError> implements java.io.Serializable
  minor version: 0
  major version: 52
  flags: (0x0031) ACC_PUBLIC, ACC_FINAL, ACC_SUPER
  this_class: #2                          // coursier/error/FetchError$DownloadingArtifacts$$anonfun$$lessinit$greater$2
  super_class: #5                         // scala/runtime/AbstractFunction1
  interfaces: 1, fields: 1, methods: 3, attributes: 6
Constant pool:
   #1 = Utf8               coursier/error/FetchError$DownloadingArtifacts$$anonfun$$lessinit$greater$2
   #2 = Class              #1             // coursier/error/FetchError$DownloadingArtifacts$$anonfun$$lessinit$greater$2
   #3 = Utf8               Lscala/runtime/AbstractFunction1<Lscala/Tuple2<Lcoursier/util/Artifact;Lcoursier/cache/ArtifactError;>;Lcoursier/cache/ArtifactError;>;Ljava/io/Serializable;
   #4 = Utf8               scala/runtime/AbstractFunction1
   #5 = Class              #4             // scala/runtime/AbstractFunction1
   #6 = Utf8               java/io/Serializable
   #7 = Class              #6             // java/io/Serializable
   #8 = Utf8               FetchError.scala
   #9 = Utf8               coursier/error/FetchError$DownloadingArtifacts
  #10 = Class              #9             // coursier/error/FetchError$DownloadingArtifacts
  #11 = Utf8               <init>
  #12 = Utf8               (Lscala/collection/immutable/Seq;)V
  #13 = NameAndType        #11:#12        // "<init>":(Lscala/collection/immutable/Seq;)V
  #14 = Utf8               coursier/error/FetchError
  #15 = Class              #14            // coursier/error/FetchError
  #16 = Utf8               DownloadingArtifacts
  #17 = Utf8               serialVersionUID
  #18 = Utf8               J
  #19 = Long               0l
  #21 = Utf8               apply
  #22 = Utf8               (Lscala/Tuple2;)Lcoursier/cache/ArtifactError;
  #23 = Utf8               (Lscala/Tuple2<Lcoursier/util/Artifact;Lcoursier/cache/ArtifactError;>;)Lcoursier/cache/ArtifactError;
  #24 = Utf8               x$1
  #25 = Utf8               scala/Tuple2
  #26 = Class              #25            // scala/Tuple2
  #27 = Utf8               _2
  #28 = Utf8               ()Ljava/lang/Object;
  #29 = NameAndType        #27:#28        // _2:()Ljava/lang/Object;
  #30 = Methodref          #26.#29        // scala/Tuple2._2:()Ljava/lang/Object;
  #31 = Utf8               coursier/cache/ArtifactError
  #32 = Class              #31            // coursier/cache/ArtifactError
  #33 = Utf8               this
  #34 = Utf8               Lcoursier/error/FetchError$DownloadingArtifacts$$anonfun$$lessinit$greater$2;
  #35 = Utf8               Lscala/Tuple2;
  #36 = Utf8               (Ljava/lang/Object;)Ljava/lang/Object;
  #37 = Utf8               v1
  #38 = NameAndType        #21:#22        // apply:(Lscala/Tuple2;)Lcoursier/cache/ArtifactError;
  #39 = Methodref          #2.#38         // coursier/error/FetchError$DownloadingArtifacts$$anonfun$$lessinit$greater$2.apply:(Lscala/Tuple2;)Lcoursier/cache/ArtifactError;
  #40 = Utf8               Ljava/lang/Object;
  #41 = Utf8               ()V
  #42 = NameAndType        #11:#41        // "<init>":()V
  #43 = Methodref          #5.#42         // scala/runtime/AbstractFunction1."<init>":()V
  #44 = Utf8               ConstantValue
  #45 = Utf8               Code
  #46 = Utf8               LineNumberTable
  #47 = Utf8               LocalVariableTable
  #48 = Utf8               Signature
  #49 = Utf8               MethodParameters
  #50 = Utf8               InnerClasses
  #51 = Utf8               EnclosingMethod
  #52 = Utf8               SourceFile
  #53 = Utf8               ScalaInlineInfo
  #54 = Utf8               Scala
{
  private static final long serialVersionUID;
    descriptor: J
    flags: (0x001a) ACC_PRIVATE, ACC_STATIC, ACC_FINAL
    ConstantValue: long 0l

  public final coursier.cache.ArtifactError apply(scala.Tuple2<coursier.util.Artifact, coursier.cache.ArtifactError>);
    descriptor: (Lscala/Tuple2;)Lcoursier/cache/ArtifactError;
    flags: (0x0011) ACC_PUBLIC, ACC_FINAL
    Code:
      stack=1, locals=2, args_size=2
         0: aload_1
         1: invokevirtual #30                 // Method scala/Tuple2._2:()Ljava/lang/Object;
         4: checkcast     #32                 // class coursier/cache/ArtifactError
         7: areturn
      LineNumberTable:
        line 13: 0
      LocalVariableTable:
        Start  Length  Slot  Name   Signature
            0       8     0  this   Lcoursier/error/FetchError$DownloadingArtifacts$$anonfun$$lessinit$greater$2;
            0       8     1   x$1   Lscala/Tuple2;
    Signature: #23                          // (Lscala/Tuple2<Lcoursier/util/Artifact;Lcoursier/cache/ArtifactError;>;)Lcoursier/cache/ArtifactError;
    MethodParameters:
      Name                           Flags
      x$1                            final

  public final java.lang.Object apply(java.lang.Object);
    descriptor: (Ljava/lang/Object;)Ljava/lang/Object;
    flags: (0x1051) ACC_PUBLIC, ACC_FINAL, ACC_BRIDGE, ACC_SYNTHETIC
    Code:
      stack=2, locals=2, args_size=2
         0: aload_0
         1: aload_1
         2: checkcast     #26                 // class scala/Tuple2
         5: invokevirtual #39                 // Method apply:(Lscala/Tuple2;)Lcoursier/cache/ArtifactError;
         8: areturn
      LineNumberTable:
        line 13: 0
      LocalVariableTable:
        Start  Length  Slot  Name   Signature
            0       9     0  this   Lcoursier/error/FetchError$DownloadingArtifacts$$anonfun$$lessinit$greater$2;
            0       9     1    v1   Ljava/lang/Object;
    MethodParameters:
      Name                           Flags
      v1                             final

  public coursier.error.FetchError$DownloadingArtifacts$$anonfun$$lessinit$greater$2();
    descriptor: ()V
    flags: (0x0001) ACC_PUBLIC
    Code:
      stack=1, locals=1, args_size=1
         0: aload_0
         1: invokespecial #43                 // Method scala/runtime/AbstractFunction1."<init>":()V
         4: return
      LineNumberTable:
        line 13: 0
      LocalVariableTable:
        Start  Length  Slot  Name   Signature
            0       5     0  this   Lcoursier/error/FetchError$DownloadingArtifacts$$anonfun$$lessinit$greater$2;
}
InnerClasses:
  public static final #16= #10 of #15;    // DownloadingArtifacts=class coursier/error/FetchError$DownloadingArtifacts of class coursier/error/FetchError
  public final #2;                        // class coursier/error/FetchError$DownloadingArtifacts$$anonfun$$lessinit$greater$2
EnclosingMethod: #10.#13                // coursier.error.FetchError$DownloadingArtifacts.<init>
Signature: #3                           // Lscala/runtime/AbstractFunction1<Lscala/Tuple2<Lcoursier/util/Artifact;Lcoursier/cache/ArtifactError;>;Lcoursier/cache/ArtifactError;>;Ljava/io/Serializable;
SourceFile: "FetchError.scala"
  ScalaInlineInfo: length = 0x13 (unknown attribute)
   01 01 00 03 00 0B 00 29 01 00 15 00 24 01 00 15
   00 16 01
  Scala: length = 0x0 (unknown attribute)

