Classfile /Users/mw/Projects/slang-braindump/.jar/jar8/assemble/slang-braindump/assemble/content/coursier/error/ResolutionError.class
  Last modified May 29, 2022; size 4307 bytes
  SHA-256 checksum 6f882940b25b5add53a472fa600eb31c2a60d8d4a8b9637407dba74b0028034d
  Compiled from "ResolutionError.scala"
public abstract class coursier.error.ResolutionError extends coursier.error.CoursierError
  minor version: 0
  major version: 52
  flags: (0x0421) ACC_PUBLIC, ACC_SUPER, ACC_ABSTRACT
  this_class: #2                          // coursier/error/ResolutionError
  super_class: #4                         // coursier/error/CoursierError
  interfaces: 0, fields: 1, methods: 5, attributes: 5
Constant pool:
   #1 = Utf8               coursier/error/ResolutionError
   #2 = Class              #1             // coursier/error/ResolutionError
   #3 = Utf8               coursier/error/CoursierError
   #4 = Class              #3             // coursier/error/CoursierError
   #5 = Utf8               ResolutionError.scala
   #6 = Utf8               Lscala/reflect/ScalaSignature;
   #7 = Utf8               bytes
   #8 = Utf8               \u0006\u0005\u0005Uh!\u0002\u001d:\u0003Cq\u0004\u0002C\"\u0001\u0005\u000b\u0007I\u0011\u0001#\t\u0011-\u0003!\u0011!Q\u0001\n\u0015C\u0001\u0002\u0014\u0001\u0003\u0002\u0003\u0006I!\u0014\u0005\t5\u0002\u0011\t\u0011)A\u00057\")A\r\u0001C\u0001K\")!\u000e\u0001D\u0001W\u001e)\u0011/\u000fE\u0001e\u001a)\u0001(\u000fE\u0001g\"1A\r\u0003C\u0001\u0003\u00031a!a\u0001\t\u0005\u0005\u0015\u0001\"C\"\u000b\u0005\u0003\u0005\u000b\u0011B#\u0002\u0011\u0019!\'\u0002\"\u0001\u0002\u0016\u001a1\u0011\u0011\u0004\u0005\u0003\u00037A\u0011bQ\u0007\u0003\u0002\u0003\u0006I!R\u0001\t\u0015\u0005uQB!b\u0001\n\u0003\ty\u0002\u0003\u0006\u0002(5\u0011\t\u0011)A\u0005\u0003CA!\"!\u000b\u000e\u0005\u000b\u0007I\u0011AA\u0016\u0011%\ti#\u0004B\u0001B\u0003%Q\n\u0003\u0006\u000205\u0011)\u0019!C\u0001\u0003cA!\"!\u000e\u000e\u0005\u0003\u0005\u000b\u0011BA\u001a\u0011\u0019!W\u0002\"\u0001\u00028\u00191\u00111\t\u0005\u0003\u0003\u000bB\u0011b\u0011\f\u0003\u0002\u0003\u0006I!R\u0001\t\u0015\u0005\u001dcC!b\u0001\n\u0003\tI\u0005\u0003\u0006\u0002XY\u0011\t\u0011)A\u0005\u0003\u0017Ba\u0001\u001a\f\u0005\u0002\u0005ecaBA\u0006\u0011\u0005\u0005\u0012Q\u0002\u0005\n\u0007n\u0011\t\u0011)A\u0005\u000b\u0006A\u0001\u0002T\u000e\u0003\u0002\u0003\u0006I!\u0014\u0005\t5n\u0011\t\u0011)A\u00057\"1Am\u0007C\u0001\u0003\u001fAQA[\u000e\u0005\u0002-<\u0011\"a\'\t\u0003\u0003E\t!!(\u0007\u0013\u0005-\u0001\"!A\t\u0002\u0005}\u0005B\u00023#\t\u0003\t\t\u000bC\u0005\u0002$\n\n\n\u0011\"\u0001\u0002&\"I\u00111\u0018\u0012\u0002\u0002\u0013%\u0011Q\u0018\u0004\u0007\u0003\u0017D!!!4\t\u0015\u0005=gE!b\u0001\n\u0003\t\t\u000e\u0003\u0006\u0002T\u001a\u0012\t\u0011)A\u0005\u0003\u000fA!\"!6\'\u0005\u000b\u0007I\u0011AAl\u0011)\tYN\nB\u0001B\u0003%\u0011\u0011\u001c\u0005\u0007I\u001a\"\t!!8\t\u000b)4C\u0011A6\t\u000f\u0005\u0015\b\u0002\"\u0001\u0002h\u001a9\u0011\u0011\r\u0005\u0002\u0002\u0005\r\u0004\"C\"/\u0005\u0003\u0005\u000b\u0011B#\u0002\u0011)\t)G\fBC\u0002\u0013\u0005\u0011q\r\u0005\u000b\u0003or#\u0011!Q\u0001\n\u0005%\u0004BCA=]\t\u0015\r\u0011\"\u0001\u0002|!Q\u0011q\u0011\u0018\u0003\u0002\u0003\u0006I!! \t\u00111s#\u0011!Q\u0001\n5Ca\u0001\u001a\u0018\u0005\u0002\u0005%\u0005\"CAR\u0011E\u0005I\u0011AAS\u0011%\tY\fCA\u0001\n\u0013\tiLA\bSKN|G.\u001e;j_:,%O]8s\u0015\tQ4(A\u0003feJ|\'OC\u0001=\u0003!\u0019w.\u001e:tS\u0016\u00148\u0001A\n\u0003\u0001}\u0002\"\u0001Q!\u000e\u0003eJ!AQ\u001d\u0003\u001b\r{WO]:jKJ,%O]8s\u0003)\u0011Xm]8mkRLwN\\\u000b\u0002\u000bB\u0011a)S\u0007\u0002\u000f*\u0011\u0001jO\u0001\u0005G>\u0014X-\u0003\u0002K\u000f\nQ!+Z:pYV$\u0018n\u001c8\u0002\u0017I,7o\u001c7vi&|g\u000eI\u0001\b[\u0016\u001c8/Y4f!\tquK\u0004\u0002P+B\u0011\u0001kU\u0007\u0002#*\u0011!+P\u0001\u0007yI|w\u000e\u001e \u000b\u0003Q\u000bQa]2bY\u0006L!AV*\u0002\rA\u0013X\rZ3g\u0013\tA\u0016L\u0001\u0004TiJLgn\u001a\u0006\u0003-N\u000bQaY1vg\u0016\u0004\"\u0001X1\u000f\u0005u{fB\u0001)_\u0013\u0005!\u0016B\u00011T\u0003\u001d\u0001\u0018mY6bO\u0016L!AY2\u0003\u0013QC\'o\\<bE2,\'B\u00011T\u0003\u0019a\u0014N\\5u}Q!am\u001a5j!\t\u0001\u0005\u0001C\u0003D\u000b\u0001\u0007Q\tC\u0003M\u000b\u0001\u0007Q\nC\u0004[\u000bA\u0005\t\u0019A.\u0002\r\u0015\u0014(o\u001c:t+\u0005a\u0007c\u0001/n_&\u0011an\u0019\u0002\u0004\'\u0016\f\bC\u00019\u001c\u001d\t\u0001u!A\bSKN|G.\u001e;j_:,%O]8s!\t\u0001\u0005bE\u0002\tib\u0004\"!\u001e<\u000e\u0003MK!a^*\u0003\r\u0005s\u0017PU3g!\tIh0D\u0001{\u0015\tYH0\u0001\u0002j_*\tQ0\u0001\u0003kCZ\f\u0017BA@{\u00051\u0019VM]5bY&T\u0018M\u00197f)\u0005\u0011(aF\'bq&lW/\\%uKJ\fG/[8o%\u0016\f7\r[3e\'\rQ\u0011q\u0001\t\u0004\u0003\u0013YR\"\u0001\u0005\u0003\rMKW\u000e\u001d7f\'\tYb\r\u0006\u0005\u0002\b\u0005E\u00111CA\u000b\u0011\u0015\u0019u\u00041\u0001F\u0011\u0015au\u00041\u0001N\u0011\u001dQv\u0004%AA\u0002mKSaG\u0007\u0017\u00159\u0012!cQ1oi\u0012{wO\u001c7pC\u0012lu\u000eZ;mKN\u0019Q\"a\u0002\u0002\r5|G-\u001e7f+\t\t\t\u0003E\u0002G\u0003GI1!!\nH\u0005\u0019iu\u000eZ;mK\u00069Qn\u001c3vY\u0016\u0004\u0013a\u0002<feNLwN\\\u000b\u0002\u001b\u0006Aa/\u001a:tS>t\u0007%A\nqKJ\u0014V\r]8tSR|\'/_#se>\u00148/\u0006\u0002\u00024A\u0019A,\\\'\u0002)A,\'OU3q_NLGo\u001c:z\u000bJ\u0014xN]:!))\tI$a\u000f\u0002>\u0005}\u0012\u0011\t\t\u0004\u0003\u0013i\u0001\"B\"\u0016\u0001\u0004)\u0005bBA\u000f+\u0001\u0007\u0011\u0011\u0005\u0005\u0007\u0003S)\u0002\u0019A\'\t\u000f\u0005=R\u00031\u0001\u00024\t92i\u001c8gY&\u001cG/\u001b8h\t\u0016\u0004XM\u001c3f]\u000eLWm]\n\u0004-\u0005\u001d\u0011\u0001\u00043fa\u0016tG-\u001a8dS\u0016\u001cXCAA&!\u0015q\u0015QJA)\u0013\r\ty%\u0017\u0002\u0004\'\u0016$\bc\u0001$\u0002T%\u0019\u0011QK$\u0003\u0015\u0011+\u0007/\u001a8eK:\u001c\u00170A\u0007eKB,g\u000eZ3oG&,7\u000f\t\u000b\u0007\u00037\ni&a\u0018\u0011\u0007\u0005%a\u0003C\u0003D5\u0001\u0007Q\tC\u0004\u0002Hi\u0001\r!a\u0013\u0003#Us7/\u0019;jg\u001aL\u0017M\u00197f%VdWmE\u0002/\u0003\u000f\tAA];mKV\u0011\u0011\u0011\u000e\t\u0005\u0003W\n\u0019(\u0004\u0002\u0002n)!\u0011QMA8\u0015\r\t\thO\u0001\u0007a\u0006\u0014\u0018-\\:\n\t\u0005U\u0014Q\u000e\u0002\u0005%VdW-A\u0003sk2,\u0007%\u0001\u0005d_:4G.[2u+\t\ti\b\u0005\u0003\u0002\u0000\u0005\rUBAAA\u0015\r\tI(O\u0005\u0005\u0003\u000b\u000b\tIA\bV]N\fG/[:gS\u0016$\'+\u001e7f\u0003%\u0019wN\u001c4mS\u000e$\b\u0005\u0006\u0006\u0002\f\u00065\u0015qRAI\u0003\'\u00032!!\u0003/\u0011\u0015\u0019U\u00071\u0001F\u0011\u001d\t)\'\u000ea\u0001\u0003SBq!!\u001f6\u0001\u0004\ti\bC\u0003Mk\u0001\u0007Q\n\u0006\u0003\u0002\u0018\u0006e\u0005cAA\u0005\u0015!)1\t\u0004a\u0001\u000b\u000611+[7qY\u0016\u00042!!\u0003#\'\r\u0011C\u000f\u001f\u000b\u0003\u0003;\u000b1\u0004\n7fgNLg.\u001b;%OJ,\u0017\r^3sI\u0011,g-Y;mi\u0012\u001aTCAATU\rY\u0016\u0011V\u0016\u0003\u0003W\u0003B!!,\u000286\u0011\u0011q\u0016\u0006\u0005\u0003c\u000b\u0019,A\u0005v]\u000eDWmY6fI*\u0019\u0011QW*\u0002\u0015\u0005tgn\u001c;bi&|g.\u0003\u0003\u0002:\u0006=&!E;oG\",7m[3e-\u0006\u0014\u0018.\u00198dK\u0006aqO]5uKJ+\u0007\u000f\\1dKR\u0011\u0011q\u0018\t\u0005\u0003\u0003\f9-\u0004\u0002\u0002D*\u0019\u0011Q\u0019?\u0002\t1\fgnZ\u0005\u0005\u0003\u0013\f\u0019M\u0001\u0004PE*,7\r\u001e\u0002\b\'\u00164XM]1m\'\t1c-\u0001\u0003iK\u0006$WCAA\u0004\u0003\u0015AW-\u00193!\u0003\u0011!\u0018-\u001b7\u0016\u0005\u0005e\u0007\u0003\u0002/n\u0003\u000f\tQ\u0001^1jY\u0002\"b!a8\u0002b\u0006\r\bcAA\u0005M!9\u0011qZ\u0016A\u0002\u0005\u001d\u0001bBAkW\u0001\u0007\u0011\u0011\\\u0001\u0005MJ|W\u000eF\u0003g\u0003S\fY\u000f\u0003\u0004\u0002P6\u0002\rA\u001a\u0005\b\u0003+l\u0003\u0019AAw!\u0011)\u0018q\u001e4\n\u0007\u0005E8K\u0001\u0006=e\u0016\u0004X-\u0019;fIzJ3\u0001\u0001\u0014\u001c\u0001
   #9 = Utf8               coursier/error/ResolutionError$CantDownloadModule
  #10 = Class              #9             // coursier/error/ResolutionError$CantDownloadModule
  #11 = Utf8               CantDownloadModule
  #12 = Utf8               coursier/error/ResolutionError$ConflictingDependencies
  #13 = Class              #12            // coursier/error/ResolutionError$ConflictingDependencies
  #14 = Utf8               ConflictingDependencies
  #15 = Utf8               coursier/error/ResolutionError$MaximumIterationReached
  #16 = Class              #15            // coursier/error/ResolutionError$MaximumIterationReached
  #17 = Utf8               MaximumIterationReached
  #18 = Utf8               coursier/error/ResolutionError$Several
  #19 = Class              #18            // coursier/error/ResolutionError$Several
  #20 = Utf8               Several
  #21 = Utf8               coursier/error/ResolutionError$Simple
  #22 = Class              #21            // coursier/error/ResolutionError$Simple
  #23 = Utf8               Simple
  #24 = Utf8               coursier/error/ResolutionError$Simple$
  #25 = Class              #24            // coursier/error/ResolutionError$Simple$
  #26 = Utf8
  #27 = Utf8               coursier/error/ResolutionError$UnsatisfiableRule
  #28 = Class              #27            // coursier/error/ResolutionError$UnsatisfiableRule
  #29 = Utf8               UnsatisfiableRule
  #30 = Utf8               resolution
  #31 = Utf8               Lcoursier/core/Resolution;
  #32 = Utf8               $lessinit$greater$default$3
  #33 = Utf8               ()Ljava/lang/Throwable;
  #34 = Utf8               coursier/error/ResolutionError$
  #35 = Class              #34            // coursier/error/ResolutionError$
  #36 = Utf8               MODULE$
  #37 = Utf8               Lcoursier/error/ResolutionError$;
  #38 = NameAndType        #36:#37        // MODULE$:Lcoursier/error/ResolutionError$;
  #39 = Fieldref           #35.#38        // coursier/error/ResolutionError$.MODULE$:Lcoursier/error/ResolutionError$;
  #40 = NameAndType        #32:#33        // $lessinit$greater$default$3:()Ljava/lang/Throwable;
  #41 = Methodref          #35.#40        // coursier/error/ResolutionError$.$lessinit$greater$default$3:()Ljava/lang/Throwable;
  #42 = Utf8               from
  #43 = Utf8               (Lcoursier/error/ResolutionError;Lscala/collection/immutable/Seq;)Lcoursier/error/ResolutionError;
  #44 = Utf8               (Lcoursier/error/ResolutionError;Lscala/collection/immutable/Seq<Lcoursier/error/ResolutionError;>;)Lcoursier/error/ResolutionError;
  #45 = Utf8               head
  #46 = Utf8               tail
  #47 = NameAndType        #42:#43        // from:(Lcoursier/error/ResolutionError;Lscala/collection/immutable/Seq;)Lcoursier/error/ResolutionError;
  #48 = Methodref          #35.#47        // coursier/error/ResolutionError$.from:(Lcoursier/error/ResolutionError;Lscala/collection/immutable/Seq;)Lcoursier/error/ResolutionError;
  #49 = Utf8               ()Lcoursier/core/Resolution;
  #50 = NameAndType        #30:#31        // resolution:Lcoursier/core/Resolution;
  #51 = Fieldref           #2.#50         // coursier/error/ResolutionError.resolution:Lcoursier/core/Resolution;
  #52 = Utf8               this
  #53 = Utf8               Lcoursier/error/ResolutionError;
  #54 = Utf8               errors
  #55 = Utf8               ()Lscala/collection/immutable/Seq;
  #56 = Utf8               ()Lscala/collection/immutable/Seq<Lcoursier/error/ResolutionError$Simple;>;
  #57 = Utf8               <init>
  #58 = Utf8               (Lcoursier/core/Resolution;Ljava/lang/String;Ljava/lang/Throwable;)V
  #59 = Utf8               message
  #60 = Utf8               cause
  #61 = Utf8               (Ljava/lang/String;Ljava/lang/Throwable;)V
  #62 = NameAndType        #57:#61        // "<init>":(Ljava/lang/String;Ljava/lang/Throwable;)V
  #63 = Methodref          #4.#62         // coursier/error/CoursierError."<init>":(Ljava/lang/String;Ljava/lang/Throwable;)V
  #64 = Utf8               Ljava/lang/String;
  #65 = Utf8               Ljava/lang/Throwable;
  #66 = Utf8               Code
  #67 = Utf8               Signature
  #68 = Utf8               MethodParameters
  #69 = Utf8               LineNumberTable
  #70 = Utf8               LocalVariableTable
  #71 = Utf8               InnerClasses
  #72 = Utf8               SourceFile
  #73 = Utf8               RuntimeVisibleAnnotations
  #74 = Utf8               ScalaInlineInfo
  #75 = Utf8               ScalaSig
{
  private final coursier.core.Resolution resolution;
    descriptor: Lcoursier/core/Resolution;
    flags: (0x0012) ACC_PRIVATE, ACC_FINAL

  public static java.lang.Throwable $lessinit$greater$default$3();
    descriptor: ()Ljava/lang/Throwable;
    flags: (0x0009) ACC_PUBLIC, ACC_STATIC
    Code:
      stack=1, locals=0, args_size=0
         0: getstatic     #39                 // Field coursier/error/ResolutionError$.MODULE$:Lcoursier/error/ResolutionError$;
         3: invokevirtual #41                 // Method coursier/error/ResolutionError$.$lessinit$greater$default$3:()Ljava/lang/Throwable;
         6: areturn

  public static coursier.error.ResolutionError from(coursier.error.ResolutionError, scala.collection.immutable.Seq<coursier.error.ResolutionError>);
    descriptor: (Lcoursier/error/ResolutionError;Lscala/collection/immutable/Seq;)Lcoursier/error/ResolutionError;
    flags: (0x0009) ACC_PUBLIC, ACC_STATIC
    Code:
      stack=3, locals=2, args_size=2
         0: getstatic     #39                 // Field coursier/error/ResolutionError$.MODULE$:Lcoursier/error/ResolutionError$;
         3: aload_0
         4: aload_1
         5: invokevirtual #48                 // Method coursier/error/ResolutionError$.from:(Lcoursier/error/ResolutionError;Lscala/collection/immutable/Seq;)Lcoursier/error/ResolutionError;
         8: areturn
    Signature: #44                          // (Lcoursier/error/ResolutionError;Lscala/collection/immutable/Seq<Lcoursier/error/ResolutionError;>;)Lcoursier/error/ResolutionError;
    MethodParameters:
      Name                           Flags
      head                           final
      tail                           final

  public coursier.core.Resolution resolution();
    descriptor: ()Lcoursier/core/Resolution;
    flags: (0x0001) ACC_PUBLIC
    Code:
      stack=1, locals=1, args_size=1
         0: aload_0
         1: getfield      #51                 // Field resolution:Lcoursier/core/Resolution;
         4: areturn
      LineNumberTable:
        line 13: 0
      LocalVariableTable:
        Start  Length  Slot  Name   Signature
            0       5     0  this   Lcoursier/error/ResolutionError;

  public abstract scala.collection.immutable.Seq<coursier.error.ResolutionError$Simple> errors();
    descriptor: ()Lscala/collection/immutable/Seq;
    flags: (0x0401) ACC_PUBLIC, ACC_ABSTRACT
    Signature: #56                          // ()Lscala/collection/immutable/Seq<Lcoursier/error/ResolutionError$Simple;>;

  public coursier.error.ResolutionError(coursier.core.Resolution, java.lang.String, java.lang.Throwable);
    descriptor: (Lcoursier/core/Resolution;Ljava/lang/String;Ljava/lang/Throwable;)V
    flags: (0x0001) ACC_PUBLIC
    Code:
      stack=3, locals=4, args_size=4
         0: aload_0
         1: aload_1
         2: putfield      #51                 // Field resolution:Lcoursier/core/Resolution;
         5: aload_0
         6: aload_2
         7: aload_3
         8: invokespecial #63                 // Method coursier/error/CoursierError."<init>":(Ljava/lang/String;Ljava/lang/Throwable;)V
        11: return
      LineNumberTable:
        line 13: 0
        line 16: 5
        line 12: 11
      LocalVariableTable:
        Start  Length  Slot  Name   Signature
            0      12     0  this   Lcoursier/error/ResolutionError;
            0      12     1 resolution   Lcoursier/core/Resolution;
            0      12     2 message   Ljava/lang/String;
            0      12     3 cause   Ljava/lang/Throwable;
    MethodParameters:
      Name                           Flags
      resolution                     final
      message                        final
      cause                          final
}
InnerClasses:
  public static final #11= #10 of #2;     // CantDownloadModule=class coursier/error/ResolutionError$CantDownloadModule of class coursier/error/ResolutionError
  public static final #14= #13 of #2;     // ConflictingDependencies=class coursier/error/ResolutionError$ConflictingDependencies of class coursier/error/ResolutionError
  public static final #17= #16 of #2;     // MaximumIterationReached=class coursier/error/ResolutionError$MaximumIterationReached of class coursier/error/ResolutionError
  public static final #20= #19 of #2;     // Several=class coursier/error/ResolutionError$Several of class coursier/error/ResolutionError
  public static abstract #23= #22 of #2;  // Simple=class coursier/error/ResolutionError$Simple of class coursier/error/ResolutionError
  public static #26= #25 of #2;           // =class coursier/error/ResolutionError$Simple$ of class coursier/error/ResolutionError
  public static abstract #29= #28 of #2;  // UnsatisfiableRule=class coursier/error/ResolutionError$UnsatisfiableRule of class coursier/error/ResolutionError
SourceFile: "ResolutionError.scala"
RuntimeVisibleAnnotations:
  0: #6(#7=s#8)
    scala.reflect.ScalaSignature(
      bytes="\u0006\u0005\u0005Uh!\u0002\u001d:\u0003Cq\u0004\u0002C\"\u0001\u0005\u000b\u0007I\u0011\u0001#\t\u0011-\u0003!\u0011!Q\u0001\n\u0015C\u0001\u0002\u0014\u0001\u0003\u0002\u0003\u0006I!\u0014\u0005\t5\u0002\u0011\t\u0011)A\u00057\")A\r\u0001C\u0001K\")!\u000e\u0001D\u0001W\u001e)\u0011/\u000fE\u0001e\u001a)\u0001(\u000fE\u0001g\"1A\r\u0003C\u0001\u0003\u00031a!a\u0001\t\u0005\u0005\u0015\u0001\"C\"\u000b\u0005\u0003\u0005\u000b\u0011B#\u0002\u0011\u0019!\'\u0002\"\u0001\u0002\u0016\u001a1\u0011\u0011\u0004\u0005\u0003\u00037A\u0011bQ\u0007\u0003\u0002\u0003\u0006I!R\u0001\t\u0015\u0005uQB!b\u0001\n\u0003\ty\u0002\u0003\u0006\u0002(5\u0011\t\u0011)A\u0005\u0003CA!\"!\u000b\u000e\u0005\u000b\u0007I\u0011AA\u0016\u0011%\ti#\u0004B\u0001B\u0003%Q\n\u0003\u0006\u000205\u0011)\u0019!C\u0001\u0003cA!\"!\u000e\u000e\u0005\u0003\u0005\u000b\u0011BA\u001a\u0011\u0019!W\u0002\"\u0001\u00028\u00191\u00111\t\u0005\u0003\u0003\u000bB\u0011b\u0011\f\u0003\u0002\u0003\u0006I!R\u0001\t\u0015\u0005\u001dcC!b\u0001\n\u0003\tI\u0005\u0003\u0006\u0002XY\u0011\t\u0011)A\u0005\u0003\u0017Ba\u0001\u001a\f\u0005\u0002\u0005ecaBA\u0006\u0011\u0005\u0005\u0012Q\u0002\u0005\n\u0007n\u0011\t\u0011)A\u0005\u000b\u0006A\u0001\u0002T\u000e\u0003\u0002\u0003\u0006I!\u0014\u0005\t5n\u0011\t\u0011)A\u00057\"1Am\u0007C\u0001\u0003\u001fAQA[\u000e\u0005\u0002-<\u0011\"a\'\t\u0003\u0003E\t!!(\u0007\u0013\u0005-\u0001\"!A\t\u0002\u0005}\u0005B\u00023#\t\u0003\t\t\u000bC\u0005\u0002$\n\n\n\u0011\"\u0001\u0002&\"I\u00111\u0018\u0012\u0002\u0002\u0013%\u0011Q\u0018\u0004\u0007\u0003\u0017D!!!4\t\u0015\u0005=gE!b\u0001\n\u0003\t\t\u000e\u0003\u0006\u0002T\u001a\u0012\t\u0011)A\u0005\u0003\u000fA!\"!6\'\u0005\u000b\u0007I\u0011AAl\u0011)\tYN\nB\u0001B\u0003%\u0011\u0011\u001c\u0005\u0007I\u001a\"\t!!8\t\u000b)4C\u0011A6\t\u000f\u0005\u0015\b\u0002\"\u0001\u0002h\u001a9\u0011\u0011\r\u0005\u0002\u0002\u0005\r\u0004\"C\"/\u0005\u0003\u0005\u000b\u0011B#\u0002\u0011)\t)G\fBC\u0002\u0013\u0005\u0011q\r\u0005\u000b\u0003or#\u0011!Q\u0001\n\u0005%\u0004BCA=]\t\u0015\r\u0011\"\u0001\u0002|!Q\u0011q\u0011\u0018\u0003\u0002\u0003\u0006I!! \t\u00111s#\u0011!Q\u0001\n5Ca\u0001\u001a\u0018\u0005\u0002\u0005%\u0005\"CAR\u0011E\u0005I\u0011AAS\u0011%\tY\fCA\u0001\n\u0013\tiLA\bSKN|G.\u001e;j_:,%O]8s\u0015\tQ4(A\u0003feJ|\'OC\u0001=\u0003!\u0019w.\u001e:tS\u0016\u00148\u0001A\n\u0003\u0001}\u0002\"\u0001Q!\u000e\u0003eJ!AQ\u001d\u0003\u001b\r{WO]:jKJ,%O]8s\u0003)\u0011Xm]8mkRLwN\\\u000b\u0002\u000bB\u0011a)S\u0007\u0002\u000f*\u0011\u0001jO\u0001\u0005G>\u0014X-\u0003\u0002K\u000f\nQ!+Z:pYV$\u0018n\u001c8\u0002\u0017I,7o\u001c7vi&|g\u000eI\u0001\b[\u0016\u001c8/Y4f!\tquK\u0004\u0002P+B\u0011\u0001kU\u0007\u0002#*\u0011!+P\u0001\u0007yI|w\u000e\u001e \u000b\u0003Q\u000bQa]2bY\u0006L!AV*\u0002\rA\u0013X\rZ3g\u0013\tA\u0016L\u0001\u0004TiJLgn\u001a\u0006\u0003-N\u000bQaY1vg\u0016\u0004\"\u0001X1\u000f\u0005u{fB\u0001)_\u0013\u0005!\u0016B\u00011T\u0003\u001d\u0001\u0018mY6bO\u0016L!AY2\u0003\u0013QC\'o\\<bE2,\'B\u00011T\u0003\u0019a\u0014N\\5u}Q!am\u001a5j!\t\u0001\u0005\u0001C\u0003D\u000b\u0001\u0007Q\tC\u0003M\u000b\u0001\u0007Q\nC\u0004[\u000bA\u0005\t\u0019A.\u0002\r\u0015\u0014(o\u001c:t+\u0005a\u0007c\u0001/n_&\u0011an\u0019\u0002\u0004\'\u0016\f\bC\u00019\u001c\u001d\t\u0001u!A\bSKN|G.\u001e;j_:,%O]8s!\t\u0001\u0005bE\u0002\tib\u0004\"!\u001e<\u000e\u0003MK!a^*\u0003\r\u0005s\u0017PU3g!\tIh0D\u0001{\u0015\tYH0\u0001\u0002j_*\tQ0\u0001\u0003kCZ\f\u0017BA@{\u00051\u0019VM]5bY&T\u0018M\u00197f)\u0005\u0011(aF\'bq&lW/\\%uKJ\fG/[8o%\u0016\f7\r[3e\'\rQ\u0011q\u0001\t\u0004\u0003\u0013YR\"\u0001\u0005\u0003\rMKW\u000e\u001d7f\'\tYb\r\u0006\u0005\u0002\b\u0005E\u00111CA\u000b\u0011\u0015\u0019u\u00041\u0001F\u0011\u0015au\u00041\u0001N\u0011\u001dQv\u0004%AA\u0002mKSaG\u0007\u0017\u00159\u0012!cQ1oi\u0012{wO\u001c7pC\u0012lu\u000eZ;mKN\u0019Q\"a\u0002\u0002\r5|G-\u001e7f+\t\t\t\u0003E\u0002G\u0003GI1!!\nH\u0005\u0019iu\u000eZ;mK\u00069Qn\u001c3vY\u0016\u0004\u0013a\u0002<feNLwN\\\u000b\u0002\u001b\u0006Aa/\u001a:tS>t\u0007%A\nqKJ\u0014V\r]8tSR|\'/_#se>\u00148/\u0006\u0002\u00024A\u0019A,\\\'\u0002)A,\'OU3q_NLGo\u001c:z\u000bJ\u0014xN]:!))\tI$a\u000f\u0002>\u0005}\u0012\u0011\t\t\u0004\u0003\u0013i\u0001\"B\"\u0016\u0001\u0004)\u0005bBA\u000f+\u0001\u0007\u0011\u0011\u0005\u0005\u0007\u0003S)\u0002\u0019A\'\t\u000f\u0005=R\u00031\u0001\u00024\t92i\u001c8gY&\u001cG/\u001b8h\t\u0016\u0004XM\u001c3f]\u000eLWm]\n\u0004-\u0005\u001d\u0011\u0001\u00043fa\u0016tG-\u001a8dS\u0016\u001cXCAA&!\u0015q\u0015QJA)\u0013\r\ty%\u0017\u0002\u0004\'\u0016$\bc\u0001$\u0002T%\u0019\u0011QK$\u0003\u0015\u0011+\u0007/\u001a8eK:\u001c\u00170A\u0007eKB,g\u000eZ3oG&,7\u000f\t\u000b\u0007\u00037\ni&a\u0018\u0011\u0007\u0005%a\u0003C\u0003D5\u0001\u0007Q\tC\u0004\u0002Hi\u0001\r!a\u0013\u0003#Us7/\u0019;jg\u001aL\u0017M\u00197f%VdWmE\u0002/\u0003\u000f\tAA];mKV\u0011\u0011\u0011\u000e\t\u0005\u0003W\n\u0019(\u0004\u0002\u0002n)!\u0011QMA8\u0015\r\t\thO\u0001\u0007a\u0006\u0014\u0018-\\:\n\t\u0005U\u0014Q\u000e\u0002\u0005%VdW-A\u0003sk2,\u0007%\u0001\u0005d_:4G.[2u+\t\ti\b\u0005\u0003\u0002\u0000\u0005\rUBAAA\u0015\r\tI(O\u0005\u0005\u0003\u000b\u000b\tIA\bV]N\fG/[:gS\u0016$\'+\u001e7f\u0003%\u0019wN\u001c4mS\u000e$\b\u0005\u0006\u0006\u0002\f\u00065\u0015qRAI\u0003\'\u00032!!\u0003/\u0011\u0015\u0019U\u00071\u0001F\u0011\u001d\t)\'\u000ea\u0001\u0003SBq!!\u001f6\u0001\u0004\ti\bC\u0003Mk\u0001\u0007Q\n\u0006\u0003\u0002\u0018\u0006e\u0005cAA\u0005\u0015!)1\t\u0004a\u0001\u000b\u000611+[7qY\u0016\u00042!!\u0003#\'\r\u0011C\u000f\u001f\u000b\u0003\u0003;\u000b1\u0004\n7fgNLg.\u001b;%OJ,\u0017\r^3sI\u0011,g-Y;mi\u0012\u001aTCAATU\rY\u0016\u0011V\u0016\u0003\u0003W\u0003B!!,\u000286\u0011\u0011q\u0016\u0006\u0005\u0003c\u000b\u0019,A\u0005v]\u000eDWmY6fI*\u0019\u0011QW*\u0002\u0015\u0005tgn\u001c;bi&|g.\u0003\u0003\u0002:\u0006=&!E;oG\",7m[3e-\u0006\u0014\u0018.\u00198dK\u0006aqO]5uKJ+\u0007\u000f\\1dKR\u0011\u0011q\u0018\t\u0005\u0003\u0003\f9-\u0004\u0002\u0002D*\u0019\u0011Q\u0019?\u0002\t1\fgnZ\u0005\u0005\u0003\u0013\f\u0019M\u0001\u0004PE*,7\r\u001e\u0002\b\'\u00164XM]1m\'\t1c-\u0001\u0003iK\u0006$WCAA\u0004\u0003\u0015AW-\u00193!\u0003\u0011!\u0018-\u001b7\u0016\u0005\u0005e\u0007\u0003\u0002/n\u0003\u000f\tQ\u0001^1jY\u0002\"b!a8\u0002b\u0006\r\bcAA\u0005M!9\u0011qZ\u0016A\u0002\u0005\u001d\u0001bBAkW\u0001\u0007\u0011\u0011\\\u0001\u0005MJ|W\u000eF\u0003g\u0003S\fY\u000f\u0003\u0004\u0002P6\u0002\rA\u001a\u0005\b\u0003+l\u0003\u0019AAw!\u0011)\u0018q\u001e4\n\u0007\u0005E8K\u0001\u0006=e\u0016\u0004X-\u0019;fIzJ3\u0001\u0001\u0014\u001c\u0001"
    )
  ScalaInlineInfo: length = 0x13 (unknown attribute)
   01 00 00 03 00 39 00 3A 00 00 36 00 37 00 00 1E
   00 31 00
  ScalaSig: length = 0x3 (unknown attribute)
   05 02 00
