Classfile /Users/mw/Projects/slang-braindump/.jar/jar8/assemble/slang-braindump/assemble/content/coursier/error/ResolutionError$Several$$anonfun$$lessinit$greater$2.class
  Last modified May 29, 2022; size 1403 bytes
  SHA-256 checksum 9fcf4e4d65d5e8fba251bba512c4b811171fa2af85e729d76295dfd93f9579c3
  Compiled from "ResolutionError.scala"
public final class coursier.error.ResolutionError$Several$$anonfun$$lessinit$greater$2 extends scala.runtime.AbstractFunction1<coursier.error.ResolutionError$Simple, java.lang.String> implements java.io.Serializable
  minor version: 0
  major version: 52
  flags: (0x0031) ACC_PUBLIC, ACC_FINAL, ACC_SUPER
  this_class: #2                          // coursier/error/ResolutionError$Several$$anonfun$$lessinit$greater$2
  super_class: #5                         // scala/runtime/AbstractFunction1
  interfaces: 1, fields: 1, methods: 3, attributes: 6
Constant pool:
   #1 = Utf8               coursier/error/ResolutionError$Several$$anonfun$$lessinit$greater$2
   #2 = Class              #1             // coursier/error/ResolutionError$Several$$anonfun$$lessinit$greater$2
   #3 = Utf8               Lscala/runtime/AbstractFunction1<Lcoursier/error/ResolutionError$Simple;Ljava/lang/String;>;Ljava/io/Serializable;
   #4 = Utf8               scala/runtime/AbstractFunction1
   #5 = Class              #4             // scala/runtime/AbstractFunction1
   #6 = Utf8               java/io/Serializable
   #7 = Class              #6             // java/io/Serializable
   #8 = Utf8               ResolutionError.scala
   #9 = Utf8               coursier/error/ResolutionError$Several
  #10 = Class              #9             // coursier/error/ResolutionError$Several
  #11 = Utf8               <init>
  #12 = Utf8               (Lcoursier/error/ResolutionError$Simple;Lscala/collection/immutable/Seq;)V
  #13 = NameAndType        #11:#12        // "<init>":(Lcoursier/error/ResolutionError$Simple;Lscala/collection/immutable/Seq;)V
  #14 = Utf8               coursier/error/ResolutionError
  #15 = Class              #14            // coursier/error/ResolutionError
  #16 = Utf8               Several
  #17 = Utf8               coursier/error/ResolutionError$Simple
  #18 = Class              #17            // coursier/error/ResolutionError$Simple
  #19 = Utf8               Simple
  #20 = Utf8               serialVersionUID
  #21 = Utf8               J
  #22 = Long               0l
  #24 = Utf8               apply
  #25 = Utf8               (Lcoursier/error/ResolutionError$Simple;)Ljava/lang/String;
  #26 = Utf8               x$7
  #27 = Utf8               getMessage
  #28 = Utf8               ()Ljava/lang/String;
  #29 = NameAndType        #27:#28        // getMessage:()Ljava/lang/String;
  #30 = Methodref          #18.#29        // coursier/error/ResolutionError$Simple.getMessage:()Ljava/lang/String;
  #31 = Utf8               this
  #32 = Utf8               Lcoursier/error/ResolutionError$Several$$anonfun$$lessinit$greater$2;
  #33 = Utf8               Lcoursier/error/ResolutionError$Simple;
  #34 = Utf8               (Ljava/lang/Object;)Ljava/lang/Object;
  #35 = Utf8               v1
  #36 = NameAndType        #24:#25        // apply:(Lcoursier/error/ResolutionError$Simple;)Ljava/lang/String;
  #37 = Methodref          #2.#36         // coursier/error/ResolutionError$Several$$anonfun$$lessinit$greater$2.apply:(Lcoursier/error/ResolutionError$Simple;)Ljava/lang/String;
  #38 = Utf8               Ljava/lang/Object;
  #39 = Utf8               ()V
  #40 = NameAndType        #11:#39        // "<init>":()V
  #41 = Methodref          #5.#40         // scala/runtime/AbstractFunction1."<init>":()V
  #42 = Utf8               ConstantValue
  #43 = Utf8               Code
  #44 = Utf8               LineNumberTable
  #45 = Utf8               LocalVariableTable
  #46 = Utf8               MethodParameters
  #47 = Utf8               InnerClasses
  #48 = Utf8               EnclosingMethod
  #49 = Utf8               Signature
  #50 = Utf8               SourceFile
  #51 = Utf8               ScalaInlineInfo
  #52 = Utf8               Scala
{
  private static final long serialVersionUID;
    descriptor: J
    flags: (0x001a) ACC_PRIVATE, ACC_STATIC, ACC_FINAL
    ConstantValue: long 0l

  public final java.lang.String apply(coursier.error.ResolutionError$Simple);
    descriptor: (Lcoursier/error/ResolutionError$Simple;)Ljava/lang/String;
    flags: (0x0011) ACC_PUBLIC, ACC_FINAL
    Code:
      stack=1, locals=2, args_size=2
         0: aload_1
         1: invokevirtual #30                 // Method coursier/error/ResolutionError$Simple.getMessage:()Ljava/lang/String;
         4: areturn
      LineNumberTable:
        line 102: 0
      LocalVariableTable:
        Start  Length  Slot  Name   Signature
            0       5     0  this   Lcoursier/error/ResolutionError$Several$$anonfun$$lessinit$greater$2;
            0       5     1   x$7   Lcoursier/error/ResolutionError$Simple;
    MethodParameters:
      Name                           Flags
      x$7                            final

  public final java.lang.Object apply(java.lang.Object);
    descriptor: (Ljava/lang/Object;)Ljava/lang/Object;
    flags: (0x1051) ACC_PUBLIC, ACC_FINAL, ACC_BRIDGE, ACC_SYNTHETIC
    Code:
      stack=2, locals=2, args_size=2
         0: aload_0
         1: aload_1
         2: checkcast     #18                 // class coursier/error/ResolutionError$Simple
         5: invokevirtual #37                 // Method apply:(Lcoursier/error/ResolutionError$Simple;)Ljava/lang/String;
         8: areturn
      LineNumberTable:
        line 102: 0
      LocalVariableTable:
        Start  Length  Slot  Name   Signature
            0       9     0  this   Lcoursier/error/ResolutionError$Several$$anonfun$$lessinit$greater$2;
            0       9     1    v1   Ljava/lang/Object;
    MethodParameters:
      Name                           Flags
      v1                             final

  public coursier.error.ResolutionError$Several$$anonfun$$lessinit$greater$2();
    descriptor: ()V
    flags: (0x0001) ACC_PUBLIC
    Code:
      stack=1, locals=1, args_size=1
         0: aload_0
         1: invokespecial #41                 // Method scala/runtime/AbstractFunction1."<init>":()V
         4: return
      LineNumberTable:
        line 102: 0
      LocalVariableTable:
        Start  Length  Slot  Name   Signature
            0       5     0  this   Lcoursier/error/ResolutionError$Several$$anonfun$$lessinit$greater$2;
}
InnerClasses:
  public static final #16= #10 of #15;    // Several=class coursier/error/ResolutionError$Several of class coursier/error/ResolutionError
  public final #2;                        // class coursier/error/ResolutionError$Several$$anonfun$$lessinit$greater$2
  public static abstract #19= #18 of #15; // Simple=class coursier/error/ResolutionError$Simple of class coursier/error/ResolutionError
EnclosingMethod: #10.#13                // coursier.error.ResolutionError$Several.<init>
Signature: #3                           // Lscala/runtime/AbstractFunction1<Lcoursier/error/ResolutionError$Simple;Ljava/lang/String;>;Ljava/io/Serializable;
SourceFile: "ResolutionError.scala"
  ScalaInlineInfo: length = 0x13 (unknown attribute)
   01 01 00 03 00 0B 00 27 01 00 18 00 19 01 00 18
   00 22 01
  Scala: length = 0x0 (unknown attribute)

