Classfile /Users/mw/Projects/slang-braindump/.jar/jar11/assemble/slang-braindump/assemble/content/coursier/cache/shaded/dirs/dev/dirs/UnsupportedOperatingSystemException.class
  Last modified May 29, 2022; size 390 bytes
  SHA-256 checksum d0a73b490b64b70c89307c215139150661617800310b3ad470f8282e2402f340
  Compiled from "UnsupportedOperatingSystemException.java"
public class coursier.cache.shaded.dirs.dev.dirs.UnsupportedOperatingSystemException extends java.lang.UnsupportedOperationException
  minor version: 0
  major version: 52
  flags: (0x0021) ACC_PUBLIC, ACC_SUPER
  this_class: #2                          // coursier/cache/shaded/dirs/dev/dirs/UnsupportedOperatingSystemException
  super_class: #4                         // java/lang/UnsupportedOperationException
  interfaces: 0, fields: 1, methods: 1, attributes: 1
Constant pool:
   #1 = Utf8               coursier/cache/shaded/dirs/dev/dirs/UnsupportedOperatingSystemException
   #2 = Class              #1             // coursier/cache/shaded/dirs/dev/dirs/UnsupportedOperatingSystemException
   #3 = Utf8               java/lang/UnsupportedOperationException
   #4 = Class              #3             // java/lang/UnsupportedOperationException
   #5 = Utf8               UnsupportedOperatingSystemException.java
   #6 = Utf8               serialVersionUID
   #7 = Utf8               J
   #8 = Long               -6241121024431394902l
  #10 = Utf8               <init>
  #11 = Utf8               (Ljava/lang/String;)V
  #12 = NameAndType        #10:#11        // "<init>":(Ljava/lang/String;)V
  #13 = Methodref          #4.#12         // java/lang/UnsupportedOperationException."<init>":(Ljava/lang/String;)V
  #14 = Utf8               ConstantValue
  #15 = Utf8               Code
  #16 = Utf8               LineNumberTable
  #17 = Utf8               SourceFile
{
  private static final long serialVersionUID;
    descriptor: J
    flags: (0x001a) ACC_PRIVATE, ACC_STATIC, ACC_FINAL
    ConstantValue: long -6241121024431394902l

  public coursier.cache.shaded.dirs.dev.dirs.UnsupportedOperatingSystemException(java.lang.String);
    descriptor: (Ljava/lang/String;)V
    flags: (0x0001) ACC_PUBLIC
    Code:
      stack=2, locals=2, args_size=2
         0: aload_0
         1: aload_1
         2: invokespecial #13                 // Method java/lang/UnsupportedOperationException."<init>":(Ljava/lang/String;)V
         5: return
      LineNumberTable:
        line 8: 0
        line 9: 5
}
SourceFile: "UnsupportedOperatingSystemException.java"
