Classfile /Users/mw/Projects/slang-braindump/.jar/jar8/assemble/slang-braindump/assemble/content/org/kohsuke/github/extras/ImpatientHttpConnector.class
  Last modified May 29, 2022; size 1707 bytes
  SHA-256 checksum 4a5741acb03ad13bc3d471e6ef04fc95bf95d5b768d00415db35af7f0d71725f
  Compiled from "ImpatientHttpConnector.java"
public class org.kohsuke.github.extras.ImpatientHttpConnector implements org.kohsuke.github.HttpConnector
  minor version: 0
  major version: 52
  flags: (0x0021) ACC_PUBLIC, ACC_SUPER
  this_class: #15                         // org/kohsuke/github/extras/ImpatientHttpConnector
  super_class: #16                        // java/lang/Object
  interfaces: 1, fields: 5, methods: 5, attributes: 1
Constant pool:
   #1 = Methodref          #16.#51        // java/lang/Object."<init>":()V
   #2 = Fieldref           #15.#52        // org/kohsuke/github/extras/ImpatientHttpConnector.base:Lorg/kohsuke/github/HttpConnector;
   #3 = Fieldref           #15.#53        // org/kohsuke/github/extras/ImpatientHttpConnector.connectTimeout:I
   #4 = Fieldref           #15.#54        // org/kohsuke/github/extras/ImpatientHttpConnector.readTimeout:I
   #5 = Methodref          #15.#55        // org/kohsuke/github/extras/ImpatientHttpConnector."<init>":(Lorg/kohsuke/github/HttpConnector;II)V
   #6 = Fieldref           #15.#56        // org/kohsuke/github/extras/ImpatientHttpConnector.CONNECT_TIMEOUT:I
   #7 = Fieldref           #15.#57        // org/kohsuke/github/extras/ImpatientHttpConnector.READ_TIMEOUT:I
   #8 = InterfaceMethodref #17.#58        // org/kohsuke/github/HttpConnector.connect:(Ljava/net/URL;)Ljava/net/HttpURLConnection;
   #9 = Methodref          #59.#60        // java/net/HttpURLConnection.setConnectTimeout:(I)V
  #10 = Methodref          #59.#61        // java/net/HttpURLConnection.setReadTimeout:(I)V
  #11 = Fieldref           #62.#63        // java/util/concurrent/TimeUnit.SECONDS:Ljava/util/concurrent/TimeUnit;
  #12 = Long               10l
  #14 = Methodref          #62.#64        // java/util/concurrent/TimeUnit.toMillis:(J)J
  #15 = Class              #65            // org/kohsuke/github/extras/ImpatientHttpConnector
  #16 = Class              #66            // java/lang/Object
  #17 = Class              #67            // org/kohsuke/github/HttpConnector
  #18 = Utf8               base
  #19 = Utf8               Lorg/kohsuke/github/HttpConnector;
  #20 = Utf8               readTimeout
  #21 = Utf8               I
  #22 = Utf8               connectTimeout
  #23 = Utf8               CONNECT_TIMEOUT
  #24 = Utf8               RuntimeInvisibleAnnotations
  #25 = Utf8               Ledu/umd/cs/findbugs/annotations/SuppressFBWarnings;
  #26 = Utf8               value
  #27 = Utf8               MS_SHOULD_BE_FINAL
  #28 = Utf8               READ_TIMEOUT
  #29 = Utf8               <init>
  #30 = Utf8               (Lorg/kohsuke/github/HttpConnector;II)V
  #31 = Utf8               Code
  #32 = Utf8               LineNumberTable
  #33 = Utf8               LocalVariableTable
  #34 = Utf8               this
  #35 = Utf8               Lorg/kohsuke/github/extras/ImpatientHttpConnector;
  #36 = Utf8               (Lorg/kohsuke/github/HttpConnector;I)V
  #37 = Utf8               timeout
  #38 = Utf8               (Lorg/kohsuke/github/HttpConnector;)V
  #39 = Utf8               connect
  #40 = Utf8               (Ljava/net/URL;)Ljava/net/HttpURLConnection;
  #41 = Utf8               url
  #42 = Utf8               Ljava/net/URL;
  #43 = Utf8               con
  #44 = Utf8               Ljava/net/HttpURLConnection;
  #45 = Utf8               Exceptions
  #46 = Class              #68            // java/io/IOException
  #47 = Utf8               <clinit>
  #48 = Utf8               ()V
  #49 = Utf8               SourceFile
  #50 = Utf8               ImpatientHttpConnector.java
  #51 = NameAndType        #29:#48        // "<init>":()V
  #52 = NameAndType        #18:#19        // base:Lorg/kohsuke/github/HttpConnector;
  #53 = NameAndType        #22:#21        // connectTimeout:I
  #54 = NameAndType        #20:#21        // readTimeout:I
  #55 = NameAndType        #29:#30        // "<init>":(Lorg/kohsuke/github/HttpConnector;II)V
  #56 = NameAndType        #23:#21        // CONNECT_TIMEOUT:I
  #57 = NameAndType        #28:#21        // READ_TIMEOUT:I
  #58 = NameAndType        #39:#40        // connect:(Ljava/net/URL;)Ljava/net/HttpURLConnection;
  #59 = Class              #69            // java/net/HttpURLConnection
  #60 = NameAndType        #70:#71        // setConnectTimeout:(I)V
  #61 = NameAndType        #72:#71        // setReadTimeout:(I)V
  #62 = Class              #73            // java/util/concurrent/TimeUnit
  #63 = NameAndType        #74:#75        // SECONDS:Ljava/util/concurrent/TimeUnit;
  #64 = NameAndType        #76:#77        // toMillis:(J)J
  #65 = Utf8               org/kohsuke/github/extras/ImpatientHttpConnector
  #66 = Utf8               java/lang/Object
  #67 = Utf8               org/kohsuke/github/HttpConnector
  #68 = Utf8               java/io/IOException
  #69 = Utf8               java/net/HttpURLConnection
  #70 = Utf8               setConnectTimeout
  #71 = Utf8               (I)V
  #72 = Utf8               setReadTimeout
  #73 = Utf8               java/util/concurrent/TimeUnit
  #74 = Utf8               SECONDS
  #75 = Utf8               Ljava/util/concurrent/TimeUnit;
  #76 = Utf8               toMillis
  #77 = Utf8               (J)J
{
  private final org.kohsuke.github.HttpConnector base;
    descriptor: Lorg/kohsuke/github/HttpConnector;
    flags: (0x0012) ACC_PRIVATE, ACC_FINAL

  private final int readTimeout;
    descriptor: I
    flags: (0x0012) ACC_PRIVATE, ACC_FINAL

  private final int connectTimeout;
    descriptor: I
    flags: (0x0012) ACC_PRIVATE, ACC_FINAL

  public static int CONNECT_TIMEOUT;
    descriptor: I
    flags: (0x0009) ACC_PUBLIC, ACC_STATIC
    RuntimeInvisibleAnnotations:
      0: #25(#26=[s#27])
        edu.umd.cs.findbugs.annotations.SuppressFBWarnings(
          value=["MS_SHOULD_BE_FINAL"]
        )

  public static int READ_TIMEOUT;
    descriptor: I
    flags: (0x0009) ACC_PUBLIC, ACC_STATIC
    RuntimeInvisibleAnnotations:
      0: #25(#26=[s#27])
        edu.umd.cs.findbugs.annotations.SuppressFBWarnings(
          value=["MS_SHOULD_BE_FINAL"]
        )

  public org.kohsuke.github.extras.ImpatientHttpConnector(org.kohsuke.github.HttpConnector, int, int);
    descriptor: (Lorg/kohsuke/github/HttpConnector;II)V
    flags: (0x0001) ACC_PUBLIC
    Code:
      stack=2, locals=4, args_size=4
         0: aload_0
         1: invokespecial #1                  // Method java/lang/Object."<init>":()V
         4: aload_0
         5: aload_1
         6: putfield      #2                  // Field base:Lorg/kohsuke/github/HttpConnector;
         9: aload_0
        10: iload_2
        11: putfield      #3                  // Field connectTimeout:I
        14: aload_0
        15: iload_3
        16: putfield      #4                  // Field readTimeout:I
        19: return
      LineNumberTable:
        line 30: 0
        line 31: 4
        line 32: 9
        line 33: 14
        line 34: 19
      LocalVariableTable:
        Start  Length  Slot  Name   Signature
            0      20     0  this   Lorg/kohsuke/github/extras/ImpatientHttpConnector;
            0      20     1  base   Lorg/kohsuke/github/HttpConnector;
            0      20     2 connectTimeout   I
            0      20     3 readTimeout   I

  public org.kohsuke.github.extras.ImpatientHttpConnector(org.kohsuke.github.HttpConnector, int);
    descriptor: (Lorg/kohsuke/github/HttpConnector;I)V
    flags: (0x0001) ACC_PUBLIC
    Code:
      stack=4, locals=3, args_size=3
         0: aload_0
         1: aload_1
         2: iload_2
         3: iload_2
         4: invokespecial #5                  // Method "<init>":(Lorg/kohsuke/github/HttpConnector;II)V
         7: return
      LineNumberTable:
        line 45: 0
        line 46: 7
      LocalVariableTable:
        Start  Length  Slot  Name   Signature
            0       8     0  this   Lorg/kohsuke/github/extras/ImpatientHttpConnector;
            0       8     1  base   Lorg/kohsuke/github/HttpConnector;
            0       8     2 timeout   I

  public org.kohsuke.github.extras.ImpatientHttpConnector(org.kohsuke.github.HttpConnector);
    descriptor: (Lorg/kohsuke/github/HttpConnector;)V
    flags: (0x0001) ACC_PUBLIC
    Code:
      stack=4, locals=2, args_size=2
         0: aload_0
         1: aload_1
         2: getstatic     #6                  // Field CONNECT_TIMEOUT:I
         5: getstatic     #7                  // Field READ_TIMEOUT:I
         8: invokespecial #5                  // Method "<init>":(Lorg/kohsuke/github/HttpConnector;II)V
        11: return
      LineNumberTable:
        line 55: 0
        line 56: 11
      LocalVariableTable:
        Start  Length  Slot  Name   Signature
            0      12     0  this   Lorg/kohsuke/github/extras/ImpatientHttpConnector;
            0      12     1  base   Lorg/kohsuke/github/HttpConnector;

  public java.net.HttpURLConnection connect(java.net.URL) throws java.io.IOException;
    descriptor: (Ljava/net/URL;)Ljava/net/HttpURLConnection;
    flags: (0x0001) ACC_PUBLIC
    Code:
      stack=2, locals=3, args_size=2
         0: aload_0
         1: getfield      #2                  // Field base:Lorg/kohsuke/github/HttpConnector;
         4: aload_1
         5: invokeinterface #8,  2            // InterfaceMethod org/kohsuke/github/HttpConnector.connect:(Ljava/net/URL;)Ljava/net/HttpURLConnection;
        10: astore_2
        11: aload_2
        12: aload_0
        13: getfield      #3                  // Field connectTimeout:I
        16: invokevirtual #9                  // Method java/net/HttpURLConnection.setConnectTimeout:(I)V
        19: aload_2
        20: aload_0
        21: getfield      #4                  // Field readTimeout:I
        24: invokevirtual #10                 // Method java/net/HttpURLConnection.setReadTimeout:(I)V
        27: aload_2
        28: areturn
      LineNumberTable:
        line 59: 0
        line 60: 11
        line 61: 19
        line 62: 27
      LocalVariableTable:
        Start  Length  Slot  Name   Signature
            0      29     0  this   Lorg/kohsuke/github/extras/ImpatientHttpConnector;
            0      29     1   url   Ljava/net/URL;
           11      18     2   con   Ljava/net/HttpURLConnection;
    Exceptions:
      throws java.io.IOException

  static {};
    descriptor: ()V
    flags: (0x0008) ACC_STATIC
    Code:
      stack=3, locals=0, args_size=0
         0: getstatic     #11                 // Field java/util/concurrent/TimeUnit.SECONDS:Ljava/util/concurrent/TimeUnit;
         3: ldc2_w        #12                 // long 10l
         6: invokevirtual #14                 // Method java/util/concurrent/TimeUnit.toMillis:(J)J
         9: l2i
        10: putstatic     #6                  // Field CONNECT_TIMEOUT:I
        13: getstatic     #11                 // Field java/util/concurrent/TimeUnit.SECONDS:Ljava/util/concurrent/TimeUnit;
        16: ldc2_w        #12                 // long 10l
        19: invokevirtual #14                 // Method java/util/concurrent/TimeUnit.toMillis:(J)J
        22: l2i
        23: putstatic     #7                  // Field READ_TIMEOUT:I
        26: return
      LineNumberTable:
        line 69: 0
        line 75: 13
}
SourceFile: "ImpatientHttpConnector.java"
