Classfile /Users/mw/Projects/slang-braindump/.jar/jar8/assemble/slang-braindump/assemble/content/shapeless/ops/record/DeepMerger.class
  Last modified May 29, 2022; size 3420 bytes
  SHA-256 checksum 097c081c57a441b4bc8ca20e8cefa4778cbfc1d39c28ca16e41920319063a378
  Compiled from "records.scala"
public interface shapeless.ops.record.DeepMerger<L extends shapeless.HList, M extends shapeless.HList> extends shapeless.package$DepFn2<L, M>, java.io.Serializable
  minor version: 0
  major version: 52
  flags: (0x0601) ACC_PUBLIC, ACC_INTERFACE, ACC_ABSTRACT
  this_class: #2                          // shapeless/ops/record/DeepMerger
  super_class: #5                         // java/lang/Object
  interfaces: 2, fields: 0, methods: 4, attributes: 6
Constant pool:
   #1 = Utf8               shapeless/ops/record/DeepMerger
   #2 = Class              #1             // shapeless/ops/record/DeepMerger
   #3 = Utf8               <L::Lshapeless/HList;M::Lshapeless/HList;>Ljava/lang/Object;Lshapeless/package$DepFn2<TL;TM;>;Ljava/io/Serializable;
   #4 = Utf8               java/lang/Object
   #5 = Class              #4             // java/lang/Object
   #6 = Utf8               shapeless/package$DepFn2
   #7 = Class              #6             // shapeless/package$DepFn2
   #8 = Utf8               java/io/Serializable
   #9 = Class              #8             // java/io/Serializable
  #10 = Utf8               records.scala
  #11 = Utf8               Lscala/reflect/ScalaSignature;
  #12 = Utf8               bytes
  #13 = Utf8               \u0006\u0005\u0005ucaB\u0005\u000b!\u0003\r\n!\u0005\u0003\u0006u\u0001\u0011\t!J\u0004\u0006w)A\t\u0001\u0010\u0004\u0006\u0013)A\tA\u0010\u0005\u0006\u0013\u000e!\tA\u0013\u0005\u0006\u0017\u000e!\t\u0001\u0014\u0005\u0006;\u000e!\u0019A\u0018\u0005\u0006M\u000e!\u0019a\u001a\u0005\n\u0003\u001b\u001a\u0011\u0011!C\u0005\u0003\u001f\u0012!\u0002R3fa6+\'oZ3s\u0015\tYA\"\u0001\u0004sK\u000e|\'\u000f\u001a\u0006\u0003\u001b9\t1a\u001c9t\u0015\u0005y\u0011!C:iCB,G.Z:t\u0007\u0001)2AE\u0012.\'\u0011\u00011#G\u0018\u0011\u0005Q9R\"A\u000b\u000b\u0003Y\tQa]2bY\u0006L!\u0001G\u000b\u0003\r\u0005s\u0017PU3g!\u0011Qb$\t\u0017\u000f\u0005maR\"\u0001\b\n\u0005uq\u0011a\u00029bG.\fw-Z\u0005\u0003?\u0001\u0012a\u0001R3q\r:\u0014$BA\u000f\u000f!\t\u00113\u0005\u0004\u0001\u0005\u000b\u0011\u0002!\u0019A\u0013\u0003\u00031\u000b\"AJ\u0015\u0011\u0005Q9\u0013B\u0001\u0015\u0016\u0005\u001dqu\u000e\u001e5j]\u001e\u0004\"a\u0007\u0016\n\u0005-r!!\u0002%MSN$\bC\u0001\u0012.\t\u0015q\u0003A1\u0001&\u0005\u0005i\u0005C\u0001\u00198\u001d\t\tdG\u0004\u00023k5\t1G\u0003\u00025!\u00051AH]8pizJ\u0011AF\u0005\u0003;UI!\u0001O\u001d\u0003\u0019M+\'/[1mSj\f\'\r\\3\u000b\u0005u)\"aA(vi\u0006QA)Z3q\u001b\u0016\u0014x-\u001a:\u0011\u0005u\u001aQ\"\u0001\u0006\u0014\t\r\u0019rH\u0011\t\u0003{\u0001K!!\u0011\u0006\u0003-1{w\u000f\u0015:j_JLG/\u001f#fKBlUM]4feB\u0002\"a\u0011%\u000e\u0003\u0011S!!\u0012$\u0002\u0005%|\'\"A$\u0002\t)\fg/Y\u0005\u0003q\u0011\u000ba\u0001P5oSRtD#\u0001\u001f\u0002\u000b\u0005\u0004\b\u000f\\=\u0016\u00075+v\u000b\u0006\u0002O5B)q\n\u0015+W16\t1!\u0003\u0002R%\n\u0019\u0011)\u001e=\n\u0005MS!!\u0006\'poB\u0013\u0018n\u001c:jif$U-\u001a9NKJ<WM\u001d\t\u0003EU#Q\u0001J\u0003C\u0002\u0015\u0002\"AI,\u0005\u000b9*!\u0019A\u0013\u0011\u0005e\u000baB\u0001\u0012[\u0011\u0015YV\u0001q\u0001]\u0003\t!W\u000e\u0005\u0003>\u0001Q3\u0016A\u00035oS2lUM]4feV\u0011q,Z\u000b\u0002AB)q\nU1eIB\u00111DY\u0005\u0003G:\u0011A\u0001\u0013(jYB\u0011!%\u001a\u0003\u0006]\u0019\u0011\r!J\u0001\rQ2L7\u000f^\'fe\u001e,\'oM\u000b\u0010Q^t\u00181AA\u0005\u0003k\tY$!\u0005\u0002\u0018Q9\u0011.a\u0007\u0002@\u0005\u001d\u0003cB(QU\u0006\u001d\u00111\u0002\t\u00067-l\u0017\u0011A\u0005\u0003Y:\u0011A\u0002J2pY>tGeY8m_:\u0004BA\\:w{:\u0011q.\u001d\b\u0003eAL\u0011aD\u0005\u0003e:\t\u0001\u0002\\1cK2dW\rZ\u0005\u0003iV\u0014\u0011BR5fY\u0012$\u0016\u0010]3\u000b\u0005It\u0001C\u0001\u0012x\t\u0015AxA1\u0001z\u0005\u0005Y\u0015C\u0001\u0014{!\t!20\u0003\u0002}+\t\u0019\u0011I\\=\u0011\u0005\trH!B@\b\u0005\u0004)#!\u0001,\u0011\u0007\t\n\u0019\u0001\u0002\u0004\u0002\u0006\u001d\u0011\r!\n\u0002\u0002)B\u0019!%!\u0003\u0005\u000b9:!\u0019A\u0013\u0011\rmY\u0017QBA\u000b!\u0015q7O^A\b!\r\u0011\u0013\u0011\u0003\u0003\u0007\u0003\'9!\u0019A\u0013\u0003\u00075{\u0015\u0007E\u0002#\u0003/!a!!\u0007\b\u0005\u0004)#aA\'Pe!9\u0011QD\u0004A\u0004\u0005}\u0011A\u0001:n!%\t\t#a\n\u0002\bY\fiCD\u0002>\u0003GI1!!\n\u000b\u0003\u001d\u0011V-\\8wKJL1!UA\u0015\u0013\r\tYC\u0003\u0002\u0013\u0019><\bK]5pe&$\u0018PU3n_Z,\'\u000fE\u0004\u0015\u0003_\t\u0019$!\u000f\n\u0007\u0005ERC\u0001\u0004UkBdWM\r\t\u0004E\u0005UBABA\u001c\u000f\t\u0007QE\u0001\u0002WcA\u0019!%a\u000f\u0005\r\u0005urA1\u0001&\u0005\tiE\u000bC\u0004\u0002B\u001d\u0001\u001d!a\u0011\u0002\u00055\f\u0004\u0003CA#!v\f\u0019$a\u0004\u000f\u0005u\u0012\u0001bBA%\u000f\u0001\u000f\u00111J\u0001\u0003[J\u0002\u0012\"!\u0012Q\u0003\u0003\tI$!\u0006\u0002\u0019]\u0014\u0018\u000e^3SKBd\u0017mY3\u0015\u0005\u0005E\u0003\u0003BA*\u00033j!!!\u0016\u000b\u0007\u0005]c)\u0001\u0003mC:<\u0017\u0002BA.\u0003+\u0012aa\u00142kK\u000e$\b
  #14 = Utf8               shapeless/package
  #15 = Class              #14            // shapeless/package
  #16 = Utf8               DepFn2
  #17 = Utf8               hlistMerger3
  #18 = Utf8               (Lshapeless/ops/record/Remover;Lshapeless/ops/record/DeepMerger;Lshapeless/ops/record/DeepMerger;)Lshapeless/ops/record/DeepMerger;
  #19 = Utf8               <K:Ljava/lang/Object;V::Lshapeless/HList;T::Lshapeless/HList;M::Lshapeless/HList;V1::Lshapeless/HList;MT::Lshapeless/HList;MO1::Lshapeless/HList;MO2::Lshapeless/HList;>(Lshapeless/ops/record/Remover<TM;TK;>;Lshapeless/ops/record/DeepMerger<TV;TV1;>;Lshapeless/ops/record/DeepMerger<TT;TMT;>;)Lshapeless/ops/record/DeepMerger<Lshapeless/$colon$colon<TV;TT;>;TM;>;
  #20 = Utf8               rm
  #21 = Utf8               m1
  #22 = Utf8               m2
  #23 = Utf8               shapeless/ops/record/DeepMerger$
  #24 = Class              #23            // shapeless/ops/record/DeepMerger$
  #25 = Utf8               MODULE$
  #26 = Utf8               Lshapeless/ops/record/DeepMerger$;
  #27 = NameAndType        #25:#26        // MODULE$:Lshapeless/ops/record/DeepMerger$;
  #28 = Fieldref           #24.#27        // shapeless/ops/record/DeepMerger$.MODULE$:Lshapeless/ops/record/DeepMerger$;
  #29 = NameAndType        #17:#18        // hlistMerger3:(Lshapeless/ops/record/Remover;Lshapeless/ops/record/DeepMerger;Lshapeless/ops/record/DeepMerger;)Lshapeless/ops/record/DeepMerger;
  #30 = Methodref          #24.#29        // shapeless/ops/record/DeepMerger$.hlistMerger3:(Lshapeless/ops/record/Remover;Lshapeless/ops/record/DeepMerger;Lshapeless/ops/record/DeepMerger;)Lshapeless/ops/record/DeepMerger;
  #31 = Utf8               hnilMerger
  #32 = Utf8               ()Lshapeless/ops/record/DeepMerger;
  #33 = Utf8               <M::Lshapeless/HList;>()Lshapeless/ops/record/DeepMerger<Lshapeless/HNil;TM;>;
  #34 = NameAndType        #31:#32        // hnilMerger:()Lshapeless/ops/record/DeepMerger;
  #35 = Methodref          #24.#34        // shapeless/ops/record/DeepMerger$.hnilMerger:()Lshapeless/ops/record/DeepMerger;
  #36 = Utf8               hlistMerger2
  #37 = Utf8               (Lshapeless/ops/record/Remover;Lshapeless/ops/record/DeepMerger;)Lshapeless/ops/record/DeepMerger;
  #38 = Utf8               <K:Ljava/lang/Object;V:Ljava/lang/Object;T::Lshapeless/HList;M::Lshapeless/HList;MR::Lshapeless/HList;>(Lshapeless/ops/record/Remover<TM;TK;>;Lshapeless/ops/record/DeepMerger<TT;TMR;>;)Lshapeless/ops/record/DeepMerger<Lshapeless/$colon$colon<TV;TT;>;TM;>;
  #39 = Utf8               mt
  #40 = NameAndType        #36:#37        // hlistMerger2:(Lshapeless/ops/record/Remover;Lshapeless/ops/record/DeepMerger;)Lshapeless/ops/record/DeepMerger;
  #41 = Methodref          #24.#40        // shapeless/ops/record/DeepMerger$.hlistMerger2:(Lshapeless/ops/record/Remover;Lshapeless/ops/record/DeepMerger;)Lshapeless/ops/record/DeepMerger;
  #42 = Utf8               hlistMerger1
  #43 = Utf8               (Lshapeless/ops/record/DeepMerger;)Lshapeless/ops/record/DeepMerger;
  #44 = Utf8               <H:Ljava/lang/Object;T::Lshapeless/HList;M::Lshapeless/HList;>(Lshapeless/ops/record/DeepMerger<TT;TM;>;)Lshapeless/ops/record/DeepMerger<Lshapeless/$colon$colon<TH;TT;>;TM;>;
  #45 = NameAndType        #42:#43        // hlistMerger1:(Lshapeless/ops/record/DeepMerger;)Lshapeless/ops/record/DeepMerger;
  #46 = Methodref          #24.#45        // shapeless/ops/record/DeepMerger$.hlistMerger1:(Lshapeless/ops/record/DeepMerger;)Lshapeless/ops/record/DeepMerger;
  #47 = Utf8               Code
  #48 = Utf8               Signature
  #49 = Utf8               MethodParameters
  #50 = Utf8               InnerClasses
  #51 = Utf8               SourceFile
  #52 = Utf8               RuntimeVisibleAnnotations
  #53 = Utf8               ScalaInlineInfo
  #54 = Utf8               ScalaSig
{
  public static <K extends java.lang.Object, V extends shapeless.HList, T extends shapeless.HList, M extends shapeless.HList, V1 extends shapeless.HList, MT extends shapeless.HList, MO1 extends shapeless.HList, MO2 extends shapeless.HList> shapeless.ops.record.DeepMerger<shapeless.$colon$colon<V, T>, M> hlistMerger3(shapeless.ops.record.Remover<M, K>, shapeless.ops.record.DeepMerger<V, V1>, shapeless.ops.record.DeepMerger<T, MT>);
    descriptor: (Lshapeless/ops/record/Remover;Lshapeless/ops/record/DeepMerger;Lshapeless/ops/record/DeepMerger;)Lshapeless/ops/record/DeepMerger;
    flags: (0x0009) ACC_PUBLIC, ACC_STATIC
    Code:
      stack=4, locals=3, args_size=3
         0: getstatic     #28                 // Field shapeless/ops/record/DeepMerger$.MODULE$:Lshapeless/ops/record/DeepMerger$;
         3: aload_0
         4: aload_1
         5: aload_2
         6: invokevirtual #30                 // Method shapeless/ops/record/DeepMerger$.hlistMerger3:(Lshapeless/ops/record/Remover;Lshapeless/ops/record/DeepMerger;Lshapeless/ops/record/DeepMerger;)Lshapeless/ops/record/DeepMerger;
         9: areturn
    Signature: #19                          // <K:Ljava/lang/Object;V::Lshapeless/HList;T::Lshapeless/HList;M::Lshapeless/HList;V1::Lshapeless/HList;MT::Lshapeless/HList;MO1::Lshapeless/HList;MO2::Lshapeless/HList;>(Lshapeless/ops/record/Remover<TM;TK;>;Lshapeless/ops/record/DeepMerger<TV;TV1;>;Lshapeless/ops/record/DeepMerger<TT;TMT;>;)Lshapeless/ops/record/DeepMerger<Lshapeless/$colon$colon<TV;TT;>;TM;>;
    MethodParameters:
      Name                           Flags
      rm                             final
      m1                             final
      m2                             final

  public static <M extends shapeless.HList> shapeless.ops.record.DeepMerger<shapeless.HNil, M> hnilMerger();
    descriptor: ()Lshapeless/ops/record/DeepMerger;
    flags: (0x0009) ACC_PUBLIC, ACC_STATIC
    Code:
      stack=1, locals=0, args_size=0
         0: getstatic     #28                 // Field shapeless/ops/record/DeepMerger$.MODULE$:Lshapeless/ops/record/DeepMerger$;
         3: invokevirtual #35                 // Method shapeless/ops/record/DeepMerger$.hnilMerger:()Lshapeless/ops/record/DeepMerger;
         6: areturn
    Signature: #33                          // <M::Lshapeless/HList;>()Lshapeless/ops/record/DeepMerger<Lshapeless/HNil;TM;>;

  public static <K extends java.lang.Object, V extends java.lang.Object, T extends shapeless.HList, M extends shapeless.HList, MR extends shapeless.HList> shapeless.ops.record.DeepMerger<shapeless.$colon$colon<V, T>, M> hlistMerger2(shapeless.ops.record.Remover<M, K>, shapeless.ops.record.DeepMerger<T, MR>);
    descriptor: (Lshapeless/ops/record/Remover;Lshapeless/ops/record/DeepMerger;)Lshapeless/ops/record/DeepMerger;
    flags: (0x0009) ACC_PUBLIC, ACC_STATIC
    Code:
      stack=3, locals=2, args_size=2
         0: getstatic     #28                 // Field shapeless/ops/record/DeepMerger$.MODULE$:Lshapeless/ops/record/DeepMerger$;
         3: aload_0
         4: aload_1
         5: invokevirtual #41                 // Method shapeless/ops/record/DeepMerger$.hlistMerger2:(Lshapeless/ops/record/Remover;Lshapeless/ops/record/DeepMerger;)Lshapeless/ops/record/DeepMerger;
         8: areturn
    Signature: #38                          // <K:Ljava/lang/Object;V:Ljava/lang/Object;T::Lshapeless/HList;M::Lshapeless/HList;MR::Lshapeless/HList;>(Lshapeless/ops/record/Remover<TM;TK;>;Lshapeless/ops/record/DeepMerger<TT;TMR;>;)Lshapeless/ops/record/DeepMerger<Lshapeless/$colon$colon<TV;TT;>;TM;>;
    MethodParameters:
      Name                           Flags
      rm                             final
      mt                             final

  public static <H extends java.lang.Object, T extends shapeless.HList, M extends shapeless.HList> shapeless.ops.record.DeepMerger<shapeless.$colon$colon<H, T>, M> hlistMerger1(shapeless.ops.record.DeepMerger<T, M>);
    descriptor: (Lshapeless/ops/record/DeepMerger;)Lshapeless/ops/record/DeepMerger;
    flags: (0x0009) ACC_PUBLIC, ACC_STATIC
    Code:
      stack=2, locals=1, args_size=1
         0: getstatic     #28                 // Field shapeless/ops/record/DeepMerger$.MODULE$:Lshapeless/ops/record/DeepMerger$;
         3: aload_0
         4: invokevirtual #46                 // Method shapeless/ops/record/DeepMerger$.hlistMerger1:(Lshapeless/ops/record/DeepMerger;)Lshapeless/ops/record/DeepMerger;
         7: areturn
    Signature: #44                          // <H:Ljava/lang/Object;T::Lshapeless/HList;M::Lshapeless/HList;>(Lshapeless/ops/record/DeepMerger<TT;TM;>;)Lshapeless/ops/record/DeepMerger<Lshapeless/$colon$colon<TH;TT;>;TM;>;
    MethodParameters:
      Name                           Flags
      mt                             final
}
InnerClasses:
  public static #16= #7 of #15;           // DepFn2=class shapeless/package$DepFn2 of class shapeless/package
Signature: #3                           // <L::Lshapeless/HList;M::Lshapeless/HList;>Ljava/lang/Object;Lshapeless/package$DepFn2<TL;TM;>;Ljava/io/Serializable;
SourceFile: "records.scala"
RuntimeVisibleAnnotations:
  0: #11(#12=s#13)
    scala.reflect.ScalaSignature(
      bytes="\u0006\u0005\u0005ucaB\u0005\u000b!\u0003\r\n!\u0005\u0003\u0006u\u0001\u0011\t!J\u0004\u0006w)A\t\u0001\u0010\u0004\u0006\u0013)A\tA\u0010\u0005\u0006\u0013\u000e!\tA\u0013\u0005\u0006\u0017\u000e!\t\u0001\u0014\u0005\u0006;\u000e!\u0019A\u0018\u0005\u0006M\u000e!\u0019a\u001a\u0005\n\u0003\u001b\u001a\u0011\u0011!C\u0005\u0003\u001f\u0012!\u0002R3fa6+\'oZ3s\u0015\tYA\"\u0001\u0004sK\u000e|\'\u000f\u001a\u0006\u0003\u001b9\t1a\u001c9t\u0015\u0005y\u0011!C:iCB,G.Z:t\u0007\u0001)2AE\u0012.\'\u0011\u00011#G\u0018\u0011\u0005Q9R\"A\u000b\u000b\u0003Y\tQa]2bY\u0006L!\u0001G\u000b\u0003\r\u0005s\u0017PU3g!\u0011Qb$\t\u0017\u000f\u0005maR\"\u0001\b\n\u0005uq\u0011a\u00029bG.\fw-Z\u0005\u0003?\u0001\u0012a\u0001R3q\r:\u0014$BA\u000f\u000f!\t\u00113\u0005\u0004\u0001\u0005\u000b\u0011\u0002!\u0019A\u0013\u0003\u00031\u000b\"AJ\u0015\u0011\u0005Q9\u0013B\u0001\u0015\u0016\u0005\u001dqu\u000e\u001e5j]\u001e\u0004\"a\u0007\u0016\n\u0005-r!!\u0002%MSN$\bC\u0001\u0012.\t\u0015q\u0003A1\u0001&\u0005\u0005i\u0005C\u0001\u00198\u001d\t\tdG\u0004\u00023k5\t1G\u0003\u00025!\u00051AH]8pizJ\u0011AF\u0005\u0003;UI!\u0001O\u001d\u0003\u0019M+\'/[1mSj\f\'\r\\3\u000b\u0005u)\"aA(vi\u0006QA)Z3q\u001b\u0016\u0014x-\u001a:\u0011\u0005u\u001aQ\"\u0001\u0006\u0014\t\r\u0019rH\u0011\t\u0003{\u0001K!!\u0011\u0006\u0003-1{w\u000f\u0015:j_JLG/\u001f#fKBlUM]4feB\u0002\"a\u0011%\u000e\u0003\u0011S!!\u0012$\u0002\u0005%|\'\"A$\u0002\t)\fg/Y\u0005\u0003q\u0011\u000ba\u0001P5oSRtD#\u0001\u001f\u0002\u000b\u0005\u0004\b\u000f\\=\u0016\u00075+v\u000b\u0006\u0002O5B)q\n\u0015+W16\t1!\u0003\u0002R%\n\u0019\u0011)\u001e=\n\u0005MS!!\u0006\'poB\u0013\u0018n\u001c:jif$U-\u001a9NKJ<WM\u001d\t\u0003EU#Q\u0001J\u0003C\u0002\u0015\u0002\"AI,\u0005\u000b9*!\u0019A\u0013\u0011\u0005e\u000baB\u0001\u0012[\u0011\u0015YV\u0001q\u0001]\u0003\t!W\u000e\u0005\u0003>\u0001Q3\u0016A\u00035oS2lUM]4feV\u0011q,Z\u000b\u0002AB)q\nU1eIB\u00111DY\u0005\u0003G:\u0011A\u0001\u0013(jYB\u0011!%\u001a\u0003\u0006]\u0019\u0011\r!J\u0001\rQ2L7\u000f^\'fe\u001e,\'oM\u000b\u0010Q^t\u00181AA\u0005\u0003k\tY$!\u0005\u0002\u0018Q9\u0011.a\u0007\u0002@\u0005\u001d\u0003cB(QU\u0006\u001d\u00111\u0002\t\u00067-l\u0017\u0011A\u0005\u0003Y:\u0011A\u0002J2pY>tGeY8m_:\u0004BA\\:w{:\u0011q.\u001d\b\u0003eAL\u0011aD\u0005\u0003e:\t\u0001\u0002\\1cK2dW\rZ\u0005\u0003iV\u0014\u0011BR5fY\u0012$\u0016\u0010]3\u000b\u0005It\u0001C\u0001\u0012x\t\u0015AxA1\u0001z\u0005\u0005Y\u0015C\u0001\u0014{!\t!20\u0003\u0002}+\t\u0019\u0011I\\=\u0011\u0005\trH!B@\b\u0005\u0004)#!\u0001,\u0011\u0007\t\n\u0019\u0001\u0002\u0004\u0002\u0006\u001d\u0011\r!\n\u0002\u0002)B\u0019!%!\u0003\u0005\u000b9:!\u0019A\u0013\u0011\rmY\u0017QBA\u000b!\u0015q7O^A\b!\r\u0011\u0013\u0011\u0003\u0003\u0007\u0003\'9!\u0019A\u0013\u0003\u00075{\u0015\u0007E\u0002#\u0003/!a!!\u0007\b\u0005\u0004)#aA\'Pe!9\u0011QD\u0004A\u0004\u0005}\u0011A\u0001:n!%\t\t#a\n\u0002\bY\fiCD\u0002>\u0003GI1!!\n\u000b\u0003\u001d\u0011V-\\8wKJL1!UA\u0015\u0013\r\tYC\u0003\u0002\u0013\u0019><\bK]5pe&$\u0018PU3n_Z,\'\u000fE\u0004\u0015\u0003_\t\u0019$!\u000f\n\u0007\u0005ERC\u0001\u0004UkBdWM\r\t\u0004E\u0005UBABA\u001c\u000f\t\u0007QE\u0001\u0002WcA\u0019!%a\u000f\u0005\r\u0005urA1\u0001&\u0005\tiE\u000bC\u0004\u0002B\u001d\u0001\u001d!a\u0011\u0002\u00055\f\u0004\u0003CA#!v\f\u0019$a\u0004\u000f\u0005u\u0012\u0001bBA%\u000f\u0001\u000f\u00111J\u0001\u0003[J\u0002\u0012\"!\u0012Q\u0003\u0003\tI$!\u0006\u0002\u0019]\u0014\u0018\u000e^3SKBd\u0017mY3\u0015\u0005\u0005E\u0003\u0003BA*\u00033j!!!\u0016\u000b\u0007\u0005]c)\u0001\u0003mC:<\u0017\u0002BA.\u0003+\u0012aa\u00142kK\u000e$\b"
    )
  ScalaInlineInfo: length = 0x4 (unknown attribute)
   01 00 00 00
  ScalaSig: length = 0x3 (unknown attribute)
   05 02 00
