Classfile /Users/mw/Projects/slang-braindump/.jar/jar8/assemble/slang-braindump/assemble/content/shapeless/ops/record/DeepMerger$.class
  Last modified May 29, 2022; size 3502 bytes
  SHA-256 checksum 4bb02df66f6a788598c4b2cfa50407370fd677908841a11bdc5364b1dc873381
  Compiled from "records.scala"
public final class shapeless.ops.record.DeepMerger$ implements shapeless.ops.record.LowPriorityDeepMerger0,java.io.Serializable
  minor version: 0
  major version: 52
  flags: (0x0031) ACC_PUBLIC, ACC_FINAL, ACC_SUPER
  this_class: #2                          // shapeless/ops/record/DeepMerger$
  super_class: #4                         // java/lang/Object
  interfaces: 2, fields: 1, methods: 8, attributes: 4
Constant pool:
   #1 = Utf8               shapeless/ops/record/DeepMerger$
   #2 = Class              #1             // shapeless/ops/record/DeepMerger$
   #3 = Utf8               java/lang/Object
   #4 = Class              #3             // java/lang/Object
   #5 = Utf8               shapeless/ops/record/LowPriorityDeepMerger0
   #6 = Class              #5             // shapeless/ops/record/LowPriorityDeepMerger0
   #7 = Utf8               java/io/Serializable
   #8 = Class              #7             // java/io/Serializable
   #9 = Utf8               records.scala
  #10 = Utf8               shapeless/ops/record/DeepMerger$$anon$8
  #11 = Class              #10            // shapeless/ops/record/DeepMerger$$anon$8
  #12 = Utf8               shapeless/ops/record/DeepMerger$$anon$9
  #13 = Class              #12            // shapeless/ops/record/DeepMerger$$anon$9
  #14 = Utf8               MODULE$
  #15 = Utf8               Lshapeless/ops/record/DeepMerger$;
  #16 = Utf8               <clinit>
  #17 = Utf8               ()V
  #18 = Utf8               <init>
  #19 = NameAndType        #18:#17        // "<init>":()V
  #20 = Methodref          #2.#19         // shapeless/ops/record/DeepMerger$."<init>":()V
  #21 = NameAndType        #14:#15        // MODULE$:Lshapeless/ops/record/DeepMerger$;
  #22 = Fieldref           #2.#21         // shapeless/ops/record/DeepMerger$.MODULE$:Lshapeless/ops/record/DeepMerger$;
  #23 = Utf8               shapeless/ops/record/LowPriorityDeepMerger
  #24 = Class              #23            // shapeless/ops/record/LowPriorityDeepMerger
  #25 = Utf8               $init$
  #26 = Utf8               (Lshapeless/ops/record/LowPriorityDeepMerger;)V
  #27 = NameAndType        #25:#26        // $init$:(Lshapeless/ops/record/LowPriorityDeepMerger;)V
  #28 = InterfaceMethodref #24.#27        // shapeless/ops/record/LowPriorityDeepMerger.$init$:(Lshapeless/ops/record/LowPriorityDeepMerger;)V
  #29 = Utf8               (Lshapeless/ops/record/LowPriorityDeepMerger0;)V
  #30 = NameAndType        #25:#29        // $init$:(Lshapeless/ops/record/LowPriorityDeepMerger0;)V
  #31 = InterfaceMethodref #6.#30         // shapeless/ops/record/LowPriorityDeepMerger0.$init$:(Lshapeless/ops/record/LowPriorityDeepMerger0;)V
  #32 = Utf8               hlistMerger2
  #33 = Utf8               (Lshapeless/ops/record/Remover;Lshapeless/ops/record/DeepMerger;)Lshapeless/ops/record/DeepMerger;
  #34 = Utf8               <K:Ljava/lang/Object;V:Ljava/lang/Object;T::Lshapeless/HList;M::Lshapeless/HList;MR::Lshapeless/HList;>(Lshapeless/ops/record/Remover<TM;TK;>;Lshapeless/ops/record/DeepMerger<TT;TMR;>;)Lshapeless/ops/record/DeepMerger<Lshapeless/$colon$colon<TV;TT;>;TM;>;
  #35 = Utf8               rm
  #36 = Utf8               mt
  #37 = Utf8               hlistMerger2$
  #38 = Utf8               (Lshapeless/ops/record/LowPriorityDeepMerger0;Lshapeless/ops/record/Remover;Lshapeless/ops/record/DeepMerger;)Lshapeless/ops/record/DeepMerger;
  #39 = NameAndType        #37:#38        // hlistMerger2$:(Lshapeless/ops/record/LowPriorityDeepMerger0;Lshapeless/ops/record/Remover;Lshapeless/ops/record/DeepMerger;)Lshapeless/ops/record/DeepMerger;
  #40 = InterfaceMethodref #6.#39         // shapeless/ops/record/LowPriorityDeepMerger0.hlistMerger2$:(Lshapeless/ops/record/LowPriorityDeepMerger0;Lshapeless/ops/record/Remover;Lshapeless/ops/record/DeepMerger;)Lshapeless/ops/record/DeepMerger;
  #41 = Utf8               this
  #42 = Utf8               Lshapeless/ops/record/Remover;
  #43 = Utf8               Lshapeless/ops/record/DeepMerger;
  #44 = Utf8               hlistMerger1
  #45 = Utf8               (Lshapeless/ops/record/DeepMerger;)Lshapeless/ops/record/DeepMerger;
  #46 = Utf8               <H:Ljava/lang/Object;T::Lshapeless/HList;M::Lshapeless/HList;>(Lshapeless/ops/record/DeepMerger<TT;TM;>;)Lshapeless/ops/record/DeepMerger<Lshapeless/$colon$colon<TH;TT;>;TM;>;
  #47 = Utf8               hlistMerger1$
  #48 = Utf8               (Lshapeless/ops/record/LowPriorityDeepMerger;Lshapeless/ops/record/DeepMerger;)Lshapeless/ops/record/DeepMerger;
  #49 = NameAndType        #47:#48        // hlistMerger1$:(Lshapeless/ops/record/LowPriorityDeepMerger;Lshapeless/ops/record/DeepMerger;)Lshapeless/ops/record/DeepMerger;
  #50 = InterfaceMethodref #24.#49        // shapeless/ops/record/LowPriorityDeepMerger.hlistMerger1$:(Lshapeless/ops/record/LowPriorityDeepMerger;Lshapeless/ops/record/DeepMerger;)Lshapeless/ops/record/DeepMerger;
  #51 = Utf8               apply
  #52 = Utf8               <L::Lshapeless/HList;M::Lshapeless/HList;>(Lshapeless/ops/record/DeepMerger<TL;TM;>;)Lshapeless/ops/record/DeepMerger<TL;TM;>;
  #53 = Utf8               dm
  #54 = Utf8               hnilMerger
  #55 = Utf8               ()Lshapeless/ops/record/DeepMerger;
  #56 = Utf8               <M::Lshapeless/HList;>()Lshapeless/ops/record/DeepMerger<Lshapeless/HNil;TM;>;
  #57 = Methodref          #11.#19        // shapeless/ops/record/DeepMerger$$anon$8."<init>":()V
  #58 = Utf8               hlistMerger3
  #59 = Utf8               (Lshapeless/ops/record/Remover;Lshapeless/ops/record/DeepMerger;Lshapeless/ops/record/DeepMerger;)Lshapeless/ops/record/DeepMerger;
  #60 = Utf8               <K:Ljava/lang/Object;V::Lshapeless/HList;T::Lshapeless/HList;M::Lshapeless/HList;V1::Lshapeless/HList;MT::Lshapeless/HList;MO1::Lshapeless/HList;MO2::Lshapeless/HList;>(Lshapeless/ops/record/Remover<TM;TK;>;Lshapeless/ops/record/DeepMerger<TV;TV1;>;Lshapeless/ops/record/DeepMerger<TT;TMT;>;)Lshapeless/ops/record/DeepMerger<Lshapeless/$colon$colon<TV;TT;>;TM;>;
  #61 = Utf8               m1
  #62 = Utf8               m2
  #63 = Utf8               (Lshapeless/ops/record/Remover;Lshapeless/ops/record/DeepMerger;Lshapeless/ops/record/DeepMerger;)V
  #64 = NameAndType        #18:#63        // "<init>":(Lshapeless/ops/record/Remover;Lshapeless/ops/record/DeepMerger;Lshapeless/ops/record/DeepMerger;)V
  #65 = Methodref          #13.#64        // shapeless/ops/record/DeepMerger$$anon$9."<init>":(Lshapeless/ops/record/Remover;Lshapeless/ops/record/DeepMerger;Lshapeless/ops/record/DeepMerger;)V
  #66 = Utf8               writeReplace
  #67 = Utf8               ()Ljava/lang/Object;
  #68 = Utf8               scala/runtime/ModuleSerializationProxy
  #69 = Class              #68            // scala/runtime/ModuleSerializationProxy
  #70 = Utf8               (Ljava/lang/Class;)V
  #71 = NameAndType        #18:#70        // "<init>":(Ljava/lang/Class;)V
  #72 = Methodref          #69.#71        // scala/runtime/ModuleSerializationProxy."<init>":(Ljava/lang/Class;)V
  #73 = Methodref          #4.#19         // java/lang/Object."<init>":()V
  #74 = Utf8               Code
  #75 = Utf8               LineNumberTable
  #76 = Utf8               LocalVariableTable
  #77 = Utf8               Signature
  #78 = Utf8               MethodParameters
  #79 = Utf8               InnerClasses
  #80 = Utf8               SourceFile
  #81 = Utf8               ScalaInlineInfo
  #82 = Utf8               Scala
{
  public static final shapeless.ops.record.DeepMerger$ MODULE$;
    descriptor: Lshapeless/ops/record/DeepMerger$;
    flags: (0x0019) ACC_PUBLIC, ACC_STATIC, ACC_FINAL

  public static {};
    descriptor: ()V
    flags: (0x0009) ACC_PUBLIC, ACC_STATIC
    Code:
      stack=2, locals=0, args_size=0
         0: new           #2                  // class shapeless/ops/record/DeepMerger$
         3: dup
         4: invokespecial #20                 // Method "<init>":()V
         7: putstatic     #22                 // Field MODULE$:Lshapeless/ops/record/DeepMerger$;
        10: getstatic     #22                 // Field MODULE$:Lshapeless/ops/record/DeepMerger$;
        13: invokestatic  #28                 // InterfaceMethod shapeless/ops/record/LowPriorityDeepMerger.$init$:(Lshapeless/ops/record/LowPriorityDeepMerger;)V
        16: getstatic     #22                 // Field MODULE$:Lshapeless/ops/record/DeepMerger$;
        19: invokestatic  #31                 // InterfaceMethod shapeless/ops/record/LowPriorityDeepMerger0.$init$:(Lshapeless/ops/record/LowPriorityDeepMerger0;)V
        22: return
      LineNumberTable:
        line 228: 0

  public <K extends java.lang.Object, V extends java.lang.Object, T extends shapeless.HList, M extends shapeless.HList, MR extends shapeless.HList> shapeless.ops.record.DeepMerger<shapeless.$colon$colon<V, T>, M> hlistMerger2(shapeless.ops.record.Remover<M, K>, shapeless.ops.record.DeepMerger<T, MR>);
    descriptor: (Lshapeless/ops/record/Remover;Lshapeless/ops/record/DeepMerger;)Lshapeless/ops/record/DeepMerger;
    flags: (0x0001) ACC_PUBLIC
    Code:
      stack=3, locals=3, args_size=3
         0: aload_0
         1: aload_1
         2: aload_2
         3: invokestatic  #40                 // InterfaceMethod shapeless/ops/record/LowPriorityDeepMerger0.hlistMerger2$:(Lshapeless/ops/record/LowPriorityDeepMerger0;Lshapeless/ops/record/Remover;Lshapeless/ops/record/DeepMerger;)Lshapeless/ops/record/DeepMerger;
         6: areturn
      LineNumberTable:
        line 228: 0
      LocalVariableTable:
        Start  Length  Slot  Name   Signature
            0       7     0  this   Lshapeless/ops/record/DeepMerger$;
            0       7     1    rm   Lshapeless/ops/record/Remover;
            0       7     2    mt   Lshapeless/ops/record/DeepMerger;
    Signature: #34                          // <K:Ljava/lang/Object;V:Ljava/lang/Object;T::Lshapeless/HList;M::Lshapeless/HList;MR::Lshapeless/HList;>(Lshapeless/ops/record/Remover<TM;TK;>;Lshapeless/ops/record/DeepMerger<TT;TMR;>;)Lshapeless/ops/record/DeepMerger<Lshapeless/$colon$colon<TV;TT;>;TM;>;
    MethodParameters:
      Name                           Flags
      rm                             final
      mt                             final

  public <H extends java.lang.Object, T extends shapeless.HList, M extends shapeless.HList> shapeless.ops.record.DeepMerger<shapeless.$colon$colon<H, T>, M> hlistMerger1(shapeless.ops.record.DeepMerger<T, M>);
    descriptor: (Lshapeless/ops/record/DeepMerger;)Lshapeless/ops/record/DeepMerger;
    flags: (0x0001) ACC_PUBLIC
    Code:
      stack=2, locals=2, args_size=2
         0: aload_0
         1: aload_1
         2: invokestatic  #50                 // InterfaceMethod shapeless/ops/record/LowPriorityDeepMerger.hlistMerger1$:(Lshapeless/ops/record/LowPriorityDeepMerger;Lshapeless/ops/record/DeepMerger;)Lshapeless/ops/record/DeepMerger;
         5: areturn
      LineNumberTable:
        line 228: 0
      LocalVariableTable:
        Start  Length  Slot  Name   Signature
            0       6     0  this   Lshapeless/ops/record/DeepMerger$;
            0       6     1    mt   Lshapeless/ops/record/DeepMerger;
    Signature: #46                          // <H:Ljava/lang/Object;T::Lshapeless/HList;M::Lshapeless/HList;>(Lshapeless/ops/record/DeepMerger<TT;TM;>;)Lshapeless/ops/record/DeepMerger<Lshapeless/$colon$colon<TH;TT;>;TM;>;
    MethodParameters:
      Name                           Flags
      mt                             final

  public <L extends shapeless.HList, M extends shapeless.HList> shapeless.ops.record.DeepMerger<L, M> apply(shapeless.ops.record.DeepMerger<L, M>);
    descriptor: (Lshapeless/ops/record/DeepMerger;)Lshapeless/ops/record/DeepMerger;
    flags: (0x0001) ACC_PUBLIC
    Code:
      stack=1, locals=2, args_size=2
         0: aload_1
         1: areturn
      LineNumberTable:
        line 230: 0
      LocalVariableTable:
        Start  Length  Slot  Name   Signature
            0       2     0  this   Lshapeless/ops/record/DeepMerger$;
            0       2     1    dm   Lshapeless/ops/record/DeepMerger;
    Signature: #52                          // <L::Lshapeless/HList;M::Lshapeless/HList;>(Lshapeless/ops/record/DeepMerger<TL;TM;>;)Lshapeless/ops/record/DeepMerger<TL;TM;>;
    MethodParameters:
      Name                           Flags
      dm                             final

  public <M extends shapeless.HList> shapeless.ops.record.DeepMerger<shapeless.HNil, M> hnilMerger();
    descriptor: ()Lshapeless/ops/record/DeepMerger;
    flags: (0x0001) ACC_PUBLIC
    Code:
      stack=2, locals=1, args_size=1
         0: new           #11                 // class shapeless/ops/record/DeepMerger$$anon$8
         3: dup
         4: invokespecial #57                 // Method shapeless/ops/record/DeepMerger$$anon$8."<init>":()V
         7: areturn
      LineNumberTable:
        line 233: 0
      LocalVariableTable:
        Start  Length  Slot  Name   Signature
            0       8     0  this   Lshapeless/ops/record/DeepMerger$;
    Signature: #56                          // <M::Lshapeless/HList;>()Lshapeless/ops/record/DeepMerger<Lshapeless/HNil;TM;>;

  public <K extends java.lang.Object, V extends shapeless.HList, T extends shapeless.HList, M extends shapeless.HList, V1 extends shapeless.HList, MT extends shapeless.HList, MO1 extends shapeless.HList, MO2 extends shapeless.HList> shapeless.ops.record.DeepMerger<shapeless.$colon$colon<V, T>, M> hlistMerger3(shapeless.ops.record.Remover<M, K>, shapeless.ops.record.DeepMerger<V, V1>, shapeless.ops.record.DeepMerger<T, MT>);
    descriptor: (Lshapeless/ops/record/Remover;Lshapeless/ops/record/DeepMerger;Lshapeless/ops/record/DeepMerger;)Lshapeless/ops/record/DeepMerger;
    flags: (0x0001) ACC_PUBLIC
    Code:
      stack=5, locals=4, args_size=4
         0: new           #13                 // class shapeless/ops/record/DeepMerger$$anon$9
         3: dup
         4: aload_1
         5: aload_2
         6: aload_3
         7: invokespecial #65                 // Method shapeless/ops/record/DeepMerger$$anon$9."<init>":(Lshapeless/ops/record/Remover;Lshapeless/ops/record/DeepMerger;Lshapeless/ops/record/DeepMerger;)V
        10: areturn
      LineNumberTable:
        line 244: 0
      LocalVariableTable:
        Start  Length  Slot  Name   Signature
            0      11     0  this   Lshapeless/ops/record/DeepMerger$;
            0      11     1    rm   Lshapeless/ops/record/Remover;
            0      11     2    m1   Lshapeless/ops/record/DeepMerger;
            0      11     3    m2   Lshapeless/ops/record/DeepMerger;
    Signature: #60                          // <K:Ljava/lang/Object;V::Lshapeless/HList;T::Lshapeless/HList;M::Lshapeless/HList;V1::Lshapeless/HList;MT::Lshapeless/HList;MO1::Lshapeless/HList;MO2::Lshapeless/HList;>(Lshapeless/ops/record/Remover<TM;TK;>;Lshapeless/ops/record/DeepMerger<TV;TV1;>;Lshapeless/ops/record/DeepMerger<TT;TMT;>;)Lshapeless/ops/record/DeepMerger<Lshapeless/$colon$colon<TV;TT;>;TM;>;
    MethodParameters:
      Name                           Flags
      rm                             final
      m1                             final
      m2                             final

  private java.lang.Object writeReplace();
    descriptor: ()Ljava/lang/Object;
    flags: (0x0002) ACC_PRIVATE
    Code:
      stack=3, locals=1, args_size=1
         0: new           #69                 // class scala/runtime/ModuleSerializationProxy
         3: dup
         4: ldc           #2                  // class shapeless/ops/record/DeepMerger$
         6: invokespecial #72                 // Method scala/runtime/ModuleSerializationProxy."<init>":(Ljava/lang/Class;)V
         9: areturn
      LineNumberTable:
        line 228: 0
      LocalVariableTable:
        Start  Length  Slot  Name   Signature
            0      10     0  this   Lshapeless/ops/record/DeepMerger$;

  private shapeless.ops.record.DeepMerger$();
    descriptor: ()V
    flags: (0x0002) ACC_PRIVATE
    Code:
      stack=1, locals=1, args_size=1
         0: aload_0
         1: invokespecial #73                 // Method java/lang/Object."<init>":()V
         4: return
      LineNumberTable:
        line 228: 0
      LocalVariableTable:
        Start  Length  Slot  Name   Signature
            0       5     0  this   Lshapeless/ops/record/DeepMerger$;
}
InnerClasses:
  public final #11;                       // class shapeless/ops/record/DeepMerger$$anon$8
  public final #13;                       // class shapeless/ops/record/DeepMerger$$anon$9
SourceFile: "records.scala"
  ScalaInlineInfo: length = 0x27 (unknown attribute)
   01 01 00 07 00 12 00 11 01 00 33 00 2D 01 00 2C
   00 2D 01 00 20 00 21 01 00 3A 00 3B 01 00 36 00
   37 01 00 42 00 43 01
  Scala: length = 0x0 (unknown attribute)

