Classfile /Users/mw/Projects/slang-braindump/.jar/jar8/assemble/slang-braindump/assemble/content/shapeless/ops/record/Fields$.class
  Last modified May 29, 2022; size 1787 bytes
  SHA-256 checksum 277d88f5adf5fee3c1d771c8d8c52e04a4d92827d0447d51078975ebf2ac94ce
  Compiled from "records.scala"
public final class shapeless.ops.record.Fields$ implements java.io.Serializable
  minor version: 0
  major version: 52
  flags: (0x0031) ACC_PUBLIC, ACC_FINAL, ACC_SUPER
  this_class: #2                          // shapeless/ops/record/Fields$
  super_class: #4                         // java/lang/Object
  interfaces: 1, fields: 1, methods: 6, attributes: 4
Constant pool:
   #1 = Utf8               shapeless/ops/record/Fields$
   #2 = Class              #1             // shapeless/ops/record/Fields$
   #3 = Utf8               java/lang/Object
   #4 = Class              #3             // java/lang/Object
   #5 = Utf8               java/io/Serializable
   #6 = Class              #5             // java/io/Serializable
   #7 = Utf8               records.scala
   #8 = Utf8               shapeless/ops/record/Fields$$anon$34
   #9 = Class              #8             // shapeless/ops/record/Fields$$anon$34
  #10 = Utf8               shapeless/ops/record/Fields$$anon$35
  #11 = Class              #10            // shapeless/ops/record/Fields$$anon$35
  #12 = Utf8               MODULE$
  #13 = Utf8               Lshapeless/ops/record/Fields$;
  #14 = Utf8               <clinit>
  #15 = Utf8               ()V
  #16 = Utf8               <init>
  #17 = NameAndType        #16:#15        // "<init>":()V
  #18 = Methodref          #2.#17         // shapeless/ops/record/Fields$."<init>":()V
  #19 = NameAndType        #12:#13        // MODULE$:Lshapeless/ops/record/Fields$;
  #20 = Fieldref           #2.#19         // shapeless/ops/record/Fields$.MODULE$:Lshapeless/ops/record/Fields$;
  #21 = Utf8               apply
  #22 = Utf8               (Lshapeless/ops/record/Fields;)Lshapeless/ops/record/Fields;
  #23 = Utf8               <L::Lshapeless/HList;>(Lshapeless/ops/record/Fields<TL;>;)Lshapeless/ops/record/Fields<TL;>;
  #24 = Utf8               fields
  #25 = Utf8               this
  #26 = Utf8               Lshapeless/ops/record/Fields;
  #27 = Utf8               hnilFields
  #28 = Utf8               ()Lshapeless/ops/record/Fields;
  #29 = Utf8               <L::Lshapeless/HNil;>()Lshapeless/ops/record/Fields<TL;>;
  #30 = Methodref          #9.#17         // shapeless/ops/record/Fields$$anon$34."<init>":()V
  #31 = Utf8               hconsFields
  #32 = Utf8               (Lshapeless/Witness;Lshapeless/ops/record/Fields;)Lshapeless/ops/record/Fields;
  #33 = Utf8               <K:Ljava/lang/Object;V:Ljava/lang/Object;T::Lshapeless/HList;>(Lshapeless/Witness;Lshapeless/ops/record/Fields<TT;>;)Lshapeless/ops/record/Fields<Lshapeless/$colon$colon<TV;TT;>;>;
  #34 = Utf8               key
  #35 = Utf8               tailFields
  #36 = Utf8               (Lshapeless/Witness;Lshapeless/ops/record/Fields;)V
  #37 = NameAndType        #16:#36        // "<init>":(Lshapeless/Witness;Lshapeless/ops/record/Fields;)V
  #38 = Methodref          #11.#37        // shapeless/ops/record/Fields$$anon$35."<init>":(Lshapeless/Witness;Lshapeless/ops/record/Fields;)V
  #39 = Utf8               Lshapeless/Witness;
  #40 = Utf8               writeReplace
  #41 = Utf8               ()Ljava/lang/Object;
  #42 = Utf8               scala/runtime/ModuleSerializationProxy
  #43 = Class              #42            // scala/runtime/ModuleSerializationProxy
  #44 = Utf8               (Ljava/lang/Class;)V
  #45 = NameAndType        #16:#44        // "<init>":(Ljava/lang/Class;)V
  #46 = Methodref          #43.#45        // scala/runtime/ModuleSerializationProxy."<init>":(Ljava/lang/Class;)V
  #47 = Methodref          #4.#17         // java/lang/Object."<init>":()V
  #48 = Utf8               Code
  #49 = Utf8               LineNumberTable
  #50 = Utf8               LocalVariableTable
  #51 = Utf8               Signature
  #52 = Utf8               MethodParameters
  #53 = Utf8               InnerClasses
  #54 = Utf8               SourceFile
  #55 = Utf8               ScalaInlineInfo
  #56 = Utf8               Scala
{
  public static final shapeless.ops.record.Fields$ MODULE$;
    descriptor: Lshapeless/ops/record/Fields$;
    flags: (0x0019) ACC_PUBLIC, ACC_STATIC, ACC_FINAL

  public static {};
    descriptor: ()V
    flags: (0x0009) ACC_PUBLIC, ACC_STATIC
    Code:
      stack=2, locals=0, args_size=0
         0: new           #2                  // class shapeless/ops/record/Fields$
         3: dup
         4: invokespecial #18                 // Method "<init>":()V
         7: putstatic     #20                 // Field MODULE$:Lshapeless/ops/record/Fields$;
        10: return
      LineNumberTable:
        line 706: 0

  public <L extends shapeless.HList> shapeless.ops.record.Fields<L> apply(shapeless.ops.record.Fields<L>);
    descriptor: (Lshapeless/ops/record/Fields;)Lshapeless/ops/record/Fields;
    flags: (0x0001) ACC_PUBLIC
    Code:
      stack=1, locals=2, args_size=2
         0: aload_1
         1: areturn
      LineNumberTable:
        line 707: 0
      LocalVariableTable:
        Start  Length  Slot  Name   Signature
            0       2     0  this   Lshapeless/ops/record/Fields$;
            0       2     1 fields   Lshapeless/ops/record/Fields;
    Signature: #23                          // <L::Lshapeless/HList;>(Lshapeless/ops/record/Fields<TL;>;)Lshapeless/ops/record/Fields<TL;>;
    MethodParameters:
      Name                           Flags
      fields                         final

  public <L extends shapeless.HNil> shapeless.ops.record.Fields<L> hnilFields();
    descriptor: ()Lshapeless/ops/record/Fields;
    flags: (0x0001) ACC_PUBLIC
    Code:
      stack=2, locals=1, args_size=1
         0: new           #9                  // class shapeless/ops/record/Fields$$anon$34
         3: dup
         4: invokespecial #30                 // Method shapeless/ops/record/Fields$$anon$34."<init>":()V
         7: areturn
      LineNumberTable:
        line 712: 0
      LocalVariableTable:
        Start  Length  Slot  Name   Signature
            0       8     0  this   Lshapeless/ops/record/Fields$;
    Signature: #29                          // <L::Lshapeless/HNil;>()Lshapeless/ops/record/Fields<TL;>;

  public <K extends java.lang.Object, V extends java.lang.Object, T extends shapeless.HList> shapeless.ops.record.Fields<shapeless.$colon$colon<V, T>> hconsFields(shapeless.Witness, shapeless.ops.record.Fields<T>);
    descriptor: (Lshapeless/Witness;Lshapeless/ops/record/Fields;)Lshapeless/ops/record/Fields;
    flags: (0x0001) ACC_PUBLIC
    Code:
      stack=4, locals=3, args_size=3
         0: new           #11                 // class shapeless/ops/record/Fields$$anon$35
         3: dup
         4: aload_1
         5: aload_2
         6: invokespecial #38                 // Method shapeless/ops/record/Fields$$anon$35."<init>":(Lshapeless/Witness;Lshapeless/ops/record/Fields;)V
         9: areturn
      LineNumberTable:
        line 721: 0
      LocalVariableTable:
        Start  Length  Slot  Name   Signature
            0      10     0  this   Lshapeless/ops/record/Fields$;
            0      10     1   key   Lshapeless/Witness;
            0      10     2 tailFields   Lshapeless/ops/record/Fields;
    Signature: #33                          // <K:Ljava/lang/Object;V:Ljava/lang/Object;T::Lshapeless/HList;>(Lshapeless/Witness;Lshapeless/ops/record/Fields<TT;>;)Lshapeless/ops/record/Fields<Lshapeless/$colon$colon<TV;TT;>;>;
    MethodParameters:
      Name                           Flags
      key                            final
      tailFields                     final

  private java.lang.Object writeReplace();
    descriptor: ()Ljava/lang/Object;
    flags: (0x0002) ACC_PRIVATE
    Code:
      stack=3, locals=1, args_size=1
         0: new           #43                 // class scala/runtime/ModuleSerializationProxy
         3: dup
         4: ldc           #2                  // class shapeless/ops/record/Fields$
         6: invokespecial #46                 // Method scala/runtime/ModuleSerializationProxy."<init>":(Ljava/lang/Class;)V
         9: areturn
      LineNumberTable:
        line 706: 0
      LocalVariableTable:
        Start  Length  Slot  Name   Signature
            0      10     0  this   Lshapeless/ops/record/Fields$;

  private shapeless.ops.record.Fields$();
    descriptor: ()V
    flags: (0x0002) ACC_PRIVATE
    Code:
      stack=1, locals=1, args_size=1
         0: aload_0
         1: invokespecial #47                 // Method java/lang/Object."<init>":()V
         4: return
      LineNumberTable:
        line 733: 0
        line 706: 4
      LocalVariableTable:
        Start  Length  Slot  Name   Signature
            0       5     0  this   Lshapeless/ops/record/Fields$;
}
InnerClasses:
  public final #9;                        // class shapeless/ops/record/Fields$$anon$34
  public final #11;                       // class shapeless/ops/record/Fields$$anon$35
SourceFile: "records.scala"
  ScalaInlineInfo: length = 0x1D (unknown attribute)
   01 01 00 05 00 10 00 0F 01 00 15 00 16 01 00 1F
   00 20 01 00 1B 00 1C 01 00 28 00 29 01
  Scala: length = 0x0 (unknown attribute)

