Classfile /Users/mw/Projects/slang-braindump/.jar/jar8/assemble/slang-braindump/assemble/content/shapeless/ops/record/Keys.class
  Last modified May 29, 2022; size 2076 bytes
  SHA-256 checksum 3cab9b34e22d277284c225e47b0062beaf098da2f8094e17639794f144cb1644
  Compiled from "records.scala"
public interface shapeless.ops.record.Keys<L extends shapeless.HList> extends shapeless.package$DepFn0, java.io.Serializable
  minor version: 0
  major version: 52
  flags: (0x0601) ACC_PUBLIC, ACC_INTERFACE, ACC_ABSTRACT
  this_class: #2                          // shapeless/ops/record/Keys
  super_class: #5                         // java/lang/Object
  interfaces: 2, fields: 0, methods: 2, attributes: 6
Constant pool:
   #1 = Utf8               shapeless/ops/record/Keys
   #2 = Class              #1             // shapeless/ops/record/Keys
   #3 = Utf8               <L::Lshapeless/HList;>Ljava/lang/Object;Lshapeless/package$DepFn0;Ljava/io/Serializable;
   #4 = Utf8               java/lang/Object
   #5 = Class              #4             // java/lang/Object
   #6 = Utf8               shapeless/package$DepFn0
   #7 = Class              #6             // shapeless/package$DepFn0
   #8 = Utf8               java/io/Serializable
   #9 = Class              #8             // java/io/Serializable
  #10 = Utf8               records.scala
  #11 = Utf8               Lscala/reflect/ScalaSignature;
  #12 = Utf8               bytes
  #13 = Utf8               \u0006\u0005\u0005Uba\u0002\u0006\f!\u0003\r\nA\u0005\u0003\u0006[\u0001\u0011\tAL\u0004\u0006o-A\t\u0001\u000f\u0004\u0006\u0015-A\tA\u000f\u0005\u0006\u0005\u000e!\ta\u0011\u0005\u0006\t\u000e!\t!R\u0003\u0005\u0013\u000e\u0001!\nC\u0003^\u0007\u0011\ra\fC\u0003h\u0007\u0011\r\u0001\u000eC\u0005\u0002&\r\t\t\u0011\"\u0003\u0002(\t!1*Z=t\u0015\taQ\"\u0001\u0004sK\u000e|\'\u000f\u001a\u0006\u0003\u001d=\t1a\u001c9t\u0015\u0005\u0001\u0012!C:iCB,G.Z:t\u0007\u0001)\"aE\u001b\u0014\t\u0001!\"D\t\t\u0003+ai\u0011A\u0006\u0006\u0002/\u0005)1oY1mC&\u0011\u0011D\u0006\u0002\u0007\u0003:L(+\u001a4\u0011\u0005mybB\u0001\u000f\u001e\u001b\u0005y\u0011B\u0001\u0010\u0010\u0003\u001d\u0001\u0018mY6bO\u0016L!\u0001I\u0011\u0003\r\u0011+\u0007O\u001281\u0015\tqr\u0002\u0005\u0002$U9\u0011A%\u000b\b\u0003K!j\u0011A\n\u0006\u0003OE\ta\u0001\u0010:p_Rt\u0014\"A\f\n\u0005y1\u0012BA\u0016-\u00051\u0019VM]5bY&T\u0018M\u00197f\u0015\tqbCA\u0002PkR\f\"a\f\u001a\u0011\u0005U\u0001\u0014BA\u0019\u0017\u0005\u001dqu\u000e\u001e5j]\u001e\u0004\"\u0001H\u001a\n\u0005Qz!!\u0002%MSN$H!\u0002\u001c\u0001\u0005\u0004q#!\u0001\'\u0002\t-+\u0017p\u001d\t\u0003s\ri\u0011aC\n\u0004\u0007QY\u0004C\u0001\u001fB\u001b\u0005i$B\u0001 @\u0003\tIwNC\u0001A\u0003\u0011Q\u0017M^1\n\u0005-j\u0014A\u0002\u001fj]&$h\bF\u00019\u0003\u0015\t\u0007\u000f\u001d7z+\t1u\u000b\u0006\u0002H5B!\u0001J\u0002,Y\u001b\u0005\u0019!aA!vqV\u00191*\u0015+\u0013\u00051se\u0001B\'\u0004\u0001-\u0013A\u0002\u0010:fM&tW-\\3oiz\u00022!\u000f\u0001P!\t\u0001\u0016\u000b\u0004\u0001\u0005\u000bY2!\u0019\u0001\u0018\u0006\t5b\u0005e\u0015\t\u0003!R#Q!\u0016\u0004C\u00029\u0012AaT;uaA\u0011\u0001k\u0016\u0003\u0006m\u0015\u0011\rA\f\t\u00033\u0006q!\u0001\u0015.\t\u000bm+\u00019\u0001/\u0002\t-,\u0017p\u001d\t\u0004s\u00011\u0016\u0001\u00035oS2\\U-_:\u0016\u0005}\u0013W#\u00011\u0011\t!3\u0011\r\u001a\t\u0003!\n$QAN\u0004C\u0002\r\f\"a\f3\u0011\u0005q)\u0017B\u00014\u0010\u0005\u0011Ae*\u001b7\u0002\u0013!d\u0017n\u001d;LKf\u001cX#B5y\u007f\u0006\u0015A#\u00026\u0002\u0016\u0005=\u0001#\u0002%\u0007W\u0006%\u0001#\u0002\u000fm]\u0006\r\u0011BA7\u0010\u00051!3m\u001c7p]\u0012\u001aw\u000e\\8o!\u0011yGo\u001e@\u000f\u0005A\u0014hBA\u0013r\u0013\u0005\u0001\u0012BA:\u0010\u0003!a\u0017MY3mY\u0016$\u0017BA;w\u0005%1\u0015.\u001a7e)f\u0004XM\u0003\u0002t\u001fA\u0011\u0001\u000b\u001f\u0003\u0006s\"\u0011\rA\u001f\u0002\u0002\u0017F\u0011qf\u001f\t\u0003+qL!! \f\u0003\u0007\u0005s\u0017\u0010\u0005\u0002Q\u007f\u00121\u0011\u0011\u0001\u0005C\u0002i\u0014\u0011A\u0016\t\u0004!\u0006\u0015AABA\u0004\u0011\t\u0007aFA\u0001U!\u0015aBn^A\u0006!\r\ti!\u0001\b\u0004!\u0006=\u0001bBA\t\u0011\u0001\u000f\u00111C\u0001\u0003WR\u0004B!\u000f\u0001\u0002\u0004!9\u0011q\u0003\u0005A\u0004\u0005e\u0011AA<l!\u0015\tY\"!\tx\u001d\ra\u0012QD\u0005\u0004\u0003?y\u0011aB,ji:,7o]\u0005\u0004\u0013\u0006\r\"bAA\u0010\u001f\u0005aqO]5uKJ+\u0007\u000f\\1dKR\u0011\u0011\u0011\u0006\t\u0005\u0003W\t\t$\u0004\u0002\u0002.)\u0019\u0011qF \u0002\t1\fgnZ\u0005\u0005\u0003g\tiC\u0001\u0004PE*,7\r\u001e
  #14 = Utf8               shapeless/package
  #15 = Class              #14            // shapeless/package
  #16 = Utf8               DepFn0
  #17 = Utf8               hlistKeys
  #18 = Utf8               (Lshapeless/Witness;Lshapeless/ops/record/Keys;)Lshapeless/ops/record/Keys;
  #19 = Utf8               <K:Ljava/lang/Object;V:Ljava/lang/Object;T::Lshapeless/HList;>(Lshapeless/Witness;Lshapeless/ops/record/Keys<TT;>;)Lshapeless/ops/record/Keys<Lshapeless/$colon$colon<TV;TT;>;>;
  #20 = Utf8               wk
  #21 = Utf8               kt
  #22 = Utf8               shapeless/ops/record/Keys$
  #23 = Class              #22            // shapeless/ops/record/Keys$
  #24 = Utf8               MODULE$
  #25 = Utf8               Lshapeless/ops/record/Keys$;
  #26 = NameAndType        #24:#25        // MODULE$:Lshapeless/ops/record/Keys$;
  #27 = Fieldref           #23.#26        // shapeless/ops/record/Keys$.MODULE$:Lshapeless/ops/record/Keys$;
  #28 = NameAndType        #17:#18        // hlistKeys:(Lshapeless/Witness;Lshapeless/ops/record/Keys;)Lshapeless/ops/record/Keys;
  #29 = Methodref          #23.#28        // shapeless/ops/record/Keys$.hlistKeys:(Lshapeless/Witness;Lshapeless/ops/record/Keys;)Lshapeless/ops/record/Keys;
  #30 = Utf8               hnilKeys
  #31 = Utf8               ()Lshapeless/ops/record/Keys;
  #32 = Utf8               <L::Lshapeless/HNil;>()Lshapeless/ops/record/Keys<TL;>;
  #33 = NameAndType        #30:#31        // hnilKeys:()Lshapeless/ops/record/Keys;
  #34 = Methodref          #23.#33        // shapeless/ops/record/Keys$.hnilKeys:()Lshapeless/ops/record/Keys;
  #35 = Utf8               Code
  #36 = Utf8               Signature
  #37 = Utf8               MethodParameters
  #38 = Utf8               InnerClasses
  #39 = Utf8               SourceFile
  #40 = Utf8               RuntimeVisibleAnnotations
  #41 = Utf8               ScalaInlineInfo
  #42 = Utf8               ScalaSig
{
  public static <K extends java.lang.Object, V extends java.lang.Object, T extends shapeless.HList> shapeless.ops.record.Keys<shapeless.$colon$colon<V, T>> hlistKeys(shapeless.Witness, shapeless.ops.record.Keys<T>);
    descriptor: (Lshapeless/Witness;Lshapeless/ops/record/Keys;)Lshapeless/ops/record/Keys;
    flags: (0x0009) ACC_PUBLIC, ACC_STATIC
    Code:
      stack=3, locals=2, args_size=2
         0: getstatic     #27                 // Field shapeless/ops/record/Keys$.MODULE$:Lshapeless/ops/record/Keys$;
         3: aload_0
         4: aload_1
         5: invokevirtual #29                 // Method shapeless/ops/record/Keys$.hlistKeys:(Lshapeless/Witness;Lshapeless/ops/record/Keys;)Lshapeless/ops/record/Keys;
         8: areturn
    Signature: #19                          // <K:Ljava/lang/Object;V:Ljava/lang/Object;T::Lshapeless/HList;>(Lshapeless/Witness;Lshapeless/ops/record/Keys<TT;>;)Lshapeless/ops/record/Keys<Lshapeless/$colon$colon<TV;TT;>;>;
    MethodParameters:
      Name                           Flags
      wk                             final
      kt                             final

  public static <L extends shapeless.HNil> shapeless.ops.record.Keys<L> hnilKeys();
    descriptor: ()Lshapeless/ops/record/Keys;
    flags: (0x0009) ACC_PUBLIC, ACC_STATIC
    Code:
      stack=1, locals=0, args_size=0
         0: getstatic     #27                 // Field shapeless/ops/record/Keys$.MODULE$:Lshapeless/ops/record/Keys$;
         3: invokevirtual #34                 // Method shapeless/ops/record/Keys$.hnilKeys:()Lshapeless/ops/record/Keys;
         6: areturn
    Signature: #32                          // <L::Lshapeless/HNil;>()Lshapeless/ops/record/Keys<TL;>;
}
InnerClasses:
  public static #16= #7 of #15;           // DepFn0=class shapeless/package$DepFn0 of class shapeless/package
Signature: #3                           // <L::Lshapeless/HList;>Ljava/lang/Object;Lshapeless/package$DepFn0;Ljava/io/Serializable;
SourceFile: "records.scala"
RuntimeVisibleAnnotations:
  0: #11(#12=s#13)
    scala.reflect.ScalaSignature(
      bytes="\u0006\u0005\u0005Uba\u0002\u0006\f!\u0003\r\nA\u0005\u0003\u0006[\u0001\u0011\tAL\u0004\u0006o-A\t\u0001\u000f\u0004\u0006\u0015-A\tA\u000f\u0005\u0006\u0005\u000e!\ta\u0011\u0005\u0006\t\u000e!\t!R\u0003\u0005\u0013\u000e\u0001!\nC\u0003^\u0007\u0011\ra\fC\u0003h\u0007\u0011\r\u0001\u000eC\u0005\u0002&\r\t\t\u0011\"\u0003\u0002(\t!1*Z=t\u0015\taQ\"\u0001\u0004sK\u000e|\'\u000f\u001a\u0006\u0003\u001d=\t1a\u001c9t\u0015\u0005\u0001\u0012!C:iCB,G.Z:t\u0007\u0001)\"aE\u001b\u0014\t\u0001!\"D\t\t\u0003+ai\u0011A\u0006\u0006\u0002/\u0005)1oY1mC&\u0011\u0011D\u0006\u0002\u0007\u0003:L(+\u001a4\u0011\u0005mybB\u0001\u000f\u001e\u001b\u0005y\u0011B\u0001\u0010\u0010\u0003\u001d\u0001\u0018mY6bO\u0016L!\u0001I\u0011\u0003\r\u0011+\u0007O\u001281\u0015\tqr\u0002\u0005\u0002$U9\u0011A%\u000b\b\u0003K!j\u0011A\n\u0006\u0003OE\ta\u0001\u0010:p_Rt\u0014\"A\f\n\u0005y1\u0012BA\u0016-\u00051\u0019VM]5bY&T\u0018M\u00197f\u0015\tqbCA\u0002PkR\f\"a\f\u001a\u0011\u0005U\u0001\u0014BA\u0019\u0017\u0005\u001dqu\u000e\u001e5j]\u001e\u0004\"\u0001H\u001a\n\u0005Qz!!\u0002%MSN$H!\u0002\u001c\u0001\u0005\u0004q#!\u0001\'\u0002\t-+\u0017p\u001d\t\u0003s\ri\u0011aC\n\u0004\u0007QY\u0004C\u0001\u001fB\u001b\u0005i$B\u0001 @\u0003\tIwNC\u0001A\u0003\u0011Q\u0017M^1\n\u0005-j\u0014A\u0002\u001fj]&$h\bF\u00019\u0003\u0015\t\u0007\u000f\u001d7z+\t1u\u000b\u0006\u0002H5B!\u0001J\u0002,Y\u001b\u0005\u0019!aA!vqV\u00191*\u0015+\u0013\u00051se\u0001B\'\u0004\u0001-\u0013A\u0002\u0010:fM&tW-\\3oiz\u00022!\u000f\u0001P!\t\u0001\u0016\u000b\u0004\u0001\u0005\u000bY2!\u0019\u0001\u0018\u0006\t5b\u0005e\u0015\t\u0003!R#Q!\u0016\u0004C\u00029\u0012AaT;uaA\u0011\u0001k\u0016\u0003\u0006m\u0015\u0011\rA\f\t\u00033\u0006q!\u0001\u0015.\t\u000bm+\u00019\u0001/\u0002\t-,\u0017p\u001d\t\u0004s\u00011\u0016\u0001\u00035oS2\\U-_:\u0016\u0005}\u0013W#\u00011\u0011\t!3\u0011\r\u001a\t\u0003!\n$QAN\u0004C\u0002\r\f\"a\f3\u0011\u0005q)\u0017B\u00014\u0010\u0005\u0011Ae*\u001b7\u0002\u0013!d\u0017n\u001d;LKf\u001cX#B5y\u007f\u0006\u0015A#\u00026\u0002\u0016\u0005=\u0001#\u0002%\u0007W\u0006%\u0001#\u0002\u000fm]\u0006\r\u0011BA7\u0010\u00051!3m\u001c7p]\u0012\u001aw\u000e\\8o!\u0011yGo\u001e@\u000f\u0005A\u0014hBA\u0013r\u0013\u0005\u0001\u0012BA:\u0010\u0003!a\u0017MY3mY\u0016$\u0017BA;w\u0005%1\u0015.\u001a7e)f\u0004XM\u0003\u0002t\u001fA\u0011\u0001\u000b\u001f\u0003\u0006s\"\u0011\rA\u001f\u0002\u0002\u0017F\u0011qf\u001f\t\u0003+qL!! \f\u0003\u0007\u0005s\u0017\u0010\u0005\u0002Q\u007f\u00121\u0011\u0011\u0001\u0005C\u0002i\u0014\u0011A\u0016\t\u0004!\u0006\u0015AABA\u0004\u0011\t\u0007aFA\u0001U!\u0015aBn^A\u0006!\r\ti!\u0001\b\u0004!\u0006=\u0001bBA\t\u0011\u0001\u000f\u00111C\u0001\u0003WR\u0004B!\u000f\u0001\u0002\u0004!9\u0011q\u0003\u0005A\u0004\u0005e\u0011AA<l!\u0015\tY\"!\tx\u001d\ra\u0012QD\u0005\u0004\u0003?y\u0011aB,ji:,7o]\u0005\u0004\u0013\u0006\r\"bAA\u0010\u001f\u0005aqO]5uKJ+\u0007\u000f\\1dKR\u0011\u0011\u0011\u0006\t\u0005\u0003W\t\t$\u0004\u0002\u0002.)\u0019\u0011qF \u0002\t1\fgnZ\u0005\u0005\u0003g\tiC\u0001\u0004PE*,7\r\u001e"
    )
  ScalaInlineInfo: length = 0x4 (unknown attribute)
   01 00 00 00
  ScalaSig: length = 0x3 (unknown attribute)
   05 02 00
