Classfile /Users/mw/Projects/slang-braindump/.jar/jar8/assemble/slang-braindump/assemble/content/shapeless/ops/record/Modifier$.class
  Last modified May 29, 2022; size 1926 bytes
  SHA-256 checksum a449b7eb2adba4235fea8c8068a6e94751a5d22a265822336223ad2ec7d86463
  Compiled from "records.scala"
public final class shapeless.ops.record.Modifier$ implements java.io.Serializable
  minor version: 0
  major version: 52
  flags: (0x0031) ACC_PUBLIC, ACC_FINAL, ACC_SUPER
  this_class: #2                          // shapeless/ops/record/Modifier$
  super_class: #4                         // java/lang/Object
  interfaces: 1, fields: 1, methods: 6, attributes: 4
Constant pool:
   #1 = Utf8               shapeless/ops/record/Modifier$
   #2 = Class              #1             // shapeless/ops/record/Modifier$
   #3 = Utf8               java/lang/Object
   #4 = Class              #3             // java/lang/Object
   #5 = Utf8               java/io/Serializable
   #6 = Class              #5             // java/io/Serializable
   #7 = Utf8               records.scala
   #8 = Utf8               shapeless/ops/record/Modifier$$anon$17
   #9 = Class              #8             // shapeless/ops/record/Modifier$$anon$17
  #10 = Utf8               shapeless/ops/record/Modifier$$anon$18
  #11 = Class              #10            // shapeless/ops/record/Modifier$$anon$18
  #12 = Utf8               MODULE$
  #13 = Utf8               Lshapeless/ops/record/Modifier$;
  #14 = Utf8               <clinit>
  #15 = Utf8               ()V
  #16 = Utf8               <init>
  #17 = NameAndType        #16:#15        // "<init>":()V
  #18 = Methodref          #2.#17         // shapeless/ops/record/Modifier$."<init>":()V
  #19 = NameAndType        #12:#13        // MODULE$:Lshapeless/ops/record/Modifier$;
  #20 = Fieldref           #2.#19         // shapeless/ops/record/Modifier$.MODULE$:Lshapeless/ops/record/Modifier$;
  #21 = Utf8               apply
  #22 = Utf8               (Lshapeless/ops/record/Modifier;)Lshapeless/ops/record/Modifier;
  #23 = Utf8               <L::Lshapeless/HList;F:Ljava/lang/Object;A:Ljava/lang/Object;B:Ljava/lang/Object;>(Lshapeless/ops/record/Modifier<TL;TF;TA;TB;>;)Lshapeless/ops/record/Modifier<TL;TF;TA;TB;>;
  #24 = Utf8               modifier
  #25 = Utf8               this
  #26 = Utf8               Lshapeless/ops/record/Modifier;
  #27 = Utf8               hlistModify1
  #28 = Utf8               ()Lshapeless/ops/record/Modifier;
  #29 = Utf8               <F:Ljava/lang/Object;A:Ljava/lang/Object;B:Ljava/lang/Object;T::Lshapeless/HList;>()Lshapeless/ops/record/Modifier<Lshapeless/$colon$colon<TA;TT;>;TF;TA;TB;>;
  #30 = Methodref          #9.#17         // shapeless/ops/record/Modifier$$anon$17."<init>":()V
  #31 = Utf8               hlistModify
  #32 = Utf8               <H:Ljava/lang/Object;T::Lshapeless/HList;F:Ljava/lang/Object;A:Ljava/lang/Object;B:Ljava/lang/Object;>(Lshapeless/ops/record/Modifier<TT;TF;TA;TB;>;)Lshapeless/ops/record/Modifier<Lshapeless/$colon$colon<TH;TT;>;TF;TA;TB;>;
  #33 = Utf8               mt
  #34 = Utf8               (Lshapeless/ops/record/Modifier;)V
  #35 = NameAndType        #16:#34        // "<init>":(Lshapeless/ops/record/Modifier;)V
  #36 = Methodref          #11.#35        // shapeless/ops/record/Modifier$$anon$18."<init>":(Lshapeless/ops/record/Modifier;)V
  #37 = Utf8               writeReplace
  #38 = Utf8               ()Ljava/lang/Object;
  #39 = Utf8               scala/runtime/ModuleSerializationProxy
  #40 = Class              #39            // scala/runtime/ModuleSerializationProxy
  #41 = Utf8               (Ljava/lang/Class;)V
  #42 = NameAndType        #16:#41        // "<init>":(Ljava/lang/Class;)V
  #43 = Methodref          #40.#42        // scala/runtime/ModuleSerializationProxy."<init>":(Ljava/lang/Class;)V
  #44 = Methodref          #4.#17         // java/lang/Object."<init>":()V
  #45 = Utf8               Code
  #46 = Utf8               LineNumberTable
  #47 = Utf8               LocalVariableTable
  #48 = Utf8               Signature
  #49 = Utf8               MethodParameters
  #50 = Utf8               Deprecated
  #51 = Utf8               InnerClasses
  #52 = Utf8               SourceFile
  #53 = Utf8               ScalaInlineInfo
  #54 = Utf8               mkModifier
  #55 = Utf8               Scala
{
  public static final shapeless.ops.record.Modifier$ MODULE$;
    descriptor: Lshapeless/ops/record/Modifier$;
    flags: (0x0019) ACC_PUBLIC, ACC_STATIC, ACC_FINAL

  public static {};
    descriptor: ()V
    flags: (0x0009) ACC_PUBLIC, ACC_STATIC
    Code:
      stack=2, locals=0, args_size=0
         0: new           #2                  // class shapeless/ops/record/Modifier$
         3: dup
         4: invokespecial #18                 // Method "<init>":()V
         7: putstatic     #20                 // Field MODULE$:Lshapeless/ops/record/Modifier$;
        10: return
      LineNumberTable:
        line 360: 0

  public <L extends shapeless.HList, F extends java.lang.Object, A extends java.lang.Object, B extends java.lang.Object> shapeless.ops.record.Modifier<L, F, A, B> apply(shapeless.ops.record.Modifier<L, F, A, B>);
    descriptor: (Lshapeless/ops/record/Modifier;)Lshapeless/ops/record/Modifier;
    flags: (0x0001) ACC_PUBLIC
    Code:
      stack=1, locals=2, args_size=2
         0: aload_1
         1: areturn
      LineNumberTable:
        line 361: 0
      LocalVariableTable:
        Start  Length  Slot  Name   Signature
            0       2     0  this   Lshapeless/ops/record/Modifier$;
            0       2     1 modifier   Lshapeless/ops/record/Modifier;
    Signature: #23                          // <L::Lshapeless/HList;F:Ljava/lang/Object;A:Ljava/lang/Object;B:Ljava/lang/Object;>(Lshapeless/ops/record/Modifier<TL;TF;TA;TB;>;)Lshapeless/ops/record/Modifier<TL;TF;TA;TB;>;
    MethodParameters:
      Name                           Flags
      modifier                       final

  public <F extends java.lang.Object, A extends java.lang.Object, B extends java.lang.Object, T extends shapeless.HList> shapeless.ops.record.Modifier<shapeless.$colon$colon<A, T>, F, A, B> hlistModify1();
    descriptor: ()Lshapeless/ops/record/Modifier;
    flags: (0x0001) ACC_PUBLIC
    Code:
      stack=2, locals=1, args_size=1
         0: new           #9                  // class shapeless/ops/record/Modifier$$anon$17
         3: dup
         4: invokespecial #30                 // Method shapeless/ops/record/Modifier$$anon$17."<init>":()V
         7: areturn
      LineNumberTable:
        line 369: 0
      LocalVariableTable:
        Start  Length  Slot  Name   Signature
            0       8     0  this   Lshapeless/ops/record/Modifier$;
    Signature: #29                          // <F:Ljava/lang/Object;A:Ljava/lang/Object;B:Ljava/lang/Object;T::Lshapeless/HList;>()Lshapeless/ops/record/Modifier<Lshapeless/$colon$colon<TA;TT;>;TF;TA;TB;>;
    Deprecated: true

  public <H extends java.lang.Object, T extends shapeless.HList, F extends java.lang.Object, A extends java.lang.Object, B extends java.lang.Object> shapeless.ops.record.Modifier<shapeless.$colon$colon<H, T>, F, A, B> hlistModify(shapeless.ops.record.Modifier<T, F, A, B>);
    descriptor: (Lshapeless/ops/record/Modifier;)Lshapeless/ops/record/Modifier;
    flags: (0x0001) ACC_PUBLIC
    Code:
      stack=3, locals=2, args_size=2
         0: new           #11                 // class shapeless/ops/record/Modifier$$anon$18
         3: dup
         4: aload_1
         5: invokespecial #36                 // Method shapeless/ops/record/Modifier$$anon$18."<init>":(Lshapeless/ops/record/Modifier;)V
         8: areturn
      LineNumberTable:
        line 377: 0
      LocalVariableTable:
        Start  Length  Slot  Name   Signature
            0       9     0  this   Lshapeless/ops/record/Modifier$;
            0       9     1    mt   Lshapeless/ops/record/Modifier;
    Signature: #32                          // <H:Ljava/lang/Object;T::Lshapeless/HList;F:Ljava/lang/Object;A:Ljava/lang/Object;B:Ljava/lang/Object;>(Lshapeless/ops/record/Modifier<TT;TF;TA;TB;>;)Lshapeless/ops/record/Modifier<Lshapeless/$colon$colon<TH;TT;>;TF;TA;TB;>;
    Deprecated: true
    MethodParameters:
      Name                           Flags
      mt                             final

  private java.lang.Object writeReplace();
    descriptor: ()Ljava/lang/Object;
    flags: (0x0002) ACC_PRIVATE
    Code:
      stack=3, locals=1, args_size=1
         0: new           #40                 // class scala/runtime/ModuleSerializationProxy
         3: dup
         4: ldc           #2                  // class shapeless/ops/record/Modifier$
         6: invokespecial #43                 // Method scala/runtime/ModuleSerializationProxy."<init>":(Ljava/lang/Class;)V
         9: areturn
      LineNumberTable:
        line 360: 0
      LocalVariableTable:
        Start  Length  Slot  Name   Signature
            0      10     0  this   Lshapeless/ops/record/Modifier$;

  private shapeless.ops.record.Modifier$();
    descriptor: ()V
    flags: (0x0002) ACC_PRIVATE
    Code:
      stack=1, locals=1, args_size=1
         0: aload_0
         1: invokespecial #44                 // Method java/lang/Object."<init>":()V
         4: return
      LineNumberTable:
        line 383: 0
        line 360: 4
      LocalVariableTable:
        Start  Length  Slot  Name   Signature
            0       5     0  this   Lshapeless/ops/record/Modifier$;
}
InnerClasses:
  public final #9;                        // class shapeless/ops/record/Modifier$$anon$17
  public final #11;                       // class shapeless/ops/record/Modifier$$anon$18
SourceFile: "records.scala"
  ScalaInlineInfo: length = 0x22 (unknown attribute)
   01 01 00 06 00 10 00 0F 01 00 15 00 16 01 00 1F
   00 16 01 00 1B 00 1C 01 00 36 00 1C 01 00 25 00
   26 01
  Scala: length = 0x0 (unknown attribute)

