Classfile /Users/mw/Projects/slang-braindump/.jar/jar8/assemble/slang-braindump/assemble/content/shapeless/ops/record/Modifier.class
  Last modified May 29, 2022; size 3777 bytes
  SHA-256 checksum 31636d6796df7ca816d2ec4d220e9cfcc1eafa6953332a0f111fc1c896304450
  Compiled from "records.scala"
public interface shapeless.ops.record.Modifier<L extends shapeless.HList, F extends java.lang.Object, A extends java.lang.Object, B extends java.lang.Object> extends shapeless.package$DepFn2<L, scala.Function1<A, B>>, java.io.Serializable
  minor version: 0
  major version: 52
  flags: (0x0601) ACC_PUBLIC, ACC_INTERFACE, ACC_ABSTRACT
  this_class: #2                          // shapeless/ops/record/Modifier
  super_class: #5                         // java/lang/Object
  interfaces: 2, fields: 0, methods: 2, attributes: 6
Constant pool:
   #1 = Utf8               shapeless/ops/record/Modifier
   #2 = Class              #1             // shapeless/ops/record/Modifier
   #3 = Utf8               <L::Lshapeless/HList;F:Ljava/lang/Object;A:Ljava/lang/Object;B:Ljava/lang/Object;>Ljava/lang/Object;Lshapeless/package$DepFn2<TL;Lscala/Function1<TA;TB;>;>;Ljava/io/Serializable;
   #4 = Utf8               java/lang/Object
   #5 = Class              #4             // java/lang/Object
   #6 = Utf8               shapeless/package$DepFn2
   #7 = Class              #6             // shapeless/package$DepFn2
   #8 = Utf8               java/io/Serializable
   #9 = Class              #8             // java/io/Serializable
  #10 = Utf8               records.scala
  #11 = Utf8               Lscala/reflect/ScalaSignature;
  #12 = Utf8               bytes
  #13 = Utf8               \u0006\u0005\t\u001ddaB\u0006\r!\u0003\r\na\u0005\u0003\u0006\r\u0002\u0011\taJ\u0004\u0006%2A\ta\u0015\u0004\u0006\u00171A\t!\u0016\u0005\u0006;\u000e!\tA\u0018\u0005\u0006?\u000e!\t\u0001Y\u0003\u0005I\u000e\u0001Q\r\u0003\u0005\u0002\b\r\u0011I1AA\u0005\u0011\u001d\t\u0019o\u0001C\u0001\u0003KDqA!\u000b\u0004\t\u0003\u0011Y\u0003C\u0005\u0003X\r\t\t\u0011\"\u0003\u0003Z\tAQj\u001c3jM&,\'O\u0003\u0002\u000e\u001d\u00051!/Z2pe\u0012T!a\u0004\t\u0002\u0007=\u00048OC\u0001\u0012\u0003%\u0019\b.\u00199fY\u0016\u001c8o\u0001\u0001\u0016\u000bQ)sIM\u001d\u0014\t\u0001)2d\u000f\t\u0003-ei\u0011a\u0006\u0006\u00021\u0005)1oY1mC&\u0011!d\u0006\u0002\u0007\u0003:L(+\u001a4\u0011\tq\u00013E\f\b\u0003;yi\u0011\u0001E\u0005\u0003?A\tq\u0001]1dW\u0006<W-\u0003\u0002\"E\t1A)\u001a9G]JR!a\b\t\u0011\u0005\u0011*C\u0002\u0001\u0003\u0006M\u0001\u0011\ra\n\u0002\u0002\u0019F\u0011\u0001f\u000b\t\u0003-%J!AK\f\u0003\u000f9{G\u000f[5oOB\u0011Q\u0004L\u0005\u0003[A\u0011Q\u0001\u0013\'jgR\u0004BAF\u00182q%\u0011\u0001g\u0006\u0002\n\rVt7\r^5p]F\u0002\"\u0001\n\u001a\u0005\u000bM\u0002!\u0019\u0001\u001b\u0003\u0003\u0005\u000b\"\u0001K\u001b\u0011\u0005Y1\u0014BA\u001c\u0018\u0005\r\te.\u001f\t\u0003Ie\"QA\u000f\u0001C\u0002Q\u0012\u0011A\u0011\t\u0003y\rs!!\u0010\"\u000f\u0005y\nU\"A \u000b\u0005\u0001\u0013\u0012A\u0002\u001fs_>$h(C\u0001\u0019\u0013\tyr#\u0003\u0002E\u000b\na1+\u001a:jC2L\'0\u00192mK*\u0011qd\u0006\u0002\u0004\u001fV$H!\u0002%\u0001\u0005\u0004!$!\u0001$)\u0007\u0001Q\u0005\u000b\u0005\u0002L\u001d6\tAJ\u0003\u0002N/\u0005Q\u0011M\u001c8pi\u0006$\u0018n\u001c8\n\u0005=c%\u0001E5na2L7-\u001b;O_R4u.\u001e8eC\u0005\t\u0016\u0001\u000e(pA\u0019LW\r\u001c3!Im4U\u0010I<ji\"\u0004c/\u00197vK\u0002zg\r\t;za\u0016\u0004Ce_!~A%t\u0007E]3d_J$\u0007\u0005J>M{\u0006AQj\u001c3jM&,\'\u000f\u0005\u0002U\u00075\tAbE\u0002\u0004+Y\u0003\"a\u0016/\u000e\u0003aS!!\u0017.\u0002\u0005%|\'\"A.\u0002\t)\fg/Y\u0005\u0003\tb\u000ba\u0001P5oSRtD#A*\u0002\u000b\u0005\u0004\b\u000f\\=\u0016\u000b\u0005<\u0018p_?\u0015\u0007\t\f\t\u0001E\u0004d\rYD(\u0010 @\u000e\u0003\r\u00111!Q;y+\u001917.\\8riJ\u0011q-\u001b\u0004\u0005Q\u000e\u0001aM\u0001\u0007=e\u00164\u0017N\\3nK:$h\b\u0005\u0004U\u0001)dg\u000e\u001d\t\u0003I-$QA\n\u0004C\u0002\u001d\u0002\"\u0001J7\u0005\u000b!3!\u0019\u0001\u001b\u0011\u0005\u0011zG!B\u001a\u0007\u0005\u0004!\u0004C\u0001\u0013r\t\u0015QdA1\u00015\u000b\u00111u\rI:\u0011\u0005\u0011\"H!B;\u0007\u0005\u00049#\u0001B(viB\u0002\"\u0001J<\u0005\u000b\u0019*!\u0019A\u0014\u0011\u0005\u0011JH!\u0002%\u0006\u0005\u0004!\u0004C\u0001\u0013|\t\u0015\u0019TA1\u00015!\t!S\u0010B\u0003;\u000b\t\u0007A\u0007\u0005\u0002\u0000\u00039\u0019A%!\u0001\t\u000f\u0005\rQ\u0001q\u0001\u0002\u0006\u0005AQn\u001c3jM&,\'\u000f\u0005\u0004U\u0001YD(\u0010`\u0001\u000b[.lu\u000eZ5gS\u0016\u0014X\u0003DA\u0006\u0003#\t)\"a\u0007\u0002 \u0005\rRCAA\u0007!1\u0019g!a\u0004\u0002\u0014\u0005e\u0011QDA\u0011!\r!\u0013\u0011\u0003\u0003\u0006M\u001d\u0011\ra\n\t\u0004I\u0005UAABA\f\u000f\t\u0007AGA\u0001L!\r!\u00131\u0004\u0003\u0006g\u001d\u0011\r\u0001\u000e\t\u0004I\u0005}A!\u0002\u001e\b\u0005\u0004!\u0004c\u0001\u0013\u0002$\u00111\u0011QE\u0004C\u0002\u001d\u0012\u0011a\u0014\u0015\u0006\u000f\u0005%\u0012Q\b\t\u0005\u0003W\tI$\u0004\u0002\u0002.)!\u0011qFA\u0019\u0003!Ig\u000e^3s]\u0006d\'\u0002BA\u001a\u0003k\ta!\\1de>\u001c(bAA\u001c/\u00059!/\u001a4mK\u000e$\u0018\u0002BA\u001e\u0003[\u0011\u0011\"\\1de>LU\u000e\u001d72\u001by\ty$!\u0011\u0002T\u0006]\u00171\\Ap\u0017\u0001\t\u0014cHA \u0003\u0007\n9%!\u0017\u0002j\u0005e\u00141RAOc\u0019!\u0013q\b\n\u0002F\u0005)Q.Y2s_F:a#a\u0010\u0002J\u0005E\u0013\'B\u0013\u0002L\u00055sBAA\'C\t\ty%A\u0006nC\u000e\u0014x.\u00128hS:,\u0017\'B\u0013\u0002T\u0005UsBAA+C\t\t9&A\u0013wo9\u0002\u0004\u0005K5na2,W.\u001a8uK\u0012\u0004\u0013N\u001c\u0011TG\u0006d\u0017\r\t\u001a/cEr\u0003\'L\'9SE:a#a\u0010\u0002\\\u0005\r\u0014\'B\u0013\u0002^\u0005}sBAA0C\t\t\t\'\u0001\u0005jg\n+h\u000e\u001a7fc\u0015)\u0013QMA4\u001f\t\t9\'G\u0001\u0002c\u001d1\u0012qHA6\u0003g\nT!JA7\u0003_z!!a\u001c\"\u0005\u0005E\u0014AC5t\u00052\f7m\u001b2pqF*Q%!\u001e\u0002x=\u0011\u0011qO\r\u0002\u0001E:a#a\u0010\u0002|\u0005\r\u0015\'B\u0013\u0002~\u0005}tBAA@C\t\t\t)A\u0005dY\u0006\u001c8OT1nKF*Q%!\"\u0002\b>\u0011\u0011qQ\u0011\u0003\u0003\u0013\u000b1e\u001d5ba\u0016dWm]:/_B\u001chF]3d_J$g&T8eS\u001aLWM]\'bGJ|7/M\u0004\u0017\u0003\u007f\ti)!&2\u000b\u0015\ny)!%\u0010\u0005\u0005E\u0015EAAJ\u0003)iW\r\u001e5pI:\u000bW.Z\u0019\u0006K\u0005]\u0015\u0011T\b\u0003\u00033\u000b#!a\'\u0002\u0013\u0005\u0004\b\u000f\\=J[Bd\u0017g\u0002\f\u0002@\u0005}\u0015qU\u0019\u0006K\u0005\u0005\u00161U\b\u0003\u0003G\u000b#!!*\u0002\u0013MLwM\\1ukJ,\u0017gB\u0010\u0002@\u0005%\u0016qW\u0019\bI\u0005}\u00121VAW\u0013\u0011\ti+a,\u0002\t1K7\u000f\u001e\u0006\u0005\u0003c\u000b\u0019,A\u0005j[6,H/\u00192mK*\u0019\u0011QW\f\u0002\u0015\r|G\u000e\\3di&|g.M\u0007 \u0003\u007f\tI,a/\u0002B\u0006\u001d\u0017QZ\u0019\bI\u0005}\u00121VAWc\u0015)\u0013QXA`\u001f\t\ty,H\u0001\u0001c\u0015)\u00131YAc\u001f\t\t)-H\u0001\u0002c\u0015)\u0013\u0011ZAf\u001f\t\tY-H\u0001\u0003c\u0015)\u0013qZAi\u001f\t\t\t.H\u0001\u0004c\r1\u0013Q\u001b\t\u0004I\u0005E\u0011g\u0001\u0014\u0002ZB\u0019A%!\u00062\u0007\u0019\ni\u000eE\u0002%\u00037\t4AJAq!\r!\u0013qD\u0001\rQ2L7\u000f^\'pI&4\u00170M\u000b\u000b\u0003O\u0014)A!\u0003\u0003\u0014\t5QCAAu!1\u0019g!a;\u0003\u0004\t\u001d!\u0011\u0003B\u000b!\u001di\u0012Q^Ay\u0005\u0017I1!a<\u0011\u00051!3m\u001c7p]\u0012\u001aw\u000e\\8o!!\t\u00190!@\u0003\u0004\t\u001da\u0002BA{\u0003st1APA|\u0013\u0005\t\u0012bAA~!\u0005AA.\u00192fY2,G-\u0003\u0003\u0002\u0000\n\u0005!!\u0003$jK2$G+\u001f9f\u0015\r\tY\u0010\u0005\t\u0004I\t\u0015A!\u0002%\t\u0005\u0004!\u0004c\u0001\u0013\u0003\n\u0011)1\u0007\u0003b\u0001iA\u0019AE!\u0004\u0005\r\t=\u0001B1\u0001(\u0005\u0005!\u0006c\u0001\u0013\u0003\u0014\u0011)!\b\u0003b\u0001iA9Q$!<\u0003\u0018\t-\u0001\u0003CAz\u0003{\u0014\u0019A!\u0005)\u000f!\u0011YB!\t\u0003&A\u0019aC!\b\n\u0007\t}qC\u0001\u0006eKB\u0014XmY1uK\u0012\f#Aa\t\u0002CI+G/Y5oK\u0012\u0004cm\u001c:!E&t\u0017M]=!G>l\u0007/\u0019;bE&d\u0017\u000e^=\"\u0005\t\u001d\u0012!\u0002\u001a/g9\n\u0014a\u00035mSN$Xj\u001c3jMf,BB!\f\u00036\tm\"q\bB\"\u0005\u000f\"BAa\f\u0003PAa1M\u0002B\u0019\u0005{\u0011\tE!\u0012\u0003JA9Q$!<\u00034\te\u0002c\u0001\u0013\u00036\u00111!qG\u0005C\u0002Q\u0012\u0011\u0001\u0013\t\u0004I\tmBA\u0002B\b\u0013\t\u0007q\u0005E\u0002%\u0005\u007f!Q\u0001S\u0005C\u0002Q\u00022\u0001\nB\"\t\u0015\u0019\u0014B1\u00015!\r!#q\t\u0003\u0006u%\u0011\r\u0001\u000e\t\b;\u00055(1\u0007B&!\r\u0011i%\u0001\b\u0004I\t=\u0003b\u0002B)\u0013\u0001\u000f!1K\u0001\u0003[R\u0004\"\u0002\u0016\u0001\u0003:\tu\"\u0011\tB#Q\u001dI!1\u0004B\u0011\u0005K\tAb\u001e:ji\u0016\u0014V\r\u001d7bG\u0016$\"Aa\u0017\u0011\t\tu#1M\u0007\u0003\u0005?R1A!\u0019[\u0003\u0011a\u0017M\\4\n\t\t\u0015$q\f\u0002\u0007\u001f\nTWm\u0019;
  #14 = Utf8               shapeless/package
  #15 = Class              #14            // shapeless/package
  #16 = Utf8               DepFn2
  #17 = Utf8               hlistModify
  #18 = Utf8               (Lshapeless/ops/record/Modifier;)Lshapeless/ops/record/Modifier;
  #19 = Utf8               <H:Ljava/lang/Object;T::Lshapeless/HList;F:Ljava/lang/Object;A:Ljava/lang/Object;B:Ljava/lang/Object;>(Lshapeless/ops/record/Modifier<TT;TF;TA;TB;>;)Lshapeless/ops/record/Modifier<Lshapeless/$colon$colon<TH;TT;>;TF;TA;TB;>;
  #20 = Utf8               mt
  #21 = Utf8               shapeless/ops/record/Modifier$
  #22 = Class              #21            // shapeless/ops/record/Modifier$
  #23 = Utf8               MODULE$
  #24 = Utf8               Lshapeless/ops/record/Modifier$;
  #25 = NameAndType        #23:#24        // MODULE$:Lshapeless/ops/record/Modifier$;
  #26 = Fieldref           #22.#25        // shapeless/ops/record/Modifier$.MODULE$:Lshapeless/ops/record/Modifier$;
  #27 = NameAndType        #17:#18        // hlistModify:(Lshapeless/ops/record/Modifier;)Lshapeless/ops/record/Modifier;
  #28 = Methodref          #22.#27        // shapeless/ops/record/Modifier$.hlistModify:(Lshapeless/ops/record/Modifier;)Lshapeless/ops/record/Modifier;
  #29 = Utf8               hlistModify1
  #30 = Utf8               ()Lshapeless/ops/record/Modifier;
  #31 = Utf8               <F:Ljava/lang/Object;A:Ljava/lang/Object;B:Ljava/lang/Object;T::Lshapeless/HList;>()Lshapeless/ops/record/Modifier<Lshapeless/$colon$colon<TA;TT;>;TF;TA;TB;>;
  #32 = NameAndType        #29:#30        // hlistModify1:()Lshapeless/ops/record/Modifier;
  #33 = Methodref          #22.#32        // shapeless/ops/record/Modifier$.hlistModify1:()Lshapeless/ops/record/Modifier;
  #34 = Utf8               Code
  #35 = Utf8               Signature
  #36 = Utf8               Deprecated
  #37 = Utf8               MethodParameters
  #38 = Utf8               InnerClasses
  #39 = Utf8               SourceFile
  #40 = Utf8               RuntimeVisibleAnnotations
  #41 = Utf8               ScalaInlineInfo
  #42 = Utf8               ScalaSig
{
  public static <H extends java.lang.Object, T extends shapeless.HList, F extends java.lang.Object, A extends java.lang.Object, B extends java.lang.Object> shapeless.ops.record.Modifier<shapeless.$colon$colon<H, T>, F, A, B> hlistModify(shapeless.ops.record.Modifier<T, F, A, B>);
    descriptor: (Lshapeless/ops/record/Modifier;)Lshapeless/ops/record/Modifier;
    flags: (0x0009) ACC_PUBLIC, ACC_STATIC
    Code:
      stack=2, locals=1, args_size=1
         0: getstatic     #26                 // Field shapeless/ops/record/Modifier$.MODULE$:Lshapeless/ops/record/Modifier$;
         3: aload_0
         4: invokevirtual #28                 // Method shapeless/ops/record/Modifier$.hlistModify:(Lshapeless/ops/record/Modifier;)Lshapeless/ops/record/Modifier;
         7: areturn
    Signature: #19                          // <H:Ljava/lang/Object;T::Lshapeless/HList;F:Ljava/lang/Object;A:Ljava/lang/Object;B:Ljava/lang/Object;>(Lshapeless/ops/record/Modifier<TT;TF;TA;TB;>;)Lshapeless/ops/record/Modifier<Lshapeless/$colon$colon<TH;TT;>;TF;TA;TB;>;
    Deprecated: true
    MethodParameters:
      Name                           Flags
      mt                             final

  public static <F extends java.lang.Object, A extends java.lang.Object, B extends java.lang.Object, T extends shapeless.HList> shapeless.ops.record.Modifier<shapeless.$colon$colon<A, T>, F, A, B> hlistModify1();
    descriptor: ()Lshapeless/ops/record/Modifier;
    flags: (0x0009) ACC_PUBLIC, ACC_STATIC
    Code:
      stack=1, locals=0, args_size=0
         0: getstatic     #26                 // Field shapeless/ops/record/Modifier$.MODULE$:Lshapeless/ops/record/Modifier$;
         3: invokevirtual #33                 // Method shapeless/ops/record/Modifier$.hlistModify1:()Lshapeless/ops/record/Modifier;
         6: areturn
    Signature: #31                          // <F:Ljava/lang/Object;A:Ljava/lang/Object;B:Ljava/lang/Object;T::Lshapeless/HList;>()Lshapeless/ops/record/Modifier<Lshapeless/$colon$colon<TA;TT;>;TF;TA;TB;>;
    Deprecated: true
}
InnerClasses:
  public static #16= #7 of #15;           // DepFn2=class shapeless/package$DepFn2 of class shapeless/package
Signature: #3                           // <L::Lshapeless/HList;F:Ljava/lang/Object;A:Ljava/lang/Object;B:Ljava/lang/Object;>Ljava/lang/Object;Lshapeless/package$DepFn2<TL;Lscala/Function1<TA;TB;>;>;Ljava/io/Serializable;
SourceFile: "records.scala"
RuntimeVisibleAnnotations:
  0: #11(#12=s#13)
    scala.reflect.ScalaSignature(
      bytes="\u0006\u0005\t\u001ddaB\u0006\r!\u0003\r\na\u0005\u0003\u0006\r\u0002\u0011\taJ\u0004\u0006%2A\ta\u0015\u0004\u0006\u00171A\t!\u0016\u0005\u0006;\u000e!\tA\u0018\u0005\u0006?\u000e!\t\u0001Y\u0003\u0005I\u000e\u0001Q\r\u0003\u0005\u0002\b\r\u0011I1AA\u0005\u0011\u001d\t\u0019o\u0001C\u0001\u0003KDqA!\u000b\u0004\t\u0003\u0011Y\u0003C\u0005\u0003X\r\t\t\u0011\"\u0003\u0003Z\tAQj\u001c3jM&,\'O\u0003\u0002\u000e\u001d\u00051!/Z2pe\u0012T!a\u0004\t\u0002\u0007=\u00048OC\u0001\u0012\u0003%\u0019\b.\u00199fY\u0016\u001c8o\u0001\u0001\u0016\u000bQ)sIM\u001d\u0014\t\u0001)2d\u000f\t\u0003-ei\u0011a\u0006\u0006\u00021\u0005)1oY1mC&\u0011!d\u0006\u0002\u0007\u0003:L(+\u001a4\u0011\tq\u00013E\f\b\u0003;yi\u0011\u0001E\u0005\u0003?A\tq\u0001]1dW\u0006<W-\u0003\u0002\"E\t1A)\u001a9G]JR!a\b\t\u0011\u0005\u0011*C\u0002\u0001\u0003\u0006M\u0001\u0011\ra\n\u0002\u0002\u0019F\u0011\u0001f\u000b\t\u0003-%J!AK\f\u0003\u000f9{G\u000f[5oOB\u0011Q\u0004L\u0005\u0003[A\u0011Q\u0001\u0013\'jgR\u0004BAF\u00182q%\u0011\u0001g\u0006\u0002\n\rVt7\r^5p]F\u0002\"\u0001\n\u001a\u0005\u000bM\u0002!\u0019\u0001\u001b\u0003\u0003\u0005\u000b\"\u0001K\u001b\u0011\u0005Y1\u0014BA\u001c\u0018\u0005\r\te.\u001f\t\u0003Ie\"QA\u000f\u0001C\u0002Q\u0012\u0011A\u0011\t\u0003y\rs!!\u0010\"\u000f\u0005y\nU\"A \u000b\u0005\u0001\u0013\u0012A\u0002\u001fs_>$h(C\u0001\u0019\u0013\tyr#\u0003\u0002E\u000b\na1+\u001a:jC2L\'0\u00192mK*\u0011qd\u0006\u0002\u0004\u001fV$H!\u0002%\u0001\u0005\u0004!$!\u0001$)\u0007\u0001Q\u0005\u000b\u0005\u0002L\u001d6\tAJ\u0003\u0002N/\u0005Q\u0011M\u001c8pi\u0006$\u0018n\u001c8\n\u0005=c%\u0001E5na2L7-\u001b;O_R4u.\u001e8eC\u0005\t\u0016\u0001\u000e(pA\u0019LW\r\u001c3!Im4U\u0010I<ji\"\u0004c/\u00197vK\u0002zg\r\t;za\u0016\u0004Ce_!~A%t\u0007E]3d_J$\u0007\u0005J>M{\u0006AQj\u001c3jM&,\'\u000f\u0005\u0002U\u00075\tAbE\u0002\u0004+Y\u0003\"a\u0016/\u000e\u0003aS!!\u0017.\u0002\u0005%|\'\"A.\u0002\t)\fg/Y\u0005\u0003\tb\u000ba\u0001P5oSRtD#A*\u0002\u000b\u0005\u0004\b\u000f\\=\u0016\u000b\u0005<\u0018p_?\u0015\u0007\t\f\t\u0001E\u0004d\rYD(\u0010 @\u000e\u0003\r\u00111!Q;y+\u001917.\\8riJ\u0011q-\u001b\u0004\u0005Q\u000e\u0001aM\u0001\u0007=e\u00164\u0017N\\3nK:$h\b\u0005\u0004U\u0001)dg\u000e\u001d\t\u0003I-$QA\n\u0004C\u0002\u001d\u0002\"\u0001J7\u0005\u000b!3!\u0019\u0001\u001b\u0011\u0005\u0011zG!B\u001a\u0007\u0005\u0004!\u0004C\u0001\u0013r\t\u0015QdA1\u00015\u000b\u00111u\rI:\u0011\u0005\u0011\"H!B;\u0007\u0005\u00049#\u0001B(viB\u0002\"\u0001J<\u0005\u000b\u0019*!\u0019A\u0014\u0011\u0005\u0011JH!\u0002%\u0006\u0005\u0004!\u0004C\u0001\u0013|\t\u0015\u0019TA1\u00015!\t!S\u0010B\u0003;\u000b\t\u0007A\u0007\u0005\u0002\u0000\u00039\u0019A%!\u0001\t\u000f\u0005\rQ\u0001q\u0001\u0002\u0006\u0005AQn\u001c3jM&,\'\u000f\u0005\u0004U\u0001YD(\u0010`\u0001\u000b[.lu\u000eZ5gS\u0016\u0014X\u0003DA\u0006\u0003#\t)\"a\u0007\u0002 \u0005\rRCAA\u0007!1\u0019g!a\u0004\u0002\u0014\u0005e\u0011QDA\u0011!\r!\u0013\u0011\u0003\u0003\u0006M\u001d\u0011\ra\n\t\u0004I\u0005UAABA\f\u000f\t\u0007AGA\u0001L!\r!\u00131\u0004\u0003\u0006g\u001d\u0011\r\u0001\u000e\t\u0004I\u0005}A!\u0002\u001e\b\u0005\u0004!\u0004c\u0001\u0013\u0002$\u00111\u0011QE\u0004C\u0002\u001d\u0012\u0011a\u0014\u0015\u0006\u000f\u0005%\u0012Q\b\t\u0005\u0003W\tI$\u0004\u0002\u0002.)!\u0011qFA\u0019\u0003!Ig\u000e^3s]\u0006d\'\u0002BA\u001a\u0003k\ta!\\1de>\u001c(bAA\u001c/\u00059!/\u001a4mK\u000e$\u0018\u0002BA\u001e\u0003[\u0011\u0011\"\\1de>LU\u000e\u001d72\u001by\ty$!\u0011\u0002T\u0006]\u00171\\Ap\u0017\u0001\t\u0014cHA \u0003\u0007\n9%!\u0017\u0002j\u0005e\u00141RAOc\u0019!\u0013q\b\n\u0002F\u0005)Q.Y2s_F:a#a\u0010\u0002J\u0005E\u0013\'B\u0013\u0002L\u00055sBAA\'C\t\ty%A\u0006nC\u000e\u0014x.\u00128hS:,\u0017\'B\u0013\u0002T\u0005UsBAA+C\t\t9&A\u0013wo9\u0002\u0004\u0005K5na2,W.\u001a8uK\u0012\u0004\u0013N\u001c\u0011TG\u0006d\u0017\r\t\u001a/cEr\u0003\'L\'9SE:a#a\u0010\u0002\\\u0005\r\u0014\'B\u0013\u0002^\u0005}sBAA0C\t\t\t\'\u0001\u0005jg\n+h\u000e\u001a7fc\u0015)\u0013QMA4\u001f\t\t9\'G\u0001\u0002c\u001d1\u0012qHA6\u0003g\nT!JA7\u0003_z!!a\u001c\"\u0005\u0005E\u0014AC5t\u00052\f7m\u001b2pqF*Q%!\u001e\u0002x=\u0011\u0011qO\r\u0002\u0001E:a#a\u0010\u0002|\u0005\r\u0015\'B\u0013\u0002~\u0005}tBAA@C\t\t\t)A\u0005dY\u0006\u001c8OT1nKF*Q%!\"\u0002\b>\u0011\u0011qQ\u0011\u0003\u0003\u0013\u000b1e\u001d5ba\u0016dWm]:/_B\u001chF]3d_J$g&T8eS\u001aLWM]\'bGJ|7/M\u0004\u0017\u0003\u007f\ti)!&2\u000b\u0015\ny)!%\u0010\u0005\u0005E\u0015EAAJ\u0003)iW\r\u001e5pI:\u000bW.Z\u0019\u0006K\u0005]\u0015\u0011T\b\u0003\u00033\u000b#!a\'\u0002\u0013\u0005\u0004\b\u000f\\=J[Bd\u0017g\u0002\f\u0002@\u0005}\u0015qU\u0019\u0006K\u0005\u0005\u00161U\b\u0003\u0003G\u000b#!!*\u0002\u0013MLwM\\1ukJ,\u0017gB\u0010\u0002@\u0005%\u0016qW\u0019\bI\u0005}\u00121VAW\u0013\u0011\ti+a,\u0002\t1K7\u000f\u001e\u0006\u0005\u0003c\u000b\u0019,A\u0005j[6,H/\u00192mK*\u0019\u0011QW\f\u0002\u0015\r|G\u000e\\3di&|g.M\u0007 \u0003\u007f\tI,a/\u0002B\u0006\u001d\u0017QZ\u0019\bI\u0005}\u00121VAWc\u0015)\u0013QXA`\u001f\t\ty,H\u0001\u0001c\u0015)\u00131YAc\u001f\t\t)-H\u0001\u0002c\u0015)\u0013\u0011ZAf\u001f\t\tY-H\u0001\u0003c\u0015)\u0013qZAi\u001f\t\t\t.H\u0001\u0004c\r1\u0013Q\u001b\t\u0004I\u0005E\u0011g\u0001\u0014\u0002ZB\u0019A%!\u00062\u0007\u0019\ni\u000eE\u0002%\u00037\t4AJAq!\r!\u0013qD\u0001\rQ2L7\u000f^\'pI&4\u00170M\u000b\u000b\u0003O\u0014)A!\u0003\u0003\u0014\t5QCAAu!1\u0019g!a;\u0003\u0004\t\u001d!\u0011\u0003B\u000b!\u001di\u0012Q^Ay\u0005\u0017I1!a<\u0011\u00051!3m\u001c7p]\u0012\u001aw\u000e\\8o!!\t\u00190!@\u0003\u0004\t\u001da\u0002BA{\u0003st1APA|\u0013\u0005\t\u0012bAA~!\u0005AA.\u00192fY2,G-\u0003\u0003\u0002\u0000\n\u0005!!\u0003$jK2$G+\u001f9f\u0015\r\tY\u0010\u0005\t\u0004I\t\u0015A!\u0002%\t\u0005\u0004!\u0004c\u0001\u0013\u0003\n\u0011)1\u0007\u0003b\u0001iA\u0019AE!\u0004\u0005\r\t=\u0001B1\u0001(\u0005\u0005!\u0006c\u0001\u0013\u0003\u0014\u0011)!\b\u0003b\u0001iA9Q$!<\u0003\u0018\t-\u0001\u0003CAz\u0003{\u0014\u0019A!\u0005)\u000f!\u0011YB!\t\u0003&A\u0019aC!\b\n\u0007\t}qC\u0001\u0006eKB\u0014XmY1uK\u0012\f#Aa\t\u0002CI+G/Y5oK\u0012\u0004cm\u001c:!E&t\u0017M]=!G>l\u0007/\u0019;bE&d\u0017\u000e^=\"\u0005\t\u001d\u0012!\u0002\u001a/g9\n\u0014a\u00035mSN$Xj\u001c3jMf,BB!\f\u00036\tm\"q\bB\"\u0005\u000f\"BAa\f\u0003PAa1M\u0002B\u0019\u0005{\u0011\tE!\u0012\u0003JA9Q$!<\u00034\te\u0002c\u0001\u0013\u00036\u00111!qG\u0005C\u0002Q\u0012\u0011\u0001\u0013\t\u0004I\tmBA\u0002B\b\u0013\t\u0007q\u0005E\u0002%\u0005\u007f!Q\u0001S\u0005C\u0002Q\u00022\u0001\nB\"\t\u0015\u0019\u0014B1\u00015!\r!#q\t\u0003\u0006u%\u0011\r\u0001\u000e\t\b;\u00055(1\u0007B&!\r\u0011i%\u0001\b\u0004I\t=\u0003b\u0002B)\u0013\u0001\u000f!1K\u0001\u0003[R\u0004\"\u0002\u0016\u0001\u0003:\tu\"\u0011\tB#Q\u001dI!1\u0004B\u0011\u0005K\tAb\u001e:ji\u0016\u0014V\r\u001d7bG\u0016$\"Aa\u0017\u0011\t\tu#1M\u0007\u0003\u0005?R1A!\u0019[\u0003\u0011a\u0017M\\4\n\t\t\u0015$q\f\u0002\u0007\u001f\nTWm\u0019;"
    )
  ScalaInlineInfo: length = 0x4 (unknown attribute)
   01 00 00 00
  ScalaSig: length = 0x3 (unknown attribute)
   05 02 00
