Classfile /Users/mw/Projects/slang-braindump/.jar/jar8/assemble/slang-braindump/assemble/content/shapeless/ops/record/SwapRecord$.class
  Last modified May 29, 2022; size 1846 bytes
  SHA-256 checksum 5e64451e43016a3d4fba292be91d7107a1e0ea9567a77d3dfdb41512fd6b7f08
  Compiled from "records.scala"
public final class shapeless.ops.record.SwapRecord$ implements java.io.Serializable
  minor version: 0
  major version: 52
  flags: (0x0031) ACC_PUBLIC, ACC_FINAL, ACC_SUPER
  this_class: #2                          // shapeless/ops/record/SwapRecord$
  super_class: #4                         // java/lang/Object
  interfaces: 1, fields: 1, methods: 6, attributes: 4
Constant pool:
   #1 = Utf8               shapeless/ops/record/SwapRecord$
   #2 = Class              #1             // shapeless/ops/record/SwapRecord$
   #3 = Utf8               java/lang/Object
   #4 = Class              #3             // java/lang/Object
   #5 = Utf8               java/io/Serializable
   #6 = Class              #5             // java/io/Serializable
   #7 = Utf8               records.scala
   #8 = Utf8               shapeless/ops/record/SwapRecord$$anon$32
   #9 = Class              #8             // shapeless/ops/record/SwapRecord$$anon$32
  #10 = Utf8               shapeless/ops/record/SwapRecord$$anon$33
  #11 = Class              #10            // shapeless/ops/record/SwapRecord$$anon$33
  #12 = Utf8               MODULE$
  #13 = Utf8               Lshapeless/ops/record/SwapRecord$;
  #14 = Utf8               <clinit>
  #15 = Utf8               ()V
  #16 = Utf8               <init>
  #17 = NameAndType        #16:#15        // "<init>":()V
  #18 = Methodref          #2.#17         // shapeless/ops/record/SwapRecord$."<init>":()V
  #19 = NameAndType        #12:#13        // MODULE$:Lshapeless/ops/record/SwapRecord$;
  #20 = Fieldref           #2.#19         // shapeless/ops/record/SwapRecord$.MODULE$:Lshapeless/ops/record/SwapRecord$;
  #21 = Utf8               apply
  #22 = Utf8               (Lshapeless/ops/record/SwapRecord;)Lshapeless/ops/record/SwapRecord;
  #23 = Utf8               <L::Lshapeless/HList;>(Lshapeless/ops/record/SwapRecord<TL;>;)Lshapeless/ops/record/SwapRecord<TL;>;
  #24 = Utf8               sr
  #25 = Utf8               this
  #26 = Utf8               Lshapeless/ops/record/SwapRecord;
  #27 = Utf8               hnilSwapRecord
  #28 = Utf8               ()Lshapeless/ops/record/SwapRecord;
  #29 = Utf8               <L::Lshapeless/HNil;>()Lshapeless/ops/record/SwapRecord<TL;>;
  #30 = Methodref          #9.#17         // shapeless/ops/record/SwapRecord$$anon$32."<init>":()V
  #31 = Utf8               hlistSwapRecord
  #32 = Utf8               (Lshapeless/Witness;Lshapeless/ops/record/SwapRecord;)Lshapeless/ops/record/SwapRecord;
  #33 = Utf8               <K:Ljava/lang/Object;V:Ljava/lang/Object;T::Lshapeless/HList;>(Lshapeless/Witness;Lshapeless/ops/record/SwapRecord<TT;>;)Lshapeless/ops/record/SwapRecord<Lshapeless/$colon$colon<TV;TT;>;>;
  #34 = Utf8               wk
  #35 = Utf8               kt
  #36 = Utf8               (Lshapeless/Witness;Lshapeless/ops/record/SwapRecord;)V
  #37 = NameAndType        #16:#36        // "<init>":(Lshapeless/Witness;Lshapeless/ops/record/SwapRecord;)V
  #38 = Methodref          #11.#37        // shapeless/ops/record/SwapRecord$$anon$33."<init>":(Lshapeless/Witness;Lshapeless/ops/record/SwapRecord;)V
  #39 = Utf8               Lshapeless/Witness;
  #40 = Utf8               writeReplace
  #41 = Utf8               ()Ljava/lang/Object;
  #42 = Utf8               scala/runtime/ModuleSerializationProxy
  #43 = Class              #42            // scala/runtime/ModuleSerializationProxy
  #44 = Utf8               (Ljava/lang/Class;)V
  #45 = NameAndType        #16:#44        // "<init>":(Ljava/lang/Class;)V
  #46 = Methodref          #43.#45        // scala/runtime/ModuleSerializationProxy."<init>":(Ljava/lang/Class;)V
  #47 = Methodref          #4.#17         // java/lang/Object."<init>":()V
  #48 = Utf8               Code
  #49 = Utf8               LineNumberTable
  #50 = Utf8               LocalVariableTable
  #51 = Utf8               Signature
  #52 = Utf8               MethodParameters
  #53 = Utf8               InnerClasses
  #54 = Utf8               SourceFile
  #55 = Utf8               ScalaInlineInfo
  #56 = Utf8               Scala
{
  public static final shapeless.ops.record.SwapRecord$ MODULE$;
    descriptor: Lshapeless/ops/record/SwapRecord$;
    flags: (0x0019) ACC_PUBLIC, ACC_STATIC, ACC_FINAL

  public static {};
    descriptor: ()V
    flags: (0x0009) ACC_PUBLIC, ACC_STATIC
    Code:
      stack=2, locals=0, args_size=0
         0: new           #2                  // class shapeless/ops/record/SwapRecord$
         3: dup
         4: invokespecial #18                 // Method "<init>":()V
         7: putstatic     #20                 // Field MODULE$:Lshapeless/ops/record/SwapRecord$;
        10: return
      LineNumberTable:
        line 679: 0

  public <L extends shapeless.HList> shapeless.ops.record.SwapRecord<L> apply(shapeless.ops.record.SwapRecord<L>);
    descriptor: (Lshapeless/ops/record/SwapRecord;)Lshapeless/ops/record/SwapRecord;
    flags: (0x0001) ACC_PUBLIC
    Code:
      stack=1, locals=2, args_size=2
         0: aload_1
         1: areturn
      LineNumberTable:
        line 680: 0
      LocalVariableTable:
        Start  Length  Slot  Name   Signature
            0       2     0  this   Lshapeless/ops/record/SwapRecord$;
            0       2     1    sr   Lshapeless/ops/record/SwapRecord;
    Signature: #23                          // <L::Lshapeless/HList;>(Lshapeless/ops/record/SwapRecord<TL;>;)Lshapeless/ops/record/SwapRecord<TL;>;
    MethodParameters:
      Name                           Flags
      sr                             final

  public <L extends shapeless.HNil> shapeless.ops.record.SwapRecord<L> hnilSwapRecord();
    descriptor: ()Lshapeless/ops/record/SwapRecord;
    flags: (0x0001) ACC_PUBLIC
    Code:
      stack=2, locals=1, args_size=1
         0: new           #9                  // class shapeless/ops/record/SwapRecord$$anon$32
         3: dup
         4: invokespecial #30                 // Method shapeless/ops/record/SwapRecord$$anon$32."<init>":()V
         7: areturn
      LineNumberTable:
        line 685: 0
      LocalVariableTable:
        Start  Length  Slot  Name   Signature
            0       8     0  this   Lshapeless/ops/record/SwapRecord$;
    Signature: #29                          // <L::Lshapeless/HNil;>()Lshapeless/ops/record/SwapRecord<TL;>;

  public <K extends java.lang.Object, V extends java.lang.Object, T extends shapeless.HList> shapeless.ops.record.SwapRecord<shapeless.$colon$colon<V, T>> hlistSwapRecord(shapeless.Witness, shapeless.ops.record.SwapRecord<T>);
    descriptor: (Lshapeless/Witness;Lshapeless/ops/record/SwapRecord;)Lshapeless/ops/record/SwapRecord;
    flags: (0x0001) ACC_PUBLIC
    Code:
      stack=4, locals=3, args_size=3
         0: new           #11                 // class shapeless/ops/record/SwapRecord$$anon$33
         3: dup
         4: aload_1
         5: aload_2
         6: invokespecial #38                 // Method shapeless/ops/record/SwapRecord$$anon$33."<init>":(Lshapeless/Witness;Lshapeless/ops/record/SwapRecord;)V
         9: areturn
      LineNumberTable:
        line 691: 0
      LocalVariableTable:
        Start  Length  Slot  Name   Signature
            0      10     0  this   Lshapeless/ops/record/SwapRecord$;
            0      10     1    wk   Lshapeless/Witness;
            0      10     2    kt   Lshapeless/ops/record/SwapRecord;
    Signature: #33                          // <K:Ljava/lang/Object;V:Ljava/lang/Object;T::Lshapeless/HList;>(Lshapeless/Witness;Lshapeless/ops/record/SwapRecord<TT;>;)Lshapeless/ops/record/SwapRecord<Lshapeless/$colon$colon<TV;TT;>;>;
    MethodParameters:
      Name                           Flags
      wk                             final
      kt                             final

  private java.lang.Object writeReplace();
    descriptor: ()Ljava/lang/Object;
    flags: (0x0002) ACC_PRIVATE
    Code:
      stack=3, locals=1, args_size=1
         0: new           #43                 // class scala/runtime/ModuleSerializationProxy
         3: dup
         4: ldc           #2                  // class shapeless/ops/record/SwapRecord$
         6: invokespecial #46                 // Method scala/runtime/ModuleSerializationProxy."<init>":(Ljava/lang/Class;)V
         9: areturn
      LineNumberTable:
        line 679: 0
      LocalVariableTable:
        Start  Length  Slot  Name   Signature
            0      10     0  this   Lshapeless/ops/record/SwapRecord$;

  private shapeless.ops.record.SwapRecord$();
    descriptor: ()V
    flags: (0x0002) ACC_PRIVATE
    Code:
      stack=1, locals=1, args_size=1
         0: aload_0
         1: invokespecial #47                 // Method java/lang/Object."<init>":()V
         4: return
      LineNumberTable:
        line 702: 0
        line 679: 4
      LocalVariableTable:
        Start  Length  Slot  Name   Signature
            0       5     0  this   Lshapeless/ops/record/SwapRecord$;
}
InnerClasses:
  public final #9;                        // class shapeless/ops/record/SwapRecord$$anon$32
  public final #11;                       // class shapeless/ops/record/SwapRecord$$anon$33
SourceFile: "records.scala"
  ScalaInlineInfo: length = 0x1D (unknown attribute)
   01 01 00 05 00 10 00 0F 01 00 15 00 16 01 00 1F
   00 20 01 00 1B 00 1C 01 00 28 00 29 01
  Scala: length = 0x0 (unknown attribute)

