Classfile /Users/mw/Projects/slang-braindump/.jar/jar8/assemble/slang-braindump/assemble/content/shapeless/ops/record/ToMap$.class
  Last modified May 29, 2022; size 2716 bytes
  SHA-256 checksum d051b5452a2516682ec3bfc5e3cebb6b77a5923e708ad11ea6500fffd6b3f536
  Compiled from "records.scala"
public final class shapeless.ops.record.ToMap$ implements java.io.Serializable
  minor version: 0
  major version: 52
  flags: (0x0031) ACC_PUBLIC, ACC_FINAL, ACC_SUPER
  this_class: #2                          // shapeless/ops/record/ToMap$
  super_class: #4                         // java/lang/Object
  interfaces: 1, fields: 1, methods: 8, attributes: 4
Constant pool:
   #1 = Utf8               shapeless/ops/record/ToMap$
   #2 = Class              #1             // shapeless/ops/record/ToMap$
   #3 = Utf8               java/lang/Object
   #4 = Class              #3             // java/lang/Object
   #5 = Utf8               java/io/Serializable
   #6 = Class              #5             // java/io/Serializable
   #7 = Utf8               records.scala
   #8 = Utf8               shapeless/ops/record/ToMap$$anon$38
   #9 = Class              #8             // shapeless/ops/record/ToMap$$anon$38
  #10 = Utf8               shapeless/ops/record/ToMap$$anon$39
  #11 = Class              #10            // shapeless/ops/record/ToMap$$anon$39
  #12 = Utf8               shapeless/ops/record/ToMap$$anon$40
  #13 = Class              #12            // shapeless/ops/record/ToMap$$anon$40
  #14 = Utf8               MODULE$
  #15 = Utf8               Lshapeless/ops/record/ToMap$;
  #16 = Utf8               <clinit>
  #17 = Utf8               ()V
  #18 = Utf8               <init>
  #19 = NameAndType        #18:#17        // "<init>":()V
  #20 = Methodref          #2.#19         // shapeless/ops/record/ToMap$."<init>":()V
  #21 = NameAndType        #14:#15        // MODULE$:Lshapeless/ops/record/ToMap$;
  #22 = Fieldref           #2.#21         // shapeless/ops/record/ToMap$.MODULE$:Lshapeless/ops/record/ToMap$;
  #23 = Utf8               apply
  #24 = Utf8               (Lshapeless/ops/record/ToMap;)Lshapeless/ops/record/ToMap;
  #25 = Utf8               <L::Lshapeless/HList;>(Lshapeless/ops/record/ToMap<TL;>;)Lshapeless/ops/record/ToMap<TL;>;
  #26 = Utf8               toMap
  #27 = Utf8               this
  #28 = Utf8               Lshapeless/ops/record/ToMap;
  #29 = Utf8               hnilToMap
  #30 = Utf8               ()Lshapeless/ops/record/ToMap;
  #31 = Utf8               <K:Ljava/lang/Object;V:Ljava/lang/Object;L::Lshapeless/HNil;>()Lshapeless/ops/record/ToMap<TL;>;
  #32 = Methodref          #9.#19         // shapeless/ops/record/ToMap$$anon$38."<init>":()V
  #33 = Utf8               hnilToMapAnyNothing
  #34 = Utf8               <L::Lshapeless/HNil;>()Lshapeless/ops/record/ToMap<TL;>;
  #35 = NameAndType        #29:#30        // hnilToMap:()Lshapeless/ops/record/ToMap;
  #36 = Methodref          #2.#35         // shapeless/ops/record/ToMap$.hnilToMap:()Lshapeless/ops/record/ToMap;
  #37 = Utf8               hsingleToMap
  #38 = Utf8               (Lshapeless/Witness;)Lshapeless/ops/record/ToMap;
  #39 = Utf8               <K:Ljava/lang/Object;V:Ljava/lang/Object;>(Lshapeless/Witness;)Lshapeless/ops/record/ToMap<Lshapeless/$colon$colon<TV;Lshapeless/HNil;>;>;
  #40 = Utf8               wk
  #41 = Utf8               (Lshapeless/Witness;)V
  #42 = NameAndType        #18:#41        // "<init>":(Lshapeless/Witness;)V
  #43 = Methodref          #11.#42        // shapeless/ops/record/ToMap$$anon$39."<init>":(Lshapeless/Witness;)V
  #44 = Utf8               Lshapeless/Witness;
  #45 = Utf8               hlistToMap
  #46 = Utf8               (Lshapeless/ops/record/ToMap;Lshapeless/Lub;Lshapeless/Lub;Lshapeless/Witness;)Lshapeless/ops/record/ToMap;
  #47 = Utf8               <HK:Ljava/lang/Object;HV:Ljava/lang/Object;TH:Ljava/lang/Object;TT::Lshapeless/HList;TK:Ljava/lang/Object;TV:Ljava/lang/Object;K:Ljava/lang/Object;V:Ljava/lang/Object;>(Lshapeless/ops/record/ToMap<Lshapeless/$colon$colon<TTH;TTT;>;>;Lshapeless/Lub<THK;TTK;TK;>;Lshapeless/Lub<THV;TTV;TV;>;Lshapeless/Witness;)Lshapeless/ops/record/ToMap<Lshapeless/$colon$colon<THV;Lshapeless/$colon$colon<TTH;TTT;>;>;>;
  #48 = Utf8               tailToMap
  #49 = Utf8               keyLub
  #50 = Utf8               valueLub
  #51 = Utf8               (Lshapeless/ops/record/ToMap;Lshapeless/Lub;Lshapeless/Lub;Lshapeless/Witness;)V
  #52 = NameAndType        #18:#51        // "<init>":(Lshapeless/ops/record/ToMap;Lshapeless/Lub;Lshapeless/Lub;Lshapeless/Witness;)V
  #53 = Methodref          #13.#52        // shapeless/ops/record/ToMap$$anon$40."<init>":(Lshapeless/ops/record/ToMap;Lshapeless/Lub;Lshapeless/Lub;Lshapeless/Witness;)V
  #54 = Utf8               Lshapeless/Lub;
  #55 = Utf8               writeReplace
  #56 = Utf8               ()Ljava/lang/Object;
  #57 = Utf8               scala/runtime/ModuleSerializationProxy
  #58 = Class              #57            // scala/runtime/ModuleSerializationProxy
  #59 = Utf8               (Ljava/lang/Class;)V
  #60 = NameAndType        #18:#59        // "<init>":(Ljava/lang/Class;)V
  #61 = Methodref          #58.#60        // scala/runtime/ModuleSerializationProxy."<init>":(Ljava/lang/Class;)V
  #62 = Methodref          #4.#19         // java/lang/Object."<init>":()V
  #63 = Utf8               Code
  #64 = Utf8               LineNumberTable
  #65 = Utf8               LocalVariableTable
  #66 = Utf8               Signature
  #67 = Utf8               MethodParameters
  #68 = Utf8               InnerClasses
  #69 = Utf8               SourceFile
  #70 = Utf8               ScalaInlineInfo
  #71 = Utf8               Scala
{
  public static final shapeless.ops.record.ToMap$ MODULE$;
    descriptor: Lshapeless/ops/record/ToMap$;
    flags: (0x0019) ACC_PUBLIC, ACC_STATIC, ACC_FINAL

  public static {};
    descriptor: ()V
    flags: (0x0009) ACC_PUBLIC, ACC_STATIC
    Code:
      stack=2, locals=0, args_size=0
         0: new           #2                  // class shapeless/ops/record/ToMap$
         3: dup
         4: invokespecial #20                 // Method "<init>":()V
         7: putstatic     #22                 // Field MODULE$:Lshapeless/ops/record/ToMap$;
        10: return
      LineNumberTable:
        line 779: 0

  public <L extends shapeless.HList> shapeless.ops.record.ToMap<L> apply(shapeless.ops.record.ToMap<L>);
    descriptor: (Lshapeless/ops/record/ToMap;)Lshapeless/ops/record/ToMap;
    flags: (0x0001) ACC_PUBLIC
    Code:
      stack=1, locals=2, args_size=2
         0: aload_1
         1: areturn
      LineNumberTable:
        line 780: 0
      LocalVariableTable:
        Start  Length  Slot  Name   Signature
            0       2     0  this   Lshapeless/ops/record/ToMap$;
            0       2     1 toMap   Lshapeless/ops/record/ToMap;
    Signature: #25                          // <L::Lshapeless/HList;>(Lshapeless/ops/record/ToMap<TL;>;)Lshapeless/ops/record/ToMap<TL;>;
    MethodParameters:
      Name                           Flags
      toMap                          final

  public <K extends java.lang.Object, V extends java.lang.Object, L extends shapeless.HNil> shapeless.ops.record.ToMap<L> hnilToMap();
    descriptor: ()Lshapeless/ops/record/ToMap;
    flags: (0x0001) ACC_PUBLIC
    Code:
      stack=2, locals=1, args_size=1
         0: new           #9                  // class shapeless/ops/record/ToMap$$anon$38
         3: dup
         4: invokespecial #32                 // Method shapeless/ops/record/ToMap$$anon$38."<init>":()V
         7: areturn
      LineNumberTable:
        line 785: 0
      LocalVariableTable:
        Start  Length  Slot  Name   Signature
            0       8     0  this   Lshapeless/ops/record/ToMap$;
    Signature: #31                          // <K:Ljava/lang/Object;V:Ljava/lang/Object;L::Lshapeless/HNil;>()Lshapeless/ops/record/ToMap<TL;>;

  public <L extends shapeless.HNil> shapeless.ops.record.ToMap<L> hnilToMapAnyNothing();
    descriptor: ()Lshapeless/ops/record/ToMap;
    flags: (0x0001) ACC_PUBLIC
    Code:
      stack=1, locals=1, args_size=1
         0: aload_0
         1: invokevirtual #36                 // Method hnilToMap:()Lshapeless/ops/record/ToMap;
         4: areturn
      LineNumberTable:
        line 791: 0
      LocalVariableTable:
        Start  Length  Slot  Name   Signature
            0       5     0  this   Lshapeless/ops/record/ToMap$;
    Signature: #34                          // <L::Lshapeless/HNil;>()Lshapeless/ops/record/ToMap<TL;>;

  public <K extends java.lang.Object, V extends java.lang.Object> shapeless.ops.record.ToMap<shapeless.$colon$colon<V, shapeless.HNil>> hsingleToMap(shapeless.Witness);
    descriptor: (Lshapeless/Witness;)Lshapeless/ops/record/ToMap;
    flags: (0x0001) ACC_PUBLIC
    Code:
      stack=3, locals=2, args_size=2
         0: new           #11                 // class shapeless/ops/record/ToMap$$anon$39
         3: dup
         4: aload_1
         5: invokespecial #43                 // Method shapeless/ops/record/ToMap$$anon$39."<init>":(Lshapeless/Witness;)V
         8: areturn
      LineNumberTable:
        line 796: 0
      LocalVariableTable:
        Start  Length  Slot  Name   Signature
            0       9     0  this   Lshapeless/ops/record/ToMap$;
            0       9     1    wk   Lshapeless/Witness;
    Signature: #39                          // <K:Ljava/lang/Object;V:Ljava/lang/Object;>(Lshapeless/Witness;)Lshapeless/ops/record/ToMap<Lshapeless/$colon$colon<TV;Lshapeless/HNil;>;>;
    MethodParameters:
      Name                           Flags
      wk                             final

  public <HK extends java.lang.Object, HV extends java.lang.Object, TH extends java.lang.Object, TT extends shapeless.HList, TK extends java.lang.Object, TV extends java.lang.Object, K extends java.lang.Object, V extends java.lang.Object> shapeless.ops.record.ToMap<shapeless.$colon$colon<HV, shapeless.$colon$colon<TH, TT>>> hlistToMap(shapeless.ops.record.ToMap<shapeless.$colon$colon<TH, TT>>, shapeless.Lub<HK, TK, K>, shapeless.Lub<HV, TV, V>, shapeless.Witness);
    descriptor: (Lshapeless/ops/record/ToMap;Lshapeless/Lub;Lshapeless/Lub;Lshapeless/Witness;)Lshapeless/ops/record/ToMap;
    flags: (0x0001) ACC_PUBLIC
    Code:
      stack=6, locals=5, args_size=5
         0: new           #13                 // class shapeless/ops/record/ToMap$$anon$40
         3: dup
         4: aload_1
         5: aload_2
         6: aload_3
         7: aload         4
         9: invokespecial #53                 // Method shapeless/ops/record/ToMap$$anon$40."<init>":(Lshapeless/ops/record/ToMap;Lshapeless/Lub;Lshapeless/Lub;Lshapeless/Witness;)V
        12: areturn
      LineNumberTable:
        line 808: 0
      LocalVariableTable:
        Start  Length  Slot  Name   Signature
            0      13     0  this   Lshapeless/ops/record/ToMap$;
            0      13     1 tailToMap   Lshapeless/ops/record/ToMap;
            0      13     2 keyLub   Lshapeless/Lub;
            0      13     3 valueLub   Lshapeless/Lub;
            0      13     4    wk   Lshapeless/Witness;
    Signature: #47                          // <HK:Ljava/lang/Object;HV:Ljava/lang/Object;TH:Ljava/lang/Object;TT::Lshapeless/HList;TK:Ljava/lang/Object;TV:Ljava/lang/Object;K:Ljava/lang/Object;V:Ljava/lang/Object;>(Lshapeless/ops/record/ToMap<Lshapeless/$colon$colon<TTH;TTT;>;>;Lshapeless/Lub<THK;TTK;TK;>;Lshapeless/Lub<THV;TTV;TV;>;Lshapeless/Witness;)Lshapeless/ops/record/ToMap<Lshapeless/$colon$colon<THV;Lshapeless/$colon$colon<TTH;TTT;>;>;>;
    MethodParameters:
      Name                           Flags
      tailToMap                      final
      keyLub                         final
      valueLub                       final
      wk                             final

  private java.lang.Object writeReplace();
    descriptor: ()Ljava/lang/Object;
    flags: (0x0002) ACC_PRIVATE
    Code:
      stack=3, locals=1, args_size=1
         0: new           #58                 // class scala/runtime/ModuleSerializationProxy
         3: dup
         4: ldc           #2                  // class shapeless/ops/record/ToMap$
         6: invokespecial #61                 // Method scala/runtime/ModuleSerializationProxy."<init>":(Ljava/lang/Class;)V
         9: areturn
      LineNumberTable:
        line 779: 0
      LocalVariableTable:
        Start  Length  Slot  Name   Signature
            0      10     0  this   Lshapeless/ops/record/ToMap$;

  private shapeless.ops.record.ToMap$();
    descriptor: ()V
    flags: (0x0002) ACC_PRIVATE
    Code:
      stack=1, locals=1, args_size=1
         0: aload_0
         1: invokespecial #62                 // Method java/lang/Object."<init>":()V
         4: return
      LineNumberTable:
        line 822: 0
        line 779: 4
      LocalVariableTable:
        Start  Length  Slot  Name   Signature
            0       5     0  this   Lshapeless/ops/record/ToMap$;
}
InnerClasses:
  public final #9;                        // class shapeless/ops/record/ToMap$$anon$38
  public final #11;                       // class shapeless/ops/record/ToMap$$anon$39
  public final #13;                       // class shapeless/ops/record/ToMap$$anon$40
SourceFile: "records.scala"
  ScalaInlineInfo: length = 0x27 (unknown attribute)
   01 01 00 07 00 12 00 11 01 00 17 00 18 01 00 2D
   00 2E 01 00 1D 00 1E 01 00 21 00 1E 01 00 25 00
   26 01 00 37 00 38 01
  Scala: length = 0x0 (unknown attribute)

