Classfile /Users/mw/Projects/slang-braindump/.jar/jar8/assemble/slang-braindump/assemble/content/shapeless/ops/record/ToMap.class
  Last modified May 29, 2022; size 3424 bytes
  SHA-256 checksum b9a65a1d591ad510468a8aafcdf6502740d9bd8b19893434f5800004ca0d7179
  Compiled from "records.scala"
public interface shapeless.ops.record.ToMap<L extends shapeless.HList> extends shapeless.package$DepFn1<L>, java.io.Serializable
  minor version: 0
  major version: 52
  flags: (0x0601) ACC_PUBLIC, ACC_INTERFACE, ACC_ABSTRACT
  this_class: #2                          // shapeless/ops/record/ToMap
  super_class: #5                         // java/lang/Object
  interfaces: 2, fields: 0, methods: 4, attributes: 6
Constant pool:
   #1 = Utf8               shapeless/ops/record/ToMap
   #2 = Class              #1             // shapeless/ops/record/ToMap
   #3 = Utf8               <L::Lshapeless/HList;>Ljava/lang/Object;Lshapeless/package$DepFn1<TL;>;Ljava/io/Serializable;
   #4 = Utf8               java/lang/Object
   #5 = Class              #4             // java/lang/Object
   #6 = Utf8               shapeless/package$DepFn1
   #7 = Class              #6             // shapeless/package$DepFn1
   #8 = Utf8               java/io/Serializable
   #9 = Class              #8             // java/io/Serializable
  #10 = Utf8               records.scala
  #11 = Utf8               Lscala/reflect/ScalaSignature;
  #12 = Utf8               bytes
  #13 = Utf8               \u0006\u0005\u0005mfa\u0002\b\u0010!\u0003\r\nA\u0006\u0003\u0006y\u0001\u0011\t!\u0010\u0003\u0006\u0003\u0002\u0011\t!P\u0003\u0005\u0005\u0002\u00011iB\u0003O\u001f!\u0005qJB\u0003\u000f\u001f!\u0005\u0011\u000bC\u0003Z\u000b\u0011\u0005!\fC\u0003\\\u000b\u0011\u0005A,\u0002\u0003a\u000b\u0001\t\u0007\"\u0002=\u0006\t\u0007I\bbBA\t\u000b\u0011\r\u00111\u0003\u0005\b\u0003;)A1AA\u0010\u0011\u001d\t)&\u0002C\u0002\u0003/B\u0011\"a+\u0006\u0003\u0003%I!!,\u0003\u000bQ{W*\u00199\u000b\u0005A\t\u0012A\u0002:fG>\u0014HM\u0003\u0002\u0013\'\u0005\u0019q\u000e]:\u000b\u0003Q\t\u0011b\u001d5ba\u0016dWm]:\u0004\u0001U\u0011q\u0003K\n\u0005\u0001aq\u0012\u0007\u0005\u0002\u001a95\t!DC\u0001\u001c\u0003\u0015\u00198-\u00197b\u0013\ti\"D\u0001\u0004B]f\u0014VM\u001a\t\u0004?\r2cB\u0001\u0011\"\u001b\u0005\u0019\u0012B\u0001\u0012\u0014\u0003\u001d\u0001\u0018mY6bO\u0016L!\u0001J\u0013\u0003\r\u0011+\u0007O\u001282\u0015\t\u00113\u0003\u0005\u0002(Q1\u0001A!B\u0015\u0001\u0005\u0004Q#!\u0001\'\u0012\u0005-r\u0003CA\r-\u0013\ti#DA\u0004O_RD\u0017N\\4\u0011\u0005\u0001z\u0013B\u0001\u0019\u0014\u0005\u0015AE*[:u!\t\u0011\u0014H\u0004\u00024q9\u0011AgN\u0007\u0002k)\u0011a\'F\u0001\u0007yI|w\u000e\u001e \n\u0003mI!A\t\u000e\n\u0005iZ$\u0001D*fe&\fG.\u001b>bE2,\'B\u0001\u0012\u001b\u0005\rYU-_\t\u0003Wy\u0002\"!G \n\u0005\u0001S\"aA!os\n)a+\u00197vK\n\u0019q*\u001e;\u0011\t\u0011C5*\u0014\b\u0003\u000b\u001a\u0003\"\u0001\u000e\u000e\n\u0005\u001dS\u0012A\u0002)sK\u0012,g-\u0003\u0002J\u0015\n\u0019Q*\u00199\u000b\u0005\u001dS\u0002C\u0001\'\u0002\u001b\u0005\u0001\u0001C\u0001\'\u0003\u0003\u0015!v.T1q!\t\u0001V!D\u0001\u0010\'\r)\u0001D\u0015\t\u0003\'bk\u0011\u0001\u0016\u0006\u0003+Z\u000b!![8\u000b\u0003]\u000bAA[1wC&\u0011!\bV\u0001\u0007y%t\u0017\u000e\u001e \u0015\u0003=\u000bQ!\u00199qYf,\"!X9\u0015\u0005y#\b#B0\taJ<X\"A\u0003\u0003\u0007\u0005+\b0\u0006\u0003cO*t\'CA2f\r\u0011!W\u0001\u00012\u0003\u0019q\u0012XMZ5oK6,g\u000e\u001e \u0011\u0007A\u0003a\r\u0005\u0002(O\u0012)\u0011\u0006\u0003b\u0001U\u0015!Ah\u0019\u0011j!\t9#\u000eB\u0003l\u0011\t\u0007QH\u0001\u0003LKf\u0004T\u0001B!dA5\u0004\"a\n8\u0005\u000b=D!\u0019A\u001f\u0003\rY\u000bG.^31!\t9\u0013\u000fB\u0003*\u000f\t\u0007!\u0006\u0005\u0002t\u00039\u0011q\u0005\u001e\u0005\u0006k\u001e\u0001\u001dA^\u0001\u0006i>l\u0015\r\u001d\t\u0004!\u0002\u0001\bCA:\u0003\u0003%Ag.\u001b7U_6\u000b\u0007/\u0006\u0004{\u0003\u000f\ti!`\u000b\u0002wB9q\f\u0003?\u0002\u0006\u0005-\u0001CA\u0014~\t\u0015I\u0013B1\u0001\u007f#\tYs\u0010E\u0002!\u0003\u0003I1!a\u0001\u0014\u0005\u0011Ae*\u001b7\u0011\u0007\u001d\n9\u0001\u0002\u0004\u0002\n%\u0011\r!\u0010\u0002\u0002\u0017B\u0019q%!\u0004\u0005\r\u0005=\u0011B1\u0001>\u0005\u00051\u0016a\u00055oS2$v.T1q\u0003:Lhj\u001c;iS:<W\u0003BA\u000b\u00037)\"!a\u0006\u0011\r}C\u0011\u0011\u0004 ,!\r9\u00131\u0004\u0003\u0006S)\u0011\rA`\u0001\rQNLgn\u001a7f)>l\u0015\r]\u000b\u0007\u0003C\ty$a\u0011\u0015\t\u0005\r\u0012Q\t\t\t?\"\t)#!\u0010\u0002BA1\u0001%a\n\u0002,}L1!!\u000b\u0014\u00051!3m\u001c7p]\u0012\u001aw\u000e\\8o!!\ti#a\u000e\u0002>\u0005\u0005c\u0002BA\u0018\u0003gq1\u0001NA\u0019\u0013\u0005!\u0012bAA\u001b\'\u0005AA.\u00192fY2,G-\u0003\u0003\u0002:\u0005m\"!\u0003$jK2$G+\u001f9f\u0015\r\t)d\u0005\t\u0004O\u0005}BABA\u0005\u0017\t\u0007Q\bE\u0002(\u0003\u0007\"a!a\u0004\f\u0005\u0004i\u0004bBA$\u0017\u0001\u000f\u0011\u0011J\u0001\u0003o.\u0004b!a\u0013\u0002R\u0005ubb\u0001\u0011\u0002N%\u0019\u0011qJ\n\u0002\u000f]KGO\\3tg&\u0019\u0001-a\u0015\u000b\u0007\u0005=3#\u0001\u0006iY&\u001cH\u000fV8NCB,\"#!\u0017\u0002d\u0005%\u0014\u0011OA<\u0003\u001b\u000b\u0019*! \u0002\u0002RQ\u00111LAB\u0003/\u000b\t+a*\u0011\u0011}C\u0011QLA>\u0003\u007f\u0002r\u0001IA\u0014\u0003?\ni\u0007\u0005\u0005\u0002.\u0005]\u0012\u0011MA4!\r9\u00131\r\u0003\u0007\u0003Kb!\u0019A\u001f\u0003\u0005![\u0005cA\u0014\u0002j\u00111\u00111\u000e\u0007C\u0002u\u0012!\u0001\u0013,\u0011\u000f\u0001\n9#a\u001c\u0002vA\u0019q%!\u001d\u0005\r\u0005MDB1\u0001>\u0005\t!\u0006\nE\u0002(\u0003o\"a!!\u001f\r\u0005\u0004Q#A\u0001+U!\r9\u0013Q\u0010\u0003\u0007\u0003\u0013a!\u0019A\u001f\u0011\u0007\u001d\n\t\t\u0002\u0004\u0002\u00101\u0011\r!\u0010\u0005\b\u0003\u000bc\u00019AAD\u0003%!\u0018-\u001b7U_6\u000b\u0007\u000fE\u0005\u0002\n\"\ti\'a#\u0002\u0012:\u0011\u0001\u000b\u0002\t\u0004O\u00055EABAH\u0019\t\u0007QH\u0001\u0002U\u0017B\u0019q%a%\u0005\r\u0005UEB1\u0001>\u0005\t!f\u000bC\u0004\u0002\u001a2\u0001\u001d!a\'\u0002\r-,\u0017\u0010T;c!%\u0001\u0013QTA1\u0003\u0017\u000bY(C\u0002\u0002 N\u00111\u0001T;c\u0011\u001d\t\u0019\u000b\u0004a\u0002\u0003K\u000b\u0001B^1mk\u0016dUO\u0019\t\nA\u0005u\u0015qMAI\u0003\u007fBq!a\u0012\r\u0001\b\tI\u000b\u0005\u0004\u0002L\u0005E\u0013\u0011M\u0001\roJLG/\u001a*fa2\f7-\u001a\u000b\u0003\u0003_\u0003B!!-\u000286\u0011\u00111\u0017\u0006\u0004\u0003k3\u0016\u0001\u00027b]\u001eLA!!/\u00024\n1qJ\u00196fGR\u0004
  #14 = Utf8               shapeless/package
  #15 = Class              #14            // shapeless/package
  #16 = Utf8               DepFn1
  #17 = Utf8               hlistToMap
  #18 = Utf8               (Lshapeless/ops/record/ToMap;Lshapeless/Lub;Lshapeless/Lub;Lshapeless/Witness;)Lshapeless/ops/record/ToMap;
  #19 = Utf8               <HK:Ljava/lang/Object;HV:Ljava/lang/Object;TH:Ljava/lang/Object;TT::Lshapeless/HList;TK:Ljava/lang/Object;TV:Ljava/lang/Object;K:Ljava/lang/Object;V:Ljava/lang/Object;>(Lshapeless/ops/record/ToMap<Lshapeless/$colon$colon<TTH;TTT;>;>;Lshapeless/Lub<THK;TTK;TK;>;Lshapeless/Lub<THV;TTV;TV;>;Lshapeless/Witness;)Lshapeless/ops/record/ToMap<Lshapeless/$colon$colon<THV;Lshapeless/$colon$colon<TTH;TTT;>;>;>;
  #20 = Utf8               tailToMap
  #21 = Utf8               keyLub
  #22 = Utf8               valueLub
  #23 = Utf8               wk
  #24 = Utf8               shapeless/ops/record/ToMap$
  #25 = Class              #24            // shapeless/ops/record/ToMap$
  #26 = Utf8               MODULE$
  #27 = Utf8               Lshapeless/ops/record/ToMap$;
  #28 = NameAndType        #26:#27        // MODULE$:Lshapeless/ops/record/ToMap$;
  #29 = Fieldref           #25.#28        // shapeless/ops/record/ToMap$.MODULE$:Lshapeless/ops/record/ToMap$;
  #30 = NameAndType        #17:#18        // hlistToMap:(Lshapeless/ops/record/ToMap;Lshapeless/Lub;Lshapeless/Lub;Lshapeless/Witness;)Lshapeless/ops/record/ToMap;
  #31 = Methodref          #25.#30        // shapeless/ops/record/ToMap$.hlistToMap:(Lshapeless/ops/record/ToMap;Lshapeless/Lub;Lshapeless/Lub;Lshapeless/Witness;)Lshapeless/ops/record/ToMap;
  #32 = Utf8               hsingleToMap
  #33 = Utf8               (Lshapeless/Witness;)Lshapeless/ops/record/ToMap;
  #34 = Utf8               <K:Ljava/lang/Object;V:Ljava/lang/Object;>(Lshapeless/Witness;)Lshapeless/ops/record/ToMap<Lshapeless/$colon$colon<TV;Lshapeless/HNil;>;>;
  #35 = NameAndType        #32:#33        // hsingleToMap:(Lshapeless/Witness;)Lshapeless/ops/record/ToMap;
  #36 = Methodref          #25.#35        // shapeless/ops/record/ToMap$.hsingleToMap:(Lshapeless/Witness;)Lshapeless/ops/record/ToMap;
  #37 = Utf8               hnilToMapAnyNothing
  #38 = Utf8               ()Lshapeless/ops/record/ToMap;
  #39 = Utf8               <L::Lshapeless/HNil;>()Lshapeless/ops/record/ToMap<TL;>;
  #40 = NameAndType        #37:#38        // hnilToMapAnyNothing:()Lshapeless/ops/record/ToMap;
  #41 = Methodref          #25.#40        // shapeless/ops/record/ToMap$.hnilToMapAnyNothing:()Lshapeless/ops/record/ToMap;
  #42 = Utf8               hnilToMap
  #43 = Utf8               <K:Ljava/lang/Object;V:Ljava/lang/Object;L::Lshapeless/HNil;>()Lshapeless/ops/record/ToMap<TL;>;
  #44 = NameAndType        #42:#38        // hnilToMap:()Lshapeless/ops/record/ToMap;
  #45 = Methodref          #25.#44        // shapeless/ops/record/ToMap$.hnilToMap:()Lshapeless/ops/record/ToMap;
  #46 = Utf8               Code
  #47 = Utf8               Signature
  #48 = Utf8               MethodParameters
  #49 = Utf8               InnerClasses
  #50 = Utf8               SourceFile
  #51 = Utf8               RuntimeVisibleAnnotations
  #52 = Utf8               ScalaInlineInfo
  #53 = Utf8               ScalaSig
{
  public static <HK extends java.lang.Object, HV extends java.lang.Object, TH extends java.lang.Object, TT extends shapeless.HList, TK extends java.lang.Object, TV extends java.lang.Object, K extends java.lang.Object, V extends java.lang.Object> shapeless.ops.record.ToMap<shapeless.$colon$colon<HV, shapeless.$colon$colon<TH, TT>>> hlistToMap(shapeless.ops.record.ToMap<shapeless.$colon$colon<TH, TT>>, shapeless.Lub<HK, TK, K>, shapeless.Lub<HV, TV, V>, shapeless.Witness);
    descriptor: (Lshapeless/ops/record/ToMap;Lshapeless/Lub;Lshapeless/Lub;Lshapeless/Witness;)Lshapeless/ops/record/ToMap;
    flags: (0x0009) ACC_PUBLIC, ACC_STATIC
    Code:
      stack=5, locals=4, args_size=4
         0: getstatic     #29                 // Field shapeless/ops/record/ToMap$.MODULE$:Lshapeless/ops/record/ToMap$;
         3: aload_0
         4: aload_1
         5: aload_2
         6: aload_3
         7: invokevirtual #31                 // Method shapeless/ops/record/ToMap$.hlistToMap:(Lshapeless/ops/record/ToMap;Lshapeless/Lub;Lshapeless/Lub;Lshapeless/Witness;)Lshapeless/ops/record/ToMap;
        10: areturn
    Signature: #19                          // <HK:Ljava/lang/Object;HV:Ljava/lang/Object;TH:Ljava/lang/Object;TT::Lshapeless/HList;TK:Ljava/lang/Object;TV:Ljava/lang/Object;K:Ljava/lang/Object;V:Ljava/lang/Object;>(Lshapeless/ops/record/ToMap<Lshapeless/$colon$colon<TTH;TTT;>;>;Lshapeless/Lub<THK;TTK;TK;>;Lshapeless/Lub<THV;TTV;TV;>;Lshapeless/Witness;)Lshapeless/ops/record/ToMap<Lshapeless/$colon$colon<THV;Lshapeless/$colon$colon<TTH;TTT;>;>;>;
    MethodParameters:
      Name                           Flags
      tailToMap                      final
      keyLub                         final
      valueLub                       final
      wk                             final

  public static <K extends java.lang.Object, V extends java.lang.Object> shapeless.ops.record.ToMap<shapeless.$colon$colon<V, shapeless.HNil>> hsingleToMap(shapeless.Witness);
    descriptor: (Lshapeless/Witness;)Lshapeless/ops/record/ToMap;
    flags: (0x0009) ACC_PUBLIC, ACC_STATIC
    Code:
      stack=2, locals=1, args_size=1
         0: getstatic     #29                 // Field shapeless/ops/record/ToMap$.MODULE$:Lshapeless/ops/record/ToMap$;
         3: aload_0
         4: invokevirtual #36                 // Method shapeless/ops/record/ToMap$.hsingleToMap:(Lshapeless/Witness;)Lshapeless/ops/record/ToMap;
         7: areturn
    Signature: #34                          // <K:Ljava/lang/Object;V:Ljava/lang/Object;>(Lshapeless/Witness;)Lshapeless/ops/record/ToMap<Lshapeless/$colon$colon<TV;Lshapeless/HNil;>;>;
    MethodParameters:
      Name                           Flags
      wk                             final

  public static <L extends shapeless.HNil> shapeless.ops.record.ToMap<L> hnilToMapAnyNothing();
    descriptor: ()Lshapeless/ops/record/ToMap;
    flags: (0x0009) ACC_PUBLIC, ACC_STATIC
    Code:
      stack=1, locals=0, args_size=0
         0: getstatic     #29                 // Field shapeless/ops/record/ToMap$.MODULE$:Lshapeless/ops/record/ToMap$;
         3: invokevirtual #41                 // Method shapeless/ops/record/ToMap$.hnilToMapAnyNothing:()Lshapeless/ops/record/ToMap;
         6: areturn
    Signature: #39                          // <L::Lshapeless/HNil;>()Lshapeless/ops/record/ToMap<TL;>;

  public static <K extends java.lang.Object, V extends java.lang.Object, L extends shapeless.HNil> shapeless.ops.record.ToMap<L> hnilToMap();
    descriptor: ()Lshapeless/ops/record/ToMap;
    flags: (0x0009) ACC_PUBLIC, ACC_STATIC
    Code:
      stack=1, locals=0, args_size=0
         0: getstatic     #29                 // Field shapeless/ops/record/ToMap$.MODULE$:Lshapeless/ops/record/ToMap$;
         3: invokevirtual #45                 // Method shapeless/ops/record/ToMap$.hnilToMap:()Lshapeless/ops/record/ToMap;
         6: areturn
    Signature: #43                          // <K:Ljava/lang/Object;V:Ljava/lang/Object;L::Lshapeless/HNil;>()Lshapeless/ops/record/ToMap<TL;>;
}
InnerClasses:
  public static #16= #7 of #15;           // DepFn1=class shapeless/package$DepFn1 of class shapeless/package
Signature: #3                           // <L::Lshapeless/HList;>Ljava/lang/Object;Lshapeless/package$DepFn1<TL;>;Ljava/io/Serializable;
SourceFile: "records.scala"
RuntimeVisibleAnnotations:
  0: #11(#12=s#13)
    scala.reflect.ScalaSignature(
      bytes="\u0006\u0005\u0005mfa\u0002\b\u0010!\u0003\r\nA\u0006\u0003\u0006y\u0001\u0011\t!\u0010\u0003\u0006\u0003\u0002\u0011\t!P\u0003\u0005\u0005\u0002\u00011iB\u0003O\u001f!\u0005qJB\u0003\u000f\u001f!\u0005\u0011\u000bC\u0003Z\u000b\u0011\u0005!\fC\u0003\\\u000b\u0011\u0005A,\u0002\u0003a\u000b\u0001\t\u0007\"\u0002=\u0006\t\u0007I\bbBA\t\u000b\u0011\r\u00111\u0003\u0005\b\u0003;)A1AA\u0010\u0011\u001d\t)&\u0002C\u0002\u0003/B\u0011\"a+\u0006\u0003\u0003%I!!,\u0003\u000bQ{W*\u00199\u000b\u0005A\t\u0012A\u0002:fG>\u0014HM\u0003\u0002\u0013\'\u0005\u0019q\u000e]:\u000b\u0003Q\t\u0011b\u001d5ba\u0016dWm]:\u0004\u0001U\u0011q\u0003K\n\u0005\u0001aq\u0012\u0007\u0005\u0002\u001a95\t!DC\u0001\u001c\u0003\u0015\u00198-\u00197b\u0013\ti\"D\u0001\u0004B]f\u0014VM\u001a\t\u0004?\r2cB\u0001\u0011\"\u001b\u0005\u0019\u0012B\u0001\u0012\u0014\u0003\u001d\u0001\u0018mY6bO\u0016L!\u0001J\u0013\u0003\r\u0011+\u0007O\u001282\u0015\t\u00113\u0003\u0005\u0002(Q1\u0001A!B\u0015\u0001\u0005\u0004Q#!\u0001\'\u0012\u0005-r\u0003CA\r-\u0013\ti#DA\u0004O_RD\u0017N\\4\u0011\u0005\u0001z\u0013B\u0001\u0019\u0014\u0005\u0015AE*[:u!\t\u0011\u0014H\u0004\u00024q9\u0011AgN\u0007\u0002k)\u0011a\'F\u0001\u0007yI|w\u000e\u001e \n\u0003mI!A\t\u000e\n\u0005iZ$\u0001D*fe&\fG.\u001b>bE2,\'B\u0001\u0012\u001b\u0005\rYU-_\t\u0003Wy\u0002\"!G \n\u0005\u0001S\"aA!os\n)a+\u00197vK\n\u0019q*\u001e;\u0011\t\u0011C5*\u0014\b\u0003\u000b\u001a\u0003\"\u0001\u000e\u000e\n\u0005\u001dS\u0012A\u0002)sK\u0012,g-\u0003\u0002J\u0015\n\u0019Q*\u00199\u000b\u0005\u001dS\u0002C\u0001\'\u0002\u001b\u0005\u0001\u0001C\u0001\'\u0003\u0003\u0015!v.T1q!\t\u0001V!D\u0001\u0010\'\r)\u0001D\u0015\t\u0003\'bk\u0011\u0001\u0016\u0006\u0003+Z\u000b!![8\u000b\u0003]\u000bAA[1wC&\u0011!\bV\u0001\u0007y%t\u0017\u000e\u001e \u0015\u0003=\u000bQ!\u00199qYf,\"!X9\u0015\u0005y#\b#B0\taJ<X\"A\u0003\u0003\u0007\u0005+\b0\u0006\u0003cO*t\'CA2f\r\u0011!W\u0001\u00012\u0003\u0019q\u0012XMZ5oK6,g\u000e\u001e \u0011\u0007A\u0003a\r\u0005\u0002(O\u0012)\u0011\u0006\u0003b\u0001U\u0015!Ah\u0019\u0011j!\t9#\u000eB\u0003l\u0011\t\u0007QH\u0001\u0003LKf\u0004T\u0001B!dA5\u0004\"a\n8\u0005\u000b=D!\u0019A\u001f\u0003\rY\u000bG.^31!\t9\u0013\u000fB\u0003*\u000f\t\u0007!\u0006\u0005\u0002t\u00039\u0011q\u0005\u001e\u0005\u0006k\u001e\u0001\u001dA^\u0001\u0006i>l\u0015\r\u001d\t\u0004!\u0002\u0001\bCA:\u0003\u0003%Ag.\u001b7U_6\u000b\u0007/\u0006\u0004{\u0003\u000f\ti!`\u000b\u0002wB9q\f\u0003?\u0002\u0006\u0005-\u0001CA\u0014~\t\u0015I\u0013B1\u0001\u007f#\tYs\u0010E\u0002!\u0003\u0003I1!a\u0001\u0014\u0005\u0011Ae*\u001b7\u0011\u0007\u001d\n9\u0001\u0002\u0004\u0002\n%\u0011\r!\u0010\u0002\u0002\u0017B\u0019q%!\u0004\u0005\r\u0005=\u0011B1\u0001>\u0005\u00051\u0016a\u00055oS2$v.T1q\u0003:Lhj\u001c;iS:<W\u0003BA\u000b\u00037)\"!a\u0006\u0011\r}C\u0011\u0011\u0004 ,!\r9\u00131\u0004\u0003\u0006S)\u0011\rA`\u0001\rQNLgn\u001a7f)>l\u0015\r]\u000b\u0007\u0003C\ty$a\u0011\u0015\t\u0005\r\u0012Q\t\t\t?\"\t)#!\u0010\u0002BA1\u0001%a\n\u0002,}L1!!\u000b\u0014\u00051!3m\u001c7p]\u0012\u001aw\u000e\\8o!!\ti#a\u000e\u0002>\u0005\u0005c\u0002BA\u0018\u0003gq1\u0001NA\u0019\u0013\u0005!\u0012bAA\u001b\'\u0005AA.\u00192fY2,G-\u0003\u0003\u0002:\u0005m\"!\u0003$jK2$G+\u001f9f\u0015\r\t)d\u0005\t\u0004O\u0005}BABA\u0005\u0017\t\u0007Q\bE\u0002(\u0003\u0007\"a!a\u0004\f\u0005\u0004i\u0004bBA$\u0017\u0001\u000f\u0011\u0011J\u0001\u0003o.\u0004b!a\u0013\u0002R\u0005ubb\u0001\u0011\u0002N%\u0019\u0011qJ\n\u0002\u000f]KGO\\3tg&\u0019\u0001-a\u0015\u000b\u0007\u0005=3#\u0001\u0006iY&\u001cH\u000fV8NCB,\"#!\u0017\u0002d\u0005%\u0014\u0011OA<\u0003\u001b\u000b\u0019*! \u0002\u0002RQ\u00111LAB\u0003/\u000b\t+a*\u0011\u0011}C\u0011QLA>\u0003\u007f\u0002r\u0001IA\u0014\u0003?\ni\u0007\u0005\u0005\u0002.\u0005]\u0012\u0011MA4!\r9\u00131\r\u0003\u0007\u0003Kb!\u0019A\u001f\u0003\u0005![\u0005cA\u0014\u0002j\u00111\u00111\u000e\u0007C\u0002u\u0012!\u0001\u0013,\u0011\u000f\u0001\n9#a\u001c\u0002vA\u0019q%!\u001d\u0005\r\u0005MDB1\u0001>\u0005\t!\u0006\nE\u0002(\u0003o\"a!!\u001f\r\u0005\u0004Q#A\u0001+U!\r9\u0013Q\u0010\u0003\u0007\u0003\u0013a!\u0019A\u001f\u0011\u0007\u001d\n\t\t\u0002\u0004\u0002\u00101\u0011\r!\u0010\u0005\b\u0003\u000bc\u00019AAD\u0003%!\u0018-\u001b7U_6\u000b\u0007\u000fE\u0005\u0002\n\"\ti\'a#\u0002\u0012:\u0011\u0001\u000b\u0002\t\u0004O\u00055EABAH\u0019\t\u0007QH\u0001\u0002U\u0017B\u0019q%a%\u0005\r\u0005UEB1\u0001>\u0005\t!f\u000bC\u0004\u0002\u001a2\u0001\u001d!a\'\u0002\r-,\u0017\u0010T;c!%\u0001\u0013QTA1\u0003\u0017\u000bY(C\u0002\u0002 N\u00111\u0001T;c\u0011\u001d\t\u0019\u000b\u0004a\u0002\u0003K\u000b\u0001B^1mk\u0016dUO\u0019\t\nA\u0005u\u0015qMAI\u0003\u007fBq!a\u0012\r\u0001\b\tI\u000b\u0005\u0004\u0002L\u0005E\u0013\u0011M\u0001\roJLG/\u001a*fa2\f7-\u001a\u000b\u0003\u0003_\u0003B!!-\u000286\u0011\u00111\u0017\u0006\u0004\u0003k3\u0016\u0001\u00027b]\u001eLA!!/\u00024\n1qJ\u00196fGR\u0004"
    )
  ScalaInlineInfo: length = 0x4 (unknown attribute)
   01 00 00 00
  ScalaSig: length = 0x3 (unknown attribute)
   05 02 00
