Classfile /Users/mw/Projects/slang-braindump/.jar/jar8/assemble/slang-braindump/assemble/content/shapeless/ops/record/UnsafeModifier.class
  Last modified May 29, 2022; size 1745 bytes
  SHA-256 checksum f288726ba6c3afcfd091366f626cbf8babd5aa98a0dca4d46825ebeb0b25bee0
  Compiled from "records.scala"
public class shapeless.ops.record.UnsafeModifier extends java.lang.Object implements shapeless.ops.record.Modifier<shapeless.HList, java.lang.Object, java.lang.Object, java.lang.Object>
  minor version: 0
  major version: 52
  flags: (0x0021) ACC_PUBLIC, ACC_SUPER
  this_class: #2                          // shapeless/ops/record/UnsafeModifier
  super_class: #5                         // java/lang/Object
  interfaces: 1, fields: 1, methods: 3, attributes: 5
Constant pool:
   #1 = Utf8               shapeless/ops/record/UnsafeModifier
   #2 = Class              #1             // shapeless/ops/record/UnsafeModifier
   #3 = Utf8               Ljava/lang/Object;Lshapeless/ops/record/Modifier<Lshapeless/HList;Ljava/lang/Object;Ljava/lang/Object;Ljava/lang/Object;>;
   #4 = Utf8               java/lang/Object
   #5 = Class              #4             // java/lang/Object
   #6 = Utf8               shapeless/ops/record/Modifier
   #7 = Class              #6             // shapeless/ops/record/Modifier
   #8 = Utf8               records.scala
   #9 = Utf8               Lscala/reflect/ScalaSignature;
  #10 = Utf8               bytes
  #11 = Utf8               \u0006\u0005E2A!\u0002\u0004\u0001\u001b!Aq\u0004\u0001B\u0001B\u0003%\u0001\u0005C\u0003$\u0001\u0011\u0005A%\u0002\u0003(\u0001\u0001A\u0002\"\u0002\u0015\u0001\t\u0003I#AD+og\u00064W-T8eS\u001aLWM\u001d\u0006\u0003\u000f!\taA]3d_J$\'BA\u0005\u000b\u0003\ry\u0007o\u001d\u0006\u0002\u0017\u0005I1\u000f[1qK2,7o]\u0002\u0001\'\r\u0001a\u0002\u0006\t\u0003\u001fIi\u0011\u0001\u0005\u0006\u0002#\u0005)1oY1mC&\u00111\u0003\u0005\u0002\u0007\u0003:L(+\u001a4\u0011\rU1\u0002\u0004\b\u000f\u001d\u001b\u00051\u0011BA\f\u0007\u0005!iu\u000eZ5gS\u0016\u0014\bCA\r\u001b\u001b\u0005Q\u0011BA\u000e\u000b\u0005\u0015AE*[:u!\tyQ$\u0003\u0002\u001f!\t\u0019\u0011I\\=\u0002\u0003%\u0004\"aD\u0011\n\u0005\t\u0002\"aA%oi\u00061A(\u001b8jiz\"\"!\n\u0014\u0011\u0005U\u0001\u0001\"B\u0010\u0003\u0001\u0004\u0001#aA(vi\u0006)\u0011\r\u001d9msR\u0019\u0001D\u000b\u0017\t\u000b-\"\u0001\u0019\u0001\r\u0002\u00031DQ!\f\u0003A\u00029\n\u0011A\u001a\t\u0005\u001f=bB$\u0003\u00021!\tIa)\u001e8di&|g.\r
  #12 = Utf8               i
  #13 = Utf8               I
  #14 = Utf8               apply
  #15 = Utf8               (Lshapeless/HList;Lscala/Function1;)Lshapeless/HList;
  #16 = Utf8               (Lshapeless/HList;Lscala/Function1<Ljava/lang/Object;Ljava/lang/Object;>;)Lshapeless/HList;
  #17 = Utf8               l
  #18 = Utf8               f
  #19 = Utf8               shapeless/HList$
  #20 = Class              #19            // shapeless/HList$
  #21 = Utf8               MODULE$
  #22 = Utf8               Lshapeless/HList$;
  #23 = NameAndType        #21:#22        // MODULE$:Lshapeless/HList$;
  #24 = Fieldref           #20.#23        // shapeless/HList$.MODULE$:Lshapeless/HList$;
  #25 = NameAndType        #12:#13        // i:I
  #26 = Fieldref           #2.#25         // shapeless/ops/record/UnsafeModifier.i:I
  #27 = Utf8               unsafeUpdateWith
  #28 = Utf8               (Lshapeless/HList;ILscala/Function1;)Lshapeless/HList;
  #29 = NameAndType        #27:#28        // unsafeUpdateWith:(Lshapeless/HList;ILscala/Function1;)Lshapeless/HList;
  #30 = Methodref          #20.#29        // shapeless/HList$.unsafeUpdateWith:(Lshapeless/HList;ILscala/Function1;)Lshapeless/HList;
  #31 = Utf8               this
  #32 = Utf8               Lshapeless/ops/record/UnsafeModifier;
  #33 = Utf8               Lshapeless/HList;
  #34 = Utf8               Lscala/Function1;
  #35 = Utf8               (Ljava/lang/Object;Ljava/lang/Object;)Ljava/lang/Object;
  #36 = Utf8               t
  #37 = Utf8               u
  #38 = Utf8               shapeless/HList
  #39 = Class              #38            // shapeless/HList
  #40 = Utf8               scala/Function1
  #41 = Class              #40            // scala/Function1
  #42 = NameAndType        #14:#15        // apply:(Lshapeless/HList;Lscala/Function1;)Lshapeless/HList;
  #43 = Methodref          #2.#42         // shapeless/ops/record/UnsafeModifier.apply:(Lshapeless/HList;Lscala/Function1;)Lshapeless/HList;
  #44 = Utf8               Ljava/lang/Object;
  #45 = Utf8               <init>
  #46 = Utf8               (I)V
  #47 = Utf8               ()V
  #48 = NameAndType        #45:#47        // "<init>":()V
  #49 = Methodref          #5.#48         // java/lang/Object."<init>":()V
  #50 = Utf8               Code
  #51 = Utf8               LineNumberTable
  #52 = Utf8               LocalVariableTable
  #53 = Utf8               Signature
  #54 = Utf8               MethodParameters
  #55 = Utf8               SourceFile
  #56 = Utf8               RuntimeVisibleAnnotations
  #57 = Utf8               ScalaInlineInfo
  #58 = Utf8               ScalaSig
{
  private final int i;
    descriptor: I
    flags: (0x0012) ACC_PRIVATE, ACC_FINAL

  public shapeless.HList apply(shapeless.HList, scala.Function1<java.lang.Object, java.lang.Object>);
    descriptor: (Lshapeless/HList;Lscala/Function1;)Lshapeless/HList;
    flags: (0x0001) ACC_PUBLIC
    Code:
      stack=4, locals=3, args_size=3
         0: getstatic     #24                 // Field shapeless/HList$.MODULE$:Lshapeless/HList$;
         3: aload_1
         4: aload_0
         5: getfield      #26                 // Field i:I
         8: aload_2
         9: invokevirtual #30                 // Method shapeless/HList$.unsafeUpdateWith:(Lshapeless/HList;ILscala/Function1;)Lshapeless/HList;
        12: areturn
      LineNumberTable:
        line 385: 0
      LocalVariableTable:
        Start  Length  Slot  Name   Signature
            0      13     0  this   Lshapeless/ops/record/UnsafeModifier;
            0      13     1     l   Lshapeless/HList;
            0      13     2     f   Lscala/Function1;
    Signature: #16                          // (Lshapeless/HList;Lscala/Function1<Ljava/lang/Object;Ljava/lang/Object;>;)Lshapeless/HList;
    MethodParameters:
      Name                           Flags
      l                              final
      f                              final

  public java.lang.Object apply(java.lang.Object, java.lang.Object);
    descriptor: (Ljava/lang/Object;Ljava/lang/Object;)Ljava/lang/Object;
    flags: (0x1041) ACC_PUBLIC, ACC_BRIDGE, ACC_SYNTHETIC
    Code:
      stack=3, locals=3, args_size=3
         0: aload_0
         1: aload_1
         2: checkcast     #39                 // class shapeless/HList
         5: aload_2
         6: checkcast     #41                 // class scala/Function1
         9: invokevirtual #43                 // Method apply:(Lshapeless/HList;Lscala/Function1;)Lshapeless/HList;
        12: areturn
      LineNumberTable:
        line 383: 0
      LocalVariableTable:
        Start  Length  Slot  Name   Signature
            0      13     0  this   Lshapeless/ops/record/UnsafeModifier;
            0      13     1     t   Ljava/lang/Object;
            0      13     2     u   Ljava/lang/Object;
    MethodParameters:
      Name                           Flags
      t                              final
      u                              final

  public shapeless.ops.record.UnsafeModifier(int);
    descriptor: (I)V
    flags: (0x0001) ACC_PUBLIC
    Code:
      stack=2, locals=2, args_size=2
         0: aload_0
         1: iload_1
         2: putfield      #26                 // Field i:I
         5: aload_0
         6: invokespecial #49                 // Method java/lang/Object."<init>":()V
         9: return
      LineNumberTable:
        line 383: 0
      LocalVariableTable:
        Start  Length  Slot  Name   Signature
            0      10     0  this   Lshapeless/ops/record/UnsafeModifier;
            0      10     1     i   I
    MethodParameters:
      Name                           Flags
      i                              final
}
Signature: #3                           // Ljava/lang/Object;Lshapeless/ops/record/Modifier<Lshapeless/HList;Ljava/lang/Object;Ljava/lang/Object;Ljava/lang/Object;>;
SourceFile: "records.scala"
RuntimeVisibleAnnotations:
  0: #9(#10=s#11)
    scala.reflect.ScalaSignature(
      bytes="\u0006\u0005E2A!\u0002\u0004\u0001\u001b!Aq\u0004\u0001B\u0001B\u0003%\u0001\u0005C\u0003$\u0001\u0011\u0005A%\u0002\u0003(\u0001\u0001A\u0002\"\u0002\u0015\u0001\t\u0003I#AD+og\u00064W-T8eS\u001aLWM\u001d\u0006\u0003\u000f!\taA]3d_J$\'BA\u0005\u000b\u0003\ry\u0007o\u001d\u0006\u0002\u0017\u0005I1\u000f[1qK2,7o]\u0002\u0001\'\r\u0001a\u0002\u0006\t\u0003\u001fIi\u0011\u0001\u0005\u0006\u0002#\u0005)1oY1mC&\u00111\u0003\u0005\u0002\u0007\u0003:L(+\u001a4\u0011\rU1\u0002\u0004\b\u000f\u001d\u001b\u00051\u0011BA\f\u0007\u0005!iu\u000eZ5gS\u0016\u0014\bCA\r\u001b\u001b\u0005Q\u0011BA\u000e\u000b\u0005\u0015AE*[:u!\tyQ$\u0003\u0002\u001f!\t\u0019\u0011I\\=\u0002\u0003%\u0004\"aD\u0011\n\u0005\t\u0002\"aA%oi\u00061A(\u001b8jiz\"\"!\n\u0014\u0011\u0005U\u0001\u0001\"B\u0010\u0003\u0001\u0004\u0001#aA(vi\u0006)\u0011\r\u001d9msR\u0019\u0001D\u000b\u0017\t\u000b-\"\u0001\u0019\u0001\r\u0002\u00031DQ!\f\u0003A\u00029\n\u0011A\u001a\t\u0005\u001f=bB$\u0003\u00021!\tIa)\u001e8di&|g.\r"
    )
  ScalaInlineInfo: length = 0x13 (unknown attribute)
   01 00 00 03 00 2D 00 2E 00 00 0E 00 23 00 00 0E
   00 0F 00
  ScalaSig: length = 0x3 (unknown attribute)
   05 02 00
