Classfile /Users/mw/Projects/slang-braindump/.jar/jar11/assemble/slang-braindump/assemble/content/org/scalatest/matchers/must/Matchers$ResultOfHaveWordForCollectedExtent.class
  Last modified May 29, 2022; size 8165 bytes
  SHA-256 checksum d79fab64a12b5e2e7f5f9fdde40702cc5ca081f86f4961b3ddb45a6206a305f1
  Compiled from "Matchers.scala"
public final class org.scalatest.matchers.must.Matchers$ResultOfHaveWordForCollectedExtent<A extends java.lang.Object> extends java.lang.Object
  minor version: 0
  major version: 52
  flags: (0x0031) ACC_PUBLIC, ACC_FINAL, ACC_SUPER
  this_class: #2                          // org/scalatest/matchers/must/Matchers$ResultOfHaveWordForCollectedExtent
  super_class: #5                         // java/lang/Object
  interfaces: 0, fields: 7, methods: 13, attributes: 6
Constant pool:
    #1 = Utf8               org/scalatest/matchers/must/Matchers$ResultOfHaveWordForCollectedExtent
    #2 = Class              #1            // org/scalatest/matchers/must/Matchers$ResultOfHaveWordForCollectedExtent
    #3 = Utf8               <A:Ljava/lang/Object;>Ljava/lang/Object;
    #4 = Utf8               java/lang/Object
    #5 = Class              #4            // java/lang/Object
    #6 = Utf8               Matchers.scala
    #7 = Utf8               java/lang/invoke/MethodHandles$Lookup
    #8 = Class              #7            // java/lang/invoke/MethodHandles$Lookup
    #9 = Utf8               java/lang/invoke/MethodHandles
   #10 = Class              #9            // java/lang/invoke/MethodHandles
   #11 = Utf8               Lookup
   #12 = Utf8               org/scalatest/matchers/must/Matchers$Collected
   #13 = Class              #12           // org/scalatest/matchers/must/Matchers$Collected
   #14 = Utf8               org/scalatest/matchers/must/Matchers
   #15 = Class              #14           // org/scalatest/matchers/must/Matchers
   #16 = Utf8               Collected
   #17 = Utf8               ResultOfHaveWordForCollectedExtent
   #18 = Utf8               collected
   #19 = Utf8               Lorg/scalatest/matchers/must/Matchers$Collected;
   #20 = Utf8               xs
   #21 = Utf8               Lscala/collection/Iterable;
   #22 = Utf8               Lscala/collection/Iterable<TA;>;
   #23 = Utf8               original
   #24 = Utf8               Ljava/lang/Object;
   #25 = Utf8               mustBeTrue
   #26 = Utf8               Z
   #27 = Utf8               prettifier
   #28 = Utf8               Lorg/scalactic/Prettifier;
   #29 = Utf8               pos
   #30 = Utf8               Lorg/scalactic/source/Position;
   #31 = Utf8               $outer
   #32 = Utf8               Lorg/scalatest/matchers/must/Matchers;
   #33 = Utf8               length
   #34 = Utf8               (JLorg/scalatest/enablers/Length;)Lorg/scalatest/compatible/Assertion;
   #35 = Utf8               (JLorg/scalatest/enablers/Length<TA;>;)Lorg/scalatest/compatible/Assertion;
   #36 = Utf8               expectedLength
   #37 = Utf8               len
   #38 = NameAndType        #31:#32       // $outer:Lorg/scalatest/matchers/must/Matchers;
   #39 = Fieldref           #2.#38        // org/scalatest/matchers/must/Matchers$ResultOfHaveWordForCollectedExtent.$outer:Lorg/scalatest/matchers/must/Matchers;
   #40 = NameAndType        #18:#19       // collected:Lorg/scalatest/matchers/must/Matchers$Collected;
   #41 = Fieldref           #2.#40        // org/scalatest/matchers/must/Matchers$ResultOfHaveWordForCollectedExtent.collected:Lorg/scalatest/matchers/must/Matchers$Collected;
   #42 = NameAndType        #20:#21       // xs:Lscala/collection/Iterable;
   #43 = Fieldref           #2.#42        // org/scalatest/matchers/must/Matchers$ResultOfHaveWordForCollectedExtent.xs:Lscala/collection/Iterable;
   #44 = NameAndType        #23:#24       // original:Ljava/lang/Object;
   #45 = Fieldref           #2.#44        // org/scalatest/matchers/must/Matchers$ResultOfHaveWordForCollectedExtent.original:Ljava/lang/Object;
   #46 = NameAndType        #27:#28       // prettifier:Lorg/scalactic/Prettifier;
   #47 = Fieldref           #2.#46        // org/scalatest/matchers/must/Matchers$ResultOfHaveWordForCollectedExtent.prettifier:Lorg/scalactic/Prettifier;
   #48 = NameAndType        #29:#30       // pos:Lorg/scalactic/source/Position;
   #49 = Fieldref           #2.#48        // org/scalatest/matchers/must/Matchers$ResultOfHaveWordForCollectedExtent.pos:Lorg/scalactic/source/Position;
   #50 = Utf8               (Ljava/lang/Object;)Ljava/lang/Object;
   #51 = MethodType         #50           //  (Ljava/lang/Object;)Ljava/lang/Object;
   #52 = Utf8               $anonfun$length$4
   #53 = Utf8               (Lorg/scalatest/matchers/must/Matchers$ResultOfHaveWordForCollectedExtent;Lorg/scalatest/enablers/Length;JLjava/lang/Object;)Lorg/scalatest/compatible/Assertion;
   #54 = NameAndType        #52:#53       // $anonfun$length$4:(Lorg/scalatest/matchers/must/Matchers$ResultOfHaveWordForCollectedExtent;Lorg/scalatest/enablers/Length;JLjava/lang/Object;)Lorg/scalatest/compatible/Assertion;
   #55 = Methodref          #2.#54        // org/scalatest/matchers/must/Matchers$ResultOfHaveWordForCollectedExtent.$anonfun$length$4:(Lorg/scalatest/matchers/must/Matchers$ResultOfHaveWordForCollectedExtent;Lorg/scalatest/enablers/Length;JLjava/lang/Object;)Lorg/scalatest/compatible/Assertion;
   #56 = MethodHandle       6:#55         // REF_invokeStatic org/scalatest/matchers/must/Matchers$ResultOfHaveWordForCollectedExtent.$anonfun$length$4:(Lorg/scalatest/matchers/must/Matchers$ResultOfHaveWordForCollectedExtent;Lorg/scalatest/enablers/Length;JLjava/lang/Object;)Lorg/scalatest/compatible/Assertion;
   #57 = Utf8               (Ljava/lang/Object;)Lorg/scalatest/compatible/Assertion;
   #58 = MethodType         #57           //  (Ljava/lang/Object;)Lorg/scalatest/compatible/Assertion;
   #59 = Integer            5
   #60 = Integer            1
   #61 = Utf8               java/lang/invoke/LambdaMetafactory
   #62 = Class              #61           // java/lang/invoke/LambdaMetafactory
   #63 = Utf8               altMetafactory
   #64 = Utf8               (Ljava/lang/invoke/MethodHandles$Lookup;Ljava/lang/String;Ljava/lang/invoke/MethodType;[Ljava/lang/Object;)Ljava/lang/invoke/CallSite;
   #65 = NameAndType        #63:#64       // altMetafactory:(Ljava/lang/invoke/MethodHandles$Lookup;Ljava/lang/String;Ljava/lang/invoke/MethodType;[Ljava/lang/Object;)Ljava/lang/invoke/CallSite;
   #66 = Methodref          #62.#65       // java/lang/invoke/LambdaMetafactory.altMetafactory:(Ljava/lang/invoke/MethodHandles$Lookup;Ljava/lang/String;Ljava/lang/invoke/MethodType;[Ljava/lang/Object;)Ljava/lang/invoke/CallSite;
   #67 = MethodHandle       6:#66         // REF_invokeStatic java/lang/invoke/LambdaMetafactory.altMetafactory:(Ljava/lang/invoke/MethodHandles$Lookup;Ljava/lang/String;Ljava/lang/invoke/MethodType;[Ljava/lang/Object;)Ljava/lang/invoke/CallSite;
   #68 = Utf8               apply
   #69 = Utf8               (Lorg/scalatest/matchers/must/Matchers$ResultOfHaveWordForCollectedExtent;Lorg/scalatest/enablers/Length;J)Lscala/Function1;
   #70 = NameAndType        #68:#69       // apply:(Lorg/scalatest/matchers/must/Matchers$ResultOfHaveWordForCollectedExtent;Lorg/scalatest/enablers/Length;J)Lscala/Function1;
   #71 = InvokeDynamic      #0:#70        // #0:apply:(Lorg/scalatest/matchers/must/Matchers$ResultOfHaveWordForCollectedExtent;Lorg/scalatest/enablers/Length;J)Lscala/Function1;
   #72 = Utf8               doCollected
   #73 = Utf8               (Lorg/scalatest/matchers/must/Matchers$Collected;Lscala/collection/Iterable;Ljava/lang/Object;Lorg/scalactic/Prettifier;Lorg/scalactic/source/Position;Lscala/Function1;)Lorg/scalatest/compatible/Assertion;
   #74 = NameAndType        #72:#73       // doCollected:(Lorg/scalatest/matchers/must/Matchers$Collected;Lscala/collection/Iterable;Ljava/lang/Object;Lorg/scalactic/Prettifier;Lorg/scalactic/source/Position;Lscala/Function1;)Lorg/scalatest/compatible/Assertion;
   #75 = InterfaceMethodref #15.#74       // org/scalatest/matchers/must/Matchers.doCollected:(Lorg/scalatest/matchers/must/Matchers$Collected;Lscala/collection/Iterable;Ljava/lang/Object;Lorg/scalactic/Prettifier;Lorg/scalactic/source/Position;Lscala/Function1;)Lorg/scalatest/compatible/Assertion;
   #76 = Utf8               this
   #77 = Utf8               Lorg/scalatest/matchers/must/Matchers$ResultOfHaveWordForCollectedExtent;
   #78 = Utf8               J
   #79 = Utf8               Lorg/scalatest/enablers/Length;
   #80 = Utf8               size
   #81 = Utf8               (JLorg/scalatest/enablers/Size;)Lorg/scalatest/compatible/Assertion;
   #82 = Utf8               (JLorg/scalatest/enablers/Size<TA;>;)Lorg/scalatest/compatible/Assertion;
   #83 = Utf8               expectedSize
   #84 = Utf8               sz
   #85 = Utf8               $anonfun$size$4
   #86 = Utf8               (Lorg/scalatest/matchers/must/Matchers$ResultOfHaveWordForCollectedExtent;Lorg/scalatest/enablers/Size;JLjava/lang/Object;)Lorg/scalatest/compatible/Assertion;
   #87 = NameAndType        #85:#86       // $anonfun$size$4:(Lorg/scalatest/matchers/must/Matchers$ResultOfHaveWordForCollectedExtent;Lorg/scalatest/enablers/Size;JLjava/lang/Object;)Lorg/scalatest/compatible/Assertion;
   #88 = Methodref          #2.#87        // org/scalatest/matchers/must/Matchers$ResultOfHaveWordForCollectedExtent.$anonfun$size$4:(Lorg/scalatest/matchers/must/Matchers$ResultOfHaveWordForCollectedExtent;Lorg/scalatest/enablers/Size;JLjava/lang/Object;)Lorg/scalatest/compatible/Assertion;
   #89 = MethodHandle       6:#88         // REF_invokeStatic org/scalatest/matchers/must/Matchers$ResultOfHaveWordForCollectedExtent.$anonfun$size$4:(Lorg/scalatest/matchers/must/Matchers$ResultOfHaveWordForCollectedExtent;Lorg/scalatest/enablers/Size;JLjava/lang/Object;)Lorg/scalatest/compatible/Assertion;
   #90 = Utf8               (Lorg/scalatest/matchers/must/Matchers$ResultOfHaveWordForCollectedExtent;Lorg/scalatest/enablers/Size;J)Lscala/Function1;
   #91 = NameAndType        #68:#90       // apply:(Lorg/scalatest/matchers/must/Matchers$ResultOfHaveWordForCollectedExtent;Lorg/scalatest/enablers/Size;J)Lscala/Function1;
   #92 = InvokeDynamic      #1:#91        // #1:apply:(Lorg/scalatest/matchers/must/Matchers$ResultOfHaveWordForCollectedExtent;Lorg/scalatest/enablers/Size;J)Lscala/Function1;
   #93 = Utf8               Lorg/scalatest/enablers/Size;
   #94 = Utf8               toString
   #95 = Utf8               ()Ljava/lang/String;
   #96 = Utf8               java/lang/StringBuilder
   #97 = Class              #96           // java/lang/StringBuilder
   #98 = Integer            40
   #99 = Utf8               <init>
  #100 = Utf8               (I)V
  #101 = NameAndType        #99:#100      // "<init>":(I)V
  #102 = Methodref          #97.#101      // java/lang/StringBuilder."<init>":(I)V
  #103 = Utf8               ResultOfHaveWordForCollectedExtent(
  #104 = String             #103          // ResultOfHaveWordForCollectedExtent(
  #105 = Utf8               append
  #106 = Utf8               (Ljava/lang/String;)Ljava/lang/StringBuilder;
  #107 = NameAndType        #105:#106     // append:(Ljava/lang/String;)Ljava/lang/StringBuilder;
  #108 = Methodref          #97.#107      // java/lang/StringBuilder.append:(Ljava/lang/String;)Ljava/lang/StringBuilder;
  #109 = Utf8               org/scalactic/Prettifier$
  #110 = Class              #109          // org/scalactic/Prettifier$
  #111 = Utf8               MODULE$
  #112 = Utf8               Lorg/scalactic/Prettifier$;
  #113 = NameAndType        #111:#112     // MODULE$:Lorg/scalactic/Prettifier$;
  #114 = Fieldref           #110.#113     // org/scalactic/Prettifier$.MODULE$:Lorg/scalactic/Prettifier$;
  #115 = Utf8               default
  #116 = Utf8               ()Lorg/scalactic/Prettifier;
  #117 = NameAndType        #115:#116     // default:()Lorg/scalactic/Prettifier;
  #118 = Methodref          #110.#117     // org/scalactic/Prettifier$.default:()Lorg/scalactic/Prettifier;
  #119 = Utf8               org/scalactic/Prettifier
  #120 = Class              #119          // org/scalactic/Prettifier
  #121 = Utf8               (Ljava/lang/Object;)Ljava/lang/String;
  #122 = NameAndType        #68:#121      // apply:(Ljava/lang/Object;)Ljava/lang/String;
  #123 = InterfaceMethodref #120.#122     // org/scalactic/Prettifier.apply:(Ljava/lang/Object;)Ljava/lang/String;
  #124 = Utf8               ,
  #125 = String             #124          // ,
  #126 = NameAndType        #25:#26       // mustBeTrue:Z
  #127 = Fieldref           #2.#126       // org/scalatest/matchers/must/Matchers$ResultOfHaveWordForCollectedExtent.mustBeTrue:Z
  #128 = Utf8               scala/runtime/BoxesRunTime
  #129 = Class              #128          // scala/runtime/BoxesRunTime
  #130 = Utf8               boxToBoolean
  #131 = Utf8               (Z)Ljava/lang/Boolean;
  #132 = NameAndType        #130:#131     // boxToBoolean:(Z)Ljava/lang/Boolean;
  #133 = Methodref          #129.#132     // scala/runtime/BoxesRunTime.boxToBoolean:(Z)Ljava/lang/Boolean;
  #134 = Utf8               )
  #135 = String             #134          // )
  #136 = NameAndType        #94:#95       // toString:()Ljava/lang/String;
  #137 = Methodref          #97.#136      // java/lang/StringBuilder.toString:()Ljava/lang/String;
  #138 = Utf8               $anonfun$length$5
  #139 = Utf8               (Lorg/scalatest/matchers/must/Matchers$ResultOfHaveWordForCollectedExtent;Ljava/lang/Object;JJ)Ljava/lang/String;
  #140 = Utf8               $this
  #141 = Utf8               e$88
  #142 = Utf8               eLength$1
  #143 = Utf8               expectedLength$2
  #144 = Utf8               org/scalatest/FailureMessages$
  #145 = Class              #144          // org/scalatest/FailureMessages$
  #146 = Utf8               Lorg/scalatest/FailureMessages$;
  #147 = NameAndType        #111:#146     // MODULE$:Lorg/scalatest/FailureMessages$;
  #148 = Fieldref           #145.#147     // org/scalatest/FailureMessages$.MODULE$:Lorg/scalatest/FailureMessages$;
  #149 = Utf8               boxToLong
  #150 = Utf8               (J)Ljava/lang/Long;
  #151 = NameAndType        #149:#150     // boxToLong:(J)Ljava/lang/Long;
  #152 = Methodref          #129.#151     // scala/runtime/BoxesRunTime.boxToLong:(J)Ljava/lang/Long;
  #153 = Utf8               hadLengthInsteadOfExpectedLength
  #154 = Utf8               (Lorg/scalactic/Prettifier;Ljava/lang/Object;Ljava/lang/Object;Ljava/lang/Object;)Ljava/lang/String;
  #155 = NameAndType        #153:#154     // hadLengthInsteadOfExpectedLength:(Lorg/scalactic/Prettifier;Ljava/lang/Object;Ljava/lang/Object;Ljava/lang/Object;)Ljava/lang/String;
  #156 = Methodref          #145.#155     // org/scalatest/FailureMessages$.hadLengthInsteadOfExpectedLength:(Lorg/scalactic/Prettifier;Ljava/lang/Object;Ljava/lang/Object;Ljava/lang/Object;)Ljava/lang/String;
  #157 = Utf8               hadLength
  #158 = Utf8               (Lorg/scalactic/Prettifier;Ljava/lang/Object;Ljava/lang/Object;)Ljava/lang/String;
  #159 = NameAndType        #157:#158     // hadLength:(Lorg/scalactic/Prettifier;Ljava/lang/Object;Ljava/lang/Object;)Ljava/lang/String;
  #160 = Methodref          #145.#159     // org/scalatest/FailureMessages$.hadLength:(Lorg/scalactic/Prettifier;Ljava/lang/Object;Ljava/lang/Object;)Ljava/lang/String;
  #161 = Utf8               java/lang/String
  #162 = Class              #161          // java/lang/String
  #163 = Utf8               $anonfun$length$6
  #164 = Utf8               (Lorg/scalatest/matchers/must/Matchers$ResultOfHaveWordForCollectedExtent;Ljava/lang/Object;J)Ljava/lang/String;
  #165 = Utf8               $anonfun$length$7
  #166 = Utf8               len$2
  #167 = Utf8               e
  #168 = Utf8               org/scalatest/enablers/Length
  #169 = Class              #168          // org/scalatest/enablers/Length
  #170 = Utf8               lengthOf
  #171 = Utf8               (Ljava/lang/Object;)J
  #172 = NameAndType        #170:#171     // lengthOf:(Ljava/lang/Object;)J
  #173 = InterfaceMethodref #169.#172     // org/scalatest/enablers/Length.lengthOf:(Ljava/lang/Object;)J
  #174 = Utf8               org/scalatest/matchers/MatchersHelper$
  #175 = Class              #174          // org/scalatest/matchers/MatchersHelper$
  #176 = Utf8               Lorg/scalatest/matchers/MatchersHelper$;
  #177 = NameAndType        #111:#176     // MODULE$:Lorg/scalatest/matchers/MatchersHelper$;
  #178 = Fieldref           #175.#177     // org/scalatest/matchers/MatchersHelper$.MODULE$:Lorg/scalatest/matchers/MatchersHelper$;
  #179 = Utf8               ()Ljava/lang/Object;
  #180 = MethodType         #179          //  ()Ljava/lang/Object;
  #181 = NameAndType        #138:#139     // $anonfun$length$5:(Lorg/scalatest/matchers/must/Matchers$ResultOfHaveWordForCollectedExtent;Ljava/lang/Object;JJ)Ljava/lang/String;
  #182 = Methodref          #2.#181       // org/scalatest/matchers/must/Matchers$ResultOfHaveWordForCollectedExtent.$anonfun$length$5:(Lorg/scalatest/matchers/must/Matchers$ResultOfHaveWordForCollectedExtent;Ljava/lang/Object;JJ)Ljava/lang/String;
  #183 = MethodHandle       6:#182        // REF_invokeStatic org/scalatest/matchers/must/Matchers$ResultOfHaveWordForCollectedExtent.$anonfun$length$5:(Lorg/scalatest/matchers/must/Matchers$ResultOfHaveWordForCollectedExtent;Ljava/lang/Object;JJ)Ljava/lang/String;
  #184 = MethodType         #95           //  ()Ljava/lang/String;
  #185 = Utf8               (Lorg/scalatest/matchers/must/Matchers$ResultOfHaveWordForCollectedExtent;Ljava/lang/Object;JJ)Lscala/Function0;
  #186 = NameAndType        #68:#185      // apply:(Lorg/scalatest/matchers/must/Matchers$ResultOfHaveWordForCollectedExtent;Ljava/lang/Object;JJ)Lscala/Function0;
  #187 = InvokeDynamic      #2:#186       // #2:apply:(Lorg/scalatest/matchers/must/Matchers$ResultOfHaveWordForCollectedExtent;Ljava/lang/Object;JJ)Lscala/Function0;
  #188 = Utf8               scala/None$
  #189 = Class              #188          // scala/None$
  #190 = Utf8               Lscala/None$;
  #191 = NameAndType        #111:#190     // MODULE$:Lscala/None$;
  #192 = Fieldref           #189.#191     // scala/None$.MODULE$:Lscala/None$;
  #193 = Utf8               indicateFailure
  #194 = Utf8               (Lscala/Function0;Lscala/Option;Lorg/scalactic/source/Position;)Lorg/scalatest/compatible/Assertion;
  #195 = NameAndType        #193:#194     // indicateFailure:(Lscala/Function0;Lscala/Option;Lorg/scalactic/source/Position;)Lorg/scalatest/compatible/Assertion;
  #196 = Methodref          #175.#195     // org/scalatest/matchers/MatchersHelper$.indicateFailure:(Lscala/Function0;Lscala/Option;Lorg/scalactic/source/Position;)Lorg/scalatest/compatible/Assertion;
  #197 = NameAndType        #163:#164     // $anonfun$length$6:(Lorg/scalatest/matchers/must/Matchers$ResultOfHaveWordForCollectedExtent;Ljava/lang/Object;J)Ljava/lang/String;
  #198 = Methodref          #2.#197       // org/scalatest/matchers/must/Matchers$ResultOfHaveWordForCollectedExtent.$anonfun$length$6:(Lorg/scalatest/matchers/must/Matchers$ResultOfHaveWordForCollectedExtent;Ljava/lang/Object;J)Ljava/lang/String;
  #199 = MethodHandle       6:#198        // REF_invokeStatic org/scalatest/matchers/must/Matchers$ResultOfHaveWordForCollectedExtent.$anonfun$length$6:(Lorg/scalatest/matchers/must/Matchers$ResultOfHaveWordForCollectedExtent;Ljava/lang/Object;J)Ljava/lang/String;
  #200 = Utf8               (Lorg/scalatest/matchers/must/Matchers$ResultOfHaveWordForCollectedExtent;Ljava/lang/Object;J)Lscala/Function0;
  #201 = NameAndType        #68:#200      // apply:(Lorg/scalatest/matchers/must/Matchers$ResultOfHaveWordForCollectedExtent;Ljava/lang/Object;J)Lscala/Function0;
  #202 = InvokeDynamic      #3:#201       // #3:apply:(Lorg/scalatest/matchers/must/Matchers$ResultOfHaveWordForCollectedExtent;Ljava/lang/Object;J)Lscala/Function0;
  #203 = NameAndType        #165:#139     // $anonfun$length$7:(Lorg/scalatest/matchers/must/Matchers$ResultOfHaveWordForCollectedExtent;Ljava/lang/Object;JJ)Ljava/lang/String;
  #204 = Methodref          #2.#203       // org/scalatest/matchers/must/Matchers$ResultOfHaveWordForCollectedExtent.$anonfun$length$7:(Lorg/scalatest/matchers/must/Matchers$ResultOfHaveWordForCollectedExtent;Ljava/lang/Object;JJ)Ljava/lang/String;
  #205 = MethodHandle       6:#204        // REF_invokeStatic org/scalatest/matchers/must/Matchers$ResultOfHaveWordForCollectedExtent.$anonfun$length$7:(Lorg/scalatest/matchers/must/Matchers$ResultOfHaveWordForCollectedExtent;Ljava/lang/Object;JJ)Ljava/lang/String;
  #206 = InvokeDynamic      #4:#186       // #4:apply:(Lorg/scalatest/matchers/must/Matchers$ResultOfHaveWordForCollectedExtent;Ljava/lang/Object;JJ)Lscala/Function0;
  #207 = Utf8               indicateSuccess
  #208 = Utf8               (ZLscala/Function0;Lscala/Function0;)Lorg/scalatest/compatible/Assertion;
  #209 = NameAndType        #207:#208     // indicateSuccess:(ZLscala/Function0;Lscala/Function0;)Lorg/scalatest/compatible/Assertion;
  #210 = Methodref          #175.#209     // org/scalatest/matchers/MatchersHelper$.indicateSuccess:(ZLscala/Function0;Lscala/Function0;)Lorg/scalatest/compatible/Assertion;
  #211 = Utf8               eLength
  #212 = Utf8               org/scalatest/compatible/Assertion
  #213 = Class              #212          // org/scalatest/compatible/Assertion
  #214 = Utf8               $anonfun$size$5
  #215 = Utf8               e$89
  #216 = Utf8               eSize$1
  #217 = Utf8               expectedSize$2
  #218 = Utf8               hadSizeInsteadOfExpectedSize
  #219 = NameAndType        #218:#154     // hadSizeInsteadOfExpectedSize:(Lorg/scalactic/Prettifier;Ljava/lang/Object;Ljava/lang/Object;Ljava/lang/Object;)Ljava/lang/String;
  #220 = Methodref          #145.#219     // org/scalatest/FailureMessages$.hadSizeInsteadOfExpectedSize:(Lorg/scalactic/Prettifier;Ljava/lang/Object;Ljava/lang/Object;Ljava/lang/Object;)Ljava/lang/String;
  #221 = Utf8               hadSize
  #222 = NameAndType        #221:#158     // hadSize:(Lorg/scalactic/Prettifier;Ljava/lang/Object;Ljava/lang/Object;)Ljava/lang/String;
  #223 = Methodref          #145.#222     // org/scalatest/FailureMessages$.hadSize:(Lorg/scalactic/Prettifier;Ljava/lang/Object;Ljava/lang/Object;)Ljava/lang/String;
  #224 = Utf8               $anonfun$size$6
  #225 = Utf8               $anonfun$size$7
  #226 = Utf8               sz$2
  #227 = Utf8               org/scalatest/enablers/Size
  #228 = Class              #227          // org/scalatest/enablers/Size
  #229 = Utf8               sizeOf
  #230 = NameAndType        #229:#171     // sizeOf:(Ljava/lang/Object;)J
  #231 = InterfaceMethodref #228.#230     // org/scalatest/enablers/Size.sizeOf:(Ljava/lang/Object;)J
  #232 = NameAndType        #214:#139     // $anonfun$size$5:(Lorg/scalatest/matchers/must/Matchers$ResultOfHaveWordForCollectedExtent;Ljava/lang/Object;JJ)Ljava/lang/String;
  #233 = Methodref          #2.#232       // org/scalatest/matchers/must/Matchers$ResultOfHaveWordForCollectedExtent.$anonfun$size$5:(Lorg/scalatest/matchers/must/Matchers$ResultOfHaveWordForCollectedExtent;Ljava/lang/Object;JJ)Ljava/lang/String;
  #234 = MethodHandle       6:#233        // REF_invokeStatic org/scalatest/matchers/must/Matchers$ResultOfHaveWordForCollectedExtent.$anonfun$size$5:(Lorg/scalatest/matchers/must/Matchers$ResultOfHaveWordForCollectedExtent;Ljava/lang/Object;JJ)Ljava/lang/String;
  #235 = InvokeDynamic      #5:#186       // #5:apply:(Lorg/scalatest/matchers/must/Matchers$ResultOfHaveWordForCollectedExtent;Ljava/lang/Object;JJ)Lscala/Function0;
  #236 = NameAndType        #224:#164     // $anonfun$size$6:(Lorg/scalatest/matchers/must/Matchers$ResultOfHaveWordForCollectedExtent;Ljava/lang/Object;J)Ljava/lang/String;
  #237 = Methodref          #2.#236       // org/scalatest/matchers/must/Matchers$ResultOfHaveWordForCollectedExtent.$anonfun$size$6:(Lorg/scalatest/matchers/must/Matchers$ResultOfHaveWordForCollectedExtent;Ljava/lang/Object;J)Ljava/lang/String;
  #238 = MethodHandle       6:#237        // REF_invokeStatic org/scalatest/matchers/must/Matchers$ResultOfHaveWordForCollectedExtent.$anonfun$size$6:(Lorg/scalatest/matchers/must/Matchers$ResultOfHaveWordForCollectedExtent;Ljava/lang/Object;J)Ljava/lang/String;
  #239 = InvokeDynamic      #6:#201       // #6:apply:(Lorg/scalatest/matchers/must/Matchers$ResultOfHaveWordForCollectedExtent;Ljava/lang/Object;J)Lscala/Function0;
  #240 = NameAndType        #225:#139     // $anonfun$size$7:(Lorg/scalatest/matchers/must/Matchers$ResultOfHaveWordForCollectedExtent;Ljava/lang/Object;JJ)Ljava/lang/String;
  #241 = Methodref          #2.#240       // org/scalatest/matchers/must/Matchers$ResultOfHaveWordForCollectedExtent.$anonfun$size$7:(Lorg/scalatest/matchers/must/Matchers$ResultOfHaveWordForCollectedExtent;Ljava/lang/Object;JJ)Ljava/lang/String;
  #242 = MethodHandle       6:#241        // REF_invokeStatic org/scalatest/matchers/must/Matchers$ResultOfHaveWordForCollectedExtent.$anonfun$size$7:(Lorg/scalatest/matchers/must/Matchers$ResultOfHaveWordForCollectedExtent;Ljava/lang/Object;JJ)Ljava/lang/String;
  #243 = InvokeDynamic      #7:#186       // #7:apply:(Lorg/scalatest/matchers/must/Matchers$ResultOfHaveWordForCollectedExtent;Ljava/lang/Object;JJ)Lscala/Function0;
  #244 = Utf8               eSize
  #245 = Utf8               (Lorg/scalatest/matchers/must/Matchers;Lorg/scalatest/matchers/must/Matchers$Collected;Lscala/collection/Iterable;Ljava/lang/Object;ZLorg/scalactic/Prettifier;Lorg/scalactic/source/Position;)V
  #246 = Utf8               (Lorg/scalatest/matchers/must/Matchers$Collected;Lscala/collection/Iterable<TA;>;Ljava/lang/Object;ZLorg/scalactic/Prettifier;Lorg/scalactic/source/Position;)V
  #247 = Utf8               ()V
  #248 = NameAndType        #99:#247      // "<init>":()V
  #249 = Methodref          #5.#248       // java/lang/Object."<init>":()V
  #250 = Utf8               $deserializeLambda$
  #251 = Utf8               (Ljava/lang/invoke/SerializedLambda;)Ljava/lang/Object;
  #252 = Utf8               scala/runtime/LambdaDeserialize
  #253 = Class              #252          // scala/runtime/LambdaDeserialize
  #254 = Utf8               bootstrap
  #255 = Utf8               (Ljava/lang/invoke/MethodHandles$Lookup;Ljava/lang/String;Ljava/lang/invoke/MethodType;[Ljava/lang/invoke/MethodHandle;)Ljava/lang/invoke/CallSite;
  #256 = NameAndType        #254:#255     // bootstrap:(Ljava/lang/invoke/MethodHandles$Lookup;Ljava/lang/String;Ljava/lang/invoke/MethodType;[Ljava/lang/invoke/MethodHandle;)Ljava/lang/invoke/CallSite;
  #257 = Methodref          #253.#256     // scala/runtime/LambdaDeserialize.bootstrap:(Ljava/lang/invoke/MethodHandles$Lookup;Ljava/lang/String;Ljava/lang/invoke/MethodType;[Ljava/lang/invoke/MethodHandle;)Ljava/lang/invoke/CallSite;
  #258 = MethodHandle       6:#257        // REF_invokeStatic scala/runtime/LambdaDeserialize.bootstrap:(Ljava/lang/invoke/MethodHandles$Lookup;Ljava/lang/String;Ljava/lang/invoke/MethodType;[Ljava/lang/invoke/MethodHandle;)Ljava/lang/invoke/CallSite;
  #259 = Utf8               lambdaDeserialize
  #260 = NameAndType        #259:#251     // lambdaDeserialize:(Ljava/lang/invoke/SerializedLambda;)Ljava/lang/Object;
  #261 = InvokeDynamic      #8:#260       // #8:lambdaDeserialize:(Ljava/lang/invoke/SerializedLambda;)Ljava/lang/Object;
  #262 = Utf8               Signature
  #263 = Utf8               Code
  #264 = Utf8               LineNumberTable
  #265 = Utf8               LocalVariableTable
  #266 = Utf8               MethodParameters
  #267 = Utf8               StackMapTable
  #268 = Utf8               InnerClasses
  #269 = Utf8               SourceFile
  #270 = Utf8               BootstrapMethods
  #271 = Utf8               ScalaInlineInfo
  #272 = Utf8               Scala
{
  private final org.scalatest.matchers.must.Matchers$Collected collected;
    descriptor: Lorg/scalatest/matchers/must/Matchers$Collected;
    flags: (0x0012) ACC_PRIVATE, ACC_FINAL

  private final scala.collection.Iterable<A> xs;
    descriptor: Lscala/collection/Iterable;
    flags: (0x0012) ACC_PRIVATE, ACC_FINAL
    Signature: #22                          // Lscala/collection/Iterable<TA;>;

  private final java.lang.Object original;
    descriptor: Ljava/lang/Object;
    flags: (0x0012) ACC_PRIVATE, ACC_FINAL

  private final boolean mustBeTrue;
    descriptor: Z
    flags: (0x0012) ACC_PRIVATE, ACC_FINAL

  private final org.scalactic.Prettifier prettifier;
    descriptor: Lorg/scalactic/Prettifier;
    flags: (0x0012) ACC_PRIVATE, ACC_FINAL

  private final org.scalactic.source.Position pos;
    descriptor: Lorg/scalactic/source/Position;
    flags: (0x0012) ACC_PRIVATE, ACC_FINAL

  private final org.scalatest.matchers.must.Matchers $outer;
    descriptor: Lorg/scalatest/matchers/must/Matchers;
    flags: (0x1012) ACC_PRIVATE, ACC_FINAL, ACC_SYNTHETIC

  public org.scalatest.compatible.Assertion length(long, org.scalatest.enablers.Length<A>);
    descriptor: (JLorg/scalatest/enablers/Length;)Lorg/scalatest/compatible/Assertion;
    flags: (0x0001) ACC_PUBLIC
    Code:
      stack=10, locals=4, args_size=3
         0: aload_0
         1: getfield      #39                 // Field $outer:Lorg/scalatest/matchers/must/Matchers;
         4: aload_0
         5: getfield      #41                 // Field collected:Lorg/scalatest/matchers/must/Matchers$Collected;
         8: aload_0
         9: getfield      #43                 // Field xs:Lscala/collection/Iterable;
        12: aload_0
        13: getfield      #45                 // Field original:Ljava/lang/Object;
        16: aload_0
        17: getfield      #47                 // Field prettifier:Lorg/scalactic/Prettifier;
        20: aload_0
        21: getfield      #49                 // Field pos:Lorg/scalactic/source/Position;
        24: aload_0
        25: aload_3
        26: lload_1
        27: invokedynamic #71,  0             // InvokeDynamic #0:apply:(Lorg/scalatest/matchers/must/Matchers$ResultOfHaveWordForCollectedExtent;Lorg/scalatest/enablers/Length;J)Lscala/Function1;
        32: invokeinterface #75,  7           // InterfaceMethod org/scalatest/matchers/must/Matchers.doCollected:(Lorg/scalatest/matchers/must/Matchers$Collected;Lscala/collection/Iterable;Ljava/lang/Object;Lorg/scalactic/Prettifier;Lorg/scalactic/source/Position;Lscala/Function1;)Lorg/scalatest/compatible/Assertion;
        37: areturn
      LineNumberTable:
        line 6120: 0
      LocalVariableTable:
        Start  Length  Slot  Name   Signature
            0      38     0  this   Lorg/scalatest/matchers/must/Matchers$ResultOfHaveWordForCollectedExtent;
            0      38     1 expectedLength   J
            0      38     3   len   Lorg/scalatest/enablers/Length;
    Signature: #35                          // (JLorg/scalatest/enablers/Length<TA;>;)Lorg/scalatest/compatible/Assertion;
    MethodParameters:
      Name                           Flags
      expectedLength                 final
      len                            final

  public org.scalatest.compatible.Assertion size(long, org.scalatest.enablers.Size<A>);
    descriptor: (JLorg/scalatest/enablers/Size;)Lorg/scalatest/compatible/Assertion;
    flags: (0x0001) ACC_PUBLIC
    Code:
      stack=10, locals=4, args_size=3
         0: aload_0
         1: getfield      #39                 // Field $outer:Lorg/scalatest/matchers/must/Matchers;
         4: aload_0
         5: getfield      #41                 // Field collected:Lorg/scalatest/matchers/must/Matchers$Collected;
         8: aload_0
         9: getfield      #43                 // Field xs:Lscala/collection/Iterable;
        12: aload_0
        13: getfield      #45                 // Field original:Ljava/lang/Object;
        16: aload_0
        17: getfield      #47                 // Field prettifier:Lorg/scalactic/Prettifier;
        20: aload_0
        21: getfield      #49                 // Field pos:Lorg/scalactic/source/Position;
        24: aload_0
        25: aload_3
        26: lload_1
        27: invokedynamic #92,  0             // InvokeDynamic #1:apply:(Lorg/scalatest/matchers/must/Matchers$ResultOfHaveWordForCollectedExtent;Lorg/scalatest/enablers/Size;J)Lscala/Function1;
        32: invokeinterface #75,  7           // InterfaceMethod org/scalatest/matchers/must/Matchers.doCollected:(Lorg/scalatest/matchers/must/Matchers$Collected;Lscala/collection/Iterable;Ljava/lang/Object;Lorg/scalactic/Prettifier;Lorg/scalactic/source/Position;Lscala/Function1;)Lorg/scalatest/compatible/Assertion;
        37: areturn
      LineNumberTable:
        line 6149: 0
      LocalVariableTable:
        Start  Length  Slot  Name   Signature
            0      38     0  this   Lorg/scalatest/matchers/must/Matchers$ResultOfHaveWordForCollectedExtent;
            0      38     1 expectedSize   J
            0      38     3    sz   Lorg/scalatest/enablers/Size;
    Signature: #82                          // (JLorg/scalatest/enablers/Size<TA;>;)Lorg/scalatest/compatible/Assertion;
    MethodParameters:
      Name                           Flags
      expectedSize                   final
      sz                             final

  public java.lang.String toString();
    descriptor: ()Ljava/lang/String;
    flags: (0x0001) ACC_PUBLIC
    Code:
      stack=3, locals=1, args_size=1
         0: new           #97                 // class java/lang/StringBuilder
         3: dup
         4: ldc           #98                 // int 40
         6: invokespecial #102                // Method java/lang/StringBuilder."<init>":(I)V
         9: ldc           #104                // String ResultOfHaveWordForCollectedExtent(
        11: invokevirtual #108                // Method java/lang/StringBuilder.append:(Ljava/lang/String;)Ljava/lang/StringBuilder;
        14: getstatic     #114                // Field org/scalactic/Prettifier$.MODULE$:Lorg/scalactic/Prettifier$;
        17: invokevirtual #118                // Method org/scalactic/Prettifier$.default:()Lorg/scalactic/Prettifier;
        20: aload_0
        21: getfield      #41                 // Field collected:Lorg/scalatest/matchers/must/Matchers$Collected;
        24: invokeinterface #123,  2          // InterfaceMethod org/scalactic/Prettifier.apply:(Ljava/lang/Object;)Ljava/lang/String;
        29: invokevirtual #108                // Method java/lang/StringBuilder.append:(Ljava/lang/String;)Ljava/lang/StringBuilder;
        32: ldc           #125                // String ,
        34: invokevirtual #108                // Method java/lang/StringBuilder.append:(Ljava/lang/String;)Ljava/lang/StringBuilder;
        37: getstatic     #114                // Field org/scalactic/Prettifier$.MODULE$:Lorg/scalactic/Prettifier$;
        40: invokevirtual #118                // Method org/scalactic/Prettifier$.default:()Lorg/scalactic/Prettifier;
        43: aload_0
        44: getfield      #43                 // Field xs:Lscala/collection/Iterable;
        47: invokeinterface #123,  2          // InterfaceMethod org/scalactic/Prettifier.apply:(Ljava/lang/Object;)Ljava/lang/String;
        52: invokevirtual #108                // Method java/lang/StringBuilder.append:(Ljava/lang/String;)Ljava/lang/StringBuilder;
        55: ldc           #125                // String ,
        57: invokevirtual #108                // Method java/lang/StringBuilder.append:(Ljava/lang/String;)Ljava/lang/StringBuilder;
        60: getstatic     #114                // Field org/scalactic/Prettifier$.MODULE$:Lorg/scalactic/Prettifier$;
        63: invokevirtual #118                // Method org/scalactic/Prettifier$.default:()Lorg/scalactic/Prettifier;
        66: aload_0
        67: getfield      #127                // Field mustBeTrue:Z
        70: invokestatic  #133                // Method scala/runtime/BoxesRunTime.boxToBoolean:(Z)Ljava/lang/Boolean;
        73: invokeinterface #123,  2          // InterfaceMethod org/scalactic/Prettifier.apply:(Ljava/lang/Object;)Ljava/lang/String;
        78: invokevirtual #108                // Method java/lang/StringBuilder.append:(Ljava/lang/String;)Ljava/lang/StringBuilder;
        81: ldc           #135                // String )
        83: invokevirtual #108                // Method java/lang/StringBuilder.append:(Ljava/lang/String;)Ljava/lang/StringBuilder;
        86: invokevirtual #137                // Method java/lang/StringBuilder.toString:()Ljava/lang/String;
        89: areturn
      LineNumberTable:
        line 6173: 0
      LocalVariableTable:
        Start  Length  Slot  Name   Signature
            0      90     0  this   Lorg/scalatest/matchers/must/Matchers$ResultOfHaveWordForCollectedExtent;

  public static final java.lang.String $anonfun$length$5(org.scalatest.matchers.must.Matchers$ResultOfHaveWordForCollectedExtent, java.lang.Object, long, long);
    descriptor: (Lorg/scalatest/matchers/must/Matchers$ResultOfHaveWordForCollectedExtent;Ljava/lang/Object;JJ)Ljava/lang/String;
    flags: (0x1019) ACC_PUBLIC, ACC_STATIC, ACC_FINAL, ACC_SYNTHETIC
    Code:
      stack=6, locals=6, args_size=4
         0: aload_0
         1: getfield      #127                // Field mustBeTrue:Z
         4: ifeq          30
         7: getstatic     #148                // Field org/scalatest/FailureMessages$.MODULE$:Lorg/scalatest/FailureMessages$;
        10: aload_0
        11: getfield      #47                 // Field prettifier:Lorg/scalactic/Prettifier;
        14: aload_1
        15: lload_2
        16: invokestatic  #152                // Method scala/runtime/BoxesRunTime.boxToLong:(J)Ljava/lang/Long;
        19: lload         4
        21: invokestatic  #152                // Method scala/runtime/BoxesRunTime.boxToLong:(J)Ljava/lang/Long;
        24: invokevirtual #156                // Method org/scalatest/FailureMessages$.hadLengthInsteadOfExpectedLength:(Lorg/scalactic/Prettifier;Ljava/lang/Object;Ljava/lang/Object;Ljava/lang/Object;)Ljava/lang/String;
        27: goto          46
        30: getstatic     #148                // Field org/scalatest/FailureMessages$.MODULE$:Lorg/scalatest/FailureMessages$;
        33: aload_0
        34: getfield      #47                 // Field prettifier:Lorg/scalactic/Prettifier;
        37: aload_1
        38: lload         4
        40: invokestatic  #152                // Method scala/runtime/BoxesRunTime.boxToLong:(J)Ljava/lang/Long;
        43: invokevirtual #160                // Method org/scalatest/FailureMessages$.hadLength:(Lorg/scalactic/Prettifier;Ljava/lang/Object;Ljava/lang/Object;)Ljava/lang/String;
        46: areturn
      StackMapTable: number_of_entries = 2
        frame_type = 30 /* same */
        frame_type = 79 /* same_locals_1_stack_item */
          stack = [ class java/lang/String ]
      LineNumberTable:
        line 6124: 0
        line 6125: 7
        line 6127: 30
      LocalVariableTable:
        Start  Length  Slot  Name   Signature
            0      47     0 $this   Lorg/scalatest/matchers/must/Matchers$ResultOfHaveWordForCollectedExtent;
            0      47     1  e$88   Ljava/lang/Object;
            0      47     2 eLength$1   J
            0      47     4 expectedLength$2   J
    MethodParameters:
      Name                           Flags
      $this                          final synthetic
      e$88                           final
      eLength$1                      final
      expectedLength$2               final

  public static final java.lang.String $anonfun$length$6(org.scalatest.matchers.must.Matchers$ResultOfHaveWordForCollectedExtent, java.lang.Object, long);
    descriptor: (Lorg/scalatest/matchers/must/Matchers$ResultOfHaveWordForCollectedExtent;Ljava/lang/Object;J)Ljava/lang/String;
    flags: (0x1019) ACC_PUBLIC, ACC_STATIC, ACC_FINAL, ACC_SYNTHETIC
    Code:
      stack=5, locals=4, args_size=3
         0: getstatic     #148                // Field org/scalatest/FailureMessages$.MODULE$:Lorg/scalatest/FailureMessages$;
         3: aload_0
         4: getfield      #47                 // Field prettifier:Lorg/scalactic/Prettifier;
         7: aload_1
         8: lload_2
         9: invokestatic  #152                // Method scala/runtime/BoxesRunTime.boxToLong:(J)Ljava/lang/Long;
        12: invokevirtual #160                // Method org/scalatest/FailureMessages$.hadLength:(Lorg/scalactic/Prettifier;Ljava/lang/Object;Ljava/lang/Object;)Ljava/lang/String;
        15: areturn
      LineNumberTable:
        line 6134: 0
      LocalVariableTable:
        Start  Length  Slot  Name   Signature
            0      16     0 $this   Lorg/scalatest/matchers/must/Matchers$ResultOfHaveWordForCollectedExtent;
            0      16     1  e$88   Ljava/lang/Object;
            0      16     2 expectedLength$2   J
    MethodParameters:
      Name                           Flags
      $this                          final synthetic
      e$88                           final
      expectedLength$2               final

  public static final java.lang.String $anonfun$length$7(org.scalatest.matchers.must.Matchers$ResultOfHaveWordForCollectedExtent, java.lang.Object, long, long);
    descriptor: (Lorg/scalatest/matchers/must/Matchers$ResultOfHaveWordForCollectedExtent;Ljava/lang/Object;JJ)Ljava/lang/String;
    flags: (0x1019) ACC_PUBLIC, ACC_STATIC, ACC_FINAL, ACC_SYNTHETIC
    Code:
      stack=6, locals=6, args_size=4
         0: getstatic     #148                // Field org/scalatest/FailureMessages$.MODULE$:Lorg/scalatest/FailureMessages$;
         3: aload_0
         4: getfield      #47                 // Field prettifier:Lorg/scalactic/Prettifier;
         7: aload_1
         8: lload_2
         9: invokestatic  #152                // Method scala/runtime/BoxesRunTime.boxToLong:(J)Ljava/lang/Long;
        12: lload         4
        14: invokestatic  #152                // Method scala/runtime/BoxesRunTime.boxToLong:(J)Ljava/lang/Long;
        17: invokevirtual #156                // Method org/scalatest/FailureMessages$.hadLengthInsteadOfExpectedLength:(Lorg/scalactic/Prettifier;Ljava/lang/Object;Ljava/lang/Object;Ljava/lang/Object;)Ljava/lang/String;
        20: areturn
      LineNumberTable:
        line 6135: 0
      LocalVariableTable:
        Start  Length  Slot  Name   Signature
            0      21     0 $this   Lorg/scalatest/matchers/must/Matchers$ResultOfHaveWordForCollectedExtent;
            0      21     1  e$88   Ljava/lang/Object;
            0      21     2 eLength$1   J
            0      21     4 expectedLength$2   J
    MethodParameters:
      Name                           Flags
      $this                          final synthetic
      e$88                           final
      eLength$1                      final
      expectedLength$2               final

  public static final org.scalatest.compatible.Assertion $anonfun$length$4(org.scalatest.matchers.must.Matchers$ResultOfHaveWordForCollectedExtent, org.scalatest.enablers.Length, long, java.lang.Object);
    descriptor: (Lorg/scalatest/matchers/must/Matchers$ResultOfHaveWordForCollectedExtent;Lorg/scalatest/enablers/Length;JLjava/lang/Object;)Lorg/scalatest/compatible/Assertion;
    flags: (0x1019) ACC_PUBLIC, ACC_STATIC, ACC_FINAL, ACC_SYNTHETIC
    Code:
      stack=9, locals=7, args_size=4
         0: aload_1
         1: aload         4
         3: invokeinterface #173,  2          // InterfaceMethod org/scalatest/enablers/Length.lengthOf:(Ljava/lang/Object;)J
         8: lstore        5
        10: lload         5
        12: lload_2
        13: lcmp
        14: ifne          21
        17: iconst_1
        18: goto          22
        21: iconst_0
        22: aload_0
        23: getfield      #127                // Field mustBeTrue:Z
        26: if_icmpeq     56
        29: getstatic     #178                // Field org/scalatest/matchers/MatchersHelper$.MODULE$:Lorg/scalatest/matchers/MatchersHelper$;
        32: aload_0
        33: aload         4
        35: lload         5
        37: lload_2
        38: invokedynamic #187,  0            // InvokeDynamic #2:apply:(Lorg/scalatest/matchers/must/Matchers$ResultOfHaveWordForCollectedExtent;Ljava/lang/Object;JJ)Lscala/Function0;
        43: getstatic     #192                // Field scala/None$.MODULE$:Lscala/None$;
        46: aload_0
        47: getfield      #49                 // Field pos:Lorg/scalactic/source/Position;
        50: invokevirtual #196                // Method org/scalatest/matchers/MatchersHelper$.indicateFailure:(Lscala/Function0;Lscala/Option;Lorg/scalactic/source/Position;)Lorg/scalatest/compatible/Assertion;
        53: goto          86
        56: getstatic     #178                // Field org/scalatest/matchers/MatchersHelper$.MODULE$:Lorg/scalatest/matchers/MatchersHelper$;
        59: aload_0
        60: getfield      #127                // Field mustBeTrue:Z
        63: aload_0
        64: aload         4
        66: lload_2
        67: invokedynamic #202,  0            // InvokeDynamic #3:apply:(Lorg/scalatest/matchers/must/Matchers$ResultOfHaveWordForCollectedExtent;Ljava/lang/Object;J)Lscala/Function0;
        72: aload_0
        73: aload         4
        75: lload         5
        77: lload_2
        78: invokedynamic #206,  0            // InvokeDynamic #4:apply:(Lorg/scalatest/matchers/must/Matchers$ResultOfHaveWordForCollectedExtent;Ljava/lang/Object;JJ)Lscala/Function0;
        83: invokevirtual #210                // Method org/scalatest/matchers/MatchersHelper$.indicateSuccess:(ZLscala/Function0;Lscala/Function0;)Lorg/scalatest/compatible/Assertion;
        86: areturn
      StackMapTable: number_of_entries = 4
        frame_type = 252 /* append */
          offset_delta = 21
          locals = [ long ]
        frame_type = 64 /* same_locals_1_stack_item */
          stack = [ int ]
        frame_type = 33 /* same */
        frame_type = 93 /* same_locals_1_stack_item */
          stack = [ class org/scalatest/compatible/Assertion ]
      LineNumberTable:
        line 6121: 0
        line 6122: 10
        line 6123: 29
        line 6124: 32
        line 6128: 43
        line 6129: 46
        line 6132: 56
        line 6133: 59
        line 6134: 63
        line 6135: 72
      LocalVariableTable:
        Start  Length  Slot  Name   Signature
           10      76     5 eLength   J
            0      87     0 $this   Lorg/scalatest/matchers/must/Matchers$ResultOfHaveWordForCollectedExtent;
            0      87     1 len$2   Lorg/scalatest/enablers/Length;
            0      87     2 expectedLength$2   J
            0      87     4     e   Ljava/lang/Object;
    MethodParameters:
      Name                           Flags
      $this                          final synthetic
      len$2                          final
      expectedLength$2               final
      e                              final

  public static final java.lang.String $anonfun$size$5(org.scalatest.matchers.must.Matchers$ResultOfHaveWordForCollectedExtent, java.lang.Object, long, long);
    descriptor: (Lorg/scalatest/matchers/must/Matchers$ResultOfHaveWordForCollectedExtent;Ljava/lang/Object;JJ)Ljava/lang/String;
    flags: (0x1019) ACC_PUBLIC, ACC_STATIC, ACC_FINAL, ACC_SYNTHETIC
    Code:
      stack=6, locals=6, args_size=4
         0: aload_0
         1: getfield      #127                // Field mustBeTrue:Z
         4: ifeq          30
         7: getstatic     #148                // Field org/scalatest/FailureMessages$.MODULE$:Lorg/scalatest/FailureMessages$;
        10: aload_0
        11: getfield      #47                 // Field prettifier:Lorg/scalactic/Prettifier;
        14: aload_1
        15: lload_2
        16: invokestatic  #152                // Method scala/runtime/BoxesRunTime.boxToLong:(J)Ljava/lang/Long;
        19: lload         4
        21: invokestatic  #152                // Method scala/runtime/BoxesRunTime.boxToLong:(J)Ljava/lang/Long;
        24: invokevirtual #220                // Method org/scalatest/FailureMessages$.hadSizeInsteadOfExpectedSize:(Lorg/scalactic/Prettifier;Ljava/lang/Object;Ljava/lang/Object;Ljava/lang/Object;)Ljava/lang/String;
        27: goto          46
        30: getstatic     #148                // Field org/scalatest/FailureMessages$.MODULE$:Lorg/scalatest/FailureMessages$;
        33: aload_0
        34: getfield      #47                 // Field prettifier:Lorg/scalactic/Prettifier;
        37: aload_1
        38: lload         4
        40: invokestatic  #152                // Method scala/runtime/BoxesRunTime.boxToLong:(J)Ljava/lang/Long;
        43: invokevirtual #223                // Method org/scalatest/FailureMessages$.hadSize:(Lorg/scalactic/Prettifier;Ljava/lang/Object;Ljava/lang/Object;)Ljava/lang/String;
        46: areturn
      StackMapTable: number_of_entries = 2
        frame_type = 30 /* same */
        frame_type = 79 /* same_locals_1_stack_item */
          stack = [ class java/lang/String ]
      LineNumberTable:
        line 6153: 0
        line 6154: 7
        line 6156: 30
      LocalVariableTable:
        Start  Length  Slot  Name   Signature
            0      47     0 $this   Lorg/scalatest/matchers/must/Matchers$ResultOfHaveWordForCollectedExtent;
            0      47     1  e$89   Ljava/lang/Object;
            0      47     2 eSize$1   J
            0      47     4 expectedSize$2   J
    MethodParameters:
      Name                           Flags
      $this                          final synthetic
      e$89                           final
      eSize$1                        final
      expectedSize$2                 final

  public static final java.lang.String $anonfun$size$6(org.scalatest.matchers.must.Matchers$ResultOfHaveWordForCollectedExtent, java.lang.Object, long);
    descriptor: (Lorg/scalatest/matchers/must/Matchers$ResultOfHaveWordForCollectedExtent;Ljava/lang/Object;J)Ljava/lang/String;
    flags: (0x1019) ACC_PUBLIC, ACC_STATIC, ACC_FINAL, ACC_SYNTHETIC
    Code:
      stack=5, locals=4, args_size=3
         0: getstatic     #148                // Field org/scalatest/FailureMessages$.MODULE$:Lorg/scalatest/FailureMessages$;
         3: aload_0
         4: getfield      #47                 // Field prettifier:Lorg/scalactic/Prettifier;
         7: aload_1
         8: lload_2
         9: invokestatic  #152                // Method scala/runtime/BoxesRunTime.boxToLong:(J)Ljava/lang/Long;
        12: invokevirtual #223                // Method org/scalatest/FailureMessages$.hadSize:(Lorg/scalactic/Prettifier;Ljava/lang/Object;Ljava/lang/Object;)Ljava/lang/String;
        15: areturn
      LineNumberTable:
        line 6163: 0
      LocalVariableTable:
        Start  Length  Slot  Name   Signature
            0      16     0 $this   Lorg/scalatest/matchers/must/Matchers$ResultOfHaveWordForCollectedExtent;
            0      16     1  e$89   Ljava/lang/Object;
            0      16     2 expectedSize$2   J
    MethodParameters:
      Name                           Flags
      $this                          final synthetic
      e$89                           final
      expectedSize$2                 final

  public static final java.lang.String $anonfun$size$7(org.scalatest.matchers.must.Matchers$ResultOfHaveWordForCollectedExtent, java.lang.Object, long, long);
    descriptor: (Lorg/scalatest/matchers/must/Matchers$ResultOfHaveWordForCollectedExtent;Ljava/lang/Object;JJ)Ljava/lang/String;
    flags: (0x1019) ACC_PUBLIC, ACC_STATIC, ACC_FINAL, ACC_SYNTHETIC
    Code:
      stack=6, locals=6, args_size=4
         0: getstatic     #148                // Field org/scalatest/FailureMessages$.MODULE$:Lorg/scalatest/FailureMessages$;
         3: aload_0
         4: getfield      #47                 // Field prettifier:Lorg/scalactic/Prettifier;
         7: aload_1
         8: lload_2
         9: invokestatic  #152                // Method scala/runtime/BoxesRunTime.boxToLong:(J)Ljava/lang/Long;
        12: lload         4
        14: invokestatic  #152                // Method scala/runtime/BoxesRunTime.boxToLong:(J)Ljava/lang/Long;
        17: invokevirtual #220                // Method org/scalatest/FailureMessages$.hadSizeInsteadOfExpectedSize:(Lorg/scalactic/Prettifier;Ljava/lang/Object;Ljava/lang/Object;Ljava/lang/Object;)Ljava/lang/String;
        20: areturn
      LineNumberTable:
        line 6164: 0
      LocalVariableTable:
        Start  Length  Slot  Name   Signature
            0      21     0 $this   Lorg/scalatest/matchers/must/Matchers$ResultOfHaveWordForCollectedExtent;
            0      21     1  e$89   Ljava/lang/Object;
            0      21     2 eSize$1   J
            0      21     4 expectedSize$2   J
    MethodParameters:
      Name                           Flags
      $this                          final synthetic
      e$89                           final
      eSize$1                        final
      expectedSize$2                 final

  public static final org.scalatest.compatible.Assertion $anonfun$size$4(org.scalatest.matchers.must.Matchers$ResultOfHaveWordForCollectedExtent, org.scalatest.enablers.Size, long, java.lang.Object);
    descriptor: (Lorg/scalatest/matchers/must/Matchers$ResultOfHaveWordForCollectedExtent;Lorg/scalatest/enablers/Size;JLjava/lang/Object;)Lorg/scalatest/compatible/Assertion;
    flags: (0x1019) ACC_PUBLIC, ACC_STATIC, ACC_FINAL, ACC_SYNTHETIC
    Code:
      stack=9, locals=7, args_size=4
         0: aload_1
         1: aload         4
         3: invokeinterface #231,  2          // InterfaceMethod org/scalatest/enablers/Size.sizeOf:(Ljava/lang/Object;)J
         8: lstore        5
        10: lload         5
        12: lload_2
        13: lcmp
        14: ifne          21
        17: iconst_1
        18: goto          22
        21: iconst_0
        22: aload_0
        23: getfield      #127                // Field mustBeTrue:Z
        26: if_icmpeq     56
        29: getstatic     #178                // Field org/scalatest/matchers/MatchersHelper$.MODULE$:Lorg/scalatest/matchers/MatchersHelper$;
        32: aload_0
        33: aload         4
        35: lload         5
        37: lload_2
        38: invokedynamic #235,  0            // InvokeDynamic #5:apply:(Lorg/scalatest/matchers/must/Matchers$ResultOfHaveWordForCollectedExtent;Ljava/lang/Object;JJ)Lscala/Function0;
        43: getstatic     #192                // Field scala/None$.MODULE$:Lscala/None$;
        46: aload_0
        47: getfield      #49                 // Field pos:Lorg/scalactic/source/Position;
        50: invokevirtual #196                // Method org/scalatest/matchers/MatchersHelper$.indicateFailure:(Lscala/Function0;Lscala/Option;Lorg/scalactic/source/Position;)Lorg/scalatest/compatible/Assertion;
        53: goto          86
        56: getstatic     #178                // Field org/scalatest/matchers/MatchersHelper$.MODULE$:Lorg/scalatest/matchers/MatchersHelper$;
        59: aload_0
        60: getfield      #127                // Field mustBeTrue:Z
        63: aload_0
        64: aload         4
        66: lload_2
        67: invokedynamic #239,  0            // InvokeDynamic #6:apply:(Lorg/scalatest/matchers/must/Matchers$ResultOfHaveWordForCollectedExtent;Ljava/lang/Object;J)Lscala/Function0;
        72: aload_0
        73: aload         4
        75: lload         5
        77: lload_2
        78: invokedynamic #243,  0            // InvokeDynamic #7:apply:(Lorg/scalatest/matchers/must/Matchers$ResultOfHaveWordForCollectedExtent;Ljava/lang/Object;JJ)Lscala/Function0;
        83: invokevirtual #210                // Method org/scalatest/matchers/MatchersHelper$.indicateSuccess:(ZLscala/Function0;Lscala/Function0;)Lorg/scalatest/compatible/Assertion;
        86: areturn
      StackMapTable: number_of_entries = 4
        frame_type = 252 /* append */
          offset_delta = 21
          locals = [ long ]
        frame_type = 64 /* same_locals_1_stack_item */
          stack = [ int ]
        frame_type = 33 /* same */
        frame_type = 93 /* same_locals_1_stack_item */
          stack = [ class org/scalatest/compatible/Assertion ]
      LineNumberTable:
        line 6150: 0
        line 6151: 10
        line 6152: 29
        line 6153: 32
        line 6157: 43
        line 6158: 46
        line 6161: 56
        line 6162: 59
        line 6163: 63
        line 6164: 72
      LocalVariableTable:
        Start  Length  Slot  Name   Signature
           10      76     5 eSize   J
            0      87     0 $this   Lorg/scalatest/matchers/must/Matchers$ResultOfHaveWordForCollectedExtent;
            0      87     1  sz$2   Lorg/scalatest/enablers/Size;
            0      87     2 expectedSize$2   J
            0      87     4     e   Ljava/lang/Object;
    MethodParameters:
      Name                           Flags
      $this                          final synthetic
      sz$2                           final
      expectedSize$2                 final
      e                              final

  public org.scalatest.matchers.must.Matchers$ResultOfHaveWordForCollectedExtent(org.scalatest.matchers.must.Matchers$Collected, scala.collection.Iterable<A>, java.lang.Object, boolean, org.scalactic.Prettifier, org.scalactic.source.Position);
    descriptor: (Lorg/scalatest/matchers/must/Matchers;Lorg/scalatest/matchers/must/Matchers$Collected;Lscala/collection/Iterable;Ljava/lang/Object;ZLorg/scalactic/Prettifier;Lorg/scalactic/source/Position;)V
    flags: (0x0001) ACC_PUBLIC
    Code:
      stack=2, locals=8, args_size=8
         0: aload_0
         1: aload_2
         2: putfield      #41                 // Field collected:Lorg/scalatest/matchers/must/Matchers$Collected;
         5: aload_0
         6: aload_3
         7: putfield      #43                 // Field xs:Lscala/collection/Iterable;
        10: aload_0
        11: aload         4
        13: putfield      #45                 // Field original:Ljava/lang/Object;
        16: aload_0
        17: iload         5
        19: putfield      #127                // Field mustBeTrue:Z
        22: aload_0
        23: aload         6
        25: putfield      #47                 // Field prettifier:Lorg/scalactic/Prettifier;
        28: aload_0
        29: aload         7
        31: putfield      #49                 // Field pos:Lorg/scalactic/source/Position;
        34: aload_1
        35: ifnonnull     40
        38: aconst_null
        39: athrow
        40: aload_0
        41: aload_1
        42: putfield      #39                 // Field $outer:Lorg/scalatest/matchers/must/Matchers;
        45: aload_0
        46: invokespecial #249                // Method java/lang/Object."<init>":()V
        49: return
      StackMapTable: number_of_entries = 1
        frame_type = 40 /* same */
      LineNumberTable:
        line 6109: 0
        line 6183: 45
        line 6109: 49
      LocalVariableTable:
        Start  Length  Slot  Name   Signature
            0      50     0  this   Lorg/scalatest/matchers/must/Matchers$ResultOfHaveWordForCollectedExtent;
            0      50     1 $outer   Lorg/scalatest/matchers/must/Matchers;
            0      50     2 collected   Lorg/scalatest/matchers/must/Matchers$Collected;
            0      50     3    xs   Lscala/collection/Iterable;
            0      50     4 original   Ljava/lang/Object;
            0      50     5 mustBeTrue   Z
            0      50     6 prettifier   Lorg/scalactic/Prettifier;
            0      50     7   pos   Lorg/scalactic/source/Position;
    Signature: #246                         // (Lorg/scalatest/matchers/must/Matchers$Collected;Lscala/collection/Iterable<TA;>;Ljava/lang/Object;ZLorg/scalactic/Prettifier;Lorg/scalactic/source/Position;)V
    MethodParameters:
      Name                           Flags
      $outer                         final synthetic
      collected                      final
      xs                             final
      original                       final
      mustBeTrue                     final
      prettifier                     final
      pos                            final

  private static java.lang.Object $deserializeLambda$(java.lang.invoke.SerializedLambda);
    descriptor: (Ljava/lang/invoke/SerializedLambda;)Ljava/lang/Object;
    flags: (0x100a) ACC_PRIVATE, ACC_STATIC, ACC_SYNTHETIC
    Code:
      stack=1, locals=1, args_size=1
         0: aload_0
         1: invokedynamic #261,  0            // InvokeDynamic #8:lambdaDeserialize:(Ljava/lang/invoke/SerializedLambda;)Ljava/lang/Object;
         6: areturn
}
InnerClasses:
  public static final #11= #8 of #10;     // Lookup=class java/lang/invoke/MethodHandles$Lookup of class java/lang/invoke/MethodHandles
  public #16= #13 of #15;                 // Collected=class org/scalatest/matchers/must/Matchers$Collected of class org/scalatest/matchers/must/Matchers
  public final #17= #2 of #15;            // ResultOfHaveWordForCollectedExtent=class org/scalatest/matchers/must/Matchers$ResultOfHaveWordForCollectedExtent of class org/scalatest/matchers/must/Matchers
Signature: #3                           // <A:Ljava/lang/Object;>Ljava/lang/Object;
SourceFile: "Matchers.scala"
BootstrapMethods:
  0: #67 REF_invokeStatic java/lang/invoke/LambdaMetafactory.altMetafactory:(Ljava/lang/invoke/MethodHandles$Lookup;Ljava/lang/String;Ljava/lang/invoke/MethodType;[Ljava/lang/Object;)Ljava/lang/invoke/CallSite;
    Method arguments:
      #51 (Ljava/lang/Object;)Ljava/lang/Object;
      #56 REF_invokeStatic org/scalatest/matchers/must/Matchers$ResultOfHaveWordForCollectedExtent.$anonfun$length$4:(Lorg/scalatest/matchers/must/Matchers$ResultOfHaveWordForCollectedExtent;Lorg/scalatest/enablers/Length;JLjava/lang/Object;)Lorg/scalatest/compatible/Assertion;
      #58 (Ljava/lang/Object;)Lorg/scalatest/compatible/Assertion;
      #59 5
      #60 1
      #58 (Ljava/lang/Object;)Lorg/scalatest/compatible/Assertion;
  1: #67 REF_invokeStatic java/lang/invoke/LambdaMetafactory.altMetafactory:(Ljava/lang/invoke/MethodHandles$Lookup;Ljava/lang/String;Ljava/lang/invoke/MethodType;[Ljava/lang/Object;)Ljava/lang/invoke/CallSite;
    Method arguments:
      #51 (Ljava/lang/Object;)Ljava/lang/Object;
      #89 REF_invokeStatic org/scalatest/matchers/must/Matchers$ResultOfHaveWordForCollectedExtent.$anonfun$size$4:(Lorg/scalatest/matchers/must/Matchers$ResultOfHaveWordForCollectedExtent;Lorg/scalatest/enablers/Size;JLjava/lang/Object;)Lorg/scalatest/compatible/Assertion;
      #58 (Ljava/lang/Object;)Lorg/scalatest/compatible/Assertion;
      #59 5
      #60 1
      #58 (Ljava/lang/Object;)Lorg/scalatest/compatible/Assertion;
  2: #67 REF_invokeStatic java/lang/invoke/LambdaMetafactory.altMetafactory:(Ljava/lang/invoke/MethodHandles$Lookup;Ljava/lang/String;Ljava/lang/invoke/MethodType;[Ljava/lang/Object;)Ljava/lang/invoke/CallSite;
    Method arguments:
      #180 ()Ljava/lang/Object;
      #183 REF_invokeStatic org/scalatest/matchers/must/Matchers$ResultOfHaveWordForCollectedExtent.$anonfun$length$5:(Lorg/scalatest/matchers/must/Matchers$ResultOfHaveWordForCollectedExtent;Ljava/lang/Object;JJ)Ljava/lang/String;
      #184 ()Ljava/lang/String;
      #59 5
      #60 1
      #184 ()Ljava/lang/String;
  3: #67 REF_invokeStatic java/lang/invoke/LambdaMetafactory.altMetafactory:(Ljava/lang/invoke/MethodHandles$Lookup;Ljava/lang/String;Ljava/lang/invoke/MethodType;[Ljava/lang/Object;)Ljava/lang/invoke/CallSite;
    Method arguments:
      #180 ()Ljava/lang/Object;
      #199 REF_invokeStatic org/scalatest/matchers/must/Matchers$ResultOfHaveWordForCollectedExtent.$anonfun$length$6:(Lorg/scalatest/matchers/must/Matchers$ResultOfHaveWordForCollectedExtent;Ljava/lang/Object;J)Ljava/lang/String;
      #184 ()Ljava/lang/String;
      #59 5
      #60 1
      #184 ()Ljava/lang/String;
  4: #67 REF_invokeStatic java/lang/invoke/LambdaMetafactory.altMetafactory:(Ljava/lang/invoke/MethodHandles$Lookup;Ljava/lang/String;Ljava/lang/invoke/MethodType;[Ljava/lang/Object;)Ljava/lang/invoke/CallSite;
    Method arguments:
      #180 ()Ljava/lang/Object;
      #205 REF_invokeStatic org/scalatest/matchers/must/Matchers$ResultOfHaveWordForCollectedExtent.$anonfun$length$7:(Lorg/scalatest/matchers/must/Matchers$ResultOfHaveWordForCollectedExtent;Ljava/lang/Object;JJ)Ljava/lang/String;
      #184 ()Ljava/lang/String;
      #59 5
      #60 1
      #184 ()Ljava/lang/String;
  5: #67 REF_invokeStatic java/lang/invoke/LambdaMetafactory.altMetafactory:(Ljava/lang/invoke/MethodHandles$Lookup;Ljava/lang/String;Ljava/lang/invoke/MethodType;[Ljava/lang/Object;)Ljava/lang/invoke/CallSite;
    Method arguments:
      #180 ()Ljava/lang/Object;
      #234 REF_invokeStatic org/scalatest/matchers/must/Matchers$ResultOfHaveWordForCollectedExtent.$anonfun$size$5:(Lorg/scalatest/matchers/must/Matchers$ResultOfHaveWordForCollectedExtent;Ljava/lang/Object;JJ)Ljava/lang/String;
      #184 ()Ljava/lang/String;
      #59 5
      #60 1
      #184 ()Ljava/lang/String;
  6: #67 REF_invokeStatic java/lang/invoke/LambdaMetafactory.altMetafactory:(Ljava/lang/invoke/MethodHandles$Lookup;Ljava/lang/String;Ljava/lang/invoke/MethodType;[Ljava/lang/Object;)Ljava/lang/invoke/CallSite;
    Method arguments:
      #180 ()Ljava/lang/Object;
      #238 REF_invokeStatic org/scalatest/matchers/must/Matchers$ResultOfHaveWordForCollectedExtent.$anonfun$size$6:(Lorg/scalatest/matchers/must/Matchers$ResultOfHaveWordForCollectedExtent;Ljava/lang/Object;J)Ljava/lang/String;
      #184 ()Ljava/lang/String;
      #59 5
      #60 1
      #184 ()Ljava/lang/String;
  7: #67 REF_invokeStatic java/lang/invoke/LambdaMetafactory.altMetafactory:(Ljava/lang/invoke/MethodHandles$Lookup;Ljava/lang/String;Ljava/lang/invoke/MethodType;[Ljava/lang/Object;)Ljava/lang/invoke/CallSite;
    Method arguments:
      #180 ()Ljava/lang/Object;
      #242 REF_invokeStatic org/scalatest/matchers/must/Matchers$ResultOfHaveWordForCollectedExtent.$anonfun$size$7:(Lorg/scalatest/matchers/must/Matchers$ResultOfHaveWordForCollectedExtent;Ljava/lang/Object;JJ)Ljava/lang/String;
      #184 ()Ljava/lang/String;
      #59 5
      #60 1
      #184 ()Ljava/lang/String;
  8: #258 REF_invokeStatic scala/runtime/LambdaDeserialize.bootstrap:(Ljava/lang/invoke/MethodHandles$Lookup;Ljava/lang/String;Ljava/lang/invoke/MethodType;[Ljava/lang/invoke/MethodHandle;)Ljava/lang/invoke/CallSite;
    Method arguments:
      #56 REF_invokeStatic org/scalatest/matchers/must/Matchers$ResultOfHaveWordForCollectedExtent.$anonfun$length$4:(Lorg/scalatest/matchers/must/Matchers$ResultOfHaveWordForCollectedExtent;Lorg/scalatest/enablers/Length;JLjava/lang/Object;)Lorg/scalatest/compatible/Assertion;
      #183 REF_invokeStatic org/scalatest/matchers/must/Matchers$ResultOfHaveWordForCollectedExtent.$anonfun$length$5:(Lorg/scalatest/matchers/must/Matchers$ResultOfHaveWordForCollectedExtent;Ljava/lang/Object;JJ)Ljava/lang/String;
      #199 REF_invokeStatic org/scalatest/matchers/must/Matchers$ResultOfHaveWordForCollectedExtent.$anonfun$length$6:(Lorg/scalatest/matchers/must/Matchers$ResultOfHaveWordForCollectedExtent;Ljava/lang/Object;J)Ljava/lang/String;
      #205 REF_invokeStatic org/scalatest/matchers/must/Matchers$ResultOfHaveWordForCollectedExtent.$anonfun$length$7:(Lorg/scalatest/matchers/must/Matchers$ResultOfHaveWordForCollectedExtent;Ljava/lang/Object;JJ)Ljava/lang/String;
      #89 REF_invokeStatic org/scalatest/matchers/must/Matchers$ResultOfHaveWordForCollectedExtent.$anonfun$size$4:(Lorg/scalatest/matchers/must/Matchers$ResultOfHaveWordForCollectedExtent;Lorg/scalatest/enablers/Size;JLjava/lang/Object;)Lorg/scalatest/compatible/Assertion;
      #234 REF_invokeStatic org/scalatest/matchers/must/Matchers$ResultOfHaveWordForCollectedExtent.$anonfun$size$5:(Lorg/scalatest/matchers/must/Matchers$ResultOfHaveWordForCollectedExtent;Ljava/lang/Object;JJ)Ljava/lang/String;
      #238 REF_invokeStatic org/scalatest/matchers/must/Matchers$ResultOfHaveWordForCollectedExtent.$anonfun$size$6:(Lorg/scalatest/matchers/must/Matchers$ResultOfHaveWordForCollectedExtent;Ljava/lang/Object;J)Ljava/lang/String;
      #242 REF_invokeStatic org/scalatest/matchers/must/Matchers$ResultOfHaveWordForCollectedExtent.$anonfun$size$7:(Lorg/scalatest/matchers/must/Matchers$ResultOfHaveWordForCollectedExtent;Ljava/lang/Object;JJ)Ljava/lang/String;
  ScalaInlineInfo: length = 0x40 (unknown attribute)
   01 01 00 0C 00 34 00 35 01 00 8A 00 8B 01 00 A3
   00 A4 01 00 A5 00 8B 01 00 55 00 56 01 00 D6 00
   8B 01 00 E0 00 A4 01 00 E1 00 8B 01 00 63 00 F5
   01 00 21 00 22 01 00 50 00 51 01 00 5E 00 5F 01

  Scala: length = 0x0 (unknown attribute)

