Classfile /Users/mw/Projects/slang-braindump/.jar/jar11/assemble/slang-braindump/assemble/content/org/scalatest/matchers/must/Matchers$HavePropertyMatcherGenerator.class
  Last modified May 29, 2022; size 1590 bytes
  SHA-256 checksum 67a3c9d236e3247d1e7c554a5020acfb7f4af2d71a82f856cd7a41c58c70f8c1
  Compiled from "Matchers.scala"
public final class org.scalatest.matchers.must.Matchers$HavePropertyMatcherGenerator
  minor version: 0
  major version: 52
  flags: (0x0031) ACC_PUBLIC, ACC_FINAL, ACC_SUPER
  this_class: #2                          // org/scalatest/matchers/must/Matchers$HavePropertyMatcherGenerator
  super_class: #4                         // java/lang/Object
  interfaces: 0, fields: 2, methods: 2, attributes: 4
Constant pool:
   #1 = Utf8               org/scalatest/matchers/must/Matchers$HavePropertyMatcherGenerator
   #2 = Class              #1             // org/scalatest/matchers/must/Matchers$HavePropertyMatcherGenerator
   #3 = Utf8               java/lang/Object
   #4 = Class              #3             // java/lang/Object
   #5 = Utf8               Matchers.scala
   #6 = Utf8               org/scalatest/matchers/must/Matchers
   #7 = Class              #6             // org/scalatest/matchers/must/Matchers
   #8 = Utf8               HavePropertyMatcherGenerator
   #9 = Utf8               org/scalatest/matchers/must/Matchers$HavePropertyMatcherGenerator$$anon$1
  #10 = Class              #9             // org/scalatest/matchers/must/Matchers$HavePropertyMatcherGenerator$$anon$1
  #11 = Utf8               org$scalatest$matchers$must$Matchers$HavePropertyMatcherGenerator$$symbol
  #12 = Utf8               Lscala/Symbol;
  #13 = Utf8               org$scalatest$matchers$must$Matchers$HavePropertyMatcherGenerator$$pos
  #14 = Utf8               Lorg/scalactic/source/Position;
  #15 = Utf8               apply
  #16 = Utf8               (Ljava/lang/Object;)Lorg/scalatest/matchers/HavePropertyMatcher;
  #17 = Utf8               (Ljava/lang/Object;)Lorg/scalatest/matchers/HavePropertyMatcher<Ljava/lang/Object;Ljava/lang/Object;>;
  #18 = Utf8               expectedValue
  #19 = Utf8               <init>
  #20 = Utf8               (Lorg/scalatest/matchers/must/Matchers$HavePropertyMatcherGenerator;Ljava/lang/Object;)V
  #21 = NameAndType        #19:#20        // "<init>":(Lorg/scalatest/matchers/must/Matchers$HavePropertyMatcherGenerator;Ljava/lang/Object;)V
  #22 = Methodref          #10.#21        // org/scalatest/matchers/must/Matchers$HavePropertyMatcherGenerator$$anon$1."<init>":(Lorg/scalatest/matchers/must/Matchers$HavePropertyMatcherGenerator;Ljava/lang/Object;)V
  #23 = Utf8               this
  #24 = Utf8               Lorg/scalatest/matchers/must/Matchers$HavePropertyMatcherGenerator;
  #25 = Utf8               Ljava/lang/Object;
  #26 = Utf8               (Lorg/scalatest/matchers/must/Matchers;Lscala/Symbol;Lorg/scalactic/Prettifier;Lorg/scalactic/source/Position;)V
  #27 = Utf8               $outer
  #28 = Utf8               symbol
  #29 = Utf8               prettifer
  #30 = Utf8               pos
  #31 = NameAndType        #11:#12        // org$scalatest$matchers$must$Matchers$HavePropertyMatcherGenerator$$symbol:Lscala/Symbol;
  #32 = Fieldref           #2.#31         // org/scalatest/matchers/must/Matchers$HavePropertyMatcherGenerator.org$scalatest$matchers$must$Matchers$HavePropertyMatcherGenerator$$symbol:Lscala/Symbol;
  #33 = NameAndType        #13:#14        // org$scalatest$matchers$must$Matchers$HavePropertyMatcherGenerator$$pos:Lorg/scalactic/source/Position;
  #34 = Fieldref           #2.#33         // org/scalatest/matchers/must/Matchers$HavePropertyMatcherGenerator.org$scalatest$matchers$must$Matchers$HavePropertyMatcherGenerator$$pos:Lorg/scalactic/source/Position;
  #35 = Utf8               ()V
  #36 = NameAndType        #19:#35        // "<init>":()V
  #37 = Methodref          #4.#36         // java/lang/Object."<init>":()V
  #38 = Utf8               Lorg/scalatest/matchers/must/Matchers;
  #39 = Utf8               Lorg/scalactic/Prettifier;
  #40 = Utf8               Code
  #41 = Utf8               LineNumberTable
  #42 = Utf8               LocalVariableTable
  #43 = Utf8               Signature
  #44 = Utf8               MethodParameters
  #45 = Utf8               InnerClasses
  #46 = Utf8               SourceFile
  #47 = Utf8               ScalaInlineInfo
  #48 = Utf8               Scala
{
  public final scala.Symbol org$scalatest$matchers$must$Matchers$HavePropertyMatcherGenerator$$symbol;
    descriptor: Lscala/Symbol;
    flags: (0x0011) ACC_PUBLIC, ACC_FINAL

  public final org.scalactic.source.Position org$scalatest$matchers$must$Matchers$HavePropertyMatcherGenerator$$pos;
    descriptor: Lorg/scalactic/source/Position;
    flags: (0x0011) ACC_PUBLIC, ACC_FINAL

  public org.scalatest.matchers.HavePropertyMatcher<java.lang.Object, java.lang.Object> apply(java.lang.Object);
    descriptor: (Ljava/lang/Object;)Lorg/scalatest/matchers/HavePropertyMatcher;
    flags: (0x0001) ACC_PUBLIC
    Code:
      stack=4, locals=2, args_size=2
         0: new           #10                 // class org/scalatest/matchers/must/Matchers$HavePropertyMatcherGenerator$$anon$1
         3: dup
         4: aload_0
         5: aload_1
         6: invokespecial #22                 // Method org/scalatest/matchers/must/Matchers$HavePropertyMatcherGenerator$$anon$1."<init>":(Lorg/scalatest/matchers/must/Matchers$HavePropertyMatcherGenerator;Ljava/lang/Object;)V
         9: areturn
      LineNumberTable:
        line 1875: 0
      LocalVariableTable:
        Start  Length  Slot  Name   Signature
            0      10     0  this   Lorg/scalatest/matchers/must/Matchers$HavePropertyMatcherGenerator;
            0      10     1 expectedValue   Ljava/lang/Object;
    Signature: #17                          // (Ljava/lang/Object;)Lorg/scalatest/matchers/HavePropertyMatcher<Ljava/lang/Object;Ljava/lang/Object;>;
    MethodParameters:
      Name                           Flags
      expectedValue                  final

  public org.scalatest.matchers.must.Matchers$HavePropertyMatcherGenerator(org.scalatest.matchers.must.Matchers, scala.Symbol, org.scalactic.Prettifier, org.scalactic.source.Position);
    descriptor: (Lorg/scalatest/matchers/must/Matchers;Lscala/Symbol;Lorg/scalactic/Prettifier;Lorg/scalactic/source/Position;)V
    flags: (0x0001) ACC_PUBLIC
    Code:
      stack=2, locals=5, args_size=5
         0: aload_0
         1: aload_2
         2: putfield      #32                 // Field org$scalatest$matchers$must$Matchers$HavePropertyMatcherGenerator$$symbol:Lscala/Symbol;
         5: aload_0
         6: aload         4
         8: putfield      #34                 // Field org$scalatest$matchers$must$Matchers$HavePropertyMatcherGenerator$$pos:Lorg/scalactic/source/Position;
        11: aload_0
        12: invokespecial #37                 // Method java/lang/Object."<init>":()V
        15: return
      LineNumberTable:
        line 1854: 0
        line 1948: 11
        line 1854: 15
      LocalVariableTable:
        Start  Length  Slot  Name   Signature
            0      16     0  this   Lorg/scalatest/matchers/must/Matchers$HavePropertyMatcherGenerator;
            0      16     1 $outer   Lorg/scalatest/matchers/must/Matchers;
            0      16     2 symbol   Lscala/Symbol;
            0      16     3 prettifer   Lorg/scalactic/Prettifier;
            0      16     4   pos   Lorg/scalactic/source/Position;
    MethodParameters:
      Name                           Flags
      $outer                         final synthetic
      symbol                         final
      prettifer                      final
      pos                            final
}
InnerClasses:
  public final #8= #2 of #7;              // HavePropertyMatcherGenerator=class org/scalatest/matchers/must/Matchers$HavePropertyMatcherGenerator of class org/scalatest/matchers/must/Matchers
  public final #10;                       // class org/scalatest/matchers/must/Matchers$HavePropertyMatcherGenerator$$anon$1
SourceFile: "Matchers.scala"
  ScalaInlineInfo: length = 0xE (unknown attribute)
   01 01 00 02 00 13 00 1A 01 00 0F 00 10 01
  Scala: length = 0x0 (unknown attribute)

