Classfile /Users/mw/Projects/slang-braindump/.jar/jar8/assemble/slang-braindump/assemble/content/coursier/core/shaded/fastparse/internal/Logger.class
  Last modified May 29, 2022; size 5079 bytes
  SHA-256 checksum f064e2ca99677ffb6afa09e7ab5e248dd1d9d381488336e14ead772ace8e6d30
  Compiled from "Util.scala"
public class coursier.core.shaded.fastparse.internal.Logger implements scala.Product,java.io.Serializable
  minor version: 0
  major version: 52
  flags: (0x0021) ACC_PUBLIC, ACC_SUPER
  this_class: #2                          // coursier/core/shaded/fastparse/internal/Logger
  super_class: #4                         // java/lang/Object
  interfaces: 2, fields: 1, methods: 17, attributes: 4
Constant pool:
    #1 = Utf8               coursier/core/shaded/fastparse/internal/Logger
    #2 = Class              #1            // coursier/core/shaded/fastparse/internal/Logger
    #3 = Utf8               java/lang/Object
    #4 = Class              #3            // java/lang/Object
    #5 = Utf8               scala/Product
    #6 = Class              #5            // scala/Product
    #7 = Utf8               java/io/Serializable
    #8 = Class              #7            // java/io/Serializable
    #9 = Utf8               Util.scala
   #10 = Utf8               Lscala/reflect/ScalaSignature;
   #11 = Utf8               bytes
   #12 = Utf8               \u0006\u0005\u0005\u0005c\u0001B\f\u0019\u0001vA\u0001b\r\u0001\u0003\u0016\u0004%\t\u0001\u000e\u0005\t\u0007\u0002\u0011\t\u0012)A\u0005k!)A\t\u0001C\u0001\u000b\"9\u0011\nAA\u0001\n\u0003Q\u0005b\u0002\'\u0001#\u0003%\t!\u0014\u0005\b1\u0002\t\t\u0011\"\u0011Z\u0011\u001d\t\u0007!!A\u0005\u0002\tDqA\u001a\u0001\u0002\u0002\u0013\u0005q\rC\u0004n\u0001\u0005\u0005I\u0011\t8\t\u000fU\u0004\u0011\u0011!C\u0001m\"91\u0010AA\u0001\n\u0003b\bb\u0002@\u0001\u0003\u0003%\te \u0005\n\u0003\u0003\u0001\u0011\u0011!C!\u0003\u0007A\u0011\"!\u0002\u0001\u0003\u0003%\t%a\u0002\b\u000f\u0005-\u0001\u0004#\u0001\u0002\u000e\u00191q\u0003\u0007E\u0001\u0003\u001fAa\u0001\u0012\t\u0005\u0002\u0005m\u0001\"CA\u000f!\t\u0007I1AA\u0010\u0011\u001d\t\t\u0003\u0005Q\u0001\n\u0019C\u0011\"a\t\u0011\u0003\u0003%\t)!\n\t\u0013\u0005%\u0002#!A\u0005\u0002\u0006-\u0002\"CA\u001c!\u0005\u0005I\u0011BA\u001d\u0005\u0019aunZ4fe*\u0011\u0011DG\u0001\tS:$XM\u001d8bY*\t1$A\u0005gCN$\b/\u0019:tK\u000e\u00011\u0003\u0002\u0001\u001fI\u001d\u0002\"a\b\u0012\u000e\u0003\u0001R\u0011!I\u0001\u0006g\u000e\fG.Y\u0005\u0003G\u0001\u0012a!\u00118z%\u00164\u0007CA\u0010&\u0013\t1\u0003EA\u0004Qe>$Wo\u0019;\u0011\u0005!\u0002dBA\u0015/\u001d\tQS&D\u0001,\u0015\taC$\u0001\u0004=e>|GOP\u0005\u0002C%\u0011q\u0006I\u0001\ba\u0006\u001c7.Y4f\u0013\t\t$G\u0001\u0007TKJL\u0017\r\\5{C\ndWM\u0003\u00020A\u0005\ta-F\u00016!\u0011yb\u0007\u000f!\n\u0005]\u0002#!\u0003$v]\u000e$\u0018n\u001c82!\tITH\u0004\u0002;wA\u0011!\u0006I\u0005\u0003y\u0001\na\u0001\u0015:fI\u00164\u0017B\u0001 @\u0005\u0019\u0019FO]5oO*\u0011A\b\t\t\u0003?\u0005K!A\u0011\u0011\u0003\tUs\u0017\u000e^\u0001\u0003M\u0002\na\u0001P5oSRtDC\u0001$I!\t9\u0005!D\u0001\u0019\u0011\u0015\u00194\u00011\u00016\u0003\u0011\u0019w\u000e]=\u0015\u0005\u0019[\u0005bB\u001a\u0005!\u0003\u0005\r!N\u0001\u000fG>\u0004\u0018\u0010\n3fM\u0006,H\u000e\u001e\u00132+\u0005q%FA\u001bPW\u0005\u0001\u0006CA)W\u001b\u0005\u0011&BA*U\u0003%)hn\u00195fG.,GM\u0003\u0002VA\u0005Q\u0011M\u001c8pi\u0006$\u0018n\u001c8\n\u0005]\u0013&!E;oG\",7m[3e-\u0006\u0014\u0018.\u00198dK\u0006i\u0001O]8ek\u000e$\bK]3gSb,\u0012A\u0017\t\u00037\u0002l\u0011\u0001\u0018\u0006\u0003;z\u000bA\u0001\\1oO*\tq,\u0001\u0003kCZ\f\u0017B\u0001 ]\u00031\u0001(o\u001c3vGR\f%/\u001b;z+\u0005\u0019\u0007CA\u0010e\u0013\t)\u0007EA\u0002J]R\fa\u0002\u001d:pIV\u001cG/\u00127f[\u0016tG\u000f\u0006\u0002iWB\u0011q$[\u0005\u0003U\u0002\u00121!\u00118z\u0011\u001da\u0007\"!AA\u0002\r\f1\u0001\u001f\u00132\u0003=\u0001(o\u001c3vGRLE/\u001a:bi>\u0014X#A8\u0011\u0007A\u001c\b.D\u0001r\u0015\t\u0011\b%\u0001\u0006d_2dWm\u0019;j_:L!\u0001^9\u0003\u0011%#XM]1u_J\f\u0001bY1o\u000bF,\u0018\r\u001c\u000b\u0003oj\u0004\"a\b=\n\u0005e\u0004#a\u0002\"p_2,\u0017M\u001c\u0005\bY*\t\t\u00111\u0001i\u0003I\u0001(o\u001c3vGR,E.Z7f]Rt\u0015-\\3\u0015\u0005ik\bb\u00027\f\u0003\u0003\u0005\raY\u0001\tQ\u0006\u001c\bnQ8eKR\t1-\u0001\u0005u_N#(/\u001b8h)\u0005Q\u0016AB3rk\u0006d7\u000fF\u0002x\u0003\u0013Aq\u0001\u001c\b\u0002\u0002\u0003\u0007\u0001.\u0001\u0004M_\u001e<WM\u001d\t\u0003\u000fB\u0019B\u0001\u0005\u0010\u0002\u0012A!\u00111CA\r\u001b\t\t)BC\u0002\u0002\u0018y\u000b!![8\n\u0007E\n)\u0002\u0006\u0002\u0002\u000e\u000511\u000f\u001e3pkR,\u0012AR\u0001\bgR$w.\u001e;!\u0003\u0015\t\u0007\u000f\u001d7z)\r1\u0015q\u0005\u0005\u0006gQ\u0001\r!N\u0001\bk:\f\u0007\u000f\u001d7z)\u0011\ti#a\r\u0011\t}\ty#N\u0005\u0004\u0003c\u0001#AB(qi&|g\u000e\u0003\u0005\u00026U\t\t\u00111\u0001G\u0003\rAH\u0005M\u0001\roJLG/\u001a*fa2\f7-\u001a\u000b\u0003\u0003w\u00012aWA\u001f\u0013\r\ty\u0004\u0018\u0002\u0007\u001f\nTWm\u0019;
   #13 = Utf8               f
   #14 = Utf8               Lscala/Function1;
   #15 = Utf8               Lscala/Function1<Ljava/lang/String;Lscala/runtime/BoxedUnit;>;
   #16 = Utf8               unapply
   #17 = Utf8               (Lcoursier/core/shaded/fastparse/internal/Logger;)Lscala/Option;
   #18 = Utf8               (Lcoursier/core/shaded/fastparse/internal/Logger;)Lscala/Option<Lscala/Function1<Ljava/lang/String;Lscala/runtime/BoxedUnit;>;>;
   #19 = Utf8               x$0
   #20 = Utf8               coursier/core/shaded/fastparse/internal/Logger$
   #21 = Class              #20           // coursier/core/shaded/fastparse/internal/Logger$
   #22 = Utf8               MODULE$
   #23 = Utf8               Lcoursier/core/shaded/fastparse/internal/Logger$;
   #24 = NameAndType        #22:#23       // MODULE$:Lcoursier/core/shaded/fastparse/internal/Logger$;
   #25 = Fieldref           #21.#24       // coursier/core/shaded/fastparse/internal/Logger$.MODULE$:Lcoursier/core/shaded/fastparse/internal/Logger$;
   #26 = NameAndType        #16:#17       // unapply:(Lcoursier/core/shaded/fastparse/internal/Logger;)Lscala/Option;
   #27 = Methodref          #21.#26       // coursier/core/shaded/fastparse/internal/Logger$.unapply:(Lcoursier/core/shaded/fastparse/internal/Logger;)Lscala/Option;
   #28 = Utf8               apply
   #29 = Utf8               (Lscala/Function1;)Lcoursier/core/shaded/fastparse/internal/Logger;
   #30 = Utf8               (Lscala/Function1<Ljava/lang/String;Lscala/runtime/BoxedUnit;>;)Lcoursier/core/shaded/fastparse/internal/Logger;
   #31 = NameAndType        #28:#29       // apply:(Lscala/Function1;)Lcoursier/core/shaded/fastparse/internal/Logger;
   #32 = Methodref          #21.#31       // coursier/core/shaded/fastparse/internal/Logger$.apply:(Lscala/Function1;)Lcoursier/core/shaded/fastparse/internal/Logger;
   #33 = Utf8               stdout
   #34 = Utf8               ()Lcoursier/core/shaded/fastparse/internal/Logger;
   #35 = NameAndType        #33:#34       // stdout:()Lcoursier/core/shaded/fastparse/internal/Logger;
   #36 = Methodref          #21.#35       // coursier/core/shaded/fastparse/internal/Logger$.stdout:()Lcoursier/core/shaded/fastparse/internal/Logger;
   #37 = Utf8               productElementNames
   #38 = Utf8               ()Lscala/collection/Iterator;
   #39 = Utf8               ()Lscala/collection/Iterator<Ljava/lang/String;>;
   #40 = Utf8               productElementNames$
   #41 = Utf8               (Lscala/Product;)Lscala/collection/Iterator;
   #42 = NameAndType        #40:#41       // productElementNames$:(Lscala/Product;)Lscala/collection/Iterator;
   #43 = InterfaceMethodref #6.#42        // scala/Product.productElementNames$:(Lscala/Product;)Lscala/collection/Iterator;
   #44 = Utf8               this
   #45 = Utf8               Lcoursier/core/shaded/fastparse/internal/Logger;
   #46 = Utf8               ()Lscala/Function1;
   #47 = Utf8               ()Lscala/Function1<Ljava/lang/String;Lscala/runtime/BoxedUnit;>;
   #48 = NameAndType        #13:#14       // f:Lscala/Function1;
   #49 = Fieldref           #2.#48        // coursier/core/shaded/fastparse/internal/Logger.f:Lscala/Function1;
   #50 = Utf8               copy
   #51 = Utf8               <init>
   #52 = Utf8               (Lscala/Function1;)V
   #53 = NameAndType        #51:#52       // "<init>":(Lscala/Function1;)V
   #54 = Methodref          #2.#53        // coursier/core/shaded/fastparse/internal/Logger."<init>":(Lscala/Function1;)V
   #55 = Utf8               copy$default$1
   #56 = NameAndType        #13:#46       // f:()Lscala/Function1;
   #57 = Methodref          #2.#56        // coursier/core/shaded/fastparse/internal/Logger.f:()Lscala/Function1;
   #58 = Utf8               productPrefix
   #59 = Utf8               ()Ljava/lang/String;
   #60 = Utf8               Logger
   #61 = String             #60           // Logger
   #62 = Utf8               productArity
   #63 = Utf8               ()I
   #64 = Utf8               productElement
   #65 = Utf8               (I)Ljava/lang/Object;
   #66 = Utf8               x$1
   #67 = Utf8               scala/runtime/Statics
   #68 = Class              #67           // scala/runtime/Statics
   #69 = Utf8               ioobe
   #70 = NameAndType        #69:#65       // ioobe:(I)Ljava/lang/Object;
   #71 = Methodref          #68.#70       // scala/runtime/Statics.ioobe:(I)Ljava/lang/Object;
   #72 = Utf8               I
   #73 = Utf8               productIterator
   #74 = Utf8               ()Lscala/collection/Iterator<Ljava/lang/Object;>;
   #75 = Utf8               scala/runtime/ScalaRunTime$
   #76 = Class              #75           // scala/runtime/ScalaRunTime$
   #77 = Utf8               Lscala/runtime/ScalaRunTime$;
   #78 = NameAndType        #22:#77       // MODULE$:Lscala/runtime/ScalaRunTime$;
   #79 = Fieldref           #76.#78       // scala/runtime/ScalaRunTime$.MODULE$:Lscala/runtime/ScalaRunTime$;
   #80 = Utf8               typedProductIterator
   #81 = NameAndType        #80:#41       // typedProductIterator:(Lscala/Product;)Lscala/collection/Iterator;
   #82 = Methodref          #76.#81       // scala/runtime/ScalaRunTime$.typedProductIterator:(Lscala/Product;)Lscala/collection/Iterator;
   #83 = Utf8               canEqual
   #84 = Utf8               (Ljava/lang/Object;)Z
   #85 = Utf8               Ljava/lang/Object;
   #86 = Utf8               productElementName
   #87 = Utf8               (I)Ljava/lang/String;
   #88 = String             #13           // f
   #89 = Utf8               java/lang/String
   #90 = Class              #89           // java/lang/String
   #91 = Utf8               hashCode
   #92 = Utf8               _hashCode
   #93 = Utf8               (Lscala/Product;)I
   #94 = NameAndType        #92:#93       // _hashCode:(Lscala/Product;)I
   #95 = Methodref          #76.#94       // scala/runtime/ScalaRunTime$._hashCode:(Lscala/Product;)I
   #96 = Utf8               toString
   #97 = Utf8               _toString
   #98 = Utf8               (Lscala/Product;)Ljava/lang/String;
   #99 = NameAndType        #97:#98       // _toString:(Lscala/Product;)Ljava/lang/String;
  #100 = Methodref          #76.#99       // scala/runtime/ScalaRunTime$._toString:(Lscala/Product;)Ljava/lang/String;
  #101 = Utf8               equals
  #102 = Utf8               scala/Function1
  #103 = Class              #102          // scala/Function1
  #104 = NameAndType        #101:#84      // equals:(Ljava/lang/Object;)Z
  #105 = Methodref          #4.#104       // java/lang/Object.equals:(Ljava/lang/Object;)Z
  #106 = NameAndType        #83:#84       // canEqual:(Ljava/lang/Object;)Z
  #107 = Methodref          #2.#106       // coursier/core/shaded/fastparse/internal/Logger.canEqual:(Ljava/lang/Object;)Z
  #108 = Utf8               (Lscala/Function1<Ljava/lang/String;Lscala/runtime/BoxedUnit;>;)V
  #109 = Utf8               ()V
  #110 = NameAndType        #51:#109      // "<init>":()V
  #111 = Methodref          #4.#110       // java/lang/Object."<init>":()V
  #112 = Utf8               $init$
  #113 = Utf8               (Lscala/Product;)V
  #114 = NameAndType        #112:#113     // $init$:(Lscala/Product;)V
  #115 = InterfaceMethodref #6.#114       // scala/Product.$init$:(Lscala/Product;)V
  #116 = Utf8               Signature
  #117 = Utf8               Code
  #118 = Utf8               MethodParameters
  #119 = Utf8               LineNumberTable
  #120 = Utf8               LocalVariableTable
  #121 = Utf8               StackMapTable
  #122 = Utf8               SourceFile
  #123 = Utf8               RuntimeVisibleAnnotations
  #124 = Utf8               ScalaInlineInfo
  #125 = Utf8               ScalaSig
{
  private final scala.Function1<java.lang.String, scala.runtime.BoxedUnit> f;
    descriptor: Lscala/Function1;
    flags: (0x0012) ACC_PRIVATE, ACC_FINAL
    Signature: #15                          // Lscala/Function1<Ljava/lang/String;Lscala/runtime/BoxedUnit;>;

  public static scala.Option<scala.Function1<java.lang.String, scala.runtime.BoxedUnit>> unapply(coursier.core.shaded.fastparse.internal.Logger);
    descriptor: (Lcoursier/core/shaded/fastparse/internal/Logger;)Lscala/Option;
    flags: (0x0009) ACC_PUBLIC, ACC_STATIC
    Code:
      stack=2, locals=1, args_size=1
         0: getstatic     #25                 // Field coursier/core/shaded/fastparse/internal/Logger$.MODULE$:Lcoursier/core/shaded/fastparse/internal/Logger$;
         3: aload_0
         4: invokevirtual #27                 // Method coursier/core/shaded/fastparse/internal/Logger$.unapply:(Lcoursier/core/shaded/fastparse/internal/Logger;)Lscala/Option;
         7: areturn
    Signature: #18                          // (Lcoursier/core/shaded/fastparse/internal/Logger;)Lscala/Option<Lscala/Function1<Ljava/lang/String;Lscala/runtime/BoxedUnit;>;>;
    MethodParameters:
      Name                           Flags
      x$0                            final

  public static coursier.core.shaded.fastparse.internal.Logger apply(scala.Function1<java.lang.String, scala.runtime.BoxedUnit>);
    descriptor: (Lscala/Function1;)Lcoursier/core/shaded/fastparse/internal/Logger;
    flags: (0x0009) ACC_PUBLIC, ACC_STATIC
    Code:
      stack=2, locals=1, args_size=1
         0: getstatic     #25                 // Field coursier/core/shaded/fastparse/internal/Logger$.MODULE$:Lcoursier/core/shaded/fastparse/internal/Logger$;
         3: aload_0
         4: invokevirtual #32                 // Method coursier/core/shaded/fastparse/internal/Logger$.apply:(Lscala/Function1;)Lcoursier/core/shaded/fastparse/internal/Logger;
         7: areturn
    Signature: #30                          // (Lscala/Function1<Ljava/lang/String;Lscala/runtime/BoxedUnit;>;)Lcoursier/core/shaded/fastparse/internal/Logger;
    MethodParameters:
      Name                           Flags
      f                              final

  public static coursier.core.shaded.fastparse.internal.Logger stdout();
    descriptor: ()Lcoursier/core/shaded/fastparse/internal/Logger;
    flags: (0x0009) ACC_PUBLIC, ACC_STATIC
    Code:
      stack=1, locals=0, args_size=0
         0: getstatic     #25                 // Field coursier/core/shaded/fastparse/internal/Logger$.MODULE$:Lcoursier/core/shaded/fastparse/internal/Logger$;
         3: invokevirtual #36                 // Method coursier/core/shaded/fastparse/internal/Logger$.stdout:()Lcoursier/core/shaded/fastparse/internal/Logger;
         6: areturn

  public scala.collection.Iterator<java.lang.String> productElementNames();
    descriptor: ()Lscala/collection/Iterator;
    flags: (0x0001) ACC_PUBLIC
    Code:
      stack=1, locals=1, args_size=1
         0: aload_0
         1: invokestatic  #43                 // InterfaceMethod scala/Product.productElementNames$:(Lscala/Product;)Lscala/collection/Iterator;
         4: areturn
      LineNumberTable:
        line 108: 0
      LocalVariableTable:
        Start  Length  Slot  Name   Signature
            0       5     0  this   Lcoursier/core/shaded/fastparse/internal/Logger;
    Signature: #39                          // ()Lscala/collection/Iterator<Ljava/lang/String;>;

  public scala.Function1<java.lang.String, scala.runtime.BoxedUnit> f();
    descriptor: ()Lscala/Function1;
    flags: (0x0001) ACC_PUBLIC
    Code:
      stack=1, locals=1, args_size=1
         0: aload_0
         1: getfield      #49                 // Field f:Lscala/Function1;
         4: areturn
      LineNumberTable:
        line 108: 0
      LocalVariableTable:
        Start  Length  Slot  Name   Signature
            0       5     0  this   Lcoursier/core/shaded/fastparse/internal/Logger;
    Signature: #47                          // ()Lscala/Function1<Ljava/lang/String;Lscala/runtime/BoxedUnit;>;

  public coursier.core.shaded.fastparse.internal.Logger copy(scala.Function1<java.lang.String, scala.runtime.BoxedUnit>);
    descriptor: (Lscala/Function1;)Lcoursier/core/shaded/fastparse/internal/Logger;
    flags: (0x0001) ACC_PUBLIC
    Code:
      stack=3, locals=2, args_size=2
         0: new           #2                  // class coursier/core/shaded/fastparse/internal/Logger
         3: dup
         4: aload_1
         5: invokespecial #54                 // Method "<init>":(Lscala/Function1;)V
         8: areturn
      LineNumberTable:
        line 108: 0
      LocalVariableTable:
        Start  Length  Slot  Name   Signature
            0       9     0  this   Lcoursier/core/shaded/fastparse/internal/Logger;
            0       9     1     f   Lscala/Function1;
    Signature: #30                          // (Lscala/Function1<Ljava/lang/String;Lscala/runtime/BoxedUnit;>;)Lcoursier/core/shaded/fastparse/internal/Logger;
    MethodParameters:
      Name                           Flags
      f                              final

  public scala.Function1<java.lang.String, scala.runtime.BoxedUnit> copy$default$1();
    descriptor: ()Lscala/Function1;
    flags: (0x0001) ACC_PUBLIC
    Code:
      stack=1, locals=1, args_size=1
         0: aload_0
         1: invokevirtual #57                 // Method f:()Lscala/Function1;
         4: areturn
      LineNumberTable:
        line 108: 0
      LocalVariableTable:
        Start  Length  Slot  Name   Signature
            0       5     0  this   Lcoursier/core/shaded/fastparse/internal/Logger;
    Signature: #47                          // ()Lscala/Function1<Ljava/lang/String;Lscala/runtime/BoxedUnit;>;

  public java.lang.String productPrefix();
    descriptor: ()Ljava/lang/String;
    flags: (0x0001) ACC_PUBLIC
    Code:
      stack=1, locals=1, args_size=1
         0: ldc           #61                 // String Logger
         2: areturn
      LineNumberTable:
        line 108: 0
      LocalVariableTable:
        Start  Length  Slot  Name   Signature
            0       3     0  this   Lcoursier/core/shaded/fastparse/internal/Logger;

  public int productArity();
    descriptor: ()I
    flags: (0x0001) ACC_PUBLIC
    Code:
      stack=1, locals=1, args_size=1
         0: iconst_1
         1: ireturn
      LineNumberTable:
        line 108: 0
      LocalVariableTable:
        Start  Length  Slot  Name   Signature
            0       2     0  this   Lcoursier/core/shaded/fastparse/internal/Logger;

  public java.lang.Object productElement(int);
    descriptor: (I)Ljava/lang/Object;
    flags: (0x0001) ACC_PUBLIC
    Code:
      stack=1, locals=3, args_size=2
         0: iload_1
         1: istore_2
         2: iload_2
         3: tableswitch   { // 0 to 0
                       0: 20
                 default: 27
            }
        20: aload_0
        21: invokevirtual #57                 // Method f:()Lscala/Function1;
        24: goto          34
        27: iload_1
        28: invokestatic  #71                 // Method scala/runtime/Statics.ioobe:(I)Ljava/lang/Object;
        31: goto          34
        34: areturn
      StackMapTable: number_of_entries = 3
        frame_type = 252 /* append */
          offset_delta = 20
          locals = [ int ]
        frame_type = 6 /* same */
        frame_type = 70 /* same_locals_1_stack_item */
          stack = [ class java/lang/Object ]
      LineNumberTable:
        line 108: 0
      LocalVariableTable:
        Start  Length  Slot  Name   Signature
            0      35     0  this   Lcoursier/core/shaded/fastparse/internal/Logger;
            0      35     1   x$1   I
    MethodParameters:
      Name                           Flags
      x$1                            final

  public scala.collection.Iterator<java.lang.Object> productIterator();
    descriptor: ()Lscala/collection/Iterator;
    flags: (0x0001) ACC_PUBLIC
    Code:
      stack=2, locals=1, args_size=1
         0: getstatic     #79                 // Field scala/runtime/ScalaRunTime$.MODULE$:Lscala/runtime/ScalaRunTime$;
         3: aload_0
         4: invokevirtual #82                 // Method scala/runtime/ScalaRunTime$.typedProductIterator:(Lscala/Product;)Lscala/collection/Iterator;
         7: areturn
      LineNumberTable:
        line 108: 0
      LocalVariableTable:
        Start  Length  Slot  Name   Signature
            0       8     0  this   Lcoursier/core/shaded/fastparse/internal/Logger;
    Signature: #74                          // ()Lscala/collection/Iterator<Ljava/lang/Object;>;

  public boolean canEqual(java.lang.Object);
    descriptor: (Ljava/lang/Object;)Z
    flags: (0x0001) ACC_PUBLIC
    Code:
      stack=1, locals=2, args_size=2
         0: aload_1
         1: instanceof    #2                  // class coursier/core/shaded/fastparse/internal/Logger
         4: ireturn
      LineNumberTable:
        line 108: 0
      LocalVariableTable:
        Start  Length  Slot  Name   Signature
            0       5     0  this   Lcoursier/core/shaded/fastparse/internal/Logger;
            0       5     1   x$1   Ljava/lang/Object;
    MethodParameters:
      Name                           Flags
      x$1                            final

  public java.lang.String productElementName(int);
    descriptor: (I)Ljava/lang/String;
    flags: (0x0001) ACC_PUBLIC
    Code:
      stack=1, locals=3, args_size=2
         0: iload_1
         1: istore_2
         2: iload_2
         3: tableswitch   { // 0 to 0
                       0: 20
                 default: 25
            }
        20: ldc           #88                 // String f
        22: goto          35
        25: iload_1
        26: invokestatic  #71                 // Method scala/runtime/Statics.ioobe:(I)Ljava/lang/Object;
        29: checkcast     #90                 // class java/lang/String
        32: goto          35
        35: areturn
      StackMapTable: number_of_entries = 3
        frame_type = 252 /* append */
          offset_delta = 20
          locals = [ int ]
        frame_type = 4 /* same */
        frame_type = 73 /* same_locals_1_stack_item */
          stack = [ class java/lang/String ]
      LineNumberTable:
        line 108: 0
      LocalVariableTable:
        Start  Length  Slot  Name   Signature
            0      36     0  this   Lcoursier/core/shaded/fastparse/internal/Logger;
            0      36     1   x$1   I
    MethodParameters:
      Name                           Flags
      x$1                            final

  public int hashCode();
    descriptor: ()I
    flags: (0x0001) ACC_PUBLIC
    Code:
      stack=2, locals=1, args_size=1
         0: getstatic     #79                 // Field scala/runtime/ScalaRunTime$.MODULE$:Lscala/runtime/ScalaRunTime$;
         3: aload_0
         4: invokevirtual #95                 // Method scala/runtime/ScalaRunTime$._hashCode:(Lscala/Product;)I
         7: ireturn
      LineNumberTable:
        line 108: 0
      LocalVariableTable:
        Start  Length  Slot  Name   Signature
            0       8     0  this   Lcoursier/core/shaded/fastparse/internal/Logger;

  public java.lang.String toString();
    descriptor: ()Ljava/lang/String;
    flags: (0x0001) ACC_PUBLIC
    Code:
      stack=2, locals=1, args_size=1
         0: getstatic     #79                 // Field scala/runtime/ScalaRunTime$.MODULE$:Lscala/runtime/ScalaRunTime$;
         3: aload_0
         4: invokevirtual #100                // Method scala/runtime/ScalaRunTime$._toString:(Lscala/Product;)Ljava/lang/String;
         7: areturn
      LineNumberTable:
        line 108: 0
      LocalVariableTable:
        Start  Length  Slot  Name   Signature
            0       8     0  this   Lcoursier/core/shaded/fastparse/internal/Logger;

  public boolean equals(java.lang.Object);
    descriptor: (Ljava/lang/Object;)Z
    flags: (0x0001) ACC_PUBLIC
    Code:
      stack=2, locals=6, args_size=2
         0: aload_0
         1: aload_1
         2: if_acmpeq     86
         5: aload_1
         6: astore_3
         7: aload_3
         8: instanceof    #2                  // class coursier/core/shaded/fastparse/internal/Logger
        11: ifeq          19
        14: iconst_1
        15: istore_2
        16: goto          27
        19: goto          22
        22: iconst_0
        23: istore_2
        24: goto          27
        27: iload_2
        28: ifeq          90
        31: aload_1
        32: checkcast     #2                  // class coursier/core/shaded/fastparse/internal/Logger
        35: astore        4
        37: aload_0
        38: invokevirtual #57                 // Method f:()Lscala/Function1;
        41: aload         4
        43: invokevirtual #57                 // Method f:()Lscala/Function1;
        46: astore        5
        48: dup
        49: ifnonnull     61
        52: pop
        53: aload         5
        55: ifnull        69
        58: goto          82
        61: aload         5
        63: invokevirtual #105                // Method java/lang/Object.equals:(Ljava/lang/Object;)Z
        66: ifeq          82
        69: aload         4
        71: aload_0
        72: invokevirtual #107                // Method canEqual:(Ljava/lang/Object;)Z
        75: ifeq          82
        78: iconst_1
        79: goto          83
        82: iconst_0
        83: ifeq          90
        86: iconst_1
        87: goto          91
        90: iconst_0
        91: ireturn
      StackMapTable: number_of_entries = 10
        frame_type = 253 /* append */
          offset_delta = 19
          locals = [ top, class java/lang/Object ]
        frame_type = 2 /* same */
        frame_type = 255 /* full_frame */
          offset_delta = 4
          locals = [ class coursier/core/shaded/fastparse/internal/Logger, class java/lang/Object, int, class java/lang/Object ]
          stack = []
        frame_type = 255 /* full_frame */
          offset_delta = 33
          locals = [ class coursier/core/shaded/fastparse/internal/Logger, class java/lang/Object, int, class java/lang/Object, class coursier/core/shaded/fastparse/internal/Logger, class scala/Function1 ]
          stack = [ class scala/Function1 ]
        frame_type = 7 /* same */
        frame_type = 12 /* same */
        frame_type = 64 /* same_locals_1_stack_item */
          stack = [ int ]
        frame_type = 255 /* full_frame */
          offset_delta = 2
          locals = [ class coursier/core/shaded/fastparse/internal/Logger, class java/lang/Object ]
          stack = []
        frame_type = 253 /* append */
          offset_delta = 3
          locals = [ int, class java/lang/Object ]
        frame_type = 255 /* full_frame */
          offset_delta = 0
          locals = [ class coursier/core/shaded/fastparse/internal/Logger, class java/lang/Object ]
          stack = [ int ]
      LineNumberTable:
        line 108: 0
      LocalVariableTable:
        Start  Length  Slot  Name   Signature
            0      92     0  this   Lcoursier/core/shaded/fastparse/internal/Logger;
            0      92     1   x$1   Ljava/lang/Object;
    MethodParameters:
      Name                           Flags
      x$1                            final

  public coursier.core.shaded.fastparse.internal.Logger(scala.Function1<java.lang.String, scala.runtime.BoxedUnit>);
    descriptor: (Lscala/Function1;)V
    flags: (0x0001) ACC_PUBLIC
    Code:
      stack=2, locals=2, args_size=2
         0: aload_0
         1: aload_1
         2: putfield      #49                 // Field f:Lscala/Function1;
         5: aload_0
         6: invokespecial #111                // Method java/lang/Object."<init>":()V
         9: aload_0
        10: invokestatic  #115                // InterfaceMethod scala/Product.$init$:(Lscala/Product;)V
        13: return
      LineNumberTable:
        line 108: 0
      LocalVariableTable:
        Start  Length  Slot  Name   Signature
            0      14     0  this   Lcoursier/core/shaded/fastparse/internal/Logger;
            0      14     1     f   Lscala/Function1;
    Signature: #108                         // (Lscala/Function1<Ljava/lang/String;Lscala/runtime/BoxedUnit;>;)V
    MethodParameters:
      Name                           Flags
      f                              final
}
SourceFile: "Util.scala"
RuntimeVisibleAnnotations:
  0: #10(#11=s#12)
    scala.reflect.ScalaSignature(
      bytes="\u0006\u0005\u0005\u0005c\u0001B\f\u0019\u0001vA\u0001b\r\u0001\u0003\u0016\u0004%\t\u0001\u000e\u0005\t\u0007\u0002\u0011\t\u0012)A\u0005k!)A\t\u0001C\u0001\u000b\"9\u0011\nAA\u0001\n\u0003Q\u0005b\u0002\'\u0001#\u0003%\t!\u0014\u0005\b1\u0002\t\t\u0011\"\u0011Z\u0011\u001d\t\u0007!!A\u0005\u0002\tDqA\u001a\u0001\u0002\u0002\u0013\u0005q\rC\u0004n\u0001\u0005\u0005I\u0011\t8\t\u000fU\u0004\u0011\u0011!C\u0001m\"91\u0010AA\u0001\n\u0003b\bb\u0002@\u0001\u0003\u0003%\te \u0005\n\u0003\u0003\u0001\u0011\u0011!C!\u0003\u0007A\u0011\"!\u0002\u0001\u0003\u0003%\t%a\u0002\b\u000f\u0005-\u0001\u0004#\u0001\u0002\u000e\u00191q\u0003\u0007E\u0001\u0003\u001fAa\u0001\u0012\t\u0005\u0002\u0005m\u0001\"CA\u000f!\t\u0007I1AA\u0010\u0011\u001d\t\t\u0003\u0005Q\u0001\n\u0019C\u0011\"a\t\u0011\u0003\u0003%\t)!\n\t\u0013\u0005%\u0002#!A\u0005\u0002\u0006-\u0002\"CA\u001c!\u0005\u0005I\u0011BA\u001d\u0005\u0019aunZ4fe*\u0011\u0011DG\u0001\tS:$XM\u001d8bY*\t1$A\u0005gCN$\b/\u0019:tK\u000e\u00011\u0003\u0002\u0001\u001fI\u001d\u0002\"a\b\u0012\u000e\u0003\u0001R\u0011!I\u0001\u0006g\u000e\fG.Y\u0005\u0003G\u0001\u0012a!\u00118z%\u00164\u0007CA\u0010&\u0013\t1\u0003EA\u0004Qe>$Wo\u0019;\u0011\u0005!\u0002dBA\u0015/\u001d\tQS&D\u0001,\u0015\taC$\u0001\u0004=e>|GOP\u0005\u0002C%\u0011q\u0006I\u0001\ba\u0006\u001c7.Y4f\u0013\t\t$G\u0001\u0007TKJL\u0017\r\\5{C\ndWM\u0003\u00020A\u0005\ta-F\u00016!\u0011yb\u0007\u000f!\n\u0005]\u0002#!\u0003$v]\u000e$\u0018n\u001c82!\tITH\u0004\u0002;wA\u0011!\u0006I\u0005\u0003y\u0001\na\u0001\u0015:fI\u00164\u0017B\u0001 @\u0005\u0019\u0019FO]5oO*\u0011A\b\t\t\u0003?\u0005K!A\u0011\u0011\u0003\tUs\u0017\u000e^\u0001\u0003M\u0002\na\u0001P5oSRtDC\u0001$I!\t9\u0005!D\u0001\u0019\u0011\u0015\u00194\u00011\u00016\u0003\u0011\u0019w\u000e]=\u0015\u0005\u0019[\u0005bB\u001a\u0005!\u0003\u0005\r!N\u0001\u000fG>\u0004\u0018\u0010\n3fM\u0006,H\u000e\u001e\u00132+\u0005q%FA\u001bPW\u0005\u0001\u0006CA)W\u001b\u0005\u0011&BA*U\u0003%)hn\u00195fG.,GM\u0003\u0002VA\u0005Q\u0011M\u001c8pi\u0006$\u0018n\u001c8\n\u0005]\u0013&!E;oG\",7m[3e-\u0006\u0014\u0018.\u00198dK\u0006i\u0001O]8ek\u000e$\bK]3gSb,\u0012A\u0017\t\u00037\u0002l\u0011\u0001\u0018\u0006\u0003;z\u000bA\u0001\\1oO*\tq,\u0001\u0003kCZ\f\u0017B\u0001 ]\u00031\u0001(o\u001c3vGR\f%/\u001b;z+\u0005\u0019\u0007CA\u0010e\u0013\t)\u0007EA\u0002J]R\fa\u0002\u001d:pIV\u001cG/\u00127f[\u0016tG\u000f\u0006\u0002iWB\u0011q$[\u0005\u0003U\u0002\u00121!\u00118z\u0011\u001da\u0007\"!AA\u0002\r\f1\u0001\u001f\u00132\u0003=\u0001(o\u001c3vGRLE/\u001a:bi>\u0014X#A8\u0011\u0007A\u001c\b.D\u0001r\u0015\t\u0011\b%\u0001\u0006d_2dWm\u0019;j_:L!\u0001^9\u0003\u0011%#XM]1u_J\f\u0001bY1o\u000bF,\u0018\r\u001c\u000b\u0003oj\u0004\"a\b=\n\u0005e\u0004#a\u0002\"p_2,\u0017M\u001c\u0005\bY*\t\t\u00111\u0001i\u0003I\u0001(o\u001c3vGR,E.Z7f]Rt\u0015-\\3\u0015\u0005ik\bb\u00027\f\u0003\u0003\u0005\raY\u0001\tQ\u0006\u001c\bnQ8eKR\t1-\u0001\u0005u_N#(/\u001b8h)\u0005Q\u0016AB3rk\u0006d7\u000fF\u0002x\u0003\u0013Aq\u0001\u001c\b\u0002\u0002\u0003\u0007\u0001.\u0001\u0004M_\u001e<WM\u001d\t\u0003\u000fB\u0019B\u0001\u0005\u0010\u0002\u0012A!\u00111CA\r\u001b\t\t)BC\u0002\u0002\u0018y\u000b!![8\n\u0007E\n)\u0002\u0006\u0002\u0002\u000e\u000511\u000f\u001e3pkR,\u0012AR\u0001\bgR$w.\u001e;!\u0003\u0015\t\u0007\u000f\u001d7z)\r1\u0015q\u0005\u0005\u0006gQ\u0001\r!N\u0001\bk:\f\u0007\u000f\u001d7z)\u0011\ti#a\r\u0011\t}\ty#N\u0005\u0004\u0003c\u0001#AB(qi&|g\u000e\u0003\u0005\u00026U\t\t\u00111\u0001G\u0003\rAH\u0005M\u0001\roJLG/\u001a*fa2\f7-\u001a\u000b\u0003\u0003w\u00012aWA\u001f\u0013\r\ty\u0004\u0018\u0002\u0007\u001f\nTWm\u0019;"
    )
  ScalaInlineInfo: length = 0x4A (unknown attribute)
   01 00 00 0E 00 33 00 34 00 00 53 00 54 00 00 32
   00 1D 00 00 37 00 2E 00 00 65 00 54 00 00 0D 00
   2E 00 00 5B 00 3F 00 00 3E 00 3F 00 00 40 00 41
   00 00 56 00 57 00 00 25 00 26 00 00 49 00 26 00
   00 3A 00 3B 00 00 60 00 3B 00
  ScalaSig: length = 0x3 (unknown attribute)
   05 02 00
