Classfile /Users/mw/Projects/slang-braindump/.jar/jar8/assemble/slang-braindump/assemble/content/coursier/core/shaded/fastparse/internal/Msgs.class
  Last modified May 29, 2022; size 6441 bytes
  SHA-256 checksum f39ecee5978f308bd6ef6dd341a6ceb9d3c3f22c1a24441900c47dde74daa6a4
  Compiled from "Util.scala"
public class coursier.core.shaded.fastparse.internal.Msgs implements scala.Product,java.io.Serializable
  minor version: 0
  major version: 52
  flags: (0x0021) ACC_PUBLIC, ACC_SUPER
  this_class: #2                          // coursier/core/shaded/fastparse/internal/Msgs
  super_class: #4                         // java/lang/Object
  interfaces: 2, fields: 1, methods: 20, attributes: 4
Constant pool:
    #1 = Utf8               coursier/core/shaded/fastparse/internal/Msgs
    #2 = Class              #1            // coursier/core/shaded/fastparse/internal/Msgs
    #3 = Utf8               java/lang/Object
    #4 = Class              #3            // java/lang/Object
    #5 = Utf8               scala/Product
    #6 = Class              #5            // scala/Product
    #7 = Utf8               java/io/Serializable
    #8 = Class              #7            // java/io/Serializable
    #9 = Utf8               Util.scala
   #10 = Utf8               Lscala/reflect/ScalaSignature;
   #11 = Utf8               bytes
   #12 = Utf8               \u0006\u0005\u0005es!\u0002\u000e\u001c\u0011\u0003\u0001c!\u0002\u0012\u001c\u0011\u0003\u0019\u0003\"\u0002\u001a\u0002\t\u0003\u0019\u0004b\u0002\u001b\u0002\u0005\u0004%\t!\u000e\u0005\b\u0003s\t\u0001\u0015!\u00037\u0011%\tY$AA\u0001\n\u0003\u000bi\u0004C\u0005\u0002B\u0005\t\t\u0011\"!\u0002D!I\u0011qJ\u0001\u0002\u0002\u0013%\u0011\u0011\u000b\u0004\u0005Em\u0001u\u0007\u0003\u0005G\u0011\tU\r\u0011\"\u0001H\u0011!1\u0006B!E!\u0002\u0013A\u0005\"\u0002\u001a\t\t\u00039\u0006\"B-\t\t\u0003Q\u0006\"B/\t\t\u0003q\u0006\"\u00021\t\t\u0003\n\u0007\"\u00022\t\t\u0003\u0019\u0007b\u00023\t\u0003\u0003%\t!\u001a\u0005\bO\"\t\n\u0011\"\u0001i\u0011\u001d\u0019\b\"!A\u0005BQDqA\u001f\u0005\u0002\u0002\u0013\u00051\u0010\u0003\u0005\u0000\u0011\u0005\u0005I\u0011AA\u0001\u0011%\ti\u0001CA\u0001\n\u0003\ny\u0001C\u0005\u0002\u001e!\t\t\u0011\"\u0001\u0002 !I\u0011\u0011\u0006\u0005\u0002\u0002\u0013\u0005\u00131\u0006\u0005\n\u0003_A\u0011\u0011!C!\u0003cA\u0011\"a\r\t\u0003\u0003%\t%!\u000e\u0002\t5\u001bxm\u001d\u0006\u00039u\t\u0001\"\u001b8uKJt\u0017\r\u001c\u0006\u0002=\u0005Ia-Y:ua\u0006\u00148/Z\u0002\u0001!\t\t\u0013!D\u0001\u001c\u0005\u0011i5oZ:\u0014\u0007\u0005!#\u0006\u0005\u0002&Q5\taEC\u0001(\u0003\u0015\u00198-\u00197b\u0013\tIcE\u0001\u0004B]f\u0014VM\u001a\t\u0003WAj\u0011\u0001\f\u0006\u0003[9\n!![8\u000b\u0003=\nAA[1wC&\u0011\u0011\u0007\f\u0002\r\'\u0016\u0014\u0018.\u00197ju\u0006\u0014G.Z\u0001\u0007y%t\u0017\u000e\u001e \u0015\u0003\u0001\nQ!Z7qif,\u0012A\u000e\t\u0003C!\u0019B\u0001\u0003\u00139wA\u0011Q%O\u0005\u0003u\u0019\u0012q\u0001\u0015:pIV\u001cG\u000f\u0005\u0002=\t:\u0011QH\u0011\b\u0003}\u0005k\u0011a\u0010\u0006\u0003\u0001~\ta\u0001\u0010:p_Rt\u0014\"A\u0014\n\u0005\r3\u0013a\u00029bG.\fw-Z\u0005\u0003c\u0015S!a\u0011\u0014\u0002\u000bY\fG.^3\u0016\u0003!\u00032\u0001P%L\u0013\tQUI\u0001\u0003MSN$\bcA\u0011M\u001d&\u0011Qj\u0007\u0002\u0005\u0019\u0006T\u0018\u0010\u0005\u0002P\':\u0011\u0001+\u0015\t\u0003}\u0019J!A\u0015\u0014\u0002\rA\u0013X\rZ3g\u0013\t!VK\u0001\u0004TiJLgn\u001a\u0006\u0003%\u001a\naA^1mk\u0016\u0004CC\u0001\u001cY\u0011\u001515\u00021\u0001I\u0003I!3m\u001c7p]\u0012\u001aw\u000e\\8oI\r|Gn\u001c8\u0015\u0005YZ\u0006\"\u0002/\r\u0001\u00041\u0014!B8uQ\u0016\u0014\u0018\u0001\u0004\u0013d_2|g\u000eJ2pY>tGC\u0001\u001c`\u0011\u0015aV\u00021\u0001L\u0003!!xn\u0015;sS:<G#\u0001(\u0002\rI,g\u000eZ3s+\u0005q\u0015\u0001B2paf$\"A\u000e4\t\u000f\u0019\u0003\u0002\u0013!a\u0001\u0011\u0006q1m\u001c9zI\u0011,g-Y;mi\u0012\nT#A5+\u0005!S7&A6\u0011\u00051\fX\"A7\u000b\u00059|\u0017!C;oG\",7m[3e\u0015\t\u0001h%\u0001\u0006b]:|G/\u0019;j_:L!A]7\u0003#Ut7\r[3dW\u0016$g+\u0019:jC:\u001cW-A\u0007qe>$Wo\u0019;Qe\u00164\u0017\u000e_\u000b\u0002kB\u0011a/_\u0007\u0002o*\u0011\u0001PL\u0001\u0005Y\u0006tw-\u0003\u0002Uo\u0006a\u0001O]8ek\u000e$\u0018I]5usV\tA\u0010\u0005\u0002&{&\u0011aP\n\u0002\u0004\u0013:$\u0018A\u00049s_\u0012,8\r^#mK6,g\u000e\u001e\u000b\u0005\u0003\u0007\tI\u0001E\u0002&\u0003\u000bI1!a\u0002\'\u0005\r\te.\u001f\u0005\t\u0003\u0017!\u0012\u0011!a\u0001y\u0006\u0019\u0001\u0010J\u0019\u0002\u001fA\u0014x\u000eZ;di&#XM]1u_J,\"!!\u0005\u0011\r\u0005M\u0011\u0011DA\u0002\u001b\t\t)BC\u0002\u0002\u0018\u0019\n!bY8mY\u0016\u001cG/[8o\u0013\u0011\tY\"!\u0006\u0003\u0011%#XM]1u_J\f\u0001bY1o\u000bF,\u0018\r\u001c\u000b\u0005\u0003C\t9\u0003E\u0002&\u0003GI1!!\n\'\u0005\u001d\u0011un\u001c7fC:D\u0011\"a\u0003\u0017\u0003\u0003\u0005\r!a\u0001\u0002%A\u0014x\u000eZ;di\u0016cW-\\3oi:\u000bW.\u001a\u000b\u0004k\u00065\u0002\u0002CA\u0006/\u0005\u0005\t\u0019\u0001?\u0002\u0011!\f7\u000f[\"pI\u0016$\u0012\u0001`\u0001\u0007KF,\u0018\r\\:\u0015\t\u0005\u0005\u0012q\u0007\u0005\n\u0003\u0017I\u0012\u0011!a\u0001\u0003\u0007\ta!Z7qif\u0004\u0013!B1qa2LHc\u0001\u001c\u0002@!)a)\u0002a\u0001\u0011\u00069QO\\1qa2LH\u0003BA#\u0003\u0017\u0002B!JA$\u0011&\u0019\u0011\u0011\n\u0014\u0003\r=\u0003H/[8o\u0011!\tiEBA\u0001\u0002\u00041\u0014a\u0001=%a\u0005aqO]5uKJ+\u0007\u000f\\1dKR\u0011\u00111\u000b\t\u0004m\u0006U\u0013bAA,o\n1qJ\u00196fGR\u0004
   #13 = Utf8               value
   #14 = Utf8               Lscala/collection/immutable/List;
   #15 = Utf8               Lscala/collection/immutable/List<Lcoursier/core/shaded/fastparse/internal/Lazy<Ljava/lang/String;>;>;
   #16 = Utf8               unapply
   #17 = Utf8               (Lcoursier/core/shaded/fastparse/internal/Msgs;)Lscala/Option;
   #18 = Utf8               (Lcoursier/core/shaded/fastparse/internal/Msgs;)Lscala/Option<Lscala/collection/immutable/List<Lcoursier/core/shaded/fastparse/internal/Lazy<Ljava/lang/String;>;>;>;
   #19 = Utf8               x$0
   #20 = Utf8               coursier/core/shaded/fastparse/internal/Msgs$
   #21 = Class              #20           // coursier/core/shaded/fastparse/internal/Msgs$
   #22 = Utf8               MODULE$
   #23 = Utf8               Lcoursier/core/shaded/fastparse/internal/Msgs$;
   #24 = NameAndType        #22:#23       // MODULE$:Lcoursier/core/shaded/fastparse/internal/Msgs$;
   #25 = Fieldref           #21.#24       // coursier/core/shaded/fastparse/internal/Msgs$.MODULE$:Lcoursier/core/shaded/fastparse/internal/Msgs$;
   #26 = NameAndType        #16:#17       // unapply:(Lcoursier/core/shaded/fastparse/internal/Msgs;)Lscala/Option;
   #27 = Methodref          #21.#26       // coursier/core/shaded/fastparse/internal/Msgs$.unapply:(Lcoursier/core/shaded/fastparse/internal/Msgs;)Lscala/Option;
   #28 = Utf8               apply
   #29 = Utf8               (Lscala/collection/immutable/List;)Lcoursier/core/shaded/fastparse/internal/Msgs;
   #30 = Utf8               (Lscala/collection/immutable/List<Lcoursier/core/shaded/fastparse/internal/Lazy<Ljava/lang/String;>;>;)Lcoursier/core/shaded/fastparse/internal/Msgs;
   #31 = NameAndType        #28:#29       // apply:(Lscala/collection/immutable/List;)Lcoursier/core/shaded/fastparse/internal/Msgs;
   #32 = Methodref          #21.#31       // coursier/core/shaded/fastparse/internal/Msgs$.apply:(Lscala/collection/immutable/List;)Lcoursier/core/shaded/fastparse/internal/Msgs;
   #33 = Utf8               empty
   #34 = Utf8               ()Lcoursier/core/shaded/fastparse/internal/Msgs;
   #35 = NameAndType        #33:#34       // empty:()Lcoursier/core/shaded/fastparse/internal/Msgs;
   #36 = Methodref          #21.#35       // coursier/core/shaded/fastparse/internal/Msgs$.empty:()Lcoursier/core/shaded/fastparse/internal/Msgs;
   #37 = Utf8               productElementNames
   #38 = Utf8               ()Lscala/collection/Iterator;
   #39 = Utf8               ()Lscala/collection/Iterator<Ljava/lang/String;>;
   #40 = Utf8               productElementNames$
   #41 = Utf8               (Lscala/Product;)Lscala/collection/Iterator;
   #42 = NameAndType        #40:#41       // productElementNames$:(Lscala/Product;)Lscala/collection/Iterator;
   #43 = InterfaceMethodref #6.#42        // scala/Product.productElementNames$:(Lscala/Product;)Lscala/collection/Iterator;
   #44 = Utf8               this
   #45 = Utf8               Lcoursier/core/shaded/fastparse/internal/Msgs;
   #46 = Utf8               ()Lscala/collection/immutable/List;
   #47 = Utf8               ()Lscala/collection/immutable/List<Lcoursier/core/shaded/fastparse/internal/Lazy<Ljava/lang/String;>;>;
   #48 = NameAndType        #13:#14       // value:Lscala/collection/immutable/List;
   #49 = Fieldref           #2.#48        // coursier/core/shaded/fastparse/internal/Msgs.value:Lscala/collection/immutable/List;
   #50 = Utf8               $colon$colon$colon
   #51 = Utf8               (Lcoursier/core/shaded/fastparse/internal/Msgs;)Lcoursier/core/shaded/fastparse/internal/Msgs;
   #52 = Utf8               other
   #53 = NameAndType        #13:#46       // value:()Lscala/collection/immutable/List;
   #54 = Methodref          #2.#53        // coursier/core/shaded/fastparse/internal/Msgs.value:()Lscala/collection/immutable/List;
   #55 = Utf8               scala/collection/immutable/List
   #56 = Class              #55           // scala/collection/immutable/List
   #57 = Utf8               (Lscala/collection/immutable/List;)Lscala/collection/immutable/List;
   #58 = NameAndType        #50:#57       // $colon$colon$colon:(Lscala/collection/immutable/List;)Lscala/collection/immutable/List;
   #59 = Methodref          #56.#58       // scala/collection/immutable/List.$colon$colon$colon:(Lscala/collection/immutable/List;)Lscala/collection/immutable/List;
   #60 = Utf8               <init>
   #61 = Utf8               (Lscala/collection/immutable/List;)V
   #62 = NameAndType        #60:#61       // "<init>":(Lscala/collection/immutable/List;)V
   #63 = Methodref          #2.#62        // coursier/core/shaded/fastparse/internal/Msgs."<init>":(Lscala/collection/immutable/List;)V
   #64 = Utf8               $colon$colon
   #65 = Utf8               (Lcoursier/core/shaded/fastparse/internal/Lazy;)Lcoursier/core/shaded/fastparse/internal/Msgs;
   #66 = Utf8               (Lcoursier/core/shaded/fastparse/internal/Lazy<Ljava/lang/String;>;)Lcoursier/core/shaded/fastparse/internal/Msgs;
   #67 = Utf8               (Ljava/lang/Object;)Lscala/collection/immutable/List;
   #68 = NameAndType        #64:#67       // $colon$colon:(Ljava/lang/Object;)Lscala/collection/immutable/List;
   #69 = Methodref          #56.#68       // scala/collection/immutable/List.$colon$colon:(Ljava/lang/Object;)Lscala/collection/immutable/List;
   #70 = Utf8               Lcoursier/core/shaded/fastparse/internal/Lazy;
   #71 = Utf8               toString
   #72 = Utf8               ()Ljava/lang/String;
   #73 = Utf8               render
   #74 = NameAndType        #73:#72       // render:()Ljava/lang/String;
   #75 = Methodref          #2.#74        // coursier/core/shaded/fastparse/internal/Msgs.render:()Ljava/lang/String;
   #76 = Utf8               coursier/core/shaded/fastparse/internal/Util$
   #77 = Class              #76           // coursier/core/shaded/fastparse/internal/Util$
   #78 = Utf8               Lcoursier/core/shaded/fastparse/internal/Util$;
   #79 = NameAndType        #22:#78       // MODULE$:Lcoursier/core/shaded/fastparse/internal/Util$;
   #80 = Fieldref           #77.#79       // coursier/core/shaded/fastparse/internal/Util$.MODULE$:Lcoursier/core/shaded/fastparse/internal/Util$;
   #81 = Utf8               parenthize
   #82 = Utf8               (Lscala/collection/immutable/Seq;)Ljava/lang/String;
   #83 = NameAndType        #81:#82       // parenthize:(Lscala/collection/immutable/Seq;)Ljava/lang/String;
   #84 = Methodref          #77.#83       // coursier/core/shaded/fastparse/internal/Util$.parenthize:(Lscala/collection/immutable/Seq;)Ljava/lang/String;
   #85 = Utf8               copy
   #86 = Utf8               copy$default$1
   #87 = Utf8               productPrefix
   #88 = Utf8               Msgs
   #89 = String             #88           // Msgs
   #90 = Utf8               productArity
   #91 = Utf8               ()I
   #92 = Utf8               productElement
   #93 = Utf8               (I)Ljava/lang/Object;
   #94 = Utf8               x$1
   #95 = Utf8               scala/runtime/Statics
   #96 = Class              #95           // scala/runtime/Statics
   #97 = Utf8               ioobe
   #98 = NameAndType        #97:#93       // ioobe:(I)Ljava/lang/Object;
   #99 = Methodref          #96.#98       // scala/runtime/Statics.ioobe:(I)Ljava/lang/Object;
  #100 = Utf8               I
  #101 = Utf8               productIterator
  #102 = Utf8               ()Lscala/collection/Iterator<Ljava/lang/Object;>;
  #103 = Utf8               scala/runtime/ScalaRunTime$
  #104 = Class              #103          // scala/runtime/ScalaRunTime$
  #105 = Utf8               Lscala/runtime/ScalaRunTime$;
  #106 = NameAndType        #22:#105      // MODULE$:Lscala/runtime/ScalaRunTime$;
  #107 = Fieldref           #104.#106     // scala/runtime/ScalaRunTime$.MODULE$:Lscala/runtime/ScalaRunTime$;
  #108 = Utf8               typedProductIterator
  #109 = NameAndType        #108:#41      // typedProductIterator:(Lscala/Product;)Lscala/collection/Iterator;
  #110 = Methodref          #104.#109     // scala/runtime/ScalaRunTime$.typedProductIterator:(Lscala/Product;)Lscala/collection/Iterator;
  #111 = Utf8               canEqual
  #112 = Utf8               (Ljava/lang/Object;)Z
  #113 = Utf8               Ljava/lang/Object;
  #114 = Utf8               productElementName
  #115 = Utf8               (I)Ljava/lang/String;
  #116 = String             #13           // value
  #117 = Utf8               java/lang/String
  #118 = Class              #117          // java/lang/String
  #119 = Utf8               hashCode
  #120 = Utf8               _hashCode
  #121 = Utf8               (Lscala/Product;)I
  #122 = NameAndType        #120:#121     // _hashCode:(Lscala/Product;)I
  #123 = Methodref          #104.#122     // scala/runtime/ScalaRunTime$._hashCode:(Lscala/Product;)I
  #124 = Utf8               equals
  #125 = NameAndType        #124:#112     // equals:(Ljava/lang/Object;)Z
  #126 = Methodref          #4.#125       // java/lang/Object.equals:(Ljava/lang/Object;)Z
  #127 = NameAndType        #111:#112     // canEqual:(Ljava/lang/Object;)Z
  #128 = Methodref          #2.#127       // coursier/core/shaded/fastparse/internal/Msgs.canEqual:(Ljava/lang/Object;)Z
  #129 = Utf8               (Lscala/collection/immutable/List<Lcoursier/core/shaded/fastparse/internal/Lazy<Ljava/lang/String;>;>;)V
  #130 = Utf8               ()V
  #131 = NameAndType        #60:#130      // "<init>":()V
  #132 = Methodref          #4.#131       // java/lang/Object."<init>":()V
  #133 = Utf8               $init$
  #134 = Utf8               (Lscala/Product;)V
  #135 = NameAndType        #133:#134     // $init$:(Lscala/Product;)V
  #136 = InterfaceMethodref #6.#135       // scala/Product.$init$:(Lscala/Product;)V
  #137 = Utf8               Signature
  #138 = Utf8               Code
  #139 = Utf8               MethodParameters
  #140 = Utf8               LineNumberTable
  #141 = Utf8               LocalVariableTable
  #142 = Utf8               StackMapTable
  #143 = Utf8               SourceFile
  #144 = Utf8               RuntimeVisibleAnnotations
  #145 = Utf8               ScalaInlineInfo
  #146 = Utf8               ScalaSig
{
  private final scala.collection.immutable.List<coursier.core.shaded.fastparse.internal.Lazy<java.lang.String>> value;
    descriptor: Lscala/collection/immutable/List;
    flags: (0x0012) ACC_PRIVATE, ACC_FINAL
    Signature: #15                          // Lscala/collection/immutable/List<Lcoursier/core/shaded/fastparse/internal/Lazy<Ljava/lang/String;>;>;

  public static scala.Option<scala.collection.immutable.List<coursier.core.shaded.fastparse.internal.Lazy<java.lang.String>>> unapply(coursier.core.shaded.fastparse.internal.Msgs);
    descriptor: (Lcoursier/core/shaded/fastparse/internal/Msgs;)Lscala/Option;
    flags: (0x0009) ACC_PUBLIC, ACC_STATIC
    Code:
      stack=2, locals=1, args_size=1
         0: getstatic     #25                 // Field coursier/core/shaded/fastparse/internal/Msgs$.MODULE$:Lcoursier/core/shaded/fastparse/internal/Msgs$;
         3: aload_0
         4: invokevirtual #27                 // Method coursier/core/shaded/fastparse/internal/Msgs$.unapply:(Lcoursier/core/shaded/fastparse/internal/Msgs;)Lscala/Option;
         7: areturn
    Signature: #18                          // (Lcoursier/core/shaded/fastparse/internal/Msgs;)Lscala/Option<Lscala/collection/immutable/List<Lcoursier/core/shaded/fastparse/internal/Lazy<Ljava/lang/String;>;>;>;
    MethodParameters:
      Name                           Flags
      x$0                            final

  public static coursier.core.shaded.fastparse.internal.Msgs apply(scala.collection.immutable.List<coursier.core.shaded.fastparse.internal.Lazy<java.lang.String>>);
    descriptor: (Lscala/collection/immutable/List;)Lcoursier/core/shaded/fastparse/internal/Msgs;
    flags: (0x0009) ACC_PUBLIC, ACC_STATIC
    Code:
      stack=2, locals=1, args_size=1
         0: getstatic     #25                 // Field coursier/core/shaded/fastparse/internal/Msgs$.MODULE$:Lcoursier/core/shaded/fastparse/internal/Msgs$;
         3: aload_0
         4: invokevirtual #32                 // Method coursier/core/shaded/fastparse/internal/Msgs$.apply:(Lscala/collection/immutable/List;)Lcoursier/core/shaded/fastparse/internal/Msgs;
         7: areturn
    Signature: #30                          // (Lscala/collection/immutable/List<Lcoursier/core/shaded/fastparse/internal/Lazy<Ljava/lang/String;>;>;)Lcoursier/core/shaded/fastparse/internal/Msgs;
    MethodParameters:
      Name                           Flags
      value                          final

  public static coursier.core.shaded.fastparse.internal.Msgs empty();
    descriptor: ()Lcoursier/core/shaded/fastparse/internal/Msgs;
    flags: (0x0009) ACC_PUBLIC, ACC_STATIC
    Code:
      stack=1, locals=0, args_size=0
         0: getstatic     #25                 // Field coursier/core/shaded/fastparse/internal/Msgs$.MODULE$:Lcoursier/core/shaded/fastparse/internal/Msgs$;
         3: invokevirtual #36                 // Method coursier/core/shaded/fastparse/internal/Msgs$.empty:()Lcoursier/core/shaded/fastparse/internal/Msgs;
         6: areturn

  public scala.collection.Iterator<java.lang.String> productElementNames();
    descriptor: ()Lscala/collection/Iterator;
    flags: (0x0001) ACC_PUBLIC
    Code:
      stack=1, locals=1, args_size=1
         0: aload_0
         1: invokestatic  #43                 // InterfaceMethod scala/Product.productElementNames$:(Lscala/Product;)Lscala/collection/Iterator;
         4: areturn
      LineNumberTable:
        line 152: 0
      LocalVariableTable:
        Start  Length  Slot  Name   Signature
            0       5     0  this   Lcoursier/core/shaded/fastparse/internal/Msgs;
    Signature: #39                          // ()Lscala/collection/Iterator<Ljava/lang/String;>;

  public scala.collection.immutable.List<coursier.core.shaded.fastparse.internal.Lazy<java.lang.String>> value();
    descriptor: ()Lscala/collection/immutable/List;
    flags: (0x0001) ACC_PUBLIC
    Code:
      stack=1, locals=1, args_size=1
         0: aload_0
         1: getfield      #49                 // Field value:Lscala/collection/immutable/List;
         4: areturn
      LineNumberTable:
        line 152: 0
      LocalVariableTable:
        Start  Length  Slot  Name   Signature
            0       5     0  this   Lcoursier/core/shaded/fastparse/internal/Msgs;
    Signature: #47                          // ()Lscala/collection/immutable/List<Lcoursier/core/shaded/fastparse/internal/Lazy<Ljava/lang/String;>;>;

  public coursier.core.shaded.fastparse.internal.Msgs $colon$colon$colon(coursier.core.shaded.fastparse.internal.Msgs);
    descriptor: (Lcoursier/core/shaded/fastparse/internal/Msgs;)Lcoursier/core/shaded/fastparse/internal/Msgs;
    flags: (0x0001) ACC_PUBLIC
    Code:
      stack=4, locals=3, args_size=2
         0: new           #2                  // class coursier/core/shaded/fastparse/internal/Msgs
         3: dup
         4: aload_1
         5: invokevirtual #54                 // Method value:()Lscala/collection/immutable/List;
         8: astore_2
         9: aload_0
        10: invokevirtual #54                 // Method value:()Lscala/collection/immutable/List;
        13: aload_2
        14: invokevirtual #59                 // Method scala/collection/immutable/List.$colon$colon$colon:(Lscala/collection/immutable/List;)Lscala/collection/immutable/List;
        17: invokespecial #63                 // Method "<init>":(Lscala/collection/immutable/List;)V
        20: areturn
      LineNumberTable:
        line 153: 0
      LocalVariableTable:
        Start  Length  Slot  Name   Signature
            0      21     0  this   Lcoursier/core/shaded/fastparse/internal/Msgs;
            0      21     1 other   Lcoursier/core/shaded/fastparse/internal/Msgs;
    MethodParameters:
      Name                           Flags
      other                          final

  public coursier.core.shaded.fastparse.internal.Msgs $colon$colon(coursier.core.shaded.fastparse.internal.Lazy<java.lang.String>);
    descriptor: (Lcoursier/core/shaded/fastparse/internal/Lazy;)Lcoursier/core/shaded/fastparse/internal/Msgs;
    flags: (0x0001) ACC_PUBLIC
    Code:
      stack=4, locals=3, args_size=2
         0: new           #2                  // class coursier/core/shaded/fastparse/internal/Msgs
         3: dup
         4: aload_1
         5: astore_2
         6: aload_0
         7: invokevirtual #54                 // Method value:()Lscala/collection/immutable/List;
        10: aload_2
        11: invokevirtual #69                 // Method scala/collection/immutable/List.$colon$colon:(Ljava/lang/Object;)Lscala/collection/immutable/List;
        14: invokespecial #63                 // Method "<init>":(Lscala/collection/immutable/List;)V
        17: areturn
      LineNumberTable:
        line 154: 0
      LocalVariableTable:
        Start  Length  Slot  Name   Signature
            0      18     0  this   Lcoursier/core/shaded/fastparse/internal/Msgs;
            0      18     1 other   Lcoursier/core/shaded/fastparse/internal/Lazy;
    Signature: #66                          // (Lcoursier/core/shaded/fastparse/internal/Lazy<Ljava/lang/String;>;)Lcoursier/core/shaded/fastparse/internal/Msgs;
    MethodParameters:
      Name                           Flags
      other                          final

  public java.lang.String toString();
    descriptor: ()Ljava/lang/String;
    flags: (0x0001) ACC_PUBLIC
    Code:
      stack=1, locals=1, args_size=1
         0: aload_0
         1: invokevirtual #75                 // Method render:()Ljava/lang/String;
         4: areturn
      LineNumberTable:
        line 155: 0
      LocalVariableTable:
        Start  Length  Slot  Name   Signature
            0       5     0  this   Lcoursier/core/shaded/fastparse/internal/Msgs;

  public java.lang.String render();
    descriptor: ()Ljava/lang/String;
    flags: (0x0001) ACC_PUBLIC
    Code:
      stack=2, locals=1, args_size=1
         0: getstatic     #80                 // Field coursier/core/shaded/fastparse/internal/Util$.MODULE$:Lcoursier/core/shaded/fastparse/internal/Util$;
         3: aload_0
         4: invokevirtual #54                 // Method value:()Lscala/collection/immutable/List;
         7: invokevirtual #84                 // Method coursier/core/shaded/fastparse/internal/Util$.parenthize:(Lscala/collection/immutable/Seq;)Ljava/lang/String;
        10: areturn
      LineNumberTable:
        line 156: 0
      LocalVariableTable:
        Start  Length  Slot  Name   Signature
            0      11     0  this   Lcoursier/core/shaded/fastparse/internal/Msgs;

  public coursier.core.shaded.fastparse.internal.Msgs copy(scala.collection.immutable.List<coursier.core.shaded.fastparse.internal.Lazy<java.lang.String>>);
    descriptor: (Lscala/collection/immutable/List;)Lcoursier/core/shaded/fastparse/internal/Msgs;
    flags: (0x0001) ACC_PUBLIC
    Code:
      stack=3, locals=2, args_size=2
         0: new           #2                  // class coursier/core/shaded/fastparse/internal/Msgs
         3: dup
         4: aload_1
         5: invokespecial #63                 // Method "<init>":(Lscala/collection/immutable/List;)V
         8: areturn
      LineNumberTable:
        line 152: 0
      LocalVariableTable:
        Start  Length  Slot  Name   Signature
            0       9     0  this   Lcoursier/core/shaded/fastparse/internal/Msgs;
            0       9     1 value   Lscala/collection/immutable/List;
    Signature: #30                          // (Lscala/collection/immutable/List<Lcoursier/core/shaded/fastparse/internal/Lazy<Ljava/lang/String;>;>;)Lcoursier/core/shaded/fastparse/internal/Msgs;
    MethodParameters:
      Name                           Flags
      value                          final

  public scala.collection.immutable.List<coursier.core.shaded.fastparse.internal.Lazy<java.lang.String>> copy$default$1();
    descriptor: ()Lscala/collection/immutable/List;
    flags: (0x0001) ACC_PUBLIC
    Code:
      stack=1, locals=1, args_size=1
         0: aload_0
         1: invokevirtual #54                 // Method value:()Lscala/collection/immutable/List;
         4: areturn
      LineNumberTable:
        line 152: 0
      LocalVariableTable:
        Start  Length  Slot  Name   Signature
            0       5     0  this   Lcoursier/core/shaded/fastparse/internal/Msgs;
    Signature: #47                          // ()Lscala/collection/immutable/List<Lcoursier/core/shaded/fastparse/internal/Lazy<Ljava/lang/String;>;>;

  public java.lang.String productPrefix();
    descriptor: ()Ljava/lang/String;
    flags: (0x0001) ACC_PUBLIC
    Code:
      stack=1, locals=1, args_size=1
         0: ldc           #89                 // String Msgs
         2: areturn
      LineNumberTable:
        line 152: 0
      LocalVariableTable:
        Start  Length  Slot  Name   Signature
            0       3     0  this   Lcoursier/core/shaded/fastparse/internal/Msgs;

  public int productArity();
    descriptor: ()I
    flags: (0x0001) ACC_PUBLIC
    Code:
      stack=1, locals=1, args_size=1
         0: iconst_1
         1: ireturn
      LineNumberTable:
        line 152: 0
      LocalVariableTable:
        Start  Length  Slot  Name   Signature
            0       2     0  this   Lcoursier/core/shaded/fastparse/internal/Msgs;

  public java.lang.Object productElement(int);
    descriptor: (I)Ljava/lang/Object;
    flags: (0x0001) ACC_PUBLIC
    Code:
      stack=1, locals=3, args_size=2
         0: iload_1
         1: istore_2
         2: iload_2
         3: tableswitch   { // 0 to 0
                       0: 20
                 default: 27
            }
        20: aload_0
        21: invokevirtual #54                 // Method value:()Lscala/collection/immutable/List;
        24: goto          34
        27: iload_1
        28: invokestatic  #99                 // Method scala/runtime/Statics.ioobe:(I)Ljava/lang/Object;
        31: goto          34
        34: areturn
      StackMapTable: number_of_entries = 3
        frame_type = 252 /* append */
          offset_delta = 20
          locals = [ int ]
        frame_type = 6 /* same */
        frame_type = 70 /* same_locals_1_stack_item */
          stack = [ class java/lang/Object ]
      LineNumberTable:
        line 152: 0
      LocalVariableTable:
        Start  Length  Slot  Name   Signature
            0      35     0  this   Lcoursier/core/shaded/fastparse/internal/Msgs;
            0      35     1   x$1   I
    MethodParameters:
      Name                           Flags
      x$1                            final

  public scala.collection.Iterator<java.lang.Object> productIterator();
    descriptor: ()Lscala/collection/Iterator;
    flags: (0x0001) ACC_PUBLIC
    Code:
      stack=2, locals=1, args_size=1
         0: getstatic     #107                // Field scala/runtime/ScalaRunTime$.MODULE$:Lscala/runtime/ScalaRunTime$;
         3: aload_0
         4: invokevirtual #110                // Method scala/runtime/ScalaRunTime$.typedProductIterator:(Lscala/Product;)Lscala/collection/Iterator;
         7: areturn
      LineNumberTable:
        line 152: 0
      LocalVariableTable:
        Start  Length  Slot  Name   Signature
            0       8     0  this   Lcoursier/core/shaded/fastparse/internal/Msgs;
    Signature: #102                         // ()Lscala/collection/Iterator<Ljava/lang/Object;>;

  public boolean canEqual(java.lang.Object);
    descriptor: (Ljava/lang/Object;)Z
    flags: (0x0001) ACC_PUBLIC
    Code:
      stack=1, locals=2, args_size=2
         0: aload_1
         1: instanceof    #2                  // class coursier/core/shaded/fastparse/internal/Msgs
         4: ireturn
      LineNumberTable:
        line 152: 0
      LocalVariableTable:
        Start  Length  Slot  Name   Signature
            0       5     0  this   Lcoursier/core/shaded/fastparse/internal/Msgs;
            0       5     1   x$1   Ljava/lang/Object;
    MethodParameters:
      Name                           Flags
      x$1                            final

  public java.lang.String productElementName(int);
    descriptor: (I)Ljava/lang/String;
    flags: (0x0001) ACC_PUBLIC
    Code:
      stack=1, locals=3, args_size=2
         0: iload_1
         1: istore_2
         2: iload_2
         3: tableswitch   { // 0 to 0
                       0: 20
                 default: 25
            }
        20: ldc           #116                // String value
        22: goto          35
        25: iload_1
        26: invokestatic  #99                 // Method scala/runtime/Statics.ioobe:(I)Ljava/lang/Object;
        29: checkcast     #118                // class java/lang/String
        32: goto          35
        35: areturn
      StackMapTable: number_of_entries = 3
        frame_type = 252 /* append */
          offset_delta = 20
          locals = [ int ]
        frame_type = 4 /* same */
        frame_type = 73 /* same_locals_1_stack_item */
          stack = [ class java/lang/String ]
      LineNumberTable:
        line 152: 0
      LocalVariableTable:
        Start  Length  Slot  Name   Signature
            0      36     0  this   Lcoursier/core/shaded/fastparse/internal/Msgs;
            0      36     1   x$1   I
    MethodParameters:
      Name                           Flags
      x$1                            final

  public int hashCode();
    descriptor: ()I
    flags: (0x0001) ACC_PUBLIC
    Code:
      stack=2, locals=1, args_size=1
         0: getstatic     #107                // Field scala/runtime/ScalaRunTime$.MODULE$:Lscala/runtime/ScalaRunTime$;
         3: aload_0
         4: invokevirtual #123                // Method scala/runtime/ScalaRunTime$._hashCode:(Lscala/Product;)I
         7: ireturn
      LineNumberTable:
        line 152: 0
      LocalVariableTable:
        Start  Length  Slot  Name   Signature
            0       8     0  this   Lcoursier/core/shaded/fastparse/internal/Msgs;

  public boolean equals(java.lang.Object);
    descriptor: (Ljava/lang/Object;)Z
    flags: (0x0001) ACC_PUBLIC
    Code:
      stack=2, locals=6, args_size=2
         0: aload_0
         1: aload_1
         2: if_acmpeq     86
         5: aload_1
         6: astore_3
         7: aload_3
         8: instanceof    #2                  // class coursier/core/shaded/fastparse/internal/Msgs
        11: ifeq          19
        14: iconst_1
        15: istore_2
        16: goto          27
        19: goto          22
        22: iconst_0
        23: istore_2
        24: goto          27
        27: iload_2
        28: ifeq          90
        31: aload_1
        32: checkcast     #2                  // class coursier/core/shaded/fastparse/internal/Msgs
        35: astore        4
        37: aload_0
        38: invokevirtual #54                 // Method value:()Lscala/collection/immutable/List;
        41: aload         4
        43: invokevirtual #54                 // Method value:()Lscala/collection/immutable/List;
        46: astore        5
        48: dup
        49: ifnonnull     61
        52: pop
        53: aload         5
        55: ifnull        69
        58: goto          82
        61: aload         5
        63: invokevirtual #126                // Method java/lang/Object.equals:(Ljava/lang/Object;)Z
        66: ifeq          82
        69: aload         4
        71: aload_0
        72: invokevirtual #128                // Method canEqual:(Ljava/lang/Object;)Z
        75: ifeq          82
        78: iconst_1
        79: goto          83
        82: iconst_0
        83: ifeq          90
        86: iconst_1
        87: goto          91
        90: iconst_0
        91: ireturn
      StackMapTable: number_of_entries = 10
        frame_type = 253 /* append */
          offset_delta = 19
          locals = [ top, class java/lang/Object ]
        frame_type = 2 /* same */
        frame_type = 255 /* full_frame */
          offset_delta = 4
          locals = [ class coursier/core/shaded/fastparse/internal/Msgs, class java/lang/Object, int, class java/lang/Object ]
          stack = []
        frame_type = 255 /* full_frame */
          offset_delta = 33
          locals = [ class coursier/core/shaded/fastparse/internal/Msgs, class java/lang/Object, int, class java/lang/Object, class coursier/core/shaded/fastparse/internal/Msgs, class scala/collection/immutable/List ]
          stack = [ class scala/collection/immutable/List ]
        frame_type = 7 /* same */
        frame_type = 12 /* same */
        frame_type = 64 /* same_locals_1_stack_item */
          stack = [ int ]
        frame_type = 255 /* full_frame */
          offset_delta = 2
          locals = [ class coursier/core/shaded/fastparse/internal/Msgs, class java/lang/Object ]
          stack = []
        frame_type = 253 /* append */
          offset_delta = 3
          locals = [ int, class java/lang/Object ]
        frame_type = 255 /* full_frame */
          offset_delta = 0
          locals = [ class coursier/core/shaded/fastparse/internal/Msgs, class java/lang/Object ]
          stack = [ int ]
      LineNumberTable:
        line 152: 0
      LocalVariableTable:
        Start  Length  Slot  Name   Signature
            0      92     0  this   Lcoursier/core/shaded/fastparse/internal/Msgs;
            0      92     1   x$1   Ljava/lang/Object;
    MethodParameters:
      Name                           Flags
      x$1                            final

  public coursier.core.shaded.fastparse.internal.Msgs(scala.collection.immutable.List<coursier.core.shaded.fastparse.internal.Lazy<java.lang.String>>);
    descriptor: (Lscala/collection/immutable/List;)V
    flags: (0x0001) ACC_PUBLIC
    Code:
      stack=2, locals=2, args_size=2
         0: aload_0
         1: aload_1
         2: putfield      #49                 // Field value:Lscala/collection/immutable/List;
         5: aload_0
         6: invokespecial #132                // Method java/lang/Object."<init>":()V
         9: aload_0
        10: invokestatic  #136                // InterfaceMethod scala/Product.$init$:(Lscala/Product;)V
        13: return
      LineNumberTable:
        line 152: 0
      LocalVariableTable:
        Start  Length  Slot  Name   Signature
            0      14     0  this   Lcoursier/core/shaded/fastparse/internal/Msgs;
            0      14     1 value   Lscala/collection/immutable/List;
    Signature: #129                         // (Lscala/collection/immutable/List<Lcoursier/core/shaded/fastparse/internal/Lazy<Ljava/lang/String;>;>;)V
    MethodParameters:
      Name                           Flags
      value                          final
}
SourceFile: "Util.scala"
RuntimeVisibleAnnotations:
  0: #10(#11=s#12)
    scala.reflect.ScalaSignature(
      bytes="\u0006\u0005\u0005es!\u0002\u000e\u001c\u0011\u0003\u0001c!\u0002\u0012\u001c\u0011\u0003\u0019\u0003\"\u0002\u001a\u0002\t\u0003\u0019\u0004b\u0002\u001b\u0002\u0005\u0004%\t!\u000e\u0005\b\u0003s\t\u0001\u0015!\u00037\u0011%\tY$AA\u0001\n\u0003\u000bi\u0004C\u0005\u0002B\u0005\t\t\u0011\"!\u0002D!I\u0011qJ\u0001\u0002\u0002\u0013%\u0011\u0011\u000b\u0004\u0005Em\u0001u\u0007\u0003\u0005G\u0011\tU\r\u0011\"\u0001H\u0011!1\u0006B!E!\u0002\u0013A\u0005\"\u0002\u001a\t\t\u00039\u0006\"B-\t\t\u0003Q\u0006\"B/\t\t\u0003q\u0006\"\u00021\t\t\u0003\n\u0007\"\u00022\t\t\u0003\u0019\u0007b\u00023\t\u0003\u0003%\t!\u001a\u0005\bO\"\t\n\u0011\"\u0001i\u0011\u001d\u0019\b\"!A\u0005BQDqA\u001f\u0005\u0002\u0002\u0013\u00051\u0010\u0003\u0005\u0000\u0011\u0005\u0005I\u0011AA\u0001\u0011%\ti\u0001CA\u0001\n\u0003\ny\u0001C\u0005\u0002\u001e!\t\t\u0011\"\u0001\u0002 !I\u0011\u0011\u0006\u0005\u0002\u0002\u0013\u0005\u00131\u0006\u0005\n\u0003_A\u0011\u0011!C!\u0003cA\u0011\"a\r\t\u0003\u0003%\t%!\u000e\u0002\t5\u001bxm\u001d\u0006\u00039u\t\u0001\"\u001b8uKJt\u0017\r\u001c\u0006\u0002=\u0005Ia-Y:ua\u0006\u00148/Z\u0002\u0001!\t\t\u0013!D\u0001\u001c\u0005\u0011i5oZ:\u0014\u0007\u0005!#\u0006\u0005\u0002&Q5\taEC\u0001(\u0003\u0015\u00198-\u00197b\u0013\tIcE\u0001\u0004B]f\u0014VM\u001a\t\u0003WAj\u0011\u0001\f\u0006\u0003[9\n!![8\u000b\u0003=\nAA[1wC&\u0011\u0011\u0007\f\u0002\r\'\u0016\u0014\u0018.\u00197ju\u0006\u0014G.Z\u0001\u0007y%t\u0017\u000e\u001e \u0015\u0003\u0001\nQ!Z7qif,\u0012A\u000e\t\u0003C!\u0019B\u0001\u0003\u00139wA\u0011Q%O\u0005\u0003u\u0019\u0012q\u0001\u0015:pIV\u001cG\u000f\u0005\u0002=\t:\u0011QH\u0011\b\u0003}\u0005k\u0011a\u0010\u0006\u0003\u0001~\ta\u0001\u0010:p_Rt\u0014\"A\u0014\n\u0005\r3\u0013a\u00029bG.\fw-Z\u0005\u0003c\u0015S!a\u0011\u0014\u0002\u000bY\fG.^3\u0016\u0003!\u00032\u0001P%L\u0013\tQUI\u0001\u0003MSN$\bcA\u0011M\u001d&\u0011Qj\u0007\u0002\u0005\u0019\u0006T\u0018\u0010\u0005\u0002P\':\u0011\u0001+\u0015\t\u0003}\u0019J!A\u0015\u0014\u0002\rA\u0013X\rZ3g\u0013\t!VK\u0001\u0004TiJLgn\u001a\u0006\u0003%\u001a\naA^1mk\u0016\u0004CC\u0001\u001cY\u0011\u001515\u00021\u0001I\u0003I!3m\u001c7p]\u0012\u001aw\u000e\\8oI\r|Gn\u001c8\u0015\u0005YZ\u0006\"\u0002/\r\u0001\u00041\u0014!B8uQ\u0016\u0014\u0018\u0001\u0004\u0013d_2|g\u000eJ2pY>tGC\u0001\u001c`\u0011\u0015aV\u00021\u0001L\u0003!!xn\u0015;sS:<G#\u0001(\u0002\rI,g\u000eZ3s+\u0005q\u0015\u0001B2paf$\"A\u000e4\t\u000f\u0019\u0003\u0002\u0013!a\u0001\u0011\u0006q1m\u001c9zI\u0011,g-Y;mi\u0012\nT#A5+\u0005!S7&A6\u0011\u00051\fX\"A7\u000b\u00059|\u0017!C;oG\",7m[3e\u0015\t\u0001h%\u0001\u0006b]:|G/\u0019;j_:L!A]7\u0003#Ut7\r[3dW\u0016$g+\u0019:jC:\u001cW-A\u0007qe>$Wo\u0019;Qe\u00164\u0017\u000e_\u000b\u0002kB\u0011a/_\u0007\u0002o*\u0011\u0001PL\u0001\u0005Y\u0006tw-\u0003\u0002Uo\u0006a\u0001O]8ek\u000e$\u0018I]5usV\tA\u0010\u0005\u0002&{&\u0011aP\n\u0002\u0004\u0013:$\u0018A\u00049s_\u0012,8\r^#mK6,g\u000e\u001e\u000b\u0005\u0003\u0007\tI\u0001E\u0002&\u0003\u000bI1!a\u0002\'\u0005\r\te.\u001f\u0005\t\u0003\u0017!\u0012\u0011!a\u0001y\u0006\u0019\u0001\u0010J\u0019\u0002\u001fA\u0014x\u000eZ;di&#XM]1u_J,\"!!\u0005\u0011\r\u0005M\u0011\u0011DA\u0002\u001b\t\t)BC\u0002\u0002\u0018\u0019\n!bY8mY\u0016\u001cG/[8o\u0013\u0011\tY\"!\u0006\u0003\u0011%#XM]1u_J\f\u0001bY1o\u000bF,\u0018\r\u001c\u000b\u0005\u0003C\t9\u0003E\u0002&\u0003GI1!!\n\'\u0005\u001d\u0011un\u001c7fC:D\u0011\"a\u0003\u0017\u0003\u0003\u0005\r!a\u0001\u0002%A\u0014x\u000eZ;di\u0016cW-\\3oi:\u000bW.\u001a\u000b\u0004k\u00065\u0002\u0002CA\u0006/\u0005\u0005\t\u0019\u0001?\u0002\u0011!\f7\u000f[\"pI\u0016$\u0012\u0001`\u0001\u0007KF,\u0018\r\\:\u0015\t\u0005\u0005\u0012q\u0007\u0005\n\u0003\u0017I\u0012\u0011!a\u0001\u0003\u0007\ta!Z7qif\u0004\u0013!B1qa2LHc\u0001\u001c\u0002@!)a)\u0002a\u0001\u0011\u00069QO\\1qa2LH\u0003BA#\u0003\u0017\u0002B!JA$\u0011&\u0019\u0011\u0011\n\u0014\u0003\r=\u0003H/[8o\u0011!\tiEBA\u0001\u0002\u00041\u0014a\u0001=%a\u0005aqO]5uKJ+\u0007\u000f\\1dKR\u0011\u00111\u000b\t\u0004m\u0006U\u0013bAA,o\n1qJ\u00196fGR\u0004"
    )
  ScalaInlineInfo: length = 0x59 (unknown attribute)
   01 00 00 11 00 40 00 41 00 00 32 00 33 00 00 3C
   00 3D 00 00 6F 00 70 00 00 55 00 1D 00 00 56 00
   2E 00 00 7C 00 70 00 00 77 00 5B 00 00 5A 00 5B
   00 00 5C 00 5D 00 00 72 00 73 00 00 25 00 26 00
   00 65 00 26 00 00 57 00 48 00 00 49 00 48 00 00
   47 00 48 00 00 0D 00 2E 00
  ScalaSig: length = 0x3 (unknown attribute)
   05 02 00
