Classfile /Users/mw/Projects/slang-braindump/.jar/jar8/assemble/slang-braindump/assemble/content/shapeless/test/TypeTrace.class
  Last modified May 29, 2022; size 1316 bytes
  SHA-256 checksum 40eb202640bb97dc69549a8f2566f7247f8abcf7855f52f8ba36524ee3ca8eea
  Compiled from "typetrace.scala"
public class shapeless.test.TypeTrace<T extends java.lang.Object> extends java.lang.Object
  minor version: 0
  major version: 52
  flags: (0x0021) ACC_PUBLIC, ACC_SUPER
  this_class: #2                          // shapeless/test/TypeTrace
  super_class: #5                         // java/lang/Object
  interfaces: 0, fields: 0, methods: 1, attributes: 5
Constant pool:
   #1 = Utf8               shapeless/test/TypeTrace
   #2 = Class              #1             // shapeless/test/TypeTrace
   #3 = Utf8               <T:Ljava/lang/Object;>Ljava/lang/Object;
   #4 = Utf8               java/lang/Object
   #5 = Class              #4             // java/lang/Object
   #6 = Utf8               typetrace.scala
   #7 = Utf8               Lscala/reflect/ScalaSignature;
   #8 = Utf8               bytes
   #9 = Utf8               \u0006\u0005i4AAB\u0004\u0001\u0019!)A\u0003\u0001C\u0001+\u001d)1e\u0002E\u0001I\u0019)aa\u0002E\u0001K!)Ac\u0001C\u0001M!1qe\u0001B\u0005\u0004!\u0012\u0011\u0002V=qKR\u0013\u0018mY3\u000b\u0005!I\u0011\u0001\u0002;fgRT\u0011AC\u0001\ng\"\f\u0007/\u001a7fgN\u001c\u0001!\u0006\u0002\u000e5M\u0011\u0001A\u0004\t\u0003\u001fIi\u0011\u0001\u0005\u0006\u0002#\u0005)1oY1mC&\u00111\u0003\u0005\u0002\u0007\u0003:L(+\u001a4\u0002\rqJg.\u001b;?)\u00051\u0002cA\f\u000115\tq\u0001\u0005\u0002\u001a51\u0001A!B\u000e\u0001\u0005\u0004a\"!\u0001+\u0012\u0005u\u0001\u0003CA\b\u001f\u0013\ty\u0002CA\u0004O_RD\u0017N\\4\u0011\u0005=\t\u0013B\u0001\u0012\u0011\u0005\r\te._\u0001\n)f\u0004X\r\u0016:bG\u0016\u0004\"aF\u0002\u0014\u0005\rqA#\u0001\u0013\u0002\u000b\u0005\u0004\b\u000f\\=\u0016\u0005%bS#\u0001\u0016\u0011\u0007]\u00011\u0006\u0005\u0002\u001aY\u0011)1$\u0002b\u00019!\u001aQA\f\u001d\u0011\u0005=2T\"\u0001\u0019\u000b\u0005E\u0012\u0014\u0001C5oi\u0016\u0014h.\u00197\u000b\u0005M\"\u0014AB7bGJ|7O\u0003\u00026!\u00059!/\u001a4mK\u000e$\u0018BA\u001c1\u0005%i\u0017m\u0019:p\u00136\u0004H.\r\u0003\u001fsiB8\u0002A\u0019\n?eZTH\u0012(U;\u001a\fD\u0001J\u001d\fy\u0005)Q.Y2s_F\"a#\u000f Cc\r)s\bQ\b\u0002\u0001\u0006\n\u0011)A\u0006nC\u000e\u0014x.\u00128hS:,\u0017gA\u0013D\t>\tA)I\u0001F\u0003\u00152xG\f\u0019!Q%l\u0007\u000f\\3nK:$X\r\u001a\u0011j]\u0002\u001a6-\u00197bAIr\u0013\'\r\u00181[5C\u0014&\r\u0003\u0017s\u001d[\u0015gA\u0013I\u0013>\t\u0011*I\u0001K\u0003!I7OQ;oI2,\u0017gA\u0013M\u001b>\tQ*G\u0001\u0002c\u00111\u0012hT*2\u0007\u0015\u0002\u0016kD\u0001RC\u0005\u0011\u0016AC5t\u00052\f7m\u001b2pqF\u001aQ\u0005T\'2\tYIT+W\u0019\u0004KY;v\"A,\"\u0003a\u000b\u0011b\u00197bgNt\u0015-\\32\u0007\u0015R6lD\u0001\\C\u0005a\u0016AH:iCB,G.Z:t]Q,7\u000f\u001e\u0018UsB,GK]1dK6\u000b7M]8tc\u00111\u0012H\u001822\u0007\u0015z\u0006mD\u0001aC\u0005\t\u0017AC7fi\"|GMT1nKF\u001aQe\u00193\u0010\u0003\u0011\f\u0013!Z\u0001\nCB\u0004H._%na2\fDAF\u001dhWF\u001aQ\u0005[5\u0010\u0003%\f\u0013A[\u0001\ng&<g.\u0019;ve\u0016\fDaH\u001dmgF\"A%O7o\u0013\tqw.\u0001\u0003MSN$(B\u00019r\u0003%IW.\\;uC\ndWM\u0003\u0002s!\u0005Q1m\u001c7mK\u000e$\u0018n\u001c82\t}ID/^\u0019\u0005Iejg.M\u0002&m^|\u0011a^\u000f\u0002\u0001E\u0012a%\u001f\t\u000331\u0002
  #10 = Utf8               <init>
  #11 = Utf8               ()V
  #12 = NameAndType        #10:#11        // "<init>":()V
  #13 = Methodref          #5.#12         // java/lang/Object."<init>":()V
  #14 = Utf8               this
  #15 = Utf8               Lshapeless/test/TypeTrace;
  #16 = Utf8               Code
  #17 = Utf8               LineNumberTable
  #18 = Utf8               LocalVariableTable
  #19 = Utf8               Signature
  #20 = Utf8               SourceFile
  #21 = Utf8               RuntimeVisibleAnnotations
  #22 = Utf8               ScalaInlineInfo
  #23 = Utf8               ScalaSig
{
  public shapeless.test.TypeTrace();
    descriptor: ()V
    flags: (0x0001) ACC_PUBLIC
    Code:
      stack=1, locals=1, args_size=1
         0: aload_0
         1: invokespecial #13                 // Method java/lang/Object."<init>":()V
         4: return
      LineNumberTable:
        line 26: 0
      LocalVariableTable:
        Start  Length  Slot  Name   Signature
            0       5     0  this   Lshapeless/test/TypeTrace;
}
Signature: #3                           // <T:Ljava/lang/Object;>Ljava/lang/Object;
SourceFile: "typetrace.scala"
RuntimeVisibleAnnotations:
  0: #7(#8=s#9)
    scala.reflect.ScalaSignature(
      bytes="\u0006\u0005i4AAB\u0004\u0001\u0019!)A\u0003\u0001C\u0001+\u001d)1e\u0002E\u0001I\u0019)aa\u0002E\u0001K!)Ac\u0001C\u0001M!1qe\u0001B\u0005\u0004!\u0012\u0011\u0002V=qKR\u0013\u0018mY3\u000b\u0005!I\u0011\u0001\u0002;fgRT\u0011AC\u0001\ng\"\f\u0007/\u001a7fgN\u001c\u0001!\u0006\u0002\u000e5M\u0011\u0001A\u0004\t\u0003\u001fIi\u0011\u0001\u0005\u0006\u0002#\u0005)1oY1mC&\u00111\u0003\u0005\u0002\u0007\u0003:L(+\u001a4\u0002\rqJg.\u001b;?)\u00051\u0002cA\f\u000115\tq\u0001\u0005\u0002\u001a51\u0001A!B\u000e\u0001\u0005\u0004a\"!\u0001+\u0012\u0005u\u0001\u0003CA\b\u001f\u0013\ty\u0002CA\u0004O_RD\u0017N\\4\u0011\u0005=\t\u0013B\u0001\u0012\u0011\u0005\r\te._\u0001\n)f\u0004X\r\u0016:bG\u0016\u0004\"aF\u0002\u0014\u0005\rqA#\u0001\u0013\u0002\u000b\u0005\u0004\b\u000f\\=\u0016\u0005%bS#\u0001\u0016\u0011\u0007]\u00011\u0006\u0005\u0002\u001aY\u0011)1$\u0002b\u00019!\u001aQA\f\u001d\u0011\u0005=2T\"\u0001\u0019\u000b\u0005E\u0012\u0014\u0001C5oi\u0016\u0014h.\u00197\u000b\u0005M\"\u0014AB7bGJ|7O\u0003\u00026!\u00059!/\u001a4mK\u000e$\u0018BA\u001c1\u0005%i\u0017m\u0019:p\u00136\u0004H.\r\u0003\u001fsiB8\u0002A\u0019\n?eZTH\u0012(U;\u001a\fD\u0001J\u001d\fy\u0005)Q.Y2s_F\"a#\u000f Cc\r)s\bQ\b\u0002\u0001\u0006\n\u0011)A\u0006nC\u000e\u0014x.\u00128hS:,\u0017gA\u0013D\t>\tA)I\u0001F\u0003\u00152xG\f\u0019!Q%l\u0007\u000f\\3nK:$X\r\u001a\u0011j]\u0002\u001a6-\u00197bAIr\u0013\'\r\u00181[5C\u0014&\r\u0003\u0017s\u001d[\u0015gA\u0013I\u0013>\t\u0011*I\u0001K\u0003!I7OQ;oI2,\u0017gA\u0013M\u001b>\tQ*G\u0001\u0002c\u00111\u0012hT*2\u0007\u0015\u0002\u0016kD\u0001RC\u0005\u0011\u0016AC5t\u00052\f7m\u001b2pqF\u001aQ\u0005T\'2\tYIT+W\u0019\u0004KY;v\"A,\"\u0003a\u000b\u0011b\u00197bgNt\u0015-\\32\u0007\u0015R6lD\u0001\\C\u0005a\u0016AH:iCB,G.Z:t]Q,7\u000f\u001e\u0018UsB,GK]1dK6\u000b7M]8tc\u00111\u0012H\u001822\u0007\u0015z\u0006mD\u0001aC\u0005\t\u0017AC7fi\"|GMT1nKF\u001aQe\u00193\u0010\u0003\u0011\f\u0013!Z\u0001\nCB\u0004H._%na2\fDAF\u001dhWF\u001aQ\u0005[5\u0010\u0003%\f\u0013A[\u0001\ng&<g.\u0019;ve\u0016\fDaH\u001dmgF\"A%O7o\u0013\tqw.\u0001\u0003MSN$(B\u00019r\u0003%IW.\\;uC\ndWM\u0003\u0002s!\u0005Q1m\u001c7mK\u000e$\u0018n\u001c82\t}ID/^\u0019\u0005Iejg.M\u0002&m^|\u0011a^\u000f\u0002\u0001E\u0012a%\u001f\t\u000331\u0002"
    )
  ScalaInlineInfo: length = 0x9 (unknown attribute)
   01 00 00 01 00 0A 00 0B 00
  ScalaSig: length = 0x3 (unknown attribute)
   05 02 00
