Classfile /Users/mw/Projects/slang-braindump/.jar/jar11/assemble/slang-braindump/assemble/content/coursier/util/Gather$ToGatherOps$$anon$1.class
  Last modified May 29, 2022; size 1336 bytes
  SHA-256 checksum 2fca910c48e6638763db4b548819538ea68f41ff41df59a3b6d62c46ad89cc69
  Compiled from "Gather.scala"
public final class coursier.util.Gather$ToGatherOps$$anon$1 extends java.lang.Object implements coursier.util.Gather$Ops<F, A>
  minor version: 0
  major version: 52
  flags: (0x0031) ACC_PUBLIC, ACC_FINAL, ACC_SUPER
  this_class: #2                          // coursier/util/Gather$ToGatherOps$$anon$1
  super_class: #5                         // java/lang/Object
  interfaces: 1, fields: 2, methods: 3, attributes: 6
Constant pool:
   #1 = Utf8               coursier/util/Gather$ToGatherOps$$anon$1
   #2 = Class              #1             // coursier/util/Gather$ToGatherOps$$anon$1
   #3 = Utf8               Ljava/lang/Object;Lcoursier/util/Gather$Ops<TF;TA;>;
   #4 = Utf8               java/lang/Object
   #5 = Class              #4             // java/lang/Object
   #6 = Utf8               coursier/util/Gather$Ops
   #7 = Class              #6             // coursier/util/Gather$Ops
   #8 = Utf8               Gather.scala
   #9 = Utf8               coursier/util/Gather$ToGatherOps
  #10 = Class              #9             // coursier/util/Gather$ToGatherOps
  #11 = Utf8               toGatherOps
  #12 = Utf8               (Ljava/lang/Object;Lcoursier/util/Gather;)Lcoursier/util/Gather$Ops;
  #13 = NameAndType        #11:#12        // toGatherOps:(Ljava/lang/Object;Lcoursier/util/Gather;)Lcoursier/util/Gather$Ops;
  #14 = Utf8               coursier/util/Gather
  #15 = Class              #14            // coursier/util/Gather
  #16 = Utf8               Ops
  #17 = Utf8               ToGatherOps
  #18 = Utf8               self
  #19 = Utf8               Ljava/lang/Object;
  #20 = Utf8               TF;
  #21 = Utf8               typeClassInstance
  #22 = Utf8               Lcoursier/util/Gather;
  #23 = Utf8               Lcoursier/util/Gather<TF;>;
  #24 = Utf8               ()Ljava/lang/Object;
  #25 = Utf8               ()TF;
  #26 = NameAndType        #18:#19        // self:Ljava/lang/Object;
  #27 = Fieldref           #2.#26         // coursier/util/Gather$ToGatherOps$$anon$1.self:Ljava/lang/Object;
  #28 = Utf8               this
  #29 = Utf8               Lcoursier/util/Gather$ToGatherOps$$anon$1;
  #30 = Utf8               ()Lcoursier/util/Gather;
  #31 = Utf8               ()Lcoursier/util/Gather<TF;>;
  #32 = NameAndType        #21:#22        // typeClassInstance:Lcoursier/util/Gather;
  #33 = Fieldref           #2.#32         // coursier/util/Gather$ToGatherOps$$anon$1.typeClassInstance:Lcoursier/util/Gather;
  #34 = Utf8               <init>
  #35 = Utf8               (Lcoursier/util/Gather$ToGatherOps;Ljava/lang/Object;Lcoursier/util/Gather;)V
  #36 = Utf8               $outer
  #37 = Utf8               target$1
  #38 = Utf8               tc$1
  #39 = Utf8               ()V
  #40 = NameAndType        #34:#39        // "<init>":()V
  #41 = Methodref          #5.#40         // java/lang/Object."<init>":()V
  #42 = Utf8               Lcoursier/util/Gather$ToGatherOps;
  #43 = Utf8               Signature
  #44 = Utf8               Code
  #45 = Utf8               LineNumberTable
  #46 = Utf8               LocalVariableTable
  #47 = Utf8               MethodParameters
  #48 = Utf8               InnerClasses
  #49 = Utf8               EnclosingMethod
  #50 = Utf8               SourceFile
  #51 = Utf8               ScalaInlineInfo
  #52 = Utf8               Scala
{
  private final F self;
    descriptor: Ljava/lang/Object;
    flags: (0x0012) ACC_PRIVATE, ACC_FINAL
    Signature: #20                          // TF;

  private final coursier.util.Gather<F> typeClassInstance;
    descriptor: Lcoursier/util/Gather;
    flags: (0x0012) ACC_PRIVATE, ACC_FINAL
    Signature: #23                          // Lcoursier/util/Gather<TF;>;

  public F self();
    descriptor: ()Ljava/lang/Object;
    flags: (0x0001) ACC_PUBLIC
    Code:
      stack=1, locals=1, args_size=1
         0: aload_0
         1: getfield      #27                 // Field self:Ljava/lang/Object;
         4: areturn
      LineNumberTable:
        line 5: 0
      LocalVariableTable:
        Start  Length  Slot  Name   Signature
            0       5     0  this   Lcoursier/util/Gather$ToGatherOps$$anon$1;
    Signature: #25                          // ()TF;

  public coursier.util.Gather<F> typeClassInstance();
    descriptor: ()Lcoursier/util/Gather;
    flags: (0x0001) ACC_PUBLIC
    Code:
      stack=1, locals=1, args_size=1
         0: aload_0
         1: getfield      #33                 // Field typeClassInstance:Lcoursier/util/Gather;
         4: areturn
      LineNumberTable:
        line 5: 0
      LocalVariableTable:
        Start  Length  Slot  Name   Signature
            0       5     0  this   Lcoursier/util/Gather$ToGatherOps$$anon$1;
    Signature: #31                          // ()Lcoursier/util/Gather<TF;>;

  public coursier.util.Gather$ToGatherOps$$anon$1(coursier.util.Gather$ToGatherOps, java.lang.Object, coursier.util.Gather);
    descriptor: (Lcoursier/util/Gather$ToGatherOps;Ljava/lang/Object;Lcoursier/util/Gather;)V
    flags: (0x0001) ACC_PUBLIC
    Code:
      stack=2, locals=4, args_size=4
         0: aload_0
         1: invokespecial #41                 // Method java/lang/Object."<init>":()V
         4: aload_0
         5: aload_2
         6: putfield      #27                 // Field self:Ljava/lang/Object;
         9: aload_0
        10: aload_3
        11: putfield      #33                 // Field typeClassInstance:Lcoursier/util/Gather;
        14: return
      LineNumberTable:
        line 5: 0
      LocalVariableTable:
        Start  Length  Slot  Name   Signature
            0      15     0  this   Lcoursier/util/Gather$ToGatherOps$$anon$1;
            0      15     1 $outer   Lcoursier/util/Gather$ToGatherOps;
            0      15     2 target$1   Ljava/lang/Object;
            0      15     3  tc$1   Lcoursier/util/Gather;
    MethodParameters:
      Name                           Flags
      $outer                         final synthetic
      target$1                       final
      tc$1                           final
}
InnerClasses:
  public static #16= #7 of #15;           // Ops=class coursier/util/Gather$Ops of class coursier/util/Gather
  public static #17= #10 of #15;          // ToGatherOps=class coursier/util/Gather$ToGatherOps of class coursier/util/Gather
  public final #2;                        // class coursier/util/Gather$ToGatherOps$$anon$1
EnclosingMethod: #10.#13                // coursier.util.Gather$ToGatherOps.toGatherOps
Signature: #3                           // Ljava/lang/Object;Lcoursier/util/Gather$Ops<TF;TA;>;
SourceFile: "Gather.scala"
  ScalaInlineInfo: length = 0x13 (unknown attribute)
   01 01 00 03 00 22 00 23 01 00 12 00 18 01 00 15
   00 1E 01
  Scala: length = 0x0 (unknown attribute)

