Classfile /Users/mw/Projects/slang-braindump/.jar/jar11/assemble/slang-braindump/assemble/content/coursier/util/ModuleMatchers.class
  Last modified May 29, 2022; size 11492 bytes
  SHA-256 checksum 62c1603cf9bb289ccff98f8e23f1d3efe9dd8bf374e132f5b247a5e7f0c05a9b
  Compiled from "ModuleMatchers.scala"
public final class coursier.util.ModuleMatchers implements scala.Product,java.io.Serializable
  minor version: 0
  major version: 52
  flags: (0x0031) ACC_PUBLIC, ACC_FINAL, ACC_SUPER
  this_class: #2                          // coursier/util/ModuleMatchers
  super_class: #4                         // java/lang/Object
  interfaces: 2, fields: 3, methods: 38, attributes: 6
Constant pool:
    #1 = Utf8               coursier/util/ModuleMatchers
    #2 = Class              #1            // coursier/util/ModuleMatchers
    #3 = Utf8               java/lang/Object
    #4 = Class              #3            // java/lang/Object
    #5 = Utf8               scala/Product
    #6 = Class              #5            // scala/Product
    #7 = Utf8               java/io/Serializable
    #8 = Class              #7            // java/io/Serializable
    #9 = Utf8               ModuleMatchers.scala
   #10 = Utf8               Lscala/reflect/ScalaSignature;
   #11 = Utf8               bytes
   #12 = Utf8               \u0006\u0005\u0005ee\u0001B\u0012%\u0005%B\u0001b\u0010\u0001\u0003\u0006\u0004%\t\u0001\u0011\u0005\t\u001b\u0002\u0011\t\u0011)A\u0005\u0003\"Aa\n\u0001BC\u0002\u0013\u0005\u0001\t\u0003\u0005P\u0001\t\u0005\t\u0015!\u0003B\u0011!\u0001\u0006A!b\u0001\n\u0003\t\u0006\u0002C+\u0001\u0005\u0003\u0005\u000b\u0011\u0002*\t\u000bY\u0003A\u0011A,\t\u000bY\u0003A\u0011\u0001/\t\u000bY\u0003A\u0011A0\t\u000b\u0005\u0004A\u0011\u00012\t\u000b-\u0004A\u0011\u00017\t\u000b=\u0004A\u0011\u00019\t\u000bI\u0004A\u0011A:\t\u000bU\u0004A\u0011\u0001<\t\u000ba\u0004A\u0011I=\t\u000f\u0005\u0015\u0001\u0001\"\u0011\u0002\b!9\u00111\u0003\u0001\u0005B\u0005U\u0001bBA\r\u0001\u0011\u0005\u00131\u0004\u0005\b\u0003G\u0001A\u0011BA\u0013\u0011\u001d\ti\u0003\u0001C!\u0003_Aq!!\r\u0001\t\u0003\n\u0019\u0004C\u0004\u00026\u0001!\t%a\u000e\t\u000f\u0005u\u0002\u0001\"\u0011\u0002@\u001d9\u00111\t\u0013\t\u0002\u0005\u0015cAB\u0012%\u0011\u0003\t9\u0005\u0003\u0004W3\u0011\u0005\u00111\u000b\u0005\b\u0003+JB\u0011AA,\u0011\u001d\tI&\u0007C\u0001\u00037Bq!!\u0017\u001a\t\u0003\t\t\u0007C\u0004\u0002Ze!\t!!\u001a\t\u000f\u0005m\u0014\u0004\"\u0001\u0002~!9\u00111P\r\u0005\u0002\u0005\u0005\u0005bBA>3\u0011\u0005\u0011q\u0011\u0005\n\u0003\u001fK\u0012\u0011!C\u0005\u0003#\u0013a\"T8ek2,W*\u0019;dQ\u0016\u00148O\u0003\u0002&M\u0005!Q\u000f^5m\u0015\u00059\u0013\u0001C2pkJ\u001c\u0018.\u001a:\u0004\u0001M!\u0001A\u000b\u00194!\tYc&D\u0001-\u0015\u0005i\u0013!B:dC2\f\u0017BA\u0018-\u0005\u0019\te.\u001f*fMB\u00111&M\u0005\u0003e1\u0012q\u0001\u0015:pIV\u001cG\u000f\u0005\u00025y9\u0011QG\u000f\b\u0003mej\u0011a\u000e\u0006\u0003q!\na\u0001\u0010:p_Rt\u0014\"A\u0017\n\u0005mb\u0013a\u00029bG.\fw-Z\u0005\u0003{y\u0012AbU3sS\u0006d\u0017N_1cY\u0016T!a\u000f\u0017\u0002\u000f\u0015D8\r\\;eKV\t\u0011\tE\u0002C\r&s!a\u0011#\u0011\u0005Yb\u0013BA#-\u0003\u0019\u0001&/\u001a3fM&\u0011q\t\u0013\u0002\u0004\'\u0016$(BA#-!\tQ5*D\u0001%\u0013\taEEA\u0007N_\u0012,H.Z\'bi\u000eDWM]\u0001\tKb\u001cG.\u001e3fA\u00059\u0011N\\2mk\u0012,\u0017\u0001C5oG2,H-\u001a\u0011\u0002!%t7\r\\;eK\nKH)\u001a4bk2$X#\u0001*\u0011\u0005-\u001a\u0016B\u0001+-\u0005\u001d\u0011un\u001c7fC:\f\u0011#\u001b8dYV$WMQ=EK\u001a\fW\u000f\u001c;!\u0003\u0019a\u0014N\\5u}Q!\u0001,\u0017.\\!\tQ\u0005\u0001C\u0003@\u000f\u0001\u0007\u0011\tC\u0003O\u000f\u0001\u0007\u0011\tC\u0003Q\u000f\u0001\u0007!\u000bF\u0002Y;zCQa\u0010\u0005A\u0002\u0005CQA\u0014\u0005A\u0002\u0005#\"\u0001\u00171\t\u000b}J\u0001\u0019A!\u0002\u000f5\fGo\u00195fgR\u0011!k\u0019\u0005\u0006I*\u0001\r!Z\u0001\u0007[>$W\u000f\\3\u0011\u0005\u0019LW\"A4\u000b\u0005!4\u0013\u0001B2pe\u0016L!A[4\u0003\r5{G-\u001e7f\u0003\u0015!\u0003\u000f\\;t)\tAV\u000eC\u0003o\u0017\u0001\u0007\u0001,A\u0003pi\",\'/A\u0006xSRDW\t_2mk\u0012,GC\u0001-r\u0011\u0015yD\u00021\u0001B\u0003-9\u0018\u000e\u001e5J]\u000edW\u000fZ3\u0015\u0005a#\b\"\u0002(\u000e\u0001\u0004\t\u0015\u0001F<ji\"Len\u00197vI\u0016\u0014\u0015\u0010R3gCVdG\u000f\u0006\u0002Yo\")\u0001K\u0004a\u0001%\u0006AAo\\*ue&tw\rF\u0001{!\rY\u0018\u0011A\u0007\u0002y*\u0011QP`\u0001\u0005Y\u0006twMC\u0001\u0000\u0003\u0011Q\u0017M^1\n\u0007\u0005\rAP\u0001\u0004TiJLgnZ\u0001\tG\u0006tW)];bYR\u0019!+!\u0003\t\u000f\u0005-\u0001\u00031\u0001\u0002\u000e\u0005\u0019qN\u00196\u0011\u0007-\ny!C\u0002\u0002\u00121\u00121!\u00118z\u0003\u0019)\u0017/^1mgR\u0019!+a\u0006\t\u000f\u0005-\u0011\u00031\u0001\u0002\u000e\u0005A\u0001.Y:i\u0007>$W\r\u0006\u0002\u0002\u001eA\u00191&a\b\n\u0007\u0005\u0005BFA\u0002J]R\fQ\u0001^;qY\u0016,\"!a\n\u0011\r-\nI#Q!S\u0013\r\tY\u0003\f\u0002\u0007)V\u0004H.Z\u001a\u0002\u001bA\u0014x\u000eZ;diB\u0013XMZ5y+\u0005Q\u0018\u0001\u00049s_\u0012,8\r^!sSRLXCAA\u000f\u00039\u0001(o\u001c3vGR,E.Z7f]R$B!!\u0004\u0002:!9\u00111\b\fA\u0002\u0005u\u0011!\u00018\u0002%A\u0014x\u000eZ;di\u0016cW-\\3oi:\u000bW.\u001a\u000b\u0004u\u0006\u0005\u0003bBA\u001e/\u0001\u0007\u0011QD\u0001\u000f\u001b>$W\u000f\\3NCR\u001c\u0007.\u001a:t!\tQ\u0015d\u0005\u0003\u001aU\u0005%\u0003\u0003BA&\u0003#j!!!\u0014\u000b\u0007\u0005=c0\u0001\u0002j_&\u0019Q(!\u0014\u0015\u0005\u0005\u0015\u0013aA1mYV\t\u0001,\u0001\u0003p]2LHc\u0001-\u0002^!1\u0011q\f\u000fA\u0002\u0015\f1!\\8e)\rA\u00161\r\u0005\u0007\u0003?j\u0002\u0019A%\u0015\u000ba\u000b9\'!\u001d\t\u000f\u0005%d\u00041\u0001\u0002l\u0005\u0019qN]4\u0011\u0007\u0019\fi\'C\u0002\u0002p\u001d\u0014Ab\u0014:hC:L\'0\u0019;j_:Dq!a\u001d\u001f\u0001\u0004\t)(\u0001\u0003oC6,\u0007c\u00014\u0002x%\u0019\u0011\u0011P4\u0003\u00155{G-\u001e7f\u001d\u0006lW-A\u0003baBd\u0017\u0010F\u0002Y\u0003\u007fBQaP\u0010A\u0002\u0005#R\u0001WAB\u0003\u000bCQa\u0010\u0011A\u0002\u0005CQA\u0014\u0011A\u0002\u0005#r\u0001WAE\u0003\u0017\u000bi\tC\u0003@C\u0001\u0007\u0011\tC\u0003OC\u0001\u0007\u0011\tC\u0003QC\u0001\u0007!+\u0001\u0007xe&$XMU3qY\u0006\u001cW\r\u0006\u0002\u0002\u0014B\u001910!&\n\u0007\u0005]EP\u0001\u0004PE*,7\r\u001e
   #13 = Utf8               java/lang/invoke/MethodHandles$Lookup
   #14 = Class              #13           // java/lang/invoke/MethodHandles$Lookup
   #15 = Utf8               java/lang/invoke/MethodHandles
   #16 = Class              #15           // java/lang/invoke/MethodHandles
   #17 = Utf8               Lookup
   #18 = Utf8               exclude
   #19 = Utf8               Lscala/collection/immutable/Set;
   #20 = Utf8               Lscala/collection/immutable/Set<Lcoursier/util/ModuleMatcher;>;
   #21 = Utf8               include
   #22 = Utf8               includeByDefault
   #23 = Utf8               Z
   #24 = Utf8               apply
   #25 = Utf8               (Lscala/collection/immutable/Set;Lscala/collection/immutable/Set;Z)Lcoursier/util/ModuleMatchers;
   #26 = Utf8               (Lscala/collection/immutable/Set<Lcoursier/util/ModuleMatcher;>;Lscala/collection/immutable/Set<Lcoursier/util/ModuleMatcher;>;Z)Lcoursier/util/ModuleMatchers;
   #27 = Utf8               coursier/util/ModuleMatchers$
   #28 = Class              #27           // coursier/util/ModuleMatchers$
   #29 = Utf8               MODULE$
   #30 = Utf8               Lcoursier/util/ModuleMatchers$;
   #31 = NameAndType        #29:#30       // MODULE$:Lcoursier/util/ModuleMatchers$;
   #32 = Fieldref           #28.#31       // coursier/util/ModuleMatchers$.MODULE$:Lcoursier/util/ModuleMatchers$;
   #33 = NameAndType        #24:#25       // apply:(Lscala/collection/immutable/Set;Lscala/collection/immutable/Set;Z)Lcoursier/util/ModuleMatchers;
   #34 = Methodref          #28.#33       // coursier/util/ModuleMatchers$.apply:(Lscala/collection/immutable/Set;Lscala/collection/immutable/Set;Z)Lcoursier/util/ModuleMatchers;
   #35 = Utf8               (Lscala/collection/immutable/Set;Lscala/collection/immutable/Set;)Lcoursier/util/ModuleMatchers;
   #36 = Utf8               (Lscala/collection/immutable/Set<Lcoursier/util/ModuleMatcher;>;Lscala/collection/immutable/Set<Lcoursier/util/ModuleMatcher;>;)Lcoursier/util/ModuleMatchers;
   #37 = NameAndType        #24:#35       // apply:(Lscala/collection/immutable/Set;Lscala/collection/immutable/Set;)Lcoursier/util/ModuleMatchers;
   #38 = Methodref          #28.#37       // coursier/util/ModuleMatchers$.apply:(Lscala/collection/immutable/Set;Lscala/collection/immutable/Set;)Lcoursier/util/ModuleMatchers;
   #39 = Utf8               (Lscala/collection/immutable/Set;)Lcoursier/util/ModuleMatchers;
   #40 = Utf8               (Lscala/collection/immutable/Set<Lcoursier/util/ModuleMatcher;>;)Lcoursier/util/ModuleMatchers;
   #41 = NameAndType        #24:#39       // apply:(Lscala/collection/immutable/Set;)Lcoursier/util/ModuleMatchers;
   #42 = Methodref          #28.#41       // coursier/util/ModuleMatchers$.apply:(Lscala/collection/immutable/Set;)Lcoursier/util/ModuleMatchers;
   #43 = Utf8               only
   #44 = Utf8               (Ljava/lang/String;Ljava/lang/String;)Lcoursier/util/ModuleMatchers;
   #45 = Utf8               org
   #46 = Utf8               name
   #47 = NameAndType        #43:#44       // only:(Ljava/lang/String;Ljava/lang/String;)Lcoursier/util/ModuleMatchers;
   #48 = Methodref          #28.#47       // coursier/util/ModuleMatchers$.only:(Ljava/lang/String;Ljava/lang/String;)Lcoursier/util/ModuleMatchers;
   #49 = Utf8               (Lcoursier/util/ModuleMatcher;)Lcoursier/util/ModuleMatchers;
   #50 = Utf8               mod
   #51 = NameAndType        #43:#49       // only:(Lcoursier/util/ModuleMatcher;)Lcoursier/util/ModuleMatchers;
   #52 = Methodref          #28.#51       // coursier/util/ModuleMatchers$.only:(Lcoursier/util/ModuleMatcher;)Lcoursier/util/ModuleMatchers;
   #53 = Utf8               (Lcoursier/core/Module;)Lcoursier/util/ModuleMatchers;
   #54 = NameAndType        #43:#53       // only:(Lcoursier/core/Module;)Lcoursier/util/ModuleMatchers;
   #55 = Methodref          #28.#54       // coursier/util/ModuleMatchers$.only:(Lcoursier/core/Module;)Lcoursier/util/ModuleMatchers;
   #56 = Utf8               all
   #57 = Utf8               ()Lcoursier/util/ModuleMatchers;
   #58 = NameAndType        #56:#57       // all:()Lcoursier/util/ModuleMatchers;
   #59 = Methodref          #28.#58       // coursier/util/ModuleMatchers$.all:()Lcoursier/util/ModuleMatchers;
   #60 = Utf8               productIterator
   #61 = Utf8               ()Lscala/collection/Iterator;
   #62 = Utf8               ()Lscala/collection/Iterator<Ljava/lang/Object;>;
   #63 = Utf8               productIterator$
   #64 = Utf8               (Lscala/Product;)Lscala/collection/Iterator;
   #65 = NameAndType        #63:#64       // productIterator$:(Lscala/Product;)Lscala/collection/Iterator;
   #66 = InterfaceMethodref #6.#65        // scala/Product.productIterator$:(Lscala/Product;)Lscala/collection/Iterator;
   #67 = Utf8               this
   #68 = Utf8               Lcoursier/util/ModuleMatchers;
   #69 = Utf8               productElementNames
   #70 = Utf8               ()Lscala/collection/Iterator<Ljava/lang/String;>;
   #71 = Utf8               productElementNames$
   #72 = NameAndType        #71:#64       // productElementNames$:(Lscala/Product;)Lscala/collection/Iterator;
   #73 = InterfaceMethodref #6.#72        // scala/Product.productElementNames$:(Lscala/Product;)Lscala/collection/Iterator;
   #74 = Utf8               ()Lscala/collection/immutable/Set;
   #75 = Utf8               ()Lscala/collection/immutable/Set<Lcoursier/util/ModuleMatcher;>;
   #76 = NameAndType        #18:#19       // exclude:Lscala/collection/immutable/Set;
   #77 = Fieldref           #2.#76        // coursier/util/ModuleMatchers.exclude:Lscala/collection/immutable/Set;
   #78 = NameAndType        #21:#19       // include:Lscala/collection/immutable/Set;
   #79 = Fieldref           #2.#78        // coursier/util/ModuleMatchers.include:Lscala/collection/immutable/Set;
   #80 = Utf8               ()Z
   #81 = NameAndType        #22:#23       // includeByDefault:Z
   #82 = Fieldref           #2.#81        // coursier/util/ModuleMatchers.includeByDefault:Z
   #83 = Utf8               matches
   #84 = Utf8               (Lcoursier/core/Module;)Z
   #85 = Utf8               module
   #86 = NameAndType        #22:#80       // includeByDefault:()Z
   #87 = Methodref          #2.#86        // coursier/util/ModuleMatchers.includeByDefault:()Z
   #88 = NameAndType        #18:#74       // exclude:()Lscala/collection/immutable/Set;
   #89 = Methodref          #2.#88        // coursier/util/ModuleMatchers.exclude:()Lscala/collection/immutable/Set;
   #90 = Utf8               (Ljava/lang/Object;)Ljava/lang/Object;
   #91 = MethodType         #90           //  (Ljava/lang/Object;)Ljava/lang/Object;
   #92 = Utf8               $anonfun$matches$1$adapted
   #93 = Utf8               (Lcoursier/core/Module;Lcoursier/util/ModuleMatcher;)Ljava/lang/Object;
   #94 = NameAndType        #92:#93       // $anonfun$matches$1$adapted:(Lcoursier/core/Module;Lcoursier/util/ModuleMatcher;)Ljava/lang/Object;
   #95 = Methodref          #2.#94        // coursier/util/ModuleMatchers.$anonfun$matches$1$adapted:(Lcoursier/core/Module;Lcoursier/util/ModuleMatcher;)Ljava/lang/Object;
   #96 = MethodHandle       6:#95         // REF_invokeStatic coursier/util/ModuleMatchers.$anonfun$matches$1$adapted:(Lcoursier/core/Module;Lcoursier/util/ModuleMatcher;)Ljava/lang/Object;
   #97 = Utf8               (Lcoursier/util/ModuleMatcher;)Ljava/lang/Object;
   #98 = MethodType         #97           //  (Lcoursier/util/ModuleMatcher;)Ljava/lang/Object;
   #99 = Integer            5
  #100 = Integer            1
  #101 = Utf8               java/lang/invoke/LambdaMetafactory
  #102 = Class              #101          // java/lang/invoke/LambdaMetafactory
  #103 = Utf8               altMetafactory
  #104 = Utf8               (Ljava/lang/invoke/MethodHandles$Lookup;Ljava/lang/String;Ljava/lang/invoke/MethodType;[Ljava/lang/Object;)Ljava/lang/invoke/CallSite;
  #105 = NameAndType        #103:#104     // altMetafactory:(Ljava/lang/invoke/MethodHandles$Lookup;Ljava/lang/String;Ljava/lang/invoke/MethodType;[Ljava/lang/Object;)Ljava/lang/invoke/CallSite;
  #106 = Methodref          #102.#105     // java/lang/invoke/LambdaMetafactory.altMetafactory:(Ljava/lang/invoke/MethodHandles$Lookup;Ljava/lang/String;Ljava/lang/invoke/MethodType;[Ljava/lang/Object;)Ljava/lang/invoke/CallSite;
  #107 = MethodHandle       6:#106        // REF_invokeStatic java/lang/invoke/LambdaMetafactory.altMetafactory:(Ljava/lang/invoke/MethodHandles$Lookup;Ljava/lang/String;Ljava/lang/invoke/MethodType;[Ljava/lang/Object;)Ljava/lang/invoke/CallSite;
  #108 = Utf8               (Lcoursier/core/Module;)Lscala/Function1;
  #109 = NameAndType        #24:#108      // apply:(Lcoursier/core/Module;)Lscala/Function1;
  #110 = InvokeDynamic      #0:#109       // #0:apply:(Lcoursier/core/Module;)Lscala/Function1;
  #111 = Utf8               scala/collection/immutable/Set
  #112 = Class              #111          // scala/collection/immutable/Set
  #113 = Utf8               exists
  #114 = Utf8               (Lscala/Function1;)Z
  #115 = NameAndType        #113:#114     // exists:(Lscala/Function1;)Z
  #116 = InterfaceMethodref #112.#115     // scala/collection/immutable/Set.exists:(Lscala/Function1;)Z
  #117 = NameAndType        #21:#74       // include:()Lscala/collection/immutable/Set;
  #118 = Methodref          #2.#117       // coursier/util/ModuleMatchers.include:()Lscala/collection/immutable/Set;
  #119 = Utf8               $anonfun$matches$2$adapted
  #120 = NameAndType        #119:#93      // $anonfun$matches$2$adapted:(Lcoursier/core/Module;Lcoursier/util/ModuleMatcher;)Ljava/lang/Object;
  #121 = Methodref          #2.#120       // coursier/util/ModuleMatchers.$anonfun$matches$2$adapted:(Lcoursier/core/Module;Lcoursier/util/ModuleMatcher;)Ljava/lang/Object;
  #122 = MethodHandle       6:#121        // REF_invokeStatic coursier/util/ModuleMatchers.$anonfun$matches$2$adapted:(Lcoursier/core/Module;Lcoursier/util/ModuleMatcher;)Ljava/lang/Object;
  #123 = InvokeDynamic      #1:#109       // #1:apply:(Lcoursier/core/Module;)Lscala/Function1;
  #124 = Utf8               $anonfun$matches$3$adapted
  #125 = NameAndType        #124:#93      // $anonfun$matches$3$adapted:(Lcoursier/core/Module;Lcoursier/util/ModuleMatcher;)Ljava/lang/Object;
  #126 = Methodref          #2.#125       // coursier/util/ModuleMatchers.$anonfun$matches$3$adapted:(Lcoursier/core/Module;Lcoursier/util/ModuleMatcher;)Ljava/lang/Object;
  #127 = MethodHandle       6:#126        // REF_invokeStatic coursier/util/ModuleMatchers.$anonfun$matches$3$adapted:(Lcoursier/core/Module;Lcoursier/util/ModuleMatcher;)Ljava/lang/Object;
  #128 = InvokeDynamic      #2:#109       // #2:apply:(Lcoursier/core/Module;)Lscala/Function1;
  #129 = Utf8               $anonfun$matches$4$adapted
  #130 = NameAndType        #129:#93      // $anonfun$matches$4$adapted:(Lcoursier/core/Module;Lcoursier/util/ModuleMatcher;)Ljava/lang/Object;
  #131 = Methodref          #2.#130       // coursier/util/ModuleMatchers.$anonfun$matches$4$adapted:(Lcoursier/core/Module;Lcoursier/util/ModuleMatcher;)Ljava/lang/Object;
  #132 = MethodHandle       6:#131        // REF_invokeStatic coursier/util/ModuleMatchers.$anonfun$matches$4$adapted:(Lcoursier/core/Module;Lcoursier/util/ModuleMatcher;)Ljava/lang/Object;
  #133 = InvokeDynamic      #3:#109       // #3:apply:(Lcoursier/core/Module;)Lscala/Function1;
  #134 = Utf8               Lcoursier/core/Module;
  #135 = Utf8               $plus
  #136 = Utf8               (Lcoursier/util/ModuleMatchers;)Lcoursier/util/ModuleMatchers;
  #137 = Utf8               other
  #138 = Utf8               $plus$plus
  #139 = Utf8               (Lscala/collection/IterableOnce;)Lscala/collection/SetOps;
  #140 = NameAndType        #138:#139     // $plus$plus:(Lscala/collection/IterableOnce;)Lscala/collection/SetOps;
  #141 = InterfaceMethodref #112.#140     // scala/collection/immutable/Set.$plus$plus:(Lscala/collection/IterableOnce;)Lscala/collection/SetOps;
  #142 = Utf8               withExclude
  #143 = Utf8               <init>
  #144 = Utf8               (Lscala/collection/immutable/Set;Lscala/collection/immutable/Set;Z)V
  #145 = NameAndType        #143:#144     // "<init>":(Lscala/collection/immutable/Set;Lscala/collection/immutable/Set;Z)V
  #146 = Methodref          #2.#145       // coursier/util/ModuleMatchers."<init>":(Lscala/collection/immutable/Set;Lscala/collection/immutable/Set;Z)V
  #147 = Utf8               withInclude
  #148 = Utf8               withIncludeByDefault
  #149 = Utf8               (Z)Lcoursier/util/ModuleMatchers;
  #150 = Utf8               toString
  #151 = Utf8               ()Ljava/lang/String;
  #152 = Utf8               java/lang/StringBuilder
  #153 = Class              #152          // java/lang/StringBuilder
  #154 = Utf8               ModuleMatchers(
  #155 = String             #154          // ModuleMatchers(
  #156 = Utf8               (Ljava/lang/String;)V
  #157 = NameAndType        #143:#156     // "<init>":(Ljava/lang/String;)V
  #158 = Methodref          #153.#157     // java/lang/StringBuilder."<init>":(Ljava/lang/String;)V
  #159 = Utf8               java/lang/String
  #160 = Class              #159          // java/lang/String
  #161 = Utf8               valueOf
  #162 = Utf8               (Ljava/lang/Object;)Ljava/lang/String;
  #163 = NameAndType        #161:#162     // valueOf:(Ljava/lang/Object;)Ljava/lang/String;
  #164 = Methodref          #160.#163     // java/lang/String.valueOf:(Ljava/lang/Object;)Ljava/lang/String;
  #165 = Utf8               append
  #166 = Utf8               (Ljava/lang/String;)Ljava/lang/StringBuilder;
  #167 = NameAndType        #165:#166     // append:(Ljava/lang/String;)Ljava/lang/StringBuilder;
  #168 = Methodref          #153.#167     // java/lang/StringBuilder.append:(Ljava/lang/String;)Ljava/lang/StringBuilder;
  #169 = Utf8               ,
  #170 = String             #169          // ,
  #171 = Utf8               (Z)Ljava/lang/String;
  #172 = NameAndType        #161:#171     // valueOf:(Z)Ljava/lang/String;
  #173 = Methodref          #160.#172     // java/lang/String.valueOf:(Z)Ljava/lang/String;
  #174 = Utf8               )
  #175 = String             #174          // )
  #176 = NameAndType        #150:#151     // toString:()Ljava/lang/String;
  #177 = Methodref          #153.#176     // java/lang/StringBuilder.toString:()Ljava/lang/String;
  #178 = Utf8               b
  #179 = Utf8               Ljava/lang/StringBuilder;
  #180 = Utf8               canEqual
  #181 = Utf8               (Ljava/lang/Object;)Z
  #182 = Utf8               obj
  #183 = Utf8               Ljava/lang/Object;
  #184 = Utf8               equals
  #185 = NameAndType        #180:#181     // canEqual:(Ljava/lang/Object;)Z
  #186 = Methodref          #2.#185       // coursier/util/ModuleMatchers.canEqual:(Ljava/lang/Object;)Z
  #187 = NameAndType        #184:#181     // equals:(Ljava/lang/Object;)Z
  #188 = Methodref          #4.#187       // java/lang/Object.equals:(Ljava/lang/Object;)Z
  #189 = Utf8               hashCode
  #190 = Utf8               ()I
  #191 = Utf8               ModuleMatchers
  #192 = String             #191          // ModuleMatchers
  #193 = Utf8               scala/runtime/Statics
  #194 = Class              #193          // scala/runtime/Statics
  #195 = Utf8               anyHash
  #196 = Utf8               (Ljava/lang/Object;)I
  #197 = NameAndType        #195:#196     // anyHash:(Ljava/lang/Object;)I
  #198 = Methodref          #194.#197     // scala/runtime/Statics.anyHash:(Ljava/lang/Object;)I
  #199 = Utf8               code
  #200 = Utf8               I
  #201 = Utf8               tuple
  #202 = Utf8               ()Lscala/Tuple3;
  #203 = Utf8               ()Lscala/Tuple3<Lscala/collection/immutable/Set<Lcoursier/util/ModuleMatcher;>;Lscala/collection/immutable/Set<Lcoursier/util/ModuleMatcher;>;Ljava/lang/Object;>;
  #204 = Utf8               scala/Tuple3
  #205 = Class              #204          // scala/Tuple3
  #206 = Utf8               scala/runtime/BoxesRunTime
  #207 = Class              #206          // scala/runtime/BoxesRunTime
  #208 = Utf8               boxToBoolean
  #209 = Utf8               (Z)Ljava/lang/Boolean;
  #210 = NameAndType        #208:#209     // boxToBoolean:(Z)Ljava/lang/Boolean;
  #211 = Methodref          #207.#210     // scala/runtime/BoxesRunTime.boxToBoolean:(Z)Ljava/lang/Boolean;
  #212 = Utf8               (Ljava/lang/Object;Ljava/lang/Object;Ljava/lang/Object;)V
  #213 = NameAndType        #143:#212     // "<init>":(Ljava/lang/Object;Ljava/lang/Object;Ljava/lang/Object;)V
  #214 = Methodref          #205.#213     // scala/Tuple3."<init>":(Ljava/lang/Object;Ljava/lang/Object;Ljava/lang/Object;)V
  #215 = Utf8               productPrefix
  #216 = Utf8               productArity
  #217 = Utf8               productElement
  #218 = Utf8               (I)Ljava/lang/Object;
  #219 = Utf8               n
  #220 = Utf8               java/lang/IndexOutOfBoundsException
  #221 = Class              #220          // java/lang/IndexOutOfBoundsException
  #222 = Utf8               boxToInteger
  #223 = Utf8               (I)Ljava/lang/Integer;
  #224 = NameAndType        #222:#223     // boxToInteger:(I)Ljava/lang/Integer;
  #225 = Methodref          #207.#224     // scala/runtime/BoxesRunTime.boxToInteger:(I)Ljava/lang/Integer;
  #226 = Methodref          #4.#176       // java/lang/Object.toString:()Ljava/lang/String;
  #227 = Methodref          #221.#157     // java/lang/IndexOutOfBoundsException."<init>":(Ljava/lang/String;)V
  #228 = Utf8               productElementName
  #229 = Utf8               (I)Ljava/lang/String;
  #230 = String             #18           // exclude
  #231 = String             #21           // include
  #232 = String             #22           // includeByDefault
  #233 = Utf8               $anonfun$matches$1
  #234 = Utf8               (Lcoursier/core/Module;Lcoursier/util/ModuleMatcher;)Z
  #235 = Utf8               module$1
  #236 = Utf8               x$1
  #237 = Utf8               coursier/util/ModuleMatcher
  #238 = Class              #237          // coursier/util/ModuleMatcher
  #239 = NameAndType        #83:#84       // matches:(Lcoursier/core/Module;)Z
  #240 = Methodref          #238.#239     // coursier/util/ModuleMatcher.matches:(Lcoursier/core/Module;)Z
  #241 = Utf8               Lcoursier/util/ModuleMatcher;
  #242 = Utf8               $anonfun$matches$2
  #243 = Utf8               x$2
  #244 = Utf8               $anonfun$matches$3
  #245 = Utf8               x$3
  #246 = Utf8               $anonfun$matches$4
  #247 = Utf8               x$4
  #248 = Utf8               (Lscala/collection/immutable/Set<Lcoursier/util/ModuleMatcher;>;Lscala/collection/immutable/Set<Lcoursier/util/ModuleMatcher;>;Z)V
  #249 = Utf8               ()V
  #250 = NameAndType        #143:#249     // "<init>":()V
  #251 = Methodref          #4.#250       // java/lang/Object."<init>":()V
  #252 = Utf8               $init$
  #253 = Utf8               (Lscala/Product;)V
  #254 = NameAndType        #252:#253     // $init$:(Lscala/Product;)V
  #255 = InterfaceMethodref #6.#254       // scala/Product.$init$:(Lscala/Product;)V
  #256 = Utf8               (Lscala/collection/immutable/Set;Lscala/collection/immutable/Set;)V
  #257 = Utf8               (Lscala/collection/immutable/Set<Lcoursier/util/ModuleMatcher;>;Lscala/collection/immutable/Set<Lcoursier/util/ModuleMatcher;>;)V
  #258 = Utf8               (Lscala/collection/immutable/Set;)V
  #259 = Utf8               (Lscala/collection/immutable/Set<Lcoursier/util/ModuleMatcher;>;)V
  #260 = Utf8               scala/Predef$
  #261 = Class              #260          // scala/Predef$
  #262 = Utf8               Lscala/Predef$;
  #263 = NameAndType        #29:#262      // MODULE$:Lscala/Predef$;
  #264 = Fieldref           #261.#263     // scala/Predef$.MODULE$:Lscala/Predef$;
  #265 = Utf8               Set
  #266 = Utf8               ()Lscala/collection/immutable/Set$;
  #267 = NameAndType        #265:#266     // Set:()Lscala/collection/immutable/Set$;
  #268 = Methodref          #261.#267     // scala/Predef$.Set:()Lscala/collection/immutable/Set$;
  #269 = Utf8               scala/collection/immutable/Nil$
  #270 = Class              #269          // scala/collection/immutable/Nil$
  #271 = Utf8               Lscala/collection/immutable/Nil$;
  #272 = NameAndType        #29:#271      // MODULE$:Lscala/collection/immutable/Nil$;
  #273 = Fieldref           #270.#272     // scala/collection/immutable/Nil$.MODULE$:Lscala/collection/immutable/Nil$;
  #274 = Utf8               scala/collection/immutable/Set$
  #275 = Class              #274          // scala/collection/immutable/Set$
  #276 = Utf8               (Lscala/collection/immutable/Seq;)Ljava/lang/Object;
  #277 = NameAndType        #24:#276      // apply:(Lscala/collection/immutable/Seq;)Ljava/lang/Object;
  #278 = Methodref          #275.#277     // scala/collection/immutable/Set$.apply:(Lscala/collection/immutable/Seq;)Ljava/lang/Object;
  #279 = NameAndType        #233:#234     // $anonfun$matches$1:(Lcoursier/core/Module;Lcoursier/util/ModuleMatcher;)Z
  #280 = Methodref          #2.#279       // coursier/util/ModuleMatchers.$anonfun$matches$1:(Lcoursier/core/Module;Lcoursier/util/ModuleMatcher;)Z
  #281 = NameAndType        #242:#234     // $anonfun$matches$2:(Lcoursier/core/Module;Lcoursier/util/ModuleMatcher;)Z
  #282 = Methodref          #2.#281       // coursier/util/ModuleMatchers.$anonfun$matches$2:(Lcoursier/core/Module;Lcoursier/util/ModuleMatcher;)Z
  #283 = NameAndType        #244:#234     // $anonfun$matches$3:(Lcoursier/core/Module;Lcoursier/util/ModuleMatcher;)Z
  #284 = Methodref          #2.#283       // coursier/util/ModuleMatchers.$anonfun$matches$3:(Lcoursier/core/Module;Lcoursier/util/ModuleMatcher;)Z
  #285 = NameAndType        #246:#234     // $anonfun$matches$4:(Lcoursier/core/Module;Lcoursier/util/ModuleMatcher;)Z
  #286 = Methodref          #2.#285       // coursier/util/ModuleMatchers.$anonfun$matches$4:(Lcoursier/core/Module;Lcoursier/util/ModuleMatcher;)Z
  #287 = Utf8               $deserializeLambda$
  #288 = Utf8               (Ljava/lang/invoke/SerializedLambda;)Ljava/lang/Object;
  #289 = Utf8               scala/runtime/LambdaDeserialize
  #290 = Class              #289          // scala/runtime/LambdaDeserialize
  #291 = Utf8               bootstrap
  #292 = Utf8               (Ljava/lang/invoke/MethodHandles$Lookup;Ljava/lang/String;Ljava/lang/invoke/MethodType;[Ljava/lang/invoke/MethodHandle;)Ljava/lang/invoke/CallSite;
  #293 = NameAndType        #291:#292     // bootstrap:(Ljava/lang/invoke/MethodHandles$Lookup;Ljava/lang/String;Ljava/lang/invoke/MethodType;[Ljava/lang/invoke/MethodHandle;)Ljava/lang/invoke/CallSite;
  #294 = Methodref          #290.#293     // scala/runtime/LambdaDeserialize.bootstrap:(Ljava/lang/invoke/MethodHandles$Lookup;Ljava/lang/String;Ljava/lang/invoke/MethodType;[Ljava/lang/invoke/MethodHandle;)Ljava/lang/invoke/CallSite;
  #295 = MethodHandle       6:#294        // REF_invokeStatic scala/runtime/LambdaDeserialize.bootstrap:(Ljava/lang/invoke/MethodHandles$Lookup;Ljava/lang/String;Ljava/lang/invoke/MethodType;[Ljava/lang/invoke/MethodHandle;)Ljava/lang/invoke/CallSite;
  #296 = Utf8               lambdaDeserialize
  #297 = NameAndType        #296:#288     // lambdaDeserialize:(Ljava/lang/invoke/SerializedLambda;)Ljava/lang/Object;
  #298 = InvokeDynamic      #4:#297       // #4:lambdaDeserialize:(Ljava/lang/invoke/SerializedLambda;)Ljava/lang/Object;
  #299 = Utf8               Signature
  #300 = Utf8               Code
  #301 = Utf8               MethodParameters
  #302 = Utf8               LineNumberTable
  #303 = Utf8               LocalVariableTable
  #304 = Utf8               StackMapTable
  #305 = Utf8               InnerClasses
  #306 = Utf8               SourceFile
  #307 = Utf8               RuntimeVisibleAnnotations
  #308 = Utf8               BootstrapMethods
  #309 = Utf8               ScalaInlineInfo
  #310 = Utf8               ScalaSig
{
  private final scala.collection.immutable.Set<coursier.util.ModuleMatcher> exclude;
    descriptor: Lscala/collection/immutable/Set;
    flags: (0x0012) ACC_PRIVATE, ACC_FINAL
    Signature: #20                          // Lscala/collection/immutable/Set<Lcoursier/util/ModuleMatcher;>;

  private final scala.collection.immutable.Set<coursier.util.ModuleMatcher> include;
    descriptor: Lscala/collection/immutable/Set;
    flags: (0x0012) ACC_PRIVATE, ACC_FINAL
    Signature: #20                          // Lscala/collection/immutable/Set<Lcoursier/util/ModuleMatcher;>;

  private final boolean includeByDefault;
    descriptor: Z
    flags: (0x0012) ACC_PRIVATE, ACC_FINAL

  public static coursier.util.ModuleMatchers apply(scala.collection.immutable.Set<coursier.util.ModuleMatcher>, scala.collection.immutable.Set<coursier.util.ModuleMatcher>, boolean);
    descriptor: (Lscala/collection/immutable/Set;Lscala/collection/immutable/Set;Z)Lcoursier/util/ModuleMatchers;
    flags: (0x0009) ACC_PUBLIC, ACC_STATIC
    Code:
      stack=4, locals=3, args_size=3
         0: getstatic     #32                 // Field coursier/util/ModuleMatchers$.MODULE$:Lcoursier/util/ModuleMatchers$;
         3: aload_0
         4: aload_1
         5: iload_2
         6: invokevirtual #34                 // Method coursier/util/ModuleMatchers$.apply:(Lscala/collection/immutable/Set;Lscala/collection/immutable/Set;Z)Lcoursier/util/ModuleMatchers;
         9: areturn
    Signature: #26                          // (Lscala/collection/immutable/Set<Lcoursier/util/ModuleMatcher;>;Lscala/collection/immutable/Set<Lcoursier/util/ModuleMatcher;>;Z)Lcoursier/util/ModuleMatchers;
    MethodParameters:
      Name                           Flags
      exclude                        final
      include                        final
      includeByDefault               final

  public static coursier.util.ModuleMatchers apply(scala.collection.immutable.Set<coursier.util.ModuleMatcher>, scala.collection.immutable.Set<coursier.util.ModuleMatcher>);
    descriptor: (Lscala/collection/immutable/Set;Lscala/collection/immutable/Set;)Lcoursier/util/ModuleMatchers;
    flags: (0x0009) ACC_PUBLIC, ACC_STATIC
    Code:
      stack=3, locals=2, args_size=2
         0: getstatic     #32                 // Field coursier/util/ModuleMatchers$.MODULE$:Lcoursier/util/ModuleMatchers$;
         3: aload_0
         4: aload_1
         5: invokevirtual #38                 // Method coursier/util/ModuleMatchers$.apply:(Lscala/collection/immutable/Set;Lscala/collection/immutable/Set;)Lcoursier/util/ModuleMatchers;
         8: areturn
    Signature: #36                          // (Lscala/collection/immutable/Set<Lcoursier/util/ModuleMatcher;>;Lscala/collection/immutable/Set<Lcoursier/util/ModuleMatcher;>;)Lcoursier/util/ModuleMatchers;
    MethodParameters:
      Name                           Flags
      exclude                        final
      include                        final

  public static coursier.util.ModuleMatchers apply(scala.collection.immutable.Set<coursier.util.ModuleMatcher>);
    descriptor: (Lscala/collection/immutable/Set;)Lcoursier/util/ModuleMatchers;
    flags: (0x0009) ACC_PUBLIC, ACC_STATIC
    Code:
      stack=2, locals=1, args_size=1
         0: getstatic     #32                 // Field coursier/util/ModuleMatchers$.MODULE$:Lcoursier/util/ModuleMatchers$;
         3: aload_0
         4: invokevirtual #42                 // Method coursier/util/ModuleMatchers$.apply:(Lscala/collection/immutable/Set;)Lcoursier/util/ModuleMatchers;
         7: areturn
    Signature: #40                          // (Lscala/collection/immutable/Set<Lcoursier/util/ModuleMatcher;>;)Lcoursier/util/ModuleMatchers;
    MethodParameters:
      Name                           Flags
      exclude                        final

  public static coursier.util.ModuleMatchers only(java.lang.String, java.lang.String);
    descriptor: (Ljava/lang/String;Ljava/lang/String;)Lcoursier/util/ModuleMatchers;
    flags: (0x0009) ACC_PUBLIC, ACC_STATIC
    Code:
      stack=3, locals=2, args_size=2
         0: getstatic     #32                 // Field coursier/util/ModuleMatchers$.MODULE$:Lcoursier/util/ModuleMatchers$;
         3: aload_0
         4: aload_1
         5: invokevirtual #48                 // Method coursier/util/ModuleMatchers$.only:(Ljava/lang/String;Ljava/lang/String;)Lcoursier/util/ModuleMatchers;
         8: areturn
    MethodParameters:
      Name                           Flags
      org                            final
      name                           final

  public static coursier.util.ModuleMatchers only(coursier.util.ModuleMatcher);
    descriptor: (Lcoursier/util/ModuleMatcher;)Lcoursier/util/ModuleMatchers;
    flags: (0x0009) ACC_PUBLIC, ACC_STATIC
    Code:
      stack=2, locals=1, args_size=1
         0: getstatic     #32                 // Field coursier/util/ModuleMatchers$.MODULE$:Lcoursier/util/ModuleMatchers$;
         3: aload_0
         4: invokevirtual #52                 // Method coursier/util/ModuleMatchers$.only:(Lcoursier/util/ModuleMatcher;)Lcoursier/util/ModuleMatchers;
         7: areturn
    MethodParameters:
      Name                           Flags
      mod                            final

  public static coursier.util.ModuleMatchers only(coursier.core.Module);
    descriptor: (Lcoursier/core/Module;)Lcoursier/util/ModuleMatchers;
    flags: (0x0009) ACC_PUBLIC, ACC_STATIC
    Code:
      stack=2, locals=1, args_size=1
         0: getstatic     #32                 // Field coursier/util/ModuleMatchers$.MODULE$:Lcoursier/util/ModuleMatchers$;
         3: aload_0
         4: invokevirtual #55                 // Method coursier/util/ModuleMatchers$.only:(Lcoursier/core/Module;)Lcoursier/util/ModuleMatchers;
         7: areturn
    MethodParameters:
      Name                           Flags
      mod                            final

  public static coursier.util.ModuleMatchers all();
    descriptor: ()Lcoursier/util/ModuleMatchers;
    flags: (0x0009) ACC_PUBLIC, ACC_STATIC
    Code:
      stack=1, locals=0, args_size=0
         0: getstatic     #32                 // Field coursier/util/ModuleMatchers$.MODULE$:Lcoursier/util/ModuleMatchers$;
         3: invokevirtual #59                 // Method coursier/util/ModuleMatchers$.all:()Lcoursier/util/ModuleMatchers;
         6: areturn

  public scala.collection.Iterator<java.lang.Object> productIterator();
    descriptor: ()Lscala/collection/Iterator;
    flags: (0x0001) ACC_PUBLIC
    Code:
      stack=1, locals=1, args_size=1
         0: aload_0
         1: invokestatic  #66                 // InterfaceMethod scala/Product.productIterator$:(Lscala/Product;)Lscala/collection/Iterator;
         4: areturn
      LineNumberTable:
        line 6: 0
      LocalVariableTable:
        Start  Length  Slot  Name   Signature
            0       5     0  this   Lcoursier/util/ModuleMatchers;
    Signature: #62                          // ()Lscala/collection/Iterator<Ljava/lang/Object;>;

  public scala.collection.Iterator<java.lang.String> productElementNames();
    descriptor: ()Lscala/collection/Iterator;
    flags: (0x0001) ACC_PUBLIC
    Code:
      stack=1, locals=1, args_size=1
         0: aload_0
         1: invokestatic  #73                 // InterfaceMethod scala/Product.productElementNames$:(Lscala/Product;)Lscala/collection/Iterator;
         4: areturn
      LineNumberTable:
        line 6: 0
      LocalVariableTable:
        Start  Length  Slot  Name   Signature
            0       5     0  this   Lcoursier/util/ModuleMatchers;
    Signature: #70                          // ()Lscala/collection/Iterator<Ljava/lang/String;>;

  public scala.collection.immutable.Set<coursier.util.ModuleMatcher> exclude();
    descriptor: ()Lscala/collection/immutable/Set;
    flags: (0x0001) ACC_PUBLIC
    Code:
      stack=1, locals=1, args_size=1
         0: aload_0
         1: getfield      #77                 // Field exclude:Lscala/collection/immutable/Set;
         4: areturn
      LineNumberTable:
        line 6: 0
      LocalVariableTable:
        Start  Length  Slot  Name   Signature
            0       5     0  this   Lcoursier/util/ModuleMatchers;
    Signature: #75                          // ()Lscala/collection/immutable/Set<Lcoursier/util/ModuleMatcher;>;

  public scala.collection.immutable.Set<coursier.util.ModuleMatcher> include();
    descriptor: ()Lscala/collection/immutable/Set;
    flags: (0x0001) ACC_PUBLIC
    Code:
      stack=1, locals=1, args_size=1
         0: aload_0
         1: getfield      #79                 // Field include:Lscala/collection/immutable/Set;
         4: areturn
      LineNumberTable:
        line 6: 0
      LocalVariableTable:
        Start  Length  Slot  Name   Signature
            0       5     0  this   Lcoursier/util/ModuleMatchers;
    Signature: #75                          // ()Lscala/collection/immutable/Set<Lcoursier/util/ModuleMatcher;>;

  public boolean includeByDefault();
    descriptor: ()Z
    flags: (0x0001) ACC_PUBLIC
    Code:
      stack=1, locals=1, args_size=1
         0: aload_0
         1: getfield      #82                 // Field includeByDefault:Z
         4: ireturn
      LineNumberTable:
        line 6: 0
      LocalVariableTable:
        Start  Length  Slot  Name   Signature
            0       5     0  this   Lcoursier/util/ModuleMatchers;

  public boolean matches(coursier.core.Module);
    descriptor: (Lcoursier/core/Module;)Z
    flags: (0x0001) ACC_PUBLIC
    Code:
      stack=2, locals=2, args_size=2
         0: aload_0
         1: invokevirtual #87                 // Method includeByDefault:()Z
         4: ifeq          51
         7: aload_0
         8: invokevirtual #89                 // Method exclude:()Lscala/collection/immutable/Set;
        11: aload_1
        12: invokedynamic #110,  0            // InvokeDynamic #0:apply:(Lcoursier/core/Module;)Lscala/Function1;
        17: invokeinterface #116,  2          // InterfaceMethod scala/collection/immutable/Set.exists:(Lscala/Function1;)Z
        22: ifeq          43
        25: aload_0
        26: invokevirtual #118                // Method include:()Lscala/collection/immutable/Set;
        29: aload_1
        30: invokedynamic #123,  0            // InvokeDynamic #1:apply:(Lcoursier/core/Module;)Lscala/Function1;
        35: invokeinterface #116,  2          // InterfaceMethod scala/collection/immutable/Set.exists:(Lscala/Function1;)Z
        40: ifeq          47
        43: iconst_1
        44: goto          48
        47: iconst_0
        48: goto          92
        51: aload_0
        52: invokevirtual #118                // Method include:()Lscala/collection/immutable/Set;
        55: aload_1
        56: invokedynamic #128,  0            // InvokeDynamic #2:apply:(Lcoursier/core/Module;)Lscala/Function1;
        61: invokeinterface #116,  2          // InterfaceMethod scala/collection/immutable/Set.exists:(Lscala/Function1;)Z
        66: ifeq          91
        69: aload_0
        70: invokevirtual #89                 // Method exclude:()Lscala/collection/immutable/Set;
        73: aload_1
        74: invokedynamic #133,  0            // InvokeDynamic #3:apply:(Lcoursier/core/Module;)Lscala/Function1;
        79: invokeinterface #116,  2          // InterfaceMethod scala/collection/immutable/Set.exists:(Lscala/Function1;)Z
        84: ifne          91
        87: iconst_1
        88: goto          92
        91: iconst_0
        92: ireturn
      StackMapTable: number_of_entries = 6
        frame_type = 43 /* same */
        frame_type = 3 /* same */
        frame_type = 64 /* same_locals_1_stack_item */
          stack = [ int ]
        frame_type = 2 /* same */
        frame_type = 39 /* same */
        frame_type = 64 /* same_locals_1_stack_item */
          stack = [ int ]
      LineNumberTable:
        line 19: 0
        line 20: 7
        line 22: 51
      LocalVariableTable:
        Start  Length  Slot  Name   Signature
            0      93     0  this   Lcoursier/util/ModuleMatchers;
            0      93     1 module   Lcoursier/core/Module;
    MethodParameters:
      Name                           Flags
      module                         final

  public coursier.util.ModuleMatchers $plus(coursier.util.ModuleMatchers);
    descriptor: (Lcoursier/util/ModuleMatchers;)Lcoursier/util/ModuleMatchers;
    flags: (0x0001) ACC_PUBLIC
    Code:
      stack=4, locals=2, args_size=2
         0: getstatic     #32                 // Field coursier/util/ModuleMatchers$.MODULE$:Lcoursier/util/ModuleMatchers$;
         3: aload_0
         4: invokevirtual #89                 // Method exclude:()Lscala/collection/immutable/Set;
         7: aload_1
         8: invokevirtual #89                 // Method exclude:()Lscala/collection/immutable/Set;
        11: invokeinterface #141,  2          // InterfaceMethod scala/collection/immutable/Set.$plus$plus:(Lscala/collection/IterableOnce;)Lscala/collection/SetOps;
        16: checkcast     #112                // class scala/collection/immutable/Set
        19: aload_0
        20: invokevirtual #118                // Method include:()Lscala/collection/immutable/Set;
        23: aload_1
        24: invokevirtual #118                // Method include:()Lscala/collection/immutable/Set;
        27: invokeinterface #141,  2          // InterfaceMethod scala/collection/immutable/Set.$plus$plus:(Lscala/collection/IterableOnce;)Lscala/collection/SetOps;
        32: checkcast     #112                // class scala/collection/immutable/Set
        35: invokevirtual #38                 // Method coursier/util/ModuleMatchers$.apply:(Lscala/collection/immutable/Set;Lscala/collection/immutable/Set;)Lcoursier/util/ModuleMatchers;
        38: areturn
      LineNumberTable:
        line 25: 0
        line 26: 3
        line 27: 19
      LocalVariableTable:
        Start  Length  Slot  Name   Signature
            0      39     0  this   Lcoursier/util/ModuleMatchers;
            0      39     1 other   Lcoursier/util/ModuleMatchers;
    MethodParameters:
      Name                           Flags
      other                          final

  public coursier.util.ModuleMatchers withExclude(scala.collection.immutable.Set<coursier.util.ModuleMatcher>);
    descriptor: (Lscala/collection/immutable/Set;)Lcoursier/util/ModuleMatchers;
    flags: (0x0001) ACC_PUBLIC
    Code:
      stack=5, locals=2, args_size=2
         0: new           #2                  // class coursier/util/ModuleMatchers
         3: dup
         4: aload_1
         5: aload_0
         6: invokevirtual #118                // Method include:()Lscala/collection/immutable/Set;
         9: aload_0
        10: invokevirtual #87                 // Method includeByDefault:()Z
        13: invokespecial #146                // Method "<init>":(Lscala/collection/immutable/Set;Lscala/collection/immutable/Set;Z)V
        16: areturn
      LineNumberTable:
        line 6: 0
      LocalVariableTable:
        Start  Length  Slot  Name   Signature
            0      17     0  this   Lcoursier/util/ModuleMatchers;
            0      17     1 exclude   Lscala/collection/immutable/Set;
    Signature: #40                          // (Lscala/collection/immutable/Set<Lcoursier/util/ModuleMatcher;>;)Lcoursier/util/ModuleMatchers;
    MethodParameters:
      Name                           Flags
      exclude                        final

  public coursier.util.ModuleMatchers withInclude(scala.collection.immutable.Set<coursier.util.ModuleMatcher>);
    descriptor: (Lscala/collection/immutable/Set;)Lcoursier/util/ModuleMatchers;
    flags: (0x0001) ACC_PUBLIC
    Code:
      stack=5, locals=2, args_size=2
         0: new           #2                  // class coursier/util/ModuleMatchers
         3: dup
         4: aload_0
         5: invokevirtual #89                 // Method exclude:()Lscala/collection/immutable/Set;
         8: aload_1
         9: aload_0
        10: invokevirtual #87                 // Method includeByDefault:()Z
        13: invokespecial #146                // Method "<init>":(Lscala/collection/immutable/Set;Lscala/collection/immutable/Set;Z)V
        16: areturn
      LineNumberTable:
        line 6: 0
      LocalVariableTable:
        Start  Length  Slot  Name   Signature
            0      17     0  this   Lcoursier/util/ModuleMatchers;
            0      17     1 include   Lscala/collection/immutable/Set;
    Signature: #40                          // (Lscala/collection/immutable/Set<Lcoursier/util/ModuleMatcher;>;)Lcoursier/util/ModuleMatchers;
    MethodParameters:
      Name                           Flags
      include                        final

  public coursier.util.ModuleMatchers withIncludeByDefault(boolean);
    descriptor: (Z)Lcoursier/util/ModuleMatchers;
    flags: (0x0001) ACC_PUBLIC
    Code:
      stack=5, locals=2, args_size=2
         0: new           #2                  // class coursier/util/ModuleMatchers
         3: dup
         4: aload_0
         5: invokevirtual #89                 // Method exclude:()Lscala/collection/immutable/Set;
         8: aload_0
         9: invokevirtual #118                // Method include:()Lscala/collection/immutable/Set;
        12: iload_1
        13: invokespecial #146                // Method "<init>":(Lscala/collection/immutable/Set;Lscala/collection/immutable/Set;Z)V
        16: areturn
      LineNumberTable:
        line 6: 0
      LocalVariableTable:
        Start  Length  Slot  Name   Signature
            0      17     0  this   Lcoursier/util/ModuleMatchers;
            0      17     1 includeByDefault   Z
    MethodParameters:
      Name                           Flags
      includeByDefault               final

  public java.lang.String toString();
    descriptor: ()Ljava/lang/String;
    flags: (0x0001) ACC_PUBLIC
    Code:
      stack=3, locals=2, args_size=1
         0: new           #153                // class java/lang/StringBuilder
         3: dup
         4: ldc           #155                // String ModuleMatchers(
         6: invokespecial #158                // Method java/lang/StringBuilder."<init>":(Ljava/lang/String;)V
         9: astore_1
        10: aload_1
        11: aload_0
        12: invokevirtual #89                 // Method exclude:()Lscala/collection/immutable/Set;
        15: invokestatic  #164                // Method java/lang/String.valueOf:(Ljava/lang/Object;)Ljava/lang/String;
        18: invokevirtual #168                // Method java/lang/StringBuilder.append:(Ljava/lang/String;)Ljava/lang/StringBuilder;
        21: pop
        22: aload_1
        23: ldc           #170                // String ,
        25: invokevirtual #168                // Method java/lang/StringBuilder.append:(Ljava/lang/String;)Ljava/lang/StringBuilder;
        28: pop
        29: aload_1
        30: aload_0
        31: invokevirtual #118                // Method include:()Lscala/collection/immutable/Set;
        34: invokestatic  #164                // Method java/lang/String.valueOf:(Ljava/lang/Object;)Ljava/lang/String;
        37: invokevirtual #168                // Method java/lang/StringBuilder.append:(Ljava/lang/String;)Ljava/lang/StringBuilder;
        40: pop
        41: aload_1
        42: ldc           #170                // String ,
        44: invokevirtual #168                // Method java/lang/StringBuilder.append:(Ljava/lang/String;)Ljava/lang/StringBuilder;
        47: pop
        48: aload_1
        49: aload_0
        50: invokevirtual #87                 // Method includeByDefault:()Z
        53: invokestatic  #173                // Method java/lang/String.valueOf:(Z)Ljava/lang/String;
        56: invokevirtual #168                // Method java/lang/StringBuilder.append:(Ljava/lang/String;)Ljava/lang/StringBuilder;
        59: pop
        60: aload_1
        61: ldc           #175                // String )
        63: invokevirtual #168                // Method java/lang/StringBuilder.append:(Ljava/lang/String;)Ljava/lang/StringBuilder;
        66: pop
        67: aload_1
        68: invokevirtual #177                // Method java/lang/StringBuilder.toString:()Ljava/lang/String;
        71: areturn
      LineNumberTable:
        line 6: 0
      LocalVariableTable:
        Start  Length  Slot  Name   Signature
           10      61     1     b   Ljava/lang/StringBuilder;
            0      72     0  this   Lcoursier/util/ModuleMatchers;

  public boolean canEqual(java.lang.Object);
    descriptor: (Ljava/lang/Object;)Z
    flags: (0x0001) ACC_PUBLIC
    Code:
      stack=1, locals=2, args_size=2
         0: aload_1
         1: ifnull        15
         4: aload_1
         5: instanceof    #2                  // class coursier/util/ModuleMatchers
         8: ifeq          15
        11: iconst_1
        12: goto          16
        15: iconst_0
        16: ireturn
      StackMapTable: number_of_entries = 2
        frame_type = 15 /* same */
        frame_type = 64 /* same_locals_1_stack_item */
          stack = [ int ]
      LineNumberTable:
        line 6: 0
      LocalVariableTable:
        Start  Length  Slot  Name   Signature
            0      17     0  this   Lcoursier/util/ModuleMatchers;
            0      17     1   obj   Ljava/lang/Object;
    MethodParameters:
      Name                           Flags
      obj                            final

  public boolean equals(java.lang.Object);
    descriptor: (Ljava/lang/Object;)Z
    flags: (0x0001) ACC_PUBLIC
    Code:
      stack=2, locals=5, args_size=2
         0: aload_0
         1: aload_1
         2: if_acmpeq     100
         5: aload_0
         6: aload_1
         7: invokevirtual #186                // Method canEqual:(Ljava/lang/Object;)Z
        10: ifeq          104
        13: aload_1
        14: checkcast     #2                  // class coursier/util/ModuleMatchers
        17: astore_2
        18: iconst_1
        19: ifeq          96
        22: aload_0
        23: invokevirtual #89                 // Method exclude:()Lscala/collection/immutable/Set;
        26: aload_2
        27: invokevirtual #89                 // Method exclude:()Lscala/collection/immutable/Set;
        30: astore_3
        31: dup
        32: ifnonnull     43
        35: pop
        36: aload_3
        37: ifnull        50
        40: goto          96
        43: aload_3
        44: invokevirtual #188                // Method java/lang/Object.equals:(Ljava/lang/Object;)Z
        47: ifeq          96
        50: aload_0
        51: invokevirtual #118                // Method include:()Lscala/collection/immutable/Set;
        54: aload_2
        55: invokevirtual #118                // Method include:()Lscala/collection/immutable/Set;
        58: astore        4
        60: dup
        61: ifnonnull     73
        64: pop
        65: aload         4
        67: ifnull        81
        70: goto          96
        73: aload         4
        75: invokevirtual #188                // Method java/lang/Object.equals:(Ljava/lang/Object;)Z
        78: ifeq          96
        81: aload_0
        82: invokevirtual #87                 // Method includeByDefault:()Z
        85: aload_2
        86: invokevirtual #87                 // Method includeByDefault:()Z
        89: if_icmpne     96
        92: iconst_1
        93: goto          97
        96: iconst_0
        97: ifeq          104
       100: iconst_1
       101: goto          105
       104: iconst_0
       105: ireturn
      StackMapTable: number_of_entries = 9
        frame_type = 255 /* full_frame */
          offset_delta = 43
          locals = [ class coursier/util/ModuleMatchers, class java/lang/Object, class coursier/util/ModuleMatchers, class scala/collection/immutable/Set ]
          stack = [ class scala/collection/immutable/Set ]
        frame_type = 6 /* same */
        frame_type = 255 /* full_frame */
          offset_delta = 22
          locals = [ class coursier/util/ModuleMatchers, class java/lang/Object, class coursier/util/ModuleMatchers, class scala/collection/immutable/Set, class scala/collection/immutable/Set ]
          stack = [ class scala/collection/immutable/Set ]
        frame_type = 7 /* same */
        frame_type = 249 /* chop */
          offset_delta = 14
        frame_type = 64 /* same_locals_1_stack_item */
          stack = [ int ]
        frame_type = 250 /* chop */
          offset_delta = 2
        frame_type = 3 /* same */
        frame_type = 64 /* same_locals_1_stack_item */
          stack = [ int ]
      LineNumberTable:
        line 6: 0
      LocalVariableTable:
        Start  Length  Slot  Name   Signature
           18      79     2 other   Lcoursier/util/ModuleMatchers;
            0     106     0  this   Lcoursier/util/ModuleMatchers;
            0     106     1   obj   Ljava/lang/Object;
    MethodParameters:
      Name                           Flags
      obj                            final

  public int hashCode();
    descriptor: ()I
    flags: (0x0001) ACC_PUBLIC
    Code:
      stack=2, locals=2, args_size=1
         0: bipush        17
         2: ldc           #192                // String ModuleMatchers
         4: invokestatic  #198                // Method scala/runtime/Statics.anyHash:(Ljava/lang/Object;)I
         7: iadd
         8: istore_1
         9: bipush        37
        11: iload_1
        12: imul
        13: aload_0
        14: invokevirtual #89                 // Method exclude:()Lscala/collection/immutable/Set;
        17: invokestatic  #198                // Method scala/runtime/Statics.anyHash:(Ljava/lang/Object;)I
        20: iadd
        21: istore_1
        22: bipush        37
        24: iload_1
        25: imul
        26: aload_0
        27: invokevirtual #118                // Method include:()Lscala/collection/immutable/Set;
        30: invokestatic  #198                // Method scala/runtime/Statics.anyHash:(Ljava/lang/Object;)I
        33: iadd
        34: istore_1
        35: bipush        37
        37: iload_1
        38: imul
        39: aload_0
        40: invokevirtual #87                 // Method includeByDefault:()Z
        43: ifeq          52
        46: sipush        1231
        49: goto          55
        52: sipush        1237
        55: iadd
        56: istore_1
        57: bipush        37
        59: iload_1
        60: imul
        61: ireturn
      StackMapTable: number_of_entries = 2
        frame_type = 255 /* full_frame */
          offset_delta = 52
          locals = [ class coursier/util/ModuleMatchers, int ]
          stack = [ int ]
        frame_type = 255 /* full_frame */
          offset_delta = 2
          locals = [ class coursier/util/ModuleMatchers, int ]
          stack = [ int, int ]
      LineNumberTable:
        line 6: 0
      LocalVariableTable:
        Start  Length  Slot  Name   Signature
            9      52     1  code   I
            0      62     0  this   Lcoursier/util/ModuleMatchers;

  private scala.Tuple3<scala.collection.immutable.Set<coursier.util.ModuleMatcher>, scala.collection.immutable.Set<coursier.util.ModuleMatcher>, java.lang.Object> tuple();
    descriptor: ()Lscala/Tuple3;
    flags: (0x0002) ACC_PRIVATE
    Code:
      stack=5, locals=1, args_size=1
         0: new           #205                // class scala/Tuple3
         3: dup
         4: aload_0
         5: invokevirtual #89                 // Method exclude:()Lscala/collection/immutable/Set;
         8: aload_0
         9: invokevirtual #118                // Method include:()Lscala/collection/immutable/Set;
        12: aload_0
        13: invokevirtual #87                 // Method includeByDefault:()Z
        16: invokestatic  #211                // Method scala/runtime/BoxesRunTime.boxToBoolean:(Z)Ljava/lang/Boolean;
        19: invokespecial #214                // Method scala/Tuple3."<init>":(Ljava/lang/Object;Ljava/lang/Object;Ljava/lang/Object;)V
        22: areturn
      LineNumberTable:
        line 6: 0
      LocalVariableTable:
        Start  Length  Slot  Name   Signature
            0      23     0  this   Lcoursier/util/ModuleMatchers;
    Signature: #203                         // ()Lscala/Tuple3<Lscala/collection/immutable/Set<Lcoursier/util/ModuleMatcher;>;Lscala/collection/immutable/Set<Lcoursier/util/ModuleMatcher;>;Ljava/lang/Object;>;

  public java.lang.String productPrefix();
    descriptor: ()Ljava/lang/String;
    flags: (0x0001) ACC_PUBLIC
    Code:
      stack=1, locals=1, args_size=1
         0: ldc           #192                // String ModuleMatchers
         2: areturn
      LineNumberTable:
        line 6: 0
      LocalVariableTable:
        Start  Length  Slot  Name   Signature
            0       3     0  this   Lcoursier/util/ModuleMatchers;

  public int productArity();
    descriptor: ()I
    flags: (0x0001) ACC_PUBLIC
    Code:
      stack=1, locals=1, args_size=1
         0: iconst_3
         1: ireturn
      LineNumberTable:
        line 6: 0
      LocalVariableTable:
        Start  Length  Slot  Name   Signature
            0       2     0  this   Lcoursier/util/ModuleMatchers;

  public java.lang.Object productElement(int);
    descriptor: (I)Ljava/lang/Object;
    flags: (0x0001) ACC_PUBLIC
    Code:
      stack=3, locals=3, args_size=2
         0: iload_1
         1: istore_2
         2: iload_2
         3: tableswitch   { // 0 to 2
                       0: 28
                       1: 35
                       2: 42
                 default: 52
            }
        28: aload_0
        29: invokevirtual #89                 // Method exclude:()Lscala/collection/immutable/Set;
        32: goto          67
        35: aload_0
        36: invokevirtual #118                // Method include:()Lscala/collection/immutable/Set;
        39: goto          67
        42: aload_0
        43: invokevirtual #87                 // Method includeByDefault:()Z
        46: invokestatic  #211                // Method scala/runtime/BoxesRunTime.boxToBoolean:(Z)Ljava/lang/Boolean;
        49: goto          67
        52: new           #221                // class java/lang/IndexOutOfBoundsException
        55: dup
        56: iload_2
        57: invokestatic  #225                // Method scala/runtime/BoxesRunTime.boxToInteger:(I)Ljava/lang/Integer;
        60: invokevirtual #226                // Method java/lang/Object.toString:()Ljava/lang/String;
        63: invokespecial #227                // Method java/lang/IndexOutOfBoundsException."<init>":(Ljava/lang/String;)V
        66: athrow
        67: areturn
      StackMapTable: number_of_entries = 5
        frame_type = 252 /* append */
          offset_delta = 28
          locals = [ int ]
        frame_type = 6 /* same */
        frame_type = 6 /* same */
        frame_type = 9 /* same */
        frame_type = 78 /* same_locals_1_stack_item */
          stack = [ class java/lang/Object ]
      LineNumberTable:
        line 6: 0
      LocalVariableTable:
        Start  Length  Slot  Name   Signature
            0      68     0  this   Lcoursier/util/ModuleMatchers;
            0      68     1     n   I
    MethodParameters:
      Name                           Flags
      n                              final

  public java.lang.String productElementName(int);
    descriptor: (I)Ljava/lang/String;
    flags: (0x0001) ACC_PUBLIC
    Code:
      stack=3, locals=3, args_size=2
         0: iload_1
         1: istore_2
         2: iload_2
         3: tableswitch   { // 0 to 2
                       0: 28
                       1: 33
                       2: 38
                 default: 43
            }
        28: ldc           #230                // String exclude
        30: goto          58
        33: ldc           #231                // String include
        35: goto          58
        38: ldc           #232                // String includeByDefault
        40: goto          58
        43: new           #221                // class java/lang/IndexOutOfBoundsException
        46: dup
        47: iload_2
        48: invokestatic  #225                // Method scala/runtime/BoxesRunTime.boxToInteger:(I)Ljava/lang/Integer;
        51: invokevirtual #226                // Method java/lang/Object.toString:()Ljava/lang/String;
        54: invokespecial #227                // Method java/lang/IndexOutOfBoundsException."<init>":(Ljava/lang/String;)V
        57: athrow
        58: areturn
      StackMapTable: number_of_entries = 5
        frame_type = 252 /* append */
          offset_delta = 28
          locals = [ int ]
        frame_type = 4 /* same */
        frame_type = 4 /* same */
        frame_type = 4 /* same */
        frame_type = 78 /* same_locals_1_stack_item */
          stack = [ class java/lang/String ]
      LineNumberTable:
        line 6: 0
      LocalVariableTable:
        Start  Length  Slot  Name   Signature
            0      59     0  this   Lcoursier/util/ModuleMatchers;
            0      59     1     n   I
    MethodParameters:
      Name                           Flags
      n                              final

  public static final boolean $anonfun$matches$1(coursier.core.Module, coursier.util.ModuleMatcher);
    descriptor: (Lcoursier/core/Module;Lcoursier/util/ModuleMatcher;)Z
    flags: (0x1019) ACC_PUBLIC, ACC_STATIC, ACC_FINAL, ACC_SYNTHETIC
    Code:
      stack=2, locals=2, args_size=2
         0: aload_1
         1: aload_0
         2: invokevirtual #240                // Method coursier/util/ModuleMatcher.matches:(Lcoursier/core/Module;)Z
         5: ireturn
      LineNumberTable:
        line 20: 0
      LocalVariableTable:
        Start  Length  Slot  Name   Signature
            0       6     0 module$1   Lcoursier/core/Module;
            0       6     1   x$1   Lcoursier/util/ModuleMatcher;
    MethodParameters:
      Name                           Flags
      module$1                       final
      x$1                            final

  public static final boolean $anonfun$matches$2(coursier.core.Module, coursier.util.ModuleMatcher);
    descriptor: (Lcoursier/core/Module;Lcoursier/util/ModuleMatcher;)Z
    flags: (0x1019) ACC_PUBLIC, ACC_STATIC, ACC_FINAL, ACC_SYNTHETIC
    Code:
      stack=2, locals=2, args_size=2
         0: aload_1
         1: aload_0
         2: invokevirtual #240                // Method coursier/util/ModuleMatcher.matches:(Lcoursier/core/Module;)Z
         5: ireturn
      LineNumberTable:
        line 20: 0
      LocalVariableTable:
        Start  Length  Slot  Name   Signature
            0       6     0 module$1   Lcoursier/core/Module;
            0       6     1   x$2   Lcoursier/util/ModuleMatcher;
    MethodParameters:
      Name                           Flags
      module$1                       final
      x$2                            final

  public static final boolean $anonfun$matches$3(coursier.core.Module, coursier.util.ModuleMatcher);
    descriptor: (Lcoursier/core/Module;Lcoursier/util/ModuleMatcher;)Z
    flags: (0x1019) ACC_PUBLIC, ACC_STATIC, ACC_FINAL, ACC_SYNTHETIC
    Code:
      stack=2, locals=2, args_size=2
         0: aload_1
         1: aload_0
         2: invokevirtual #240                // Method coursier/util/ModuleMatcher.matches:(Lcoursier/core/Module;)Z
         5: ireturn
      LineNumberTable:
        line 22: 0
      LocalVariableTable:
        Start  Length  Slot  Name   Signature
            0       6     0 module$1   Lcoursier/core/Module;
            0       6     1   x$3   Lcoursier/util/ModuleMatcher;
    MethodParameters:
      Name                           Flags
      module$1                       final
      x$3                            final

  public static final boolean $anonfun$matches$4(coursier.core.Module, coursier.util.ModuleMatcher);
    descriptor: (Lcoursier/core/Module;Lcoursier/util/ModuleMatcher;)Z
    flags: (0x1019) ACC_PUBLIC, ACC_STATIC, ACC_FINAL, ACC_SYNTHETIC
    Code:
      stack=2, locals=2, args_size=2
         0: aload_1
         1: aload_0
         2: invokevirtual #240                // Method coursier/util/ModuleMatcher.matches:(Lcoursier/core/Module;)Z
         5: ireturn
      LineNumberTable:
        line 22: 0
      LocalVariableTable:
        Start  Length  Slot  Name   Signature
            0       6     0 module$1   Lcoursier/core/Module;
            0       6     1   x$4   Lcoursier/util/ModuleMatcher;
    MethodParameters:
      Name                           Flags
      module$1                       final
      x$4                            final

  public coursier.util.ModuleMatchers(scala.collection.immutable.Set<coursier.util.ModuleMatcher>, scala.collection.immutable.Set<coursier.util.ModuleMatcher>, boolean);
    descriptor: (Lscala/collection/immutable/Set;Lscala/collection/immutable/Set;Z)V
    flags: (0x0001) ACC_PUBLIC
    Code:
      stack=2, locals=4, args_size=4
         0: aload_0
         1: aload_1
         2: putfield      #77                 // Field exclude:Lscala/collection/immutable/Set;
         5: aload_0
         6: aload_2
         7: putfield      #79                 // Field include:Lscala/collection/immutable/Set;
        10: aload_0
        11: iload_3
        12: putfield      #82                 // Field includeByDefault:Z
        15: aload_0
        16: invokespecial #251                // Method java/lang/Object."<init>":()V
        19: aload_0
        20: invokestatic  #255                // InterfaceMethod scala/Product.$init$:(Lscala/Product;)V
        23: return
      LineNumberTable:
        line 6: 0
        line 32: 15
        line 6: 23
      LocalVariableTable:
        Start  Length  Slot  Name   Signature
            0      24     0  this   Lcoursier/util/ModuleMatchers;
            0      24     1 exclude   Lscala/collection/immutable/Set;
            0      24     2 include   Lscala/collection/immutable/Set;
            0      24     3 includeByDefault   Z
    Signature: #248                         // (Lscala/collection/immutable/Set<Lcoursier/util/ModuleMatcher;>;Lscala/collection/immutable/Set<Lcoursier/util/ModuleMatcher;>;Z)V
    MethodParameters:
      Name                           Flags
      exclude                        final
      include                        final
      includeByDefault               final

  public coursier.util.ModuleMatchers(scala.collection.immutable.Set<coursier.util.ModuleMatcher>, scala.collection.immutable.Set<coursier.util.ModuleMatcher>);
    descriptor: (Lscala/collection/immutable/Set;Lscala/collection/immutable/Set;)V
    flags: (0x0001) ACC_PUBLIC
    Code:
      stack=4, locals=3, args_size=3
         0: aload_0
         1: aload_1
         2: aload_2
         3: iconst_1
         4: invokespecial #146                // Method "<init>":(Lscala/collection/immutable/Set;Lscala/collection/immutable/Set;Z)V
         7: return
      LineNumberTable:
        line 6: 0
        line 10: 3
        line 6: 7
      LocalVariableTable:
        Start  Length  Slot  Name   Signature
            0       8     0  this   Lcoursier/util/ModuleMatchers;
            0       8     1 exclude   Lscala/collection/immutable/Set;
            0       8     2 include   Lscala/collection/immutable/Set;
    Signature: #257                         // (Lscala/collection/immutable/Set<Lcoursier/util/ModuleMatcher;>;Lscala/collection/immutable/Set<Lcoursier/util/ModuleMatcher;>;)V
    MethodParameters:
      Name                           Flags
      exclude                        final
      include                        final

  public coursier.util.ModuleMatchers(scala.collection.immutable.Set<coursier.util.ModuleMatcher>);
    descriptor: (Lscala/collection/immutable/Set;)V
    flags: (0x0001) ACC_PUBLIC
    Code:
      stack=4, locals=2, args_size=2
         0: aload_0
         1: aload_1
         2: getstatic     #264                // Field scala/Predef$.MODULE$:Lscala/Predef$;
         5: invokevirtual #268                // Method scala/Predef$.Set:()Lscala/collection/immutable/Set$;
         8: getstatic     #273                // Field scala/collection/immutable/Nil$.MODULE$:Lscala/collection/immutable/Nil$;
        11: invokevirtual #278                // Method scala/collection/immutable/Set$.apply:(Lscala/collection/immutable/Seq;)Ljava/lang/Object;
        14: checkcast     #112                // class scala/collection/immutable/Set
        17: iconst_1
        18: invokespecial #146                // Method "<init>":(Lscala/collection/immutable/Set;Lscala/collection/immutable/Set;Z)V
        21: return
      LineNumberTable:
        line 6: 0
        line 8: 2
        line 10: 17
        line 6: 21
      LocalVariableTable:
        Start  Length  Slot  Name   Signature
            0      22     0  this   Lcoursier/util/ModuleMatchers;
            0      22     1 exclude   Lscala/collection/immutable/Set;
    Signature: #259                         // (Lscala/collection/immutable/Set<Lcoursier/util/ModuleMatcher;>;)V
    MethodParameters:
      Name                           Flags
      exclude                        final

  public static final java.lang.Object $anonfun$matches$1$adapted(coursier.core.Module, coursier.util.ModuleMatcher);
    descriptor: (Lcoursier/core/Module;Lcoursier/util/ModuleMatcher;)Ljava/lang/Object;
    flags: (0x1019) ACC_PUBLIC, ACC_STATIC, ACC_FINAL, ACC_SYNTHETIC
    Code:
      stack=2, locals=2, args_size=2
         0: aload_0
         1: aload_1
         2: invokestatic  #280                // Method $anonfun$matches$1:(Lcoursier/core/Module;Lcoursier/util/ModuleMatcher;)Z
         5: invokestatic  #211                // Method scala/runtime/BoxesRunTime.boxToBoolean:(Z)Ljava/lang/Boolean;
         8: areturn
      LineNumberTable:
        line 20: 0
      LocalVariableTable:
        Start  Length  Slot  Name   Signature
            0       9     0 module$1   Lcoursier/core/Module;
            0       9     1   x$1   Lcoursier/util/ModuleMatcher;
    MethodParameters:
      Name                           Flags
      module$1                       final
      x$1                            final

  public static final java.lang.Object $anonfun$matches$2$adapted(coursier.core.Module, coursier.util.ModuleMatcher);
    descriptor: (Lcoursier/core/Module;Lcoursier/util/ModuleMatcher;)Ljava/lang/Object;
    flags: (0x1019) ACC_PUBLIC, ACC_STATIC, ACC_FINAL, ACC_SYNTHETIC
    Code:
      stack=2, locals=2, args_size=2
         0: aload_0
         1: aload_1
         2: invokestatic  #282                // Method $anonfun$matches$2:(Lcoursier/core/Module;Lcoursier/util/ModuleMatcher;)Z
         5: invokestatic  #211                // Method scala/runtime/BoxesRunTime.boxToBoolean:(Z)Ljava/lang/Boolean;
         8: areturn
      LineNumberTable:
        line 20: 0
      LocalVariableTable:
        Start  Length  Slot  Name   Signature
            0       9     0 module$1   Lcoursier/core/Module;
            0       9     1   x$2   Lcoursier/util/ModuleMatcher;
    MethodParameters:
      Name                           Flags
      module$1                       final
      x$2                            final

  public static final java.lang.Object $anonfun$matches$3$adapted(coursier.core.Module, coursier.util.ModuleMatcher);
    descriptor: (Lcoursier/core/Module;Lcoursier/util/ModuleMatcher;)Ljava/lang/Object;
    flags: (0x1019) ACC_PUBLIC, ACC_STATIC, ACC_FINAL, ACC_SYNTHETIC
    Code:
      stack=2, locals=2, args_size=2
         0: aload_0
         1: aload_1
         2: invokestatic  #284                // Method $anonfun$matches$3:(Lcoursier/core/Module;Lcoursier/util/ModuleMatcher;)Z
         5: invokestatic  #211                // Method scala/runtime/BoxesRunTime.boxToBoolean:(Z)Ljava/lang/Boolean;
         8: areturn
      LineNumberTable:
        line 22: 0
      LocalVariableTable:
        Start  Length  Slot  Name   Signature
            0       9     0 module$1   Lcoursier/core/Module;
            0       9     1   x$3   Lcoursier/util/ModuleMatcher;
    MethodParameters:
      Name                           Flags
      module$1                       final
      x$3                            final

  public static final java.lang.Object $anonfun$matches$4$adapted(coursier.core.Module, coursier.util.ModuleMatcher);
    descriptor: (Lcoursier/core/Module;Lcoursier/util/ModuleMatcher;)Ljava/lang/Object;
    flags: (0x1019) ACC_PUBLIC, ACC_STATIC, ACC_FINAL, ACC_SYNTHETIC
    Code:
      stack=2, locals=2, args_size=2
         0: aload_0
         1: aload_1
         2: invokestatic  #286                // Method $anonfun$matches$4:(Lcoursier/core/Module;Lcoursier/util/ModuleMatcher;)Z
         5: invokestatic  #211                // Method scala/runtime/BoxesRunTime.boxToBoolean:(Z)Ljava/lang/Boolean;
         8: areturn
      LineNumberTable:
        line 22: 0
      LocalVariableTable:
        Start  Length  Slot  Name   Signature
            0       9     0 module$1   Lcoursier/core/Module;
            0       9     1   x$4   Lcoursier/util/ModuleMatcher;
    MethodParameters:
      Name                           Flags
      module$1                       final
      x$4                            final

  private static java.lang.Object $deserializeLambda$(java.lang.invoke.SerializedLambda);
    descriptor: (Ljava/lang/invoke/SerializedLambda;)Ljava/lang/Object;
    flags: (0x100a) ACC_PRIVATE, ACC_STATIC, ACC_SYNTHETIC
    Code:
      stack=1, locals=1, args_size=1
         0: aload_0
         1: invokedynamic #298,  0            // InvokeDynamic #4:lambdaDeserialize:(Ljava/lang/invoke/SerializedLambda;)Ljava/lang/Object;
         6: areturn
}
InnerClasses:
  public static final #17= #14 of #16;    // Lookup=class java/lang/invoke/MethodHandles$Lookup of class java/lang/invoke/MethodHandles
SourceFile: "ModuleMatchers.scala"
RuntimeVisibleAnnotations:
  0: #10(#11=s#12)
    scala.reflect.ScalaSignature(
      bytes="\u0006\u0005\u0005ee\u0001B\u0012%\u0005%B\u0001b\u0010\u0001\u0003\u0006\u0004%\t\u0001\u0011\u0005\t\u001b\u0002\u0011\t\u0011)A\u0005\u0003\"Aa\n\u0001BC\u0002\u0013\u0005\u0001\t\u0003\u0005P\u0001\t\u0005\t\u0015!\u0003B\u0011!\u0001\u0006A!b\u0001\n\u0003\t\u0006\u0002C+\u0001\u0005\u0003\u0005\u000b\u0011\u0002*\t\u000bY\u0003A\u0011A,\t\u000bY\u0003A\u0011\u0001/\t\u000bY\u0003A\u0011A0\t\u000b\u0005\u0004A\u0011\u00012\t\u000b-\u0004A\u0011\u00017\t\u000b=\u0004A\u0011\u00019\t\u000bI\u0004A\u0011A:\t\u000bU\u0004A\u0011\u0001<\t\u000ba\u0004A\u0011I=\t\u000f\u0005\u0015\u0001\u0001\"\u0011\u0002\b!9\u00111\u0003\u0001\u0005B\u0005U\u0001bBA\r\u0001\u0011\u0005\u00131\u0004\u0005\b\u0003G\u0001A\u0011BA\u0013\u0011\u001d\ti\u0003\u0001C!\u0003_Aq!!\r\u0001\t\u0003\n\u0019\u0004C\u0004\u00026\u0001!\t%a\u000e\t\u000f\u0005u\u0002\u0001\"\u0011\u0002@\u001d9\u00111\t\u0013\t\u0002\u0005\u0015cAB\u0012%\u0011\u0003\t9\u0005\u0003\u0004W3\u0011\u0005\u00111\u000b\u0005\b\u0003+JB\u0011AA,\u0011\u001d\tI&\u0007C\u0001\u00037Bq!!\u0017\u001a\t\u0003\t\t\u0007C\u0004\u0002Ze!\t!!\u001a\t\u000f\u0005m\u0014\u0004\"\u0001\u0002~!9\u00111P\r\u0005\u0002\u0005\u0005\u0005bBA>3\u0011\u0005\u0011q\u0011\u0005\n\u0003\u001fK\u0012\u0011!C\u0005\u0003#\u0013a\"T8ek2,W*\u0019;dQ\u0016\u00148O\u0003\u0002&M\u0005!Q\u000f^5m\u0015\u00059\u0013\u0001C2pkJ\u001c\u0018.\u001a:\u0004\u0001M!\u0001A\u000b\u00194!\tYc&D\u0001-\u0015\u0005i\u0013!B:dC2\f\u0017BA\u0018-\u0005\u0019\te.\u001f*fMB\u00111&M\u0005\u0003e1\u0012q\u0001\u0015:pIV\u001cG\u000f\u0005\u00025y9\u0011QG\u000f\b\u0003mej\u0011a\u000e\u0006\u0003q!\na\u0001\u0010:p_Rt\u0014\"A\u0017\n\u0005mb\u0013a\u00029bG.\fw-Z\u0005\u0003{y\u0012AbU3sS\u0006d\u0017N_1cY\u0016T!a\u000f\u0017\u0002\u000f\u0015D8\r\\;eKV\t\u0011\tE\u0002C\r&s!a\u0011#\u0011\u0005Yb\u0013BA#-\u0003\u0019\u0001&/\u001a3fM&\u0011q\t\u0013\u0002\u0004\'\u0016$(BA#-!\tQ5*D\u0001%\u0013\taEEA\u0007N_\u0012,H.Z\'bi\u000eDWM]\u0001\tKb\u001cG.\u001e3fA\u00059\u0011N\\2mk\u0012,\u0017\u0001C5oG2,H-\u001a\u0011\u0002!%t7\r\\;eK\nKH)\u001a4bk2$X#\u0001*\u0011\u0005-\u001a\u0016B\u0001+-\u0005\u001d\u0011un\u001c7fC:\f\u0011#\u001b8dYV$WMQ=EK\u001a\fW\u000f\u001c;!\u0003\u0019a\u0014N\\5u}Q!\u0001,\u0017.\\!\tQ\u0005\u0001C\u0003@\u000f\u0001\u0007\u0011\tC\u0003O\u000f\u0001\u0007\u0011\tC\u0003Q\u000f\u0001\u0007!\u000bF\u0002Y;zCQa\u0010\u0005A\u0002\u0005CQA\u0014\u0005A\u0002\u0005#\"\u0001\u00171\t\u000b}J\u0001\u0019A!\u0002\u000f5\fGo\u00195fgR\u0011!k\u0019\u0005\u0006I*\u0001\r!Z\u0001\u0007[>$W\u000f\\3\u0011\u0005\u0019LW\"A4\u000b\u0005!4\u0013\u0001B2pe\u0016L!A[4\u0003\r5{G-\u001e7f\u0003\u0015!\u0003\u000f\\;t)\tAV\u000eC\u0003o\u0017\u0001\u0007\u0001,A\u0003pi\",\'/A\u0006xSRDW\t_2mk\u0012,GC\u0001-r\u0011\u0015yD\u00021\u0001B\u0003-9\u0018\u000e\u001e5J]\u000edW\u000fZ3\u0015\u0005a#\b\"\u0002(\u000e\u0001\u0004\t\u0015\u0001F<ji\"Len\u00197vI\u0016\u0014\u0015\u0010R3gCVdG\u000f\u0006\u0002Yo\")\u0001K\u0004a\u0001%\u0006AAo\\*ue&tw\rF\u0001{!\rY\u0018\u0011A\u0007\u0002y*\u0011QP`\u0001\u0005Y\u0006twMC\u0001\u0000\u0003\u0011Q\u0017M^1\n\u0007\u0005\rAP\u0001\u0004TiJLgnZ\u0001\tG\u0006tW)];bYR\u0019!+!\u0003\t\u000f\u0005-\u0001\u00031\u0001\u0002\u000e\u0005\u0019qN\u00196\u0011\u0007-\ny!C\u0002\u0002\u00121\u00121!\u00118z\u0003\u0019)\u0017/^1mgR\u0019!+a\u0006\t\u000f\u0005-\u0011\u00031\u0001\u0002\u000e\u0005A\u0001.Y:i\u0007>$W\r\u0006\u0002\u0002\u001eA\u00191&a\b\n\u0007\u0005\u0005BFA\u0002J]R\fQ\u0001^;qY\u0016,\"!a\n\u0011\r-\nI#Q!S\u0013\r\tY\u0003\f\u0002\u0007)V\u0004H.Z\u001a\u0002\u001bA\u0014x\u000eZ;diB\u0013XMZ5y+\u0005Q\u0018\u0001\u00049s_\u0012,8\r^!sSRLXCAA\u000f\u00039\u0001(o\u001c3vGR,E.Z7f]R$B!!\u0004\u0002:!9\u00111\b\fA\u0002\u0005u\u0011!\u00018\u0002%A\u0014x\u000eZ;di\u0016cW-\\3oi:\u000bW.\u001a\u000b\u0004u\u0006\u0005\u0003bBA\u001e/\u0001\u0007\u0011QD\u0001\u000f\u001b>$W\u000f\\3NCR\u001c\u0007.\u001a:t!\tQ\u0015d\u0005\u0003\u001aU\u0005%\u0003\u0003BA&\u0003#j!!!\u0014\u000b\u0007\u0005=c0\u0001\u0002j_&\u0019Q(!\u0014\u0015\u0005\u0005\u0015\u0013aA1mYV\t\u0001,\u0001\u0003p]2LHc\u0001-\u0002^!1\u0011q\f\u000fA\u0002\u0015\f1!\\8e)\rA\u00161\r\u0005\u0007\u0003?j\u0002\u0019A%\u0015\u000ba\u000b9\'!\u001d\t\u000f\u0005%d\u00041\u0001\u0002l\u0005\u0019qN]4\u0011\u0007\u0019\fi\'C\u0002\u0002p\u001d\u0014Ab\u0014:hC:L\'0\u0019;j_:Dq!a\u001d\u001f\u0001\u0004\t)(\u0001\u0003oC6,\u0007c\u00014\u0002x%\u0019\u0011\u0011P4\u0003\u00155{G-\u001e7f\u001d\u0006lW-A\u0003baBd\u0017\u0010F\u0002Y\u0003\u007fBQaP\u0010A\u0002\u0005#R\u0001WAB\u0003\u000bCQa\u0010\u0011A\u0002\u0005CQA\u0014\u0011A\u0002\u0005#r\u0001WAE\u0003\u0017\u000bi\tC\u0003@C\u0001\u0007\u0011\tC\u0003OC\u0001\u0007\u0011\tC\u0003QC\u0001\u0007!+\u0001\u0007xe&$XMU3qY\u0006\u001cW\r\u0006\u0002\u0002\u0014B\u001910!&\n\u0007\u0005]EP\u0001\u0004PE*,7\r\u001e"
    )
BootstrapMethods:
  0: #107 REF_invokeStatic java/lang/invoke/LambdaMetafactory.altMetafactory:(Ljava/lang/invoke/MethodHandles$Lookup;Ljava/lang/String;Ljava/lang/invoke/MethodType;[Ljava/lang/Object;)Ljava/lang/invoke/CallSite;
    Method arguments:
      #91 (Ljava/lang/Object;)Ljava/lang/Object;
      #96 REF_invokeStatic coursier/util/ModuleMatchers.$anonfun$matches$1$adapted:(Lcoursier/core/Module;Lcoursier/util/ModuleMatcher;)Ljava/lang/Object;
      #98 (Lcoursier/util/ModuleMatcher;)Ljava/lang/Object;
      #99 5
      #100 1
      #98 (Lcoursier/util/ModuleMatcher;)Ljava/lang/Object;
  1: #107 REF_invokeStatic java/lang/invoke/LambdaMetafactory.altMetafactory:(Ljava/lang/invoke/MethodHandles$Lookup;Ljava/lang/String;Ljava/lang/invoke/MethodType;[Ljava/lang/Object;)Ljava/lang/invoke/CallSite;
    Method arguments:
      #91 (Ljava/lang/Object;)Ljava/lang/Object;
      #122 REF_invokeStatic coursier/util/ModuleMatchers.$anonfun$matches$2$adapted:(Lcoursier/core/Module;Lcoursier/util/ModuleMatcher;)Ljava/lang/Object;
      #98 (Lcoursier/util/ModuleMatcher;)Ljava/lang/Object;
      #99 5
      #100 1
      #98 (Lcoursier/util/ModuleMatcher;)Ljava/lang/Object;
  2: #107 REF_invokeStatic java/lang/invoke/LambdaMetafactory.altMetafactory:(Ljava/lang/invoke/MethodHandles$Lookup;Ljava/lang/String;Ljava/lang/invoke/MethodType;[Ljava/lang/Object;)Ljava/lang/invoke/CallSite;
    Method arguments:
      #91 (Ljava/lang/Object;)Ljava/lang/Object;
      #127 REF_invokeStatic coursier/util/ModuleMatchers.$anonfun$matches$3$adapted:(Lcoursier/core/Module;Lcoursier/util/ModuleMatcher;)Ljava/lang/Object;
      #98 (Lcoursier/util/ModuleMatcher;)Ljava/lang/Object;
      #99 5
      #100 1
      #98 (Lcoursier/util/ModuleMatcher;)Ljava/lang/Object;
  3: #107 REF_invokeStatic java/lang/invoke/LambdaMetafactory.altMetafactory:(Ljava/lang/invoke/MethodHandles$Lookup;Ljava/lang/String;Ljava/lang/invoke/MethodType;[Ljava/lang/Object;)Ljava/lang/invoke/CallSite;
    Method arguments:
      #91 (Ljava/lang/Object;)Ljava/lang/Object;
      #132 REF_invokeStatic coursier/util/ModuleMatchers.$anonfun$matches$4$adapted:(Lcoursier/core/Module;Lcoursier/util/ModuleMatcher;)Ljava/lang/Object;
      #98 (Lcoursier/util/ModuleMatcher;)Ljava/lang/Object;
      #99 5
      #100 1
      #98 (Lcoursier/util/ModuleMatcher;)Ljava/lang/Object;
  4: #295 REF_invokeStatic scala/runtime/LambdaDeserialize.bootstrap:(Ljava/lang/invoke/MethodHandles$Lookup;Ljava/lang/String;Ljava/lang/invoke/MethodType;[Ljava/lang/invoke/MethodHandle;)Ljava/lang/invoke/CallSite;
    Method arguments:
      #96 REF_invokeStatic coursier/util/ModuleMatchers.$anonfun$matches$1$adapted:(Lcoursier/core/Module;Lcoursier/util/ModuleMatcher;)Ljava/lang/Object;
      #122 REF_invokeStatic coursier/util/ModuleMatchers.$anonfun$matches$2$adapted:(Lcoursier/core/Module;Lcoursier/util/ModuleMatcher;)Ljava/lang/Object;
      #127 REF_invokeStatic coursier/util/ModuleMatchers.$anonfun$matches$3$adapted:(Lcoursier/core/Module;Lcoursier/util/ModuleMatcher;)Ljava/lang/Object;
      #132 REF_invokeStatic coursier/util/ModuleMatchers.$anonfun$matches$4$adapted:(Lcoursier/core/Module;Lcoursier/util/ModuleMatcher;)Ljava/lang/Object;
  ScalaInlineInfo: length = 0x9A (unknown attribute)
   01 01 00 1E 00 E9 00 EA 01 00 5C 00 5D 01 00 F2
   00 EA 01 00 77 00 5D 01 00 F4 00 EA 01 00 7C 00
   5D 01 00 F6 00 EA 01 00 81 00 5D 01 00 87 00 88
   01 00 8F 01 02 01 00 8F 01 00 01 00 8F 00 90 01
   00 B4 00 B5 01 00 B8 00 B5 01 00 12 00 4A 01 00
   BD 00 BE 01 00 15 00 4A 01 00 16 00 50 01 00 53
   00 54 01 00 D8 00 BE 01 00 D9 00 DA 01 00 E4 00
   E5 01 00 45 00 3D 01 00 3C 00 3D 01 00 D7 00 97
   01 00 96 00 97 01 00 C9 00 CA 01 00 8E 00 27 01
   00 93 00 27 01 00 94 00 95 01
  ScalaSig: length = 0x3 (unknown attribute)
   05 02 00
