Classfile /Users/mw/Projects/slang-braindump/.jar/jar11/assemble/slang-braindump/assemble/content/coursier/util/PlatformTaskCompanion.class
  Last modified May 29, 2022; size 7584 bytes
  SHA-256 checksum a3f6e4f6e7a05c61db34135333c6a7e78c4ad4549b4251b56249408d688c5e1c
  Compiled from "PlatformTaskCompanion.scala"
public abstract class coursier.util.PlatformTaskCompanion
  minor version: 0
  major version: 52
  flags: (0x0421) ACC_PUBLIC, ACC_SUPER, ACC_ABSTRACT
  this_class: #2                          // coursier/util/PlatformTaskCompanion
  super_class: #4                         // java/lang/Object
  interfaces: 0, fields: 1, methods: 12, attributes: 6
Constant pool:
    #1 = Utf8               coursier/util/PlatformTaskCompanion
    #2 = Class              #1            // coursier/util/PlatformTaskCompanion
    #3 = Utf8               java/lang/Object
    #4 = Class              #3            // java/lang/Object
    #5 = Utf8               PlatformTaskCompanion.scala
    #6 = Utf8               Lscala/reflect/ScalaSignature;
    #7 = Utf8               bytes
    #8 = Utf8               \u0006\u0005]4Q\u0001D\u0007\u0002\u0002IAQ!\u0007\u0001\u0005\u0002iAQ!\b\u0001\u0005\u0002yAQa\u0010\u0001\u0005\u0002\u0001Cq!\u0015\u0001C\u0002\u0013\r!\u000b\u0003\u0004X\u0001\u0001\u0006Ia\u0015\u0004\u00051\u0002\t\u0011\f\u0003\u0005\\\r\t\u0015\r\u0011\"\u0003]\u0011!\tgA!A!\u0002\u0013i\u0006\"B\r\u0007\t\u0003\u0011\u0007\"\u00024\u0007\t\u00039\u0007bB8\u0001\u0003\u0003%\u0019\u0001\u001d\u0002\u0016!2\fGOZ8s[R\u000b7o[\"p[B\fg.[8o\u0015\tqq\"\u0001\u0003vi&d\'\"\u0001\t\u0002\u0011\r|WO]:jKJ\u001c\u0001a\u0005\u0002\u0001\'A\u0011AcF\u0007\u0002+)\ta#A\u0003tG\u0006d\u0017-\u0003\u0002\u0019+\t1\u0011I\\=SK\u001a\fa\u0001P5oSRtD#A\u000e\u0011\u0005q\u0001Q\"A\u0007\u0002\u0011M\u001c\u0007.\u001a3vY\u0016,\"a\b\u0014\u0015\u0005\u0001\"DCA\u00110!\ra\"\u0005J\u0005\u0003G5\u0011A\u0001V1tWB\u0011QE\n\u0007\u0001\t\u00159#A1\u0001)\u0005\u0005\t\u0015CA\u0015-!\t!\"&\u0003\u0002,+\t9aj\u001c;iS:<\u0007C\u0001\u000b.\u0013\tqSCA\u0002B]fDa\u0001\r\u0002\u0005\u0002\u0004\t\u0014!\u00014\u0011\u0007Q\u0011D%\u0003\u00024+\tAAHY=oC6,g\bC\u00036\u0005\u0001\u0007a\'\u0001\u0003q_>d\u0007CA\u001c>\u001b\u0005A$BA\u001d;\u0003)\u0019wN\\2veJ,g\u000e\u001e\u0006\u0003\u001dmR\u0011\u0001P\u0001\u0005U\u00064\u0018-\u0003\u0002?q\tyQ\t_3dkR|\'oU3sm&\u001cW-A\u0007d_6\u0004H.\u001a;f\u0003\u001a$XM\u001d\u000b\u0004\u0003\u0016K\u0005c\u0001\u000f#\u0005B\u0011AcQ\u0005\u0003\tV\u0011A!\u00168ji\")Qg\u0001a\u0001\rB\u0011qgR\u0005\u0003\u0011b\u0012\u0001dU2iK\u0012,H.\u001a3Fq\u0016\u001cW\u000f^8s\'\u0016\u0014h/[2f\u0011\u0015Q5\u00011\u0001L\u0003!!WO]1uS>t\u0007C\u0001\'P\u001b\u0005i%B\u0001&O\u0015\tIT#\u0003\u0002Q\u001b\nqa)\u001b8ji\u0016$UO]1uS>t\u0017\u0001B:z]\u000e,\u0012a\u0015\t\u00049Q3\u0016BA+\u000e\u0005\u0011\u0019\u0016P\\2\u0011\u0005q\u0011\u0013!B:z]\u000e\u0004#a\u0004)mCR4wN]7UCN\\w\n]:\u0016\u0005i{6C\u0001\u0004\u0014\u0003\u0011!\u0018m]6\u0016\u0003u\u00032\u0001\b\u0012_!\t)s\fB\u0003a\r\t\u0007\u0001FA\u0001U\u0003\u0015!\u0018m]6!)\t\u0019W\rE\u0002e\ryk\u0011\u0001\u0001\u0005\u00067&\u0001\r!X\u0001\nk:\u001c\u0018MZ3Sk:$\u0012\u0001\u001b\u000b\u0003=&DQA\u001b\u0006A\u0004-\f!!Z2\u0011\u00051lW\"\u0001(\n\u00059t%\u0001E#yK\u000e,H/[8o\u0007>tG/\u001a=u\u0003=\u0001F.\u0019;g_JlG+Y:l\u001fB\u001cXCA9u)\t\u0011X\u000fE\u0002e\rM\u0004\"!\n;\u0005\u000b\u0001\\!\u0019\u0001\u0015\t\u000bm[\u0001\u0019\u0001<\u0011\u0007q\u00113\u000f
    #9 = Utf8               coursier/util/PlatformTaskCompanion$$anon$1
   #10 = Class              #9            // coursier/util/PlatformTaskCompanion$$anon$1
   #11 = Utf8               coursier/util/PlatformTaskCompanion$$anon$2
   #12 = Class              #11           // coursier/util/PlatformTaskCompanion$$anon$2
   #13 = Utf8               coursier/util/PlatformTaskCompanion$PlatformTaskOps
   #14 = Class              #13           // coursier/util/PlatformTaskCompanion$PlatformTaskOps
   #15 = Utf8               PlatformTaskOps
   #16 = Utf8               java/lang/invoke/MethodHandles$Lookup
   #17 = Class              #16           // java/lang/invoke/MethodHandles$Lookup
   #18 = Utf8               java/lang/invoke/MethodHandles
   #19 = Class              #18           // java/lang/invoke/MethodHandles
   #20 = Utf8               Lookup
   #21 = Utf8               sync
   #22 = Utf8               Lcoursier/util/Sync;
   #23 = Utf8               Lcoursier/util/Sync<Lcoursier/util/Task;>;
   #24 = Utf8               schedule
   #25 = Utf8               (Ljava/util/concurrent/ExecutorService;Lscala/Function0;)Lscala/Function1;
   #26 = Utf8               <A:Ljava/lang/Object;>(Ljava/util/concurrent/ExecutorService;Lscala/Function0<TA;>;)Lscala/Function1<Lscala/concurrent/ExecutionContext;Lscala/concurrent/Future<TA;>;>;
   #27 = Utf8               pool
   #28 = Utf8               f
   #29 = Utf8               scala/concurrent/ExecutionContextExecutorService
   #30 = Class              #29           // scala/concurrent/ExecutionContextExecutorService
   #31 = Utf8               java/util/concurrent/ExecutorService
   #32 = Class              #31           // java/util/concurrent/ExecutorService
   #33 = Utf8               scala/concurrent/ExecutionContext$
   #34 = Class              #33           // scala/concurrent/ExecutionContext$
   #35 = Utf8               MODULE$
   #36 = Utf8               Lscala/concurrent/ExecutionContext$;
   #37 = NameAndType        #35:#36       // MODULE$:Lscala/concurrent/ExecutionContext$;
   #38 = Fieldref           #34.#37       // scala/concurrent/ExecutionContext$.MODULE$:Lscala/concurrent/ExecutionContext$;
   #39 = Utf8               fromExecutorService
   #40 = Utf8               (Ljava/util/concurrent/ExecutorService;)Lscala/concurrent/ExecutionContextExecutorService;
   #41 = NameAndType        #39:#40       // fromExecutorService:(Ljava/util/concurrent/ExecutorService;)Lscala/concurrent/ExecutionContextExecutorService;
   #42 = Methodref          #34.#41       // scala/concurrent/ExecutionContext$.fromExecutorService:(Ljava/util/concurrent/ExecutorService;)Lscala/concurrent/ExecutionContextExecutorService;
   #43 = Utf8               scala/Function0
   #44 = Class              #43           // scala/Function0
   #45 = Utf8               (Ljava/lang/Object;)Ljava/lang/Object;
   #46 = MethodType         #45           //  (Ljava/lang/Object;)Ljava/lang/Object;
   #47 = Utf8               $anonfun$schedule$1
   #48 = Utf8               (Lscala/Function0;Lscala/concurrent/ExecutionContextExecutorService;Lscala/concurrent/ExecutionContext;)Lscala/concurrent/Future;
   #49 = NameAndType        #47:#48       // $anonfun$schedule$1:(Lscala/Function0;Lscala/concurrent/ExecutionContextExecutorService;Lscala/concurrent/ExecutionContext;)Lscala/concurrent/Future;
   #50 = Methodref          #2.#49        // coursier/util/PlatformTaskCompanion.$anonfun$schedule$1:(Lscala/Function0;Lscala/concurrent/ExecutionContextExecutorService;Lscala/concurrent/ExecutionContext;)Lscala/concurrent/Future;
   #51 = MethodHandle       6:#50         // REF_invokeStatic coursier/util/PlatformTaskCompanion.$anonfun$schedule$1:(Lscala/Function0;Lscala/concurrent/ExecutionContextExecutorService;Lscala/concurrent/ExecutionContext;)Lscala/concurrent/Future;
   #52 = Utf8               (Lscala/concurrent/ExecutionContext;)Lscala/concurrent/Future;
   #53 = MethodType         #52           //  (Lscala/concurrent/ExecutionContext;)Lscala/concurrent/Future;
   #54 = Integer            5
   #55 = Integer            1
   #56 = Utf8               java/lang/invoke/LambdaMetafactory
   #57 = Class              #56           // java/lang/invoke/LambdaMetafactory
   #58 = Utf8               altMetafactory
   #59 = Utf8               (Ljava/lang/invoke/MethodHandles$Lookup;Ljava/lang/String;Ljava/lang/invoke/MethodType;[Ljava/lang/Object;)Ljava/lang/invoke/CallSite;
   #60 = NameAndType        #58:#59       // altMetafactory:(Ljava/lang/invoke/MethodHandles$Lookup;Ljava/lang/String;Ljava/lang/invoke/MethodType;[Ljava/lang/Object;)Ljava/lang/invoke/CallSite;
   #61 = Methodref          #57.#60       // java/lang/invoke/LambdaMetafactory.altMetafactory:(Ljava/lang/invoke/MethodHandles$Lookup;Ljava/lang/String;Ljava/lang/invoke/MethodType;[Ljava/lang/Object;)Ljava/lang/invoke/CallSite;
   #62 = MethodHandle       6:#61         // REF_invokeStatic java/lang/invoke/LambdaMetafactory.altMetafactory:(Ljava/lang/invoke/MethodHandles$Lookup;Ljava/lang/String;Ljava/lang/invoke/MethodType;[Ljava/lang/Object;)Ljava/lang/invoke/CallSite;
   #63 = Utf8               apply
   #64 = Utf8               (Lscala/Function0;Lscala/concurrent/ExecutionContextExecutorService;)Lscala/Function1;
   #65 = NameAndType        #63:#64       // apply:(Lscala/Function0;Lscala/concurrent/ExecutionContextExecutorService;)Lscala/Function1;
   #66 = InvokeDynamic      #0:#65        // #0:apply:(Lscala/Function0;Lscala/concurrent/ExecutionContextExecutorService;)Lscala/Function1;
   #67 = Utf8               ec0
   #68 = Utf8               Lscala/concurrent/ExecutionContextExecutorService;
   #69 = Utf8               this
   #70 = Utf8               Lcoursier/util/PlatformTaskCompanion;
   #71 = Utf8               Ljava/util/concurrent/ExecutorService;
   #72 = Utf8               Lscala/Function0;
   #73 = Utf8               completeAfter
   #74 = Utf8               (Ljava/util/concurrent/ScheduledExecutorService;Lscala/concurrent/duration/FiniteDuration;)Lscala/Function1;
   #75 = Utf8               (Ljava/util/concurrent/ScheduledExecutorService;Lscala/concurrent/duration/FiniteDuration;)Lscala/Function1<Lscala/concurrent/ExecutionContext;Lscala/concurrent/Future<Lscala/runtime/BoxedUnit;>;>;
   #76 = Utf8               duration
   #77 = Utf8               coursier/util/Task$
   #78 = Class              #77           // coursier/util/Task$
   #79 = Utf8               Lcoursier/util/Task$;
   #80 = NameAndType        #35:#79       // MODULE$:Lcoursier/util/Task$;
   #81 = Fieldref           #78.#80       // coursier/util/Task$.MODULE$:Lcoursier/util/Task$;
   #82 = Utf8               ()Ljava/lang/Object;
   #83 = MethodType         #82           //  ()Ljava/lang/Object;
   #84 = Utf8               $anonfun$completeAfter$1$adapted
   #85 = Utf8               (Ljava/util/concurrent/ScheduledExecutorService;Lscala/concurrent/duration/FiniteDuration;)Ljava/lang/Object;
   #86 = NameAndType        #84:#85       // $anonfun$completeAfter$1$adapted:(Ljava/util/concurrent/ScheduledExecutorService;Lscala/concurrent/duration/FiniteDuration;)Ljava/lang/Object;
   #87 = Methodref          #2.#86        // coursier/util/PlatformTaskCompanion.$anonfun$completeAfter$1$adapted:(Ljava/util/concurrent/ScheduledExecutorService;Lscala/concurrent/duration/FiniteDuration;)Ljava/lang/Object;
   #88 = MethodHandle       6:#87         // REF_invokeStatic coursier/util/PlatformTaskCompanion.$anonfun$completeAfter$1$adapted:(Ljava/util/concurrent/ScheduledExecutorService;Lscala/concurrent/duration/FiniteDuration;)Ljava/lang/Object;
   #89 = Utf8               (Ljava/util/concurrent/ScheduledExecutorService;Lscala/concurrent/duration/FiniteDuration;)Lscala/Function0;
   #90 = NameAndType        #63:#89       // apply:(Ljava/util/concurrent/ScheduledExecutorService;Lscala/concurrent/duration/FiniteDuration;)Lscala/Function0;
   #91 = InvokeDynamic      #1:#90        // #1:apply:(Ljava/util/concurrent/ScheduledExecutorService;Lscala/concurrent/duration/FiniteDuration;)Lscala/Function0;
   #92 = Utf8               delay
   #93 = Utf8               (Lscala/Function0;)Lscala/Function1;
   #94 = NameAndType        #92:#93       // delay:(Lscala/Function0;)Lscala/Function1;
   #95 = Methodref          #78.#94       // coursier/util/Task$.delay:(Lscala/Function0;)Lscala/Function1;
   #96 = Utf8               $anonfun$completeAfter$3$adapted
   #97 = NameAndType        #96:#45       // $anonfun$completeAfter$3$adapted:(Ljava/lang/Object;)Ljava/lang/Object;
   #98 = Methodref          #2.#97        // coursier/util/PlatformTaskCompanion.$anonfun$completeAfter$3$adapted:(Ljava/lang/Object;)Ljava/lang/Object;
   #99 = MethodHandle       6:#98         // REF_invokeStatic coursier/util/PlatformTaskCompanion.$anonfun$completeAfter$3$adapted:(Ljava/lang/Object;)Ljava/lang/Object;
  #100 = Utf8               ()Lscala/Function1;
  #101 = NameAndType        #63:#100      // apply:()Lscala/Function1;
  #102 = InvokeDynamic      #2:#101       // #2:apply:()Lscala/Function1;
  #103 = Utf8               flatMap$extension
  #104 = Utf8               (Lscala/Function1;Lscala/Function1;)Lscala/Function1;
  #105 = NameAndType        #103:#104     // flatMap$extension:(Lscala/Function1;Lscala/Function1;)Lscala/Function1;
  #106 = Methodref          #78.#105      // coursier/util/Task$.flatMap$extension:(Lscala/Function1;Lscala/Function1;)Lscala/Function1;
  #107 = Utf8               Ljava/util/concurrent/ScheduledExecutorService;
  #108 = Utf8               Lscala/concurrent/duration/FiniteDuration;
  #109 = Utf8               ()Lcoursier/util/Sync;
  #110 = Utf8               ()Lcoursier/util/Sync<Lcoursier/util/Task;>;
  #111 = NameAndType        #21:#22       // sync:Lcoursier/util/Sync;
  #112 = Fieldref           #2.#111       // coursier/util/PlatformTaskCompanion.sync:Lcoursier/util/Sync;
  #113 = Utf8               (Lscala/Function1;)Lcoursier/util/PlatformTaskCompanion$PlatformTaskOps;
  #114 = Utf8               <T:Ljava/lang/Object;>(Lscala/Function1<Lscala/concurrent/ExecutionContext;Lscala/concurrent/Future<TT;>;>;)Lcoursier/util/PlatformTaskCompanion$PlatformTaskOps<TT;>;
  #115 = Utf8               task
  #116 = Utf8               <init>
  #117 = Utf8               (Lcoursier/util/PlatformTaskCompanion;Lscala/Function1;)V
  #118 = NameAndType        #116:#117     // "<init>":(Lcoursier/util/PlatformTaskCompanion;Lscala/Function1;)V
  #119 = Methodref          #14.#118      // coursier/util/PlatformTaskCompanion$PlatformTaskOps."<init>":(Lcoursier/util/PlatformTaskCompanion;Lscala/Function1;)V
  #120 = Utf8               Lscala/Function1;
  #121 = Utf8               f$1
  #122 = Utf8               ec0$1
  #123 = Utf8               x$1
  #124 = Utf8               scala/concurrent/Future$
  #125 = Class              #124          // scala/concurrent/Future$
  #126 = Utf8               Lscala/concurrent/Future$;
  #127 = NameAndType        #35:#126      // MODULE$:Lscala/concurrent/Future$;
  #128 = Fieldref           #125.#127     // scala/concurrent/Future$.MODULE$:Lscala/concurrent/Future$;
  #129 = Utf8               (Lscala/Function0;Lscala/concurrent/ExecutionContext;)Lscala/concurrent/Future;
  #130 = NameAndType        #63:#129      // apply:(Lscala/Function0;Lscala/concurrent/ExecutionContext;)Lscala/concurrent/Future;
  #131 = Methodref          #125.#130     // scala/concurrent/Future$.apply:(Lscala/Function0;Lscala/concurrent/ExecutionContext;)Lscala/concurrent/Future;
  #132 = Utf8               Lscala/concurrent/ExecutionContext;
  #133 = Utf8               $anonfun$completeAfter$2
  #134 = Utf8               (Lscala/concurrent/Promise;Lscala/concurrent/ExecutionContext;)Lscala/concurrent/Future;
  #135 = Utf8               p$1
  #136 = Utf8               x$2
  #137 = Utf8               scala/concurrent/Promise
  #138 = Class              #137          // scala/concurrent/Promise
  #139 = Utf8               future
  #140 = Utf8               ()Lscala/concurrent/Future;
  #141 = NameAndType        #139:#140     // future:()Lscala/concurrent/Future;
  #142 = InterfaceMethodref #138.#141     // scala/concurrent/Promise.future:()Lscala/concurrent/Future;
  #143 = Utf8               Lscala/concurrent/Promise;
  #144 = Utf8               $anonfun$completeAfter$1
  #145 = Utf8               pool$1
  #146 = Utf8               duration$1
  #147 = Utf8               scala/concurrent/Promise$
  #148 = Class              #147          // scala/concurrent/Promise$
  #149 = Utf8               Lscala/concurrent/Promise$;
  #150 = NameAndType        #35:#149      // MODULE$:Lscala/concurrent/Promise$;
  #151 = Fieldref           #148.#150     // scala/concurrent/Promise$.MODULE$:Lscala/concurrent/Promise$;
  #152 = Utf8               ()Lscala/concurrent/Promise;
  #153 = NameAndType        #63:#152      // apply:()Lscala/concurrent/Promise;
  #154 = Methodref          #148.#153     // scala/concurrent/Promise$.apply:()Lscala/concurrent/Promise;
  #155 = Utf8               (Lcoursier/util/PlatformTaskCompanion;Lscala/concurrent/Promise;)V
  #156 = NameAndType        #116:#155     // "<init>":(Lcoursier/util/PlatformTaskCompanion;Lscala/concurrent/Promise;)V
  #157 = Methodref          #10.#156      // coursier/util/PlatformTaskCompanion$$anon$1."<init>":(Lcoursier/util/PlatformTaskCompanion;Lscala/concurrent/Promise;)V
  #158 = Utf8               scala/concurrent/duration/FiniteDuration
  #159 = Class              #158          // scala/concurrent/duration/FiniteDuration
  #160 = Utf8               length
  #161 = Utf8               ()J
  #162 = NameAndType        #160:#161     // length:()J
  #163 = Methodref          #159.#162     // scala/concurrent/duration/FiniteDuration.length:()J
  #164 = Utf8               unit
  #165 = Utf8               ()Ljava/util/concurrent/TimeUnit;
  #166 = NameAndType        #164:#165     // unit:()Ljava/util/concurrent/TimeUnit;
  #167 = Methodref          #159.#166     // scala/concurrent/duration/FiniteDuration.unit:()Ljava/util/concurrent/TimeUnit;
  #168 = Utf8               java/util/concurrent/ScheduledExecutorService
  #169 = Class              #168          // java/util/concurrent/ScheduledExecutorService
  #170 = Utf8               (Ljava/lang/Runnable;JLjava/util/concurrent/TimeUnit;)Ljava/util/concurrent/ScheduledFuture;
  #171 = NameAndType        #24:#170      // schedule:(Ljava/lang/Runnable;JLjava/util/concurrent/TimeUnit;)Ljava/util/concurrent/ScheduledFuture;
  #172 = InterfaceMethodref #169.#171     // java/util/concurrent/ScheduledExecutorService.schedule:(Ljava/lang/Runnable;JLjava/util/concurrent/TimeUnit;)Ljava/util/concurrent/ScheduledFuture;
  #173 = NameAndType        #133:#134     // $anonfun$completeAfter$2:(Lscala/concurrent/Promise;Lscala/concurrent/ExecutionContext;)Lscala/concurrent/Future;
  #174 = Methodref          #2.#173       // coursier/util/PlatformTaskCompanion.$anonfun$completeAfter$2:(Lscala/concurrent/Promise;Lscala/concurrent/ExecutionContext;)Lscala/concurrent/Future;
  #175 = MethodHandle       6:#174        // REF_invokeStatic coursier/util/PlatformTaskCompanion.$anonfun$completeAfter$2:(Lscala/concurrent/Promise;Lscala/concurrent/ExecutionContext;)Lscala/concurrent/Future;
  #176 = Utf8               (Lscala/concurrent/Promise;)Lscala/Function1;
  #177 = NameAndType        #63:#176      // apply:(Lscala/concurrent/Promise;)Lscala/Function1;
  #178 = InvokeDynamic      #3:#177       // #3:apply:(Lscala/concurrent/Promise;)Lscala/Function1;
  #179 = Utf8               p
  #180 = Utf8               runnable
  #181 = Utf8               Ljava/lang/Runnable;
  #182 = Utf8               $anonfun$completeAfter$3
  #183 = Utf8               (Lscala/Function1;)Lscala/Function1;
  #184 = Utf8               x
  #185 = Utf8               scala/Predef$
  #186 = Class              #185          // scala/Predef$
  #187 = Utf8               Lscala/Predef$;
  #188 = NameAndType        #35:#187      // MODULE$:Lscala/Predef$;
  #189 = Fieldref           #186.#188     // scala/Predef$.MODULE$:Lscala/Predef$;
  #190 = Utf8               coursier/util/Task
  #191 = Class              #190          // coursier/util/Task
  #192 = Utf8               (Lscala/Function1;)V
  #193 = NameAndType        #116:#192     // "<init>":(Lscala/Function1;)V
  #194 = Methodref          #191.#193     // coursier/util/Task."<init>":(Lscala/Function1;)V
  #195 = Utf8               identity
  #196 = NameAndType        #195:#45      // identity:(Ljava/lang/Object;)Ljava/lang/Object;
  #197 = Methodref          #186.#196     // scala/Predef$.identity:(Ljava/lang/Object;)Ljava/lang/Object;
  #198 = Utf8               value
  #199 = NameAndType        #198:#100     // value:()Lscala/Function1;
  #200 = Methodref          #191.#199     // coursier/util/Task.value:()Lscala/Function1;
  #201 = Utf8               ()V
  #202 = NameAndType        #116:#201     // "<init>":()V
  #203 = Methodref          #4.#202       // java/lang/Object."<init>":()V
  #204 = Utf8               (Lcoursier/util/PlatformTaskCompanion;)V
  #205 = NameAndType        #116:#204     // "<init>":(Lcoursier/util/PlatformTaskCompanion;)V
  #206 = Methodref          #12.#205      // coursier/util/PlatformTaskCompanion$$anon$2."<init>":(Lcoursier/util/PlatformTaskCompanion;)V
  #207 = NameAndType        #144:#74      // $anonfun$completeAfter$1:(Ljava/util/concurrent/ScheduledExecutorService;Lscala/concurrent/duration/FiniteDuration;)Lscala/Function1;
  #208 = Methodref          #2.#207       // coursier/util/PlatformTaskCompanion.$anonfun$completeAfter$1:(Ljava/util/concurrent/ScheduledExecutorService;Lscala/concurrent/duration/FiniteDuration;)Lscala/Function1;
  #209 = NameAndType        #182:#183     // $anonfun$completeAfter$3:(Lscala/Function1;)Lscala/Function1;
  #210 = Methodref          #2.#209       // coursier/util/PlatformTaskCompanion.$anonfun$completeAfter$3:(Lscala/Function1;)Lscala/Function1;
  #211 = Utf8               Ljava/lang/Object;
  #212 = Utf8               $deserializeLambda$
  #213 = Utf8               (Ljava/lang/invoke/SerializedLambda;)Ljava/lang/Object;
  #214 = Utf8               scala/runtime/LambdaDeserialize
  #215 = Class              #214          // scala/runtime/LambdaDeserialize
  #216 = Utf8               bootstrap
  #217 = Utf8               (Ljava/lang/invoke/MethodHandles$Lookup;Ljava/lang/String;Ljava/lang/invoke/MethodType;[Ljava/lang/invoke/MethodHandle;)Ljava/lang/invoke/CallSite;
  #218 = NameAndType        #216:#217     // bootstrap:(Ljava/lang/invoke/MethodHandles$Lookup;Ljava/lang/String;Ljava/lang/invoke/MethodType;[Ljava/lang/invoke/MethodHandle;)Ljava/lang/invoke/CallSite;
  #219 = Methodref          #215.#218     // scala/runtime/LambdaDeserialize.bootstrap:(Ljava/lang/invoke/MethodHandles$Lookup;Ljava/lang/String;Ljava/lang/invoke/MethodType;[Ljava/lang/invoke/MethodHandle;)Ljava/lang/invoke/CallSite;
  #220 = MethodHandle       6:#219        // REF_invokeStatic scala/runtime/LambdaDeserialize.bootstrap:(Ljava/lang/invoke/MethodHandles$Lookup;Ljava/lang/String;Ljava/lang/invoke/MethodType;[Ljava/lang/invoke/MethodHandle;)Ljava/lang/invoke/CallSite;
  #221 = Utf8               lambdaDeserialize
  #222 = NameAndType        #221:#213     // lambdaDeserialize:(Ljava/lang/invoke/SerializedLambda;)Ljava/lang/Object;
  #223 = InvokeDynamic      #4:#222       // #4:lambdaDeserialize:(Ljava/lang/invoke/SerializedLambda;)Ljava/lang/Object;
  #224 = Utf8               Signature
  #225 = Utf8               Code
  #226 = Utf8               StackMapTable
  #227 = Utf8               LineNumberTable
  #228 = Utf8               LocalVariableTable
  #229 = Utf8               MethodParameters
  #230 = Utf8               InnerClasses
  #231 = Utf8               SourceFile
  #232 = Utf8               RuntimeVisibleAnnotations
  #233 = Utf8               BootstrapMethods
  #234 = Utf8               ScalaInlineInfo
  #235 = Utf8               ScalaSig
{
  private final coursier.util.Sync<coursier.util.Task> sync;
    descriptor: Lcoursier/util/Sync;
    flags: (0x0012) ACC_PRIVATE, ACC_FINAL
    Signature: #23                          // Lcoursier/util/Sync<Lcoursier/util/Task;>;

  public <A extends java.lang.Object> scala.Function1<scala.concurrent.ExecutionContext, scala.concurrent.Future<A>> schedule(java.util.concurrent.ExecutorService, scala.Function0<A>);
    descriptor: (Ljava/util/concurrent/ExecutorService;Lscala/Function0;)Lscala/Function1;
    flags: (0x0001) ACC_PUBLIC
    Code:
      stack=2, locals=7, args_size=3
         0: aload_1
         1: astore        5
         3: aload         5
         5: instanceof    #30                 // class scala/concurrent/ExecutionContextExecutorService
         8: ifeq          24
        11: aload         5
        13: checkcast     #30                 // class scala/concurrent/ExecutionContextExecutorService
        16: astore        6
        18: aload         6
        20: astore_3
        21: goto          38
        24: goto          27
        27: getstatic     #38                 // Field scala/concurrent/ExecutionContext$.MODULE$:Lscala/concurrent/ExecutionContext$;
        30: aload_1
        31: invokevirtual #42                 // Method scala/concurrent/ExecutionContext$.fromExecutorService:(Ljava/util/concurrent/ExecutorService;)Lscala/concurrent/ExecutionContextExecutorService;
        34: astore_3
        35: goto          38
        38: aload_3
        39: astore        4
        41: aload_2
        42: aload         4
        44: invokedynamic #66,  0             // InvokeDynamic #0:apply:(Lscala/Function0;Lscala/concurrent/ExecutionContextExecutorService;)Lscala/Function1;
        49: areturn
      StackMapTable: number_of_entries = 3
        frame_type = 254 /* append */
          offset_delta = 24
          locals = [ top, top, class java/util/concurrent/ExecutorService ]
        frame_type = 2 /* same */
        frame_type = 255 /* full_frame */
          offset_delta = 10
          locals = [ class coursier/util/PlatformTaskCompanion, class java/util/concurrent/ExecutorService, class scala/Function0, class scala/concurrent/ExecutionContextExecutorService, top, class java/util/concurrent/ExecutorService ]
          stack = []
      LineNumberTable:
        line 14: 0
        line 15: 3
        line 16: 27
        line 14: 38
        line 19: 41
      LocalVariableTable:
        Start  Length  Slot  Name   Signature
           41       8     4   ec0   Lscala/concurrent/ExecutionContextExecutorService;
            0      50     0  this   Lcoursier/util/PlatformTaskCompanion;
            0      50     1  pool   Ljava/util/concurrent/ExecutorService;
            0      50     2     f   Lscala/Function0;
    Signature: #26                          // <A:Ljava/lang/Object;>(Ljava/util/concurrent/ExecutorService;Lscala/Function0<TA;>;)Lscala/Function1<Lscala/concurrent/ExecutionContext;Lscala/concurrent/Future<TA;>;>;
    MethodParameters:
      Name                           Flags
      pool                           final
      f                              final

  public scala.Function1<scala.concurrent.ExecutionContext, scala.concurrent.Future<scala.runtime.BoxedUnit>> completeAfter(java.util.concurrent.ScheduledExecutorService, scala.concurrent.duration.FiniteDuration);
    descriptor: (Ljava/util/concurrent/ScheduledExecutorService;Lscala/concurrent/duration/FiniteDuration;)Lscala/Function1;
    flags: (0x0001) ACC_PUBLIC
    Code:
      stack=4, locals=3, args_size=3
         0: getstatic     #81                 // Field coursier/util/Task$.MODULE$:Lcoursier/util/Task$;
         3: getstatic     #81                 // Field coursier/util/Task$.MODULE$:Lcoursier/util/Task$;
         6: aload_1
         7: aload_2
         8: invokedynamic #91,  0             // InvokeDynamic #1:apply:(Ljava/util/concurrent/ScheduledExecutorService;Lscala/concurrent/duration/FiniteDuration;)Lscala/Function0;
        13: invokevirtual #95                 // Method coursier/util/Task$.delay:(Lscala/Function0;)Lscala/Function1;
        16: invokedynamic #102,  0            // InvokeDynamic #2:apply:()Lscala/Function1;
        21: invokevirtual #106                // Method coursier/util/Task$.flatMap$extension:(Lscala/Function1;Lscala/Function1;)Lscala/Function1;
        24: areturn
      LineNumberTable:
        line 23: 3
        line 32: 16
      LocalVariableTable:
        Start  Length  Slot  Name   Signature
            0      25     0  this   Lcoursier/util/PlatformTaskCompanion;
            0      25     1  pool   Ljava/util/concurrent/ScheduledExecutorService;
            0      25     2 duration   Lscala/concurrent/duration/FiniteDuration;
    Signature: #75                          // (Ljava/util/concurrent/ScheduledExecutorService;Lscala/concurrent/duration/FiniteDuration;)Lscala/Function1<Lscala/concurrent/ExecutionContext;Lscala/concurrent/Future<Lscala/runtime/BoxedUnit;>;>;
    MethodParameters:
      Name                           Flags
      pool                           final
      duration                       final

  public coursier.util.Sync<coursier.util.Task> sync();
    descriptor: ()Lcoursier/util/Sync;
    flags: (0x0001) ACC_PUBLIC
    Code:
      stack=1, locals=1, args_size=1
         0: aload_0
         1: getfield      #112                // Field sync:Lcoursier/util/Sync;
         4: areturn
      LineNumberTable:
        line 34: 0
      LocalVariableTable:
        Start  Length  Slot  Name   Signature
            0       5     0  this   Lcoursier/util/PlatformTaskCompanion;
    Signature: #110                         // ()Lcoursier/util/Sync<Lcoursier/util/Task;>;

  public <T extends java.lang.Object> coursier.util.PlatformTaskCompanion$PlatformTaskOps<T> PlatformTaskOps(scala.Function1<scala.concurrent.ExecutionContext, scala.concurrent.Future<T>>);
    descriptor: (Lscala/Function1;)Lcoursier/util/PlatformTaskCompanion$PlatformTaskOps;
    flags: (0x0001) ACC_PUBLIC
    Code:
      stack=4, locals=2, args_size=2
         0: new           #14                 // class coursier/util/PlatformTaskCompanion$PlatformTaskOps
         3: dup
         4: aload_0
         5: aload_1
         6: invokespecial #119                // Method coursier/util/PlatformTaskCompanion$PlatformTaskOps."<init>":(Lcoursier/util/PlatformTaskCompanion;Lscala/Function1;)V
         9: areturn
      LineNumberTable:
        line 39: 0
      LocalVariableTable:
        Start  Length  Slot  Name   Signature
            0      10     0  this   Lcoursier/util/PlatformTaskCompanion;
            0      10     1  task   Lscala/Function1;
    Signature: #114                         // <T:Ljava/lang/Object;>(Lscala/Function1<Lscala/concurrent/ExecutionContext;Lscala/concurrent/Future<TT;>;>;)Lcoursier/util/PlatformTaskCompanion$PlatformTaskOps<TT;>;
    MethodParameters:
      Name                           Flags
      task                           final

  public static final scala.concurrent.Future $anonfun$schedule$1(scala.Function0, scala.concurrent.ExecutionContextExecutorService, scala.concurrent.ExecutionContext);
    descriptor: (Lscala/Function0;Lscala/concurrent/ExecutionContextExecutorService;Lscala/concurrent/ExecutionContext;)Lscala/concurrent/Future;
    flags: (0x1019) ACC_PUBLIC, ACC_STATIC, ACC_FINAL, ACC_SYNTHETIC
    Code:
      stack=3, locals=3, args_size=3
         0: getstatic     #128                // Field scala/concurrent/Future$.MODULE$:Lscala/concurrent/Future$;
         3: aload_0
         4: aload_1
         5: invokevirtual #131                // Method scala/concurrent/Future$.apply:(Lscala/Function0;Lscala/concurrent/ExecutionContext;)Lscala/concurrent/Future;
         8: areturn
      LineNumberTable:
        line 19: 0
      LocalVariableTable:
        Start  Length  Slot  Name   Signature
            0       9     0   f$1   Lscala/Function0;
            0       9     1 ec0$1   Lscala/concurrent/ExecutionContextExecutorService;
            0       9     2   x$1   Lscala/concurrent/ExecutionContext;
    MethodParameters:
      Name                           Flags
      f$1                            final
      ec0$1                          final
      x$1                            final

  public static final scala.concurrent.Future $anonfun$completeAfter$2(scala.concurrent.Promise, scala.concurrent.ExecutionContext);
    descriptor: (Lscala/concurrent/Promise;Lscala/concurrent/ExecutionContext;)Lscala/concurrent/Future;
    flags: (0x1019) ACC_PUBLIC, ACC_STATIC, ACC_FINAL, ACC_SYNTHETIC
    Code:
      stack=1, locals=2, args_size=2
         0: aload_0
         1: invokeinterface #142,  1          // InterfaceMethod scala/concurrent/Promise.future:()Lscala/concurrent/Future;
         6: areturn
      LineNumberTable:
        line 31: 0
      LocalVariableTable:
        Start  Length  Slot  Name   Signature
            0       7     0   p$1   Lscala/concurrent/Promise;
            0       7     1   x$2   Lscala/concurrent/ExecutionContext;
    MethodParameters:
      Name                           Flags
      p$1                            final
      x$2                            final

  public static final scala.Function1 $anonfun$completeAfter$1(java.util.concurrent.ScheduledExecutorService, scala.concurrent.duration.FiniteDuration);
    descriptor: (Ljava/util/concurrent/ScheduledExecutorService;Lscala/concurrent/duration/FiniteDuration;)Lscala/Function1;
    flags: (0x1019) ACC_PUBLIC, ACC_STATIC, ACC_FINAL, ACC_SYNTHETIC
    Code:
      stack=5, locals=4, args_size=2
         0: getstatic     #151                // Field scala/concurrent/Promise$.MODULE$:Lscala/concurrent/Promise$;
         3: invokevirtual #154                // Method scala/concurrent/Promise$.apply:()Lscala/concurrent/Promise;
         6: astore_2
         7: new           #10                 // class coursier/util/PlatformTaskCompanion$$anon$1
        10: dup
        11: aconst_null
        12: aload_2
        13: invokespecial #157                // Method coursier/util/PlatformTaskCompanion$$anon$1."<init>":(Lcoursier/util/PlatformTaskCompanion;Lscala/concurrent/Promise;)V
        16: astore_3
        17: aload_0
        18: aload_3
        19: aload_1
        20: invokevirtual #163                // Method scala/concurrent/duration/FiniteDuration.length:()J
        23: aload_1
        24: invokevirtual #167                // Method scala/concurrent/duration/FiniteDuration.unit:()Ljava/util/concurrent/TimeUnit;
        27: invokeinterface #172,  5          // InterfaceMethod java/util/concurrent/ScheduledExecutorService.schedule:(Ljava/lang/Runnable;JLjava/util/concurrent/TimeUnit;)Ljava/util/concurrent/ScheduledFuture;
        32: pop
        33: aload_2
        34: invokedynamic #178,  0            // InvokeDynamic #3:apply:(Lscala/concurrent/Promise;)Lscala/Function1;
        39: areturn
      LineNumberTable:
        line 24: 0
        line 26: 7
        line 30: 17
        line 31: 33
      LocalVariableTable:
        Start  Length  Slot  Name   Signature
            7      32     2     p   Lscala/concurrent/Promise;
           17      22     3 runnable   Ljava/lang/Runnable;
            0      40     0 pool$1   Ljava/util/concurrent/ScheduledExecutorService;
            0      40     1 duration$1   Lscala/concurrent/duration/FiniteDuration;
    MethodParameters:
      Name                           Flags
      pool$1                         final
      duration$1                     final

  public static final scala.Function1 $anonfun$completeAfter$3(scala.Function1);
    descriptor: (Lscala/Function1;)Lscala/Function1;
    flags: (0x1019) ACC_PUBLIC, ACC_STATIC, ACC_FINAL, ACC_SYNTHETIC
    Code:
      stack=4, locals=1, args_size=1
         0: getstatic     #189                // Field scala/Predef$.MODULE$:Lscala/Predef$;
         3: new           #191                // class coursier/util/Task
         6: dup
         7: aload_0
         8: invokespecial #194                // Method coursier/util/Task."<init>":(Lscala/Function1;)V
        11: invokevirtual #197                // Method scala/Predef$.identity:(Ljava/lang/Object;)Ljava/lang/Object;
        14: checkcast     #191                // class coursier/util/Task
        17: invokevirtual #200                // Method coursier/util/Task.value:()Lscala/Function1;
        20: areturn
      LineNumberTable:
        line 32: 0
      LocalVariableTable:
        Start  Length  Slot  Name   Signature
            0      21     0     x   Lscala/Function1;
    MethodParameters:
      Name                           Flags
      x                              final

  public coursier.util.PlatformTaskCompanion();
    descriptor: ()V
    flags: (0x0001) ACC_PUBLIC
    Code:
      stack=4, locals=1, args_size=1
         0: aload_0
         1: invokespecial #203                // Method java/lang/Object."<init>":()V
         4: aload_0
         5: new           #12                 // class coursier/util/PlatformTaskCompanion$$anon$2
         8: dup
         9: aload_0
        10: invokespecial #206                // Method coursier/util/PlatformTaskCompanion$$anon$2."<init>":(Lcoursier/util/PlatformTaskCompanion;)V
        13: putfield      #112                // Field sync:Lcoursier/util/Sync;
        16: return
      LineNumberTable:
        line 44: 0
        line 34: 4
        line 35: 5
        line 34: 13
        line 10: 16
      LocalVariableTable:
        Start  Length  Slot  Name   Signature
            0      17     0  this   Lcoursier/util/PlatformTaskCompanion;

  public static final java.lang.Object $anonfun$completeAfter$1$adapted(java.util.concurrent.ScheduledExecutorService, scala.concurrent.duration.FiniteDuration);
    descriptor: (Ljava/util/concurrent/ScheduledExecutorService;Lscala/concurrent/duration/FiniteDuration;)Ljava/lang/Object;
    flags: (0x1019) ACC_PUBLIC, ACC_STATIC, ACC_FINAL, ACC_SYNTHETIC
    Code:
      stack=4, locals=2, args_size=2
         0: new           #191                // class coursier/util/Task
         3: dup
         4: aload_0
         5: aload_1
         6: invokestatic  #208                // Method $anonfun$completeAfter$1:(Ljava/util/concurrent/ScheduledExecutorService;Lscala/concurrent/duration/FiniteDuration;)Lscala/Function1;
         9: invokespecial #194                // Method coursier/util/Task."<init>":(Lscala/Function1;)V
        12: areturn
      LineNumberTable:
        line 23: 0
      LocalVariableTable:
        Start  Length  Slot  Name   Signature
            0      13     0 pool$1   Ljava/util/concurrent/ScheduledExecutorService;
            0      13     1 duration$1   Lscala/concurrent/duration/FiniteDuration;
    MethodParameters:
      Name                           Flags
      pool$1                         final
      duration$1                     final

  public static final java.lang.Object $anonfun$completeAfter$3$adapted(java.lang.Object);
    descriptor: (Ljava/lang/Object;)Ljava/lang/Object;
    flags: (0x1019) ACC_PUBLIC, ACC_STATIC, ACC_FINAL, ACC_SYNTHETIC
    Code:
      stack=3, locals=1, args_size=1
         0: new           #191                // class coursier/util/Task
         3: dup
         4: aload_0
         5: checkcast     #191                // class coursier/util/Task
         8: invokevirtual #200                // Method coursier/util/Task.value:()Lscala/Function1;
        11: invokestatic  #210                // Method $anonfun$completeAfter$3:(Lscala/Function1;)Lscala/Function1;
        14: invokespecial #194                // Method coursier/util/Task."<init>":(Lscala/Function1;)V
        17: areturn
      LineNumberTable:
        line 32: 0
      LocalVariableTable:
        Start  Length  Slot  Name   Signature
            0      18     0     x   Ljava/lang/Object;
    MethodParameters:
      Name                           Flags
      x                              final

  private static java.lang.Object $deserializeLambda$(java.lang.invoke.SerializedLambda);
    descriptor: (Ljava/lang/invoke/SerializedLambda;)Ljava/lang/Object;
    flags: (0x100a) ACC_PRIVATE, ACC_STATIC, ACC_SYNTHETIC
    Code:
      stack=1, locals=1, args_size=1
         0: aload_0
         1: invokedynamic #223,  0            // InvokeDynamic #4:lambdaDeserialize:(Ljava/lang/invoke/SerializedLambda;)Ljava/lang/Object;
         6: areturn
}
InnerClasses:
  public final #10;                       // class coursier/util/PlatformTaskCompanion$$anon$1
  public final #12;                       // class coursier/util/PlatformTaskCompanion$$anon$2
  public #15= #14 of #2;                  // PlatformTaskOps=class coursier/util/PlatformTaskCompanion$PlatformTaskOps of class coursier/util/PlatformTaskCompanion
  public static final #20= #17 of #19;    // Lookup=class java/lang/invoke/MethodHandles$Lookup of class java/lang/invoke/MethodHandles
SourceFile: "PlatformTaskCompanion.scala"
RuntimeVisibleAnnotations:
  0: #6(#7=s#8)
    scala.reflect.ScalaSignature(
      bytes="\u0006\u0005]4Q\u0001D\u0007\u0002\u0002IAQ!\u0007\u0001\u0005\u0002iAQ!\b\u0001\u0005\u0002yAQa\u0010\u0001\u0005\u0002\u0001Cq!\u0015\u0001C\u0002\u0013\r!\u000b\u0003\u0004X\u0001\u0001\u0006Ia\u0015\u0004\u00051\u0002\t\u0011\f\u0003\u0005\\\r\t\u0015\r\u0011\"\u0003]\u0011!\tgA!A!\u0002\u0013i\u0006\"B\r\u0007\t\u0003\u0011\u0007\"\u00024\u0007\t\u00039\u0007bB8\u0001\u0003\u0003%\u0019\u0001\u001d\u0002\u0016!2\fGOZ8s[R\u000b7o[\"p[B\fg.[8o\u0015\tqq\"\u0001\u0003vi&d\'\"\u0001\t\u0002\u0011\r|WO]:jKJ\u001c\u0001a\u0005\u0002\u0001\'A\u0011AcF\u0007\u0002+)\ta#A\u0003tG\u0006d\u0017-\u0003\u0002\u0019+\t1\u0011I\\=SK\u001a\fa\u0001P5oSRtD#A\u000e\u0011\u0005q\u0001Q\"A\u0007\u0002\u0011M\u001c\u0007.\u001a3vY\u0016,\"a\b\u0014\u0015\u0005\u0001\"DCA\u00110!\ra\"\u0005J\u0005\u0003G5\u0011A\u0001V1tWB\u0011QE\n\u0007\u0001\t\u00159#A1\u0001)\u0005\u0005\t\u0015CA\u0015-!\t!\"&\u0003\u0002,+\t9aj\u001c;iS:<\u0007C\u0001\u000b.\u0013\tqSCA\u0002B]fDa\u0001\r\u0002\u0005\u0002\u0004\t\u0014!\u00014\u0011\u0007Q\u0011D%\u0003\u00024+\tAAHY=oC6,g\bC\u00036\u0005\u0001\u0007a\'\u0001\u0003q_>d\u0007CA\u001c>\u001b\u0005A$BA\u001d;\u0003)\u0019wN\\2veJ,g\u000e\u001e\u0006\u0003\u001dmR\u0011\u0001P\u0001\u0005U\u00064\u0018-\u0003\u0002?q\tyQ\t_3dkR|\'oU3sm&\u001cW-A\u0007d_6\u0004H.\u001a;f\u0003\u001a$XM\u001d\u000b\u0004\u0003\u0016K\u0005c\u0001\u000f#\u0005B\u0011AcQ\u0005\u0003\tV\u0011A!\u00168ji\")Qg\u0001a\u0001\rB\u0011qgR\u0005\u0003\u0011b\u0012\u0001dU2iK\u0012,H.\u001a3Fq\u0016\u001cW\u000f^8s\'\u0016\u0014h/[2f\u0011\u0015Q5\u00011\u0001L\u0003!!WO]1uS>t\u0007C\u0001\'P\u001b\u0005i%B\u0001&O\u0015\tIT#\u0003\u0002Q\u001b\nqa)\u001b8ji\u0016$UO]1uS>t\u0017\u0001B:z]\u000e,\u0012a\u0015\t\u00049Q3\u0016BA+\u000e\u0005\u0011\u0019\u0016P\\2\u0011\u0005q\u0011\u0013!B:z]\u000e\u0004#a\u0004)mCR4wN]7UCN\\w\n]:\u0016\u0005i{6C\u0001\u0004\u0014\u0003\u0011!\u0018m]6\u0016\u0003u\u00032\u0001\b\u0012_!\t)s\fB\u0003a\r\t\u0007\u0001FA\u0001U\u0003\u0015!\u0018m]6!)\t\u0019W\rE\u0002e\ryk\u0011\u0001\u0001\u0005\u00067&\u0001\r!X\u0001\nk:\u001c\u0018MZ3Sk:$\u0012\u0001\u001b\u000b\u0003=&DQA\u001b\u0006A\u0004-\f!!Z2\u0011\u00051lW\"\u0001(\n\u00059t%\u0001E#yK\u000e,H/[8o\u0007>tG/\u001a=u\u0003=\u0001F.\u0019;g_JlG+Y:l\u001fB\u001cXCA9u)\t\u0011X\u000fE\u0002e\rM\u0004\"!\n;\u0005\u000b\u0001\\!\u0019\u0001\u0015\t\u000bm[\u0001\u0019\u0001<\u0011\u0007q\u00113\u000f"
    )
BootstrapMethods:
  0: #62 REF_invokeStatic java/lang/invoke/LambdaMetafactory.altMetafactory:(Ljava/lang/invoke/MethodHandles$Lookup;Ljava/lang/String;Ljava/lang/invoke/MethodType;[Ljava/lang/Object;)Ljava/lang/invoke/CallSite;
    Method arguments:
      #46 (Ljava/lang/Object;)Ljava/lang/Object;
      #51 REF_invokeStatic coursier/util/PlatformTaskCompanion.$anonfun$schedule$1:(Lscala/Function0;Lscala/concurrent/ExecutionContextExecutorService;Lscala/concurrent/ExecutionContext;)Lscala/concurrent/Future;
      #53 (Lscala/concurrent/ExecutionContext;)Lscala/concurrent/Future;
      #54 5
      #55 1
      #53 (Lscala/concurrent/ExecutionContext;)Lscala/concurrent/Future;
  1: #62 REF_invokeStatic java/lang/invoke/LambdaMetafactory.altMetafactory:(Ljava/lang/invoke/MethodHandles$Lookup;Ljava/lang/String;Ljava/lang/invoke/MethodType;[Ljava/lang/Object;)Ljava/lang/invoke/CallSite;
    Method arguments:
      #83 ()Ljava/lang/Object;
      #88 REF_invokeStatic coursier/util/PlatformTaskCompanion.$anonfun$completeAfter$1$adapted:(Ljava/util/concurrent/ScheduledExecutorService;Lscala/concurrent/duration/FiniteDuration;)Ljava/lang/Object;
      #83 ()Ljava/lang/Object;
      #55 1
  2: #62 REF_invokeStatic java/lang/invoke/LambdaMetafactory.altMetafactory:(Ljava/lang/invoke/MethodHandles$Lookup;Ljava/lang/String;Ljava/lang/invoke/MethodType;[Ljava/lang/Object;)Ljava/lang/invoke/CallSite;
    Method arguments:
      #46 (Ljava/lang/Object;)Ljava/lang/Object;
      #99 REF_invokeStatic coursier/util/PlatformTaskCompanion.$anonfun$completeAfter$3$adapted:(Ljava/lang/Object;)Ljava/lang/Object;
      #46 (Ljava/lang/Object;)Ljava/lang/Object;
      #55 1
  3: #62 REF_invokeStatic java/lang/invoke/LambdaMetafactory.altMetafactory:(Ljava/lang/invoke/MethodHandles$Lookup;Ljava/lang/String;Ljava/lang/invoke/MethodType;[Ljava/lang/Object;)Ljava/lang/invoke/CallSite;
    Method arguments:
      #46 (Ljava/lang/Object;)Ljava/lang/Object;
      #175 REF_invokeStatic coursier/util/PlatformTaskCompanion.$anonfun$completeAfter$2:(Lscala/concurrent/Promise;Lscala/concurrent/ExecutionContext;)Lscala/concurrent/Future;
      #53 (Lscala/concurrent/ExecutionContext;)Lscala/concurrent/Future;
      #54 5
      #55 1
      #53 (Lscala/concurrent/ExecutionContext;)Lscala/concurrent/Future;
  4: #220 REF_invokeStatic scala/runtime/LambdaDeserialize.bootstrap:(Ljava/lang/invoke/MethodHandles$Lookup;Ljava/lang/String;Ljava/lang/invoke/MethodType;[Ljava/lang/invoke/MethodHandle;)Ljava/lang/invoke/CallSite;
    Method arguments:
      #88 REF_invokeStatic coursier/util/PlatformTaskCompanion.$anonfun$completeAfter$1$adapted:(Ljava/util/concurrent/ScheduledExecutorService;Lscala/concurrent/duration/FiniteDuration;)Ljava/lang/Object;
      #175 REF_invokeStatic coursier/util/PlatformTaskCompanion.$anonfun$completeAfter$2:(Lscala/concurrent/Promise;Lscala/concurrent/ExecutionContext;)Lscala/concurrent/Future;
      #99 REF_invokeStatic coursier/util/PlatformTaskCompanion.$anonfun$completeAfter$3$adapted:(Ljava/lang/Object;)Ljava/lang/Object;
      #51 REF_invokeStatic coursier/util/PlatformTaskCompanion.$anonfun$schedule$1:(Lscala/Function0;Lscala/concurrent/ExecutionContextExecutorService;Lscala/concurrent/ExecutionContext;)Lscala/concurrent/Future;
  ScalaInlineInfo: length = 0x3B (unknown attribute)
   01 00 00 0B 00 90 00 4A 01 00 54 00 55 01 00 85
   00 86 01 00 B6 00 B7 01 00 60 00 29 01 00 2B 00
   2C 01 00 74 00 C9 00 00 0F 00 71 00 00 49 00 4A
   00 00 18 00 19 00 00 15 00 6D 00
  ScalaSig: length = 0x3 (unknown attribute)
   05 02 00
