Classfile /Users/mw/Projects/slang-braindump/.jar/jar11/assemble/slang-braindump/assemble/content/coursier/util/PlatformTaskCompanion$$anon$2.class
  Last modified May 29, 2022; size 6054 bytes
  SHA-256 checksum 6a979dc849bb562721e6f39f13c59e5e1c78b3814de4aecbfbc41acca3dab469
  Compiled from "PlatformTaskCompanion.scala"
public final class coursier.util.PlatformTaskCompanion$$anon$2 implements coursier.util.TaskSync
  minor version: 0
  major version: 52
  flags: (0x0031) ACC_PUBLIC, ACC_FINAL, ACC_SUPER
  this_class: #2                          // coursier/util/PlatformTaskCompanion$$anon$2
  super_class: #4                         // java/lang/Object
  interfaces: 1, fields: 1, methods: 18, attributes: 5
Constant pool:
    #1 = Utf8               coursier/util/PlatformTaskCompanion$$anon$2
    #2 = Class              #1            // coursier/util/PlatformTaskCompanion$$anon$2
    #3 = Utf8               java/lang/Object
    #4 = Class              #3            // java/lang/Object
    #5 = Utf8               coursier/util/TaskSync
    #6 = Class              #5            // coursier/util/TaskSync
    #7 = Utf8               PlatformTaskCompanion.scala
    #8 = Utf8               coursier/util/PlatformTaskCompanion
    #9 = Class              #8            // coursier/util/PlatformTaskCompanion
   #10 = Utf8               $outer
   #11 = Utf8               Lcoursier/util/PlatformTaskCompanion;
   #12 = Utf8               point
   #13 = Utf8               (Ljava/lang/Object;)Lscala/Function1;
   #14 = Utf8               <A:Ljava/lang/Object;>(TA;)Lscala/Function1<Lscala/concurrent/ExecutionContext;Lscala/concurrent/Future<TA;>;>;
   #15 = Utf8               a
   #16 = Utf8               point$
   #17 = Utf8               (Lcoursier/util/TaskSync;Ljava/lang/Object;)Lscala/Function1;
   #18 = NameAndType        #16:#17       // point$:(Lcoursier/util/TaskSync;Ljava/lang/Object;)Lscala/Function1;
   #19 = InterfaceMethodref #6.#18        // coursier/util/TaskSync.point$:(Lcoursier/util/TaskSync;Ljava/lang/Object;)Lscala/Function1;
   #20 = Utf8               this
   #21 = Utf8               Lcoursier/util/PlatformTaskCompanion$$anon$2;
   #22 = Utf8               Ljava/lang/Object;
   #23 = Utf8               bind
   #24 = Utf8               (Lscala/Function1;Lscala/Function1;)Lscala/Function1;
   #25 = Utf8               <A:Ljava/lang/Object;B:Ljava/lang/Object;>(Lscala/Function1<Lscala/concurrent/ExecutionContext;Lscala/concurrent/Future<TA;>;>;Lscala/Function1<TA;Lcoursier/util/Task<TB;>;>;)Lscala/Function1<Lscala/concurrent/ExecutionContext;Lscala/concurrent/Future<TB;>;>;
   #26 = Utf8               elem
   #27 = Utf8               f
   #28 = Utf8               bind$
   #29 = Utf8               (Lcoursier/util/TaskSync;Lscala/Function1;Lscala/Function1;)Lscala/Function1;
   #30 = NameAndType        #28:#29       // bind$:(Lcoursier/util/TaskSync;Lscala/Function1;Lscala/Function1;)Lscala/Function1;
   #31 = InterfaceMethodref #6.#30        // coursier/util/TaskSync.bind$:(Lcoursier/util/TaskSync;Lscala/Function1;Lscala/Function1;)Lscala/Function1;
   #32 = Utf8               Lscala/Function1;
   #33 = Utf8               map
   #34 = Utf8               <A:Ljava/lang/Object;B:Ljava/lang/Object;>(Lscala/Function1<Lscala/concurrent/ExecutionContext;Lscala/concurrent/Future<TA;>;>;Lscala/Function1<TA;TB;>;)Lscala/Function1<Lscala/concurrent/ExecutionContext;Lscala/concurrent/Future<TB;>;>;
   #35 = Utf8               map$
   #36 = NameAndType        #35:#29       // map$:(Lcoursier/util/TaskSync;Lscala/Function1;Lscala/Function1;)Lscala/Function1;
   #37 = InterfaceMethodref #6.#36        // coursier/util/TaskSync.map$:(Lcoursier/util/TaskSync;Lscala/Function1;Lscala/Function1;)Lscala/Function1;
   #38 = Utf8               gather
   #39 = Utf8               (Lscala/collection/immutable/Seq;)Lscala/Function1;
   #40 = Utf8               <A:Ljava/lang/Object;>(Lscala/collection/immutable/Seq<Lcoursier/util/Task<TA;>;>;)Lscala/Function1<Lscala/concurrent/ExecutionContext;Lscala/concurrent/Future<Lscala/collection/immutable/Seq<TA;>;>;>;
   #41 = Utf8               elems
   #42 = Utf8               gather$
   #43 = Utf8               (Lcoursier/util/TaskSync;Lscala/collection/immutable/Seq;)Lscala/Function1;
   #44 = NameAndType        #42:#43       // gather$:(Lcoursier/util/TaskSync;Lscala/collection/immutable/Seq;)Lscala/Function1;
   #45 = InterfaceMethodref #6.#44        // coursier/util/TaskSync.gather$:(Lcoursier/util/TaskSync;Lscala/collection/immutable/Seq;)Lscala/Function1;
   #46 = Utf8               Lscala/collection/immutable/Seq;
   #47 = Utf8               delay
   #48 = Utf8               (Lscala/Function0;)Lscala/Function1;
   #49 = Utf8               <A:Ljava/lang/Object;>(Lscala/Function0<TA;>;)Lscala/Function1<Lscala/concurrent/ExecutionContext;Lscala/concurrent/Future<TA;>;>;
   #50 = Utf8               delay$
   #51 = Utf8               (Lcoursier/util/TaskSync;Lscala/Function0;)Lscala/Function1;
   #52 = NameAndType        #50:#51       // delay$:(Lcoursier/util/TaskSync;Lscala/Function0;)Lscala/Function1;
   #53 = InterfaceMethodref #6.#52        // coursier/util/TaskSync.delay$:(Lcoursier/util/TaskSync;Lscala/Function0;)Lscala/Function1;
   #54 = Utf8               Lscala/Function0;
   #55 = Utf8               fromAttempt
   #56 = Utf8               (Lscala/util/Either;)Lscala/Function1;
   #57 = Utf8               <A:Ljava/lang/Object;>(Lscala/util/Either<Ljava/lang/Throwable;TA;>;)Lscala/Function1<Lscala/concurrent/ExecutionContext;Lscala/concurrent/Future<TA;>;>;
   #58 = Utf8               fromAttempt$
   #59 = Utf8               (Lcoursier/util/TaskSync;Lscala/util/Either;)Lscala/Function1;
   #60 = NameAndType        #58:#59       // fromAttempt$:(Lcoursier/util/TaskSync;Lscala/util/Either;)Lscala/Function1;
   #61 = InterfaceMethodref #6.#60        // coursier/util/TaskSync.fromAttempt$:(Lcoursier/util/TaskSync;Lscala/util/Either;)Lscala/Function1;
   #62 = Utf8               Lscala/util/Either;
   #63 = Utf8               handle
   #64 = Utf8               (Lscala/Function1;Lscala/PartialFunction;)Lscala/Function1;
   #65 = Utf8               <A:Ljava/lang/Object;>(Lscala/Function1<Lscala/concurrent/ExecutionContext;Lscala/concurrent/Future<TA;>;>;Lscala/PartialFunction<Ljava/lang/Throwable;TA;>;)Lscala/Function1<Lscala/concurrent/ExecutionContext;Lscala/concurrent/Future<TA;>;>;
   #66 = Utf8               handle$
   #67 = Utf8               (Lcoursier/util/TaskSync;Lscala/Function1;Lscala/PartialFunction;)Lscala/Function1;
   #68 = NameAndType        #66:#67       // handle$:(Lcoursier/util/TaskSync;Lscala/Function1;Lscala/PartialFunction;)Lscala/Function1;
   #69 = InterfaceMethodref #6.#68        // coursier/util/TaskSync.handle$:(Lcoursier/util/TaskSync;Lscala/Function1;Lscala/PartialFunction;)Lscala/Function1;
   #70 = Utf8               Lscala/PartialFunction;
   #71 = Utf8               attempt
   #72 = Utf8               (Ljava/lang/Object;)Ljava/lang/Object;
   #73 = Utf8               coursier/util/Sync
   #74 = Class              #73           // coursier/util/Sync
   #75 = Utf8               attempt$
   #76 = Utf8               (Lcoursier/util/Sync;Ljava/lang/Object;)Ljava/lang/Object;
   #77 = NameAndType        #75:#76       // attempt$:(Lcoursier/util/Sync;Ljava/lang/Object;)Ljava/lang/Object;
   #78 = InterfaceMethodref #74.#77       // coursier/util/Sync.attempt$:(Lcoursier/util/Sync;Ljava/lang/Object;)Ljava/lang/Object;
   #79 = Utf8               schedule
   #80 = Utf8               (Ljava/util/concurrent/ExecutorService;Lscala/Function0;)Lscala/Function1;
   #81 = Utf8               <A:Ljava/lang/Object;>(Ljava/util/concurrent/ExecutorService;Lscala/Function0<TA;>;)Lscala/Function1<Lscala/concurrent/ExecutionContext;Lscala/concurrent/Future<TA;>;>;
   #82 = Utf8               pool
   #83 = NameAndType        #10:#11       // $outer:Lcoursier/util/PlatformTaskCompanion;
   #84 = Fieldref           #2.#83        // coursier/util/PlatformTaskCompanion$$anon$2.$outer:Lcoursier/util/PlatformTaskCompanion;
   #85 = NameAndType        #79:#80       // schedule:(Ljava/util/concurrent/ExecutorService;Lscala/Function0;)Lscala/Function1;
   #86 = Methodref          #9.#85        // coursier/util/PlatformTaskCompanion.schedule:(Ljava/util/concurrent/ExecutorService;Lscala/Function0;)Lscala/Function1;
   #87 = Utf8               Ljava/util/concurrent/ExecutorService;
   #88 = Utf8               (Ljava/lang/Object;Lscala/PartialFunction;)Ljava/lang/Object;
   #89 = Utf8               coursier/util/Task
   #90 = Class              #89           // coursier/util/Task
   #91 = Utf8               value
   #92 = Utf8               ()Lscala/Function1;
   #93 = NameAndType        #91:#92       // value:()Lscala/Function1;
   #94 = Methodref          #90.#93       // coursier/util/Task.value:()Lscala/Function1;
   #95 = NameAndType        #63:#64       // handle:(Lscala/Function1;Lscala/PartialFunction;)Lscala/Function1;
   #96 = Methodref          #2.#95        // coursier/util/PlatformTaskCompanion$$anon$2.handle:(Lscala/Function1;Lscala/PartialFunction;)Lscala/Function1;
   #97 = Utf8               <init>
   #98 = Utf8               (Lscala/Function1;)V
   #99 = NameAndType        #97:#98       // "<init>":(Lscala/Function1;)V
  #100 = Methodref          #90.#99       // coursier/util/Task."<init>":(Lscala/Function1;)V
  #101 = Utf8               (Lscala/util/Either;)Ljava/lang/Object;
  #102 = NameAndType        #55:#56       // fromAttempt:(Lscala/util/Either;)Lscala/Function1;
  #103 = Methodref          #2.#102       // coursier/util/PlatformTaskCompanion$$anon$2.fromAttempt:(Lscala/util/Either;)Lscala/Function1;
  #104 = Utf8               (Lscala/Function0;)Ljava/lang/Object;
  #105 = NameAndType        #47:#48       // delay:(Lscala/Function0;)Lscala/Function1;
  #106 = Methodref          #2.#105       // coursier/util/PlatformTaskCompanion$$anon$2.delay:(Lscala/Function0;)Lscala/Function1;
  #107 = Utf8               (Lscala/collection/immutable/Seq;)Ljava/lang/Object;
  #108 = NameAndType        #38:#39       // gather:(Lscala/collection/immutable/Seq;)Lscala/Function1;
  #109 = Methodref          #2.#108       // coursier/util/PlatformTaskCompanion$$anon$2.gather:(Lscala/collection/immutable/Seq;)Lscala/Function1;
  #110 = Utf8               (Ljava/lang/Object;Lscala/Function1;)Ljava/lang/Object;
  #111 = NameAndType        #33:#24       // map:(Lscala/Function1;Lscala/Function1;)Lscala/Function1;
  #112 = Methodref          #2.#111       // coursier/util/PlatformTaskCompanion$$anon$2.map:(Lscala/Function1;Lscala/Function1;)Lscala/Function1;
  #113 = NameAndType        #23:#24       // bind:(Lscala/Function1;Lscala/Function1;)Lscala/Function1;
  #114 = Methodref          #2.#113       // coursier/util/PlatformTaskCompanion$$anon$2.bind:(Lscala/Function1;Lscala/Function1;)Lscala/Function1;
  #115 = NameAndType        #12:#13       // point:(Ljava/lang/Object;)Lscala/Function1;
  #116 = Methodref          #2.#115       // coursier/util/PlatformTaskCompanion$$anon$2.point:(Ljava/lang/Object;)Lscala/Function1;
  #117 = Utf8               (Ljava/util/concurrent/ExecutorService;Lscala/Function0;)Ljava/lang/Object;
  #118 = Methodref          #2.#85        // coursier/util/PlatformTaskCompanion$$anon$2.schedule:(Ljava/util/concurrent/ExecutorService;Lscala/Function0;)Lscala/Function1;
  #119 = Utf8               (Lcoursier/util/PlatformTaskCompanion;)V
  #120 = Utf8               ()V
  #121 = NameAndType        #97:#120      // "<init>":()V
  #122 = Methodref          #4.#121       // java/lang/Object."<init>":()V
  #123 = Utf8               coursier/util/Monad
  #124 = Class              #123          // coursier/util/Monad
  #125 = Utf8               $init$
  #126 = Utf8               (Lcoursier/util/Monad;)V
  #127 = NameAndType        #125:#126     // $init$:(Lcoursier/util/Monad;)V
  #128 = InterfaceMethodref #124.#127     // coursier/util/Monad.$init$:(Lcoursier/util/Monad;)V
  #129 = Utf8               (Lcoursier/util/Sync;)V
  #130 = NameAndType        #125:#129     // $init$:(Lcoursier/util/Sync;)V
  #131 = InterfaceMethodref #74.#130      // coursier/util/Sync.$init$:(Lcoursier/util/Sync;)V
  #132 = Utf8               (Lcoursier/util/TaskSync;)V
  #133 = NameAndType        #125:#132     // $init$:(Lcoursier/util/TaskSync;)V
  #134 = InterfaceMethodref #6.#133       // coursier/util/TaskSync.$init$:(Lcoursier/util/TaskSync;)V
  #135 = Utf8               Code
  #136 = Utf8               LineNumberTable
  #137 = Utf8               LocalVariableTable
  #138 = Utf8               Signature
  #139 = Utf8               MethodParameters
  #140 = Utf8               StackMapTable
  #141 = Utf8               InnerClasses
  #142 = Utf8               EnclosingMethod
  #143 = Utf8               SourceFile
  #144 = Utf8               ScalaInlineInfo
  #145 = Utf8               Scala
{
  private final coursier.util.PlatformTaskCompanion $outer;
    descriptor: Lcoursier/util/PlatformTaskCompanion;
    flags: (0x1012) ACC_PRIVATE, ACC_FINAL, ACC_SYNTHETIC

  public <A extends java.lang.Object> scala.Function1<scala.concurrent.ExecutionContext, scala.concurrent.Future<A>> point(A);
    descriptor: (Ljava/lang/Object;)Lscala/Function1;
    flags: (0x0001) ACC_PUBLIC
    Code:
      stack=2, locals=2, args_size=2
         0: aload_0
         1: aload_1
         2: invokestatic  #19                 // InterfaceMethod coursier/util/TaskSync.point$:(Lcoursier/util/TaskSync;Ljava/lang/Object;)Lscala/Function1;
         5: areturn
      LineNumberTable:
        line 35: 0
      LocalVariableTable:
        Start  Length  Slot  Name   Signature
            0       6     0  this   Lcoursier/util/PlatformTaskCompanion$$anon$2;
            0       6     1     a   Ljava/lang/Object;
    Signature: #14                          // <A:Ljava/lang/Object;>(TA;)Lscala/Function1<Lscala/concurrent/ExecutionContext;Lscala/concurrent/Future<TA;>;>;
    MethodParameters:
      Name                           Flags
      a                              final

  public <A extends java.lang.Object, B extends java.lang.Object> scala.Function1<scala.concurrent.ExecutionContext, scala.concurrent.Future<B>> bind(scala.Function1<scala.concurrent.ExecutionContext, scala.concurrent.Future<A>>, scala.Function1<A, coursier.util.Task<B>>);
    descriptor: (Lscala/Function1;Lscala/Function1;)Lscala/Function1;
    flags: (0x0001) ACC_PUBLIC
    Code:
      stack=3, locals=3, args_size=3
         0: aload_0
         1: aload_1
         2: aload_2
         3: invokestatic  #31                 // InterfaceMethod coursier/util/TaskSync.bind$:(Lcoursier/util/TaskSync;Lscala/Function1;Lscala/Function1;)Lscala/Function1;
         6: areturn
      LineNumberTable:
        line 35: 0
      LocalVariableTable:
        Start  Length  Slot  Name   Signature
            0       7     0  this   Lcoursier/util/PlatformTaskCompanion$$anon$2;
            0       7     1  elem   Lscala/Function1;
            0       7     2     f   Lscala/Function1;
    Signature: #25                          // <A:Ljava/lang/Object;B:Ljava/lang/Object;>(Lscala/Function1<Lscala/concurrent/ExecutionContext;Lscala/concurrent/Future<TA;>;>;Lscala/Function1<TA;Lcoursier/util/Task<TB;>;>;)Lscala/Function1<Lscala/concurrent/ExecutionContext;Lscala/concurrent/Future<TB;>;>;
    MethodParameters:
      Name                           Flags
      elem                           final
      f                              final

  public <A extends java.lang.Object, B extends java.lang.Object> scala.Function1<scala.concurrent.ExecutionContext, scala.concurrent.Future<B>> map(scala.Function1<scala.concurrent.ExecutionContext, scala.concurrent.Future<A>>, scala.Function1<A, B>);
    descriptor: (Lscala/Function1;Lscala/Function1;)Lscala/Function1;
    flags: (0x0001) ACC_PUBLIC
    Code:
      stack=3, locals=3, args_size=3
         0: aload_0
         1: aload_1
         2: aload_2
         3: invokestatic  #37                 // InterfaceMethod coursier/util/TaskSync.map$:(Lcoursier/util/TaskSync;Lscala/Function1;Lscala/Function1;)Lscala/Function1;
         6: areturn
      LineNumberTable:
        line 35: 0
      LocalVariableTable:
        Start  Length  Slot  Name   Signature
            0       7     0  this   Lcoursier/util/PlatformTaskCompanion$$anon$2;
            0       7     1  elem   Lscala/Function1;
            0       7     2     f   Lscala/Function1;
    Signature: #34                          // <A:Ljava/lang/Object;B:Ljava/lang/Object;>(Lscala/Function1<Lscala/concurrent/ExecutionContext;Lscala/concurrent/Future<TA;>;>;Lscala/Function1<TA;TB;>;)Lscala/Function1<Lscala/concurrent/ExecutionContext;Lscala/concurrent/Future<TB;>;>;
    MethodParameters:
      Name                           Flags
      elem                           final
      f                              final

  public <A extends java.lang.Object> scala.Function1<scala.concurrent.ExecutionContext, scala.concurrent.Future<scala.collection.immutable.Seq<A>>> gather(scala.collection.immutable.Seq<coursier.util.Task<A>>);
    descriptor: (Lscala/collection/immutable/Seq;)Lscala/Function1;
    flags: (0x0001) ACC_PUBLIC
    Code:
      stack=2, locals=2, args_size=2
         0: aload_0
         1: aload_1
         2: invokestatic  #45                 // InterfaceMethod coursier/util/TaskSync.gather$:(Lcoursier/util/TaskSync;Lscala/collection/immutable/Seq;)Lscala/Function1;
         5: areturn
      LineNumberTable:
        line 35: 0
      LocalVariableTable:
        Start  Length  Slot  Name   Signature
            0       6     0  this   Lcoursier/util/PlatformTaskCompanion$$anon$2;
            0       6     1 elems   Lscala/collection/immutable/Seq;
    Signature: #40                          // <A:Ljava/lang/Object;>(Lscala/collection/immutable/Seq<Lcoursier/util/Task<TA;>;>;)Lscala/Function1<Lscala/concurrent/ExecutionContext;Lscala/concurrent/Future<Lscala/collection/immutable/Seq<TA;>;>;>;
    MethodParameters:
      Name                           Flags
      elems                          final

  public <A extends java.lang.Object> scala.Function1<scala.concurrent.ExecutionContext, scala.concurrent.Future<A>> delay(scala.Function0<A>);
    descriptor: (Lscala/Function0;)Lscala/Function1;
    flags: (0x0001) ACC_PUBLIC
    Code:
      stack=2, locals=2, args_size=2
         0: aload_0
         1: aload_1
         2: invokestatic  #53                 // InterfaceMethod coursier/util/TaskSync.delay$:(Lcoursier/util/TaskSync;Lscala/Function0;)Lscala/Function1;
         5: areturn
      LineNumberTable:
        line 35: 0
      LocalVariableTable:
        Start  Length  Slot  Name   Signature
            0       6     0  this   Lcoursier/util/PlatformTaskCompanion$$anon$2;
            0       6     1     a   Lscala/Function0;
    Signature: #49                          // <A:Ljava/lang/Object;>(Lscala/Function0<TA;>;)Lscala/Function1<Lscala/concurrent/ExecutionContext;Lscala/concurrent/Future<TA;>;>;
    MethodParameters:
      Name                           Flags
      a                              final

  public <A extends java.lang.Object> scala.Function1<scala.concurrent.ExecutionContext, scala.concurrent.Future<A>> fromAttempt(scala.util.Either<java.lang.Throwable, A>);
    descriptor: (Lscala/util/Either;)Lscala/Function1;
    flags: (0x0001) ACC_PUBLIC
    Code:
      stack=2, locals=2, args_size=2
         0: aload_0
         1: aload_1
         2: invokestatic  #61                 // InterfaceMethod coursier/util/TaskSync.fromAttempt$:(Lcoursier/util/TaskSync;Lscala/util/Either;)Lscala/Function1;
         5: areturn
      LineNumberTable:
        line 35: 0
      LocalVariableTable:
        Start  Length  Slot  Name   Signature
            0       6     0  this   Lcoursier/util/PlatformTaskCompanion$$anon$2;
            0       6     1     a   Lscala/util/Either;
    Signature: #57                          // <A:Ljava/lang/Object;>(Lscala/util/Either<Ljava/lang/Throwable;TA;>;)Lscala/Function1<Lscala/concurrent/ExecutionContext;Lscala/concurrent/Future<TA;>;>;
    MethodParameters:
      Name                           Flags
      a                              final

  public <A extends java.lang.Object> scala.Function1<scala.concurrent.ExecutionContext, scala.concurrent.Future<A>> handle(scala.Function1<scala.concurrent.ExecutionContext, scala.concurrent.Future<A>>, scala.PartialFunction<java.lang.Throwable, A>);
    descriptor: (Lscala/Function1;Lscala/PartialFunction;)Lscala/Function1;
    flags: (0x0001) ACC_PUBLIC
    Code:
      stack=3, locals=3, args_size=3
         0: aload_0
         1: aload_1
         2: aload_2
         3: invokestatic  #69                 // InterfaceMethod coursier/util/TaskSync.handle$:(Lcoursier/util/TaskSync;Lscala/Function1;Lscala/PartialFunction;)Lscala/Function1;
         6: areturn
      LineNumberTable:
        line 35: 0
      LocalVariableTable:
        Start  Length  Slot  Name   Signature
            0       7     0  this   Lcoursier/util/PlatformTaskCompanion$$anon$2;
            0       7     1     a   Lscala/Function1;
            0       7     2     f   Lscala/PartialFunction;
    Signature: #65                          // <A:Ljava/lang/Object;>(Lscala/Function1<Lscala/concurrent/ExecutionContext;Lscala/concurrent/Future<TA;>;>;Lscala/PartialFunction<Ljava/lang/Throwable;TA;>;)Lscala/Function1<Lscala/concurrent/ExecutionContext;Lscala/concurrent/Future<TA;>;>;
    MethodParameters:
      Name                           Flags
      a                              final
      f                              final

  public java.lang.Object attempt(java.lang.Object);
    descriptor: (Ljava/lang/Object;)Ljava/lang/Object;
    flags: (0x0001) ACC_PUBLIC
    Code:
      stack=2, locals=2, args_size=2
         0: aload_0
         1: aload_1
         2: invokestatic  #78                 // InterfaceMethod coursier/util/Sync.attempt$:(Lcoursier/util/Sync;Ljava/lang/Object;)Ljava/lang/Object;
         5: areturn
      LineNumberTable:
        line 35: 0
      LocalVariableTable:
        Start  Length  Slot  Name   Signature
            0       6     0  this   Lcoursier/util/PlatformTaskCompanion$$anon$2;
            0       6     1     f   Ljava/lang/Object;
    MethodParameters:
      Name                           Flags
      f                              final

  public <A extends java.lang.Object> scala.Function1<scala.concurrent.ExecutionContext, scala.concurrent.Future<A>> schedule(java.util.concurrent.ExecutorService, scala.Function0<A>);
    descriptor: (Ljava/util/concurrent/ExecutorService;Lscala/Function0;)Lscala/Function1;
    flags: (0x0001) ACC_PUBLIC
    Code:
      stack=3, locals=3, args_size=3
         0: aload_0
         1: getfield      #84                 // Field $outer:Lcoursier/util/PlatformTaskCompanion;
         4: aload_1
         5: aload_2
         6: invokevirtual #86                 // Method coursier/util/PlatformTaskCompanion.schedule:(Ljava/util/concurrent/ExecutorService;Lscala/Function0;)Lscala/Function1;
         9: areturn
      LineNumberTable:
        line 36: 0
      LocalVariableTable:
        Start  Length  Slot  Name   Signature
            0      10     0  this   Lcoursier/util/PlatformTaskCompanion$$anon$2;
            0      10     1  pool   Ljava/util/concurrent/ExecutorService;
            0      10     2     f   Lscala/Function0;
    Signature: #81                          // <A:Ljava/lang/Object;>(Ljava/util/concurrent/ExecutorService;Lscala/Function0<TA;>;)Lscala/Function1<Lscala/concurrent/ExecutionContext;Lscala/concurrent/Future<TA;>;>;
    MethodParameters:
      Name                           Flags
      pool                           final
      f                              final

  public java.lang.Object handle(java.lang.Object, scala.PartialFunction);
    descriptor: (Ljava/lang/Object;Lscala/PartialFunction;)Ljava/lang/Object;
    flags: (0x1041) ACC_PUBLIC, ACC_BRIDGE, ACC_SYNTHETIC
    Code:
      stack=5, locals=3, args_size=3
         0: new           #90                 // class coursier/util/Task
         3: dup
         4: aload_0
         5: aload_1
         6: checkcast     #90                 // class coursier/util/Task
         9: invokevirtual #94                 // Method coursier/util/Task.value:()Lscala/Function1;
        12: aload_2
        13: invokevirtual #96                 // Method handle:(Lscala/Function1;Lscala/PartialFunction;)Lscala/Function1;
        16: invokespecial #100                // Method coursier/util/Task."<init>":(Lscala/Function1;)V
        19: areturn
      LineNumberTable:
        line 35: 0
      LocalVariableTable:
        Start  Length  Slot  Name   Signature
            0      20     0  this   Lcoursier/util/PlatformTaskCompanion$$anon$2;
            0      20     1     a   Ljava/lang/Object;
            0      20     2     f   Lscala/PartialFunction;
    MethodParameters:
      Name                           Flags
      a                              final
      f                              final

  public java.lang.Object fromAttempt(scala.util.Either);
    descriptor: (Lscala/util/Either;)Ljava/lang/Object;
    flags: (0x1041) ACC_PUBLIC, ACC_BRIDGE, ACC_SYNTHETIC
    Code:
      stack=4, locals=2, args_size=2
         0: new           #90                 // class coursier/util/Task
         3: dup
         4: aload_0
         5: aload_1
         6: invokevirtual #103                // Method fromAttempt:(Lscala/util/Either;)Lscala/Function1;
         9: invokespecial #100                // Method coursier/util/Task."<init>":(Lscala/Function1;)V
        12: areturn
      LineNumberTable:
        line 35: 0
      LocalVariableTable:
        Start  Length  Slot  Name   Signature
            0      13     0  this   Lcoursier/util/PlatformTaskCompanion$$anon$2;
            0      13     1     a   Lscala/util/Either;
    MethodParameters:
      Name                           Flags
      a                              final

  public java.lang.Object delay(scala.Function0);
    descriptor: (Lscala/Function0;)Ljava/lang/Object;
    flags: (0x1041) ACC_PUBLIC, ACC_BRIDGE, ACC_SYNTHETIC
    Code:
      stack=4, locals=2, args_size=2
         0: new           #90                 // class coursier/util/Task
         3: dup
         4: aload_0
         5: aload_1
         6: invokevirtual #106                // Method delay:(Lscala/Function0;)Lscala/Function1;
         9: invokespecial #100                // Method coursier/util/Task."<init>":(Lscala/Function1;)V
        12: areturn
      LineNumberTable:
        line 35: 0
      LocalVariableTable:
        Start  Length  Slot  Name   Signature
            0      13     0  this   Lcoursier/util/PlatformTaskCompanion$$anon$2;
            0      13     1     a   Lscala/Function0;
    MethodParameters:
      Name                           Flags
      a                              final

  public java.lang.Object gather(scala.collection.immutable.Seq);
    descriptor: (Lscala/collection/immutable/Seq;)Ljava/lang/Object;
    flags: (0x1041) ACC_PUBLIC, ACC_BRIDGE, ACC_SYNTHETIC
    Code:
      stack=4, locals=2, args_size=2
         0: new           #90                 // class coursier/util/Task
         3: dup
         4: aload_0
         5: aload_1
         6: invokevirtual #109                // Method gather:(Lscala/collection/immutable/Seq;)Lscala/Function1;
         9: invokespecial #100                // Method coursier/util/Task."<init>":(Lscala/Function1;)V
        12: areturn
      LineNumberTable:
        line 35: 0
      LocalVariableTable:
        Start  Length  Slot  Name   Signature
            0      13     0  this   Lcoursier/util/PlatformTaskCompanion$$anon$2;
            0      13     1 elems   Lscala/collection/immutable/Seq;
    MethodParameters:
      Name                           Flags
      elems                          final

  public java.lang.Object map(java.lang.Object, scala.Function1);
    descriptor: (Ljava/lang/Object;Lscala/Function1;)Ljava/lang/Object;
    flags: (0x1041) ACC_PUBLIC, ACC_BRIDGE, ACC_SYNTHETIC
    Code:
      stack=5, locals=3, args_size=3
         0: new           #90                 // class coursier/util/Task
         3: dup
         4: aload_0
         5: aload_1
         6: checkcast     #90                 // class coursier/util/Task
         9: invokevirtual #94                 // Method coursier/util/Task.value:()Lscala/Function1;
        12: aload_2
        13: invokevirtual #112                // Method map:(Lscala/Function1;Lscala/Function1;)Lscala/Function1;
        16: invokespecial #100                // Method coursier/util/Task."<init>":(Lscala/Function1;)V
        19: areturn
      LineNumberTable:
        line 35: 0
      LocalVariableTable:
        Start  Length  Slot  Name   Signature
            0      20     0  this   Lcoursier/util/PlatformTaskCompanion$$anon$2;
            0      20     1  elem   Ljava/lang/Object;
            0      20     2     f   Lscala/Function1;
    MethodParameters:
      Name                           Flags
      elem                           final
      f                              final

  public java.lang.Object bind(java.lang.Object, scala.Function1);
    descriptor: (Ljava/lang/Object;Lscala/Function1;)Ljava/lang/Object;
    flags: (0x1041) ACC_PUBLIC, ACC_BRIDGE, ACC_SYNTHETIC
    Code:
      stack=5, locals=3, args_size=3
         0: new           #90                 // class coursier/util/Task
         3: dup
         4: aload_0
         5: aload_1
         6: checkcast     #90                 // class coursier/util/Task
         9: invokevirtual #94                 // Method coursier/util/Task.value:()Lscala/Function1;
        12: aload_2
        13: invokevirtual #114                // Method bind:(Lscala/Function1;Lscala/Function1;)Lscala/Function1;
        16: invokespecial #100                // Method coursier/util/Task."<init>":(Lscala/Function1;)V
        19: areturn
      LineNumberTable:
        line 35: 0
      LocalVariableTable:
        Start  Length  Slot  Name   Signature
            0      20     0  this   Lcoursier/util/PlatformTaskCompanion$$anon$2;
            0      20     1  elem   Ljava/lang/Object;
            0      20     2     f   Lscala/Function1;
    MethodParameters:
      Name                           Flags
      elem                           final
      f                              final

  public java.lang.Object point(java.lang.Object);
    descriptor: (Ljava/lang/Object;)Ljava/lang/Object;
    flags: (0x1041) ACC_PUBLIC, ACC_BRIDGE, ACC_SYNTHETIC
    Code:
      stack=4, locals=2, args_size=2
         0: new           #90                 // class coursier/util/Task
         3: dup
         4: aload_0
         5: aload_1
         6: invokevirtual #116                // Method point:(Ljava/lang/Object;)Lscala/Function1;
         9: invokespecial #100                // Method coursier/util/Task."<init>":(Lscala/Function1;)V
        12: areturn
      LineNumberTable:
        line 35: 0
      LocalVariableTable:
        Start  Length  Slot  Name   Signature
            0      13     0  this   Lcoursier/util/PlatformTaskCompanion$$anon$2;
            0      13     1     a   Ljava/lang/Object;
    MethodParameters:
      Name                           Flags
      a                              final

  public java.lang.Object schedule(java.util.concurrent.ExecutorService, scala.Function0);
    descriptor: (Ljava/util/concurrent/ExecutorService;Lscala/Function0;)Ljava/lang/Object;
    flags: (0x1041) ACC_PUBLIC, ACC_BRIDGE, ACC_SYNTHETIC
    Code:
      stack=5, locals=3, args_size=3
         0: new           #90                 // class coursier/util/Task
         3: dup
         4: aload_0
         5: aload_1
         6: aload_2
         7: invokevirtual #118                // Method schedule:(Ljava/util/concurrent/ExecutorService;Lscala/Function0;)Lscala/Function1;
        10: invokespecial #100                // Method coursier/util/Task."<init>":(Lscala/Function1;)V
        13: areturn
      LineNumberTable:
        line 35: 0
      LocalVariableTable:
        Start  Length  Slot  Name   Signature
            0      14     0  this   Lcoursier/util/PlatformTaskCompanion$$anon$2;
            0      14     1  pool   Ljava/util/concurrent/ExecutorService;
            0      14     2     f   Lscala/Function0;
    MethodParameters:
      Name                           Flags
      pool                           final
      f                              final

  public coursier.util.PlatformTaskCompanion$$anon$2(coursier.util.PlatformTaskCompanion);
    descriptor: (Lcoursier/util/PlatformTaskCompanion;)V
    flags: (0x0001) ACC_PUBLIC
    Code:
      stack=2, locals=2, args_size=2
         0: aload_1
         1: ifnonnull     6
         4: aconst_null
         5: athrow
         6: aload_0
         7: aload_1
         8: putfield      #84                 // Field $outer:Lcoursier/util/PlatformTaskCompanion;
        11: aload_0
        12: invokespecial #122                // Method java/lang/Object."<init>":()V
        15: aload_0
        16: invokestatic  #128                // InterfaceMethod coursier/util/Monad.$init$:(Lcoursier/util/Monad;)V
        19: aload_0
        20: invokestatic  #131                // InterfaceMethod coursier/util/Sync.$init$:(Lcoursier/util/Sync;)V
        23: aload_0
        24: invokestatic  #134                // InterfaceMethod coursier/util/TaskSync.$init$:(Lcoursier/util/TaskSync;)V
        27: return
      StackMapTable: number_of_entries = 1
        frame_type = 6 /* same */
      LineNumberTable:
        line 35: 0
      LocalVariableTable:
        Start  Length  Slot  Name   Signature
            0      28     0  this   Lcoursier/util/PlatformTaskCompanion$$anon$2;
            0      28     1 $outer   Lcoursier/util/PlatformTaskCompanion;
    MethodParameters:
      Name                           Flags
      $outer                         final synthetic
}
InnerClasses:
  public final #2;                        // class coursier/util/PlatformTaskCompanion$$anon$2
EnclosingMethod: #9.#0                  // coursier.util.PlatformTaskCompanion
SourceFile: "PlatformTaskCompanion.scala"
  ScalaInlineInfo: length = 0x5E (unknown attribute)
   01 01 00 12 00 61 00 77 01 00 47 00 48 01 00 17
   00 6E 01 00 17 00 18 01 00 2F 00 68 01 00 2F 00
   30 01 00 37 00 65 01 00 37 00 38 01 00 26 00 6B
   01 00 26 00 27 01 00 3F 00 58 01 00 3F 00 40 01
   00 21 00 6E 01 00 21 00 18 01 00 0C 00 48 01 00
   0C 00 0D 01 00 4F 00 75 01 00 4F 00 50 01
  Scala: length = 0x0 (unknown attribute)

