Classfile /Users/mw/Projects/slang-braindump/.jar/jar11/assemble/slang-braindump/assemble/content/coursier/util/Task.class
  Last modified May 29, 2022; size 14713 bytes
  SHA-256 checksum 7e878f50d92148d79a91e6e0befc1cda12caab76840dc5e35e57fe73b94cc241
  Compiled from "Task.scala"
public final class coursier.util.Task<T extends java.lang.Object> extends java.lang.Object implements scala.Product, java.io.Serializable
  minor version: 0
  major version: 52
  flags: (0x0031) ACC_PUBLIC, ACC_FINAL, ACC_SUPER
  this_class: #2                          // coursier/util/Task
  super_class: #5                         // java/lang/Object
  interfaces: 2, fields: 1, methods: 49, attributes: 6
Constant pool:
    #1 = Utf8               coursier/util/Task
    #2 = Class              #1            // coursier/util/Task
    #3 = Utf8               <T:Ljava/lang/Object;>Ljava/lang/Object;Lscala/Product;Ljava/io/Serializable;
    #4 = Utf8               java/lang/Object
    #5 = Class              #4            // java/lang/Object
    #6 = Utf8               scala/Product
    #7 = Class              #6            // scala/Product
    #8 = Utf8               java/io/Serializable
    #9 = Class              #8            // java/io/Serializable
   #10 = Utf8               Task.scala
   #11 = Utf8               Lscala/reflect/ScalaSignature;
   #12 = Utf8               bytes
   #13 = Utf8               \u0006\u0005\u0011ua\u0001B\u001c9\u0005vB\u0001\u0002\u0016\u0001\u0003\u0016\u0004%\t!\u0016\u0005\t[\u0002\u0011\t\u0012)A\u0005-\")a\u000e\u0001C\u0001_\")1\u000f\u0001C\u0001i\")Q\u0010\u0001C\u0001}\"9\u00111\u0002\u0001\u0005\u0002\u00055\u0001bBA\u0014\u0001\u0011\u0005\u0011\u0011\u0006\u0005\b\u0003c\u0001A\u0011AA\u001a\u0011\u001d\ti\u0004\u0001C\u0001\u0003\u007fA\u0011\"a\u0019\u0001\u0003\u0003%\t!!\u001a\t\u0013\u0005U\u0004!%A\u0005\u0002\u0005]\u0004\"CAI\u0001\u0005\u0005I\u0011IAJ\u0011%\t\t\u000bAA\u0001\n\u0003\t\u0019\u000bC\u0005\u0002,\u0002\t\t\u0011\"\u0001\u0002.\"I\u00111\u0017\u0001\u0002\u0002\u0013\u0005\u0013Q\u0017\u0005\n\u0003\u0007\u0004\u0011\u0011!C\u0001\u0003\u000bD\u0011\"a4\u0001\u0003\u0003%\t%!5\t\u0013\u0005U\u0007!!A\u0005B\u0005]\u0007\"CAm\u0001\u0005\u0005I\u0011IAn\u0011%\ty\u000eAA\u0001\n\u0003\n\toB\u0004\u0002dbB\t!!:\u0007\r]B\u0004\u0012AAt\u0011\u0019qg\u0003\"\u0001\u0002z\"9\u00111 \f\u0005\u0002\u0005u\bb\u0002B\u0007-\u0011\u0005!q\u0002\u0005\b\u0005C1B\u0011\u0001B\u0012\u0011\u001d\u0011iC\u0006C\u0001\u0005_AqAa\u0010\u0017\t\u0003\u0011\t\u0005C\u0004\u0003HY!\tA!\u0013\t\u000f\t\u001dd\u0003\"\u0001\u0003j\u00191!1\u000f\f\u0003\u0005kB!Ba\u001e \u0005\u0003\u0005\u000b\u0011BA\u0011\u0011\u0019qw\u0004\"\u0001\u0003z!9!\u0011\u0011\f\u0005\n\t\r\u0005\"\u0003BM-\u0005\u0005I\u0011\u0011BN\u0011%\u0011YKFA\u0001\n\u0003\u0013i\u000bC\u0005\u0003FZ\t\t\u0011\"\u0003\u0003H\"9!q\u001a\f\u0005\u0006\tE\u0007b\u0002Bv-\u0011\u0015!Q\u001e\u0005\b\u0007\u000b1BQAB\u0004\u0011\u001d\u0019\tC\u0006C\u0003\u0007GAqaa\u000e\u0017\t\u000b\u0019I\u0004C\u0004\u0004JY!)aa\u0013\t\u0013\ruc#!A\u0005\u0006\r}\u0003\"CB=-E\u0005IQAB>\u0011%\u0019yIFA\u0001\n\u000b\u0019\t\nC\u0005\u0004\u001eZ\t\t\u0011\"\u0002\u0004 \"I11\u0016\f\u0002\u0002\u0013\u00151Q\u0016\u0005\n\u0007{3\u0012\u0011!C\u0003\u0007\u007fC\u0011ba3\u0017\u0003\u0003%)a!4\t\u0013\rug#!A\u0005\u0006\r}\u0007\"CBx-\u0005\u0005IQABy\u0011%\u0019iPFA\u0001\n\u000b\u0019y\u0010C\u0005\u0005\u0010Y\t\t\u0011\"\u0002\u0005\u0012\t!A+Y:l\u0015\tI$(\u0001\u0003vi&d\'\"A\u001e\u0002\u0011\r|WO]:jKJ\u001c\u0001!\u0006\u0002?IN!\u0001aP#I!\t\u00015)D\u0001B\u0015\u0005\u0011\u0015!B:dC2\f\u0017B\u0001#B\u0005\u0019\te.\u001f,bYB\u0011\u0001IR\u0005\u0003\u000f\u0006\u0013q\u0001\u0015:pIV\u001cG\u000f\u0005\u0002J#:\u0011!j\u0014\b\u0003\u0017:k\u0011\u0001\u0014\u0006\u0003\u001br\na\u0001\u0010:p_Rt\u0014\"\u0001\"\n\u0005A\u000b\u0015a\u00029bG.\fw-Z\u0005\u0003%N\u0013AbU3sS\u0006d\u0017N_1cY\u0016T!\u0001U!\u0002\u000bY\fG.^3\u0016\u0003Y\u0003B\u0001Q,Z?&\u0011\u0001,\u0011\u0002\n\rVt7\r^5p]F\u0002\"AW/\u000e\u0003mS!\u0001X!\u0002\u0015\r|gnY;se\u0016tG/\u0003\u0002_7\n\u0001R\t_3dkRLwN\\\"p]R,\u0007\u0010\u001e\t\u00045\u0002\u0014\u0017BA1\\\u0005\u00191U\u000f^;sKB\u00111\r\u001a\u0007\u0001\t\u0019)\u0007\u0001\"b\u0001M\n\tA+\u0005\u0002hUB\u0011\u0001\t[\u0005\u0003S\u0006\u0013qAT8uQ&tw\r\u0005\u0002AW&\u0011A.\u0011\u0002\u0004\u0003:L\u0018A\u0002<bYV,\u0007%\u0001\u0004=S:LGO\u0010\u000b\u0003aJ\u00042!\u001d\u0001c\u001b\u0005A\u0004\"\u0002+\u0004\u0001\u00041\u0016aA7baV\u0011Q\u000f\u001f\u000b\u0003mj\u00042!\u001d\u0001x!\t\u0019\u0007\u0010B\u0003z\t\t\u0007aMA\u0001V\u0011\u0015YH\u00011\u0001}\u0003\u00051\u0007\u0003\u0002!XE^\fqA\u001a7bi6\u000b\u0007/F\u0002\u0000\u0003\u000b!B!!\u0001\u0002\bA!\u0011\u000fAA\u0002!\r\u0019\u0017Q\u0001\u0003\u0006s\u0016\u0011\rA\u001a\u0005\u0007w\u0016\u0001\r!!\u0003\u0011\u000b\u0001;&-!\u0001\u0002\r!\fg\u000e\u001a7f+\u0011\ty!!\u0006\u0015\t\u0005E\u0011\u0011\u0004\t\u0005c\u0002\t\u0019\u0002E\u0002d\u0003+!a!\u001f\u0004C\u0002\u0005]\u0011C\u00012k\u0011\u0019Yh\u00011\u0001\u0002\u001cA9\u0001)!\b\u0002\"\u0005M\u0011bAA\u0010\u0003\ny\u0001+\u0019:uS\u0006dg)\u001e8di&|g\u000eE\u0002J\u0003GI1!!\nT\u0005%!\u0006N]8xC\ndW-\u0001\u0004gkR,(/\u001a\u000b\u0003\u0003W!2aXA\u0017\u0011\u0019\tyc\u0002a\u00023\u0006\u0011QmY\u0001\bCR$X-\u001c9u+\t\t)\u0004\u0005\u0003r\u0001\u0005]\u0002CB%\u0002:\u0005\u0005\"-C\u0002\u0002<M\u0013a!R5uQ\u0016\u0014\u0018\u0001C:dQ\u0016$W\u000f\\3\u0015\u000bA\f\t%a\u0014\t\u000f\u0005\r\u0013\u00021\u0001\u0002F\u0005AA-\u001e:bi&|g\u000e\u0005\u0003\u0002H\u0005-SBAA%\u0015\r\t\u0019eW\u0005\u0005\u0003\u001b\nIE\u0001\u0005EkJ\fG/[8o\u0011\u001d\t\t&\u0003a\u0001\u0003\'\n!!Z:\u0011\t\u0005U\u0013qL\u0007\u0003\u0003/R1\u0001XA-\u0015\rI\u00141\f\u0006\u0003\u0003;\nAA[1wC&!\u0011\u0011MA,\u0005a\u00196\r[3ek2,G-\u0012=fGV$xN]*feZL7-Z\u0001\u0005G>\u0004\u00180\u0006\u0003\u0002h\u00055D\u0003BA5\u0003_\u0002B!\u001d\u0001\u0002lA\u00191-!\u001c\u0005\u000b\u0015T!\u0019\u00014\t\u0011QS\u0001\u0013!a\u0001\u0003c\u0002R\u0001Q,Z\u0003g\u0002BA\u00171\u0002l\u0005q1m\u001c9zI\u0011,g-Y;mi\u0012\nT\u0003BA=\u0003\u001f+\"!a\u001f+\u0007Y\u000bih\u000b\u0002\u0002\u0000A!\u0011\u0011QAF\u001b\t\t\u0019I\u0003\u0003\u0002\u0006\u0006\u001d\u0015!C;oG\",7m[3e\u0015\r\tI)Q\u0001\u000bC:tw\u000e^1uS>t\u0017\u0002BAG\u0003\u0007\u0013\u0011#\u001e8dQ\u0016\u001c7.\u001a3WCJL\u0017M\\2f\t\u0015)7B1\u0001g\u00035\u0001(o\u001c3vGR\u0004&/\u001a4jqV\u0011\u0011Q\u0013\t\u0005\u0003/\u000bi*\u0004\u0002\u0002\u001a*!\u00111TA.\u0003\u0011a\u0017M\\4\n\t\u0005}\u0015\u0011\u0014\u0002\u0007\'R\u0014\u0018N\\4\u0002\u0019A\u0014x\u000eZ;di\u0006\u0013\u0018\u000e^=\u0016\u0005\u0005\u0015\u0006c\u0001!\u0002(&\u0019\u0011\u0011V!\u0003\u0007%sG/\u0001\bqe>$Wo\u0019;FY\u0016lWM\u001c;\u0015\u0007)\fy\u000bC\u0005\u00022:\t\t\u00111\u0001\u0002&\u0006\u0019\u0001\u0010J\u0019\u0002\u001fA\u0014x\u000eZ;di&#XM]1u_J,\"!a.\u0011\u000b\u0005e\u0016q\u00186\u000e\u0005\u0005m&bAA_\u0003\u0006Q1m\u001c7mK\u000e$\u0018n\u001c8\n\t\u0005\u0005\u00171\u0018\u0002\t\u0013R,\'/\u0019;pe\u0006A1-\u00198FcV\fG\u000e\u0006\u0003\u0002H\u00065\u0007c\u0001!\u0002J&\u0019\u00111Z!\u0003\u000f\t{w\u000e\\3b]\"A\u0011\u0011\u0017\t\u0002\u0002\u0003\u0007!.\u0001\nqe>$Wo\u0019;FY\u0016lWM\u001c;OC6,G\u0003BAK\u0003\'D\u0011\"!-\u0012\u0003\u0003\u0005\r!!*\u0002\u0011!\f7\u000f[\"pI\u0016$\"!!*\u0002\r\u0015\fX/\u00197t)\u0011\t9-!8\t\u0011\u0005E6#!AA\u0002)\f\u0001\u0002^8TiJLgn\u001a\u000b\u0003\u0003+\u000bA\u0001V1tWB\u0011\u0011OF\n\u0006-\u0005%\u0018q\u001e\t\u0004c\u0006-\u0018bAAwq\t)\u0002\u000b\\1uM>\u0014X\u000eV1tW\u000e{W\u000e]1oS>t\u0007\u0003BAy\u0003ol!!a=\u000b\t\u0005U\u00181L\u0001\u0003S>L1AUAz)\t\t)/A\u0003q_&tG/\u0006\u0003\u0002\u0000\n\u0015A\u0003\u0002B\u0001\u0005\u0013\u0001B!\u001d\u0001\u0003\u0004A\u00191M!\u0002\u0005\r\t\u001d\u0001D1\u0001g\u0005\u0005\t\u0005b\u0002B\u00061\u0001\u0007!1A\u0001\u0002C\u0006)A-\u001a7bsV!!\u0011\u0003B\f)\u0011\u0011\u0019B!\u0007\u0011\tE\u0004!Q\u0003\t\u0004G\n]AA\u0002B\u00043\t\u0007a\r\u0003\u0005\u0003\fe!\t\u0019\u0001B\u000e!\u0015\u0001%Q\u0004B\u000b\u0013\r\u0011y\"\u0011\u0002\ty\tLh.Y7f}\u0005)a.\u001a<feV!!Q\u0005B\u0016+\t\u00119\u0003\u0005\u0003r\u0001\t%\u0002cA2\u0003,\u00111!q\u0001\u000eC\u0002\u0019\f!B\u001a:p[\u0016KG\u000f[3s+\u0011\u0011\tDa\u000e\u0015\t\tM\"\u0011\b\t\u0005c\u0002\u0011)\u0004E\u0002d\u0005o!Q!Z\u000eC\u0002\u0019DqAa\u000f\u001c\u0001\u0004\u0011i$A\u0001f!\u001dI\u0015\u0011HA\u0011\u0005k\tAAZ1jYR!!1\tB#!\r\t\ba\u001a\u0005\b\u0005wa\u0002\u0019AA\u0011\u0003!!\u0018-\u001b7SK\u000elUC\u0002B&\u0005?\u0012\u0019\u0006\u0006\u0003\u0003N\t\u0015D\u0003\u0002B(\u0005/\u0002B!\u001d\u0001\u0003RA\u00191Ma\u0015\u0005\r\tUSD1\u0001g\u0005\u0005\u0011\u0005b\u0002B-;\u0001\u0007!1L\u0001\u0003M:\u0004b\u0001Q,\u0003^\t\u0005\u0004cA2\u0003`\u00111!qA\u000fC\u0002\u0019\u0004B!\u001d\u0001\u0003dA9\u0011*!\u000f\u0003^\tE\u0003b\u0002B\u0006;\u0001\u0007!QL\u0001\u0007O\u0006$\b.\u001a:\u0016\u0005\t-\u0004#B9\u0003n\tE\u0014b\u0001B8q\t1q)\u0019;iKJ\u0004\"!\u001d\u0001\u0003!]\u0013\u0018\r\u001d9fI\u0016C8-\u001a9uS>t7cA\u0010\u0002\"\u0005)1-Y;tKR!!1\u0010B@!\r\u0011ihH\u0007\u0002-!9!qO\u0011A\u0002\u0005\u0005\u0012\u0001B<sCB,BA!\"\u0003\nR!!q\u0011BF!\r\u0019\'\u0011\u0012\u0003\u0006K\n\u0012\rA\u001a\u0005\t\u0005\u001b\u0013C\u00111\u0001\u0003\u0010\u0006\tA\u000fE\u0003A\u0005;\u00119\tK\u0002#\u0005\'\u00032\u0001\u0011BK\u0013\r\u00119*\u0011\u0002\u0007S:d\u0017N\\3\u0002\u000b\u0005\u0004\b\u000f\\=\u0016\t\tu%1\u0015\u000b\u0005\u0005?\u0013)\u000b\u0005\u0003r\u0001\t\u0005\u0006cA2\u0003$\u0012)Qm\tb\u0001M\"1Ak\ta\u0001\u0005O\u0003R\u0001Q,Z\u0005S\u0003BA\u00171\u0003\"\u00069QO\\1qa2LX\u0003\u0002BX\u0005{#BA!-\u0003@B)\u0001Ia-\u00038&\u0019!QW!\u0003\r=\u0003H/[8o!\u0015\u0001u+\u0017B]!\u0011Q\u0006Ma/\u0011\u0007\r\u0014i\fB\u0003fI\t\u0007a\rC\u0005\u0003B\u0012\n\t\u00111\u0001\u0003D\u0006\u0019\u0001\u0010\n\u0019\u0011\tE\u0004!1X\u0001\roJLG/\u001a*fa2\f7-\u001a\u000b\u0003\u0005\u0013\u0004B!a&\u0003L&!!QZAM\u0005\u0019y%M[3di\u0006iQ.\u00199%Kb$XM\\:j_:,bAa5\u0003\\\n\rH\u0003\u0002Bk\u0005K$BAa6\u0003^B!\u0011\u000f\u0001Bm!\r\u0019\'1\u001c\u0003\u0006s\u001a\u0012\rA\u001a\u0005\u0007w\u001a\u0002\rAa8\u0011\r\u0001;&\u0011\u001dBm!\r\u0019\'1\u001d\u0003\u0006K\u001a\u0012\rA\u001a\u0005\b\u0005O4\u0003\u0019\u0001Bu\u0003\u0015!C\u000f[5t!\u0011\t\bA!9\u0002#\u0019d\u0017\r^\'ba\u0012*\u0007\u0010^3og&|g.\u0006\u0004\u0003p\n](q \u000b\u0005\u0005c\u001c\t\u0001\u0006\u0003\u0003t\ne\b\u0003B9\u0001\u0005k\u00042a\u0019B|\t\u0015IxE1\u0001g\u0011\u0019Yx\u00051\u0001\u0003|B1\u0001i\u0016B\u007f\u0005g\u00042a\u0019B\u0000\t\u0015)wE1\u0001g\u0011\u001d\u00119o\na\u0001\u0007\u0007\u0001B!\u001d\u0001\u0003~\u0006\u0001\u0002.\u00198eY\u0016$S\r\u001f;f]NLwN\\\u000b\u0007\u0007\u0013\u0019\tba\u0006\u0015\t\r-1Q\u0004\u000b\u0005\u0007\u001b\u0019I\u0002\u0005\u0003r\u0001\r=\u0001cA2\u0004\u0012\u00111\u0011\u0010\u000bb\u0001\u0007\'\t2a!\u0006k!\r\u00197q\u0003\u0003\u0006K\"\u0012\rA\u001a\u0005\u0007w\"\u0002\raa\u0007\u0011\u000f\u0001\u000bi\"!\t\u0004\u0010!9!q\u001d\u0015A\u0002\r}\u0001\u0003B9\u0001\u0007+\t\u0001CZ;ukJ,G%\u001a=uK:\u001c\u0018n\u001c8\u0016\t\r\u00152q\u0006\u000b\u0005\u0007O\u0019\u0019\u0004\u0006\u0002\u0004*Q!11FB\u0019!\u0011Q\u0006m!\f\u0011\u0007\r\u001cy\u0003B\u0003fS\t\u0007a\r\u0003\u0004\u00020%\u0002\u001d!\u0017\u0005\b\u0005OL\u0003\u0019AB\u001b!\u0011\t\ba!\f\u0002#\u0005$H/Z7qi\u0012*\u0007\u0010^3og&|g.\u0006\u0003\u0004<\r\rC\u0003BB\u001f\u0007\u000b\u0002B!\u001d\u0001\u0004@A9\u0011*!\u000f\u0002\"\r\u0005\u0003cA2\u0004D\u0011)QM\u000bb\u0001M\"9!q\u001d\u0016A\u0002\r\u001d\u0003\u0003B9\u0001\u0007\u0003\n!c]2iK\u0012,H.\u001a\u0013fqR,gn]5p]V!1QJB+)\u0011\u0019yea\u0017\u0015\r\rE3qKB-!\u0011\t\baa\u0015\u0011\u0007\r\u001c)\u0006B\u0003fW\t\u0007a\rC\u0004\u0002D-\u0002\r!!\u0012\t\u000f\u0005E3\u00061\u0001\u0002T!9!q]\u0016A\u0002\rE\u0013AD2paf$S\r\u001f;f]NLwN\\\u000b\u0007\u0007C\u001aIga\u001e\u0015\t\r\r4\u0011\u000f\u000b\u0005\u0007K\u001aY\u0007\u0005\u0003r\u0001\r\u001d\u0004cA2\u0004j\u0011)Q\r\fb\u0001M\"AA\u000b\fI\u0001\u0002\u0004\u0019i\u0007E\u0003A/f\u001by\u0007\u0005\u0003[A\u000e\u001d\u0004b\u0002BtY\u0001\u000711\u000f\t\u0005c\u0002\u0019)\bE\u0002d\u0007o\"Q!\u001a\u0017C\u0002\u0019\f\u0001dY8qs\u0012\"WMZ1vYR$\u0013\u0007J3yi\u0016t7/[8o+\u0019\u0019ih!$\u0004\bR!1qPBEU\u0011\u0019\t)! \u0011\u000b\u0001;\u0016la!\u0011\ti\u00037Q\u0011\t\u0004G\u000e\u001dE!B3.\u0005\u00041\u0007b\u0002Bt[\u0001\u000711\u0012\t\u0005c\u0002\u0019)\tB\u0003f[\t\u0007a-A\fqe>$Wo\u0019;Qe\u00164\u0017\u000e\u001f\u0013fqR,gn]5p]V!11SBN)\u0011\t)j!&\t\u000f\t\u001dh\u00061\u0001\u0004\u0018B!\u0011\u000fABM!\r\u001971\u0014\u0003\u0006K:\u0012\rAZ\u0001\u0017aJ|G-^2u\u0003JLG/\u001f\u0013fqR,gn]5p]V!1\u0011UBU)\u0011\t)ka)\t\u000f\t\u001dx\u00061\u0001\u0004&B!\u0011\u000fABT!\r\u00197\u0011\u0016\u0003\u0006K>\u0012\rAZ\u0001\u0019aJ|G-^2u\u000b2,W.\u001a8uI\u0015DH/\u001a8tS>tW\u0003BBX\u0007w#Ba!-\u00046R\u0019!na-\t\u0013\u0005E\u0006\'!AA\u0002\u0005\u0015\u0006b\u0002Bta\u0001\u00071q\u0017\t\u0005c\u0002\u0019I\fE\u0002d\u0007w#Q!\u001a\u0019C\u0002\u0019\f\u0011\u0004\u001d:pIV\u001cG/\u0013;fe\u0006$xN\u001d\u0013fqR,gn]5p]V!1\u0011YBe)\u0011\t9la1\t\u000f\t\u001d\u0018\u00071\u0001\u0004FB!\u0011\u000fABd!\r\u00197\u0011\u001a\u0003\u0006KF\u0012\rAZ\u0001\u0013G\u0006tW)];bY\u0012*\u0007\u0010^3og&|g.\u0006\u0003\u0004P\u000emG\u0003BBi\u0007+$B!a2\u0004T\"A\u0011\u0011\u0017\u001a\u0002\u0002\u0003\u0007!\u000eC\u0004\u0003hJ\u0002\raa6\u0011\tE\u00041\u0011\u001c\t\u0004G\u000emG!B33\u0005\u00041\u0017\u0001\b9s_\u0012,8\r^#mK6,g\u000e\u001e(b[\u0016$S\r\u001f;f]NLwN\\\u000b\u0005\u0007C\u001ci\u000f\u0006\u0003\u0004d\u000e\u001dH\u0003BAK\u0007KD\u0011\"!-4\u0003\u0003\u0005\r!!*\t\u000f\t\u001d8\u00071\u0001\u0004jB!\u0011\u000fABv!\r\u00197Q\u001e\u0003\u0006KN\u0012\rAZ\u0001\u0013Q\u0006\u001c\bnQ8eK\u0012*\u0007\u0010^3og&|g.\u0006\u0003\u0004t\u000emH\u0003BAl\u0007kDqAa:5\u0001\u0004\u00199\u0010\u0005\u0003r\u0001\re\bcA2\u0004|\u0012)Q\r\u000eb\u0001M\u0006\u0001R-];bYN$S\r\u001f;f]NLwN\\\u000b\u0005\t\u0003!i\u0001\u0006\u0003\u0005\u0004\u0011\u001dA\u0003BAd\t\u000bA\u0001\"!-6\u0003\u0003\u0005\rA\u001b\u0005\b\u0005O,\u0004\u0019\u0001C\u0005!\u0011\t\b\u0001b\u0003\u0011\u0007\r$i\u0001B\u0003fk\t\u0007a-\u0001\nu_N#(/\u001b8hI\u0015DH/\u001a8tS>tW\u0003\u0002C\n\t7!B!!9\u0005\u0016!9!q\u001d\u001cA\u0002\u0011]\u0001\u0003B9\u0001\t3\u00012a\u0019C\u000e\t\u0015)gG1\u0001g\u0001
   #14 = Utf8               coursier/util/PlatformTaskCompanion$PlatformTaskOps
   #15 = Class              #14           // coursier/util/PlatformTaskCompanion$PlatformTaskOps
   #16 = Utf8               coursier/util/PlatformTaskCompanion
   #17 = Class              #16           // coursier/util/PlatformTaskCompanion
   #18 = Utf8               PlatformTaskOps
   #19 = Utf8               coursier/util/Task$$anon$1
   #20 = Class              #19           // coursier/util/Task$$anon$1
   #21 = Utf8               coursier/util/Task$$anonfun$attempt$extension$1
   #22 = Class              #21           // coursier/util/Task$$anonfun$attempt$extension$1
   #23 = Utf8               coursier/util/Task$WrappedException
   #24 = Class              #23           // coursier/util/Task$WrappedException
   #25 = Utf8               WrappedException
   #26 = Utf8               value
   #27 = Utf8               Lscala/Function1;
   #28 = Utf8               Lscala/Function1<Lscala/concurrent/ExecutionContext;Lscala/concurrent/Future<TT;>;>;
   #29 = Utf8               toString$extension
   #30 = Utf8               (Lscala/Function1;)Ljava/lang/String;
   #31 = Utf8               <T:Ljava/lang/Object;>(Lscala/Function1<Lscala/concurrent/ExecutionContext;Lscala/concurrent/Future<TT;>;>;)Ljava/lang/String;
   #32 = Utf8               $this
   #33 = Utf8               coursier/util/Task$
   #34 = Class              #33           // coursier/util/Task$
   #35 = Utf8               MODULE$
   #36 = Utf8               Lcoursier/util/Task$;
   #37 = NameAndType        #35:#36       // MODULE$:Lcoursier/util/Task$;
   #38 = Fieldref           #34.#37       // coursier/util/Task$.MODULE$:Lcoursier/util/Task$;
   #39 = NameAndType        #29:#30       // toString$extension:(Lscala/Function1;)Ljava/lang/String;
   #40 = Methodref          #34.#39       // coursier/util/Task$.toString$extension:(Lscala/Function1;)Ljava/lang/String;
   #41 = Utf8               equals$extension
   #42 = Utf8               (Lscala/Function1;Ljava/lang/Object;)Z
   #43 = Utf8               <T:Ljava/lang/Object;>(Lscala/Function1<Lscala/concurrent/ExecutionContext;Lscala/concurrent/Future<TT;>;>;Ljava/lang/Object;)Z
   #44 = Utf8               x$1
   #45 = NameAndType        #41:#42       // equals$extension:(Lscala/Function1;Ljava/lang/Object;)Z
   #46 = Methodref          #34.#45       // coursier/util/Task$.equals$extension:(Lscala/Function1;Ljava/lang/Object;)Z
   #47 = Utf8               hashCode$extension
   #48 = Utf8               (Lscala/Function1;)I
   #49 = Utf8               <T:Ljava/lang/Object;>(Lscala/Function1<Lscala/concurrent/ExecutionContext;Lscala/concurrent/Future<TT;>;>;)I
   #50 = NameAndType        #47:#48       // hashCode$extension:(Lscala/Function1;)I
   #51 = Methodref          #34.#50       // coursier/util/Task$.hashCode$extension:(Lscala/Function1;)I
   #52 = Utf8               productElementName$extension
   #53 = Utf8               (Lscala/Function1;I)Ljava/lang/String;
   #54 = Utf8               <T:Ljava/lang/Object;>(Lscala/Function1<Lscala/concurrent/ExecutionContext;Lscala/concurrent/Future<TT;>;>;I)Ljava/lang/String;
   #55 = NameAndType        #52:#53       // productElementName$extension:(Lscala/Function1;I)Ljava/lang/String;
   #56 = Methodref          #34.#55       // coursier/util/Task$.productElementName$extension:(Lscala/Function1;I)Ljava/lang/String;
   #57 = Utf8               canEqual$extension
   #58 = NameAndType        #57:#42       // canEqual$extension:(Lscala/Function1;Ljava/lang/Object;)Z
   #59 = Methodref          #34.#58       // coursier/util/Task$.canEqual$extension:(Lscala/Function1;Ljava/lang/Object;)Z
   #60 = Utf8               productIterator$extension
   #61 = Utf8               (Lscala/Function1;)Lscala/collection/Iterator;
   #62 = Utf8               <T:Ljava/lang/Object;>(Lscala/Function1<Lscala/concurrent/ExecutionContext;Lscala/concurrent/Future<TT;>;>;)Lscala/collection/Iterator<Ljava/lang/Object;>;
   #63 = NameAndType        #60:#61       // productIterator$extension:(Lscala/Function1;)Lscala/collection/Iterator;
   #64 = Methodref          #34.#63       // coursier/util/Task$.productIterator$extension:(Lscala/Function1;)Lscala/collection/Iterator;
   #65 = Utf8               productElement$extension
   #66 = Utf8               (Lscala/Function1;I)Ljava/lang/Object;
   #67 = Utf8               <T:Ljava/lang/Object;>(Lscala/Function1<Lscala/concurrent/ExecutionContext;Lscala/concurrent/Future<TT;>;>;I)Ljava/lang/Object;
   #68 = NameAndType        #65:#66       // productElement$extension:(Lscala/Function1;I)Ljava/lang/Object;
   #69 = Methodref          #34.#68       // coursier/util/Task$.productElement$extension:(Lscala/Function1;I)Ljava/lang/Object;
   #70 = Utf8               productArity$extension
   #71 = NameAndType        #70:#48       // productArity$extension:(Lscala/Function1;)I
   #72 = Methodref          #34.#71       // coursier/util/Task$.productArity$extension:(Lscala/Function1;)I
   #73 = Utf8               productPrefix$extension
   #74 = NameAndType        #73:#30       // productPrefix$extension:(Lscala/Function1;)Ljava/lang/String;
   #75 = Methodref          #34.#74       // coursier/util/Task$.productPrefix$extension:(Lscala/Function1;)Ljava/lang/String;
   #76 = Utf8               copy$default$1$extension
   #77 = Utf8               (Lscala/Function1;)Lscala/Function1;
   #78 = Utf8               <T:Ljava/lang/Object;T:Ljava/lang/Object;>(Lscala/Function1<Lscala/concurrent/ExecutionContext;Lscala/concurrent/Future<TT;>;>;)Lscala/Function1<Lscala/concurrent/ExecutionContext;Lscala/concurrent/Future<TT;>;>;
   #79 = NameAndType        #76:#77       // copy$default$1$extension:(Lscala/Function1;)Lscala/Function1;
   #80 = Methodref          #34.#79       // coursier/util/Task$.copy$default$1$extension:(Lscala/Function1;)Lscala/Function1;
   #81 = Utf8               copy$extension
   #82 = Utf8               (Lscala/Function1;Lscala/Function1;)Lscala/Function1;
   #83 = NameAndType        #81:#82       // copy$extension:(Lscala/Function1;Lscala/Function1;)Lscala/Function1;
   #84 = Methodref          #34.#83       // coursier/util/Task$.copy$extension:(Lscala/Function1;Lscala/Function1;)Lscala/Function1;
   #85 = Utf8               schedule$extension
   #86 = Utf8               (Lscala/Function1;Lscala/concurrent/duration/Duration;Ljava/util/concurrent/ScheduledExecutorService;)Lscala/Function1;
   #87 = Utf8               duration
   #88 = Utf8               es
   #89 = NameAndType        #85:#86       // schedule$extension:(Lscala/Function1;Lscala/concurrent/duration/Duration;Ljava/util/concurrent/ScheduledExecutorService;)Lscala/Function1;
   #90 = Methodref          #34.#89       // coursier/util/Task$.schedule$extension:(Lscala/Function1;Lscala/concurrent/duration/Duration;Ljava/util/concurrent/ScheduledExecutorService;)Lscala/Function1;
   #91 = Utf8               attempt$extension
   #92 = NameAndType        #91:#77       // attempt$extension:(Lscala/Function1;)Lscala/Function1;
   #93 = Methodref          #34.#92       // coursier/util/Task$.attempt$extension:(Lscala/Function1;)Lscala/Function1;
   #94 = Utf8               future$extension
   #95 = Utf8               (Lscala/Function1;Lscala/concurrent/ExecutionContext;)Lscala/concurrent/Future;
   #96 = Utf8               <T:Ljava/lang/Object;>(Lscala/Function1<Lscala/concurrent/ExecutionContext;Lscala/concurrent/Future<TT;>;>;Lscala/concurrent/ExecutionContext;)Lscala/concurrent/Future<TT;>;
   #97 = Utf8               ec
   #98 = NameAndType        #94:#95       // future$extension:(Lscala/Function1;Lscala/concurrent/ExecutionContext;)Lscala/concurrent/Future;
   #99 = Methodref          #34.#98       // coursier/util/Task$.future$extension:(Lscala/Function1;Lscala/concurrent/ExecutionContext;)Lscala/concurrent/Future;
  #100 = Utf8               handle$extension
  #101 = Utf8               (Lscala/Function1;Lscala/PartialFunction;)Lscala/Function1;
  #102 = Utf8               f
  #103 = NameAndType        #100:#101     // handle$extension:(Lscala/Function1;Lscala/PartialFunction;)Lscala/Function1;
  #104 = Methodref          #34.#103      // coursier/util/Task$.handle$extension:(Lscala/Function1;Lscala/PartialFunction;)Lscala/Function1;
  #105 = Utf8               flatMap$extension
  #106 = NameAndType        #105:#82      // flatMap$extension:(Lscala/Function1;Lscala/Function1;)Lscala/Function1;
  #107 = Methodref          #34.#106      // coursier/util/Task$.flatMap$extension:(Lscala/Function1;Lscala/Function1;)Lscala/Function1;
  #108 = Utf8               map$extension
  #109 = NameAndType        #108:#82      // map$extension:(Lscala/Function1;Lscala/Function1;)Lscala/Function1;
  #110 = Methodref          #34.#109      // coursier/util/Task$.map$extension:(Lscala/Function1;Lscala/Function1;)Lscala/Function1;
  #111 = Utf8               unapply
  #112 = Utf8               (Lscala/Function1;)Lscala/Option;
  #113 = Utf8               <T:Ljava/lang/Object;>(Lscala/Function1<Lscala/concurrent/ExecutionContext;Lscala/concurrent/Future<TT;>;>;)Lscala/Option<Lscala/Function1<Lscala/concurrent/ExecutionContext;Lscala/concurrent/Future<TT;>;>;>;
  #114 = Utf8               x$0
  #115 = NameAndType        #111:#112     // unapply:(Lscala/Function1;)Lscala/Option;
  #116 = Methodref          #34.#115      // coursier/util/Task$.unapply:(Lscala/Function1;)Lscala/Option;
  #117 = Utf8               apply
  #118 = NameAndType        #117:#77      // apply:(Lscala/Function1;)Lscala/Function1;
  #119 = Methodref          #34.#118      // coursier/util/Task$.apply:(Lscala/Function1;)Lscala/Function1;
  #120 = Utf8               gather
  #121 = Utf8               ()Lcoursier/util/Gather;
  #122 = Utf8               ()Lcoursier/util/Gather<Lcoursier/util/Task;>;
  #123 = NameAndType        #120:#121     // gather:()Lcoursier/util/Gather;
  #124 = Methodref          #34.#123      // coursier/util/Task$.gather:()Lcoursier/util/Gather;
  #125 = Utf8               tailRecM
  #126 = Utf8               (Ljava/lang/Object;Lscala/Function1;)Lscala/Function1;
  #127 = Utf8               a
  #128 = Utf8               fn
  #129 = NameAndType        #125:#126     // tailRecM:(Ljava/lang/Object;Lscala/Function1;)Lscala/Function1;
  #130 = Methodref          #34.#129      // coursier/util/Task$.tailRecM:(Ljava/lang/Object;Lscala/Function1;)Lscala/Function1;
  #131 = Utf8               fail
  #132 = Utf8               (Ljava/lang/Throwable;)Lscala/Function1;
  #133 = Utf8               e
  #134 = NameAndType        #131:#132     // fail:(Ljava/lang/Throwable;)Lscala/Function1;
  #135 = Methodref          #34.#134      // coursier/util/Task$.fail:(Ljava/lang/Throwable;)Lscala/Function1;
  #136 = Utf8               fromEither
  #137 = Utf8               (Lscala/util/Either;)Lscala/Function1;
  #138 = NameAndType        #136:#137     // fromEither:(Lscala/util/Either;)Lscala/Function1;
  #139 = Methodref          #34.#138      // coursier/util/Task$.fromEither:(Lscala/util/Either;)Lscala/Function1;
  #140 = Utf8               never
  #141 = Utf8               ()Lscala/Function1;
  #142 = NameAndType        #140:#141     // never:()Lscala/Function1;
  #143 = Methodref          #34.#142      // coursier/util/Task$.never:()Lscala/Function1;
  #144 = Utf8               delay
  #145 = Utf8               (Lscala/Function0;)Lscala/Function1;
  #146 = NameAndType        #144:#145     // delay:(Lscala/Function0;)Lscala/Function1;
  #147 = Methodref          #34.#146      // coursier/util/Task$.delay:(Lscala/Function0;)Lscala/Function1;
  #148 = Utf8               point
  #149 = Utf8               (Ljava/lang/Object;)Lscala/Function1;
  #150 = NameAndType        #148:#149     // point:(Ljava/lang/Object;)Lscala/Function1;
  #151 = Methodref          #34.#150      // coursier/util/Task$.point:(Ljava/lang/Object;)Lscala/Function1;
  #152 = Utf8               (Lscala/Function1;)Lcoursier/util/PlatformTaskCompanion$PlatformTaskOps;
  #153 = Utf8               <T:Ljava/lang/Object;>(Lscala/Function1<Lscala/concurrent/ExecutionContext;Lscala/concurrent/Future<TT;>;>;)Lcoursier/util/PlatformTaskCompanion$PlatformTaskOps<TT;>;
  #154 = Utf8               task
  #155 = NameAndType        #18:#152      // PlatformTaskOps:(Lscala/Function1;)Lcoursier/util/PlatformTaskCompanion$PlatformTaskOps;
  #156 = Methodref          #34.#155      // coursier/util/Task$.PlatformTaskOps:(Lscala/Function1;)Lcoursier/util/PlatformTaskCompanion$PlatformTaskOps;
  #157 = Utf8               sync
  #158 = Utf8               ()Lcoursier/util/Sync;
  #159 = Utf8               ()Lcoursier/util/Sync<Lcoursier/util/Task;>;
  #160 = NameAndType        #157:#158     // sync:()Lcoursier/util/Sync;
  #161 = Methodref          #34.#160      // coursier/util/Task$.sync:()Lcoursier/util/Sync;
  #162 = Utf8               completeAfter
  #163 = Utf8               (Ljava/util/concurrent/ScheduledExecutorService;Lscala/concurrent/duration/FiniteDuration;)Lscala/Function1;
  #164 = Utf8               pool
  #165 = NameAndType        #162:#163     // completeAfter:(Ljava/util/concurrent/ScheduledExecutorService;Lscala/concurrent/duration/FiniteDuration;)Lscala/Function1;
  #166 = Methodref          #34.#165      // coursier/util/Task$.completeAfter:(Ljava/util/concurrent/ScheduledExecutorService;Lscala/concurrent/duration/FiniteDuration;)Lscala/Function1;
  #167 = Utf8               productElementNames
  #168 = Utf8               ()Lscala/collection/Iterator;
  #169 = Utf8               ()Lscala/collection/Iterator<Ljava/lang/String;>;
  #170 = Utf8               productElementNames$
  #171 = Utf8               (Lscala/Product;)Lscala/collection/Iterator;
  #172 = NameAndType        #170:#171     // productElementNames$:(Lscala/Product;)Lscala/collection/Iterator;
  #173 = InterfaceMethodref #7.#172       // scala/Product.productElementNames$:(Lscala/Product;)Lscala/collection/Iterator;
  #174 = Utf8               this
  #175 = Utf8               Lcoursier/util/Task;
  #176 = Utf8               ()Lscala/Function1<Lscala/concurrent/ExecutionContext;Lscala/concurrent/Future<TT;>;>;
  #177 = NameAndType        #26:#27       // value:Lscala/Function1;
  #178 = Fieldref           #2.#177       // coursier/util/Task.value:Lscala/Function1;
  #179 = Utf8               map
  #180 = Utf8               <U:Ljava/lang/Object;>(Lscala/Function1<TT;TU;>;)Lscala/Function1<Lscala/concurrent/ExecutionContext;Lscala/concurrent/Future<TU;>;>;
  #181 = NameAndType        #26:#141      // value:()Lscala/Function1;
  #182 = Methodref          #2.#181       // coursier/util/Task.value:()Lscala/Function1;
  #183 = Utf8               flatMap
  #184 = Utf8               <U:Ljava/lang/Object;>(Lscala/Function1<TT;Lcoursier/util/Task<TU;>;>;)Lscala/Function1<Lscala/concurrent/ExecutionContext;Lscala/concurrent/Future<TU;>;>;
  #185 = Utf8               handle
  #186 = Utf8               (Lscala/PartialFunction;)Lscala/Function1;
  #187 = Utf8               <U:Ljava/lang/Object;>(Lscala/PartialFunction<Ljava/lang/Throwable;TU;>;)Lscala/Function1<Lscala/concurrent/ExecutionContext;Lscala/concurrent/Future<TU;>;>;
  #188 = Utf8               Lscala/PartialFunction;
  #189 = Utf8               future
  #190 = Utf8               (Lscala/concurrent/ExecutionContext;)Lscala/concurrent/Future;
  #191 = Utf8               (Lscala/concurrent/ExecutionContext;)Lscala/concurrent/Future<TT;>;
  #192 = Utf8               Lscala/concurrent/ExecutionContext;
  #193 = Utf8               attempt
  #194 = Utf8               ()Lscala/Function1<Lscala/concurrent/ExecutionContext;Lscala/concurrent/Future<Lscala/util/Either<Ljava/lang/Throwable;TT;>;>;>;
  #195 = Utf8               schedule
  #196 = Utf8               (Lscala/concurrent/duration/Duration;Ljava/util/concurrent/ScheduledExecutorService;)Lscala/Function1;
  #197 = Utf8               (Lscala/concurrent/duration/Duration;Ljava/util/concurrent/ScheduledExecutorService;)Lscala/Function1<Lscala/concurrent/ExecutionContext;Lscala/concurrent/Future<TT;>;>;
  #198 = Utf8               Lscala/concurrent/duration/Duration;
  #199 = Utf8               Ljava/util/concurrent/ScheduledExecutorService;
  #200 = Utf8               copy
  #201 = Utf8               <T:Ljava/lang/Object;>(Lscala/Function1<Lscala/concurrent/ExecutionContext;Lscala/concurrent/Future<TT;>;>;)Lscala/Function1<Lscala/concurrent/ExecutionContext;Lscala/concurrent/Future<TT;>;>;
  #202 = Utf8               copy$default$1
  #203 = Utf8               <T:Ljava/lang/Object;>()Lscala/Function1<Lscala/concurrent/ExecutionContext;Lscala/concurrent/Future<TT;>;>;
  #204 = Utf8               productPrefix
  #205 = Utf8               ()Ljava/lang/String;
  #206 = Utf8               productArity
  #207 = Utf8               ()I
  #208 = Utf8               productElement
  #209 = Utf8               (I)Ljava/lang/Object;
  #210 = Utf8               I
  #211 = Utf8               productIterator
  #212 = Utf8               ()Lscala/collection/Iterator<Ljava/lang/Object;>;
  #213 = Utf8               canEqual
  #214 = Utf8               (Ljava/lang/Object;)Z
  #215 = Utf8               Ljava/lang/Object;
  #216 = Utf8               productElementName
  #217 = Utf8               (I)Ljava/lang/String;
  #218 = Utf8               hashCode
  #219 = Utf8               equals
  #220 = Utf8               toString
  #221 = Utf8               <init>
  #222 = Utf8               (Lscala/Function1;)V
  #223 = Utf8               (Lscala/Function1<Lscala/concurrent/ExecutionContext;Lscala/concurrent/Future<TT;>;>;)V
  #224 = Utf8               ()V
  #225 = NameAndType        #221:#224     // "<init>":()V
  #226 = Methodref          #5.#225       // java/lang/Object."<init>":()V
  #227 = Utf8               $init$
  #228 = Utf8               (Lscala/Product;)V
  #229 = NameAndType        #227:#228     // $init$:(Lscala/Product;)V
  #230 = InterfaceMethodref #7.#229       // scala/Product.$init$:(Lscala/Product;)V
  #231 = Utf8               Signature
  #232 = Utf8               Code
  #233 = Utf8               MethodParameters
  #234 = Utf8               LineNumberTable
  #235 = Utf8               LocalVariableTable
  #236 = Utf8               InnerClasses
  #237 = Utf8               SourceFile
  #238 = Utf8               RuntimeVisibleAnnotations
  #239 = Utf8               ScalaInlineInfo
  #240 = Utf8               ScalaSig
{
  private final scala.Function1<scala.concurrent.ExecutionContext, scala.concurrent.Future<T>> value;
    descriptor: Lscala/Function1;
    flags: (0x0012) ACC_PRIVATE, ACC_FINAL
    Signature: #28                          // Lscala/Function1<Lscala/concurrent/ExecutionContext;Lscala/concurrent/Future<TT;>;>;

  public static <T extends java.lang.Object> java.lang.String toString$extension(scala.Function1<scala.concurrent.ExecutionContext, scala.concurrent.Future<T>>);
    descriptor: (Lscala/Function1;)Ljava/lang/String;
    flags: (0x0009) ACC_PUBLIC, ACC_STATIC
    Code:
      stack=2, locals=1, args_size=1
         0: getstatic     #38                 // Field coursier/util/Task$.MODULE$:Lcoursier/util/Task$;
         3: aload_0
         4: invokevirtual #40                 // Method coursier/util/Task$.toString$extension:(Lscala/Function1;)Ljava/lang/String;
         7: areturn
    Signature: #31                          // <T:Ljava/lang/Object;>(Lscala/Function1<Lscala/concurrent/ExecutionContext;Lscala/concurrent/Future<TT;>;>;)Ljava/lang/String;
    MethodParameters:
      Name                           Flags
      $this                          final

  public static <T extends java.lang.Object> boolean equals$extension(scala.Function1<scala.concurrent.ExecutionContext, scala.concurrent.Future<T>>, java.lang.Object);
    descriptor: (Lscala/Function1;Ljava/lang/Object;)Z
    flags: (0x0009) ACC_PUBLIC, ACC_STATIC
    Code:
      stack=3, locals=2, args_size=2
         0: getstatic     #38                 // Field coursier/util/Task$.MODULE$:Lcoursier/util/Task$;
         3: aload_0
         4: aload_1
         5: invokevirtual #46                 // Method coursier/util/Task$.equals$extension:(Lscala/Function1;Ljava/lang/Object;)Z
         8: ireturn
    Signature: #43                          // <T:Ljava/lang/Object;>(Lscala/Function1<Lscala/concurrent/ExecutionContext;Lscala/concurrent/Future<TT;>;>;Ljava/lang/Object;)Z
    MethodParameters:
      Name                           Flags
      $this                          final
      x$1                            final

  public static <T extends java.lang.Object> int hashCode$extension(scala.Function1<scala.concurrent.ExecutionContext, scala.concurrent.Future<T>>);
    descriptor: (Lscala/Function1;)I
    flags: (0x0009) ACC_PUBLIC, ACC_STATIC
    Code:
      stack=2, locals=1, args_size=1
         0: getstatic     #38                 // Field coursier/util/Task$.MODULE$:Lcoursier/util/Task$;
         3: aload_0
         4: invokevirtual #51                 // Method coursier/util/Task$.hashCode$extension:(Lscala/Function1;)I
         7: ireturn
    Signature: #49                          // <T:Ljava/lang/Object;>(Lscala/Function1<Lscala/concurrent/ExecutionContext;Lscala/concurrent/Future<TT;>;>;)I
    MethodParameters:
      Name                           Flags
      $this                          final

  public static <T extends java.lang.Object> java.lang.String productElementName$extension(scala.Function1<scala.concurrent.ExecutionContext, scala.concurrent.Future<T>>, int);
    descriptor: (Lscala/Function1;I)Ljava/lang/String;
    flags: (0x0009) ACC_PUBLIC, ACC_STATIC
    Code:
      stack=3, locals=2, args_size=2
         0: getstatic     #38                 // Field coursier/util/Task$.MODULE$:Lcoursier/util/Task$;
         3: aload_0
         4: iload_1
         5: invokevirtual #56                 // Method coursier/util/Task$.productElementName$extension:(Lscala/Function1;I)Ljava/lang/String;
         8: areturn
    Signature: #54                          // <T:Ljava/lang/Object;>(Lscala/Function1<Lscala/concurrent/ExecutionContext;Lscala/concurrent/Future<TT;>;>;I)Ljava/lang/String;
    MethodParameters:
      Name                           Flags
      $this                          final
      x$1                            final

  public static <T extends java.lang.Object> boolean canEqual$extension(scala.Function1<scala.concurrent.ExecutionContext, scala.concurrent.Future<T>>, java.lang.Object);
    descriptor: (Lscala/Function1;Ljava/lang/Object;)Z
    flags: (0x0009) ACC_PUBLIC, ACC_STATIC
    Code:
      stack=3, locals=2, args_size=2
         0: getstatic     #38                 // Field coursier/util/Task$.MODULE$:Lcoursier/util/Task$;
         3: aload_0
         4: aload_1
         5: invokevirtual #59                 // Method coursier/util/Task$.canEqual$extension:(Lscala/Function1;Ljava/lang/Object;)Z
         8: ireturn
    Signature: #43                          // <T:Ljava/lang/Object;>(Lscala/Function1<Lscala/concurrent/ExecutionContext;Lscala/concurrent/Future<TT;>;>;Ljava/lang/Object;)Z
    MethodParameters:
      Name                           Flags
      $this                          final
      x$1                            final

  public static <T extends java.lang.Object> scala.collection.Iterator<java.lang.Object> productIterator$extension(scala.Function1<scala.concurrent.ExecutionContext, scala.concurrent.Future<T>>);
    descriptor: (Lscala/Function1;)Lscala/collection/Iterator;
    flags: (0x0009) ACC_PUBLIC, ACC_STATIC
    Code:
      stack=2, locals=1, args_size=1
         0: getstatic     #38                 // Field coursier/util/Task$.MODULE$:Lcoursier/util/Task$;
         3: aload_0
         4: invokevirtual #64                 // Method coursier/util/Task$.productIterator$extension:(Lscala/Function1;)Lscala/collection/Iterator;
         7: areturn
    Signature: #62                          // <T:Ljava/lang/Object;>(Lscala/Function1<Lscala/concurrent/ExecutionContext;Lscala/concurrent/Future<TT;>;>;)Lscala/collection/Iterator<Ljava/lang/Object;>;
    MethodParameters:
      Name                           Flags
      $this                          final

  public static <T extends java.lang.Object> java.lang.Object productElement$extension(scala.Function1<scala.concurrent.ExecutionContext, scala.concurrent.Future<T>>, int);
    descriptor: (Lscala/Function1;I)Ljava/lang/Object;
    flags: (0x0009) ACC_PUBLIC, ACC_STATIC
    Code:
      stack=3, locals=2, args_size=2
         0: getstatic     #38                 // Field coursier/util/Task$.MODULE$:Lcoursier/util/Task$;
         3: aload_0
         4: iload_1
         5: invokevirtual #69                 // Method coursier/util/Task$.productElement$extension:(Lscala/Function1;I)Ljava/lang/Object;
         8: areturn
    Signature: #67                          // <T:Ljava/lang/Object;>(Lscala/Function1<Lscala/concurrent/ExecutionContext;Lscala/concurrent/Future<TT;>;>;I)Ljava/lang/Object;
    MethodParameters:
      Name                           Flags
      $this                          final
      x$1                            final

  public static <T extends java.lang.Object> int productArity$extension(scala.Function1<scala.concurrent.ExecutionContext, scala.concurrent.Future<T>>);
    descriptor: (Lscala/Function1;)I
    flags: (0x0009) ACC_PUBLIC, ACC_STATIC
    Code:
      stack=2, locals=1, args_size=1
         0: getstatic     #38                 // Field coursier/util/Task$.MODULE$:Lcoursier/util/Task$;
         3: aload_0
         4: invokevirtual #72                 // Method coursier/util/Task$.productArity$extension:(Lscala/Function1;)I
         7: ireturn
    Signature: #49                          // <T:Ljava/lang/Object;>(Lscala/Function1<Lscala/concurrent/ExecutionContext;Lscala/concurrent/Future<TT;>;>;)I
    MethodParameters:
      Name                           Flags
      $this                          final

  public static <T extends java.lang.Object> java.lang.String productPrefix$extension(scala.Function1<scala.concurrent.ExecutionContext, scala.concurrent.Future<T>>);
    descriptor: (Lscala/Function1;)Ljava/lang/String;
    flags: (0x0009) ACC_PUBLIC, ACC_STATIC
    Code:
      stack=2, locals=1, args_size=1
         0: getstatic     #38                 // Field coursier/util/Task$.MODULE$:Lcoursier/util/Task$;
         3: aload_0
         4: invokevirtual #75                 // Method coursier/util/Task$.productPrefix$extension:(Lscala/Function1;)Ljava/lang/String;
         7: areturn
    Signature: #31                          // <T:Ljava/lang/Object;>(Lscala/Function1<Lscala/concurrent/ExecutionContext;Lscala/concurrent/Future<TT;>;>;)Ljava/lang/String;
    MethodParameters:
      Name                           Flags
      $this                          final

  public static <T extends java.lang.Object, T extends java.lang.Object> scala.Function1<scala.concurrent.ExecutionContext, scala.concurrent.Future<T>> copy$default$1$extension(scala.Function1<scala.concurrent.ExecutionContext, scala.concurrent.Future<T>>);
    descriptor: (Lscala/Function1;)Lscala/Function1;
    flags: (0x0009) ACC_PUBLIC, ACC_STATIC
    Code:
      stack=2, locals=1, args_size=1
         0: getstatic     #38                 // Field coursier/util/Task$.MODULE$:Lcoursier/util/Task$;
         3: aload_0
         4: invokevirtual #80                 // Method coursier/util/Task$.copy$default$1$extension:(Lscala/Function1;)Lscala/Function1;
         7: areturn
    Signature: #78                          // <T:Ljava/lang/Object;T:Ljava/lang/Object;>(Lscala/Function1<Lscala/concurrent/ExecutionContext;Lscala/concurrent/Future<TT;>;>;)Lscala/Function1<Lscala/concurrent/ExecutionContext;Lscala/concurrent/Future<TT;>;>;
    MethodParameters:
      Name                           Flags
      $this                          final

  public static scala.Function1 copy$extension(scala.Function1, scala.Function1);
    descriptor: (Lscala/Function1;Lscala/Function1;)Lscala/Function1;
    flags: (0x0009) ACC_PUBLIC, ACC_STATIC
    Code:
      stack=3, locals=2, args_size=2
         0: getstatic     #38                 // Field coursier/util/Task$.MODULE$:Lcoursier/util/Task$;
         3: aload_0
         4: aload_1
         5: invokevirtual #84                 // Method coursier/util/Task$.copy$extension:(Lscala/Function1;Lscala/Function1;)Lscala/Function1;
         8: areturn
    MethodParameters:
      Name                           Flags
      $this                          final
      value                          final

  public static scala.Function1 schedule$extension(scala.Function1, scala.concurrent.duration.Duration, java.util.concurrent.ScheduledExecutorService);
    descriptor: (Lscala/Function1;Lscala/concurrent/duration/Duration;Ljava/util/concurrent/ScheduledExecutorService;)Lscala/Function1;
    flags: (0x0009) ACC_PUBLIC, ACC_STATIC
    Code:
      stack=4, locals=3, args_size=3
         0: getstatic     #38                 // Field coursier/util/Task$.MODULE$:Lcoursier/util/Task$;
         3: aload_0
         4: aload_1
         5: aload_2
         6: invokevirtual #90                 // Method coursier/util/Task$.schedule$extension:(Lscala/Function1;Lscala/concurrent/duration/Duration;Ljava/util/concurrent/ScheduledExecutorService;)Lscala/Function1;
         9: areturn
    MethodParameters:
      Name                           Flags
      $this                          final
      duration                       final
      es                             final

  public static scala.Function1 attempt$extension(scala.Function1);
    descriptor: (Lscala/Function1;)Lscala/Function1;
    flags: (0x0009) ACC_PUBLIC, ACC_STATIC
    Code:
      stack=2, locals=1, args_size=1
         0: getstatic     #38                 // Field coursier/util/Task$.MODULE$:Lcoursier/util/Task$;
         3: aload_0
         4: invokevirtual #93                 // Method coursier/util/Task$.attempt$extension:(Lscala/Function1;)Lscala/Function1;
         7: areturn
    MethodParameters:
      Name                           Flags
      $this                          final

  public static <T extends java.lang.Object> scala.concurrent.Future<T> future$extension(scala.Function1<scala.concurrent.ExecutionContext, scala.concurrent.Future<T>>, scala.concurrent.ExecutionContext);
    descriptor: (Lscala/Function1;Lscala/concurrent/ExecutionContext;)Lscala/concurrent/Future;
    flags: (0x0009) ACC_PUBLIC, ACC_STATIC
    Code:
      stack=3, locals=2, args_size=2
         0: getstatic     #38                 // Field coursier/util/Task$.MODULE$:Lcoursier/util/Task$;
         3: aload_0
         4: aload_1
         5: invokevirtual #99                 // Method coursier/util/Task$.future$extension:(Lscala/Function1;Lscala/concurrent/ExecutionContext;)Lscala/concurrent/Future;
         8: areturn
    Signature: #96                          // <T:Ljava/lang/Object;>(Lscala/Function1<Lscala/concurrent/ExecutionContext;Lscala/concurrent/Future<TT;>;>;Lscala/concurrent/ExecutionContext;)Lscala/concurrent/Future<TT;>;
    MethodParameters:
      Name                           Flags
      $this                          final
      ec                             final

  public static scala.Function1 handle$extension(scala.Function1, scala.PartialFunction);
    descriptor: (Lscala/Function1;Lscala/PartialFunction;)Lscala/Function1;
    flags: (0x0009) ACC_PUBLIC, ACC_STATIC
    Code:
      stack=3, locals=2, args_size=2
         0: getstatic     #38                 // Field coursier/util/Task$.MODULE$:Lcoursier/util/Task$;
         3: aload_0
         4: aload_1
         5: invokevirtual #104                // Method coursier/util/Task$.handle$extension:(Lscala/Function1;Lscala/PartialFunction;)Lscala/Function1;
         8: areturn
    MethodParameters:
      Name                           Flags
      $this                          final
      f                              final

  public static scala.Function1 flatMap$extension(scala.Function1, scala.Function1);
    descriptor: (Lscala/Function1;Lscala/Function1;)Lscala/Function1;
    flags: (0x0009) ACC_PUBLIC, ACC_STATIC
    Code:
      stack=3, locals=2, args_size=2
         0: getstatic     #38                 // Field coursier/util/Task$.MODULE$:Lcoursier/util/Task$;
         3: aload_0
         4: aload_1
         5: invokevirtual #107                // Method coursier/util/Task$.flatMap$extension:(Lscala/Function1;Lscala/Function1;)Lscala/Function1;
         8: areturn
    MethodParameters:
      Name                           Flags
      $this                          final
      f                              final

  public static scala.Function1 map$extension(scala.Function1, scala.Function1);
    descriptor: (Lscala/Function1;Lscala/Function1;)Lscala/Function1;
    flags: (0x0009) ACC_PUBLIC, ACC_STATIC
    Code:
      stack=3, locals=2, args_size=2
         0: getstatic     #38                 // Field coursier/util/Task$.MODULE$:Lcoursier/util/Task$;
         3: aload_0
         4: aload_1
         5: invokevirtual #110                // Method coursier/util/Task$.map$extension:(Lscala/Function1;Lscala/Function1;)Lscala/Function1;
         8: areturn
    MethodParameters:
      Name                           Flags
      $this                          final
      f                              final

  public static <T extends java.lang.Object> scala.Option<scala.Function1<scala.concurrent.ExecutionContext, scala.concurrent.Future<T>>> unapply(scala.Function1<scala.concurrent.ExecutionContext, scala.concurrent.Future<T>>);
    descriptor: (Lscala/Function1;)Lscala/Option;
    flags: (0x0009) ACC_PUBLIC, ACC_STATIC
    Code:
      stack=2, locals=1, args_size=1
         0: getstatic     #38                 // Field coursier/util/Task$.MODULE$:Lcoursier/util/Task$;
         3: aload_0
         4: invokevirtual #116                // Method coursier/util/Task$.unapply:(Lscala/Function1;)Lscala/Option;
         7: areturn
    Signature: #113                         // <T:Ljava/lang/Object;>(Lscala/Function1<Lscala/concurrent/ExecutionContext;Lscala/concurrent/Future<TT;>;>;)Lscala/Option<Lscala/Function1<Lscala/concurrent/ExecutionContext;Lscala/concurrent/Future<TT;>;>;>;
    MethodParameters:
      Name                           Flags
      x$0                            final

  public static scala.Function1 apply(scala.Function1);
    descriptor: (Lscala/Function1;)Lscala/Function1;
    flags: (0x0009) ACC_PUBLIC, ACC_STATIC
    Code:
      stack=2, locals=1, args_size=1
         0: getstatic     #38                 // Field coursier/util/Task$.MODULE$:Lcoursier/util/Task$;
         3: aload_0
         4: invokevirtual #119                // Method coursier/util/Task$.apply:(Lscala/Function1;)Lscala/Function1;
         7: areturn
    MethodParameters:
      Name                           Flags
      value                          final

  public static coursier.util.Gather<coursier.util.Task> gather();
    descriptor: ()Lcoursier/util/Gather;
    flags: (0x0009) ACC_PUBLIC, ACC_STATIC
    Code:
      stack=1, locals=0, args_size=0
         0: getstatic     #38                 // Field coursier/util/Task$.MODULE$:Lcoursier/util/Task$;
         3: invokevirtual #124                // Method coursier/util/Task$.gather:()Lcoursier/util/Gather;
         6: areturn
    Signature: #122                         // ()Lcoursier/util/Gather<Lcoursier/util/Task;>;

  public static scala.Function1 tailRecM(java.lang.Object, scala.Function1);
    descriptor: (Ljava/lang/Object;Lscala/Function1;)Lscala/Function1;
    flags: (0x0009) ACC_PUBLIC, ACC_STATIC
    Code:
      stack=3, locals=2, args_size=2
         0: getstatic     #38                 // Field coursier/util/Task$.MODULE$:Lcoursier/util/Task$;
         3: aload_0
         4: aload_1
         5: invokevirtual #130                // Method coursier/util/Task$.tailRecM:(Ljava/lang/Object;Lscala/Function1;)Lscala/Function1;
         8: areturn
    MethodParameters:
      Name                           Flags
      a                              final
      fn                             final

  public static scala.Function1 fail(java.lang.Throwable);
    descriptor: (Ljava/lang/Throwable;)Lscala/Function1;
    flags: (0x0009) ACC_PUBLIC, ACC_STATIC
    Code:
      stack=2, locals=1, args_size=1
         0: getstatic     #38                 // Field coursier/util/Task$.MODULE$:Lcoursier/util/Task$;
         3: aload_0
         4: invokevirtual #135                // Method coursier/util/Task$.fail:(Ljava/lang/Throwable;)Lscala/Function1;
         7: areturn
    MethodParameters:
      Name                           Flags
      e                              final

  public static scala.Function1 fromEither(scala.util.Either);
    descriptor: (Lscala/util/Either;)Lscala/Function1;
    flags: (0x0009) ACC_PUBLIC, ACC_STATIC
    Code:
      stack=2, locals=1, args_size=1
         0: getstatic     #38                 // Field coursier/util/Task$.MODULE$:Lcoursier/util/Task$;
         3: aload_0
         4: invokevirtual #139                // Method coursier/util/Task$.fromEither:(Lscala/util/Either;)Lscala/Function1;
         7: areturn
    MethodParameters:
      Name                           Flags
      e                              final

  public static scala.Function1 never();
    descriptor: ()Lscala/Function1;
    flags: (0x0009) ACC_PUBLIC, ACC_STATIC
    Code:
      stack=1, locals=0, args_size=0
         0: getstatic     #38                 // Field coursier/util/Task$.MODULE$:Lcoursier/util/Task$;
         3: invokevirtual #143                // Method coursier/util/Task$.never:()Lscala/Function1;
         6: areturn

  public static scala.Function1 delay(scala.Function0);
    descriptor: (Lscala/Function0;)Lscala/Function1;
    flags: (0x0009) ACC_PUBLIC, ACC_STATIC
    Code:
      stack=2, locals=1, args_size=1
         0: getstatic     #38                 // Field coursier/util/Task$.MODULE$:Lcoursier/util/Task$;
         3: aload_0
         4: invokevirtual #147                // Method coursier/util/Task$.delay:(Lscala/Function0;)Lscala/Function1;
         7: areturn
    MethodParameters:
      Name                           Flags
      a                              final

  public static scala.Function1 point(java.lang.Object);
    descriptor: (Ljava/lang/Object;)Lscala/Function1;
    flags: (0x0009) ACC_PUBLIC, ACC_STATIC
    Code:
      stack=2, locals=1, args_size=1
         0: getstatic     #38                 // Field coursier/util/Task$.MODULE$:Lcoursier/util/Task$;
         3: aload_0
         4: invokevirtual #151                // Method coursier/util/Task$.point:(Ljava/lang/Object;)Lscala/Function1;
         7: areturn
    MethodParameters:
      Name                           Flags
      a                              final

  public static <T extends java.lang.Object> coursier.util.PlatformTaskCompanion$PlatformTaskOps<T> PlatformTaskOps(scala.Function1<scala.concurrent.ExecutionContext, scala.concurrent.Future<T>>);
    descriptor: (Lscala/Function1;)Lcoursier/util/PlatformTaskCompanion$PlatformTaskOps;
    flags: (0x0009) ACC_PUBLIC, ACC_STATIC
    Code:
      stack=2, locals=1, args_size=1
         0: getstatic     #38                 // Field coursier/util/Task$.MODULE$:Lcoursier/util/Task$;
         3: aload_0
         4: invokevirtual #156                // Method coursier/util/Task$.PlatformTaskOps:(Lscala/Function1;)Lcoursier/util/PlatformTaskCompanion$PlatformTaskOps;
         7: areturn
    Signature: #153                         // <T:Ljava/lang/Object;>(Lscala/Function1<Lscala/concurrent/ExecutionContext;Lscala/concurrent/Future<TT;>;>;)Lcoursier/util/PlatformTaskCompanion$PlatformTaskOps<TT;>;
    MethodParameters:
      Name                           Flags
      task                           final

  public static coursier.util.Sync<coursier.util.Task> sync();
    descriptor: ()Lcoursier/util/Sync;
    flags: (0x0009) ACC_PUBLIC, ACC_STATIC
    Code:
      stack=1, locals=0, args_size=0
         0: getstatic     #38                 // Field coursier/util/Task$.MODULE$:Lcoursier/util/Task$;
         3: invokevirtual #161                // Method coursier/util/Task$.sync:()Lcoursier/util/Sync;
         6: areturn
    Signature: #159                         // ()Lcoursier/util/Sync<Lcoursier/util/Task;>;

  public static scala.Function1 completeAfter(java.util.concurrent.ScheduledExecutorService, scala.concurrent.duration.FiniteDuration);
    descriptor: (Ljava/util/concurrent/ScheduledExecutorService;Lscala/concurrent/duration/FiniteDuration;)Lscala/Function1;
    flags: (0x0009) ACC_PUBLIC, ACC_STATIC
    Code:
      stack=3, locals=2, args_size=2
         0: getstatic     #38                 // Field coursier/util/Task$.MODULE$:Lcoursier/util/Task$;
         3: aload_0
         4: aload_1
         5: invokevirtual #166                // Method coursier/util/Task$.completeAfter:(Ljava/util/concurrent/ScheduledExecutorService;Lscala/concurrent/duration/FiniteDuration;)Lscala/Function1;
         8: areturn
    MethodParameters:
      Name                           Flags
      pool                           final
      duration                       final

  public scala.collection.Iterator<java.lang.String> productElementNames();
    descriptor: ()Lscala/collection/Iterator;
    flags: (0x0001) ACC_PUBLIC
    Code:
      stack=1, locals=1, args_size=1
         0: aload_0
         1: invokestatic  #173                // InterfaceMethod scala/Product.productElementNames$:(Lscala/Product;)Lscala/collection/Iterator;
         4: areturn
      LineNumberTable:
        line 9: 0
      LocalVariableTable:
        Start  Length  Slot  Name   Signature
            0       5     0  this   Lcoursier/util/Task;
    Signature: #169                         // ()Lscala/collection/Iterator<Ljava/lang/String;>;

  public scala.Function1<scala.concurrent.ExecutionContext, scala.concurrent.Future<T>> value();
    descriptor: ()Lscala/Function1;
    flags: (0x0001) ACC_PUBLIC
    Code:
      stack=1, locals=1, args_size=1
         0: aload_0
         1: getfield      #178                // Field value:Lscala/Function1;
         4: areturn
      LineNumberTable:
        line 9: 0
      LocalVariableTable:
        Start  Length  Slot  Name   Signature
            0       5     0  this   Lcoursier/util/Task;
    Signature: #176                         // ()Lscala/Function1<Lscala/concurrent/ExecutionContext;Lscala/concurrent/Future<TT;>;>;

  public <U extends java.lang.Object> scala.Function1<scala.concurrent.ExecutionContext, scala.concurrent.Future<U>> map(scala.Function1<T, U>);
    descriptor: (Lscala/Function1;)Lscala/Function1;
    flags: (0x0001) ACC_PUBLIC
    Code:
      stack=3, locals=2, args_size=2
         0: getstatic     #38                 // Field coursier/util/Task$.MODULE$:Lcoursier/util/Task$;
         3: aload_0
         4: invokevirtual #182                // Method value:()Lscala/Function1;
         7: aload_1
         8: invokevirtual #110                // Method coursier/util/Task$.map$extension:(Lscala/Function1;Lscala/Function1;)Lscala/Function1;
        11: areturn
      LineNumberTable:
        line 12: 0
      LocalVariableTable:
        Start  Length  Slot  Name   Signature
            0      12     0  this   Lcoursier/util/Task;
            0      12     1     f   Lscala/Function1;
    Signature: #180                         // <U:Ljava/lang/Object;>(Lscala/Function1<TT;TU;>;)Lscala/Function1<Lscala/concurrent/ExecutionContext;Lscala/concurrent/Future<TU;>;>;
    MethodParameters:
      Name                           Flags
      f                              final

  public <U extends java.lang.Object> scala.Function1<scala.concurrent.ExecutionContext, scala.concurrent.Future<U>> flatMap(scala.Function1<T, coursier.util.Task<U>>);
    descriptor: (Lscala/Function1;)Lscala/Function1;
    flags: (0x0001) ACC_PUBLIC
    Code:
      stack=3, locals=2, args_size=2
         0: getstatic     #38                 // Field coursier/util/Task$.MODULE$:Lcoursier/util/Task$;
         3: aload_0
         4: invokevirtual #182                // Method value:()Lscala/Function1;
         7: aload_1
         8: invokevirtual #107                // Method coursier/util/Task$.flatMap$extension:(Lscala/Function1;Lscala/Function1;)Lscala/Function1;
        11: areturn
      LineNumberTable:
        line 14: 0
      LocalVariableTable:
        Start  Length  Slot  Name   Signature
            0      12     0  this   Lcoursier/util/Task;
            0      12     1     f   Lscala/Function1;
    Signature: #184                         // <U:Ljava/lang/Object;>(Lscala/Function1<TT;Lcoursier/util/Task<TU;>;>;)Lscala/Function1<Lscala/concurrent/ExecutionContext;Lscala/concurrent/Future<TU;>;>;
    MethodParameters:
      Name                           Flags
      f                              final

  public <U extends java.lang.Object> scala.Function1<scala.concurrent.ExecutionContext, scala.concurrent.Future<U>> handle(scala.PartialFunction<java.lang.Throwable, U>);
    descriptor: (Lscala/PartialFunction;)Lscala/Function1;
    flags: (0x0001) ACC_PUBLIC
    Code:
      stack=3, locals=2, args_size=2
         0: getstatic     #38                 // Field coursier/util/Task$.MODULE$:Lcoursier/util/Task$;
         3: aload_0
         4: invokevirtual #182                // Method value:()Lscala/Function1;
         7: aload_1
         8: invokevirtual #104                // Method coursier/util/Task$.handle$extension:(Lscala/Function1;Lscala/PartialFunction;)Lscala/Function1;
        11: areturn
      LineNumberTable:
        line 17: 0
      LocalVariableTable:
        Start  Length  Slot  Name   Signature
            0      12     0  this   Lcoursier/util/Task;
            0      12     1     f   Lscala/PartialFunction;
    Signature: #187                         // <U:Ljava/lang/Object;>(Lscala/PartialFunction<Ljava/lang/Throwable;TU;>;)Lscala/Function1<Lscala/concurrent/ExecutionContext;Lscala/concurrent/Future<TU;>;>;
    MethodParameters:
      Name                           Flags
      f                              final

  public scala.concurrent.Future<T> future(scala.concurrent.ExecutionContext);
    descriptor: (Lscala/concurrent/ExecutionContext;)Lscala/concurrent/Future;
    flags: (0x0001) ACC_PUBLIC
    Code:
      stack=3, locals=2, args_size=2
         0: getstatic     #38                 // Field coursier/util/Task$.MODULE$:Lcoursier/util/Task$;
         3: aload_0
         4: invokevirtual #182                // Method value:()Lscala/Function1;
         7: aload_1
         8: invokevirtual #99                 // Method coursier/util/Task$.future$extension:(Lscala/Function1;Lscala/concurrent/ExecutionContext;)Lscala/concurrent/Future;
        11: areturn
      LineNumberTable:
        line 20: 0
      LocalVariableTable:
        Start  Length  Slot  Name   Signature
            0      12     0  this   Lcoursier/util/Task;
            0      12     1    ec   Lscala/concurrent/ExecutionContext;
    Signature: #191                         // (Lscala/concurrent/ExecutionContext;)Lscala/concurrent/Future<TT;>;
    MethodParameters:
      Name                           Flags
      ec                             final

  public scala.Function1<scala.concurrent.ExecutionContext, scala.concurrent.Future<scala.util.Either<java.lang.Throwable, T>>> attempt();
    descriptor: ()Lscala/Function1;
    flags: (0x0001) ACC_PUBLIC
    Code:
      stack=2, locals=1, args_size=1
         0: getstatic     #38                 // Field coursier/util/Task$.MODULE$:Lcoursier/util/Task$;
         3: aload_0
         4: invokevirtual #182                // Method value:()Lscala/Function1;
         7: invokevirtual #93                 // Method coursier/util/Task$.attempt$extension:(Lscala/Function1;)Lscala/Function1;
        10: areturn
      LineNumberTable:
        line 24: 0
      LocalVariableTable:
        Start  Length  Slot  Name   Signature
            0      11     0  this   Lcoursier/util/Task;
    Signature: #194                         // ()Lscala/Function1<Lscala/concurrent/ExecutionContext;Lscala/concurrent/Future<Lscala/util/Either<Ljava/lang/Throwable;TT;>;>;>;

  public scala.Function1<scala.concurrent.ExecutionContext, scala.concurrent.Future<T>> schedule(scala.concurrent.duration.Duration, java.util.concurrent.ScheduledExecutorService);
    descriptor: (Lscala/concurrent/duration/Duration;Ljava/util/concurrent/ScheduledExecutorService;)Lscala/Function1;
    flags: (0x0001) ACC_PUBLIC
    Code:
      stack=4, locals=3, args_size=3
         0: getstatic     #38                 // Field coursier/util/Task$.MODULE$:Lcoursier/util/Task$;
         3: aload_0
         4: invokevirtual #182                // Method value:()Lscala/Function1;
         7: aload_1
         8: aload_2
         9: invokevirtual #90                 // Method coursier/util/Task$.schedule$extension:(Lscala/Function1;Lscala/concurrent/duration/Duration;Ljava/util/concurrent/ScheduledExecutorService;)Lscala/Function1;
        12: areturn
      LineNumberTable:
        line 29: 0
      LocalVariableTable:
        Start  Length  Slot  Name   Signature
            0      13     0  this   Lcoursier/util/Task;
            0      13     1 duration   Lscala/concurrent/duration/Duration;
            0      13     2    es   Ljava/util/concurrent/ScheduledExecutorService;
    Signature: #197                         // (Lscala/concurrent/duration/Duration;Ljava/util/concurrent/ScheduledExecutorService;)Lscala/Function1<Lscala/concurrent/ExecutionContext;Lscala/concurrent/Future<TT;>;>;
    MethodParameters:
      Name                           Flags
      duration                       final
      es                             final

  public <T extends java.lang.Object> scala.Function1<scala.concurrent.ExecutionContext, scala.concurrent.Future<T>> copy(scala.Function1<scala.concurrent.ExecutionContext, scala.concurrent.Future<T>>);
    descriptor: (Lscala/Function1;)Lscala/Function1;
    flags: (0x0001) ACC_PUBLIC
    Code:
      stack=3, locals=2, args_size=2
         0: getstatic     #38                 // Field coursier/util/Task$.MODULE$:Lcoursier/util/Task$;
         3: aload_0
         4: invokevirtual #182                // Method value:()Lscala/Function1;
         7: aload_1
         8: invokevirtual #84                 // Method coursier/util/Task$.copy$extension:(Lscala/Function1;Lscala/Function1;)Lscala/Function1;
        11: areturn
      LineNumberTable:
        line 9: 0
      LocalVariableTable:
        Start  Length  Slot  Name   Signature
            0      12     0  this   Lcoursier/util/Task;
            0      12     1 value   Lscala/Function1;
    Signature: #201                         // <T:Ljava/lang/Object;>(Lscala/Function1<Lscala/concurrent/ExecutionContext;Lscala/concurrent/Future<TT;>;>;)Lscala/Function1<Lscala/concurrent/ExecutionContext;Lscala/concurrent/Future<TT;>;>;
    MethodParameters:
      Name                           Flags
      value                          final

  public <T extends java.lang.Object> scala.Function1<scala.concurrent.ExecutionContext, scala.concurrent.Future<T>> copy$default$1();
    descriptor: ()Lscala/Function1;
    flags: (0x0001) ACC_PUBLIC
    Code:
      stack=2, locals=1, args_size=1
         0: getstatic     #38                 // Field coursier/util/Task$.MODULE$:Lcoursier/util/Task$;
         3: aload_0
         4: invokevirtual #182                // Method value:()Lscala/Function1;
         7: invokevirtual #80                 // Method coursier/util/Task$.copy$default$1$extension:(Lscala/Function1;)Lscala/Function1;
        10: areturn
      LineNumberTable:
        line 9: 0
      LocalVariableTable:
        Start  Length  Slot  Name   Signature
            0      11     0  this   Lcoursier/util/Task;
    Signature: #203                         // <T:Ljava/lang/Object;>()Lscala/Function1<Lscala/concurrent/ExecutionContext;Lscala/concurrent/Future<TT;>;>;

  public java.lang.String productPrefix();
    descriptor: ()Ljava/lang/String;
    flags: (0x0001) ACC_PUBLIC
    Code:
      stack=2, locals=1, args_size=1
         0: getstatic     #38                 // Field coursier/util/Task$.MODULE$:Lcoursier/util/Task$;
         3: aload_0
         4: invokevirtual #182                // Method value:()Lscala/Function1;
         7: invokevirtual #75                 // Method coursier/util/Task$.productPrefix$extension:(Lscala/Function1;)Ljava/lang/String;
        10: areturn
      LineNumberTable:
        line 9: 0
      LocalVariableTable:
        Start  Length  Slot  Name   Signature
            0      11     0  this   Lcoursier/util/Task;

  public int productArity();
    descriptor: ()I
    flags: (0x0001) ACC_PUBLIC
    Code:
      stack=2, locals=1, args_size=1
         0: getstatic     #38                 // Field coursier/util/Task$.MODULE$:Lcoursier/util/Task$;
         3: aload_0
         4: invokevirtual #182                // Method value:()Lscala/Function1;
         7: invokevirtual #72                 // Method coursier/util/Task$.productArity$extension:(Lscala/Function1;)I
        10: ireturn
      LineNumberTable:
        line 9: 0
      LocalVariableTable:
        Start  Length  Slot  Name   Signature
            0      11     0  this   Lcoursier/util/Task;

  public java.lang.Object productElement(int);
    descriptor: (I)Ljava/lang/Object;
    flags: (0x0001) ACC_PUBLIC
    Code:
      stack=3, locals=2, args_size=2
         0: getstatic     #38                 // Field coursier/util/Task$.MODULE$:Lcoursier/util/Task$;
         3: aload_0
         4: invokevirtual #182                // Method value:()Lscala/Function1;
         7: iload_1
         8: invokevirtual #69                 // Method coursier/util/Task$.productElement$extension:(Lscala/Function1;I)Ljava/lang/Object;
        11: areturn
      LineNumberTable:
        line 9: 0
      LocalVariableTable:
        Start  Length  Slot  Name   Signature
            0      12     0  this   Lcoursier/util/Task;
            0      12     1   x$1   I
    MethodParameters:
      Name                           Flags
      x$1                            final

  public scala.collection.Iterator<java.lang.Object> productIterator();
    descriptor: ()Lscala/collection/Iterator;
    flags: (0x0001) ACC_PUBLIC
    Code:
      stack=2, locals=1, args_size=1
         0: getstatic     #38                 // Field coursier/util/Task$.MODULE$:Lcoursier/util/Task$;
         3: aload_0
         4: invokevirtual #182                // Method value:()Lscala/Function1;
         7: invokevirtual #64                 // Method coursier/util/Task$.productIterator$extension:(Lscala/Function1;)Lscala/collection/Iterator;
        10: areturn
      LineNumberTable:
        line 9: 0
      LocalVariableTable:
        Start  Length  Slot  Name   Signature
            0      11     0  this   Lcoursier/util/Task;
    Signature: #212                         // ()Lscala/collection/Iterator<Ljava/lang/Object;>;

  public boolean canEqual(java.lang.Object);
    descriptor: (Ljava/lang/Object;)Z
    flags: (0x0001) ACC_PUBLIC
    Code:
      stack=3, locals=2, args_size=2
         0: getstatic     #38                 // Field coursier/util/Task$.MODULE$:Lcoursier/util/Task$;
         3: aload_0
         4: invokevirtual #182                // Method value:()Lscala/Function1;
         7: aload_1
         8: invokevirtual #59                 // Method coursier/util/Task$.canEqual$extension:(Lscala/Function1;Ljava/lang/Object;)Z
        11: ireturn
      LineNumberTable:
        line 9: 0
      LocalVariableTable:
        Start  Length  Slot  Name   Signature
            0      12     0  this   Lcoursier/util/Task;
            0      12     1   x$1   Ljava/lang/Object;
    MethodParameters:
      Name                           Flags
      x$1                            final

  public java.lang.String productElementName(int);
    descriptor: (I)Ljava/lang/String;
    flags: (0x0001) ACC_PUBLIC
    Code:
      stack=3, locals=2, args_size=2
         0: getstatic     #38                 // Field coursier/util/Task$.MODULE$:Lcoursier/util/Task$;
         3: aload_0
         4: invokevirtual #182                // Method value:()Lscala/Function1;
         7: iload_1
         8: invokevirtual #56                 // Method coursier/util/Task$.productElementName$extension:(Lscala/Function1;I)Ljava/lang/String;
        11: areturn
      LineNumberTable:
        line 9: 0
      LocalVariableTable:
        Start  Length  Slot  Name   Signature
            0      12     0  this   Lcoursier/util/Task;
            0      12     1   x$1   I
    MethodParameters:
      Name                           Flags
      x$1                            final

  public int hashCode();
    descriptor: ()I
    flags: (0x0001) ACC_PUBLIC
    Code:
      stack=2, locals=1, args_size=1
         0: getstatic     #38                 // Field coursier/util/Task$.MODULE$:Lcoursier/util/Task$;
         3: aload_0
         4: invokevirtual #182                // Method value:()Lscala/Function1;
         7: invokevirtual #51                 // Method coursier/util/Task$.hashCode$extension:(Lscala/Function1;)I
        10: ireturn
      LineNumberTable:
        line 9: 0
      LocalVariableTable:
        Start  Length  Slot  Name   Signature
            0      11     0  this   Lcoursier/util/Task;

  public boolean equals(java.lang.Object);
    descriptor: (Ljava/lang/Object;)Z
    flags: (0x0001) ACC_PUBLIC
    Code:
      stack=3, locals=2, args_size=2
         0: getstatic     #38                 // Field coursier/util/Task$.MODULE$:Lcoursier/util/Task$;
         3: aload_0
         4: invokevirtual #182                // Method value:()Lscala/Function1;
         7: aload_1
         8: invokevirtual #46                 // Method coursier/util/Task$.equals$extension:(Lscala/Function1;Ljava/lang/Object;)Z
        11: ireturn
      LineNumberTable:
        line 9: 0
      LocalVariableTable:
        Start  Length  Slot  Name   Signature
            0      12     0  this   Lcoursier/util/Task;
            0      12     1   x$1   Ljava/lang/Object;
    MethodParameters:
      Name                           Flags
      x$1                            final

  public java.lang.String toString();
    descriptor: ()Ljava/lang/String;
    flags: (0x0001) ACC_PUBLIC
    Code:
      stack=2, locals=1, args_size=1
         0: getstatic     #38                 // Field coursier/util/Task$.MODULE$:Lcoursier/util/Task$;
         3: aload_0
         4: invokevirtual #182                // Method value:()Lscala/Function1;
         7: invokevirtual #40                 // Method coursier/util/Task$.toString$extension:(Lscala/Function1;)Ljava/lang/String;
        10: areturn
      LineNumberTable:
        line 9: 0
      LocalVariableTable:
        Start  Length  Slot  Name   Signature
            0      11     0  this   Lcoursier/util/Task;

  public coursier.util.Task(scala.Function1<scala.concurrent.ExecutionContext, scala.concurrent.Future<T>>);
    descriptor: (Lscala/Function1;)V
    flags: (0x0001) ACC_PUBLIC
    Code:
      stack=2, locals=2, args_size=2
         0: aload_0
         1: aload_1
         2: putfield      #178                // Field value:Lscala/Function1;
         5: aload_0
         6: invokespecial #226                // Method java/lang/Object."<init>":()V
         9: aload_0
        10: invokestatic  #230                // InterfaceMethod scala/Product.$init$:(Lscala/Product;)V
        13: return
      LineNumberTable:
        line 9: 0
      LocalVariableTable:
        Start  Length  Slot  Name   Signature
            0      14     0  this   Lcoursier/util/Task;
            0      14     1 value   Lscala/Function1;
    Signature: #223                         // (Lscala/Function1<Lscala/concurrent/ExecutionContext;Lscala/concurrent/Future<TT;>;>;)V
    MethodParameters:
      Name                           Flags
      value                          final
}
InnerClasses:
  public #18= #15 of #17;                 // PlatformTaskOps=class coursier/util/PlatformTaskCompanion$PlatformTaskOps of class coursier/util/PlatformTaskCompanion
  public final #20;                       // class coursier/util/Task$$anon$1
  public final #22;                       // class coursier/util/Task$$anonfun$attempt$extension$1
  public static final #25= #24 of #2;     // WrappedException=class coursier/util/Task$WrappedException of class coursier/util/Task
Signature: #3                           // <T:Ljava/lang/Object;>Ljava/lang/Object;Lscala/Product;Ljava/io/Serializable;
SourceFile: "Task.scala"
RuntimeVisibleAnnotations:
  0: #11(#12=s#13)
    scala.reflect.ScalaSignature(
      bytes="\u0006\u0005\u0011ua\u0001B\u001c9\u0005vB\u0001\u0002\u0016\u0001\u0003\u0016\u0004%\t!\u0016\u0005\t[\u0002\u0011\t\u0012)A\u0005-\")a\u000e\u0001C\u0001_\")1\u000f\u0001C\u0001i\")Q\u0010\u0001C\u0001}\"9\u00111\u0002\u0001\u0005\u0002\u00055\u0001bBA\u0014\u0001\u0011\u0005\u0011\u0011\u0006\u0005\b\u0003c\u0001A\u0011AA\u001a\u0011\u001d\ti\u0004\u0001C\u0001\u0003\u007fA\u0011\"a\u0019\u0001\u0003\u0003%\t!!\u001a\t\u0013\u0005U\u0004!%A\u0005\u0002\u0005]\u0004\"CAI\u0001\u0005\u0005I\u0011IAJ\u0011%\t\t\u000bAA\u0001\n\u0003\t\u0019\u000bC\u0005\u0002,\u0002\t\t\u0011\"\u0001\u0002.\"I\u00111\u0017\u0001\u0002\u0002\u0013\u0005\u0013Q\u0017\u0005\n\u0003\u0007\u0004\u0011\u0011!C\u0001\u0003\u000bD\u0011\"a4\u0001\u0003\u0003%\t%!5\t\u0013\u0005U\u0007!!A\u0005B\u0005]\u0007\"CAm\u0001\u0005\u0005I\u0011IAn\u0011%\ty\u000eAA\u0001\n\u0003\n\toB\u0004\u0002dbB\t!!:\u0007\r]B\u0004\u0012AAt\u0011\u0019qg\u0003\"\u0001\u0002z\"9\u00111 \f\u0005\u0002\u0005u\bb\u0002B\u0007-\u0011\u0005!q\u0002\u0005\b\u0005C1B\u0011\u0001B\u0012\u0011\u001d\u0011iC\u0006C\u0001\u0005_AqAa\u0010\u0017\t\u0003\u0011\t\u0005C\u0004\u0003HY!\tA!\u0013\t\u000f\t\u001dd\u0003\"\u0001\u0003j\u00191!1\u000f\f\u0003\u0005kB!Ba\u001e \u0005\u0003\u0005\u000b\u0011BA\u0011\u0011\u0019qw\u0004\"\u0001\u0003z!9!\u0011\u0011\f\u0005\n\t\r\u0005\"\u0003BM-\u0005\u0005I\u0011\u0011BN\u0011%\u0011YKFA\u0001\n\u0003\u0013i\u000bC\u0005\u0003FZ\t\t\u0011\"\u0003\u0003H\"9!q\u001a\f\u0005\u0006\tE\u0007b\u0002Bv-\u0011\u0015!Q\u001e\u0005\b\u0007\u000b1BQAB\u0004\u0011\u001d\u0019\tC\u0006C\u0003\u0007GAqaa\u000e\u0017\t\u000b\u0019I\u0004C\u0004\u0004JY!)aa\u0013\t\u0013\ruc#!A\u0005\u0006\r}\u0003\"CB=-E\u0005IQAB>\u0011%\u0019yIFA\u0001\n\u000b\u0019\t\nC\u0005\u0004\u001eZ\t\t\u0011\"\u0002\u0004 \"I11\u0016\f\u0002\u0002\u0013\u00151Q\u0016\u0005\n\u0007{3\u0012\u0011!C\u0003\u0007\u007fC\u0011ba3\u0017\u0003\u0003%)a!4\t\u0013\rug#!A\u0005\u0006\r}\u0007\"CBx-\u0005\u0005IQABy\u0011%\u0019iPFA\u0001\n\u000b\u0019y\u0010C\u0005\u0005\u0010Y\t\t\u0011\"\u0002\u0005\u0012\t!A+Y:l\u0015\tI$(\u0001\u0003vi&d\'\"A\u001e\u0002\u0011\r|WO]:jKJ\u001c\u0001!\u0006\u0002?IN!\u0001aP#I!\t\u00015)D\u0001B\u0015\u0005\u0011\u0015!B:dC2\f\u0017B\u0001#B\u0005\u0019\te.\u001f,bYB\u0011\u0001IR\u0005\u0003\u000f\u0006\u0013q\u0001\u0015:pIV\u001cG\u000f\u0005\u0002J#:\u0011!j\u0014\b\u0003\u0017:k\u0011\u0001\u0014\u0006\u0003\u001br\na\u0001\u0010:p_Rt\u0014\"\u0001\"\n\u0005A\u000b\u0015a\u00029bG.\fw-Z\u0005\u0003%N\u0013AbU3sS\u0006d\u0017N_1cY\u0016T!\u0001U!\u0002\u000bY\fG.^3\u0016\u0003Y\u0003B\u0001Q,Z?&\u0011\u0001,\u0011\u0002\n\rVt7\r^5p]F\u0002\"AW/\u000e\u0003mS!\u0001X!\u0002\u0015\r|gnY;se\u0016tG/\u0003\u0002_7\n\u0001R\t_3dkRLwN\\\"p]R,\u0007\u0010\u001e\t\u00045\u0002\u0014\u0017BA1\\\u0005\u00191U\u000f^;sKB\u00111\r\u001a\u0007\u0001\t\u0019)\u0007\u0001\"b\u0001M\n\tA+\u0005\u0002hUB\u0011\u0001\t[\u0005\u0003S\u0006\u0013qAT8uQ&tw\r\u0005\u0002AW&\u0011A.\u0011\u0002\u0004\u0003:L\u0018A\u0002<bYV,\u0007%\u0001\u0004=S:LGO\u0010\u000b\u0003aJ\u00042!\u001d\u0001c\u001b\u0005A\u0004\"\u0002+\u0004\u0001\u00041\u0016aA7baV\u0011Q\u000f\u001f\u000b\u0003mj\u00042!\u001d\u0001x!\t\u0019\u0007\u0010B\u0003z\t\t\u0007aMA\u0001V\u0011\u0015YH\u00011\u0001}\u0003\u00051\u0007\u0003\u0002!XE^\fqA\u001a7bi6\u000b\u0007/F\u0002\u0000\u0003\u000b!B!!\u0001\u0002\bA!\u0011\u000fAA\u0002!\r\u0019\u0017Q\u0001\u0003\u0006s\u0016\u0011\rA\u001a\u0005\u0007w\u0016\u0001\r!!\u0003\u0011\u000b\u0001;&-!\u0001\u0002\r!\fg\u000e\u001a7f+\u0011\ty!!\u0006\u0015\t\u0005E\u0011\u0011\u0004\t\u0005c\u0002\t\u0019\u0002E\u0002d\u0003+!a!\u001f\u0004C\u0002\u0005]\u0011C\u00012k\u0011\u0019Yh\u00011\u0001\u0002\u001cA9\u0001)!\b\u0002\"\u0005M\u0011bAA\u0010\u0003\ny\u0001+\u0019:uS\u0006dg)\u001e8di&|g\u000eE\u0002J\u0003GI1!!\nT\u0005%!\u0006N]8xC\ndW-\u0001\u0004gkR,(/\u001a\u000b\u0003\u0003W!2aXA\u0017\u0011\u0019\tyc\u0002a\u00023\u0006\u0011QmY\u0001\bCR$X-\u001c9u+\t\t)\u0004\u0005\u0003r\u0001\u0005]\u0002CB%\u0002:\u0005\u0005\"-C\u0002\u0002<M\u0013a!R5uQ\u0016\u0014\u0018\u0001C:dQ\u0016$W\u000f\\3\u0015\u000bA\f\t%a\u0014\t\u000f\u0005\r\u0013\u00021\u0001\u0002F\u0005AA-\u001e:bi&|g\u000e\u0005\u0003\u0002H\u0005-SBAA%\u0015\r\t\u0019eW\u0005\u0005\u0003\u001b\nIE\u0001\u0005EkJ\fG/[8o\u0011\u001d\t\t&\u0003a\u0001\u0003\'\n!!Z:\u0011\t\u0005U\u0013qL\u0007\u0003\u0003/R1\u0001XA-\u0015\rI\u00141\f\u0006\u0003\u0003;\nAA[1wC&!\u0011\u0011MA,\u0005a\u00196\r[3ek2,G-\u0012=fGV$xN]*feZL7-Z\u0001\u0005G>\u0004\u00180\u0006\u0003\u0002h\u00055D\u0003BA5\u0003_\u0002B!\u001d\u0001\u0002lA\u00191-!\u001c\u0005\u000b\u0015T!\u0019\u00014\t\u0011QS\u0001\u0013!a\u0001\u0003c\u0002R\u0001Q,Z\u0003g\u0002BA\u00171\u0002l\u0005q1m\u001c9zI\u0011,g-Y;mi\u0012\nT\u0003BA=\u0003\u001f+\"!a\u001f+\u0007Y\u000bih\u000b\u0002\u0002\u0000A!\u0011\u0011QAF\u001b\t\t\u0019I\u0003\u0003\u0002\u0006\u0006\u001d\u0015!C;oG\",7m[3e\u0015\r\tI)Q\u0001\u000bC:tw\u000e^1uS>t\u0017\u0002BAG\u0003\u0007\u0013\u0011#\u001e8dQ\u0016\u001c7.\u001a3WCJL\u0017M\\2f\t\u0015)7B1\u0001g\u00035\u0001(o\u001c3vGR\u0004&/\u001a4jqV\u0011\u0011Q\u0013\t\u0005\u0003/\u000bi*\u0004\u0002\u0002\u001a*!\u00111TA.\u0003\u0011a\u0017M\\4\n\t\u0005}\u0015\u0011\u0014\u0002\u0007\'R\u0014\u0018N\\4\u0002\u0019A\u0014x\u000eZ;di\u0006\u0013\u0018\u000e^=\u0016\u0005\u0005\u0015\u0006c\u0001!\u0002(&\u0019\u0011\u0011V!\u0003\u0007%sG/\u0001\bqe>$Wo\u0019;FY\u0016lWM\u001c;\u0015\u0007)\fy\u000bC\u0005\u00022:\t\t\u00111\u0001\u0002&\u0006\u0019\u0001\u0010J\u0019\u0002\u001fA\u0014x\u000eZ;di&#XM]1u_J,\"!a.\u0011\u000b\u0005e\u0016q\u00186\u000e\u0005\u0005m&bAA_\u0003\u0006Q1m\u001c7mK\u000e$\u0018n\u001c8\n\t\u0005\u0005\u00171\u0018\u0002\t\u0013R,\'/\u0019;pe\u0006A1-\u00198FcV\fG\u000e\u0006\u0003\u0002H\u00065\u0007c\u0001!\u0002J&\u0019\u00111Z!\u0003\u000f\t{w\u000e\\3b]\"A\u0011\u0011\u0017\t\u0002\u0002\u0003\u0007!.\u0001\nqe>$Wo\u0019;FY\u0016lWM\u001c;OC6,G\u0003BAK\u0003\'D\u0011\"!-\u0012\u0003\u0003\u0005\r!!*\u0002\u0011!\f7\u000f[\"pI\u0016$\"!!*\u0002\r\u0015\fX/\u00197t)\u0011\t9-!8\t\u0011\u0005E6#!AA\u0002)\f\u0001\u0002^8TiJLgn\u001a\u000b\u0003\u0003+\u000bA\u0001V1tWB\u0011\u0011OF\n\u0006-\u0005%\u0018q\u001e\t\u0004c\u0006-\u0018bAAwq\t)\u0002\u000b\\1uM>\u0014X\u000eV1tW\u000e{W\u000e]1oS>t\u0007\u0003BAy\u0003ol!!a=\u000b\t\u0005U\u00181L\u0001\u0003S>L1AUAz)\t\t)/A\u0003q_&tG/\u0006\u0003\u0002\u0000\n\u0015A\u0003\u0002B\u0001\u0005\u0013\u0001B!\u001d\u0001\u0003\u0004A\u00191M!\u0002\u0005\r\t\u001d\u0001D1\u0001g\u0005\u0005\t\u0005b\u0002B\u00061\u0001\u0007!1A\u0001\u0002C\u0006)A-\u001a7bsV!!\u0011\u0003B\f)\u0011\u0011\u0019B!\u0007\u0011\tE\u0004!Q\u0003\t\u0004G\n]AA\u0002B\u00043\t\u0007a\r\u0003\u0005\u0003\fe!\t\u0019\u0001B\u000e!\u0015\u0001%Q\u0004B\u000b\u0013\r\u0011y\"\u0011\u0002\ty\tLh.Y7f}\u0005)a.\u001a<feV!!Q\u0005B\u0016+\t\u00119\u0003\u0005\u0003r\u0001\t%\u0002cA2\u0003,\u00111!q\u0001\u000eC\u0002\u0019\f!B\u001a:p[\u0016KG\u000f[3s+\u0011\u0011\tDa\u000e\u0015\t\tM\"\u0011\b\t\u0005c\u0002\u0011)\u0004E\u0002d\u0005o!Q!Z\u000eC\u0002\u0019DqAa\u000f\u001c\u0001\u0004\u0011i$A\u0001f!\u001dI\u0015\u0011HA\u0011\u0005k\tAAZ1jYR!!1\tB#!\r\t\ba\u001a\u0005\b\u0005wa\u0002\u0019AA\u0011\u0003!!\u0018-\u001b7SK\u000elUC\u0002B&\u0005?\u0012\u0019\u0006\u0006\u0003\u0003N\t\u0015D\u0003\u0002B(\u0005/\u0002B!\u001d\u0001\u0003RA\u00191Ma\u0015\u0005\r\tUSD1\u0001g\u0005\u0005\u0011\u0005b\u0002B-;\u0001\u0007!1L\u0001\u0003M:\u0004b\u0001Q,\u0003^\t\u0005\u0004cA2\u0003`\u00111!qA\u000fC\u0002\u0019\u0004B!\u001d\u0001\u0003dA9\u0011*!\u000f\u0003^\tE\u0003b\u0002B\u0006;\u0001\u0007!QL\u0001\u0007O\u0006$\b.\u001a:\u0016\u0005\t-\u0004#B9\u0003n\tE\u0014b\u0001B8q\t1q)\u0019;iKJ\u0004\"!\u001d\u0001\u0003!]\u0013\u0018\r\u001d9fI\u0016C8-\u001a9uS>t7cA\u0010\u0002\"\u0005)1-Y;tKR!!1\u0010B@!\r\u0011ihH\u0007\u0002-!9!qO\u0011A\u0002\u0005\u0005\u0012\u0001B<sCB,BA!\"\u0003\nR!!q\u0011BF!\r\u0019\'\u0011\u0012\u0003\u0006K\n\u0012\rA\u001a\u0005\t\u0005\u001b\u0013C\u00111\u0001\u0003\u0010\u0006\tA\u000fE\u0003A\u0005;\u00119\tK\u0002#\u0005\'\u00032\u0001\u0011BK\u0013\r\u00119*\u0011\u0002\u0007S:d\u0017N\\3\u0002\u000b\u0005\u0004\b\u000f\\=\u0016\t\tu%1\u0015\u000b\u0005\u0005?\u0013)\u000b\u0005\u0003r\u0001\t\u0005\u0006cA2\u0003$\u0012)Qm\tb\u0001M\"1Ak\ta\u0001\u0005O\u0003R\u0001Q,Z\u0005S\u0003BA\u00171\u0003\"\u00069QO\\1qa2LX\u0003\u0002BX\u0005{#BA!-\u0003@B)\u0001Ia-\u00038&\u0019!QW!\u0003\r=\u0003H/[8o!\u0015\u0001u+\u0017B]!\u0011Q\u0006Ma/\u0011\u0007\r\u0014i\fB\u0003fI\t\u0007a\rC\u0005\u0003B\u0012\n\t\u00111\u0001\u0003D\u0006\u0019\u0001\u0010\n\u0019\u0011\tE\u0004!1X\u0001\roJLG/\u001a*fa2\f7-\u001a\u000b\u0003\u0005\u0013\u0004B!a&\u0003L&!!QZAM\u0005\u0019y%M[3di\u0006iQ.\u00199%Kb$XM\\:j_:,bAa5\u0003\\\n\rH\u0003\u0002Bk\u0005K$BAa6\u0003^B!\u0011\u000f\u0001Bm!\r\u0019\'1\u001c\u0003\u0006s\u001a\u0012\rA\u001a\u0005\u0007w\u001a\u0002\rAa8\u0011\r\u0001;&\u0011\u001dBm!\r\u0019\'1\u001d\u0003\u0006K\u001a\u0012\rA\u001a\u0005\b\u0005O4\u0003\u0019\u0001Bu\u0003\u0015!C\u000f[5t!\u0011\t\bA!9\u0002#\u0019d\u0017\r^\'ba\u0012*\u0007\u0010^3og&|g.\u0006\u0004\u0003p\n](q \u000b\u0005\u0005c\u001c\t\u0001\u0006\u0003\u0003t\ne\b\u0003B9\u0001\u0005k\u00042a\u0019B|\t\u0015IxE1\u0001g\u0011\u0019Yx\u00051\u0001\u0003|B1\u0001i\u0016B\u007f\u0005g\u00042a\u0019B\u0000\t\u0015)wE1\u0001g\u0011\u001d\u00119o\na\u0001\u0007\u0007\u0001B!\u001d\u0001\u0003~\u0006\u0001\u0002.\u00198eY\u0016$S\r\u001f;f]NLwN\\\u000b\u0007\u0007\u0013\u0019\tba\u0006\u0015\t\r-1Q\u0004\u000b\u0005\u0007\u001b\u0019I\u0002\u0005\u0003r\u0001\r=\u0001cA2\u0004\u0012\u00111\u0011\u0010\u000bb\u0001\u0007\'\t2a!\u0006k!\r\u00197q\u0003\u0003\u0006K\"\u0012\rA\u001a\u0005\u0007w\"\u0002\raa\u0007\u0011\u000f\u0001\u000bi\"!\t\u0004\u0010!9!q\u001d\u0015A\u0002\r}\u0001\u0003B9\u0001\u0007+\t\u0001CZ;ukJ,G%\u001a=uK:\u001c\u0018n\u001c8\u0016\t\r\u00152q\u0006\u000b\u0005\u0007O\u0019\u0019\u0004\u0006\u0002\u0004*Q!11FB\u0019!\u0011Q\u0006m!\f\u0011\u0007\r\u001cy\u0003B\u0003fS\t\u0007a\r\u0003\u0004\u00020%\u0002\u001d!\u0017\u0005\b\u0005OL\u0003\u0019AB\u001b!\u0011\t\ba!\f\u0002#\u0005$H/Z7qi\u0012*\u0007\u0010^3og&|g.\u0006\u0003\u0004<\r\rC\u0003BB\u001f\u0007\u000b\u0002B!\u001d\u0001\u0004@A9\u0011*!\u000f\u0002\"\r\u0005\u0003cA2\u0004D\u0011)QM\u000bb\u0001M\"9!q\u001d\u0016A\u0002\r\u001d\u0003\u0003B9\u0001\u0007\u0003\n!c]2iK\u0012,H.\u001a\u0013fqR,gn]5p]V!1QJB+)\u0011\u0019yea\u0017\u0015\r\rE3qKB-!\u0011\t\baa\u0015\u0011\u0007\r\u001c)\u0006B\u0003fW\t\u0007a\rC\u0004\u0002D-\u0002\r!!\u0012\t\u000f\u0005E3\u00061\u0001\u0002T!9!q]\u0016A\u0002\rE\u0013AD2paf$S\r\u001f;f]NLwN\\\u000b\u0007\u0007C\u001aIga\u001e\u0015\t\r\r4\u0011\u000f\u000b\u0005\u0007K\u001aY\u0007\u0005\u0003r\u0001\r\u001d\u0004cA2\u0004j\u0011)Q\r\fb\u0001M\"AA\u000b\fI\u0001\u0002\u0004\u0019i\u0007E\u0003A/f\u001by\u0007\u0005\u0003[A\u000e\u001d\u0004b\u0002BtY\u0001\u000711\u000f\t\u0005c\u0002\u0019)\bE\u0002d\u0007o\"Q!\u001a\u0017C\u0002\u0019\f\u0001dY8qs\u0012\"WMZ1vYR$\u0013\u0007J3yi\u0016t7/[8o+\u0019\u0019ih!$\u0004\bR!1qPBEU\u0011\u0019\t)! \u0011\u000b\u0001;\u0016la!\u0011\ti\u00037Q\u0011\t\u0004G\u000e\u001dE!B3.\u0005\u00041\u0007b\u0002Bt[\u0001\u000711\u0012\t\u0005c\u0002\u0019)\tB\u0003f[\t\u0007a-A\fqe>$Wo\u0019;Qe\u00164\u0017\u000e\u001f\u0013fqR,gn]5p]V!11SBN)\u0011\t)j!&\t\u000f\t\u001dh\u00061\u0001\u0004\u0018B!\u0011\u000fABM!\r\u001971\u0014\u0003\u0006K:\u0012\rAZ\u0001\u0017aJ|G-^2u\u0003JLG/\u001f\u0013fqR,gn]5p]V!1\u0011UBU)\u0011\t)ka)\t\u000f\t\u001dx\u00061\u0001\u0004&B!\u0011\u000fABT!\r\u00197\u0011\u0016\u0003\u0006K>\u0012\rAZ\u0001\u0019aJ|G-^2u\u000b2,W.\u001a8uI\u0015DH/\u001a8tS>tW\u0003BBX\u0007w#Ba!-\u00046R\u0019!na-\t\u0013\u0005E\u0006\'!AA\u0002\u0005\u0015\u0006b\u0002Bta\u0001\u00071q\u0017\t\u0005c\u0002\u0019I\fE\u0002d\u0007w#Q!\u001a\u0019C\u0002\u0019\f\u0011\u0004\u001d:pIV\u001cG/\u0013;fe\u0006$xN\u001d\u0013fqR,gn]5p]V!1\u0011YBe)\u0011\t9la1\t\u000f\t\u001d\u0018\u00071\u0001\u0004FB!\u0011\u000fABd!\r\u00197\u0011\u001a\u0003\u0006KF\u0012\rAZ\u0001\u0013G\u0006tW)];bY\u0012*\u0007\u0010^3og&|g.\u0006\u0003\u0004P\u000emG\u0003BBi\u0007+$B!a2\u0004T\"A\u0011\u0011\u0017\u001a\u0002\u0002\u0003\u0007!\u000eC\u0004\u0003hJ\u0002\raa6\u0011\tE\u00041\u0011\u001c\t\u0004G\u000emG!B33\u0005\u00041\u0017\u0001\b9s_\u0012,8\r^#mK6,g\u000e\u001e(b[\u0016$S\r\u001f;f]NLwN\\\u000b\u0005\u0007C\u001ci\u000f\u0006\u0003\u0004d\u000e\u001dH\u0003BAK\u0007KD\u0011\"!-4\u0003\u0003\u0005\r!!*\t\u000f\t\u001d8\u00071\u0001\u0004jB!\u0011\u000fABv!\r\u00197Q\u001e\u0003\u0006KN\u0012\rAZ\u0001\u0013Q\u0006\u001c\bnQ8eK\u0012*\u0007\u0010^3og&|g.\u0006\u0003\u0004t\u000emH\u0003BAl\u0007kDqAa:5\u0001\u0004\u00199\u0010\u0005\u0003r\u0001\re\bcA2\u0004|\u0012)Q\r\u000eb\u0001M\u0006\u0001R-];bYN$S\r\u001f;f]NLwN\\\u000b\u0005\t\u0003!i\u0001\u0006\u0003\u0005\u0004\u0011\u001dA\u0003BAd\t\u000bA\u0001\"!-6\u0003\u0003\u0005\rA\u001b\u0005\b\u0005O,\u0004\u0019\u0001C\u0005!\u0011\t\b\u0001b\u0003\u0011\u0007\r$i\u0001B\u0003fk\t\u0007a-\u0001\nu_N#(/\u001b8hI\u0015DH/\u001a8tS>tW\u0003\u0002C\n\t7!B!!9\u0005\u0016!9!q\u001d\u001cA\u0002\u0011]\u0001\u0003B9\u0001\t3\u00012a\u0019C\u000e\t\u0015)gG1\u0001g\u0001"
    )
  ScalaInlineInfo: length = 0x68 (unknown attribute)
   01 01 00 14 00 DD 00 DE 01 00 C1 00 8D 01 00 D5
   00 D6 01 00 C8 00 4D 01 00 CA 00 8D 01 00 DB 00
   D6 01 00 B7 00 4D 01 00 BD 00 BE 01 00 B9 00 BA
   01 00 DA 00 CF 01 00 B3 00 4D 01 00 CE 00 CF 01
   00 D0 00 D1 01 00 D8 00 D9 01 00 A7 00 A8 01 00
   D3 00 A8 01 00 CC 00 CD 01 00 C3 00 C4 01 00 DC
   00 CD 01 00 1A 00 8D 01
  ScalaSig: length = 0x3 (unknown attribute)
   05 02 00
