Classfile /Users/mw/Projects/slang-braindump/.jar/jar11/assemble/slang-braindump/assemble/content/coursier/util/Traverse$.class
  Last modified May 29, 2022; size 934 bytes
  SHA-256 checksum 4841b766c29de10dee571e80734fed0f996bd824a931d23f73b094ded089a647
  Compiled from "Traverse.scala"
public final class coursier.util.Traverse$
  minor version: 0
  major version: 52
  flags: (0x0031) ACC_PUBLIC, ACC_FINAL, ACC_SUPER
  this_class: #2                          // coursier/util/Traverse$
  super_class: #4                         // java/lang/Object
  interfaces: 0, fields: 1, methods: 3, attributes: 4
Constant pool:
   #1 = Utf8               coursier/util/Traverse$
   #2 = Class              #1             // coursier/util/Traverse$
   #3 = Utf8               java/lang/Object
   #4 = Class              #3             // java/lang/Object
   #5 = Utf8               Traverse.scala
   #6 = Utf8               coursier/util/Traverse$TraverseOps
   #7 = Class              #6             // coursier/util/Traverse$TraverseOps
   #8 = Utf8               coursier/util/Traverse
   #9 = Class              #8             // coursier/util/Traverse
  #10 = Utf8               TraverseOps
  #11 = Utf8               MODULE$
  #12 = Utf8               Lcoursier/util/Traverse$;
  #13 = Utf8               <clinit>
  #14 = Utf8               ()V
  #15 = Utf8               <init>
  #16 = NameAndType        #15:#14        // "<init>":()V
  #17 = Methodref          #2.#16         // coursier/util/Traverse$."<init>":()V
  #18 = NameAndType        #11:#12        // MODULE$:Lcoursier/util/Traverse$;
  #19 = Fieldref           #2.#18         // coursier/util/Traverse$.MODULE$:Lcoursier/util/Traverse$;
  #20 = Utf8               (Lscala/collection/immutable/Seq;)Lcoursier/util/Traverse$TraverseOps;
  #21 = Utf8               <T:Ljava/lang/Object;>(Lscala/collection/immutable/Seq<TT;>;)Lcoursier/util/Traverse$TraverseOps<TT;>;
  #22 = Utf8               seq
  #23 = Utf8               (Lscala/collection/immutable/Seq;)V
  #24 = NameAndType        #15:#23        // "<init>":(Lscala/collection/immutable/Seq;)V
  #25 = Methodref          #7.#24         // coursier/util/Traverse$TraverseOps."<init>":(Lscala/collection/immutable/Seq;)V
  #26 = Utf8               this
  #27 = Utf8               Lscala/collection/immutable/Seq;
  #28 = Methodref          #4.#16         // java/lang/Object."<init>":()V
  #29 = Utf8               Code
  #30 = Utf8               LineNumberTable
  #31 = Utf8               LocalVariableTable
  #32 = Utf8               Signature
  #33 = Utf8               MethodParameters
  #34 = Utf8               InnerClasses
  #35 = Utf8               SourceFile
  #36 = Utf8               ScalaInlineInfo
  #37 = Utf8               Scala
{
  public static final coursier.util.Traverse$ MODULE$;
    descriptor: Lcoursier/util/Traverse$;
    flags: (0x0019) ACC_PUBLIC, ACC_STATIC, ACC_FINAL

  public static {};
    descriptor: ()V
    flags: (0x0009) ACC_PUBLIC, ACC_STATIC
    Code:
      stack=2, locals=0, args_size=0
         0: new           #2                  // class coursier/util/Traverse$
         3: dup
         4: invokespecial #17                 // Method "<init>":()V
         7: putstatic     #19                 // Field MODULE$:Lcoursier/util/Traverse$;
        10: return
      LineNumberTable:
        line 5: 0

  public <T extends java.lang.Object> coursier.util.Traverse$TraverseOps<T> TraverseOps(scala.collection.immutable.Seq<T>);
    descriptor: (Lscala/collection/immutable/Seq;)Lcoursier/util/Traverse$TraverseOps;
    flags: (0x0001) ACC_PUBLIC
    Code:
      stack=3, locals=2, args_size=2
         0: new           #7                  // class coursier/util/Traverse$TraverseOps
         3: dup
         4: aload_1
         5: invokespecial #25                 // Method coursier/util/Traverse$TraverseOps."<init>":(Lscala/collection/immutable/Seq;)V
         8: areturn
      LineNumberTable:
        line 7: 0
      LocalVariableTable:
        Start  Length  Slot  Name   Signature
            0       9     0  this   Lcoursier/util/Traverse$;
            0       9     1   seq   Lscala/collection/immutable/Seq;
    Signature: #21                          // <T:Ljava/lang/Object;>(Lscala/collection/immutable/Seq<TT;>;)Lcoursier/util/Traverse$TraverseOps<TT;>;
    MethodParameters:
      Name                           Flags
      seq                            final

  private coursier.util.Traverse$();
    descriptor: ()V
    flags: (0x0002) ACC_PRIVATE
    Code:
      stack=1, locals=1, args_size=1
         0: aload_0
         1: invokespecial #28                 // Method java/lang/Object."<init>":()V
         4: return
      LineNumberTable:
        line 51: 0
        line 5: 4
      LocalVariableTable:
        Start  Length  Slot  Name   Signature
            0       5     0  this   Lcoursier/util/Traverse$;
}
InnerClasses:
  public static #10= #7 of #9;            // TraverseOps=class coursier/util/Traverse$TraverseOps of class coursier/util/Traverse
SourceFile: "Traverse.scala"
  ScalaInlineInfo: length = 0xE (unknown attribute)
   01 01 00 02 00 0F 00 0E 01 00 0A 00 14 01
  Scala: length = 0x0 (unknown attribute)

