Classfile /Users/mw/Projects/slang-braindump/.jar/jar11/assemble/slang-braindump/assemble/content/coursier/util/WebPageCompatibility.class
  Last modified May 29, 2022; size 3145 bytes
  SHA-256 checksum 82aa9493e47ef27d77e99bfe55c08611e3ae452ab4a3796880848b772f42029a
  Compiled from "WebPageCompatibility.scala"
public abstract class coursier.util.WebPageCompatibility
  minor version: 0
  major version: 52
  flags: (0x0421) ACC_PUBLIC, ACC_SUPER, ACC_ABSTRACT
  this_class: #2                          // coursier/util/WebPageCompatibility
  super_class: #4                         // java/lang/Object
  interfaces: 0, fields: 0, methods: 4, attributes: 6
Constant pool:
    #1 = Utf8               coursier/util/WebPageCompatibility
    #2 = Class              #1            // coursier/util/WebPageCompatibility
    #3 = Utf8               java/lang/Object
    #4 = Class              #3            // java/lang/Object
    #5 = Utf8               WebPageCompatibility.scala
    #6 = Utf8               Lscala/reflect/ScalaSignature;
    #7 = Utf8               bytes
    #8 = Utf8               \u0006\u000512aa\u0001\u0003\u0002\u0002\u0019A\u0001\"B\b\u0001\t\u0003\t\u0002\"\u0002\u000b\u0001\t\u0003)\"\u0001F,fEB\u000bw-Z\"p[B\fG/\u001b2jY&$\u0018P\u0003\u0002\u0006\r\u0005!Q\u000f^5m\u0015\u00059\u0011\u0001C2pkJ\u001c\u0018.\u001a:\u0014\u0005\u0001I\u0001C\u0001\u0006\u000e\u001b\u0005Y!\"\u0001\u0007\u0002\u000bM\u001c\u0017\r\\1\n\u00059Y!AB!osJ+g-\u0001\u0004=S:LGOP\u0002\u0001)\u0005\u0011\u0002CA\n\u0001\u001b\u0005!\u0011A\u00067jgR<VM\u0019)bO\u0016\u0014\u0016m^#mK6,g\u000e^:\u0015\u0005YQ\u0003cA\f E9\u0011\u0001$\b\b\u00033qi\u0011A\u0007\u0006\u00037A\ta\u0001\u0010:p_Rt\u0014\"\u0001\u0007\n\u0005yY\u0011a\u00029bG.\fw-Z\u0005\u0003A\u0005\u0012\u0001\"\u0013;fe\u0006$xN\u001d\u0006\u0003=-\u0001\"aI\u0014\u000f\u0005\u0011*\u0003CA\r\f\u0013\t13\"\u0001\u0004Qe\u0016$WMZ\u0005\u0003Q%\u0012aa\u0015;sS:<\'B\u0001\u0014\f\u0011\u0015Y#\u00011\u0001#\u0003\u0011\u0001\u0018mZ3
    #9 = Utf8               java/lang/invoke/MethodHandles$Lookup
   #10 = Class              #9            // java/lang/invoke/MethodHandles$Lookup
   #11 = Utf8               java/lang/invoke/MethodHandles
   #12 = Class              #11           // java/lang/invoke/MethodHandles
   #13 = Utf8               Lookup
   #14 = Utf8               scala/collection/convert/AsScalaExtensions$ListHasAsScala
   #15 = Class              #14           // scala/collection/convert/AsScalaExtensions$ListHasAsScala
   #16 = Utf8               scala/collection/convert/AsScalaExtensions
   #17 = Class              #16           // scala/collection/convert/AsScalaExtensions
   #18 = Utf8               ListHasAsScala
   #19 = Utf8               listWebPageRawElements
   #20 = Utf8               (Ljava/lang/String;)Lscala/collection/Iterator;
   #21 = Utf8               (Ljava/lang/String;)Lscala/collection/Iterator<Ljava/lang/String;>;
   #22 = Utf8               page
   #23 = Utf8               scala/jdk/CollectionConverters$
   #24 = Class              #23           // scala/jdk/CollectionConverters$
   #25 = Utf8               MODULE$
   #26 = Utf8               Lscala/jdk/CollectionConverters$;
   #27 = NameAndType        #25:#26       // MODULE$:Lscala/jdk/CollectionConverters$;
   #28 = Fieldref           #24.#27       // scala/jdk/CollectionConverters$.MODULE$:Lscala/jdk/CollectionConverters$;
   #29 = Utf8               coursier/util/shaded/org/jsoup/Jsoup
   #30 = Class              #29           // coursier/util/shaded/org/jsoup/Jsoup
   #31 = Utf8               parse
   #32 = Utf8               (Ljava/lang/String;)Lcoursier/util/shaded/org/jsoup/nodes/Document;
   #33 = NameAndType        #31:#32       // parse:(Ljava/lang/String;)Lcoursier/util/shaded/org/jsoup/nodes/Document;
   #34 = Methodref          #30.#33       // coursier/util/shaded/org/jsoup/Jsoup.parse:(Ljava/lang/String;)Lcoursier/util/shaded/org/jsoup/nodes/Document;
   #35 = Utf8               a
   #36 = String             #35           // a
   #37 = Utf8               coursier/util/shaded/org/jsoup/nodes/Document
   #38 = Class              #37           // coursier/util/shaded/org/jsoup/nodes/Document
   #39 = Utf8               select
   #40 = Utf8               (Ljava/lang/String;)Lcoursier/util/shaded/org/jsoup/select/Elements;
   #41 = NameAndType        #39:#40       // select:(Ljava/lang/String;)Lcoursier/util/shaded/org/jsoup/select/Elements;
   #42 = Methodref          #38.#41       // coursier/util/shaded/org/jsoup/nodes/Document.select:(Ljava/lang/String;)Lcoursier/util/shaded/org/jsoup/select/Elements;
   #43 = Utf8               (Ljava/util/List;)Lscala/collection/convert/AsScalaExtensions$ListHasAsScala;
   #44 = NameAndType        #18:#43       // ListHasAsScala:(Ljava/util/List;)Lscala/collection/convert/AsScalaExtensions$ListHasAsScala;
   #45 = Methodref          #24.#44       // scala/jdk/CollectionConverters$.ListHasAsScala:(Ljava/util/List;)Lscala/collection/convert/AsScalaExtensions$ListHasAsScala;
   #46 = Utf8               asScala
   #47 = Utf8               ()Lscala/collection/mutable/Buffer;
   #48 = NameAndType        #46:#47       // asScala:()Lscala/collection/mutable/Buffer;
   #49 = Methodref          #15.#48       // scala/collection/convert/AsScalaExtensions$ListHasAsScala.asScala:()Lscala/collection/mutable/Buffer;
   #50 = Utf8               scala/collection/mutable/Buffer
   #51 = Class              #50           // scala/collection/mutable/Buffer
   #52 = Utf8               iterator
   #53 = Utf8               ()Lscala/collection/Iterator;
   #54 = NameAndType        #52:#53       // iterator:()Lscala/collection/Iterator;
   #55 = InterfaceMethodref #51.#54       // scala/collection/mutable/Buffer.iterator:()Lscala/collection/Iterator;
   #56 = Utf8               (Ljava/lang/Object;)Ljava/lang/Object;
   #57 = MethodType         #56           //  (Ljava/lang/Object;)Ljava/lang/Object;
   #58 = Utf8               $anonfun$listWebPageRawElements$1
   #59 = Utf8               (Lcoursier/util/shaded/org/jsoup/nodes/Element;)Ljava/lang/String;
   #60 = NameAndType        #58:#59       // $anonfun$listWebPageRawElements$1:(Lcoursier/util/shaded/org/jsoup/nodes/Element;)Ljava/lang/String;
   #61 = Methodref          #2.#60        // coursier/util/WebPageCompatibility.$anonfun$listWebPageRawElements$1:(Lcoursier/util/shaded/org/jsoup/nodes/Element;)Ljava/lang/String;
   #62 = MethodHandle       6:#61         // REF_invokeStatic coursier/util/WebPageCompatibility.$anonfun$listWebPageRawElements$1:(Lcoursier/util/shaded/org/jsoup/nodes/Element;)Ljava/lang/String;
   #63 = MethodType         #59           //  (Lcoursier/util/shaded/org/jsoup/nodes/Element;)Ljava/lang/String;
   #64 = Integer            5
   #65 = Integer            1
   #66 = Utf8               java/lang/invoke/LambdaMetafactory
   #67 = Class              #66           // java/lang/invoke/LambdaMetafactory
   #68 = Utf8               altMetafactory
   #69 = Utf8               (Ljava/lang/invoke/MethodHandles$Lookup;Ljava/lang/String;Ljava/lang/invoke/MethodType;[Ljava/lang/Object;)Ljava/lang/invoke/CallSite;
   #70 = NameAndType        #68:#69       // altMetafactory:(Ljava/lang/invoke/MethodHandles$Lookup;Ljava/lang/String;Ljava/lang/invoke/MethodType;[Ljava/lang/Object;)Ljava/lang/invoke/CallSite;
   #71 = Methodref          #67.#70       // java/lang/invoke/LambdaMetafactory.altMetafactory:(Ljava/lang/invoke/MethodHandles$Lookup;Ljava/lang/String;Ljava/lang/invoke/MethodType;[Ljava/lang/Object;)Ljava/lang/invoke/CallSite;
   #72 = MethodHandle       6:#71         // REF_invokeStatic java/lang/invoke/LambdaMetafactory.altMetafactory:(Ljava/lang/invoke/MethodHandles$Lookup;Ljava/lang/String;Ljava/lang/invoke/MethodType;[Ljava/lang/Object;)Ljava/lang/invoke/CallSite;
   #73 = Utf8               apply
   #74 = Utf8               ()Lscala/Function1;
   #75 = NameAndType        #73:#74       // apply:()Lscala/Function1;
   #76 = InvokeDynamic      #0:#75        // #0:apply:()Lscala/Function1;
   #77 = Utf8               scala/collection/Iterator
   #78 = Class              #77           // scala/collection/Iterator
   #79 = Utf8               map
   #80 = Utf8               (Lscala/Function1;)Lscala/collection/Iterator;
   #81 = NameAndType        #79:#80       // map:(Lscala/Function1;)Lscala/collection/Iterator;
   #82 = InterfaceMethodref #78.#81       // scala/collection/Iterator.map:(Lscala/Function1;)Lscala/collection/Iterator;
   #83 = Utf8               this
   #84 = Utf8               Lcoursier/util/WebPageCompatibility;
   #85 = Utf8               Ljava/lang/String;
   #86 = Utf8               x$1
   #87 = Utf8               href
   #88 = String             #87           // href
   #89 = Utf8               coursier/util/shaded/org/jsoup/nodes/Element
   #90 = Class              #89           // coursier/util/shaded/org/jsoup/nodes/Element
   #91 = Utf8               attr
   #92 = Utf8               (Ljava/lang/String;)Ljava/lang/String;
   #93 = NameAndType        #91:#92       // attr:(Ljava/lang/String;)Ljava/lang/String;
   #94 = Methodref          #90.#93       // coursier/util/shaded/org/jsoup/nodes/Element.attr:(Ljava/lang/String;)Ljava/lang/String;
   #95 = Utf8               Lcoursier/util/shaded/org/jsoup/nodes/Element;
   #96 = Utf8               <init>
   #97 = Utf8               ()V
   #98 = NameAndType        #96:#97       // "<init>":()V
   #99 = Methodref          #4.#98        // java/lang/Object."<init>":()V
  #100 = Utf8               $deserializeLambda$
  #101 = Utf8               (Ljava/lang/invoke/SerializedLambda;)Ljava/lang/Object;
  #102 = Utf8               scala/runtime/LambdaDeserialize
  #103 = Class              #102          // scala/runtime/LambdaDeserialize
  #104 = Utf8               bootstrap
  #105 = Utf8               (Ljava/lang/invoke/MethodHandles$Lookup;Ljava/lang/String;Ljava/lang/invoke/MethodType;[Ljava/lang/invoke/MethodHandle;)Ljava/lang/invoke/CallSite;
  #106 = NameAndType        #104:#105     // bootstrap:(Ljava/lang/invoke/MethodHandles$Lookup;Ljava/lang/String;Ljava/lang/invoke/MethodType;[Ljava/lang/invoke/MethodHandle;)Ljava/lang/invoke/CallSite;
  #107 = Methodref          #103.#106     // scala/runtime/LambdaDeserialize.bootstrap:(Ljava/lang/invoke/MethodHandles$Lookup;Ljava/lang/String;Ljava/lang/invoke/MethodType;[Ljava/lang/invoke/MethodHandle;)Ljava/lang/invoke/CallSite;
  #108 = MethodHandle       6:#107        // REF_invokeStatic scala/runtime/LambdaDeserialize.bootstrap:(Ljava/lang/invoke/MethodHandles$Lookup;Ljava/lang/String;Ljava/lang/invoke/MethodType;[Ljava/lang/invoke/MethodHandle;)Ljava/lang/invoke/CallSite;
  #109 = Utf8               lambdaDeserialize
  #110 = NameAndType        #109:#101     // lambdaDeserialize:(Ljava/lang/invoke/SerializedLambda;)Ljava/lang/Object;
  #111 = InvokeDynamic      #1:#110       // #1:lambdaDeserialize:(Ljava/lang/invoke/SerializedLambda;)Ljava/lang/Object;
  #112 = Utf8               Code
  #113 = Utf8               LineNumberTable
  #114 = Utf8               LocalVariableTable
  #115 = Utf8               Signature
  #116 = Utf8               MethodParameters
  #117 = Utf8               InnerClasses
  #118 = Utf8               SourceFile
  #119 = Utf8               RuntimeVisibleAnnotations
  #120 = Utf8               BootstrapMethods
  #121 = Utf8               ScalaInlineInfo
  #122 = Utf8               ScalaSig
{
  public scala.collection.Iterator<java.lang.String> listWebPageRawElements(java.lang.String);
    descriptor: (Ljava/lang/String;)Lscala/collection/Iterator;
    flags: (0x0001) ACC_PUBLIC
    Code:
      stack=3, locals=2, args_size=2
         0: getstatic     #28                 // Field scala/jdk/CollectionConverters$.MODULE$:Lscala/jdk/CollectionConverters$;
         3: aload_1
         4: invokestatic  #34                 // Method coursier/util/shaded/org/jsoup/Jsoup.parse:(Ljava/lang/String;)Lcoursier/util/shaded/org/jsoup/nodes/Document;
         7: ldc           #36                 // String a
         9: invokevirtual #42                 // Method coursier/util/shaded/org/jsoup/nodes/Document.select:(Ljava/lang/String;)Lcoursier/util/shaded/org/jsoup/select/Elements;
        12: invokevirtual #45                 // Method scala/jdk/CollectionConverters$.ListHasAsScala:(Ljava/util/List;)Lscala/collection/convert/AsScalaExtensions$ListHasAsScala;
        15: invokevirtual #49                 // Method scala/collection/convert/AsScalaExtensions$ListHasAsScala.asScala:()Lscala/collection/mutable/Buffer;
        18: invokeinterface #55,  1           // InterfaceMethod scala/collection/mutable/Buffer.iterator:()Lscala/collection/Iterator;
        23: invokedynamic #76,  0             // InvokeDynamic #0:apply:()Lscala/Function1;
        28: invokeinterface #82,  2           // InterfaceMethod scala/collection/Iterator.map:(Lscala/Function1;)Lscala/collection/Iterator;
        33: areturn
      LineNumberTable:
        line 11: 0
        line 10: 3
        line 11: 7
        line 14: 23
      LocalVariableTable:
        Start  Length  Slot  Name   Signature
            0      34     0  this   Lcoursier/util/WebPageCompatibility;
            0      34     1  page   Ljava/lang/String;
    Signature: #21                          // (Ljava/lang/String;)Lscala/collection/Iterator<Ljava/lang/String;>;
    MethodParameters:
      Name                           Flags
      page                           final

  public static final java.lang.String $anonfun$listWebPageRawElements$1(coursier.util.shaded.org.jsoup.nodes.Element);
    descriptor: (Lcoursier/util/shaded/org/jsoup/nodes/Element;)Ljava/lang/String;
    flags: (0x1019) ACC_PUBLIC, ACC_STATIC, ACC_FINAL, ACC_SYNTHETIC
    Code:
      stack=2, locals=1, args_size=1
         0: aload_0
         1: ldc           #88                 // String href
         3: invokevirtual #94                 // Method coursier/util/shaded/org/jsoup/nodes/Element.attr:(Ljava/lang/String;)Ljava/lang/String;
         6: areturn
      LineNumberTable:
        line 14: 0
      LocalVariableTable:
        Start  Length  Slot  Name   Signature
            0       7     0   x$1   Lcoursier/util/shaded/org/jsoup/nodes/Element;
    MethodParameters:
      Name                           Flags
      x$1                            final

  public coursier.util.WebPageCompatibility();
    descriptor: ()V
    flags: (0x0001) ACC_PUBLIC
    Code:
      stack=1, locals=1, args_size=1
         0: aload_0
         1: invokespecial #99                 // Method java/lang/Object."<init>":()V
         4: return
      LineNumberTable:
        line 16: 0
        line 7: 4
      LocalVariableTable:
        Start  Length  Slot  Name   Signature
            0       5     0  this   Lcoursier/util/WebPageCompatibility;

  private static java.lang.Object $deserializeLambda$(java.lang.invoke.SerializedLambda);
    descriptor: (Ljava/lang/invoke/SerializedLambda;)Ljava/lang/Object;
    flags: (0x100a) ACC_PRIVATE, ACC_STATIC, ACC_SYNTHETIC
    Code:
      stack=1, locals=1, args_size=1
         0: aload_0
         1: invokedynamic #111,  0            // InvokeDynamic #1:lambdaDeserialize:(Ljava/lang/invoke/SerializedLambda;)Ljava/lang/Object;
         6: areturn
}
InnerClasses:
  public static final #13= #10 of #12;    // Lookup=class java/lang/invoke/MethodHandles$Lookup of class java/lang/invoke/MethodHandles
  public #18= #15 of #17;                 // ListHasAsScala=class scala/collection/convert/AsScalaExtensions$ListHasAsScala of class scala/collection/convert/AsScalaExtensions
SourceFile: "WebPageCompatibility.scala"
RuntimeVisibleAnnotations:
  0: #6(#7=s#8)
    scala.reflect.ScalaSignature(
      bytes="\u0006\u000512aa\u0001\u0003\u0002\u0002\u0019A\u0001\"B\b\u0001\t\u0003\t\u0002\"\u0002\u000b\u0001\t\u0003)\"\u0001F,fEB\u000bw-Z\"p[B\fG/\u001b2jY&$\u0018P\u0003\u0002\u0006\r\u0005!Q\u000f^5m\u0015\u00059\u0011\u0001C2pkJ\u001c\u0018.\u001a:\u0014\u0005\u0001I\u0001C\u0001\u0006\u000e\u001b\u0005Y!\"\u0001\u0007\u0002\u000bM\u001c\u0017\r\\1\n\u00059Y!AB!osJ+g-\u0001\u0004=S:LGOP\u0002\u0001)\u0005\u0011\u0002CA\n\u0001\u001b\u0005!\u0011A\u00067jgR<VM\u0019)bO\u0016\u0014\u0016m^#mK6,g\u000e^:\u0015\u0005YQ\u0003cA\f E9\u0011\u0001$\b\b\u00033qi\u0011A\u0007\u0006\u00037A\ta\u0001\u0010:p_Rt\u0014\"\u0001\u0007\n\u0005yY\u0011a\u00029bG.\fw-Z\u0005\u0003A\u0005\u0012\u0001\"\u0013;fe\u0006$xN\u001d\u0006\u0003=-\u0001\"aI\u0014\u000f\u0005\u0011*\u0003CA\r\f\u0013\t13\"\u0001\u0004Qe\u0016$WMZ\u0005\u0003Q%\u0012aa\u0015;sS:<\'B\u0001\u0014\f\u0011\u0015Y#\u00011\u0001#\u0003\u0011\u0001\u0018mZ3"
    )
BootstrapMethods:
  0: #72 REF_invokeStatic java/lang/invoke/LambdaMetafactory.altMetafactory:(Ljava/lang/invoke/MethodHandles$Lookup;Ljava/lang/String;Ljava/lang/invoke/MethodType;[Ljava/lang/Object;)Ljava/lang/invoke/CallSite;
    Method arguments:
      #57 (Ljava/lang/Object;)Ljava/lang/Object;
      #62 REF_invokeStatic coursier/util/WebPageCompatibility.$anonfun$listWebPageRawElements$1:(Lcoursier/util/shaded/org/jsoup/nodes/Element;)Ljava/lang/String;
      #63 (Lcoursier/util/shaded/org/jsoup/nodes/Element;)Ljava/lang/String;
      #64 5
      #65 1
      #63 (Lcoursier/util/shaded/org/jsoup/nodes/Element;)Ljava/lang/String;
  1: #108 REF_invokeStatic scala/runtime/LambdaDeserialize.bootstrap:(Ljava/lang/invoke/MethodHandles$Lookup;Ljava/lang/String;Ljava/lang/invoke/MethodType;[Ljava/lang/invoke/MethodHandle;)Ljava/lang/invoke/CallSite;
    Method arguments:
      #62 REF_invokeStatic coursier/util/WebPageCompatibility.$anonfun$listWebPageRawElements$1:(Lcoursier/util/shaded/org/jsoup/nodes/Element;)Ljava/lang/String;
  ScalaInlineInfo: length = 0x13 (unknown attribute)
   01 00 00 03 00 3A 00 3B 01 00 60 00 61 00 00 13
   00 14 00
  ScalaSig: length = 0x3 (unknown attribute)
   05 02 00
