Classfile /Users/mw/Projects/slang-braindump/.jar/jar11/assemble/slang-braindump/assemble/content/coursier/util/Xml$$anonfun$$nestedInanonfun$text$2$1.class
  Last modified May 29, 2022; size 2264 bytes
  SHA-256 checksum e491ced33e4430b6ecd94a277380fd831988a45629547c208b3afb40334b8ef5
  Compiled from "Xml.scala"
public final class coursier.util.Xml$$anonfun$$nestedInanonfun$text$2$1 extends scala.runtime.AbstractPartialFunction<coursier.util.Xml$Node, java.lang.String> implements java.io.Serializable
  minor version: 0
  major version: 52
  flags: (0x0031) ACC_PUBLIC, ACC_FINAL, ACC_SUPER
  this_class: #2                          // coursier/util/Xml$$anonfun$$nestedInanonfun$text$2$1
  super_class: #5                         // scala/runtime/AbstractPartialFunction
  interfaces: 1, fields: 1, methods: 5, attributes: 6
Constant pool:
   #1 = Utf8               coursier/util/Xml$$anonfun$$nestedInanonfun$text$2$1
   #2 = Class              #1             // coursier/util/Xml$$anonfun$$nestedInanonfun$text$2$1
   #3 = Utf8               Lscala/runtime/AbstractPartialFunction<Lcoursier/util/Xml$Node;Ljava/lang/String;>;Ljava/io/Serializable;
   #4 = Utf8               scala/runtime/AbstractPartialFunction
   #5 = Class              #4             // scala/runtime/AbstractPartialFunction
   #6 = Utf8               java/io/Serializable
   #7 = Class              #6             // java/io/Serializable
   #8 = Utf8               Xml.scala
   #9 = Utf8               coursier/util/Xml$
  #10 = Class              #9             // coursier/util/Xml$
  #11 = Utf8               text
  #12 = Utf8               (Lcoursier/util/Xml$Node;Ljava/lang/String;Ljava/lang/String;)Lscala/util/Either;
  #13 = NameAndType        #11:#12        // text:(Lcoursier/util/Xml$Node;Ljava/lang/String;Ljava/lang/String;)Lscala/util/Either;
  #14 = Utf8               coursier/util/Xml$Node
  #15 = Class              #14            // coursier/util/Xml$Node
  #16 = Utf8               coursier/util/Xml
  #17 = Class              #16            // coursier/util/Xml
  #18 = Utf8               Node
  #19 = Utf8               coursier/util/Xml$Text$
  #20 = Class              #19            // coursier/util/Xml$Text$
  #21 = Utf8
  #22 = Utf8               serialVersionUID
  #23 = Utf8               J
  #24 = Long               0l
  #26 = Utf8               applyOrElse
  #27 = Utf8               (Lcoursier/util/Xml$Node;Lscala/Function1;)Ljava/lang/Object;
  #28 = Utf8               <A1::Lcoursier/util/Xml$Node;B1:Ljava/lang/Object;>(TA1;Lscala/Function1<TA1;TB1;>;)TB1;
  #29 = Utf8               x1
  #30 = Utf8               default
  #31 = Utf8               MODULE$
  #32 = Utf8               Lcoursier/util/Xml$Text$;
  #33 = NameAndType        #31:#32        // MODULE$:Lcoursier/util/Xml$Text$;
  #34 = Fieldref           #20.#33        // coursier/util/Xml$Text$.MODULE$:Lcoursier/util/Xml$Text$;
  #35 = Utf8               unapply
  #36 = Utf8               (Lcoursier/util/Xml$Node;)Lscala/Option;
  #37 = NameAndType        #35:#36        // unapply:(Lcoursier/util/Xml$Node;)Lscala/Option;
  #38 = Methodref          #20.#37        // coursier/util/Xml$Text$.unapply:(Lcoursier/util/Xml$Node;)Lscala/Option;
  #39 = Utf8               scala/Option
  #40 = Class              #39            // scala/Option
  #41 = Utf8               isEmpty
  #42 = Utf8               ()Z
  #43 = NameAndType        #41:#42        // isEmpty:()Z
  #44 = Methodref          #40.#43        // scala/Option.isEmpty:()Z
  #45 = Utf8               get
  #46 = Utf8               ()Ljava/lang/Object;
  #47 = NameAndType        #45:#46        // get:()Ljava/lang/Object;
  #48 = Methodref          #40.#47        // scala/Option.get:()Ljava/lang/Object;
  #49 = Utf8               java/lang/String
  #50 = Class              #49            // java/lang/String
  #51 = Utf8               scala/Function1
  #52 = Class              #51            // scala/Function1
  #53 = Utf8               apply
  #54 = Utf8               (Ljava/lang/Object;)Ljava/lang/Object;
  #55 = NameAndType        #53:#54        // apply:(Ljava/lang/Object;)Ljava/lang/Object;
  #56 = InterfaceMethodref #52.#55        // scala/Function1.apply:(Ljava/lang/Object;)Ljava/lang/Object;
  #57 = Utf8               java/lang/Object
  #58 = Class              #57            // java/lang/Object
  #59 = Utf8               t
  #60 = Utf8               Ljava/lang/String;
  #61 = Utf8               this
  #62 = Utf8               Lcoursier/util/Xml$$anonfun$$nestedInanonfun$text$2$1;
  #63 = Utf8               Lcoursier/util/Xml$Node;
  #64 = Utf8               Lscala/Function1;
  #65 = Utf8               isDefinedAt
  #66 = Utf8               (Lcoursier/util/Xml$Node;)Z
  #67 = Utf8               (Ljava/lang/Object;)Z
  #68 = Utf8               x
  #69 = NameAndType        #65:#66        // isDefinedAt:(Lcoursier/util/Xml$Node;)Z
  #70 = Methodref          #2.#69         // coursier/util/Xml$$anonfun$$nestedInanonfun$text$2$1.isDefinedAt:(Lcoursier/util/Xml$Node;)Z
  #71 = Utf8               Ljava/lang/Object;
  #72 = Utf8               (Ljava/lang/Object;Lscala/Function1;)Ljava/lang/Object;
  #73 = NameAndType        #26:#27        // applyOrElse:(Lcoursier/util/Xml$Node;Lscala/Function1;)Ljava/lang/Object;
  #74 = Methodref          #2.#73         // coursier/util/Xml$$anonfun$$nestedInanonfun$text$2$1.applyOrElse:(Lcoursier/util/Xml$Node;Lscala/Function1;)Ljava/lang/Object;
  #75 = Utf8               <init>
  #76 = Utf8               ()V
  #77 = NameAndType        #75:#76        // "<init>":()V
  #78 = Methodref          #5.#77         // scala/runtime/AbstractPartialFunction."<init>":()V
  #79 = Utf8               ConstantValue
  #80 = Utf8               Code
  #81 = Utf8               StackMapTable
  #82 = Utf8               LineNumberTable
  #83 = Utf8               LocalVariableTable
  #84 = Utf8               Signature
  #85 = Utf8               MethodParameters
  #86 = Utf8               InnerClasses
  #87 = Utf8               EnclosingMethod
  #88 = Utf8               SourceFile
  #89 = Utf8               ScalaInlineInfo
  #90 = Utf8               Scala
{
  private static final long serialVersionUID;
    descriptor: J
    flags: (0x001a) ACC_PRIVATE, ACC_STATIC, ACC_FINAL
    ConstantValue: long 0l

  public final <A1 extends coursier.util.Xml$Node, B1 extends java.lang.Object> B1 applyOrElse(A1, scala.Function1<A1, B1>);
    descriptor: (Lcoursier/util/Xml$Node;Lscala/Function1;)Ljava/lang/Object;
    flags: (0x0011) ACC_PUBLIC, ACC_FINAL
    Code:
      stack=2, locals=7, args_size=3
         0: aload_1
         1: astore        4
         3: aload         4
         5: ifnull        45
         8: getstatic     #34                 // Field coursier/util/Xml$Text$.MODULE$:Lcoursier/util/Xml$Text$;
        11: aload         4
        13: invokevirtual #38                 // Method coursier/util/Xml$Text$.unapply:(Lcoursier/util/Xml$Node;)Lscala/Option;
        16: astore        5
        18: aload         5
        20: invokevirtual #44                 // Method scala/Option.isEmpty:()Z
        23: ifne          42
        26: aload         5
        28: invokevirtual #48                 // Method scala/Option.get:()Ljava/lang/Object;
        31: checkcast     #50                 // class java/lang/String
        34: astore        6
        36: aload         6
        38: astore_3
        39: goto          59
        42: goto          48
        45: goto          48
        48: aload_2
        49: aload_1
        50: invokeinterface #56,  2           // InterfaceMethod scala/Function1.apply:(Ljava/lang/Object;)Ljava/lang/Object;
        55: astore_3
        56: goto          59
        59: aload_3
        60: areturn
      StackMapTable: number_of_entries = 4
        frame_type = 254 /* append */
          offset_delta = 42
          locals = [ top, class coursier/util/Xml$Node, class scala/Option ]
        frame_type = 250 /* chop */
          offset_delta = 2
        frame_type = 2 /* same */
        frame_type = 255 /* full_frame */
          offset_delta = 10
          locals = [ class coursier/util/Xml$$anonfun$$nestedInanonfun$text$2$1, class coursier/util/Xml$Node, class scala/Function1, class java/lang/Object, class coursier/util/Xml$Node ]
          stack = []
      LineNumberTable:
        line 52: 0
      LocalVariableTable:
        Start  Length  Slot  Name   Signature
           36       6     6     t   Ljava/lang/String;
            0      61     0  this   Lcoursier/util/Xml$$anonfun$$nestedInanonfun$text$2$1;
            0      61     1    x1   Lcoursier/util/Xml$Node;
            0      61     2 default   Lscala/Function1;
    Signature: #28                          // <A1::Lcoursier/util/Xml$Node;B1:Ljava/lang/Object;>(TA1;Lscala/Function1<TA1;TB1;>;)TB1;
    MethodParameters:
      Name                           Flags
      x1                             final
      default                        final

  public final boolean isDefinedAt(coursier.util.Xml$Node);
    descriptor: (Lcoursier/util/Xml$Node;)Z
    flags: (0x0011) ACC_PUBLIC, ACC_FINAL
    Code:
      stack=2, locals=5, args_size=2
         0: aload_1
         1: astore_3
         2: aload_3
         3: ifnull        31
         6: getstatic     #34                 // Field coursier/util/Xml$Text$.MODULE$:Lcoursier/util/Xml$Text$;
         9: aload_3
        10: invokevirtual #38                 // Method coursier/util/Xml$Text$.unapply:(Lcoursier/util/Xml$Node;)Lscala/Option;
        13: astore        4
        15: aload         4
        17: invokevirtual #44                 // Method scala/Option.isEmpty:()Z
        20: ifne          28
        23: iconst_1
        24: istore_2
        25: goto          39
        28: goto          34
        31: goto          34
        34: iconst_0
        35: istore_2
        36: goto          39
        39: iload_2
        40: ireturn
      StackMapTable: number_of_entries = 4
        frame_type = 254 /* append */
          offset_delta = 28
          locals = [ top, class coursier/util/Xml$Node, class scala/Option ]
        frame_type = 250 /* chop */
          offset_delta = 2
        frame_type = 2 /* same */
        frame_type = 255 /* full_frame */
          offset_delta = 4
          locals = [ class coursier/util/Xml$$anonfun$$nestedInanonfun$text$2$1, class coursier/util/Xml$Node, int, class coursier/util/Xml$Node ]
          stack = []
      LineNumberTable:
        line 52: 0
      LocalVariableTable:
        Start  Length  Slot  Name   Signature
            0      41     0  this   Lcoursier/util/Xml$$anonfun$$nestedInanonfun$text$2$1;
            0      41     1    x1   Lcoursier/util/Xml$Node;
    MethodParameters:
      Name                           Flags
      x1                             final

  public final boolean isDefinedAt(java.lang.Object);
    descriptor: (Ljava/lang/Object;)Z
    flags: (0x1051) ACC_PUBLIC, ACC_FINAL, ACC_BRIDGE, ACC_SYNTHETIC
    Code:
      stack=2, locals=2, args_size=2
         0: aload_0
         1: aload_1
         2: checkcast     #15                 // class coursier/util/Xml$Node
         5: invokevirtual #70                 // Method isDefinedAt:(Lcoursier/util/Xml$Node;)Z
         8: ireturn
      LineNumberTable:
        line 52: 0
      LocalVariableTable:
        Start  Length  Slot  Name   Signature
            0       9     0  this   Lcoursier/util/Xml$$anonfun$$nestedInanonfun$text$2$1;
            0       9     1     x   Ljava/lang/Object;
    MethodParameters:
      Name                           Flags
      x                              final

  public final java.lang.Object applyOrElse(java.lang.Object, scala.Function1);
    descriptor: (Ljava/lang/Object;Lscala/Function1;)Ljava/lang/Object;
    flags: (0x1051) ACC_PUBLIC, ACC_FINAL, ACC_BRIDGE, ACC_SYNTHETIC
    Code:
      stack=3, locals=3, args_size=3
         0: aload_0
         1: aload_1
         2: checkcast     #15                 // class coursier/util/Xml$Node
         5: aload_2
         6: invokevirtual #74                 // Method applyOrElse:(Lcoursier/util/Xml$Node;Lscala/Function1;)Ljava/lang/Object;
         9: areturn
      LineNumberTable:
        line 52: 0
      LocalVariableTable:
        Start  Length  Slot  Name   Signature
            0      10     0  this   Lcoursier/util/Xml$$anonfun$$nestedInanonfun$text$2$1;
            0      10     1     x   Ljava/lang/Object;
            0      10     2 default   Lscala/Function1;
    MethodParameters:
      Name                           Flags
      x                              final
      default                        final

  public coursier.util.Xml$$anonfun$$nestedInanonfun$text$2$1();
    descriptor: ()V
    flags: (0x0001) ACC_PUBLIC
    Code:
      stack=1, locals=1, args_size=1
         0: aload_0
         1: invokespecial #78                 // Method scala/runtime/AbstractPartialFunction."<init>":()V
         4: return
      LineNumberTable:
        line 52: 0
      LocalVariableTable:
        Start  Length  Slot  Name   Signature
            0       5     0  this   Lcoursier/util/Xml$$anonfun$$nestedInanonfun$text$2$1;
}
InnerClasses:
  public final #2;                        // class coursier/util/Xml$$anonfun$$nestedInanonfun$text$2$1
  public static #18= #15 of #17;          // Node=class coursier/util/Xml$Node of class coursier/util/Xml
  public static #21= #20 of #17;          // =class coursier/util/Xml$Text$ of class coursier/util/Xml
EnclosingMethod: #10.#13                // coursier.util.Xml$.text
Signature: #3                           // Lscala/runtime/AbstractPartialFunction<Lcoursier/util/Xml$Node;Ljava/lang/String;>;Ljava/io/Serializable;
SourceFile: "Xml.scala"
  ScalaInlineInfo: length = 0x1D (unknown attribute)
   01 01 00 05 00 4B 00 4C 01 00 1A 00 1B 01 00 1A
   00 48 01 00 41 00 42 01 00 41 00 43 01
  Scala: length = 0x0 (unknown attribute)

