Classfile /Users/mw/Projects/slang-braindump/.jar/jar8/assemble/slang-braindump/assemble/content/scala/sys/process/Parser$ParseException.class
  Last modified May 29, 2022; size 531 bytes
  SHA-256 checksum 13d275e46f75087fc6e4fe6dec2100fc96ac00d6664edce2a9f2e7d55435c4bc
  Compiled from "Parser.scala"
public class scala.sys.process.Parser$ParseException extends java.lang.RuntimeException
  minor version: 0
  major version: 52
  flags: (0x0021) ACC_PUBLIC, ACC_SUPER
  this_class: #2                          // scala/sys/process/Parser$ParseException
  super_class: #4                         // java/lang/RuntimeException
  interfaces: 0, fields: 0, methods: 1, attributes: 4
Constant pool:
   #1 = Utf8               scala/sys/process/Parser$ParseException
   #2 = Class              #1             // scala/sys/process/Parser$ParseException
   #3 = Utf8               java/lang/RuntimeException
   #4 = Class              #3             // java/lang/RuntimeException
   #5 = Utf8               Parser.scala
   #6 = Utf8               scala/sys/process/Parser
   #7 = Class              #6             // scala/sys/process/Parser
   #8 = Utf8               ParseException
   #9 = Utf8               <init>
  #10 = Utf8               (Ljava/lang/String;)V
  #11 = Utf8               msg
  #12 = NameAndType        #9:#10         // "<init>":(Ljava/lang/String;)V
  #13 = Methodref          #4.#12         // java/lang/RuntimeException."<init>":(Ljava/lang/String;)V
  #14 = Utf8               this
  #15 = Utf8               Lscala/sys/process/Parser$ParseException;
  #16 = Utf8               Ljava/lang/String;
  #17 = Utf8               Code
  #18 = Utf8               LineNumberTable
  #19 = Utf8               LocalVariableTable
  #20 = Utf8               MethodParameters
  #21 = Utf8               InnerClasses
  #22 = Utf8               SourceFile
  #23 = Utf8               ScalaInlineInfo
  #24 = Utf8               Scala
{
  public scala.sys.process.Parser$ParseException(java.lang.String);
    descriptor: (Ljava/lang/String;)V
    flags: (0x0001) ACC_PUBLIC
    Code:
      stack=2, locals=2, args_size=2
         0: aload_0
         1: aload_1
         2: invokespecial #13                 // Method java/lang/RuntimeException."<init>":(Ljava/lang/String;)V
         5: return
      LineNumberTable:
        line 103: 0
      LocalVariableTable:
        Start  Length  Slot  Name   Signature
            0       6     0  this   Lscala/sys/process/Parser$ParseException;
            0       6     1   msg   Ljava/lang/String;
    MethodParameters:
      Name                           Flags
      msg                            final
}
InnerClasses:
  public static #8= #2 of #7;             // ParseException=class scala/sys/process/Parser$ParseException of class scala/sys/process/Parser
SourceFile: "Parser.scala"
  ScalaInlineInfo: length = 0x9 (unknown attribute)
   01 00 00 01 00 09 00 0A 00
  Scala: length = 0x0 (unknown attribute)

