Classfile /Users/mw/Projects/slang-braindump/.jar/jar8/assemble/slang-braindump/assemble/content/scala/sys/process/ProcessBuilder$Sink.class
  Last modified May 29, 2022; size 3044 bytes
  SHA-256 checksum 06c0d604b2ba8281c4249ae86ba18ce1993a045e1efe103ca478aaebb9116266
  Compiled from "ProcessBuilder.scala"
public interface scala.sys.process.ProcessBuilder$Sink
  minor version: 0
  major version: 52
  flags: (0x0601) ACC_PUBLIC, ACC_INTERFACE, ACC_ABSTRACT
  this_class: #2                          // scala/sys/process/ProcessBuilder$Sink
  super_class: #4                         // java/lang/Object
  interfaces: 0, fields: 0, methods: 10, attributes: 4
Constant pool:
   #1 = Utf8               scala/sys/process/ProcessBuilder$Sink
   #2 = Class              #1             // scala/sys/process/ProcessBuilder$Sink
   #3 = Utf8               java/lang/Object
   #4 = Class              #3             // java/lang/Object
   #5 = Utf8               ProcessBuilder.scala
   #6 = Utf8               scala/sys/process/ProcessBuilder
   #7 = Class              #6             // scala/sys/process/ProcessBuilder
   #8 = Utf8               Sink
   #9 = Utf8               scala/sys/process/ProcessBuilderImpl$FileInput
  #10 = Class              #9             // scala/sys/process/ProcessBuilderImpl$FileInput
  #11 = Utf8               scala/sys/process/ProcessBuilderImpl
  #12 = Class              #11            // scala/sys/process/ProcessBuilderImpl
  #13 = Utf8               FileInput
  #14 = Utf8               scala/sys/process/ProcessBuilderImpl$IStreamBuilder
  #15 = Class              #14            // scala/sys/process/ProcessBuilderImpl$IStreamBuilder
  #16 = Utf8               IStreamBuilder
  #17 = Utf8               scala/sys/process/ProcessBuilderImpl$PipedBuilder
  #18 = Class              #17            // scala/sys/process/ProcessBuilderImpl$PipedBuilder
  #19 = Utf8               PipedBuilder
  #20 = Utf8               scala/sys/process/ProcessBuilderImpl$URLInput
  #21 = Class              #20            // scala/sys/process/ProcessBuilderImpl$URLInput
  #22 = Utf8               URLInput
  #23 = Utf8               toSink
  #24 = Utf8               ()Lscala/sys/process/ProcessBuilder;
  #25 = Utf8               $hash$less$
  #26 = Utf8               (Lscala/sys/process/ProcessBuilder$Sink;Ljava/io/File;)Lscala/sys/process/ProcessBuilder;
  #27 = Utf8               $this
  #28 = Utf8               f
  #29 = Utf8               $hash$less
  #30 = Utf8               (Ljava/io/File;)Lscala/sys/process/ProcessBuilder;
  #31 = NameAndType        #29:#30        // $hash$less:(Ljava/io/File;)Lscala/sys/process/ProcessBuilder;
  #32 = InterfaceMethodref #2.#31         // scala/sys/process/ProcessBuilder$Sink.$hash$less:(Ljava/io/File;)Lscala/sys/process/ProcessBuilder;
  #33 = Utf8               Lscala/sys/process/ProcessBuilder$Sink;
  #34 = Utf8               Ljava/io/File;
  #35 = Utf8               scala/sys/process/ProcessBuilder$
  #36 = Class              #35            // scala/sys/process/ProcessBuilder$
  #37 = Utf8               MODULE$
  #38 = Utf8               Lscala/sys/process/ProcessBuilder$;
  #39 = NameAndType        #37:#38        // MODULE$:Lscala/sys/process/ProcessBuilder$;
  #40 = Fieldref           #36.#39        // scala/sys/process/ProcessBuilder$.MODULE$:Lscala/sys/process/ProcessBuilder$;
  #41 = Utf8               <init>
  #42 = Utf8               (Lscala/sys/process/ProcessBuilder$;Ljava/io/File;)V
  #43 = NameAndType        #41:#42        // "<init>":(Lscala/sys/process/ProcessBuilder$;Ljava/io/File;)V
  #44 = Methodref          #10.#43        // scala/sys/process/ProcessBuilderImpl$FileInput."<init>":(Lscala/sys/process/ProcessBuilder$;Ljava/io/File;)V
  #45 = Utf8               (Lscala/sys/process/ProcessBuilder;)Lscala/sys/process/ProcessBuilder;
  #46 = NameAndType        #29:#45        // $hash$less:(Lscala/sys/process/ProcessBuilder;)Lscala/sys/process/ProcessBuilder;
  #47 = InterfaceMethodref #2.#46         // scala/sys/process/ProcessBuilder$Sink.$hash$less:(Lscala/sys/process/ProcessBuilder;)Lscala/sys/process/ProcessBuilder;
  #48 = Utf8               this
  #49 = Utf8               (Lscala/sys/process/ProcessBuilder$Sink;Ljava/net/URL;)Lscala/sys/process/ProcessBuilder;
  #50 = Utf8               (Ljava/net/URL;)Lscala/sys/process/ProcessBuilder;
  #51 = NameAndType        #29:#50        // $hash$less:(Ljava/net/URL;)Lscala/sys/process/ProcessBuilder;
  #52 = InterfaceMethodref #2.#51         // scala/sys/process/ProcessBuilder$Sink.$hash$less:(Ljava/net/URL;)Lscala/sys/process/ProcessBuilder;
  #53 = Utf8               Ljava/net/URL;
  #54 = Utf8               (Lscala/sys/process/ProcessBuilder$;Ljava/net/URL;)V
  #55 = NameAndType        #41:#54        // "<init>":(Lscala/sys/process/ProcessBuilder$;Ljava/net/URL;)V
  #56 = Methodref          #21.#55        // scala/sys/process/ProcessBuilderImpl$URLInput."<init>":(Lscala/sys/process/ProcessBuilder$;Ljava/net/URL;)V
  #57 = Utf8               (Lscala/sys/process/ProcessBuilder$Sink;Lscala/Function0;)Lscala/sys/process/ProcessBuilder;
  #58 = Utf8               in
  #59 = Utf8               (Lscala/Function0;)Lscala/sys/process/ProcessBuilder;
  #60 = NameAndType        #29:#59        // $hash$less:(Lscala/Function0;)Lscala/sys/process/ProcessBuilder;
  #61 = InterfaceMethodref #2.#60         // scala/sys/process/ProcessBuilder$Sink.$hash$less:(Lscala/Function0;)Lscala/sys/process/ProcessBuilder;
  #62 = Utf8               Lscala/Function0;
  #63 = Utf8               (Lscala/Function0<Ljava/io/InputStream;>;)Lscala/sys/process/ProcessBuilder;
  #64 = Utf8               <input stream>
  #65 = String             #64            // <input stream>
  #66 = Utf8               (Lscala/sys/process/ProcessBuilder$;Lscala/Function0;Ljava/lang/String;)V
  #67 = NameAndType        #41:#66        // "<init>":(Lscala/sys/process/ProcessBuilder$;Lscala/Function0;Ljava/lang/String;)V
  #68 = Methodref          #15.#67        // scala/sys/process/ProcessBuilderImpl$IStreamBuilder."<init>":(Lscala/sys/process/ProcessBuilder$;Lscala/Function0;Ljava/lang/String;)V
  #69 = Utf8               (Lscala/sys/process/ProcessBuilder$Sink;Lscala/sys/process/ProcessBuilder;)Lscala/sys/process/ProcessBuilder;
  #70 = Utf8               b
  #71 = Utf8               Lscala/sys/process/ProcessBuilder;
  #72 = NameAndType        #23:#24        // toSink:()Lscala/sys/process/ProcessBuilder;
  #73 = InterfaceMethodref #2.#72         // scala/sys/process/ProcessBuilder$Sink.toSink:()Lscala/sys/process/ProcessBuilder;
  #74 = Utf8               (Lscala/sys/process/ProcessBuilder$;Lscala/sys/process/ProcessBuilder;Lscala/sys/process/ProcessBuilder;Z)V
  #75 = NameAndType        #41:#74        // "<init>":(Lscala/sys/process/ProcessBuilder$;Lscala/sys/process/ProcessBuilder;Lscala/sys/process/ProcessBuilder;Z)V
  #76 = Methodref          #18.#75        // scala/sys/process/ProcessBuilderImpl$PipedBuilder."<init>":(Lscala/sys/process/ProcessBuilder$;Lscala/sys/process/ProcessBuilder;Lscala/sys/process/ProcessBuilder;Z)V
  #77 = Utf8               $init$
  #78 = Utf8               (Lscala/sys/process/ProcessBuilder$Sink;)V
  #79 = Utf8               Code
  #80 = Utf8               LineNumberTable
  #81 = Utf8               LocalVariableTable
  #82 = Utf8               MethodParameters
  #83 = Utf8               Signature
  #84 = Utf8               InnerClasses
  #85 = Utf8               SourceFile
  #86 = Utf8               ScalaInlineInfo
  #87 = Utf8               Scala
{
  public abstract scala.sys.process.ProcessBuilder toSink();
    descriptor: ()Lscala/sys/process/ProcessBuilder;
    flags: (0x0401) ACC_PUBLIC, ACC_ABSTRACT

  public static scala.sys.process.ProcessBuilder $hash$less$(scala.sys.process.ProcessBuilder$Sink, java.io.File);
    descriptor: (Lscala/sys/process/ProcessBuilder$Sink;Ljava/io/File;)Lscala/sys/process/ProcessBuilder;
    flags: (0x1009) ACC_PUBLIC, ACC_STATIC, ACC_SYNTHETIC
    Code:
      stack=2, locals=2, args_size=2
         0: aload_0
         1: aload_1
         2: invokespecial #32                 // InterfaceMethod $hash$less:(Ljava/io/File;)Lscala/sys/process/ProcessBuilder;
         5: areturn
      LineNumberTable:
        line 465: 0
      LocalVariableTable:
        Start  Length  Slot  Name   Signature
            0       6     0 $this   Lscala/sys/process/ProcessBuilder$Sink;
            0       6     1     f   Ljava/io/File;
    MethodParameters:
      Name                           Flags
      $this                          final synthetic
      f                              final

  public default scala.sys.process.ProcessBuilder $hash$less(java.io.File);
    descriptor: (Ljava/io/File;)Lscala/sys/process/ProcessBuilder;
    flags: (0x0001) ACC_PUBLIC
    Code:
      stack=5, locals=2, args_size=2
         0: aload_0
         1: new           #10                 // class scala/sys/process/ProcessBuilderImpl$FileInput
         4: dup
         5: getstatic     #40                 // Field scala/sys/process/ProcessBuilder$.MODULE$:Lscala/sys/process/ProcessBuilder$;
         8: aload_1
         9: invokespecial #44                 // Method scala/sys/process/ProcessBuilderImpl$FileInput."<init>":(Lscala/sys/process/ProcessBuilder$;Ljava/io/File;)V
        12: invokeinterface #47,  2           // InterfaceMethod $hash$less:(Lscala/sys/process/ProcessBuilder;)Lscala/sys/process/ProcessBuilder;
        17: areturn
      LineNumberTable:
        line 465: 0
      LocalVariableTable:
        Start  Length  Slot  Name   Signature
            0      18     0  this   Lscala/sys/process/ProcessBuilder$Sink;
            0      18     1     f   Ljava/io/File;
    MethodParameters:
      Name                           Flags
      f                              final

  public static scala.sys.process.ProcessBuilder $hash$less$(scala.sys.process.ProcessBuilder$Sink, java.net.URL);
    descriptor: (Lscala/sys/process/ProcessBuilder$Sink;Ljava/net/URL;)Lscala/sys/process/ProcessBuilder;
    flags: (0x1009) ACC_PUBLIC, ACC_STATIC, ACC_SYNTHETIC
    Code:
      stack=2, locals=2, args_size=2
         0: aload_0
         1: aload_1
         2: invokespecial #52                 // InterfaceMethod $hash$less:(Ljava/net/URL;)Lscala/sys/process/ProcessBuilder;
         5: areturn
      LineNumberTable:
        line 468: 0
      LocalVariableTable:
        Start  Length  Slot  Name   Signature
            0       6     0 $this   Lscala/sys/process/ProcessBuilder$Sink;
            0       6     1     f   Ljava/net/URL;
    MethodParameters:
      Name                           Flags
      $this                          final synthetic
      f                              final

  public default scala.sys.process.ProcessBuilder $hash$less(java.net.URL);
    descriptor: (Ljava/net/URL;)Lscala/sys/process/ProcessBuilder;
    flags: (0x0001) ACC_PUBLIC
    Code:
      stack=5, locals=2, args_size=2
         0: aload_0
         1: new           #21                 // class scala/sys/process/ProcessBuilderImpl$URLInput
         4: dup
         5: getstatic     #40                 // Field scala/sys/process/ProcessBuilder$.MODULE$:Lscala/sys/process/ProcessBuilder$;
         8: aload_1
         9: invokespecial #56                 // Method scala/sys/process/ProcessBuilderImpl$URLInput."<init>":(Lscala/sys/process/ProcessBuilder$;Ljava/net/URL;)V
        12: invokeinterface #47,  2           // InterfaceMethod $hash$less:(Lscala/sys/process/ProcessBuilder;)Lscala/sys/process/ProcessBuilder;
        17: areturn
      LineNumberTable:
        line 468: 0
      LocalVariableTable:
        Start  Length  Slot  Name   Signature
            0      18     0  this   Lscala/sys/process/ProcessBuilder$Sink;
            0      18     1     f   Ljava/net/URL;
    MethodParameters:
      Name                           Flags
      f                              final

  public static scala.sys.process.ProcessBuilder $hash$less$(scala.sys.process.ProcessBuilder$Sink, scala.Function0);
    descriptor: (Lscala/sys/process/ProcessBuilder$Sink;Lscala/Function0;)Lscala/sys/process/ProcessBuilder;
    flags: (0x1009) ACC_PUBLIC, ACC_STATIC, ACC_SYNTHETIC
    Code:
      stack=2, locals=2, args_size=2
         0: aload_0
         1: aload_1
         2: invokespecial #61                 // InterfaceMethod $hash$less:(Lscala/Function0;)Lscala/sys/process/ProcessBuilder;
         5: areturn
      LineNumberTable:
        line 474: 0
      LocalVariableTable:
        Start  Length  Slot  Name   Signature
            0       6     0 $this   Lscala/sys/process/ProcessBuilder$Sink;
            0       6     1    in   Lscala/Function0;
    MethodParameters:
      Name                           Flags
      $this                          final synthetic
      in                             final

  public default scala.sys.process.ProcessBuilder $hash$less(scala.Function0<java.io.InputStream>);
    descriptor: (Lscala/Function0;)Lscala/sys/process/ProcessBuilder;
    flags: (0x0001) ACC_PUBLIC
    Code:
      stack=6, locals=2, args_size=2
         0: aload_0
         1: new           #15                 // class scala/sys/process/ProcessBuilderImpl$IStreamBuilder
         4: dup
         5: getstatic     #40                 // Field scala/sys/process/ProcessBuilder$.MODULE$:Lscala/sys/process/ProcessBuilder$;
         8: aload_1
         9: ldc           #65                 // String <input stream>
        11: invokespecial #68                 // Method scala/sys/process/ProcessBuilderImpl$IStreamBuilder."<init>":(Lscala/sys/process/ProcessBuilder$;Lscala/Function0;Ljava/lang/String;)V
        14: invokeinterface #47,  2           // InterfaceMethod $hash$less:(Lscala/sys/process/ProcessBuilder;)Lscala/sys/process/ProcessBuilder;
        19: areturn
      LineNumberTable:
        line 474: 0
      LocalVariableTable:
        Start  Length  Slot  Name   Signature
            0      20     0  this   Lscala/sys/process/ProcessBuilder$Sink;
            0      20     1    in   Lscala/Function0;
    Signature: #63                          // (Lscala/Function0<Ljava/io/InputStream;>;)Lscala/sys/process/ProcessBuilder;
    MethodParameters:
      Name                           Flags
      in                             final

  public static scala.sys.process.ProcessBuilder $hash$less$(scala.sys.process.ProcessBuilder$Sink, scala.sys.process.ProcessBuilder);
    descriptor: (Lscala/sys/process/ProcessBuilder$Sink;Lscala/sys/process/ProcessBuilder;)Lscala/sys/process/ProcessBuilder;
    flags: (0x1009) ACC_PUBLIC, ACC_STATIC, ACC_SYNTHETIC
    Code:
      stack=2, locals=2, args_size=2
         0: aload_0
         1: aload_1
         2: invokespecial #47                 // InterfaceMethod $hash$less:(Lscala/sys/process/ProcessBuilder;)Lscala/sys/process/ProcessBuilder;
         5: areturn
      LineNumberTable:
        line 477: 0
      LocalVariableTable:
        Start  Length  Slot  Name   Signature
            0       6     0 $this   Lscala/sys/process/ProcessBuilder$Sink;
            0       6     1     b   Lscala/sys/process/ProcessBuilder;
    MethodParameters:
      Name                           Flags
      $this                          final synthetic
      b                              final

  public default scala.sys.process.ProcessBuilder $hash$less(scala.sys.process.ProcessBuilder);
    descriptor: (Lscala/sys/process/ProcessBuilder;)Lscala/sys/process/ProcessBuilder;
    flags: (0x0001) ACC_PUBLIC
    Code:
      stack=6, locals=2, args_size=2
         0: new           #18                 // class scala/sys/process/ProcessBuilderImpl$PipedBuilder
         3: dup
         4: getstatic     #40                 // Field scala/sys/process/ProcessBuilder$.MODULE$:Lscala/sys/process/ProcessBuilder$;
         7: aload_1
         8: aload_0
         9: invokeinterface #73,  1           // InterfaceMethod toSink:()Lscala/sys/process/ProcessBuilder;
        14: iconst_0
        15: invokespecial #76                 // Method scala/sys/process/ProcessBuilderImpl$PipedBuilder."<init>":(Lscala/sys/process/ProcessBuilder$;Lscala/sys/process/ProcessBuilder;Lscala/sys/process/ProcessBuilder;Z)V
        18: areturn
      LineNumberTable:
        line 477: 0
      LocalVariableTable:
        Start  Length  Slot  Name   Signature
            0      19     0  this   Lscala/sys/process/ProcessBuilder$Sink;
            0      19     1     b   Lscala/sys/process/ProcessBuilder;
    MethodParameters:
      Name                           Flags
      b                              final

  public static void $init$(scala.sys.process.ProcessBuilder$Sink);
    descriptor: (Lscala/sys/process/ProcessBuilder$Sink;)V
    flags: (0x0009) ACC_PUBLIC, ACC_STATIC
    Code:
      stack=0, locals=1, args_size=1
         0: return
      LineNumberTable:
        line 461: 0
      LocalVariableTable:
        Start  Length  Slot  Name   Signature
            0       1     0 $this   Lscala/sys/process/ProcessBuilder$Sink;
    MethodParameters:
      Name                           Flags
      $this                          final synthetic
}
InnerClasses:
  public static #8= #2 of #7;             // Sink=class scala/sys/process/ProcessBuilder$Sink of class scala/sys/process/ProcessBuilder
  public #13= #10 of #12;                 // FileInput=class scala/sys/process/ProcessBuilderImpl$FileInput of class scala/sys/process/ProcessBuilderImpl
  public #16= #15 of #12;                 // IStreamBuilder=class scala/sys/process/ProcessBuilderImpl$IStreamBuilder of class scala/sys/process/ProcessBuilderImpl
  public #19= #18 of #12;                 // PipedBuilder=class scala/sys/process/ProcessBuilderImpl$PipedBuilder of class scala/sys/process/ProcessBuilderImpl
  public #22= #21 of #12;                 // URLInput=class scala/sys/process/ProcessBuilderImpl$URLInput of class scala/sys/process/ProcessBuilderImpl
SourceFile: "ProcessBuilder.scala"
  ScalaInlineInfo: length = 0x36 (unknown attribute)
   01 00 00 0A 00 1D 00 1E 00 00 1D 00 32 00 00 1D
   00 3B 00 00 1D 00 2D 00 00 19 00 1A 01 00 19 00
   31 01 00 19 00 39 01 00 19 00 45 01 00 4D 00 4E
   01 00 17 00 18 00
  Scala: length = 0x0 (unknown attribute)

