Classfile /Users/mw/Projects/slang-braindump/.jar/jar8/assemble/slang-braindump/assemble/content/scala/sys/process/ProcessBuilder$Source.class
  Last modified May 29, 2022; size 3251 bytes
  SHA-256 checksum 1691c01890de87494ab389e71e155dea85c8e16f7aeb38e2c6c227be824c8ed6
  Compiled from "ProcessBuilder.scala"
public interface scala.sys.process.ProcessBuilder$Source
  minor version: 0
  major version: 52
  flags: (0x0601) ACC_PUBLIC, ACC_INTERFACE, ACC_ABSTRACT
  this_class: #2                          // scala/sys/process/ProcessBuilder$Source
  super_class: #4                         // java/lang/Object
  interfaces: 0, fields: 0, methods: 13, attributes: 4
Constant pool:
   #1 = Utf8               scala/sys/process/ProcessBuilder$Source
   #2 = Class              #1             // scala/sys/process/ProcessBuilder$Source
   #3 = Utf8               java/lang/Object
   #4 = Class              #3             // java/lang/Object
   #5 = Utf8               ProcessBuilder.scala
   #6 = Utf8               scala/sys/process/ProcessBuilder
   #7 = Class              #6             // scala/sys/process/ProcessBuilder
   #8 = Utf8               Source
   #9 = Utf8               scala/sys/process/ProcessBuilderImpl$FileOutput
  #10 = Class              #9             // scala/sys/process/ProcessBuilderImpl$FileOutput
  #11 = Utf8               scala/sys/process/ProcessBuilderImpl
  #12 = Class              #11            // scala/sys/process/ProcessBuilderImpl
  #13 = Utf8               FileOutput
  #14 = Utf8               scala/sys/process/ProcessBuilderImpl$OStreamBuilder
  #15 = Class              #14            // scala/sys/process/ProcessBuilderImpl$OStreamBuilder
  #16 = Utf8               OStreamBuilder
  #17 = Utf8               scala/sys/process/ProcessBuilderImpl$PipedBuilder
  #18 = Class              #17            // scala/sys/process/ProcessBuilderImpl$PipedBuilder
  #19 = Utf8               PipedBuilder
  #20 = Utf8               toSource
  #21 = Utf8               ()Lscala/sys/process/ProcessBuilder;
  #22 = Utf8               $hash$greater$
  #23 = Utf8               (Lscala/sys/process/ProcessBuilder$Source;Ljava/io/File;)Lscala/sys/process/ProcessBuilder;
  #24 = Utf8               $this
  #25 = Utf8               f
  #26 = Utf8               $hash$greater
  #27 = Utf8               (Ljava/io/File;)Lscala/sys/process/ProcessBuilder;
  #28 = NameAndType        #26:#27        // $hash$greater:(Ljava/io/File;)Lscala/sys/process/ProcessBuilder;
  #29 = InterfaceMethodref #2.#28         // scala/sys/process/ProcessBuilder$Source.$hash$greater:(Ljava/io/File;)Lscala/sys/process/ProcessBuilder;
  #30 = Utf8               Lscala/sys/process/ProcessBuilder$Source;
  #31 = Utf8               Ljava/io/File;
  #32 = Utf8               toFile
  #33 = Utf8               (Ljava/io/File;Z)Lscala/sys/process/ProcessBuilder;
  #34 = NameAndType        #32:#33        // toFile:(Ljava/io/File;Z)Lscala/sys/process/ProcessBuilder;
  #35 = InterfaceMethodref #2.#34         // scala/sys/process/ProcessBuilder$Source.toFile:(Ljava/io/File;Z)Lscala/sys/process/ProcessBuilder;
  #36 = Utf8               this
  #37 = Utf8               $hash$greater$greater$
  #38 = Utf8               $hash$greater$greater
  #39 = NameAndType        #38:#27        // $hash$greater$greater:(Ljava/io/File;)Lscala/sys/process/ProcessBuilder;
  #40 = InterfaceMethodref #2.#39         // scala/sys/process/ProcessBuilder$Source.$hash$greater$greater:(Ljava/io/File;)Lscala/sys/process/ProcessBuilder;
  #41 = Utf8               (Lscala/sys/process/ProcessBuilder$Source;Lscala/Function0;)Lscala/sys/process/ProcessBuilder;
  #42 = Utf8               out
  #43 = Utf8               (Lscala/Function0;)Lscala/sys/process/ProcessBuilder;
  #44 = NameAndType        #26:#43        // $hash$greater:(Lscala/Function0;)Lscala/sys/process/ProcessBuilder;
  #45 = InterfaceMethodref #2.#44         // scala/sys/process/ProcessBuilder$Source.$hash$greater:(Lscala/Function0;)Lscala/sys/process/ProcessBuilder;
  #46 = Utf8               Lscala/Function0;
  #47 = Utf8               (Lscala/Function0<Ljava/io/OutputStream;>;)Lscala/sys/process/ProcessBuilder;
  #48 = Utf8               scala/sys/process/ProcessBuilder$
  #49 = Class              #48            // scala/sys/process/ProcessBuilder$
  #50 = Utf8               MODULE$
  #51 = Utf8               Lscala/sys/process/ProcessBuilder$;
  #52 = NameAndType        #50:#51        // MODULE$:Lscala/sys/process/ProcessBuilder$;
  #53 = Fieldref           #49.#52        // scala/sys/process/ProcessBuilder$.MODULE$:Lscala/sys/process/ProcessBuilder$;
  #54 = Utf8               <output stream>
  #55 = String             #54            // <output stream>
  #56 = Utf8               <init>
  #57 = Utf8               (Lscala/sys/process/ProcessBuilder$;Lscala/Function0;Ljava/lang/String;)V
  #58 = NameAndType        #56:#57        // "<init>":(Lscala/sys/process/ProcessBuilder$;Lscala/Function0;Ljava/lang/String;)V
  #59 = Methodref          #15.#58        // scala/sys/process/ProcessBuilderImpl$OStreamBuilder."<init>":(Lscala/sys/process/ProcessBuilder$;Lscala/Function0;Ljava/lang/String;)V
  #60 = Utf8               (Lscala/sys/process/ProcessBuilder;)Lscala/sys/process/ProcessBuilder;
  #61 = NameAndType        #26:#60        // $hash$greater:(Lscala/sys/process/ProcessBuilder;)Lscala/sys/process/ProcessBuilder;
  #62 = InterfaceMethodref #2.#61         // scala/sys/process/ProcessBuilder$Source.$hash$greater:(Lscala/sys/process/ProcessBuilder;)Lscala/sys/process/ProcessBuilder;
  #63 = Utf8               (Lscala/sys/process/ProcessBuilder$Source;Lscala/sys/process/ProcessBuilder;)Lscala/sys/process/ProcessBuilder;
  #64 = Utf8               b
  #65 = Utf8               Lscala/sys/process/ProcessBuilder;
  #66 = NameAndType        #20:#21        // toSource:()Lscala/sys/process/ProcessBuilder;
  #67 = InterfaceMethodref #2.#66         // scala/sys/process/ProcessBuilder$Source.toSource:()Lscala/sys/process/ProcessBuilder;
  #68 = Utf8               (Lscala/sys/process/ProcessBuilder$;Lscala/sys/process/ProcessBuilder;Lscala/sys/process/ProcessBuilder;Z)V
  #69 = NameAndType        #56:#68        // "<init>":(Lscala/sys/process/ProcessBuilder$;Lscala/sys/process/ProcessBuilder;Lscala/sys/process/ProcessBuilder;Z)V
  #70 = Methodref          #18.#69        // scala/sys/process/ProcessBuilderImpl$PipedBuilder."<init>":(Lscala/sys/process/ProcessBuilder$;Lscala/sys/process/ProcessBuilder;Lscala/sys/process/ProcessBuilder;Z)V
  #71 = Utf8               cat$
  #72 = Utf8               (Lscala/sys/process/ProcessBuilder$Source;)Lscala/sys/process/ProcessBuilder;
  #73 = Utf8               cat
  #74 = NameAndType        #73:#21        // cat:()Lscala/sys/process/ProcessBuilder;
  #75 = InterfaceMethodref #2.#74         // scala/sys/process/ProcessBuilder$Source.cat:()Lscala/sys/process/ProcessBuilder;
  #76 = Utf8               append
  #77 = Utf8               (Lscala/sys/process/ProcessBuilder$;Ljava/io/File;Z)V
  #78 = NameAndType        #56:#77        // "<init>":(Lscala/sys/process/ProcessBuilder$;Ljava/io/File;Z)V
  #79 = Methodref          #10.#78        // scala/sys/process/ProcessBuilderImpl$FileOutput."<init>":(Lscala/sys/process/ProcessBuilder$;Ljava/io/File;Z)V
  #80 = Utf8               Z
  #81 = Utf8               $init$
  #82 = Utf8               (Lscala/sys/process/ProcessBuilder$Source;)V
  #83 = Utf8               Code
  #84 = Utf8               LineNumberTable
  #85 = Utf8               LocalVariableTable
  #86 = Utf8               MethodParameters
  #87 = Utf8               Signature
  #88 = Utf8               InnerClasses
  #89 = Utf8               SourceFile
  #90 = Utf8               ScalaInlineInfo
  #91 = Utf8               Scala
{
  public abstract scala.sys.process.ProcessBuilder toSource();
    descriptor: ()Lscala/sys/process/ProcessBuilder;
    flags: (0x0401) ACC_PUBLIC, ACC_ABSTRACT

  public static scala.sys.process.ProcessBuilder $hash$greater$(scala.sys.process.ProcessBuilder$Source, java.io.File);
    descriptor: (Lscala/sys/process/ProcessBuilder$Source;Ljava/io/File;)Lscala/sys/process/ProcessBuilder;
    flags: (0x1009) ACC_PUBLIC, ACC_STATIC, ACC_SYNTHETIC
    Code:
      stack=2, locals=2, args_size=2
         0: aload_0
         1: aload_1
         2: invokespecial #29                 // InterfaceMethod $hash$greater:(Ljava/io/File;)Lscala/sys/process/ProcessBuilder;
         5: areturn
      LineNumberTable:
        line 439: 0
      LocalVariableTable:
        Start  Length  Slot  Name   Signature
            0       6     0 $this   Lscala/sys/process/ProcessBuilder$Source;
            0       6     1     f   Ljava/io/File;
    MethodParameters:
      Name                           Flags
      $this                          final synthetic
      f                              final

  public default scala.sys.process.ProcessBuilder $hash$greater(java.io.File);
    descriptor: (Ljava/io/File;)Lscala/sys/process/ProcessBuilder;
    flags: (0x0001) ACC_PUBLIC
    Code:
      stack=3, locals=2, args_size=2
         0: aload_0
         1: aload_1
         2: iconst_0
         3: invokespecial #35                 // InterfaceMethod toFile:(Ljava/io/File;Z)Lscala/sys/process/ProcessBuilder;
         6: areturn
      LineNumberTable:
        line 439: 0
      LocalVariableTable:
        Start  Length  Slot  Name   Signature
            0       7     0  this   Lscala/sys/process/ProcessBuilder$Source;
            0       7     1     f   Ljava/io/File;
    MethodParameters:
      Name                           Flags
      f                              final

  public static scala.sys.process.ProcessBuilder $hash$greater$greater$(scala.sys.process.ProcessBuilder$Source, java.io.File);
    descriptor: (Lscala/sys/process/ProcessBuilder$Source;Ljava/io/File;)Lscala/sys/process/ProcessBuilder;
    flags: (0x1009) ACC_PUBLIC, ACC_STATIC, ACC_SYNTHETIC
    Code:
      stack=2, locals=2, args_size=2
         0: aload_0
         1: aload_1
         2: invokespecial #40                 // InterfaceMethod $hash$greater$greater:(Ljava/io/File;)Lscala/sys/process/ProcessBuilder;
         5: areturn
      LineNumberTable:
        line 442: 0
      LocalVariableTable:
        Start  Length  Slot  Name   Signature
            0       6     0 $this   Lscala/sys/process/ProcessBuilder$Source;
            0       6     1     f   Ljava/io/File;
    MethodParameters:
      Name                           Flags
      $this                          final synthetic
      f                              final

  public default scala.sys.process.ProcessBuilder $hash$greater$greater(java.io.File);
    descriptor: (Ljava/io/File;)Lscala/sys/process/ProcessBuilder;
    flags: (0x0001) ACC_PUBLIC
    Code:
      stack=3, locals=2, args_size=2
         0: aload_0
         1: aload_1
         2: iconst_1
         3: invokespecial #35                 // InterfaceMethod toFile:(Ljava/io/File;Z)Lscala/sys/process/ProcessBuilder;
         6: areturn
      LineNumberTable:
        line 442: 0
      LocalVariableTable:
        Start  Length  Slot  Name   Signature
            0       7     0  this   Lscala/sys/process/ProcessBuilder$Source;
            0       7     1     f   Ljava/io/File;
    MethodParameters:
      Name                           Flags
      f                              final

  public static scala.sys.process.ProcessBuilder $hash$greater$(scala.sys.process.ProcessBuilder$Source, scala.Function0);
    descriptor: (Lscala/sys/process/ProcessBuilder$Source;Lscala/Function0;)Lscala/sys/process/ProcessBuilder;
    flags: (0x1009) ACC_PUBLIC, ACC_STATIC, ACC_SYNTHETIC
    Code:
      stack=2, locals=2, args_size=2
         0: aload_0
         1: aload_1
         2: invokespecial #45                 // InterfaceMethod $hash$greater:(Lscala/Function0;)Lscala/sys/process/ProcessBuilder;
         5: areturn
      LineNumberTable:
        line 448: 0
      LocalVariableTable:
        Start  Length  Slot  Name   Signature
            0       6     0 $this   Lscala/sys/process/ProcessBuilder$Source;
            0       6     1   out   Lscala/Function0;
    MethodParameters:
      Name                           Flags
      $this                          final synthetic
      out                            final

  public default scala.sys.process.ProcessBuilder $hash$greater(scala.Function0<java.io.OutputStream>);
    descriptor: (Lscala/Function0;)Lscala/sys/process/ProcessBuilder;
    flags: (0x0001) ACC_PUBLIC
    Code:
      stack=6, locals=2, args_size=2
         0: aload_0
         1: new           #15                 // class scala/sys/process/ProcessBuilderImpl$OStreamBuilder
         4: dup
         5: getstatic     #53                 // Field scala/sys/process/ProcessBuilder$.MODULE$:Lscala/sys/process/ProcessBuilder$;
         8: aload_1
         9: ldc           #55                 // String <output stream>
        11: invokespecial #59                 // Method scala/sys/process/ProcessBuilderImpl$OStreamBuilder."<init>":(Lscala/sys/process/ProcessBuilder$;Lscala/Function0;Ljava/lang/String;)V
        14: invokeinterface #62,  2           // InterfaceMethod $hash$greater:(Lscala/sys/process/ProcessBuilder;)Lscala/sys/process/ProcessBuilder;
        19: areturn
      LineNumberTable:
        line 448: 0
      LocalVariableTable:
        Start  Length  Slot  Name   Signature
            0      20     0  this   Lscala/sys/process/ProcessBuilder$Source;
            0      20     1   out   Lscala/Function0;
    Signature: #47                          // (Lscala/Function0<Ljava/io/OutputStream;>;)Lscala/sys/process/ProcessBuilder;
    MethodParameters:
      Name                           Flags
      out                            final

  public static scala.sys.process.ProcessBuilder $hash$greater$(scala.sys.process.ProcessBuilder$Source, scala.sys.process.ProcessBuilder);
    descriptor: (Lscala/sys/process/ProcessBuilder$Source;Lscala/sys/process/ProcessBuilder;)Lscala/sys/process/ProcessBuilder;
    flags: (0x1009) ACC_PUBLIC, ACC_STATIC, ACC_SYNTHETIC
    Code:
      stack=2, locals=2, args_size=2
         0: aload_0
         1: aload_1
         2: invokespecial #62                 // InterfaceMethod $hash$greater:(Lscala/sys/process/ProcessBuilder;)Lscala/sys/process/ProcessBuilder;
         5: areturn
      LineNumberTable:
        line 451: 0
      LocalVariableTable:
        Start  Length  Slot  Name   Signature
            0       6     0 $this   Lscala/sys/process/ProcessBuilder$Source;
            0       6     1     b   Lscala/sys/process/ProcessBuilder;
    MethodParameters:
      Name                           Flags
      $this                          final synthetic
      b                              final

  public default scala.sys.process.ProcessBuilder $hash$greater(scala.sys.process.ProcessBuilder);
    descriptor: (Lscala/sys/process/ProcessBuilder;)Lscala/sys/process/ProcessBuilder;
    flags: (0x0001) ACC_PUBLIC
    Code:
      stack=6, locals=2, args_size=2
         0: new           #18                 // class scala/sys/process/ProcessBuilderImpl$PipedBuilder
         3: dup
         4: getstatic     #53                 // Field scala/sys/process/ProcessBuilder$.MODULE$:Lscala/sys/process/ProcessBuilder$;
         7: aload_0
         8: invokeinterface #67,  1           // InterfaceMethod toSource:()Lscala/sys/process/ProcessBuilder;
        13: aload_1
        14: iconst_0
        15: invokespecial #70                 // Method scala/sys/process/ProcessBuilderImpl$PipedBuilder."<init>":(Lscala/sys/process/ProcessBuilder$;Lscala/sys/process/ProcessBuilder;Lscala/sys/process/ProcessBuilder;Z)V
        18: areturn
      LineNumberTable:
        line 451: 0
      LocalVariableTable:
        Start  Length  Slot  Name   Signature
            0      19     0  this   Lscala/sys/process/ProcessBuilder$Source;
            0      19     1     b   Lscala/sys/process/ProcessBuilder;
    MethodParameters:
      Name                           Flags
      b                              final

  public static scala.sys.process.ProcessBuilder cat$(scala.sys.process.ProcessBuilder$Source);
    descriptor: (Lscala/sys/process/ProcessBuilder$Source;)Lscala/sys/process/ProcessBuilder;
    flags: (0x1009) ACC_PUBLIC, ACC_STATIC, ACC_SYNTHETIC
    Code:
      stack=1, locals=1, args_size=1
         0: aload_0
         1: invokespecial #75                 // InterfaceMethod cat:()Lscala/sys/process/ProcessBuilder;
         4: areturn
      LineNumberTable:
        line 454: 0
      LocalVariableTable:
        Start  Length  Slot  Name   Signature
            0       5     0 $this   Lscala/sys/process/ProcessBuilder$Source;
    MethodParameters:
      Name                           Flags
      $this                          final synthetic

  public default scala.sys.process.ProcessBuilder cat();
    descriptor: ()Lscala/sys/process/ProcessBuilder;
    flags: (0x0001) ACC_PUBLIC
    Code:
      stack=1, locals=1, args_size=1
         0: aload_0
         1: invokeinterface #67,  1           // InterfaceMethod toSource:()Lscala/sys/process/ProcessBuilder;
         6: areturn
      LineNumberTable:
        line 454: 0
      LocalVariableTable:
        Start  Length  Slot  Name   Signature
            0       7     0  this   Lscala/sys/process/ProcessBuilder$Source;

  private scala.sys.process.ProcessBuilder toFile(java.io.File, boolean);
    descriptor: (Ljava/io/File;Z)Lscala/sys/process/ProcessBuilder;
    flags: (0x0002) ACC_PRIVATE
    Code:
      stack=6, locals=3, args_size=3
         0: aload_0
         1: new           #10                 // class scala/sys/process/ProcessBuilderImpl$FileOutput
         4: dup
         5: getstatic     #53                 // Field scala/sys/process/ProcessBuilder$.MODULE$:Lscala/sys/process/ProcessBuilder$;
         8: aload_1
         9: iload_2
        10: invokespecial #79                 // Method scala/sys/process/ProcessBuilderImpl$FileOutput."<init>":(Lscala/sys/process/ProcessBuilder$;Ljava/io/File;Z)V
        13: invokeinterface #62,  2           // InterfaceMethod $hash$greater:(Lscala/sys/process/ProcessBuilder;)Lscala/sys/process/ProcessBuilder;
        18: areturn
      LineNumberTable:
        line 455: 0
      LocalVariableTable:
        Start  Length  Slot  Name   Signature
            0      19     0  this   Lscala/sys/process/ProcessBuilder$Source;
            0      19     1     f   Ljava/io/File;
            0      19     2 append   Z
    MethodParameters:
      Name                           Flags
      f                              final
      append                         final

  public static void $init$(scala.sys.process.ProcessBuilder$Source);
    descriptor: (Lscala/sys/process/ProcessBuilder$Source;)V
    flags: (0x0009) ACC_PUBLIC, ACC_STATIC
    Code:
      stack=0, locals=1, args_size=1
         0: return
      LineNumberTable:
        line 435: 0
      LocalVariableTable:
        Start  Length  Slot  Name   Signature
            0       1     0 $this   Lscala/sys/process/ProcessBuilder$Source;
    MethodParameters:
      Name                           Flags
      $this                          final synthetic
}
InnerClasses:
  public static #8= #2 of #7;             // Source=class scala/sys/process/ProcessBuilder$Source of class scala/sys/process/ProcessBuilder
  public #13= #10 of #12;                 // FileOutput=class scala/sys/process/ProcessBuilderImpl$FileOutput of class scala/sys/process/ProcessBuilderImpl
  public #16= #15 of #12;                 // OStreamBuilder=class scala/sys/process/ProcessBuilderImpl$OStreamBuilder of class scala/sys/process/ProcessBuilderImpl
  public #19= #18 of #12;                 // PipedBuilder=class scala/sys/process/ProcessBuilderImpl$PipedBuilder of class scala/sys/process/ProcessBuilderImpl
SourceFile: "ProcessBuilder.scala"
  ScalaInlineInfo: length = 0x45 (unknown attribute)
   01 00 00 0D 00 1A 00 1B 00 00 1A 00 2B 00 00 1A
   00 3C 00 00 16 00 17 01 00 16 00 29 01 00 16 00
   3F 01 00 26 00 1B 00 00 25 00 17 01 00 51 00 52
   01 00 49 00 15 00 00 47 00 48 01 00 20 00 21 01
   00 14 00 15 00
  Scala: length = 0x0 (unknown attribute)

