Classfile /Users/mw/Projects/slang-braindump/.jar/jar8/assemble/slang-braindump/assemble/content/scala/sys/process/ProcessLogger.class
  Last modified May 29, 2022; size 2342 bytes
  SHA-256 checksum 2b1daf489a4dd688899965f31602050d3207f6c5040a6987ce61598ab43ad326
  Compiled from "ProcessLogger.scala"
public interface scala.sys.process.ProcessLogger
  minor version: 0
  major version: 52
  flags: (0x0601) ACC_PUBLIC, ACC_INTERFACE, ACC_ABSTRACT
  this_class: #2                          // scala/sys/process/ProcessLogger
  super_class: #4                         // java/lang/Object
  interfaces: 0, fields: 0, methods: 6, attributes: 5
Constant pool:
   #1 = Utf8               scala/sys/process/ProcessLogger
   #2 = Class              #1             // scala/sys/process/ProcessLogger
   #3 = Utf8               java/lang/Object
   #4 = Class              #3             // java/lang/Object
   #5 = Utf8               ProcessLogger.scala
   #6 = Utf8               Lscala/reflect/ScalaSignature;
   #7 = Utf8               bytes
   #8 = Utf8               \u0006\u0005\u00054qAC\u0006\u0011\u0002G\u0005!\u0003C\u0003\u0018\u0001\u0019\u0005\u0001\u0004C\u0003-\u0001\u0019\u0005Q\u0006C\u00030\u0001\u0019\u0005\u0001gB\u0003A\u0017!\u0005\u0011IB\u0003\u000b\u0017!\u00051\tC\u0003E\u000b\u0011\u0005Q\tC\u0003G\u000b\u0011\u0005q\tC\u0003G\u000b\u0011\u0005Q\u000bC\u0003G\u000b\u0011\u0005ALA\u0007Qe>\u001cWm]:M_\u001e<WM\u001d\u0006\u0003\u00195\tq\u0001\u001d:pG\u0016\u001c8O\u0003\u0002\u000f\u001f\u0005\u00191/_:\u000b\u0003A\tQa]2bY\u0006\u001c\u0001a\u0005\u0002\u0001\'A\u0011A#F\u0007\u0002\u001f%\u0011ac\u0004\u0002\u0007\u0003:L(+\u001a4\u0002\u0007=,H\u000f\u0006\u0002\u001a9A\u0011ACG\u0005\u00037=\u0011A!\u00168ji\"1Q$\u0001CA\u0002y\t\u0011a\u001d\t\u0004)}\t\u0013B\u0001\u0011\u0010\u0005!a$-\u001f8b[\u0016t\u0004C\u0001\u0012*\u001d\t\u0019s\u0005\u0005\u0002%\u001f5\tQE\u0003\u0002\'#\u00051AH]8pizJ!\u0001K\b\u0002\rA\u0013X\rZ3g\u0013\tQ3F\u0001\u0004TiJLgn\u001a\u0006\u0003Q=\t1!\u001a:s)\tIb\u0006\u0003\u0004\u001e\u0005\u0011\u0005\rAH\u0001\u0007EV4g-\u001a:\u0016\u0005E\"DC\u0001\u001a>!\t\u0019D\u0007\u0004\u0001\u0005\u000bU\u001a!\u0019\u0001\u001c\u0003\u0003Q\u000b\"a\u000e\u001e\u0011\u0005QA\u0014BA\u001d\u0010\u0005\u001dqu\u000e\u001e5j]\u001e\u0004\"\u0001F\u001e\n\u0005qz!aA!os\"1ah\u0001CA\u0002}\n\u0011A\u001a\t\u0004)}\u0011\u0014!\u0004)s_\u000e,7o\u001d\'pO\u001e,\'\u000f\u0005\u0002C\u000b5\t1b\u0005\u0002\u0006\'\u00051A(\u001b8jiz\"\u0012!Q\u0001\u0006CB\u0004H.\u001f\u000b\u0003\u0011.\u0003\"AQ%\n\u0005)[!!\u0005$jY\u0016\u0004&o\\2fgNdunZ4fe\")Aj\u0002a\u0001\u001b\u0006!a-\u001b7f!\tq5+D\u0001P\u0015\t\u0001\u0016+\u0001\u0002j_*\t!+\u0001\u0003kCZ\f\u0017B\u0001+P\u0005\u00111\u0015\u000e\\3\u0015\u0005Y;\u0006C\u0001\"\u0001\u0011\u0015A\u0006\u00021\u0001Z\u0003\t1g\u000e\u0005\u0003\u00155\u0006J\u0012BA.\u0010\u0005%1UO\\2uS>t\u0017\u0007F\u0002W;~CQAX\u0005A\u0002e\u000bAAZ8vi\")\u0001-\u0003a\u00013\u0006!a-\u001a:s\u0001
   #9 = Utf8               scala/sys/process/ProcessLogger$$anon$1
  #10 = Class              #9             // scala/sys/process/ProcessLogger$$anon$1
  #11 = Utf8               apply
  #12 = Utf8               (Lscala/Function1;Lscala/Function1;)Lscala/sys/process/ProcessLogger;
  #13 = Utf8               (Lscala/Function1<Ljava/lang/String;Lscala/runtime/BoxedUnit;>;Lscala/Function1<Ljava/lang/String;Lscala/runtime/BoxedUnit;>;)Lscala/sys/process/ProcessLogger;
  #14 = Utf8               fout
  #15 = Utf8               ferr
  #16 = Utf8               scala/sys/process/ProcessLogger$
  #17 = Class              #16            // scala/sys/process/ProcessLogger$
  #18 = Utf8               MODULE$
  #19 = Utf8               Lscala/sys/process/ProcessLogger$;
  #20 = NameAndType        #18:#19        // MODULE$:Lscala/sys/process/ProcessLogger$;
  #21 = Fieldref           #17.#20        // scala/sys/process/ProcessLogger$.MODULE$:Lscala/sys/process/ProcessLogger$;
  #22 = Utf8               <init>
  #23 = Utf8               (Lscala/Function1;Lscala/Function1;)V
  #24 = NameAndType        #22:#23        // "<init>":(Lscala/Function1;Lscala/Function1;)V
  #25 = Methodref          #10.#24        // scala/sys/process/ProcessLogger$$anon$1."<init>":(Lscala/Function1;Lscala/Function1;)V
  #26 = Utf8               Lscala/Function1;
  #27 = Utf8               (Lscala/Function1;)Lscala/sys/process/ProcessLogger;
  #28 = Utf8               (Lscala/Function1<Ljava/lang/String;Lscala/runtime/BoxedUnit;>;)Lscala/sys/process/ProcessLogger;
  #29 = Utf8               fn
  #30 = Utf8               (Ljava/io/File;)Lscala/sys/process/FileProcessLogger;
  #31 = Utf8               file
  #32 = Utf8               scala/sys/process/FileProcessLogger
  #33 = Class              #32            // scala/sys/process/FileProcessLogger
  #34 = Utf8               (Ljava/io/File;)V
  #35 = NameAndType        #22:#34        // "<init>":(Ljava/io/File;)V
  #36 = Methodref          #33.#35        // scala/sys/process/FileProcessLogger."<init>":(Ljava/io/File;)V
  #37 = Utf8               Ljava/io/File;
  #38 = Utf8               out
  #39 = Utf8               (Lscala/Function0;)V
  #40 = Utf8               (Lscala/Function0<Ljava/lang/String;>;)V
  #41 = Utf8               s
  #42 = Utf8               err
  #43 = Utf8               buffer
  #44 = Utf8               (Lscala/Function0;)Ljava/lang/Object;
  #45 = Utf8               <T:Ljava/lang/Object;>(Lscala/Function0<TT;>;)TT;
  #46 = Utf8               f
  #47 = Utf8               Code
  #48 = Utf8               LineNumberTable
  #49 = Utf8               LocalVariableTable
  #50 = Utf8               Signature
  #51 = Utf8               MethodParameters
  #52 = Utf8               InnerClasses
  #53 = Utf8               SourceFile
  #54 = Utf8               RuntimeVisibleAnnotations
  #55 = Utf8               ScalaInlineInfo
  #56 = Utf8               ScalaSig
{
  public static scala.sys.process.ProcessLogger apply(scala.Function1<java.lang.String, scala.runtime.BoxedUnit>, scala.Function1<java.lang.String, scala.runtime.BoxedUnit>);
    descriptor: (Lscala/Function1;Lscala/Function1;)Lscala/sys/process/ProcessLogger;
    flags: (0x0009) ACC_PUBLIC, ACC_STATIC
    Code:
      stack=4, locals=2, args_size=2
         0: getstatic     #21                 // Field scala/sys/process/ProcessLogger$.MODULE$:Lscala/sys/process/ProcessLogger$;
         3: pop
         4: new           #10                 // class scala/sys/process/ProcessLogger$$anon$1
         7: dup
         8: aload_0
         9: aload_1
        10: invokespecial #25                 // Method scala/sys/process/ProcessLogger$$anon$1."<init>":(Lscala/Function1;Lscala/Function1;)V
        13: areturn
      LineNumberTable:
        line 100: 4
      LocalVariableTable:
        Start  Length  Slot  Name   Signature
            0      14     0  fout   Lscala/Function1;
            0      14     1  ferr   Lscala/Function1;
    Signature: #13                          // (Lscala/Function1<Ljava/lang/String;Lscala/runtime/BoxedUnit;>;Lscala/Function1<Ljava/lang/String;Lscala/runtime/BoxedUnit;>;)Lscala/sys/process/ProcessLogger;
    MethodParameters:
      Name                           Flags
      fout                           final
      ferr                           final

  public static scala.sys.process.ProcessLogger apply(scala.Function1<java.lang.String, scala.runtime.BoxedUnit>);
    descriptor: (Lscala/Function1;)Lscala/sys/process/ProcessLogger;
    flags: (0x0009) ACC_PUBLIC, ACC_STATIC
    Code:
      stack=4, locals=1, args_size=1
         0: getstatic     #21                 // Field scala/sys/process/ProcessLogger$.MODULE$:Lscala/sys/process/ProcessLogger$;
         3: pop
         4: new           #10                 // class scala/sys/process/ProcessLogger$$anon$1
         7: dup
         8: aload_0
         9: aload_0
        10: invokespecial #25                 // Method scala/sys/process/ProcessLogger$$anon$1."<init>":(Lscala/Function1;Lscala/Function1;)V
        13: areturn
      LineNumberTable:
        line 100: 4
        line 90: 13
      LocalVariableTable:
        Start  Length  Slot  Name   Signature
            0      14     0    fn   Lscala/Function1;
    Signature: #28                          // (Lscala/Function1<Ljava/lang/String;Lscala/runtime/BoxedUnit;>;)Lscala/sys/process/ProcessLogger;
    MethodParameters:
      Name                           Flags
      fn                             final

  public static scala.sys.process.FileProcessLogger apply(java.io.File);
    descriptor: (Ljava/io/File;)Lscala/sys/process/FileProcessLogger;
    flags: (0x0009) ACC_PUBLIC, ACC_STATIC
    Code:
      stack=3, locals=1, args_size=1
         0: getstatic     #21                 // Field scala/sys/process/ProcessLogger$.MODULE$:Lscala/sys/process/ProcessLogger$;
         3: pop
         4: new           #33                 // class scala/sys/process/FileProcessLogger
         7: dup
         8: aload_0
         9: invokespecial #36                 // Method scala/sys/process/FileProcessLogger."<init>":(Ljava/io/File;)V
        12: areturn
      LineNumberTable:
        line 85: 4
      LocalVariableTable:
        Start  Length  Slot  Name   Signature
            0      13     0  file   Ljava/io/File;
    MethodParameters:
      Name                           Flags
      file                           final

  public abstract void out(scala.Function0<java.lang.String>);
    descriptor: (Lscala/Function0;)V
    flags: (0x0401) ACC_PUBLIC, ACC_ABSTRACT
    Signature: #40                          // (Lscala/Function0<Ljava/lang/String;>;)V
    MethodParameters:
      Name                           Flags
      s                              final

  public abstract void err(scala.Function0<java.lang.String>);
    descriptor: (Lscala/Function0;)V
    flags: (0x0401) ACC_PUBLIC, ACC_ABSTRACT
    Signature: #40                          // (Lscala/Function0<Ljava/lang/String;>;)V
    MethodParameters:
      Name                           Flags
      s                              final

  public abstract <T extends java.lang.Object> T buffer(scala.Function0<T>);
    descriptor: (Lscala/Function0;)Ljava/lang/Object;
    flags: (0x0401) ACC_PUBLIC, ACC_ABSTRACT
    Signature: #45                          // <T:Ljava/lang/Object;>(Lscala/Function0<TT;>;)TT;
    MethodParameters:
      Name                           Flags
      f                              final
}
InnerClasses:
  public final #10;                       // class scala/sys/process/ProcessLogger$$anon$1
SourceFile: "ProcessLogger.scala"
RuntimeVisibleAnnotations:
  0: #6(#7=s#8)
    scala.reflect.ScalaSignature(
      bytes="\u0006\u0005\u00054qAC\u0006\u0011\u0002G\u0005!\u0003C\u0003\u0018\u0001\u0019\u0005\u0001\u0004C\u0003-\u0001\u0019\u0005Q\u0006C\u00030\u0001\u0019\u0005\u0001gB\u0003A\u0017!\u0005\u0011IB\u0003\u000b\u0017!\u00051\tC\u0003E\u000b\u0011\u0005Q\tC\u0003G\u000b\u0011\u0005q\tC\u0003G\u000b\u0011\u0005Q\u000bC\u0003G\u000b\u0011\u0005ALA\u0007Qe>\u001cWm]:M_\u001e<WM\u001d\u0006\u0003\u00195\tq\u0001\u001d:pG\u0016\u001c8O\u0003\u0002\u000f\u001f\u0005\u00191/_:\u000b\u0003A\tQa]2bY\u0006\u001c\u0001a\u0005\u0002\u0001\'A\u0011A#F\u0007\u0002\u001f%\u0011ac\u0004\u0002\u0007\u0003:L(+\u001a4\u0002\u0007=,H\u000f\u0006\u0002\u001a9A\u0011ACG\u0005\u00037=\u0011A!\u00168ji\"1Q$\u0001CA\u0002y\t\u0011a\u001d\t\u0004)}\t\u0013B\u0001\u0011\u0010\u0005!a$-\u001f8b[\u0016t\u0004C\u0001\u0012*\u001d\t\u0019s\u0005\u0005\u0002%\u001f5\tQE\u0003\u0002\'#\u00051AH]8pizJ!\u0001K\b\u0002\rA\u0013X\rZ3g\u0013\tQ3F\u0001\u0004TiJLgn\u001a\u0006\u0003Q=\t1!\u001a:s)\tIb\u0006\u0003\u0004\u001e\u0005\u0011\u0005\rAH\u0001\u0007EV4g-\u001a:\u0016\u0005E\"DC\u0001\u001a>!\t\u0019D\u0007\u0004\u0001\u0005\u000bU\u001a!\u0019\u0001\u001c\u0003\u0003Q\u000b\"a\u000e\u001e\u0011\u0005QA\u0014BA\u001d\u0010\u0005\u001dqu\u000e\u001e5j]\u001e\u0004\"\u0001F\u001e\n\u0005qz!aA!os\"1ah\u0001CA\u0002}\n\u0011A\u001a\t\u0004)}\u0011\u0014!\u0004)s_\u000e,7o\u001d\'pO\u001e,\'\u000f\u0005\u0002C\u000b5\t1b\u0005\u0002\u0006\'\u00051A(\u001b8jiz\"\u0012!Q\u0001\u0006CB\u0004H.\u001f\u000b\u0003\u0011.\u0003\"AQ%\n\u0005)[!!\u0005$jY\u0016\u0004&o\\2fgNdunZ4fe\")Aj\u0002a\u0001\u001b\u0006!a-\u001b7f!\tq5+D\u0001P\u0015\t\u0001\u0016+\u0001\u0002j_*\t!+\u0001\u0003kCZ\f\u0017B\u0001+P\u0005\u00111\u0015\u000e\\3\u0015\u0005Y;\u0006C\u0001\"\u0001\u0011\u0015A\u0006\u00021\u0001Z\u0003\t1g\u000e\u0005\u0003\u00155\u0006J\u0012BA.\u0010\u0005%1UO\\2uS>t\u0017\u0007F\u0002W;~CQAX\u0005A\u0002e\u000bAAZ8vi\")\u0001-\u0003a\u00013\u0006!a-\u001a:s\u0001"
    )
  ScalaInlineInfo: length = 0x13 (unknown attribute)
   01 00 00 03 00 2B 00 2C 00 00 2A 00 27 00 00 26
   00 27 00
  ScalaSig: length = 0x3 (unknown attribute)
   05 02 00
