Classfile /Users/mw/Projects/slang-braindump/.jar/jar8/assemble/slang-braindump/assemble/content/scala/sys/process/ProcessImpl$AndProcess$$anonfun$$lessinit$greater$1.class
  Last modified May 29, 2022; size 1503 bytes
  SHA-256 checksum 8dff9c07a215c300ebe45b828a7e9d98d1f6fc8d7a6f8e6dad1c6abb6aa105a4
  Compiled from "ProcessImpl.scala"
public final class scala.sys.process.ProcessImpl$AndProcess$$anonfun$$lessinit$greater$1 extends scala.runtime.AbstractFunction1$mcZI$sp implements java.io.Serializable
  minor version: 0
  major version: 52
  flags: (0x0031) ACC_PUBLIC, ACC_FINAL, ACC_SUPER
  this_class: #2                          // scala/sys/process/ProcessImpl$AndProcess$$anonfun$$lessinit$greater$1
  super_class: #4                         // scala/runtime/AbstractFunction1$mcZI$sp
  interfaces: 1, fields: 1, methods: 4, attributes: 5
Constant pool:
   #1 = Utf8               scala/sys/process/ProcessImpl$AndProcess$$anonfun$$lessinit$greater$1
   #2 = Class              #1             // scala/sys/process/ProcessImpl$AndProcess$$anonfun$$lessinit$greater$1
   #3 = Utf8               scala/runtime/AbstractFunction1$mcZI$sp
   #4 = Class              #3             // scala/runtime/AbstractFunction1$mcZI$sp
   #5 = Utf8               java/io/Serializable
   #6 = Class              #5             // java/io/Serializable
   #7 = Utf8               ProcessImpl.scala
   #8 = Utf8               scala/sys/process/ProcessImpl$AndProcess
   #9 = Class              #8             // scala/sys/process/ProcessImpl$AndProcess
  #10 = Utf8               <init>
  #11 = Utf8               (Lscala/sys/process/Process$;Lscala/sys/process/ProcessBuilder;Lscala/sys/process/ProcessBuilder;Lscala/sys/process/ProcessIO;)V
  #12 = NameAndType        #10:#11        // "<init>":(Lscala/sys/process/Process$;Lscala/sys/process/ProcessBuilder;Lscala/sys/process/ProcessBuilder;Lscala/sys/process/ProcessIO;)V
  #13 = Utf8               scala/sys/process/ProcessImpl
  #14 = Class              #13            // scala/sys/process/ProcessImpl
  #15 = Utf8               AndProcess
  #16 = Utf8               serialVersionUID
  #17 = Utf8               J
  #18 = Long               0l
  #20 = Utf8               apply
  #21 = Utf8               (I)Z
  #22 = Utf8               x$1
  #23 = Utf8               apply$mcZI$sp
  #24 = NameAndType        #23:#21        // apply$mcZI$sp:(I)Z
  #25 = Methodref          #2.#24         // scala/sys/process/ProcessImpl$AndProcess$$anonfun$$lessinit$greater$1.apply$mcZI$sp:(I)Z
  #26 = Utf8               this
  #27 = Utf8               Lscala/sys/process/ProcessImpl$AndProcess$$anonfun$$lessinit$greater$1;
  #28 = Utf8               I
  #29 = Utf8               (Ljava/lang/Object;)Ljava/lang/Object;
  #30 = Utf8               v1
  #31 = Utf8               scala/runtime/BoxesRunTime
  #32 = Class              #31            // scala/runtime/BoxesRunTime
  #33 = Utf8               unboxToInt
  #34 = Utf8               (Ljava/lang/Object;)I
  #35 = NameAndType        #33:#34        // unboxToInt:(Ljava/lang/Object;)I
  #36 = Methodref          #32.#35        // scala/runtime/BoxesRunTime.unboxToInt:(Ljava/lang/Object;)I
  #37 = NameAndType        #20:#21        // apply:(I)Z
  #38 = Methodref          #2.#37         // scala/sys/process/ProcessImpl$AndProcess$$anonfun$$lessinit$greater$1.apply:(I)Z
  #39 = Utf8               boxToBoolean
  #40 = Utf8               (Z)Ljava/lang/Boolean;
  #41 = NameAndType        #39:#40        // boxToBoolean:(Z)Ljava/lang/Boolean;
  #42 = Methodref          #32.#41        // scala/runtime/BoxesRunTime.boxToBoolean:(Z)Ljava/lang/Boolean;
  #43 = Utf8               Ljava/lang/Object;
  #44 = Utf8               (Lscala/sys/process/Process$;)V
  #45 = Utf8               $outer
  #46 = Utf8               ()V
  #47 = NameAndType        #10:#46        // "<init>":()V
  #48 = Methodref          #4.#47         // scala/runtime/AbstractFunction1$mcZI$sp."<init>":()V
  #49 = Utf8               Lscala/sys/process/Process$;
  #50 = Utf8               ConstantValue
  #51 = Utf8               Code
  #52 = Utf8               LineNumberTable
  #53 = Utf8               LocalVariableTable
  #54 = Utf8               MethodParameters
  #55 = Utf8               StackMapTable
  #56 = Utf8               InnerClasses
  #57 = Utf8               EnclosingMethod
  #58 = Utf8               SourceFile
  #59 = Utf8               ScalaInlineInfo
  #60 = Utf8               Scala
{
  private static final long serialVersionUID;
    descriptor: J
    flags: (0x001a) ACC_PRIVATE, ACC_STATIC, ACC_FINAL
    ConstantValue: long 0l

  public final boolean apply(int);
    descriptor: (I)Z
    flags: (0x0011) ACC_PUBLIC, ACC_FINAL
    Code:
      stack=2, locals=2, args_size=2
         0: aload_0
         1: iload_1
         2: invokevirtual #25                 // Method apply$mcZI$sp:(I)Z
         5: ireturn
      LineNumberTable:
        line 56: 0
      LocalVariableTable:
        Start  Length  Slot  Name   Signature
            0       6     0  this   Lscala/sys/process/ProcessImpl$AndProcess$$anonfun$$lessinit$greater$1;
            0       6     1   x$1   I
    MethodParameters:
      Name                           Flags
      x$1                            final

  public boolean apply$mcZI$sp(int);
    descriptor: (I)Z
    flags: (0x0001) ACC_PUBLIC
    Code:
      stack=2, locals=2, args_size=2
         0: iload_1
         1: iconst_0
         2: if_icmpne     7
         5: iconst_1
         6: ireturn
         7: iconst_0
         8: ireturn
      StackMapTable: number_of_entries = 1
        frame_type = 7 /* same */
      LineNumberTable:
        line 56: 0
      LocalVariableTable:
        Start  Length  Slot  Name   Signature
            0       9     0  this   Lscala/sys/process/ProcessImpl$AndProcess$$anonfun$$lessinit$greater$1;
            0       9     1   x$1   I
    MethodParameters:
      Name                           Flags
      x$1                            final

  public final java.lang.Object apply(java.lang.Object);
    descriptor: (Ljava/lang/Object;)Ljava/lang/Object;
    flags: (0x1051) ACC_PUBLIC, ACC_FINAL, ACC_BRIDGE, ACC_SYNTHETIC
    Code:
      stack=2, locals=2, args_size=2
         0: aload_0
         1: aload_1
         2: invokestatic  #36                 // Method scala/runtime/BoxesRunTime.unboxToInt:(Ljava/lang/Object;)I
         5: invokevirtual #38                 // Method apply:(I)Z
         8: invokestatic  #42                 // Method scala/runtime/BoxesRunTime.boxToBoolean:(Z)Ljava/lang/Boolean;
        11: areturn
      LineNumberTable:
        line 56: 0
      LocalVariableTable:
        Start  Length  Slot  Name   Signature
            0      12     0  this   Lscala/sys/process/ProcessImpl$AndProcess$$anonfun$$lessinit$greater$1;
            0      12     1    v1   Ljava/lang/Object;
    MethodParameters:
      Name                           Flags
      v1                             final

  public scala.sys.process.ProcessImpl$AndProcess$$anonfun$$lessinit$greater$1(scala.sys.process.Process$);
    descriptor: (Lscala/sys/process/Process$;)V
    flags: (0x0001) ACC_PUBLIC
    Code:
      stack=1, locals=2, args_size=2
         0: aload_0
         1: invokespecial #48                 // Method scala/runtime/AbstractFunction1$mcZI$sp."<init>":()V
         4: return
      LineNumberTable:
        line 56: 0
      LocalVariableTable:
        Start  Length  Slot  Name   Signature
            0       5     0  this   Lscala/sys/process/ProcessImpl$AndProcess$$anonfun$$lessinit$greater$1;
            0       5     1 $outer   Lscala/sys/process/Process$;
    MethodParameters:
      Name                           Flags
      $outer                         final synthetic
}
InnerClasses:
  public #15= #9 of #14;                  // AndProcess=class scala/sys/process/ProcessImpl$AndProcess of class scala/sys/process/ProcessImpl
  public final #2;                        // class scala/sys/process/ProcessImpl$AndProcess$$anonfun$$lessinit$greater$1
EnclosingMethod: #9.#12                 // scala.sys.process.ProcessImpl$AndProcess.<init>
SourceFile: "ProcessImpl.scala"
  ScalaInlineInfo: length = 0x18 (unknown attribute)
   01 01 00 04 00 0A 00 2C 01 00 14 00 15 01 00 14
   00 1D 01 00 17 00 15 01
  Scala: length = 0x0 (unknown attribute)

