Classfile /Users/mw/Projects/slang-braindump/.jar/jar8/assemble/slang-braindump/assemble/content/scala/sys/process/ProcessBuilderImpl$URLInput.class
  Last modified May 29, 2022; size 1120 bytes
  SHA-256 checksum 708251c446f7c60adc9066596de4c6c8f19b5886c06706e5b5b8f7d475d8ccc9
  Compiled from "ProcessBuilderImpl.scala"
public class scala.sys.process.ProcessBuilderImpl$URLInput extends scala.sys.process.ProcessBuilderImpl$IStreamBuilder
  minor version: 0
  major version: 52
  flags: (0x0021) ACC_PUBLIC, ACC_SUPER
  this_class: #2                          // scala/sys/process/ProcessBuilderImpl$URLInput
  super_class: #4                         // scala/sys/process/ProcessBuilderImpl$IStreamBuilder
  interfaces: 0, fields: 0, methods: 2, attributes: 4
Constant pool:
   #1 = Utf8               scala/sys/process/ProcessBuilderImpl$URLInput
   #2 = Class              #1             // scala/sys/process/ProcessBuilderImpl$URLInput
   #3 = Utf8               scala/sys/process/ProcessBuilderImpl$IStreamBuilder
   #4 = Class              #3             // scala/sys/process/ProcessBuilderImpl$IStreamBuilder
   #5 = Utf8               ProcessBuilderImpl.scala
   #6 = Utf8               scala/sys/process/ProcessBuilderImpl
   #7 = Class              #6             // scala/sys/process/ProcessBuilderImpl
   #8 = Utf8               IStreamBuilder
   #9 = Utf8               URLInput
  #10 = Utf8               scala/sys/process/ProcessBuilderImpl$URLInput$$anonfun$$lessinit$greater$1
  #11 = Class              #10            // scala/sys/process/ProcessBuilderImpl$URLInput$$anonfun$$lessinit$greater$1
  #12 = Utf8               scala$sys$process$ProcessBuilderImpl$URLInput$$$outer
  #13 = Utf8               ()Lscala/sys/process/ProcessBuilder$;
  #14 = Utf8               $outer
  #15 = Utf8               Lscala/sys/process/ProcessBuilder$;
  #16 = NameAndType        #14:#15        // $outer:Lscala/sys/process/ProcessBuilder$;
  #17 = Fieldref           #2.#16         // scala/sys/process/ProcessBuilderImpl$URLInput.$outer:Lscala/sys/process/ProcessBuilder$;
  #18 = Utf8               this
  #19 = Utf8               Lscala/sys/process/ProcessBuilderImpl$URLInput;
  #20 = Utf8               <init>
  #21 = Utf8               (Lscala/sys/process/ProcessBuilder$;Ljava/net/URL;)V
  #22 = Utf8               url
  #23 = NameAndType        #20:#21        // "<init>":(Lscala/sys/process/ProcessBuilder$;Ljava/net/URL;)V
  #24 = Methodref          #11.#23        // scala/sys/process/ProcessBuilderImpl$URLInput$$anonfun$$lessinit$greater$1."<init>":(Lscala/sys/process/ProcessBuilder$;Ljava/net/URL;)V
  #25 = Utf8               java/net/URL
  #26 = Class              #25            // java/net/URL
  #27 = Utf8               toString
  #28 = Utf8               ()Ljava/lang/String;
  #29 = NameAndType        #27:#28        // toString:()Ljava/lang/String;
  #30 = Methodref          #26.#29        // java/net/URL.toString:()Ljava/lang/String;
  #31 = Utf8               (Lscala/sys/process/ProcessBuilder$;Lscala/Function0;Ljava/lang/String;)V
  #32 = NameAndType        #20:#31        // "<init>":(Lscala/sys/process/ProcessBuilder$;Lscala/Function0;Ljava/lang/String;)V
  #33 = Methodref          #4.#32         // scala/sys/process/ProcessBuilderImpl$IStreamBuilder."<init>":(Lscala/sys/process/ProcessBuilder$;Lscala/Function0;Ljava/lang/String;)V
  #34 = Utf8               Ljava/net/URL;
  #35 = Utf8               Code
  #36 = Utf8               LineNumberTable
  #37 = Utf8               LocalVariableTable
  #38 = Utf8               MethodParameters
  #39 = Utf8               InnerClasses
  #40 = Utf8               SourceFile
  #41 = Utf8               ScalaInlineInfo
  #42 = Utf8               Scala
{
  public scala.sys.process.ProcessBuilder$ scala$sys$process$ProcessBuilderImpl$URLInput$$$outer();
    descriptor: ()Lscala/sys/process/ProcessBuilder$;
    flags: (0x1001) ACC_PUBLIC, ACC_SYNTHETIC
    Code:
      stack=1, locals=1, args_size=1
         0: aload_0
         1: getfield      #17                 // Field $outer:Lscala/sys/process/ProcessBuilder$;
         4: areturn
      LineNumberTable:
        line 39: 0
      LocalVariableTable:
        Start  Length  Slot  Name   Signature
            0       5     0  this   Lscala/sys/process/ProcessBuilderImpl$URLInput;

  public scala.sys.process.ProcessBuilderImpl$URLInput(scala.sys.process.ProcessBuilder$, java.net.URL);
    descriptor: (Lscala/sys/process/ProcessBuilder$;Ljava/net/URL;)V
    flags: (0x0001) ACC_PUBLIC
    Code:
      stack=6, locals=3, args_size=3
         0: aload_0
         1: aload_1
         2: new           #11                 // class scala/sys/process/ProcessBuilderImpl$URLInput$$anonfun$$lessinit$greater$1
         5: dup
         6: aconst_null
         7: aload_2
         8: invokespecial #24                 // Method scala/sys/process/ProcessBuilderImpl$URLInput$$anonfun$$lessinit$greater$1."<init>":(Lscala/sys/process/ProcessBuilder$;Ljava/net/URL;)V
        11: aload_2
        12: invokevirtual #30                 // Method java/net/URL.toString:()Ljava/lang/String;
        15: invokespecial #33                 // Method scala/sys/process/ProcessBuilderImpl$IStreamBuilder."<init>":(Lscala/sys/process/ProcessBuilder$;Lscala/Function0;Ljava/lang/String;)V
        18: return
      LineNumberTable:
        line 39: 0
      LocalVariableTable:
        Start  Length  Slot  Name   Signature
            0      19     0  this   Lscala/sys/process/ProcessBuilderImpl$URLInput;
            0      19     1 $outer   Lscala/sys/process/ProcessBuilder$;
            0      19     2   url   Ljava/net/URL;
    MethodParameters:
      Name                           Flags
      $outer                         final synthetic
      url                            final
}
InnerClasses:
  public #8= #4 of #7;                    // IStreamBuilder=class scala/sys/process/ProcessBuilderImpl$IStreamBuilder of class scala/sys/process/ProcessBuilderImpl
  public #9= #2 of #7;                    // URLInput=class scala/sys/process/ProcessBuilderImpl$URLInput of class scala/sys/process/ProcessBuilderImpl
  public final #11;                       // class scala/sys/process/ProcessBuilderImpl$URLInput$$anonfun$$lessinit$greater$1
SourceFile: "ProcessBuilderImpl.scala"
  ScalaInlineInfo: length = 0xE (unknown attribute)
   01 00 00 02 00 14 00 15 00 00 0C 00 0D 00
  Scala: length = 0x0 (unknown attribute)

