Classfile /Users/mw/Projects/slang-braindump/.jar/jar8/assemble/slang-braindump/assemble/content/scala/sys/process/ProcessBuilderImpl$OStreamBuilder.class
  Last modified May 29, 2022; size 1384 bytes
  SHA-256 checksum bb2b8e1234ed2c4d18a527a1168cff7683d7c71b022b4fa08dbf95938a6f5b37
  Compiled from "ProcessBuilderImpl.scala"
public class scala.sys.process.ProcessBuilderImpl$OStreamBuilder extends scala.sys.process.ProcessBuilderImpl$ThreadBuilder
  minor version: 0
  major version: 52
  flags: (0x0021) ACC_PUBLIC, ACC_SUPER
  this_class: #2                          // scala/sys/process/ProcessBuilderImpl$OStreamBuilder
  super_class: #4                         // scala/sys/process/ProcessBuilderImpl$ThreadBuilder
  interfaces: 0, fields: 0, methods: 3, attributes: 4
Constant pool:
   #1 = Utf8               scala/sys/process/ProcessBuilderImpl$OStreamBuilder
   #2 = Class              #1             // scala/sys/process/ProcessBuilderImpl$OStreamBuilder
   #3 = Utf8               scala/sys/process/ProcessBuilderImpl$ThreadBuilder
   #4 = Class              #3             // scala/sys/process/ProcessBuilderImpl$ThreadBuilder
   #5 = Utf8               ProcessBuilderImpl.scala
   #6 = Utf8               scala/sys/process/ProcessBuilderImpl
   #7 = Class              #6             // scala/sys/process/ProcessBuilderImpl
   #8 = Utf8               OStreamBuilder
   #9 = Utf8               scala/sys/process/ProcessBuilderImpl$OStreamBuilder$$anonfun$$lessinit$greater$4
  #10 = Class              #9             // scala/sys/process/ProcessBuilderImpl$OStreamBuilder$$anonfun$$lessinit$greater$4
  #11 = Utf8               ThreadBuilder
  #12 = Utf8               hasExitValue
  #13 = Utf8               ()Z
  #14 = Utf8               this
  #15 = Utf8               Lscala/sys/process/ProcessBuilderImpl$OStreamBuilder;
  #16 = Utf8               scala$sys$process$ProcessBuilderImpl$OStreamBuilder$$$outer
  #17 = Utf8               ()Lscala/sys/process/ProcessBuilder$;
  #18 = Utf8               $outer
  #19 = Utf8               Lscala/sys/process/ProcessBuilder$;
  #20 = NameAndType        #18:#19        // $outer:Lscala/sys/process/ProcessBuilder$;
  #21 = Fieldref           #2.#20         // scala/sys/process/ProcessBuilderImpl$OStreamBuilder.$outer:Lscala/sys/process/ProcessBuilder$;
  #22 = Utf8               <init>
  #23 = Utf8               (Lscala/sys/process/ProcessBuilder$;Lscala/Function0;Ljava/lang/String;)V
  #24 = Utf8               (Lscala/Function0<Ljava/io/OutputStream;>;Ljava/lang/String;)V
  #25 = Utf8               stream
  #26 = Utf8               label
  #27 = Utf8               (Lscala/sys/process/ProcessBuilder$;Lscala/Function0;)V
  #28 = NameAndType        #22:#27        // "<init>":(Lscala/sys/process/ProcessBuilder$;Lscala/Function0;)V
  #29 = Methodref          #10.#28        // scala/sys/process/ProcessBuilderImpl$OStreamBuilder$$anonfun$$lessinit$greater$4."<init>":(Lscala/sys/process/ProcessBuilder$;Lscala/Function0;)V
  #30 = Utf8               (Lscala/sys/process/ProcessBuilder$;Ljava/lang/String;Lscala/Function1;)V
  #31 = NameAndType        #22:#30        // "<init>":(Lscala/sys/process/ProcessBuilder$;Ljava/lang/String;Lscala/Function1;)V
  #32 = Methodref          #4.#31         // scala/sys/process/ProcessBuilderImpl$ThreadBuilder."<init>":(Lscala/sys/process/ProcessBuilder$;Ljava/lang/String;Lscala/Function1;)V
  #33 = Utf8               Lscala/Function0;
  #34 = Utf8               Ljava/lang/String;
  #35 = Utf8               Code
  #36 = Utf8               LineNumberTable
  #37 = Utf8               LocalVariableTable
  #38 = Utf8               Signature
  #39 = Utf8               MethodParameters
  #40 = Utf8               InnerClasses
  #41 = Utf8               SourceFile
  #42 = Utf8               ScalaInlineInfo
  #43 = Utf8               Scala
{
  public boolean hasExitValue();
    descriptor: ()Z
    flags: (0x0001) ACC_PUBLIC
    Code:
      stack=1, locals=1, args_size=1
         0: iconst_0
         1: ireturn
      LineNumberTable:
        line 47: 0
      LocalVariableTable:
        Start  Length  Slot  Name   Signature
            0       2     0  this   Lscala/sys/process/ProcessBuilderImpl$OStreamBuilder;

  public scala.sys.process.ProcessBuilder$ scala$sys$process$ProcessBuilderImpl$OStreamBuilder$$$outer();
    descriptor: ()Lscala/sys/process/ProcessBuilder$;
    flags: (0x1001) ACC_PUBLIC, ACC_SYNTHETIC
    Code:
      stack=1, locals=1, args_size=1
         0: aload_0
         1: getfield      #21                 // Field $outer:Lscala/sys/process/ProcessBuilder$;
         4: areturn
      LineNumberTable:
        line 43: 0
      LocalVariableTable:
        Start  Length  Slot  Name   Signature
            0       5     0  this   Lscala/sys/process/ProcessBuilderImpl$OStreamBuilder;

  public scala.sys.process.ProcessBuilderImpl$OStreamBuilder(scala.Function0<java.io.OutputStream>, java.lang.String);
    descriptor: (Lscala/sys/process/ProcessBuilder$;Lscala/Function0;Ljava/lang/String;)V
    flags: (0x0001) ACC_PUBLIC
    Code:
      stack=7, locals=4, args_size=4
         0: aload_0
         1: aload_1
         2: aload_3
         3: new           #10                 // class scala/sys/process/ProcessBuilderImpl$OStreamBuilder$$anonfun$$lessinit$greater$4
         6: dup
         7: aconst_null
         8: aload_2
         9: invokespecial #29                 // Method scala/sys/process/ProcessBuilderImpl$OStreamBuilder$$anonfun$$lessinit$greater$4."<init>":(Lscala/sys/process/ProcessBuilder$;Lscala/Function0;)V
        12: invokespecial #32                 // Method scala/sys/process/ProcessBuilderImpl$ThreadBuilder."<init>":(Lscala/sys/process/ProcessBuilder$;Ljava/lang/String;Lscala/Function1;)V
        15: return
      LineNumberTable:
        line 46: 0
        line 43: 15
      LocalVariableTable:
        Start  Length  Slot  Name   Signature
            0      16     0  this   Lscala/sys/process/ProcessBuilderImpl$OStreamBuilder;
            0      16     1 $outer   Lscala/sys/process/ProcessBuilder$;
            0      16     2 stream   Lscala/Function0;
            0      16     3 label   Ljava/lang/String;
    Signature: #24                          // (Lscala/Function0<Ljava/io/OutputStream;>;Ljava/lang/String;)V
    MethodParameters:
      Name                           Flags
      $outer                         final synthetic
      stream                         final
      label                          final
}
InnerClasses:
  public #8= #2 of #7;                    // OStreamBuilder=class scala/sys/process/ProcessBuilderImpl$OStreamBuilder of class scala/sys/process/ProcessBuilderImpl
  public final #10;                       // class scala/sys/process/ProcessBuilderImpl$OStreamBuilder$$anonfun$$lessinit$greater$4
  public abstract #11= #4 of #7;          // ThreadBuilder=class scala/sys/process/ProcessBuilderImpl$ThreadBuilder of class scala/sys/process/ProcessBuilderImpl
SourceFile: "ProcessBuilderImpl.scala"
  ScalaInlineInfo: length = 0x13 (unknown attribute)
   01 00 00 03 00 16 00 17 00 00 0C 00 0D 00 00 10
   00 11 00
  Scala: length = 0x0 (unknown attribute)

