Classfile /Users/mw/Projects/slang-braindump/.jar/jar8/assemble/slang-braindump/assemble/content/com/fasterxml/jackson/core/filter/TokenFilter$Inclusion.class
  Last modified May 29, 2022; size 1332 bytes
  SHA-256 checksum 246796467e009f2ba264bdf3af02a4099d1fd85498294e2d87803314b5c663e9
  Compiled from "TokenFilter.java"
public final class com.fasterxml.jackson.core.filter.TokenFilter$Inclusion extends java.lang.Enum<com.fasterxml.jackson.core.filter.TokenFilter$Inclusion>
  minor version: 0
  major version: 50
  flags: (0x4031) ACC_PUBLIC, ACC_FINAL, ACC_SUPER, ACC_ENUM
  this_class: #4                          // com/fasterxml/jackson/core/filter/TokenFilter$Inclusion
  super_class: #14                        // java/lang/Enum
  interfaces: 0, fields: 4, methods: 4, attributes: 3
Constant pool:
   #1 = Fieldref           #4.#41         // com/fasterxml/jackson/core/filter/TokenFilter$Inclusion.$VALUES:[Lcom/fasterxml/jackson/core/filter/TokenFilter$Inclusion;
   #2 = Methodref          #42.#43        // "[Lcom/fasterxml/jackson/core/filter/TokenFilter$Inclusion;".clone:()Ljava/lang/Object;
   #3 = Class              #22            // "[Lcom/fasterxml/jackson/core/filter/TokenFilter$Inclusion;"
   #4 = Class              #45            // com/fasterxml/jackson/core/filter/TokenFilter$Inclusion
   #5 = Methodref          #14.#46        // java/lang/Enum.valueOf:(Ljava/lang/Class;Ljava/lang/String;)Ljava/lang/Enum;
   #6 = Methodref          #14.#47        // java/lang/Enum."<init>":(Ljava/lang/String;I)V
   #7 = String             #15            // ONLY_INCLUDE_ALL
   #8 = Methodref          #4.#47         // com/fasterxml/jackson/core/filter/TokenFilter$Inclusion."<init>":(Ljava/lang/String;I)V
   #9 = Fieldref           #4.#48         // com/fasterxml/jackson/core/filter/TokenFilter$Inclusion.ONLY_INCLUDE_ALL:Lcom/fasterxml/jackson/core/filter/TokenFilter$Inclusion;
  #10 = String             #19            // INCLUDE_ALL_AND_PATH
  #11 = Fieldref           #4.#49         // com/fasterxml/jackson/core/filter/TokenFilter$Inclusion.INCLUDE_ALL_AND_PATH:Lcom/fasterxml/jackson/core/filter/TokenFilter$Inclusion;
  #12 = String             #20            // INCLUDE_NON_NULL
  #13 = Fieldref           #4.#50         // com/fasterxml/jackson/core/filter/TokenFilter$Inclusion.INCLUDE_NON_NULL:Lcom/fasterxml/jackson/core/filter/TokenFilter$Inclusion;
  #14 = Class              #51            // java/lang/Enum
  #15 = Utf8               ONLY_INCLUDE_ALL
  #16 = Utf8               Inclusion
  #17 = Utf8               InnerClasses
  #18 = Utf8               Lcom/fasterxml/jackson/core/filter/TokenFilter$Inclusion;
  #19 = Utf8               INCLUDE_ALL_AND_PATH
  #20 = Utf8               INCLUDE_NON_NULL
  #21 = Utf8               $VALUES
  #22 = Utf8               [Lcom/fasterxml/jackson/core/filter/TokenFilter$Inclusion;
  #23 = Utf8               values
  #24 = Utf8               ()[Lcom/fasterxml/jackson/core/filter/TokenFilter$Inclusion;
  #25 = Utf8               Code
  #26 = Utf8               LineNumberTable
  #27 = Utf8               valueOf
  #28 = Utf8               (Ljava/lang/String;)Lcom/fasterxml/jackson/core/filter/TokenFilter$Inclusion;
  #29 = Utf8               LocalVariableTable
  #30 = Utf8               name
  #31 = Utf8               Ljava/lang/String;
  #32 = Utf8               <init>
  #33 = Utf8               (Ljava/lang/String;I)V
  #34 = Utf8               this
  #35 = Utf8               Signature
  #36 = Utf8               ()V
  #37 = Utf8               <clinit>
  #38 = Utf8               Ljava/lang/Enum<Lcom/fasterxml/jackson/core/filter/TokenFilter$Inclusion;>;
  #39 = Utf8               SourceFile
  #40 = Utf8               TokenFilter.java
  #41 = NameAndType        #21:#22        // $VALUES:[Lcom/fasterxml/jackson/core/filter/TokenFilter$Inclusion;
  #42 = Class              #22            // "[Lcom/fasterxml/jackson/core/filter/TokenFilter$Inclusion;"
  #43 = NameAndType        #52:#53        // clone:()Ljava/lang/Object;
  #44 = Class              #54            // com/fasterxml/jackson/core/filter/TokenFilter
  #45 = Utf8               com/fasterxml/jackson/core/filter/TokenFilter$Inclusion
  #46 = NameAndType        #27:#55        // valueOf:(Ljava/lang/Class;Ljava/lang/String;)Ljava/lang/Enum;
  #47 = NameAndType        #32:#33        // "<init>":(Ljava/lang/String;I)V
  #48 = NameAndType        #15:#18        // ONLY_INCLUDE_ALL:Lcom/fasterxml/jackson/core/filter/TokenFilter$Inclusion;
  #49 = NameAndType        #19:#18        // INCLUDE_ALL_AND_PATH:Lcom/fasterxml/jackson/core/filter/TokenFilter$Inclusion;
  #50 = NameAndType        #20:#18        // INCLUDE_NON_NULL:Lcom/fasterxml/jackson/core/filter/TokenFilter$Inclusion;
  #51 = Utf8               java/lang/Enum
  #52 = Utf8               clone
  #53 = Utf8               ()Ljava/lang/Object;
  #54 = Utf8               com/fasterxml/jackson/core/filter/TokenFilter
  #55 = Utf8               (Ljava/lang/Class;Ljava/lang/String;)Ljava/lang/Enum;
{
  public static final com.fasterxml.jackson.core.filter.TokenFilter$Inclusion ONLY_INCLUDE_ALL;
    descriptor: Lcom/fasterxml/jackson/core/filter/TokenFilter$Inclusion;
    flags: (0x4019) ACC_PUBLIC, ACC_STATIC, ACC_FINAL, ACC_ENUM

  public static final com.fasterxml.jackson.core.filter.TokenFilter$Inclusion INCLUDE_ALL_AND_PATH;
    descriptor: Lcom/fasterxml/jackson/core/filter/TokenFilter$Inclusion;
    flags: (0x4019) ACC_PUBLIC, ACC_STATIC, ACC_FINAL, ACC_ENUM

  public static final com.fasterxml.jackson.core.filter.TokenFilter$Inclusion INCLUDE_NON_NULL;
    descriptor: Lcom/fasterxml/jackson/core/filter/TokenFilter$Inclusion;
    flags: (0x4019) ACC_PUBLIC, ACC_STATIC, ACC_FINAL, ACC_ENUM

  private static final com.fasterxml.jackson.core.filter.TokenFilter$Inclusion[] $VALUES;
    descriptor: [Lcom/fasterxml/jackson/core/filter/TokenFilter$Inclusion;
    flags: (0x101a) ACC_PRIVATE, ACC_STATIC, ACC_FINAL, ACC_SYNTHETIC

  public static com.fasterxml.jackson.core.filter.TokenFilter$Inclusion[] values();
    descriptor: ()[Lcom/fasterxml/jackson/core/filter/TokenFilter$Inclusion;
    flags: (0x0009) ACC_PUBLIC, ACC_STATIC
    Code:
      stack=1, locals=0, args_size=0
         0: getstatic     #1                  // Field $VALUES:[Lcom/fasterxml/jackson/core/filter/TokenFilter$Inclusion;
         3: invokevirtual #2                  // Method "[Lcom/fasterxml/jackson/core/filter/TokenFilter$Inclusion;".clone:()Ljava/lang/Object;
         6: checkcast     #3                  // class "[Lcom/fasterxml/jackson/core/filter/TokenFilter$Inclusion;"
         9: areturn
      LineNumberTable:
        line 24: 0

  public static com.fasterxml.jackson.core.filter.TokenFilter$Inclusion valueOf(java.lang.String);
    descriptor: (Ljava/lang/String;)Lcom/fasterxml/jackson/core/filter/TokenFilter$Inclusion;
    flags: (0x0009) ACC_PUBLIC, ACC_STATIC
    Code:
      stack=2, locals=1, args_size=1
         0: ldc           #4                  // class com/fasterxml/jackson/core/filter/TokenFilter$Inclusion
         2: aload_0
         3: invokestatic  #5                  // Method java/lang/Enum.valueOf:(Ljava/lang/Class;Ljava/lang/String;)Ljava/lang/Enum;
         6: checkcast     #4                  // class com/fasterxml/jackson/core/filter/TokenFilter$Inclusion
         9: areturn
      LineNumberTable:
        line 24: 0
      LocalVariableTable:
        Start  Length  Slot  Name   Signature
            0      10     0  name   Ljava/lang/String;

  private com.fasterxml.jackson.core.filter.TokenFilter$Inclusion();
    descriptor: (Ljava/lang/String;I)V
    flags: (0x0002) ACC_PRIVATE
    Code:
      stack=3, locals=3, args_size=3
         0: aload_0
         1: aload_1
         2: iload_2
         3: invokespecial #6                  // Method java/lang/Enum."<init>":(Ljava/lang/String;I)V
         6: return
      LineNumberTable:
        line 24: 0
      LocalVariableTable:
        Start  Length  Slot  Name   Signature
            0       7     0  this   Lcom/fasterxml/jackson/core/filter/TokenFilter$Inclusion;
    Signature: #36                          // ()V

  static {};
    descriptor: ()V
    flags: (0x0008) ACC_STATIC
    Code:
      stack=4, locals=0, args_size=0
         0: new           #4                  // class com/fasterxml/jackson/core/filter/TokenFilter$Inclusion
         3: dup
         4: ldc           #7                  // String ONLY_INCLUDE_ALL
         6: iconst_0
         7: invokespecial #8                  // Method "<init>":(Ljava/lang/String;I)V
        10: putstatic     #9                  // Field ONLY_INCLUDE_ALL:Lcom/fasterxml/jackson/core/filter/TokenFilter$Inclusion;
        13: new           #4                  // class com/fasterxml/jackson/core/filter/TokenFilter$Inclusion
        16: dup
        17: ldc           #10                 // String INCLUDE_ALL_AND_PATH
        19: iconst_1
        20: invokespecial #8                  // Method "<init>":(Ljava/lang/String;I)V
        23: putstatic     #11                 // Field INCLUDE_ALL_AND_PATH:Lcom/fasterxml/jackson/core/filter/TokenFilter$Inclusion;
        26: new           #4                  // class com/fasterxml/jackson/core/filter/TokenFilter$Inclusion
        29: dup
        30: ldc           #12                 // String INCLUDE_NON_NULL
        32: iconst_2
        33: invokespecial #8                  // Method "<init>":(Ljava/lang/String;I)V
        36: putstatic     #13                 // Field INCLUDE_NON_NULL:Lcom/fasterxml/jackson/core/filter/TokenFilter$Inclusion;
        39: iconst_3
        40: anewarray     #4                  // class com/fasterxml/jackson/core/filter/TokenFilter$Inclusion
        43: dup
        44: iconst_0
        45: getstatic     #9                  // Field ONLY_INCLUDE_ALL:Lcom/fasterxml/jackson/core/filter/TokenFilter$Inclusion;
        48: aastore
        49: dup
        50: iconst_1
        51: getstatic     #11                 // Field INCLUDE_ALL_AND_PATH:Lcom/fasterxml/jackson/core/filter/TokenFilter$Inclusion;
        54: aastore
        55: dup
        56: iconst_2
        57: getstatic     #13                 // Field INCLUDE_NON_NULL:Lcom/fasterxml/jackson/core/filter/TokenFilter$Inclusion;
        60: aastore
        61: putstatic     #1                  // Field $VALUES:[Lcom/fasterxml/jackson/core/filter/TokenFilter$Inclusion;
        64: return
      LineNumberTable:
        line 28: 0
        line 33: 13
        line 40: 26
        line 24: 39
}
Signature: #38                          // Ljava/lang/Enum<Lcom/fasterxml/jackson/core/filter/TokenFilter$Inclusion;>;
SourceFile: "TokenFilter.java"
InnerClasses:
  public static final #16= #4 of #44;     // Inclusion=class com/fasterxml/jackson/core/filter/TokenFilter$Inclusion of class com/fasterxml/jackson/core/filter/TokenFilter
