Classfile /Users/mw/Projects/slang-braindump/.jar/jar8/assemble/slang-braindump/assemble/content/org/apache/commons/lang3/time/DurationFormatUtils.class
  Last modified May 29, 2022; size 8527 bytes
  SHA-256 checksum 4046a9288879e86e613785ec7f0e0f34b2a110d5bbbeb3addb6f9ae5be7caab1
  Compiled from "DurationFormatUtils.java"
public class org.apache.commons.lang3.time.DurationFormatUtils
  minor version: 0
  major version: 52
  flags: (0x0021) ACC_PUBLIC, ACC_SUPER
  this_class: #4                          // org/apache/commons/lang3/time/DurationFormatUtils
  super_class: #56                        // java/lang/Object
  interfaces: 0, fields: 8, methods: 13, attributes: 2
Constant pool:
    #1 = Methodref          #56.#188      // java/lang/Object."<init>":()V
    #2 = String             #189          // HH:mm:ss.SSS
    #3 = Methodref          #4.#190       // org/apache/commons/lang3/time/DurationFormatUtils.formatDuration:(JLjava/lang/String;)Ljava/lang/String;
    #4 = Class              #191          // org/apache/commons/lang3/time/DurationFormatUtils
    #5 = String             #192          // \'P\'yyyy\'Y\'M\'M\'d\'DT\'H\'H\'m\'M\'s.SSS\'S\'
    #6 = Methodref          #4.#193       // org/apache/commons/lang3/time/DurationFormatUtils.formatDuration:(JLjava/lang/String;Z)Ljava/lang/String;
    #7 = Class              #194          // java/lang/Long
    #8 = Long               9223372036854775807l
   #10 = String             #195          // durationMillis must not be negative
   #11 = Methodref          #196.#197     // org/apache/commons/lang3/Validate.inclusiveBetween:(JJJLjava/lang/String;)V
   #12 = Methodref          #4.#198       // org/apache/commons/lang3/time/DurationFormatUtils.lexx:(Ljava/lang/String;)[Lorg/apache/commons/lang3/time/DurationFormatUtils$Token;
   #13 = Fieldref           #4.#199       // org/apache/commons/lang3/time/DurationFormatUtils.d:Ljava/lang/Object;
   #14 = Methodref          #82.#200      // org/apache/commons/lang3/time/DurationFormatUtils$Token.containsTokenWithValue:([Lorg/apache/commons/lang3/time/DurationFormatUtils$Token;Ljava/lang/Object;)Z
   #15 = Class              #201          // org/apache/commons/lang3/time/DateUtils
   #16 = Long               86400000l
   #18 = Fieldref           #4.#202       // org/apache/commons/lang3/time/DurationFormatUtils.H:Ljava/lang/Object;
   #19 = Long               3600000l
   #21 = Fieldref           #4.#203       // org/apache/commons/lang3/time/DurationFormatUtils.m:Ljava/lang/Object;
   #22 = Long               60000l
   #24 = Fieldref           #4.#204       // org/apache/commons/lang3/time/DurationFormatUtils.s:Ljava/lang/Object;
   #25 = Long               1000l
   #27 = Methodref          #4.#205       // org/apache/commons/lang3/time/DurationFormatUtils.format:([Lorg/apache/commons/lang3/time/DurationFormatUtils$Token;JJJJJJJZ)Ljava/lang/String;
   #28 = String             #206          // d\' days \'H\' hours \'m\' minutes \'s\' seconds\'
   #29 = Class              #207          // java/lang/StringBuilder
   #30 = Methodref          #29.#188      // java/lang/StringBuilder."<init>":()V
   #31 = String             #208          //
   #32 = Methodref          #29.#209      // java/lang/StringBuilder.append:(Ljava/lang/String;)Ljava/lang/StringBuilder;
   #33 = Methodref          #29.#210      // java/lang/StringBuilder.toString:()Ljava/lang/String;
   #34 = String             #211          //  0 days
   #35 = Class              #212          // org/apache/commons/lang3/StringUtils
   #36 = String             #213          //
   #37 = Methodref          #35.#214      // org/apache/commons/lang3/StringUtils.replaceOnce:(Ljava/lang/String;Ljava/lang/String;Ljava/lang/String;)Ljava/lang/String;
   #38 = Methodref          #138.#215     // java/lang/String.length:()I
   #39 = String             #216          //  0 hours
   #40 = String             #217          //  0 minutes
   #41 = String             #218          //  0 seconds
   #42 = Methodref          #138.#219     // java/lang/String.isEmpty:()Z
   #43 = Methodref          #138.#220     // java/lang/String.substring:(I)Ljava/lang/String;
   #44 = String             #221          //  1 seconds
   #45 = String             #222          //  1 second
   #46 = String             #223          //  1 minutes
   #47 = String             #224          //  1 minute
   #48 = String             #225          //  1 hours
   #49 = String             #226          //  1 hour
   #50 = String             #227          //  1 days
   #51 = String             #228          //  1 day
   #52 = Methodref          #138.#229     // java/lang/String.trim:()Ljava/lang/String;
   #53 = Methodref          #161.#230     // java/util/TimeZone.getDefault:()Ljava/util/TimeZone;
   #54 = Methodref          #4.#231       // org/apache/commons/lang3/time/DurationFormatUtils.formatPeriod:(JJLjava/lang/String;ZLjava/util/TimeZone;)Ljava/lang/String;
   #55 = String             #232          // startMillis must not be greater than endMillis
   #56 = Class              #233          // java/lang/Object
   #57 = Methodref          #196.#234     // org/apache/commons/lang3/Validate.isTrue:(ZLjava/lang/String;[Ljava/lang/Object;)V
   #58 = Methodref          #62.#235      // java/util/Calendar.getInstance:(Ljava/util/TimeZone;)Ljava/util/Calendar;
   #59 = Class              #236          // java/util/Date
   #60 = Methodref          #59.#237      // java/util/Date."<init>":(J)V
   #61 = Methodref          #62.#238      // java/util/Calendar.setTime:(Ljava/util/Date;)V
   #62 = Class              #239          // java/util/Calendar
   #63 = Methodref          #62.#240      // java/util/Calendar.get:(I)I
   #64 = Fieldref           #4.#241       // org/apache/commons/lang3/time/DurationFormatUtils.M:Ljava/lang/Object;
   #65 = Methodref          #62.#242      // java/util/Calendar.getActualMaximum:(I)I
   #66 = Methodref          #62.#243      // java/util/Calendar.add:(II)V
   #67 = Fieldref           #4.#244       // org/apache/commons/lang3/time/DurationFormatUtils.y:Ljava/lang/Object;
   #68 = Class              #245          // java/util/GregorianCalendar
   #69 = Methodref          #82.#246      // org/apache/commons/lang3/time/DurationFormatUtils$Token.getValue:()Ljava/lang/Object;
   #70 = Methodref          #82.#247      // org/apache/commons/lang3/time/DurationFormatUtils$Token.getCount:()I
   #71 = Methodref          #56.#210      // java/lang/Object.toString:()Ljava/lang/String;
   #72 = Methodref          #56.#248      // java/lang/Object.equals:(Ljava/lang/Object;)Z
   #73 = Methodref          #4.#249       // org/apache/commons/lang3/time/DurationFormatUtils.paddedValue:(JZI)Ljava/lang/String;
   #74 = Fieldref           #4.#250       // org/apache/commons/lang3/time/DurationFormatUtils.S:Ljava/lang/Object;
   #75 = Methodref          #251.#252     // java/lang/Math.max:(II)I
   #76 = Methodref          #7.#253       // java/lang/Long.toString:(J)Ljava/lang/String;
   #77 = Methodref          #35.#254      // org/apache/commons/lang3/StringUtils.leftPad:(Ljava/lang/String;IC)Ljava/lang/String;
   #78 = Class              #255          // java/util/ArrayList
   #79 = Methodref          #78.#256      // java/util/ArrayList."<init>":(I)V
   #80 = Methodref          #138.#257     // java/lang/String.charAt:(I)C
   #81 = Methodref          #29.#258      // java/lang/StringBuilder.append:(C)Ljava/lang/StringBuilder;
   #82 = Class              #259          // org/apache/commons/lang3/time/DurationFormatUtils$Token
   #83 = Methodref          #82.#260      // org/apache/commons/lang3/time/DurationFormatUtils$Token."<init>":(Ljava/lang/Object;)V
   #84 = Methodref          #78.#261      // java/util/ArrayList.add:(Ljava/lang/Object;)Z
   #85 = Methodref          #82.#262      // org/apache/commons/lang3/time/DurationFormatUtils$Token.increment:()V
   #86 = Class              #263          // java/lang/IllegalArgumentException
   #87 = String             #264          // Unmatched quote in format:
   #88 = Methodref          #86.#265      // java/lang/IllegalArgumentException."<init>":(Ljava/lang/String;)V
   #89 = Methodref          #78.#266      // java/util/ArrayList.size:()I
   #90 = Methodref          #78.#267      // java/util/ArrayList.toArray:([Ljava/lang/Object;)[Ljava/lang/Object;
   #91 = Class              #131          // "[Lorg/apache/commons/lang3/time/DurationFormatUtils$Token;"
   #92 = String             #104          // y
   #93 = String             #106          // M
   #94 = String             #107          // d
   #95 = String             #108          // H
   #96 = String             #109          // m
   #97 = String             #110          // s
   #98 = String             #111          // S
   #99 = Utf8               Token
  #100 = Utf8               InnerClasses
  #101 = Utf8               ISO_EXTENDED_FORMAT_PATTERN
  #102 = Utf8               Ljava/lang/String;
  #103 = Utf8               ConstantValue
  #104 = Utf8               y
  #105 = Utf8               Ljava/lang/Object;
  #106 = Utf8               M
  #107 = Utf8               d
  #108 = Utf8               H
  #109 = Utf8               m
  #110 = Utf8               s
  #111 = Utf8               S
  #112 = Utf8               <init>
  #113 = Utf8               ()V
  #114 = Utf8               Code
  #115 = Utf8               LineNumberTable
  #116 = Utf8               LocalVariableTable
  #117 = Utf8               this
  #118 = Utf8               Lorg/apache/commons/lang3/time/DurationFormatUtils;
  #119 = Utf8               formatDurationHMS
  #120 = Utf8               (J)Ljava/lang/String;
  #121 = Utf8               durationMillis
  #122 = Utf8               J
  #123 = Utf8               formatDurationISO
  #124 = Utf8               formatDuration
  #125 = Utf8               (JLjava/lang/String;)Ljava/lang/String;
  #126 = Utf8               format
  #127 = Utf8               (JLjava/lang/String;Z)Ljava/lang/String;
  #128 = Utf8               padWithZeros
  #129 = Utf8               Z
  #130 = Utf8               tokens
  #131 = Utf8               [Lorg/apache/commons/lang3/time/DurationFormatUtils$Token;
  #132 = Utf8               days
  #133 = Utf8               hours
  #134 = Utf8               minutes
  #135 = Utf8               seconds
  #136 = Utf8               milliseconds
  #137 = Utf8               StackMapTable
  #138 = Class              #268          // java/lang/String
  #139 = Utf8               formatDurationWords
  #140 = Utf8               (JZZ)Ljava/lang/String;
  #141 = Utf8               tmp
  #142 = Utf8               suppressLeadingZeroElements
  #143 = Utf8               suppressTrailingZeroElements
  #144 = Utf8               duration
  #145 = Utf8               formatPeriodISO
  #146 = Utf8               (JJ)Ljava/lang/String;
  #147 = Utf8               startMillis
  #148 = Utf8               endMillis
  #149 = Utf8               formatPeriod
  #150 = Utf8               (JJLjava/lang/String;)Ljava/lang/String;
  #151 = Utf8               (JJLjava/lang/String;ZLjava/util/TimeZone;)Ljava/lang/String;
  #152 = Utf8               target
  #153 = Utf8               I
  #154 = Utf8               timezone
  #155 = Utf8               Ljava/util/TimeZone;
  #156 = Utf8               start
  #157 = Utf8               Ljava/util/Calendar;
  #158 = Utf8               end
  #159 = Utf8               months
  #160 = Utf8               years
  #161 = Class              #269          // java/util/TimeZone
  #162 = Utf8               ([Lorg/apache/commons/lang3/time/DurationFormatUtils$Token;JJJJJJJZ)Ljava/lang/String;
  #163 = Utf8               width
  #164 = Utf8               value
  #165 = Utf8               count
  #166 = Utf8               token
  #167 = Utf8               Lorg/apache/commons/lang3/time/DurationFormatUtils$Token;
  #168 = Utf8               buffer
  #169 = Utf8               Ljava/lang/StringBuilder;
  #170 = Utf8               lastOutputSeconds
  #171 = Utf8               paddedValue
  #172 = Utf8               (JZI)Ljava/lang/String;
  #173 = Utf8               longString
  #174 = Utf8               lexx
  #175 = Utf8               (Ljava/lang/String;)[Lorg/apache/commons/lang3/time/DurationFormatUtils$Token;
  #176 = Utf8               ch
  #177 = Utf8               C
  #178 = Utf8               i
  #179 = Utf8               list
  #180 = Utf8               Ljava/util/ArrayList;
  #181 = Utf8               inLiteral
  #182 = Utf8               previous
  #183 = Utf8               LocalVariableTypeTable
  #184 = Utf8               Ljava/util/ArrayList<Lorg/apache/commons/lang3/time/DurationFormatUtils$Token;>;
  #185 = Utf8               <clinit>
  #186 = Utf8               SourceFile
  #187 = Utf8               DurationFormatUtils.java
  #188 = NameAndType        #112:#113     // "<init>":()V
  #189 = Utf8               HH:mm:ss.SSS
  #190 = NameAndType        #124:#125     // formatDuration:(JLjava/lang/String;)Ljava/lang/String;
  #191 = Utf8               org/apache/commons/lang3/time/DurationFormatUtils
  #192 = Utf8               \'P\'yyyy\'Y\'M\'M\'d\'DT\'H\'H\'m\'M\'s.SSS\'S\'
  #193 = NameAndType        #124:#127     // formatDuration:(JLjava/lang/String;Z)Ljava/lang/String;
  #194 = Utf8               java/lang/Long
  #195 = Utf8               durationMillis must not be negative
  #196 = Class              #270          // org/apache/commons/lang3/Validate
  #197 = NameAndType        #271:#272     // inclusiveBetween:(JJJLjava/lang/String;)V
  #198 = NameAndType        #174:#175     // lexx:(Ljava/lang/String;)[Lorg/apache/commons/lang3/time/DurationFormatUtils$Token;
  #199 = NameAndType        #107:#105     // d:Ljava/lang/Object;
  #200 = NameAndType        #273:#274     // containsTokenWithValue:([Lorg/apache/commons/lang3/time/DurationFormatUtils$Token;Ljava/lang/Object;)Z
  #201 = Utf8               org/apache/commons/lang3/time/DateUtils
  #202 = NameAndType        #108:#105     // H:Ljava/lang/Object;
  #203 = NameAndType        #109:#105     // m:Ljava/lang/Object;
  #204 = NameAndType        #110:#105     // s:Ljava/lang/Object;
  #205 = NameAndType        #126:#162     // format:([Lorg/apache/commons/lang3/time/DurationFormatUtils$Token;JJJJJJJZ)Ljava/lang/String;
  #206 = Utf8               d\' days \'H\' hours \'m\' minutes \'s\' seconds\'
  #207 = Utf8               java/lang/StringBuilder
  #208 = Utf8
  #209 = NameAndType        #275:#276     // append:(Ljava/lang/String;)Ljava/lang/StringBuilder;
  #210 = NameAndType        #277:#278     // toString:()Ljava/lang/String;
  #211 = Utf8                0 days
  #212 = Utf8               org/apache/commons/lang3/StringUtils
  #213 = Utf8
  #214 = NameAndType        #279:#280     // replaceOnce:(Ljava/lang/String;Ljava/lang/String;Ljava/lang/String;)Ljava/lang/String;
  #215 = NameAndType        #281:#282     // length:()I
  #216 = Utf8                0 hours
  #217 = Utf8                0 minutes
  #218 = Utf8                0 seconds
  #219 = NameAndType        #283:#284     // isEmpty:()Z
  #220 = NameAndType        #285:#286     // substring:(I)Ljava/lang/String;
  #221 = Utf8                1 seconds
  #222 = Utf8                1 second
  #223 = Utf8                1 minutes
  #224 = Utf8                1 minute
  #225 = Utf8                1 hours
  #226 = Utf8                1 hour
  #227 = Utf8                1 days
  #228 = Utf8                1 day
  #229 = NameAndType        #287:#278     // trim:()Ljava/lang/String;
  #230 = NameAndType        #288:#289     // getDefault:()Ljava/util/TimeZone;
  #231 = NameAndType        #149:#151     // formatPeriod:(JJLjava/lang/String;ZLjava/util/TimeZone;)Ljava/lang/String;
  #232 = Utf8               startMillis must not be greater than endMillis
  #233 = Utf8               java/lang/Object
  #234 = NameAndType        #290:#291     // isTrue:(ZLjava/lang/String;[Ljava/lang/Object;)V
  #235 = NameAndType        #292:#293     // getInstance:(Ljava/util/TimeZone;)Ljava/util/Calendar;
  #236 = Utf8               java/util/Date
  #237 = NameAndType        #112:#294     // "<init>":(J)V
  #238 = NameAndType        #295:#296     // setTime:(Ljava/util/Date;)V
  #239 = Utf8               java/util/Calendar
  #240 = NameAndType        #297:#298     // get:(I)I
  #241 = NameAndType        #106:#105     // M:Ljava/lang/Object;
  #242 = NameAndType        #299:#298     // getActualMaximum:(I)I
  #243 = NameAndType        #300:#301     // add:(II)V
  #244 = NameAndType        #104:#105     // y:Ljava/lang/Object;
  #245 = Utf8               java/util/GregorianCalendar
  #246 = NameAndType        #302:#303     // getValue:()Ljava/lang/Object;
  #247 = NameAndType        #304:#282     // getCount:()I
  #248 = NameAndType        #305:#306     // equals:(Ljava/lang/Object;)Z
  #249 = NameAndType        #171:#172     // paddedValue:(JZI)Ljava/lang/String;
  #250 = NameAndType        #111:#105     // S:Ljava/lang/Object;
  #251 = Class              #307          // java/lang/Math
  #252 = NameAndType        #308:#309     // max:(II)I
  #253 = NameAndType        #277:#120     // toString:(J)Ljava/lang/String;
  #254 = NameAndType        #310:#311     // leftPad:(Ljava/lang/String;IC)Ljava/lang/String;
  #255 = Utf8               java/util/ArrayList
  #256 = NameAndType        #112:#312     // "<init>":(I)V
  #257 = NameAndType        #313:#314     // charAt:(I)C
  #258 = NameAndType        #275:#315     // append:(C)Ljava/lang/StringBuilder;
  #259 = Utf8               org/apache/commons/lang3/time/DurationFormatUtils$Token
  #260 = NameAndType        #112:#316     // "<init>":(Ljava/lang/Object;)V
  #261 = NameAndType        #300:#306     // add:(Ljava/lang/Object;)Z
  #262 = NameAndType        #317:#113     // increment:()V
  #263 = Utf8               java/lang/IllegalArgumentException
  #264 = Utf8               Unmatched quote in format:
  #265 = NameAndType        #112:#318     // "<init>":(Ljava/lang/String;)V
  #266 = NameAndType        #319:#282     // size:()I
  #267 = NameAndType        #320:#321     // toArray:([Ljava/lang/Object;)[Ljava/lang/Object;
  #268 = Utf8               java/lang/String
  #269 = Utf8               java/util/TimeZone
  #270 = Utf8               org/apache/commons/lang3/Validate
  #271 = Utf8               inclusiveBetween
  #272 = Utf8               (JJJLjava/lang/String;)V
  #273 = Utf8               containsTokenWithValue
  #274 = Utf8               ([Lorg/apache/commons/lang3/time/DurationFormatUtils$Token;Ljava/lang/Object;)Z
  #275 = Utf8               append
  #276 = Utf8               (Ljava/lang/String;)Ljava/lang/StringBuilder;
  #277 = Utf8               toString
  #278 = Utf8               ()Ljava/lang/String;
  #279 = Utf8               replaceOnce
  #280 = Utf8               (Ljava/lang/String;Ljava/lang/String;Ljava/lang/String;)Ljava/lang/String;
  #281 = Utf8               length
  #282 = Utf8               ()I
  #283 = Utf8               isEmpty
  #284 = Utf8               ()Z
  #285 = Utf8               substring
  #286 = Utf8               (I)Ljava/lang/String;
  #287 = Utf8               trim
  #288 = Utf8               getDefault
  #289 = Utf8               ()Ljava/util/TimeZone;
  #290 = Utf8               isTrue
  #291 = Utf8               (ZLjava/lang/String;[Ljava/lang/Object;)V
  #292 = Utf8               getInstance
  #293 = Utf8               (Ljava/util/TimeZone;)Ljava/util/Calendar;
  #294 = Utf8               (J)V
  #295 = Utf8               setTime
  #296 = Utf8               (Ljava/util/Date;)V
  #297 = Utf8               get
  #298 = Utf8               (I)I
  #299 = Utf8               getActualMaximum
  #300 = Utf8               add
  #301 = Utf8               (II)V
  #302 = Utf8               getValue
  #303 = Utf8               ()Ljava/lang/Object;
  #304 = Utf8               getCount
  #305 = Utf8               equals
  #306 = Utf8               (Ljava/lang/Object;)Z
  #307 = Utf8               java/lang/Math
  #308 = Utf8               max
  #309 = Utf8               (II)I
  #310 = Utf8               leftPad
  #311 = Utf8               (Ljava/lang/String;IC)Ljava/lang/String;
  #312 = Utf8               (I)V
  #313 = Utf8               charAt
  #314 = Utf8               (I)C
  #315 = Utf8               (C)Ljava/lang/StringBuilder;
  #316 = Utf8               (Ljava/lang/Object;)V
  #317 = Utf8               increment
  #318 = Utf8               (Ljava/lang/String;)V
  #319 = Utf8               size
  #320 = Utf8               toArray
  #321 = Utf8               ([Ljava/lang/Object;)[Ljava/lang/Object;
{
  public static final java.lang.String ISO_EXTENDED_FORMAT_PATTERN;
    descriptor: Ljava/lang/String;
    flags: (0x0019) ACC_PUBLIC, ACC_STATIC, ACC_FINAL
    ConstantValue: String \'P\'yyyy\'Y\'M\'M\'d\'DT\'H\'H\'m\'M\'s.SSS\'S\'

  static final java.lang.Object y;
    descriptor: Ljava/lang/Object;
    flags: (0x0018) ACC_STATIC, ACC_FINAL

  static final java.lang.Object M;
    descriptor: Ljava/lang/Object;
    flags: (0x0018) ACC_STATIC, ACC_FINAL

  static final java.lang.Object d;
    descriptor: Ljava/lang/Object;
    flags: (0x0018) ACC_STATIC, ACC_FINAL

  static final java.lang.Object H;
    descriptor: Ljava/lang/Object;
    flags: (0x0018) ACC_STATIC, ACC_FINAL

  static final java.lang.Object m;
    descriptor: Ljava/lang/Object;
    flags: (0x0018) ACC_STATIC, ACC_FINAL

  static final java.lang.Object s;
    descriptor: Ljava/lang/Object;
    flags: (0x0018) ACC_STATIC, ACC_FINAL

  static final java.lang.Object S;
    descriptor: Ljava/lang/Object;
    flags: (0x0018) ACC_STATIC, ACC_FINAL

  public org.apache.commons.lang3.time.DurationFormatUtils();
    descriptor: ()V
    flags: (0x0001) ACC_PUBLIC
    Code:
      stack=1, locals=1, args_size=1
         0: aload_0
         1: invokespecial #1                  // Method java/lang/Object."<init>":()V
         4: return
      LineNumberTable:
        line 60: 0
        line 61: 4
      LocalVariableTable:
        Start  Length  Slot  Name   Signature
            0       5     0  this   Lorg/apache/commons/lang3/time/DurationFormatUtils;

  public static java.lang.String formatDurationHMS(long);
    descriptor: (J)Ljava/lang/String;
    flags: (0x0009) ACC_PUBLIC, ACC_STATIC
    Code:
      stack=3, locals=2, args_size=1
         0: lload_0
         1: ldc           #2                  // String HH:mm:ss.SSS
         3: invokestatic  #3                  // Method formatDuration:(JLjava/lang/String;)Ljava/lang/String;
         6: areturn
      LineNumberTable:
        line 83: 0
      LocalVariableTable:
        Start  Length  Slot  Name   Signature
            0       7     0 durationMillis   J

  public static java.lang.String formatDurationISO(long);
    descriptor: (J)Ljava/lang/String;
    flags: (0x0009) ACC_PUBLIC, ACC_STATIC
    Code:
      stack=4, locals=2, args_size=1
         0: lload_0
         1: ldc           #5                  // String \'P\'yyyy\'Y\'M\'M\'d\'DT\'H\'H\'m\'M\'s.SSS\'S\'
         3: iconst_0
         4: invokestatic  #6                  // Method formatDuration:(JLjava/lang/String;Z)Ljava/lang/String;
         7: areturn
      LineNumberTable:
        line 99: 0
      LocalVariableTable:
        Start  Length  Slot  Name   Signature
            0       8     0 durationMillis   J

  public static java.lang.String formatDuration(long, java.lang.String);
    descriptor: (JLjava/lang/String;)Ljava/lang/String;
    flags: (0x0009) ACC_PUBLIC, ACC_STATIC
    Code:
      stack=4, locals=3, args_size=2
         0: lload_0
         1: aload_2
         2: iconst_1
         3: invokestatic  #6                  // Method formatDuration:(JLjava/lang/String;Z)Ljava/lang/String;
         6: areturn
      LineNumberTable:
        line 114: 0
      LocalVariableTable:
        Start  Length  Slot  Name   Signature
            0       7     0 durationMillis   J
            0       7     2 format   Ljava/lang/String;

  public static java.lang.String formatDuration(long, java.lang.String, boolean);
    descriptor: (JLjava/lang/String;Z)Ljava/lang/String;
    flags: (0x0009) ACC_PUBLIC, ACC_STATIC
    Code:
      stack=16, locals=15, args_size=3
         0: lconst_0
         1: ldc2_w        #8                  // long 9223372036854775807l
         4: lload_0
         5: ldc           #10                 // String durationMillis must not be negative
         7: invokestatic  #11                 // Method org/apache/commons/lang3/Validate.inclusiveBetween:(JJJLjava/lang/String;)V
        10: aload_2
        11: invokestatic  #12                 // Method lexx:(Ljava/lang/String;)[Lorg/apache/commons/lang3/time/DurationFormatUtils$Token;
        14: astore        4
        16: lconst_0
        17: lstore        5
        19: lconst_0
        20: lstore        7
        22: lconst_0
        23: lstore        9
        25: lconst_0
        26: lstore        11
        28: lload_0
        29: lstore        13
        31: aload         4
        33: getstatic     #13                 // Field d:Ljava/lang/Object;
        36: invokestatic  #14                 // Method org/apache/commons/lang3/time/DurationFormatUtils$Token.containsTokenWithValue:([Lorg/apache/commons/lang3/time/DurationFormatUtils$Token;Ljava/lang/Object;)Z
        39: ifeq          61
        42: lload         13
        44: ldc2_w        #16                 // long 86400000l
        47: ldiv
        48: lstore        5
        50: lload         13
        52: lload         5
        54: ldc2_w        #16                 // long 86400000l
        57: lmul
        58: lsub
        59: lstore        13
        61: aload         4
        63: getstatic     #18                 // Field H:Ljava/lang/Object;
        66: invokestatic  #14                 // Method org/apache/commons/lang3/time/DurationFormatUtils$Token.containsTokenWithValue:([Lorg/apache/commons/lang3/time/DurationFormatUtils$Token;Ljava/lang/Object;)Z
        69: ifeq          91
        72: lload         13
        74: ldc2_w        #19                 // long 3600000l
        77: ldiv
        78: lstore        7
        80: lload         13
        82: lload         7
        84: ldc2_w        #19                 // long 3600000l
        87: lmul
        88: lsub
        89: lstore        13
        91: aload         4
        93: getstatic     #21                 // Field m:Ljava/lang/Object;
        96: invokestatic  #14                 // Method org/apache/commons/lang3/time/DurationFormatUtils$Token.containsTokenWithValue:([Lorg/apache/commons/lang3/time/DurationFormatUtils$Token;Ljava/lang/Object;)Z
        99: ifeq          121
       102: lload         13
       104: ldc2_w        #22                 // long 60000l
       107: ldiv
       108: lstore        9
       110: lload         13
       112: lload         9
       114: ldc2_w        #22                 // long 60000l
       117: lmul
       118: lsub
       119: lstore        13
       121: aload         4
       123: getstatic     #24                 // Field s:Ljava/lang/Object;
       126: invokestatic  #14                 // Method org/apache/commons/lang3/time/DurationFormatUtils$Token.containsTokenWithValue:([Lorg/apache/commons/lang3/time/DurationFormatUtils$Token;Ljava/lang/Object;)Z
       129: ifeq          151
       132: lload         13
       134: ldc2_w        #25                 // long 1000l
       137: ldiv
       138: lstore        11
       140: lload         13
       142: lload         11
       144: ldc2_w        #25                 // long 1000l
       147: lmul
       148: lsub
       149: lstore        13
       151: aload         4
       153: lconst_0
       154: lconst_0
       155: lload         5
       157: lload         7
       159: lload         9
       161: lload         11
       163: lload         13
       165: iload_3
       166: invokestatic  #27                 // Method format:([Lorg/apache/commons/lang3/time/DurationFormatUtils$Token;JJJJJJJZ)Ljava/lang/String;
       169: areturn
      LineNumberTable:
        line 131: 0
        line 133: 10
        line 135: 16
        line 136: 19
        line 137: 22
        line 138: 25
        line 139: 28
        line 141: 31
        line 142: 42
        line 143: 50
        line 145: 61
        line 146: 72
        line 147: 80
        line 149: 91
        line 150: 102
        line 151: 110
        line 153: 121
        line 154: 132
        line 155: 140
        line 158: 151
      LocalVariableTable:
        Start  Length  Slot  Name   Signature
            0     170     0 durationMillis   J
            0     170     2 format   Ljava/lang/String;
            0     170     3 padWithZeros   Z
           16     154     4 tokens   [Lorg/apache/commons/lang3/time/DurationFormatUtils$Token;
           19     151     5  days   J
           22     148     7 hours   J
           25     145     9 minutes   J
           28     142    11 seconds   J
           31     139    13 milliseconds   J
      StackMapTable: number_of_entries = 4
        frame_type = 255 /* full_frame */
          offset_delta = 61
          locals = [ long, class java/lang/String, int, class "[Lorg/apache/commons/lang3/time/DurationFormatUtils$Token;", long, long, long, long, long ]
          stack = []
        frame_type = 29 /* same */
        frame_type = 29 /* same */
        frame_type = 29 /* same */

  public static java.lang.String formatDurationWords(long, boolean, boolean);
    descriptor: (JZZ)Ljava/lang/String;
    flags: (0x0009) ACC_PUBLIC, ACC_STATIC
    Code:
      stack=3, locals=6, args_size=3
         0: lload_0
         1: ldc           #28                 // String d\' days \'H\' hours \'m\' minutes \'s\' seconds\'
         3: invokestatic  #3                  // Method formatDuration:(JLjava/lang/String;)Ljava/lang/String;
         6: astore        4
         8: iload_2
         9: ifeq          145
        12: new           #29                 // class java/lang/StringBuilder
        15: dup
        16: invokespecial #30                 // Method java/lang/StringBuilder."<init>":()V
        19: ldc           #31                 // String
        21: invokevirtual #32                 // Method java/lang/StringBuilder.append:(Ljava/lang/String;)Ljava/lang/StringBuilder;
        24: aload         4
        26: invokevirtual #32                 // Method java/lang/StringBuilder.append:(Ljava/lang/String;)Ljava/lang/StringBuilder;
        29: invokevirtual #33                 // Method java/lang/StringBuilder.toString:()Ljava/lang/String;
        32: astore        4
        34: aload         4
        36: ldc           #34                 // String  0 days
        38: ldc           #36                 // String
        40: invokestatic  #37                 // Method org/apache/commons/lang3/StringUtils.replaceOnce:(Ljava/lang/String;Ljava/lang/String;Ljava/lang/String;)Ljava/lang/String;
        43: astore        5
        45: aload         5
        47: invokevirtual #38                 // Method java/lang/String.length:()I
        50: aload         4
        52: invokevirtual #38                 // Method java/lang/String.length:()I
        55: if_icmpeq     129
        58: aload         5
        60: astore        4
        62: aload         4
        64: ldc           #39                 // String  0 hours
        66: ldc           #36                 // String
        68: invokestatic  #37                 // Method org/apache/commons/lang3/StringUtils.replaceOnce:(Ljava/lang/String;Ljava/lang/String;Ljava/lang/String;)Ljava/lang/String;
        71: astore        5
        73: aload         5
        75: invokevirtual #38                 // Method java/lang/String.length:()I
        78: aload         4
        80: invokevirtual #38                 // Method java/lang/String.length:()I
        83: if_icmpeq     129
        86: aload         5
        88: astore        4
        90: aload         4
        92: ldc           #40                 // String  0 minutes
        94: ldc           #36                 // String
        96: invokestatic  #37                 // Method org/apache/commons/lang3/StringUtils.replaceOnce:(Ljava/lang/String;Ljava/lang/String;Ljava/lang/String;)Ljava/lang/String;
        99: astore        5
       101: aload         5
       103: astore        4
       105: aload         5
       107: invokevirtual #38                 // Method java/lang/String.length:()I
       110: aload         4
       112: invokevirtual #38                 // Method java/lang/String.length:()I
       115: if_icmpeq     129
       118: aload         5
       120: ldc           #41                 // String  0 seconds
       122: ldc           #36                 // String
       124: invokestatic  #37                 // Method org/apache/commons/lang3/StringUtils.replaceOnce:(Ljava/lang/String;Ljava/lang/String;Ljava/lang/String;)Ljava/lang/String;
       127: astore        4
       129: aload         4
       131: invokevirtual #42                 // Method java/lang/String.isEmpty:()Z
       134: ifne          145
       137: aload         4
       139: iconst_1
       140: invokevirtual #43                 // Method java/lang/String.substring:(I)Ljava/lang/String;
       143: astore        4
       145: iload_3
       146: ifeq          240
       149: aload         4
       151: ldc           #41                 // String  0 seconds
       153: ldc           #36                 // String
       155: invokestatic  #37                 // Method org/apache/commons/lang3/StringUtils.replaceOnce:(Ljava/lang/String;Ljava/lang/String;Ljava/lang/String;)Ljava/lang/String;
       158: astore        5
       160: aload         5
       162: invokevirtual #38                 // Method java/lang/String.length:()I
       165: aload         4
       167: invokevirtual #38                 // Method java/lang/String.length:()I
       170: if_icmpeq     240
       173: aload         5
       175: astore        4
       177: aload         4
       179: ldc           #40                 // String  0 minutes
       181: ldc           #36                 // String
       183: invokestatic  #37                 // Method org/apache/commons/lang3/StringUtils.replaceOnce:(Ljava/lang/String;Ljava/lang/String;Ljava/lang/String;)Ljava/lang/String;
       186: astore        5
       188: aload         5
       190: invokevirtual #38                 // Method java/lang/String.length:()I
       193: aload         4
       195: invokevirtual #38                 // Method java/lang/String.length:()I
       198: if_icmpeq     240
       201: aload         5
       203: astore        4
       205: aload         4
       207: ldc           #39                 // String  0 hours
       209: ldc           #36                 // String
       211: invokestatic  #37                 // Method org/apache/commons/lang3/StringUtils.replaceOnce:(Ljava/lang/String;Ljava/lang/String;Ljava/lang/String;)Ljava/lang/String;
       214: astore        5
       216: aload         5
       218: invokevirtual #38                 // Method java/lang/String.length:()I
       221: aload         4
       223: invokevirtual #38                 // Method java/lang/String.length:()I
       226: if_icmpeq     240
       229: aload         5
       231: ldc           #34                 // String  0 days
       233: ldc           #36                 // String
       235: invokestatic  #37                 // Method org/apache/commons/lang3/StringUtils.replaceOnce:(Ljava/lang/String;Ljava/lang/String;Ljava/lang/String;)Ljava/lang/String;
       238: astore        4
       240: new           #29                 // class java/lang/StringBuilder
       243: dup
       244: invokespecial #30                 // Method java/lang/StringBuilder."<init>":()V
       247: ldc           #31                 // String
       249: invokevirtual #32                 // Method java/lang/StringBuilder.append:(Ljava/lang/String;)Ljava/lang/StringBuilder;
       252: aload         4
       254: invokevirtual #32                 // Method java/lang/StringBuilder.append:(Ljava/lang/String;)Ljava/lang/StringBuilder;
       257: invokevirtual #33                 // Method java/lang/StringBuilder.toString:()Ljava/lang/String;
       260: astore        4
       262: aload         4
       264: ldc           #44                 // String  1 seconds
       266: ldc           #45                 // String  1 second
       268: invokestatic  #37                 // Method org/apache/commons/lang3/StringUtils.replaceOnce:(Ljava/lang/String;Ljava/lang/String;Ljava/lang/String;)Ljava/lang/String;
       271: astore        4
       273: aload         4
       275: ldc           #46                 // String  1 minutes
       277: ldc           #47                 // String  1 minute
       279: invokestatic  #37                 // Method org/apache/commons/lang3/StringUtils.replaceOnce:(Ljava/lang/String;Ljava/lang/String;Ljava/lang/String;)Ljava/lang/String;
       282: astore        4
       284: aload         4
       286: ldc           #48                 // String  1 hours
       288: ldc           #49                 // String  1 hour
       290: invokestatic  #37                 // Method org/apache/commons/lang3/StringUtils.replaceOnce:(Ljava/lang/String;Ljava/lang/String;Ljava/lang/String;)Ljava/lang/String;
       293: astore        4
       295: aload         4
       297: ldc           #50                 // String  1 days
       299: ldc           #51                 // String  1 day
       301: invokestatic  #37                 // Method org/apache/commons/lang3/StringUtils.replaceOnce:(Ljava/lang/String;Ljava/lang/String;Ljava/lang/String;)Ljava/lang/String;
       304: astore        4
       306: aload         4
       308: invokevirtual #52                 // Method java/lang/String.trim:()Ljava/lang/String;
       311: areturn
      LineNumberTable:
        line 181: 0
        line 182: 8
        line 184: 12
        line 185: 34
        line 186: 45
        line 187: 58
        line 188: 62
        line 189: 73
        line 190: 86
        line 191: 90
        line 192: 101
        line 193: 105
        line 194: 118
        line 198: 129
        line 200: 137
        line 203: 145
        line 204: 149
        line 205: 160
        line 206: 173
        line 207: 177
        line 208: 188
        line 209: 201
        line 210: 205
        line 211: 216
        line 212: 229
        line 218: 240
        line 219: 262
        line 220: 273
        line 221: 284
        line 222: 295
        line 223: 306
      LocalVariableTable:
        Start  Length  Slot  Name   Signature
           45     100     5   tmp   Ljava/lang/String;
          160      80     5   tmp   Ljava/lang/String;
            0     312     0 durationMillis   J
            0     312     2 suppressLeadingZeroElements   Z
            0     312     3 suppressTrailingZeroElements   Z
            8     304     4 duration   Ljava/lang/String;
      StackMapTable: number_of_entries = 3
        frame_type = 253 /* append */
          offset_delta = 129
          locals = [ class java/lang/String, class java/lang/String ]
        frame_type = 250 /* chop */
          offset_delta = 15
        frame_type = 251 /* same_frame_extended */
          offset_delta = 94

  public static java.lang.String formatPeriodISO(long, long);
    descriptor: (JJ)Ljava/lang/String;
    flags: (0x0009) ACC_PUBLIC, ACC_STATIC
    Code:
      stack=7, locals=4, args_size=2
         0: lload_0
         1: lload_2
         2: ldc           #5                  // String \'P\'yyyy\'Y\'M\'M\'d\'DT\'H\'H\'m\'M\'s.SSS\'S\'
         4: iconst_0
         5: invokestatic  #53                 // Method java/util/TimeZone.getDefault:()Ljava/util/TimeZone;
         8: invokestatic  #54                 // Method formatPeriod:(JJLjava/lang/String;ZLjava/util/TimeZone;)Ljava/lang/String;
        11: areturn
      LineNumberTable:
        line 238: 0
      LocalVariableTable:
        Start  Length  Slot  Name   Signature
            0      12     0 startMillis   J
            0      12     2 endMillis   J

  public static java.lang.String formatPeriod(long, long, java.lang.String);
    descriptor: (JJLjava/lang/String;)Ljava/lang/String;
    flags: (0x0009) ACC_PUBLIC, ACC_STATIC
    Code:
      stack=7, locals=5, args_size=3
         0: lload_0
         1: lload_2
         2: aload         4
         4: iconst_1
         5: invokestatic  #53                 // Method java/util/TimeZone.getDefault:()Ljava/util/TimeZone;
         8: invokestatic  #54                 // Method formatPeriod:(JJLjava/lang/String;ZLjava/util/TimeZone;)Ljava/lang/String;
        11: areturn
      LineNumberTable:
        line 252: 0
      LocalVariableTable:
        Start  Length  Slot  Name   Signature
            0      12     0 startMillis   J
            0      12     2 endMillis   J
            0      12     4 format   Ljava/lang/String;

  public static java.lang.String formatPeriod(long, long, java.lang.String, boolean, java.util.TimeZone);
    descriptor: (JJLjava/lang/String;ZLjava/util/TimeZone;)Ljava/lang/String;
    flags: (0x0009) ACC_PUBLIC, ACC_STATIC
    Code:
      stack=16, locals=18, args_size=5
         0: lload_0
         1: lload_2
         2: lcmp
         3: ifgt          10
         6: iconst_1
         7: goto          11
        10: iconst_0
        11: ldc           #55                 // String startMillis must not be greater than endMillis
        13: iconst_0
        14: anewarray     #56                 // class java/lang/Object
        17: invokestatic  #57                 // Method org/apache/commons/lang3/Validate.isTrue:(ZLjava/lang/String;[Ljava/lang/Object;)V
        20: aload         4
        22: invokestatic  #12                 // Method lexx:(Ljava/lang/String;)[Lorg/apache/commons/lang3/time/DurationFormatUtils$Token;
        25: astore        7
        27: aload         6
        29: invokestatic  #58                 // Method java/util/Calendar.getInstance:(Ljava/util/TimeZone;)Ljava/util/Calendar;
        32: astore        8
        34: aload         8
        36: new           #59                 // class java/util/Date
        39: dup
        40: lload_0
        41: invokespecial #60                 // Method java/util/Date."<init>":(J)V
        44: invokevirtual #61                 // Method java/util/Calendar.setTime:(Ljava/util/Date;)V
        47: aload         6
        49: invokestatic  #58                 // Method java/util/Calendar.getInstance:(Ljava/util/TimeZone;)Ljava/util/Calendar;
        52: astore        9
        54: aload         9
        56: new           #59                 // class java/util/Date
        59: dup
        60: lload_2
        61: invokespecial #60                 // Method java/util/Date."<init>":(J)V
        64: invokevirtual #61                 // Method java/util/Calendar.setTime:(Ljava/util/Date;)V
        67: aload         9
        69: bipush        14
        71: invokevirtual #63                 // Method java/util/Calendar.get:(I)I
        74: aload         8
        76: bipush        14
        78: invokevirtual #63                 // Method java/util/Calendar.get:(I)I
        81: isub
        82: istore        10
        84: aload         9
        86: bipush        13
        88: invokevirtual #63                 // Method java/util/Calendar.get:(I)I
        91: aload         8
        93: bipush        13
        95: invokevirtual #63                 // Method java/util/Calendar.get:(I)I
        98: isub
        99: istore        11
       101: aload         9
       103: bipush        12
       105: invokevirtual #63                 // Method java/util/Calendar.get:(I)I
       108: aload         8
       110: bipush        12
       112: invokevirtual #63                 // Method java/util/Calendar.get:(I)I
       115: isub
       116: istore        12
       118: aload         9
       120: bipush        11
       122: invokevirtual #63                 // Method java/util/Calendar.get:(I)I
       125: aload         8
       127: bipush        11
       129: invokevirtual #63                 // Method java/util/Calendar.get:(I)I
       132: isub
       133: istore        13
       135: aload         9
       137: iconst_5
       138: invokevirtual #63                 // Method java/util/Calendar.get:(I)I
       141: aload         8
       143: iconst_5
       144: invokevirtual #63                 // Method java/util/Calendar.get:(I)I
       147: isub
       148: istore        14
       150: aload         9
       152: iconst_2
       153: invokevirtual #63                 // Method java/util/Calendar.get:(I)I
       156: aload         8
       158: iconst_2
       159: invokevirtual #63                 // Method java/util/Calendar.get:(I)I
       162: isub
       163: istore        15
       165: aload         9
       167: iconst_1
       168: invokevirtual #63                 // Method java/util/Calendar.get:(I)I
       171: aload         8
       173: iconst_1
       174: invokevirtual #63                 // Method java/util/Calendar.get:(I)I
       177: isub
       178: istore        16
       180: iload         10
       182: ifge          197
       185: iinc_w        10, 1000
       191: iinc          11, -1
       194: goto          180
       197: iload         11
       199: ifge          211
       202: iinc          11, 60
       205: iinc          12, -1
       208: goto          197
       211: iload         12
       213: ifge          225
       216: iinc          12, 60
       219: iinc          13, -1
       222: goto          211
       225: iload         13
       227: ifge          239
       230: iinc          13, 24
       233: iinc          14, -1
       236: goto          225
       239: aload         7
       241: getstatic     #64                 // Field M:Ljava/lang/Object;
       244: invokestatic  #14                 // Method org/apache/commons/lang3/time/DurationFormatUtils$Token.containsTokenWithValue:([Lorg/apache/commons/lang3/time/DurationFormatUtils$Token;Ljava/lang/Object;)Z
       247: ifeq          330
       250: iload         14
       252: ifge          279
       255: iload         14
       257: aload         8
       259: iconst_5
       260: invokevirtual #65                 // Method java/util/Calendar.getActualMaximum:(I)I
       263: iadd
       264: istore        14
       266: iinc          15, -1
       269: aload         8
       271: iconst_2
       272: iconst_1
       273: invokevirtual #66                 // Method java/util/Calendar.add:(II)V
       276: goto          250
       279: iload         15
       281: ifge          293
       284: iinc          15, 12
       287: iinc          16, -1
       290: goto          279
       293: aload         7
       295: getstatic     #67                 // Field y:Ljava/lang/Object;
       298: invokestatic  #14                 // Method org/apache/commons/lang3/time/DurationFormatUtils$Token.containsTokenWithValue:([Lorg/apache/commons/lang3/time/DurationFormatUtils$Token;Ljava/lang/Object;)Z
       301: ifne          513
       304: iload         16
       306: ifeq          513
       309: iload         16
       311: ifeq          513
       314: iload         15
       316: bipush        12
       318: iload         16
       320: imul
       321: iadd
       322: istore        15
       324: iconst_0
       325: istore        16
       327: goto          309
       330: aload         7
       332: getstatic     #67                 // Field y:Ljava/lang/Object;
       335: invokestatic  #14                 // Method org/apache/commons/lang3/time/DurationFormatUtils$Token.containsTokenWithValue:([Lorg/apache/commons/lang3/time/DurationFormatUtils$Token;Ljava/lang/Object;)Z
       338: ifne          445
       341: aload         9
       343: iconst_1
       344: invokevirtual #63                 // Method java/util/Calendar.get:(I)I
       347: istore        17
       349: iload         15
       351: ifge          357
       354: iinc          17, -1
       357: aload         8
       359: iconst_1
       360: invokevirtual #63                 // Method java/util/Calendar.get:(I)I
       363: iload         17
       365: if_icmpeq     442
       368: iload         14
       370: aload         8
       372: bipush        6
       374: invokevirtual #65                 // Method java/util/Calendar.getActualMaximum:(I)I
       377: aload         8
       379: bipush        6
       381: invokevirtual #63                 // Method java/util/Calendar.get:(I)I
       384: isub
       385: iadd
       386: istore        14
       388: aload         8
       390: instanceof    #68                 // class java/util/GregorianCalendar
       393: ifeq          420
       396: aload         8
       398: iconst_2
       399: invokevirtual #63                 // Method java/util/Calendar.get:(I)I
       402: iconst_1
       403: if_icmpne     420
       406: aload         8
       408: iconst_5
       409: invokevirtual #63                 // Method java/util/Calendar.get:(I)I
       412: bipush        29
       414: if_icmpne     420
       417: iinc          14, 1
       420: aload         8
       422: iconst_1
       423: iconst_1
       424: invokevirtual #66                 // Method java/util/Calendar.add:(II)V
       427: iload         14
       429: aload         8
       431: bipush        6
       433: invokevirtual #63                 // Method java/util/Calendar.get:(I)I
       436: iadd
       437: istore        14
       439: goto          357
       442: iconst_0
       443: istore        16
       445: aload         8
       447: iconst_2
       448: invokevirtual #63                 // Method java/util/Calendar.get:(I)I
       451: aload         9
       453: iconst_2
       454: invokevirtual #63                 // Method java/util/Calendar.get:(I)I
       457: if_icmpeq     481
       460: iload         14
       462: aload         8
       464: iconst_5
       465: invokevirtual #65                 // Method java/util/Calendar.getActualMaximum:(I)I
       468: iadd
       469: istore        14
       471: aload         8
       473: iconst_2
       474: iconst_1
       475: invokevirtual #66                 // Method java/util/Calendar.add:(II)V
       478: goto          445
       481: iconst_0
       482: istore        15
       484: iload         14
       486: ifge          513
       489: iload         14
       491: aload         8
       493: iconst_5
       494: invokevirtual #65                 // Method java/util/Calendar.getActualMaximum:(I)I
       497: iadd
       498: istore        14
       500: iinc          15, -1
       503: aload         8
       505: iconst_2
       506: iconst_1
       507: invokevirtual #66                 // Method java/util/Calendar.add:(II)V
       510: goto          484
       513: aload         7
       515: getstatic     #13                 // Field d:Ljava/lang/Object;
       518: invokestatic  #14                 // Method org/apache/commons/lang3/time/DurationFormatUtils$Token.containsTokenWithValue:([Lorg/apache/commons/lang3/time/DurationFormatUtils$Token;Ljava/lang/Object;)Z
       521: ifne          537
       524: iload         13
       526: bipush        24
       528: iload         14
       530: imul
       531: iadd
       532: istore        13
       534: iconst_0
       535: istore        14
       537: aload         7
       539: getstatic     #18                 // Field H:Ljava/lang/Object;
       542: invokestatic  #14                 // Method org/apache/commons/lang3/time/DurationFormatUtils$Token.containsTokenWithValue:([Lorg/apache/commons/lang3/time/DurationFormatUtils$Token;Ljava/lang/Object;)Z
       545: ifne          561
       548: iload         12
       550: bipush        60
       552: iload         13
       554: imul
       555: iadd
       556: istore        12
       558: iconst_0
       559: istore        13
       561: aload         7
       563: getstatic     #21                 // Field m:Ljava/lang/Object;
       566: invokestatic  #14                 // Method org/apache/commons/lang3/time/DurationFormatUtils$Token.containsTokenWithValue:([Lorg/apache/commons/lang3/time/DurationFormatUtils$Token;Ljava/lang/Object;)Z
       569: ifne          585
       572: iload         11
       574: bipush        60
       576: iload         12
       578: imul
       579: iadd
       580: istore        11
       582: iconst_0
       583: istore        12
       585: aload         7
       587: getstatic     #24                 // Field s:Ljava/lang/Object;
       590: invokestatic  #14                 // Method org/apache/commons/lang3/time/DurationFormatUtils$Token.containsTokenWithValue:([Lorg/apache/commons/lang3/time/DurationFormatUtils$Token;Ljava/lang/Object;)Z
       593: ifne          610
       596: iload         10
       598: sipush        1000
       601: iload         11
       603: imul
       604: iadd
       605: istore        10
       607: iconst_0
       608: istore        11
       610: aload         7
       612: iload         16
       614: i2l
       615: iload         15
       617: i2l
       618: iload         14
       620: i2l
       621: iload         13
       623: i2l
       624: iload         12
       626: i2l
       627: iload         11
       629: i2l
       630: iload         10
       632: i2l
       633: iload         5
       635: invokestatic  #27                 // Method format:([Lorg/apache/commons/lang3/time/DurationFormatUtils$Token;JJJJJJJZ)Ljava/lang/String;
       638: areturn
      LineNumberTable:
        line 281: 0
        line 290: 20
        line 294: 27
        line 295: 34
        line 296: 47
        line 297: 54
        line 300: 67
        line 301: 84
        line 302: 101
        line 303: 118
        line 304: 135
        line 305: 150
        line 306: 165
        line 309: 180
        line 310: 185
        line 311: 191
        line 313: 197
        line 314: 202
        line 315: 205
        line 317: 211
        line 318: 216
        line 319: 219
        line 321: 225
        line 322: 230
        line 323: 233
        line 326: 239
        line 327: 250
        line 328: 255
        line 329: 266
        line 330: 269
        line 333: 279
        line 334: 284
        line 335: 287
        line 338: 293
        line 339: 309
        line 340: 314
        line 341: 324
        line 347: 330
        line 348: 341
        line 349: 349
        line 351: 354
        line 354: 357
        line 355: 368
        line 358: 388
        line 359: 399
        line 360: 409
        line 361: 417
        line 364: 420
        line 366: 427
        line 369: 442
        line 372: 445
        line 373: 460
        line 374: 471
        line 377: 481
        line 379: 484
        line 380: 489
        line 381: 500
        line 382: 503
        line 391: 513
        line 392: 524
        line 393: 534
        line 395: 537
        line 396: 548
        line 397: 558
        line 399: 561
        line 400: 572
        line 401: 582
        line 403: 585
        line 404: 596
        line 405: 607
        line 408: 610
      LocalVariableTable:
        Start  Length  Slot  Name   Signature
          349      96    17 target   I
            0     639     0 startMillis   J
            0     639     2 endMillis   J
            0     639     4 format   Ljava/lang/String;
            0     639     5 padWithZeros   Z
            0     639     6 timezone   Ljava/util/TimeZone;
           27     612     7 tokens   [Lorg/apache/commons/lang3/time/DurationFormatUtils$Token;
           34     605     8 start   Ljava/util/Calendar;
           54     585     9   end   Ljava/util/Calendar;
           84     555    10 milliseconds   I
          101     538    11 seconds   I
          118     521    12 minutes   I
          135     504    13 hours   I
          150     489    14  days   I
          165     474    15 months   I
          180     459    16 years   I
      StackMapTable: number_of_entries = 23
        frame_type = 10 /* same */
        frame_type = 64 /* same_locals_1_stack_item */
          stack = [ int ]
        frame_type = 255 /* full_frame */
          offset_delta = 168
          locals = [ long, long, class java/lang/String, int, class java/util/TimeZone, class "[Lorg/apache/commons/lang3/time/DurationFormatUtils$Token;", class java/util/Calendar, class java/util/Calendar, int, int, int, int, int, int, int ]
          stack = []
        frame_type = 16 /* same */
        frame_type = 13 /* same */
        frame_type = 13 /* same */
        frame_type = 13 /* same */
        frame_type = 10 /* same */
        frame_type = 28 /* same */
        frame_type = 13 /* same */
        frame_type = 15 /* same */
        frame_type = 20 /* same */
        frame_type = 252 /* append */
          offset_delta = 26
          locals = [ int ]
        frame_type = 62 /* same */
        frame_type = 21 /* same */
        frame_type = 250 /* chop */
          offset_delta = 2
        frame_type = 35 /* same */
        frame_type = 2 /* same */
        frame_type = 28 /* same */
        frame_type = 23 /* same */
        frame_type = 23 /* same */
        frame_type = 23 /* same */
        frame_type = 24 /* same */

  static java.lang.String format(org.apache.commons.lang3.time.DurationFormatUtils$Token[], long, long, long, long, long, long, long, boolean);
    descriptor: ([Lorg/apache/commons/lang3/time/DurationFormatUtils$Token;JJJJJJJZ)Ljava/lang/String;
    flags: (0x0008) ACC_STATIC
    Code:
      stack=5, locals=25, args_size=9
         0: new           #29                 // class java/lang/StringBuilder
         3: dup
         4: invokespecial #30                 // Method java/lang/StringBuilder."<init>":()V
         7: astore        16
         9: iconst_0
        10: istore        17
        12: aload_0
        13: astore        18
        15: aload         18
        17: arraylength
        18: istore        19
        20: iconst_0
        21: istore        20
        23: iload         20
        25: iload         19
        27: if_icmpge     337
        30: aload         18
        32: iload         20
        34: aaload
        35: astore        21
        37: aload         21
        39: invokevirtual #69                 // Method org/apache/commons/lang3/time/DurationFormatUtils$Token.getValue:()Ljava/lang/Object;
        42: astore        22
        44: aload         21
        46: invokevirtual #70                 // Method org/apache/commons/lang3/time/DurationFormatUtils$Token.getCount:()I
        49: istore        23
        51: aload         22
        53: instanceof    #29                 // class java/lang/StringBuilder
        56: ifeq          73
        59: aload         16
        61: aload         22
        63: invokevirtual #71                 // Method java/lang/Object.toString:()Ljava/lang/String;
        66: invokevirtual #32                 // Method java/lang/StringBuilder.append:(Ljava/lang/String;)Ljava/lang/StringBuilder;
        69: pop
        70: goto          331
        73: aload         22
        75: getstatic     #67                 // Field y:Ljava/lang/Object;
        78: invokevirtual #72                 // Method java/lang/Object.equals:(Ljava/lang/Object;)Z
        81: ifeq          104
        84: aload         16
        86: lload_1
        87: iload         15
        89: iload         23
        91: invokestatic  #73                 // Method paddedValue:(JZI)Ljava/lang/String;
        94: invokevirtual #32                 // Method java/lang/StringBuilder.append:(Ljava/lang/String;)Ljava/lang/StringBuilder;
        97: pop
        98: iconst_0
        99: istore        17
       101: goto          331
       104: aload         22
       106: getstatic     #64                 // Field M:Ljava/lang/Object;
       109: invokevirtual #72                 // Method java/lang/Object.equals:(Ljava/lang/Object;)Z
       112: ifeq          135
       115: aload         16
       117: lload_3
       118: iload         15
       120: iload         23
       122: invokestatic  #73                 // Method paddedValue:(JZI)Ljava/lang/String;
       125: invokevirtual #32                 // Method java/lang/StringBuilder.append:(Ljava/lang/String;)Ljava/lang/StringBuilder;
       128: pop
       129: iconst_0
       130: istore        17
       132: goto          331
       135: aload         22
       137: getstatic     #13                 // Field d:Ljava/lang/Object;
       140: invokevirtual #72                 // Method java/lang/Object.equals:(Ljava/lang/Object;)Z
       143: ifeq          167
       146: aload         16
       148: lload         5
       150: iload         15
       152: iload         23
       154: invokestatic  #73                 // Method paddedValue:(JZI)Ljava/lang/String;
       157: invokevirtual #32                 // Method java/lang/StringBuilder.append:(Ljava/lang/String;)Ljava/lang/StringBuilder;
       160: pop
       161: iconst_0
       162: istore        17
       164: goto          331
       167: aload         22
       169: getstatic     #18                 // Field H:Ljava/lang/Object;
       172: invokevirtual #72                 // Method java/lang/Object.equals:(Ljava/lang/Object;)Z
       175: ifeq          199
       178: aload         16
       180: lload         7
       182: iload         15
       184: iload         23
       186: invokestatic  #73                 // Method paddedValue:(JZI)Ljava/lang/String;
       189: invokevirtual #32                 // Method java/lang/StringBuilder.append:(Ljava/lang/String;)Ljava/lang/StringBuilder;
       192: pop
       193: iconst_0
       194: istore        17
       196: goto          331
       199: aload         22
       201: getstatic     #21                 // Field m:Ljava/lang/Object;
       204: invokevirtual #72                 // Method java/lang/Object.equals:(Ljava/lang/Object;)Z
       207: ifeq          231
       210: aload         16
       212: lload         9
       214: iload         15
       216: iload         23
       218: invokestatic  #73                 // Method paddedValue:(JZI)Ljava/lang/String;
       221: invokevirtual #32                 // Method java/lang/StringBuilder.append:(Ljava/lang/String;)Ljava/lang/StringBuilder;
       224: pop
       225: iconst_0
       226: istore        17
       228: goto          331
       231: aload         22
       233: getstatic     #24                 // Field s:Ljava/lang/Object;
       236: invokevirtual #72                 // Method java/lang/Object.equals:(Ljava/lang/Object;)Z
       239: ifeq          263
       242: aload         16
       244: lload         11
       246: iload         15
       248: iload         23
       250: invokestatic  #73                 // Method paddedValue:(JZI)Ljava/lang/String;
       253: invokevirtual #32                 // Method java/lang/StringBuilder.append:(Ljava/lang/String;)Ljava/lang/StringBuilder;
       256: pop
       257: iconst_1
       258: istore        17
       260: goto          331
       263: aload         22
       265: getstatic     #74                 // Field S:Ljava/lang/Object;
       268: invokevirtual #72                 // Method java/lang/Object.equals:(Ljava/lang/Object;)Z
       271: ifeq          331
       274: iload         17
       276: ifeq          313
       279: iload         15
       281: ifeq          293
       284: iconst_3
       285: iload         23
       287: invokestatic  #75                 // Method java/lang/Math.max:(II)I
       290: goto          294
       293: iconst_3
       294: istore        24
       296: aload         16
       298: lload         13
       300: iconst_1
       301: iload         24
       303: invokestatic  #73                 // Method paddedValue:(JZI)Ljava/lang/String;
       306: invokevirtual #32                 // Method java/lang/StringBuilder.append:(Ljava/lang/String;)Ljava/lang/StringBuilder;
       309: pop
       310: goto          328
       313: aload         16
       315: lload         13
       317: iload         15
       319: iload         23
       321: invokestatic  #73                 // Method paddedValue:(JZI)Ljava/lang/String;
       324: invokevirtual #32                 // Method java/lang/StringBuilder.append:(Ljava/lang/String;)Ljava/lang/StringBuilder;
       327: pop
       328: iconst_0
       329: istore        17
       331: iinc          20, 1
       334: goto          23
       337: aload         16
       339: invokevirtual #33                 // Method java/lang/StringBuilder.toString:()Ljava/lang/String;
       342: areturn
      LineNumberTable:
        line 428: 0
        line 429: 9
        line 430: 12
        line 431: 37
        line 432: 44
        line 433: 51
        line 434: 59
        line 436: 73
        line 437: 84
        line 438: 98
        line 439: 104
        line 440: 115
        line 441: 129
        line 442: 135
        line 443: 146
        line 444: 161
        line 445: 167
        line 446: 178
        line 447: 193
        line 448: 199
        line 449: 210
        line 450: 225
        line 451: 231
        line 452: 242
        line 453: 257
        line 454: 263
        line 455: 274
        line 457: 279
        line 458: 296
        line 459: 310
        line 460: 313
        line 462: 328
        line 430: 331
        line 466: 337
      LocalVariableTable:
        Start  Length  Slot  Name   Signature
          296      14    24 width   I
           44     287    22 value   Ljava/lang/Object;
           51     280    23 count   I
           37     294    21 token   Lorg/apache/commons/lang3/time/DurationFormatUtils$Token;
            0     343     0 tokens   [Lorg/apache/commons/lang3/time/DurationFormatUtils$Token;
            0     343     1 years   J
            0     343     3 months   J
            0     343     5  days   J
            0     343     7 hours   J
            0     343     9 minutes   J
            0     343    11 seconds   J
            0     343    13 milliseconds   J
            0     343    15 padWithZeros   Z
            9     334    16 buffer   Ljava/lang/StringBuilder;
           12     331    17 lastOutputSeconds   Z
      StackMapTable: number_of_entries = 14
        frame_type = 255 /* full_frame */
          offset_delta = 23
          locals = [ class "[Lorg/apache/commons/lang3/time/DurationFormatUtils$Token;", long, long, long, long, long, long, long, int, class java/lang/StringBuilder, int, class "[Lorg/apache/commons/lang3/time/DurationFormatUtils$Token;", int, int ]
          stack = []
        frame_type = 254 /* append */
          offset_delta = 49
          locals = [ class org/apache/commons/lang3/time/DurationFormatUtils$Token, class java/lang/Object, int ]
        frame_type = 30 /* same */
        frame_type = 30 /* same */
        frame_type = 31 /* same */
        frame_type = 31 /* same */
        frame_type = 31 /* same */
        frame_type = 31 /* same */
        frame_type = 29 /* same */
        frame_type = 64 /* same_locals_1_stack_item */
          stack = [ int ]
        frame_type = 18 /* same */
        frame_type = 14 /* same */
        frame_type = 248 /* chop */
          offset_delta = 2
        frame_type = 248 /* chop */
          offset_delta = 5

  private static java.lang.String paddedValue(long, boolean, int);
    descriptor: (JZI)Ljava/lang/String;
    flags: (0x000a) ACC_PRIVATE, ACC_STATIC
    Code:
      stack=3, locals=5, args_size=3
         0: lload_0
         1: invokestatic  #76                 // Method java/lang/Long.toString:(J)Ljava/lang/String;
         4: astore        4
         6: iload_2
         7: ifeq          21
        10: aload         4
        12: iload_3
        13: bipush        48
        15: invokestatic  #77                 // Method org/apache/commons/lang3/StringUtils.leftPad:(Ljava/lang/String;IC)Ljava/lang/String;
        18: goto          23
        21: aload         4
        23: areturn
      LineNumberTable:
        line 479: 0
        line 480: 6
      LocalVariableTable:
        Start  Length  Slot  Name   Signature
            0      24     0 value   J
            0      24     2 padWithZeros   Z
            0      24     3 count   I
            6      18     4 longString   Ljava/lang/String;
      StackMapTable: number_of_entries = 2
        frame_type = 252 /* append */
          offset_delta = 21
          locals = [ class java/lang/String ]
        frame_type = 65 /* same_locals_1_stack_item */
          stack = [ class java/lang/String ]

  static org.apache.commons.lang3.time.DurationFormatUtils$Token[] lexx(java.lang.String);
    descriptor: (Ljava/lang/String;)[Lorg/apache/commons/lang3/time/DurationFormatUtils$Token;
    flags: (0x0008) ACC_STATIC
    Code:
      stack=4, locals=9, args_size=1
         0: new           #78                 // class java/util/ArrayList
         3: dup
         4: aload_0
         5: invokevirtual #38                 // Method java/lang/String.length:()I
         8: invokespecial #79                 // Method java/util/ArrayList."<init>":(I)V
        11: astore_1
        12: iconst_0
        13: istore_2
        14: aconst_null
        15: astore_3
        16: aconst_null
        17: astore        4
        19: iconst_0
        20: istore        5
        22: iload         5
        24: aload_0
        25: invokevirtual #38                 // Method java/lang/String.length:()I
        28: if_icmpge     326
        31: aload_0
        32: iload         5
        34: invokevirtual #80                 // Method java/lang/String.charAt:(I)C
        37: istore        6
        39: iload_2
        40: ifeq          60
        43: iload         6
        45: bipush        39
        47: if_icmpeq     60
        50: aload_3
        51: iload         6
        53: invokevirtual #81                 // Method java/lang/StringBuilder.append:(C)Ljava/lang/StringBuilder;
        56: pop
        57: goto          320
        60: aconst_null
        61: astore        7
        63: iload         6
        65: lookupswitch  { // 8
                      39: 140
                      72: 201
                      77: 185
                      83: 225
                     100: 193
                     109: 209
                     115: 217
                     121: 177
                 default: 233
            }
       140: iload_2
       141: ifeq          151
       144: aconst_null
       145: astore_3
       146: iconst_0
       147: istore_2
       148: goto          265
       151: new           #29                 // class java/lang/StringBuilder
       154: dup
       155: invokespecial #30                 // Method java/lang/StringBuilder."<init>":()V
       158: astore_3
       159: aload_1
       160: new           #82                 // class org/apache/commons/lang3/time/DurationFormatUtils$Token
       163: dup
       164: aload_3
       165: invokespecial #83                 // Method org/apache/commons/lang3/time/DurationFormatUtils$Token."<init>":(Ljava/lang/Object;)V
       168: invokevirtual #84                 // Method java/util/ArrayList.add:(Ljava/lang/Object;)Z
       171: pop
       172: iconst_1
       173: istore_2
       174: goto          265
       177: getstatic     #67                 // Field y:Ljava/lang/Object;
       180: astore        7
       182: goto          265
       185: getstatic     #64                 // Field M:Ljava/lang/Object;
       188: astore        7
       190: goto          265
       193: getstatic     #13                 // Field d:Ljava/lang/Object;
       196: astore        7
       198: goto          265
       201: getstatic     #18                 // Field H:Ljava/lang/Object;
       204: astore        7
       206: goto          265
       209: getstatic     #21                 // Field m:Ljava/lang/Object;
       212: astore        7
       214: goto          265
       217: getstatic     #24                 // Field s:Ljava/lang/Object;
       220: astore        7
       222: goto          265
       225: getstatic     #74                 // Field S:Ljava/lang/Object;
       228: astore        7
       230: goto          265
       233: aload_3
       234: ifnonnull     258
       237: new           #29                 // class java/lang/StringBuilder
       240: dup
       241: invokespecial #30                 // Method java/lang/StringBuilder."<init>":()V
       244: astore_3
       245: aload_1
       246: new           #82                 // class org/apache/commons/lang3/time/DurationFormatUtils$Token
       249: dup
       250: aload_3
       251: invokespecial #83                 // Method org/apache/commons/lang3/time/DurationFormatUtils$Token."<init>":(Ljava/lang/Object;)V
       254: invokevirtual #84                 // Method java/util/ArrayList.add:(Ljava/lang/Object;)Z
       257: pop
       258: aload_3
       259: iload         6
       261: invokevirtual #81                 // Method java/lang/StringBuilder.append:(C)Ljava/lang/StringBuilder;
       264: pop
       265: aload         7
       267: ifnull        320
       270: aload         4
       272: ifnull        296
       275: aload         4
       277: invokevirtual #69                 // Method org/apache/commons/lang3/time/DurationFormatUtils$Token.getValue:()Ljava/lang/Object;
       280: aload         7
       282: invokevirtual #72                 // Method java/lang/Object.equals:(Ljava/lang/Object;)Z
       285: ifeq          296
       288: aload         4
       290: invokevirtual #85                 // Method org/apache/commons/lang3/time/DurationFormatUtils$Token.increment:()V
       293: goto          318
       296: new           #82                 // class org/apache/commons/lang3/time/DurationFormatUtils$Token
       299: dup
       300: aload         7
       302: invokespecial #83                 // Method org/apache/commons/lang3/time/DurationFormatUtils$Token."<init>":(Ljava/lang/Object;)V
       305: astore        8
       307: aload_1
       308: aload         8
       310: invokevirtual #84                 // Method java/util/ArrayList.add:(Ljava/lang/Object;)Z
       313: pop
       314: aload         8
       316: astore        4
       318: aconst_null
       319: astore_3
       320: iinc          5, 1
       323: goto          22
       326: iload_2
       327: ifeq          357
       330: new           #86                 // class java/lang/IllegalArgumentException
       333: dup
       334: new           #29                 // class java/lang/StringBuilder
       337: dup
       338: invokespecial #30                 // Method java/lang/StringBuilder."<init>":()V
       341: ldc           #87                 // String Unmatched quote in format:
       343: invokevirtual #32                 // Method java/lang/StringBuilder.append:(Ljava/lang/String;)Ljava/lang/StringBuilder;
       346: aload_0
       347: invokevirtual #32                 // Method java/lang/StringBuilder.append:(Ljava/lang/String;)Ljava/lang/StringBuilder;
       350: invokevirtual #33                 // Method java/lang/StringBuilder.toString:()Ljava/lang/String;
       353: invokespecial #88                 // Method java/lang/IllegalArgumentException."<init>":(Ljava/lang/String;)V
       356: athrow
       357: aload_1
       358: aload_1
       359: invokevirtual #89                 // Method java/util/ArrayList.size:()I
       362: anewarray     #82                 // class org/apache/commons/lang3/time/DurationFormatUtils$Token
       365: invokevirtual #90                 // Method java/util/ArrayList.toArray:([Ljava/lang/Object;)[Ljava/lang/Object;
       368: checkcast     #91                 // class "[Lorg/apache/commons/lang3/time/DurationFormatUtils$Token;"
       371: areturn
      LineNumberTable:
        line 498: 0
        line 500: 12
        line 503: 14
        line 504: 16
        line 505: 19
        line 506: 31
        line 507: 39
        line 508: 50
        line 509: 57
        line 511: 60
        line 512: 63
        line 515: 140
        line 516: 144
        line 517: 146
        line 519: 151
        line 520: 159
        line 521: 172
        line 523: 174
        line 525: 177
        line 526: 182
        line 528: 185
        line 529: 190
        line 531: 193
        line 532: 198
        line 534: 201
        line 535: 206
        line 537: 209
        line 538: 214
        line 540: 217
        line 541: 222
        line 543: 225
        line 544: 230
        line 546: 233
        line 547: 237
        line 548: 245
        line 550: 258
        line 553: 265
        line 554: 270
        line 555: 288
        line 557: 296
        line 558: 307
        line 559: 314
        line 561: 318
        line 505: 320
        line 564: 326
        line 565: 330
        line 567: 357
      LocalVariableTable:
        Start  Length  Slot  Name   Signature
          307      11     8 token   Lorg/apache/commons/lang3/time/DurationFormatUtils$Token;
           39     281     6    ch   C
           63     257     7 value   Ljava/lang/Object;
           22     304     5     i   I
            0     372     0 format   Ljava/lang/String;
           12     360     1  list   Ljava/util/ArrayList;
           14     358     2 inLiteral   Z
           16     356     3 buffer   Ljava/lang/StringBuilder;
           19     353     4 previous   Lorg/apache/commons/lang3/time/DurationFormatUtils$Token;
      LocalVariableTypeTable:
        Start  Length  Slot  Name   Signature
           12     360     1  list   Ljava/util/ArrayList<Lorg/apache/commons/lang3/time/DurationFormatUtils$Token;>;
      StackMapTable: number_of_entries = 19
        frame_type = 255 /* full_frame */
          offset_delta = 22
          locals = [ class java/lang/String, class java/util/ArrayList, int, class java/lang/StringBuilder, class org/apache/commons/lang3/time/DurationFormatUtils$Token, int ]
          stack = []
        frame_type = 252 /* append */
          offset_delta = 37
          locals = [ int ]
        frame_type = 252 /* append */
          offset_delta = 79
          locals = [ class java/lang/Object ]
        frame_type = 10 /* same */
        frame_type = 25 /* same */
        frame_type = 7 /* same */
        frame_type = 7 /* same */
        frame_type = 7 /* same */
        frame_type = 7 /* same */
        frame_type = 7 /* same */
        frame_type = 7 /* same */
        frame_type = 7 /* same */
        frame_type = 24 /* same */
        frame_type = 6 /* same */
        frame_type = 30 /* same */
        frame_type = 21 /* same */
        frame_type = 249 /* chop */
          offset_delta = 1
        frame_type = 250 /* chop */
          offset_delta = 5
        frame_type = 30 /* same */

  static {};
    descriptor: ()V
    flags: (0x0008) ACC_STATIC
    Code:
      stack=1, locals=0, args_size=0
         0: ldc           #92                 // String y
         2: putstatic     #67                 // Field y:Ljava/lang/Object;
         5: ldc           #93                 // String M
         7: putstatic     #64                 // Field M:Ljava/lang/Object;
        10: ldc           #94                 // String d
        12: putstatic     #13                 // Field d:Ljava/lang/Object;
        15: ldc           #95                 // String H
        17: putstatic     #18                 // Field H:Ljava/lang/Object;
        20: ldc           #96                 // String m
        22: putstatic     #21                 // Field m:Ljava/lang/Object;
        25: ldc           #97                 // String s
        27: putstatic     #24                 // Field s:Ljava/lang/Object;
        30: ldc           #98                 // String S
        32: putstatic     #74                 // Field S:Ljava/lang/Object;
        35: return
      LineNumberTable:
        line 483: 0
        line 484: 5
        line 485: 10
        line 486: 15
        line 487: 20
        line 488: 25
        line 489: 30
}
SourceFile: "DurationFormatUtils.java"
InnerClasses:
  static #99= #82 of #4;                  // Token=class org/apache/commons/lang3/time/DurationFormatUtils$Token of class org/apache/commons/lang3/time/DurationFormatUtils
