Classfile /Users/mw/Projects/slang-braindump/.jar/jar8/assemble/slang-braindump/assemble/content/org/apache/commons/lang3/time/FastDatePrinter$UnpaddedNumberField.class
  Last modified May 29, 2022; size 1396 bytes
  SHA-256 checksum 9abf53033536a823793cd03736e198a104c911aadfe3a78221b4de167baac6f1
  Compiled from "FastDatePrinter.java"
class org.apache.commons.lang3.time.FastDatePrinter$UnpaddedNumberField implements org.apache.commons.lang3.time.FastDatePrinter$NumberRule
  minor version: 0
  major version: 52
  flags: (0x0020) ACC_SUPER
  this_class: #8                          // org/apache/commons/lang3/time/FastDatePrinter$UnpaddedNumberField
  super_class: #9                         // java/lang/Object
  interfaces: 1, fields: 1, methods: 4, attributes: 2
Constant pool:
   #1 = Methodref          #9.#38         // java/lang/Object."<init>":()V
   #2 = Fieldref           #8.#39         // org/apache/commons/lang3/time/FastDatePrinter$UnpaddedNumberField.mField:I
   #3 = Methodref          #40.#41        // java/util/Calendar.get:(I)I
   #4 = Methodref          #8.#42         // org/apache/commons/lang3/time/FastDatePrinter$UnpaddedNumberField.appendTo:(Ljava/lang/Appendable;I)V
   #5 = InterfaceMethodref #43.#44        // java/lang/Appendable.append:(C)Ljava/lang/Appendable;
   #6 = Methodref          #45.#46        // org/apache/commons/lang3/time/FastDatePrinter.access$000:(Ljava/lang/Appendable;I)V
   #7 = Methodref          #45.#47        // org/apache/commons/lang3/time/FastDatePrinter.access$100:(Ljava/lang/Appendable;II)V
   #8 = Class              #48            // org/apache/commons/lang3/time/FastDatePrinter$UnpaddedNumberField
   #9 = Class              #49            // java/lang/Object
  #10 = Class              #50            // org/apache/commons/lang3/time/FastDatePrinter$NumberRule
  #11 = Utf8               mField
  #12 = Utf8               I
  #13 = Utf8               <init>
  #14 = Utf8               (I)V
  #15 = Utf8               Code
  #16 = Utf8               LineNumberTable
  #17 = Utf8               LocalVariableTable
  #18 = Utf8               this
  #19 = Utf8               UnpaddedNumberField
  #20 = Utf8               InnerClasses
  #21 = Utf8               Lorg/apache/commons/lang3/time/FastDatePrinter$UnpaddedNumberField;
  #22 = Utf8               field
  #23 = Utf8               estimateLength
  #24 = Utf8               ()I
  #25 = Utf8               appendTo
  #26 = Utf8               (Ljava/lang/Appendable;Ljava/util/Calendar;)V
  #27 = Utf8               buffer
  #28 = Utf8               Ljava/lang/Appendable;
  #29 = Utf8               calendar
  #30 = Utf8               Ljava/util/Calendar;
  #31 = Utf8               Exceptions
  #32 = Class              #52            // java/io/IOException
  #33 = Utf8               (Ljava/lang/Appendable;I)V
  #34 = Utf8               value
  #35 = Utf8               StackMapTable
  #36 = Utf8               SourceFile
  #37 = Utf8               FastDatePrinter.java
  #38 = NameAndType        #13:#53        // "<init>":()V
  #39 = NameAndType        #11:#12        // mField:I
  #40 = Class              #54            // java/util/Calendar
  #41 = NameAndType        #55:#56        // get:(I)I
  #42 = NameAndType        #25:#33        // appendTo:(Ljava/lang/Appendable;I)V
  #43 = Class              #57            // java/lang/Appendable
  #44 = NameAndType        #58:#59        // append:(C)Ljava/lang/Appendable;
  #45 = Class              #60            // org/apache/commons/lang3/time/FastDatePrinter
  #46 = NameAndType        #61:#33        // access$000:(Ljava/lang/Appendable;I)V
  #47 = NameAndType        #62:#63        // access$100:(Ljava/lang/Appendable;II)V
  #48 = Utf8               org/apache/commons/lang3/time/FastDatePrinter$UnpaddedNumberField
  #49 = Utf8               java/lang/Object
  #50 = Utf8               org/apache/commons/lang3/time/FastDatePrinter$NumberRule
  #51 = Utf8               NumberRule
  #52 = Utf8               java/io/IOException
  #53 = Utf8               ()V
  #54 = Utf8               java/util/Calendar
  #55 = Utf8               get
  #56 = Utf8               (I)I
  #57 = Utf8               java/lang/Appendable
  #58 = Utf8               append
  #59 = Utf8               (C)Ljava/lang/Appendable;
  #60 = Utf8               org/apache/commons/lang3/time/FastDatePrinter
  #61 = Utf8               access$000
  #62 = Utf8               access$100
  #63 = Utf8               (Ljava/lang/Appendable;II)V
{
  private final int mField;
    descriptor: I
    flags: (0x0012) ACC_PRIVATE, ACC_FINAL

  org.apache.commons.lang3.time.FastDatePrinter$UnpaddedNumberField(int);
    descriptor: (I)V
    flags: (0x0000)
    Code:
      stack=2, locals=2, args_size=2
         0: aload_0
         1: invokespecial #1                  // Method java/lang/Object."<init>":()V
         4: aload_0
         5: iload_1
         6: putfield      #2                  // Field mField:I
         9: return
      LineNumberTable:
        line 916: 0
        line 917: 4
        line 918: 9
      LocalVariableTable:
        Start  Length  Slot  Name   Signature
            0      10     0  this   Lorg/apache/commons/lang3/time/FastDatePrinter$UnpaddedNumberField;
            0      10     1 field   I

  public int estimateLength();
    descriptor: ()I
    flags: (0x0001) ACC_PUBLIC
    Code:
      stack=1, locals=1, args_size=1
         0: iconst_4
         1: ireturn
      LineNumberTable:
        line 925: 0
      LocalVariableTable:
        Start  Length  Slot  Name   Signature
            0       2     0  this   Lorg/apache/commons/lang3/time/FastDatePrinter$UnpaddedNumberField;

  public void appendTo(java.lang.Appendable, java.util.Calendar) throws java.io.IOException;
    descriptor: (Ljava/lang/Appendable;Ljava/util/Calendar;)V
    flags: (0x0001) ACC_PUBLIC
    Code:
      stack=4, locals=3, args_size=3
         0: aload_0
         1: aload_1
         2: aload_2
         3: aload_0
         4: getfield      #2                  // Field mField:I
         7: invokevirtual #3                  // Method java/util/Calendar.get:(I)I
        10: invokevirtual #4                  // Method appendTo:(Ljava/lang/Appendable;I)V
        13: return
      LineNumberTable:
        line 933: 0
        line 934: 13
      LocalVariableTable:
        Start  Length  Slot  Name   Signature
            0      14     0  this   Lorg/apache/commons/lang3/time/FastDatePrinter$UnpaddedNumberField;
            0      14     1 buffer   Ljava/lang/Appendable;
            0      14     2 calendar   Ljava/util/Calendar;
    Exceptions:
      throws java.io.IOException

  public final void appendTo(java.lang.Appendable, int) throws java.io.IOException;
    descriptor: (Ljava/lang/Appendable;I)V
    flags: (0x0011) ACC_PUBLIC, ACC_FINAL
    Code:
      stack=3, locals=3, args_size=3
         0: iload_2
         1: bipush        10
         3: if_icmpge     21
         6: aload_1
         7: iload_2
         8: bipush        48
        10: iadd
        11: i2c
        12: invokeinterface #5,  2            // InterfaceMethod java/lang/Appendable.append:(C)Ljava/lang/Appendable;
        17: pop
        18: goto          41
        21: iload_2
        22: bipush        100
        24: if_icmpge     35
        27: aload_1
        28: iload_2
        29: invokestatic  #6                  // Method org/apache/commons/lang3/time/FastDatePrinter.access$000:(Ljava/lang/Appendable;I)V
        32: goto          41
        35: aload_1
        36: iload_2
        37: iconst_1
        38: invokestatic  #7                  // Method org/apache/commons/lang3/time/FastDatePrinter.access$100:(Ljava/lang/Appendable;II)V
        41: return
      LineNumberTable:
        line 941: 0
        line 942: 6
        line 943: 21
        line 944: 27
        line 946: 35
        line 948: 41
      LocalVariableTable:
        Start  Length  Slot  Name   Signature
            0      42     0  this   Lorg/apache/commons/lang3/time/FastDatePrinter$UnpaddedNumberField;
            0      42     1 buffer   Ljava/lang/Appendable;
            0      42     2 value   I
      StackMapTable: number_of_entries = 3
        frame_type = 21 /* same */
        frame_type = 13 /* same */
        frame_type = 5 /* same */
    Exceptions:
      throws java.io.IOException
}
SourceFile: "FastDatePrinter.java"
InnerClasses:
  private static #19= #8 of #45;          // UnpaddedNumberField=class org/apache/commons/lang3/time/FastDatePrinter$UnpaddedNumberField of class org/apache/commons/lang3/time/FastDatePrinter
  private static #51= #10 of #45;         // NumberRule=class org/apache/commons/lang3/time/FastDatePrinter$NumberRule of class org/apache/commons/lang3/time/FastDatePrinter
