Classfile /Users/mw/Projects/slang-braindump/.jar/jar8/assemble/slang-braindump/assemble/content/org/apache/commons/lang3/time/FastDatePrinter$Iso8601_Rule.class
  Last modified May 29, 2022; size 1988 bytes
  SHA-256 checksum 68768e0bfef20e66a70e2323e9f3025d783d6669db91617f55cb4cd37551896e
  Compiled from "FastDatePrinter.java"
class org.apache.commons.lang3.time.FastDatePrinter$Iso8601_Rule implements org.apache.commons.lang3.time.FastDatePrinter$Rule
  minor version: 0
  major version: 52
  flags: (0x0020) ACC_SUPER
  this_class: #17                         // org/apache/commons/lang3/time/FastDatePrinter$Iso8601_Rule
  super_class: #19                        // java/lang/Object
  interfaces: 1, fields: 4, methods: 5, attributes: 2
Constant pool:
   #1 = Fieldref           #17.#56        // org/apache/commons/lang3/time/FastDatePrinter$Iso8601_Rule.ISO8601_HOURS:Lorg/apache/commons/lang3/time/FastDatePrinter$Iso8601_Rule;
   #2 = Fieldref           #17.#57        // org/apache/commons/lang3/time/FastDatePrinter$Iso8601_Rule.ISO8601_HOURS_MINUTES:Lorg/apache/commons/lang3/time/FastDatePrinter$Iso8601_Rule;
   #3 = Fieldref           #17.#58        // org/apache/commons/lang3/time/FastDatePrinter$Iso8601_Rule.ISO8601_HOURS_COLON_MINUTES:Lorg/apache/commons/lang3/time/FastDatePrinter$Iso8601_Rule;
   #4 = Class              #59            // java/lang/IllegalArgumentException
   #5 = String             #60            // invalid number of X
   #6 = Methodref          #4.#61         // java/lang/IllegalArgumentException."<init>":(Ljava/lang/String;)V
   #7 = Methodref          #19.#62        // java/lang/Object."<init>":()V
   #8 = Fieldref           #17.#63        // org/apache/commons/lang3/time/FastDatePrinter$Iso8601_Rule.length:I
   #9 = Class              #64            // java/util/Calendar
  #10 = Methodref          #9.#65         // java/util/Calendar.get:(I)I
  #11 = String             #66            // Z
  #12 = InterfaceMethodref #67.#68        // java/lang/Appendable.append:(Ljava/lang/CharSequence;)Ljava/lang/Appendable;
  #13 = InterfaceMethodref #67.#69        // java/lang/Appendable.append:(C)Ljava/lang/Appendable;
  #14 = Integer            3600000
  #15 = Methodref          #70.#71        // org/apache/commons/lang3/time/FastDatePrinter.access$000:(Ljava/lang/Appendable;I)V
  #16 = Integer            60000
  #17 = Class              #72            // org/apache/commons/lang3/time/FastDatePrinter$Iso8601_Rule
  #18 = Methodref          #17.#73        // org/apache/commons/lang3/time/FastDatePrinter$Iso8601_Rule."<init>":(I)V
  #19 = Class              #74            // java/lang/Object
  #20 = Class              #75            // org/apache/commons/lang3/time/FastDatePrinter$Rule
  #21 = Utf8               ISO8601_HOURS
  #22 = Utf8               Iso8601_Rule
  #23 = Utf8               InnerClasses
  #24 = Utf8               Lorg/apache/commons/lang3/time/FastDatePrinter$Iso8601_Rule;
  #25 = Utf8               ISO8601_HOURS_MINUTES
  #26 = Utf8               ISO8601_HOURS_COLON_MINUTES
  #27 = Utf8               length
  #28 = Utf8               I
  #29 = Utf8               getRule
  #30 = Utf8               (I)Lorg/apache/commons/lang3/time/FastDatePrinter$Iso8601_Rule;
  #31 = Utf8               Code
  #32 = Utf8               LineNumberTable
  #33 = Utf8               LocalVariableTable
  #34 = Utf8               tokenLen
  #35 = Utf8               StackMapTable
  #36 = Utf8               <init>
  #37 = Utf8               (I)V
  #38 = Utf8               this
  #39 = Utf8               estimateLength
  #40 = Utf8               ()I
  #41 = Utf8               appendTo
  #42 = Utf8               (Ljava/lang/Appendable;Ljava/util/Calendar;)V
  #43 = Utf8               buffer
  #44 = Utf8               Ljava/lang/Appendable;
  #45 = Utf8               calendar
  #46 = Utf8               Ljava/util/Calendar;
  #47 = Utf8               offset
  #48 = Utf8               hours
  #49 = Utf8               minutes
  #50 = Utf8               Exceptions
  #51 = Class              #77            // java/io/IOException
  #52 = Utf8               <clinit>
  #53 = Utf8               ()V
  #54 = Utf8               SourceFile
  #55 = Utf8               FastDatePrinter.java
  #56 = NameAndType        #21:#24        // ISO8601_HOURS:Lorg/apache/commons/lang3/time/FastDatePrinter$Iso8601_Rule;
  #57 = NameAndType        #25:#24        // ISO8601_HOURS_MINUTES:Lorg/apache/commons/lang3/time/FastDatePrinter$Iso8601_Rule;
  #58 = NameAndType        #26:#24        // ISO8601_HOURS_COLON_MINUTES:Lorg/apache/commons/lang3/time/FastDatePrinter$Iso8601_Rule;
  #59 = Utf8               java/lang/IllegalArgumentException
  #60 = Utf8               invalid number of X
  #61 = NameAndType        #36:#78        // "<init>":(Ljava/lang/String;)V
  #62 = NameAndType        #36:#53        // "<init>":()V
  #63 = NameAndType        #27:#28        // length:I
  #64 = Utf8               java/util/Calendar
  #65 = NameAndType        #79:#80        // get:(I)I
  #66 = Utf8               Z
  #67 = Class              #81            // java/lang/Appendable
  #68 = NameAndType        #82:#83        // append:(Ljava/lang/CharSequence;)Ljava/lang/Appendable;
  #69 = NameAndType        #82:#84        // append:(C)Ljava/lang/Appendable;
  #70 = Class              #85            // org/apache/commons/lang3/time/FastDatePrinter
  #71 = NameAndType        #86:#87        // access$000:(Ljava/lang/Appendable;I)V
  #72 = Utf8               org/apache/commons/lang3/time/FastDatePrinter$Iso8601_Rule
  #73 = NameAndType        #36:#37        // "<init>":(I)V
  #74 = Utf8               java/lang/Object
  #75 = Utf8               org/apache/commons/lang3/time/FastDatePrinter$Rule
  #76 = Utf8               Rule
  #77 = Utf8               java/io/IOException
  #78 = Utf8               (Ljava/lang/String;)V
  #79 = Utf8               get
  #80 = Utf8               (I)I
  #81 = Utf8               java/lang/Appendable
  #82 = Utf8               append
  #83 = Utf8               (Ljava/lang/CharSequence;)Ljava/lang/Appendable;
  #84 = Utf8               (C)Ljava/lang/Appendable;
  #85 = Utf8               org/apache/commons/lang3/time/FastDatePrinter
  #86 = Utf8               access$000
  #87 = Utf8               (Ljava/lang/Appendable;I)V
{
  static final org.apache.commons.lang3.time.FastDatePrinter$Iso8601_Rule ISO8601_HOURS;
    descriptor: Lorg/apache/commons/lang3/time/FastDatePrinter$Iso8601_Rule;
    flags: (0x0018) ACC_STATIC, ACC_FINAL

  static final org.apache.commons.lang3.time.FastDatePrinter$Iso8601_Rule ISO8601_HOURS_MINUTES;
    descriptor: Lorg/apache/commons/lang3/time/FastDatePrinter$Iso8601_Rule;
    flags: (0x0018) ACC_STATIC, ACC_FINAL

  static final org.apache.commons.lang3.time.FastDatePrinter$Iso8601_Rule ISO8601_HOURS_COLON_MINUTES;
    descriptor: Lorg/apache/commons/lang3/time/FastDatePrinter$Iso8601_Rule;
    flags: (0x0018) ACC_STATIC, ACC_FINAL

  final int length;
    descriptor: I
    flags: (0x0010) ACC_FINAL

  static org.apache.commons.lang3.time.FastDatePrinter$Iso8601_Rule getRule(int);
    descriptor: (I)Lorg/apache/commons/lang3/time/FastDatePrinter$Iso8601_Rule;
    flags: (0x0008) ACC_STATIC
    Code:
      stack=3, locals=1, args_size=1
         0: iload_0
         1: tableswitch   { // 1 to 3
                       1: 28
                       2: 32
                       3: 36
                 default: 40
            }
        28: getstatic     #1                  // Field ISO8601_HOURS:Lorg/apache/commons/lang3/time/FastDatePrinter$Iso8601_Rule;
        31: areturn
        32: getstatic     #2                  // Field ISO8601_HOURS_MINUTES:Lorg/apache/commons/lang3/time/FastDatePrinter$Iso8601_Rule;
        35: areturn
        36: getstatic     #3                  // Field ISO8601_HOURS_COLON_MINUTES:Lorg/apache/commons/lang3/time/FastDatePrinter$Iso8601_Rule;
        39: areturn
        40: new           #4                  // class java/lang/IllegalArgumentException
        43: dup
        44: ldc           #5                  // String invalid number of X
        46: invokespecial #6                  // Method java/lang/IllegalArgumentException."<init>":(Ljava/lang/String;)V
        49: athrow
      LineNumberTable:
        line 1455: 0
        line 1457: 28
        line 1459: 32
        line 1461: 36
        line 1463: 40
      LocalVariableTable:
        Start  Length  Slot  Name   Signature
            0      50     0 tokenLen   I
      StackMapTable: number_of_entries = 4
        frame_type = 28 /* same */
        frame_type = 3 /* same */
        frame_type = 3 /* same */
        frame_type = 3 /* same */

  org.apache.commons.lang3.time.FastDatePrinter$Iso8601_Rule(int);
    descriptor: (I)V
    flags: (0x0000)
    Code:
      stack=2, locals=2, args_size=2
         0: aload_0
         1: invokespecial #7                  // Method java/lang/Object."<init>":()V
         4: aload_0
         5: iload_1
         6: putfield      #8                  // Field length:I
         9: return
      LineNumberTable:
        line 1474: 0
        line 1475: 4
        line 1476: 9
      LocalVariableTable:
        Start  Length  Slot  Name   Signature
            0      10     0  this   Lorg/apache/commons/lang3/time/FastDatePrinter$Iso8601_Rule;
            0      10     1 length   I

  public int estimateLength();
    descriptor: ()I
    flags: (0x0001) ACC_PUBLIC
    Code:
      stack=1, locals=1, args_size=1
         0: aload_0
         1: getfield      #8                  // Field length:I
         4: ireturn
      LineNumberTable:
        line 1483: 0
      LocalVariableTable:
        Start  Length  Slot  Name   Signature
            0       5     0  this   Lorg/apache/commons/lang3/time/FastDatePrinter$Iso8601_Rule;

  public void appendTo(java.lang.Appendable, java.util.Calendar) throws java.io.IOException;
    descriptor: (Ljava/lang/Appendable;Ljava/util/Calendar;)V
    flags: (0x0001) ACC_PUBLIC
    Code:
      stack=3, locals=6, args_size=3
         0: aload_2
         1: bipush        15
         3: invokevirtual #10                 // Method java/util/Calendar.get:(I)I
         6: aload_2
         7: bipush        16
         9: invokevirtual #10                 // Method java/util/Calendar.get:(I)I
        12: iadd
        13: istore_3
        14: iload_3
        15: ifne          28
        18: aload_1
        19: ldc           #11                 // String Z
        21: invokeinterface #12,  2           // InterfaceMethod java/lang/Appendable.append:(Ljava/lang/CharSequence;)Ljava/lang/Appendable;
        26: pop
        27: return
        28: iload_3
        29: ifge          47
        32: aload_1
        33: bipush        45
        35: invokeinterface #13,  2           // InterfaceMethod java/lang/Appendable.append:(C)Ljava/lang/Appendable;
        40: pop
        41: iload_3
        42: ineg
        43: istore_3
        44: goto          56
        47: aload_1
        48: bipush        43
        50: invokeinterface #13,  2           // InterfaceMethod java/lang/Appendable.append:(C)Ljava/lang/Appendable;
        55: pop
        56: iload_3
        57: ldc           #14                 // int 3600000
        59: idiv
        60: istore        4
        62: aload_1
        63: iload         4
        65: invokestatic  #15                 // Method org/apache/commons/lang3/time/FastDatePrinter.access$000:(Ljava/lang/Appendable;I)V
        68: aload_0
        69: getfield      #8                  // Field length:I
        72: iconst_5
        73: if_icmpge     77
        76: return
        77: aload_0
        78: getfield      #8                  // Field length:I
        81: bipush        6
        83: if_icmpne     95
        86: aload_1
        87: bipush        58
        89: invokeinterface #13,  2           // InterfaceMethod java/lang/Appendable.append:(C)Ljava/lang/Appendable;
        94: pop
        95: iload_3
        96: ldc           #16                 // int 60000
        98: idiv
        99: bipush        60
       101: iload         4
       103: imul
       104: isub
       105: istore        5
       107: aload_1
       108: iload         5
       110: invokestatic  #15                 // Method org/apache/commons/lang3/time/FastDatePrinter.access$000:(Ljava/lang/Appendable;I)V
       113: return
      LineNumberTable:
        line 1491: 0
        line 1492: 14
        line 1493: 18
        line 1494: 27
        line 1497: 28
        line 1498: 32
        line 1499: 41
        line 1501: 47
        line 1504: 56
        line 1505: 62
        line 1507: 68
        line 1508: 76
        line 1511: 77
        line 1512: 86
        line 1515: 95
        line 1516: 107
        line 1517: 113
      LocalVariableTable:
        Start  Length  Slot  Name   Signature
            0     114     0  this   Lorg/apache/commons/lang3/time/FastDatePrinter$Iso8601_Rule;
            0     114     1 buffer   Ljava/lang/Appendable;
            0     114     2 calendar   Ljava/util/Calendar;
           14     100     3 offset   I
           62      52     4 hours   I
          107       7     5 minutes   I
      StackMapTable: number_of_entries = 5
        frame_type = 252 /* append */
          offset_delta = 28
          locals = [ int ]
        frame_type = 18 /* same */
        frame_type = 8 /* same */
        frame_type = 252 /* append */
          offset_delta = 20
          locals = [ int ]
        frame_type = 17 /* same */
    Exceptions:
      throws java.io.IOException

  static {};
    descriptor: ()V
    flags: (0x0008) ACC_STATIC
    Code:
      stack=3, locals=0, args_size=0
         0: new           #17                 // class org/apache/commons/lang3/time/FastDatePrinter$Iso8601_Rule
         3: dup
         4: iconst_3
         5: invokespecial #18                 // Method "<init>":(I)V
         8: putstatic     #1                  // Field ISO8601_HOURS:Lorg/apache/commons/lang3/time/FastDatePrinter$Iso8601_Rule;
        11: new           #17                 // class org/apache/commons/lang3/time/FastDatePrinter$Iso8601_Rule
        14: dup
        15: iconst_5
        16: invokespecial #18                 // Method "<init>":(I)V
        19: putstatic     #2                  // Field ISO8601_HOURS_MINUTES:Lorg/apache/commons/lang3/time/FastDatePrinter$Iso8601_Rule;
        22: new           #17                 // class org/apache/commons/lang3/time/FastDatePrinter$Iso8601_Rule
        25: dup
        26: bipush        6
        28: invokespecial #18                 // Method "<init>":(I)V
        31: putstatic     #3                  // Field ISO8601_HOURS_COLON_MINUTES:Lorg/apache/commons/lang3/time/FastDatePrinter$Iso8601_Rule;
        34: return
      LineNumberTable:
        line 1441: 0
        line 1443: 11
        line 1445: 22
}
SourceFile: "FastDatePrinter.java"
InnerClasses:
  private static #22= #17 of #70;         // Iso8601_Rule=class org/apache/commons/lang3/time/FastDatePrinter$Iso8601_Rule of class org/apache/commons/lang3/time/FastDatePrinter
  private static #76= #20 of #70;         // Rule=class org/apache/commons/lang3/time/FastDatePrinter$Rule of class org/apache/commons/lang3/time/FastDatePrinter
