Classfile /Users/mw/Projects/slang-braindump/.jar/jar8/assemble/slang-braindump/assemble/content/org/apache/commons/lang3/time/FastDateParser$2.class
  Last modified May 29, 2022; size 803 bytes
  SHA-256 checksum ab79b2cc013023115fe46b3123be221cecfb1b8685bea904592164b7231653a2
  Compiled from "FastDateParser.java"
class org.apache.commons.lang3.time.FastDateParser$2 extends org.apache.commons.lang3.time.FastDateParser$NumberStrategy
  minor version: 0
  major version: 52
  flags: (0x0020) ACC_SUPER
  this_class: #3                          // org/apache/commons/lang3/time/FastDateParser$2
  super_class: #4                         // org/apache/commons/lang3/time/FastDateParser$NumberStrategy
  interfaces: 0, fields: 0, methods: 2, attributes: 3
Constant pool:
   #1 = Methodref          #4.#25         // org/apache/commons/lang3/time/FastDateParser$NumberStrategy."<init>":(I)V
   #2 = Methodref          #24.#26        // org/apache/commons/lang3/time/FastDateParser.access$700:(Lorg/apache/commons/lang3/time/FastDateParser;I)I
   #3 = Class              #27            // org/apache/commons/lang3/time/FastDateParser$2
   #4 = Class              #28            // org/apache/commons/lang3/time/FastDateParser$NumberStrategy
   #5 = Utf8               <init>
   #6 = Utf8               (I)V
   #7 = Utf8               Code
   #8 = Utf8               LineNumberTable
   #9 = Utf8               LocalVariableTable
  #10 = Utf8               this
  #11 = Utf8               InnerClasses
  #12 = Utf8               Lorg/apache/commons/lang3/time/FastDateParser$2;
  #13 = Utf8               field
  #14 = Utf8               I
  #15 = Utf8               modify
  #16 = Utf8               (Lorg/apache/commons/lang3/time/FastDateParser;I)I
  #17 = Utf8               parser
  #18 = Utf8               Lorg/apache/commons/lang3/time/FastDateParser;
  #19 = Utf8               iValue
  #20 = Utf8               StackMapTable
  #21 = Utf8               SourceFile
  #22 = Utf8               FastDateParser.java
  #23 = Utf8               EnclosingMethod
  #24 = Class              #30            // org/apache/commons/lang3/time/FastDateParser
  #25 = NameAndType        #5:#6          // "<init>":(I)V
  #26 = NameAndType        #31:#16        // access$700:(Lorg/apache/commons/lang3/time/FastDateParser;I)I
  #27 = Utf8               org/apache/commons/lang3/time/FastDateParser$2
  #28 = Utf8               org/apache/commons/lang3/time/FastDateParser$NumberStrategy
  #29 = Utf8               NumberStrategy
  #30 = Utf8               org/apache/commons/lang3/time/FastDateParser
  #31 = Utf8               access$700
{
  org.apache.commons.lang3.time.FastDateParser$2(int);
    descriptor: (I)V
    flags: (0x0000)
    Code:
      stack=2, locals=2, args_size=2
         0: aload_0
         1: iload_1
         2: invokespecial #1                  // Method org/apache/commons/lang3/time/FastDateParser$NumberStrategy."<init>":(I)V
         5: return
      LineNumberTable:
        line 805: 0
      LocalVariableTable:
        Start  Length  Slot  Name   Signature
            0       6     0  this   Lorg/apache/commons/lang3/time/FastDateParser$2;
            0       6     1 field   I

  int modify(org.apache.commons.lang3.time.FastDateParser, int);
    descriptor: (Lorg/apache/commons/lang3/time/FastDateParser;I)I
    flags: (0x0000)
    Code:
      stack=2, locals=3, args_size=3
         0: iload_2
         1: bipush        100
         3: if_icmpge     14
         6: aload_1
         7: iload_2
         8: invokestatic  #2                  // Method org/apache/commons/lang3/time/FastDateParser.access$700:(Lorg/apache/commons/lang3/time/FastDateParser;I)I
        11: goto          15
        14: iload_2
        15: ireturn
      LineNumberTable:
        line 811: 0
      LocalVariableTable:
        Start  Length  Slot  Name   Signature
            0      16     0  this   Lorg/apache/commons/lang3/time/FastDateParser$2;
            0      16     1 parser   Lorg/apache/commons/lang3/time/FastDateParser;
            0      16     2 iValue   I
      StackMapTable: number_of_entries = 2
        frame_type = 14 /* same */
        frame_type = 64 /* same_locals_1_stack_item */
          stack = [ int ]
}
SourceFile: "FastDateParser.java"
EnclosingMethod: #24.#0                 // org.apache.commons.lang3.time.FastDateParser
InnerClasses:
  #3;                                     // class org/apache/commons/lang3/time/FastDateParser$2
  private static #29= #4 of #24;          // NumberStrategy=class org/apache/commons/lang3/time/FastDateParser$NumberStrategy of class org/apache/commons/lang3/time/FastDateParser
