Classfile /Users/mw/Projects/slang-braindump/.jar/jar8/assemble/slang-braindump/assemble/content/org/apache/commons/lang3/time/FastDatePrinter$TimeZoneNameRule.class
  Last modified May 29, 2022; size 1742 bytes
  SHA-256 checksum 1ddd4f4bb932d2ecdb1ae16c338b3ae134c4dd71fd7fe09e4d015c06a13b920e
  Compiled from "FastDatePrinter.java"
class org.apache.commons.lang3.time.FastDatePrinter$TimeZoneNameRule implements org.apache.commons.lang3.time.FastDatePrinter$Rule
  minor version: 0
  major version: 52
  flags: (0x0020) ACC_SUPER
  this_class: #13                         // org/apache/commons/lang3/time/FastDatePrinter$TimeZoneNameRule
  super_class: #14                        // java/lang/Object
  interfaces: 1, fields: 4, methods: 3, attributes: 2
Constant pool:
   #1 = Methodref          #14.#51        // java/lang/Object."<init>":()V
   #2 = Fieldref           #13.#52        // org/apache/commons/lang3/time/FastDatePrinter$TimeZoneNameRule.mLocale:Ljava/util/Locale;
   #3 = Fieldref           #13.#53        // org/apache/commons/lang3/time/FastDatePrinter$TimeZoneNameRule.mStyle:I
   #4 = Methodref          #54.#55        // org/apache/commons/lang3/time/FastDatePrinter.getTimeZoneDisplay:(Ljava/util/TimeZone;ZILjava/util/Locale;)Ljava/lang/String;
   #5 = Fieldref           #13.#56        // org/apache/commons/lang3/time/FastDatePrinter$TimeZoneNameRule.mStandard:Ljava/lang/String;
   #6 = Fieldref           #13.#57        // org/apache/commons/lang3/time/FastDatePrinter$TimeZoneNameRule.mDaylight:Ljava/lang/String;
   #7 = Methodref          #58.#59        // java/lang/String.length:()I
   #8 = Methodref          #60.#61        // java/lang/Math.max:(II)I
   #9 = Methodref          #10.#62        // java/util/Calendar.getTimeZone:()Ljava/util/TimeZone;
  #10 = Class              #63            // java/util/Calendar
  #11 = Methodref          #10.#64        // java/util/Calendar.get:(I)I
  #12 = InterfaceMethodref #65.#66        // java/lang/Appendable.append:(Ljava/lang/CharSequence;)Ljava/lang/Appendable;
  #13 = Class              #67            // org/apache/commons/lang3/time/FastDatePrinter$TimeZoneNameRule
  #14 = Class              #68            // java/lang/Object
  #15 = Class              #69            // org/apache/commons/lang3/time/FastDatePrinter$Rule
  #16 = Utf8               mLocale
  #17 = Utf8               Ljava/util/Locale;
  #18 = Utf8               mStyle
  #19 = Utf8               I
  #20 = Utf8               mStandard
  #21 = Utf8               Ljava/lang/String;
  #22 = Utf8               mDaylight
  #23 = Utf8               <init>
  #24 = Utf8               (Ljava/util/TimeZone;Ljava/util/Locale;I)V
  #25 = Utf8               Code
  #26 = Utf8               LineNumberTable
  #27 = Utf8               LocalVariableTable
  #28 = Utf8               this
  #29 = Utf8               TimeZoneNameRule
  #30 = Utf8               InnerClasses
  #31 = Utf8               Lorg/apache/commons/lang3/time/FastDatePrinter$TimeZoneNameRule;
  #32 = Utf8               timeZone
  #33 = Utf8               Ljava/util/TimeZone;
  #34 = Utf8               locale
  #35 = Utf8               style
  #36 = Utf8               estimateLength
  #37 = Utf8               ()I
  #38 = Utf8               appendTo
  #39 = Utf8               (Ljava/lang/Appendable;Ljava/util/Calendar;)V
  #40 = Utf8               buffer
  #41 = Utf8               Ljava/lang/Appendable;
  #42 = Utf8               calendar
  #43 = Utf8               Ljava/util/Calendar;
  #44 = Utf8               zone
  #45 = Utf8               StackMapTable
  #46 = Class              #71            // java/util/TimeZone
  #47 = Utf8               Exceptions
  #48 = Class              #72            // java/io/IOException
  #49 = Utf8               SourceFile
  #50 = Utf8               FastDatePrinter.java
  #51 = NameAndType        #23:#73        // "<init>":()V
  #52 = NameAndType        #16:#17        // mLocale:Ljava/util/Locale;
  #53 = NameAndType        #18:#19        // mStyle:I
  #54 = Class              #74            // org/apache/commons/lang3/time/FastDatePrinter
  #55 = NameAndType        #75:#76        // getTimeZoneDisplay:(Ljava/util/TimeZone;ZILjava/util/Locale;)Ljava/lang/String;
  #56 = NameAndType        #20:#21        // mStandard:Ljava/lang/String;
  #57 = NameAndType        #22:#21        // mDaylight:Ljava/lang/String;
  #58 = Class              #77            // java/lang/String
  #59 = NameAndType        #78:#37        // length:()I
  #60 = Class              #79            // java/lang/Math
  #61 = NameAndType        #80:#81        // max:(II)I
  #62 = NameAndType        #82:#83        // getTimeZone:()Ljava/util/TimeZone;
  #63 = Utf8               java/util/Calendar
  #64 = NameAndType        #84:#85        // get:(I)I
  #65 = Class              #86            // java/lang/Appendable
  #66 = NameAndType        #87:#88        // append:(Ljava/lang/CharSequence;)Ljava/lang/Appendable;
  #67 = Utf8               org/apache/commons/lang3/time/FastDatePrinter$TimeZoneNameRule
  #68 = Utf8               java/lang/Object
  #69 = Utf8               org/apache/commons/lang3/time/FastDatePrinter$Rule
  #70 = Utf8               Rule
  #71 = Utf8               java/util/TimeZone
  #72 = Utf8               java/io/IOException
  #73 = Utf8               ()V
  #74 = Utf8               org/apache/commons/lang3/time/FastDatePrinter
  #75 = Utf8               getTimeZoneDisplay
  #76 = Utf8               (Ljava/util/TimeZone;ZILjava/util/Locale;)Ljava/lang/String;
  #77 = Utf8               java/lang/String
  #78 = Utf8               length
  #79 = Utf8               java/lang/Math
  #80 = Utf8               max
  #81 = Utf8               (II)I
  #82 = Utf8               getTimeZone
  #83 = Utf8               ()Ljava/util/TimeZone;
  #84 = Utf8               get
  #85 = Utf8               (I)I
  #86 = Utf8               java/lang/Appendable
  #87 = Utf8               append
  #88 = Utf8               (Ljava/lang/CharSequence;)Ljava/lang/Appendable;
{
  private final java.util.Locale mLocale;
    descriptor: Ljava/util/Locale;
    flags: (0x0012) ACC_PRIVATE, ACC_FINAL

  private final int mStyle;
    descriptor: I
    flags: (0x0012) ACC_PRIVATE, ACC_FINAL

  private final java.lang.String mStandard;
    descriptor: Ljava/lang/String;
    flags: (0x0012) ACC_PRIVATE, ACC_FINAL

  private final java.lang.String mDaylight;
    descriptor: Ljava/lang/String;
    flags: (0x0012) ACC_PRIVATE, ACC_FINAL

  org.apache.commons.lang3.time.FastDatePrinter$TimeZoneNameRule(java.util.TimeZone, java.util.Locale, int);
    descriptor: (Ljava/util/TimeZone;Ljava/util/Locale;I)V
    flags: (0x0000)
    Code:
      stack=5, locals=4, args_size=4
         0: aload_0
         1: invokespecial #1                  // Method java/lang/Object."<init>":()V
         4: aload_0
         5: aload_2
         6: putfield      #2                  // Field mLocale:Ljava/util/Locale;
         9: aload_0
        10: iload_3
        11: putfield      #3                  // Field mStyle:I
        14: aload_0
        15: aload_1
        16: iconst_0
        17: iload_3
        18: aload_2
        19: invokestatic  #4                  // Method org/apache/commons/lang3/time/FastDatePrinter.getTimeZoneDisplay:(Ljava/util/TimeZone;ZILjava/util/Locale;)Ljava/lang/String;
        22: putfield      #5                  // Field mStandard:Ljava/lang/String;
        25: aload_0
        26: aload_1
        27: iconst_1
        28: iload_3
        29: aload_2
        30: invokestatic  #4                  // Method org/apache/commons/lang3/time/FastDatePrinter.getTimeZoneDisplay:(Ljava/util/TimeZone;ZILjava/util/Locale;)Ljava/lang/String;
        33: putfield      #6                  // Field mDaylight:Ljava/lang/String;
        36: return
      LineNumberTable:
        line 1347: 0
        line 1348: 4
        line 1349: 9
        line 1351: 14
        line 1352: 25
        line 1353: 36
      LocalVariableTable:
        Start  Length  Slot  Name   Signature
            0      37     0  this   Lorg/apache/commons/lang3/time/FastDatePrinter$TimeZoneNameRule;
            0      37     1 timeZone   Ljava/util/TimeZone;
            0      37     2 locale   Ljava/util/Locale;
            0      37     3 style   I

  public int estimateLength();
    descriptor: ()I
    flags: (0x0001) ACC_PUBLIC
    Code:
      stack=2, locals=1, args_size=1
         0: aload_0
         1: getfield      #5                  // Field mStandard:Ljava/lang/String;
         4: invokevirtual #7                  // Method java/lang/String.length:()I
         7: aload_0
         8: getfield      #6                  // Field mDaylight:Ljava/lang/String;
        11: invokevirtual #7                  // Method java/lang/String.length:()I
        14: invokestatic  #8                  // Method java/lang/Math.max:(II)I
        17: ireturn
      LineNumberTable:
        line 1363: 0
      LocalVariableTable:
        Start  Length  Slot  Name   Signature
            0      18     0  this   Lorg/apache/commons/lang3/time/FastDatePrinter$TimeZoneNameRule;

  public void appendTo(java.lang.Appendable, java.util.Calendar) throws java.io.IOException;
    descriptor: (Ljava/lang/Appendable;Ljava/util/Calendar;)V
    flags: (0x0001) ACC_PUBLIC
    Code:
      stack=5, locals=4, args_size=3
         0: aload_2
         1: invokevirtual #9                  // Method java/util/Calendar.getTimeZone:()Ljava/util/TimeZone;
         4: astore_3
         5: aload_2
         6: bipush        16
         8: invokevirtual #11                 // Method java/util/Calendar.get:(I)I
        11: ifne          37
        14: aload_1
        15: aload_3
        16: iconst_0
        17: aload_0
        18: getfield      #3                  // Field mStyle:I
        21: aload_0
        22: getfield      #2                  // Field mLocale:Ljava/util/Locale;
        25: invokestatic  #4                  // Method org/apache/commons/lang3/time/FastDatePrinter.getTimeZoneDisplay:(Ljava/util/TimeZone;ZILjava/util/Locale;)Ljava/lang/String;
        28: invokeinterface #12,  2           // InterfaceMethod java/lang/Appendable.append:(Ljava/lang/CharSequence;)Ljava/lang/Appendable;
        33: pop
        34: goto          57
        37: aload_1
        38: aload_3
        39: iconst_1
        40: aload_0
        41: getfield      #3                  // Field mStyle:I
        44: aload_0
        45: getfield      #2                  // Field mLocale:Ljava/util/Locale;
        48: invokestatic  #4                  // Method org/apache/commons/lang3/time/FastDatePrinter.getTimeZoneDisplay:(Ljava/util/TimeZone;ZILjava/util/Locale;)Ljava/lang/String;
        51: invokeinterface #12,  2           // InterfaceMethod java/lang/Appendable.append:(Ljava/lang/CharSequence;)Ljava/lang/Appendable;
        56: pop
        57: return
      LineNumberTable:
        line 1371: 0
        line 1372: 5
        line 1373: 14
        line 1375: 37
        line 1377: 57
      LocalVariableTable:
        Start  Length  Slot  Name   Signature
            0      58     0  this   Lorg/apache/commons/lang3/time/FastDatePrinter$TimeZoneNameRule;
            0      58     1 buffer   Ljava/lang/Appendable;
            0      58     2 calendar   Ljava/util/Calendar;
            5      53     3  zone   Ljava/util/TimeZone;
      StackMapTable: number_of_entries = 2
        frame_type = 252 /* append */
          offset_delta = 37
          locals = [ class java/util/TimeZone ]
        frame_type = 19 /* same */
    Exceptions:
      throws java.io.IOException
}
SourceFile: "FastDatePrinter.java"
InnerClasses:
  private static #29= #13 of #54;         // TimeZoneNameRule=class org/apache/commons/lang3/time/FastDatePrinter$TimeZoneNameRule of class org/apache/commons/lang3/time/FastDatePrinter
  private static #70= #15 of #54;         // Rule=class org/apache/commons/lang3/time/FastDatePrinter$Rule of class org/apache/commons/lang3/time/FastDatePrinter
