Classfile /Users/mw/Projects/slang-braindump/.jar/jar8/assemble/slang-braindump/assemble/content/org/apache/commons/lang3/time/FastDateParser$NumberStrategy.class
  Last modified May 29, 2022; size 2113 bytes
  SHA-256 checksum 67106159c7ae583799eb6f09b4cd6fd8d328598fd2e5f237af7517c3628693aa
  Compiled from "FastDateParser.java"
class org.apache.commons.lang3.time.FastDateParser$NumberStrategy extends org.apache.commons.lang3.time.FastDateParser$Strategy
  minor version: 0
  major version: 52
  flags: (0x0020) ACC_SUPER
  this_class: #14                         // org/apache/commons/lang3/time/FastDateParser$NumberStrategy
  super_class: #15                        // org/apache/commons/lang3/time/FastDateParser$Strategy
  interfaces: 0, fields: 1, methods: 4, attributes: 2
Constant pool:
   #1 = Methodref          #15.#52        // org/apache/commons/lang3/time/FastDateParser$Strategy."<init>":(Lorg/apache/commons/lang3/time/FastDateParser$1;)V
   #2 = Fieldref           #14.#53        // org/apache/commons/lang3/time/FastDateParser$NumberStrategy.field:I
   #3 = Methodref          #54.#55        // java/text/ParsePosition.getIndex:()I
   #4 = Methodref          #56.#57        // java/lang/String.length:()I
   #5 = Methodref          #56.#58        // java/lang/String.charAt:(I)C
   #6 = Methodref          #59.#60        // java/lang/Character.isWhitespace:(C)Z
   #7 = Methodref          #54.#61        // java/text/ParsePosition.setIndex:(I)V
   #8 = Methodref          #59.#62        // java/lang/Character.isDigit:(C)Z
   #9 = Methodref          #54.#63        // java/text/ParsePosition.setErrorIndex:(I)V
  #10 = Methodref          #56.#64        // java/lang/String.substring:(II)Ljava/lang/String;
  #11 = Methodref          #65.#66        // java/lang/Integer.parseInt:(Ljava/lang/String;)I
  #12 = Methodref          #14.#67        // org/apache/commons/lang3/time/FastDateParser$NumberStrategy.modify:(Lorg/apache/commons/lang3/time/FastDateParser;I)I
  #13 = Methodref          #68.#69        // java/util/Calendar.set:(II)V
  #14 = Class              #71            // org/apache/commons/lang3/time/FastDateParser$NumberStrategy
  #15 = Class              #72            // org/apache/commons/lang3/time/FastDateParser$Strategy
  #16 = Utf8               field
  #17 = Utf8               I
  #18 = Utf8               <init>
  #19 = Utf8               (I)V
  #20 = Utf8               Code
  #21 = Utf8               LineNumberTable
  #22 = Utf8               LocalVariableTable
  #23 = Utf8               this
  #24 = Utf8               NumberStrategy
  #25 = Utf8               InnerClasses
  #26 = Utf8               Lorg/apache/commons/lang3/time/FastDateParser$NumberStrategy;
  #27 = Utf8               isNumber
  #28 = Utf8               ()Z
  #29 = Utf8               parse
  #30 = Utf8               (Lorg/apache/commons/lang3/time/FastDateParser;Ljava/util/Calendar;Ljava/lang/String;Ljava/text/ParsePosition;I)Z
  #31 = Utf8               c
  #32 = Utf8               C
  #33 = Utf8               end
  #34 = Utf8               parser
  #35 = Utf8               Lorg/apache/commons/lang3/time/FastDateParser;
  #36 = Utf8               calendar
  #37 = Utf8               Ljava/util/Calendar;
  #38 = Utf8               source
  #39 = Utf8               Ljava/lang/String;
  #40 = Utf8               pos
  #41 = Utf8               Ljava/text/ParsePosition;
  #42 = Utf8               maxWidth
  #43 = Utf8               idx
  #44 = Utf8               last
  #45 = Utf8               value
  #46 = Utf8               StackMapTable
  #47 = Utf8               modify
  #48 = Utf8               (Lorg/apache/commons/lang3/time/FastDateParser;I)I
  #49 = Utf8               iValue
  #50 = Utf8               SourceFile
  #51 = Utf8               FastDateParser.java
  #52 = NameAndType        #18:#75        // "<init>":(Lorg/apache/commons/lang3/time/FastDateParser$1;)V
  #53 = NameAndType        #16:#17        // field:I
  #54 = Class              #76            // java/text/ParsePosition
  #55 = NameAndType        #77:#78        // getIndex:()I
  #56 = Class              #79            // java/lang/String
  #57 = NameAndType        #80:#78        // length:()I
  #58 = NameAndType        #81:#82        // charAt:(I)C
  #59 = Class              #83            // java/lang/Character
  #60 = NameAndType        #84:#85        // isWhitespace:(C)Z
  #61 = NameAndType        #86:#19        // setIndex:(I)V
  #62 = NameAndType        #87:#85        // isDigit:(C)Z
  #63 = NameAndType        #88:#19        // setErrorIndex:(I)V
  #64 = NameAndType        #89:#90        // substring:(II)Ljava/lang/String;
  #65 = Class              #91            // java/lang/Integer
  #66 = NameAndType        #92:#93        // parseInt:(Ljava/lang/String;)I
  #67 = NameAndType        #47:#48        // modify:(Lorg/apache/commons/lang3/time/FastDateParser;I)I
  #68 = Class              #94            // java/util/Calendar
  #69 = NameAndType        #95:#96        // set:(II)V
  #70 = Class              #97            // org/apache/commons/lang3/time/FastDateParser
  #71 = Utf8               org/apache/commons/lang3/time/FastDateParser$NumberStrategy
  #72 = Utf8               org/apache/commons/lang3/time/FastDateParser$Strategy
  #73 = Utf8               Strategy
  #74 = Class              #98            // org/apache/commons/lang3/time/FastDateParser$1
  #75 = Utf8               (Lorg/apache/commons/lang3/time/FastDateParser$1;)V
  #76 = Utf8               java/text/ParsePosition
  #77 = Utf8               getIndex
  #78 = Utf8               ()I
  #79 = Utf8               java/lang/String
  #80 = Utf8               length
  #81 = Utf8               charAt
  #82 = Utf8               (I)C
  #83 = Utf8               java/lang/Character
  #84 = Utf8               isWhitespace
  #85 = Utf8               (C)Z
  #86 = Utf8               setIndex
  #87 = Utf8               isDigit
  #88 = Utf8               setErrorIndex
  #89 = Utf8               substring
  #90 = Utf8               (II)Ljava/lang/String;
  #91 = Utf8               java/lang/Integer
  #92 = Utf8               parseInt
  #93 = Utf8               (Ljava/lang/String;)I
  #94 = Utf8               java/util/Calendar
  #95 = Utf8               set
  #96 = Utf8               (II)V
  #97 = Utf8               org/apache/commons/lang3/time/FastDateParser
  #98 = Utf8               org/apache/commons/lang3/time/FastDateParser$1
{
  private final int field;
    descriptor: I
    flags: (0x0012) ACC_PRIVATE, ACC_FINAL

  org.apache.commons.lang3.time.FastDateParser$NumberStrategy(int);
    descriptor: (I)V
    flags: (0x0000)
    Code:
      stack=2, locals=2, args_size=2
         0: aload_0
         1: aconst_null
         2: invokespecial #1                  // Method org/apache/commons/lang3/time/FastDateParser$Strategy."<init>":(Lorg/apache/commons/lang3/time/FastDateParser$1;)V
         5: aload_0
         6: iload_1
         7: putfield      #2                  // Field field:I
        10: return
      LineNumberTable:
        line 741: 0
        line 742: 5
        line 743: 10
      LocalVariableTable:
        Start  Length  Slot  Name   Signature
            0      11     0  this   Lorg/apache/commons/lang3/time/FastDateParser$NumberStrategy;
            0      11     1 field   I

  boolean isNumber();
    descriptor: ()Z
    flags: (0x0000)
    Code:
      stack=1, locals=1, args_size=1
         0: iconst_1
         1: ireturn
      LineNumberTable:
        line 750: 0
      LocalVariableTable:
        Start  Length  Slot  Name   Signature
            0       2     0  this   Lorg/apache/commons/lang3/time/FastDateParser$NumberStrategy;

  boolean parse(org.apache.commons.lang3.time.FastDateParser, java.util.Calendar, java.lang.String, java.text.ParsePosition, int);
    descriptor: (Lorg/apache/commons/lang3/time/FastDateParser;Ljava/util/Calendar;Ljava/lang/String;Ljava/text/ParsePosition;I)Z
    flags: (0x0000)
    Code:
      stack=5, locals=9, args_size=6
         0: aload         4
         2: invokevirtual #3                  // Method java/text/ParsePosition.getIndex:()I
         5: istore        6
         7: aload_3
         8: invokevirtual #4                  // Method java/lang/String.length:()I
        11: istore        7
        13: iload         5
        15: ifne          60
        18: iload         6
        20: iload         7
        22: if_icmpge     50
        25: aload_3
        26: iload         6
        28: invokevirtual #5                  // Method java/lang/String.charAt:(I)C
        31: istore        8
        33: iload         8
        35: invokestatic  #6                  // Method java/lang/Character.isWhitespace:(C)Z
        38: ifne          44
        41: goto          50
        44: iinc          6, 1
        47: goto          18
        50: aload         4
        52: iload         6
        54: invokevirtual #7                  // Method java/text/ParsePosition.setIndex:(I)V
        57: goto          78
        60: iload         6
        62: iload         5
        64: iadd
        65: istore        8
        67: iload         7
        69: iload         8
        71: if_icmple     78
        74: iload         8
        76: istore        7
        78: iload         6
        80: iload         7
        82: if_icmpge     110
        85: aload_3
        86: iload         6
        88: invokevirtual #5                  // Method java/lang/String.charAt:(I)C
        91: istore        8
        93: iload         8
        95: invokestatic  #8                  // Method java/lang/Character.isDigit:(C)Z
        98: ifne          104
       101: goto          110
       104: iinc          6, 1
       107: goto          78
       110: aload         4
       112: invokevirtual #3                  // Method java/text/ParsePosition.getIndex:()I
       115: iload         6
       117: if_icmpne     129
       120: aload         4
       122: iload         6
       124: invokevirtual #9                  // Method java/text/ParsePosition.setErrorIndex:(I)V
       127: iconst_0
       128: ireturn
       129: aload_3
       130: aload         4
       132: invokevirtual #3                  // Method java/text/ParsePosition.getIndex:()I
       135: iload         6
       137: invokevirtual #10                 // Method java/lang/String.substring:(II)Ljava/lang/String;
       140: invokestatic  #11                 // Method java/lang/Integer.parseInt:(Ljava/lang/String;)I
       143: istore        8
       145: aload         4
       147: iload         6
       149: invokevirtual #7                  // Method java/text/ParsePosition.setIndex:(I)V
       152: aload_2
       153: aload_0
       154: getfield      #2                  // Field field:I
       157: aload_0
       158: aload_1
       159: iload         8
       161: invokevirtual #12                 // Method modify:(Lorg/apache/commons/lang3/time/FastDateParser;I)I
       164: invokevirtual #13                 // Method java/util/Calendar.set:(II)V
       167: iconst_1
       168: ireturn
      LineNumberTable:
        line 755: 0
        line 756: 7
        line 758: 13
        line 760: 18
        line 761: 25
        line 762: 33
        line 763: 41
        line 760: 44
        line 766: 50
        line 768: 60
        line 769: 67
        line 770: 74
        line 774: 78
        line 775: 85
        line 776: 93
        line 777: 101
        line 774: 104
        line 781: 110
        line 782: 120
        line 783: 127
        line 786: 129
        line 787: 145
        line 789: 152
        line 790: 167
      LocalVariableTable:
        Start  Length  Slot  Name   Signature
           33      11     8     c   C
           67      11     8   end   I
           93      11     8     c   C
            0     169     0  this   Lorg/apache/commons/lang3/time/FastDateParser$NumberStrategy;
            0     169     1 parser   Lorg/apache/commons/lang3/time/FastDateParser;
            0     169     2 calendar   Ljava/util/Calendar;
            0     169     3 source   Ljava/lang/String;
            0     169     4   pos   Ljava/text/ParsePosition;
            0     169     5 maxWidth   I
            7     162     6   idx   I
           13     156     7  last   I
          145      24     8 value   I
      StackMapTable: number_of_entries = 8
        frame_type = 253 /* append */
          offset_delta = 18
          locals = [ int, int ]
        frame_type = 25 /* same */
        frame_type = 5 /* same */
        frame_type = 9 /* same */
        frame_type = 17 /* same */
        frame_type = 25 /* same */
        frame_type = 5 /* same */
        frame_type = 18 /* same */

  int modify(org.apache.commons.lang3.time.FastDateParser, int);
    descriptor: (Lorg/apache/commons/lang3/time/FastDateParser;I)I
    flags: (0x0000)
    Code:
      stack=1, locals=3, args_size=3
         0: iload_2
         1: ireturn
      LineNumberTable:
        line 800: 0
      LocalVariableTable:
        Start  Length  Slot  Name   Signature
            0       2     0  this   Lorg/apache/commons/lang3/time/FastDateParser$NumberStrategy;
            0       2     1 parser   Lorg/apache/commons/lang3/time/FastDateParser;
            0       2     2 iValue   I
}
SourceFile: "FastDateParser.java"
InnerClasses:
  private static #24= #14 of #70;         // NumberStrategy=class org/apache/commons/lang3/time/FastDateParser$NumberStrategy of class org/apache/commons/lang3/time/FastDateParser
  private static abstract #73= #15 of #70; // Strategy=class org/apache/commons/lang3/time/FastDateParser$Strategy of class org/apache/commons/lang3/time/FastDateParser
  #74;                                    // class org/apache/commons/lang3/time/FastDateParser$1
