Classfile /Users/mw/Projects/slang-braindump/.jar/jar11/assemble/slang-braindump/assemble/content/org/scalatest/diagrams/DiagrammedExprMacro$ApplyInfo$.class
  Last modified May 29, 2022; size 2996 bytes
  SHA-256 checksum 873d126998a707f594f11083276725e0970db5ec5b26f833dbb262f422e25fec
  Compiled from "DiagrammedExprMacro.scala"
public class org.scalatest.diagrams.DiagrammedExprMacro$ApplyInfo$ extends scala.runtime.AbstractFunction2<scala.reflect.api.Trees$SelectApi, scala.collection.immutable.List<scala.reflect.api.Trees$GenericApplyApi>, org.scalatest.diagrams.DiagrammedExprMacro<C>.ApplyInfo> implements java.io.Serializable
  minor version: 0
  major version: 52
  flags: (0x0021) ACC_PUBLIC, ACC_SUPER
  this_class: #2                          // org/scalatest/diagrams/DiagrammedExprMacro$ApplyInfo$
  super_class: #5                         // scala/runtime/AbstractFunction2
  interfaces: 1, fields: 1, methods: 5, attributes: 5
Constant pool:
   #1 = Utf8               org/scalatest/diagrams/DiagrammedExprMacro$ApplyInfo$
   #2 = Class              #1             // org/scalatest/diagrams/DiagrammedExprMacro$ApplyInfo$
   #3 = Utf8               Lscala/runtime/AbstractFunction2<Lscala/reflect/api/Trees$SelectApi;Lscala/collection/immutable/List<Lscala/reflect/api/Trees$GenericApplyApi;>;Lorg/scalatest/diagrams/DiagrammedExprMacro<TC;>.ApplyInfo;>;Ljava/io/Serializable;
   #4 = Utf8               scala/runtime/AbstractFunction2
   #5 = Class              #4             // scala/runtime/AbstractFunction2
   #6 = Utf8               java/io/Serializable
   #7 = Class              #6             // java/io/Serializable
   #8 = Utf8               DiagrammedExprMacro.scala
   #9 = Utf8               org/scalatest/diagrams/DiagrammedExprMacro$ApplyInfo
  #10 = Class              #9             // org/scalatest/diagrams/DiagrammedExprMacro$ApplyInfo
  #11 = Utf8               org/scalatest/diagrams/DiagrammedExprMacro
  #12 = Class              #11            // org/scalatest/diagrams/DiagrammedExprMacro
  #13 = Utf8               ApplyInfo
  #14 = Utf8               ApplyInfo$
  #15 = Utf8               scala/reflect/api/Trees$GenericApplyApi
  #16 = Class              #15            // scala/reflect/api/Trees$GenericApplyApi
  #17 = Utf8               scala/reflect/api/Trees
  #18 = Class              #17            // scala/reflect/api/Trees
  #19 = Utf8               GenericApplyApi
  #20 = Utf8               scala/reflect/api/Trees$SelectApi
  #21 = Class              #20            // scala/reflect/api/Trees$SelectApi
  #22 = Utf8               SelectApi
  #23 = Utf8               $outer
  #24 = Utf8               Lorg/scalatest/diagrams/DiagrammedExprMacro;
  #25 = Utf8               toString
  #26 = Utf8               ()Ljava/lang/String;
  #27 = String             #13            // ApplyInfo
  #28 = Utf8               this
  #29 = Utf8               Lorg/scalatest/diagrams/DiagrammedExprMacro$ApplyInfo$;
  #30 = Utf8               apply
  #31 = Utf8               (Lscala/reflect/api/Trees$SelectApi;Lscala/collection/immutable/List;)Lorg/scalatest/diagrams/DiagrammedExprMacro$ApplyInfo;
  #32 = Utf8               (Lscala/reflect/api/Trees$SelectApi;Lscala/collection/immutable/List<Lscala/reflect/api/Trees$GenericApplyApi;>;)Lorg/scalatest/diagrams/DiagrammedExprMacro<TC;>.ApplyInfo;
  #33 = Utf8               select
  #34 = Utf8               applyList
  #35 = NameAndType        #23:#24        // $outer:Lorg/scalatest/diagrams/DiagrammedExprMacro;
  #36 = Fieldref           #2.#35         // org/scalatest/diagrams/DiagrammedExprMacro$ApplyInfo$.$outer:Lorg/scalatest/diagrams/DiagrammedExprMacro;
  #37 = Utf8               <init>
  #38 = Utf8               (Lorg/scalatest/diagrams/DiagrammedExprMacro;Lscala/reflect/api/Trees$SelectApi;Lscala/collection/immutable/List;)V
  #39 = NameAndType        #37:#38        // "<init>":(Lorg/scalatest/diagrams/DiagrammedExprMacro;Lscala/reflect/api/Trees$SelectApi;Lscala/collection/immutable/List;)V
  #40 = Methodref          #10.#39        // org/scalatest/diagrams/DiagrammedExprMacro$ApplyInfo."<init>":(Lorg/scalatest/diagrams/DiagrammedExprMacro;Lscala/reflect/api/Trees$SelectApi;Lscala/collection/immutable/List;)V
  #41 = Utf8               Lscala/reflect/api/Trees$SelectApi;
  #42 = Utf8               Lscala/collection/immutable/List;
  #43 = Utf8               unapply
  #44 = Utf8               (Lorg/scalatest/diagrams/DiagrammedExprMacro$ApplyInfo;)Lscala/Option;
  #45 = Utf8               (Lorg/scalatest/diagrams/DiagrammedExprMacro<TC;>.ApplyInfo;)Lscala/Option<Lscala/Tuple2<Lscala/reflect/api/Trees$SelectApi;Lscala/collection/immutable/List<Lscala/reflect/api/Trees$GenericApplyApi;>;>;>;
  #46 = Utf8               x$0
  #47 = Utf8               scala/None$
  #48 = Class              #47            // scala/None$
  #49 = Utf8               MODULE$
  #50 = Utf8               Lscala/None$;
  #51 = NameAndType        #49:#50        // MODULE$:Lscala/None$;
  #52 = Fieldref           #48.#51        // scala/None$.MODULE$:Lscala/None$;
  #53 = Utf8               scala/Some
  #54 = Class              #53            // scala/Some
  #55 = Utf8               scala/Tuple2
  #56 = Class              #55            // scala/Tuple2
  #57 = Utf8               ()Lscala/reflect/api/Trees$SelectApi;
  #58 = NameAndType        #33:#57        // select:()Lscala/reflect/api/Trees$SelectApi;
  #59 = Methodref          #10.#58        // org/scalatest/diagrams/DiagrammedExprMacro$ApplyInfo.select:()Lscala/reflect/api/Trees$SelectApi;
  #60 = Utf8               ()Lscala/collection/immutable/List;
  #61 = NameAndType        #34:#60        // applyList:()Lscala/collection/immutable/List;
  #62 = Methodref          #10.#61        // org/scalatest/diagrams/DiagrammedExprMacro$ApplyInfo.applyList:()Lscala/collection/immutable/List;
  #63 = Utf8               (Ljava/lang/Object;Ljava/lang/Object;)V
  #64 = NameAndType        #37:#63        // "<init>":(Ljava/lang/Object;Ljava/lang/Object;)V
  #65 = Methodref          #56.#64        // scala/Tuple2."<init>":(Ljava/lang/Object;Ljava/lang/Object;)V
  #66 = Utf8               (Ljava/lang/Object;)V
  #67 = NameAndType        #37:#66        // "<init>":(Ljava/lang/Object;)V
  #68 = Methodref          #54.#67        // scala/Some."<init>":(Ljava/lang/Object;)V
  #69 = Utf8               Lorg/scalatest/diagrams/DiagrammedExprMacro$ApplyInfo;
  #70 = Utf8               scala/Option
  #71 = Class              #70            // scala/Option
  #72 = Utf8               (Ljava/lang/Object;Ljava/lang/Object;)Ljava/lang/Object;
  #73 = Utf8               v1
  #74 = Utf8               v2
  #75 = Utf8               scala/collection/immutable/List
  #76 = Class              #75            // scala/collection/immutable/List
  #77 = NameAndType        #30:#31        // apply:(Lscala/reflect/api/Trees$SelectApi;Lscala/collection/immutable/List;)Lorg/scalatest/diagrams/DiagrammedExprMacro$ApplyInfo;
  #78 = Methodref          #2.#77         // org/scalatest/diagrams/DiagrammedExprMacro$ApplyInfo$.apply:(Lscala/reflect/api/Trees$SelectApi;Lscala/collection/immutable/List;)Lorg/scalatest/diagrams/DiagrammedExprMacro$ApplyInfo;
  #79 = Utf8               Ljava/lang/Object;
  #80 = Utf8               (Lorg/scalatest/diagrams/DiagrammedExprMacro;)V
  #81 = Utf8               ()V
  #82 = NameAndType        #37:#81        // "<init>":()V
  #83 = Methodref          #5.#82         // scala/runtime/AbstractFunction2."<init>":()V
  #84 = Utf8               Code
  #85 = Utf8               LineNumberTable
  #86 = Utf8               LocalVariableTable
  #87 = Utf8               Signature
  #88 = Utf8               MethodParameters
  #89 = Utf8               StackMapTable
  #90 = Utf8               InnerClasses
  #91 = Utf8               SourceFile
  #92 = Utf8               ScalaInlineInfo
  #93 = Utf8               Scala
{
  private final org.scalatest.diagrams.DiagrammedExprMacro $outer;
    descriptor: Lorg/scalatest/diagrams/DiagrammedExprMacro;
    flags: (0x1012) ACC_PRIVATE, ACC_FINAL, ACC_SYNTHETIC

  public final java.lang.String toString();
    descriptor: ()Ljava/lang/String;
    flags: (0x0011) ACC_PUBLIC, ACC_FINAL
    Code:
      stack=1, locals=1, args_size=1
         0: ldc           #27                 // String ApplyInfo
         2: areturn
      LineNumberTable:
        line 106: 0
      LocalVariableTable:
        Start  Length  Slot  Name   Signature
            0       3     0  this   Lorg/scalatest/diagrams/DiagrammedExprMacro$ApplyInfo$;

  public org.scalatest.diagrams.DiagrammedExprMacro<C>.ApplyInfo apply(scala.reflect.api.Trees$SelectApi, scala.collection.immutable.List<scala.reflect.api.Trees$GenericApplyApi>);
    descriptor: (Lscala/reflect/api/Trees$SelectApi;Lscala/collection/immutable/List;)Lorg/scalatest/diagrams/DiagrammedExprMacro$ApplyInfo;
    flags: (0x0001) ACC_PUBLIC
    Code:
      stack=5, locals=3, args_size=3
         0: new           #10                 // class org/scalatest/diagrams/DiagrammedExprMacro$ApplyInfo
         3: dup
         4: aload_0
         5: getfield      #36                 // Field $outer:Lorg/scalatest/diagrams/DiagrammedExprMacro;
         8: aload_1
         9: aload_2
        10: invokespecial #40                 // Method org/scalatest/diagrams/DiagrammedExprMacro$ApplyInfo."<init>":(Lorg/scalatest/diagrams/DiagrammedExprMacro;Lscala/reflect/api/Trees$SelectApi;Lscala/collection/immutable/List;)V
        13: areturn
      LineNumberTable:
        line 106: 0
      LocalVariableTable:
        Start  Length  Slot  Name   Signature
            0      14     0  this   Lorg/scalatest/diagrams/DiagrammedExprMacro$ApplyInfo$;
            0      14     1 select   Lscala/reflect/api/Trees$SelectApi;
            0      14     2 applyList   Lscala/collection/immutable/List;
    Signature: #32                          // (Lscala/reflect/api/Trees$SelectApi;Lscala/collection/immutable/List<Lscala/reflect/api/Trees$GenericApplyApi;>;)Lorg/scalatest/diagrams/DiagrammedExprMacro<TC;>.ApplyInfo;
    MethodParameters:
      Name                           Flags
      select                         final
      applyList                      final

  public scala.Option<scala.Tuple2<scala.reflect.api.Trees$SelectApi, scala.collection.immutable.List<scala.reflect.api.Trees$GenericApplyApi>>> unapply(org.scalatest.diagrams.DiagrammedExprMacro<C>.ApplyInfo);
    descriptor: (Lorg/scalatest/diagrams/DiagrammedExprMacro$ApplyInfo;)Lscala/Option;
    flags: (0x0001) ACC_PUBLIC
    Code:
      stack=6, locals=2, args_size=2
         0: aload_1
         1: ifnonnull     10
         4: getstatic     #52                 // Field scala/None$.MODULE$:Lscala/None$;
         7: goto          32
        10: new           #54                 // class scala/Some
        13: dup
        14: new           #56                 // class scala/Tuple2
        17: dup
        18: aload_1
        19: invokevirtual #59                 // Method org/scalatest/diagrams/DiagrammedExprMacro$ApplyInfo.select:()Lscala/reflect/api/Trees$SelectApi;
        22: aload_1
        23: invokevirtual #62                 // Method org/scalatest/diagrams/DiagrammedExprMacro$ApplyInfo.applyList:()Lscala/collection/immutable/List;
        26: invokespecial #65                 // Method scala/Tuple2."<init>":(Ljava/lang/Object;Ljava/lang/Object;)V
        29: invokespecial #68                 // Method scala/Some."<init>":(Ljava/lang/Object;)V
        32: areturn
      StackMapTable: number_of_entries = 2
        frame_type = 10 /* same */
        frame_type = 85 /* same_locals_1_stack_item */
          stack = [ class scala/Option ]
      LineNumberTable:
        line 106: 0
      LocalVariableTable:
        Start  Length  Slot  Name   Signature
            0      33     0  this   Lorg/scalatest/diagrams/DiagrammedExprMacro$ApplyInfo$;
            0      33     1   x$0   Lorg/scalatest/diagrams/DiagrammedExprMacro$ApplyInfo;
    Signature: #45                          // (Lorg/scalatest/diagrams/DiagrammedExprMacro<TC;>.ApplyInfo;)Lscala/Option<Lscala/Tuple2<Lscala/reflect/api/Trees$SelectApi;Lscala/collection/immutable/List<Lscala/reflect/api/Trees$GenericApplyApi;>;>;>;
    MethodParameters:
      Name                           Flags
      x$0                            final

  public java.lang.Object apply(java.lang.Object, java.lang.Object);
    descriptor: (Ljava/lang/Object;Ljava/lang/Object;)Ljava/lang/Object;
    flags: (0x1041) ACC_PUBLIC, ACC_BRIDGE, ACC_SYNTHETIC
    Code:
      stack=3, locals=3, args_size=3
         0: aload_0
         1: aload_1
         2: checkcast     #21                 // class scala/reflect/api/Trees$SelectApi
         5: aload_2
         6: checkcast     #76                 // class scala/collection/immutable/List
         9: invokevirtual #78                 // Method apply:(Lscala/reflect/api/Trees$SelectApi;Lscala/collection/immutable/List;)Lorg/scalatest/diagrams/DiagrammedExprMacro$ApplyInfo;
        12: areturn
      LineNumberTable:
        line 106: 0
      LocalVariableTable:
        Start  Length  Slot  Name   Signature
            0      13     0  this   Lorg/scalatest/diagrams/DiagrammedExprMacro$ApplyInfo$;
            0      13     1    v1   Ljava/lang/Object;
            0      13     2    v2   Ljava/lang/Object;
    MethodParameters:
      Name                           Flags
      v1                             final
      v2                             final

  public org.scalatest.diagrams.DiagrammedExprMacro$ApplyInfo$(org.scalatest.diagrams.DiagrammedExprMacro);
    descriptor: (Lorg/scalatest/diagrams/DiagrammedExprMacro;)V
    flags: (0x0001) ACC_PUBLIC
    Code:
      stack=2, locals=2, args_size=2
         0: aload_1
         1: ifnonnull     6
         4: aconst_null
         5: athrow
         6: aload_0
         7: aload_1
         8: putfield      #36                 // Field $outer:Lorg/scalatest/diagrams/DiagrammedExprMacro;
        11: aload_0
        12: invokespecial #83                 // Method scala/runtime/AbstractFunction2."<init>":()V
        15: return
      StackMapTable: number_of_entries = 1
        frame_type = 6 /* same */
      LineNumberTable:
        line 106: 0
      LocalVariableTable:
        Start  Length  Slot  Name   Signature
            0      16     0  this   Lorg/scalatest/diagrams/DiagrammedExprMacro$ApplyInfo$;
            0      16     1 $outer   Lorg/scalatest/diagrams/DiagrammedExprMacro;
    MethodParameters:
      Name                           Flags
      $outer                         final synthetic
}
InnerClasses:
  public #13= #10 of #12;                 // ApplyInfo=class org/scalatest/diagrams/DiagrammedExprMacro$ApplyInfo of class org/scalatest/diagrams/DiagrammedExprMacro
  public #14= #2 of #12;                  // ApplyInfo$=class org/scalatest/diagrams/DiagrammedExprMacro$ApplyInfo$ of class org/scalatest/diagrams/DiagrammedExprMacro
  public #19= #16 of #18;                 // GenericApplyApi=class scala/reflect/api/Trees$GenericApplyApi of class scala/reflect/api/Trees
  public #22= #21 of #18;                 // SelectApi=class scala/reflect/api/Trees$SelectApi of class scala/reflect/api/Trees
Signature: #3                           // Lscala/runtime/AbstractFunction2<Lscala/reflect/api/Trees$SelectApi;Lscala/collection/immutable/List<Lscala/reflect/api/Trees$GenericApplyApi;>;Lorg/scalatest/diagrams/DiagrammedExprMacro<TC;>.ApplyInfo;>;Ljava/io/Serializable;
SourceFile: "DiagrammedExprMacro.scala"
  ScalaInlineInfo: length = 0x1D (unknown attribute)
   01 01 00 05 00 25 00 50 01 00 1E 00 48 01 00 1E
   00 1F 01 00 19 00 1A 01 00 2B 00 2C 01
  Scala: length = 0x0 (unknown attribute)

