Classfile /Users/mw/Projects/slang-braindump/.jar/jar11/assemble/slang-braindump/assemble/content/org/scalatest/diagrams/DiagrammedExpr.class
  Last modified May 29, 2022; size 5619 bytes
  SHA-256 checksum 004fcd55f3ed71a0b29c83fde1a8e5f965070a1c235cae6d92103b7c6832b2d3
  Compiled from "DiagrammedExpr.scala"
public interface org.scalatest.diagrams.DiagrammedExpr<T extends java.lang.Object>
  minor version: 0
  major version: 52
  flags: (0x0601) ACC_PUBLIC, ACC_INTERFACE, ACC_ABSTRACT
  this_class: #2                          // org/scalatest/diagrams/DiagrammedExpr
  super_class: #5                         // java/lang/Object
  interfaces: 0, fields: 0, methods: 13, attributes: 7
Constant pool:
    #1 = Utf8               org/scalatest/diagrams/DiagrammedExpr
    #2 = Class              #1            // org/scalatest/diagrams/DiagrammedExpr
    #3 = Utf8               <T:Ljava/lang/Object;>Ljava/lang/Object;
    #4 = Utf8               java/lang/Object
    #5 = Class              #4            // java/lang/Object
    #6 = Utf8               DiagrammedExpr.scala
    #7 = Utf8               Lscala/reflect/ScalaSignature;
    #8 = Utf8               bytes
    #9 = Utf8               \u0006\u0005q4q\u0001D\u0007\u0011\u0002\u0007\u0005A\u0003C\u0003\u001d\u0001\u0011\u0005Q\u0004C\u0004\"\u0001\t\u0007i\u0011\u0001\u0012\t\u000b\u0019\u0002a\u0011A\u0014\t\u000ba\u0002a\u0011A\u001d\t\r\u0015\u0003A\u0011C\u0007G\u000f\u0015AU\u0002#\u0001J\r\u0015aQ\u0002#\u0001K\u0011\u0015Yu\u0001\"\u0001M\u0011\u0015iu\u0001\"\u0001O\u0011\u00151v\u0001\"\u0001X\u0011\u0015qw\u0001\"\u0001p\u00059!\u0015.Y4sC6lW\rZ#yaJT!AD\b\u0002\u0011\u0011L\u0017m\u001a:b[NT!\u0001E\t\u0002\u0013M\u001c\u0017\r\\1uKN$(\"\u0001\n\u0002\u0007=\u0014xm\u0001\u0001\u0016\u0005Ua4C\u0001\u0001\u0017!\t9\"$D\u0001\u0019\u0015\u0005I\u0012!B:dC2\f\u0017BA\u000e\u0019\u0005\u0019\te.\u001f*fM\u00061A%\u001b8ji\u0012\"\u0012A\b\t\u0003/}I!\u0001\t\r\u0003\tUs\u0017\u000e^\u0001\u0007C:\u001c\u0007n\u001c:\u0016\u0003\r\u0002\"a\u0006\u0013\n\u0005\u0015B\"aA%oi\u0006a\u0011M\\2i_J4\u0016\r\\;fgV\t\u0001\u0006E\u0002*cQr!AK\u0018\u000f\u0005-rS\"\u0001\u0017\u000b\u00055\u001a\u0012A\u0002\u001fs_>$h(C\u0001\u001a\u0013\t\u0001\u0004$A\u0004qC\u000e\\\u0017mZ3\n\u0005I\u001a$\u0001\u0002\'jgRT!\u0001\r\r\u0011\u0005U2T\"A\u0007\n\u0005]j!aC!oG\"|\'OV1mk\u0016\fQA^1mk\u0016,\u0012A\u000f\t\u0003wqb\u0001\u0001B\u0003>\u0001\t\u0007aHA\u0001U#\ty$\t\u0005\u0002\u0018\u0001&\u0011\u0011\t\u0007\u0002\b\u001d>$\b.\u001b8h!\t92)\u0003\u0002E1\t\u0019\u0011I\\=\u0002\'\u0015d\u0017.\\5oCR,G)\u001e9mS\u000e\fG/Z:\u0015\u0005!:\u0005\"\u0002\u0014\u0006\u0001\u0004A\u0013A\u0004#jC\u001e\u0014\u0018-\\7fI\u0016C\bO\u001d\t\u0003k\u001d\u0019\"a\u0002\f\u0002\rqJg.\u001b;?)\u0005I\u0015AC:j[BdW-\u0012=qeV\u0011qJ\u0015\u000b\u0004!N+\u0006cA\u001b\u0001#B\u00111H\u0015\u0003\u0006{%\u0011\rA\u0010\u0005\u0006)&\u0001\r!U\u0001\u000bKb\u0004(/Z:tS>t\u0007\"B\u0011\n\u0001\u0004\u0019\u0013!C1qa2LX\t\u001f9s+\tA6\fF\u0003Z9\u000edW\u000eE\u00026\u0001i\u0003\"aO.\u0005\u000buR!\u0019\u0001 \t\u000buS\u0001\u0019\u00010\u0002\u0013E,\u0018\r\\5gS\u0016\u0014\bGA0b!\r)\u0004\u0001\u0019\t\u0003w\u0005$\u0011B\u0019/\u0002\u0002\u0003\u0005)\u0011\u0001 \u0003\u0007}#\u0013\u0007C\u0003e\u0015\u0001\u0007Q-\u0001\u0003be\u001e\u001c\bcA\u00152MB\u0012q-\u001b\t\u0004k\u0001A\u0007CA\u001ej\t%Q7.!A\u0001\u0002\u000b\u0005aHA\u0002`IIBQ\u0001\u001a\u0006A\u0002\u0015DQ\u0001\u000f\u0006A\u0002iCQ!\t\u0006A\u0002\r\n!b]3mK\u000e$X\t\u001f9s+\t\u00018\u000f\u0006\u0003rij\\\bcA\u001b\u0001eB\u00111h\u001d\u0003\u0006{-\u0011\rA\u0010\u0005\u0006;.\u0001\r!\u001e\u0019\u0003mb\u00042!\u000e\u0001x!\tY\u0004\u0010B\u0005zi\u0006\u0005\t\u0011!B\u0001}\t\u0019q\fJ\u001a\t\u000baZ\u0001\u0019\u0001:\t\u000b\u0005Z\u0001\u0019A\u0012
   #10 = Utf8               java/lang/invoke/MethodHandles$Lookup
   #11 = Class              #10           // java/lang/invoke/MethodHandles$Lookup
   #12 = Utf8               java/lang/invoke/MethodHandles
   #13 = Class              #12           // java/lang/invoke/MethodHandles
   #14 = Utf8               Lookup
   #15 = Utf8               selectExpr
   #16 = Utf8               (Lorg/scalatest/diagrams/DiagrammedExpr;Ljava/lang/Object;I)Lorg/scalatest/diagrams/DiagrammedExpr;
   #17 = Utf8               <T:Ljava/lang/Object;>(Lorg/scalatest/diagrams/DiagrammedExpr<*>;TT;I)Lorg/scalatest/diagrams/DiagrammedExpr<TT;>;
   #18 = Utf8               qualifier
   #19 = Utf8               value
   #20 = Utf8               anchor
   #21 = Utf8               org/scalatest/diagrams/DiagrammedExpr$
   #22 = Class              #21           // org/scalatest/diagrams/DiagrammedExpr$
   #23 = Utf8               MODULE$
   #24 = Utf8               Lorg/scalatest/diagrams/DiagrammedExpr$;
   #25 = NameAndType        #23:#24       // MODULE$:Lorg/scalatest/diagrams/DiagrammedExpr$;
   #26 = Fieldref           #22.#25       // org/scalatest/diagrams/DiagrammedExpr$.MODULE$:Lorg/scalatest/diagrams/DiagrammedExpr$;
   #27 = NameAndType        #15:#16       // selectExpr:(Lorg/scalatest/diagrams/DiagrammedExpr;Ljava/lang/Object;I)Lorg/scalatest/diagrams/DiagrammedExpr;
   #28 = Methodref          #22.#27       // org/scalatest/diagrams/DiagrammedExpr$.selectExpr:(Lorg/scalatest/diagrams/DiagrammedExpr;Ljava/lang/Object;I)Lorg/scalatest/diagrams/DiagrammedExpr;
   #29 = Utf8               Lorg/scalatest/diagrams/DiagrammedExpr;
   #30 = Utf8               Ljava/lang/Object;
   #31 = Utf8               I
   #32 = Utf8               applyExpr
   #33 = Utf8               (Lorg/scalatest/diagrams/DiagrammedExpr;Lscala/collection/immutable/List;Ljava/lang/Object;I)Lorg/scalatest/diagrams/DiagrammedExpr;
   #34 = Utf8               <T:Ljava/lang/Object;>(Lorg/scalatest/diagrams/DiagrammedExpr<*>;Lscala/collection/immutable/List<Lorg/scalatest/diagrams/DiagrammedExpr<*>;>;TT;I)Lorg/scalatest/diagrams/DiagrammedExpr<TT;>;
   #35 = Utf8               args
   #36 = NameAndType        #32:#33       // applyExpr:(Lorg/scalatest/diagrams/DiagrammedExpr;Lscala/collection/immutable/List;Ljava/lang/Object;I)Lorg/scalatest/diagrams/DiagrammedExpr;
   #37 = Methodref          #22.#36       // org/scalatest/diagrams/DiagrammedExpr$.applyExpr:(Lorg/scalatest/diagrams/DiagrammedExpr;Lscala/collection/immutable/List;Ljava/lang/Object;I)Lorg/scalatest/diagrams/DiagrammedExpr;
   #38 = Utf8               Lscala/collection/immutable/List;
   #39 = Utf8               simpleExpr
   #40 = Utf8               (Ljava/lang/Object;I)Lorg/scalatest/diagrams/DiagrammedExpr;
   #41 = Utf8               <T:Ljava/lang/Object;>(TT;I)Lorg/scalatest/diagrams/DiagrammedExpr<TT;>;
   #42 = Utf8               expression
   #43 = NameAndType        #39:#40       // simpleExpr:(Ljava/lang/Object;I)Lorg/scalatest/diagrams/DiagrammedExpr;
   #44 = Methodref          #22.#43       // org/scalatest/diagrams/DiagrammedExpr$.simpleExpr:(Ljava/lang/Object;I)Lorg/scalatest/diagrams/DiagrammedExpr;
   #45 = Utf8               ()I
   #46 = Utf8               anchorValues
   #47 = Utf8               ()Lscala/collection/immutable/List;
   #48 = Utf8               ()Lscala/collection/immutable/List<Lorg/scalatest/diagrams/AnchorValue;>;
   #49 = Utf8               ()Ljava/lang/Object;
   #50 = Utf8               ()TT;
   #51 = Utf8               eliminateDuplicates$
   #52 = Utf8               (Lorg/scalatest/diagrams/DiagrammedExpr;Lscala/collection/immutable/List;)Lscala/collection/immutable/List;
   #53 = Utf8               $this
   #54 = Utf8               eliminateDuplicates
   #55 = Utf8               (Lscala/collection/immutable/List;)Lscala/collection/immutable/List;
   #56 = NameAndType        #54:#55       // eliminateDuplicates:(Lscala/collection/immutable/List;)Lscala/collection/immutable/List;
   #57 = InterfaceMethodref #2.#56        // org/scalatest/diagrams/DiagrammedExpr.eliminateDuplicates:(Lscala/collection/immutable/List;)Lscala/collection/immutable/List;
   #58 = Utf8               (Lscala/collection/immutable/List<Lorg/scalatest/diagrams/AnchorValue;>;)Lscala/collection/immutable/List<Lorg/scalatest/diagrams/AnchorValue;>;
   #59 = Utf8               (Ljava/lang/Object;)Ljava/lang/Object;
   #60 = MethodType         #59           //  (Ljava/lang/Object;)Ljava/lang/Object;
   #61 = Utf8               $anonfun$eliminateDuplicates$1$adapted
   #62 = Utf8               (Lorg/scalatest/diagrams/AnchorValue;)Ljava/lang/Object;
   #63 = NameAndType        #61:#62       // $anonfun$eliminateDuplicates$1$adapted:(Lorg/scalatest/diagrams/AnchorValue;)Ljava/lang/Object;
   #64 = InterfaceMethodref #2.#63        // org/scalatest/diagrams/DiagrammedExpr.$anonfun$eliminateDuplicates$1$adapted:(Lorg/scalatest/diagrams/AnchorValue;)Ljava/lang/Object;
   #65 = MethodHandle       6:#64         // REF_invokeStatic org/scalatest/diagrams/DiagrammedExpr.$anonfun$eliminateDuplicates$1$adapted:(Lorg/scalatest/diagrams/AnchorValue;)Ljava/lang/Object;
   #66 = MethodType         #62           //  (Lorg/scalatest/diagrams/AnchorValue;)Ljava/lang/Object;
   #67 = Integer            5
   #68 = Integer            1
   #69 = Utf8               java/lang/invoke/LambdaMetafactory
   #70 = Class              #69           // java/lang/invoke/LambdaMetafactory
   #71 = Utf8               altMetafactory
   #72 = Utf8               (Ljava/lang/invoke/MethodHandles$Lookup;Ljava/lang/String;Ljava/lang/invoke/MethodType;[Ljava/lang/Object;)Ljava/lang/invoke/CallSite;
   #73 = NameAndType        #71:#72       // altMetafactory:(Ljava/lang/invoke/MethodHandles$Lookup;Ljava/lang/String;Ljava/lang/invoke/MethodType;[Ljava/lang/Object;)Ljava/lang/invoke/CallSite;
   #74 = Methodref          #70.#73       // java/lang/invoke/LambdaMetafactory.altMetafactory:(Ljava/lang/invoke/MethodHandles$Lookup;Ljava/lang/String;Ljava/lang/invoke/MethodType;[Ljava/lang/Object;)Ljava/lang/invoke/CallSite;
   #75 = MethodHandle       6:#74         // REF_invokeStatic java/lang/invoke/LambdaMetafactory.altMetafactory:(Ljava/lang/invoke/MethodHandles$Lookup;Ljava/lang/String;Ljava/lang/invoke/MethodType;[Ljava/lang/Object;)Ljava/lang/invoke/CallSite;
   #76 = Utf8               apply
   #77 = Utf8               ()Lscala/Function1;
   #78 = NameAndType        #76:#77       // apply:()Lscala/Function1;
   #79 = InvokeDynamic      #0:#78        // #0:apply:()Lscala/Function1;
   #80 = Utf8               scala/collection/immutable/List
   #81 = Class              #80           // scala/collection/immutable/List
   #82 = Utf8               groupBy
   #83 = Utf8               (Lscala/Function1;)Lscala/collection/immutable/Map;
   #84 = NameAndType        #82:#83       // groupBy:(Lscala/Function1;)Lscala/collection/immutable/Map;
   #85 = Methodref          #81.#84       // scala/collection/immutable/List.groupBy:(Lscala/Function1;)Lscala/collection/immutable/Map;
   #86 = Utf8               $anonfun$eliminateDuplicates$2
   #87 = Utf8               (Lscala/Tuple2;)Lorg/scalatest/diagrams/AnchorValue;
   #88 = NameAndType        #86:#87       // $anonfun$eliminateDuplicates$2:(Lscala/Tuple2;)Lorg/scalatest/diagrams/AnchorValue;
   #89 = InterfaceMethodref #2.#88        // org/scalatest/diagrams/DiagrammedExpr.$anonfun$eliminateDuplicates$2:(Lscala/Tuple2;)Lorg/scalatest/diagrams/AnchorValue;
   #90 = MethodHandle       6:#89         // REF_invokeStatic org/scalatest/diagrams/DiagrammedExpr.$anonfun$eliminateDuplicates$2:(Lscala/Tuple2;)Lorg/scalatest/diagrams/AnchorValue;
   #91 = MethodType         #87           //  (Lscala/Tuple2;)Lorg/scalatest/diagrams/AnchorValue;
   #92 = InvokeDynamic      #1:#78        // #1:apply:()Lscala/Function1;
   #93 = Utf8               scala/collection/immutable/Map
   #94 = Class              #93           // scala/collection/immutable/Map
   #95 = Utf8               map
   #96 = Utf8               (Lscala/Function1;)Ljava/lang/Object;
   #97 = NameAndType        #95:#96       // map:(Lscala/Function1;)Ljava/lang/Object;
   #98 = InterfaceMethodref #94.#97       // scala/collection/immutable/Map.map:(Lscala/Function1;)Ljava/lang/Object;
   #99 = Utf8               scala/collection/IterableOnceOps
  #100 = Class              #99           // scala/collection/IterableOnceOps
  #101 = Utf8               toList
  #102 = NameAndType        #101:#47      // toList:()Lscala/collection/immutable/List;
  #103 = InterfaceMethodref #100.#102     // scala/collection/IterableOnceOps.toList:()Lscala/collection/immutable/List;
  #104 = Utf8               this
  #105 = Utf8               $anonfun$eliminateDuplicates$1
  #106 = Utf8               (Lorg/scalatest/diagrams/AnchorValue;)I
  #107 = Utf8               x$1
  #108 = Utf8               org/scalatest/diagrams/AnchorValue
  #109 = Class              #108          // org/scalatest/diagrams/AnchorValue
  #110 = NameAndType        #20:#45       // anchor:()I
  #111 = Methodref          #109.#110     // org/scalatest/diagrams/AnchorValue.anchor:()I
  #112 = Utf8               Lorg/scalatest/diagrams/AnchorValue;
  #113 = Utf8               x0$1
  #114 = Utf8               scala/Tuple2
  #115 = Class              #114          // scala/Tuple2
  #116 = Utf8               _2
  #117 = NameAndType        #116:#49      // _2:()Ljava/lang/Object;
  #118 = Methodref          #115.#117     // scala/Tuple2._2:()Ljava/lang/Object;
  #119 = Utf8               last
  #120 = NameAndType        #119:#49      // last:()Ljava/lang/Object;
  #121 = Methodref          #81.#120      // scala/collection/immutable/List.last:()Ljava/lang/Object;
  #122 = Utf8               scala/MatchError
  #123 = Class              #122          // scala/MatchError
  #124 = Utf8               <init>
  #125 = Utf8               (Ljava/lang/Object;)V
  #126 = NameAndType        #124:#125     // "<init>":(Ljava/lang/Object;)V
  #127 = Methodref          #123.#126     // scala/MatchError."<init>":(Ljava/lang/Object;)V
  #128 = Utf8               group
  #129 = Utf8               Lscala/Tuple2;
  #130 = Utf8               $init$
  #131 = Utf8               (Lorg/scalatest/diagrams/DiagrammedExpr;)V
  #132 = NameAndType        #105:#106     // $anonfun$eliminateDuplicates$1:(Lorg/scalatest/diagrams/AnchorValue;)I
  #133 = InterfaceMethodref #2.#132       // org/scalatest/diagrams/DiagrammedExpr.$anonfun$eliminateDuplicates$1:(Lorg/scalatest/diagrams/AnchorValue;)I
  #134 = Utf8               scala/runtime/BoxesRunTime
  #135 = Class              #134          // scala/runtime/BoxesRunTime
  #136 = Utf8               boxToInteger
  #137 = Utf8               (I)Ljava/lang/Integer;
  #138 = NameAndType        #136:#137     // boxToInteger:(I)Ljava/lang/Integer;
  #139 = Methodref          #135.#138     // scala/runtime/BoxesRunTime.boxToInteger:(I)Ljava/lang/Integer;
  #140 = Utf8               $deserializeLambda$
  #141 = Utf8               (Ljava/lang/invoke/SerializedLambda;)Ljava/lang/Object;
  #142 = Utf8               scala/runtime/LambdaDeserialize
  #143 = Class              #142          // scala/runtime/LambdaDeserialize
  #144 = Utf8               bootstrap
  #145 = Utf8               (Ljava/lang/invoke/MethodHandles$Lookup;Ljava/lang/String;Ljava/lang/invoke/MethodType;[Ljava/lang/invoke/MethodHandle;)Ljava/lang/invoke/CallSite;
  #146 = NameAndType        #144:#145     // bootstrap:(Ljava/lang/invoke/MethodHandles$Lookup;Ljava/lang/String;Ljava/lang/invoke/MethodType;[Ljava/lang/invoke/MethodHandle;)Ljava/lang/invoke/CallSite;
  #147 = Methodref          #143.#146     // scala/runtime/LambdaDeserialize.bootstrap:(Ljava/lang/invoke/MethodHandles$Lookup;Ljava/lang/String;Ljava/lang/invoke/MethodType;[Ljava/lang/invoke/MethodHandle;)Ljava/lang/invoke/CallSite;
  #148 = MethodHandle       6:#147        // REF_invokeStatic scala/runtime/LambdaDeserialize.bootstrap:(Ljava/lang/invoke/MethodHandles$Lookup;Ljava/lang/String;Ljava/lang/invoke/MethodType;[Ljava/lang/invoke/MethodHandle;)Ljava/lang/invoke/CallSite;
  #149 = Utf8               lambdaDeserialize
  #150 = NameAndType        #149:#141     // lambdaDeserialize:(Ljava/lang/invoke/SerializedLambda;)Ljava/lang/Object;
  #151 = InvokeDynamic      #2:#150       // #2:lambdaDeserialize:(Ljava/lang/invoke/SerializedLambda;)Ljava/lang/Object;
  #152 = Utf8               Code
  #153 = Utf8               LocalVariableTable
  #154 = Utf8               Signature
  #155 = Utf8               MethodParameters
  #156 = Utf8               LineNumberTable
  #157 = Utf8               StackMapTable
  #158 = Utf8               InnerClasses
  #159 = Utf8               SourceFile
  #160 = Utf8               RuntimeVisibleAnnotations
  #161 = Utf8               BootstrapMethods
  #162 = Utf8               ScalaInlineInfo
  #163 = Utf8               ScalaSig
{
  public static <T extends java.lang.Object> org.scalatest.diagrams.DiagrammedExpr<T> selectExpr(org.scalatest.diagrams.DiagrammedExpr<?>, T, int);
    descriptor: (Lorg/scalatest/diagrams/DiagrammedExpr;Ljava/lang/Object;I)Lorg/scalatest/diagrams/DiagrammedExpr;
    flags: (0x0009) ACC_PUBLIC, ACC_STATIC
    Code:
      stack=4, locals=3, args_size=3
         0: getstatic     #26                 // Field org/scalatest/diagrams/DiagrammedExpr$.MODULE$:Lorg/scalatest/diagrams/DiagrammedExpr$;
         3: aload_0
         4: aload_1
         5: iload_2
         6: invokevirtual #28                 // Method org/scalatest/diagrams/DiagrammedExpr$.selectExpr:(Lorg/scalatest/diagrams/DiagrammedExpr;Ljava/lang/Object;I)Lorg/scalatest/diagrams/DiagrammedExpr;
         9: areturn
      LocalVariableTable:
        Start  Length  Slot  Name   Signature
            0      10     0 qualifier   Lorg/scalatest/diagrams/DiagrammedExpr;
            0      10     1 value   Ljava/lang/Object;
            0      10     2 anchor   I
    Signature: #17                          // <T:Ljava/lang/Object;>(Lorg/scalatest/diagrams/DiagrammedExpr<*>;TT;I)Lorg/scalatest/diagrams/DiagrammedExpr<TT;>;
    MethodParameters:
      Name                           Flags
      qualifier                      final
      value                          final
      anchor                         final

  public static <T extends java.lang.Object> org.scalatest.diagrams.DiagrammedExpr<T> applyExpr(org.scalatest.diagrams.DiagrammedExpr<?>, scala.collection.immutable.List<org.scalatest.diagrams.DiagrammedExpr<?>>, T, int);
    descriptor: (Lorg/scalatest/diagrams/DiagrammedExpr;Lscala/collection/immutable/List;Ljava/lang/Object;I)Lorg/scalatest/diagrams/DiagrammedExpr;
    flags: (0x0009) ACC_PUBLIC, ACC_STATIC
    Code:
      stack=5, locals=4, args_size=4
         0: getstatic     #26                 // Field org/scalatest/diagrams/DiagrammedExpr$.MODULE$:Lorg/scalatest/diagrams/DiagrammedExpr$;
         3: aload_0
         4: aload_1
         5: aload_2
         6: iload_3
         7: invokevirtual #37                 // Method org/scalatest/diagrams/DiagrammedExpr$.applyExpr:(Lorg/scalatest/diagrams/DiagrammedExpr;Lscala/collection/immutable/List;Ljava/lang/Object;I)Lorg/scalatest/diagrams/DiagrammedExpr;
        10: areturn
      LocalVariableTable:
        Start  Length  Slot  Name   Signature
            0      11     0 qualifier   Lorg/scalatest/diagrams/DiagrammedExpr;
            0      11     1  args   Lscala/collection/immutable/List;
            0      11     2 value   Ljava/lang/Object;
            0      11     3 anchor   I
    Signature: #34                          // <T:Ljava/lang/Object;>(Lorg/scalatest/diagrams/DiagrammedExpr<*>;Lscala/collection/immutable/List<Lorg/scalatest/diagrams/DiagrammedExpr<*>;>;TT;I)Lorg/scalatest/diagrams/DiagrammedExpr<TT;>;
    MethodParameters:
      Name                           Flags
      qualifier                      final
      args                           final
      value                          final
      anchor                         final

  public static <T extends java.lang.Object> org.scalatest.diagrams.DiagrammedExpr<T> simpleExpr(T, int);
    descriptor: (Ljava/lang/Object;I)Lorg/scalatest/diagrams/DiagrammedExpr;
    flags: (0x0009) ACC_PUBLIC, ACC_STATIC
    Code:
      stack=3, locals=2, args_size=2
         0: getstatic     #26                 // Field org/scalatest/diagrams/DiagrammedExpr$.MODULE$:Lorg/scalatest/diagrams/DiagrammedExpr$;
         3: aload_0
         4: iload_1
         5: invokevirtual #44                 // Method org/scalatest/diagrams/DiagrammedExpr$.simpleExpr:(Ljava/lang/Object;I)Lorg/scalatest/diagrams/DiagrammedExpr;
         8: areturn
      LocalVariableTable:
        Start  Length  Slot  Name   Signature
            0       9     0 expression   Ljava/lang/Object;
            0       9     1 anchor   I
    Signature: #41                          // <T:Ljava/lang/Object;>(TT;I)Lorg/scalatest/diagrams/DiagrammedExpr<TT;>;
    MethodParameters:
      Name                           Flags
      expression                     final
      anchor                         final

  public abstract int anchor();
    descriptor: ()I
    flags: (0x0401) ACC_PUBLIC, ACC_ABSTRACT

  public abstract scala.collection.immutable.List<org.scalatest.diagrams.AnchorValue> anchorValues();
    descriptor: ()Lscala/collection/immutable/List;
    flags: (0x0401) ACC_PUBLIC, ACC_ABSTRACT
    Signature: #48                          // ()Lscala/collection/immutable/List<Lorg/scalatest/diagrams/AnchorValue;>;

  public abstract T value();
    descriptor: ()Ljava/lang/Object;
    flags: (0x0401) ACC_PUBLIC, ACC_ABSTRACT
    Signature: #50                          // ()TT;

  public static scala.collection.immutable.List eliminateDuplicates$(org.scalatest.diagrams.DiagrammedExpr, scala.collection.immutable.List);
    descriptor: (Lorg/scalatest/diagrams/DiagrammedExpr;Lscala/collection/immutable/List;)Lscala/collection/immutable/List;
    flags: (0x1009) ACC_PUBLIC, ACC_STATIC, ACC_SYNTHETIC
    Code:
      stack=2, locals=2, args_size=2
         0: aload_0
         1: aload_1
         2: invokespecial #57                 // InterfaceMethod eliminateDuplicates:(Lscala/collection/immutable/List;)Lscala/collection/immutable/List;
         5: areturn
      LineNumberTable:
        line 38: 0
      LocalVariableTable:
        Start  Length  Slot  Name   Signature
            0       6     0 $this   Lorg/scalatest/diagrams/DiagrammedExpr;
            0       6     1 anchorValues   Lscala/collection/immutable/List;
    MethodParameters:
      Name                           Flags
      $this                          final synthetic
      anchorValues                   final

  public default scala.collection.immutable.List<org.scalatest.diagrams.AnchorValue> eliminateDuplicates(scala.collection.immutable.List<org.scalatest.diagrams.AnchorValue>);
    descriptor: (Lscala/collection/immutable/List;)Lscala/collection/immutable/List;
    flags: (0x0001) ACC_PUBLIC
    Code:
      stack=2, locals=2, args_size=2
         0: aload_1
         1: invokedynamic #79,  0             // InvokeDynamic #0:apply:()Lscala/Function1;
         6: invokevirtual #85                 // Method scala/collection/immutable/List.groupBy:(Lscala/Function1;)Lscala/collection/immutable/Map;
         9: invokedynamic #92,  0             // InvokeDynamic #1:apply:()Lscala/Function1;
        14: invokeinterface #98,  2           // InterfaceMethod scala/collection/immutable/Map.map:(Lscala/Function1;)Ljava/lang/Object;
        19: checkcast     #100                // class scala/collection/IterableOnceOps
        22: invokeinterface #103,  1          // InterfaceMethod scala/collection/IterableOnceOps.toList:()Lscala/collection/immutable/List;
        27: areturn
      LineNumberTable:
        line 39: 0
      LocalVariableTable:
        Start  Length  Slot  Name   Signature
            0      28     0  this   Lorg/scalatest/diagrams/DiagrammedExpr;
            0      28     1 anchorValues   Lscala/collection/immutable/List;
    Signature: #58                          // (Lscala/collection/immutable/List<Lorg/scalatest/diagrams/AnchorValue;>;)Lscala/collection/immutable/List<Lorg/scalatest/diagrams/AnchorValue;>;
    MethodParameters:
      Name                           Flags
      anchorValues                   final

  public static int $anonfun$eliminateDuplicates$1(org.scalatest.diagrams.AnchorValue);
    descriptor: (Lorg/scalatest/diagrams/AnchorValue;)I
    flags: (0x1009) ACC_PUBLIC, ACC_STATIC, ACC_SYNTHETIC
    Code:
      stack=1, locals=1, args_size=1
         0: aload_0
         1: invokevirtual #111                // Method org/scalatest/diagrams/AnchorValue.anchor:()I
         4: ireturn
      LineNumberTable:
        line 39: 0
      LocalVariableTable:
        Start  Length  Slot  Name   Signature
            0       5     0   x$1   Lorg/scalatest/diagrams/AnchorValue;
    MethodParameters:
      Name                           Flags
      x$1                            final

  public static org.scalatest.diagrams.AnchorValue $anonfun$eliminateDuplicates$2(scala.Tuple2);
    descriptor: (Lscala/Tuple2;)Lorg/scalatest/diagrams/AnchorValue;
    flags: (0x1009) ACC_PUBLIC, ACC_STATIC, ACC_SYNTHETIC
    Code:
      stack=3, locals=4, args_size=1
         0: aload_0
         1: astore_2
         2: aload_2
         3: ifnull        25
         6: aload_2
         7: invokevirtual #118                // Method scala/Tuple2._2:()Ljava/lang/Object;
        10: checkcast     #81                 // class scala/collection/immutable/List
        13: astore_3
        14: aload_3
        15: invokevirtual #121                // Method scala/collection/immutable/List.last:()Ljava/lang/Object;
        18: checkcast     #109                // class org/scalatest/diagrams/AnchorValue
        21: astore_1
        22: goto          37
        25: goto          28
        28: new           #123                // class scala/MatchError
        31: dup
        32: aload_2
        33: invokespecial #127                // Method scala/MatchError."<init>":(Ljava/lang/Object;)V
        36: athrow
        37: aload_1
        38: areturn
      StackMapTable: number_of_entries = 3
        frame_type = 253 /* append */
          offset_delta = 25
          locals = [ top, class scala/Tuple2 ]
        frame_type = 2 /* same */
        frame_type = 255 /* full_frame */
          offset_delta = 8
          locals = [ class scala/Tuple2, class org/scalatest/diagrams/AnchorValue, class scala/Tuple2, class scala/collection/immutable/List ]
          stack = []
      LineNumberTable:
        line 39: 0
        line 40: 14
        line 39: 25
      LocalVariableTable:
        Start  Length  Slot  Name   Signature
           14      11     3 group   Lscala/collection/immutable/List;
            0      39     0  x0$1   Lscala/Tuple2;
    MethodParameters:
      Name                           Flags
      x0$1                           final

  public static void $init$(org.scalatest.diagrams.DiagrammedExpr);
    descriptor: (Lorg/scalatest/diagrams/DiagrammedExpr;)V
    flags: (0x0009) ACC_PUBLIC, ACC_STATIC
    Code:
      stack=0, locals=1, args_size=1
         0: return
      LineNumberTable:
        line 33: 0
      LocalVariableTable:
        Start  Length  Slot  Name   Signature
            0       1     0 $this   Lorg/scalatest/diagrams/DiagrammedExpr;
    MethodParameters:
      Name                           Flags
      $this                          final synthetic

  public static java.lang.Object $anonfun$eliminateDuplicates$1$adapted(org.scalatest.diagrams.AnchorValue);
    descriptor: (Lorg/scalatest/diagrams/AnchorValue;)Ljava/lang/Object;
    flags: (0x1009) ACC_PUBLIC, ACC_STATIC, ACC_SYNTHETIC
    Code:
      stack=1, locals=1, args_size=1
         0: aload_0
         1: invokestatic  #133                // InterfaceMethod $anonfun$eliminateDuplicates$1:(Lorg/scalatest/diagrams/AnchorValue;)I
         4: invokestatic  #139                // Method scala/runtime/BoxesRunTime.boxToInteger:(I)Ljava/lang/Integer;
         7: areturn
      LineNumberTable:
        line 39: 0
      LocalVariableTable:
        Start  Length  Slot  Name   Signature
            0       8     0   x$1   Lorg/scalatest/diagrams/AnchorValue;
    MethodParameters:
      Name                           Flags
      x$1                            final

  private static java.lang.Object $deserializeLambda$(java.lang.invoke.SerializedLambda);
    descriptor: (Ljava/lang/invoke/SerializedLambda;)Ljava/lang/Object;
    flags: (0x100a) ACC_PRIVATE, ACC_STATIC, ACC_SYNTHETIC
    Code:
      stack=1, locals=1, args_size=1
         0: aload_0
         1: invokedynamic #151,  0            // InvokeDynamic #2:lambdaDeserialize:(Ljava/lang/invoke/SerializedLambda;)Ljava/lang/Object;
         6: areturn
}
InnerClasses:
  public static final #14= #11 of #13;    // Lookup=class java/lang/invoke/MethodHandles$Lookup of class java/lang/invoke/MethodHandles
Signature: #3                           // <T:Ljava/lang/Object;>Ljava/lang/Object;
SourceFile: "DiagrammedExpr.scala"
RuntimeVisibleAnnotations:
  0: #7(#8=s#9)
    scala.reflect.ScalaSignature(
      bytes="\u0006\u0005q4q\u0001D\u0007\u0011\u0002\u0007\u0005A\u0003C\u0003\u001d\u0001\u0011\u0005Q\u0004C\u0004\"\u0001\t\u0007i\u0011\u0001\u0012\t\u000b\u0019\u0002a\u0011A\u0014\t\u000ba\u0002a\u0011A\u001d\t\r\u0015\u0003A\u0011C\u0007G\u000f\u0015AU\u0002#\u0001J\r\u0015aQ\u0002#\u0001K\u0011\u0015Yu\u0001\"\u0001M\u0011\u0015iu\u0001\"\u0001O\u0011\u00151v\u0001\"\u0001X\u0011\u0015qw\u0001\"\u0001p\u00059!\u0015.Y4sC6lW\rZ#yaJT!AD\b\u0002\u0011\u0011L\u0017m\u001a:b[NT!\u0001E\t\u0002\u0013M\u001c\u0017\r\\1uKN$(\"\u0001\n\u0002\u0007=\u0014xm\u0001\u0001\u0016\u0005Ua4C\u0001\u0001\u0017!\t9\"$D\u0001\u0019\u0015\u0005I\u0012!B:dC2\f\u0017BA\u000e\u0019\u0005\u0019\te.\u001f*fM\u00061A%\u001b8ji\u0012\"\u0012A\b\t\u0003/}I!\u0001\t\r\u0003\tUs\u0017\u000e^\u0001\u0007C:\u001c\u0007n\u001c:\u0016\u0003\r\u0002\"a\u0006\u0013\n\u0005\u0015B\"aA%oi\u0006a\u0011M\\2i_J4\u0016\r\\;fgV\t\u0001\u0006E\u0002*cQr!AK\u0018\u000f\u0005-rS\"\u0001\u0017\u000b\u00055\u001a\u0012A\u0002\u001fs_>$h(C\u0001\u001a\u0013\t\u0001\u0004$A\u0004qC\u000e\\\u0017mZ3\n\u0005I\u001a$\u0001\u0002\'jgRT!\u0001\r\r\u0011\u0005U2T\"A\u0007\n\u0005]j!aC!oG\"|\'OV1mk\u0016\fQA^1mk\u0016,\u0012A\u000f\t\u0003wqb\u0001\u0001B\u0003>\u0001\t\u0007aHA\u0001U#\ty$\t\u0005\u0002\u0018\u0001&\u0011\u0011\t\u0007\u0002\b\u001d>$\b.\u001b8h!\t92)\u0003\u0002E1\t\u0019\u0011I\\=\u0002\'\u0015d\u0017.\\5oCR,G)\u001e9mS\u000e\fG/Z:\u0015\u0005!:\u0005\"\u0002\u0014\u0006\u0001\u0004A\u0013A\u0004#jC\u001e\u0014\u0018-\\7fI\u0016C\bO\u001d\t\u0003k\u001d\u0019\"a\u0002\f\u0002\rqJg.\u001b;?)\u0005I\u0015AC:j[BdW-\u0012=qeV\u0011qJ\u0015\u000b\u0004!N+\u0006cA\u001b\u0001#B\u00111H\u0015\u0003\u0006{%\u0011\rA\u0010\u0005\u0006)&\u0001\r!U\u0001\u000bKb\u0004(/Z:tS>t\u0007\"B\u0011\n\u0001\u0004\u0019\u0013!C1qa2LX\t\u001f9s+\tA6\fF\u0003Z9\u000edW\u000eE\u00026\u0001i\u0003\"aO.\u0005\u000buR!\u0019\u0001 \t\u000buS\u0001\u0019\u00010\u0002\u0013E,\u0018\r\\5gS\u0016\u0014\bGA0b!\r)\u0004\u0001\u0019\t\u0003w\u0005$\u0011B\u0019/\u0002\u0002\u0003\u0005)\u0011\u0001 \u0003\u0007}#\u0013\u0007C\u0003e\u0015\u0001\u0007Q-\u0001\u0003be\u001e\u001c\bcA\u00152MB\u0012q-\u001b\t\u0004k\u0001A\u0007CA\u001ej\t%Q7.!A\u0001\u0002\u000b\u0005aHA\u0002`IIBQ\u0001\u001a\u0006A\u0002\u0015DQ\u0001\u000f\u0006A\u0002iCQ!\t\u0006A\u0002\r\n!b]3mK\u000e$X\t\u001f9s+\t\u00018\u000f\u0006\u0003rij\\\bcA\u001b\u0001eB\u00111h\u001d\u0003\u0006{-\u0011\rA\u0010\u0005\u0006;.\u0001\r!\u001e\u0019\u0003mb\u00042!\u000e\u0001x!\tY\u0004\u0010B\u0005zi\u0006\u0005\t\u0011!B\u0001}\t\u0019q\fJ\u001a\t\u000baZ\u0001\u0019\u0001:\t\u000b\u0005Z\u0001\u0019A\u0012"
    )
BootstrapMethods:
  0: #75 REF_invokeStatic java/lang/invoke/LambdaMetafactory.altMetafactory:(Ljava/lang/invoke/MethodHandles$Lookup;Ljava/lang/String;Ljava/lang/invoke/MethodType;[Ljava/lang/Object;)Ljava/lang/invoke/CallSite;
    Method arguments:
      #60 (Ljava/lang/Object;)Ljava/lang/Object;
      #65 REF_invokeStatic org/scalatest/diagrams/DiagrammedExpr.$anonfun$eliminateDuplicates$1$adapted:(Lorg/scalatest/diagrams/AnchorValue;)Ljava/lang/Object;
      #66 (Lorg/scalatest/diagrams/AnchorValue;)Ljava/lang/Object;
      #67 5
      #68 1
      #66 (Lorg/scalatest/diagrams/AnchorValue;)Ljava/lang/Object;
  1: #75 REF_invokeStatic java/lang/invoke/LambdaMetafactory.altMetafactory:(Ljava/lang/invoke/MethodHandles$Lookup;Ljava/lang/String;Ljava/lang/invoke/MethodType;[Ljava/lang/Object;)Ljava/lang/invoke/CallSite;
    Method arguments:
      #60 (Ljava/lang/Object;)Ljava/lang/Object;
      #90 REF_invokeStatic org/scalatest/diagrams/DiagrammedExpr.$anonfun$eliminateDuplicates$2:(Lscala/Tuple2;)Lorg/scalatest/diagrams/AnchorValue;
      #91 (Lscala/Tuple2;)Lorg/scalatest/diagrams/AnchorValue;
      #67 5
      #68 1
      #91 (Lscala/Tuple2;)Lorg/scalatest/diagrams/AnchorValue;
  2: #148 REF_invokeStatic scala/runtime/LambdaDeserialize.bootstrap:(Ljava/lang/invoke/MethodHandles$Lookup;Ljava/lang/String;Ljava/lang/invoke/MethodType;[Ljava/lang/invoke/MethodHandle;)Ljava/lang/invoke/CallSite;
    Method arguments:
      #65 REF_invokeStatic org/scalatest/diagrams/DiagrammedExpr.$anonfun$eliminateDuplicates$1$adapted:(Lorg/scalatest/diagrams/AnchorValue;)Ljava/lang/Object;
      #90 REF_invokeStatic org/scalatest/diagrams/DiagrammedExpr.$anonfun$eliminateDuplicates$2:(Lscala/Tuple2;)Lorg/scalatest/diagrams/AnchorValue;
  ScalaInlineInfo: length = 0x31 (unknown attribute)
   01 00 00 09 00 69 00 6A 01 00 3D 00 3E 01 00 56
   00 57 01 00 82 00 83 01 00 14 00 2D 00 00 2E 00
   2F 00 00 36 00 37 00 00 33 00 34 01 00 13 00 31
   00
  ScalaSig: length = 0x3 (unknown attribute)
   05 02 00
