Classfile /Users/mw/Projects/slang-braindump/.jar/jar11/assemble/slang-braindump/assemble/content/org/scalatest/diagrams/DiagrammedExpr$.class
  Last modified May 29, 2022; size 2117 bytes
  SHA-256 checksum fa6b42a82d16be6c9c695008c8026af6cb53408d62f0fc1f0551a7315cf1c80c
  Compiled from "DiagrammedExpr.scala"
public final class org.scalatest.diagrams.DiagrammedExpr$
  minor version: 0
  major version: 52
  flags: (0x0031) ACC_PUBLIC, ACC_FINAL, ACC_SUPER
  this_class: #2                          // org/scalatest/diagrams/DiagrammedExpr$
  super_class: #4                         // java/lang/Object
  interfaces: 0, fields: 1, methods: 5, attributes: 3
Constant pool:
   #1 = Utf8               org/scalatest/diagrams/DiagrammedExpr$
   #2 = Class              #1             // org/scalatest/diagrams/DiagrammedExpr$
   #3 = Utf8               java/lang/Object
   #4 = Class              #3             // java/lang/Object
   #5 = Utf8               DiagrammedExpr.scala
   #6 = Utf8               MODULE$
   #7 = Utf8               Lorg/scalatest/diagrams/DiagrammedExpr$;
   #8 = Utf8               <clinit>
   #9 = Utf8               ()V
  #10 = Utf8               <init>
  #11 = NameAndType        #10:#9         // "<init>":()V
  #12 = Methodref          #2.#11         // org/scalatest/diagrams/DiagrammedExpr$."<init>":()V
  #13 = NameAndType        #6:#7          // MODULE$:Lorg/scalatest/diagrams/DiagrammedExpr$;
  #14 = Fieldref           #2.#13         // org/scalatest/diagrams/DiagrammedExpr$.MODULE$:Lorg/scalatest/diagrams/DiagrammedExpr$;
  #15 = Utf8               simpleExpr
  #16 = Utf8               (Ljava/lang/Object;I)Lorg/scalatest/diagrams/DiagrammedExpr;
  #17 = Utf8               <T:Ljava/lang/Object;>(TT;I)Lorg/scalatest/diagrams/DiagrammedExpr<TT;>;
  #18 = Utf8               expression
  #19 = Utf8               anchor
  #20 = Utf8               org/scalatest/diagrams/DiagrammedSimpleExpr
  #21 = Class              #20            // org/scalatest/diagrams/DiagrammedSimpleExpr
  #22 = Utf8               (Ljava/lang/Object;I)V
  #23 = NameAndType        #10:#22        // "<init>":(Ljava/lang/Object;I)V
  #24 = Methodref          #21.#23        // org/scalatest/diagrams/DiagrammedSimpleExpr."<init>":(Ljava/lang/Object;I)V
  #25 = Utf8               this
  #26 = Utf8               Ljava/lang/Object;
  #27 = Utf8               I
  #28 = Utf8               applyExpr
  #29 = Utf8               (Lorg/scalatest/diagrams/DiagrammedExpr;Lscala/collection/immutable/List;Ljava/lang/Object;I)Lorg/scalatest/diagrams/DiagrammedExpr;
  #30 = Utf8               <T:Ljava/lang/Object;>(Lorg/scalatest/diagrams/DiagrammedExpr<*>;Lscala/collection/immutable/List<Lorg/scalatest/diagrams/DiagrammedExpr<*>;>;TT;I)Lorg/scalatest/diagrams/DiagrammedExpr<TT;>;
  #31 = Utf8               qualifier
  #32 = Utf8               args
  #33 = Utf8               value
  #34 = Utf8               org/scalatest/diagrams/DiagrammedApplyExpr
  #35 = Class              #34            // org/scalatest/diagrams/DiagrammedApplyExpr
  #36 = Utf8               (Lorg/scalatest/diagrams/DiagrammedExpr;Lscala/collection/immutable/List;Ljava/lang/Object;I)V
  #37 = NameAndType        #10:#36        // "<init>":(Lorg/scalatest/diagrams/DiagrammedExpr;Lscala/collection/immutable/List;Ljava/lang/Object;I)V
  #38 = Methodref          #35.#37        // org/scalatest/diagrams/DiagrammedApplyExpr."<init>":(Lorg/scalatest/diagrams/DiagrammedExpr;Lscala/collection/immutable/List;Ljava/lang/Object;I)V
  #39 = Utf8               Lorg/scalatest/diagrams/DiagrammedExpr;
  #40 = Utf8               Lscala/collection/immutable/List;
  #41 = Utf8               selectExpr
  #42 = Utf8               (Lorg/scalatest/diagrams/DiagrammedExpr;Ljava/lang/Object;I)Lorg/scalatest/diagrams/DiagrammedExpr;
  #43 = Utf8               <T:Ljava/lang/Object;>(Lorg/scalatest/diagrams/DiagrammedExpr<*>;TT;I)Lorg/scalatest/diagrams/DiagrammedExpr<TT;>;
  #44 = Utf8               org/scalatest/diagrams/DiagrammedSelectExpr
  #45 = Class              #44            // org/scalatest/diagrams/DiagrammedSelectExpr
  #46 = Utf8               (Lorg/scalatest/diagrams/DiagrammedExpr;Ljava/lang/Object;I)V
  #47 = NameAndType        #10:#46        // "<init>":(Lorg/scalatest/diagrams/DiagrammedExpr;Ljava/lang/Object;I)V
  #48 = Methodref          #45.#47        // org/scalatest/diagrams/DiagrammedSelectExpr."<init>":(Lorg/scalatest/diagrams/DiagrammedExpr;Ljava/lang/Object;I)V
  #49 = Methodref          #4.#11         // java/lang/Object."<init>":()V
  #50 = Utf8               Code
  #51 = Utf8               LineNumberTable
  #52 = Utf8               LocalVariableTable
  #53 = Utf8               Signature
  #54 = Utf8               MethodParameters
  #55 = Utf8               SourceFile
  #56 = Utf8               ScalaInlineInfo
  #57 = Utf8               Scala
{
  public static final org.scalatest.diagrams.DiagrammedExpr$ MODULE$;
    descriptor: Lorg/scalatest/diagrams/DiagrammedExpr$;
    flags: (0x0019) ACC_PUBLIC, ACC_STATIC, ACC_FINAL

  public static {};
    descriptor: ()V
    flags: (0x0009) ACC_PUBLIC, ACC_STATIC
    Code:
      stack=2, locals=0, args_size=0
         0: new           #2                  // class org/scalatest/diagrams/DiagrammedExpr$
         3: dup
         4: invokespecial #12                 // Method "<init>":()V
         7: putstatic     #14                 // Field MODULE$:Lorg/scalatest/diagrams/DiagrammedExpr$;
        10: return
      LineNumberTable:
        line 51: 0

  public <T extends java.lang.Object> org.scalatest.diagrams.DiagrammedExpr<T> simpleExpr(T, int);
    descriptor: (Ljava/lang/Object;I)Lorg/scalatest/diagrams/DiagrammedExpr;
    flags: (0x0001) ACC_PUBLIC
    Code:
      stack=4, locals=3, args_size=3
         0: new           #21                 // class org/scalatest/diagrams/DiagrammedSimpleExpr
         3: dup
         4: aload_1
         5: iload_2
         6: invokespecial #24                 // Method org/scalatest/diagrams/DiagrammedSimpleExpr."<init>":(Ljava/lang/Object;I)V
         9: areturn
      LineNumberTable:
        line 60: 0
      LocalVariableTable:
        Start  Length  Slot  Name   Signature
            0      10     0  this   Lorg/scalatest/diagrams/DiagrammedExpr$;
            0      10     1 expression   Ljava/lang/Object;
            0      10     2 anchor   I
    Signature: #17                          // <T:Ljava/lang/Object;>(TT;I)Lorg/scalatest/diagrams/DiagrammedExpr<TT;>;
    MethodParameters:
      Name                           Flags
      expression                     final
      anchor                         final

  public <T extends java.lang.Object> org.scalatest.diagrams.DiagrammedExpr<T> applyExpr(org.scalatest.diagrams.DiagrammedExpr<?>, scala.collection.immutable.List<org.scalatest.diagrams.DiagrammedExpr<?>>, T, int);
    descriptor: (Lorg/scalatest/diagrams/DiagrammedExpr;Lscala/collection/immutable/List;Ljava/lang/Object;I)Lorg/scalatest/diagrams/DiagrammedExpr;
    flags: (0x0001) ACC_PUBLIC
    Code:
      stack=6, locals=5, args_size=5
         0: new           #35                 // class org/scalatest/diagrams/DiagrammedApplyExpr
         3: dup
         4: aload_1
         5: aload_2
         6: aload_3
         7: iload         4
         9: invokespecial #38                 // Method org/scalatest/diagrams/DiagrammedApplyExpr."<init>":(Lorg/scalatest/diagrams/DiagrammedExpr;Lscala/collection/immutable/List;Ljava/lang/Object;I)V
        12: areturn
      LineNumberTable:
        line 72: 0
      LocalVariableTable:
        Start  Length  Slot  Name   Signature
            0      13     0  this   Lorg/scalatest/diagrams/DiagrammedExpr$;
            0      13     1 qualifier   Lorg/scalatest/diagrams/DiagrammedExpr;
            0      13     2  args   Lscala/collection/immutable/List;
            0      13     3 value   Ljava/lang/Object;
            0      13     4 anchor   I
    Signature: #30                          // <T:Ljava/lang/Object;>(Lorg/scalatest/diagrams/DiagrammedExpr<*>;Lscala/collection/immutable/List<Lorg/scalatest/diagrams/DiagrammedExpr<*>;>;TT;I)Lorg/scalatest/diagrams/DiagrammedExpr<TT;>;
    MethodParameters:
      Name                           Flags
      qualifier                      final
      args                           final
      value                          final
      anchor                         final

  public <T extends java.lang.Object> org.scalatest.diagrams.DiagrammedExpr<T> selectExpr(org.scalatest.diagrams.DiagrammedExpr<?>, T, int);
    descriptor: (Lorg/scalatest/diagrams/DiagrammedExpr;Ljava/lang/Object;I)Lorg/scalatest/diagrams/DiagrammedExpr;
    flags: (0x0001) ACC_PUBLIC
    Code:
      stack=5, locals=4, args_size=4
         0: new           #45                 // class org/scalatest/diagrams/DiagrammedSelectExpr
         3: dup
         4: aload_1
         5: aload_2
         6: iload_3
         7: invokespecial #48                 // Method org/scalatest/diagrams/DiagrammedSelectExpr."<init>":(Lorg/scalatest/diagrams/DiagrammedExpr;Ljava/lang/Object;I)V
        10: areturn
      LineNumberTable:
        line 83: 0
      LocalVariableTable:
        Start  Length  Slot  Name   Signature
            0      11     0  this   Lorg/scalatest/diagrams/DiagrammedExpr$;
            0      11     1 qualifier   Lorg/scalatest/diagrams/DiagrammedExpr;
            0      11     2 value   Ljava/lang/Object;
            0      11     3 anchor   I
    Signature: #43                          // <T:Ljava/lang/Object;>(Lorg/scalatest/diagrams/DiagrammedExpr<*>;TT;I)Lorg/scalatest/diagrams/DiagrammedExpr<TT;>;
    MethodParameters:
      Name                           Flags
      qualifier                      final
      value                          final
      anchor                         final

  private org.scalatest.diagrams.DiagrammedExpr$();
    descriptor: ()V
    flags: (0x0002) ACC_PRIVATE
    Code:
      stack=1, locals=1, args_size=1
         0: aload_0
         1: invokespecial #49                 // Method java/lang/Object."<init>":()V
         4: return
      LineNumberTable:
        line 86: 0
        line 51: 4
      LocalVariableTable:
        Start  Length  Slot  Name   Signature
            0       5     0  this   Lorg/scalatest/diagrams/DiagrammedExpr$;
}
SourceFile: "DiagrammedExpr.scala"
  ScalaInlineInfo: length = 0x18 (unknown attribute)
   01 01 00 04 00 0A 00 09 01 00 1C 00 1D 01 00 29
   00 2A 01 00 0F 00 10 01
  Scala: length = 0x0 (unknown attribute)

