Classfile /Users/mw/Projects/slang-braindump/.jar/jar11/assemble/slang-braindump/assemble/content/org/scalatest/diagrams/DiagrammedApplyExpr.class
  Last modified May 29, 2022; size 5262 bytes
  SHA-256 checksum 337207762d40e9e12a6abc5e0da422e497b6dfdb736c6a42e23261b5ffd7d8ff
  Compiled from "DiagrammedExpr.scala"
public class org.scalatest.diagrams.DiagrammedApplyExpr<T extends java.lang.Object> extends java.lang.Object implements org.scalatest.diagrams.DiagrammedExpr<T>
  minor version: 0
  major version: 52
  flags: (0x0021) ACC_PUBLIC, ACC_SUPER
  this_class: #2                          // org/scalatest/diagrams/DiagrammedApplyExpr
  super_class: #5                         // java/lang/Object
  interfaces: 1, fields: 4, methods: 9, attributes: 7
Constant pool:
    #1 = Utf8               org/scalatest/diagrams/DiagrammedApplyExpr
    #2 = Class              #1            // org/scalatest/diagrams/DiagrammedApplyExpr
    #3 = Utf8               <T:Ljava/lang/Object;>Ljava/lang/Object;Lorg/scalatest/diagrams/DiagrammedExpr<TT;>;
    #4 = Utf8               java/lang/Object
    #5 = Class              #4            // java/lang/Object
    #6 = Utf8               org/scalatest/diagrams/DiagrammedExpr
    #7 = Class              #6            // org/scalatest/diagrams/DiagrammedExpr
    #8 = Utf8               DiagrammedExpr.scala
    #9 = Utf8               Lscala/reflect/ScalaSignature;
   #10 = Utf8               bytes
   #11 = Utf8               \u0006\u0005\u00154Q!\u0003\u0006\u0001\u0015AA\u0001\u0002\u000b\u0001\u0003\u0002\u0003\u0006I!\u000b\u0005\t]\u0001\u0011\t\u0011)A\u0005_!A\u0001\t\u0001BC\u0002\u0013\u0005\u0011\t\u0003\u0005C\u0001\t\u0005\t\u0015!\u0003\u001d\u0011!\u0019\u0005A!b\u0001\n\u0003!\u0005\u0002\u0003%\u0001\u0005\u0003\u0005\u000b\u0011B#\t\u000b%\u0003A\u0011\u0001&\t\u000be\u0003A\u0011\u0001.\u0003\'\u0011K\u0017m\u001a:b[6,G-\u00119qYf,\u0005\u0010\u001d:\u000b\u0005-a\u0011\u0001\u00033jC\u001e\u0014\u0018-\\:\u000b\u00055q\u0011!C:dC2\fG/Z:u\u0015\u0005y\u0011aA8sOV\u0011\u0011CH\n\u0004\u0001IA\u0002CA\n\u0017\u001b\u0005!\"\"A\u000b\u0002\u000bM\u001c\u0017\r\\1\n\u0005]!\"AB!osJ+g\rE\u0002\u001a5qi\u0011AC\u0005\u00037)\u0011a\u0002R5bOJ\fW.\\3e\u000bb\u0004(\u000f\u0005\u0002\u001e=1\u0001A!B\u0010\u0001\u0005\u0004\t#!\u0001+\u0004\u0001E\u0011!%\n\t\u0003\'\rJ!\u0001\n\u000b\u0003\u000f9{G\u000f[5oOB\u00111CJ\u0005\u0003OQ\u00111!\u00118z\u0003%\tX/\u00197jM&,\'\u000f\r\u0002+YA\u0019\u0011DG\u0016\u0011\u0005uaC!C\u0017\u0002\u0003\u0003\u0005\tQ!\u0001\"\u0005\ryF\u0005N\u0001\u0005CJ<7\u000fE\u00021qmr!!\r\u001c\u000f\u0005I*T\"A\u001a\u000b\u0005Q\u0002\u0013A\u0002\u001fs_>$h(C\u0001\u0016\u0013\t9D#A\u0004qC\u000e\\\u0017mZ3\n\u0005eR$\u0001\u0002\'jgRT!a\u000e\u000b1\u0005qr\u0004cA\r\u001b{A\u0011QD\u0010\u0003\n\u007f\t\t\t\u0011!A\u0003\u0002\u0005\u00121a\u0018\u00136\u0003\u00151\u0018\r\\;f+\u0005a\u0012A\u0002<bYV,\u0007%\u0001\u0004b]\u000eDwN]\u000b\u0002\u000bB\u00111CR\u0005\u0003\u000fR\u00111!\u00138u\u0003\u001d\tgn\u00195pe\u0002\na\u0001P5oSRtD#B&M#^C\u0006cA\r\u00019!)\u0001f\u0002a\u0001\u001bB\u0012a\n\u0015\t\u00043iy\u0005CA\u000fQ\t%iC*!A\u0001\u0002\u000b\u0005\u0011\u0005C\u0003/\u000f\u0001\u0007!\u000bE\u00021qM\u0003$\u0001\u0016,\u0011\u0007eQR\u000b\u0005\u0002\u001e-\u0012Iq(UA\u0001\u0002\u0003\u0015\t!\t\u0005\u0006\u0001\u001e\u0001\r\u0001\b\u0005\u0006\u0007\u001e\u0001\r!R\u0001\rC:\u001c\u0007n\u001c:WC2,Xm]\u000b\u00027B\u0019A,\u00192\u000e\u0003uS!AX0\u0002\u0013%lW.\u001e;bE2,\'B\u00011\u0015\u0003)\u0019w\u000e\u001c7fGRLwN\\\u0005\u0003su\u0003\"!G2\n\u0005\u0011T!aC!oG\"|\'OV1mk\u0016\u0004
   #12 = Utf8               java/lang/invoke/MethodHandles$Lookup
   #13 = Class              #12           // java/lang/invoke/MethodHandles$Lookup
   #14 = Utf8               java/lang/invoke/MethodHandles
   #15 = Class              #14           // java/lang/invoke/MethodHandles
   #16 = Utf8               Lookup
   #17 = Utf8               qualifier
   #18 = Utf8               Lorg/scalatest/diagrams/DiagrammedExpr;
   #19 = Utf8               Lorg/scalatest/diagrams/DiagrammedExpr<*>;
   #20 = Utf8               args
   #21 = Utf8               Lscala/collection/immutable/List;
   #22 = Utf8               Lscala/collection/immutable/List<Lorg/scalatest/diagrams/DiagrammedExpr<*>;>;
   #23 = Utf8               value
   #24 = Utf8               Ljava/lang/Object;
   #25 = Utf8               TT;
   #26 = Utf8               anchor
   #27 = Utf8               I
   #28 = Utf8               eliminateDuplicates
   #29 = Utf8               (Lscala/collection/immutable/List;)Lscala/collection/immutable/List;
   #30 = Utf8               (Lscala/collection/immutable/List<Lorg/scalatest/diagrams/AnchorValue;>;)Lscala/collection/immutable/List<Lorg/scalatest/diagrams/AnchorValue;>;
   #31 = Utf8               anchorValues
   #32 = Utf8               eliminateDuplicates$
   #33 = Utf8               (Lorg/scalatest/diagrams/DiagrammedExpr;Lscala/collection/immutable/List;)Lscala/collection/immutable/List;
   #34 = NameAndType        #32:#33       // eliminateDuplicates$:(Lorg/scalatest/diagrams/DiagrammedExpr;Lscala/collection/immutable/List;)Lscala/collection/immutable/List;
   #35 = InterfaceMethodref #7.#34        // org/scalatest/diagrams/DiagrammedExpr.eliminateDuplicates$:(Lorg/scalatest/diagrams/DiagrammedExpr;Lscala/collection/immutable/List;)Lscala/collection/immutable/List;
   #36 = Utf8               this
   #37 = Utf8               Lorg/scalatest/diagrams/DiagrammedApplyExpr;
   #38 = Utf8               ()Ljava/lang/Object;
   #39 = Utf8               ()TT;
   #40 = NameAndType        #23:#24       // value:Ljava/lang/Object;
   #41 = Fieldref           #2.#40        // org/scalatest/diagrams/DiagrammedApplyExpr.value:Ljava/lang/Object;
   #42 = Utf8               ()I
   #43 = NameAndType        #26:#27       // anchor:I
   #44 = Fieldref           #2.#43        // org/scalatest/diagrams/DiagrammedApplyExpr.anchor:I
   #45 = Utf8               ()Lscala/collection/immutable/List;
   #46 = Utf8               ()Lscala/collection/immutable/List<Lorg/scalatest/diagrams/AnchorValue;>;
   #47 = NameAndType        #17:#18       // qualifier:Lorg/scalatest/diagrams/DiagrammedExpr;
   #48 = Fieldref           #2.#47        // org/scalatest/diagrams/DiagrammedApplyExpr.qualifier:Lorg/scalatest/diagrams/DiagrammedExpr;
   #49 = NameAndType        #31:#45       // anchorValues:()Lscala/collection/immutable/List;
   #50 = InterfaceMethodref #7.#49        // org/scalatest/diagrams/DiagrammedExpr.anchorValues:()Lscala/collection/immutable/List;
   #51 = NameAndType        #28:#29       // eliminateDuplicates:(Lscala/collection/immutable/List;)Lscala/collection/immutable/List;
   #52 = Methodref          #2.#51        // org/scalatest/diagrams/DiagrammedApplyExpr.eliminateDuplicates:(Lscala/collection/immutable/List;)Lscala/collection/immutable/List;
   #53 = NameAndType        #20:#21       // args:Lscala/collection/immutable/List;
   #54 = Fieldref           #2.#53        // org/scalatest/diagrams/DiagrammedApplyExpr.args:Lscala/collection/immutable/List;
   #55 = Utf8               (Ljava/lang/Object;)Ljava/lang/Object;
   #56 = MethodType         #55           //  (Ljava/lang/Object;)Ljava/lang/Object;
   #57 = Utf8               $anonfun$anchorValues$1
   #58 = Utf8               (Lorg/scalatest/diagrams/DiagrammedApplyExpr;Lorg/scalatest/diagrams/DiagrammedExpr;)Lscala/collection/immutable/List;
   #59 = NameAndType        #57:#58       // $anonfun$anchorValues$1:(Lorg/scalatest/diagrams/DiagrammedApplyExpr;Lorg/scalatest/diagrams/DiagrammedExpr;)Lscala/collection/immutable/List;
   #60 = Methodref          #2.#59        // org/scalatest/diagrams/DiagrammedApplyExpr.$anonfun$anchorValues$1:(Lorg/scalatest/diagrams/DiagrammedApplyExpr;Lorg/scalatest/diagrams/DiagrammedExpr;)Lscala/collection/immutable/List;
   #61 = MethodHandle       6:#60         // REF_invokeStatic org/scalatest/diagrams/DiagrammedApplyExpr.$anonfun$anchorValues$1:(Lorg/scalatest/diagrams/DiagrammedApplyExpr;Lorg/scalatest/diagrams/DiagrammedExpr;)Lscala/collection/immutable/List;
   #62 = Utf8               (Lorg/scalatest/diagrams/DiagrammedExpr;)Lscala/collection/immutable/List;
   #63 = MethodType         #62           //  (Lorg/scalatest/diagrams/DiagrammedExpr;)Lscala/collection/immutable/List;
   #64 = Integer            5
   #65 = Integer            1
   #66 = Utf8               java/lang/invoke/LambdaMetafactory
   #67 = Class              #66           // java/lang/invoke/LambdaMetafactory
   #68 = Utf8               altMetafactory
   #69 = Utf8               (Ljava/lang/invoke/MethodHandles$Lookup;Ljava/lang/String;Ljava/lang/invoke/MethodType;[Ljava/lang/Object;)Ljava/lang/invoke/CallSite;
   #70 = NameAndType        #68:#69       // altMetafactory:(Ljava/lang/invoke/MethodHandles$Lookup;Ljava/lang/String;Ljava/lang/invoke/MethodType;[Ljava/lang/Object;)Ljava/lang/invoke/CallSite;
   #71 = Methodref          #67.#70       // java/lang/invoke/LambdaMetafactory.altMetafactory:(Ljava/lang/invoke/MethodHandles$Lookup;Ljava/lang/String;Ljava/lang/invoke/MethodType;[Ljava/lang/Object;)Ljava/lang/invoke/CallSite;
   #72 = MethodHandle       6:#71         // REF_invokeStatic java/lang/invoke/LambdaMetafactory.altMetafactory:(Ljava/lang/invoke/MethodHandles$Lookup;Ljava/lang/String;Ljava/lang/invoke/MethodType;[Ljava/lang/Object;)Ljava/lang/invoke/CallSite;
   #73 = Utf8               apply
   #74 = Utf8               (Lorg/scalatest/diagrams/DiagrammedApplyExpr;)Lscala/Function1;
   #75 = NameAndType        #73:#74       // apply:(Lorg/scalatest/diagrams/DiagrammedApplyExpr;)Lscala/Function1;
   #76 = InvokeDynamic      #0:#75        // #0:apply:(Lorg/scalatest/diagrams/DiagrammedApplyExpr;)Lscala/Function1;
   #77 = Utf8               scala/collection/immutable/List
   #78 = Class              #77           // scala/collection/immutable/List
   #79 = Utf8               flatMap
   #80 = Utf8               (Lscala/Function1;)Lscala/collection/immutable/List;
   #81 = NameAndType        #79:#80       // flatMap:(Lscala/Function1;)Lscala/collection/immutable/List;
   #82 = Methodref          #78.#81       // scala/collection/immutable/List.flatMap:(Lscala/Function1;)Lscala/collection/immutable/List;
   #83 = Utf8               toList
   #84 = NameAndType        #83:#45       // toList:()Lscala/collection/immutable/List;
   #85 = Methodref          #78.#84       // scala/collection/immutable/List.toList:()Lscala/collection/immutable/List;
   #86 = Utf8               org/scalatest/diagrams/AnchorValue
   #87 = Class              #86           // org/scalatest/diagrams/AnchorValue
   #88 = NameAndType        #26:#42       // anchor:()I
   #89 = Methodref          #2.#88        // org/scalatest/diagrams/DiagrammedApplyExpr.anchor:()I
   #90 = NameAndType        #23:#38       // value:()Ljava/lang/Object;
   #91 = Methodref          #2.#90        // org/scalatest/diagrams/DiagrammedApplyExpr.value:()Ljava/lang/Object;
   #92 = Utf8               <init>
   #93 = Utf8               (ILjava/lang/Object;)V
   #94 = NameAndType        #92:#93       // "<init>":(ILjava/lang/Object;)V
   #95 = Methodref          #87.#94       // org/scalatest/diagrams/AnchorValue."<init>":(ILjava/lang/Object;)V
   #96 = Utf8               $anonfun$anchorValues$2$adapted
   #97 = Utf8               (Lorg/scalatest/diagrams/AnchorValue;)Ljava/lang/Object;
   #98 = NameAndType        #96:#97       // $anonfun$anchorValues$2$adapted:(Lorg/scalatest/diagrams/AnchorValue;)Ljava/lang/Object;
   #99 = Methodref          #2.#98        // org/scalatest/diagrams/DiagrammedApplyExpr.$anonfun$anchorValues$2$adapted:(Lorg/scalatest/diagrams/AnchorValue;)Ljava/lang/Object;
  #100 = MethodHandle       6:#99         // REF_invokeStatic org/scalatest/diagrams/DiagrammedApplyExpr.$anonfun$anchorValues$2$adapted:(Lorg/scalatest/diagrams/AnchorValue;)Ljava/lang/Object;
  #101 = MethodType         #97           //  (Lorg/scalatest/diagrams/AnchorValue;)Ljava/lang/Object;
  #102 = Utf8               ()Lscala/Function1;
  #103 = NameAndType        #73:#102      // apply:()Lscala/Function1;
  #104 = InvokeDynamic      #1:#103       // #1:apply:()Lscala/Function1;
  #105 = Utf8               filter
  #106 = NameAndType        #105:#80      // filter:(Lscala/Function1;)Lscala/collection/immutable/List;
  #107 = Methodref          #78.#106      // scala/collection/immutable/List.filter:(Lscala/Function1;)Lscala/collection/immutable/List;
  #108 = Utf8               $colon$colon
  #109 = Utf8               (Ljava/lang/Object;)Lscala/collection/immutable/List;
  #110 = NameAndType        #108:#109     // $colon$colon:(Ljava/lang/Object;)Lscala/collection/immutable/List;
  #111 = Methodref          #78.#110      // scala/collection/immutable/List.$colon$colon:(Ljava/lang/Object;)Lscala/collection/immutable/List;
  #112 = Utf8               $colon$colon$colon
  #113 = NameAndType        #112:#29      // $colon$colon$colon:(Lscala/collection/immutable/List;)Lscala/collection/immutable/List;
  #114 = Methodref          #78.#113      // scala/collection/immutable/List.$colon$colon$colon:(Lscala/collection/immutable/List;)Lscala/collection/immutable/List;
  #115 = Utf8               quantifierAnchorValues
  #116 = Utf8               argsAnchorValues
  #117 = Utf8               $this
  #118 = Utf8               arg
  #119 = Utf8               $anonfun$anchorValues$2
  #120 = Utf8               (Lorg/scalatest/diagrams/AnchorValue;)Z
  #121 = Utf8               x$2
  #122 = Methodref          #87.#88       // org/scalatest/diagrams/AnchorValue.anchor:()I
  #123 = Utf8               Lorg/scalatest/diagrams/AnchorValue;
  #124 = Utf8               (Lorg/scalatest/diagrams/DiagrammedExpr;Lscala/collection/immutable/List;Ljava/lang/Object;I)V
  #125 = Utf8               (Lorg/scalatest/diagrams/DiagrammedExpr<*>;Lscala/collection/immutable/List<Lorg/scalatest/diagrams/DiagrammedExpr<*>;>;TT;I)V
  #126 = Utf8               ()V
  #127 = NameAndType        #92:#126      // "<init>":()V
  #128 = Methodref          #5.#127       // java/lang/Object."<init>":()V
  #129 = Utf8               $init$
  #130 = Utf8               (Lorg/scalatest/diagrams/DiagrammedExpr;)V
  #131 = NameAndType        #129:#130     // $init$:(Lorg/scalatest/diagrams/DiagrammedExpr;)V
  #132 = InterfaceMethodref #7.#131       // org/scalatest/diagrams/DiagrammedExpr.$init$:(Lorg/scalatest/diagrams/DiagrammedExpr;)V
  #133 = NameAndType        #119:#120     // $anonfun$anchorValues$2:(Lorg/scalatest/diagrams/AnchorValue;)Z
  #134 = Methodref          #2.#133       // org/scalatest/diagrams/DiagrammedApplyExpr.$anonfun$anchorValues$2:(Lorg/scalatest/diagrams/AnchorValue;)Z
  #135 = Utf8               scala/runtime/BoxesRunTime
  #136 = Class              #135          // scala/runtime/BoxesRunTime
  #137 = Utf8               boxToBoolean
  #138 = Utf8               (Z)Ljava/lang/Boolean;
  #139 = NameAndType        #137:#138     // boxToBoolean:(Z)Ljava/lang/Boolean;
  #140 = Methodref          #136.#139     // scala/runtime/BoxesRunTime.boxToBoolean:(Z)Ljava/lang/Boolean;
  #141 = Utf8               $deserializeLambda$
  #142 = Utf8               (Ljava/lang/invoke/SerializedLambda;)Ljava/lang/Object;
  #143 = Utf8               scala/runtime/LambdaDeserialize
  #144 = Class              #143          // scala/runtime/LambdaDeserialize
  #145 = Utf8               bootstrap
  #146 = Utf8               (Ljava/lang/invoke/MethodHandles$Lookup;Ljava/lang/String;Ljava/lang/invoke/MethodType;[Ljava/lang/invoke/MethodHandle;)Ljava/lang/invoke/CallSite;
  #147 = NameAndType        #145:#146     // bootstrap:(Ljava/lang/invoke/MethodHandles$Lookup;Ljava/lang/String;Ljava/lang/invoke/MethodType;[Ljava/lang/invoke/MethodHandle;)Ljava/lang/invoke/CallSite;
  #148 = Methodref          #144.#147     // scala/runtime/LambdaDeserialize.bootstrap:(Ljava/lang/invoke/MethodHandles$Lookup;Ljava/lang/String;Ljava/lang/invoke/MethodType;[Ljava/lang/invoke/MethodHandle;)Ljava/lang/invoke/CallSite;
  #149 = MethodHandle       6:#148        // REF_invokeStatic scala/runtime/LambdaDeserialize.bootstrap:(Ljava/lang/invoke/MethodHandles$Lookup;Ljava/lang/String;Ljava/lang/invoke/MethodType;[Ljava/lang/invoke/MethodHandle;)Ljava/lang/invoke/CallSite;
  #150 = Utf8               lambdaDeserialize
  #151 = NameAndType        #150:#142     // lambdaDeserialize:(Ljava/lang/invoke/SerializedLambda;)Ljava/lang/Object;
  #152 = InvokeDynamic      #2:#151       // #2:lambdaDeserialize:(Ljava/lang/invoke/SerializedLambda;)Ljava/lang/Object;
  #153 = Utf8               Signature
  #154 = Utf8               Code
  #155 = Utf8               LineNumberTable
  #156 = Utf8               LocalVariableTable
  #157 = Utf8               MethodParameters
  #158 = Utf8               StackMapTable
  #159 = Utf8               InnerClasses
  #160 = Utf8               SourceFile
  #161 = Utf8               RuntimeVisibleAnnotations
  #162 = Utf8               BootstrapMethods
  #163 = Utf8               ScalaInlineInfo
  #164 = Utf8               ScalaSig
{
  private final org.scalatest.diagrams.DiagrammedExpr<?> qualifier;
    descriptor: Lorg/scalatest/diagrams/DiagrammedExpr;
    flags: (0x0012) ACC_PRIVATE, ACC_FINAL
    Signature: #19                          // Lorg/scalatest/diagrams/DiagrammedExpr<*>;

  private final scala.collection.immutable.List<org.scalatest.diagrams.DiagrammedExpr<?>> args;
    descriptor: Lscala/collection/immutable/List;
    flags: (0x0012) ACC_PRIVATE, ACC_FINAL
    Signature: #22                          // Lscala/collection/immutable/List<Lorg/scalatest/diagrams/DiagrammedExpr<*>;>;

  private final T value;
    descriptor: Ljava/lang/Object;
    flags: (0x0012) ACC_PRIVATE, ACC_FINAL
    Signature: #25                          // TT;

  private final int anchor;
    descriptor: I
    flags: (0x0012) ACC_PRIVATE, ACC_FINAL

  public scala.collection.immutable.List<org.scalatest.diagrams.AnchorValue> eliminateDuplicates(scala.collection.immutable.List<org.scalatest.diagrams.AnchorValue>);
    descriptor: (Lscala/collection/immutable/List;)Lscala/collection/immutable/List;
    flags: (0x0001) ACC_PUBLIC
    Code:
      stack=2, locals=2, args_size=2
         0: aload_0
         1: aload_1
         2: invokestatic  #35                 // InterfaceMethod org/scalatest/diagrams/DiagrammedExpr.eliminateDuplicates$:(Lorg/scalatest/diagrams/DiagrammedExpr;Lscala/collection/immutable/List;)Lscala/collection/immutable/List;
         5: areturn
      LineNumberTable:
        line 90: 0
      LocalVariableTable:
        Start  Length  Slot  Name   Signature
            0       6     0  this   Lorg/scalatest/diagrams/DiagrammedApplyExpr;
            0       6     1 anchorValues   Lscala/collection/immutable/List;
    Signature: #30                          // (Lscala/collection/immutable/List<Lorg/scalatest/diagrams/AnchorValue;>;)Lscala/collection/immutable/List<Lorg/scalatest/diagrams/AnchorValue;>;
    MethodParameters:
      Name                           Flags
      anchorValues                   final

  public T value();
    descriptor: ()Ljava/lang/Object;
    flags: (0x0001) ACC_PUBLIC
    Code:
      stack=1, locals=1, args_size=1
         0: aload_0
         1: getfield      #41                 // Field value:Ljava/lang/Object;
         4: areturn
      LineNumberTable:
        line 90: 0
      LocalVariableTable:
        Start  Length  Slot  Name   Signature
            0       5     0  this   Lorg/scalatest/diagrams/DiagrammedApplyExpr;
    Signature: #39                          // ()TT;

  public int anchor();
    descriptor: ()I
    flags: (0x0001) ACC_PUBLIC
    Code:
      stack=1, locals=1, args_size=1
         0: aload_0
         1: getfield      #44                 // Field anchor:I
         4: ireturn
      LineNumberTable:
        line 90: 0
      LocalVariableTable:
        Start  Length  Slot  Name   Signature
            0       5     0  this   Lorg/scalatest/diagrams/DiagrammedApplyExpr;

  public scala.collection.immutable.List<org.scalatest.diagrams.AnchorValue> anchorValues();
    descriptor: ()Lscala/collection/immutable/List;
    flags: (0x0001) ACC_PUBLIC
    Code:
      stack=4, locals=5, args_size=1
         0: aload_0
         1: aload_0
         2: getfield      #48                 // Field qualifier:Lorg/scalatest/diagrams/DiagrammedExpr;
         5: invokeinterface #50,  1           // InterfaceMethod org/scalatest/diagrams/DiagrammedExpr.anchorValues:()Lscala/collection/immutable/List;
        10: invokevirtual #52                 // Method eliminateDuplicates:(Lscala/collection/immutable/List;)Lscala/collection/immutable/List;
        13: astore_1
        14: aload_0
        15: getfield      #54                 // Field args:Lscala/collection/immutable/List;
        18: aload_0
        19: invokedynamic #76,  0             // InvokeDynamic #0:apply:(Lorg/scalatest/diagrams/DiagrammedApplyExpr;)Lscala/Function1;
        24: invokevirtual #82                 // Method scala/collection/immutable/List.flatMap:(Lscala/Function1;)Lscala/collection/immutable/List;
        27: astore_2
        28: aload_1
        29: invokevirtual #85                 // Method scala/collection/immutable/List.toList:()Lscala/collection/immutable/List;
        32: astore_3
        33: new           #87                 // class org/scalatest/diagrams/AnchorValue
        36: dup
        37: aload_0
        38: invokevirtual #89                 // Method anchor:()I
        41: aload_0
        42: invokevirtual #91                 // Method value:()Ljava/lang/Object;
        45: invokespecial #95                 // Method org/scalatest/diagrams/AnchorValue."<init>":(ILjava/lang/Object;)V
        48: astore        4
        50: aload_2
        51: invokedynamic #104,  0            // InvokeDynamic #1:apply:()Lscala/Function1;
        56: invokevirtual #107                // Method scala/collection/immutable/List.filter:(Lscala/Function1;)Lscala/collection/immutable/List;
        59: aload         4
        61: invokevirtual #111                // Method scala/collection/immutable/List.$colon$colon:(Ljava/lang/Object;)Lscala/collection/immutable/List;
        64: aload_3
        65: invokevirtual #114                // Method scala/collection/immutable/List.$colon$colon$colon:(Lscala/collection/immutable/List;)Lscala/collection/immutable/List;
        68: areturn
      LineNumberTable:
        line 93: 0
        line 96: 14
        line 100: 28
      LocalVariableTable:
        Start  Length  Slot  Name   Signature
           14      54     1 quantifierAnchorValues   Lscala/collection/immutable/List;
           28      40     2 argsAnchorValues   Lscala/collection/immutable/List;
            0      69     0  this   Lorg/scalatest/diagrams/DiagrammedApplyExpr;
    Signature: #46                          // ()Lscala/collection/immutable/List<Lorg/scalatest/diagrams/AnchorValue;>;

  public static final scala.collection.immutable.List $anonfun$anchorValues$1(org.scalatest.diagrams.DiagrammedApplyExpr, org.scalatest.diagrams.DiagrammedExpr);
    descriptor: (Lorg/scalatest/diagrams/DiagrammedApplyExpr;Lorg/scalatest/diagrams/DiagrammedExpr;)Lscala/collection/immutable/List;
    flags: (0x1019) ACC_PUBLIC, ACC_STATIC, ACC_FINAL, ACC_SYNTHETIC
    Code:
      stack=2, locals=2, args_size=2
         0: aload_0
         1: aload_1
         2: invokeinterface #50,  1           // InterfaceMethod org/scalatest/diagrams/DiagrammedExpr.anchorValues:()Lscala/collection/immutable/List;
         7: invokevirtual #52                 // Method eliminateDuplicates:(Lscala/collection/immutable/List;)Lscala/collection/immutable/List;
        10: areturn
      LineNumberTable:
        line 97: 0
      LocalVariableTable:
        Start  Length  Slot  Name   Signature
            0      11     0 $this   Lorg/scalatest/diagrams/DiagrammedApplyExpr;
            0      11     1   arg   Lorg/scalatest/diagrams/DiagrammedExpr;
    MethodParameters:
      Name                           Flags
      $this                          final synthetic
      arg                            final

  public static final boolean $anonfun$anchorValues$2(org.scalatest.diagrams.AnchorValue);
    descriptor: (Lorg/scalatest/diagrams/AnchorValue;)Z
    flags: (0x1019) ACC_PUBLIC, ACC_STATIC, ACC_FINAL, ACC_SYNTHETIC
    Code:
      stack=2, locals=1, args_size=1
         0: aload_0
         1: invokevirtual #122                // Method org/scalatest/diagrams/AnchorValue.anchor:()I
         4: iconst_0
         5: if_icmplt     12
         8: iconst_1
         9: goto          13
        12: iconst_0
        13: ireturn
      StackMapTable: number_of_entries = 2
        frame_type = 12 /* same */
        frame_type = 64 /* same_locals_1_stack_item */
          stack = [ int ]
      LineNumberTable:
        line 100: 0
      LocalVariableTable:
        Start  Length  Slot  Name   Signature
            0      14     0   x$2   Lorg/scalatest/diagrams/AnchorValue;
    MethodParameters:
      Name                           Flags
      x$2                            final

  public org.scalatest.diagrams.DiagrammedApplyExpr(org.scalatest.diagrams.DiagrammedExpr<?>, scala.collection.immutable.List<org.scalatest.diagrams.DiagrammedExpr<?>>, T, int);
    descriptor: (Lorg/scalatest/diagrams/DiagrammedExpr;Lscala/collection/immutable/List;Ljava/lang/Object;I)V
    flags: (0x0001) ACC_PUBLIC
    Code:
      stack=2, locals=5, args_size=5
         0: aload_0
         1: aload_1
         2: putfield      #48                 // Field qualifier:Lorg/scalatest/diagrams/DiagrammedExpr;
         5: aload_0
         6: aload_2
         7: putfield      #54                 // Field args:Lscala/collection/immutable/List;
        10: aload_0
        11: aload_3
        12: putfield      #41                 // Field value:Ljava/lang/Object;
        15: aload_0
        16: iload         4
        18: putfield      #44                 // Field anchor:I
        21: aload_0
        22: invokespecial #128                // Method java/lang/Object."<init>":()V
        25: aload_0
        26: invokestatic  #132                // InterfaceMethod org/scalatest/diagrams/DiagrammedExpr.$init$:(Lorg/scalatest/diagrams/DiagrammedExpr;)V
        29: return
      LineNumberTable:
        line 90: 0
      LocalVariableTable:
        Start  Length  Slot  Name   Signature
            0      30     0  this   Lorg/scalatest/diagrams/DiagrammedApplyExpr;
            0      30     1 qualifier   Lorg/scalatest/diagrams/DiagrammedExpr;
            0      30     2  args   Lscala/collection/immutable/List;
            0      30     3 value   Ljava/lang/Object;
            0      30     4 anchor   I
    Signature: #125                         // (Lorg/scalatest/diagrams/DiagrammedExpr<*>;Lscala/collection/immutable/List<Lorg/scalatest/diagrams/DiagrammedExpr<*>;>;TT;I)V
    MethodParameters:
      Name                           Flags
      qualifier                      final
      args                           final
      value                          final
      anchor                         final

  public static final java.lang.Object $anonfun$anchorValues$2$adapted(org.scalatest.diagrams.AnchorValue);
    descriptor: (Lorg/scalatest/diagrams/AnchorValue;)Ljava/lang/Object;
    flags: (0x1019) ACC_PUBLIC, ACC_STATIC, ACC_FINAL, ACC_SYNTHETIC
    Code:
      stack=1, locals=1, args_size=1
         0: aload_0
         1: invokestatic  #134                // Method $anonfun$anchorValues$2:(Lorg/scalatest/diagrams/AnchorValue;)Z
         4: invokestatic  #140                // Method scala/runtime/BoxesRunTime.boxToBoolean:(Z)Ljava/lang/Boolean;
         7: areturn
      LineNumberTable:
        line 100: 0
      LocalVariableTable:
        Start  Length  Slot  Name   Signature
            0       8     0   x$2   Lorg/scalatest/diagrams/AnchorValue;
    MethodParameters:
      Name                           Flags
      x$2                            final

  private static java.lang.Object $deserializeLambda$(java.lang.invoke.SerializedLambda);
    descriptor: (Ljava/lang/invoke/SerializedLambda;)Ljava/lang/Object;
    flags: (0x100a) ACC_PRIVATE, ACC_STATIC, ACC_SYNTHETIC
    Code:
      stack=1, locals=1, args_size=1
         0: aload_0
         1: invokedynamic #152,  0            // InvokeDynamic #2:lambdaDeserialize:(Ljava/lang/invoke/SerializedLambda;)Ljava/lang/Object;
         6: areturn
}
InnerClasses:
  public static final #16= #13 of #15;    // Lookup=class java/lang/invoke/MethodHandles$Lookup of class java/lang/invoke/MethodHandles
Signature: #3                           // <T:Ljava/lang/Object;>Ljava/lang/Object;Lorg/scalatest/diagrams/DiagrammedExpr<TT;>;
SourceFile: "DiagrammedExpr.scala"
RuntimeVisibleAnnotations:
  0: #9(#10=s#11)
    scala.reflect.ScalaSignature(
      bytes="\u0006\u0005\u00154Q!\u0003\u0006\u0001\u0015AA\u0001\u0002\u000b\u0001\u0003\u0002\u0003\u0006I!\u000b\u0005\t]\u0001\u0011\t\u0011)A\u0005_!A\u0001\t\u0001BC\u0002\u0013\u0005\u0011\t\u0003\u0005C\u0001\t\u0005\t\u0015!\u0003\u001d\u0011!\u0019\u0005A!b\u0001\n\u0003!\u0005\u0002\u0003%\u0001\u0005\u0003\u0005\u000b\u0011B#\t\u000b%\u0003A\u0011\u0001&\t\u000be\u0003A\u0011\u0001.\u0003\'\u0011K\u0017m\u001a:b[6,G-\u00119qYf,\u0005\u0010\u001d:\u000b\u0005-a\u0011\u0001\u00033jC\u001e\u0014\u0018-\\:\u000b\u00055q\u0011!C:dC2\fG/Z:u\u0015\u0005y\u0011aA8sOV\u0011\u0011CH\n\u0004\u0001IA\u0002CA\n\u0017\u001b\u0005!\"\"A\u000b\u0002\u000bM\u001c\u0017\r\\1\n\u0005]!\"AB!osJ+g\rE\u0002\u001a5qi\u0011AC\u0005\u00037)\u0011a\u0002R5bOJ\fW.\\3e\u000bb\u0004(\u000f\u0005\u0002\u001e=1\u0001A!B\u0010\u0001\u0005\u0004\t#!\u0001+\u0004\u0001E\u0011!%\n\t\u0003\'\rJ!\u0001\n\u000b\u0003\u000f9{G\u000f[5oOB\u00111CJ\u0005\u0003OQ\u00111!\u00118z\u0003%\tX/\u00197jM&,\'\u000f\r\u0002+YA\u0019\u0011DG\u0016\u0011\u0005uaC!C\u0017\u0002\u0003\u0003\u0005\tQ!\u0001\"\u0005\ryF\u0005N\u0001\u0005CJ<7\u000fE\u00021qmr!!\r\u001c\u000f\u0005I*T\"A\u001a\u000b\u0005Q\u0002\u0013A\u0002\u001fs_>$h(C\u0001\u0016\u0013\t9D#A\u0004qC\u000e\\\u0017mZ3\n\u0005eR$\u0001\u0002\'jgRT!a\u000e\u000b1\u0005qr\u0004cA\r\u001b{A\u0011QD\u0010\u0003\n\u007f\t\t\t\u0011!A\u0003\u0002\u0005\u00121a\u0018\u00136\u0003\u00151\u0018\r\\;f+\u0005a\u0012A\u0002<bYV,\u0007%\u0001\u0004b]\u000eDwN]\u000b\u0002\u000bB\u00111CR\u0005\u0003\u000fR\u00111!\u00138u\u0003\u001d\tgn\u00195pe\u0002\na\u0001P5oSRtD#B&M#^C\u0006cA\r\u00019!)\u0001f\u0002a\u0001\u001bB\u0012a\n\u0015\t\u00043iy\u0005CA\u000fQ\t%iC*!A\u0001\u0002\u000b\u0005\u0011\u0005C\u0003/\u000f\u0001\u0007!\u000bE\u00021qM\u0003$\u0001\u0016,\u0011\u0007eQR\u000b\u0005\u0002\u001e-\u0012Iq(UA\u0001\u0002\u0003\u0015\t!\t\u0005\u0006\u0001\u001e\u0001\r\u0001\b\u0005\u0006\u0007\u001e\u0001\r!R\u0001\rC:\u001c\u0007n\u001c:WC2,Xm]\u000b\u00027B\u0019A,\u00192\u000e\u0003uS!AX0\u0002\u0013%lW.\u001e;bE2,\'B\u00011\u0015\u0003)\u0019w\u000e\u001c7fGRLwN\\\u0005\u0003su\u0003\"!G2\n\u0005\u0011T!aC!oG\"|\'OV1mk\u0016\u0004"
    )
BootstrapMethods:
  0: #72 REF_invokeStatic java/lang/invoke/LambdaMetafactory.altMetafactory:(Ljava/lang/invoke/MethodHandles$Lookup;Ljava/lang/String;Ljava/lang/invoke/MethodType;[Ljava/lang/Object;)Ljava/lang/invoke/CallSite;
    Method arguments:
      #56 (Ljava/lang/Object;)Ljava/lang/Object;
      #61 REF_invokeStatic org/scalatest/diagrams/DiagrammedApplyExpr.$anonfun$anchorValues$1:(Lorg/scalatest/diagrams/DiagrammedApplyExpr;Lorg/scalatest/diagrams/DiagrammedExpr;)Lscala/collection/immutable/List;
      #63 (Lorg/scalatest/diagrams/DiagrammedExpr;)Lscala/collection/immutable/List;
      #64 5
      #65 1
      #63 (Lorg/scalatest/diagrams/DiagrammedExpr;)Lscala/collection/immutable/List;
  1: #72 REF_invokeStatic java/lang/invoke/LambdaMetafactory.altMetafactory:(Ljava/lang/invoke/MethodHandles$Lookup;Ljava/lang/String;Ljava/lang/invoke/MethodType;[Ljava/lang/Object;)Ljava/lang/invoke/CallSite;
    Method arguments:
      #56 (Ljava/lang/Object;)Ljava/lang/Object;
      #100 REF_invokeStatic org/scalatest/diagrams/DiagrammedApplyExpr.$anonfun$anchorValues$2$adapted:(Lorg/scalatest/diagrams/AnchorValue;)Ljava/lang/Object;
      #101 (Lorg/scalatest/diagrams/AnchorValue;)Ljava/lang/Object;
      #64 5
      #65 1
      #101 (Lorg/scalatest/diagrams/AnchorValue;)Ljava/lang/Object;
  2: #149 REF_invokeStatic scala/runtime/LambdaDeserialize.bootstrap:(Ljava/lang/invoke/MethodHandles$Lookup;Ljava/lang/String;Ljava/lang/invoke/MethodType;[Ljava/lang/invoke/MethodHandle;)Ljava/lang/invoke/CallSite;
    Method arguments:
      #61 REF_invokeStatic org/scalatest/diagrams/DiagrammedApplyExpr.$anonfun$anchorValues$1:(Lorg/scalatest/diagrams/DiagrammedApplyExpr;Lorg/scalatest/diagrams/DiagrammedExpr;)Lscala/collection/immutable/List;
      #100 REF_invokeStatic org/scalatest/diagrams/DiagrammedApplyExpr.$anonfun$anchorValues$2$adapted:(Lorg/scalatest/diagrams/AnchorValue;)Ljava/lang/Object;
  ScalaInlineInfo: length = 0x2C (unknown attribute)
   01 00 00 08 00 39 00 3A 01 00 77 00 78 01 00 60
   00 61 01 00 5C 00 7C 00 00 1A 00 2A 00 00 1F 00
   2D 00 00 1C 00 1D 00 00 17 00 26 00
  ScalaSig: length = 0x3 (unknown attribute)
   05 02 00
