Classfile /Users/mw/Projects/slang-braindump/.jar/jar11/assemble/slang-braindump/assemble/content/org/sireum/logika/package$$Long2Z$.class
  Last modified May 29, 2022; size 3685 bytes
  SHA-256 checksum 55aae3a5c0d321d54f8017f31f9f0a9fa2ca1a86e34d311248a3da91bcb656a3
  Compiled from "package.scala"
public class org.sireum.logika.package$$Long2Z$
  minor version: 0
  major version: 52
  flags: (0x0021) ACC_PUBLIC, ACC_SUPER
  this_class: #2                          // org/sireum/logika/package$$Long2Z$
  super_class: #4                         // java/lang/Object
  interfaces: 0, fields: 1, methods: 17, attributes: 4
Constant pool:
    #1 = Utf8               org/sireum/logika/package$$Long2Z$
    #2 = Class              #1            // org/sireum/logika/package$$Long2Z$
    #3 = Utf8               java/lang/Object
    #4 = Class              #3            // java/lang/Object
    #5 = Utf8               package.scala
    #6 = Utf8               org/sireum/logika/package$$Long2Z
    #7 = Class              #6            // org/sireum/logika/package$$Long2Z
    #8 = Utf8               org/sireum/logika/package
    #9 = Class              #8            // org/sireum/logika/package
   #10 = Utf8               $Long2Z
   #11 = Utf8               $Long2Z$
   #12 = Utf8               MODULE$
   #13 = Utf8               Lorg/sireum/logika/package$$Long2Z$;
   #14 = Utf8               <clinit>
   #15 = Utf8               ()V
   #16 = Utf8               <init>
   #17 = NameAndType        #16:#15       // "<init>":()V
   #18 = Methodref          #2.#17        // org/sireum/logika/package$$Long2Z$."<init>":()V
   #19 = NameAndType        #12:#13       // MODULE$:Lorg/sireum/logika/package$$Long2Z$;
   #20 = Fieldref           #2.#19        // org/sireum/logika/package$$Long2Z$.MODULE$:Lorg/sireum/logika/package$$Long2Z$;
   #21 = Utf8               $less$extension
   #22 = Utf8               (JLorg/sireum/Z;)Z
   #23 = Utf8               $this
   #24 = Utf8               other
   #25 = Utf8               org/sireum/logika/package$
   #26 = Class              #25           // org/sireum/logika/package$
   #27 = Utf8               Lorg/sireum/logika/package$;
   #28 = NameAndType        #12:#27       // MODULE$:Lorg/sireum/logika/package$;
   #29 = Fieldref           #26.#28       // org/sireum/logika/package$.MODULE$:Lorg/sireum/logika/package$;
   #30 = Utf8               Z
   #31 = Utf8               (J)Lorg/sireum/Z;
   #32 = NameAndType        #30:#31       // Z:(J)Lorg/sireum/Z;
   #33 = Methodref          #26.#32       // org/sireum/logika/package$.Z:(J)Lorg/sireum/Z;
   #34 = Utf8               org/sireum/Z
   #35 = Class              #34           // org/sireum/Z
   #36 = Utf8               $less
   #37 = Utf8               (Lorg/sireum/Z;)Z
   #38 = NameAndType        #36:#37       // $less:(Lorg/sireum/Z;)Z
   #39 = InterfaceMethodref #35.#38       // org/sireum/Z.$less:(Lorg/sireum/Z;)Z
   #40 = Utf8               this
   #41 = Utf8               J
   #42 = Utf8               Lorg/sireum/Z;
   #43 = Utf8               $less$eq$extension
   #44 = Utf8               $less$eq
   #45 = NameAndType        #44:#37       // $less$eq:(Lorg/sireum/Z;)Z
   #46 = InterfaceMethodref #35.#45       // org/sireum/Z.$less$eq:(Lorg/sireum/Z;)Z
   #47 = Utf8               $greater$extension
   #48 = Utf8               $greater
   #49 = NameAndType        #48:#37       // $greater:(Lorg/sireum/Z;)Z
   #50 = InterfaceMethodref #35.#49       // org/sireum/Z.$greater:(Lorg/sireum/Z;)Z
   #51 = Utf8               $greater$eq$extension
   #52 = Utf8               $greater$eq
   #53 = NameAndType        #52:#37       // $greater$eq:(Lorg/sireum/Z;)Z
   #54 = InterfaceMethodref #35.#53       // org/sireum/Z.$greater$eq:(Lorg/sireum/Z;)Z
   #55 = Utf8               $eq$eq$eq$extension
   #56 = Utf8               org/sireum/B$
   #57 = Class              #56           // org/sireum/B$
   #58 = Utf8               Lorg/sireum/B$;
   #59 = NameAndType        #12:#58       // MODULE$:Lorg/sireum/B$;
   #60 = Fieldref           #57.#59       // org/sireum/B$.MODULE$:Lorg/sireum/B$;
   #61 = Utf8               equals
   #62 = Utf8               (Ljava/lang/Object;)Z
   #63 = NameAndType        #61:#62       // equals:(Ljava/lang/Object;)Z
   #64 = Methodref          #4.#63        // java/lang/Object.equals:(Ljava/lang/Object;)Z
   #65 = Utf8               apply
   #66 = Utf8               (Z)Z
   #67 = NameAndType        #65:#66       // apply:(Z)Z
   #68 = Methodref          #57.#67       // org/sireum/B$.apply:(Z)Z
   #69 = Utf8               $eq$bang$eq$extension
   #70 = Utf8               $plus$extension
   #71 = Utf8               (JLorg/sireum/Z;)Lorg/sireum/Z;
   #72 = Utf8               $plus
   #73 = Utf8               (Lorg/sireum/Z;)Lorg/sireum/Z;
   #74 = NameAndType        #72:#73       // $plus:(Lorg/sireum/Z;)Lorg/sireum/Z;
   #75 = InterfaceMethodref #35.#74       // org/sireum/Z.$plus:(Lorg/sireum/Z;)Lorg/sireum/Z;
   #76 = Utf8               $minus$extension
   #77 = Utf8               $minus
   #78 = NameAndType        #77:#73       // $minus:(Lorg/sireum/Z;)Lorg/sireum/Z;
   #79 = InterfaceMethodref #35.#78       // org/sireum/Z.$minus:(Lorg/sireum/Z;)Lorg/sireum/Z;
   #80 = Utf8               $times$extension
   #81 = Utf8               $times
   #82 = NameAndType        #81:#73       // $times:(Lorg/sireum/Z;)Lorg/sireum/Z;
   #83 = InterfaceMethodref #35.#82       // org/sireum/Z.$times:(Lorg/sireum/Z;)Lorg/sireum/Z;
   #84 = Utf8               $div$extension
   #85 = Utf8               $div
   #86 = NameAndType        #85:#73       // $div:(Lorg/sireum/Z;)Lorg/sireum/Z;
   #87 = InterfaceMethodref #35.#86       // org/sireum/Z.$div:(Lorg/sireum/Z;)Lorg/sireum/Z;
   #88 = Utf8               $percent$extension
   #89 = Utf8               $percent
   #90 = NameAndType        #89:#73       // $percent:(Lorg/sireum/Z;)Lorg/sireum/Z;
   #91 = InterfaceMethodref #35.#90       // org/sireum/Z.$percent:(Lorg/sireum/Z;)Lorg/sireum/Z;
   #92 = Utf8               to$extension
   #93 = Utf8               (JLorg/sireum/Z;)Lorg/sireum/ZRange;
   #94 = Utf8               (JLorg/sireum/Z;)Lorg/sireum/ZRange<Lorg/sireum/Z;>;
   #95 = Utf8               to
   #96 = Utf8               (Lorg/sireum/ZLike;)Lorg/sireum/ZRange;
   #97 = NameAndType        #95:#96       // to:(Lorg/sireum/ZLike;)Lorg/sireum/ZRange;
   #98 = InterfaceMethodref #35.#97       // org/sireum/Z.to:(Lorg/sireum/ZLike;)Lorg/sireum/ZRange;
   #99 = Utf8               until$extension
  #100 = Utf8               until
  #101 = NameAndType        #100:#96      // until:(Lorg/sireum/ZLike;)Lorg/sireum/ZRange;
  #102 = InterfaceMethodref #35.#101      // org/sireum/Z.until:(Lorg/sireum/ZLike;)Lorg/sireum/ZRange;
  #103 = Utf8               hashCode$extension
  #104 = Utf8               (J)I
  #105 = Utf8               java/lang/Long
  #106 = Class              #105          // java/lang/Long
  #107 = Utf8               hashCode
  #108 = NameAndType        #107:#104     // hashCode:(J)I
  #109 = Methodref          #106.#108     // java/lang/Long.hashCode:(J)I
  #110 = Utf8               equals$extension
  #111 = Utf8               (JLjava/lang/Object;)Z
  #112 = Utf8               x$1
  #113 = Utf8               _value
  #114 = Utf8               ()J
  #115 = NameAndType        #113:#114     // _value:()J
  #116 = Methodref          #7.#115       // org/sireum/logika/package$$Long2Z._value:()J
  #117 = Utf8               Ljava/lang/Object;
  #118 = Methodref          #4.#17        // java/lang/Object."<init>":()V
  #119 = Utf8               Code
  #120 = Utf8               LineNumberTable
  #121 = Utf8               LocalVariableTable
  #122 = Utf8               MethodParameters
  #123 = Utf8               StackMapTable
  #124 = Utf8               Signature
  #125 = Utf8               InnerClasses
  #126 = Utf8               SourceFile
  #127 = Utf8               ScalaInlineInfo
  #128 = Utf8               Scala
{
  public static final org.sireum.logika.package$$Long2Z$ MODULE$;
    descriptor: Lorg/sireum/logika/package$$Long2Z$;
    flags: (0x0019) ACC_PUBLIC, ACC_STATIC, ACC_FINAL

  public static {};
    descriptor: ()V
    flags: (0x0009) ACC_PUBLIC, ACC_STATIC
    Code:
      stack=2, locals=0, args_size=0
         0: new           #2                  // class org/sireum/logika/package$$Long2Z$
         3: dup
         4: invokespecial #18                 // Method "<init>":()V
         7: putstatic     #20                 // Field MODULE$:Lorg/sireum/logika/package$$Long2Z$;
        10: return
      LineNumberTable:
        line 532: 0

  public final boolean $less$extension(long, org.sireum.Z);
    descriptor: (JLorg/sireum/Z;)Z
    flags: (0x0011) ACC_PUBLIC, ACC_FINAL
    Code:
      stack=3, locals=4, args_size=3
         0: getstatic     #29                 // Field org/sireum/logika/package$.MODULE$:Lorg/sireum/logika/package$;
         3: lload_1
         4: invokevirtual #33                 // Method org/sireum/logika/package$.Z:(J)Lorg/sireum/Z;
         7: aload_3
         8: invokeinterface #39,  2           // InterfaceMethod org/sireum/Z.$less:(Lorg/sireum/Z;)Z
        13: ireturn
      LineNumberTable:
        line 534: 0
      LocalVariableTable:
        Start  Length  Slot  Name   Signature
            0      14     0  this   Lorg/sireum/logika/package$$Long2Z$;
            0      14     1 $this   J
            0      14     3 other   Lorg/sireum/Z;
    MethodParameters:
      Name                           Flags
      $this                          final
      other                          final

  public final boolean $less$eq$extension(long, org.sireum.Z);
    descriptor: (JLorg/sireum/Z;)Z
    flags: (0x0011) ACC_PUBLIC, ACC_FINAL
    Code:
      stack=3, locals=4, args_size=3
         0: getstatic     #29                 // Field org/sireum/logika/package$.MODULE$:Lorg/sireum/logika/package$;
         3: lload_1
         4: invokevirtual #33                 // Method org/sireum/logika/package$.Z:(J)Lorg/sireum/Z;
         7: aload_3
         8: invokeinterface #46,  2           // InterfaceMethod org/sireum/Z.$less$eq:(Lorg/sireum/Z;)Z
        13: ireturn
      LineNumberTable:
        line 536: 0
      LocalVariableTable:
        Start  Length  Slot  Name   Signature
            0      14     0  this   Lorg/sireum/logika/package$$Long2Z$;
            0      14     1 $this   J
            0      14     3 other   Lorg/sireum/Z;
    MethodParameters:
      Name                           Flags
      $this                          final
      other                          final

  public final boolean $greater$extension(long, org.sireum.Z);
    descriptor: (JLorg/sireum/Z;)Z
    flags: (0x0011) ACC_PUBLIC, ACC_FINAL
    Code:
      stack=3, locals=4, args_size=3
         0: getstatic     #29                 // Field org/sireum/logika/package$.MODULE$:Lorg/sireum/logika/package$;
         3: lload_1
         4: invokevirtual #33                 // Method org/sireum/logika/package$.Z:(J)Lorg/sireum/Z;
         7: aload_3
         8: invokeinterface #50,  2           // InterfaceMethod org/sireum/Z.$greater:(Lorg/sireum/Z;)Z
        13: ireturn
      LineNumberTable:
        line 538: 0
      LocalVariableTable:
        Start  Length  Slot  Name   Signature
            0      14     0  this   Lorg/sireum/logika/package$$Long2Z$;
            0      14     1 $this   J
            0      14     3 other   Lorg/sireum/Z;
    MethodParameters:
      Name                           Flags
      $this                          final
      other                          final

  public final boolean $greater$eq$extension(long, org.sireum.Z);
    descriptor: (JLorg/sireum/Z;)Z
    flags: (0x0011) ACC_PUBLIC, ACC_FINAL
    Code:
      stack=3, locals=4, args_size=3
         0: getstatic     #29                 // Field org/sireum/logika/package$.MODULE$:Lorg/sireum/logika/package$;
         3: lload_1
         4: invokevirtual #33                 // Method org/sireum/logika/package$.Z:(J)Lorg/sireum/Z;
         7: aload_3
         8: invokeinterface #54,  2           // InterfaceMethod org/sireum/Z.$greater$eq:(Lorg/sireum/Z;)Z
        13: ireturn
      LineNumberTable:
        line 540: 0
      LocalVariableTable:
        Start  Length  Slot  Name   Signature
            0      14     0  this   Lorg/sireum/logika/package$$Long2Z$;
            0      14     1 $this   J
            0      14     3 other   Lorg/sireum/Z;
    MethodParameters:
      Name                           Flags
      $this                          final
      other                          final

  public final boolean $eq$eq$eq$extension(long, org.sireum.Z);
    descriptor: (JLorg/sireum/Z;)Z
    flags: (0x0011) ACC_PUBLIC, ACC_FINAL
    Code:
      stack=4, locals=5, args_size=3
         0: getstatic     #60                 // Field org/sireum/B$.MODULE$:Lorg/sireum/B$;
         3: getstatic     #29                 // Field org/sireum/logika/package$.MODULE$:Lorg/sireum/logika/package$;
         6: lload_1
         7: invokevirtual #33                 // Method org/sireum/logika/package$.Z:(J)Lorg/sireum/Z;
        10: aload_3
        11: astore        4
        13: dup
        14: ifnonnull     26
        17: pop
        18: aload         4
        20: ifnull        34
        23: goto          38
        26: aload         4
        28: invokevirtual #64                 // Method java/lang/Object.equals:(Ljava/lang/Object;)Z
        31: ifeq          38
        34: iconst_1
        35: goto          39
        38: iconst_0
        39: invokevirtual #68                 // Method org/sireum/B$.apply:(Z)Z
        42: ireturn
      StackMapTable: number_of_entries = 4
        frame_type = 255 /* full_frame */
          offset_delta = 26
          locals = [ class org/sireum/logika/package$$Long2Z$, long, class org/sireum/Z, class org/sireum/Z ]
          stack = [ class org/sireum/B$, class org/sireum/Z ]
        frame_type = 71 /* same_locals_1_stack_item */
          stack = [ class org/sireum/B$ ]
        frame_type = 67 /* same_locals_1_stack_item */
          stack = [ class org/sireum/B$ ]
        frame_type = 255 /* full_frame */
          offset_delta = 0
          locals = [ class org/sireum/logika/package$$Long2Z$, long, class org/sireum/Z, class org/sireum/Z ]
          stack = [ class org/sireum/B$, int ]
      LineNumberTable:
        line 542: 0
      LocalVariableTable:
        Start  Length  Slot  Name   Signature
            0      43     0  this   Lorg/sireum/logika/package$$Long2Z$;
            0      43     1 $this   J
            0      43     3 other   Lorg/sireum/Z;
    MethodParameters:
      Name                           Flags
      $this                          final
      other                          final

  public final boolean $eq$bang$eq$extension(long, org.sireum.Z);
    descriptor: (JLorg/sireum/Z;)Z
    flags: (0x0011) ACC_PUBLIC, ACC_FINAL
    Code:
      stack=4, locals=5, args_size=3
         0: getstatic     #60                 // Field org/sireum/B$.MODULE$:Lorg/sireum/B$;
         3: getstatic     #29                 // Field org/sireum/logika/package$.MODULE$:Lorg/sireum/logika/package$;
         6: lload_1
         7: invokevirtual #33                 // Method org/sireum/logika/package$.Z:(J)Lorg/sireum/Z;
        10: aload_3
        11: astore        4
        13: dup
        14: ifnonnull     26
        17: pop
        18: aload         4
        20: ifnull        38
        23: goto          34
        26: aload         4
        28: invokevirtual #64                 // Method java/lang/Object.equals:(Ljava/lang/Object;)Z
        31: ifne          38
        34: iconst_1
        35: goto          39
        38: iconst_0
        39: invokevirtual #68                 // Method org/sireum/B$.apply:(Z)Z
        42: ireturn
      StackMapTable: number_of_entries = 4
        frame_type = 255 /* full_frame */
          offset_delta = 26
          locals = [ class org/sireum/logika/package$$Long2Z$, long, class org/sireum/Z, class org/sireum/Z ]
          stack = [ class org/sireum/B$, class org/sireum/Z ]
        frame_type = 71 /* same_locals_1_stack_item */
          stack = [ class org/sireum/B$ ]
        frame_type = 67 /* same_locals_1_stack_item */
          stack = [ class org/sireum/B$ ]
        frame_type = 255 /* full_frame */
          offset_delta = 0
          locals = [ class org/sireum/logika/package$$Long2Z$, long, class org/sireum/Z, class org/sireum/Z ]
          stack = [ class org/sireum/B$, int ]
      LineNumberTable:
        line 544: 0
      LocalVariableTable:
        Start  Length  Slot  Name   Signature
            0      43     0  this   Lorg/sireum/logika/package$$Long2Z$;
            0      43     1 $this   J
            0      43     3 other   Lorg/sireum/Z;
    MethodParameters:
      Name                           Flags
      $this                          final
      other                          final

  public final org.sireum.Z $plus$extension(long, org.sireum.Z);
    descriptor: (JLorg/sireum/Z;)Lorg/sireum/Z;
    flags: (0x0011) ACC_PUBLIC, ACC_FINAL
    Code:
      stack=3, locals=4, args_size=3
         0: getstatic     #29                 // Field org/sireum/logika/package$.MODULE$:Lorg/sireum/logika/package$;
         3: lload_1
         4: invokevirtual #33                 // Method org/sireum/logika/package$.Z:(J)Lorg/sireum/Z;
         7: aload_3
         8: invokeinterface #75,  2           // InterfaceMethod org/sireum/Z.$plus:(Lorg/sireum/Z;)Lorg/sireum/Z;
        13: areturn
      LineNumberTable:
        line 546: 0
      LocalVariableTable:
        Start  Length  Slot  Name   Signature
            0      14     0  this   Lorg/sireum/logika/package$$Long2Z$;
            0      14     1 $this   J
            0      14     3 other   Lorg/sireum/Z;
    MethodParameters:
      Name                           Flags
      $this                          final
      other                          final

  public final org.sireum.Z $minus$extension(long, org.sireum.Z);
    descriptor: (JLorg/sireum/Z;)Lorg/sireum/Z;
    flags: (0x0011) ACC_PUBLIC, ACC_FINAL
    Code:
      stack=3, locals=4, args_size=3
         0: getstatic     #29                 // Field org/sireum/logika/package$.MODULE$:Lorg/sireum/logika/package$;
         3: lload_1
         4: invokevirtual #33                 // Method org/sireum/logika/package$.Z:(J)Lorg/sireum/Z;
         7: aload_3
         8: invokeinterface #79,  2           // InterfaceMethod org/sireum/Z.$minus:(Lorg/sireum/Z;)Lorg/sireum/Z;
        13: areturn
      LineNumberTable:
        line 548: 0
      LocalVariableTable:
        Start  Length  Slot  Name   Signature
            0      14     0  this   Lorg/sireum/logika/package$$Long2Z$;
            0      14     1 $this   J
            0      14     3 other   Lorg/sireum/Z;
    MethodParameters:
      Name                           Flags
      $this                          final
      other                          final

  public final org.sireum.Z $times$extension(long, org.sireum.Z);
    descriptor: (JLorg/sireum/Z;)Lorg/sireum/Z;
    flags: (0x0011) ACC_PUBLIC, ACC_FINAL
    Code:
      stack=3, locals=4, args_size=3
         0: getstatic     #29                 // Field org/sireum/logika/package$.MODULE$:Lorg/sireum/logika/package$;
         3: lload_1
         4: invokevirtual #33                 // Method org/sireum/logika/package$.Z:(J)Lorg/sireum/Z;
         7: aload_3
         8: invokeinterface #83,  2           // InterfaceMethod org/sireum/Z.$times:(Lorg/sireum/Z;)Lorg/sireum/Z;
        13: areturn
      LineNumberTable:
        line 550: 0
      LocalVariableTable:
        Start  Length  Slot  Name   Signature
            0      14     0  this   Lorg/sireum/logika/package$$Long2Z$;
            0      14     1 $this   J
            0      14     3 other   Lorg/sireum/Z;
    MethodParameters:
      Name                           Flags
      $this                          final
      other                          final

  public final org.sireum.Z $div$extension(long, org.sireum.Z);
    descriptor: (JLorg/sireum/Z;)Lorg/sireum/Z;
    flags: (0x0011) ACC_PUBLIC, ACC_FINAL
    Code:
      stack=3, locals=4, args_size=3
         0: getstatic     #29                 // Field org/sireum/logika/package$.MODULE$:Lorg/sireum/logika/package$;
         3: lload_1
         4: invokevirtual #33                 // Method org/sireum/logika/package$.Z:(J)Lorg/sireum/Z;
         7: aload_3
         8: invokeinterface #87,  2           // InterfaceMethod org/sireum/Z.$div:(Lorg/sireum/Z;)Lorg/sireum/Z;
        13: areturn
      LineNumberTable:
        line 552: 0
      LocalVariableTable:
        Start  Length  Slot  Name   Signature
            0      14     0  this   Lorg/sireum/logika/package$$Long2Z$;
            0      14     1 $this   J
            0      14     3 other   Lorg/sireum/Z;
    MethodParameters:
      Name                           Flags
      $this                          final
      other                          final

  public final org.sireum.Z $percent$extension(long, org.sireum.Z);
    descriptor: (JLorg/sireum/Z;)Lorg/sireum/Z;
    flags: (0x0011) ACC_PUBLIC, ACC_FINAL
    Code:
      stack=3, locals=4, args_size=3
         0: getstatic     #29                 // Field org/sireum/logika/package$.MODULE$:Lorg/sireum/logika/package$;
         3: lload_1
         4: invokevirtual #33                 // Method org/sireum/logika/package$.Z:(J)Lorg/sireum/Z;
         7: aload_3
         8: invokeinterface #91,  2           // InterfaceMethod org/sireum/Z.$percent:(Lorg/sireum/Z;)Lorg/sireum/Z;
        13: areturn
      LineNumberTable:
        line 554: 0
      LocalVariableTable:
        Start  Length  Slot  Name   Signature
            0      14     0  this   Lorg/sireum/logika/package$$Long2Z$;
            0      14     1 $this   J
            0      14     3 other   Lorg/sireum/Z;
    MethodParameters:
      Name                           Flags
      $this                          final
      other                          final

  public final org.sireum.ZRange<org.sireum.Z> to$extension(long, org.sireum.Z);
    descriptor: (JLorg/sireum/Z;)Lorg/sireum/ZRange;
    flags: (0x0011) ACC_PUBLIC, ACC_FINAL
    Code:
      stack=3, locals=4, args_size=3
         0: getstatic     #29                 // Field org/sireum/logika/package$.MODULE$:Lorg/sireum/logika/package$;
         3: lload_1
         4: invokevirtual #33                 // Method org/sireum/logika/package$.Z:(J)Lorg/sireum/Z;
         7: aload_3
         8: invokeinterface #98,  2           // InterfaceMethod org/sireum/Z.to:(Lorg/sireum/ZLike;)Lorg/sireum/ZRange;
        13: areturn
      LineNumberTable:
        line 556: 0
      LocalVariableTable:
        Start  Length  Slot  Name   Signature
            0      14     0  this   Lorg/sireum/logika/package$$Long2Z$;
            0      14     1 $this   J
            0      14     3 other   Lorg/sireum/Z;
    Signature: #94                          // (JLorg/sireum/Z;)Lorg/sireum/ZRange<Lorg/sireum/Z;>;
    MethodParameters:
      Name                           Flags
      $this                          final
      other                          final

  public final org.sireum.ZRange<org.sireum.Z> until$extension(long, org.sireum.Z);
    descriptor: (JLorg/sireum/Z;)Lorg/sireum/ZRange;
    flags: (0x0011) ACC_PUBLIC, ACC_FINAL
    Code:
      stack=3, locals=4, args_size=3
         0: getstatic     #29                 // Field org/sireum/logika/package$.MODULE$:Lorg/sireum/logika/package$;
         3: lload_1
         4: invokevirtual #33                 // Method org/sireum/logika/package$.Z:(J)Lorg/sireum/Z;
         7: aload_3
         8: invokeinterface #102,  2          // InterfaceMethod org/sireum/Z.until:(Lorg/sireum/ZLike;)Lorg/sireum/ZRange;
        13: areturn
      LineNumberTable:
        line 558: 0
      LocalVariableTable:
        Start  Length  Slot  Name   Signature
            0      14     0  this   Lorg/sireum/logika/package$$Long2Z$;
            0      14     1 $this   J
            0      14     3 other   Lorg/sireum/Z;
    Signature: #94                          // (JLorg/sireum/Z;)Lorg/sireum/ZRange<Lorg/sireum/Z;>;
    MethodParameters:
      Name                           Flags
      $this                          final
      other                          final

  public final int hashCode$extension(long);
    descriptor: (J)I
    flags: (0x0011) ACC_PUBLIC, ACC_FINAL
    Code:
      stack=2, locals=3, args_size=2
         0: lload_1
         1: invokestatic  #109                // Method java/lang/Long.hashCode:(J)I
         4: ireturn
      LineNumberTable:
        line 532: 0
      LocalVariableTable:
        Start  Length  Slot  Name   Signature
            0       5     0  this   Lorg/sireum/logika/package$$Long2Z$;
            0       5     1 $this   J
    MethodParameters:
      Name                           Flags
      $this                          final

  public final boolean equals$extension(long, java.lang.Object);
    descriptor: (JLjava/lang/Object;)Z
    flags: (0x0011) ACC_PUBLIC, ACC_FINAL
    Code:
      stack=4, locals=8, args_size=3
         0: aload_3
         1: astore        5
         3: aload         5
         5: instanceof    #7                  // class org/sireum/logika/package$$Long2Z
         8: ifeq          17
        11: iconst_1
        12: istore        4
        14: goto          26
        17: goto          20
        20: iconst_0
        21: istore        4
        23: goto          26
        26: iload         4
        28: ifeq          59
        31: aload_3
        32: checkcast     #7                  // class org/sireum/logika/package$$Long2Z
        35: invokevirtual #116                // Method org/sireum/logika/package$$Long2Z._value:()J
        38: lstore        6
        40: lload_1
        41: lload         6
        43: lcmp
        44: ifne          51
        47: iconst_1
        48: goto          52
        51: iconst_0
        52: ifeq          59
        55: iconst_1
        56: goto          60
        59: iconst_0
        60: ireturn
      StackMapTable: number_of_entries = 7
        frame_type = 253 /* append */
          offset_delta = 17
          locals = [ top, class java/lang/Object ]
        frame_type = 2 /* same */
        frame_type = 255 /* full_frame */
          offset_delta = 5
          locals = [ class org/sireum/logika/package$$Long2Z$, long, class java/lang/Object, int, class java/lang/Object ]
          stack = []
        frame_type = 252 /* append */
          offset_delta = 24
          locals = [ long ]
        frame_type = 64 /* same_locals_1_stack_item */
          stack = [ int ]
        frame_type = 250 /* chop */
          offset_delta = 6
        frame_type = 64 /* same_locals_1_stack_item */
          stack = [ int ]
      LineNumberTable:
        line 532: 0
      LocalVariableTable:
        Start  Length  Slot  Name   Signature
            0      61     0  this   Lorg/sireum/logika/package$$Long2Z$;
            0      61     1 $this   J
            0      61     3   x$1   Ljava/lang/Object;
    MethodParameters:
      Name                           Flags
      $this                          final
      x$1                            final

  public org.sireum.logika.package$$Long2Z$();
    descriptor: ()V
    flags: (0x0001) ACC_PUBLIC
    Code:
      stack=1, locals=1, args_size=1
         0: aload_0
         1: invokespecial #118                // Method java/lang/Object."<init>":()V
         4: return
      LineNumberTable:
        line 532: 0
      LocalVariableTable:
        Start  Length  Slot  Name   Signature
            0       5     0  this   Lorg/sireum/logika/package$$Long2Z$;
}
InnerClasses:
  public static final #10= #7 of #9;      // $Long2Z=class org/sireum/logika/package$$Long2Z of class org/sireum/logika/package
  public static #11= #2 of #9;            // $Long2Z$=class org/sireum/logika/package$$Long2Z$ of class org/sireum/logika/package
SourceFile: "package.scala"
  ScalaInlineInfo: length = 0x54 (unknown attribute)
   01 01 00 10 00 54 00 47 05 00 45 00 16 05 00 37
   00 16 05 00 33 00 16 05 00 2F 00 16 05 00 2B 00
   16 05 00 15 00 16 05 00 4C 00 47 05 00 58 00 47
   05 00 46 00 47 05 00 50 00 47 05 00 10 00 0F 01
   00 6E 00 6F 01 00 67 00 68 01 00 5C 00 5D 05 00
   63 00 5D 05
  Scala: length = 0x0 (unknown attribute)

