Classfile /Users/mw/Projects/slang-braindump/.jar/jar8/assemble/slang-braindump/assemble/content/scala/compat/java8/converterImpl/AccumulateLongArray.class
  Last modified May 29, 2022; size 2493 bytes
  SHA-256 checksum 00a96bc8df3f6f6670ec11e2869d545115115a16df405551358206c9eedfdb90
  Compiled from "Accumulates.scala"
public final class scala.compat.java8.converterImpl.AccumulateLongArray
  minor version: 0
  major version: 52
  flags: (0x0031) ACC_PUBLIC, ACC_FINAL, ACC_SUPER
  this_class: #2                          // scala/compat/java8/converterImpl/AccumulateLongArray
  super_class: #4                         // java/lang/Object
  interfaces: 0, fields: 1, methods: 8, attributes: 4
Constant pool:
   #1 = Utf8               scala/compat/java8/converterImpl/AccumulateLongArray
   #2 = Class              #1             // scala/compat/java8/converterImpl/AccumulateLongArray
   #3 = Utf8               java/lang/Object
   #4 = Class              #3             // java/lang/Object
   #5 = Utf8               Accumulates.scala
   #6 = Utf8               Lscala/reflect/ScalaSignature;
   #7 = Utf8               bytes
   #8 = Utf8               \u0006\u0005\r4A!\u0004\b\u0003/!aA\u0004\u0001C\u0001\u0002\u000b\u0015)\u0019!C\u0005;!IA\u0005\u0001B\u0003\u0002\u0003\u0006IA\b\u0005\u0006K\u0001!\tA\n\u0005\u0006W\u0001!\t\u0001\f\u0005\b\u0003\u0002\t\t\u0011\"\u0011C\u0011\u001d1\u0005!!A\u0005B\u001d;q\u0001\u0015\b\u0002\u0002#\u0005\u0011KB\u0004\u000e\u001d\u0005\u0005\t\u0012\u0001*\t\u000b\u0015BA\u0011\u0001,\t\u000b]CAQ\u0001-\t\u000fmC\u0011\u0011!C\u00039\"9a\fCA\u0001\n\u000by&aE!dGVlW\u000f\\1uK2{gnZ!se\u0006L(BA\b\u0011\u00035\u0019wN\u001c<feR,\'/S7qY*\u0011\u0011CE\u0001\u0006U\u00064\u0018\r\u000f\u0006\u0003\'Q\taaY8na\u0006$(\"A\u000b\u0002\u000bM\u001c\u0017\r\\1\u0004\u0001M\u0011\u0001\u0001\u0007\t\u00033ii\u0011\u0001F\u0005\u00037Q\u0011a!\u00118z-\u0006d\u0017\u0001Q:dC2\fGeY8na\u0006$HE[1wCb\"3m\u001c8wKJ$XM]%na2$\u0013iY2v[Vd\u0017\r^3M_:<\u0017I\u001d:bs\u0012\"SO\u001c3fe2L\u0018N\\4\u0016\u0003y\u00012!G\u0010\"\u0013\t\u0001CCA\u0003BeJ\f\u0017\u0010\u0005\u0002\u001aE%\u00111\u0005\u0006\u0002\u0005\u0019>tw-A!tG\u0006d\u0017\rJ2p[B\fG\u000f\n6bm\u0006DDeY8om\u0016\u0014H/\u001a:J[BdG%Q2dk6,H.\u0019;f\u0019>tw-\u0011:sCf$C%\u001e8eKJd\u00170\u001b8hA\u00051A(\u001b8jiz\"\"aJ\u0015\u0011\u0005!\u0002Q\"\u0001\b\t\u000b)\u001a\u0001\u0019\u0001\u0010\u0002\u0015UtG-\u001a:ms&tw-\u0001\u0006bG\u000e,X.\u001e7bi\u0016,\u0012!\f\t\u0003]yr!aL\u001e\u000f\u0005AJdBA\u00199\u001d\t\u0011tG\u0004\u00024m5\tAG\u0003\u00026-\u00051AH]8pizJ\u0011!F\u0005\u0003\'QI!!\u0005\n\n\u0005i\u0002\u0012AD2pY2,7\r^5p]&k\u0007\u000f\\\u0005\u0003yu\nq\u0001]1dW\u0006<WM\u0003\u0002;!%\u0011q\b\u0011\u0002\u0010\u0019>tw-Q2dk6,H.\u0019;pe*\u0011A(P\u0001\tQ\u0006\u001c\bnQ8eKR\t1\t\u0005\u0002\u001a\t&\u0011Q\t\u0006\u0002\u0004\u0013:$\u0018AB3rk\u0006d7\u000f\u0006\u0002I\u0017B\u0011\u0011$S\u0005\u0003\u0015R\u0011qAQ8pY\u0016\fg\u000eC\u0004M\r\u0005\u0005\t\u0019A\'\u0002\u0007a$\u0013\u0007\u0005\u0002\u001a\u001d&\u0011q\n\u0006\u0002\u0004\u0003:L\u0018aE!dGVlW\u000f\\1uK2{gnZ!se\u0006L\bC\u0001\u0015\t\'\tA1\u000b\u0005\u0002\u001a)&\u0011Q\u000b\u0006\u0002\u0007\u0003:L(+\u001a4\u0015\u0003E\u000bA#Y2dk6,H.\u0019;fI\u0015DH/\u001a8tS>tGCA\u0017Z\u0011\u0015Q&\u00021\u0001(\u0003\u0015!C\u000f[5t\u0003IA\u0017m\u001d5D_\u0012,G%\u001a=uK:\u001c\u0018n\u001c8\u0015\u0005\tk\u0006\"\u0002.\f\u0001\u00049\u0013\u0001E3rk\u0006d7\u000fJ3yi\u0016t7/[8o)\t\u0001\'\r\u0006\u0002IC\"9A\nDA\u0001\u0002\u0004i\u0005\"\u0002.\r\u0001\u00049\u0003
   #9 = Utf8               scala$compat$java8$converterImpl$AccumulateLongArray$$underlying
  #10 = Utf8               [J
  #11 = Utf8               equals$extension
  #12 = Utf8               ([JLjava/lang/Object;)Z
  #13 = Utf8               $this
  #14 = Utf8               x$1
  #15 = Utf8               scala/compat/java8/converterImpl/AccumulateLongArray$
  #16 = Class              #15            // scala/compat/java8/converterImpl/AccumulateLongArray$
  #17 = Utf8               MODULE$
  #18 = Utf8               Lscala/compat/java8/converterImpl/AccumulateLongArray$;
  #19 = NameAndType        #17:#18        // MODULE$:Lscala/compat/java8/converterImpl/AccumulateLongArray$;
  #20 = Fieldref           #16.#19        // scala/compat/java8/converterImpl/AccumulateLongArray$.MODULE$:Lscala/compat/java8/converterImpl/AccumulateLongArray$;
  #21 = NameAndType        #11:#12        // equals$extension:([JLjava/lang/Object;)Z
  #22 = Methodref          #16.#21        // scala/compat/java8/converterImpl/AccumulateLongArray$.equals$extension:([JLjava/lang/Object;)Z
  #23 = Utf8               Ljava/lang/Object;
  #24 = Utf8               hashCode$extension
  #25 = Utf8               ([J)I
  #26 = NameAndType        #24:#25        // hashCode$extension:([J)I
  #27 = Methodref          #16.#26        // scala/compat/java8/converterImpl/AccumulateLongArray$.hashCode$extension:([J)I
  #28 = Utf8               accumulate$extension
  #29 = Utf8               ([J)Lscala/jdk/LongAccumulator;
  #30 = NameAndType        #28:#29        // accumulate$extension:([J)Lscala/jdk/LongAccumulator;
  #31 = Methodref          #16.#30        // scala/compat/java8/converterImpl/AccumulateLongArray$.accumulate$extension:([J)Lscala/jdk/LongAccumulator;
  #32 = Utf8               ()[J
  #33 = NameAndType        #9:#10         // scala$compat$java8$converterImpl$AccumulateLongArray$$underlying:[J
  #34 = Fieldref           #2.#33         // scala/compat/java8/converterImpl/AccumulateLongArray.scala$compat$java8$converterImpl$AccumulateLongArray$$underlying:[J
  #35 = Utf8               this
  #36 = Utf8               Lscala/compat/java8/converterImpl/AccumulateLongArray;
  #37 = Utf8               accumulate
  #38 = Utf8               ()Lscala/jdk/LongAccumulator;
  #39 = NameAndType        #9:#32         // scala$compat$java8$converterImpl$AccumulateLongArray$$underlying:()[J
  #40 = Methodref          #2.#39         // scala/compat/java8/converterImpl/AccumulateLongArray.scala$compat$java8$converterImpl$AccumulateLongArray$$underlying:()[J
  #41 = Utf8               hashCode
  #42 = Utf8               ()I
  #43 = Utf8               equals
  #44 = Utf8               (Ljava/lang/Object;)Z
  #45 = Utf8               <init>
  #46 = Utf8               ([J)V
  #47 = Utf8               underlying
  #48 = Utf8               ()V
  #49 = NameAndType        #45:#48        // "<init>":()V
  #50 = Methodref          #4.#49         // java/lang/Object."<init>":()V
  #51 = Utf8               Code
  #52 = Utf8               LocalVariableTable
  #53 = Utf8               MethodParameters
  #54 = Utf8               LineNumberTable
  #55 = Utf8               SourceFile
  #56 = Utf8               RuntimeVisibleAnnotations
  #57 = Utf8               ScalaInlineInfo
  #58 = Utf8               ScalaSig
{
  private final long[] scala$compat$java8$converterImpl$AccumulateLongArray$$underlying;
    descriptor: [J
    flags: (0x0012) ACC_PRIVATE, ACC_FINAL

  public static boolean equals$extension(long[], java.lang.Object);
    descriptor: ([JLjava/lang/Object;)Z
    flags: (0x0009) ACC_PUBLIC, ACC_STATIC
    Code:
      stack=3, locals=2, args_size=2
         0: getstatic     #20                 // Field scala/compat/java8/converterImpl/AccumulateLongArray$.MODULE$:Lscala/compat/java8/converterImpl/AccumulateLongArray$;
         3: aload_0
         4: aload_1
         5: invokevirtual #22                 // Method scala/compat/java8/converterImpl/AccumulateLongArray$.equals$extension:([JLjava/lang/Object;)Z
         8: ireturn
      LocalVariableTable:
        Start  Length  Slot  Name   Signature
            0       9     0 $this   [J
            0       9     1   x$1   Ljava/lang/Object;
    MethodParameters:
      Name                           Flags
      $this                          final
      x$1                            final

  public static int hashCode$extension(long[]);
    descriptor: ([J)I
    flags: (0x0009) ACC_PUBLIC, ACC_STATIC
    Code:
      stack=2, locals=1, args_size=1
         0: getstatic     #20                 // Field scala/compat/java8/converterImpl/AccumulateLongArray$.MODULE$:Lscala/compat/java8/converterImpl/AccumulateLongArray$;
         3: aload_0
         4: invokevirtual #27                 // Method scala/compat/java8/converterImpl/AccumulateLongArray$.hashCode$extension:([J)I
         7: ireturn
      LocalVariableTable:
        Start  Length  Slot  Name   Signature
            0       8     0 $this   [J
    MethodParameters:
      Name                           Flags
      $this                          final

  public static scala.jdk.LongAccumulator accumulate$extension(long[]);
    descriptor: ([J)Lscala/jdk/LongAccumulator;
    flags: (0x0009) ACC_PUBLIC, ACC_STATIC
    Code:
      stack=2, locals=1, args_size=1
         0: getstatic     #20                 // Field scala/compat/java8/converterImpl/AccumulateLongArray$.MODULE$:Lscala/compat/java8/converterImpl/AccumulateLongArray$;
         3: aload_0
         4: invokevirtual #31                 // Method scala/compat/java8/converterImpl/AccumulateLongArray$.accumulate$extension:([J)Lscala/jdk/LongAccumulator;
         7: areturn
      LocalVariableTable:
        Start  Length  Slot  Name   Signature
            0       8     0 $this   [J
    MethodParameters:
      Name                           Flags
      $this                          final

  public long[] scala$compat$java8$converterImpl$AccumulateLongArray$$underlying();
    descriptor: ()[J
    flags: (0x0001) ACC_PUBLIC
    Code:
      stack=1, locals=1, args_size=1
         0: aload_0
         1: getfield      #34                 // Field scala$compat$java8$converterImpl$AccumulateLongArray$$underlying:[J
         4: areturn
      LineNumberTable:
        line 45: 0
      LocalVariableTable:
        Start  Length  Slot  Name   Signature
            0       5     0  this   Lscala/compat/java8/converterImpl/AccumulateLongArray;

  public scala.jdk.LongAccumulator accumulate();
    descriptor: ()Lscala/jdk/LongAccumulator;
    flags: (0x0001) ACC_PUBLIC
    Code:
      stack=2, locals=1, args_size=1
         0: getstatic     #20                 // Field scala/compat/java8/converterImpl/AccumulateLongArray$.MODULE$:Lscala/compat/java8/converterImpl/AccumulateLongArray$;
         3: aload_0
         4: invokevirtual #40                 // Method scala$compat$java8$converterImpl$AccumulateLongArray$$underlying:()[J
         7: invokevirtual #31                 // Method scala/compat/java8/converterImpl/AccumulateLongArray$.accumulate$extension:([J)Lscala/jdk/LongAccumulator;
        10: areturn
      LineNumberTable:
        line 46: 0
      LocalVariableTable:
        Start  Length  Slot  Name   Signature
            0      11     0  this   Lscala/compat/java8/converterImpl/AccumulateLongArray;

  public int hashCode();
    descriptor: ()I
    flags: (0x0001) ACC_PUBLIC
    Code:
      stack=2, locals=1, args_size=1
         0: getstatic     #20                 // Field scala/compat/java8/converterImpl/AccumulateLongArray$.MODULE$:Lscala/compat/java8/converterImpl/AccumulateLongArray$;
         3: aload_0
         4: invokevirtual #40                 // Method scala$compat$java8$converterImpl$AccumulateLongArray$$underlying:()[J
         7: invokevirtual #27                 // Method scala/compat/java8/converterImpl/AccumulateLongArray$.hashCode$extension:([J)I
        10: ireturn
      LineNumberTable:
        line 45: 0
      LocalVariableTable:
        Start  Length  Slot  Name   Signature
            0      11     0  this   Lscala/compat/java8/converterImpl/AccumulateLongArray;

  public boolean equals(java.lang.Object);
    descriptor: (Ljava/lang/Object;)Z
    flags: (0x0001) ACC_PUBLIC
    Code:
      stack=3, locals=2, args_size=2
         0: getstatic     #20                 // Field scala/compat/java8/converterImpl/AccumulateLongArray$.MODULE$:Lscala/compat/java8/converterImpl/AccumulateLongArray$;
         3: aload_0
         4: invokevirtual #40                 // Method scala$compat$java8$converterImpl$AccumulateLongArray$$underlying:()[J
         7: aload_1
         8: invokevirtual #22                 // Method scala/compat/java8/converterImpl/AccumulateLongArray$.equals$extension:([JLjava/lang/Object;)Z
        11: ireturn
      LineNumberTable:
        line 45: 0
      LocalVariableTable:
        Start  Length  Slot  Name   Signature
            0      12     0  this   Lscala/compat/java8/converterImpl/AccumulateLongArray;
            0      12     1   x$1   Ljava/lang/Object;
    MethodParameters:
      Name                           Flags
      x$1                            final

  public scala.compat.java8.converterImpl.AccumulateLongArray(long[]);
    descriptor: ([J)V
    flags: (0x0001) ACC_PUBLIC
    Code:
      stack=2, locals=2, args_size=2
         0: aload_0
         1: aload_1
         2: putfield      #34                 // Field scala$compat$java8$converterImpl$AccumulateLongArray$$underlying:[J
         5: aload_0
         6: invokespecial #50                 // Method java/lang/Object."<init>":()V
         9: return
      LineNumberTable:
        line 45: 0
      LocalVariableTable:
        Start  Length  Slot  Name   Signature
            0      10     0  this   Lscala/compat/java8/converterImpl/AccumulateLongArray;
            0      10     1 underlying   [J
    MethodParameters:
      Name                           Flags
      underlying                     final
}
SourceFile: "Accumulates.scala"
RuntimeVisibleAnnotations:
  0: #6(#7=s#8)
    scala.reflect.ScalaSignature(
      bytes="\u0006\u0005\r4A!\u0004\b\u0003/!aA\u0004\u0001C\u0001\u0002\u000b\u0015)\u0019!C\u0005;!IA\u0005\u0001B\u0003\u0002\u0003\u0006IA\b\u0005\u0006K\u0001!\tA\n\u0005\u0006W\u0001!\t\u0001\f\u0005\b\u0003\u0002\t\t\u0011\"\u0011C\u0011\u001d1\u0005!!A\u0005B\u001d;q\u0001\u0015\b\u0002\u0002#\u0005\u0011KB\u0004\u000e\u001d\u0005\u0005\t\u0012\u0001*\t\u000b\u0015BA\u0011\u0001,\t\u000b]CAQ\u0001-\t\u000fmC\u0011\u0011!C\u00039\"9a\fCA\u0001\n\u000by&aE!dGVlW\u000f\\1uK2{gnZ!se\u0006L(BA\b\u0011\u00035\u0019wN\u001c<feR,\'/S7qY*\u0011\u0011CE\u0001\u0006U\u00064\u0018\r\u000f\u0006\u0003\'Q\taaY8na\u0006$(\"A\u000b\u0002\u000bM\u001c\u0017\r\\1\u0004\u0001M\u0011\u0001\u0001\u0007\t\u00033ii\u0011\u0001F\u0005\u00037Q\u0011a!\u00118z-\u0006d\u0017\u0001Q:dC2\fGeY8na\u0006$HE[1wCb\"3m\u001c8wKJ$XM]%na2$\u0013iY2v[Vd\u0017\r^3M_:<\u0017I\u001d:bs\u0012\"SO\u001c3fe2L\u0018N\\4\u0016\u0003y\u00012!G\u0010\"\u0013\t\u0001CCA\u0003BeJ\f\u0017\u0010\u0005\u0002\u001aE%\u00111\u0005\u0006\u0002\u0005\u0019>tw-A!tG\u0006d\u0017\rJ2p[B\fG\u000f\n6bm\u0006DDeY8om\u0016\u0014H/\u001a:J[BdG%Q2dk6,H.\u0019;f\u0019>tw-\u0011:sCf$C%\u001e8eKJd\u00170\u001b8hA\u00051A(\u001b8jiz\"\"aJ\u0015\u0011\u0005!\u0002Q\"\u0001\b\t\u000b)\u001a\u0001\u0019\u0001\u0010\u0002\u0015UtG-\u001a:ms&tw-\u0001\u0006bG\u000e,X.\u001e7bi\u0016,\u0012!\f\t\u0003]yr!aL\u001e\u000f\u0005AJdBA\u00199\u001d\t\u0011tG\u0004\u00024m5\tAG\u0003\u00026-\u00051AH]8pizJ\u0011!F\u0005\u0003\'QI!!\u0005\n\n\u0005i\u0002\u0012AD2pY2,7\r^5p]&k\u0007\u000f\\\u0005\u0003yu\nq\u0001]1dW\u0006<WM\u0003\u0002;!%\u0011q\b\u0011\u0002\u0010\u0019>tw-Q2dk6,H.\u0019;pe*\u0011A(P\u0001\tQ\u0006\u001c\bnQ8eKR\t1\t\u0005\u0002\u001a\t&\u0011Q\t\u0006\u0002\u0004\u0013:$\u0018AB3rk\u0006d7\u000f\u0006\u0002I\u0017B\u0011\u0011$S\u0005\u0003\u0015R\u0011qAQ8pY\u0016\fg\u000eC\u0004M\r\u0005\u0005\t\u0019A\'\u0002\u0007a$\u0013\u0007\u0005\u0002\u001a\u001d&\u0011q\n\u0006\u0002\u0004\u0003:L\u0018aE!dGVlW\u000f\\1uK2{gnZ!se\u0006L\bC\u0001\u0015\t\'\tA1\u000b\u0005\u0002\u001a)&\u0011Q\u000b\u0006\u0002\u0007\u0003:L(+\u001a4\u0015\u0003E\u000bA#Y2dk6,H.\u0019;fI\u0015DH/\u001a8tS>tGCA\u0017Z\u0011\u0015Q&\u00021\u0001(\u0003\u0015!C\u000f[5t\u0003IA\u0017m\u001d5D_\u0012,G%\u001a=uK:\u001c\u0018n\u001c8\u0015\u0005\tk\u0006\"\u0002.\f\u0001\u00049\u0013\u0001E3rk\u0006d7\u000fJ3yi\u0016t7/[8o)\t\u0001\'\r\u0006\u0002IC\"9A\nDA\u0001\u0002\u0004i\u0005\"\u0002.\r\u0001\u00049\u0003"
    )
  ScalaInlineInfo: length = 0x1D (unknown attribute)
   01 01 00 05 00 2D 00 2E 01 00 25 00 26 01 00 2B
   00 2C 01 00 29 00 2A 01 00 09 00 20 01
  ScalaSig: length = 0x3 (unknown attribute)
   05 02 00
