Classfile /Users/mw/Projects/slang-braindump/.jar/jar8/assemble/slang-braindump/assemble/content/scala/compat/java8/converterImpl/Priority1AccumulatorConverters.class
  Last modified May 29, 2022; size 2201 bytes
  SHA-256 checksum c28e9eda7fcf536d4a1ba11c8bb2ce4e405c95769021be9324708532991ad7f9
  Compiled from "AccumulatorConverters.scala"
public interface scala.compat.java8.converterImpl.Priority1AccumulatorConverters extends scala.compat.java8.converterImpl.Priority2AccumulatorConverters
  minor version: 0
  major version: 52
  flags: (0x0601) ACC_PUBLIC, ACC_INTERFACE, ACC_ABSTRACT
  this_class: #2                          // scala/compat/java8/converterImpl/Priority1AccumulatorConverters
  super_class: #4                         // java/lang/Object
  interfaces: 1, fields: 0, methods: 7, attributes: 4
Constant pool:
   #1 = Utf8               scala/compat/java8/converterImpl/Priority1AccumulatorConverters
   #2 = Class              #1             // scala/compat/java8/converterImpl/Priority1AccumulatorConverters
   #3 = Utf8               java/lang/Object
   #4 = Class              #3             // java/lang/Object
   #5 = Utf8               scala/compat/java8/converterImpl/Priority2AccumulatorConverters
   #6 = Class              #5             // scala/compat/java8/converterImpl/Priority2AccumulatorConverters
   #7 = Utf8               AccumulatorConverters.scala
   #8 = Utf8               Lscala/reflect/ScalaSignature;
   #9 = Utf8               bytes
  #10 = Utf8               \u0006\u0005y2q!\u0002\u0004\u0011\u0002\u0007\u0005q\u0002C\u0003\u0019\u0001\u0011\u0005\u0011\u0004C\u0003\u001e\u0001\u0011\ra\u0004C\u0003+\u0001\u0011\r1\u0006C\u00035\u0001\u0011\rQG\u0001\u0010Qe&|\'/\u001b;zc\u0005\u001b7-^7vY\u0006$xN]\"p]Z,\'\u000f^3sg*\u0011q\u0001C\u0001\u000eG>tg/\u001a:uKJLU\u000e\u001d7\u000b\u0005%Q\u0011!\u00026bm\u0006D$BA\u0006\r\u0003\u0019\u0019w.\u001c9bi*\tQ\"A\u0003tG\u0006d\u0017m\u0001\u0001\u0014\u0007\u0001\u0001B\u0003\u0005\u0002\u0012%5\tA\"\u0003\u0002\u0014\u0019\t1\u0011I\\=SK\u001a\u0004\"!\u0006\f\u000e\u0003\u0019I!a\u0006\u0004\u0003=A\u0013\u0018n\u001c:jif\u0014\u0014iY2v[Vd\u0017\r^8s\u0007>tg/\u001a:uKJ\u001c\u0018A\u0002\u0013j]&$H\u0005F\u0001\u001b!\t\t2$\u0003\u0002\u001d\u0019\t!QK\\5u\u0003U\t7mY;nk2\fG/\u001a#pk\ndW-\u0011:sCf$\"a\b\u0012\u0011\u0005U\u0001\u0013BA\u0011\u0007\u0005U\t5mY;nk2\fG/\u001a#pk\ndW-\u0011:sCfDQa\t\u0002A\u0002\u0011\n!\"\u001e8eKJd\u00170\u001b8h!\r\tReJ\u0005\u0003M1\u0011Q!\u0011:sCf\u0004\"!\u0005\u0015\n\u0005%b!A\u0002#pk\ndW-\u0001\nbG\u000e,X.\u001e7bi\u0016Le\u000e^!se\u0006LHC\u0001\u00170!\t)R&\u0003\u0002/\r\t\u0011\u0012iY2v[Vd\u0017\r^3J]R\f%O]1z\u0011\u0015\u00193\u00011\u00011!\r\tR%\r\t\u0003#IJ!a\r\u0007\u0003\u0007%sG/A\nbG\u000e,X.\u001e7bi\u0016duN\\4BeJ\f\u0017\u0010\u0006\u00027sA\u0011QcN\u0005\u0003q\u0019\u00111#Q2dk6,H.\u0019;f\u0019>tw-\u0011:sCfDQa\t\u0003A\u0002i\u00022!E\u0013<!\t\tB(\u0003\u0002>\u0019\t!Aj\u001c8h\u0001
  #11 = Utf8               accumulateDoubleArray$
  #12 = Utf8               (Lscala/compat/java8/converterImpl/Priority1AccumulatorConverters;[D)[D
  #13 = Utf8               $this
  #14 = Utf8               underlying
  #15 = Utf8               accumulateDoubleArray
  #16 = Utf8               ([D)[D
  #17 = NameAndType        #15:#16        // accumulateDoubleArray:([D)[D
  #18 = InterfaceMethodref #2.#17         // scala/compat/java8/converterImpl/Priority1AccumulatorConverters.accumulateDoubleArray:([D)[D
  #19 = Utf8               Lscala/compat/java8/converterImpl/Priority1AccumulatorConverters;
  #20 = Utf8               [D
  #21 = Utf8               this
  #22 = Utf8               accumulateIntArray$
  #23 = Utf8               (Lscala/compat/java8/converterImpl/Priority1AccumulatorConverters;[I)[I
  #24 = Utf8               accumulateIntArray
  #25 = Utf8               ([I)[I
  #26 = NameAndType        #24:#25        // accumulateIntArray:([I)[I
  #27 = InterfaceMethodref #2.#26         // scala/compat/java8/converterImpl/Priority1AccumulatorConverters.accumulateIntArray:([I)[I
  #28 = Utf8               [I
  #29 = Utf8               accumulateLongArray$
  #30 = Utf8               (Lscala/compat/java8/converterImpl/Priority1AccumulatorConverters;[J)[J
  #31 = Utf8               accumulateLongArray
  #32 = Utf8               ([J)[J
  #33 = NameAndType        #31:#32        // accumulateLongArray:([J)[J
  #34 = InterfaceMethodref #2.#33         // scala/compat/java8/converterImpl/Priority1AccumulatorConverters.accumulateLongArray:([J)[J
  #35 = Utf8               [J
  #36 = Utf8               $init$
  #37 = Utf8               (Lscala/compat/java8/converterImpl/Priority1AccumulatorConverters;)V
  #38 = Utf8               Code
  #39 = Utf8               LineNumberTable
  #40 = Utf8               LocalVariableTable
  #41 = Utf8               MethodParameters
  #42 = Utf8               SourceFile
  #43 = Utf8               RuntimeVisibleAnnotations
  #44 = Utf8               ScalaInlineInfo
  #45 = Utf8               ScalaSig
{
  public static double[] accumulateDoubleArray$(scala.compat.java8.converterImpl.Priority1AccumulatorConverters, double[]);
    descriptor: (Lscala/compat/java8/converterImpl/Priority1AccumulatorConverters;[D)[D
    flags: (0x1009) ACC_PUBLIC, ACC_STATIC, ACC_SYNTHETIC
    Code:
      stack=2, locals=2, args_size=2
         0: aload_0
         1: aload_1
         2: invokespecial #18                 // InterfaceMethod accumulateDoubleArray:([D)[D
         5: areturn
      LineNumberTable:
        line 34: 0
      LocalVariableTable:
        Start  Length  Slot  Name   Signature
            0       6     0 $this   Lscala/compat/java8/converterImpl/Priority1AccumulatorConverters;
            0       6     1 underlying   [D
    MethodParameters:
      Name                           Flags
      $this                          final synthetic
      underlying                     final

  public default double[] accumulateDoubleArray(double[]);
    descriptor: ([D)[D
    flags: (0x0001) ACC_PUBLIC
    Code:
      stack=1, locals=2, args_size=2
         0: aload_1
         1: areturn
      LineNumberTable:
        line 35: 0
      LocalVariableTable:
        Start  Length  Slot  Name   Signature
            0       2     0  this   Lscala/compat/java8/converterImpl/Priority1AccumulatorConverters;
            0       2     1 underlying   [D
    MethodParameters:
      Name                           Flags
      underlying                     final

  public static int[] accumulateIntArray$(scala.compat.java8.converterImpl.Priority1AccumulatorConverters, int[]);
    descriptor: (Lscala/compat/java8/converterImpl/Priority1AccumulatorConverters;[I)[I
    flags: (0x1009) ACC_PUBLIC, ACC_STATIC, ACC_SYNTHETIC
    Code:
      stack=2, locals=2, args_size=2
         0: aload_0
         1: aload_1
         2: invokespecial #27                 // InterfaceMethod accumulateIntArray:([I)[I
         5: areturn
      LineNumberTable:
        line 36: 0
      LocalVariableTable:
        Start  Length  Slot  Name   Signature
            0       6     0 $this   Lscala/compat/java8/converterImpl/Priority1AccumulatorConverters;
            0       6     1 underlying   [I
    MethodParameters:
      Name                           Flags
      $this                          final synthetic
      underlying                     final

  public default int[] accumulateIntArray(int[]);
    descriptor: ([I)[I
    flags: (0x0001) ACC_PUBLIC
    Code:
      stack=1, locals=2, args_size=2
         0: aload_1
         1: areturn
      LineNumberTable:
        line 37: 0
      LocalVariableTable:
        Start  Length  Slot  Name   Signature
            0       2     0  this   Lscala/compat/java8/converterImpl/Priority1AccumulatorConverters;
            0       2     1 underlying   [I
    MethodParameters:
      Name                           Flags
      underlying                     final

  public static long[] accumulateLongArray$(scala.compat.java8.converterImpl.Priority1AccumulatorConverters, long[]);
    descriptor: (Lscala/compat/java8/converterImpl/Priority1AccumulatorConverters;[J)[J
    flags: (0x1009) ACC_PUBLIC, ACC_STATIC, ACC_SYNTHETIC
    Code:
      stack=2, locals=2, args_size=2
         0: aload_0
         1: aload_1
         2: invokespecial #34                 // InterfaceMethod accumulateLongArray:([J)[J
         5: areturn
      LineNumberTable:
        line 38: 0
      LocalVariableTable:
        Start  Length  Slot  Name   Signature
            0       6     0 $this   Lscala/compat/java8/converterImpl/Priority1AccumulatorConverters;
            0       6     1 underlying   [J
    MethodParameters:
      Name                           Flags
      $this                          final synthetic
      underlying                     final

  public default long[] accumulateLongArray(long[]);
    descriptor: ([J)[J
    flags: (0x0001) ACC_PUBLIC
    Code:
      stack=1, locals=2, args_size=2
         0: aload_1
         1: areturn
      LineNumberTable:
        line 39: 0
      LocalVariableTable:
        Start  Length  Slot  Name   Signature
            0       2     0  this   Lscala/compat/java8/converterImpl/Priority1AccumulatorConverters;
            0       2     1 underlying   [J
    MethodParameters:
      Name                           Flags
      underlying                     final

  public static void $init$(scala.compat.java8.converterImpl.Priority1AccumulatorConverters);
    descriptor: (Lscala/compat/java8/converterImpl/Priority1AccumulatorConverters;)V
    flags: (0x0009) ACC_PUBLIC, ACC_STATIC
    Code:
      stack=0, locals=1, args_size=1
         0: return
      LineNumberTable:
        line 33: 0
      LocalVariableTable:
        Start  Length  Slot  Name   Signature
            0       1     0 $this   Lscala/compat/java8/converterImpl/Priority1AccumulatorConverters;
    MethodParameters:
      Name                           Flags
      $this                          final synthetic
}
SourceFile: "AccumulatorConverters.scala"
RuntimeVisibleAnnotations:
  0: #8(#9=s#10)
    scala.reflect.ScalaSignature(
      bytes="\u0006\u0005y2q!\u0002\u0004\u0011\u0002\u0007\u0005q\u0002C\u0003\u0019\u0001\u0011\u0005\u0011\u0004C\u0003\u001e\u0001\u0011\ra\u0004C\u0003+\u0001\u0011\r1\u0006C\u00035\u0001\u0011\rQG\u0001\u0010Qe&|\'/\u001b;zc\u0005\u001b7-^7vY\u0006$xN]\"p]Z,\'\u000f^3sg*\u0011q\u0001C\u0001\u000eG>tg/\u001a:uKJLU\u000e\u001d7\u000b\u0005%Q\u0011!\u00026bm\u0006D$BA\u0006\r\u0003\u0019\u0019w.\u001c9bi*\tQ\"A\u0003tG\u0006d\u0017m\u0001\u0001\u0014\u0007\u0001\u0001B\u0003\u0005\u0002\u0012%5\tA\"\u0003\u0002\u0014\u0019\t1\u0011I\\=SK\u001a\u0004\"!\u0006\f\u000e\u0003\u0019I!a\u0006\u0004\u0003=A\u0013\u0018n\u001c:jif\u0014\u0014iY2v[Vd\u0017\r^8s\u0007>tg/\u001a:uKJ\u001c\u0018A\u0002\u0013j]&$H\u0005F\u0001\u001b!\t\t2$\u0003\u0002\u001d\u0019\t!QK\\5u\u0003U\t7mY;nk2\fG/\u001a#pk\ndW-\u0011:sCf$\"a\b\u0012\u0011\u0005U\u0001\u0013BA\u0011\u0007\u0005U\t5mY;nk2\fG/\u001a#pk\ndW-\u0011:sCfDQa\t\u0002A\u0002\u0011\n!\"\u001e8eKJd\u00170\u001b8h!\r\tReJ\u0005\u0003M1\u0011Q!\u0011:sCf\u0004\"!\u0005\u0015\n\u0005%b!A\u0002#pk\ndW-\u0001\nbG\u000e,X.\u001e7bi\u0016Le\u000e^!se\u0006LHC\u0001\u00170!\t)R&\u0003\u0002/\r\t\u0011\u0012iY2v[Vd\u0017\r^3J]R\f%O]1z\u0011\u0015\u00193\u00011\u00011!\r\tR%\r\t\u0003#IJ!a\r\u0007\u0003\u0007%sG/A\nbG\u000e,X.\u001e7bi\u0016duN\\4BeJ\f\u0017\u0010\u0006\u00027sA\u0011QcN\u0005\u0003q\u0019\u00111#Q2dk6,H.\u0019;f\u0019>tw-\u0011:sCfDQa\t\u0003A\u0002i\u00022!E\u0013<!\t\tB(\u0003\u0002>\u0019\t!Aj\u001c8h\u0001"
    )
  ScalaInlineInfo: length = 0x27 (unknown attribute)
   01 00 00 07 00 24 00 25 01 00 0F 00 10 00 00 0B
   00 0C 01 00 18 00 19 00 00 16 00 17 01 00 1F 00
   20 00 00 1D 00 1E 01
  ScalaSig: length = 0x3 (unknown attribute)
   05 02 00
