Classfile /Users/mw/Projects/slang-braindump/.jar/jar11/assemble/slang-braindump/assemble/content/shapeless/syntax/std/EitherOps$.class
  Last modified May 29, 2022; size 2208 bytes
  SHA-256 checksum 15af5ee2731316811957657497b3d92511f67b164125555d44b12bb72495e329
  Compiled from "either.scala"
public final class shapeless.syntax.std.EitherOps$ implements java.io.Serializable
  minor version: 0
  major version: 52
  flags: (0x0031) ACC_PUBLIC, ACC_FINAL, ACC_SUPER
  this_class: #2                          // shapeless/syntax/std/EitherOps$
  super_class: #4                         // java/lang/Object
  interfaces: 1, fields: 1, methods: 6, attributes: 4
Constant pool:
   #1 = Utf8               shapeless/syntax/std/EitherOps$
   #2 = Class              #1             // shapeless/syntax/std/EitherOps$
   #3 = Utf8               java/lang/Object
   #4 = Class              #3             // java/lang/Object
   #5 = Utf8               java/io/Serializable
   #6 = Class              #5             // java/io/Serializable
   #7 = Utf8               either.scala
   #8 = Utf8               shapeless/ops/coproduct$EitherToCoproduct
   #9 = Class              #8             // shapeless/ops/coproduct$EitherToCoproduct
  #10 = Utf8               shapeless/ops/coproduct
  #11 = Class              #10            // shapeless/ops/coproduct
  #12 = Utf8               EitherToCoproduct
  #13 = Utf8               MODULE$
  #14 = Utf8               Lshapeless/syntax/std/EitherOps$;
  #15 = Utf8               <clinit>
  #16 = Utf8               ()V
  #17 = Utf8               <init>
  #18 = NameAndType        #17:#16        // "<init>":()V
  #19 = Methodref          #2.#18         // shapeless/syntax/std/EitherOps$."<init>":()V
  #20 = NameAndType        #13:#14        // MODULE$:Lshapeless/syntax/std/EitherOps$;
  #21 = Fieldref           #2.#20         // shapeless/syntax/std/EitherOps$.MODULE$:Lshapeless/syntax/std/EitherOps$;
  #22 = Utf8               writeReplace
  #23 = Utf8               ()Ljava/lang/Object;
  #24 = Utf8               scala/runtime/ModuleSerializationProxy
  #25 = Class              #24            // scala/runtime/ModuleSerializationProxy
  #26 = Utf8               (Ljava/lang/Class;)V
  #27 = NameAndType        #17:#26        // "<init>":(Ljava/lang/Class;)V
  #28 = Methodref          #25.#27        // scala/runtime/ModuleSerializationProxy."<init>":(Ljava/lang/Class;)V
  #29 = Utf8               this
  #30 = Utf8               toCoproduct$extension
  #31 = Utf8               (Lscala/util/Either;Lshapeless/ops/coproduct$EitherToCoproduct;)Lshapeless/Coproduct;
  #32 = Utf8               <L:Ljava/lang/Object;R:Ljava/lang/Object;>(Lscala/util/Either<TL;TR;>;Lshapeless/ops/coproduct$EitherToCoproduct<TL;TR;>;)Lshapeless/Coproduct;
  #33 = Utf8               $this
  #34 = Utf8               eitherToCoproduct
  #35 = Utf8               apply
  #36 = Utf8               (Ljava/lang/Object;)Ljava/lang/Object;
  #37 = NameAndType        #35:#36        // apply:(Ljava/lang/Object;)Ljava/lang/Object;
  #38 = InterfaceMethodref #9.#37         // shapeless/ops/coproduct$EitherToCoproduct.apply:(Ljava/lang/Object;)Ljava/lang/Object;
  #39 = Utf8               shapeless/Coproduct
  #40 = Class              #39            // shapeless/Coproduct
  #41 = Utf8               Lscala/util/Either;
  #42 = Utf8               Lshapeless/ops/coproduct$EitherToCoproduct;
  #43 = Utf8               hashCode$extension
  #44 = Utf8               (Lscala/util/Either;)I
  #45 = Utf8               <L:Ljava/lang/Object;R:Ljava/lang/Object;>(Lscala/util/Either<TL;TR;>;)I
  #46 = Utf8               scala/util/Either
  #47 = Class              #46            // scala/util/Either
  #48 = Utf8               hashCode
  #49 = Utf8               ()I
  #50 = NameAndType        #48:#49        // hashCode:()I
  #51 = Methodref          #47.#50        // scala/util/Either.hashCode:()I
  #52 = Utf8               equals$extension
  #53 = Utf8               (Lscala/util/Either;Ljava/lang/Object;)Z
  #54 = Utf8               <L:Ljava/lang/Object;R:Ljava/lang/Object;>(Lscala/util/Either<TL;TR;>;Ljava/lang/Object;)Z
  #55 = Utf8               x$1
  #56 = Utf8               shapeless/syntax/std/EitherOps
  #57 = Class              #56            // shapeless/syntax/std/EitherOps
  #58 = Utf8               e
  #59 = Utf8               ()Lscala/util/Either;
  #60 = NameAndType        #58:#59        // e:()Lscala/util/Either;
  #61 = Methodref          #57.#60        // shapeless/syntax/std/EitherOps.e:()Lscala/util/Either;
  #62 = Utf8               equals
  #63 = Utf8               (Ljava/lang/Object;)Z
  #64 = NameAndType        #62:#63        // equals:(Ljava/lang/Object;)Z
  #65 = Methodref          #4.#64         // java/lang/Object.equals:(Ljava/lang/Object;)Z
  #66 = Utf8               Ljava/lang/Object;
  #67 = Methodref          #4.#18         // java/lang/Object."<init>":()V
  #68 = Utf8               Code
  #69 = Utf8               LineNumberTable
  #70 = Utf8               LocalVariableTable
  #71 = Utf8               Signature
  #72 = Utf8               MethodParameters
  #73 = Utf8               StackMapTable
  #74 = Utf8               InnerClasses
  #75 = Utf8               SourceFile
  #76 = Utf8               ScalaInlineInfo
  #77 = Utf8               Scala
{
  public static final shapeless.syntax.std.EitherOps$ MODULE$;
    descriptor: Lshapeless/syntax/std/EitherOps$;
    flags: (0x0019) ACC_PUBLIC, ACC_STATIC, ACC_FINAL

  public static {};
    descriptor: ()V
    flags: (0x0009) ACC_PUBLIC, ACC_STATIC
    Code:
      stack=2, locals=0, args_size=0
         0: new           #2                  // class shapeless/syntax/std/EitherOps$
         3: dup
         4: invokespecial #19                 // Method "<init>":()V
         7: putstatic     #21                 // Field MODULE$:Lshapeless/syntax/std/EitherOps$;
        10: return
      LineNumberTable:
        line 9: 0

  private java.lang.Object writeReplace();
    descriptor: ()Ljava/lang/Object;
    flags: (0x0002) ACC_PRIVATE
    Code:
      stack=3, locals=1, args_size=1
         0: new           #25                 // class scala/runtime/ModuleSerializationProxy
         3: dup
         4: ldc           #2                  // class shapeless/syntax/std/EitherOps$
         6: invokespecial #28                 // Method scala/runtime/ModuleSerializationProxy."<init>":(Ljava/lang/Class;)V
         9: areturn
      LineNumberTable:
        line 9: 0
      LocalVariableTable:
        Start  Length  Slot  Name   Signature
            0      10     0  this   Lshapeless/syntax/std/EitherOps$;

  public final <L extends java.lang.Object, R extends java.lang.Object> shapeless.Coproduct toCoproduct$extension(scala.util.Either<L, R>, shapeless.ops.coproduct$EitherToCoproduct<L, R>);
    descriptor: (Lscala/util/Either;Lshapeless/ops/coproduct$EitherToCoproduct;)Lshapeless/Coproduct;
    flags: (0x0011) ACC_PUBLIC, ACC_FINAL
    Code:
      stack=2, locals=3, args_size=3
         0: aload_2
         1: aload_1
         2: invokeinterface #38,  2           // InterfaceMethod shapeless/ops/coproduct$EitherToCoproduct.apply:(Ljava/lang/Object;)Ljava/lang/Object;
         7: checkcast     #40                 // class shapeless/Coproduct
        10: areturn
      LineNumberTable:
        line 15: 0
      LocalVariableTable:
        Start  Length  Slot  Name   Signature
            0      11     0  this   Lshapeless/syntax/std/EitherOps$;
            0      11     1 $this   Lscala/util/Either;
            0      11     2 eitherToCoproduct   Lshapeless/ops/coproduct$EitherToCoproduct;
    Signature: #32                          // <L:Ljava/lang/Object;R:Ljava/lang/Object;>(Lscala/util/Either<TL;TR;>;Lshapeless/ops/coproduct$EitherToCoproduct<TL;TR;>;)Lshapeless/Coproduct;
    MethodParameters:
      Name                           Flags
      $this                          final
      eitherToCoproduct              final

  public final <L extends java.lang.Object, R extends java.lang.Object> int hashCode$extension(scala.util.Either<L, R>);
    descriptor: (Lscala/util/Either;)I
    flags: (0x0011) ACC_PUBLIC, ACC_FINAL
    Code:
      stack=1, locals=2, args_size=2
         0: aload_1
         1: invokevirtual #51                 // Method scala/util/Either.hashCode:()I
         4: ireturn
      LineNumberTable:
        line 9: 0
      LocalVariableTable:
        Start  Length  Slot  Name   Signature
            0       5     0  this   Lshapeless/syntax/std/EitherOps$;
            0       5     1 $this   Lscala/util/Either;
    Signature: #45                          // <L:Ljava/lang/Object;R:Ljava/lang/Object;>(Lscala/util/Either<TL;TR;>;)I
    MethodParameters:
      Name                           Flags
      $this                          final

  public final <L extends java.lang.Object, R extends java.lang.Object> boolean equals$extension(scala.util.Either<L, R>, java.lang.Object);
    descriptor: (Lscala/util/Either;Ljava/lang/Object;)Z
    flags: (0x0011) ACC_PUBLIC, ACC_FINAL
    Code:
      stack=2, locals=7, args_size=3
         0: aload_2
         1: astore        4
         3: aload         4
         5: instanceof    #57                 // class shapeless/syntax/std/EitherOps
         8: ifeq          16
        11: iconst_1
        12: istore_3
        13: goto          24
        16: goto          19
        19: iconst_0
        20: istore_3
        21: goto          24
        24: iload_3
        25: ifeq          83
        28: aload_2
        29: ifnonnull     36
        32: aconst_null
        33: goto          43
        36: aload_2
        37: checkcast     #57                 // class shapeless/syntax/std/EitherOps
        40: invokevirtual #61                 // Method shapeless/syntax/std/EitherOps.e:()Lscala/util/Either;
        43: astore        5
        45: aload_1
        46: aload         5
        48: astore        6
        50: dup
        51: ifnonnull     63
        54: pop
        55: aload         6
        57: ifnull        71
        60: goto          75
        63: aload         6
        65: invokevirtual #65                 // Method java/lang/Object.equals:(Ljava/lang/Object;)Z
        68: ifeq          75
        71: iconst_1
        72: goto          76
        75: iconst_0
        76: ifeq          83
        79: iconst_1
        80: goto          84
        83: iconst_0
        84: ireturn
      StackMapTable: number_of_entries = 11
        frame_type = 253 /* append */
          offset_delta = 16
          locals = [ top, class java/lang/Object ]
        frame_type = 2 /* same */
        frame_type = 255 /* full_frame */
          offset_delta = 4
          locals = [ class shapeless/syntax/std/EitherOps$, class scala/util/Either, class java/lang/Object, int, class java/lang/Object ]
          stack = []
        frame_type = 11 /* same */
        frame_type = 70 /* same_locals_1_stack_item */
          stack = [ class scala/util/Either ]
        frame_type = 255 /* full_frame */
          offset_delta = 19
          locals = [ class shapeless/syntax/std/EitherOps$, class scala/util/Either, class java/lang/Object, int, class java/lang/Object, class scala/util/Either, class scala/util/Either ]
          stack = [ class scala/util/Either ]
        frame_type = 7 /* same */
        frame_type = 3 /* same */
        frame_type = 64 /* same_locals_1_stack_item */
          stack = [ int ]
        frame_type = 249 /* chop */
          offset_delta = 6
        frame_type = 64 /* same_locals_1_stack_item */
          stack = [ int ]
      LineNumberTable:
        line 9: 0
      LocalVariableTable:
        Start  Length  Slot  Name   Signature
            0      85     0  this   Lshapeless/syntax/std/EitherOps$;
            0      85     1 $this   Lscala/util/Either;
            0      85     2   x$1   Ljava/lang/Object;
    Signature: #54                          // <L:Ljava/lang/Object;R:Ljava/lang/Object;>(Lscala/util/Either<TL;TR;>;Ljava/lang/Object;)Z
    MethodParameters:
      Name                           Flags
      $this                          final
      x$1                            final

  private shapeless.syntax.std.EitherOps$();
    descriptor: ()V
    flags: (0x0002) ACC_PRIVATE
    Code:
      stack=1, locals=1, args_size=1
         0: aload_0
         1: invokespecial #67                 // Method java/lang/Object."<init>":()V
         4: return
      LineNumberTable:
        line 9: 0
      LocalVariableTable:
        Start  Length  Slot  Name   Signature
            0       5     0  this   Lshapeless/syntax/std/EitherOps$;
}
InnerClasses:
  public static #12= #9 of #11;           // EitherToCoproduct=class shapeless/ops/coproduct$EitherToCoproduct of class shapeless/ops/coproduct
SourceFile: "either.scala"
  ScalaInlineInfo: length = 0x1D (unknown attribute)
   01 01 00 05 00 11 00 10 01 00 34 00 35 01 00 2B
   00 2C 01 00 1E 00 1F 01 00 16 00 17 01
  Scala: length = 0x0 (unknown attribute)

