Classfile /Users/mw/Projects/slang-braindump/.jar/jar11/assemble/slang-braindump/assemble/content/shapeless/syntax/std/maps.class
  Last modified May 29, 2022; size 943 bytes
  SHA-256 checksum ba46b6e13fc32be754cde2b39adb5028bdf4a8b6d8523502f44b9ccd96b8e453
  Compiled from "maps.scala"
public final class shapeless.syntax.std.maps
  minor version: 0
  major version: 52
  flags: (0x0031) ACC_PUBLIC, ACC_FINAL, ACC_SUPER
  this_class: #2                          // shapeless/syntax/std/maps
  super_class: #4                         // java/lang/Object
  interfaces: 0, fields: 0, methods: 1, attributes: 3
Constant pool:
   #1 = Utf8               shapeless/syntax/std/maps
   #2 = Class              #1             // shapeless/syntax/std/maps
   #3 = Utf8               java/lang/Object
   #4 = Class              #3             // java/lang/Object
   #5 = Utf8               maps.scala
   #6 = Utf8               Lscala/reflect/ScalaSignature;
   #7 = Utf8               bytes
   #8 = Utf8               \u0006\u0005e:Q\u0001B\u0003\t\u000211QAD\u0003\t\u0002=AQAF\u0001\u0005\u0002]AQ\u0001G\u0001\u0005\u0004e\tA!\\1qg*\u0011aaB\u0001\u0004gR$\'B\u0001\u0005\n\u0003\u0019\u0019\u0018P\u001c;bq*\t!\"A\u0005tQ\u0006\u0004X\r\\3tg\u000e\u0001\u0001CA\u0007\u0002\u001b\u0005)!\u0001B7baN\u001c\"!\u0001\t\u0011\u0005E!R\"\u0001\n\u000b\u0003M\tQa]2bY\u0006L!!\u0006\n\u0003\r\u0005s\u0017PU3g\u0003\u0019a\u0014N\\5u}Q\tA\"\u0001\u0004nCB|\u0005o]\u000b\u00045\u0001RCCA\u000e-!\u0011iADH\u0015\n\u0005u)!AB\'ba>\u00038\u000f\u0005\u0002 A1\u0001A!B\u0011\u0004\u0005\u0004\u0011#!A&\u0012\u0005\r2\u0003CA\t%\u0013\t)#CA\u0004O_RD\u0017N\\4\u0011\u0005E9\u0013B\u0001\u0015\u0013\u0005\r\te.\u001f\t\u0003?)\"QaK\u0002C\u0002\t\u0012\u0011A\u0016\u0005\u0006[\r\u0001\rAL\u0001\u0002[B!qF\u000e\u0010*\u001d\t\u0001D\u0007\u0005\u00022%5\t!G\u0003\u00024\u0017\u00051AH]8pizJ!!\u000e\n\u0002\rA\u0013X\rZ3g\u0013\t9\u0004HA\u0002NCBT!!\u000e\n
   #9 = Utf8               mapOps
  #10 = Utf8               (Lscala/collection/immutable/Map;)Lshapeless/syntax/std/MapOps;
  #11 = Utf8               <K:Ljava/lang/Object;V:Ljava/lang/Object;>(Lscala/collection/immutable/Map<TK;TV;>;)Lshapeless/syntax/std/MapOps<TK;TV;>;
  #12 = Utf8               m
  #13 = Utf8               shapeless/syntax/std/maps$
  #14 = Class              #13            // shapeless/syntax/std/maps$
  #15 = Utf8               MODULE$
  #16 = Utf8               Lshapeless/syntax/std/maps$;
  #17 = NameAndType        #15:#16        // MODULE$:Lshapeless/syntax/std/maps$;
  #18 = Fieldref           #14.#17        // shapeless/syntax/std/maps$.MODULE$:Lshapeless/syntax/std/maps$;
  #19 = NameAndType        #9:#10         // mapOps:(Lscala/collection/immutable/Map;)Lshapeless/syntax/std/MapOps;
  #20 = Methodref          #14.#19        // shapeless/syntax/std/maps$.mapOps:(Lscala/collection/immutable/Map;)Lshapeless/syntax/std/MapOps;
  #21 = Utf8               Code
  #22 = Utf8               Signature
  #23 = Utf8               MethodParameters
  #24 = Utf8               SourceFile
  #25 = Utf8               RuntimeVisibleAnnotations
  #26 = Utf8               ScalaSig
{
  public static <K extends java.lang.Object, V extends java.lang.Object> shapeless.syntax.std.MapOps<K, V> mapOps(scala.collection.immutable.Map<K, V>);
    descriptor: (Lscala/collection/immutable/Map;)Lshapeless/syntax/std/MapOps;
    flags: (0x0009) ACC_PUBLIC, ACC_STATIC
    Code:
      stack=2, locals=1, args_size=1
         0: getstatic     #18                 // Field shapeless/syntax/std/maps$.MODULE$:Lshapeless/syntax/std/maps$;
         3: aload_0
         4: invokevirtual #20                 // Method shapeless/syntax/std/maps$.mapOps:(Lscala/collection/immutable/Map;)Lshapeless/syntax/std/MapOps;
         7: areturn
    Signature: #11                          // <K:Ljava/lang/Object;V:Ljava/lang/Object;>(Lscala/collection/immutable/Map<TK;TV;>;)Lshapeless/syntax/std/MapOps<TK;TV;>;
    MethodParameters:
      Name                           Flags
      m                              final
}
SourceFile: "maps.scala"
RuntimeVisibleAnnotations:
  0: #6(#7=s#8)
    scala.reflect.ScalaSignature(
      bytes="\u0006\u0005e:Q\u0001B\u0003\t\u000211QAD\u0003\t\u0002=AQAF\u0001\u0005\u0002]AQ\u0001G\u0001\u0005\u0004e\tA!\\1qg*\u0011aaB\u0001\u0004gR$\'B\u0001\u0005\n\u0003\u0019\u0019\u0018P\u001c;bq*\t!\"A\u0005tQ\u0006\u0004X\r\\3tg\u000e\u0001\u0001CA\u0007\u0002\u001b\u0005)!\u0001B7baN\u001c\"!\u0001\t\u0011\u0005E!R\"\u0001\n\u000b\u0003M\tQa]2bY\u0006L!!\u0006\n\u0003\r\u0005s\u0017PU3g\u0003\u0019a\u0014N\\5u}Q\tA\"\u0001\u0004nCB|\u0005o]\u000b\u00045\u0001RCCA\u000e-!\u0011iADH\u0015\n\u0005u)!AB\'ba>\u00038\u000f\u0005\u0002 A1\u0001A!B\u0011\u0004\u0005\u0004\u0011#!A&\u0012\u0005\r2\u0003CA\t%\u0013\t)#CA\u0004O_RD\u0017N\\4\u0011\u0005E9\u0013B\u0001\u0015\u0013\u0005\r\te.\u001f\t\u0003?)\"QaK\u0002C\u0002\t\u0012\u0011A\u0016\u0005\u0006[\r\u0001\rAL\u0001\u0002[B!qF\u000e\u0010*\u001d\t\u0001D\u0007\u0005\u00022%5\t!G\u0003\u00024\u0017\u00051AH]8pizJ!!\u000e\n\u0002\rA\u0013X\rZ3g\u0013\t9\u0004HA\u0002NCBT!!\u000e\n"
    )
  ScalaSig: length = 0x3 (unknown attribute)
   05 02 00
