Classfile /Users/mw/Projects/slang-braindump/.jar/jar8/assemble/slang-braindump/assemble/content/org/apache/commons/io/FileCleaningTracker.class
  Last modified May 29, 2022; size 3373 bytes
  SHA-256 checksum f23865c53ab85ed0c1f09a048265d29521c67ae80f3688ea653e2cd9aa901145
  Compiled from "FileCleaningTracker.java"
public class org.apache.commons.io.FileCleaningTracker
  minor version: 0
  major version: 52
  flags: (0x0021) ACC_PUBLIC, ACC_SUPER
  this_class: #33                         // org/apache/commons/io/FileCleaningTracker
  super_class: #34                        // java/lang/Object
  interfaces: 0, fields: 5, methods: 9, attributes: 2
Constant pool:
    #1 = Methodref          #34.#84       // java/lang/Object."<init>":()V
    #2 = Class              #85           // java/lang/ref/ReferenceQueue
    #3 = Methodref          #2.#84        // java/lang/ref/ReferenceQueue."<init>":()V
    #4 = Fieldref           #33.#86       // org/apache/commons/io/FileCleaningTracker.q:Ljava/lang/ref/ReferenceQueue;
    #5 = Class              #87           // java/util/HashSet
    #6 = Methodref          #5.#84        // java/util/HashSet."<init>":()V
    #7 = Methodref          #88.#89       // java/util/Collections.synchronizedSet:(Ljava/util/Set;)Ljava/util/Set;
    #8 = Fieldref           #33.#90       // org/apache/commons/io/FileCleaningTracker.trackers:Ljava/util/Collection;
    #9 = Class              #91           // java/util/ArrayList
   #10 = Methodref          #9.#84        // java/util/ArrayList."<init>":()V
   #11 = Methodref          #88.#92       // java/util/Collections.synchronizedList:(Ljava/util/List;)Ljava/util/List;
   #12 = Fieldref           #33.#93       // org/apache/commons/io/FileCleaningTracker.deleteFailures:Ljava/util/List;
   #13 = Fieldref           #33.#94       // org/apache/commons/io/FileCleaningTracker.exitWhenFinished:Z
   #14 = Methodref          #33.#95       // org/apache/commons/io/FileCleaningTracker.track:(Ljava/io/File;Ljava/lang/Object;Lorg/apache/commons/io/FileDeleteStrategy;)V
   #15 = String             #61           // file
   #16 = Methodref          #96.#97       // java/util/Objects.requireNonNull:(Ljava/lang/Object;Ljava/lang/String;)Ljava/lang/Object;
   #17 = Methodref          #98.#99       // java/io/File.getPath:()Ljava/lang/String;
   #18 = Methodref          #33.#100      // org/apache/commons/io/FileCleaningTracker.addTracker:(Ljava/lang/String;Ljava/lang/Object;Lorg/apache/commons/io/FileDeleteStrategy;)V
   #19 = Methodref          #33.#101      // org/apache/commons/io/FileCleaningTracker.track:(Ljava/lang/String;Ljava/lang/Object;Lorg/apache/commons/io/FileDeleteStrategy;)V
   #20 = String             #69           // path
   #21 = Class              #102          // java/lang/IllegalStateException
   #22 = String             #103          // No new trackers can be added once exitWhenFinished() is called
   #23 = Methodref          #21.#104      // java/lang/IllegalStateException."<init>":(Ljava/lang/String;)V
   #24 = Fieldref           #33.#105      // org/apache/commons/io/FileCleaningTracker.reaper:Ljava/lang/Thread;
   #25 = Class              #106          // org/apache/commons/io/FileCleaningTracker$Reaper
   #26 = Methodref          #25.#107      // org/apache/commons/io/FileCleaningTracker$Reaper."<init>":(Lorg/apache/commons/io/FileCleaningTracker;)V
   #27 = Methodref          #108.#109     // java/lang/Thread.start:()V
   #28 = Class              #110          // org/apache/commons/io/FileCleaningTracker$Tracker
   #29 = Methodref          #28.#111      // org/apache/commons/io/FileCleaningTracker$Tracker."<init>":(Ljava/lang/String;Lorg/apache/commons/io/FileDeleteStrategy;Ljava/lang/Object;Ljava/lang/ref/ReferenceQueue;)V
   #30 = InterfaceMethodref #112.#113     // java/util/Collection.add:(Ljava/lang/Object;)Z
   #31 = InterfaceMethodref #112.#114     // java/util/Collection.size:()I
   #32 = Methodref          #108.#115     // java/lang/Thread.interrupt:()V
   #33 = Class              #116          // org/apache/commons/io/FileCleaningTracker
   #34 = Class              #117          // java/lang/Object
   #35 = Utf8               Tracker
   #36 = Utf8               InnerClasses
   #37 = Utf8               Reaper
   #38 = Utf8               q
   #39 = Utf8               Ljava/lang/ref/ReferenceQueue;
   #40 = Utf8               Signature
   #41 = Utf8               Ljava/lang/ref/ReferenceQueue<Ljava/lang/Object;>;
   #42 = Utf8               trackers
   #43 = Utf8               Ljava/util/Collection;
   #44 = Utf8               Ljava/util/Collection<Lorg/apache/commons/io/FileCleaningTracker$Tracker;>;
   #45 = Utf8               deleteFailures
   #46 = Utf8               Ljava/util/List;
   #47 = Utf8               Ljava/util/List<Ljava/lang/String;>;
   #48 = Utf8               exitWhenFinished
   #49 = Utf8               Z
   #50 = Utf8               reaper
   #51 = Utf8               Ljava/lang/Thread;
   #52 = Utf8               <init>
   #53 = Utf8               ()V
   #54 = Utf8               Code
   #55 = Utf8               LineNumberTable
   #56 = Utf8               LocalVariableTable
   #57 = Utf8               this
   #58 = Utf8               Lorg/apache/commons/io/FileCleaningTracker;
   #59 = Utf8               track
   #60 = Utf8               (Ljava/io/File;Ljava/lang/Object;)V
   #61 = Utf8               file
   #62 = Utf8               Ljava/io/File;
   #63 = Utf8               marker
   #64 = Utf8               Ljava/lang/Object;
   #65 = Utf8               (Ljava/io/File;Ljava/lang/Object;Lorg/apache/commons/io/FileDeleteStrategy;)V
   #66 = Utf8               deleteStrategy
   #67 = Utf8               Lorg/apache/commons/io/FileDeleteStrategy;
   #68 = Utf8               (Ljava/lang/String;Ljava/lang/Object;)V
   #69 = Utf8               path
   #70 = Utf8               Ljava/lang/String;
   #71 = Utf8               (Ljava/lang/String;Ljava/lang/Object;Lorg/apache/commons/io/FileDeleteStrategy;)V
   #72 = Utf8               addTracker
   #73 = Utf8               StackMapTable
   #74 = Utf8               getTrackCount
   #75 = Utf8               ()I
   #76 = Utf8               getDeleteFailures
   #77 = Utf8               ()Ljava/util/List;
   #78 = Utf8               ()Ljava/util/List<Ljava/lang/String;>;
   #79 = Class              #116          // org/apache/commons/io/FileCleaningTracker
   #80 = Class              #117          // java/lang/Object
   #81 = Class              #118          // java/lang/Throwable
   #82 = Utf8               SourceFile
   #83 = Utf8               FileCleaningTracker.java
   #84 = NameAndType        #52:#53       // "<init>":()V
   #85 = Utf8               java/lang/ref/ReferenceQueue
   #86 = NameAndType        #38:#39       // q:Ljava/lang/ref/ReferenceQueue;
   #87 = Utf8               java/util/HashSet
   #88 = Class              #119          // java/util/Collections
   #89 = NameAndType        #120:#121     // synchronizedSet:(Ljava/util/Set;)Ljava/util/Set;
   #90 = NameAndType        #42:#43       // trackers:Ljava/util/Collection;
   #91 = Utf8               java/util/ArrayList
   #92 = NameAndType        #122:#123     // synchronizedList:(Ljava/util/List;)Ljava/util/List;
   #93 = NameAndType        #45:#46       // deleteFailures:Ljava/util/List;
   #94 = NameAndType        #48:#49       // exitWhenFinished:Z
   #95 = NameAndType        #59:#65       // track:(Ljava/io/File;Ljava/lang/Object;Lorg/apache/commons/io/FileDeleteStrategy;)V
   #96 = Class              #124          // java/util/Objects
   #97 = NameAndType        #125:#126     // requireNonNull:(Ljava/lang/Object;Ljava/lang/String;)Ljava/lang/Object;
   #98 = Class              #127          // java/io/File
   #99 = NameAndType        #128:#129     // getPath:()Ljava/lang/String;
  #100 = NameAndType        #72:#71       // addTracker:(Ljava/lang/String;Ljava/lang/Object;Lorg/apache/commons/io/FileDeleteStrategy;)V
  #101 = NameAndType        #59:#71       // track:(Ljava/lang/String;Ljava/lang/Object;Lorg/apache/commons/io/FileDeleteStrategy;)V
  #102 = Utf8               java/lang/IllegalStateException
  #103 = Utf8               No new trackers can be added once exitWhenFinished() is called
  #104 = NameAndType        #52:#130      // "<init>":(Ljava/lang/String;)V
  #105 = NameAndType        #50:#51       // reaper:Ljava/lang/Thread;
  #106 = Utf8               org/apache/commons/io/FileCleaningTracker$Reaper
  #107 = NameAndType        #52:#131      // "<init>":(Lorg/apache/commons/io/FileCleaningTracker;)V
  #108 = Class              #132          // java/lang/Thread
  #109 = NameAndType        #133:#53      // start:()V
  #110 = Utf8               org/apache/commons/io/FileCleaningTracker$Tracker
  #111 = NameAndType        #52:#134      // "<init>":(Ljava/lang/String;Lorg/apache/commons/io/FileDeleteStrategy;Ljava/lang/Object;Ljava/lang/ref/ReferenceQueue;)V
  #112 = Class              #135          // java/util/Collection
  #113 = NameAndType        #136:#137     // add:(Ljava/lang/Object;)Z
  #114 = NameAndType        #138:#75      // size:()I
  #115 = NameAndType        #139:#53      // interrupt:()V
  #116 = Utf8               org/apache/commons/io/FileCleaningTracker
  #117 = Utf8               java/lang/Object
  #118 = Utf8               java/lang/Throwable
  #119 = Utf8               java/util/Collections
  #120 = Utf8               synchronizedSet
  #121 = Utf8               (Ljava/util/Set;)Ljava/util/Set;
  #122 = Utf8               synchronizedList
  #123 = Utf8               (Ljava/util/List;)Ljava/util/List;
  #124 = Utf8               java/util/Objects
  #125 = Utf8               requireNonNull
  #126 = Utf8               (Ljava/lang/Object;Ljava/lang/String;)Ljava/lang/Object;
  #127 = Utf8               java/io/File
  #128 = Utf8               getPath
  #129 = Utf8               ()Ljava/lang/String;
  #130 = Utf8               (Ljava/lang/String;)V
  #131 = Utf8               (Lorg/apache/commons/io/FileCleaningTracker;)V
  #132 = Utf8               java/lang/Thread
  #133 = Utf8               start
  #134 = Utf8               (Ljava/lang/String;Lorg/apache/commons/io/FileDeleteStrategy;Ljava/lang/Object;Ljava/lang/ref/ReferenceQueue;)V
  #135 = Utf8               java/util/Collection
  #136 = Utf8               add
  #137 = Utf8               (Ljava/lang/Object;)Z
  #138 = Utf8               size
  #139 = Utf8               interrupt
{
  java.lang.ref.ReferenceQueue<java.lang.Object> q;
    descriptor: Ljava/lang/ref/ReferenceQueue;
    flags: (0x0000)
    Signature: #41                          // Ljava/lang/ref/ReferenceQueue<Ljava/lang/Object;>;

  final java.util.Collection<org.apache.commons.io.FileCleaningTracker$Tracker> trackers;
    descriptor: Ljava/util/Collection;
    flags: (0x0010) ACC_FINAL
    Signature: #44                          // Ljava/util/Collection<Lorg/apache/commons/io/FileCleaningTracker$Tracker;>;

  final java.util.List<java.lang.String> deleteFailures;
    descriptor: Ljava/util/List;
    flags: (0x0010) ACC_FINAL
    Signature: #47                          // Ljava/util/List<Ljava/lang/String;>;

  volatile boolean exitWhenFinished;
    descriptor: Z
    flags: (0x0040) ACC_VOLATILE

  java.lang.Thread reaper;
    descriptor: Ljava/lang/Thread;
    flags: (0x0000)

  public org.apache.commons.io.FileCleaningTracker();
    descriptor: ()V
    flags: (0x0001) ACC_PUBLIC
    Code:
      stack=3, locals=1, args_size=1
         0: aload_0
         1: invokespecial #1                  // Method java/lang/Object."<init>":()V
         4: aload_0
         5: new           #2                  // class java/lang/ref/ReferenceQueue
         8: dup
         9: invokespecial #3                  // Method java/lang/ref/ReferenceQueue."<init>":()V
        12: putfield      #4                  // Field q:Ljava/lang/ref/ReferenceQueue;
        15: aload_0
        16: new           #5                  // class java/util/HashSet
        19: dup
        20: invokespecial #6                  // Method java/util/HashSet."<init>":()V
        23: invokestatic  #7                  // Method java/util/Collections.synchronizedSet:(Ljava/util/Set;)Ljava/util/Set;
        26: putfield      #8                  // Field trackers:Ljava/util/Collection;
        29: aload_0
        30: new           #9                  // class java/util/ArrayList
        33: dup
        34: invokespecial #10                 // Method java/util/ArrayList."<init>":()V
        37: invokestatic  #11                 // Method java/util/Collections.synchronizedList:(Ljava/util/List;)Ljava/util/List;
        40: putfield      #12                 // Field deleteFailures:Ljava/util/List;
        43: aload_0
        44: iconst_0
        45: putfield      #13                 // Field exitWhenFinished:Z
        48: return
      LineNumberTable:
        line 44: 0
        line 51: 4
        line 55: 15
        line 59: 29
        line 63: 43
      LocalVariableTable:
        Start  Length  Slot  Name   Signature
            0      49     0  this   Lorg/apache/commons/io/FileCleaningTracker;

  public void track(java.io.File, java.lang.Object);
    descriptor: (Ljava/io/File;Ljava/lang/Object;)V
    flags: (0x0001) ACC_PUBLIC
    Code:
      stack=4, locals=3, args_size=3
         0: aload_0
         1: aload_1
         2: aload_2
         3: aconst_null
         4: invokevirtual #14                 // Method track:(Ljava/io/File;Ljava/lang/Object;Lorg/apache/commons/io/FileDeleteStrategy;)V
         7: return
      LineNumberTable:
        line 80: 0
        line 81: 7
      LocalVariableTable:
        Start  Length  Slot  Name   Signature
            0       8     0  this   Lorg/apache/commons/io/FileCleaningTracker;
            0       8     1  file   Ljava/io/File;
            0       8     2 marker   Ljava/lang/Object;

  public void track(java.io.File, java.lang.Object, org.apache.commons.io.FileDeleteStrategy);
    descriptor: (Ljava/io/File;Ljava/lang/Object;Lorg/apache/commons/io/FileDeleteStrategy;)V
    flags: (0x0001) ACC_PUBLIC
    Code:
      stack=4, locals=4, args_size=4
         0: aload_1
         1: ldc           #15                 // String file
         3: invokestatic  #16                 // Method java/util/Objects.requireNonNull:(Ljava/lang/Object;Ljava/lang/String;)Ljava/lang/Object;
         6: pop
         7: aload_0
         8: aload_1
         9: invokevirtual #17                 // Method java/io/File.getPath:()Ljava/lang/String;
        12: aload_2
        13: aload_3
        14: invokespecial #18                 // Method addTracker:(Ljava/lang/String;Ljava/lang/Object;Lorg/apache/commons/io/FileDeleteStrategy;)V
        17: return
      LineNumberTable:
        line 94: 0
        line 95: 7
        line 96: 17
      LocalVariableTable:
        Start  Length  Slot  Name   Signature
            0      18     0  this   Lorg/apache/commons/io/FileCleaningTracker;
            0      18     1  file   Ljava/io/File;
            0      18     2 marker   Ljava/lang/Object;
            0      18     3 deleteStrategy   Lorg/apache/commons/io/FileDeleteStrategy;

  public void track(java.lang.String, java.lang.Object);
    descriptor: (Ljava/lang/String;Ljava/lang/Object;)V
    flags: (0x0001) ACC_PUBLIC
    Code:
      stack=4, locals=3, args_size=3
         0: aload_0
         1: aload_1
         2: aload_2
         3: aconst_null
         4: invokevirtual #19                 // Method track:(Ljava/lang/String;Ljava/lang/Object;Lorg/apache/commons/io/FileDeleteStrategy;)V
         7: return
      LineNumberTable:
        line 108: 0
        line 109: 7
      LocalVariableTable:
        Start  Length  Slot  Name   Signature
            0       8     0  this   Lorg/apache/commons/io/FileCleaningTracker;
            0       8     1  path   Ljava/lang/String;
            0       8     2 marker   Ljava/lang/Object;

  public void track(java.lang.String, java.lang.Object, org.apache.commons.io.FileDeleteStrategy);
    descriptor: (Ljava/lang/String;Ljava/lang/Object;Lorg/apache/commons/io/FileDeleteStrategy;)V
    flags: (0x0001) ACC_PUBLIC
    Code:
      stack=4, locals=4, args_size=4
         0: aload_1
         1: ldc           #20                 // String path
         3: invokestatic  #16                 // Method java/util/Objects.requireNonNull:(Ljava/lang/Object;Ljava/lang/String;)Ljava/lang/Object;
         6: pop
         7: aload_0
         8: aload_1
         9: aload_2
        10: aload_3
        11: invokespecial #18                 // Method addTracker:(Ljava/lang/String;Ljava/lang/Object;Lorg/apache/commons/io/FileDeleteStrategy;)V
        14: return
      LineNumberTable:
        line 122: 0
        line 123: 7
        line 124: 14
      LocalVariableTable:
        Start  Length  Slot  Name   Signature
            0      15     0  this   Lorg/apache/commons/io/FileCleaningTracker;
            0      15     1  path   Ljava/lang/String;
            0      15     2 marker   Ljava/lang/Object;
            0      15     3 deleteStrategy   Lorg/apache/commons/io/FileDeleteStrategy;

  private synchronized void addTracker(java.lang.String, java.lang.Object, org.apache.commons.io.FileDeleteStrategy);
    descriptor: (Ljava/lang/String;Ljava/lang/Object;Lorg/apache/commons/io/FileDeleteStrategy;)V
    flags: (0x0022) ACC_PRIVATE, ACC_SYNCHRONIZED
    Code:
      stack=7, locals=4, args_size=4
         0: aload_0
         1: getfield      #13                 // Field exitWhenFinished:Z
         4: ifeq          17
         7: new           #21                 // class java/lang/IllegalStateException
        10: dup
        11: ldc           #22                 // String No new trackers can be added once exitWhenFinished() is called
        13: invokespecial #23                 // Method java/lang/IllegalStateException."<init>":(Ljava/lang/String;)V
        16: athrow
        17: aload_0
        18: getfield      #24                 // Field reaper:Ljava/lang/Thread;
        21: ifnonnull     43
        24: aload_0
        25: new           #25                 // class org/apache/commons/io/FileCleaningTracker$Reaper
        28: dup
        29: aload_0
        30: invokespecial #26                 // Method org/apache/commons/io/FileCleaningTracker$Reaper."<init>":(Lorg/apache/commons/io/FileCleaningTracker;)V
        33: putfield      #24                 // Field reaper:Ljava/lang/Thread;
        36: aload_0
        37: getfield      #24                 // Field reaper:Ljava/lang/Thread;
        40: invokevirtual #27                 // Method java/lang/Thread.start:()V
        43: aload_0
        44: getfield      #8                  // Field trackers:Ljava/util/Collection;
        47: new           #28                 // class org/apache/commons/io/FileCleaningTracker$Tracker
        50: dup
        51: aload_1
        52: aload_3
        53: aload_2
        54: aload_0
        55: getfield      #4                  // Field q:Ljava/lang/ref/ReferenceQueue;
        58: invokespecial #29                 // Method org/apache/commons/io/FileCleaningTracker$Tracker."<init>":(Ljava/lang/String;Lorg/apache/commons/io/FileDeleteStrategy;Ljava/lang/Object;Ljava/lang/ref/ReferenceQueue;)V
        61: invokeinterface #30,  2           // InterfaceMethod java/util/Collection.add:(Ljava/lang/Object;)Z
        66: pop
        67: return
      LineNumberTable:
        line 136: 0
        line 137: 7
        line 139: 17
        line 140: 24
        line 141: 36
        line 143: 43
        line 144: 67
      LocalVariableTable:
        Start  Length  Slot  Name   Signature
            0      68     0  this   Lorg/apache/commons/io/FileCleaningTracker;
            0      68     1  path   Ljava/lang/String;
            0      68     2 marker   Ljava/lang/Object;
            0      68     3 deleteStrategy   Lorg/apache/commons/io/FileDeleteStrategy;
      StackMapTable: number_of_entries = 2
        frame_type = 17 /* same */
        frame_type = 25 /* same */

  public int getTrackCount();
    descriptor: ()I
    flags: (0x0001) ACC_PUBLIC
    Code:
      stack=1, locals=1, args_size=1
         0: aload_0
         1: getfield      #8                  // Field trackers:Ljava/util/Collection;
         4: invokeinterface #31,  1           // InterfaceMethod java/util/Collection.size:()I
         9: ireturn
      LineNumberTable:
        line 154: 0
      LocalVariableTable:
        Start  Length  Slot  Name   Signature
            0      10     0  this   Lorg/apache/commons/io/FileCleaningTracker;

  public java.util.List<java.lang.String> getDeleteFailures();
    descriptor: ()Ljava/util/List;
    flags: (0x0001) ACC_PUBLIC
    Code:
      stack=1, locals=1, args_size=1
         0: aload_0
         1: getfield      #12                 // Field deleteFailures:Ljava/util/List;
         4: areturn
      LineNumberTable:
        line 164: 0
      LocalVariableTable:
        Start  Length  Slot  Name   Signature
            0       5     0  this   Lorg/apache/commons/io/FileCleaningTracker;
    Signature: #78                          // ()Ljava/util/List<Ljava/lang/String;>;

  public synchronized void exitWhenFinished();
    descriptor: ()V
    flags: (0x0021) ACC_PUBLIC, ACC_SYNCHRONIZED
    Code:
      stack=2, locals=3, args_size=1
         0: aload_0
         1: iconst_1
         2: putfield      #13                 // Field exitWhenFinished:Z
         5: aload_0
         6: getfield      #24                 // Field reaper:Ljava/lang/Thread;
         9: ifnull        36
        12: aload_0
        13: getfield      #24                 // Field reaper:Ljava/lang/Thread;
        16: dup
        17: astore_1
        18: monitorenter
        19: aload_0
        20: getfield      #24                 // Field reaper:Ljava/lang/Thread;
        23: invokevirtual #32                 // Method java/lang/Thread.interrupt:()V
        26: aload_1
        27: monitorexit
        28: goto          36
        31: astore_2
        32: aload_1
        33: monitorexit
        34: aload_2
        35: athrow
        36: return
      Exception table:
         from    to  target type
            19    28    31   any
            31    34    31   any
      LineNumberTable:
        line 191: 0
        line 192: 5
        line 193: 12
        line 194: 19
        line 195: 26
        line 197: 36
      LocalVariableTable:
        Start  Length  Slot  Name   Signature
            0      37     0  this   Lorg/apache/commons/io/FileCleaningTracker;
      StackMapTable: number_of_entries = 2
        frame_type = 255 /* full_frame */
          offset_delta = 31
          locals = [ class org/apache/commons/io/FileCleaningTracker, class java/lang/Object ]
          stack = [ class java/lang/Throwable ]
        frame_type = 250 /* chop */
          offset_delta = 4
}
SourceFile: "FileCleaningTracker.java"
InnerClasses:
  private static final #35= #28 of #33;   // Tracker=class org/apache/commons/io/FileCleaningTracker$Tracker of class org/apache/commons/io/FileCleaningTracker
  private final #37= #25 of #33;          // Reaper=class org/apache/commons/io/FileCleaningTracker$Reaper of class org/apache/commons/io/FileCleaningTracker
