Classfile /Users/mw/Projects/slang-braindump/.jar/jar8/assemble/slang-braindump/assemble/content/org/apache/commons/io/IOExceptionList.class
  Last modified May 29, 2022; size 2094 bytes
  SHA-256 checksum f89fc617f1261078703647a6cca16a048e7113c9c72d02e820ebe931d6204603
  Compiled from "IOExceptionList.java"
public class org.apache.commons.io.IOExceptionList extends java.io.IOException
  minor version: 0
  major version: 52
  flags: (0x0021) ACC_PUBLIC, ACC_SUPER
  this_class: #11                         // org/apache/commons/io/IOExceptionList
  super_class: #12                        // java/io/IOException
  interfaces: 0, fields: 2, methods: 5, attributes: 1
Constant pool:
   #1 = String             #54            // %,d exceptions: %s
   #2 = Class              #55            // java/lang/Object
   #3 = InterfaceMethodref #56.#57        // java/util/List.size:()I
   #4 = Methodref          #58.#59        // java/lang/Integer.valueOf:(I)Ljava/lang/Integer;
   #5 = Methodref          #60.#61        // java/lang/String.format:(Ljava/lang/String;[Ljava/lang/Object;)Ljava/lang/String;
   #6 = InterfaceMethodref #56.#62        // java/util/List.get:(I)Ljava/lang/Object;
   #7 = Class              #63            // java/lang/Throwable
   #8 = Methodref          #12.#64        // java/io/IOException."<init>":(Ljava/lang/String;Ljava/lang/Throwable;)V
   #9 = Methodref          #65.#66        // java/util/Collections.emptyList:()Ljava/util/List;
  #10 = Fieldref           #11.#67        // org/apache/commons/io/IOExceptionList.causeList:Ljava/util/List;
  #11 = Class              #68            // org/apache/commons/io/IOExceptionList
  #12 = Class              #69            // java/io/IOException
  #13 = Utf8               serialVersionUID
  #14 = Utf8               J
  #15 = Utf8               ConstantValue
  #16 = Long               1l
  #18 = Utf8               causeList
  #19 = Utf8               Ljava/util/List;
  #20 = Utf8               Signature
  #21 = Utf8               Ljava/util/List<+Ljava/lang/Throwable;>;
  #22 = Utf8               <init>
  #23 = Utf8               (Ljava/util/List;)V
  #24 = Utf8               Code
  #25 = Utf8               LineNumberTable
  #26 = Utf8               LocalVariableTable
  #27 = Utf8               this
  #28 = Utf8               Lorg/apache/commons/io/IOExceptionList;
  #29 = Utf8               LocalVariableTypeTable
  #30 = Utf8               StackMapTable
  #31 = Class              #70            // java/util/List
  #32 = Class              #71            // java/lang/String
  #33 = Class              #72            // "[Ljava/lang/Object;"
  #34 = Class              #63            // java/lang/Throwable
  #35 = Class              #68            // org/apache/commons/io/IOExceptionList
  #36 = Utf8               (Ljava/util/List<+Ljava/lang/Throwable;>;)V
  #37 = Utf8               getCauseList
  #38 = Utf8               ()Ljava/util/List;
  #39 = Utf8               <T:Ljava/lang/Throwable;>()Ljava/util/List<TT;>;
  #40 = Utf8               getCause
  #41 = Utf8               (I)Ljava/lang/Throwable;
  #42 = Utf8               index
  #43 = Utf8               I
  #44 = Utf8               <T:Ljava/lang/Throwable;>(I)TT;
  #45 = Utf8               (ILjava/lang/Class;)Ljava/lang/Throwable;
  #46 = Utf8               clazz
  #47 = Utf8               Ljava/lang/Class;
  #48 = Utf8               Ljava/lang/Class<TT;>;
  #49 = Utf8               <T:Ljava/lang/Throwable;>(ILjava/lang/Class<TT;>;)TT;
  #50 = Utf8               (Ljava/lang/Class;)Ljava/util/List;
  #51 = Utf8               <T:Ljava/lang/Throwable;>(Ljava/lang/Class<TT;>;)Ljava/util/List<TT;>;
  #52 = Utf8               SourceFile
  #53 = Utf8               IOExceptionList.java
  #54 = Utf8               %,d exceptions: %s
  #55 = Utf8               java/lang/Object
  #56 = Class              #70            // java/util/List
  #57 = NameAndType        #73:#74        // size:()I
  #58 = Class              #75            // java/lang/Integer
  #59 = NameAndType        #76:#77        // valueOf:(I)Ljava/lang/Integer;
  #60 = Class              #71            // java/lang/String
  #61 = NameAndType        #78:#79        // format:(Ljava/lang/String;[Ljava/lang/Object;)Ljava/lang/String;
  #62 = NameAndType        #80:#81        // get:(I)Ljava/lang/Object;
  #63 = Utf8               java/lang/Throwable
  #64 = NameAndType        #22:#82        // "<init>":(Ljava/lang/String;Ljava/lang/Throwable;)V
  #65 = Class              #83            // java/util/Collections
  #66 = NameAndType        #84:#38        // emptyList:()Ljava/util/List;
  #67 = NameAndType        #18:#19        // causeList:Ljava/util/List;
  #68 = Utf8               org/apache/commons/io/IOExceptionList
  #69 = Utf8               java/io/IOException
  #70 = Utf8               java/util/List
  #71 = Utf8               java/lang/String
  #72 = Utf8               [Ljava/lang/Object;
  #73 = Utf8               size
  #74 = Utf8               ()I
  #75 = Utf8               java/lang/Integer
  #76 = Utf8               valueOf
  #77 = Utf8               (I)Ljava/lang/Integer;
  #78 = Utf8               format
  #79 = Utf8               (Ljava/lang/String;[Ljava/lang/Object;)Ljava/lang/String;
  #80 = Utf8               get
  #81 = Utf8               (I)Ljava/lang/Object;
  #82 = Utf8               (Ljava/lang/String;Ljava/lang/Throwable;)V
  #83 = Utf8               java/util/Collections
  #84 = Utf8               emptyList
{
  private static final long serialVersionUID;
    descriptor: J
    flags: (0x001a) ACC_PRIVATE, ACC_STATIC, ACC_FINAL
    ConstantValue: long 1l

  private final java.util.List<? extends java.lang.Throwable> causeList;
    descriptor: Ljava/util/List;
    flags: (0x0012) ACC_PRIVATE, ACC_FINAL
    Signature: #21                          // Ljava/util/List<+Ljava/lang/Throwable;>;

  public org.apache.commons.io.IOExceptionList(java.util.List<? extends java.lang.Throwable>);
    descriptor: (Ljava/util/List;)V
    flags: (0x0001) ACC_PUBLIC
    Code:
      stack=6, locals=2, args_size=2
         0: aload_0
         1: ldc           #1                  // String %,d exceptions: %s
         3: iconst_2
         4: anewarray     #2                  // class java/lang/Object
         7: dup
         8: iconst_0
         9: aload_1
        10: ifnonnull     17
        13: iconst_0
        14: goto          23
        17: aload_1
        18: invokeinterface #3,  1            // InterfaceMethod java/util/List.size:()I
        23: invokestatic  #4                  // Method java/lang/Integer.valueOf:(I)Ljava/lang/Integer;
        26: aastore
        27: dup
        28: iconst_1
        29: aload_1
        30: aastore
        31: invokestatic  #5                  // Method java/lang/String.format:(Ljava/lang/String;[Ljava/lang/Object;)Ljava/lang/String;
        34: aload_1
        35: ifnonnull     42
        38: aconst_null
        39: goto          52
        42: aload_1
        43: iconst_0
        44: invokeinterface #6,  2            // InterfaceMethod java/util/List.get:(I)Ljava/lang/Object;
        49: checkcast     #7                  // class java/lang/Throwable
        52: invokespecial #8                  // Method java/io/IOException."<init>":(Ljava/lang/String;Ljava/lang/Throwable;)V
        55: aload_0
        56: aload_1
        57: ifnonnull     66
        60: invokestatic  #9                  // Method java/util/Collections.emptyList:()Ljava/util/List;
        63: goto          67
        66: aload_1
        67: putfield      #10                 // Field causeList:Ljava/util/List;
        70: return
      LineNumberTable:
        line 44: 0
        line 45: 44
        line 44: 52
        line 46: 55
        line 47: 70
      LocalVariableTable:
        Start  Length  Slot  Name   Signature
            0      71     0  this   Lorg/apache/commons/io/IOExceptionList;
            0      71     1 causeList   Ljava/util/List;
      LocalVariableTypeTable:
        Start  Length  Slot  Name   Signature
            0      71     1 causeList   Ljava/util/List<+Ljava/lang/Throwable;>;
      StackMapTable: number_of_entries = 6
        frame_type = 255 /* full_frame */
          offset_delta = 17
          locals = [ this, class java/util/List ]
          stack = [ this, class java/lang/String, class "[Ljava/lang/Object;", class "[Ljava/lang/Object;", int ]
        frame_type = 255 /* full_frame */
          offset_delta = 5
          locals = [ this, class java/util/List ]
          stack = [ this, class java/lang/String, class "[Ljava/lang/Object;", class "[Ljava/lang/Object;", int, int ]
        frame_type = 255 /* full_frame */
          offset_delta = 18
          locals = [ this, class java/util/List ]
          stack = [ this, class java/lang/String ]
        frame_type = 255 /* full_frame */
          offset_delta = 9
          locals = [ this, class java/util/List ]
          stack = [ this, class java/lang/String, class java/lang/Throwable ]
        frame_type = 255 /* full_frame */
          offset_delta = 13
          locals = [ class org/apache/commons/io/IOExceptionList, class java/util/List ]
          stack = [ class org/apache/commons/io/IOExceptionList ]
        frame_type = 255 /* full_frame */
          offset_delta = 0
          locals = [ class org/apache/commons/io/IOExceptionList, class java/util/List ]
          stack = [ class org/apache/commons/io/IOExceptionList, class java/util/List ]
    Signature: #36                          // (Ljava/util/List<+Ljava/lang/Throwable;>;)V

  public <T extends java.lang.Throwable> java.util.List<T> getCauseList();
    descriptor: ()Ljava/util/List;
    flags: (0x0001) ACC_PUBLIC
    Code:
      stack=1, locals=1, args_size=1
         0: aload_0
         1: getfield      #10                 // Field causeList:Ljava/util/List;
         4: areturn
      LineNumberTable:
        line 56: 0
      LocalVariableTable:
        Start  Length  Slot  Name   Signature
            0       5     0  this   Lorg/apache/commons/io/IOExceptionList;
    Signature: #39                          // <T:Ljava/lang/Throwable;>()Ljava/util/List<TT;>;

  public <T extends java.lang.Throwable> T getCause(int);
    descriptor: (I)Ljava/lang/Throwable;
    flags: (0x0001) ACC_PUBLIC
    Code:
      stack=2, locals=2, args_size=2
         0: aload_0
         1: getfield      #10                 // Field causeList:Ljava/util/List;
         4: iload_1
         5: invokeinterface #6,  2            // InterfaceMethod java/util/List.get:(I)Ljava/lang/Object;
        10: checkcast     #7                  // class java/lang/Throwable
        13: areturn
      LineNumberTable:
        line 67: 0
      LocalVariableTable:
        Start  Length  Slot  Name   Signature
            0      14     0  this   Lorg/apache/commons/io/IOExceptionList;
            0      14     1 index   I
    Signature: #44                          // <T:Ljava/lang/Throwable;>(I)TT;

  public <T extends java.lang.Throwable> T getCause(int, java.lang.Class<T>);
    descriptor: (ILjava/lang/Class;)Ljava/lang/Throwable;
    flags: (0x0001) ACC_PUBLIC
    Code:
      stack=2, locals=3, args_size=3
         0: aload_0
         1: getfield      #10                 // Field causeList:Ljava/util/List;
         4: iload_1
         5: invokeinterface #6,  2            // InterfaceMethod java/util/List.get:(I)Ljava/lang/Object;
        10: checkcast     #7                  // class java/lang/Throwable
        13: areturn
      LineNumberTable:
        line 79: 0
      LocalVariableTable:
        Start  Length  Slot  Name   Signature
            0      14     0  this   Lorg/apache/commons/io/IOExceptionList;
            0      14     1 index   I
            0      14     2 clazz   Ljava/lang/Class;
      LocalVariableTypeTable:
        Start  Length  Slot  Name   Signature
            0      14     2 clazz   Ljava/lang/Class<TT;>;
    Signature: #49                          // <T:Ljava/lang/Throwable;>(ILjava/lang/Class<TT;>;)TT;

  public <T extends java.lang.Throwable> java.util.List<T> getCauseList(java.lang.Class<T>);
    descriptor: (Ljava/lang/Class;)Ljava/util/List;
    flags: (0x0001) ACC_PUBLIC
    Code:
      stack=1, locals=2, args_size=2
         0: aload_0
         1: getfield      #10                 // Field causeList:Ljava/util/List;
         4: areturn
      LineNumberTable:
        line 90: 0
      LocalVariableTable:
        Start  Length  Slot  Name   Signature
            0       5     0  this   Lorg/apache/commons/io/IOExceptionList;
            0       5     1 clazz   Ljava/lang/Class;
      LocalVariableTypeTable:
        Start  Length  Slot  Name   Signature
            0       5     1 clazz   Ljava/lang/Class<TT;>;
    Signature: #51                          // <T:Ljava/lang/Throwable;>(Ljava/lang/Class<TT;>;)Ljava/util/List<TT;>;
}
SourceFile: "IOExceptionList.java"
