Classfile /Users/mw/Projects/slang-braindump/.jar/jar8/assemble/slang-braindump/assemble/content/org/apache/commons/io/ThreadMonitor.class
  Last modified May 29, 2022; size 1649 bytes
  SHA-256 checksum 842d1d8aa77186e4208f68b3cf353b9097c604d98c265d7897be6fd9e9662f92
  Compiled from "ThreadMonitor.java"
class org.apache.commons.io.ThreadMonitor implements java.lang.Runnable
  minor version: 0
  major version: 52
  flags: (0x0020) ACC_SUPER
  this_class: #3                          // org/apache/commons/io/ThreadMonitor
  super_class: #18                        // java/lang/Object
  interfaces: 1, fields: 2, methods: 6, attributes: 1
Constant pool:
   #1 = Methodref          #5.#51         // java/lang/Thread.currentThread:()Ljava/lang/Thread;
   #2 = Methodref          #3.#52         // org/apache/commons/io/ThreadMonitor.start:(Ljava/lang/Thread;J)Ljava/lang/Thread;
   #3 = Class              #53            // org/apache/commons/io/ThreadMonitor
   #4 = Methodref          #3.#54         // org/apache/commons/io/ThreadMonitor."<init>":(Ljava/lang/Thread;J)V
   #5 = Class              #55            // java/lang/Thread
   #6 = Methodref          #56.#57        // java/lang/Class.getSimpleName:()Ljava/lang/String;
   #7 = Methodref          #5.#58         // java/lang/Thread."<init>":(Ljava/lang/Runnable;Ljava/lang/String;)V
   #8 = Methodref          #5.#59         // java/lang/Thread.setDaemon:(Z)V
   #9 = Methodref          #5.#60         // java/lang/Thread.start:()V
  #10 = Methodref          #5.#61         // java/lang/Thread.interrupt:()V
  #11 = Methodref          #18.#62        // java/lang/Object."<init>":()V
  #12 = Fieldref           #3.#63         // org/apache/commons/io/ThreadMonitor.thread:Ljava/lang/Thread;
  #13 = Fieldref           #3.#64         // org/apache/commons/io/ThreadMonitor.timeout:J
  #14 = Methodref          #3.#65         // org/apache/commons/io/ThreadMonitor.sleep:(J)V
  #15 = Class              #66            // java/lang/InterruptedException
  #16 = Methodref          #67.#68        // java/lang/System.currentTimeMillis:()J
  #17 = Methodref          #5.#65         // java/lang/Thread.sleep:(J)V
  #18 = Class              #69            // java/lang/Object
  #19 = Class              #70            // java/lang/Runnable
  #20 = Utf8               thread
  #21 = Utf8               Ljava/lang/Thread;
  #22 = Utf8               timeout
  #23 = Utf8               J
  #24 = Utf8               start
  #25 = Utf8               (J)Ljava/lang/Thread;
  #26 = Utf8               Code
  #27 = Utf8               LineNumberTable
  #28 = Utf8               LocalVariableTable
  #29 = Utf8               (Ljava/lang/Thread;J)Ljava/lang/Thread;
  #30 = Utf8               timout
  #31 = Utf8               Lorg/apache/commons/io/ThreadMonitor;
  #32 = Utf8               monitor
  #33 = Utf8               StackMapTable
  #34 = Class              #55            // java/lang/Thread
  #35 = Utf8               stop
  #36 = Utf8               (Ljava/lang/Thread;)V
  #37 = Utf8               <init>
  #38 = Utf8               (Ljava/lang/Thread;J)V
  #39 = Utf8               this
  #40 = Utf8               run
  #41 = Utf8               ()V
  #42 = Class              #66            // java/lang/InterruptedException
  #43 = Utf8               sleep
  #44 = Utf8               (J)V
  #45 = Utf8               ms
  #46 = Utf8               finishAt
  #47 = Utf8               remaining
  #48 = Utf8               Exceptions
  #49 = Utf8               SourceFile
  #50 = Utf8               ThreadMonitor.java
  #51 = NameAndType        #71:#72        // currentThread:()Ljava/lang/Thread;
  #52 = NameAndType        #24:#29        // start:(Ljava/lang/Thread;J)Ljava/lang/Thread;
  #53 = Utf8               org/apache/commons/io/ThreadMonitor
  #54 = NameAndType        #37:#38        // "<init>":(Ljava/lang/Thread;J)V
  #55 = Utf8               java/lang/Thread
  #56 = Class              #73            // java/lang/Class
  #57 = NameAndType        #74:#75        // getSimpleName:()Ljava/lang/String;
  #58 = NameAndType        #37:#76        // "<init>":(Ljava/lang/Runnable;Ljava/lang/String;)V
  #59 = NameAndType        #77:#78        // setDaemon:(Z)V
  #60 = NameAndType        #24:#41        // start:()V
  #61 = NameAndType        #79:#41        // interrupt:()V
  #62 = NameAndType        #37:#41        // "<init>":()V
  #63 = NameAndType        #20:#21        // thread:Ljava/lang/Thread;
  #64 = NameAndType        #22:#23        // timeout:J
  #65 = NameAndType        #43:#44        // sleep:(J)V
  #66 = Utf8               java/lang/InterruptedException
  #67 = Class              #80            // java/lang/System
  #68 = NameAndType        #81:#82        // currentTimeMillis:()J
  #69 = Utf8               java/lang/Object
  #70 = Utf8               java/lang/Runnable
  #71 = Utf8               currentThread
  #72 = Utf8               ()Ljava/lang/Thread;
  #73 = Utf8               java/lang/Class
  #74 = Utf8               getSimpleName
  #75 = Utf8               ()Ljava/lang/String;
  #76 = Utf8               (Ljava/lang/Runnable;Ljava/lang/String;)V
  #77 = Utf8               setDaemon
  #78 = Utf8               (Z)V
  #79 = Utf8               interrupt
  #80 = Utf8               java/lang/System
  #81 = Utf8               currentTimeMillis
  #82 = Utf8               ()J
{
  private final java.lang.Thread thread;
    descriptor: Ljava/lang/Thread;
    flags: (0x0012) ACC_PRIVATE, ACC_FINAL

  private final long timeout;
    descriptor: J
    flags: (0x0012) ACC_PRIVATE, ACC_FINAL

  public static java.lang.Thread start(long);
    descriptor: (J)Ljava/lang/Thread;
    flags: (0x0009) ACC_PUBLIC, ACC_STATIC
    Code:
      stack=3, locals=2, args_size=1
         0: invokestatic  #1                  // Method java/lang/Thread.currentThread:()Ljava/lang/Thread;
         3: lload_0
         4: invokestatic  #2                  // Method start:(Ljava/lang/Thread;J)Ljava/lang/Thread;
         7: areturn
      LineNumberTable:
        line 54: 0
      LocalVariableTable:
        Start  Length  Slot  Name   Signature
            0       8     0 timeout   J

  public static java.lang.Thread start(java.lang.Thread, long);
    descriptor: (Ljava/lang/Thread;J)Ljava/lang/Thread;
    flags: (0x0009) ACC_PUBLIC, ACC_STATIC
    Code:
      stack=5, locals=5, args_size=2
         0: aconst_null
         1: astore_3
         2: lload_1
         3: lconst_0
         4: lcmp
         5: ifle          43
         8: new           #3                  // class org/apache/commons/io/ThreadMonitor
        11: dup
        12: aload_0
        13: lload_1
        14: invokespecial #4                  // Method "<init>":(Ljava/lang/Thread;J)V
        17: astore        4
        19: new           #5                  // class java/lang/Thread
        22: dup
        23: aload         4
        25: ldc           #3                  // class org/apache/commons/io/ThreadMonitor
        27: invokevirtual #6                  // Method java/lang/Class.getSimpleName:()Ljava/lang/String;
        30: invokespecial #7                  // Method java/lang/Thread."<init>":(Ljava/lang/Runnable;Ljava/lang/String;)V
        33: astore_3
        34: aload_3
        35: iconst_1
        36: invokevirtual #8                  // Method java/lang/Thread.setDaemon:(Z)V
        39: aload_3
        40: invokevirtual #9                  // Method java/lang/Thread.start:()V
        43: aload_3
        44: areturn
      LineNumberTable:
        line 67: 0
        line 68: 2
        line 69: 8
        line 70: 19
        line 71: 34
        line 72: 39
        line 74: 43
      LocalVariableTable:
        Start  Length  Slot  Name   Signature
           19      24     4 timout   Lorg/apache/commons/io/ThreadMonitor;
            0      45     0 thread   Ljava/lang/Thread;
            0      45     1 timeout   J
            2      43     3 monitor   Ljava/lang/Thread;
      StackMapTable: number_of_entries = 1
        frame_type = 252 /* append */
          offset_delta = 43
          locals = [ class java/lang/Thread ]

  public static void stop(java.lang.Thread);
    descriptor: (Ljava/lang/Thread;)V
    flags: (0x0009) ACC_PUBLIC, ACC_STATIC
    Code:
      stack=1, locals=1, args_size=1
         0: aload_0
         1: ifnull        8
         4: aload_0
         5: invokevirtual #10                 // Method java/lang/Thread.interrupt:()V
         8: return
      LineNumberTable:
        line 83: 0
        line 84: 4
        line 86: 8
      LocalVariableTable:
        Start  Length  Slot  Name   Signature
            0       9     0 thread   Ljava/lang/Thread;
      StackMapTable: number_of_entries = 1
        frame_type = 8 /* same */

  private org.apache.commons.io.ThreadMonitor(java.lang.Thread, long);
    descriptor: (Ljava/lang/Thread;J)V
    flags: (0x0002) ACC_PRIVATE
    Code:
      stack=3, locals=4, args_size=3
         0: aload_0
         1: invokespecial #11                 // Method java/lang/Object."<init>":()V
         4: aload_0
         5: aload_1
         6: putfield      #12                 // Field thread:Ljava/lang/Thread;
         9: aload_0
        10: lload_2
        11: putfield      #13                 // Field timeout:J
        14: return
      LineNumberTable:
        line 94: 0
        line 95: 4
        line 96: 9
        line 97: 14
      LocalVariableTable:
        Start  Length  Slot  Name   Signature
            0      15     0  this   Lorg/apache/commons/io/ThreadMonitor;
            0      15     1 thread   Ljava/lang/Thread;
            0      15     2 timeout   J

  public void run();
    descriptor: ()V
    flags: (0x0001) ACC_PUBLIC
    Code:
      stack=2, locals=2, args_size=1
         0: aload_0
         1: getfield      #13                 // Field timeout:J
         4: invokestatic  #14                 // Method sleep:(J)V
         7: aload_0
         8: getfield      #12                 // Field thread:Ljava/lang/Thread;
        11: invokevirtual #10                 // Method java/lang/Thread.interrupt:()V
        14: goto          18
        17: astore_1
        18: return
      Exception table:
         from    to  target type
             0    14    17   Class java/lang/InterruptedException
      LineNumberTable:
        line 108: 0
        line 109: 7
        line 112: 14
        line 110: 17
        line 113: 18
      LocalVariableTable:
        Start  Length  Slot  Name   Signature
            0      19     0  this   Lorg/apache/commons/io/ThreadMonitor;
      StackMapTable: number_of_entries = 2
        frame_type = 81 /* same_locals_1_stack_item */
          stack = [ class java/lang/InterruptedException ]
        frame_type = 0 /* same */

  private static void sleep(long) throws java.lang.InterruptedException;
    descriptor: (J)V
    flags: (0x000a) ACC_PRIVATE, ACC_STATIC
    Code:
      stack=4, locals=6, args_size=1
         0: invokestatic  #16                 // Method java/lang/System.currentTimeMillis:()J
         3: lload_0
         4: ladd
         5: lstore_2
         6: lload_0
         7: lstore        4
         9: lload         4
        11: invokestatic  #17                 // Method java/lang/Thread.sleep:(J)V
        14: lload_2
        15: invokestatic  #16                 // Method java/lang/System.currentTimeMillis:()J
        18: lsub
        19: lstore        4
        21: lload         4
        23: lconst_0
        24: lcmp
        25: ifgt          9
        28: return
      LineNumberTable:
        line 125: 0
        line 126: 6
        line 128: 9
        line 129: 14
        line 130: 21
        line 131: 28
      LocalVariableTable:
        Start  Length  Slot  Name   Signature
            0      29     0    ms   J
            6      23     2 finishAt   J
            9      20     4 remaining   J
      StackMapTable: number_of_entries = 1
        frame_type = 253 /* append */
          offset_delta = 9
          locals = [ long, long ]
    Exceptions:
      throws java.lang.InterruptedException
}
SourceFile: "ThreadMonitor.java"
