Classfile /Users/mw/Projects/slang-braindump/.jar/jar8/assemble/slang-braindump/assemble/content/org/sireum/bitcodec/Spec$Ext$.class
  Last modified May 29, 2022; size 1181 bytes
  SHA-256 checksum b9a63513ac4496034409438a0596d85a5c3643eee6b7810e438629089331bb47
  Compiled from "Spec.scala"
public class org.sireum.bitcodec.Spec$Ext$
  minor version: 0
  major version: 52
  flags: (0x0021) ACC_PUBLIC, ACC_SUPER
  this_class: #2                          // org/sireum/bitcodec/Spec$Ext$
  super_class: #4                         // java/lang/Object
  interfaces: 0, fields: 1, methods: 4, attributes: 4
Constant pool:
   #1 = Utf8               org/sireum/bitcodec/Spec$Ext$
   #2 = Class              #1             // org/sireum/bitcodec/Spec$Ext$
   #3 = Utf8               java/lang/Object
   #4 = Class              #3             // java/lang/Object
   #5 = Utf8               Spec.scala
   #6 = Utf8               org/sireum/Json$ErrorMsg
   #7 = Class              #6             // org/sireum/Json$ErrorMsg
   #8 = Utf8               org/sireum/Json
   #9 = Class              #8             // org/sireum/Json
  #10 = Utf8               ErrorMsg
  #11 = Utf8               org/sireum/bitcodec/Spec
  #12 = Class              #11            // org/sireum/bitcodec/Spec
  #13 = Utf8               Ext$
  #14 = Utf8               MODULE$
  #15 = Utf8               Lorg/sireum/bitcodec/Spec$Ext$;
  #16 = Utf8               <clinit>
  #17 = Utf8               ()V
  #18 = Utf8               <init>
  #19 = NameAndType        #18:#17        // "<init>":()V
  #20 = Methodref          #2.#19         // org/sireum/bitcodec/Spec$Ext$."<init>":()V
  #21 = NameAndType        #14:#15        // MODULE$:Lorg/sireum/bitcodec/Spec$Ext$;
  #22 = Fieldref           #2.#21         // org/sireum/bitcodec/Spec$Ext$.MODULE$:Lorg/sireum/bitcodec/Spec$Ext$;
  #23 = Utf8               toJSON
  #24 = Utf8               (Lorg/sireum/bitcodec/Spec;Z)Ljava/lang/String;
  #25 = Utf8               o
  #26 = Utf8               isCompact
  #27 = Utf8               org/sireum/bitcodec/Spec_Ext$
  #28 = Class              #27            // org/sireum/bitcodec/Spec_Ext$
  #29 = Utf8               Lorg/sireum/bitcodec/Spec_Ext$;
  #30 = NameAndType        #14:#29        // MODULE$:Lorg/sireum/bitcodec/Spec_Ext$;
  #31 = Fieldref           #28.#30        // org/sireum/bitcodec/Spec_Ext$.MODULE$:Lorg/sireum/bitcodec/Spec_Ext$;
  #32 = NameAndType        #23:#24        // toJSON:(Lorg/sireum/bitcodec/Spec;Z)Ljava/lang/String;
  #33 = Methodref          #28.#32        // org/sireum/bitcodec/Spec_Ext$.toJSON:(Lorg/sireum/bitcodec/Spec;Z)Ljava/lang/String;
  #34 = Utf8               this
  #35 = Utf8               Lorg/sireum/bitcodec/Spec;
  #36 = Utf8               Z
  #37 = Utf8               fromJSON
  #38 = Utf8               (Ljava/lang/String;)Lorg/sireum/Either;
  #39 = Utf8               (Ljava/lang/String;)Lorg/sireum/Either<Lorg/sireum/bitcodec/Spec;Lorg/sireum/Json$ErrorMsg;>;
  #40 = Utf8               s
  #41 = NameAndType        #37:#38        // fromJSON:(Ljava/lang/String;)Lorg/sireum/Either;
  #42 = Methodref          #28.#41        // org/sireum/bitcodec/Spec_Ext$.fromJSON:(Ljava/lang/String;)Lorg/sireum/Either;
  #43 = Utf8               Ljava/lang/String;
  #44 = Methodref          #4.#19         // java/lang/Object."<init>":()V
  #45 = Utf8               Code
  #46 = Utf8               LineNumberTable
  #47 = Utf8               LocalVariableTable
  #48 = Utf8               MethodParameters
  #49 = Utf8               Signature
  #50 = Utf8               InnerClasses
  #51 = Utf8               SourceFile
  #52 = Utf8               ScalaInlineInfo
  #53 = Utf8               Scala
{
  public static final org.sireum.bitcodec.Spec$Ext$ MODULE$;
    descriptor: Lorg/sireum/bitcodec/Spec$Ext$;
    flags: (0x0019) ACC_PUBLIC, ACC_STATIC, ACC_FINAL

  public static {};
    descriptor: ()V
    flags: (0x0009) ACC_PUBLIC, ACC_STATIC
    Code:
      stack=2, locals=0, args_size=0
         0: new           #2                  // class org/sireum/bitcodec/Spec$Ext$
         3: dup
         4: invokespecial #20                 // Method "<init>":()V
         7: putstatic     #22                 // Field MODULE$:Lorg/sireum/bitcodec/Spec$Ext$;
        10: return
      LineNumberTable:
        line 651: 0

  public java.lang.String toJSON(org.sireum.bitcodec.Spec, boolean);
    descriptor: (Lorg/sireum/bitcodec/Spec;Z)Ljava/lang/String;
    flags: (0x0001) ACC_PUBLIC
    Code:
      stack=3, locals=3, args_size=3
         0: getstatic     #31                 // Field org/sireum/bitcodec/Spec_Ext$.MODULE$:Lorg/sireum/bitcodec/Spec_Ext$;
         3: aload_1
         4: iload_2
         5: invokevirtual #33                 // Method org/sireum/bitcodec/Spec_Ext$.toJSON:(Lorg/sireum/bitcodec/Spec;Z)Ljava/lang/String;
         8: areturn
      LineNumberTable:
        line 652: 0
      LocalVariableTable:
        Start  Length  Slot  Name   Signature
            0       9     0  this   Lorg/sireum/bitcodec/Spec$Ext$;
            0       9     1     o   Lorg/sireum/bitcodec/Spec;
            0       9     2 isCompact   Z
    MethodParameters:
      Name                           Flags
      o                              final
      isCompact                      final

  public org.sireum.Either<org.sireum.bitcodec.Spec, org.sireum.Json$ErrorMsg> fromJSON(java.lang.String);
    descriptor: (Ljava/lang/String;)Lorg/sireum/Either;
    flags: (0x0001) ACC_PUBLIC
    Code:
      stack=2, locals=2, args_size=2
         0: getstatic     #31                 // Field org/sireum/bitcodec/Spec_Ext$.MODULE$:Lorg/sireum/bitcodec/Spec_Ext$;
         3: aload_1
         4: invokevirtual #42                 // Method org/sireum/bitcodec/Spec_Ext$.fromJSON:(Ljava/lang/String;)Lorg/sireum/Either;
         7: areturn
      LineNumberTable:
        line 653: 0
      LocalVariableTable:
        Start  Length  Slot  Name   Signature
            0       8     0  this   Lorg/sireum/bitcodec/Spec$Ext$;
            0       8     1     s   Ljava/lang/String;
    Signature: #39                          // (Ljava/lang/String;)Lorg/sireum/Either<Lorg/sireum/bitcodec/Spec;Lorg/sireum/Json$ErrorMsg;>;
    MethodParameters:
      Name                           Flags
      s                              final

  public org.sireum.bitcodec.Spec$Ext$();
    descriptor: ()V
    flags: (0x0001) ACC_PUBLIC
    Code:
      stack=1, locals=1, args_size=1
         0: aload_0
         1: invokespecial #44                 // Method java/lang/Object."<init>":()V
         4: return
      LineNumberTable:
        line 651: 0
      LocalVariableTable:
        Start  Length  Slot  Name   Signature
            0       5     0  this   Lorg/sireum/bitcodec/Spec$Ext$;
}
InnerClasses:
  public static final #10= #7 of #9;      // ErrorMsg=class org/sireum/Json$ErrorMsg of class org/sireum/Json
  public static #13= #2 of #12;           // Ext$=class org/sireum/bitcodec/Spec$Ext$ of class org/sireum/bitcodec/Spec
SourceFile: "Spec.scala"
  ScalaInlineInfo: length = 0x13 (unknown attribute)
   01 01 00 03 00 12 00 11 01 00 25 00 26 01 00 17
   00 18 01
  Scala: length = 0x0 (unknown attribute)

