Classfile /Users/mw/Projects/slang-braindump/.jar/jar11/assemble/slang-braindump/assemble/content/scala/collection/generic/DefaultSerializable.class
  Last modified May 29, 2022; size 2391 bytes
  SHA-256 checksum 7fcb13cbee6b7e4f00db36aca4cfd5acfdd3f5fce6a0982206ffd1a73163c6e2
  Compiled from "DefaultSerializationProxy.scala"
public interface scala.collection.generic.DefaultSerializable extends java.io.Serializable
  minor version: 0
  major version: 52
  flags: (0x0601) ACC_PUBLIC, ACC_INTERFACE, ACC_ABSTRACT
  this_class: #2                          // scala/collection/generic/DefaultSerializable
  super_class: #4                         // java/lang/Object
  interfaces: 1, fields: 0, methods: 3, attributes: 4
Constant pool:
   #1 = Utf8               scala/collection/generic/DefaultSerializable
   #2 = Class              #1             // scala/collection/generic/DefaultSerializable
   #3 = Utf8               java/lang/Object
   #4 = Class              #3             // java/lang/Object
   #5 = Utf8               java/io/Serializable
   #6 = Class              #5             // java/io/Serializable
   #7 = Utf8               DefaultSerializationProxy.scala
   #8 = Utf8               Lscala/reflect/ScalaSignature;
   #9 = Utf8               bytes
  #10 = Utf8               \u0006\u0005a2\u0001b\u0001\u0003\u0011\u0002\u0007\u00051b\t\u0005\u00069\u0001!\t!\b\u0005\u0007C\u0001\u0001K\u0011\u0003\u0012\u0003\'\u0011+g-Y;miN+\'/[1mSj\f\'\r\\3\u000b\u0005\u00151\u0011aB4f]\u0016\u0014\u0018n\u0019\u0006\u0003\u000f!\t!bY8mY\u0016\u001cG/[8o\u0015\u0005I\u0011!B:dC2\f7\u0001A\n\u0004\u00011\u0001\u0002CA\u0007\u000f\u001b\u0005A\u0011BA\b\t\u0005\u0019\te.\u001f*fMB\u0011\u0011#\u0007\b\u0003%]q!a\u0005\f\u000e\u0003QQ!!\u0006\u0006\u0002\rq\u0012xn\u001c;?\u0013\u0005I\u0011B\u0001\r\t\u0003\u001d\u0001\u0018mY6bO\u0016L!AG\u000e\u0003\u0019M+\'/[1mSj\f\'\r\\3\u000b\u0005aA\u0011A\u0002\u0013j]&$H\u0005F\u0001\u001f!\tiq$\u0003\u0002!\u0011\t!QK\\5u\u000319(/\u001b;f%\u0016\u0004H.Y2f)\u0005a!c\u0001\u0013\'Q\u0019!Q\u0005\u0001\u0001$\u00051a$/\u001a4j]\u0016lWM\u001c;?!\t9\u0003!D\u0001\u0005a\tIs\u0006E\u0002+W5j\u0011AB\u0005\u0003Y\u0019\u0011\u0001\"\u0013;fe\u0006\u0014G.\u001a\t\u0003]=b\u0001\u0001B\u00051\u0001\u0005\u0005\t\u0011!B\u0001c\t\u0019q\fJ\u0019\u0012\u0005I*\u0004CA\u00074\u0013\t!\u0004BA\u0004O_RD\u0017N\\4\u0011\u000551\u0014BA\u001c\t\u0005\r\te.\u001f
  #11 = Utf8               writeReplace$
  #12 = Utf8               (Lscala/collection/generic/DefaultSerializable;)Ljava/lang/Object;
  #13 = Utf8               $this
  #14 = Utf8               writeReplace
  #15 = Utf8               ()Ljava/lang/Object;
  #16 = NameAndType        #14:#15        // writeReplace:()Ljava/lang/Object;
  #17 = InterfaceMethodref #2.#16         // scala/collection/generic/DefaultSerializable.writeReplace:()Ljava/lang/Object;
  #18 = Utf8               Lscala/collection/generic/DefaultSerializable;
  #19 = Utf8               scala/collection/SortedMap
  #20 = Class              #19            // scala/collection/SortedMap
  #21 = Utf8               sortedMapFactory
  #22 = Utf8               ()Lscala/collection/SortedMapFactory;
  #23 = NameAndType        #21:#22        // sortedMapFactory:()Lscala/collection/SortedMapFactory;
  #24 = InterfaceMethodref #20.#23        // scala/collection/SortedMap.sortedMapFactory:()Lscala/collection/SortedMapFactory;
  #25 = Utf8               scala/collection/SortedOps
  #26 = Class              #25            // scala/collection/SortedOps
  #27 = Utf8               ordering
  #28 = Utf8               ()Lscala/math/Ordering;
  #29 = NameAndType        #27:#28        // ordering:()Lscala/math/Ordering;
  #30 = InterfaceMethodref #26.#29        // scala/collection/SortedOps.ordering:()Lscala/math/Ordering;
  #31 = Utf8               scala/collection/SortedMapFactory
  #32 = Class              #31            // scala/collection/SortedMapFactory
  #33 = Utf8               (Lscala/math/Ordering;)Lscala/collection/Factory;
  #34 = NameAndType        #21:#33        // sortedMapFactory:(Lscala/math/Ordering;)Lscala/collection/Factory;
  #35 = InterfaceMethodref #32.#34        // scala/collection/SortedMapFactory.sortedMapFactory:(Lscala/math/Ordering;)Lscala/collection/Factory;
  #36 = Utf8               scala/collection/Map
  #37 = Class              #36            // scala/collection/Map
  #38 = Utf8               mapFactory
  #39 = Utf8               ()Lscala/collection/MapFactory;
  #40 = NameAndType        #38:#39        // mapFactory:()Lscala/collection/MapFactory;
  #41 = InterfaceMethodref #37.#40        // scala/collection/Map.mapFactory:()Lscala/collection/MapFactory;
  #42 = Utf8               scala/collection/MapFactory
  #43 = Class              #42            // scala/collection/MapFactory
  #44 = Utf8               ()Lscala/collection/Factory;
  #45 = NameAndType        #38:#44        // mapFactory:()Lscala/collection/Factory;
  #46 = InterfaceMethodref #43.#45        // scala/collection/MapFactory.mapFactory:()Lscala/collection/Factory;
  #47 = Utf8               scala/collection/SortedSet
  #48 = Class              #47            // scala/collection/SortedSet
  #49 = Utf8               sortedIterableFactory
  #50 = Utf8               ()Lscala/collection/SortedIterableFactory;
  #51 = NameAndType        #49:#50        // sortedIterableFactory:()Lscala/collection/SortedIterableFactory;
  #52 = InterfaceMethodref #48.#51        // scala/collection/SortedSet.sortedIterableFactory:()Lscala/collection/SortedIterableFactory;
  #53 = Utf8               scala/collection/SortedIterableFactory
  #54 = Class              #53            // scala/collection/SortedIterableFactory
  #55 = Utf8               evidenceIterableFactory
  #56 = Utf8               (Ljava/lang/Object;)Lscala/collection/Factory;
  #57 = NameAndType        #55:#56        // evidenceIterableFactory:(Ljava/lang/Object;)Lscala/collection/Factory;
  #58 = InterfaceMethodref #54.#57        // scala/collection/SortedIterableFactory.evidenceIterableFactory:(Ljava/lang/Object;)Lscala/collection/Factory;
  #59 = Utf8               scala/collection/Iterable
  #60 = Class              #59            // scala/collection/Iterable
  #61 = Utf8               iterableFactory
  #62 = Utf8               ()Lscala/collection/IterableFactory;
  #63 = NameAndType        #61:#62        // iterableFactory:()Lscala/collection/IterableFactory;
  #64 = InterfaceMethodref #60.#63        // scala/collection/Iterable.iterableFactory:()Lscala/collection/IterableFactory;
  #65 = Utf8               scala/collection/IterableFactory
  #66 = Class              #65            // scala/collection/IterableFactory
  #67 = NameAndType        #61:#44        // iterableFactory:()Lscala/collection/Factory;
  #68 = InterfaceMethodref #66.#67        // scala/collection/IterableFactory.iterableFactory:()Lscala/collection/Factory;
  #69 = Utf8               scala/collection/generic/DefaultSerializationProxy
  #70 = Class              #69            // scala/collection/generic/DefaultSerializationProxy
  #71 = Utf8               <init>
  #72 = Utf8               (Lscala/collection/Factory;Lscala/collection/Iterable;)V
  #73 = NameAndType        #71:#72        // "<init>":(Lscala/collection/Factory;Lscala/collection/Iterable;)V
  #74 = Methodref          #70.#73        // scala/collection/generic/DefaultSerializationProxy."<init>":(Lscala/collection/Factory;Lscala/collection/Iterable;)V
  #75 = Utf8               this
  #76 = Utf8               scala/collection/Factory
  #77 = Class              #76            // scala/collection/Factory
  #78 = Utf8               $init$
  #79 = Utf8               (Lscala/collection/generic/DefaultSerializable;)V
  #80 = Utf8               Code
  #81 = Utf8               LineNumberTable
  #82 = Utf8               LocalVariableTable
  #83 = Utf8               MethodParameters
  #84 = Utf8               StackMapTable
  #85 = Utf8               SourceFile
  #86 = Utf8               RuntimeVisibleAnnotations
  #87 = Utf8               ScalaInlineInfo
  #88 = Utf8               ScalaSig
{
  public static java.lang.Object writeReplace$(scala.collection.generic.DefaultSerializable);
    descriptor: (Lscala/collection/generic/DefaultSerializable;)Ljava/lang/Object;
    flags: (0x1009) ACC_PUBLIC, ACC_STATIC, ACC_SYNTHETIC
    Code:
      stack=1, locals=1, args_size=1
         0: aload_0
         1: invokespecial #17                 // InterfaceMethod writeReplace:()Ljava/lang/Object;
         4: areturn
      LineNumberTable:
        line 78: 0
      LocalVariableTable:
        Start  Length  Slot  Name   Signature
            0       5     0 $this   Lscala/collection/generic/DefaultSerializable;
    MethodParameters:
      Name                           Flags
      $this                          final synthetic

  public default java.lang.Object writeReplace();
    descriptor: ()Ljava/lang/Object;
    flags: (0x0001) ACC_PUBLIC
    Code:
      stack=4, locals=2, args_size=1
         0: aload_0
         1: instanceof    #20                 // class scala/collection/SortedMap
         4: ifeq          34
         7: aload_0
         8: checkcast     #20                 // class scala/collection/SortedMap
        11: invokeinterface #24,  1           // InterfaceMethod scala/collection/SortedMap.sortedMapFactory:()Lscala/collection/SortedMapFactory;
        16: aload_0
        17: checkcast     #26                 // class scala/collection/SortedOps
        20: invokeinterface #30,  1           // InterfaceMethod scala/collection/SortedOps.ordering:()Lscala/math/Ordering;
        25: invokeinterface #35,  2           // InterfaceMethod scala/collection/SortedMapFactory.sortedMapFactory:(Lscala/math/Ordering;)Lscala/collection/Factory;
        30: astore_1
        31: goto          108
        34: aload_0
        35: instanceof    #37                 // class scala/collection/Map
        38: ifeq          59
        41: aload_0
        42: checkcast     #37                 // class scala/collection/Map
        45: invokeinterface #41,  1           // InterfaceMethod scala/collection/Map.mapFactory:()Lscala/collection/MapFactory;
        50: invokeinterface #46,  1           // InterfaceMethod scala/collection/MapFactory.mapFactory:()Lscala/collection/Factory;
        55: astore_1
        56: goto          108
        59: aload_0
        60: instanceof    #48                 // class scala/collection/SortedSet
        63: ifeq          93
        66: aload_0
        67: checkcast     #48                 // class scala/collection/SortedSet
        70: invokeinterface #52,  1           // InterfaceMethod scala/collection/SortedSet.sortedIterableFactory:()Lscala/collection/SortedIterableFactory;
        75: aload_0
        76: checkcast     #26                 // class scala/collection/SortedOps
        79: invokeinterface #30,  1           // InterfaceMethod scala/collection/SortedOps.ordering:()Lscala/math/Ordering;
        84: invokeinterface #58,  2           // InterfaceMethod scala/collection/SortedIterableFactory.evidenceIterableFactory:(Ljava/lang/Object;)Lscala/collection/Factory;
        89: astore_1
        90: goto          108
        93: aload_0
        94: checkcast     #60                 // class scala/collection/Iterable
        97: invokeinterface #64,  1           // InterfaceMethod scala/collection/Iterable.iterableFactory:()Lscala/collection/IterableFactory;
       102: invokeinterface #68,  1           // InterfaceMethod scala/collection/IterableFactory.iterableFactory:()Lscala/collection/Factory;
       107: astore_1
       108: new           #70                 // class scala/collection/generic/DefaultSerializationProxy
       111: dup
       112: aload_1
       113: aload_0
       114: checkcast     #60                 // class scala/collection/Iterable
       117: invokespecial #74                 // Method scala/collection/generic/DefaultSerializationProxy."<init>":(Lscala/collection/Factory;Lscala/collection/Iterable;)V
       120: areturn
      StackMapTable: number_of_entries = 4
        frame_type = 34 /* same */
        frame_type = 24 /* same */
        frame_type = 33 /* same */
        frame_type = 252 /* append */
          offset_delta = 14
          locals = [ class scala/collection/Factory ]
      LineNumberTable:
        line 80: 0
        line 81: 34
        line 82: 59
        line 83: 93
        line 85: 108
      LocalVariableTable:
        Start  Length  Slot  Name   Signature
            0     121     0  this   Lscala/collection/generic/DefaultSerializable;

  public static void $init$(scala.collection.generic.DefaultSerializable);
    descriptor: (Lscala/collection/generic/DefaultSerializable;)V
    flags: (0x0009) ACC_PUBLIC, ACC_STATIC
    Code:
      stack=0, locals=1, args_size=1
         0: return
      LineNumberTable:
        line 77: 0
      LocalVariableTable:
        Start  Length  Slot  Name   Signature
            0       1     0 $this   Lscala/collection/generic/DefaultSerializable;
    MethodParameters:
      Name                           Flags
      $this                          final synthetic
}
SourceFile: "DefaultSerializationProxy.scala"
RuntimeVisibleAnnotations:
  0: #8(#9=s#10)
    scala.reflect.ScalaSignature(
      bytes="\u0006\u0005a2\u0001b\u0001\u0003\u0011\u0002\u0007\u00051b\t\u0005\u00069\u0001!\t!\b\u0005\u0007C\u0001\u0001K\u0011\u0003\u0012\u0003\'\u0011+g-Y;miN+\'/[1mSj\f\'\r\\3\u000b\u0005\u00151\u0011aB4f]\u0016\u0014\u0018n\u0019\u0006\u0003\u000f!\t!bY8mY\u0016\u001cG/[8o\u0015\u0005I\u0011!B:dC2\f7\u0001A\n\u0004\u00011\u0001\u0002CA\u0007\u000f\u001b\u0005A\u0011BA\b\t\u0005\u0019\te.\u001f*fMB\u0011\u0011#\u0007\b\u0003%]q!a\u0005\f\u000e\u0003QQ!!\u0006\u0006\u0002\rq\u0012xn\u001c;?\u0013\u0005I\u0011B\u0001\r\t\u0003\u001d\u0001\u0018mY6bO\u0016L!AG\u000e\u0003\u0019M+\'/[1mSj\f\'\r\\3\u000b\u0005aA\u0011A\u0002\u0013j]&$H\u0005F\u0001\u001f!\tiq$\u0003\u0002!\u0011\t!QK\\5u\u000319(/\u001b;f%\u0016\u0004H.Y2f)\u0005a!c\u0001\u0013\'Q\u0019!Q\u0005\u0001\u0001$\u00051a$/\u001a4j]\u0016lWM\u001c;?!\t9\u0003!D\u0001\u0005a\tIs\u0006E\u0002+W5j\u0011AB\u0005\u0003Y\u0019\u0011\u0001\"\u0013;fe\u0006\u0014G.\u001a\t\u0003]=b\u0001\u0001B\u00051\u0001\u0005\u0005\t\u0011!B\u0001c\t\u0019q\fJ\u0019\u0012\u0005I*\u0004CA\u00074\u0013\t!\u0004BA\u0004O_RD\u0017N\\4\u0011\u000551\u0014BA\u001c\t\u0005\r\te.\u001f"
    )
  ScalaInlineInfo: length = 0x13 (unknown attribute)
   01 00 00 03 00 4E 00 4F 01 00 0E 00 0F 00 00 0B
   00 0C 01
  ScalaSig: length = 0x3 (unknown attribute)
   05 02 00
