Classfile /Users/mw/Projects/slang-braindump/.jar/jar11/assemble/slang-braindump/assemble/content/scala/collection/generic/IsIterableOnce.class
  Last modified May 29, 2022; size 3818 bytes
  SHA-256 checksum ac32c9cfce12c5295f56dc008ba3c23bf9bffc34449b4c36b41f137bbd0bba43
  Compiled from "IsIterableOnce.scala"
public interface scala.collection.generic.IsIterableOnce<Repr extends java.lang.Object>
  minor version: 0
  major version: 52
  flags: (0x0601) ACC_PUBLIC, ACC_INTERFACE, ACC_ABSTRACT
  this_class: #2                          // scala/collection/generic/IsIterableOnce
  super_class: #5                         // java/lang/Object
  interfaces: 0, fields: 0, methods: 8, attributes: 7
Constant pool:
   #1 = Utf8               scala/collection/generic/IsIterableOnce
   #2 = Class              #1             // scala/collection/generic/IsIterableOnce
   #3 = Utf8               <Repr:Ljava/lang/Object;>Ljava/lang/Object;
   #4 = Utf8               java/lang/Object
   #5 = Class              #4             // java/lang/Object
   #6 = Utf8               IsIterableOnce.scala
   #7 = Utf8               Lscala/reflect/ScalaSignature;
   #8 = Utf8               bytes
   #9 = Utf8               \u0006\u0005u3q!\u0003\u0006\u0011\u0002\u0007\u0005\u0011\u0003C\u0003\u0018\u0001\u0011\u0005\u0001\u0004B\u0003\u001d\u0001\t\u0005Q\u0004C\u0004%\u0001\t\u0007I\u0011A\u0013\t\u000bu\u0002a\u0011\u0001 \b\u000b\u0005S\u0001\u0012\u0001\"\u0007\u000b%Q\u0001\u0012\u0001#\t\u000b!3A\u0011A%\t\u000b)3A1A&\u0003\u001d%\u001b\u0018\n^3sC\ndWm\u00148dK*\u00111\u0002D\u0001\bO\u0016tWM]5d\u0015\tia\"\u0001\u0006d_2dWm\u0019;j_:T\u0011aD\u0001\u0006g\u000e\fG.Y\u0002\u0001+\t\u00112f\u0005\u0002\u0001\'A\u0011A#F\u0007\u0002\u001d%\u0011aC\u0004\u0002\u0007\u0003:L(+\u001a4\u0002\r\u0011Jg.\u001b;%)\u0005I\u0002C\u0001\u000b\u001b\u0013\tYbB\u0001\u0003V]&$(!A!\u0012\u0005y\t\u0003C\u0001\u000b \u0013\t\u0001cBA\u0004O_RD\u0017N\\4\u0011\u0005Q\u0011\u0013BA\u0012\u000f\u0005\r\te._\u0001\u000bG>tg/\u001a:tS>tW#\u0001\u0014\u0011\tQ9\u0013&L\u0005\u0003Q9\u0011\u0011BR;oGRLwN\\\u0019\u0011\u0005)ZC\u0002\u0001\u0003\u0006Y\u0001\u0011\r!\b\u0002\u0005%\u0016\u0004(\u000fE\u0002/_Ej\u0011\u0001D\u0005\u0003a1\u0011A\"\u0013;fe\u0006\u0014G.Z(oG\u0016\u0004\"A\r\u0002\u000e\u0003\u0001Aca\u0001\u001b8qiZ\u0004C\u0001\u000b6\u0013\t1dB\u0001\u0006eKB\u0014XmY1uK\u0012\fq!\\3tg\u0006<W-I\u0001:\u0003):3m\u001c8wKJ\u001c\u0018n\u001c8(A%\u001c\bE\\8xA\u0005\u0004S.\u001a;i_\u0012\u0004c.Y7fI\u0002:\u0013\r\u001d9ms\u001e\nQa]5oG\u0016\f\u0013\u0001P\u0001\u0007e9\n4G\f\u0019\u0002\u000b\u0005\u0004\b\u000f\\=\u0015\u00055z\u0004\"\u0002!\u0005\u0001\u0004I\u0013\u0001B2pY2\fa\"S:Ji\u0016\u0014\u0018M\u00197f\u001f:\u001cW\r\u0005\u0002D\r5\t!bE\u0002\u0007\'\u0015\u0003\"a\u0011$\n\u0005\u001dS!!G%t\u0013R,\'/\u00192mK>s7-\u001a\'poB\u0013\u0018n\u001c:jif\fa\u0001P5oSRtD#\u0001\"\u00025%$XM]1cY\u0016|enY3Jg&#XM]1cY\u0016|enY3\u0016\u00071\u0013&,F\u0001N%\tq\u0005K\u0002\u0003P\r\u0001i%\u0001\u0004\u001fsK\u001aLg.Z7f]Rt\u0004cA\"\u0001#B\u0019!FU-\u0005\u000bMC!\u0019\u0001+\u0003\u0007\r\u001b\u0005\'\u0006\u0002V1F\u0011aD\u0016\t\u0004]=:\u0006C\u0001\u0016Y\t\u0015a\"K1\u0001\u001e!\tQ#\fB\u0003\\\u0011\t\u0007QD\u0001\u0002Ba\u0015!AD\u0014\u0001Z\u0001
  #10 = Utf8               java/lang/invoke/MethodHandles$Lookup
  #11 = Class              #10            // java/lang/invoke/MethodHandles$Lookup
  #12 = Utf8               java/lang/invoke/MethodHandles
  #13 = Class              #12            // java/lang/invoke/MethodHandles
  #14 = Utf8               Lookup
  #15 = Utf8               scala/collection/generic/IsIterableOnce$$anon$1
  #16 = Class              #15            // scala/collection/generic/IsIterableOnce$$anon$1
  #17 = Utf8               iterableOnceIsIterableOnce
  #18 = Utf8               ()Lscala/collection/generic/IsIterableOnce;
  #19 = Utf8               <CC0::Lscala/collection/IterableOnce<Ljava/lang/Object;>;A0:Ljava/lang/Object;>()Lscala/collection/generic/IsIterableOnce<TCC0;>;
  #20 = Utf8               scala/collection/generic/IsIterableOnce$
  #21 = Class              #20            // scala/collection/generic/IsIterableOnce$
  #22 = Utf8               MODULE$
  #23 = Utf8               Lscala/collection/generic/IsIterableOnce$;
  #24 = NameAndType        #22:#23        // MODULE$:Lscala/collection/generic/IsIterableOnce$;
  #25 = Fieldref           #21.#24        // scala/collection/generic/IsIterableOnce$.MODULE$:Lscala/collection/generic/IsIterableOnce$;
  #26 = Utf8               <init>
  #27 = Utf8               ()V
  #28 = NameAndType        #26:#27        // "<init>":()V
  #29 = Methodref          #16.#28        // scala/collection/generic/IsIterableOnce$$anon$1."<init>":()V
  #30 = Utf8               isIterableLikeIsIterableOnce
  #31 = Utf8               (Lscala/collection/generic/IsIterable;)Lscala/collection/generic/IsIterableOnce;
  #32 = Utf8               <Repr:Ljava/lang/Object;>(Lscala/collection/generic/IsIterable<TRepr;>;)Lscala/collection/generic/IsIterableOnce<TRepr;>;
  #33 = Utf8               isIterableLike
  #34 = Utf8               Lscala/collection/generic/IsIterable;
  #35 = Utf8               scala$collection$generic$IsIterableOnce$_setter_$conversion_$eq
  #36 = Utf8               (Lscala/Function1;)V
  #37 = Utf8               (Lscala/Function1<TRepr;Lscala/collection/IterableOnce<Ljava/lang/Object;>;>;)V
  #38 = Utf8               x$1
  #39 = Utf8               conversion
  #40 = Utf8               ()Lscala/Function1;
  #41 = Utf8               ()Lscala/Function1<TRepr;Lscala/collection/IterableOnce<Ljava/lang/Object;>;>;
  #42 = Utf8               apply
  #43 = Utf8               (Ljava/lang/Object;)Lscala/collection/IterableOnce;
  #44 = Utf8               (TRepr;)Lscala/collection/IterableOnce<Ljava/lang/Object;>;
  #45 = Utf8               coll
  #46 = Utf8               $anonfun$conversion$1
  #47 = Utf8               (Lscala/collection/generic/IsIterableOnce;Ljava/lang/Object;)Lscala/collection/IterableOnce;
  #48 = Utf8               $this
  #49 = NameAndType        #42:#43        // apply:(Ljava/lang/Object;)Lscala/collection/IterableOnce;
  #50 = InterfaceMethodref #2.#49         // scala/collection/generic/IsIterableOnce.apply:(Ljava/lang/Object;)Lscala/collection/IterableOnce;
  #51 = Utf8               Lscala/collection/generic/IsIterableOnce;
  #52 = Utf8               Ljava/lang/Object;
  #53 = Utf8               $init$
  #54 = Utf8               (Lscala/collection/generic/IsIterableOnce;)V
  #55 = Utf8               (Ljava/lang/Object;)Ljava/lang/Object;
  #56 = MethodType         #55            //  (Ljava/lang/Object;)Ljava/lang/Object;
  #57 = NameAndType        #46:#47        // $anonfun$conversion$1:(Lscala/collection/generic/IsIterableOnce;Ljava/lang/Object;)Lscala/collection/IterableOnce;
  #58 = InterfaceMethodref #2.#57         // scala/collection/generic/IsIterableOnce.$anonfun$conversion$1:(Lscala/collection/generic/IsIterableOnce;Ljava/lang/Object;)Lscala/collection/IterableOnce;
  #59 = MethodHandle       6:#58          // REF_invokeStatic scala/collection/generic/IsIterableOnce.$anonfun$conversion$1:(Lscala/collection/generic/IsIterableOnce;Ljava/lang/Object;)Lscala/collection/IterableOnce;
  #60 = MethodType         #43            //  (Ljava/lang/Object;)Lscala/collection/IterableOnce;
  #61 = Integer            5
  #62 = Integer            1
  #63 = Utf8               java/lang/invoke/LambdaMetafactory
  #64 = Class              #63            // java/lang/invoke/LambdaMetafactory
  #65 = Utf8               altMetafactory
  #66 = Utf8               (Ljava/lang/invoke/MethodHandles$Lookup;Ljava/lang/String;Ljava/lang/invoke/MethodType;[Ljava/lang/Object;)Ljava/lang/invoke/CallSite;
  #67 = NameAndType        #65:#66        // altMetafactory:(Ljava/lang/invoke/MethodHandles$Lookup;Ljava/lang/String;Ljava/lang/invoke/MethodType;[Ljava/lang/Object;)Ljava/lang/invoke/CallSite;
  #68 = Methodref          #64.#67        // java/lang/invoke/LambdaMetafactory.altMetafactory:(Ljava/lang/invoke/MethodHandles$Lookup;Ljava/lang/String;Ljava/lang/invoke/MethodType;[Ljava/lang/Object;)Ljava/lang/invoke/CallSite;
  #69 = MethodHandle       6:#68          // REF_invokeStatic java/lang/invoke/LambdaMetafactory.altMetafactory:(Ljava/lang/invoke/MethodHandles$Lookup;Ljava/lang/String;Ljava/lang/invoke/MethodType;[Ljava/lang/Object;)Ljava/lang/invoke/CallSite;
  #70 = Utf8               (Lscala/collection/generic/IsIterableOnce;)Lscala/Function1;
  #71 = NameAndType        #42:#70        // apply:(Lscala/collection/generic/IsIterableOnce;)Lscala/Function1;
  #72 = InvokeDynamic      #0:#71         // #0:apply:(Lscala/collection/generic/IsIterableOnce;)Lscala/Function1;
  #73 = NameAndType        #35:#36        // scala$collection$generic$IsIterableOnce$_setter_$conversion_$eq:(Lscala/Function1;)V
  #74 = InterfaceMethodref #2.#73         // scala/collection/generic/IsIterableOnce.scala$collection$generic$IsIterableOnce$_setter_$conversion_$eq:(Lscala/Function1;)V
  #75 = Utf8               $deserializeLambda$
  #76 = Utf8               (Ljava/lang/invoke/SerializedLambda;)Ljava/lang/Object;
  #77 = Utf8               scala/runtime/LambdaDeserialize
  #78 = Class              #77            // scala/runtime/LambdaDeserialize
  #79 = Utf8               bootstrap
  #80 = Utf8               (Ljava/lang/invoke/MethodHandles$Lookup;Ljava/lang/String;Ljava/lang/invoke/MethodType;[Ljava/lang/invoke/MethodHandle;)Ljava/lang/invoke/CallSite;
  #81 = NameAndType        #79:#80        // bootstrap:(Ljava/lang/invoke/MethodHandles$Lookup;Ljava/lang/String;Ljava/lang/invoke/MethodType;[Ljava/lang/invoke/MethodHandle;)Ljava/lang/invoke/CallSite;
  #82 = Methodref          #78.#81        // scala/runtime/LambdaDeserialize.bootstrap:(Ljava/lang/invoke/MethodHandles$Lookup;Ljava/lang/String;Ljava/lang/invoke/MethodType;[Ljava/lang/invoke/MethodHandle;)Ljava/lang/invoke/CallSite;
  #83 = MethodHandle       6:#82          // REF_invokeStatic scala/runtime/LambdaDeserialize.bootstrap:(Ljava/lang/invoke/MethodHandles$Lookup;Ljava/lang/String;Ljava/lang/invoke/MethodType;[Ljava/lang/invoke/MethodHandle;)Ljava/lang/invoke/CallSite;
  #84 = Utf8               lambdaDeserialize
  #85 = NameAndType        #84:#76        // lambdaDeserialize:(Ljava/lang/invoke/SerializedLambda;)Ljava/lang/Object;
  #86 = InvokeDynamic      #1:#85         // #1:lambdaDeserialize:(Ljava/lang/invoke/SerializedLambda;)Ljava/lang/Object;
  #87 = Utf8               Code
  #88 = Utf8               LineNumberTable
  #89 = Utf8               Signature
  #90 = Utf8               LocalVariableTable
  #91 = Utf8               MethodParameters
  #92 = Utf8               Deprecated
  #93 = Utf8               InnerClasses
  #94 = Utf8               SourceFile
  #95 = Utf8               RuntimeVisibleAnnotations
  #96 = Utf8               BootstrapMethods
  #97 = Utf8               ScalaInlineInfo
  #98 = Utf8               ScalaSig
{
  public static <CC0 extends scala.collection.IterableOnce<java.lang.Object>, A0 extends java.lang.Object> scala.collection.generic.IsIterableOnce<CC0> iterableOnceIsIterableOnce();
    descriptor: ()Lscala/collection/generic/IsIterableOnce;
    flags: (0x0009) ACC_PUBLIC, ACC_STATIC
    Code:
      stack=2, locals=0, args_size=0
         0: getstatic     #25                 // Field scala/collection/generic/IsIterableOnce$.MODULE$:Lscala/collection/generic/IsIterableOnce$;
         3: pop
         4: new           #16                 // class scala/collection/generic/IsIterableOnce$$anon$1
         7: dup
         8: invokespecial #29                 // Method scala/collection/generic/IsIterableOnce$$anon$1."<init>":()V
        11: areturn
      LineNumberTable:
        line 57: 4
    Signature: #19                          // <CC0::Lscala/collection/IterableOnce<Ljava/lang/Object;>;A0:Ljava/lang/Object;>()Lscala/collection/generic/IsIterableOnce<TCC0;>;

  public static <Repr extends java.lang.Object> scala.collection.generic.IsIterableOnce<Repr> isIterableLikeIsIterableOnce(scala.collection.generic.IsIterable<Repr>);
    descriptor: (Lscala/collection/generic/IsIterable;)Lscala/collection/generic/IsIterableOnce;
    flags: (0x0009) ACC_PUBLIC, ACC_STATIC
    Code:
      stack=1, locals=1, args_size=1
         0: getstatic     #25                 // Field scala/collection/generic/IsIterableOnce$.MODULE$:Lscala/collection/generic/IsIterableOnce$;
         3: pop
         4: aload_0
         5: areturn
      LineNumberTable:
        line 53: 4
      LocalVariableTable:
        Start  Length  Slot  Name   Signature
            0       6     0 isIterableLike   Lscala/collection/generic/IsIterable;
    Signature: #32                          // <Repr:Ljava/lang/Object;>(Lscala/collection/generic/IsIterable<TRepr;>;)Lscala/collection/generic/IsIterableOnce<TRepr;>;
    MethodParameters:
      Name                           Flags
      isIterableLike                 final

  public abstract void scala$collection$generic$IsIterableOnce$_setter_$conversion_$eq(scala.Function1<Repr, scala.collection.IterableOnce<java.lang.Object>>);
    descriptor: (Lscala/Function1;)V
    flags: (0x0401) ACC_PUBLIC, ACC_ABSTRACT
    Signature: #37                          // (Lscala/Function1<TRepr;Lscala/collection/IterableOnce<Ljava/lang/Object;>;>;)V
    MethodParameters:
      Name                           Flags
      x$1                            final

  public abstract scala.Function1<Repr, scala.collection.IterableOnce<java.lang.Object>> conversion();
    descriptor: ()Lscala/Function1;
    flags: (0x0401) ACC_PUBLIC, ACC_ABSTRACT
    Signature: #41                          // ()Lscala/Function1<TRepr;Lscala/collection/IterableOnce<Ljava/lang/Object;>;>;
    Deprecated: true

  public abstract scala.collection.IterableOnce<java.lang.Object> apply(Repr);
    descriptor: (Ljava/lang/Object;)Lscala/collection/IterableOnce;
    flags: (0x0401) ACC_PUBLIC, ACC_ABSTRACT
    Signature: #44                          // (TRepr;)Lscala/collection/IterableOnce<Ljava/lang/Object;>;
    MethodParameters:
      Name                           Flags
      coll                           final

  public static scala.collection.IterableOnce $anonfun$conversion$1(scala.collection.generic.IsIterableOnce, java.lang.Object);
    descriptor: (Lscala/collection/generic/IsIterableOnce;Ljava/lang/Object;)Lscala/collection/IterableOnce;
    flags: (0x1009) ACC_PUBLIC, ACC_STATIC, ACC_SYNTHETIC
    Code:
      stack=2, locals=2, args_size=2
         0: aload_0
         1: aload_1
         2: invokeinterface #50,  2           // InterfaceMethod apply:(Ljava/lang/Object;)Lscala/collection/IterableOnce;
         7: areturn
      LineNumberTable:
        line 46: 0
      LocalVariableTable:
        Start  Length  Slot  Name   Signature
            0       8     0 $this   Lscala/collection/generic/IsIterableOnce;
            0       8     1   x$1   Ljava/lang/Object;
    MethodParameters:
      Name                           Flags
      $this                          final synthetic
      x$1                            final

  public static void $init$(scala.collection.generic.IsIterableOnce);
    descriptor: (Lscala/collection/generic/IsIterableOnce;)V
    flags: (0x0009) ACC_PUBLIC, ACC_STATIC
    Code:
      stack=2, locals=1, args_size=1
         0: aload_0
         1: aload_0
         2: invokedynamic #72,  0             // InvokeDynamic #0:apply:(Lscala/collection/generic/IsIterableOnce;)Lscala/Function1;
         7: invokeinterface #74,  2           // InterfaceMethod scala$collection$generic$IsIterableOnce$_setter_$conversion_$eq:(Lscala/Function1;)V
        12: return
      LineNumberTable:
        line 46: 0
        line 40: 12
      LocalVariableTable:
        Start  Length  Slot  Name   Signature
            0      13     0 $this   Lscala/collection/generic/IsIterableOnce;
    MethodParameters:
      Name                           Flags
      $this                          final synthetic

  private static java.lang.Object $deserializeLambda$(java.lang.invoke.SerializedLambda);
    descriptor: (Ljava/lang/invoke/SerializedLambda;)Ljava/lang/Object;
    flags: (0x100a) ACC_PRIVATE, ACC_STATIC, ACC_SYNTHETIC
    Code:
      stack=1, locals=1, args_size=1
         0: aload_0
         1: invokedynamic #86,  0             // InvokeDynamic #1:lambdaDeserialize:(Ljava/lang/invoke/SerializedLambda;)Ljava/lang/Object;
         6: areturn
}
InnerClasses:
  public static final #14= #11 of #13;    // Lookup=class java/lang/invoke/MethodHandles$Lookup of class java/lang/invoke/MethodHandles
  public final #16;                       // class scala/collection/generic/IsIterableOnce$$anon$1
Signature: #3                           // <Repr:Ljava/lang/Object;>Ljava/lang/Object;
SourceFile: "IsIterableOnce.scala"
RuntimeVisibleAnnotations:
  0: #7(#8=s#9)
    scala.reflect.ScalaSignature(
      bytes="\u0006\u0005u3q!\u0003\u0006\u0011\u0002\u0007\u0005\u0011\u0003C\u0003\u0018\u0001\u0011\u0005\u0001\u0004B\u0003\u001d\u0001\t\u0005Q\u0004C\u0004%\u0001\t\u0007I\u0011A\u0013\t\u000bu\u0002a\u0011\u0001 \b\u000b\u0005S\u0001\u0012\u0001\"\u0007\u000b%Q\u0001\u0012\u0001#\t\u000b!3A\u0011A%\t\u000b)3A1A&\u0003\u001d%\u001b\u0018\n^3sC\ndWm\u00148dK*\u00111\u0002D\u0001\bO\u0016tWM]5d\u0015\tia\"\u0001\u0006d_2dWm\u0019;j_:T\u0011aD\u0001\u0006g\u000e\fG.Y\u0002\u0001+\t\u00112f\u0005\u0002\u0001\'A\u0011A#F\u0007\u0002\u001d%\u0011aC\u0004\u0002\u0007\u0003:L(+\u001a4\u0002\r\u0011Jg.\u001b;%)\u0005I\u0002C\u0001\u000b\u001b\u0013\tYbB\u0001\u0003V]&$(!A!\u0012\u0005y\t\u0003C\u0001\u000b \u0013\t\u0001cBA\u0004O_RD\u0017N\\4\u0011\u0005Q\u0011\u0013BA\u0012\u000f\u0005\r\te._\u0001\u000bG>tg/\u001a:tS>tW#\u0001\u0014\u0011\tQ9\u0013&L\u0005\u0003Q9\u0011\u0011BR;oGRLwN\\\u0019\u0011\u0005)ZC\u0002\u0001\u0003\u0006Y\u0001\u0011\r!\b\u0002\u0005%\u0016\u0004(\u000fE\u0002/_Ej\u0011\u0001D\u0005\u0003a1\u0011A\"\u0013;fe\u0006\u0014G.Z(oG\u0016\u0004\"A\r\u0002\u000e\u0003\u0001Aca\u0001\u001b8qiZ\u0004C\u0001\u000b6\u0013\t1dB\u0001\u0006eKB\u0014XmY1uK\u0012\fq!\\3tg\u0006<W-I\u0001:\u0003):3m\u001c8wKJ\u001c\u0018n\u001c8(A%\u001c\bE\\8xA\u0005\u0004S.\u001a;i_\u0012\u0004c.Y7fI\u0002:\u0013\r\u001d9ms\u001e\nQa]5oG\u0016\f\u0013\u0001P\u0001\u0007e9\n4G\f\u0019\u0002\u000b\u0005\u0004\b\u000f\\=\u0015\u00055z\u0004\"\u0002!\u0005\u0001\u0004I\u0013\u0001B2pY2\fa\"S:Ji\u0016\u0014\u0018M\u00197f\u001f:\u001cW\r\u0005\u0002D\r5\t!bE\u0002\u0007\'\u0015\u0003\"a\u0011$\n\u0005\u001dS!!G%t\u0013R,\'/\u00192mK>s7-\u001a\'poB\u0013\u0018n\u001c:jif\fa\u0001P5oSRtD#\u0001\"\u00025%$XM]1cY\u0016|enY3Jg&#XM]1cY\u0016|enY3\u0016\u00071\u0013&,F\u0001N%\tq\u0005K\u0002\u0003P\r\u0001i%\u0001\u0004\u001fsK\u001aLg.Z7f]Rt\u0004cA\"\u0001#B\u0019!FU-\u0005\u000bMC!\u0019\u0001+\u0003\u0007\r\u001b\u0005\'\u0006\u0002V1F\u0011aD\u0016\t\u0004]=:\u0006C\u0001\u0016Y\t\u0015a\"K1\u0001\u001e!\tQ#\fB\u0003\\\u0011\t\u0007QD\u0001\u0002Ba\u0015!AD\u0014\u0001Z\u0001"
    )
BootstrapMethods:
  0: #69 REF_invokeStatic java/lang/invoke/LambdaMetafactory.altMetafactory:(Ljava/lang/invoke/MethodHandles$Lookup;Ljava/lang/String;Ljava/lang/invoke/MethodType;[Ljava/lang/Object;)Ljava/lang/invoke/CallSite;
    Method arguments:
      #56 (Ljava/lang/Object;)Ljava/lang/Object;
      #59 REF_invokeStatic scala/collection/generic/IsIterableOnce.$anonfun$conversion$1:(Lscala/collection/generic/IsIterableOnce;Ljava/lang/Object;)Lscala/collection/IterableOnce;
      #60 (Ljava/lang/Object;)Lscala/collection/IterableOnce;
      #61 5
      #62 1
      #60 (Ljava/lang/Object;)Lscala/collection/IterableOnce;
  1: #83 REF_invokeStatic scala/runtime/LambdaDeserialize.bootstrap:(Ljava/lang/invoke/MethodHandles$Lookup;Ljava/lang/String;Ljava/lang/invoke/MethodType;[Ljava/lang/invoke/MethodHandle;)Ljava/lang/invoke/CallSite;
    Method arguments:
      #59 REF_invokeStatic scala/collection/generic/IsIterableOnce.$anonfun$conversion$1:(Lscala/collection/generic/IsIterableOnce;Ljava/lang/Object;)Lscala/collection/IterableOnce;
  ScalaInlineInfo: length = 0x1D (unknown attribute)
   01 00 00 05 00 2E 00 2F 01 00 35 00 36 01 00 2A
   00 2B 00 00 27 00 28 00 00 23 00 24 00
  ScalaSig: length = 0x3 (unknown attribute)
   05 02 00
