Classfile /Users/mw/Projects/slang-braindump/.jar/jar11/assemble/slang-braindump/assemble/content/scala/collection/generic/ParFactory$GenericCanCombineFrom.class
  Last modified May 29, 2022; size 1787 bytes
  SHA-256 checksum 2430a2c61f03b498e4091575fca0023f4097c254006d769ce780dced0c0016f2
  Compiled from "ParFactory.scala"
public class scala.collection.generic.ParFactory$GenericCanCombineFrom<From extends java.lang.Object, To extends java.lang.Object> extends java.lang.Object implements scala.collection.generic.CanCombineFrom<CC, To, CC>
  minor version: 0
  major version: 52
  flags: (0x0021) ACC_PUBLIC, ACC_SUPER
  this_class: #2                          // scala/collection/generic/ParFactory$GenericCanCombineFrom
  super_class: #5                         // java/lang/Object
  interfaces: 1, fields: 1, methods: 5, attributes: 5
Constant pool:
   #1 = Utf8               scala/collection/generic/ParFactory$GenericCanCombineFrom
   #2 = Class              #1             // scala/collection/generic/ParFactory$GenericCanCombineFrom
   #3 = Utf8               <From:Ljava/lang/Object;To:Ljava/lang/Object;>Ljava/lang/Object;Lscala/collection/generic/CanCombineFrom<TCC;TTo;TCC;>;
   #4 = Utf8               java/lang/Object
   #5 = Class              #4             // java/lang/Object
   #6 = Utf8               scala/collection/generic/CanCombineFrom
   #7 = Class              #6             // scala/collection/generic/CanCombineFrom
   #8 = Utf8               ParFactory.scala
   #9 = Utf8               scala/collection/generic/ParFactory
  #10 = Class              #9             // scala/collection/generic/ParFactory
  #11 = Utf8               GenericCanCombineFrom
  #12 = Utf8               $outer
  #13 = Utf8               Lscala/collection/generic/ParFactory;
  #14 = Utf8               apply
  #15 = Utf8               (Lscala/collection/parallel/ParIterable;)Lscala/collection/parallel/Combiner;
  #16 = Utf8               (TCC;)Lscala/collection/parallel/Combiner<TTo;TCC;>;
  #17 = Utf8               from
  #18 = Utf8               scala/collection/parallel/ParIterable
  #19 = Class              #18            // scala/collection/parallel/ParIterable
  #20 = Utf8               genericCombiner
  #21 = Utf8               ()Lscala/collection/parallel/Combiner;
  #22 = NameAndType        #20:#21        // genericCombiner:()Lscala/collection/parallel/Combiner;
  #23 = InterfaceMethodref #19.#22        // scala/collection/parallel/ParIterable.genericCombiner:()Lscala/collection/parallel/Combiner;
  #24 = Utf8               this
  #25 = Utf8               Lscala/collection/generic/ParFactory$GenericCanCombineFrom;
  #26 = Utf8               Lscala/collection/parallel/ParIterable;
  #27 = Utf8               ()Lscala/collection/parallel/Combiner<TTo;TCC;>;
  #28 = Utf8               scala$collection$generic$ParFactory$GenericCanCombineFrom$$$outer
  #29 = Utf8               ()Lscala/collection/generic/ParFactory;
  #30 = NameAndType        #28:#29        // scala$collection$generic$ParFactory$GenericCanCombineFrom$$$outer:()Lscala/collection/generic/ParFactory;
  #31 = Methodref          #2.#30         // scala/collection/generic/ParFactory$GenericCanCombineFrom.scala$collection$generic$ParFactory$GenericCanCombineFrom$$$outer:()Lscala/collection/generic/ParFactory;
  #32 = Utf8               newBuilder
  #33 = NameAndType        #32:#21        // newBuilder:()Lscala/collection/parallel/Combiner;
  #34 = Methodref          #10.#33        // scala/collection/generic/ParFactory.newBuilder:()Lscala/collection/parallel/Combiner;
  #35 = NameAndType        #12:#13        // $outer:Lscala/collection/generic/ParFactory;
  #36 = Fieldref           #2.#35         // scala/collection/generic/ParFactory$GenericCanCombineFrom.$outer:Lscala/collection/generic/ParFactory;
  #37 = Utf8               (Ljava/lang/Object;)Lscala/collection/parallel/Combiner;
  #38 = NameAndType        #14:#15        // apply:(Lscala/collection/parallel/ParIterable;)Lscala/collection/parallel/Combiner;
  #39 = Methodref          #2.#38         // scala/collection/generic/ParFactory$GenericCanCombineFrom.apply:(Lscala/collection/parallel/ParIterable;)Lscala/collection/parallel/Combiner;
  #40 = Utf8               Ljava/lang/Object;
  #41 = Utf8               <init>
  #42 = Utf8               (Lscala/collection/generic/ParFactory;)V
  #43 = Utf8               ()V
  #44 = NameAndType        #41:#43        // "<init>":()V
  #45 = Methodref          #5.#44         // java/lang/Object."<init>":()V
  #46 = Utf8               Code
  #47 = Utf8               LineNumberTable
  #48 = Utf8               LocalVariableTable
  #49 = Utf8               Signature
  #50 = Utf8               MethodParameters
  #51 = Utf8               StackMapTable
  #52 = Utf8               InnerClasses
  #53 = Utf8               SourceFile
  #54 = Utf8               ScalaInlineInfo
  #55 = Utf8               Scala
{
  public final scala.collection.generic.ParFactory $outer;
    descriptor: Lscala/collection/generic/ParFactory;
    flags: (0x1011) ACC_PUBLIC, ACC_FINAL, ACC_SYNTHETIC

  public scala.collection.parallel.Combiner<To, CC> apply(CC);
    descriptor: (Lscala/collection/parallel/ParIterable;)Lscala/collection/parallel/Combiner;
    flags: (0x0001) ACC_PUBLIC
    Code:
      stack=1, locals=2, args_size=2
         0: aload_1
         1: invokeinterface #23,  1           // InterfaceMethod scala/collection/parallel/ParIterable.genericCombiner:()Lscala/collection/parallel/Combiner;
         6: areturn
      LineNumberTable:
        line 229: 0
      LocalVariableTable:
        Start  Length  Slot  Name   Signature
            0       7     0  this   Lscala/collection/generic/ParFactory$GenericCanCombineFrom;
            0       7     1  from   Lscala/collection/parallel/ParIterable;
    Signature: #16                          // (TCC;)Lscala/collection/parallel/Combiner<TTo;TCC;>;
    MethodParameters:
      Name                           Flags
      from                           final

  public scala.collection.parallel.Combiner<To, CC> apply();
    descriptor: ()Lscala/collection/parallel/Combiner;
    flags: (0x0001) ACC_PUBLIC
    Code:
      stack=1, locals=1, args_size=1
         0: aload_0
         1: invokevirtual #31                 // Method scala$collection$generic$ParFactory$GenericCanCombineFrom$$$outer:()Lscala/collection/generic/ParFactory;
         4: invokevirtual #34                 // Method scala/collection/generic/ParFactory.newBuilder:()Lscala/collection/parallel/Combiner;
         7: areturn
      LineNumberTable:
        line 230: 0
      LocalVariableTable:
        Start  Length  Slot  Name   Signature
            0       8     0  this   Lscala/collection/generic/ParFactory$GenericCanCombineFrom;
    Signature: #27                          // ()Lscala/collection/parallel/Combiner<TTo;TCC;>;

  public scala.collection.generic.ParFactory scala$collection$generic$ParFactory$GenericCanCombineFrom$$$outer();
    descriptor: ()Lscala/collection/generic/ParFactory;
    flags: (0x1001) ACC_PUBLIC, ACC_SYNTHETIC
    Code:
      stack=1, locals=1, args_size=1
         0: aload_0
         1: getfield      #36                 // Field $outer:Lscala/collection/generic/ParFactory;
         4: areturn
      LineNumberTable:
        line 228: 0
      LocalVariableTable:
        Start  Length  Slot  Name   Signature
            0       5     0  this   Lscala/collection/generic/ParFactory$GenericCanCombineFrom;

  public scala.collection.parallel.Combiner apply(java.lang.Object);
    descriptor: (Ljava/lang/Object;)Lscala/collection/parallel/Combiner;
    flags: (0x1041) ACC_PUBLIC, ACC_BRIDGE, ACC_SYNTHETIC
    Code:
      stack=2, locals=2, args_size=2
         0: aload_0
         1: aload_1
         2: checkcast     #19                 // class scala/collection/parallel/ParIterable
         5: invokevirtual #39                 // Method apply:(Lscala/collection/parallel/ParIterable;)Lscala/collection/parallel/Combiner;
         8: areturn
      LineNumberTable:
        line 228: 0
      LocalVariableTable:
        Start  Length  Slot  Name   Signature
            0       9     0  this   Lscala/collection/generic/ParFactory$GenericCanCombineFrom;
            0       9     1  from   Ljava/lang/Object;
    MethodParameters:
      Name                           Flags
      from                           final

  public scala.collection.generic.ParFactory$GenericCanCombineFrom(scala.collection.generic.ParFactory);
    descriptor: (Lscala/collection/generic/ParFactory;)V
    flags: (0x0001) ACC_PUBLIC
    Code:
      stack=2, locals=2, args_size=2
         0: aload_1
         1: ifnonnull     6
         4: aconst_null
         5: athrow
         6: aload_0
         7: aload_1
         8: putfield      #36                 // Field $outer:Lscala/collection/generic/ParFactory;
        11: aload_0
        12: invokespecial #45                 // Method java/lang/Object."<init>":()V
        15: return
      StackMapTable: number_of_entries = 1
        frame_type = 6 /* same */
      LineNumberTable:
        line 228: 0
      LocalVariableTable:
        Start  Length  Slot  Name   Signature
            0      16     0  this   Lscala/collection/generic/ParFactory$GenericCanCombineFrom;
            0      16     1 $outer   Lscala/collection/generic/ParFactory;
    MethodParameters:
      Name                           Flags
      $outer                         final synthetic
}
InnerClasses:
  public #11= #2 of #10;                  // GenericCanCombineFrom=class scala/collection/generic/ParFactory$GenericCanCombineFrom of class scala/collection/generic/ParFactory
Signature: #3                           // <From:Ljava/lang/Object;To:Ljava/lang/Object;>Ljava/lang/Object;Lscala/collection/generic/CanCombineFrom<TCC;TTo;TCC;>;
SourceFile: "ParFactory.scala"
  ScalaInlineInfo: length = 0x1D (unknown attribute)
   01 00 00 05 00 29 00 2A 00 00 0E 00 15 00 00 0E
   00 25 00 00 0E 00 0F 00 00 1C 00 1D 00
  Scala: length = 0x0 (unknown attribute)

