Classfile /Users/mw/Projects/slang-braindump/.jar/jar11/assemble/slang-braindump/assemble/content/com/fasterxml/jackson/databind/jsontype/impl/MinimalClassNameIdResolver.class
  Last modified May 29, 2022; size 3766 bytes
  SHA-256 checksum 5e06dac381cc9915d51ffd0665528b0715821504e4caa41612450d2cbcf103a3
  Compiled from "MinimalClassNameIdResolver.java"
public class com.fasterxml.jackson.databind.jsontype.impl.MinimalClassNameIdResolver extends com.fasterxml.jackson.databind.jsontype.impl.ClassNameIdResolver
  minor version: 0
  major version: 52
  flags: (0x0021) ACC_PUBLIC, ACC_SUPER
  this_class: #10                         // com/fasterxml/jackson/databind/jsontype/impl/MinimalClassNameIdResolver
  super_class: #24                        // com/fasterxml/jackson/databind/jsontype/impl/ClassNameIdResolver
  interfaces: 0, fields: 2, methods: 5, attributes: 2
Constant pool:
    #1 = Methodref          #24.#80       // com/fasterxml/jackson/databind/jsontype/impl/ClassNameIdResolver."<init>":(Lcom/fasterxml/jackson/databind/JavaType;Lcom/fasterxml/jackson/databind/type/TypeFactory;Lcom/fasterxml/jackson/databind/jsontype/PolymorphicTypeValidator;)V
    #2 = Methodref          #81.#82       // com/fasterxml/jackson/databind/JavaType.getRawClass:()Ljava/lang/Class;
    #3 = Methodref          #83.#84       // java/lang/Class.getName:()Ljava/lang/String;
    #4 = Methodref          #85.#86       // java/lang/String.lastIndexOf:(I)I
    #5 = String             #87           //
    #6 = Fieldref           #10.#88       // com/fasterxml/jackson/databind/jsontype/impl/MinimalClassNameIdResolver._basePackageName:Ljava/lang/String;
    #7 = String             #89           // .
    #8 = Fieldref           #10.#90       // com/fasterxml/jackson/databind/jsontype/impl/MinimalClassNameIdResolver._basePackagePrefix:Ljava/lang/String;
    #9 = Methodref          #85.#91       // java/lang/String.substring:(II)Ljava/lang/String;
   #10 = Class              #92           // com/fasterxml/jackson/databind/jsontype/impl/MinimalClassNameIdResolver
   #11 = Methodref          #93.#94       // com/fasterxml/jackson/databind/cfg/MapperConfig.getTypeFactory:()Lcom/fasterxml/jackson/databind/type/TypeFactory;
   #12 = Methodref          #10.#80       // com/fasterxml/jackson/databind/jsontype/impl/MinimalClassNameIdResolver."<init>":(Lcom/fasterxml/jackson/databind/JavaType;Lcom/fasterxml/jackson/databind/type/TypeFactory;Lcom/fasterxml/jackson/databind/jsontype/PolymorphicTypeValidator;)V
   #13 = Fieldref           #59.#95       // com/fasterxml/jackson/annotation/JsonTypeInfo$Id.MINIMAL_CLASS:Lcom/fasterxml/jackson/annotation/JsonTypeInfo$Id;
   #14 = Methodref          #96.#97       // java/lang/Object.getClass:()Ljava/lang/Class;
   #15 = Methodref          #85.#98       // java/lang/String.startsWith:(Ljava/lang/String;)Z
   #16 = Methodref          #85.#99       // java/lang/String.length:()I
   #17 = Methodref          #85.#100      // java/lang/String.substring:(I)Ljava/lang/String;
   #18 = Class              #101          // java/lang/StringBuilder
   #19 = Methodref          #18.#102      // java/lang/StringBuilder."<init>":(I)V
   #20 = Methodref          #85.#103      // java/lang/String.isEmpty:()Z
   #21 = Methodref          #18.#104      // java/lang/StringBuilder.append:(Ljava/lang/String;)Ljava/lang/StringBuilder;
   #22 = Methodref          #18.#105      // java/lang/StringBuilder.toString:()Ljava/lang/String;
   #23 = Methodref          #24.#106      // com/fasterxml/jackson/databind/jsontype/impl/ClassNameIdResolver._typeFromId:(Ljava/lang/String;Lcom/fasterxml/jackson/databind/DatabindContext;)Lcom/fasterxml/jackson/databind/JavaType;
   #24 = Class              #107          // com/fasterxml/jackson/databind/jsontype/impl/ClassNameIdResolver
   #25 = Utf8               _basePackageName
   #26 = Utf8               Ljava/lang/String;
   #27 = Utf8               _basePackagePrefix
   #28 = Utf8               <init>
   #29 = Utf8               (Lcom/fasterxml/jackson/databind/JavaType;Lcom/fasterxml/jackson/databind/type/TypeFactory;Lcom/fasterxml/jackson/databind/jsontype/PolymorphicTypeValidator;)V
   #30 = Utf8               Code
   #31 = Utf8               LineNumberTable
   #32 = Utf8               LocalVariableTable
   #33 = Utf8               this
   #34 = Utf8               Lcom/fasterxml/jackson/databind/jsontype/impl/MinimalClassNameIdResolver;
   #35 = Utf8               baseType
   #36 = Utf8               Lcom/fasterxml/jackson/databind/JavaType;
   #37 = Utf8               typeFactory
   #38 = Utf8               Lcom/fasterxml/jackson/databind/type/TypeFactory;
   #39 = Utf8               ptv
   #40 = Utf8               Lcom/fasterxml/jackson/databind/jsontype/PolymorphicTypeValidator;
   #41 = Utf8               base
   #42 = Utf8               ix
   #43 = Utf8               I
   #44 = Utf8               StackMapTable
   #45 = Class              #92           // com/fasterxml/jackson/databind/jsontype/impl/MinimalClassNameIdResolver
   #46 = Class              #108          // com/fasterxml/jackson/databind/JavaType
   #47 = Class              #109          // com/fasterxml/jackson/databind/type/TypeFactory
   #48 = Class              #110          // com/fasterxml/jackson/databind/jsontype/PolymorphicTypeValidator
   #49 = Class              #111          // java/lang/String
   #50 = Utf8               construct
   #51 = Utf8               (Lcom/fasterxml/jackson/databind/JavaType;Lcom/fasterxml/jackson/databind/cfg/MapperConfig;Lcom/fasterxml/jackson/databind/jsontype/PolymorphicTypeValidator;)Lcom/fasterxml/jackson/databind/jsontype/impl/MinimalClassNameIdResolver;
   #52 = Utf8               config
   #53 = Utf8               Lcom/fasterxml/jackson/databind/cfg/MapperConfig;
   #54 = Utf8               LocalVariableTypeTable
   #55 = Utf8               Lcom/fasterxml/jackson/databind/cfg/MapperConfig<*>;
   #56 = Utf8               Signature
   #57 = Utf8               (Lcom/fasterxml/jackson/databind/JavaType;Lcom/fasterxml/jackson/databind/cfg/MapperConfig<*>;Lcom/fasterxml/jackson/databind/jsontype/PolymorphicTypeValidator;)Lcom/fasterxml/jackson/databind/jsontype/impl/MinimalClassNameIdResolver;
   #58 = Utf8               getMechanism
   #59 = Class              #113          // com/fasterxml/jackson/annotation/JsonTypeInfo$Id
   #60 = Utf8               Id
   #61 = Utf8               InnerClasses
   #62 = Utf8               ()Lcom/fasterxml/jackson/annotation/JsonTypeInfo$Id;
   #63 = Utf8               idFromValue
   #64 = Utf8               (Ljava/lang/Object;)Ljava/lang/String;
   #65 = Utf8               value
   #66 = Utf8               Ljava/lang/Object;
   #67 = Utf8               n
   #68 = Utf8               _typeFromId
   #69 = Utf8               (Ljava/lang/String;Lcom/fasterxml/jackson/databind/DatabindContext;)Lcom/fasterxml/jackson/databind/JavaType;
   #70 = Utf8               sb
   #71 = Utf8               Ljava/lang/StringBuilder;
   #72 = Utf8               id
   #73 = Utf8               ctxt
   #74 = Utf8               Lcom/fasterxml/jackson/databind/DatabindContext;
   #75 = Class              #101          // java/lang/StringBuilder
   #76 = Utf8               Exceptions
   #77 = Class              #114          // java/io/IOException
   #78 = Utf8               SourceFile
   #79 = Utf8               MinimalClassNameIdResolver.java
   #80 = NameAndType        #28:#29       // "<init>":(Lcom/fasterxml/jackson/databind/JavaType;Lcom/fasterxml/jackson/databind/type/TypeFactory;Lcom/fasterxml/jackson/databind/jsontype/PolymorphicTypeValidator;)V
   #81 = Class              #108          // com/fasterxml/jackson/databind/JavaType
   #82 = NameAndType        #115:#116     // getRawClass:()Ljava/lang/Class;
   #83 = Class              #117          // java/lang/Class
   #84 = NameAndType        #118:#119     // getName:()Ljava/lang/String;
   #85 = Class              #111          // java/lang/String
   #86 = NameAndType        #120:#121     // lastIndexOf:(I)I
   #87 = Utf8
   #88 = NameAndType        #25:#26       // _basePackageName:Ljava/lang/String;
   #89 = Utf8               .
   #90 = NameAndType        #27:#26       // _basePackagePrefix:Ljava/lang/String;
   #91 = NameAndType        #122:#123     // substring:(II)Ljava/lang/String;
   #92 = Utf8               com/fasterxml/jackson/databind/jsontype/impl/MinimalClassNameIdResolver
   #93 = Class              #124          // com/fasterxml/jackson/databind/cfg/MapperConfig
   #94 = NameAndType        #125:#126     // getTypeFactory:()Lcom/fasterxml/jackson/databind/type/TypeFactory;
   #95 = NameAndType        #127:#128     // MINIMAL_CLASS:Lcom/fasterxml/jackson/annotation/JsonTypeInfo$Id;
   #96 = Class              #129          // java/lang/Object
   #97 = NameAndType        #130:#116     // getClass:()Ljava/lang/Class;
   #98 = NameAndType        #131:#132     // startsWith:(Ljava/lang/String;)Z
   #99 = NameAndType        #133:#134     // length:()I
  #100 = NameAndType        #122:#135     // substring:(I)Ljava/lang/String;
  #101 = Utf8               java/lang/StringBuilder
  #102 = NameAndType        #28:#136      // "<init>":(I)V
  #103 = NameAndType        #137:#138     // isEmpty:()Z
  #104 = NameAndType        #139:#140     // append:(Ljava/lang/String;)Ljava/lang/StringBuilder;
  #105 = NameAndType        #141:#119     // toString:()Ljava/lang/String;
  #106 = NameAndType        #68:#69       // _typeFromId:(Ljava/lang/String;Lcom/fasterxml/jackson/databind/DatabindContext;)Lcom/fasterxml/jackson/databind/JavaType;
  #107 = Utf8               com/fasterxml/jackson/databind/jsontype/impl/ClassNameIdResolver
  #108 = Utf8               com/fasterxml/jackson/databind/JavaType
  #109 = Utf8               com/fasterxml/jackson/databind/type/TypeFactory
  #110 = Utf8               com/fasterxml/jackson/databind/jsontype/PolymorphicTypeValidator
  #111 = Utf8               java/lang/String
  #112 = Class              #142          // com/fasterxml/jackson/annotation/JsonTypeInfo
  #113 = Utf8               com/fasterxml/jackson/annotation/JsonTypeInfo$Id
  #114 = Utf8               java/io/IOException
  #115 = Utf8               getRawClass
  #116 = Utf8               ()Ljava/lang/Class;
  #117 = Utf8               java/lang/Class
  #118 = Utf8               getName
  #119 = Utf8               ()Ljava/lang/String;
  #120 = Utf8               lastIndexOf
  #121 = Utf8               (I)I
  #122 = Utf8               substring
  #123 = Utf8               (II)Ljava/lang/String;
  #124 = Utf8               com/fasterxml/jackson/databind/cfg/MapperConfig
  #125 = Utf8               getTypeFactory
  #126 = Utf8               ()Lcom/fasterxml/jackson/databind/type/TypeFactory;
  #127 = Utf8               MINIMAL_CLASS
  #128 = Utf8               Lcom/fasterxml/jackson/annotation/JsonTypeInfo$Id;
  #129 = Utf8               java/lang/Object
  #130 = Utf8               getClass
  #131 = Utf8               startsWith
  #132 = Utf8               (Ljava/lang/String;)Z
  #133 = Utf8               length
  #134 = Utf8               ()I
  #135 = Utf8               (I)Ljava/lang/String;
  #136 = Utf8               (I)V
  #137 = Utf8               isEmpty
  #138 = Utf8               ()Z
  #139 = Utf8               append
  #140 = Utf8               (Ljava/lang/String;)Ljava/lang/StringBuilder;
  #141 = Utf8               toString
  #142 = Utf8               com/fasterxml/jackson/annotation/JsonTypeInfo
{
  protected final java.lang.String _basePackageName;
    descriptor: Ljava/lang/String;
    flags: (0x0014) ACC_PROTECTED, ACC_FINAL

  protected final java.lang.String _basePackagePrefix;
    descriptor: Ljava/lang/String;
    flags: (0x0014) ACC_PROTECTED, ACC_FINAL

  protected com.fasterxml.jackson.databind.jsontype.impl.MinimalClassNameIdResolver(com.fasterxml.jackson.databind.JavaType, com.fasterxml.jackson.databind.type.TypeFactory, com.fasterxml.jackson.databind.jsontype.PolymorphicTypeValidator);
    descriptor: (Lcom/fasterxml/jackson/databind/JavaType;Lcom/fasterxml/jackson/databind/type/TypeFactory;Lcom/fasterxml/jackson/databind/jsontype/PolymorphicTypeValidator;)V
    flags: (0x0004) ACC_PROTECTED
    Code:
      stack=5, locals=6, args_size=4
         0: aload_0
         1: aload_1
         2: aload_2
         3: aload_3
         4: invokespecial #1                  // Method com/fasterxml/jackson/databind/jsontype/impl/ClassNameIdResolver."<init>":(Lcom/fasterxml/jackson/databind/JavaType;Lcom/fasterxml/jackson/databind/type/TypeFactory;Lcom/fasterxml/jackson/databind/jsontype/PolymorphicTypeValidator;)V
         7: aload_1
         8: invokevirtual #2                  // Method com/fasterxml/jackson/databind/JavaType.getRawClass:()Ljava/lang/Class;
        11: invokevirtual #3                  // Method java/lang/Class.getName:()Ljava/lang/String;
        14: astore        4
        16: aload         4
        18: bipush        46
        20: invokevirtual #4                  // Method java/lang/String.lastIndexOf:(I)I
        23: istore        5
        25: iload         5
        27: ifge          45
        30: aload_0
        31: ldc           #5                  // String
        33: putfield      #6                  // Field _basePackageName:Ljava/lang/String;
        36: aload_0
        37: ldc           #7                  // String .
        39: putfield      #8                  // Field _basePackagePrefix:Ljava/lang/String;
        42: goto          71
        45: aload_0
        46: aload         4
        48: iconst_0
        49: iload         5
        51: iconst_1
        52: iadd
        53: invokevirtual #9                  // Method java/lang/String.substring:(II)Ljava/lang/String;
        56: putfield      #8                  // Field _basePackagePrefix:Ljava/lang/String;
        59: aload_0
        60: aload         4
        62: iconst_0
        63: iload         5
        65: invokevirtual #9                  // Method java/lang/String.substring:(II)Ljava/lang/String;
        68: putfield      #6                  // Field _basePackageName:Ljava/lang/String;
        71: return
      LineNumberTable:
        line 30: 0
        line 31: 7
        line 32: 16
        line 33: 25
        line 34: 30
        line 35: 36
        line 37: 45
        line 38: 59
        line 40: 71
      LocalVariableTable:
        Start  Length  Slot  Name   Signature
            0      72     0  this   Lcom/fasterxml/jackson/databind/jsontype/impl/MinimalClassNameIdResolver;
            0      72     1 baseType   Lcom/fasterxml/jackson/databind/JavaType;
            0      72     2 typeFactory   Lcom/fasterxml/jackson/databind/type/TypeFactory;
            0      72     3   ptv   Lcom/fasterxml/jackson/databind/jsontype/PolymorphicTypeValidator;
           16      56     4  base   Ljava/lang/String;
           25      47     5    ix   I
      StackMapTable: number_of_entries = 2
        frame_type = 255 /* full_frame */
          offset_delta = 45
          locals = [ class com/fasterxml/jackson/databind/jsontype/impl/MinimalClassNameIdResolver, class com/fasterxml/jackson/databind/JavaType, class com/fasterxml/jackson/databind/type/TypeFactory, class com/fasterxml/jackson/databind/jsontype/PolymorphicTypeValidator, class java/lang/String, int ]
          stack = []
        frame_type = 25 /* same */

  public static com.fasterxml.jackson.databind.jsontype.impl.MinimalClassNameIdResolver construct(com.fasterxml.jackson.databind.JavaType, com.fasterxml.jackson.databind.cfg.MapperConfig<?>, com.fasterxml.jackson.databind.jsontype.PolymorphicTypeValidator);
    descriptor: (Lcom/fasterxml/jackson/databind/JavaType;Lcom/fasterxml/jackson/databind/cfg/MapperConfig;Lcom/fasterxml/jackson/databind/jsontype/PolymorphicTypeValidator;)Lcom/fasterxml/jackson/databind/jsontype/impl/MinimalClassNameIdResolver;
    flags: (0x0009) ACC_PUBLIC, ACC_STATIC
    Code:
      stack=5, locals=3, args_size=3
         0: new           #10                 // class com/fasterxml/jackson/databind/jsontype/impl/MinimalClassNameIdResolver
         3: dup
         4: aload_0
         5: aload_1
         6: invokevirtual #11                 // Method com/fasterxml/jackson/databind/cfg/MapperConfig.getTypeFactory:()Lcom/fasterxml/jackson/databind/type/TypeFactory;
         9: aload_2
        10: invokespecial #12                 // Method "<init>":(Lcom/fasterxml/jackson/databind/JavaType;Lcom/fasterxml/jackson/databind/type/TypeFactory;Lcom/fasterxml/jackson/databind/jsontype/PolymorphicTypeValidator;)V
        13: areturn
      LineNumberTable:
        line 44: 0
      LocalVariableTable:
        Start  Length  Slot  Name   Signature
            0      14     0 baseType   Lcom/fasterxml/jackson/databind/JavaType;
            0      14     1 config   Lcom/fasterxml/jackson/databind/cfg/MapperConfig;
            0      14     2   ptv   Lcom/fasterxml/jackson/databind/jsontype/PolymorphicTypeValidator;
      LocalVariableTypeTable:
        Start  Length  Slot  Name   Signature
            0      14     1 config   Lcom/fasterxml/jackson/databind/cfg/MapperConfig<*>;
    Signature: #57                          // (Lcom/fasterxml/jackson/databind/JavaType;Lcom/fasterxml/jackson/databind/cfg/MapperConfig<*>;Lcom/fasterxml/jackson/databind/jsontype/PolymorphicTypeValidator;)Lcom/fasterxml/jackson/databind/jsontype/impl/MinimalClassNameIdResolver;

  public com.fasterxml.jackson.annotation.JsonTypeInfo$Id getMechanism();
    descriptor: ()Lcom/fasterxml/jackson/annotation/JsonTypeInfo$Id;
    flags: (0x0001) ACC_PUBLIC
    Code:
      stack=1, locals=1, args_size=1
         0: getstatic     #13                 // Field com/fasterxml/jackson/annotation/JsonTypeInfo$Id.MINIMAL_CLASS:Lcom/fasterxml/jackson/annotation/JsonTypeInfo$Id;
         3: areturn
      LineNumberTable:
        line 48: 0
      LocalVariableTable:
        Start  Length  Slot  Name   Signature
            0       4     0  this   Lcom/fasterxml/jackson/databind/jsontype/impl/MinimalClassNameIdResolver;

  public java.lang.String idFromValue(java.lang.Object);
    descriptor: (Ljava/lang/Object;)Ljava/lang/String;
    flags: (0x0001) ACC_PUBLIC
    Code:
      stack=3, locals=3, args_size=2
         0: aload_1
         1: invokevirtual #14                 // Method java/lang/Object.getClass:()Ljava/lang/Class;
         4: invokevirtual #3                  // Method java/lang/Class.getName:()Ljava/lang/String;
         7: astore_2
         8: aload_2
         9: aload_0
        10: getfield      #8                  // Field _basePackagePrefix:Ljava/lang/String;
        13: invokevirtual #15                 // Method java/lang/String.startsWith:(Ljava/lang/String;)Z
        16: ifeq          33
        19: aload_2
        20: aload_0
        21: getfield      #8                  // Field _basePackagePrefix:Ljava/lang/String;
        24: invokevirtual #16                 // Method java/lang/String.length:()I
        27: iconst_1
        28: isub
        29: invokevirtual #17                 // Method java/lang/String.substring:(I)Ljava/lang/String;
        32: areturn
        33: aload_2
        34: areturn
      LineNumberTable:
        line 53: 0
        line 54: 8
        line 56: 19
        line 58: 33
      LocalVariableTable:
        Start  Length  Slot  Name   Signature
            0      35     0  this   Lcom/fasterxml/jackson/databind/jsontype/impl/MinimalClassNameIdResolver;
            0      35     1 value   Ljava/lang/Object;
            8      27     2     n   Ljava/lang/String;
      StackMapTable: number_of_entries = 1
        frame_type = 252 /* append */
          offset_delta = 33
          locals = [ class java/lang/String ]

  protected com.fasterxml.jackson.databind.JavaType _typeFromId(java.lang.String, com.fasterxml.jackson.databind.DatabindContext) throws java.io.IOException;
    descriptor: (Ljava/lang/String;Lcom/fasterxml/jackson/databind/DatabindContext;)Lcom/fasterxml/jackson/databind/JavaType;
    flags: (0x0004) ACC_PROTECTED
    Code:
      stack=4, locals=4, args_size=3
         0: aload_1
         1: ldc           #7                  // String .
         3: invokevirtual #15                 // Method java/lang/String.startsWith:(Ljava/lang/String;)Z
         6: ifeq          70
         9: new           #18                 // class java/lang/StringBuilder
        12: dup
        13: aload_1
        14: invokevirtual #16                 // Method java/lang/String.length:()I
        17: aload_0
        18: getfield      #6                  // Field _basePackageName:Ljava/lang/String;
        21: invokevirtual #16                 // Method java/lang/String.length:()I
        24: iadd
        25: invokespecial #19                 // Method java/lang/StringBuilder."<init>":(I)V
        28: astore_3
        29: aload_0
        30: getfield      #6                  // Field _basePackageName:Ljava/lang/String;
        33: invokevirtual #20                 // Method java/lang/String.isEmpty:()Z
        36: ifeq          52
        39: aload_3
        40: aload_1
        41: iconst_1
        42: invokevirtual #17                 // Method java/lang/String.substring:(I)Ljava/lang/String;
        45: invokevirtual #21                 // Method java/lang/StringBuilder.append:(Ljava/lang/String;)Ljava/lang/StringBuilder;
        48: pop
        49: goto          65
        52: aload_3
        53: aload_0
        54: getfield      #6                  // Field _basePackageName:Ljava/lang/String;
        57: invokevirtual #21                 // Method java/lang/StringBuilder.append:(Ljava/lang/String;)Ljava/lang/StringBuilder;
        60: aload_1
        61: invokevirtual #21                 // Method java/lang/StringBuilder.append:(Ljava/lang/String;)Ljava/lang/StringBuilder;
        64: pop
        65: aload_3
        66: invokevirtual #22                 // Method java/lang/StringBuilder.toString:()Ljava/lang/String;
        69: astore_1
        70: aload_0
        71: aload_1
        72: aload_2
        73: invokespecial #23                 // Method com/fasterxml/jackson/databind/jsontype/impl/ClassNameIdResolver._typeFromId:(Ljava/lang/String;Lcom/fasterxml/jackson/databind/DatabindContext;)Lcom/fasterxml/jackson/databind/JavaType;
        76: areturn
      LineNumberTable:
        line 64: 0
        line 65: 9
        line 66: 29
        line 68: 39
        line 71: 52
        line 73: 65
        line 75: 70
      LocalVariableTable:
        Start  Length  Slot  Name   Signature
           29      41     3    sb   Ljava/lang/StringBuilder;
            0      77     0  this   Lcom/fasterxml/jackson/databind/jsontype/impl/MinimalClassNameIdResolver;
            0      77     1    id   Ljava/lang/String;
            0      77     2  ctxt   Lcom/fasterxml/jackson/databind/DatabindContext;
      StackMapTable: number_of_entries = 3
        frame_type = 252 /* append */
          offset_delta = 52
          locals = [ class java/lang/StringBuilder ]
        frame_type = 12 /* same */
        frame_type = 250 /* chop */
          offset_delta = 4
    Exceptions:
      throws java.io.IOException
}
SourceFile: "MinimalClassNameIdResolver.java"
InnerClasses:
  public static final #60= #59 of #112;   // Id=class com/fasterxml/jackson/annotation/JsonTypeInfo$Id of class com/fasterxml/jackson/annotation/JsonTypeInfo
