Classfile /Users/mw/Projects/slang-braindump/.jar/jar11/assemble/slang-braindump/assemble/content/coursier/core/shaded/fastparse/internal/CompactTrieNode.class
  Last modified May 29, 2022; size 4642 bytes
  SHA-256 checksum 7de694f1da37d588280471d7f67c8c704210697a8ede33e0cd111a69a48516d7
  Compiled from "Util.scala"
public final class coursier.core.shaded.fastparse.internal.CompactTrieNode
  minor version: 0
  major version: 52
  flags: (0x0031) ACC_PUBLIC, ACC_FINAL, ACC_SUPER
  this_class: #2                          // coursier/core/shaded/fastparse/internal/CompactTrieNode
  super_class: #4                         // java/lang/Object
  interfaces: 0, fields: 3, methods: 6, attributes: 6
Constant pool:
    #1 = Utf8               coursier/core/shaded/fastparse/internal/CompactTrieNode
    #2 = Class              #1            // coursier/core/shaded/fastparse/internal/CompactTrieNode
    #3 = Utf8               java/lang/Object
    #4 = Class              #3            // java/lang/Object
    #5 = Utf8               Util.scala
    #6 = Utf8               Lscala/reflect/ScalaSignature;
    #7 = Utf8               bytes
    #8 = Utf8               \u0006\u0005i2Aa\u0002\u0005\u0003\u001b!AA\u0003\u0001B\u0001B\u0003%Q\u0003C\u0003\u001a\u0001\u0011\u0005!\u0004C\u0004\u001e\u0001\t\u0007I\u0011\u0001\u0010\t\rM\u0002\u0001\u0015!\u0003 \u0011\u001d!\u0004A1A\u0005\u0002UBa!\u000f\u0001!\u0002\u00131$aD\"p[B\f7\r\u001e+sS\u0016tu\u000eZ3\u000b\u0005%Q\u0011\u0001C5oi\u0016\u0014h.\u00197\u000b\u0003-\t\u0011BZ1tiB\f\'o]3\u0004\u0001M\u0011\u0001A\u0004\t\u0003\u001fIi\u0011\u0001\u0005\u0006\u0002#\u0005)1oY1mC&\u00111\u0003\u0005\u0002\u0007\u0003:L(+\u001a4\u0002\rM|WO]2f!\t1r#D\u0001\t\u0013\tA\u0002B\u0001\u0005Ue&,gj\u001c3f\u0003\u0019a\u0014N\\5u}Q\u00111\u0004\b\t\u0003-\u0001AQ\u0001\u0006\u0002A\u0002U\t\u0001b\u00195jY\u0012\u0014XM\\\u000b\u0002?A!\u0001e\n\u0016.\u001d\t\tS\u0005\u0005\u0002#!5\t1E\u0003\u0002%\u0019\u00051AH]8pizJ!A\n\t\u0002\rA\u0013X\rZ3g\u0013\tA\u0013FA\u0002NCBT!A\n\t\u0011\u0005=Y\u0013B\u0001\u0017\u0011\u0005\u0011\u0019\u0005.\u0019:\u0011\t=q\u0003gG\u0005\u0003_A\u0011a\u0001V;qY\u0016\u0014\u0004C\u0001\u00112\u0013\t\u0011\u0014F\u0001\u0004TiJLgnZ\u0001\nG\"LG\u000e\u001a:f]\u0002\nAa^8sIV\ta\u0007\u0005\u0002\u0010o%\u0011\u0001\b\u0005\u0002\b\u0005>|G.Z1o\u0003\u00159xN\u001d3!\u0001
    #9 = Utf8               java/lang/invoke/MethodHandles$Lookup
   #10 = Class              #9            // java/lang/invoke/MethodHandles$Lookup
   #11 = Utf8               java/lang/invoke/MethodHandles
   #12 = Class              #11           // java/lang/invoke/MethodHandles
   #13 = Utf8               Lookup
   #14 = Utf8               scala/Predef$ArrowAssoc$
   #15 = Class              #14           // scala/Predef$ArrowAssoc$
   #16 = Utf8               scala/Predef
   #17 = Class              #16           // scala/Predef
   #18 = Utf8
   #19 = Utf8               source
   #20 = Utf8               Lcoursier/core/shaded/fastparse/internal/TrieNode;
   #21 = Utf8               children
   #22 = Utf8               Lscala/collection/immutable/Map;
   #23 = Utf8               Lscala/collection/immutable/Map<Ljava/lang/Object;Lscala/Tuple2<Ljava/lang/String;Lcoursier/core/shaded/fastparse/internal/CompactTrieNode;>;>;
   #24 = Utf8               word
   #25 = Utf8               Z
   #26 = Utf8               ()Lscala/collection/immutable/Map;
   #27 = Utf8               ()Lscala/collection/immutable/Map<Ljava/lang/Object;Lscala/Tuple2<Ljava/lang/String;Lcoursier/core/shaded/fastparse/internal/CompactTrieNode;>;>;
   #28 = NameAndType        #21:#22       // children:Lscala/collection/immutable/Map;
   #29 = Fieldref           #2.#28        // coursier/core/shaded/fastparse/internal/CompactTrieNode.children:Lscala/collection/immutable/Map;
   #30 = Utf8               this
   #31 = Utf8               Lcoursier/core/shaded/fastparse/internal/CompactTrieNode;
   #32 = Utf8               ()Z
   #33 = NameAndType        #24:#25       // word:Z
   #34 = Fieldref           #2.#33        // coursier/core/shaded/fastparse/internal/CompactTrieNode.word:Z
   #35 = Utf8               $anonfun$children$5
   #36 = Utf8               (Lcoursier/core/shaded/fastparse/internal/CompactTrieNode;C)Lscala/Tuple2;
   #37 = Utf8               $this
   #38 = Utf8               char
   #39 = Utf8               MODULE$
   #40 = Utf8               Lscala/Predef$ArrowAssoc$;
   #41 = NameAndType        #39:#40       // MODULE$:Lscala/Predef$ArrowAssoc$;
   #42 = Fieldref           #15.#41       // scala/Predef$ArrowAssoc$.MODULE$:Lscala/Predef$ArrowAssoc$;
   #43 = Utf8               scala/Predef$
   #44 = Class              #43           // scala/Predef$
   #45 = Utf8               Lscala/Predef$;
   #46 = NameAndType        #39:#45       // MODULE$:Lscala/Predef$;
   #47 = Fieldref           #44.#46       // scala/Predef$.MODULE$:Lscala/Predef$;
   #48 = Utf8               scala/runtime/BoxesRunTime
   #49 = Class              #48           // scala/runtime/BoxesRunTime
   #50 = Utf8               boxToCharacter
   #51 = Utf8               (C)Ljava/lang/Character;
   #52 = NameAndType        #50:#51       // boxToCharacter:(C)Ljava/lang/Character;
   #53 = Methodref          #49.#52       // scala/runtime/BoxesRunTime.boxToCharacter:(C)Ljava/lang/Character;
   #54 = Utf8               ArrowAssoc
   #55 = Utf8               (Ljava/lang/Object;)Ljava/lang/Object;
   #56 = NameAndType        #54:#55       // ArrowAssoc:(Ljava/lang/Object;)Ljava/lang/Object;
   #57 = Methodref          #44.#56       // scala/Predef$.ArrowAssoc:(Ljava/lang/Object;)Ljava/lang/Object;
   #58 = Utf8               scala/collection/mutable/StringBuilder
   #59 = Class              #58           // scala/collection/mutable/StringBuilder
   #60 = Utf8               <init>
   #61 = Utf8               ()V
   #62 = NameAndType        #60:#61       // "<init>":()V
   #63 = Methodref          #59.#62       // scala/collection/mutable/StringBuilder."<init>":()V
   #64 = NameAndType        #19:#20       // source:Lcoursier/core/shaded/fastparse/internal/TrieNode;
   #65 = Fieldref           #2.#64        // coursier/core/shaded/fastparse/internal/CompactTrieNode.source:Lcoursier/core/shaded/fastparse/internal/TrieNode;
   #66 = Utf8               coursier/core/shaded/fastparse/internal/TrieNode
   #67 = Class              #66           // coursier/core/shaded/fastparse/internal/TrieNode
   #68 = NameAndType        #21:#26       // children:()Lscala/collection/immutable/Map;
   #69 = Methodref          #67.#68       // coursier/core/shaded/fastparse/internal/TrieNode.children:()Lscala/collection/immutable/Map;
   #70 = Utf8               scala/collection/immutable/Map
   #71 = Class              #70           // scala/collection/immutable/Map
   #72 = Utf8               apply
   #73 = NameAndType        #72:#55       // apply:(Ljava/lang/Object;)Ljava/lang/Object;
   #74 = InterfaceMethodref #71.#73       // scala/collection/immutable/Map.apply:(Ljava/lang/Object;)Ljava/lang/Object;
   #75 = NameAndType        #24:#32       // word:()Z
   #76 = Methodref          #67.#75       // coursier/core/shaded/fastparse/internal/TrieNode.word:()Z
   #77 = Utf8               size
   #78 = Utf8               ()I
   #79 = NameAndType        #77:#78       // size:()I
   #80 = InterfaceMethodref #71.#79       // scala/collection/immutable/Map.size:()I
   #81 = Utf8               keys
   #82 = Utf8               ()Lscala/collection/Iterable;
   #83 = NameAndType        #81:#82       // keys:()Lscala/collection/Iterable;
   #84 = InterfaceMethodref #71.#83       // scala/collection/immutable/Map.keys:()Lscala/collection/Iterable;
   #85 = Utf8               scala/collection/Iterable
   #86 = Class              #85           // scala/collection/Iterable
   #87 = Utf8               head
   #88 = Utf8               ()Ljava/lang/Object;
   #89 = NameAndType        #87:#88       // head:()Ljava/lang/Object;
   #90 = InterfaceMethodref #86.#89       // scala/collection/Iterable.head:()Ljava/lang/Object;
   #91 = Utf8               unboxToChar
   #92 = Utf8               (Ljava/lang/Object;)C
   #93 = NameAndType        #91:#92       // unboxToChar:(Ljava/lang/Object;)C
   #94 = Methodref          #49.#93       // scala/runtime/BoxesRunTime.unboxToChar:(Ljava/lang/Object;)C
   #95 = Utf8               append
   #96 = Utf8               (C)Lscala/collection/mutable/StringBuilder;
   #97 = NameAndType        #95:#96       // append:(C)Lscala/collection/mutable/StringBuilder;
   #98 = Methodref          #59.#97       // scala/collection/mutable/StringBuilder.append:(C)Lscala/collection/mutable/StringBuilder;
   #99 = Utf8               values
  #100 = NameAndType        #99:#82       // values:()Lscala/collection/Iterable;
  #101 = InterfaceMethodref #71.#100      // scala/collection/immutable/Map.values:()Lscala/collection/Iterable;
  #102 = Utf8               scala/Tuple2
  #103 = Class              #102          // scala/Tuple2
  #104 = Utf8               toString
  #105 = Utf8               ()Ljava/lang/String;
  #106 = NameAndType        #104:#105     // toString:()Ljava/lang/String;
  #107 = Methodref          #59.#106      // scala/collection/mutable/StringBuilder.toString:()Ljava/lang/String;
  #108 = Utf8               (Lcoursier/core/shaded/fastparse/internal/TrieNode;)V
  #109 = NameAndType        #60:#108      // "<init>":(Lcoursier/core/shaded/fastparse/internal/TrieNode;)V
  #110 = Methodref          #2.#109       // coursier/core/shaded/fastparse/internal/CompactTrieNode."<init>":(Lcoursier/core/shaded/fastparse/internal/TrieNode;)V
  #111 = Utf8               (Ljava/lang/Object;Ljava/lang/Object;)V
  #112 = NameAndType        #60:#111      // "<init>":(Ljava/lang/Object;Ljava/lang/Object;)V
  #113 = Methodref          #103.#112     // scala/Tuple2."<init>":(Ljava/lang/Object;Ljava/lang/Object;)V
  #114 = Utf8               $minus$greater$extension
  #115 = Utf8               (Ljava/lang/Object;Ljava/lang/Object;)Lscala/Tuple2;
  #116 = NameAndType        #114:#115     // $minus$greater$extension:(Ljava/lang/Object;Ljava/lang/Object;)Lscala/Tuple2;
  #117 = Methodref          #15.#116      // scala/Predef$ArrowAssoc$.$minus$greater$extension:(Ljava/lang/Object;Ljava/lang/Object;)Lscala/Tuple2;
  #118 = Utf8               string
  #119 = Utf8               Lscala/collection/mutable/StringBuilder;
  #120 = Utf8               child
  #121 = Utf8               C
  #122 = Methodref          #4.#62        // java/lang/Object."<init>":()V
  #123 = MethodType         #55           //  (Ljava/lang/Object;)Ljava/lang/Object;
  #124 = Utf8               $anonfun$children$5$adapted
  #125 = Utf8               (Lcoursier/core/shaded/fastparse/internal/CompactTrieNode;Ljava/lang/Object;)Lscala/Tuple2;
  #126 = NameAndType        #124:#125     // $anonfun$children$5$adapted:(Lcoursier/core/shaded/fastparse/internal/CompactTrieNode;Ljava/lang/Object;)Lscala/Tuple2;
  #127 = Methodref          #2.#126       // coursier/core/shaded/fastparse/internal/CompactTrieNode.$anonfun$children$5$adapted:(Lcoursier/core/shaded/fastparse/internal/CompactTrieNode;Ljava/lang/Object;)Lscala/Tuple2;
  #128 = MethodHandle       6:#127        // REF_invokeStatic coursier/core/shaded/fastparse/internal/CompactTrieNode.$anonfun$children$5$adapted:(Lcoursier/core/shaded/fastparse/internal/CompactTrieNode;Ljava/lang/Object;)Lscala/Tuple2;
  #129 = Utf8               (Ljava/lang/Object;)Lscala/Tuple2;
  #130 = MethodType         #129          //  (Ljava/lang/Object;)Lscala/Tuple2;
  #131 = Integer            5
  #132 = Integer            1
  #133 = Utf8               java/lang/invoke/LambdaMetafactory
  #134 = Class              #133          // java/lang/invoke/LambdaMetafactory
  #135 = Utf8               altMetafactory
  #136 = Utf8               (Ljava/lang/invoke/MethodHandles$Lookup;Ljava/lang/String;Ljava/lang/invoke/MethodType;[Ljava/lang/Object;)Ljava/lang/invoke/CallSite;
  #137 = NameAndType        #135:#136     // altMetafactory:(Ljava/lang/invoke/MethodHandles$Lookup;Ljava/lang/String;Ljava/lang/invoke/MethodType;[Ljava/lang/Object;)Ljava/lang/invoke/CallSite;
  #138 = Methodref          #134.#137     // java/lang/invoke/LambdaMetafactory.altMetafactory:(Ljava/lang/invoke/MethodHandles$Lookup;Ljava/lang/String;Ljava/lang/invoke/MethodType;[Ljava/lang/Object;)Ljava/lang/invoke/CallSite;
  #139 = MethodHandle       6:#138        // REF_invokeStatic java/lang/invoke/LambdaMetafactory.altMetafactory:(Ljava/lang/invoke/MethodHandles$Lookup;Ljava/lang/String;Ljava/lang/invoke/MethodType;[Ljava/lang/Object;)Ljava/lang/invoke/CallSite;
  #140 = Utf8               (Lcoursier/core/shaded/fastparse/internal/CompactTrieNode;)Lscala/Function1;
  #141 = NameAndType        #72:#140      // apply:(Lcoursier/core/shaded/fastparse/internal/CompactTrieNode;)Lscala/Function1;
  #142 = InvokeDynamic      #0:#141       // #0:apply:(Lcoursier/core/shaded/fastparse/internal/CompactTrieNode;)Lscala/Function1;
  #143 = Utf8               map
  #144 = Utf8               (Lscala/Function1;)Ljava/lang/Object;
  #145 = NameAndType        #143:#144     // map:(Lscala/Function1;)Ljava/lang/Object;
  #146 = InterfaceMethodref #86.#145      // scala/collection/Iterable.map:(Lscala/Function1;)Ljava/lang/Object;
  #147 = Utf8               scala/$less$colon$less$
  #148 = Class              #147          // scala/$less$colon$less$
  #149 = Utf8               Lscala/$less$colon$less$;
  #150 = NameAndType        #39:#149      // MODULE$:Lscala/$less$colon$less$;
  #151 = Fieldref           #148.#150     // scala/$less$colon$less$.MODULE$:Lscala/$less$colon$less$;
  #152 = Utf8               refl
  #153 = Utf8               ()Lscala/$eq$colon$eq;
  #154 = NameAndType        #152:#153     // refl:()Lscala/$eq$colon$eq;
  #155 = Methodref          #148.#154     // scala/$less$colon$less$.refl:()Lscala/$eq$colon$eq;
  #156 = Utf8               toMap
  #157 = Utf8               (Lscala/$less$colon$less;)Lscala/collection/immutable/Map;
  #158 = NameAndType        #156:#157     // toMap:(Lscala/$less$colon$less;)Lscala/collection/immutable/Map;
  #159 = InterfaceMethodref #86.#158      // scala/collection/Iterable.toMap:(Lscala/$less$colon$less;)Lscala/collection/immutable/Map;
  #160 = Utf8               iter
  #161 = Utf8               Lscala/collection/Iterable;
  #162 = NameAndType        #35:#36       // $anonfun$children$5:(Lcoursier/core/shaded/fastparse/internal/CompactTrieNode;C)Lscala/Tuple2;
  #163 = Methodref          #2.#162       // coursier/core/shaded/fastparse/internal/CompactTrieNode.$anonfun$children$5:(Lcoursier/core/shaded/fastparse/internal/CompactTrieNode;C)Lscala/Tuple2;
  #164 = Utf8               Ljava/lang/Object;
  #165 = Utf8               $deserializeLambda$
  #166 = Utf8               (Ljava/lang/invoke/SerializedLambda;)Ljava/lang/Object;
  #167 = Utf8               scala/runtime/LambdaDeserialize
  #168 = Class              #167          // scala/runtime/LambdaDeserialize
  #169 = Utf8               bootstrap
  #170 = Utf8               (Ljava/lang/invoke/MethodHandles$Lookup;Ljava/lang/String;Ljava/lang/invoke/MethodType;[Ljava/lang/invoke/MethodHandle;)Ljava/lang/invoke/CallSite;
  #171 = NameAndType        #169:#170     // bootstrap:(Ljava/lang/invoke/MethodHandles$Lookup;Ljava/lang/String;Ljava/lang/invoke/MethodType;[Ljava/lang/invoke/MethodHandle;)Ljava/lang/invoke/CallSite;
  #172 = Methodref          #168.#171     // scala/runtime/LambdaDeserialize.bootstrap:(Ljava/lang/invoke/MethodHandles$Lookup;Ljava/lang/String;Ljava/lang/invoke/MethodType;[Ljava/lang/invoke/MethodHandle;)Ljava/lang/invoke/CallSite;
  #173 = MethodHandle       6:#172        // REF_invokeStatic scala/runtime/LambdaDeserialize.bootstrap:(Ljava/lang/invoke/MethodHandles$Lookup;Ljava/lang/String;Ljava/lang/invoke/MethodType;[Ljava/lang/invoke/MethodHandle;)Ljava/lang/invoke/CallSite;
  #174 = Utf8               lambdaDeserialize
  #175 = NameAndType        #174:#166     // lambdaDeserialize:(Ljava/lang/invoke/SerializedLambda;)Ljava/lang/Object;
  #176 = InvokeDynamic      #1:#175       // #1:lambdaDeserialize:(Ljava/lang/invoke/SerializedLambda;)Ljava/lang/Object;
  #177 = Utf8               Signature
  #178 = Utf8               Code
  #179 = Utf8               LineNumberTable
  #180 = Utf8               LocalVariableTable
  #181 = Utf8               StackMapTable
  #182 = Utf8               MethodParameters
  #183 = Utf8               InnerClasses
  #184 = Utf8               SourceFile
  #185 = Utf8               RuntimeVisibleAnnotations
  #186 = Utf8               BootstrapMethods
  #187 = Utf8               ScalaInlineInfo
  #188 = Utf8               ScalaSig
{
  private final coursier.core.shaded.fastparse.internal.TrieNode source;
    descriptor: Lcoursier/core/shaded/fastparse/internal/TrieNode;
    flags: (0x0012) ACC_PRIVATE, ACC_FINAL

  private final scala.collection.immutable.Map<java.lang.Object, scala.Tuple2<java.lang.String, coursier.core.shaded.fastparse.internal.CompactTrieNode>> children;
    descriptor: Lscala/collection/immutable/Map;
    flags: (0x0012) ACC_PRIVATE, ACC_FINAL
    Signature: #23                          // Lscala/collection/immutable/Map<Ljava/lang/Object;Lscala/Tuple2<Ljava/lang/String;Lcoursier/core/shaded/fastparse/internal/CompactTrieNode;>;>;

  private final boolean word;
    descriptor: Z
    flags: (0x0012) ACC_PRIVATE, ACC_FINAL

  public scala.collection.immutable.Map<java.lang.Object, scala.Tuple2<java.lang.String, coursier.core.shaded.fastparse.internal.CompactTrieNode>> children();
    descriptor: ()Lscala/collection/immutable/Map;
    flags: (0x0001) ACC_PUBLIC
    Code:
      stack=1, locals=1, args_size=1
         0: aload_0
         1: getfield      #29                 // Field children:Lscala/collection/immutable/Map;
         4: areturn
      LineNumberTable:
        line 133: 0
      LocalVariableTable:
        Start  Length  Slot  Name   Signature
            0       5     0  this   Lcoursier/core/shaded/fastparse/internal/CompactTrieNode;
    Signature: #27                          // ()Lscala/collection/immutable/Map<Ljava/lang/Object;Lscala/Tuple2<Ljava/lang/String;Lcoursier/core/shaded/fastparse/internal/CompactTrieNode;>;>;

  public boolean word();
    descriptor: ()Z
    flags: (0x0001) ACC_PUBLIC
    Code:
      stack=1, locals=1, args_size=1
         0: aload_0
         1: getfield      #34                 // Field word:Z
         4: ireturn
      LineNumberTable:
        line 147: 0
      LocalVariableTable:
        Start  Length  Slot  Name   Signature
            0       5     0  this   Lcoursier/core/shaded/fastparse/internal/CompactTrieNode;

  public static final scala.Tuple2 $anonfun$children$5(coursier.core.shaded.fastparse.internal.CompactTrieNode, char);
    descriptor: (Lcoursier/core/shaded/fastparse/internal/CompactTrieNode;C)Lscala/Tuple2;
    flags: (0x1019) ACC_PUBLIC, ACC_STATIC, ACC_FINAL, ACC_SYNTHETIC
    Code:
      stack=8, locals=4, args_size=2
         0: getstatic     #42                 // Field scala/Predef$ArrowAssoc$.MODULE$:Lscala/Predef$ArrowAssoc$;
         3: getstatic     #47                 // Field scala/Predef$.MODULE$:Lscala/Predef$;
         6: iload_1
         7: invokestatic  #53                 // Method scala/runtime/BoxesRunTime.boxToCharacter:(C)Ljava/lang/Character;
        10: invokevirtual #57                 // Method scala/Predef$.ArrowAssoc:(Ljava/lang/Object;)Ljava/lang/Object;
        13: new           #59                 // class scala/collection/mutable/StringBuilder
        16: dup
        17: invokespecial #63                 // Method scala/collection/mutable/StringBuilder."<init>":()V
        20: astore_2
        21: aload_0
        22: getfield      #65                 // Field source:Lcoursier/core/shaded/fastparse/internal/TrieNode;
        25: invokevirtual #69                 // Method coursier/core/shaded/fastparse/internal/TrieNode.children:()Lscala/collection/immutable/Map;
        28: iload_1
        29: invokestatic  #53                 // Method scala/runtime/BoxesRunTime.boxToCharacter:(C)Ljava/lang/Character;
        32: invokeinterface #74,  2           // InterfaceMethod scala/collection/immutable/Map.apply:(Ljava/lang/Object;)Ljava/lang/Object;
        37: checkcast     #67                 // class coursier/core/shaded/fastparse/internal/TrieNode
        40: astore_3
        41: aload_3
        42: invokevirtual #76                 // Method coursier/core/shaded/fastparse/internal/TrieNode.word:()Z
        45: ifne          104
        48: aload_3
        49: invokevirtual #69                 // Method coursier/core/shaded/fastparse/internal/TrieNode.children:()Lscala/collection/immutable/Map;
        52: invokeinterface #80,  1           // InterfaceMethod scala/collection/immutable/Map.size:()I
        57: iconst_1
        58: if_icmpne     104
        61: aload_2
        62: aload_3
        63: invokevirtual #69                 // Method coursier/core/shaded/fastparse/internal/TrieNode.children:()Lscala/collection/immutable/Map;
        66: invokeinterface #84,  1           // InterfaceMethod scala/collection/immutable/Map.keys:()Lscala/collection/Iterable;
        71: invokeinterface #90,  1           // InterfaceMethod scala/collection/Iterable.head:()Ljava/lang/Object;
        76: invokestatic  #94                 // Method scala/runtime/BoxesRunTime.unboxToChar:(Ljava/lang/Object;)C
        79: invokevirtual #98                 // Method scala/collection/mutable/StringBuilder.append:(C)Lscala/collection/mutable/StringBuilder;
        82: pop
        83: aload_3
        84: invokevirtual #69                 // Method coursier/core/shaded/fastparse/internal/TrieNode.children:()Lscala/collection/immutable/Map;
        87: invokeinterface #101,  1          // InterfaceMethod scala/collection/immutable/Map.values:()Lscala/collection/Iterable;
        92: invokeinterface #90,  1           // InterfaceMethod scala/collection/Iterable.head:()Ljava/lang/Object;
        97: checkcast     #67                 // class coursier/core/shaded/fastparse/internal/TrieNode
       100: astore_3
       101: goto          41
       104: new           #103                // class scala/Tuple2
       107: dup
       108: aload_2
       109: invokevirtual #107                // Method scala/collection/mutable/StringBuilder.toString:()Ljava/lang/String;
       112: new           #2                  // class coursier/core/shaded/fastparse/internal/CompactTrieNode
       115: dup
       116: aload_3
       117: invokespecial #110                // Method "<init>":(Lcoursier/core/shaded/fastparse/internal/TrieNode;)V
       120: invokespecial #113                // Method scala/Tuple2."<init>":(Ljava/lang/Object;Ljava/lang/Object;)V
       123: invokevirtual #117                // Method scala/Predef$ArrowAssoc$.$minus$greater$extension:(Ljava/lang/Object;Ljava/lang/Object;)Lscala/Tuple2;
       126: areturn
      StackMapTable: number_of_entries = 2
        frame_type = 255 /* full_frame */
          offset_delta = 41
          locals = [ class coursier/core/shaded/fastparse/internal/CompactTrieNode, int, class scala/collection/mutable/StringBuilder, class coursier/core/shaded/fastparse/internal/TrieNode ]
          stack = [ class scala/Predef$ArrowAssoc$, class java/lang/Object ]
        frame_type = 255 /* full_frame */
          offset_delta = 62
          locals = [ class coursier/core/shaded/fastparse/internal/CompactTrieNode, int, class scala/collection/mutable/StringBuilder, class coursier/core/shaded/fastparse/internal/TrieNode ]
          stack = [ class scala/Predef$ArrowAssoc$, class java/lang/Object ]
      LineNumberTable:
        line 134: 3
        line 135: 13
        line 136: 21
        line 137: 41
        line 138: 61
        line 139: 83
        line 137: 101
        line 141: 104
      LocalVariableTable:
        Start  Length  Slot  Name   Signature
           20     103     2 string   Lscala/collection/mutable/StringBuilder;
           40      83     3 child   Lcoursier/core/shaded/fastparse/internal/TrieNode;
            0     127     0 $this   Lcoursier/core/shaded/fastparse/internal/CompactTrieNode;
            0     127     1  char   C
    MethodParameters:
      Name                           Flags
      $this                          final synthetic
      char                           final

  public coursier.core.shaded.fastparse.internal.CompactTrieNode(coursier.core.shaded.fastparse.internal.TrieNode);
    descriptor: (Lcoursier/core/shaded/fastparse/internal/TrieNode;)V
    flags: (0x0001) ACC_PUBLIC
    Code:
      stack=3, locals=3, args_size=2
         0: aload_0
         1: aload_1
         2: putfield      #65                 // Field source:Lcoursier/core/shaded/fastparse/internal/TrieNode;
         5: aload_0
         6: invokespecial #122                // Method java/lang/Object."<init>":()V
         9: aload_0
        10: aload_1
        11: invokevirtual #69                 // Method coursier/core/shaded/fastparse/internal/TrieNode.children:()Lscala/collection/immutable/Map;
        14: invokeinterface #84,  1           // InterfaceMethod scala/collection/immutable/Map.keys:()Lscala/collection/Iterable;
        19: aload_0
        20: invokedynamic #142,  0            // InvokeDynamic #0:apply:(Lcoursier/core/shaded/fastparse/internal/CompactTrieNode;)Lscala/Function1;
        25: invokeinterface #146,  2          // InterfaceMethod scala/collection/Iterable.map:(Lscala/Function1;)Ljava/lang/Object;
        30: checkcast     #86                 // class scala/collection/Iterable
        33: astore_2
        34: aload_2
        35: getstatic     #151                // Field scala/$less$colon$less$.MODULE$:Lscala/$less$colon$less$;
        38: invokevirtual #155                // Method scala/$less$colon$less$.refl:()Lscala/$eq$colon$eq;
        41: invokeinterface #159,  2          // InterfaceMethod scala/collection/Iterable.toMap:(Lscala/$less$colon$less;)Lscala/collection/immutable/Map;
        46: putfield      #29                 // Field children:Lscala/collection/immutable/Map;
        49: aload_0
        50: aload_1
        51: invokevirtual #76                 // Method coursier/core/shaded/fastparse/internal/TrieNode.word:()Z
        54: putfield      #34                 // Field word:Z
        57: return
      LineNumberTable:
        line 132: 0
        line 149: 5
        line 133: 9
        line 134: 10
        line 143: 34
        line 133: 46
        line 147: 49
        line 132: 57
      LocalVariableTable:
        Start  Length  Slot  Name   Signature
           33      13     2  iter   Lscala/collection/Iterable;
            0      58     0  this   Lcoursier/core/shaded/fastparse/internal/CompactTrieNode;
            0      58     1 source   Lcoursier/core/shaded/fastparse/internal/TrieNode;
    MethodParameters:
      Name                           Flags
      source                         final

  public static final scala.Tuple2 $anonfun$children$5$adapted(coursier.core.shaded.fastparse.internal.CompactTrieNode, java.lang.Object);
    descriptor: (Lcoursier/core/shaded/fastparse/internal/CompactTrieNode;Ljava/lang/Object;)Lscala/Tuple2;
    flags: (0x1019) ACC_PUBLIC, ACC_STATIC, ACC_FINAL, ACC_SYNTHETIC
    Code:
      stack=2, locals=2, args_size=2
         0: aload_0
         1: aload_1
         2: invokestatic  #94                 // Method scala/runtime/BoxesRunTime.unboxToChar:(Ljava/lang/Object;)C
         5: invokestatic  #163                // Method $anonfun$children$5:(Lcoursier/core/shaded/fastparse/internal/CompactTrieNode;C)Lscala/Tuple2;
         8: areturn
      LineNumberTable:
        line 134: 0
      LocalVariableTable:
        Start  Length  Slot  Name   Signature
            0       9     0 $this   Lcoursier/core/shaded/fastparse/internal/CompactTrieNode;
            0       9     1  char   Ljava/lang/Object;
    MethodParameters:
      Name                           Flags
      $this                          final
      char                           final

  private static java.lang.Object $deserializeLambda$(java.lang.invoke.SerializedLambda);
    descriptor: (Ljava/lang/invoke/SerializedLambda;)Ljava/lang/Object;
    flags: (0x100a) ACC_PRIVATE, ACC_STATIC, ACC_SYNTHETIC
    Code:
      stack=1, locals=1, args_size=1
         0: aload_0
         1: invokedynamic #176,  0            // InvokeDynamic #1:lambdaDeserialize:(Ljava/lang/invoke/SerializedLambda;)Ljava/lang/Object;
         6: areturn
}
InnerClasses:
  public static final #13= #10 of #12;    // Lookup=class java/lang/invoke/MethodHandles$Lookup of class java/lang/invoke/MethodHandles
  public static #18= #15 of #17;          // =class scala/Predef$ArrowAssoc$ of class scala/Predef
SourceFile: "Util.scala"
RuntimeVisibleAnnotations:
  0: #6(#7=s#8)
    scala.reflect.ScalaSignature(
      bytes="\u0006\u0005i2Aa\u0002\u0005\u0003\u001b!AA\u0003\u0001B\u0001B\u0003%Q\u0003C\u0003\u001a\u0001\u0011\u0005!\u0004C\u0004\u001e\u0001\t\u0007I\u0011\u0001\u0010\t\rM\u0002\u0001\u0015!\u0003 \u0011\u001d!\u0004A1A\u0005\u0002UBa!\u000f\u0001!\u0002\u00131$aD\"p[B\f7\r\u001e+sS\u0016tu\u000eZ3\u000b\u0005%Q\u0011\u0001C5oi\u0016\u0014h.\u00197\u000b\u0003-\t\u0011BZ1tiB\f\'o]3\u0004\u0001M\u0011\u0001A\u0004\t\u0003\u001fIi\u0011\u0001\u0005\u0006\u0002#\u0005)1oY1mC&\u00111\u0003\u0005\u0002\u0007\u0003:L(+\u001a4\u0002\rM|WO]2f!\t1r#D\u0001\t\u0013\tA\u0002B\u0001\u0005Ue&,gj\u001c3f\u0003\u0019a\u0014N\\5u}Q\u00111\u0004\b\t\u0003-\u0001AQ\u0001\u0006\u0002A\u0002U\t\u0001b\u00195jY\u0012\u0014XM\\\u000b\u0002?A!\u0001e\n\u0016.\u001d\t\tS\u0005\u0005\u0002#!5\t1E\u0003\u0002%\u0019\u00051AH]8pizJ!A\n\t\u0002\rA\u0013X\rZ3g\u0013\tA\u0013FA\u0002NCBT!A\n\t\u0011\u0005=Y\u0013B\u0001\u0017\u0011\u0005\u0011\u0019\u0005.\u0019:\u0011\t=q\u0003gG\u0005\u0003_A\u0011a\u0001V;qY\u0016\u0014\u0004C\u0001\u00112\u0013\t\u0011\u0014F\u0001\u0004TiJLgnZ\u0001\nG\"LG\u000e\u001a:f]\u0002\nAa^8sIV\ta\u0007\u0005\u0002\u0010o%\u0011\u0001\b\u0005\u0002\b\u0005>|G.Z1o\u0003\u00159xN\u001d3!\u0001"
    )
BootstrapMethods:
  0: #139 REF_invokeStatic java/lang/invoke/LambdaMetafactory.altMetafactory:(Ljava/lang/invoke/MethodHandles$Lookup;Ljava/lang/String;Ljava/lang/invoke/MethodType;[Ljava/lang/Object;)Ljava/lang/invoke/CallSite;
    Method arguments:
      #123 (Ljava/lang/Object;)Ljava/lang/Object;
      #128 REF_invokeStatic coursier/core/shaded/fastparse/internal/CompactTrieNode.$anonfun$children$5$adapted:(Lcoursier/core/shaded/fastparse/internal/CompactTrieNode;Ljava/lang/Object;)Lscala/Tuple2;
      #130 (Ljava/lang/Object;)Lscala/Tuple2;
      #131 5
      #132 1
      #130 (Ljava/lang/Object;)Lscala/Tuple2;
  1: #173 REF_invokeStatic scala/runtime/LambdaDeserialize.bootstrap:(Ljava/lang/invoke/MethodHandles$Lookup;Ljava/lang/String;Ljava/lang/invoke/MethodType;[Ljava/lang/invoke/MethodHandle;)Ljava/lang/invoke/CallSite;
    Method arguments:
      #128 REF_invokeStatic coursier/core/shaded/fastparse/internal/CompactTrieNode.$anonfun$children$5$adapted:(Lcoursier/core/shaded/fastparse/internal/CompactTrieNode;Ljava/lang/Object;)Lscala/Tuple2;
  ScalaInlineInfo: length = 0x1D (unknown attribute)
   01 01 00 05 00 23 00 24 01 00 7C 00 7D 01 00 3C
   00 6C 01 00 15 00 1A 01 00 18 00 20 01
  ScalaSig: length = 0x3 (unknown attribute)
   05 02 00
