Classfile /Users/mw/Projects/slang-braindump/.jar/jar11/assemble/slang-braindump/assemble/content/coursier/core/shaded/fastparse/internal/MacroRepImpls.class
  Last modified May 29, 2022; size 4965 bytes
  SHA-256 checksum 4dcac53292ef9f44a854cf0fcec0acb3ab556428dc6a3a642aab9944bc58420c
  Compiled from "RepImpls.scala"
public final class coursier.core.shaded.fastparse.internal.MacroRepImpls
  minor version: 0
  major version: 52
  flags: (0x0031) ACC_PUBLIC, ACC_FINAL, ACC_SUPER
  this_class: #2                          // coursier/core/shaded/fastparse/internal/MacroRepImpls
  super_class: #4                         // java/lang/Object
  interfaces: 0, fields: 0, methods: 5, attributes: 4
Constant pool:
   #1 = Utf8               coursier/core/shaded/fastparse/internal/MacroRepImpls
   #2 = Class              #1             // coursier/core/shaded/fastparse/internal/MacroRepImpls
   #3 = Utf8               java/lang/Object
   #4 = Class              #3             // java/lang/Object
   #5 = Utf8               RepImpls.scala
   #6 = Utf8               Lscala/reflect/ScalaSignature;
   #7 = Utf8               bytes
   #8 = Utf8               \u0006\u0005\u0005Ms!\u0002\u0005\n\u0011\u0003qa!\u0002\t\n\u0011\u0003\t\u0002\"\u0002\r\u0002\t\u0003I\u0002\"\u0002\u000e\u0002\t\u0003Y\u0002\"B*\u0002\t\u0003!\u0006\"B4\u0002\t\u0003A\u0007\"B?\u0002\t\u0003q\bbBA\u0013\u0003\u0011\u0005\u0011qE\u0001\u000e\u001b\u0006\u001c\'o\u001c*fa&k\u0007\u000f\\:\u000b\u0005)Y\u0011\u0001C5oi\u0016\u0014h.\u00197\u000b\u00031\t\u0011BZ1tiB\f\'o]3\u0004\u0001A\u0011q\"A\u0007\u0002\u0013\tiQ*Y2s_J+\u0007/S7qYN\u001c\"!\u0001\n\u0011\u0005M1R\"\u0001\u000b\u000b\u0003U\tQa]2bY\u0006L!a\u0006\u000b\u0003\r\u0005s\u0017PU3g\u0003\u0019a\u0014N\\5u}Q\ta\"\u0001\u0006sKBDV*Y2s_B*2\u0001H\u001dG)\ti2\u0005F\u0002\u001f\u0019F#2a\b%K)\r\u00013G\u0011\t\u0003C=r!AI\u0012\r\u0001!)Ae\u0001a\u0001K\u0005\t1\r\u0005\u0002\'[5\tqE\u0003\u0002)S\u0005A!\r\\1dW\n|\u0007P\u0003\u0002+W\u00051Q.Y2s_NT!\u0001\f\u000b\u0002\u000fI,g\r\\3di&\u0011af\n\u0002\b\u0007>tG/\u001a=u\u0013\t\u0001\u0014G\u0001\u0003Ue\u0016,\u0017B\u0001\u001a*\u0005\u001d\tE.[1tKNDq\u0001N\u0002\u0002\u0002\u0003\u000fQ\'\u0001\u0006fm&$WM\\2fIE\u00022!\t\u001c9\u0013\t9\u0014GA\u0006XK\u0006\\G+\u001f9f)\u0006<\u0007C\u0001\u0012:\t\u0015Q4A1\u0001<\u0005\u0005!\u0016C\u0001\u001f@!\t\u0019R(\u0003\u0002?)\t9aj\u001c;iS:<\u0007CA\nA\u0013\t\tECA\u0002B]fDqaQ\u0002\u0002\u0002\u0003\u000fA)\u0001\u0006fm&$WM\\2fII\u00022!\t\u001cF!\t\u0011c\tB\u0003H\u0007\t\u00071HA\u0001W\u0011\u0015I5\u00011\u0001!\u0003!\u0011X\r]3bi\u0016\u0014\b\"B&\u0004\u0001\u0004\u0001\u0013aA2uq\")Qj\u0001a\u0001\u001d\u0006Qq\u000f[5uKN\u0004\u0018mY3\u0011\u0007My\u0005%\u0003\u0002Q)\t1q\n\u001d;j_:DQAU\u0002A\u00029\u000b1!\\5o\u0003)\u0011X\r\u001d-NC\u000e\u0014x.M\u000b\u0004+~#GC\u0001,[)\r9VM\u001a\u000b\u00041n\u0003\u0007CA-0\u001d\t\u0011#\fC\u0003%\t\u0001\u0007Q\u0005C\u0004]\t\u0005\u0005\t9A/\u0002\u0015\u00154\u0018\u000eZ3oG\u0016$3\u0007E\u0002Zmy\u0003\"AI0\u0005\u000bi\"!\u0019A\u001e\t\u000f\u0005$\u0011\u0011!a\u0002E\u0006QQM^5eK:\u001cW\r\n\u001b\u0011\u0007e34\r\u0005\u0002#I\u0012)q\t\u0002b\u0001w!)\u0011\n\u0002a\u00011\")1\n\u0002a\u00011\u0006Q!/\u001a9Y\u001b\u0006\u001c\'o\u001c\u001a\u0016\u0007%$\u0018\u0010\u0006\u0002k_R\u00111\u000e \u000b\u0004Yj\\HcA7qkB\u0011an\f\b\u0003E=DQ\u0001J\u0003A\u0002\u0015Bq!]\u0003\u0002\u0002\u0003\u000f!/\u0001\u0006fm&$WM\\2fIU\u00022A\u001c\u001ct!\t\u0011C\u000fB\u0003;\u000b\t\u00071\bC\u0004w\u000b\u0005\u0005\t9A<\u0002\u0015\u00154\u0018\u000eZ3oG\u0016$c\u0007E\u0002oma\u0004\"AI=\u0005\u000b\u001d+!\u0019A\u001e\t\u000b%+\u0001\u0019A7\t\u000b-+\u0001\u0019A7\t\u000bI+\u0001\u0019A7\u0002\u0019I,\u0007\u000fW\'bGJ|\u0017g^:\u0016\u000b}\f\u0019\"!\b\u0015\t\u0005\u0005\u0011\u0011\u0002\u000b\t\u0003\u0007\ty\"!\t\u0002$Q1\u0011QAA\u0006\u0003+\u00012!a\u00020\u001d\r\u0011\u0013\u0011\u0002\u0005\u0006I\u0019\u0001\r!\n\u0005\n\u0003\u001b1\u0011\u0011!a\u0002\u0003\u001f\t!\"\u001a<jI\u0016t7-\u001a\u00138!\u0015\t9ANA\t!\r\u0011\u00131\u0003\u0003\u0006u\u0019\u0011\ra\u000f\u0005\n\u0003/1\u0011\u0011!a\u0002\u00033\t!\"\u001a<jI\u0016t7-\u001a\u00139!\u0015\t9ANA\u000e!\r\u0011\u0013Q\u0004\u0003\u0006\u000f\u001a\u0011\ra\u000f\u0005\u0007\u0013\u001a\u0001\r!!\u0002\t\r53\u0001\u0019AA\u0003\u0011\u0019Ye\u00011\u0001\u0002\u0006\u0005a!/\u001a9Y\u001b\u0006\u001c\'o\u001c\u001axgV1\u0011\u0011FA \u0003\u0013\"B!a\u000b\u00026Q!\u0011QFA))!\ty#a\u0013\u0002N\u0005=CCBA\u0019\u0003o\t\t\u0005E\u0002\u00024=r1AIA\u001b\u0011\u0015!s\u00011\u0001&\u0011%\tIdBA\u0001\u0002\b\tY$\u0001\u0006fm&$WM\\2fIe\u0002R!a\r7\u0003{\u00012AIA \t\u0015QtA1\u0001<\u0011%\t\u0019eBA\u0001\u0002\b\t)%A\u0006fm&$WM\\2fIE\u0002\u0004#BA\u001am\u0005\u001d\u0003c\u0001\u0012\u0002J\u0011)qi\u0002b\u0001w!1\u0011j\u0002a\u0001\u0003cAa!T\u0004A\u0002\u0005E\u0002BB&\b\u0001\u0004\t\t\u0004\u0003\u0004S\u000f\u0001\u0007\u0011\u0011\u0007
   #9 = Utf8               scala/reflect/api/Trees$TreeApi
  #10 = Class              #9             // scala/reflect/api/Trees$TreeApi
  #11 = Utf8               scala/reflect/api/Trees
  #12 = Class              #11            // scala/reflect/api/Trees
  #13 = Utf8               TreeApi
  #14 = Utf8               scala/reflect/api/TypeTags$WeakTypeTag
  #15 = Class              #14            // scala/reflect/api/TypeTags$WeakTypeTag
  #16 = Utf8               scala/reflect/api/TypeTags
  #17 = Class              #16            // scala/reflect/api/TypeTags
  #18 = Utf8               WeakTypeTag
  #19 = Utf8               repXMacro2ws
  #20 = Utf8               (Lscala/reflect/macros/blackbox/Context;Lscala/reflect/api/Trees$TreeApi;Lscala/reflect/api/Trees$TreeApi;Lscala/reflect/api/Trees$TreeApi;Lscala/reflect/api/Trees$TreeApi;Lscala/reflect/api/TypeTags$WeakTypeTag;Lscala/reflect/api/TypeTags$WeakTypeTag;)Lscala/reflect/api/Trees$TreeApi;
  #21 = Utf8               <T:Ljava/lang/Object;V:Ljava/lang/Object;>(Lscala/reflect/macros/blackbox/Context;Lscala/reflect/api/Trees$TreeApi;Lscala/reflect/api/Trees$TreeApi;Lscala/reflect/api/Trees$TreeApi;Lscala/reflect/api/Trees$TreeApi;Lscala/reflect/api/TypeTags$WeakTypeTag<TT;>;Lscala/reflect/api/TypeTags$WeakTypeTag<TV;>;)Lscala/reflect/api/Trees$TreeApi;
  #22 = Utf8               c
  #23 = Utf8               min
  #24 = Utf8               repeater
  #25 = Utf8               whitespace
  #26 = Utf8               ctx
  #27 = Utf8               evidence$9
  #28 = Utf8               evidence$10
  #29 = Utf8               coursier/core/shaded/fastparse/internal/MacroRepImpls$
  #30 = Class              #29            // coursier/core/shaded/fastparse/internal/MacroRepImpls$
  #31 = Utf8               MODULE$
  #32 = Utf8               Lcoursier/core/shaded/fastparse/internal/MacroRepImpls$;
  #33 = NameAndType        #31:#32        // MODULE$:Lcoursier/core/shaded/fastparse/internal/MacroRepImpls$;
  #34 = Fieldref           #30.#33        // coursier/core/shaded/fastparse/internal/MacroRepImpls$.MODULE$:Lcoursier/core/shaded/fastparse/internal/MacroRepImpls$;
  #35 = NameAndType        #19:#20        // repXMacro2ws:(Lscala/reflect/macros/blackbox/Context;Lscala/reflect/api/Trees$TreeApi;Lscala/reflect/api/Trees$TreeApi;Lscala/reflect/api/Trees$TreeApi;Lscala/reflect/api/Trees$TreeApi;Lscala/reflect/api/TypeTags$WeakTypeTag;Lscala/reflect/api/TypeTags$WeakTypeTag;)Lscala/reflect/api/Trees$TreeApi;
  #36 = Methodref          #30.#35        // coursier/core/shaded/fastparse/internal/MacroRepImpls$.repXMacro2ws:(Lscala/reflect/macros/blackbox/Context;Lscala/reflect/api/Trees$TreeApi;Lscala/reflect/api/Trees$TreeApi;Lscala/reflect/api/Trees$TreeApi;Lscala/reflect/api/Trees$TreeApi;Lscala/reflect/api/TypeTags$WeakTypeTag;Lscala/reflect/api/TypeTags$WeakTypeTag;)Lscala/reflect/api/Trees$TreeApi;
  #37 = Utf8               repXMacro1ws
  #38 = Utf8               (Lscala/reflect/macros/blackbox/Context;Lscala/reflect/api/Trees$TreeApi;Lscala/reflect/api/Trees$TreeApi;Lscala/reflect/api/Trees$TreeApi;Lscala/reflect/api/TypeTags$WeakTypeTag;Lscala/reflect/api/TypeTags$WeakTypeTag;)Lscala/reflect/api/Trees$TreeApi;
  #39 = Utf8               <T:Ljava/lang/Object;V:Ljava/lang/Object;>(Lscala/reflect/macros/blackbox/Context;Lscala/reflect/api/Trees$TreeApi;Lscala/reflect/api/Trees$TreeApi;Lscala/reflect/api/Trees$TreeApi;Lscala/reflect/api/TypeTags$WeakTypeTag<TT;>;Lscala/reflect/api/TypeTags$WeakTypeTag<TV;>;)Lscala/reflect/api/Trees$TreeApi;
  #40 = Utf8               evidence$7
  #41 = Utf8               evidence$8
  #42 = NameAndType        #37:#38        // repXMacro1ws:(Lscala/reflect/macros/blackbox/Context;Lscala/reflect/api/Trees$TreeApi;Lscala/reflect/api/Trees$TreeApi;Lscala/reflect/api/Trees$TreeApi;Lscala/reflect/api/TypeTags$WeakTypeTag;Lscala/reflect/api/TypeTags$WeakTypeTag;)Lscala/reflect/api/Trees$TreeApi;
  #43 = Methodref          #30.#42        // coursier/core/shaded/fastparse/internal/MacroRepImpls$.repXMacro1ws:(Lscala/reflect/macros/blackbox/Context;Lscala/reflect/api/Trees$TreeApi;Lscala/reflect/api/Trees$TreeApi;Lscala/reflect/api/Trees$TreeApi;Lscala/reflect/api/TypeTags$WeakTypeTag;Lscala/reflect/api/TypeTags$WeakTypeTag;)Lscala/reflect/api/Trees$TreeApi;
  #44 = Utf8               repXMacro2
  #45 = Utf8               evidence$5
  #46 = Utf8               evidence$6
  #47 = NameAndType        #44:#38        // repXMacro2:(Lscala/reflect/macros/blackbox/Context;Lscala/reflect/api/Trees$TreeApi;Lscala/reflect/api/Trees$TreeApi;Lscala/reflect/api/Trees$TreeApi;Lscala/reflect/api/TypeTags$WeakTypeTag;Lscala/reflect/api/TypeTags$WeakTypeTag;)Lscala/reflect/api/Trees$TreeApi;
  #48 = Methodref          #30.#47        // coursier/core/shaded/fastparse/internal/MacroRepImpls$.repXMacro2:(Lscala/reflect/macros/blackbox/Context;Lscala/reflect/api/Trees$TreeApi;Lscala/reflect/api/Trees$TreeApi;Lscala/reflect/api/Trees$TreeApi;Lscala/reflect/api/TypeTags$WeakTypeTag;Lscala/reflect/api/TypeTags$WeakTypeTag;)Lscala/reflect/api/Trees$TreeApi;
  #49 = Utf8               repXMacro1
  #50 = Utf8               (Lscala/reflect/macros/blackbox/Context;Lscala/reflect/api/Trees$TreeApi;Lscala/reflect/api/Trees$TreeApi;Lscala/reflect/api/TypeTags$WeakTypeTag;Lscala/reflect/api/TypeTags$WeakTypeTag;)Lscala/reflect/api/Trees$TreeApi;
  #51 = Utf8               <T:Ljava/lang/Object;V:Ljava/lang/Object;>(Lscala/reflect/macros/blackbox/Context;Lscala/reflect/api/Trees$TreeApi;Lscala/reflect/api/Trees$TreeApi;Lscala/reflect/api/TypeTags$WeakTypeTag<TT;>;Lscala/reflect/api/TypeTags$WeakTypeTag<TV;>;)Lscala/reflect/api/Trees$TreeApi;
  #52 = Utf8               evidence$3
  #53 = Utf8               evidence$4
  #54 = NameAndType        #49:#50        // repXMacro1:(Lscala/reflect/macros/blackbox/Context;Lscala/reflect/api/Trees$TreeApi;Lscala/reflect/api/Trees$TreeApi;Lscala/reflect/api/TypeTags$WeakTypeTag;Lscala/reflect/api/TypeTags$WeakTypeTag;)Lscala/reflect/api/Trees$TreeApi;
  #55 = Methodref          #30.#54        // coursier/core/shaded/fastparse/internal/MacroRepImpls$.repXMacro1:(Lscala/reflect/macros/blackbox/Context;Lscala/reflect/api/Trees$TreeApi;Lscala/reflect/api/Trees$TreeApi;Lscala/reflect/api/TypeTags$WeakTypeTag;Lscala/reflect/api/TypeTags$WeakTypeTag;)Lscala/reflect/api/Trees$TreeApi;
  #56 = Utf8               repXMacro0
  #57 = Utf8               (Lscala/reflect/macros/blackbox/Context;Lscala/Option;Lscala/Option;Lscala/reflect/api/Trees$TreeApi;Lscala/reflect/api/Trees$TreeApi;Lscala/reflect/api/TypeTags$WeakTypeTag;Lscala/reflect/api/TypeTags$WeakTypeTag;)Lscala/reflect/api/Trees$TreeApi;
  #58 = Utf8               <T:Ljava/lang/Object;V:Ljava/lang/Object;>(Lscala/reflect/macros/blackbox/Context;Lscala/Option<Lscala/reflect/api/Trees$TreeApi;>;Lscala/Option<Lscala/reflect/api/Trees$TreeApi;>;Lscala/reflect/api/Trees$TreeApi;Lscala/reflect/api/Trees$TreeApi;Lscala/reflect/api/TypeTags$WeakTypeTag<TT;>;Lscala/reflect/api/TypeTags$WeakTypeTag<TV;>;)Lscala/reflect/api/Trees$TreeApi;
  #59 = Utf8               evidence$1
  #60 = Utf8               evidence$2
  #61 = NameAndType        #56:#57        // repXMacro0:(Lscala/reflect/macros/blackbox/Context;Lscala/Option;Lscala/Option;Lscala/reflect/api/Trees$TreeApi;Lscala/reflect/api/Trees$TreeApi;Lscala/reflect/api/TypeTags$WeakTypeTag;Lscala/reflect/api/TypeTags$WeakTypeTag;)Lscala/reflect/api/Trees$TreeApi;
  #62 = Methodref          #30.#61        // coursier/core/shaded/fastparse/internal/MacroRepImpls$.repXMacro0:(Lscala/reflect/macros/blackbox/Context;Lscala/Option;Lscala/Option;Lscala/reflect/api/Trees$TreeApi;Lscala/reflect/api/Trees$TreeApi;Lscala/reflect/api/TypeTags$WeakTypeTag;Lscala/reflect/api/TypeTags$WeakTypeTag;)Lscala/reflect/api/Trees$TreeApi;
  #63 = Utf8               Code
  #64 = Utf8               Signature
  #65 = Utf8               MethodParameters
  #66 = Utf8               InnerClasses
  #67 = Utf8               SourceFile
  #68 = Utf8               RuntimeVisibleAnnotations
  #69 = Utf8               ScalaSig
{
  public static <T extends java.lang.Object, V extends java.lang.Object> scala.reflect.api.Trees$TreeApi repXMacro2ws(scala.reflect.macros.blackbox.Context, scala.reflect.api.Trees$TreeApi, scala.reflect.api.Trees$TreeApi, scala.reflect.api.Trees$TreeApi, scala.reflect.api.Trees$TreeApi, scala.reflect.api.TypeTags$WeakTypeTag<T>, scala.reflect.api.TypeTags$WeakTypeTag<V>);
    descriptor: (Lscala/reflect/macros/blackbox/Context;Lscala/reflect/api/Trees$TreeApi;Lscala/reflect/api/Trees$TreeApi;Lscala/reflect/api/Trees$TreeApi;Lscala/reflect/api/Trees$TreeApi;Lscala/reflect/api/TypeTags$WeakTypeTag;Lscala/reflect/api/TypeTags$WeakTypeTag;)Lscala/reflect/api/Trees$TreeApi;
    flags: (0x0009) ACC_PUBLIC, ACC_STATIC
    Code:
      stack=8, locals=7, args_size=7
         0: getstatic     #34                 // Field coursier/core/shaded/fastparse/internal/MacroRepImpls$.MODULE$:Lcoursier/core/shaded/fastparse/internal/MacroRepImpls$;
         3: aload_0
         4: aload_1
         5: aload_2
         6: aload_3
         7: aload         4
         9: aload         5
        11: aload         6
        13: invokevirtual #36                 // Method coursier/core/shaded/fastparse/internal/MacroRepImpls$.repXMacro2ws:(Lscala/reflect/macros/blackbox/Context;Lscala/reflect/api/Trees$TreeApi;Lscala/reflect/api/Trees$TreeApi;Lscala/reflect/api/Trees$TreeApi;Lscala/reflect/api/Trees$TreeApi;Lscala/reflect/api/TypeTags$WeakTypeTag;Lscala/reflect/api/TypeTags$WeakTypeTag;)Lscala/reflect/api/Trees$TreeApi;
        16: areturn
    Signature: #21                          // <T:Ljava/lang/Object;V:Ljava/lang/Object;>(Lscala/reflect/macros/blackbox/Context;Lscala/reflect/api/Trees$TreeApi;Lscala/reflect/api/Trees$TreeApi;Lscala/reflect/api/Trees$TreeApi;Lscala/reflect/api/Trees$TreeApi;Lscala/reflect/api/TypeTags$WeakTypeTag<TT;>;Lscala/reflect/api/TypeTags$WeakTypeTag<TV;>;)Lscala/reflect/api/Trees$TreeApi;
    MethodParameters:
      Name                           Flags
      c                              final
      min                            final
      repeater                       final
      whitespace                     final
      ctx                            final
      evidence$9                     final
      evidence$10                    final

  public static <T extends java.lang.Object, V extends java.lang.Object> scala.reflect.api.Trees$TreeApi repXMacro1ws(scala.reflect.macros.blackbox.Context, scala.reflect.api.Trees$TreeApi, scala.reflect.api.Trees$TreeApi, scala.reflect.api.Trees$TreeApi, scala.reflect.api.TypeTags$WeakTypeTag<T>, scala.reflect.api.TypeTags$WeakTypeTag<V>);
    descriptor: (Lscala/reflect/macros/blackbox/Context;Lscala/reflect/api/Trees$TreeApi;Lscala/reflect/api/Trees$TreeApi;Lscala/reflect/api/Trees$TreeApi;Lscala/reflect/api/TypeTags$WeakTypeTag;Lscala/reflect/api/TypeTags$WeakTypeTag;)Lscala/reflect/api/Trees$TreeApi;
    flags: (0x0009) ACC_PUBLIC, ACC_STATIC
    Code:
      stack=7, locals=6, args_size=6
         0: getstatic     #34                 // Field coursier/core/shaded/fastparse/internal/MacroRepImpls$.MODULE$:Lcoursier/core/shaded/fastparse/internal/MacroRepImpls$;
         3: aload_0
         4: aload_1
         5: aload_2
         6: aload_3
         7: aload         4
         9: aload         5
        11: invokevirtual #43                 // Method coursier/core/shaded/fastparse/internal/MacroRepImpls$.repXMacro1ws:(Lscala/reflect/macros/blackbox/Context;Lscala/reflect/api/Trees$TreeApi;Lscala/reflect/api/Trees$TreeApi;Lscala/reflect/api/Trees$TreeApi;Lscala/reflect/api/TypeTags$WeakTypeTag;Lscala/reflect/api/TypeTags$WeakTypeTag;)Lscala/reflect/api/Trees$TreeApi;
        14: areturn
    Signature: #39                          // <T:Ljava/lang/Object;V:Ljava/lang/Object;>(Lscala/reflect/macros/blackbox/Context;Lscala/reflect/api/Trees$TreeApi;Lscala/reflect/api/Trees$TreeApi;Lscala/reflect/api/Trees$TreeApi;Lscala/reflect/api/TypeTags$WeakTypeTag<TT;>;Lscala/reflect/api/TypeTags$WeakTypeTag<TV;>;)Lscala/reflect/api/Trees$TreeApi;
    MethodParameters:
      Name                           Flags
      c                              final
      repeater                       final
      whitespace                     final
      ctx                            final
      evidence$7                     final
      evidence$8                     final

  public static <T extends java.lang.Object, V extends java.lang.Object> scala.reflect.api.Trees$TreeApi repXMacro2(scala.reflect.macros.blackbox.Context, scala.reflect.api.Trees$TreeApi, scala.reflect.api.Trees$TreeApi, scala.reflect.api.Trees$TreeApi, scala.reflect.api.TypeTags$WeakTypeTag<T>, scala.reflect.api.TypeTags$WeakTypeTag<V>);
    descriptor: (Lscala/reflect/macros/blackbox/Context;Lscala/reflect/api/Trees$TreeApi;Lscala/reflect/api/Trees$TreeApi;Lscala/reflect/api/Trees$TreeApi;Lscala/reflect/api/TypeTags$WeakTypeTag;Lscala/reflect/api/TypeTags$WeakTypeTag;)Lscala/reflect/api/Trees$TreeApi;
    flags: (0x0009) ACC_PUBLIC, ACC_STATIC
    Code:
      stack=7, locals=6, args_size=6
         0: getstatic     #34                 // Field coursier/core/shaded/fastparse/internal/MacroRepImpls$.MODULE$:Lcoursier/core/shaded/fastparse/internal/MacroRepImpls$;
         3: aload_0
         4: aload_1
         5: aload_2
         6: aload_3
         7: aload         4
         9: aload         5
        11: invokevirtual #48                 // Method coursier/core/shaded/fastparse/internal/MacroRepImpls$.repXMacro2:(Lscala/reflect/macros/blackbox/Context;Lscala/reflect/api/Trees$TreeApi;Lscala/reflect/api/Trees$TreeApi;Lscala/reflect/api/Trees$TreeApi;Lscala/reflect/api/TypeTags$WeakTypeTag;Lscala/reflect/api/TypeTags$WeakTypeTag;)Lscala/reflect/api/Trees$TreeApi;
        14: areturn
    Signature: #39                          // <T:Ljava/lang/Object;V:Ljava/lang/Object;>(Lscala/reflect/macros/blackbox/Context;Lscala/reflect/api/Trees$TreeApi;Lscala/reflect/api/Trees$TreeApi;Lscala/reflect/api/Trees$TreeApi;Lscala/reflect/api/TypeTags$WeakTypeTag<TT;>;Lscala/reflect/api/TypeTags$WeakTypeTag<TV;>;)Lscala/reflect/api/Trees$TreeApi;
    MethodParameters:
      Name                           Flags
      c                              final
      min                            final
      repeater                       final
      ctx                            final
      evidence$5                     final
      evidence$6                     final

  public static <T extends java.lang.Object, V extends java.lang.Object> scala.reflect.api.Trees$TreeApi repXMacro1(scala.reflect.macros.blackbox.Context, scala.reflect.api.Trees$TreeApi, scala.reflect.api.Trees$TreeApi, scala.reflect.api.TypeTags$WeakTypeTag<T>, scala.reflect.api.TypeTags$WeakTypeTag<V>);
    descriptor: (Lscala/reflect/macros/blackbox/Context;Lscala/reflect/api/Trees$TreeApi;Lscala/reflect/api/Trees$TreeApi;Lscala/reflect/api/TypeTags$WeakTypeTag;Lscala/reflect/api/TypeTags$WeakTypeTag;)Lscala/reflect/api/Trees$TreeApi;
    flags: (0x0009) ACC_PUBLIC, ACC_STATIC
    Code:
      stack=6, locals=5, args_size=5
         0: getstatic     #34                 // Field coursier/core/shaded/fastparse/internal/MacroRepImpls$.MODULE$:Lcoursier/core/shaded/fastparse/internal/MacroRepImpls$;
         3: aload_0
         4: aload_1
         5: aload_2
         6: aload_3
         7: aload         4
         9: invokevirtual #55                 // Method coursier/core/shaded/fastparse/internal/MacroRepImpls$.repXMacro1:(Lscala/reflect/macros/blackbox/Context;Lscala/reflect/api/Trees$TreeApi;Lscala/reflect/api/Trees$TreeApi;Lscala/reflect/api/TypeTags$WeakTypeTag;Lscala/reflect/api/TypeTags$WeakTypeTag;)Lscala/reflect/api/Trees$TreeApi;
        12: areturn
    Signature: #51                          // <T:Ljava/lang/Object;V:Ljava/lang/Object;>(Lscala/reflect/macros/blackbox/Context;Lscala/reflect/api/Trees$TreeApi;Lscala/reflect/api/Trees$TreeApi;Lscala/reflect/api/TypeTags$WeakTypeTag<TT;>;Lscala/reflect/api/TypeTags$WeakTypeTag<TV;>;)Lscala/reflect/api/Trees$TreeApi;
    MethodParameters:
      Name                           Flags
      c                              final
      repeater                       final
      ctx                            final
      evidence$3                     final
      evidence$4                     final

  public static <T extends java.lang.Object, V extends java.lang.Object> scala.reflect.api.Trees$TreeApi repXMacro0(scala.reflect.macros.blackbox.Context, scala.Option<scala.reflect.api.Trees$TreeApi>, scala.Option<scala.reflect.api.Trees$TreeApi>, scala.reflect.api.Trees$TreeApi, scala.reflect.api.Trees$TreeApi, scala.reflect.api.TypeTags$WeakTypeTag<T>, scala.reflect.api.TypeTags$WeakTypeTag<V>);
    descriptor: (Lscala/reflect/macros/blackbox/Context;Lscala/Option;Lscala/Option;Lscala/reflect/api/Trees$TreeApi;Lscala/reflect/api/Trees$TreeApi;Lscala/reflect/api/TypeTags$WeakTypeTag;Lscala/reflect/api/TypeTags$WeakTypeTag;)Lscala/reflect/api/Trees$TreeApi;
    flags: (0x0009) ACC_PUBLIC, ACC_STATIC
    Code:
      stack=8, locals=7, args_size=7
         0: getstatic     #34                 // Field coursier/core/shaded/fastparse/internal/MacroRepImpls$.MODULE$:Lcoursier/core/shaded/fastparse/internal/MacroRepImpls$;
         3: aload_0
         4: aload_1
         5: aload_2
         6: aload_3
         7: aload         4
         9: aload         5
        11: aload         6
        13: invokevirtual #62                 // Method coursier/core/shaded/fastparse/internal/MacroRepImpls$.repXMacro0:(Lscala/reflect/macros/blackbox/Context;Lscala/Option;Lscala/Option;Lscala/reflect/api/Trees$TreeApi;Lscala/reflect/api/Trees$TreeApi;Lscala/reflect/api/TypeTags$WeakTypeTag;Lscala/reflect/api/TypeTags$WeakTypeTag;)Lscala/reflect/api/Trees$TreeApi;
        16: areturn
    Signature: #58                          // <T:Ljava/lang/Object;V:Ljava/lang/Object;>(Lscala/reflect/macros/blackbox/Context;Lscala/Option<Lscala/reflect/api/Trees$TreeApi;>;Lscala/Option<Lscala/reflect/api/Trees$TreeApi;>;Lscala/reflect/api/Trees$TreeApi;Lscala/reflect/api/Trees$TreeApi;Lscala/reflect/api/TypeTags$WeakTypeTag<TT;>;Lscala/reflect/api/TypeTags$WeakTypeTag<TV;>;)Lscala/reflect/api/Trees$TreeApi;
    MethodParameters:
      Name                           Flags
      c                              final
      whitespace                     final
      min                            final
      repeater                       final
      ctx                            final
      evidence$1                     final
      evidence$2                     final
}
InnerClasses:
  public #13= #10 of #12;                 // TreeApi=class scala/reflect/api/Trees$TreeApi of class scala/reflect/api/Trees
  public #18= #15 of #17;                 // WeakTypeTag=class scala/reflect/api/TypeTags$WeakTypeTag of class scala/reflect/api/TypeTags
SourceFile: "RepImpls.scala"
RuntimeVisibleAnnotations:
  0: #6(#7=s#8)
    scala.reflect.ScalaSignature(
      bytes="\u0006\u0005\u0005Ms!\u0002\u0005\n\u0011\u0003qa!\u0002\t\n\u0011\u0003\t\u0002\"\u0002\r\u0002\t\u0003I\u0002\"\u0002\u000e\u0002\t\u0003Y\u0002\"B*\u0002\t\u0003!\u0006\"B4\u0002\t\u0003A\u0007\"B?\u0002\t\u0003q\bbBA\u0013\u0003\u0011\u0005\u0011qE\u0001\u000e\u001b\u0006\u001c\'o\u001c*fa&k\u0007\u000f\\:\u000b\u0005)Y\u0011\u0001C5oi\u0016\u0014h.\u00197\u000b\u00031\t\u0011BZ1tiB\f\'o]3\u0004\u0001A\u0011q\"A\u0007\u0002\u0013\tiQ*Y2s_J+\u0007/S7qYN\u001c\"!\u0001\n\u0011\u0005M1R\"\u0001\u000b\u000b\u0003U\tQa]2bY\u0006L!a\u0006\u000b\u0003\r\u0005s\u0017PU3g\u0003\u0019a\u0014N\\5u}Q\ta\"\u0001\u0006sKBDV*Y2s_B*2\u0001H\u001dG)\ti2\u0005F\u0002\u001f\u0019F#2a\b%K)\r\u00013G\u0011\t\u0003C=r!AI\u0012\r\u0001!)Ae\u0001a\u0001K\u0005\t1\r\u0005\u0002\'[5\tqE\u0003\u0002)S\u0005A!\r\\1dW\n|\u0007P\u0003\u0002+W\u00051Q.Y2s_NT!\u0001\f\u000b\u0002\u000fI,g\r\\3di&\u0011af\n\u0002\b\u0007>tG/\u001a=u\u0013\t\u0001\u0014G\u0001\u0003Ue\u0016,\u0017B\u0001\u001a*\u0005\u001d\tE.[1tKNDq\u0001N\u0002\u0002\u0002\u0003\u000fQ\'\u0001\u0006fm&$WM\\2fIE\u00022!\t\u001c9\u0013\t9\u0014GA\u0006XK\u0006\\G+\u001f9f)\u0006<\u0007C\u0001\u0012:\t\u0015Q4A1\u0001<\u0005\u0005!\u0016C\u0001\u001f@!\t\u0019R(\u0003\u0002?)\t9aj\u001c;iS:<\u0007CA\nA\u0013\t\tECA\u0002B]fDqaQ\u0002\u0002\u0002\u0003\u000fA)\u0001\u0006fm&$WM\\2fII\u00022!\t\u001cF!\t\u0011c\tB\u0003H\u0007\t\u00071HA\u0001W\u0011\u0015I5\u00011\u0001!\u0003!\u0011X\r]3bi\u0016\u0014\b\"B&\u0004\u0001\u0004\u0001\u0013aA2uq\")Qj\u0001a\u0001\u001d\u0006Qq\u000f[5uKN\u0004\u0018mY3\u0011\u0007My\u0005%\u0003\u0002Q)\t1q\n\u001d;j_:DQAU\u0002A\u00029\u000b1!\\5o\u0003)\u0011X\r\u001d-NC\u000e\u0014x.M\u000b\u0004+~#GC\u0001,[)\r9VM\u001a\u000b\u00041n\u0003\u0007CA-0\u001d\t\u0011#\fC\u0003%\t\u0001\u0007Q\u0005C\u0004]\t\u0005\u0005\t9A/\u0002\u0015\u00154\u0018\u000eZ3oG\u0016$3\u0007E\u0002Zmy\u0003\"AI0\u0005\u000bi\"!\u0019A\u001e\t\u000f\u0005$\u0011\u0011!a\u0002E\u0006QQM^5eK:\u001cW\r\n\u001b\u0011\u0007e34\r\u0005\u0002#I\u0012)q\t\u0002b\u0001w!)\u0011\n\u0002a\u00011\")1\n\u0002a\u00011\u0006Q!/\u001a9Y\u001b\u0006\u001c\'o\u001c\u001a\u0016\u0007%$\u0018\u0010\u0006\u0002k_R\u00111\u000e \u000b\u0004Yj\\HcA7qkB\u0011an\f\b\u0003E=DQ\u0001J\u0003A\u0002\u0015Bq!]\u0003\u0002\u0002\u0003\u000f!/\u0001\u0006fm&$WM\\2fIU\u00022A\u001c\u001ct!\t\u0011C\u000fB\u0003;\u000b\t\u00071\bC\u0004w\u000b\u0005\u0005\t9A<\u0002\u0015\u00154\u0018\u000eZ3oG\u0016$c\u0007E\u0002oma\u0004\"AI=\u0005\u000b\u001d+!\u0019A\u001e\t\u000b%+\u0001\u0019A7\t\u000b-+\u0001\u0019A7\t\u000bI+\u0001\u0019A7\u0002\u0019I,\u0007\u000fW\'bGJ|\u0017g^:\u0016\u000b}\f\u0019\"!\b\u0015\t\u0005\u0005\u0011\u0011\u0002\u000b\t\u0003\u0007\ty\"!\t\u0002$Q1\u0011QAA\u0006\u0003+\u00012!a\u00020\u001d\r\u0011\u0013\u0011\u0002\u0005\u0006I\u0019\u0001\r!\n\u0005\n\u0003\u001b1\u0011\u0011!a\u0002\u0003\u001f\t!\"\u001a<jI\u0016t7-\u001a\u00138!\u0015\t9ANA\t!\r\u0011\u00131\u0003\u0003\u0006u\u0019\u0011\ra\u000f\u0005\n\u0003/1\u0011\u0011!a\u0002\u00033\t!\"\u001a<jI\u0016t7-\u001a\u00139!\u0015\t9ANA\u000e!\r\u0011\u0013Q\u0004\u0003\u0006\u000f\u001a\u0011\ra\u000f\u0005\u0007\u0013\u001a\u0001\r!!\u0002\t\r53\u0001\u0019AA\u0003\u0011\u0019Ye\u00011\u0001\u0002\u0006\u0005a!/\u001a9Y\u001b\u0006\u001c\'o\u001c\u001axgV1\u0011\u0011FA \u0003\u0013\"B!a\u000b\u00026Q!\u0011QFA))!\ty#a\u0013\u0002N\u0005=CCBA\u0019\u0003o\t\t\u0005E\u0002\u00024=r1AIA\u001b\u0011\u0015!s\u00011\u0001&\u0011%\tIdBA\u0001\u0002\b\tY$\u0001\u0006fm&$WM\\2fIe\u0002R!a\r7\u0003{\u00012AIA \t\u0015QtA1\u0001<\u0011%\t\u0019eBA\u0001\u0002\b\t)%A\u0006fm&$WM\\2fIE\u0002\u0004#BA\u001am\u0005\u001d\u0003c\u0001\u0012\u0002J\u0011)qi\u0002b\u0001w!1\u0011j\u0002a\u0001\u0003cAa!T\u0004A\u0002\u0005E\u0002BB&\b\u0001\u0004\t\t\u0004\u0003\u0004S\u000f\u0001\u0007\u0011\u0011\u0007"
    )
  ScalaSig: length = 0x3 (unknown attribute)
   05 02 00
