Classfile /Users/mw/Projects/slang-braindump/.jar/jar11/assemble/slang-braindump/assemble/content/coursier/core/shaded/fastparse/internal/RepImpls$.class
  Last modified May 29, 2022; size 19846 bytes
  SHA-256 checksum 5ff7c408fba6d0fa8e0719e8465a43e9ddff35dbded0c8428075ad0fcf094616
  Compiled from "RepImpls.scala"
public final class coursier.core.shaded.fastparse.internal.RepImpls$
  minor version: 0
  major version: 52
  flags: (0x0031) ACC_PUBLIC, ACC_FINAL, ACC_SUPER
  this_class: #2                          // coursier/core/shaded/fastparse/internal/RepImpls$
  super_class: #4                         // java/lang/Object
  interfaces: 0, fields: 1, methods: 32, attributes: 5
Constant pool:
    #1 = Utf8               coursier/core/shaded/fastparse/internal/RepImpls$
    #2 = Class              #1            // coursier/core/shaded/fastparse/internal/RepImpls$
    #3 = Utf8               java/lang/Object
    #4 = Class              #3            // java/lang/Object
    #5 = Utf8               RepImpls.scala
    #6 = Utf8               coursier/core/shaded/fastparse/Implicits$Repeater
    #7 = Class              #6            // coursier/core/shaded/fastparse/Implicits$Repeater
    #8 = Utf8               coursier/core/shaded/fastparse/Implicits
    #9 = Class              #8            // coursier/core/shaded/fastparse/Implicits
   #10 = Utf8               Repeater
   #11 = Utf8               coursier/core/shaded/fastparse/NoWhitespace$noWhitespaceImplicit$
   #12 = Class              #11           // coursier/core/shaded/fastparse/NoWhitespace$noWhitespaceImplicit$
   #13 = Utf8               coursier/core/shaded/fastparse/NoWhitespace
   #14 = Class              #13           // coursier/core/shaded/fastparse/NoWhitespace
   #15 = Utf8
   #16 = Utf8               java/lang/invoke/MethodHandles$Lookup
   #17 = Class              #16           // java/lang/invoke/MethodHandles$Lookup
   #18 = Utf8               java/lang/invoke/MethodHandles
   #19 = Class              #18           // java/lang/invoke/MethodHandles
   #20 = Utf8               Lookup
   #21 = Utf8               MODULE$
   #22 = Utf8               Lcoursier/core/shaded/fastparse/internal/RepImpls$;
   #23 = Utf8               <clinit>
   #24 = Utf8               ()V
   #25 = Utf8               <init>
   #26 = NameAndType        #25:#24       // "<init>":()V
   #27 = Methodref          #2.#26        // coursier/core/shaded/fastparse/internal/RepImpls$."<init>":()V
   #28 = NameAndType        #21:#22       // MODULE$:Lcoursier/core/shaded/fastparse/internal/RepImpls$;
   #29 = Fieldref           #2.#28        // coursier/core/shaded/fastparse/internal/RepImpls$.MODULE$:Lcoursier/core/shaded/fastparse/internal/RepImpls$;
   #30 = Utf8               repX$extension
   #31 = Utf8               (Lscala/Function0;ILscala/Function0;IILcoursier/core/shaded/fastparse/Implicits$Repeater;Lcoursier/core/shaded/fastparse/ParsingRun;)Lcoursier/core/shaded/fastparse/ParsingRun;
   #32 = Utf8               <V:Ljava/lang/Object;T:Ljava/lang/Object;>(Lscala/Function0<Lcoursier/core/shaded/fastparse/ParsingRun<TT;>;>;ILscala/Function0<Lcoursier/core/shaded/fastparse/ParsingRun<*>;>;IILcoursier/core/shaded/fastparse/Implicits$Repeater<TT;TV;>;Lcoursier/core/shaded/fastparse/ParsingRun<Ljava/lang/Object;>;)Lcoursier/core/shaded/fastparse/ParsingRun<TV;>;
   #33 = Utf8               $this
   #34 = Utf8               min
   #35 = Utf8               sep
   #36 = Utf8               max
   #37 = Utf8               exactly
   #38 = Utf8               repeater
   #39 = Utf8               ctx
   #40 = Utf8               initial
   #41 = Utf8               ()Ljava/lang/Object;
   #42 = NameAndType        #40:#41       // initial:()Ljava/lang/Object;
   #43 = InterfaceMethodref #7.#42        // coursier/core/shaded/fastparse/Implicits$Repeater.initial:()Ljava/lang/Object;
   #44 = Utf8               coursier/core/shaded/fastparse/ParsingRun
   #45 = Class              #44           // coursier/core/shaded/fastparse/ParsingRun
   #46 = Utf8               index
   #47 = Utf8               ()I
   #48 = NameAndType        #46:#47       // index:()I
   #49 = Methodref          #45.#48       // coursier/core/shaded/fastparse/ParsingRun.index:()I
   #50 = Utf8               cut
   #51 = Utf8               ()Z
   #52 = NameAndType        #50:#51       // cut:()Z
   #53 = Methodref          #45.#52       // coursier/core/shaded/fastparse/ParsingRun.cut:()Z
   #54 = Utf8               rec$1
   #55 = Utf8               (IIZZLcoursier/core/shaded/fastparse/internal/Msgs;Lcoursier/core/shaded/fastparse/internal/Msgs;Lcoursier/core/shaded/fastparse/ParsingRun;IILcoursier/core/shaded/fastparse/Implicits$Repeater;Ljava/lang/Object;Lscala/Function0;Lscala/Function0;I)Lcoursier/core/shaded/fastparse/ParsingRun;
   #56 = NameAndType        #54:#55       // rec$1:(IIZZLcoursier/core/shaded/fastparse/internal/Msgs;Lcoursier/core/shaded/fastparse/internal/Msgs;Lcoursier/core/shaded/fastparse/ParsingRun;IILcoursier/core/shaded/fastparse/Implicits$Repeater;Ljava/lang/Object;Lscala/Function0;Lscala/Function0;I)Lcoursier/core/shaded/fastparse/ParsingRun;
   #57 = Methodref          #2.#56        // coursier/core/shaded/fastparse/internal/RepImpls$.rec$1:(IIZZLcoursier/core/shaded/fastparse/internal/Msgs;Lcoursier/core/shaded/fastparse/internal/Msgs;Lcoursier/core/shaded/fastparse/ParsingRun;IILcoursier/core/shaded/fastparse/Implicits$Repeater;Ljava/lang/Object;Lscala/Function0;Lscala/Function0;I)Lcoursier/core/shaded/fastparse/ParsingRun;
   #58 = Utf8               acc
   #59 = Utf8               Ljava/lang/Object;
   #60 = Utf8               actualMin
   #61 = Utf8               I
   #62 = Utf8               actualMax
   #63 = Utf8               this
   #64 = Utf8               Lscala/Function0;
   #65 = Utf8               Lcoursier/core/shaded/fastparse/Implicits$Repeater;
   #66 = Utf8               Lcoursier/core/shaded/fastparse/ParsingRun;
   #67 = Utf8               (Lscala/Function0;ILscala/Function0;Lcoursier/core/shaded/fastparse/Implicits$Repeater;Lcoursier/core/shaded/fastparse/ParsingRun;)Lcoursier/core/shaded/fastparse/ParsingRun;
   #68 = Utf8               <V:Ljava/lang/Object;T:Ljava/lang/Object;>(Lscala/Function0<Lcoursier/core/shaded/fastparse/ParsingRun<TT;>;>;ILscala/Function0<Lcoursier/core/shaded/fastparse/ParsingRun<*>;>;Lcoursier/core/shaded/fastparse/Implicits$Repeater<TT;TV;>;Lcoursier/core/shaded/fastparse/ParsingRun<Ljava/lang/Object;>;)Lcoursier/core/shaded/fastparse/ParsingRun<TV;>;
   #69 = Utf8               rec$2
   #70 = Utf8               (IIZZLcoursier/core/shaded/fastparse/internal/Msgs;Lcoursier/core/shaded/fastparse/internal/Msgs;Lcoursier/core/shaded/fastparse/ParsingRun;ILscala/Function0;Lcoursier/core/shaded/fastparse/Implicits$Repeater;Ljava/lang/Object;Lscala/Function0;)Lcoursier/core/shaded/fastparse/ParsingRun;
   #71 = NameAndType        #69:#70       // rec$2:(IIZZLcoursier/core/shaded/fastparse/internal/Msgs;Lcoursier/core/shaded/fastparse/internal/Msgs;Lcoursier/core/shaded/fastparse/ParsingRun;ILscala/Function0;Lcoursier/core/shaded/fastparse/Implicits$Repeater;Ljava/lang/Object;Lscala/Function0;)Lcoursier/core/shaded/fastparse/ParsingRun;
   #72 = Methodref          #2.#71        // coursier/core/shaded/fastparse/internal/RepImpls$.rec$2:(IIZZLcoursier/core/shaded/fastparse/internal/Msgs;Lcoursier/core/shaded/fastparse/internal/Msgs;Lcoursier/core/shaded/fastparse/ParsingRun;ILscala/Function0;Lcoursier/core/shaded/fastparse/Implicits$Repeater;Ljava/lang/Object;Lscala/Function0;)Lcoursier/core/shaded/fastparse/ParsingRun;
   #73 = Utf8               rep$extension
   #74 = Utf8               (Lscala/Function0;ILscala/Function0;IILcoursier/core/shaded/fastparse/Implicits$Repeater;Lscala/Function1;Lcoursier/core/shaded/fastparse/ParsingRun;)Lcoursier/core/shaded/fastparse/ParsingRun;
   #75 = Utf8               <V:Ljava/lang/Object;T:Ljava/lang/Object;>(Lscala/Function0<Lcoursier/core/shaded/fastparse/ParsingRun<TT;>;>;ILscala/Function0<Lcoursier/core/shaded/fastparse/ParsingRun<*>;>;IILcoursier/core/shaded/fastparse/Implicits$Repeater<TT;TV;>;Lscala/Function1<Lcoursier/core/shaded/fastparse/ParsingRun<*>;Lcoursier/core/shaded/fastparse/ParsingRun<Lscala/runtime/BoxedUnit;>;>;Lcoursier/core/shaded/fastparse/ParsingRun<Ljava/lang/Object;>;)Lcoursier/core/shaded/fastparse/ParsingRun<TV;>;
   #76 = Utf8               whitespace
   #77 = Utf8               rec$3
   #78 = Utf8               (IIZZLcoursier/core/shaded/fastparse/internal/Msgs;Lcoursier/core/shaded/fastparse/internal/Msgs;Lcoursier/core/shaded/fastparse/ParsingRun;IILcoursier/core/shaded/fastparse/Implicits$Repeater;Ljava/lang/Object;Lscala/Function0;Lscala/Function1;Lscala/Function0;I)Lcoursier/core/shaded/fastparse/ParsingRun;
   #79 = NameAndType        #77:#78       // rec$3:(IIZZLcoursier/core/shaded/fastparse/internal/Msgs;Lcoursier/core/shaded/fastparse/internal/Msgs;Lcoursier/core/shaded/fastparse/ParsingRun;IILcoursier/core/shaded/fastparse/Implicits$Repeater;Ljava/lang/Object;Lscala/Function0;Lscala/Function1;Lscala/Function0;I)Lcoursier/core/shaded/fastparse/ParsingRun;
   #80 = Methodref          #2.#79        // coursier/core/shaded/fastparse/internal/RepImpls$.rec$3:(IIZZLcoursier/core/shaded/fastparse/internal/Msgs;Lcoursier/core/shaded/fastparse/internal/Msgs;Lcoursier/core/shaded/fastparse/ParsingRun;IILcoursier/core/shaded/fastparse/Implicits$Repeater;Ljava/lang/Object;Lscala/Function0;Lscala/Function1;Lscala/Function0;I)Lcoursier/core/shaded/fastparse/ParsingRun;
   #81 = Utf8               Lscala/Function1;
   #82 = Utf8               (Lscala/Function0;ILscala/Function0;Lcoursier/core/shaded/fastparse/Implicits$Repeater;Lscala/Function1;Lcoursier/core/shaded/fastparse/ParsingRun;)Lcoursier/core/shaded/fastparse/ParsingRun;
   #83 = Utf8               <V:Ljava/lang/Object;T:Ljava/lang/Object;>(Lscala/Function0<Lcoursier/core/shaded/fastparse/ParsingRun<TT;>;>;ILscala/Function0<Lcoursier/core/shaded/fastparse/ParsingRun<*>;>;Lcoursier/core/shaded/fastparse/Implicits$Repeater<TT;TV;>;Lscala/Function1<Lcoursier/core/shaded/fastparse/ParsingRun<*>;Lcoursier/core/shaded/fastparse/ParsingRun<Lscala/runtime/BoxedUnit;>;>;Lcoursier/core/shaded/fastparse/ParsingRun<Ljava/lang/Object;>;)Lcoursier/core/shaded/fastparse/ParsingRun<TV;>;
   #84 = Utf8               rec$4
   #85 = Utf8               (IIZZLcoursier/core/shaded/fastparse/internal/Msgs;Lcoursier/core/shaded/fastparse/internal/Msgs;Lcoursier/core/shaded/fastparse/ParsingRun;ILscala/Function0;Lcoursier/core/shaded/fastparse/Implicits$Repeater;Ljava/lang/Object;Lscala/Function1;Lscala/Function0;)Lcoursier/core/shaded/fastparse/ParsingRun;
   #86 = NameAndType        #84:#85       // rec$4:(IIZZLcoursier/core/shaded/fastparse/internal/Msgs;Lcoursier/core/shaded/fastparse/internal/Msgs;Lcoursier/core/shaded/fastparse/ParsingRun;ILscala/Function0;Lcoursier/core/shaded/fastparse/Implicits$Repeater;Ljava/lang/Object;Lscala/Function1;Lscala/Function0;)Lcoursier/core/shaded/fastparse/ParsingRun;
   #87 = Methodref          #2.#86        // coursier/core/shaded/fastparse/internal/RepImpls$.rec$4:(IIZZLcoursier/core/shaded/fastparse/internal/Msgs;Lcoursier/core/shaded/fastparse/internal/Msgs;Lcoursier/core/shaded/fastparse/ParsingRun;ILscala/Function0;Lcoursier/core/shaded/fastparse/Implicits$Repeater;Ljava/lang/Object;Lscala/Function1;Lscala/Function0;)Lcoursier/core/shaded/fastparse/ParsingRun;
   #88 = Utf8               repX$default$1$extension
   #89 = Utf8               (Lscala/Function0;)I
   #90 = Utf8               <V:Ljava/lang/Object;T:Ljava/lang/Object;>(Lscala/Function0<Lcoursier/core/shaded/fastparse/ParsingRun<TT;>;>;)I
   #91 = Utf8               repX$default$2$extension
   #92 = Utf8               (Lscala/Function0;)Lcoursier/core/shaded/fastparse/ParsingRun;
   #93 = Utf8               <V:Ljava/lang/Object;T:Ljava/lang/Object;>(Lscala/Function0<Lcoursier/core/shaded/fastparse/ParsingRun<TT;>;>;)Lcoursier/core/shaded/fastparse/ParsingRun<*>;
   #94 = Utf8               repX$default$3$extension
   #95 = Integer            2147483647
   #96 = Utf8               repX$default$4$extension
   #97 = Utf8               rep$default$1$extension
   #98 = Utf8               rep$default$2$extension
   #99 = Utf8               rep$default$3$extension
  #100 = Utf8               rep$default$4$extension
  #101 = Utf8               aggregateMsgPostSep$extension
  #102 = Utf8               (Lscala/Function0;IILcoursier/core/shaded/fastparse/ParsingRun;Lcoursier/core/shaded/fastparse/internal/Msgs;Lcoursier/core/shaded/fastparse/internal/Msgs;)V
  #103 = Utf8               <V:Ljava/lang/Object;T:Ljava/lang/Object;>(Lscala/Function0<Lcoursier/core/shaded/fastparse/ParsingRun<TT;>;>;IILcoursier/core/shaded/fastparse/ParsingRun<Ljava/lang/Object;>;Lcoursier/core/shaded/fastparse/internal/Msgs;Lcoursier/core/shaded/fastparse/internal/Msgs;)V
  #104 = Utf8               startIndex
  #105 = Utf8               parsedMsg
  #106 = Utf8               lastAgg
  #107 = MethodType         #41           //  ()Ljava/lang/Object;
  #108 = Utf8               $anonfun$aggregateMsgPostSep$1
  #109 = Utf8               (Lcoursier/core/shaded/fastparse/internal/Msgs;I)Ljava/lang/String;
  #110 = NameAndType        #108:#109     // $anonfun$aggregateMsgPostSep$1:(Lcoursier/core/shaded/fastparse/internal/Msgs;I)Ljava/lang/String;
  #111 = Methodref          #2.#110       // coursier/core/shaded/fastparse/internal/RepImpls$.$anonfun$aggregateMsgPostSep$1:(Lcoursier/core/shaded/fastparse/internal/Msgs;I)Ljava/lang/String;
  #112 = MethodHandle       6:#111        // REF_invokeStatic coursier/core/shaded/fastparse/internal/RepImpls$.$anonfun$aggregateMsgPostSep$1:(Lcoursier/core/shaded/fastparse/internal/Msgs;I)Ljava/lang/String;
  #113 = Utf8               ()Ljava/lang/String;
  #114 = MethodType         #113          //  ()Ljava/lang/String;
  #115 = Integer            5
  #116 = Integer            1
  #117 = Utf8               java/lang/invoke/LambdaMetafactory
  #118 = Class              #117          // java/lang/invoke/LambdaMetafactory
  #119 = Utf8               altMetafactory
  #120 = Utf8               (Ljava/lang/invoke/MethodHandles$Lookup;Ljava/lang/String;Ljava/lang/invoke/MethodType;[Ljava/lang/Object;)Ljava/lang/invoke/CallSite;
  #121 = NameAndType        #119:#120     // altMetafactory:(Ljava/lang/invoke/MethodHandles$Lookup;Ljava/lang/String;Ljava/lang/invoke/MethodType;[Ljava/lang/Object;)Ljava/lang/invoke/CallSite;
  #122 = Methodref          #118.#121     // java/lang/invoke/LambdaMetafactory.altMetafactory:(Ljava/lang/invoke/MethodHandles$Lookup;Ljava/lang/String;Ljava/lang/invoke/MethodType;[Ljava/lang/Object;)Ljava/lang/invoke/CallSite;
  #123 = MethodHandle       6:#122        // REF_invokeStatic java/lang/invoke/LambdaMetafactory.altMetafactory:(Ljava/lang/invoke/MethodHandles$Lookup;Ljava/lang/String;Ljava/lang/invoke/MethodType;[Ljava/lang/Object;)Ljava/lang/invoke/CallSite;
  #124 = Utf8               apply
  #125 = Utf8               (Lcoursier/core/shaded/fastparse/internal/Msgs;I)Lscala/Function0;
  #126 = NameAndType        #124:#125     // apply:(Lcoursier/core/shaded/fastparse/internal/Msgs;I)Lscala/Function0;
  #127 = InvokeDynamic      #0:#126       // #0:apply:(Lcoursier/core/shaded/fastparse/internal/Msgs;I)Lscala/Function0;
  #128 = Utf8               failureGroupAggregate
  #129 = Utf8               ()Lcoursier/core/shaded/fastparse/internal/Msgs;
  #130 = NameAndType        #128:#129     // failureGroupAggregate:()Lcoursier/core/shaded/fastparse/internal/Msgs;
  #131 = Methodref          #45.#130      // coursier/core/shaded/fastparse/ParsingRun.failureGroupAggregate:()Lcoursier/core/shaded/fastparse/internal/Msgs;
  #132 = Utf8               coursier/core/shaded/fastparse/internal/Msgs
  #133 = Class              #132          // coursier/core/shaded/fastparse/internal/Msgs
  #134 = Utf8               $colon$colon$colon
  #135 = Utf8               (Lcoursier/core/shaded/fastparse/internal/Msgs;)Lcoursier/core/shaded/fastparse/internal/Msgs;
  #136 = NameAndType        #134:#135     // $colon$colon$colon:(Lcoursier/core/shaded/fastparse/internal/Msgs;)Lcoursier/core/shaded/fastparse/internal/Msgs;
  #137 = Methodref          #133.#136     // coursier/core/shaded/fastparse/internal/Msgs.$colon$colon$colon:(Lcoursier/core/shaded/fastparse/internal/Msgs;)Lcoursier/core/shaded/fastparse/internal/Msgs;
  #138 = Utf8               aggregateMsg
  #139 = Utf8               (ILscala/Function0;Lcoursier/core/shaded/fastparse/internal/Msgs;)V
  #140 = NameAndType        #138:#139     // aggregateMsg:(ILscala/Function0;Lcoursier/core/shaded/fastparse/internal/Msgs;)V
  #141 = Methodref          #45.#140      // coursier/core/shaded/fastparse/ParsingRun.aggregateMsg:(ILscala/Function0;Lcoursier/core/shaded/fastparse/internal/Msgs;)V
  #142 = Utf8               Lcoursier/core/shaded/fastparse/internal/Msgs;
  #143 = Utf8               aggregateMsgInRep$extension
  #144 = Utf8               (Lscala/Function0;IILcoursier/core/shaded/fastparse/ParsingRun;Lcoursier/core/shaded/fastparse/internal/Msgs;Lcoursier/core/shaded/fastparse/internal/Msgs;Lcoursier/core/shaded/fastparse/internal/Msgs;Z)V
  #145 = Utf8               <V:Ljava/lang/Object;T:Ljava/lang/Object;>(Lscala/Function0<Lcoursier/core/shaded/fastparse/ParsingRun<TT;>;>;IILcoursier/core/shaded/fastparse/ParsingRun<Ljava/lang/Object;>;Lcoursier/core/shaded/fastparse/internal/Msgs;Lcoursier/core/shaded/fastparse/internal/Msgs;Lcoursier/core/shaded/fastparse/internal/Msgs;Z)V
  #146 = Utf8               sepMsg
  #147 = Utf8               precut
  #148 = Utf8               $anonfun$aggregateMsgInRep$1
  #149 = NameAndType        #148:#109     // $anonfun$aggregateMsgInRep$1:(Lcoursier/core/shaded/fastparse/internal/Msgs;I)Ljava/lang/String;
  #150 = Methodref          #2.#149       // coursier/core/shaded/fastparse/internal/RepImpls$.$anonfun$aggregateMsgInRep$1:(Lcoursier/core/shaded/fastparse/internal/Msgs;I)Ljava/lang/String;
  #151 = MethodHandle       6:#150        // REF_invokeStatic coursier/core/shaded/fastparse/internal/RepImpls$.$anonfun$aggregateMsgInRep$1:(Lcoursier/core/shaded/fastparse/internal/Msgs;I)Ljava/lang/String;
  #152 = InvokeDynamic      #1:#126       // #1:apply:(Lcoursier/core/shaded/fastparse/internal/Msgs;I)Lscala/Function0;
  #153 = Utf8               $anonfun$aggregateMsgInRep$2
  #154 = NameAndType        #153:#109     // $anonfun$aggregateMsgInRep$2:(Lcoursier/core/shaded/fastparse/internal/Msgs;I)Ljava/lang/String;
  #155 = Methodref          #2.#154       // coursier/core/shaded/fastparse/internal/RepImpls$.$anonfun$aggregateMsgInRep$2:(Lcoursier/core/shaded/fastparse/internal/Msgs;I)Ljava/lang/String;
  #156 = MethodHandle       6:#155        // REF_invokeStatic coursier/core/shaded/fastparse/internal/RepImpls$.$anonfun$aggregateMsgInRep$2:(Lcoursier/core/shaded/fastparse/internal/Msgs;I)Ljava/lang/String;
  #157 = InvokeDynamic      #2:#126       // #2:apply:(Lcoursier/core/shaded/fastparse/internal/Msgs;I)Lscala/Function0;
  #158 = Utf8               coursier/core/shaded/fastparse/internal/Util$
  #159 = Class              #158          // coursier/core/shaded/fastparse/internal/Util$
  #160 = Utf8               Lcoursier/core/shaded/fastparse/internal/Util$;
  #161 = NameAndType        #21:#160      // MODULE$:Lcoursier/core/shaded/fastparse/internal/Util$;
  #162 = Fieldref           #159.#161     // coursier/core/shaded/fastparse/internal/Util$.MODULE$:Lcoursier/core/shaded/fastparse/internal/Util$;
  #163 = Utf8               joinBinOp
  #164 = Utf8               (Lcoursier/core/shaded/fastparse/internal/Msgs;Lcoursier/core/shaded/fastparse/internal/Msgs;)Lcoursier/core/shaded/fastparse/internal/Msgs;
  #165 = NameAndType        #163:#164     // joinBinOp:(Lcoursier/core/shaded/fastparse/internal/Msgs;Lcoursier/core/shaded/fastparse/internal/Msgs;)Lcoursier/core/shaded/fastparse/internal/Msgs;
  #166 = Methodref          #159.#165     // coursier/core/shaded/fastparse/internal/Util$.joinBinOp:(Lcoursier/core/shaded/fastparse/internal/Msgs;Lcoursier/core/shaded/fastparse/internal/Msgs;)Lcoursier/core/shaded/fastparse/internal/Msgs;
  #167 = Utf8               scala/Function0
  #168 = Class              #167          // scala/Function0
  #169 = Utf8               Z
  #170 = Utf8               hashCode$extension
  #171 = Utf8               <T:Ljava/lang/Object;>(Lscala/Function0<Lcoursier/core/shaded/fastparse/ParsingRun<TT;>;>;)I
  #172 = Utf8               hashCode
  #173 = NameAndType        #172:#47      // hashCode:()I
  #174 = Methodref          #4.#173       // java/lang/Object.hashCode:()I
  #175 = Utf8               equals$extension
  #176 = Utf8               (Lscala/Function0;Ljava/lang/Object;)Z
  #177 = Utf8               <T:Ljava/lang/Object;>(Lscala/Function0<Lcoursier/core/shaded/fastparse/ParsingRun<TT;>;>;Ljava/lang/Object;)Z
  #178 = Utf8               x$1
  #179 = Utf8               coursier/core/shaded/fastparse/internal/RepImpls
  #180 = Class              #179          // coursier/core/shaded/fastparse/internal/RepImpls
  #181 = Utf8               parse0
  #182 = Utf8               ()Lscala/Function0;
  #183 = NameAndType        #181:#182     // parse0:()Lscala/Function0;
  #184 = Methodref          #180.#183     // coursier/core/shaded/fastparse/internal/RepImpls.parse0:()Lscala/Function0;
  #185 = Utf8               equals
  #186 = Utf8               (Ljava/lang/Object;)Z
  #187 = NameAndType        #185:#186     // equals:(Ljava/lang/Object;)Z
  #188 = Methodref          #4.#187       // java/lang/Object.equals:(Ljava/lang/Object;)Z
  #189 = Utf8               end$1
  #190 = Utf8               (IIIZILcoursier/core/shaded/fastparse/ParsingRun;Lcoursier/core/shaded/fastparse/Implicits$Repeater;Ljava/lang/Object;)Lcoursier/core/shaded/fastparse/ParsingRun;
  #191 = Utf8               successIndex
  #192 = Utf8               count
  #193 = Utf8               endCut
  #194 = Utf8               actualMin$1
  #195 = Utf8               ctx$6
  #196 = Utf8               repeater$6
  #197 = Utf8               acc$1
  #198 = Utf8               augmentFailure
  #199 = Utf8               (IZ)Lcoursier/core/shaded/fastparse/ParsingRun;
  #200 = NameAndType        #198:#199     // augmentFailure:(IZ)Lcoursier/core/shaded/fastparse/ParsingRun;
  #201 = Methodref          #45.#200      // coursier/core/shaded/fastparse/ParsingRun.augmentFailure:(IZ)Lcoursier/core/shaded/fastparse/ParsingRun;
  #202 = Utf8               result
  #203 = Utf8               (Ljava/lang/Object;)Ljava/lang/Object;
  #204 = NameAndType        #202:#203     // result:(Ljava/lang/Object;)Ljava/lang/Object;
  #205 = InterfaceMethodref #7.#204       // coursier/core/shaded/fastparse/Implicits$Repeater.result:(Ljava/lang/Object;)Ljava/lang/Object;
  #206 = Utf8               freshSuccess
  #207 = Utf8               (Ljava/lang/Object;IZ)Lcoursier/core/shaded/fastparse/ParsingRun;
  #208 = NameAndType        #206:#207     // freshSuccess:(Ljava/lang/Object;IZ)Lcoursier/core/shaded/fastparse/ParsingRun;
  #209 = Methodref          #45.#208      // coursier/core/shaded/fastparse/ParsingRun.freshSuccess:(Ljava/lang/Object;IZ)Lcoursier/core/shaded/fastparse/ParsingRun;
  #210 = Utf8               $anonfun$repX$1
  #211 = Utf8               parsedMsg$1
  #212 = Utf8               min$4
  #213 = Utf8               java/lang/StringBuilder
  #214 = Class              #213          // java/lang/StringBuilder
  #215 = Utf8               (I)V
  #216 = NameAndType        #25:#215      // "<init>":(I)V
  #217 = Methodref          #214.#216     // java/lang/StringBuilder."<init>":(I)V
  #218 = Utf8               render
  #219 = NameAndType        #218:#113     // render:()Ljava/lang/String;
  #220 = Methodref          #133.#219     // coursier/core/shaded/fastparse/internal/Msgs.render:()Ljava/lang/String;
  #221 = Utf8               append
  #222 = Utf8               (Ljava/lang/String;)Ljava/lang/StringBuilder;
  #223 = NameAndType        #221:#222     // append:(Ljava/lang/String;)Ljava/lang/StringBuilder;
  #224 = Methodref          #214.#223     // java/lang/StringBuilder.append:(Ljava/lang/String;)Ljava/lang/StringBuilder;
  #225 = Utf8               .repX
  #226 = String             #225          // .repX
  #227 = String             #15           //
  #228 = Integer            2
  #229 = Utf8               (
  #230 = String             #229          // (
  #231 = Utf8               (I)Ljava/lang/StringBuilder;
  #232 = NameAndType        #221:#231     // append:(I)Ljava/lang/StringBuilder;
  #233 = Methodref          #214.#232     // java/lang/StringBuilder.append:(I)Ljava/lang/StringBuilder;
  #234 = Utf8               )
  #235 = String             #234          // )
  #236 = Utf8               toString
  #237 = NameAndType        #236:#113     // toString:()Ljava/lang/String;
  #238 = Methodref          #214.#237     // java/lang/StringBuilder.toString:()Ljava/lang/String;
  #239 = Utf8               java/lang/String
  #240 = Class              #239          // java/lang/String
  #241 = Utf8               (Ljava/lang/Object;)Ljava/lang/StringBuilder;
  #242 = NameAndType        #221:#241     // append:(Ljava/lang/Object;)Ljava/lang/StringBuilder;
  #243 = Methodref          #214.#242     // java/lang/StringBuilder.append:(Ljava/lang/Object;)Ljava/lang/StringBuilder;
  #244 = Utf8               outerCut
  #245 = Utf8               actualMax$1
  #246 = Utf8               $this$1
  #247 = Utf8               sep$1
  #248 = Utf8               cut_$eq
  #249 = Utf8               (Z)V
  #250 = NameAndType        #248:#249     // cut_$eq:(Z)V
  #251 = Methodref          #45.#250      // coursier/core/shaded/fastparse/ParsingRun.cut_$eq:(Z)V
  #252 = Utf8               (Ljava/lang/Object;I)Lcoursier/core/shaded/fastparse/ParsingRun;
  #253 = NameAndType        #206:#252     // freshSuccess:(Ljava/lang/Object;I)Lcoursier/core/shaded/fastparse/ParsingRun;
  #254 = Methodref          #45.#253      // coursier/core/shaded/fastparse/ParsingRun.freshSuccess:(Ljava/lang/Object;I)Lcoursier/core/shaded/fastparse/ParsingRun;
  #255 = Utf8               verboseFailures
  #256 = NameAndType        #255:#51      // verboseFailures:()Z
  #257 = Methodref          #45.#256      // coursier/core/shaded/fastparse/ParsingRun.verboseFailures:()Z
  #258 = NameAndType        #124:#41      // apply:()Ljava/lang/Object;
  #259 = InterfaceMethodref #168.#258     // scala/Function0.apply:()Ljava/lang/Object;
  #260 = Utf8               shortParserMsg
  #261 = NameAndType        #260:#129     // shortParserMsg:()Lcoursier/core/shaded/fastparse/internal/Msgs;
  #262 = Methodref          #45.#261      // coursier/core/shaded/fastparse/ParsingRun.shortParserMsg:()Lcoursier/core/shaded/fastparse/internal/Msgs;
  #263 = Utf8               isSuccess
  #264 = NameAndType        #263:#51      // isSuccess:()Z
  #265 = Methodref          #45.#264      // coursier/core/shaded/fastparse/ParsingRun.isSuccess:()Z
  #266 = NameAndType        #189:#190     // end$1:(IIIZILcoursier/core/shaded/fastparse/ParsingRun;Lcoursier/core/shaded/fastparse/Implicits$Repeater;Ljava/lang/Object;)Lcoursier/core/shaded/fastparse/ParsingRun;
  #267 = Methodref          #2.#266       // coursier/core/shaded/fastparse/internal/RepImpls$.end$1:(IIIZILcoursier/core/shaded/fastparse/ParsingRun;Lcoursier/core/shaded/fastparse/Implicits$Repeater;Ljava/lang/Object;)Lcoursier/core/shaded/fastparse/ParsingRun;
  #268 = NameAndType        #143:#144     // aggregateMsgInRep$extension:(Lscala/Function0;IILcoursier/core/shaded/fastparse/ParsingRun;Lcoursier/core/shaded/fastparse/internal/Msgs;Lcoursier/core/shaded/fastparse/internal/Msgs;Lcoursier/core/shaded/fastparse/internal/Msgs;Z)V
  #269 = Methodref          #2.#268       // coursier/core/shaded/fastparse/internal/RepImpls$.aggregateMsgInRep$extension:(Lscala/Function0;IILcoursier/core/shaded/fastparse/ParsingRun;Lcoursier/core/shaded/fastparse/internal/Msgs;Lcoursier/core/shaded/fastparse/internal/Msgs;Lcoursier/core/shaded/fastparse/internal/Msgs;Z)V
  #270 = Utf8               successValue
  #271 = NameAndType        #270:#41      // successValue:()Ljava/lang/Object;
  #272 = Methodref          #45.#271      // coursier/core/shaded/fastparse/ParsingRun.successValue:()Ljava/lang/Object;
  #273 = Utf8               accumulate
  #274 = Utf8               (Ljava/lang/Object;Ljava/lang/Object;)V
  #275 = NameAndType        #273:#274     // accumulate:(Ljava/lang/Object;Ljava/lang/Object;)V
  #276 = InterfaceMethodref #7.#275       // coursier/core/shaded/fastparse/Implicits$Repeater.accumulate:(Ljava/lang/Object;Ljava/lang/Object;)V
  #277 = NameAndType        #210:#109     // $anonfun$repX$1:(Lcoursier/core/shaded/fastparse/internal/Msgs;I)Ljava/lang/String;
  #278 = Methodref          #2.#277       // coursier/core/shaded/fastparse/internal/RepImpls$.$anonfun$repX$1:(Lcoursier/core/shaded/fastparse/internal/Msgs;I)Ljava/lang/String;
  #279 = MethodHandle       6:#278        // REF_invokeStatic coursier/core/shaded/fastparse/internal/RepImpls$.$anonfun$repX$1:(Lcoursier/core/shaded/fastparse/internal/Msgs;I)Ljava/lang/String;
  #280 = InvokeDynamic      #3:#126       // #3:apply:(Lcoursier/core/shaded/fastparse/internal/Msgs;I)Lscala/Function0;
  #281 = Utf8               setMsg
  #282 = Utf8               (ILscala/Function0;)V
  #283 = NameAndType        #281:#282     // setMsg:(ILscala/Function0;)V
  #284 = Methodref          #45.#283      // coursier/core/shaded/fastparse/ParsingRun.setMsg:(ILscala/Function0;)V
  #285 = NameAndType        #101:#102     // aggregateMsgPostSep$extension:(Lscala/Function0;IILcoursier/core/shaded/fastparse/ParsingRun;Lcoursier/core/shaded/fastparse/internal/Msgs;Lcoursier/core/shaded/fastparse/internal/Msgs;)V
  #286 = Methodref          #2.#285       // coursier/core/shaded/fastparse/internal/RepImpls$.aggregateMsgPostSep$extension:(Lscala/Function0;IILcoursier/core/shaded/fastparse/ParsingRun;Lcoursier/core/shaded/fastparse/internal/Msgs;Lcoursier/core/shaded/fastparse/internal/Msgs;)V
  #287 = Utf8               res
  #288 = Utf8               sep1
  #289 = Utf8               sepCut
  #290 = Utf8               beforeSepIndex
  #291 = Utf8               nextCount
  #292 = Utf8               parsedAgg
  #293 = Utf8               postCut
  #294 = Utf8               end$2
  #295 = Utf8               min$5
  #296 = Utf8               ctx$7
  #297 = Utf8               repeater$7
  #298 = Utf8               acc$2
  #299 = Utf8               $this$2
  #300 = Utf8               sep$2
  #301 = NameAndType        #294:#190     // end$2:(IIIZILcoursier/core/shaded/fastparse/ParsingRun;Lcoursier/core/shaded/fastparse/Implicits$Repeater;Ljava/lang/Object;)Lcoursier/core/shaded/fastparse/ParsingRun;
  #302 = Methodref          #2.#301       // coursier/core/shaded/fastparse/internal/RepImpls$.end$2:(IIIZILcoursier/core/shaded/fastparse/ParsingRun;Lcoursier/core/shaded/fastparse/Implicits$Repeater;Ljava/lang/Object;)Lcoursier/core/shaded/fastparse/ParsingRun;
  #303 = Utf8               end$3
  #304 = Utf8               actualMin$2
  #305 = Utf8               ctx$8
  #306 = Utf8               repeater$8
  #307 = Utf8               acc$3
  #308 = Utf8               $anonfun$rep$1
  #309 = Utf8               parsedMsg$2
  #310 = Utf8               min$6
  #311 = Integer            4
  #312 = Utf8               .rep
  #313 = String             #312          // .rep
  #314 = Utf8               actualMax$2
  #315 = Utf8               $this$3
  #316 = Utf8               whitespace$4
  #317 = Utf8               sep$3
  #318 = Utf8               scala/Function1
  #319 = Class              #318          // scala/Function1
  #320 = NameAndType        #303:#190     // end$3:(IIIZILcoursier/core/shaded/fastparse/ParsingRun;Lcoursier/core/shaded/fastparse/Implicits$Repeater;Ljava/lang/Object;)Lcoursier/core/shaded/fastparse/ParsingRun;
  #321 = Methodref          #2.#320       // coursier/core/shaded/fastparse/internal/RepImpls$.end$3:(IIIZILcoursier/core/shaded/fastparse/ParsingRun;Lcoursier/core/shaded/fastparse/Implicits$Repeater;Ljava/lang/Object;)Lcoursier/core/shaded/fastparse/ParsingRun;
  #322 = NameAndType        #308:#109     // $anonfun$rep$1:(Lcoursier/core/shaded/fastparse/internal/Msgs;I)Ljava/lang/String;
  #323 = Methodref          #2.#322       // coursier/core/shaded/fastparse/internal/RepImpls$.$anonfun$rep$1:(Lcoursier/core/shaded/fastparse/internal/Msgs;I)Ljava/lang/String;
  #324 = MethodHandle       6:#323        // REF_invokeStatic coursier/core/shaded/fastparse/internal/RepImpls$.$anonfun$rep$1:(Lcoursier/core/shaded/fastparse/internal/Msgs;I)Ljava/lang/String;
  #325 = InvokeDynamic      #4:#126       // #4:apply:(Lcoursier/core/shaded/fastparse/internal/Msgs;I)Lscala/Function0;
  #326 = Utf8               Lcoursier/core/shaded/fastparse/NoWhitespace$noWhitespaceImplicit$;
  #327 = NameAndType        #21:#326      // MODULE$:Lcoursier/core/shaded/fastparse/NoWhitespace$noWhitespaceImplicit$;
  #328 = Fieldref           #12.#327      // coursier/core/shaded/fastparse/NoWhitespace$noWhitespaceImplicit$.MODULE$:Lcoursier/core/shaded/fastparse/NoWhitespace$noWhitespaceImplicit$;
  #329 = Utf8               consumeWhitespace
  #330 = Utf8               (Lscala/Function1;Lcoursier/core/shaded/fastparse/ParsingRun;)V
  #331 = NameAndType        #329:#330     // consumeWhitespace:(Lscala/Function1;Lcoursier/core/shaded/fastparse/ParsingRun;)V
  #332 = Methodref          #159.#331     // coursier/core/shaded/fastparse/internal/Util$.consumeWhitespace:(Lscala/Function1;Lcoursier/core/shaded/fastparse/ParsingRun;)V
  #333 = Utf8               end$4
  #334 = Utf8               min$7
  #335 = Utf8               ctx$9
  #336 = Utf8               repeater$9
  #337 = Utf8               acc$4
  #338 = Utf8               $this$4
  #339 = Utf8               whitespace$5
  #340 = Utf8               sep$4
  #341 = NameAndType        #333:#190     // end$4:(IIIZILcoursier/core/shaded/fastparse/ParsingRun;Lcoursier/core/shaded/fastparse/Implicits$Repeater;Ljava/lang/Object;)Lcoursier/core/shaded/fastparse/ParsingRun;
  #342 = Methodref          #2.#341       // coursier/core/shaded/fastparse/internal/RepImpls$.end$4:(IIIZILcoursier/core/shaded/fastparse/ParsingRun;Lcoursier/core/shaded/fastparse/Implicits$Repeater;Ljava/lang/Object;)Lcoursier/core/shaded/fastparse/ParsingRun;
  #343 = Utf8               parsedMsg$3
  #344 = Utf8               min$8
  #345 = Integer            0
  #346 = Integer            6
  #347 = Utf8               .rep(
  #348 = String             #347          // .rep(
  #349 = Utf8               parsedMsg$4
  #350 = Utf8               min$9
  #351 = Methodref          #4.#26        // java/lang/Object."<init>":()V
  #352 = Utf8               $deserializeLambda$
  #353 = Utf8               (Ljava/lang/invoke/SerializedLambda;)Ljava/lang/Object;
  #354 = Utf8               scala/runtime/LambdaDeserialize
  #355 = Class              #354          // scala/runtime/LambdaDeserialize
  #356 = Utf8               bootstrap
  #357 = Utf8               (Ljava/lang/invoke/MethodHandles$Lookup;Ljava/lang/String;Ljava/lang/invoke/MethodType;[Ljava/lang/invoke/MethodHandle;)Ljava/lang/invoke/CallSite;
  #358 = NameAndType        #356:#357     // bootstrap:(Ljava/lang/invoke/MethodHandles$Lookup;Ljava/lang/String;Ljava/lang/invoke/MethodType;[Ljava/lang/invoke/MethodHandle;)Ljava/lang/invoke/CallSite;
  #359 = Methodref          #355.#358     // scala/runtime/LambdaDeserialize.bootstrap:(Ljava/lang/invoke/MethodHandles$Lookup;Ljava/lang/String;Ljava/lang/invoke/MethodType;[Ljava/lang/invoke/MethodHandle;)Ljava/lang/invoke/CallSite;
  #360 = MethodHandle       6:#359        // REF_invokeStatic scala/runtime/LambdaDeserialize.bootstrap:(Ljava/lang/invoke/MethodHandles$Lookup;Ljava/lang/String;Ljava/lang/invoke/MethodType;[Ljava/lang/invoke/MethodHandle;)Ljava/lang/invoke/CallSite;
  #361 = Utf8               lambdaDeserialize
  #362 = NameAndType        #361:#353     // lambdaDeserialize:(Ljava/lang/invoke/SerializedLambda;)Ljava/lang/Object;
  #363 = InvokeDynamic      #5:#362       // #5:lambdaDeserialize:(Ljava/lang/invoke/SerializedLambda;)Ljava/lang/Object;
  #364 = Utf8               Code
  #365 = Utf8               LineNumberTable
  #366 = Utf8               StackMapTable
  #367 = Utf8               LocalVariableTable
  #368 = Utf8               Signature
  #369 = Utf8               MethodParameters
  #370 = Utf8               InnerClasses
  #371 = Utf8               SourceFile
  #372 = Utf8               BootstrapMethods
  #373 = Utf8               ScalaInlineInfo
  #374 = Utf8               Scala
{
  public static final coursier.core.shaded.fastparse.internal.RepImpls$ MODULE$;
    descriptor: Lcoursier/core/shaded/fastparse/internal/RepImpls$;
    flags: (0x0019) ACC_PUBLIC, ACC_STATIC, ACC_FINAL

  public static {};
    descriptor: ()V
    flags: (0x0009) ACC_PUBLIC, ACC_STATIC
    Code:
      stack=2, locals=0, args_size=0
         0: new           #2                  // class coursier/core/shaded/fastparse/internal/RepImpls$
         3: dup
         4: invokespecial #27                 // Method "<init>":()V
         7: putstatic     #29                 // Field MODULE$:Lcoursier/core/shaded/fastparse/internal/RepImpls$;
        10: return
      LineNumberTable:
        line 142: 0

  public final <V extends java.lang.Object, T extends java.lang.Object> coursier.core.shaded.fastparse.ParsingRun<V> repX$extension(scala.Function0<coursier.core.shaded.fastparse.ParsingRun<T>>, int, scala.Function0<coursier.core.shaded.fastparse.ParsingRun<?>>, int, int, coursier.core.shaded.fastparse.Implicits$Repeater<T, V>, coursier.core.shaded.fastparse.ParsingRun<java.lang.Object>);
    descriptor: (Lscala/Function0;ILscala/Function0;IILcoursier/core/shaded/fastparse/Implicits$Repeater;Lcoursier/core/shaded/fastparse/ParsingRun;)Lcoursier/core/shaded/fastparse/ParsingRun;
    flags: (0x0011) ACC_PUBLIC, ACC_FINAL
    Code:
      stack=15, locals=11, args_size=8
         0: aload         6
         2: invokeinterface #43,  1           // InterfaceMethod coursier/core/shaded/fastparse/Implicits$Repeater.initial:()Ljava/lang/Object;
         7: astore        8
         9: iload         5
        11: iconst_m1
        12: if_icmpne     19
        15: iload_2
        16: goto          21
        19: iload         5
        21: istore        9
        23: iload         5
        25: iconst_m1
        26: if_icmpne     34
        29: iload         4
        31: goto          36
        34: iload         5
        36: istore        10
        38: aload_0
        39: aload         7
        41: invokevirtual #49                 // Method coursier/core/shaded/fastparse/ParsingRun.index:()I
        44: iconst_0
        45: iconst_0
        46: aload         7
        48: invokevirtual #53                 // Method coursier/core/shaded/fastparse/ParsingRun.cut:()Z
        51: aconst_null
        52: aconst_null
        53: aload         7
        55: iload_2
        56: iload         10
        58: aload         6
        60: aload         8
        62: aload_1
        63: aload_3
        64: iload         9
        66: invokespecial #57                 // Method rec$1:(IIZZLcoursier/core/shaded/fastparse/internal/Msgs;Lcoursier/core/shaded/fastparse/internal/Msgs;Lcoursier/core/shaded/fastparse/ParsingRun;IILcoursier/core/shaded/fastparse/Implicits$Repeater;Ljava/lang/Object;Lscala/Function0;Lscala/Function0;I)Lcoursier/core/shaded/fastparse/ParsingRun;
        69: areturn
      StackMapTable: number_of_entries = 4
        frame_type = 252 /* append */
          offset_delta = 19
          locals = [ class java/lang/Object ]
        frame_type = 65 /* same_locals_1_stack_item */
          stack = [ int ]
        frame_type = 252 /* append */
          offset_delta = 12
          locals = [ int ]
        frame_type = 65 /* same_locals_1_stack_item */
          stack = [ int ]
      LineNumberTable:
        line 150: 0
        line 151: 9
        line 152: 23
        line 208: 38
      LocalVariableTable:
        Start  Length  Slot  Name   Signature
            7      62     8   acc   Ljava/lang/Object;
           21      48     9 actualMin   I
           36      33    10 actualMax   I
            0      70     0  this   Lcoursier/core/shaded/fastparse/internal/RepImpls$;
            0      70     1 $this   Lscala/Function0;
            0      70     2   min   I
            0      70     3   sep   Lscala/Function0;
            0      70     4   max   I
            0      70     5 exactly   I
            0      70     6 repeater   Lcoursier/core/shaded/fastparse/Implicits$Repeater;
            0      70     7   ctx   Lcoursier/core/shaded/fastparse/ParsingRun;
    Signature: #32                          // <V:Ljava/lang/Object;T:Ljava/lang/Object;>(Lscala/Function0<Lcoursier/core/shaded/fastparse/ParsingRun<TT;>;>;ILscala/Function0<Lcoursier/core/shaded/fastparse/ParsingRun<*>;>;IILcoursier/core/shaded/fastparse/Implicits$Repeater<TT;TV;>;Lcoursier/core/shaded/fastparse/ParsingRun<Ljava/lang/Object;>;)Lcoursier/core/shaded/fastparse/ParsingRun<TV;>;
    MethodParameters:
      Name                           Flags
      $this                          final
      min                            final
      sep                            final
      max                            final
      exactly                        final
      repeater                       final
      ctx                            final

  public final <V extends java.lang.Object, T extends java.lang.Object> coursier.core.shaded.fastparse.ParsingRun<V> repX$extension(scala.Function0<coursier.core.shaded.fastparse.ParsingRun<T>>, int, scala.Function0<coursier.core.shaded.fastparse.ParsingRun<?>>, coursier.core.shaded.fastparse.Implicits$Repeater<T, V>, coursier.core.shaded.fastparse.ParsingRun<java.lang.Object>);
    descriptor: (Lscala/Function0;ILscala/Function0;Lcoursier/core/shaded/fastparse/Implicits$Repeater;Lcoursier/core/shaded/fastparse/ParsingRun;)Lcoursier/core/shaded/fastparse/ParsingRun;
    flags: (0x0011) ACC_PUBLIC, ACC_FINAL
    Code:
      stack=13, locals=7, args_size=6
         0: aload         4
         2: invokeinterface #43,  1           // InterfaceMethod coursier/core/shaded/fastparse/Implicits$Repeater.initial:()Ljava/lang/Object;
         7: astore        6
         9: aload_0
        10: aload         5
        12: invokevirtual #49                 // Method coursier/core/shaded/fastparse/ParsingRun.index:()I
        15: iconst_0
        16: iconst_0
        17: aload         5
        19: invokevirtual #53                 // Method coursier/core/shaded/fastparse/ParsingRun.cut:()Z
        22: aconst_null
        23: aconst_null
        24: aload         5
        26: iload_2
        27: aload_1
        28: aload         4
        30: aload         6
        32: aload_3
        33: invokespecial #72                 // Method rec$2:(IIZZLcoursier/core/shaded/fastparse/internal/Msgs;Lcoursier/core/shaded/fastparse/internal/Msgs;Lcoursier/core/shaded/fastparse/ParsingRun;ILscala/Function0;Lcoursier/core/shaded/fastparse/Implicits$Repeater;Ljava/lang/Object;Lscala/Function0;)Lcoursier/core/shaded/fastparse/ParsingRun;
        36: areturn
      LineNumberTable:
        line 216: 0
        line 261: 9
      LocalVariableTable:
        Start  Length  Slot  Name   Signature
            7      29     6   acc   Ljava/lang/Object;
            0      37     0  this   Lcoursier/core/shaded/fastparse/internal/RepImpls$;
            0      37     1 $this   Lscala/Function0;
            0      37     2   min   I
            0      37     3   sep   Lscala/Function0;
            0      37     4 repeater   Lcoursier/core/shaded/fastparse/Implicits$Repeater;
            0      37     5   ctx   Lcoursier/core/shaded/fastparse/ParsingRun;
    Signature: #68                          // <V:Ljava/lang/Object;T:Ljava/lang/Object;>(Lscala/Function0<Lcoursier/core/shaded/fastparse/ParsingRun<TT;>;>;ILscala/Function0<Lcoursier/core/shaded/fastparse/ParsingRun<*>;>;Lcoursier/core/shaded/fastparse/Implicits$Repeater<TT;TV;>;Lcoursier/core/shaded/fastparse/ParsingRun<Ljava/lang/Object;>;)Lcoursier/core/shaded/fastparse/ParsingRun<TV;>;
    MethodParameters:
      Name                           Flags
      $this                          final
      min                            final
      sep                            final
      repeater                       final
      ctx                            final

  public final <V extends java.lang.Object, T extends java.lang.Object> coursier.core.shaded.fastparse.ParsingRun<V> rep$extension(scala.Function0<coursier.core.shaded.fastparse.ParsingRun<T>>, int, scala.Function0<coursier.core.shaded.fastparse.ParsingRun<?>>, int, int, coursier.core.shaded.fastparse.Implicits$Repeater<T, V>, scala.Function1<coursier.core.shaded.fastparse.ParsingRun<?>, coursier.core.shaded.fastparse.ParsingRun<scala.runtime.BoxedUnit>>, coursier.core.shaded.fastparse.ParsingRun<java.lang.Object>);
    descriptor: (Lscala/Function0;ILscala/Function0;IILcoursier/core/shaded/fastparse/Implicits$Repeater;Lscala/Function1;Lcoursier/core/shaded/fastparse/ParsingRun;)Lcoursier/core/shaded/fastparse/ParsingRun;
    flags: (0x0011) ACC_PUBLIC, ACC_FINAL
    Code:
      stack=16, locals=12, args_size=9
         0: aload         6
         2: invokeinterface #43,  1           // InterfaceMethod coursier/core/shaded/fastparse/Implicits$Repeater.initial:()Ljava/lang/Object;
         7: astore        9
         9: iload         5
        11: iconst_m1
        12: if_icmpne     19
        15: iload_2
        16: goto          21
        19: iload         5
        21: istore        10
        23: iload         5
        25: iconst_m1
        26: if_icmpne     34
        29: iload         4
        31: goto          36
        34: iload         5
        36: istore        11
        38: aload_0
        39: aload         8
        41: invokevirtual #49                 // Method coursier/core/shaded/fastparse/ParsingRun.index:()I
        44: iconst_0
        45: iconst_0
        46: aload         8
        48: invokevirtual #53                 // Method coursier/core/shaded/fastparse/ParsingRun.cut:()Z
        51: aconst_null
        52: aconst_null
        53: aload         8
        55: iload_2
        56: iload         11
        58: aload         6
        60: aload         9
        62: aload_1
        63: aload         7
        65: aload_3
        66: iload         10
        68: invokespecial #80                 // Method rec$3:(IIZZLcoursier/core/shaded/fastparse/internal/Msgs;Lcoursier/core/shaded/fastparse/internal/Msgs;Lcoursier/core/shaded/fastparse/ParsingRun;IILcoursier/core/shaded/fastparse/Implicits$Repeater;Ljava/lang/Object;Lscala/Function0;Lscala/Function1;Lscala/Function0;I)Lcoursier/core/shaded/fastparse/ParsingRun;
        71: areturn
      StackMapTable: number_of_entries = 4
        frame_type = 252 /* append */
          offset_delta = 19
          locals = [ class java/lang/Object ]
        frame_type = 65 /* same_locals_1_stack_item */
          stack = [ int ]
        frame_type = 252 /* append */
          offset_delta = 12
          locals = [ int ]
        frame_type = 65 /* same_locals_1_stack_item */
          stack = [ int ]
      LineNumberTable:
        line 271: 0
        line 272: 9
        line 273: 23
        line 336: 38
      LocalVariableTable:
        Start  Length  Slot  Name   Signature
            7      64     9   acc   Ljava/lang/Object;
           21      50    10 actualMin   I
           36      35    11 actualMax   I
            0      72     0  this   Lcoursier/core/shaded/fastparse/internal/RepImpls$;
            0      72     1 $this   Lscala/Function0;
            0      72     2   min   I
            0      72     3   sep   Lscala/Function0;
            0      72     4   max   I
            0      72     5 exactly   I
            0      72     6 repeater   Lcoursier/core/shaded/fastparse/Implicits$Repeater;
            0      72     7 whitespace   Lscala/Function1;
            0      72     8   ctx   Lcoursier/core/shaded/fastparse/ParsingRun;
    Signature: #75                          // <V:Ljava/lang/Object;T:Ljava/lang/Object;>(Lscala/Function0<Lcoursier/core/shaded/fastparse/ParsingRun<TT;>;>;ILscala/Function0<Lcoursier/core/shaded/fastparse/ParsingRun<*>;>;IILcoursier/core/shaded/fastparse/Implicits$Repeater<TT;TV;>;Lscala/Function1<Lcoursier/core/shaded/fastparse/ParsingRun<*>;Lcoursier/core/shaded/fastparse/ParsingRun<Lscala/runtime/BoxedUnit;>;>;Lcoursier/core/shaded/fastparse/ParsingRun<Ljava/lang/Object;>;)Lcoursier/core/shaded/fastparse/ParsingRun<TV;>;
    MethodParameters:
      Name                           Flags
      $this                          final
      min                            final
      sep                            final
      max                            final
      exactly                        final
      repeater                       final
      whitespace                     final
      ctx                            final

  public final <V extends java.lang.Object, T extends java.lang.Object> coursier.core.shaded.fastparse.ParsingRun<V> rep$extension(scala.Function0<coursier.core.shaded.fastparse.ParsingRun<T>>, int, scala.Function0<coursier.core.shaded.fastparse.ParsingRun<?>>, coursier.core.shaded.fastparse.Implicits$Repeater<T, V>, scala.Function1<coursier.core.shaded.fastparse.ParsingRun<?>, coursier.core.shaded.fastparse.ParsingRun<scala.runtime.BoxedUnit>>, coursier.core.shaded.fastparse.ParsingRun<java.lang.Object>);
    descriptor: (Lscala/Function0;ILscala/Function0;Lcoursier/core/shaded/fastparse/Implicits$Repeater;Lscala/Function1;Lcoursier/core/shaded/fastparse/ParsingRun;)Lcoursier/core/shaded/fastparse/ParsingRun;
    flags: (0x0011) ACC_PUBLIC, ACC_FINAL
    Code:
      stack=14, locals=8, args_size=7
         0: aload         4
         2: invokeinterface #43,  1           // InterfaceMethod coursier/core/shaded/fastparse/Implicits$Repeater.initial:()Ljava/lang/Object;
         7: astore        7
         9: aload_0
        10: aload         6
        12: invokevirtual #49                 // Method coursier/core/shaded/fastparse/ParsingRun.index:()I
        15: iconst_0
        16: iconst_0
        17: aload         6
        19: invokevirtual #53                 // Method coursier/core/shaded/fastparse/ParsingRun.cut:()Z
        22: aconst_null
        23: aconst_null
        24: aload         6
        26: iload_2
        27: aload_1
        28: aload         4
        30: aload         7
        32: aload         5
        34: aload_3
        35: invokespecial #87                 // Method rec$4:(IIZZLcoursier/core/shaded/fastparse/internal/Msgs;Lcoursier/core/shaded/fastparse/internal/Msgs;Lcoursier/core/shaded/fastparse/ParsingRun;ILscala/Function0;Lcoursier/core/shaded/fastparse/Implicits$Repeater;Ljava/lang/Object;Lscala/Function1;Lscala/Function0;)Lcoursier/core/shaded/fastparse/ParsingRun;
        38: areturn
      LineNumberTable:
        line 344: 0
        line 398: 9
      LocalVariableTable:
        Start  Length  Slot  Name   Signature
            7      31     7   acc   Ljava/lang/Object;
            0      39     0  this   Lcoursier/core/shaded/fastparse/internal/RepImpls$;
            0      39     1 $this   Lscala/Function0;
            0      39     2   min   I
            0      39     3   sep   Lscala/Function0;
            0      39     4 repeater   Lcoursier/core/shaded/fastparse/Implicits$Repeater;
            0      39     5 whitespace   Lscala/Function1;
            0      39     6   ctx   Lcoursier/core/shaded/fastparse/ParsingRun;
    Signature: #83                          // <V:Ljava/lang/Object;T:Ljava/lang/Object;>(Lscala/Function0<Lcoursier/core/shaded/fastparse/ParsingRun<TT;>;>;ILscala/Function0<Lcoursier/core/shaded/fastparse/ParsingRun<*>;>;Lcoursier/core/shaded/fastparse/Implicits$Repeater<TT;TV;>;Lscala/Function1<Lcoursier/core/shaded/fastparse/ParsingRun<*>;Lcoursier/core/shaded/fastparse/ParsingRun<Lscala/runtime/BoxedUnit;>;>;Lcoursier/core/shaded/fastparse/ParsingRun<Ljava/lang/Object;>;)Lcoursier/core/shaded/fastparse/ParsingRun<TV;>;
    MethodParameters:
      Name                           Flags
      $this                          final
      min                            final
      sep                            final
      repeater                       final
      whitespace                     final
      ctx                            final

  public final <V extends java.lang.Object, T extends java.lang.Object> int repX$default$1$extension(scala.Function0<coursier.core.shaded.fastparse.ParsingRun<T>>);
    descriptor: (Lscala/Function0;)I
    flags: (0x0011) ACC_PUBLIC, ACC_FINAL
    Code:
      stack=1, locals=2, args_size=2
         0: iconst_0
         1: ireturn
      LineNumberTable:
        line 143: 0
      LocalVariableTable:
        Start  Length  Slot  Name   Signature
            0       2     0  this   Lcoursier/core/shaded/fastparse/internal/RepImpls$;
            0       2     1 $this   Lscala/Function0;
    Signature: #90                          // <V:Ljava/lang/Object;T:Ljava/lang/Object;>(Lscala/Function0<Lcoursier/core/shaded/fastparse/ParsingRun<TT;>;>;)I
    MethodParameters:
      Name                           Flags
      $this                          final

  public final <V extends java.lang.Object, T extends java.lang.Object> coursier.core.shaded.fastparse.ParsingRun<?> repX$default$2$extension(scala.Function0<coursier.core.shaded.fastparse.ParsingRun<T>>);
    descriptor: (Lscala/Function0;)Lcoursier/core/shaded/fastparse/ParsingRun;
    flags: (0x0011) ACC_PUBLIC, ACC_FINAL
    Code:
      stack=1, locals=2, args_size=2
         0: aconst_null
         1: areturn
      LineNumberTable:
        line 144: 0
      LocalVariableTable:
        Start  Length  Slot  Name   Signature
            0       2     0  this   Lcoursier/core/shaded/fastparse/internal/RepImpls$;
            0       2     1 $this   Lscala/Function0;
    Signature: #93                          // <V:Ljava/lang/Object;T:Ljava/lang/Object;>(Lscala/Function0<Lcoursier/core/shaded/fastparse/ParsingRun<TT;>;>;)Lcoursier/core/shaded/fastparse/ParsingRun<*>;
    MethodParameters:
      Name                           Flags
      $this                          final

  public final <V extends java.lang.Object, T extends java.lang.Object> int repX$default$3$extension(scala.Function0<coursier.core.shaded.fastparse.ParsingRun<T>>);
    descriptor: (Lscala/Function0;)I
    flags: (0x0011) ACC_PUBLIC, ACC_FINAL
    Code:
      stack=1, locals=2, args_size=2
         0: ldc           #95                 // int 2147483647
         2: ireturn
      LineNumberTable:
        line 145: 0
      LocalVariableTable:
        Start  Length  Slot  Name   Signature
            0       3     0  this   Lcoursier/core/shaded/fastparse/internal/RepImpls$;
            0       3     1 $this   Lscala/Function0;
    Signature: #90                          // <V:Ljava/lang/Object;T:Ljava/lang/Object;>(Lscala/Function0<Lcoursier/core/shaded/fastparse/ParsingRun<TT;>;>;)I
    MethodParameters:
      Name                           Flags
      $this                          final

  public final <V extends java.lang.Object, T extends java.lang.Object> int repX$default$4$extension(scala.Function0<coursier.core.shaded.fastparse.ParsingRun<T>>);
    descriptor: (Lscala/Function0;)I
    flags: (0x0011) ACC_PUBLIC, ACC_FINAL
    Code:
      stack=1, locals=2, args_size=2
         0: iconst_m1
         1: ireturn
      LineNumberTable:
        line 146: 0
      LocalVariableTable:
        Start  Length  Slot  Name   Signature
            0       2     0  this   Lcoursier/core/shaded/fastparse/internal/RepImpls$;
            0       2     1 $this   Lscala/Function0;
    Signature: #90                          // <V:Ljava/lang/Object;T:Ljava/lang/Object;>(Lscala/Function0<Lcoursier/core/shaded/fastparse/ParsingRun<TT;>;>;)I
    MethodParameters:
      Name                           Flags
      $this                          final

  public final <V extends java.lang.Object, T extends java.lang.Object> int rep$default$1$extension(scala.Function0<coursier.core.shaded.fastparse.ParsingRun<T>>);
    descriptor: (Lscala/Function0;)I
    flags: (0x0011) ACC_PUBLIC, ACC_FINAL
    Code:
      stack=1, locals=2, args_size=2
         0: iconst_0
         1: ireturn
      LineNumberTable:
        line 263: 0
      LocalVariableTable:
        Start  Length  Slot  Name   Signature
            0       2     0  this   Lcoursier/core/shaded/fastparse/internal/RepImpls$;
            0       2     1 $this   Lscala/Function0;
    Signature: #90                          // <V:Ljava/lang/Object;T:Ljava/lang/Object;>(Lscala/Function0<Lcoursier/core/shaded/fastparse/ParsingRun<TT;>;>;)I
    MethodParameters:
      Name                           Flags
      $this                          final

  public final <V extends java.lang.Object, T extends java.lang.Object> coursier.core.shaded.fastparse.ParsingRun<?> rep$default$2$extension(scala.Function0<coursier.core.shaded.fastparse.ParsingRun<T>>);
    descriptor: (Lscala/Function0;)Lcoursier/core/shaded/fastparse/ParsingRun;
    flags: (0x0011) ACC_PUBLIC, ACC_FINAL
    Code:
      stack=1, locals=2, args_size=2
         0: aconst_null
         1: areturn
      LineNumberTable:
        line 264: 0
      LocalVariableTable:
        Start  Length  Slot  Name   Signature
            0       2     0  this   Lcoursier/core/shaded/fastparse/internal/RepImpls$;
            0       2     1 $this   Lscala/Function0;
    Signature: #93                          // <V:Ljava/lang/Object;T:Ljava/lang/Object;>(Lscala/Function0<Lcoursier/core/shaded/fastparse/ParsingRun<TT;>;>;)Lcoursier/core/shaded/fastparse/ParsingRun<*>;
    MethodParameters:
      Name                           Flags
      $this                          final

  public final <V extends java.lang.Object, T extends java.lang.Object> int rep$default$3$extension(scala.Function0<coursier.core.shaded.fastparse.ParsingRun<T>>);
    descriptor: (Lscala/Function0;)I
    flags: (0x0011) ACC_PUBLIC, ACC_FINAL
    Code:
      stack=1, locals=2, args_size=2
         0: ldc           #95                 // int 2147483647
         2: ireturn
      LineNumberTable:
        line 265: 0
      LocalVariableTable:
        Start  Length  Slot  Name   Signature
            0       3     0  this   Lcoursier/core/shaded/fastparse/internal/RepImpls$;
            0       3     1 $this   Lscala/Function0;
    Signature: #90                          // <V:Ljava/lang/Object;T:Ljava/lang/Object;>(Lscala/Function0<Lcoursier/core/shaded/fastparse/ParsingRun<TT;>;>;)I
    MethodParameters:
      Name                           Flags
      $this                          final

  public final <V extends java.lang.Object, T extends java.lang.Object> int rep$default$4$extension(scala.Function0<coursier.core.shaded.fastparse.ParsingRun<T>>);
    descriptor: (Lscala/Function0;)I
    flags: (0x0011) ACC_PUBLIC, ACC_FINAL
    Code:
      stack=1, locals=2, args_size=2
         0: iconst_m1
         1: ireturn
      LineNumberTable:
        line 266: 0
      LocalVariableTable:
        Start  Length  Slot  Name   Signature
            0       2     0  this   Lcoursier/core/shaded/fastparse/internal/RepImpls$;
            0       2     1 $this   Lscala/Function0;
    Signature: #90                          // <V:Ljava/lang/Object;T:Ljava/lang/Object;>(Lscala/Function0<Lcoursier/core/shaded/fastparse/ParsingRun<TT;>;>;)I
    MethodParameters:
      Name                           Flags
      $this                          final

  public final <V extends java.lang.Object, T extends java.lang.Object> void aggregateMsgPostSep$extension(scala.Function0<coursier.core.shaded.fastparse.ParsingRun<T>>, int, int, coursier.core.shaded.fastparse.ParsingRun<java.lang.Object>, coursier.core.shaded.fastparse.internal.Msgs, coursier.core.shaded.fastparse.internal.Msgs);
    descriptor: (Lscala/Function0;IILcoursier/core/shaded/fastparse/ParsingRun;Lcoursier/core/shaded/fastparse/internal/Msgs;Lcoursier/core/shaded/fastparse/internal/Msgs;)V
    flags: (0x0011) ACC_PUBLIC, ACC_FINAL
    Code:
      stack=5, locals=8, args_size=7
         0: aload         4
         2: iload_2
         3: aload         5
         5: iload_3
         6: invokedynamic #127,  0            // InvokeDynamic #0:apply:(Lcoursier/core/shaded/fastparse/internal/Msgs;I)Lscala/Function0;
        11: aload         4
        13: invokevirtual #131                // Method coursier/core/shaded/fastparse/ParsingRun.failureGroupAggregate:()Lcoursier/core/shaded/fastparse/internal/Msgs;
        16: astore        7
        18: aload         6
        20: aload         7
        22: invokevirtual #137                // Method coursier/core/shaded/fastparse/internal/Msgs.$colon$colon$colon:(Lcoursier/core/shaded/fastparse/internal/Msgs;)Lcoursier/core/shaded/fastparse/internal/Msgs;
        25: invokevirtual #141                // Method coursier/core/shaded/fastparse/ParsingRun.aggregateMsg:(ILscala/Function0;Lcoursier/core/shaded/fastparse/internal/Msgs;)V
        28: return
      LineNumberTable:
        line 406: 0
        line 407: 2
        line 408: 3
        line 413: 11
      LocalVariableTable:
        Start  Length  Slot  Name   Signature
            0      29     0  this   Lcoursier/core/shaded/fastparse/internal/RepImpls$;
            0      29     1 $this   Lscala/Function0;
            0      29     2 startIndex   I
            0      29     3   min   I
            0      29     4   ctx   Lcoursier/core/shaded/fastparse/ParsingRun;
            0      29     5 parsedMsg   Lcoursier/core/shaded/fastparse/internal/Msgs;
            0      29     6 lastAgg   Lcoursier/core/shaded/fastparse/internal/Msgs;
    Signature: #103                         // <V:Ljava/lang/Object;T:Ljava/lang/Object;>(Lscala/Function0<Lcoursier/core/shaded/fastparse/ParsingRun<TT;>;>;IILcoursier/core/shaded/fastparse/ParsingRun<Ljava/lang/Object;>;Lcoursier/core/shaded/fastparse/internal/Msgs;Lcoursier/core/shaded/fastparse/internal/Msgs;)V
    MethodParameters:
      Name                           Flags
      $this                          final
      startIndex                     final
      min                            final
      ctx                            final
      parsedMsg                      final
      lastAgg                        final

  public final <V extends java.lang.Object, T extends java.lang.Object> void aggregateMsgInRep$extension(scala.Function0<coursier.core.shaded.fastparse.ParsingRun<T>>, int, int, coursier.core.shaded.fastparse.ParsingRun<java.lang.Object>, coursier.core.shaded.fastparse.internal.Msgs, coursier.core.shaded.fastparse.internal.Msgs, coursier.core.shaded.fastparse.internal.Msgs, boolean);
    descriptor: (Lscala/Function0;IILcoursier/core/shaded/fastparse/ParsingRun;Lcoursier/core/shaded/fastparse/internal/Msgs;Lcoursier/core/shaded/fastparse/internal/Msgs;Lcoursier/core/shaded/fastparse/internal/Msgs;Z)V
    flags: (0x0011) ACC_PUBLIC, ACC_FINAL
    Code:
      stack=6, locals=10, args_size=9
         0: aload         5
         2: ifnull        10
         5: iload         8
         7: ifeq          32
        10: aload         4
        12: iload_2
        13: aload         6
        15: iload_3
        16: invokedynamic #152,  0            // InvokeDynamic #1:apply:(Lcoursier/core/shaded/fastparse/internal/Msgs;I)Lscala/Function0;
        21: aload         4
        23: invokevirtual #131                // Method coursier/core/shaded/fastparse/ParsingRun.failureGroupAggregate:()Lcoursier/core/shaded/fastparse/internal/Msgs;
        26: invokevirtual #141                // Method coursier/core/shaded/fastparse/ParsingRun.aggregateMsg:(ILscala/Function0;Lcoursier/core/shaded/fastparse/internal/Msgs;)V
        29: goto          83
        32: aload         4
        34: iload_2
        35: aload         6
        37: iload_3
        38: invokedynamic #157,  0            // InvokeDynamic #2:apply:(Lcoursier/core/shaded/fastparse/internal/Msgs;I)Lscala/Function0;
        43: aload         7
        45: ifnonnull     61
        48: getstatic     #162                // Field coursier/core/shaded/fastparse/internal/Util$.MODULE$:Lcoursier/core/shaded/fastparse/internal/Util$;
        51: aload         5
        53: aload         6
        55: invokevirtual #166                // Method coursier/core/shaded/fastparse/internal/Util$.joinBinOp:(Lcoursier/core/shaded/fastparse/internal/Msgs;Lcoursier/core/shaded/fastparse/internal/Msgs;)Lcoursier/core/shaded/fastparse/internal/Msgs;
        58: goto          80
        61: getstatic     #162                // Field coursier/core/shaded/fastparse/internal/Util$.MODULE$:Lcoursier/core/shaded/fastparse/internal/Util$;
        64: aload         5
        66: aload         6
        68: invokevirtual #166                // Method coursier/core/shaded/fastparse/internal/Util$.joinBinOp:(Lcoursier/core/shaded/fastparse/internal/Msgs;Lcoursier/core/shaded/fastparse/internal/Msgs;)Lcoursier/core/shaded/fastparse/internal/Msgs;
        71: astore        9
        73: aload         7
        75: aload         9
        77: invokevirtual #137                // Method coursier/core/shaded/fastparse/internal/Msgs.$colon$colon$colon:(Lcoursier/core/shaded/fastparse/internal/Msgs;)Lcoursier/core/shaded/fastparse/internal/Msgs;
        80: invokevirtual #141                // Method coursier/core/shaded/fastparse/ParsingRun.aggregateMsg:(ILscala/Function0;Lcoursier/core/shaded/fastparse/internal/Msgs;)V
        83: return
      StackMapTable: number_of_entries = 5
        frame_type = 10 /* same */
        frame_type = 21 /* same */
        frame_type = 255 /* full_frame */
          offset_delta = 28
          locals = [ class coursier/core/shaded/fastparse/internal/RepImpls$, class scala/Function0, int, int, class coursier/core/shaded/fastparse/ParsingRun, class coursier/core/shaded/fastparse/internal/Msgs, class coursier/core/shaded/fastparse/internal/Msgs, class coursier/core/shaded/fastparse/internal/Msgs, int ]
          stack = [ class coursier/core/shaded/fastparse/ParsingRun, int, class scala/Function0 ]
        frame_type = 255 /* full_frame */
          offset_delta = 18
          locals = [ class coursier/core/shaded/fastparse/internal/RepImpls$, class scala/Function0, int, int, class coursier/core/shaded/fastparse/ParsingRun, class coursier/core/shaded/fastparse/internal/Msgs, class coursier/core/shaded/fastparse/internal/Msgs, class coursier/core/shaded/fastparse/internal/Msgs, int ]
          stack = [ class coursier/core/shaded/fastparse/ParsingRun, int, class scala/Function0, class coursier/core/shaded/fastparse/internal/Msgs ]
        frame_type = 2 /* same */
      LineNumberTable:
        line 425: 0
        line 426: 10
        line 427: 12
        line 428: 13
        line 429: 21
        line 432: 32
        line 433: 34
        line 434: 35
        line 439: 43
        line 440: 61
      LocalVariableTable:
        Start  Length  Slot  Name   Signature
            0      84     0  this   Lcoursier/core/shaded/fastparse/internal/RepImpls$;
            0      84     1 $this   Lscala/Function0;
            0      84     2 startIndex   I
            0      84     3   min   I
            0      84     4   ctx   Lcoursier/core/shaded/fastparse/ParsingRun;
            0      84     5 sepMsg   Lcoursier/core/shaded/fastparse/internal/Msgs;
            0      84     6 parsedMsg   Lcoursier/core/shaded/fastparse/internal/Msgs;
            0      84     7 lastAgg   Lcoursier/core/shaded/fastparse/internal/Msgs;
            0      84     8 precut   Z
    Signature: #145                         // <V:Ljava/lang/Object;T:Ljava/lang/Object;>(Lscala/Function0<Lcoursier/core/shaded/fastparse/ParsingRun<TT;>;>;IILcoursier/core/shaded/fastparse/ParsingRun<Ljava/lang/Object;>;Lcoursier/core/shaded/fastparse/internal/Msgs;Lcoursier/core/shaded/fastparse/internal/Msgs;Lcoursier/core/shaded/fastparse/internal/Msgs;Z)V
    MethodParameters:
      Name                           Flags
      $this                          final
      startIndex                     final
      min                            final
      ctx                            final
      sepMsg                         final
      parsedMsg                      final
      lastAgg                        final
      precut                         final

  public final <T extends java.lang.Object> int hashCode$extension(scala.Function0<coursier.core.shaded.fastparse.ParsingRun<T>>);
    descriptor: (Lscala/Function0;)I
    flags: (0x0011) ACC_PUBLIC, ACC_FINAL
    Code:
      stack=1, locals=2, args_size=2
         0: aload_1
         1: invokevirtual #174                // Method java/lang/Object.hashCode:()I
         4: ireturn
      LineNumberTable:
        line 142: 0
      LocalVariableTable:
        Start  Length  Slot  Name   Signature
            0       5     0  this   Lcoursier/core/shaded/fastparse/internal/RepImpls$;
            0       5     1 $this   Lscala/Function0;
    Signature: #171                         // <T:Ljava/lang/Object;>(Lscala/Function0<Lcoursier/core/shaded/fastparse/ParsingRun<TT;>;>;)I
    MethodParameters:
      Name                           Flags
      $this                          final

  public final <T extends java.lang.Object> boolean equals$extension(scala.Function0<coursier.core.shaded.fastparse.ParsingRun<T>>, java.lang.Object);
    descriptor: (Lscala/Function0;Ljava/lang/Object;)Z
    flags: (0x0011) ACC_PUBLIC, ACC_FINAL
    Code:
      stack=2, locals=7, args_size=3
         0: aload_2
         1: astore        4
         3: aload         4
         5: instanceof    #180                // class coursier/core/shaded/fastparse/internal/RepImpls
         8: ifeq          16
        11: iconst_1
        12: istore_3
        13: goto          24
        16: goto          19
        19: iconst_0
        20: istore_3
        21: goto          24
        24: iload_3
        25: ifeq          83
        28: aload_2
        29: ifnonnull     36
        32: aconst_null
        33: goto          43
        36: aload_2
        37: checkcast     #180                // class coursier/core/shaded/fastparse/internal/RepImpls
        40: invokevirtual #184                // Method coursier/core/shaded/fastparse/internal/RepImpls.parse0:()Lscala/Function0;
        43: astore        5
        45: aload_1
        46: aload         5
        48: astore        6
        50: dup
        51: ifnonnull     63
        54: pop
        55: aload         6
        57: ifnull        71
        60: goto          75
        63: aload         6
        65: invokevirtual #188                // Method java/lang/Object.equals:(Ljava/lang/Object;)Z
        68: ifeq          75
        71: iconst_1
        72: goto          76
        75: iconst_0
        76: ifeq          83
        79: iconst_1
        80: goto          84
        83: iconst_0
        84: ireturn
      StackMapTable: number_of_entries = 11
        frame_type = 253 /* append */
          offset_delta = 16
          locals = [ top, class java/lang/Object ]
        frame_type = 2 /* same */
        frame_type = 255 /* full_frame */
          offset_delta = 4
          locals = [ class coursier/core/shaded/fastparse/internal/RepImpls$, class scala/Function0, class java/lang/Object, int, class java/lang/Object ]
          stack = []
        frame_type = 11 /* same */
        frame_type = 70 /* same_locals_1_stack_item */
          stack = [ class scala/Function0 ]
        frame_type = 255 /* full_frame */
          offset_delta = 19
          locals = [ class coursier/core/shaded/fastparse/internal/RepImpls$, class scala/Function0, class java/lang/Object, int, class java/lang/Object, class scala/Function0, class scala/Function0 ]
          stack = [ class scala/Function0 ]
        frame_type = 7 /* same */
        frame_type = 3 /* same */
        frame_type = 64 /* same_locals_1_stack_item */
          stack = [ int ]
        frame_type = 249 /* chop */
          offset_delta = 6
        frame_type = 64 /* same_locals_1_stack_item */
          stack = [ int ]
      LineNumberTable:
        line 142: 0
      LocalVariableTable:
        Start  Length  Slot  Name   Signature
            0      85     0  this   Lcoursier/core/shaded/fastparse/internal/RepImpls$;
            0      85     1 $this   Lscala/Function0;
            0      85     2   x$1   Ljava/lang/Object;
    Signature: #177                         // <T:Ljava/lang/Object;>(Lscala/Function0<Lcoursier/core/shaded/fastparse/ParsingRun<TT;>;>;Ljava/lang/Object;)Z
    MethodParameters:
      Name                           Flags
      $this                          final
      x$1                            final

  private static final coursier.core.shaded.fastparse.ParsingRun end$1(int, int, int, boolean, int, coursier.core.shaded.fastparse.ParsingRun, coursier.core.shaded.fastparse.Implicits$Repeater, java.lang.Object);
    descriptor: (IIIZILcoursier/core/shaded/fastparse/ParsingRun;Lcoursier/core/shaded/fastparse/Implicits$Repeater;Ljava/lang/Object;)Lcoursier/core/shaded/fastparse/ParsingRun;
    flags: (0x001a) ACC_PRIVATE, ACC_STATIC, ACC_FINAL
    Code:
      stack=4, locals=8, args_size=8
         0: iload_2
         1: iload         4
         3: if_icmpge     16
         6: aload         5
         8: iload_1
         9: iload_3
        10: invokevirtual #201                // Method coursier/core/shaded/fastparse/ParsingRun.augmentFailure:(IZ)Lcoursier/core/shaded/fastparse/ParsingRun;
        13: goto          32
        16: aload         5
        18: aload         6
        20: aload         7
        22: invokeinterface #205,  2          // InterfaceMethod coursier/core/shaded/fastparse/Implicits$Repeater.result:(Ljava/lang/Object;)Ljava/lang/Object;
        27: iload_0
        28: iload_3
        29: invokevirtual #209                // Method coursier/core/shaded/fastparse/ParsingRun.freshSuccess:(Ljava/lang/Object;IZ)Lcoursier/core/shaded/fastparse/ParsingRun;
        32: areturn
      StackMapTable: number_of_entries = 2
        frame_type = 16 /* same */
        frame_type = 79 /* same_locals_1_stack_item */
          stack = [ class coursier/core/shaded/fastparse/ParsingRun ]
      LineNumberTable:
        line 155: 0
        line 156: 16
      LocalVariableTable:
        Start  Length  Slot  Name   Signature
            0      33     0 successIndex   I
            0      33     1 index   I
            0      33     2 count   I
            0      33     3 endCut   Z
            0      33     4 actualMin$1   I
            0      33     5 ctx$6   Lcoursier/core/shaded/fastparse/ParsingRun;
            0      33     6 repeater$6   Lcoursier/core/shaded/fastparse/Implicits$Repeater;
            0      33     7 acc$1   Ljava/lang/Object;
    MethodParameters:
      Name                           Flags
      successIndex                   final
      index                          final
      count                          final
      endCut                         final
      actualMin$1                    final
      ctx$6                          final
      repeater$6                     final
      acc$1                          final

  public static final java.lang.String $anonfun$repX$1(coursier.core.shaded.fastparse.internal.Msgs, int);
    descriptor: (Lcoursier/core/shaded/fastparse/internal/Msgs;I)Ljava/lang/String;
    flags: (0x1019) ACC_PUBLIC, ACC_STATIC, ACC_FINAL, ACC_SYNTHETIC
    Code:
      stack=4, locals=2, args_size=2
         0: new           #214                // class java/lang/StringBuilder
         3: dup
         4: ldc           #115                // int 5
         6: invokespecial #217                // Method java/lang/StringBuilder."<init>":(I)V
         9: aload_0
        10: invokevirtual #220                // Method coursier/core/shaded/fastparse/internal/Msgs.render:()Ljava/lang/String;
        13: invokevirtual #224                // Method java/lang/StringBuilder.append:(Ljava/lang/String;)Ljava/lang/StringBuilder;
        16: ldc           #226                // String .repX
        18: invokevirtual #224                // Method java/lang/StringBuilder.append:(Ljava/lang/String;)Ljava/lang/StringBuilder;
        21: iload_1
        22: iconst_0
        23: if_icmpne     31
        26: ldc           #227                // String
        28: goto          57
        31: new           #214                // class java/lang/StringBuilder
        34: dup
        35: ldc           #228                // int 2
        37: invokespecial #217                // Method java/lang/StringBuilder."<init>":(I)V
        40: ldc           #230                // String (
        42: invokevirtual #224                // Method java/lang/StringBuilder.append:(Ljava/lang/String;)Ljava/lang/StringBuilder;
        45: iload_1
        46: invokevirtual #233                // Method java/lang/StringBuilder.append:(I)Ljava/lang/StringBuilder;
        49: ldc           #235                // String )
        51: invokevirtual #224                // Method java/lang/StringBuilder.append:(Ljava/lang/String;)Ljava/lang/StringBuilder;
        54: invokevirtual #238                // Method java/lang/StringBuilder.toString:()Ljava/lang/String;
        57: invokevirtual #243                // Method java/lang/StringBuilder.append:(Ljava/lang/Object;)Ljava/lang/StringBuilder;
        60: invokevirtual #238                // Method java/lang/StringBuilder.toString:()Ljava/lang/String;
        63: areturn
      StackMapTable: number_of_entries = 2
        frame_type = 95 /* same_locals_1_stack_item */
          stack = [ class java/lang/StringBuilder ]
        frame_type = 255 /* full_frame */
          offset_delta = 25
          locals = [ class coursier/core/shaded/fastparse/internal/Msgs, int ]
          stack = [ class java/lang/StringBuilder, class java/lang/String ]
      LineNumberTable:
        line 185: 0
      LocalVariableTable:
        Start  Length  Slot  Name   Signature
            0      64     0 parsedMsg$1   Lcoursier/core/shaded/fastparse/internal/Msgs;
            0      64     1 min$4   I
    MethodParameters:
      Name                           Flags
      parsedMsg$1                    final
      min$4                          final

  private final coursier.core.shaded.fastparse.ParsingRun rec$1(int, int, boolean, boolean, coursier.core.shaded.fastparse.internal.Msgs, coursier.core.shaded.fastparse.internal.Msgs, coursier.core.shaded.fastparse.ParsingRun, int, int, coursier.core.shaded.fastparse.Implicits$Repeater, java.lang.Object, scala.Function0, scala.Function0, int);
    descriptor: (IIZZLcoursier/core/shaded/fastparse/internal/Msgs;Lcoursier/core/shaded/fastparse/internal/Msgs;Lcoursier/core/shaded/fastparse/ParsingRun;IILcoursier/core/shaded/fastparse/Implicits$Repeater;Ljava/lang/Object;Lscala/Function0;Lscala/Function0;I)Lcoursier/core/shaded/fastparse/ParsingRun;
    flags: (0x0012) ACC_PRIVATE, ACC_FINAL
    Code:
      stack=9, locals=28, args_size=15
         0: aload         7
         2: iload_3
         3: iload_2
         4: iload         8
         6: if_icmpge     18
         9: iload         4
        11: ifeq          18
        14: iconst_1
        15: goto          19
        18: iconst_0
        19: ior
        20: invokevirtual #251                // Method coursier/core/shaded/fastparse/ParsingRun.cut_$eq:(Z)V
        23: iload_2
        24: iconst_0
        25: if_icmpne     52
        28: iload         9
        30: iconst_0
        31: if_icmpne     52
        34: aload         7
        36: aload         10
        38: aload         11
        40: invokeinterface #205,  2          // InterfaceMethod coursier/core/shaded/fastparse/Implicits$Repeater.result:(Ljava/lang/Object;)Ljava/lang/Object;
        45: iload_1
        46: invokevirtual #254                // Method coursier/core/shaded/fastparse/ParsingRun.freshSuccess:(Ljava/lang/Object;I)Lcoursier/core/shaded/fastparse/ParsingRun;
        49: goto          403
        52: aload         7
        54: invokevirtual #257                // Method coursier/core/shaded/fastparse/ParsingRun.verboseFailures:()Z
        57: istore        16
        59: aload         12
        61: invokeinterface #259,  1          // InterfaceMethod scala/Function0.apply:()Ljava/lang/Object;
        66: pop
        67: aload         7
        69: invokevirtual #262                // Method coursier/core/shaded/fastparse/ParsingRun.shortParserMsg:()Lcoursier/core/shaded/fastparse/internal/Msgs;
        72: astore        17
        74: aload         7
        76: invokevirtual #131                // Method coursier/core/shaded/fastparse/ParsingRun.failureGroupAggregate:()Lcoursier/core/shaded/fastparse/internal/Msgs;
        79: astore        18
        81: aload         7
        83: invokevirtual #53                 // Method coursier/core/shaded/fastparse/ParsingRun.cut:()Z
        86: istore        19
        88: aload         7
        90: invokevirtual #265                // Method coursier/core/shaded/fastparse/ParsingRun.isSuccess:()Z
        93: ifne          158
        96: iload         19
        98: ifeq          106
       101: aload         7
       103: goto          125
       106: iload_1
       107: iload_1
       108: iload_2
       109: iload         4
       111: iload         19
       113: ior
       114: iload         14
       116: aload         7
       118: aload         10
       120: aload         11
       122: invokestatic  #267                // Method end$1:(IIIZILcoursier/core/shaded/fastparse/ParsingRun;Lcoursier/core/shaded/fastparse/Implicits$Repeater;Ljava/lang/Object;)Lcoursier/core/shaded/fastparse/ParsingRun;
       125: astore        20
       127: iload         16
       129: ifeq          153
       132: aload_0
       133: aload         12
       135: iload_1
       136: iload         8
       138: aload         7
       140: aload         5
       142: aload         17
       144: aload         6
       146: iload_3
       147: invokevirtual #269                // Method aggregateMsgInRep$extension:(Lscala/Function0;IILcoursier/core/shaded/fastparse/ParsingRun;Lcoursier/core/shaded/fastparse/internal/Msgs;Lcoursier/core/shaded/fastparse/internal/Msgs;Lcoursier/core/shaded/fastparse/internal/Msgs;Z)V
       150: goto          153
       153: aload         20
       155: goto          403
       158: aload         7
       160: invokevirtual #49                 // Method coursier/core/shaded/fastparse/ParsingRun.index:()I
       163: istore        21
       165: aload         10
       167: aload         7
       169: invokevirtual #272                // Method coursier/core/shaded/fastparse/ParsingRun.successValue:()Ljava/lang/Object;
       172: aload         11
       174: invokeinterface #276,  3          // InterfaceMethod coursier/core/shaded/fastparse/Implicits$Repeater.accumulate:(Ljava/lang/Object;Ljava/lang/Object;)V
       179: iload_2
       180: iconst_1
       181: iadd
       182: istore        22
       184: iload         22
       186: iload         9
       188: if_icmpne     243
       191: iload         21
       193: iload         21
       195: iload         22
       197: iload         4
       199: iload         19
       201: ior
       202: iload         14
       204: aload         7
       206: aload         10
       208: aload         11
       210: invokestatic  #267                // Method end$1:(IIIZILcoursier/core/shaded/fastparse/ParsingRun;Lcoursier/core/shaded/fastparse/Implicits$Repeater;Ljava/lang/Object;)Lcoursier/core/shaded/fastparse/ParsingRun;
       213: astore        23
       215: iload         16
       217: ifeq          238
       220: aload         7
       222: iload_1
       223: aload         17
       225: iload         8
       227: invokedynamic #280,  0            // InvokeDynamic #3:apply:(Lcoursier/core/shaded/fastparse/internal/Msgs;I)Lscala/Function0;
       232: invokevirtual #284                // Method coursier/core/shaded/fastparse/ParsingRun.setMsg:(ILscala/Function0;)V
       235: goto          238
       238: aload         23
       240: goto          403
       243: aload         7
       245: iconst_0
       246: invokevirtual #251                // Method coursier/core/shaded/fastparse/ParsingRun.cut_$eq:(Z)V
       249: aload         13
       251: invokeinterface #259,  1          // InterfaceMethod scala/Function0.apply:()Ljava/lang/Object;
       256: checkcast     #45                 // class coursier/core/shaded/fastparse/ParsingRun
       259: astore        24
       261: aload         7
       263: invokevirtual #53                 // Method coursier/core/shaded/fastparse/ParsingRun.cut:()Z
       266: istore        25
       268: iload         4
       270: iload         19
       272: ior
       273: iload         25
       275: ior
       276: istore        26
       278: aload         24
       280: ifnonnull     305
       283: iload         21
       285: iload         22
       287: iconst_0
       288: iload         26
       290: aconst_null
       291: aload         18
       293: astore        6
       295: astore        5
       297: istore        4
       299: istore_3
       300: istore_2
       301: istore_1
       302: goto          0
       305: aload         7
       307: invokevirtual #265                // Method coursier/core/shaded/fastparse/ParsingRun.isSuccess:()Z
       310: ifeq          340
       313: iload         21
       315: iload         22
       317: iload         25
       319: iload         26
       321: aload         7
       323: invokevirtual #262                // Method coursier/core/shaded/fastparse/ParsingRun.shortParserMsg:()Lcoursier/core/shaded/fastparse/internal/Msgs;
       326: aload         18
       328: astore        6
       330: astore        5
       332: istore        4
       334: istore_3
       335: istore_2
       336: istore_1
       337: goto          0
       340: iload         25
       342: ifeq          357
       345: aload         7
       347: iload         21
       349: iload         26
       351: invokevirtual #201                // Method coursier/core/shaded/fastparse/ParsingRun.augmentFailure:(IZ)Lcoursier/core/shaded/fastparse/ParsingRun;
       354: goto          376
       357: iload         21
       359: iload         21
       361: iload         22
       363: iload         26
       365: iload         14
       367: aload         7
       369: aload         10
       371: aload         11
       373: invokestatic  #267                // Method end$1:(IIIZILcoursier/core/shaded/fastparse/ParsingRun;Lcoursier/core/shaded/fastparse/Implicits$Repeater;Ljava/lang/Object;)Lcoursier/core/shaded/fastparse/ParsingRun;
       376: astore        27
       378: iload         16
       380: ifeq          401
       383: aload_0
       384: aload         12
       386: iload_1
       387: iload         8
       389: aload         7
       391: aload         17
       393: aload         18
       395: invokevirtual #286                // Method aggregateMsgPostSep$extension:(Lscala/Function0;IILcoursier/core/shaded/fastparse/ParsingRun;Lcoursier/core/shaded/fastparse/internal/Msgs;Lcoursier/core/shaded/fastparse/internal/Msgs;)V
       398: goto          401
       401: aload         27
       403: areturn
      StackMapTable: number_of_entries = 16
        frame_type = 0 /* same */
        frame_type = 255 /* full_frame */
          offset_delta = 17
          locals = [ class coursier/core/shaded/fastparse/internal/RepImpls$, int, int, int, int, class coursier/core/shaded/fastparse/internal/Msgs, class coursier/core/shaded/fastparse/internal/Msgs, class coursier/core/shaded/fastparse/ParsingRun, int, int, class coursier/core/shaded/fastparse/Implicits$Repeater, class java/lang/Object, class scala/Function0, class scala/Function0, int ]
          stack = [ class coursier/core/shaded/fastparse/ParsingRun, int ]
        frame_type = 255 /* full_frame */
          offset_delta = 0
          locals = [ class coursier/core/shaded/fastparse/internal/RepImpls$, int, int, int, int, class coursier/core/shaded/fastparse/internal/Msgs, class coursier/core/shaded/fastparse/internal/Msgs, class coursier/core/shaded/fastparse/ParsingRun, int, int, class coursier/core/shaded/fastparse/Implicits$Repeater, class java/lang/Object, class scala/Function0, class scala/Function0, int ]
          stack = [ class coursier/core/shaded/fastparse/ParsingRun, int, int ]
        frame_type = 32 /* same */
        frame_type = 255 /* full_frame */
          offset_delta = 53
          locals = [ class coursier/core/shaded/fastparse/internal/RepImpls$, int, int, int, int, class coursier/core/shaded/fastparse/internal/Msgs, class coursier/core/shaded/fastparse/internal/Msgs, class coursier/core/shaded/fastparse/ParsingRun, int, int, class coursier/core/shaded/fastparse/Implicits$Repeater, class java/lang/Object, class scala/Function0, class scala/Function0, int, top, int, class coursier/core/shaded/fastparse/internal/Msgs, class coursier/core/shaded/fastparse/internal/Msgs, int ]
          stack = []
        frame_type = 82 /* same_locals_1_stack_item */
          stack = [ class coursier/core/shaded/fastparse/ParsingRun ]
        frame_type = 252 /* append */
          offset_delta = 27
          locals = [ class coursier/core/shaded/fastparse/ParsingRun ]
        frame_type = 250 /* chop */
          offset_delta = 4
        frame_type = 255 /* full_frame */
          offset_delta = 79
          locals = [ class coursier/core/shaded/fastparse/internal/RepImpls$, int, int, int, int, class coursier/core/shaded/fastparse/internal/Msgs, class coursier/core/shaded/fastparse/internal/Msgs, class coursier/core/shaded/fastparse/ParsingRun, int, int, class coursier/core/shaded/fastparse/Implicits$Repeater, class java/lang/Object, class scala/Function0, class scala/Function0, int, top, int, class coursier/core/shaded/fastparse/internal/Msgs, class coursier/core/shaded/fastparse/internal/Msgs, int, top, int, int, class coursier/core/shaded/fastparse/ParsingRun ]
          stack = []
        frame_type = 250 /* chop */
          offset_delta = 4
        frame_type = 255 /* full_frame */
          offset_delta = 61
          locals = [ class coursier/core/shaded/fastparse/internal/RepImpls$, int, int, int, int, class coursier/core/shaded/fastparse/internal/Msgs, class coursier/core/shaded/fastparse/internal/Msgs, class coursier/core/shaded/fastparse/ParsingRun, int, int, class coursier/core/shaded/fastparse/Implicits$Repeater, class java/lang/Object, class scala/Function0, class scala/Function0, int, top, int, class coursier/core/shaded/fastparse/internal/Msgs, class coursier/core/shaded/fastparse/internal/Msgs, int, top, int, int, top, class coursier/core/shaded/fastparse/ParsingRun, int, int ]
          stack = []
        frame_type = 34 /* same */
        frame_type = 16 /* same */
        frame_type = 82 /* same_locals_1_stack_item */
          stack = [ class coursier/core/shaded/fastparse/ParsingRun ]
        frame_type = 252 /* append */
          offset_delta = 24
          locals = [ class coursier/core/shaded/fastparse/ParsingRun ]
        frame_type = 255 /* full_frame */
          offset_delta = 1
          locals = [ class coursier/core/shaded/fastparse/internal/RepImpls$, int, int, int, int, class coursier/core/shaded/fastparse/internal/Msgs, class coursier/core/shaded/fastparse/internal/Msgs, class coursier/core/shaded/fastparse/ParsingRun, int, int, class coursier/core/shaded/fastparse/Implicits$Repeater, class java/lang/Object, class scala/Function0, class scala/Function0, int ]
          stack = [ class coursier/core/shaded/fastparse/ParsingRun ]
      LineNumberTable:
        line 164: 0
        line 165: 23
        line 167: 52
        line 168: 59
        line 169: 67
        line 170: 74
        line 171: 81
        line 172: 88
        line 174: 96
        line 175: 106
        line 177: 127
        line 178: 153
        line 180: 158
        line 181: 165
        line 182: 179
        line 183: 184
        line 184: 191
        line 185: 215
        line 186: 238
        line 189: 243
        line 190: 249
        line 191: 261
        line 192: 268
        line 193: 278
        line 195: 305
        line 198: 340
        line 199: 357
        line 200: 378
        line 201: 401
      LocalVariableTable:
        Start  Length  Slot  Name   Signature
          125      30    20   res   Lcoursier/core/shaded/fastparse/ParsingRun;
          213      27    23   res   Lcoursier/core/shaded/fastparse/ParsingRun;
          376      27    27   res   Lcoursier/core/shaded/fastparse/ParsingRun;
          259     144    24  sep1   Lcoursier/core/shaded/fastparse/ParsingRun;
          266     137    25 sepCut   Z
          276     127    26 endCut   Z
          163     240    21 beforeSepIndex   I
          182     221    22 nextCount   I
           57     346    16 verboseFailures   Z
           72     331    17 parsedMsg   Lcoursier/core/shaded/fastparse/internal/Msgs;
           79     324    18 parsedAgg   Lcoursier/core/shaded/fastparse/internal/Msgs;
           86     317    19 postCut   Z
            0     404     0  this   Lcoursier/core/shaded/fastparse/internal/RepImpls$;
            0     404     1 startIndex   I
            0     404     2 count   I
            0     404     3 precut   Z
            0     404     4 outerCut   Z
            0     404     5 sepMsg   Lcoursier/core/shaded/fastparse/internal/Msgs;
            0     404     6 lastAgg   Lcoursier/core/shaded/fastparse/internal/Msgs;
            0     404     7 ctx$6   Lcoursier/core/shaded/fastparse/ParsingRun;
            0     404     8 min$4   I
            0     404     9 actualMax$1   I
            0     404    10 repeater$6   Lcoursier/core/shaded/fastparse/Implicits$Repeater;
            0     404    11 acc$1   Ljava/lang/Object;
            0     404    12 $this$1   Lscala/Function0;
            0     404    13 sep$1   Lscala/Function0;
            0     404    14 actualMin$1   I
    MethodParameters:
      Name                           Flags
      startIndex                     final
      count                          final
      precut                         final
      outerCut                       final
      sepMsg                         final
      lastAgg                        final
      ctx$6                          final
      min$4                          final
      actualMax$1                    final
      repeater$6                     final
      acc$1                          final
      $this$1                        final
      sep$1                          final
      actualMin$1                    final

  private static final coursier.core.shaded.fastparse.ParsingRun end$2(int, int, int, boolean, int, coursier.core.shaded.fastparse.ParsingRun, coursier.core.shaded.fastparse.Implicits$Repeater, java.lang.Object);
    descriptor: (IIIZILcoursier/core/shaded/fastparse/ParsingRun;Lcoursier/core/shaded/fastparse/Implicits$Repeater;Ljava/lang/Object;)Lcoursier/core/shaded/fastparse/ParsingRun;
    flags: (0x001a) ACC_PRIVATE, ACC_STATIC, ACC_FINAL
    Code:
      stack=4, locals=8, args_size=8
         0: iload_2
         1: iload         4
         3: if_icmpge     16
         6: aload         5
         8: iload_1
         9: iload_3
        10: invokevirtual #201                // Method coursier/core/shaded/fastparse/ParsingRun.augmentFailure:(IZ)Lcoursier/core/shaded/fastparse/ParsingRun;
        13: goto          32
        16: aload         5
        18: aload         6
        20: aload         7
        22: invokeinterface #205,  2          // InterfaceMethod coursier/core/shaded/fastparse/Implicits$Repeater.result:(Ljava/lang/Object;)Ljava/lang/Object;
        27: iload_0
        28: iload_3
        29: invokevirtual #209                // Method coursier/core/shaded/fastparse/ParsingRun.freshSuccess:(Ljava/lang/Object;IZ)Lcoursier/core/shaded/fastparse/ParsingRun;
        32: areturn
      StackMapTable: number_of_entries = 2
        frame_type = 16 /* same */
        frame_type = 79 /* same_locals_1_stack_item */
          stack = [ class coursier/core/shaded/fastparse/ParsingRun ]
      LineNumberTable:
        line 219: 0
        line 220: 16
      LocalVariableTable:
        Start  Length  Slot  Name   Signature
            0      33     0 successIndex   I
            0      33     1 index   I
            0      33     2 count   I
            0      33     3 endCut   Z
            0      33     4 min$5   I
            0      33     5 ctx$7   Lcoursier/core/shaded/fastparse/ParsingRun;
            0      33     6 repeater$7   Lcoursier/core/shaded/fastparse/Implicits$Repeater;
            0      33     7 acc$2   Ljava/lang/Object;
    MethodParameters:
      Name                           Flags
      successIndex                   final
      index                          final
      count                          final
      endCut                         final
      min$5                          final
      ctx$7                          final
      repeater$7                     final
      acc$2                          final

  private final coursier.core.shaded.fastparse.ParsingRun rec$2(int, int, boolean, boolean, coursier.core.shaded.fastparse.internal.Msgs, coursier.core.shaded.fastparse.internal.Msgs, coursier.core.shaded.fastparse.ParsingRun, int, scala.Function0, coursier.core.shaded.fastparse.Implicits$Repeater, java.lang.Object, scala.Function0);
    descriptor: (IIZZLcoursier/core/shaded/fastparse/internal/Msgs;Lcoursier/core/shaded/fastparse/internal/Msgs;Lcoursier/core/shaded/fastparse/ParsingRun;ILscala/Function0;Lcoursier/core/shaded/fastparse/Implicits$Repeater;Ljava/lang/Object;Lscala/Function0;)Lcoursier/core/shaded/fastparse/ParsingRun;
    flags: (0x0012) ACC_PRIVATE, ACC_FINAL
    Code:
      stack=9, locals=25, args_size=13
         0: aload         7
         2: iload_3
         3: iload_2
         4: iload         8
         6: if_icmpge     18
         9: iload         4
        11: ifeq          18
        14: iconst_1
        15: goto          19
        18: iconst_0
        19: ior
        20: invokevirtual #251                // Method coursier/core/shaded/fastparse/ParsingRun.cut_$eq:(Z)V
        23: aload         9
        25: invokeinterface #259,  1          // InterfaceMethod scala/Function0.apply:()Ljava/lang/Object;
        30: pop
        31: aload         7
        33: invokevirtual #262                // Method coursier/core/shaded/fastparse/ParsingRun.shortParserMsg:()Lcoursier/core/shaded/fastparse/internal/Msgs;
        36: astore        14
        38: aload         7
        40: invokevirtual #131                // Method coursier/core/shaded/fastparse/ParsingRun.failureGroupAggregate:()Lcoursier/core/shaded/fastparse/internal/Msgs;
        43: astore        15
        45: aload         7
        47: invokevirtual #53                 // Method coursier/core/shaded/fastparse/ParsingRun.cut:()Z
        50: istore        16
        52: aload         7
        54: invokevirtual #257                // Method coursier/core/shaded/fastparse/ParsingRun.verboseFailures:()Z
        57: istore        17
        59: aload         7
        61: invokevirtual #265                // Method coursier/core/shaded/fastparse/ParsingRun.isSuccess:()Z
        64: ifne          129
        67: iload         16
        69: ifeq          77
        72: aload         7
        74: goto          96
        77: iload_1
        78: iload_1
        79: iload_2
        80: iload         4
        82: iload         16
        84: ior
        85: iload         8
        87: aload         7
        89: aload         10
        91: aload         11
        93: invokestatic  #302                // Method end$2:(IIIZILcoursier/core/shaded/fastparse/ParsingRun;Lcoursier/core/shaded/fastparse/Implicits$Repeater;Ljava/lang/Object;)Lcoursier/core/shaded/fastparse/ParsingRun;
        96: astore        18
        98: iload         17
       100: ifeq          124
       103: aload_0
       104: aload         9
       106: iload_1
       107: iload         8
       109: aload         7
       111: aload         5
       113: aload         14
       115: aload         6
       117: iload_3
       118: invokevirtual #269                // Method aggregateMsgInRep$extension:(Lscala/Function0;IILcoursier/core/shaded/fastparse/ParsingRun;Lcoursier/core/shaded/fastparse/internal/Msgs;Lcoursier/core/shaded/fastparse/internal/Msgs;Lcoursier/core/shaded/fastparse/internal/Msgs;Z)V
       121: goto          124
       124: aload         18
       126: goto          315
       129: aload         7
       131: invokevirtual #49                 // Method coursier/core/shaded/fastparse/ParsingRun.index:()I
       134: istore        19
       136: aload         10
       138: aload         7
       140: invokevirtual #272                // Method coursier/core/shaded/fastparse/ParsingRun.successValue:()Ljava/lang/Object;
       143: aload         11
       145: invokeinterface #276,  3          // InterfaceMethod coursier/core/shaded/fastparse/Implicits$Repeater.accumulate:(Ljava/lang/Object;Ljava/lang/Object;)V
       150: iload_2
       151: iconst_1
       152: iadd
       153: istore        20
       155: aload         7
       157: iconst_0
       158: invokevirtual #251                // Method coursier/core/shaded/fastparse/ParsingRun.cut_$eq:(Z)V
       161: aload         12
       163: invokeinterface #259,  1          // InterfaceMethod scala/Function0.apply:()Ljava/lang/Object;
       168: checkcast     #45                 // class coursier/core/shaded/fastparse/ParsingRun
       171: astore        21
       173: aload         7
       175: invokevirtual #53                 // Method coursier/core/shaded/fastparse/ParsingRun.cut:()Z
       178: istore        22
       180: iload         4
       182: iload         16
       184: ior
       185: iload         22
       187: ior
       188: istore        23
       190: aload         21
       192: ifnonnull     217
       195: iload         19
       197: iload         20
       199: iconst_0
       200: iload         23
       202: aconst_null
       203: aload         15
       205: astore        6
       207: astore        5
       209: istore        4
       211: istore_3
       212: istore_2
       213: istore_1
       214: goto          0
       217: aload         7
       219: invokevirtual #265                // Method coursier/core/shaded/fastparse/ParsingRun.isSuccess:()Z
       222: ifeq          252
       225: iload         19
       227: iload         20
       229: iload         22
       231: iload         23
       233: aload         7
       235: invokevirtual #262                // Method coursier/core/shaded/fastparse/ParsingRun.shortParserMsg:()Lcoursier/core/shaded/fastparse/internal/Msgs;
       238: aload         15
       240: astore        6
       242: astore        5
       244: istore        4
       246: istore_3
       247: istore_2
       248: istore_1
       249: goto          0
       252: iload         22
       254: ifeq          269
       257: aload         7
       259: iload         19
       261: iload         23
       263: invokevirtual #201                // Method coursier/core/shaded/fastparse/ParsingRun.augmentFailure:(IZ)Lcoursier/core/shaded/fastparse/ParsingRun;
       266: goto          288
       269: iload         19
       271: iload         19
       273: iload         20
       275: iload         23
       277: iload         8
       279: aload         7
       281: aload         10
       283: aload         11
       285: invokestatic  #302                // Method end$2:(IIIZILcoursier/core/shaded/fastparse/ParsingRun;Lcoursier/core/shaded/fastparse/Implicits$Repeater;Ljava/lang/Object;)Lcoursier/core/shaded/fastparse/ParsingRun;
       288: astore        24
       290: iload         17
       292: ifeq          313
       295: aload_0
       296: aload         9
       298: iload_1
       299: iload         8
       301: aload         7
       303: aload         14
       305: aload         15
       307: invokevirtual #286                // Method aggregateMsgPostSep$extension:(Lscala/Function0;IILcoursier/core/shaded/fastparse/ParsingRun;Lcoursier/core/shaded/fastparse/internal/Msgs;Lcoursier/core/shaded/fastparse/internal/Msgs;)V
       310: goto          313
       313: aload         24
       315: areturn
      StackMapTable: number_of_entries = 13
        frame_type = 0 /* same */
        frame_type = 255 /* full_frame */
          offset_delta = 17
          locals = [ class coursier/core/shaded/fastparse/internal/RepImpls$, int, int, int, int, class coursier/core/shaded/fastparse/internal/Msgs, class coursier/core/shaded/fastparse/internal/Msgs, class coursier/core/shaded/fastparse/ParsingRun, int, class scala/Function0, class coursier/core/shaded/fastparse/Implicits$Repeater, class java/lang/Object, class scala/Function0 ]
          stack = [ class coursier/core/shaded/fastparse/ParsingRun, int ]
        frame_type = 255 /* full_frame */
          offset_delta = 0
          locals = [ class coursier/core/shaded/fastparse/internal/RepImpls$, int, int, int, int, class coursier/core/shaded/fastparse/internal/Msgs, class coursier/core/shaded/fastparse/internal/Msgs, class coursier/core/shaded/fastparse/ParsingRun, int, class scala/Function0, class coursier/core/shaded/fastparse/Implicits$Repeater, class java/lang/Object, class scala/Function0 ]
          stack = [ class coursier/core/shaded/fastparse/ParsingRun, int, int ]
        frame_type = 255 /* full_frame */
          offset_delta = 57
          locals = [ class coursier/core/shaded/fastparse/internal/RepImpls$, int, int, int, int, class coursier/core/shaded/fastparse/internal/Msgs, class coursier/core/shaded/fastparse/internal/Msgs, class coursier/core/shaded/fastparse/ParsingRun, int, class scala/Function0, class coursier/core/shaded/fastparse/Implicits$Repeater, class java/lang/Object, class scala/Function0, top, class coursier/core/shaded/fastparse/internal/Msgs, class coursier/core/shaded/fastparse/internal/Msgs, int, int ]
          stack = []
        frame_type = 82 /* same_locals_1_stack_item */
          stack = [ class coursier/core/shaded/fastparse/ParsingRun ]
        frame_type = 252 /* append */
          offset_delta = 27
          locals = [ class coursier/core/shaded/fastparse/ParsingRun ]
        frame_type = 250 /* chop */
          offset_delta = 4
        frame_type = 255 /* full_frame */
          offset_delta = 87
          locals = [ class coursier/core/shaded/fastparse/internal/RepImpls$, int, int, int, int, class coursier/core/shaded/fastparse/internal/Msgs, class coursier/core/shaded/fastparse/internal/Msgs, class coursier/core/shaded/fastparse/ParsingRun, int, class scala/Function0, class coursier/core/shaded/fastparse/Implicits$Repeater, class java/lang/Object, class scala/Function0, top, class coursier/core/shaded/fastparse/internal/Msgs, class coursier/core/shaded/fastparse/internal/Msgs, int, int, top, int, int, class coursier/core/shaded/fastparse/ParsingRun, int, int ]
          stack = []
        frame_type = 34 /* same */
        frame_type = 16 /* same */
        frame_type = 82 /* same_locals_1_stack_item */
          stack = [ class coursier/core/shaded/fastparse/ParsingRun ]
        frame_type = 252 /* append */
          offset_delta = 24
          locals = [ class coursier/core/shaded/fastparse/ParsingRun ]
        frame_type = 255 /* full_frame */
          offset_delta = 1
          locals = [ class coursier/core/shaded/fastparse/internal/RepImpls$, int, int, int, int, class coursier/core/shaded/fastparse/internal/Msgs, class coursier/core/shaded/fastparse/internal/Msgs, class coursier/core/shaded/fastparse/ParsingRun, int, class scala/Function0, class coursier/core/shaded/fastparse/Implicits$Repeater, class java/lang/Object, class scala/Function0, top, class coursier/core/shaded/fastparse/internal/Msgs, class coursier/core/shaded/fastparse/internal/Msgs, int, int ]
          stack = [ class coursier/core/shaded/fastparse/ParsingRun ]
      LineNumberTable:
        line 228: 0
        line 229: 23
        line 230: 31
        line 231: 38
        line 232: 45
        line 233: 52
        line 234: 59
        line 236: 67
        line 237: 77
        line 238: 98
        line 239: 124
        line 241: 129
        line 242: 136
        line 243: 150
        line 244: 155
        line 245: 161
        line 246: 173
        line 247: 180
        line 248: 190
        line 250: 217
        line 253: 252
        line 254: 269
        line 255: 290
        line 256: 313
      LocalVariableTable:
        Start  Length  Slot  Name   Signature
           96      30    18   res   Lcoursier/core/shaded/fastparse/ParsingRun;
          288      27    24   res   Lcoursier/core/shaded/fastparse/ParsingRun;
          134     181    19 beforeSepIndex   I
          153     162    20 nextCount   I
          171     144    21  sep1   Lcoursier/core/shaded/fastparse/ParsingRun;
          178     137    22 sepCut   Z
          188     127    23 endCut   Z
           36     279    14 parsedMsg   Lcoursier/core/shaded/fastparse/internal/Msgs;
           43     272    15 parsedAgg   Lcoursier/core/shaded/fastparse/internal/Msgs;
           50     265    16 postCut   Z
           57     258    17 verboseFailures   Z
            0     316     0  this   Lcoursier/core/shaded/fastparse/internal/RepImpls$;
            0     316     1 startIndex   I
            0     316     2 count   I
            0     316     3 precut   Z
            0     316     4 outerCut   Z
            0     316     5 sepMsg   Lcoursier/core/shaded/fastparse/internal/Msgs;
            0     316     6 lastAgg   Lcoursier/core/shaded/fastparse/internal/Msgs;
            0     316     7 ctx$7   Lcoursier/core/shaded/fastparse/ParsingRun;
            0     316     8 min$5   I
            0     316     9 $this$2   Lscala/Function0;
            0     316    10 repeater$7   Lcoursier/core/shaded/fastparse/Implicits$Repeater;
            0     316    11 acc$2   Ljava/lang/Object;
            0     316    12 sep$2   Lscala/Function0;
    MethodParameters:
      Name                           Flags
      startIndex                     final
      count                          final
      precut                         final
      outerCut                       final
      sepMsg                         final
      lastAgg                        final
      ctx$7                          final
      min$5                          final
      $this$2                        final
      repeater$7                     final
      acc$2                          final
      sep$2                          final

  private static final coursier.core.shaded.fastparse.ParsingRun end$3(int, int, int, boolean, int, coursier.core.shaded.fastparse.ParsingRun, coursier.core.shaded.fastparse.Implicits$Repeater, java.lang.Object);
    descriptor: (IIIZILcoursier/core/shaded/fastparse/ParsingRun;Lcoursier/core/shaded/fastparse/Implicits$Repeater;Ljava/lang/Object;)Lcoursier/core/shaded/fastparse/ParsingRun;
    flags: (0x001a) ACC_PRIVATE, ACC_STATIC, ACC_FINAL
    Code:
      stack=4, locals=8, args_size=8
         0: iload_2
         1: iload         4
         3: if_icmpge     16
         6: aload         5
         8: iload_1
         9: iload_3
        10: invokevirtual #201                // Method coursier/core/shaded/fastparse/ParsingRun.augmentFailure:(IZ)Lcoursier/core/shaded/fastparse/ParsingRun;
        13: goto          32
        16: aload         5
        18: aload         6
        20: aload         7
        22: invokeinterface #205,  2          // InterfaceMethod coursier/core/shaded/fastparse/Implicits$Repeater.result:(Ljava/lang/Object;)Ljava/lang/Object;
        27: iload_0
        28: iload_3
        29: invokevirtual #209                // Method coursier/core/shaded/fastparse/ParsingRun.freshSuccess:(Ljava/lang/Object;IZ)Lcoursier/core/shaded/fastparse/ParsingRun;
        32: areturn
      StackMapTable: number_of_entries = 2
        frame_type = 16 /* same */
        frame_type = 79 /* same_locals_1_stack_item */
          stack = [ class coursier/core/shaded/fastparse/ParsingRun ]
      LineNumberTable:
        line 276: 0
        line 277: 16
      LocalVariableTable:
        Start  Length  Slot  Name   Signature
            0      33     0 successIndex   I
            0      33     1 index   I
            0      33     2 count   I
            0      33     3 endCut   Z
            0      33     4 actualMin$2   I
            0      33     5 ctx$8   Lcoursier/core/shaded/fastparse/ParsingRun;
            0      33     6 repeater$8   Lcoursier/core/shaded/fastparse/Implicits$Repeater;
            0      33     7 acc$3   Ljava/lang/Object;
    MethodParameters:
      Name                           Flags
      successIndex                   final
      index                          final
      count                          final
      endCut                         final
      actualMin$2                    final
      ctx$8                          final
      repeater$8                     final
      acc$3                          final

  public static final java.lang.String $anonfun$rep$1(coursier.core.shaded.fastparse.internal.Msgs, int);
    descriptor: (Lcoursier/core/shaded/fastparse/internal/Msgs;I)Ljava/lang/String;
    flags: (0x1019) ACC_PUBLIC, ACC_STATIC, ACC_FINAL, ACC_SYNTHETIC
    Code:
      stack=4, locals=2, args_size=2
         0: new           #214                // class java/lang/StringBuilder
         3: dup
         4: ldc_w         #311                // int 4
         7: invokespecial #217                // Method java/lang/StringBuilder."<init>":(I)V
        10: aload_0
        11: invokevirtual #220                // Method coursier/core/shaded/fastparse/internal/Msgs.render:()Ljava/lang/String;
        14: invokevirtual #224                // Method java/lang/StringBuilder.append:(Ljava/lang/String;)Ljava/lang/StringBuilder;
        17: ldc_w         #313                // String .rep
        20: invokevirtual #224                // Method java/lang/StringBuilder.append:(Ljava/lang/String;)Ljava/lang/StringBuilder;
        23: iload_1
        24: iconst_0
        25: if_icmpne     33
        28: ldc           #227                // String
        30: goto          59
        33: new           #214                // class java/lang/StringBuilder
        36: dup
        37: ldc           #228                // int 2
        39: invokespecial #217                // Method java/lang/StringBuilder."<init>":(I)V
        42: ldc           #230                // String (
        44: invokevirtual #224                // Method java/lang/StringBuilder.append:(Ljava/lang/String;)Ljava/lang/StringBuilder;
        47: iload_1
        48: invokevirtual #233                // Method java/lang/StringBuilder.append:(I)Ljava/lang/StringBuilder;
        51: ldc           #235                // String )
        53: invokevirtual #224                // Method java/lang/StringBuilder.append:(Ljava/lang/String;)Ljava/lang/StringBuilder;
        56: invokevirtual #238                // Method java/lang/StringBuilder.toString:()Ljava/lang/String;
        59: invokevirtual #243                // Method java/lang/StringBuilder.append:(Ljava/lang/Object;)Ljava/lang/StringBuilder;
        62: invokevirtual #238                // Method java/lang/StringBuilder.toString:()Ljava/lang/String;
        65: areturn
      StackMapTable: number_of_entries = 2
        frame_type = 97 /* same_locals_1_stack_item */
          stack = [ class java/lang/StringBuilder ]
        frame_type = 255 /* full_frame */
          offset_delta = 25
          locals = [ class coursier/core/shaded/fastparse/internal/Msgs, int ]
          stack = [ class java/lang/StringBuilder, class java/lang/String ]
      LineNumberTable:
        line 305: 0
      LocalVariableTable:
        Start  Length  Slot  Name   Signature
            0      66     0 parsedMsg$2   Lcoursier/core/shaded/fastparse/internal/Msgs;
            0      66     1 min$6   I
    MethodParameters:
      Name                           Flags
      parsedMsg$2                    final
      min$6                          final

  private final coursier.core.shaded.fastparse.ParsingRun rec$3(int, int, boolean, boolean, coursier.core.shaded.fastparse.internal.Msgs, coursier.core.shaded.fastparse.internal.Msgs, coursier.core.shaded.fastparse.ParsingRun, int, int, coursier.core.shaded.fastparse.Implicits$Repeater, java.lang.Object, scala.Function0, scala.Function1, scala.Function0, int);
    descriptor: (IIZZLcoursier/core/shaded/fastparse/internal/Msgs;Lcoursier/core/shaded/fastparse/internal/Msgs;Lcoursier/core/shaded/fastparse/ParsingRun;IILcoursier/core/shaded/fastparse/Implicits$Repeater;Ljava/lang/Object;Lscala/Function0;Lscala/Function1;Lscala/Function0;I)Lcoursier/core/shaded/fastparse/ParsingRun;
    flags: (0x0012) ACC_PRIVATE, ACC_FINAL
    Code:
      stack=9, locals=29, args_size=16
         0: aload         7
         2: iload_3
         3: iload_2
         4: iload         8
         6: if_icmpge     18
         9: iload         4
        11: ifeq          18
        14: iconst_1
        15: goto          19
        18: iconst_0
        19: ior
        20: invokevirtual #251                // Method coursier/core/shaded/fastparse/ParsingRun.cut_$eq:(Z)V
        23: iload_2
        24: iconst_0
        25: if_icmpne     52
        28: iload         9
        30: iconst_0
        31: if_icmpne     52
        34: aload         7
        36: aload         10
        38: aload         11
        40: invokeinterface #205,  2          // InterfaceMethod coursier/core/shaded/fastparse/Implicits$Repeater.result:(Ljava/lang/Object;)Ljava/lang/Object;
        45: iload_1
        46: invokevirtual #254                // Method coursier/core/shaded/fastparse/ParsingRun.freshSuccess:(Ljava/lang/Object;I)Lcoursier/core/shaded/fastparse/ParsingRun;
        49: goto          487
        52: aload         12
        54: invokeinterface #259,  1          // InterfaceMethod scala/Function0.apply:()Ljava/lang/Object;
        59: pop
        60: aload         7
        62: invokevirtual #262                // Method coursier/core/shaded/fastparse/ParsingRun.shortParserMsg:()Lcoursier/core/shaded/fastparse/internal/Msgs;
        65: astore        17
        67: aload         7
        69: invokevirtual #131                // Method coursier/core/shaded/fastparse/ParsingRun.failureGroupAggregate:()Lcoursier/core/shaded/fastparse/internal/Msgs;
        72: astore        18
        74: aload         7
        76: invokevirtual #53                 // Method coursier/core/shaded/fastparse/ParsingRun.cut:()Z
        79: istore        19
        81: aload         7
        83: invokevirtual #257                // Method coursier/core/shaded/fastparse/ParsingRun.verboseFailures:()Z
        86: istore        20
        88: aload         7
        90: invokevirtual #265                // Method coursier/core/shaded/fastparse/ParsingRun.isSuccess:()Z
        93: ifne          158
        96: iload         19
        98: ifeq          106
       101: aload         7
       103: goto          125
       106: iload_1
       107: iload_1
       108: iload_2
       109: iload         4
       111: iload         19
       113: ior
       114: iload         15
       116: aload         7
       118: aload         10
       120: aload         11
       122: invokestatic  #321                // Method end$3:(IIIZILcoursier/core/shaded/fastparse/ParsingRun;Lcoursier/core/shaded/fastparse/Implicits$Repeater;Ljava/lang/Object;)Lcoursier/core/shaded/fastparse/ParsingRun;
       125: astore        21
       127: iload         20
       129: ifeq          153
       132: aload_0
       133: aload         12
       135: iload_1
       136: iload         8
       138: aload         7
       140: aload         5
       142: aload         17
       144: aload         6
       146: iload_3
       147: invokevirtual #269                // Method aggregateMsgInRep$extension:(Lscala/Function0;IILcoursier/core/shaded/fastparse/ParsingRun;Lcoursier/core/shaded/fastparse/internal/Msgs;Lcoursier/core/shaded/fastparse/internal/Msgs;Lcoursier/core/shaded/fastparse/internal/Msgs;Z)V
       150: goto          153
       153: aload         21
       155: goto          487
       158: aload         7
       160: invokevirtual #49                 // Method coursier/core/shaded/fastparse/ParsingRun.index:()I
       163: istore        22
       165: aload         10
       167: aload         7
       169: invokevirtual #272                // Method coursier/core/shaded/fastparse/ParsingRun.successValue:()Ljava/lang/Object;
       172: aload         11
       174: invokeinterface #276,  3          // InterfaceMethod coursier/core/shaded/fastparse/Implicits$Repeater.accumulate:(Ljava/lang/Object;Ljava/lang/Object;)V
       179: iload_2
       180: iconst_1
       181: iadd
       182: istore        23
       184: iload         23
       186: iload         9
       188: if_icmpne     243
       191: iload         22
       193: iload         22
       195: iload         23
       197: iload         4
       199: iload         19
       201: ior
       202: iload         15
       204: aload         7
       206: aload         10
       208: aload         11
       210: invokestatic  #321                // Method end$3:(IIIZILcoursier/core/shaded/fastparse/ParsingRun;Lcoursier/core/shaded/fastparse/Implicits$Repeater;Ljava/lang/Object;)Lcoursier/core/shaded/fastparse/ParsingRun;
       213: astore        24
       215: iload         20
       217: ifeq          238
       220: aload         7
       222: iload_1
       223: aload         17
       225: iload         8
       227: invokedynamic #325,  0            // InvokeDynamic #4:apply:(Lcoursier/core/shaded/fastparse/internal/Msgs;I)Lscala/Function0;
       232: invokevirtual #284                // Method coursier/core/shaded/fastparse/ParsingRun.setMsg:(ILscala/Function0;)V
       235: goto          238
       238: aload         24
       240: goto          487
       243: aload         13
       245: getstatic     #328                // Field coursier/core/shaded/fastparse/NoWhitespace$noWhitespaceImplicit$.MODULE$:Lcoursier/core/shaded/fastparse/NoWhitespace$noWhitespaceImplicit$;
       248: if_acmpeq     264
       251: getstatic     #162                // Field coursier/core/shaded/fastparse/internal/Util$.MODULE$:Lcoursier/core/shaded/fastparse/internal/Util$;
       254: aload         13
       256: aload         7
       258: invokevirtual #332                // Method coursier/core/shaded/fastparse/internal/Util$.consumeWhitespace:(Lscala/Function1;Lcoursier/core/shaded/fastparse/ParsingRun;)V
       261: goto          264
       264: aload         7
       266: invokevirtual #265                // Method coursier/core/shaded/fastparse/ParsingRun.isSuccess:()Z
       269: ifne          285
       272: aload         7
       274: invokevirtual #53                 // Method coursier/core/shaded/fastparse/ParsingRun.cut:()Z
       277: ifeq          285
       280: aload         7
       282: goto          487
       285: aload         7
       287: iconst_0
       288: invokevirtual #251                // Method coursier/core/shaded/fastparse/ParsingRun.cut_$eq:(Z)V
       291: aload         14
       293: invokeinterface #259,  1          // InterfaceMethod scala/Function0.apply:()Ljava/lang/Object;
       298: checkcast     #45                 // class coursier/core/shaded/fastparse/ParsingRun
       301: astore        25
       303: aload         7
       305: invokevirtual #53                 // Method coursier/core/shaded/fastparse/ParsingRun.cut:()Z
       308: istore        26
       310: iload         4
       312: iload         19
       314: ior
       315: iload         26
       317: ior
       318: istore        27
       320: aload         25
       322: ifnonnull     347
       325: iload         22
       327: iload         23
       329: iconst_0
       330: iload         27
       332: aconst_null
       333: aload         18
       335: astore        6
       337: astore        5
       339: istore        4
       341: istore_3
       342: istore_2
       343: istore_1
       344: goto          0
       347: aload         7
       349: invokevirtual #265                // Method coursier/core/shaded/fastparse/ParsingRun.isSuccess:()Z
       352: ifeq          424
       355: aload         13
       357: getstatic     #328                // Field coursier/core/shaded/fastparse/NoWhitespace$noWhitespaceImplicit$.MODULE$:Lcoursier/core/shaded/fastparse/NoWhitespace$noWhitespaceImplicit$;
       360: if_acmpeq     376
       363: getstatic     #162                // Field coursier/core/shaded/fastparse/internal/Util$.MODULE$:Lcoursier/core/shaded/fastparse/internal/Util$;
       366: aload         13
       368: aload         7
       370: invokevirtual #332                // Method coursier/core/shaded/fastparse/internal/Util$.consumeWhitespace:(Lscala/Function1;Lcoursier/core/shaded/fastparse/ParsingRun;)V
       373: goto          376
       376: aload         7
       378: invokevirtual #265                // Method coursier/core/shaded/fastparse/ParsingRun.isSuccess:()Z
       381: ifne          394
       384: iload         26
       386: ifeq          394
       389: aload         7
       391: goto          421
       394: iload         22
       396: iload         23
       398: iload         26
       400: iload         27
       402: aload         7
       404: invokevirtual #262                // Method coursier/core/shaded/fastparse/ParsingRun.shortParserMsg:()Lcoursier/core/shaded/fastparse/internal/Msgs;
       407: aload         18
       409: astore        6
       411: astore        5
       413: istore        4
       415: istore_3
       416: istore_2
       417: istore_1
       418: goto          0
       421: goto          487
       424: iload         26
       426: ifeq          441
       429: aload         7
       431: iload         22
       433: iload         27
       435: invokevirtual #201                // Method coursier/core/shaded/fastparse/ParsingRun.augmentFailure:(IZ)Lcoursier/core/shaded/fastparse/ParsingRun;
       438: goto          460
       441: iload         22
       443: iload         22
       445: iload         23
       447: iload         27
       449: iload         15
       451: aload         7
       453: aload         10
       455: aload         11
       457: invokestatic  #321                // Method end$3:(IIIZILcoursier/core/shaded/fastparse/ParsingRun;Lcoursier/core/shaded/fastparse/Implicits$Repeater;Ljava/lang/Object;)Lcoursier/core/shaded/fastparse/ParsingRun;
       460: astore        28
       462: iload         20
       464: ifeq          485
       467: aload_0
       468: aload         12
       470: iload_1
       471: iload         8
       473: aload         7
       475: aload         17
       477: aload         18
       479: invokevirtual #286                // Method aggregateMsgPostSep$extension:(Lscala/Function0;IILcoursier/core/shaded/fastparse/ParsingRun;Lcoursier/core/shaded/fastparse/internal/Msgs;Lcoursier/core/shaded/fastparse/internal/Msgs;)V
       482: goto          485
       485: aload         28
       487: areturn
      StackMapTable: number_of_entries = 21
        frame_type = 0 /* same */
        frame_type = 255 /* full_frame */
          offset_delta = 17
          locals = [ class coursier/core/shaded/fastparse/internal/RepImpls$, int, int, int, int, class coursier/core/shaded/fastparse/internal/Msgs, class coursier/core/shaded/fastparse/internal/Msgs, class coursier/core/shaded/fastparse/ParsingRun, int, int, class coursier/core/shaded/fastparse/Implicits$Repeater, class java/lang/Object, class scala/Function0, class scala/Function1, class scala/Function0, int ]
          stack = [ class coursier/core/shaded/fastparse/ParsingRun, int ]
        frame_type = 255 /* full_frame */
          offset_delta = 0
          locals = [ class coursier/core/shaded/fastparse/internal/RepImpls$, int, int, int, int, class coursier/core/shaded/fastparse/internal/Msgs, class coursier/core/shaded/fastparse/internal/Msgs, class coursier/core/shaded/fastparse/ParsingRun, int, int, class coursier/core/shaded/fastparse/Implicits$Repeater, class java/lang/Object, class scala/Function0, class scala/Function1, class scala/Function0, int ]
          stack = [ class coursier/core/shaded/fastparse/ParsingRun, int, int ]
        frame_type = 32 /* same */
        frame_type = 255 /* full_frame */
          offset_delta = 53
          locals = [ class coursier/core/shaded/fastparse/internal/RepImpls$, int, int, int, int, class coursier/core/shaded/fastparse/internal/Msgs, class coursier/core/shaded/fastparse/internal/Msgs, class coursier/core/shaded/fastparse/ParsingRun, int, int, class coursier/core/shaded/fastparse/Implicits$Repeater, class java/lang/Object, class scala/Function0, class scala/Function1, class scala/Function0, int, top, class coursier/core/shaded/fastparse/internal/Msgs, class coursier/core/shaded/fastparse/internal/Msgs, int, int ]
          stack = []
        frame_type = 82 /* same_locals_1_stack_item */
          stack = [ class coursier/core/shaded/fastparse/ParsingRun ]
        frame_type = 252 /* append */
          offset_delta = 27
          locals = [ class coursier/core/shaded/fastparse/ParsingRun ]
        frame_type = 250 /* chop */
          offset_delta = 4
        frame_type = 255 /* full_frame */
          offset_delta = 79
          locals = [ class coursier/core/shaded/fastparse/internal/RepImpls$, int, int, int, int, class coursier/core/shaded/fastparse/internal/Msgs, class coursier/core/shaded/fastparse/internal/Msgs, class coursier/core/shaded/fastparse/ParsingRun, int, int, class coursier/core/shaded/fastparse/Implicits$Repeater, class java/lang/Object, class scala/Function0, class scala/Function1, class scala/Function0, int, top, class coursier/core/shaded/fastparse/internal/Msgs, class coursier/core/shaded/fastparse/internal/Msgs, int, int, top, int, int, class coursier/core/shaded/fastparse/ParsingRun ]
          stack = []
        frame_type = 250 /* chop */
          offset_delta = 4
        frame_type = 20 /* same */
        frame_type = 20 /* same */
        frame_type = 255 /* full_frame */
          offset_delta = 61
          locals = [ class coursier/core/shaded/fastparse/internal/RepImpls$, int, int, int, int, class coursier/core/shaded/fastparse/internal/Msgs, class coursier/core/shaded/fastparse/internal/Msgs, class coursier/core/shaded/fastparse/ParsingRun, int, int, class coursier/core/shaded/fastparse/Implicits$Repeater, class java/lang/Object, class scala/Function0, class scala/Function1, class scala/Function0, int, top, class coursier/core/shaded/fastparse/internal/Msgs, class coursier/core/shaded/fastparse/internal/Msgs, int, int, top, int, int, top, class coursier/core/shaded/fastparse/ParsingRun, int, int ]
          stack = []
        frame_type = 28 /* same */
        frame_type = 17 /* same */
        frame_type = 90 /* same_locals_1_stack_item */
          stack = [ class coursier/core/shaded/fastparse/ParsingRun ]
        frame_type = 2 /* same */
        frame_type = 16 /* same */
        frame_type = 82 /* same_locals_1_stack_item */
          stack = [ class coursier/core/shaded/fastparse/ParsingRun ]
        frame_type = 252 /* append */
          offset_delta = 24
          locals = [ class coursier/core/shaded/fastparse/ParsingRun ]
        frame_type = 255 /* full_frame */
          offset_delta = 1
          locals = [ class coursier/core/shaded/fastparse/internal/RepImpls$, int, int, int, int, class coursier/core/shaded/fastparse/internal/Msgs, class coursier/core/shaded/fastparse/internal/Msgs, class coursier/core/shaded/fastparse/ParsingRun, int, int, class coursier/core/shaded/fastparse/Implicits$Repeater, class java/lang/Object, class scala/Function0, class scala/Function1, class scala/Function0, int ]
          stack = [ class coursier/core/shaded/fastparse/ParsingRun ]
      LineNumberTable:
        line 285: 0
        line 286: 23
        line 288: 52
        line 289: 60
        line 290: 67
        line 291: 74
        line 292: 81
        line 293: 88
        line 295: 96
        line 296: 106
        line 297: 127
        line 298: 153
        line 300: 158
        line 301: 165
        line 302: 179
        line 303: 184
        line 304: 191
        line 305: 215
        line 306: 238
        line 309: 243
        line 311: 264
        line 313: 285
        line 314: 291
        line 315: 303
        line 316: 310
        line 317: 320
        line 318: 347
        line 319: 355
        line 320: 376
        line 321: 394
        line 325: 424
        line 326: 441
        line 328: 462
        line 329: 485
      LocalVariableTable:
        Start  Length  Slot  Name   Signature
          125      30    21   res   Lcoursier/core/shaded/fastparse/ParsingRun;
          213      27    24   res   Lcoursier/core/shaded/fastparse/ParsingRun;
          460      27    28   res   Lcoursier/core/shaded/fastparse/ParsingRun;
          301     186    25  sep1   Lcoursier/core/shaded/fastparse/ParsingRun;
          308     179    26 sepCut   Z
          318     169    27 endCut   Z
          163     324    22 beforeSepIndex   I
          182     305    23 nextCount   I
           65     422    17 parsedMsg   Lcoursier/core/shaded/fastparse/internal/Msgs;
           72     415    18 parsedAgg   Lcoursier/core/shaded/fastparse/internal/Msgs;
           79     408    19 postCut   Z
           86     401    20 verboseFailures   Z
            0     488     0  this   Lcoursier/core/shaded/fastparse/internal/RepImpls$;
            0     488     1 startIndex   I
            0     488     2 count   I
            0     488     3 precut   Z
            0     488     4 outerCut   Z
            0     488     5 sepMsg   Lcoursier/core/shaded/fastparse/internal/Msgs;
            0     488     6 lastAgg   Lcoursier/core/shaded/fastparse/internal/Msgs;
            0     488     7 ctx$8   Lcoursier/core/shaded/fastparse/ParsingRun;
            0     488     8 min$6   I
            0     488     9 actualMax$2   I
            0     488    10 repeater$8   Lcoursier/core/shaded/fastparse/Implicits$Repeater;
            0     488    11 acc$3   Ljava/lang/Object;
            0     488    12 $this$3   Lscala/Function0;
            0     488    13 whitespace$4   Lscala/Function1;
            0     488    14 sep$3   Lscala/Function0;
            0     488    15 actualMin$2   I
    MethodParameters:
      Name                           Flags
      startIndex                     final
      count                          final
      precut                         final
      outerCut                       final
      sepMsg                         final
      lastAgg                        final
      ctx$8                          final
      min$6                          final
      actualMax$2                    final
      repeater$8                     final
      acc$3                          final
      $this$3                        final
      whitespace$4                   final
      sep$3                          final
      actualMin$2                    final

  private static final coursier.core.shaded.fastparse.ParsingRun end$4(int, int, int, boolean, int, coursier.core.shaded.fastparse.ParsingRun, coursier.core.shaded.fastparse.Implicits$Repeater, java.lang.Object);
    descriptor: (IIIZILcoursier/core/shaded/fastparse/ParsingRun;Lcoursier/core/shaded/fastparse/Implicits$Repeater;Ljava/lang/Object;)Lcoursier/core/shaded/fastparse/ParsingRun;
    flags: (0x001a) ACC_PRIVATE, ACC_STATIC, ACC_FINAL
    Code:
      stack=4, locals=8, args_size=8
         0: iload_2
         1: iload         4
         3: if_icmpge     16
         6: aload         5
         8: iload_1
         9: iload_3
        10: invokevirtual #201                // Method coursier/core/shaded/fastparse/ParsingRun.augmentFailure:(IZ)Lcoursier/core/shaded/fastparse/ParsingRun;
        13: goto          32
        16: aload         5
        18: aload         6
        20: aload         7
        22: invokeinterface #205,  2          // InterfaceMethod coursier/core/shaded/fastparse/Implicits$Repeater.result:(Ljava/lang/Object;)Ljava/lang/Object;
        27: iload_0
        28: iload_3
        29: invokevirtual #209                // Method coursier/core/shaded/fastparse/ParsingRun.freshSuccess:(Ljava/lang/Object;IZ)Lcoursier/core/shaded/fastparse/ParsingRun;
        32: areturn
      StackMapTable: number_of_entries = 2
        frame_type = 16 /* same */
        frame_type = 79 /* same_locals_1_stack_item */
          stack = [ class coursier/core/shaded/fastparse/ParsingRun ]
      LineNumberTable:
        line 347: 0
        line 348: 16
      LocalVariableTable:
        Start  Length  Slot  Name   Signature
            0      33     0 successIndex   I
            0      33     1 index   I
            0      33     2 count   I
            0      33     3 endCut   Z
            0      33     4 min$7   I
            0      33     5 ctx$9   Lcoursier/core/shaded/fastparse/ParsingRun;
            0      33     6 repeater$9   Lcoursier/core/shaded/fastparse/Implicits$Repeater;
            0      33     7 acc$4   Ljava/lang/Object;
    MethodParameters:
      Name                           Flags
      successIndex                   final
      index                          final
      count                          final
      endCut                         final
      min$7                          final
      ctx$9                          final
      repeater$9                     final
      acc$4                          final

  private final coursier.core.shaded.fastparse.ParsingRun rec$4(int, int, boolean, boolean, coursier.core.shaded.fastparse.internal.Msgs, coursier.core.shaded.fastparse.internal.Msgs, coursier.core.shaded.fastparse.ParsingRun, int, scala.Function0, coursier.core.shaded.fastparse.Implicits$Repeater, java.lang.Object, scala.Function1, scala.Function0);
    descriptor: (IIZZLcoursier/core/shaded/fastparse/internal/Msgs;Lcoursier/core/shaded/fastparse/internal/Msgs;Lcoursier/core/shaded/fastparse/ParsingRun;ILscala/Function0;Lcoursier/core/shaded/fastparse/Implicits$Repeater;Ljava/lang/Object;Lscala/Function1;Lscala/Function0;)Lcoursier/core/shaded/fastparse/ParsingRun;
    flags: (0x0012) ACC_PRIVATE, ACC_FINAL
    Code:
      stack=9, locals=26, args_size=14
         0: aload         7
         2: iload_3
         3: iload_2
         4: iload         8
         6: if_icmpge     18
         9: iload         4
        11: ifeq          18
        14: iconst_1
        15: goto          19
        18: iconst_0
        19: ior
        20: invokevirtual #251                // Method coursier/core/shaded/fastparse/ParsingRun.cut_$eq:(Z)V
        23: aload         9
        25: invokeinterface #259,  1          // InterfaceMethod scala/Function0.apply:()Ljava/lang/Object;
        30: pop
        31: aload         7
        33: invokevirtual #262                // Method coursier/core/shaded/fastparse/ParsingRun.shortParserMsg:()Lcoursier/core/shaded/fastparse/internal/Msgs;
        36: astore        15
        38: aload         7
        40: invokevirtual #131                // Method coursier/core/shaded/fastparse/ParsingRun.failureGroupAggregate:()Lcoursier/core/shaded/fastparse/internal/Msgs;
        43: astore        16
        45: aload         7
        47: invokevirtual #53                 // Method coursier/core/shaded/fastparse/ParsingRun.cut:()Z
        50: istore        17
        52: aload         7
        54: invokevirtual #257                // Method coursier/core/shaded/fastparse/ParsingRun.verboseFailures:()Z
        57: istore        18
        59: aload         7
        61: invokevirtual #265                // Method coursier/core/shaded/fastparse/ParsingRun.isSuccess:()Z
        64: ifne          129
        67: iload         17
        69: ifeq          77
        72: aload         7
        74: goto          96
        77: iload_1
        78: iload_1
        79: iload_2
        80: iload         4
        82: iload         17
        84: ior
        85: iload         8
        87: aload         7
        89: aload         10
        91: aload         11
        93: invokestatic  #342                // Method end$4:(IIIZILcoursier/core/shaded/fastparse/ParsingRun;Lcoursier/core/shaded/fastparse/Implicits$Repeater;Ljava/lang/Object;)Lcoursier/core/shaded/fastparse/ParsingRun;
        96: astore        19
        98: iload         18
       100: ifeq          124
       103: aload_0
       104: aload         9
       106: iload_1
       107: iload         8
       109: aload         7
       111: aload         5
       113: aload         15
       115: aload         6
       117: iload_3
       118: invokevirtual #269                // Method aggregateMsgInRep$extension:(Lscala/Function0;IILcoursier/core/shaded/fastparse/ParsingRun;Lcoursier/core/shaded/fastparse/internal/Msgs;Lcoursier/core/shaded/fastparse/internal/Msgs;Lcoursier/core/shaded/fastparse/internal/Msgs;Z)V
       121: goto          124
       124: aload         19
       126: goto          378
       129: aload         7
       131: invokevirtual #49                 // Method coursier/core/shaded/fastparse/ParsingRun.index:()I
       134: istore        20
       136: aload         10
       138: aload         7
       140: invokevirtual #272                // Method coursier/core/shaded/fastparse/ParsingRun.successValue:()Ljava/lang/Object;
       143: aload         11
       145: invokeinterface #276,  3          // InterfaceMethod coursier/core/shaded/fastparse/Implicits$Repeater.accumulate:(Ljava/lang/Object;Ljava/lang/Object;)V
       150: iload_2
       151: iconst_1
       152: iadd
       153: istore        21
       155: aload         12
       157: getstatic     #328                // Field coursier/core/shaded/fastparse/NoWhitespace$noWhitespaceImplicit$.MODULE$:Lcoursier/core/shaded/fastparse/NoWhitespace$noWhitespaceImplicit$;
       160: if_acmpeq     176
       163: getstatic     #162                // Field coursier/core/shaded/fastparse/internal/Util$.MODULE$:Lcoursier/core/shaded/fastparse/internal/Util$;
       166: aload         12
       168: aload         7
       170: invokevirtual #332                // Method coursier/core/shaded/fastparse/internal/Util$.consumeWhitespace:(Lscala/Function1;Lcoursier/core/shaded/fastparse/ParsingRun;)V
       173: goto          176
       176: aload         7
       178: invokevirtual #265                // Method coursier/core/shaded/fastparse/ParsingRun.isSuccess:()Z
       181: ifne          197
       184: aload         7
       186: invokevirtual #53                 // Method coursier/core/shaded/fastparse/ParsingRun.cut:()Z
       189: ifeq          197
       192: aload         7
       194: goto          378
       197: aload         7
       199: iconst_0
       200: invokevirtual #251                // Method coursier/core/shaded/fastparse/ParsingRun.cut_$eq:(Z)V
       203: aload         13
       205: invokeinterface #259,  1          // InterfaceMethod scala/Function0.apply:()Ljava/lang/Object;
       210: checkcast     #45                 // class coursier/core/shaded/fastparse/ParsingRun
       213: astore        22
       215: aload         7
       217: invokevirtual #53                 // Method coursier/core/shaded/fastparse/ParsingRun.cut:()Z
       220: istore        23
       222: iload         4
       224: iload         17
       226: ior
       227: iload         23
       229: ior
       230: istore        24
       232: aload         22
       234: ifnonnull     259
       237: iload         20
       239: iload         21
       241: iconst_0
       242: iload         24
       244: aconst_null
       245: aload         16
       247: astore        6
       249: astore        5
       251: istore        4
       253: istore_3
       254: istore_2
       255: istore_1
       256: goto          0
       259: aload         7
       261: invokevirtual #265                // Method coursier/core/shaded/fastparse/ParsingRun.isSuccess:()Z
       264: ifeq          315
       267: aload         12
       269: getstatic     #328                // Field coursier/core/shaded/fastparse/NoWhitespace$noWhitespaceImplicit$.MODULE$:Lcoursier/core/shaded/fastparse/NoWhitespace$noWhitespaceImplicit$;
       272: if_acmpeq     288
       275: getstatic     #162                // Field coursier/core/shaded/fastparse/internal/Util$.MODULE$:Lcoursier/core/shaded/fastparse/internal/Util$;
       278: aload         12
       280: aload         7
       282: invokevirtual #332                // Method coursier/core/shaded/fastparse/internal/Util$.consumeWhitespace:(Lscala/Function1;Lcoursier/core/shaded/fastparse/ParsingRun;)V
       285: goto          288
       288: iload         20
       290: iload         21
       292: iload         23
       294: iload         24
       296: aload         7
       298: invokevirtual #262                // Method coursier/core/shaded/fastparse/ParsingRun.shortParserMsg:()Lcoursier/core/shaded/fastparse/internal/Msgs;
       301: aload         16
       303: astore        6
       305: astore        5
       307: istore        4
       309: istore_3
       310: istore_2
       311: istore_1
       312: goto          0
       315: iload         23
       317: ifeq          332
       320: aload         7
       322: iload         20
       324: iload         24
       326: invokevirtual #201                // Method coursier/core/shaded/fastparse/ParsingRun.augmentFailure:(IZ)Lcoursier/core/shaded/fastparse/ParsingRun;
       329: goto          351
       332: iload         20
       334: iload         20
       336: iload         21
       338: iload         24
       340: iload         8
       342: aload         7
       344: aload         10
       346: aload         11
       348: invokestatic  #342                // Method end$4:(IIIZILcoursier/core/shaded/fastparse/ParsingRun;Lcoursier/core/shaded/fastparse/Implicits$Repeater;Ljava/lang/Object;)Lcoursier/core/shaded/fastparse/ParsingRun;
       351: astore        25
       353: iload         18
       355: ifeq          376
       358: aload_0
       359: aload         9
       361: iload_1
       362: iload         8
       364: aload         7
       366: aload         15
       368: aload         16
       370: invokevirtual #286                // Method aggregateMsgPostSep$extension:(Lscala/Function0;IILcoursier/core/shaded/fastparse/ParsingRun;Lcoursier/core/shaded/fastparse/internal/Msgs;Lcoursier/core/shaded/fastparse/internal/Msgs;)V
       373: goto          376
       376: aload         25
       378: areturn
      StackMapTable: number_of_entries = 16
        frame_type = 0 /* same */
        frame_type = 255 /* full_frame */
          offset_delta = 17
          locals = [ class coursier/core/shaded/fastparse/internal/RepImpls$, int, int, int, int, class coursier/core/shaded/fastparse/internal/Msgs, class coursier/core/shaded/fastparse/internal/Msgs, class coursier/core/shaded/fastparse/ParsingRun, int, class scala/Function0, class coursier/core/shaded/fastparse/Implicits$Repeater, class java/lang/Object, class scala/Function1, class scala/Function0 ]
          stack = [ class coursier/core/shaded/fastparse/ParsingRun, int ]
        frame_type = 255 /* full_frame */
          offset_delta = 0
          locals = [ class coursier/core/shaded/fastparse/internal/RepImpls$, int, int, int, int, class coursier/core/shaded/fastparse/internal/Msgs, class coursier/core/shaded/fastparse/internal/Msgs, class coursier/core/shaded/fastparse/ParsingRun, int, class scala/Function0, class coursier/core/shaded/fastparse/Implicits$Repeater, class java/lang/Object, class scala/Function1, class scala/Function0 ]
          stack = [ class coursier/core/shaded/fastparse/ParsingRun, int, int ]
        frame_type = 255 /* full_frame */
          offset_delta = 57
          locals = [ class coursier/core/shaded/fastparse/internal/RepImpls$, int, int, int, int, class coursier/core/shaded/fastparse/internal/Msgs, class coursier/core/shaded/fastparse/internal/Msgs, class coursier/core/shaded/fastparse/ParsingRun, int, class scala/Function0, class coursier/core/shaded/fastparse/Implicits$Repeater, class java/lang/Object, class scala/Function1, class scala/Function0, top, class coursier/core/shaded/fastparse/internal/Msgs, class coursier/core/shaded/fastparse/internal/Msgs, int, int ]
          stack = []
        frame_type = 82 /* same_locals_1_stack_item */
          stack = [ class coursier/core/shaded/fastparse/ParsingRun ]
        frame_type = 252 /* append */
          offset_delta = 27
          locals = [ class coursier/core/shaded/fastparse/ParsingRun ]
        frame_type = 250 /* chop */
          offset_delta = 4
        frame_type = 254 /* append */
          offset_delta = 46
          locals = [ top, int, int ]
        frame_type = 20 /* same */
        frame_type = 254 /* append */
          offset_delta = 61
          locals = [ class coursier/core/shaded/fastparse/ParsingRun, int, int ]
        frame_type = 28 /* same */
        frame_type = 26 /* same */
        frame_type = 16 /* same */
        frame_type = 82 /* same_locals_1_stack_item */
          stack = [ class coursier/core/shaded/fastparse/ParsingRun ]
        frame_type = 252 /* append */
          offset_delta = 24
          locals = [ class coursier/core/shaded/fastparse/ParsingRun ]
        frame_type = 255 /* full_frame */
          offset_delta = 1
          locals = [ class coursier/core/shaded/fastparse/internal/RepImpls$, int, int, int, int, class coursier/core/shaded/fastparse/internal/Msgs, class coursier/core/shaded/fastparse/internal/Msgs, class coursier/core/shaded/fastparse/ParsingRun, int, class scala/Function0, class coursier/core/shaded/fastparse/Implicits$Repeater, class java/lang/Object, class scala/Function1, class scala/Function0, top, class coursier/core/shaded/fastparse/internal/Msgs, class coursier/core/shaded/fastparse/internal/Msgs, int, int ]
          stack = [ class coursier/core/shaded/fastparse/ParsingRun ]
      LineNumberTable:
        line 357: 0
        line 358: 23
        line 359: 31
        line 360: 38
        line 361: 45
        line 362: 52
        line 363: 59
        line 365: 67
        line 366: 77
        line 367: 98
        line 368: 124
        line 370: 129
        line 371: 136
        line 372: 150
        line 373: 155
        line 375: 176
        line 377: 197
        line 378: 203
        line 379: 215
        line 380: 222
        line 381: 232
        line 382: 259
        line 383: 267
        line 385: 288
        line 389: 315
        line 390: 332
        line 392: 353
        line 393: 376
      LocalVariableTable:
        Start  Length  Slot  Name   Signature
           96      30    19   res   Lcoursier/core/shaded/fastparse/ParsingRun;
          351      27    25   res   Lcoursier/core/shaded/fastparse/ParsingRun;
          213     165    22  sep1   Lcoursier/core/shaded/fastparse/ParsingRun;
          220     158    23 sepCut   Z
          230     148    24 endCut   Z
          134     244    20 beforeSepIndex   I
          153     225    21 nextCount   I
           36     342    15 parsedMsg   Lcoursier/core/shaded/fastparse/internal/Msgs;
           43     335    16 parsedAgg   Lcoursier/core/shaded/fastparse/internal/Msgs;
           50     328    17 postCut   Z
           57     321    18 verboseFailures   Z
            0     379     0  this   Lcoursier/core/shaded/fastparse/internal/RepImpls$;
            0     379     1 startIndex   I
            0     379     2 count   I
            0     379     3 precut   Z
            0     379     4 outerCut   Z
            0     379     5 sepMsg   Lcoursier/core/shaded/fastparse/internal/Msgs;
            0     379     6 lastAgg   Lcoursier/core/shaded/fastparse/internal/Msgs;
            0     379     7 ctx$9   Lcoursier/core/shaded/fastparse/ParsingRun;
            0     379     8 min$7   I
            0     379     9 $this$4   Lscala/Function0;
            0     379    10 repeater$9   Lcoursier/core/shaded/fastparse/Implicits$Repeater;
            0     379    11 acc$4   Ljava/lang/Object;
            0     379    12 whitespace$5   Lscala/Function1;
            0     379    13 sep$4   Lscala/Function0;
    MethodParameters:
      Name                           Flags
      startIndex                     final
      count                          final
      precut                         final
      outerCut                       final
      sepMsg                         final
      lastAgg                        final
      ctx$9                          final
      min$7                          final
      $this$4                        final
      repeater$9                     final
      acc$4                          final
      whitespace$5                   final
      sep$4                          final

  public static final java.lang.String $anonfun$aggregateMsgPostSep$1(coursier.core.shaded.fastparse.internal.Msgs, int);
    descriptor: (Lcoursier/core/shaded/fastparse/internal/Msgs;I)Ljava/lang/String;
    flags: (0x1019) ACC_PUBLIC, ACC_STATIC, ACC_FINAL, ACC_SYNTHETIC
    Code:
      stack=4, locals=2, args_size=2
         0: new           #214                // class java/lang/StringBuilder
         3: dup
         4: ldc_w         #345                // int 0
         7: invokespecial #217                // Method java/lang/StringBuilder."<init>":(I)V
        10: aload_0
        11: invokevirtual #220                // Method coursier/core/shaded/fastparse/internal/Msgs.render:()Ljava/lang/String;
        14: invokevirtual #224                // Method java/lang/StringBuilder.append:(Ljava/lang/String;)Ljava/lang/StringBuilder;
        17: new           #214                // class java/lang/StringBuilder
        20: dup
        21: ldc_w         #346                // int 6
        24: invokespecial #217                // Method java/lang/StringBuilder."<init>":(I)V
        27: ldc_w         #348                // String .rep(
        30: invokevirtual #224                // Method java/lang/StringBuilder.append:(Ljava/lang/String;)Ljava/lang/StringBuilder;
        33: iload_1
        34: invokevirtual #233                // Method java/lang/StringBuilder.append:(I)Ljava/lang/StringBuilder;
        37: ldc           #235                // String )
        39: invokevirtual #224                // Method java/lang/StringBuilder.append:(Ljava/lang/String;)Ljava/lang/StringBuilder;
        42: invokevirtual #238                // Method java/lang/StringBuilder.toString:()Ljava/lang/String;
        45: invokevirtual #224                // Method java/lang/StringBuilder.append:(Ljava/lang/String;)Ljava/lang/StringBuilder;
        48: invokevirtual #238                // Method java/lang/StringBuilder.toString:()Ljava/lang/String;
        51: areturn
      LineNumberTable:
        line 408: 0
      LocalVariableTable:
        Start  Length  Slot  Name   Signature
            0      52     0 parsedMsg$3   Lcoursier/core/shaded/fastparse/internal/Msgs;
            0      52     1 min$8   I
    MethodParameters:
      Name                           Flags
      parsedMsg$3                    final
      min$8                          final

  public static final java.lang.String $anonfun$aggregateMsgInRep$1(coursier.core.shaded.fastparse.internal.Msgs, int);
    descriptor: (Lcoursier/core/shaded/fastparse/internal/Msgs;I)Ljava/lang/String;
    flags: (0x1019) ACC_PUBLIC, ACC_STATIC, ACC_FINAL, ACC_SYNTHETIC
    Code:
      stack=4, locals=2, args_size=2
         0: new           #214                // class java/lang/StringBuilder
         3: dup
         4: ldc_w         #345                // int 0
         7: invokespecial #217                // Method java/lang/StringBuilder."<init>":(I)V
        10: aload_0
        11: invokevirtual #220                // Method coursier/core/shaded/fastparse/internal/Msgs.render:()Ljava/lang/String;
        14: invokevirtual #224                // Method java/lang/StringBuilder.append:(Ljava/lang/String;)Ljava/lang/StringBuilder;
        17: new           #214                // class java/lang/StringBuilder
        20: dup
        21: ldc_w         #346                // int 6
        24: invokespecial #217                // Method java/lang/StringBuilder."<init>":(I)V
        27: ldc_w         #348                // String .rep(
        30: invokevirtual #224                // Method java/lang/StringBuilder.append:(Ljava/lang/String;)Ljava/lang/StringBuilder;
        33: iload_1
        34: invokevirtual #233                // Method java/lang/StringBuilder.append:(I)Ljava/lang/StringBuilder;
        37: ldc           #235                // String )
        39: invokevirtual #224                // Method java/lang/StringBuilder.append:(Ljava/lang/String;)Ljava/lang/StringBuilder;
        42: invokevirtual #238                // Method java/lang/StringBuilder.toString:()Ljava/lang/String;
        45: invokevirtual #224                // Method java/lang/StringBuilder.append:(Ljava/lang/String;)Ljava/lang/StringBuilder;
        48: invokevirtual #238                // Method java/lang/StringBuilder.toString:()Ljava/lang/String;
        51: areturn
      LineNumberTable:
        line 428: 0
      LocalVariableTable:
        Start  Length  Slot  Name   Signature
            0      52     0 parsedMsg$4   Lcoursier/core/shaded/fastparse/internal/Msgs;
            0      52     1 min$9   I
    MethodParameters:
      Name                           Flags
      parsedMsg$4                    final
      min$9                          final

  public static final java.lang.String $anonfun$aggregateMsgInRep$2(coursier.core.shaded.fastparse.internal.Msgs, int);
    descriptor: (Lcoursier/core/shaded/fastparse/internal/Msgs;I)Ljava/lang/String;
    flags: (0x1019) ACC_PUBLIC, ACC_STATIC, ACC_FINAL, ACC_SYNTHETIC
    Code:
      stack=4, locals=2, args_size=2
         0: new           #214                // class java/lang/StringBuilder
         3: dup
         4: ldc_w         #345                // int 0
         7: invokespecial #217                // Method java/lang/StringBuilder."<init>":(I)V
        10: aload_0
        11: invokevirtual #220                // Method coursier/core/shaded/fastparse/internal/Msgs.render:()Ljava/lang/String;
        14: invokevirtual #224                // Method java/lang/StringBuilder.append:(Ljava/lang/String;)Ljava/lang/StringBuilder;
        17: new           #214                // class java/lang/StringBuilder
        20: dup
        21: ldc_w         #346                // int 6
        24: invokespecial #217                // Method java/lang/StringBuilder."<init>":(I)V
        27: ldc_w         #348                // String .rep(
        30: invokevirtual #224                // Method java/lang/StringBuilder.append:(Ljava/lang/String;)Ljava/lang/StringBuilder;
        33: iload_1
        34: invokevirtual #233                // Method java/lang/StringBuilder.append:(I)Ljava/lang/StringBuilder;
        37: ldc           #235                // String )
        39: invokevirtual #224                // Method java/lang/StringBuilder.append:(Ljava/lang/String;)Ljava/lang/StringBuilder;
        42: invokevirtual #238                // Method java/lang/StringBuilder.toString:()Ljava/lang/String;
        45: invokevirtual #224                // Method java/lang/StringBuilder.append:(Ljava/lang/String;)Ljava/lang/StringBuilder;
        48: invokevirtual #238                // Method java/lang/StringBuilder.toString:()Ljava/lang/String;
        51: areturn
      LineNumberTable:
        line 434: 0
      LocalVariableTable:
        Start  Length  Slot  Name   Signature
            0      52     0 parsedMsg$4   Lcoursier/core/shaded/fastparse/internal/Msgs;
            0      52     1 min$9   I
    MethodParameters:
      Name                           Flags
      parsedMsg$4                    final
      min$9                          final

  private coursier.core.shaded.fastparse.internal.RepImpls$();
    descriptor: ()V
    flags: (0x0002) ACC_PRIVATE
    Code:
      stack=1, locals=1, args_size=1
         0: aload_0
         1: invokespecial #351                // Method java/lang/Object."<init>":()V
         4: return
      LineNumberTable:
        line 142: 0
      LocalVariableTable:
        Start  Length  Slot  Name   Signature
            0       5     0  this   Lcoursier/core/shaded/fastparse/internal/RepImpls$;

  private static java.lang.Object $deserializeLambda$(java.lang.invoke.SerializedLambda);
    descriptor: (Ljava/lang/invoke/SerializedLambda;)Ljava/lang/Object;
    flags: (0x100a) ACC_PRIVATE, ACC_STATIC, ACC_SYNTHETIC
    Code:
      stack=1, locals=1, args_size=1
         0: aload_0
         1: invokedynamic #363,  0            // InvokeDynamic #5:lambdaDeserialize:(Ljava/lang/invoke/SerializedLambda;)Ljava/lang/Object;
         6: areturn
}
InnerClasses:
  public static #10= #7 of #9;            // Repeater=class coursier/core/shaded/fastparse/Implicits$Repeater of class coursier/core/shaded/fastparse/Implicits
  public static #15= #12 of #14;          // =class coursier/core/shaded/fastparse/NoWhitespace$noWhitespaceImplicit$ of class coursier/core/shaded/fastparse/NoWhitespace
  public static final #20= #17 of #19;    // Lookup=class java/lang/invoke/MethodHandles$Lookup of class java/lang/invoke/MethodHandles
SourceFile: "RepImpls.scala"
BootstrapMethods:
  0: #123 REF_invokeStatic java/lang/invoke/LambdaMetafactory.altMetafactory:(Ljava/lang/invoke/MethodHandles$Lookup;Ljava/lang/String;Ljava/lang/invoke/MethodType;[Ljava/lang/Object;)Ljava/lang/invoke/CallSite;
    Method arguments:
      #107 ()Ljava/lang/Object;
      #112 REF_invokeStatic coursier/core/shaded/fastparse/internal/RepImpls$.$anonfun$aggregateMsgPostSep$1:(Lcoursier/core/shaded/fastparse/internal/Msgs;I)Ljava/lang/String;
      #114 ()Ljava/lang/String;
      #115 5
      #116 1
      #114 ()Ljava/lang/String;
  1: #123 REF_invokeStatic java/lang/invoke/LambdaMetafactory.altMetafactory:(Ljava/lang/invoke/MethodHandles$Lookup;Ljava/lang/String;Ljava/lang/invoke/MethodType;[Ljava/lang/Object;)Ljava/lang/invoke/CallSite;
    Method arguments:
      #107 ()Ljava/lang/Object;
      #151 REF_invokeStatic coursier/core/shaded/fastparse/internal/RepImpls$.$anonfun$aggregateMsgInRep$1:(Lcoursier/core/shaded/fastparse/internal/Msgs;I)Ljava/lang/String;
      #114 ()Ljava/lang/String;
      #115 5
      #116 1
      #114 ()Ljava/lang/String;
  2: #123 REF_invokeStatic java/lang/invoke/LambdaMetafactory.altMetafactory:(Ljava/lang/invoke/MethodHandles$Lookup;Ljava/lang/String;Ljava/lang/invoke/MethodType;[Ljava/lang/Object;)Ljava/lang/invoke/CallSite;
    Method arguments:
      #107 ()Ljava/lang/Object;
      #156 REF_invokeStatic coursier/core/shaded/fastparse/internal/RepImpls$.$anonfun$aggregateMsgInRep$2:(Lcoursier/core/shaded/fastparse/internal/Msgs;I)Ljava/lang/String;
      #114 ()Ljava/lang/String;
      #115 5
      #116 1
      #114 ()Ljava/lang/String;
  3: #123 REF_invokeStatic java/lang/invoke/LambdaMetafactory.altMetafactory:(Ljava/lang/invoke/MethodHandles$Lookup;Ljava/lang/String;Ljava/lang/invoke/MethodType;[Ljava/lang/Object;)Ljava/lang/invoke/CallSite;
    Method arguments:
      #107 ()Ljava/lang/Object;
      #279 REF_invokeStatic coursier/core/shaded/fastparse/internal/RepImpls$.$anonfun$repX$1:(Lcoursier/core/shaded/fastparse/internal/Msgs;I)Ljava/lang/String;
      #114 ()Ljava/lang/String;
      #115 5
      #116 1
      #114 ()Ljava/lang/String;
  4: #123 REF_invokeStatic java/lang/invoke/LambdaMetafactory.altMetafactory:(Ljava/lang/invoke/MethodHandles$Lookup;Ljava/lang/String;Ljava/lang/invoke/MethodType;[Ljava/lang/Object;)Ljava/lang/invoke/CallSite;
    Method arguments:
      #107 ()Ljava/lang/Object;
      #324 REF_invokeStatic coursier/core/shaded/fastparse/internal/RepImpls$.$anonfun$rep$1:(Lcoursier/core/shaded/fastparse/internal/Msgs;I)Ljava/lang/String;
      #114 ()Ljava/lang/String;
      #115 5
      #116 1
      #114 ()Ljava/lang/String;
  5: #360 REF_invokeStatic scala/runtime/LambdaDeserialize.bootstrap:(Ljava/lang/invoke/MethodHandles$Lookup;Ljava/lang/String;Ljava/lang/invoke/MethodType;[Ljava/lang/invoke/MethodHandle;)Ljava/lang/invoke/CallSite;
    Method arguments:
      #151 REF_invokeStatic coursier/core/shaded/fastparse/internal/RepImpls$.$anonfun$aggregateMsgInRep$1:(Lcoursier/core/shaded/fastparse/internal/Msgs;I)Ljava/lang/String;
      #156 REF_invokeStatic coursier/core/shaded/fastparse/internal/RepImpls$.$anonfun$aggregateMsgInRep$2:(Lcoursier/core/shaded/fastparse/internal/Msgs;I)Ljava/lang/String;
      #112 REF_invokeStatic coursier/core/shaded/fastparse/internal/RepImpls$.$anonfun$aggregateMsgPostSep$1:(Lcoursier/core/shaded/fastparse/internal/Msgs;I)Ljava/lang/String;
      #324 REF_invokeStatic coursier/core/shaded/fastparse/internal/RepImpls$.$anonfun$rep$1:(Lcoursier/core/shaded/fastparse/internal/Msgs;I)Ljava/lang/String;
      #279 REF_invokeStatic coursier/core/shaded/fastparse/internal/RepImpls$.$anonfun$repX$1:(Lcoursier/core/shaded/fastparse/internal/Msgs;I)Ljava/lang/String;
  ScalaInlineInfo: length = 0x9A (unknown attribute)
   01 01 00 1E 00 94 00 6D 01 00 99 00 6D 01 00 6C
   00 6D 01 01 35 00 6D 01 00 D2 00 6D 01 00 19 00
   18 01 00 8F 00 90 01 00 65 00 66 01 00 BD 00 BE
   01 01 27 00 BE 01 01 30 00 BE 01 01 4E 00 BE 01
   00 AF 00 B0 01 00 AA 00 59 01 00 36 00 37 01 00
   45 00 46 01 00 4D 00 4E 01 00 54 00 55 01 00 61
   00 59 01 00 62 00 5C 01 00 63 00 59 01 00 64 00
   59 01 00 49 00 4A 01 00 49 00 52 01 00 58 00 59
   01 00 5B 00 5C 01 00 5E 00 59 01 00 60 00 59 01
   00 1E 00 1F 01 00 1E 00 43 01
  Scala: length = 0x0 (unknown attribute)

