Classfile /Users/mw/Projects/slang-braindump/.jar/jar11/assemble/slang-braindump/assemble/content/org/antlr/runtime/LegacyCommonTokenStream.class
  Last modified May 29, 2022; size 7574 bytes
  SHA-256 checksum 37197876b19344b61d61fc45d5693a0e6aba1e211599877ff41fe46849f68f06
  Compiled from "LegacyCommonTokenStream.java"
public class org.antlr.runtime.LegacyCommonTokenStream implements org.antlr.runtime.TokenStream
  minor version: 0
  major version: 49
  flags: (0x0021) ACC_PUBLIC, ACC_SUPER
  this_class: #61                         // org/antlr/runtime/LegacyCommonTokenStream
  super_class: #62                        // java/lang/Object
  interfaces: 1, fields: 9, methods: 35, attributes: 1
Constant pool:
    #1 = Methodref          #62.#155      // java/lang/Object."<init>":()V
    #2 = Fieldref           #61.#156      // org/antlr/runtime/LegacyCommonTokenStream.channel:I
    #3 = Fieldref           #61.#157      // org/antlr/runtime/LegacyCommonTokenStream.discardOffChannelTokens:Z
    #4 = Fieldref           #61.#158      // org/antlr/runtime/LegacyCommonTokenStream.range:I
    #5 = Fieldref           #61.#159      // org/antlr/runtime/LegacyCommonTokenStream.p:I
    #6 = Class              #160          // java/util/ArrayList
    #7 = Methodref          #6.#161       // java/util/ArrayList."<init>":(I)V
    #8 = Fieldref           #61.#162      // org/antlr/runtime/LegacyCommonTokenStream.tokens:Ljava/util/List;
    #9 = Methodref          #61.#155      // org/antlr/runtime/LegacyCommonTokenStream."<init>":()V
   #10 = Fieldref           #61.#163      // org/antlr/runtime/LegacyCommonTokenStream.tokenSource:Lorg/antlr/runtime/TokenSource;
   #11 = Methodref          #61.#164      // org/antlr/runtime/LegacyCommonTokenStream."<init>":(Lorg/antlr/runtime/TokenSource;)V
   #12 = InterfaceMethodref #165.#166     // java/util/List.clear:()V
   #13 = InterfaceMethodref #167.#168     // org/antlr/runtime/TokenSource.nextToken:()Lorg/antlr/runtime/Token;
   #14 = InterfaceMethodref #30.#169      // org/antlr/runtime/Token.getType:()I
   #15 = Fieldref           #61.#170      // org/antlr/runtime/LegacyCommonTokenStream.channelOverrideMap:Ljava/util/Map;
   #16 = Methodref          #18.#171      // java/lang/Integer.valueOf:(I)Ljava/lang/Integer;
   #17 = InterfaceMethodref #172.#173     // java/util/Map.get:(Ljava/lang/Object;)Ljava/lang/Object;
   #18 = Class              #174          // java/lang/Integer
   #19 = Methodref          #18.#175      // java/lang/Integer.intValue:()I
   #20 = InterfaceMethodref #30.#176      // org/antlr/runtime/Token.setChannel:(I)V
   #21 = Fieldref           #61.#177      // org/antlr/runtime/LegacyCommonTokenStream.discardSet:Ljava/util/Set;
   #22 = Methodref          #18.#161      // java/lang/Integer."<init>":(I)V
   #23 = InterfaceMethodref #178.#179     // java/util/Set.contains:(Ljava/lang/Object;)Z
   #24 = InterfaceMethodref #30.#180      // org/antlr/runtime/Token.getChannel:()I
   #25 = InterfaceMethodref #30.#181      // org/antlr/runtime/Token.setTokenIndex:(I)V
   #26 = InterfaceMethodref #165.#182     // java/util/List.add:(Ljava/lang/Object;)Z
   #27 = Methodref          #61.#183      // org/antlr/runtime/LegacyCommonTokenStream.skipOffTokenChannels:(I)I
   #28 = InterfaceMethodref #165.#184     // java/util/List.size:()I
   #29 = InterfaceMethodref #165.#185     // java/util/List.get:(I)Ljava/lang/Object;
   #30 = Class              #186          // org/antlr/runtime/Token
   #31 = Class              #187          // java/util/HashMap
   #32 = Methodref          #31.#155      // java/util/HashMap."<init>":()V
   #33 = InterfaceMethodref #172.#188     // java/util/Map.put:(Ljava/lang/Object;Ljava/lang/Object;)Ljava/lang/Object;
   #34 = Class              #189          // java/util/HashSet
   #35 = Methodref          #34.#155      // java/util/HashSet."<init>":()V
   #36 = InterfaceMethodref #178.#182     // java/util/Set.add:(Ljava/lang/Object;)Z
   #37 = Methodref          #61.#190      // org/antlr/runtime/LegacyCommonTokenStream.fillBuffer:()V
   #38 = Class              #191          // org/antlr/runtime/BitSet
   #39 = Methodref          #61.#192      // org/antlr/runtime/LegacyCommonTokenStream.getTokens:(IILorg/antlr/runtime/BitSet;)Ljava/util/List;
   #40 = Methodref          #6.#155       // java/util/ArrayList."<init>":()V
   #41 = Methodref          #38.#193      // org/antlr/runtime/BitSet.member:(I)Z
   #42 = InterfaceMethodref #165.#194     // java/util/List.isEmpty:()Z
   #43 = Methodref          #38.#195      // org/antlr/runtime/BitSet."<init>":(Ljava/util/List;)V
   #44 = Methodref          #38.#196      // org/antlr/runtime/BitSet.of:(I)Lorg/antlr/runtime/BitSet;
   #45 = Methodref          #61.#197      // org/antlr/runtime/LegacyCommonTokenStream.LB:(I)Lorg/antlr/runtime/Token;
   #46 = Methodref          #61.#198      // org/antlr/runtime/LegacyCommonTokenStream.skipOffTokenChannelsReverse:(I)I
   #47 = InterfaceMethodref #165.#199     // java/util/List.subList:(II)Ljava/util/List;
   #48 = Methodref          #61.#200      // org/antlr/runtime/LegacyCommonTokenStream.LT:(I)Lorg/antlr/runtime/Token;
   #49 = Methodref          #61.#201      // org/antlr/runtime/LegacyCommonTokenStream.index:()I
   #50 = Fieldref           #61.#202      // org/antlr/runtime/LegacyCommonTokenStream.lastMarker:I
   #51 = Methodref          #61.#203      // org/antlr/runtime/LegacyCommonTokenStream.seek:(I)V
   #52 = Methodref          #61.#204      // org/antlr/runtime/LegacyCommonTokenStream.getTokenSource:()Lorg/antlr/runtime/TokenSource;
   #53 = InterfaceMethodref #167.#205     // org/antlr/runtime/TokenSource.getSourceName:()Ljava/lang/String;
   #54 = Methodref          #61.#206      // org/antlr/runtime/LegacyCommonTokenStream.toString:(II)Ljava/lang/String;
   #55 = Class              #207          // java/lang/StringBuilder
   #56 = Methodref          #55.#155      // java/lang/StringBuilder."<init>":()V
   #57 = InterfaceMethodref #30.#208      // org/antlr/runtime/Token.getText:()Ljava/lang/String;
   #58 = Methodref          #55.#209      // java/lang/StringBuilder.append:(Ljava/lang/String;)Ljava/lang/StringBuilder;
   #59 = Methodref          #55.#210      // java/lang/StringBuilder.toString:()Ljava/lang/String;
   #60 = InterfaceMethodref #30.#211      // org/antlr/runtime/Token.getTokenIndex:()I
   #61 = Class              #212          // org/antlr/runtime/LegacyCommonTokenStream
   #62 = Class              #213          // java/lang/Object
   #63 = Class              #214          // org/antlr/runtime/TokenStream
   #64 = Utf8               tokenSource
   #65 = Utf8               Lorg/antlr/runtime/TokenSource;
   #66 = Utf8               tokens
   #67 = Utf8               Ljava/util/List;
   #68 = Utf8               Signature
   #69 = Utf8               Ljava/util/List<Lorg/antlr/runtime/Token;>;
   #70 = Utf8               channelOverrideMap
   #71 = Utf8               Ljava/util/Map;
   #72 = Utf8               Ljava/util/Map<Ljava/lang/Integer;Ljava/lang/Integer;>;
   #73 = Utf8               discardSet
   #74 = Utf8               Ljava/util/Set;
   #75 = Utf8               Ljava/util/Set<Ljava/lang/Integer;>;
   #76 = Utf8               channel
   #77 = Utf8               I
   #78 = Utf8               discardOffChannelTokens
   #79 = Utf8               Z
   #80 = Utf8               lastMarker
   #81 = Utf8               range
   #82 = Utf8               p
   #83 = Utf8               <init>
   #84 = Utf8               ()V
   #85 = Utf8               Code
   #86 = Utf8               LineNumberTable
   #87 = Utf8               LocalVariableTable
   #88 = Utf8               this
   #89 = Utf8               Lorg/antlr/runtime/LegacyCommonTokenStream;
   #90 = Utf8               (Lorg/antlr/runtime/TokenSource;)V
   #91 = Utf8               (Lorg/antlr/runtime/TokenSource;I)V
   #92 = Utf8               setTokenSource
   #93 = Utf8               fillBuffer
   #94 = Utf8               channelI
   #95 = Utf8               Ljava/lang/Integer;
   #96 = Utf8               discard
   #97 = Utf8               index
   #98 = Utf8               t
   #99 = Utf8               Lorg/antlr/runtime/Token;
  #100 = Utf8               consume
  #101 = Utf8               skipOffTokenChannels
  #102 = Utf8               (I)I
  #103 = Utf8               i
  #104 = Utf8               n
  #105 = Utf8               skipOffTokenChannelsReverse
  #106 = Utf8               setTokenTypeChannel
  #107 = Utf8               (II)V
  #108 = Utf8               ttype
  #109 = Utf8               discardTokenType
  #110 = Utf8               (I)V
  #111 = Utf8               (Z)V
  #112 = Utf8               getTokens
  #113 = Utf8               ()Ljava/util/List;
  #114 = Utf8               ()Ljava/util/List<+Lorg/antlr/runtime/Token;>;
  #115 = Utf8               (II)Ljava/util/List;
  #116 = Utf8               start
  #117 = Utf8               stop
  #118 = Utf8               (II)Ljava/util/List<+Lorg/antlr/runtime/Token;>;
  #119 = Utf8               (IILorg/antlr/runtime/BitSet;)Ljava/util/List;
  #120 = Utf8               types
  #121 = Utf8               Lorg/antlr/runtime/BitSet;
  #122 = Utf8               filteredTokens
  #123 = Utf8               LocalVariableTypeTable
  #124 = Utf8               (IILorg/antlr/runtime/BitSet;)Ljava/util/List<+Lorg/antlr/runtime/Token;>;
  #125 = Utf8               (IILjava/util/List;)Ljava/util/List;
  #126 = Utf8               Ljava/util/List<Ljava/lang/Integer;>;
  #127 = Utf8               (IILjava/util/List<Ljava/lang/Integer;>;)Ljava/util/List<+Lorg/antlr/runtime/Token;>;
  #128 = Utf8               (III)Ljava/util/List;
  #129 = Utf8               (III)Ljava/util/List<+Lorg/antlr/runtime/Token;>;
  #130 = Utf8               LT
  #131 = Utf8               (I)Lorg/antlr/runtime/Token;
  #132 = Utf8               k
  #133 = Utf8               LB
  #134 = Utf8               get
  #135 = Utf8               LA
  #136 = Utf8               mark
  #137 = Utf8               ()I
  #138 = Utf8               release
  #139 = Utf8               marker
  #140 = Utf8               size
  #141 = Utf8               rewind
  #142 = Utf8               reset
  #143 = Utf8               seek
  #144 = Utf8               getTokenSource
  #145 = Utf8               ()Lorg/antlr/runtime/TokenSource;
  #146 = Utf8               getSourceName
  #147 = Utf8               ()Ljava/lang/String;
  #148 = Utf8               toString
  #149 = Utf8               (II)Ljava/lang/String;
  #150 = Utf8               buf
  #151 = Utf8               Ljava/lang/StringBuilder;
  #152 = Utf8               (Lorg/antlr/runtime/Token;Lorg/antlr/runtime/Token;)Ljava/lang/String;
  #153 = Utf8               SourceFile
  #154 = Utf8               LegacyCommonTokenStream.java
  #155 = NameAndType        #83:#84       // "<init>":()V
  #156 = NameAndType        #76:#77       // channel:I
  #157 = NameAndType        #78:#79       // discardOffChannelTokens:Z
  #158 = NameAndType        #81:#77       // range:I
  #159 = NameAndType        #82:#77       // p:I
  #160 = Utf8               java/util/ArrayList
  #161 = NameAndType        #83:#110      // "<init>":(I)V
  #162 = NameAndType        #66:#67       // tokens:Ljava/util/List;
  #163 = NameAndType        #64:#65       // tokenSource:Lorg/antlr/runtime/TokenSource;
  #164 = NameAndType        #83:#90       // "<init>":(Lorg/antlr/runtime/TokenSource;)V
  #165 = Class              #215          // java/util/List
  #166 = NameAndType        #216:#84      // clear:()V
  #167 = Class              #217          // org/antlr/runtime/TokenSource
  #168 = NameAndType        #218:#219     // nextToken:()Lorg/antlr/runtime/Token;
  #169 = NameAndType        #220:#137     // getType:()I
  #170 = NameAndType        #70:#71       // channelOverrideMap:Ljava/util/Map;
  #171 = NameAndType        #221:#222     // valueOf:(I)Ljava/lang/Integer;
  #172 = Class              #223          // java/util/Map
  #173 = NameAndType        #134:#224     // get:(Ljava/lang/Object;)Ljava/lang/Object;
  #174 = Utf8               java/lang/Integer
  #175 = NameAndType        #225:#137     // intValue:()I
  #176 = NameAndType        #226:#110     // setChannel:(I)V
  #177 = NameAndType        #73:#74       // discardSet:Ljava/util/Set;
  #178 = Class              #227          // java/util/Set
  #179 = NameAndType        #228:#229     // contains:(Ljava/lang/Object;)Z
  #180 = NameAndType        #230:#137     // getChannel:()I
  #181 = NameAndType        #231:#110     // setTokenIndex:(I)V
  #182 = NameAndType        #232:#229     // add:(Ljava/lang/Object;)Z
  #183 = NameAndType        #101:#102     // skipOffTokenChannels:(I)I
  #184 = NameAndType        #140:#137     // size:()I
  #185 = NameAndType        #134:#233     // get:(I)Ljava/lang/Object;
  #186 = Utf8               org/antlr/runtime/Token
  #187 = Utf8               java/util/HashMap
  #188 = NameAndType        #234:#235     // put:(Ljava/lang/Object;Ljava/lang/Object;)Ljava/lang/Object;
  #189 = Utf8               java/util/HashSet
  #190 = NameAndType        #93:#84       // fillBuffer:()V
  #191 = Utf8               org/antlr/runtime/BitSet
  #192 = NameAndType        #112:#119     // getTokens:(IILorg/antlr/runtime/BitSet;)Ljava/util/List;
  #193 = NameAndType        #236:#237     // member:(I)Z
  #194 = NameAndType        #238:#239     // isEmpty:()Z
  #195 = NameAndType        #83:#240      // "<init>":(Ljava/util/List;)V
  #196 = NameAndType        #241:#242     // of:(I)Lorg/antlr/runtime/BitSet;
  #197 = NameAndType        #133:#131     // LB:(I)Lorg/antlr/runtime/Token;
  #198 = NameAndType        #105:#102     // skipOffTokenChannelsReverse:(I)I
  #199 = NameAndType        #243:#115     // subList:(II)Ljava/util/List;
  #200 = NameAndType        #130:#131     // LT:(I)Lorg/antlr/runtime/Token;
  #201 = NameAndType        #97:#137      // index:()I
  #202 = NameAndType        #80:#77       // lastMarker:I
  #203 = NameAndType        #143:#110     // seek:(I)V
  #204 = NameAndType        #144:#145     // getTokenSource:()Lorg/antlr/runtime/TokenSource;
  #205 = NameAndType        #146:#147     // getSourceName:()Ljava/lang/String;
  #206 = NameAndType        #148:#149     // toString:(II)Ljava/lang/String;
  #207 = Utf8               java/lang/StringBuilder
  #208 = NameAndType        #244:#147     // getText:()Ljava/lang/String;
  #209 = NameAndType        #245:#246     // append:(Ljava/lang/String;)Ljava/lang/StringBuilder;
  #210 = NameAndType        #148:#147     // toString:()Ljava/lang/String;
  #211 = NameAndType        #247:#137     // getTokenIndex:()I
  #212 = Utf8               org/antlr/runtime/LegacyCommonTokenStream
  #213 = Utf8               java/lang/Object
  #214 = Utf8               org/antlr/runtime/TokenStream
  #215 = Utf8               java/util/List
  #216 = Utf8               clear
  #217 = Utf8               org/antlr/runtime/TokenSource
  #218 = Utf8               nextToken
  #219 = Utf8               ()Lorg/antlr/runtime/Token;
  #220 = Utf8               getType
  #221 = Utf8               valueOf
  #222 = Utf8               (I)Ljava/lang/Integer;
  #223 = Utf8               java/util/Map
  #224 = Utf8               (Ljava/lang/Object;)Ljava/lang/Object;
  #225 = Utf8               intValue
  #226 = Utf8               setChannel
  #227 = Utf8               java/util/Set
  #228 = Utf8               contains
  #229 = Utf8               (Ljava/lang/Object;)Z
  #230 = Utf8               getChannel
  #231 = Utf8               setTokenIndex
  #232 = Utf8               add
  #233 = Utf8               (I)Ljava/lang/Object;
  #234 = Utf8               put
  #235 = Utf8               (Ljava/lang/Object;Ljava/lang/Object;)Ljava/lang/Object;
  #236 = Utf8               member
  #237 = Utf8               (I)Z
  #238 = Utf8               isEmpty
  #239 = Utf8               ()Z
  #240 = Utf8               (Ljava/util/List;)V
  #241 = Utf8               of
  #242 = Utf8               (I)Lorg/antlr/runtime/BitSet;
  #243 = Utf8               subList
  #244 = Utf8               getText
  #245 = Utf8               append
  #246 = Utf8               (Ljava/lang/String;)Ljava/lang/StringBuilder;
  #247 = Utf8               getTokenIndex
{
  protected org.antlr.runtime.TokenSource tokenSource;
    descriptor: Lorg/antlr/runtime/TokenSource;
    flags: (0x0004) ACC_PROTECTED

  protected java.util.List<org.antlr.runtime.Token> tokens;
    descriptor: Ljava/util/List;
    flags: (0x0004) ACC_PROTECTED
    Signature: #69                          // Ljava/util/List<Lorg/antlr/runtime/Token;>;

  protected java.util.Map<java.lang.Integer, java.lang.Integer> channelOverrideMap;
    descriptor: Ljava/util/Map;
    flags: (0x0004) ACC_PROTECTED
    Signature: #72                          // Ljava/util/Map<Ljava/lang/Integer;Ljava/lang/Integer;>;

  protected java.util.Set<java.lang.Integer> discardSet;
    descriptor: Ljava/util/Set;
    flags: (0x0004) ACC_PROTECTED
    Signature: #75                          // Ljava/util/Set<Ljava/lang/Integer;>;

  protected int channel;
    descriptor: I
    flags: (0x0004) ACC_PROTECTED

  protected boolean discardOffChannelTokens;
    descriptor: Z
    flags: (0x0004) ACC_PROTECTED

  protected int lastMarker;
    descriptor: I
    flags: (0x0004) ACC_PROTECTED

  protected int range;
    descriptor: I
    flags: (0x0004) ACC_PROTECTED

  protected int p;
    descriptor: I
    flags: (0x0004) ACC_PROTECTED

  public org.antlr.runtime.LegacyCommonTokenStream();
    descriptor: ()V
    flags: (0x0001) ACC_PUBLIC
    Code:
      stack=4, locals=1, args_size=1
         0: aload_0
         1: invokespecial #1                  // Method java/lang/Object."<init>":()V
         4: aload_0
         5: iconst_0
         6: putfield      #2                  // Field channel:I
         9: aload_0
        10: iconst_0
        11: putfield      #3                  // Field discardOffChannelTokens:Z
        14: aload_0
        15: iconst_m1
        16: putfield      #4                  // Field range:I
        19: aload_0
        20: iconst_m1
        21: putfield      #5                  // Field p:I
        24: aload_0
        25: new           #6                  // class java/util/ArrayList
        28: dup
        29: sipush        500
        32: invokespecial #7                  // Method java/util/ArrayList."<init>":(I)V
        35: putfield      #8                  // Field tokens:Ljava/util/List;
        38: return
      LineNumberTable:
        line 69: 0
        line 54: 4
        line 57: 9
        line 62: 14
        line 67: 19
        line 70: 24
        line 71: 38
      LocalVariableTable:
        Start  Length  Slot  Name   Signature
            0      39     0  this   Lorg/antlr/runtime/LegacyCommonTokenStream;

  public org.antlr.runtime.LegacyCommonTokenStream(org.antlr.runtime.TokenSource);
    descriptor: (Lorg/antlr/runtime/TokenSource;)V
    flags: (0x0001) ACC_PUBLIC
    Code:
      stack=2, locals=2, args_size=2
         0: aload_0
         1: invokespecial #9                  // Method "<init>":()V
         4: aload_0
         5: aload_1
         6: putfield      #10                 // Field tokenSource:Lorg/antlr/runtime/TokenSource;
         9: return
      LineNumberTable:
        line 74: 0
        line 75: 4
        line 76: 9
      LocalVariableTable:
        Start  Length  Slot  Name   Signature
            0      10     0  this   Lorg/antlr/runtime/LegacyCommonTokenStream;
            0      10     1 tokenSource   Lorg/antlr/runtime/TokenSource;

  public org.antlr.runtime.LegacyCommonTokenStream(org.antlr.runtime.TokenSource, int);
    descriptor: (Lorg/antlr/runtime/TokenSource;I)V
    flags: (0x0001) ACC_PUBLIC
    Code:
      stack=2, locals=3, args_size=3
         0: aload_0
         1: aload_1
         2: invokespecial #11                 // Method "<init>":(Lorg/antlr/runtime/TokenSource;)V
         5: aload_0
         6: iload_2
         7: putfield      #2                  // Field channel:I
        10: return
      LineNumberTable:
        line 79: 0
        line 80: 5
        line 81: 10
      LocalVariableTable:
        Start  Length  Slot  Name   Signature
            0      11     0  this   Lorg/antlr/runtime/LegacyCommonTokenStream;
            0      11     1 tokenSource   Lorg/antlr/runtime/TokenSource;
            0      11     2 channel   I

  public void setTokenSource(org.antlr.runtime.TokenSource);
    descriptor: (Lorg/antlr/runtime/TokenSource;)V
    flags: (0x0001) ACC_PUBLIC
    Code:
      stack=2, locals=2, args_size=2
         0: aload_0
         1: aload_1
         2: putfield      #10                 // Field tokenSource:Lorg/antlr/runtime/TokenSource;
         5: aload_0
         6: getfield      #8                  // Field tokens:Ljava/util/List;
         9: invokeinterface #12,  1           // InterfaceMethod java/util/List.clear:()V
        14: aload_0
        15: iconst_m1
        16: putfield      #5                  // Field p:I
        19: aload_0
        20: iconst_0
        21: putfield      #2                  // Field channel:I
        24: return
      LineNumberTable:
        line 85: 0
        line 86: 5
        line 87: 14
        line 88: 19
        line 89: 24
      LocalVariableTable:
        Start  Length  Slot  Name   Signature
            0      25     0  this   Lorg/antlr/runtime/LegacyCommonTokenStream;
            0      25     1 tokenSource   Lorg/antlr/runtime/TokenSource;

  protected void fillBuffer();
    descriptor: ()V
    flags: (0x0004) ACC_PROTECTED
    Code:
      stack=4, locals=5, args_size=1
         0: iconst_0
         1: istore_1
         2: aload_0
         3: getfield      #10                 // Field tokenSource:Lorg/antlr/runtime/TokenSource;
         6: invokeinterface #13,  1           // InterfaceMethod org/antlr/runtime/TokenSource.nextToken:()Lorg/antlr/runtime/Token;
        11: astore_2
        12: aload_2
        13: ifnull        171
        16: aload_2
        17: invokeinterface #14,  1           // InterfaceMethod org/antlr/runtime/Token.getType:()I
        22: iconst_m1
        23: if_icmpeq     171
        26: iconst_0
        27: istore_3
        28: aload_0
        29: getfield      #15                 // Field channelOverrideMap:Ljava/util/Map;
        32: ifnull        74
        35: aload_0
        36: getfield      #15                 // Field channelOverrideMap:Ljava/util/Map;
        39: aload_2
        40: invokeinterface #14,  1           // InterfaceMethod org/antlr/runtime/Token.getType:()I
        45: invokestatic  #16                 // Method java/lang/Integer.valueOf:(I)Ljava/lang/Integer;
        48: invokeinterface #17,  2           // InterfaceMethod java/util/Map.get:(Ljava/lang/Object;)Ljava/lang/Object;
        53: checkcast     #18                 // class java/lang/Integer
        56: astore        4
        58: aload         4
        60: ifnull        74
        63: aload_2
        64: aload         4
        66: invokevirtual #19                 // Method java/lang/Integer.intValue:()I
        69: invokeinterface #20,  2           // InterfaceMethod org/antlr/runtime/Token.setChannel:(I)V
        74: aload_0
        75: getfield      #21                 // Field discardSet:Ljava/util/Set;
        78: ifnull        111
        81: aload_0
        82: getfield      #21                 // Field discardSet:Ljava/util/Set;
        85: new           #18                 // class java/lang/Integer
        88: dup
        89: aload_2
        90: invokeinterface #14,  1           // InterfaceMethod org/antlr/runtime/Token.getType:()I
        95: invokespecial #22                 // Method java/lang/Integer."<init>":(I)V
        98: invokeinterface #23,  2           // InterfaceMethod java/util/Set.contains:(Ljava/lang/Object;)Z
       103: ifeq          111
       106: iconst_1
       107: istore_3
       108: goto          133
       111: aload_0
       112: getfield      #3                  // Field discardOffChannelTokens:Z
       115: ifeq          133
       118: aload_2
       119: invokeinterface #24,  1           // InterfaceMethod org/antlr/runtime/Token.getChannel:()I
       124: aload_0
       125: getfield      #2                  // Field channel:I
       128: if_icmpeq     133
       131: iconst_1
       132: istore_3
       133: iload_3
       134: ifne          158
       137: aload_2
       138: iload_1
       139: invokeinterface #25,  2           // InterfaceMethod org/antlr/runtime/Token.setTokenIndex:(I)V
       144: aload_0
       145: getfield      #8                  // Field tokens:Ljava/util/List;
       148: aload_2
       149: invokeinterface #26,  2           // InterfaceMethod java/util/List.add:(Ljava/lang/Object;)Z
       154: pop
       155: iinc          1, 1
       158: aload_0
       159: getfield      #10                 // Field tokenSource:Lorg/antlr/runtime/TokenSource;
       162: invokeinterface #13,  1           // InterfaceMethod org/antlr/runtime/TokenSource.nextToken:()Lorg/antlr/runtime/Token;
       167: astore_2
       168: goto          12
       171: aload_0
       172: iconst_0
       173: putfield      #5                  // Field p:I
       176: aload_0
       177: aload_0
       178: aload_0
       179: getfield      #5                  // Field p:I
       182: invokevirtual #27                 // Method skipOffTokenChannels:(I)I
       185: putfield      #5                  // Field p:I
       188: return
      LineNumberTable:
        line 96: 0
        line 97: 2
        line 98: 12
        line 99: 26
        line 101: 28
        line 102: 35
        line 103: 58
        line 104: 63
        line 107: 74
        line 110: 106
        line 112: 111
        line 113: 131
        line 115: 133
        line 116: 137
        line 117: 144
        line 118: 155
        line 120: 158
        line 121: 168
        line 123: 171
        line 124: 176
        line 125: 188
      LocalVariableTable:
        Start  Length  Slot  Name   Signature
           58      16     4 channelI   Ljava/lang/Integer;
           28     140     3 discard   Z
            0     189     0  this   Lorg/antlr/runtime/LegacyCommonTokenStream;
            2     187     1 index   I
           12     177     2     t   Lorg/antlr/runtime/Token;

  public void consume();
    descriptor: ()V
    flags: (0x0001) ACC_PUBLIC
    Code:
      stack=3, locals=1, args_size=1
         0: aload_0
         1: getfield      #5                  // Field p:I
         4: aload_0
         5: getfield      #8                  // Field tokens:Ljava/util/List;
         8: invokeinterface #28,  1           // InterfaceMethod java/util/List.size:()I
        13: if_icmpge     38
        16: aload_0
        17: dup
        18: getfield      #5                  // Field p:I
        21: iconst_1
        22: iadd
        23: putfield      #5                  // Field p:I
        26: aload_0
        27: aload_0
        28: aload_0
        29: getfield      #5                  // Field p:I
        32: invokevirtual #27                 // Method skipOffTokenChannels:(I)I
        35: putfield      #5                  // Field p:I
        38: return
      LineNumberTable:
        line 136: 0
        line 137: 16
        line 138: 26
        line 140: 38
      LocalVariableTable:
        Start  Length  Slot  Name   Signature
            0      39     0  this   Lorg/antlr/runtime/LegacyCommonTokenStream;

  protected int skipOffTokenChannels(int);
    descriptor: (I)I
    flags: (0x0004) ACC_PROTECTED
    Code:
      stack=2, locals=3, args_size=2
         0: aload_0
         1: getfield      #8                  // Field tokens:Ljava/util/List;
         4: invokeinterface #28,  1           // InterfaceMethod java/util/List.size:()I
         9: istore_2
        10: iload_1
        11: iload_2
        12: if_icmpge     46
        15: aload_0
        16: getfield      #8                  // Field tokens:Ljava/util/List;
        19: iload_1
        20: invokeinterface #29,  2           // InterfaceMethod java/util/List.get:(I)Ljava/lang/Object;
        25: checkcast     #30                 // class org/antlr/runtime/Token
        28: invokeinterface #24,  1           // InterfaceMethod org/antlr/runtime/Token.getChannel:()I
        33: aload_0
        34: getfield      #2                  // Field channel:I
        37: if_icmpeq     46
        40: iinc          1, 1
        43: goto          10
        46: iload_1
        47: ireturn
      LineNumberTable:
        line 146: 0
        line 147: 10
        line 148: 40
        line 150: 46
      LocalVariableTable:
        Start  Length  Slot  Name   Signature
            0      48     0  this   Lorg/antlr/runtime/LegacyCommonTokenStream;
            0      48     1     i   I
           10      38     2     n   I

  protected int skipOffTokenChannelsReverse(int);
    descriptor: (I)I
    flags: (0x0004) ACC_PROTECTED
    Code:
      stack=2, locals=2, args_size=2
         0: iload_1
         1: iflt          35
         4: aload_0
         5: getfield      #8                  // Field tokens:Ljava/util/List;
         8: iload_1
         9: invokeinterface #29,  2           // InterfaceMethod java/util/List.get:(I)Ljava/lang/Object;
        14: checkcast     #30                 // class org/antlr/runtime/Token
        17: invokeinterface #24,  1           // InterfaceMethod org/antlr/runtime/Token.getChannel:()I
        22: aload_0
        23: getfield      #2                  // Field channel:I
        26: if_icmpeq     35
        29: iinc          1, -1
        32: goto          0
        35: iload_1
        36: ireturn
      LineNumberTable:
        line 154: 0
        line 155: 29
        line 157: 35
      LocalVariableTable:
        Start  Length  Slot  Name   Signature
            0      37     0  this   Lorg/antlr/runtime/LegacyCommonTokenStream;
            0      37     1     i   I

  public void setTokenTypeChannel(int, int);
    descriptor: (II)V
    flags: (0x0001) ACC_PUBLIC
    Code:
      stack=3, locals=3, args_size=3
         0: aload_0
         1: getfield      #15                 // Field channelOverrideMap:Ljava/util/Map;
         4: ifnonnull     18
         7: aload_0
         8: new           #31                 // class java/util/HashMap
        11: dup
        12: invokespecial #32                 // Method java/util/HashMap."<init>":()V
        15: putfield      #15                 // Field channelOverrideMap:Ljava/util/Map;
        18: aload_0
        19: getfield      #15                 // Field channelOverrideMap:Ljava/util/Map;
        22: iload_1
        23: invokestatic  #16                 // Method java/lang/Integer.valueOf:(I)Ljava/lang/Integer;
        26: iload_2
        27: invokestatic  #16                 // Method java/lang/Integer.valueOf:(I)Ljava/lang/Integer;
        30: invokeinterface #33,  3           // InterfaceMethod java/util/Map.put:(Ljava/lang/Object;Ljava/lang/Object;)Ljava/lang/Object;
        35: pop
        36: return
      LineNumberTable:
        line 167: 0
        line 168: 7
        line 170: 18
        line 171: 36
      LocalVariableTable:
        Start  Length  Slot  Name   Signature
            0      37     0  this   Lorg/antlr/runtime/LegacyCommonTokenStream;
            0      37     1 ttype   I
            0      37     2 channel   I

  public void discardTokenType(int);
    descriptor: (I)V
    flags: (0x0001) ACC_PUBLIC
    Code:
      stack=3, locals=2, args_size=2
         0: aload_0
         1: getfield      #21                 // Field discardSet:Ljava/util/Set;
         4: ifnonnull     18
         7: aload_0
         8: new           #34                 // class java/util/HashSet
        11: dup
        12: invokespecial #35                 // Method java/util/HashSet."<init>":()V
        15: putfield      #21                 // Field discardSet:Ljava/util/Set;
        18: aload_0
        19: getfield      #21                 // Field discardSet:Ljava/util/Set;
        22: iload_1
        23: invokestatic  #16                 // Method java/lang/Integer.valueOf:(I)Ljava/lang/Integer;
        26: invokeinterface #36,  2           // InterfaceMethod java/util/Set.add:(Ljava/lang/Object;)Z
        31: pop
        32: return
      LineNumberTable:
        line 174: 0
        line 175: 7
        line 177: 18
        line 178: 32
      LocalVariableTable:
        Start  Length  Slot  Name   Signature
            0      33     0  this   Lorg/antlr/runtime/LegacyCommonTokenStream;
            0      33     1 ttype   I

  public void discardOffChannelTokens(boolean);
    descriptor: (Z)V
    flags: (0x0001) ACC_PUBLIC
    Code:
      stack=2, locals=2, args_size=2
         0: aload_0
         1: iload_1
         2: putfield      #3                  // Field discardOffChannelTokens:Z
         5: return
      LineNumberTable:
        line 181: 0
        line 182: 5
      LocalVariableTable:
        Start  Length  Slot  Name   Signature
            0       6     0  this   Lorg/antlr/runtime/LegacyCommonTokenStream;
            0       6     1 discardOffChannelTokens   Z

  public java.util.List<? extends org.antlr.runtime.Token> getTokens();
    descriptor: ()Ljava/util/List;
    flags: (0x0001) ACC_PUBLIC
    Code:
      stack=2, locals=1, args_size=1
         0: aload_0
         1: getfield      #5                  // Field p:I
         4: iconst_m1
         5: if_icmpne     12
         8: aload_0
         9: invokevirtual #37                 // Method fillBuffer:()V
        12: aload_0
        13: getfield      #8                  // Field tokens:Ljava/util/List;
        16: areturn
      LineNumberTable:
        line 185: 0
        line 186: 8
        line 188: 12
      LocalVariableTable:
        Start  Length  Slot  Name   Signature
            0      17     0  this   Lorg/antlr/runtime/LegacyCommonTokenStream;
    Signature: #114                         // ()Ljava/util/List<+Lorg/antlr/runtime/Token;>;

  public java.util.List<? extends org.antlr.runtime.Token> getTokens(int, int);
    descriptor: (II)Ljava/util/List;
    flags: (0x0001) ACC_PUBLIC
    Code:
      stack=4, locals=3, args_size=3
         0: aload_0
         1: iload_1
         2: iload_2
         3: aconst_null
         4: checkcast     #38                 // class org/antlr/runtime/BitSet
         7: invokevirtual #39                 // Method getTokens:(IILorg/antlr/runtime/BitSet;)Ljava/util/List;
        10: areturn
      LineNumberTable:
        line 192: 0
      LocalVariableTable:
        Start  Length  Slot  Name   Signature
            0      11     0  this   Lorg/antlr/runtime/LegacyCommonTokenStream;
            0      11     1 start   I
            0      11     2  stop   I
    Signature: #118                         // (II)Ljava/util/List<+Lorg/antlr/runtime/Token;>;

  public java.util.List<? extends org.antlr.runtime.Token> getTokens(int, int, org.antlr.runtime.BitSet);
    descriptor: (IILorg/antlr/runtime/BitSet;)Ljava/util/List;
    flags: (0x0001) ACC_PUBLIC
    Code:
      stack=2, locals=7, args_size=4
         0: aload_0
         1: getfield      #5                  // Field p:I
         4: iconst_m1
         5: if_icmpne     12
         8: aload_0
         9: invokevirtual #37                 // Method fillBuffer:()V
        12: iload_2
        13: aload_0
        14: getfield      #8                  // Field tokens:Ljava/util/List;
        17: invokeinterface #28,  1           // InterfaceMethod java/util/List.size:()I
        22: if_icmplt     37
        25: aload_0
        26: getfield      #8                  // Field tokens:Ljava/util/List;
        29: invokeinterface #28,  1           // InterfaceMethod java/util/List.size:()I
        34: iconst_1
        35: isub
        36: istore_2
        37: iload_1
        38: ifge          43
        41: iconst_0
        42: istore_1
        43: iload_1
        44: iload_2
        45: if_icmple     50
        48: aconst_null
        49: areturn
        50: new           #6                  // class java/util/ArrayList
        53: dup
        54: invokespecial #40                 // Method java/util/ArrayList."<init>":()V
        57: astore        4
        59: iload_1
        60: istore        5
        62: iload         5
        64: iload_2
        65: if_icmpgt     118
        68: aload_0
        69: getfield      #8                  // Field tokens:Ljava/util/List;
        72: iload         5
        74: invokeinterface #29,  2           // InterfaceMethod java/util/List.get:(I)Ljava/lang/Object;
        79: checkcast     #30                 // class org/antlr/runtime/Token
        82: astore        6
        84: aload_3
        85: ifnull        102
        88: aload_3
        89: aload         6
        91: invokeinterface #14,  1           // InterfaceMethod org/antlr/runtime/Token.getType:()I
        96: invokevirtual #41                 // Method org/antlr/runtime/BitSet.member:(I)Z
        99: ifeq          112
       102: aload         4
       104: aload         6
       106: invokeinterface #26,  2           // InterfaceMethod java/util/List.add:(Ljava/lang/Object;)Z
       111: pop
       112: iinc          5, 1
       115: goto          62
       118: aload         4
       120: invokeinterface #42,  1           // InterfaceMethod java/util/List.isEmpty:()Z
       125: ifeq          131
       128: aconst_null
       129: astore        4
       131: aload         4
       133: areturn
      LineNumberTable:
        line 200: 0
        line 201: 8
        line 203: 12
        line 204: 25
        line 206: 37
        line 207: 41
        line 209: 43
        line 210: 48
        line 214: 50
        line 215: 59
        line 216: 68
        line 217: 84
        line 218: 102
        line 215: 112
        line 221: 118
        line 222: 128
        line 224: 131
      LocalVariableTable:
        Start  Length  Slot  Name   Signature
           84      28     6     t   Lorg/antlr/runtime/Token;
           62      56     5     i   I
            0     134     0  this   Lorg/antlr/runtime/LegacyCommonTokenStream;
            0     134     1 start   I
            0     134     2  stop   I
            0     134     3 types   Lorg/antlr/runtime/BitSet;
           59      75     4 filteredTokens   Ljava/util/List;
      LocalVariableTypeTable:
        Start  Length  Slot  Name   Signature
           59      75     4 filteredTokens   Ljava/util/List<Lorg/antlr/runtime/Token;>;
    Signature: #124                         // (IILorg/antlr/runtime/BitSet;)Ljava/util/List<+Lorg/antlr/runtime/Token;>;

  public java.util.List<? extends org.antlr.runtime.Token> getTokens(int, int, java.util.List<java.lang.Integer>);
    descriptor: (IILjava/util/List;)Ljava/util/List;
    flags: (0x0001) ACC_PUBLIC
    Code:
      stack=6, locals=4, args_size=4
         0: aload_0
         1: iload_1
         2: iload_2
         3: new           #38                 // class org/antlr/runtime/BitSet
         6: dup
         7: aload_3
         8: invokespecial #43                 // Method org/antlr/runtime/BitSet."<init>":(Ljava/util/List;)V
        11: invokevirtual #39                 // Method getTokens:(IILorg/antlr/runtime/BitSet;)Ljava/util/List;
        14: areturn
      LineNumberTable:
        line 228: 0
      LocalVariableTable:
        Start  Length  Slot  Name   Signature
            0      15     0  this   Lorg/antlr/runtime/LegacyCommonTokenStream;
            0      15     1 start   I
            0      15     2  stop   I
            0      15     3 types   Ljava/util/List;
      LocalVariableTypeTable:
        Start  Length  Slot  Name   Signature
            0      15     3 types   Ljava/util/List<Ljava/lang/Integer;>;
    Signature: #127                         // (IILjava/util/List<Ljava/lang/Integer;>;)Ljava/util/List<+Lorg/antlr/runtime/Token;>;

  public java.util.List<? extends org.antlr.runtime.Token> getTokens(int, int, int);
    descriptor: (III)Ljava/util/List;
    flags: (0x0001) ACC_PUBLIC
    Code:
      stack=4, locals=4, args_size=4
         0: aload_0
         1: iload_1
         2: iload_2
         3: iload_3
         4: invokestatic  #44                 // Method org/antlr/runtime/BitSet.of:(I)Lorg/antlr/runtime/BitSet;
         7: invokevirtual #39                 // Method getTokens:(IILorg/antlr/runtime/BitSet;)Ljava/util/List;
        10: areturn
      LineNumberTable:
        line 232: 0
      LocalVariableTable:
        Start  Length  Slot  Name   Signature
            0      11     0  this   Lorg/antlr/runtime/LegacyCommonTokenStream;
            0      11     1 start   I
            0      11     2  stop   I
            0      11     3 ttype   I
    Signature: #129                         // (III)Ljava/util/List<+Lorg/antlr/runtime/Token;>;

  public org.antlr.runtime.Token LT(int);
    descriptor: (I)Lorg/antlr/runtime/Token;
    flags: (0x0001) ACC_PUBLIC
    Code:
      stack=3, locals=4, args_size=2
         0: aload_0
         1: getfield      #5                  // Field p:I
         4: iconst_m1
         5: if_icmpne     12
         8: aload_0
         9: invokevirtual #37                 // Method fillBuffer:()V
        12: iload_1
        13: ifne          18
        16: aconst_null
        17: areturn
        18: iload_1
        19: ifge          29
        22: aload_0
        23: iload_1
        24: ineg
        25: invokevirtual #45                 // Method LB:(I)Lorg/antlr/runtime/Token;
        28: areturn
        29: aload_0
        30: getfield      #5                  // Field p:I
        33: iload_1
        34: iadd
        35: iconst_1
        36: isub
        37: aload_0
        38: getfield      #8                  // Field tokens:Ljava/util/List;
        41: invokeinterface #28,  1           // InterfaceMethod java/util/List.size:()I
        46: if_icmplt     73
        49: aload_0
        50: getfield      #8                  // Field tokens:Ljava/util/List;
        53: aload_0
        54: getfield      #8                  // Field tokens:Ljava/util/List;
        57: invokeinterface #28,  1           // InterfaceMethod java/util/List.size:()I
        62: iconst_1
        63: isub
        64: invokeinterface #29,  2           // InterfaceMethod java/util/List.get:(I)Ljava/lang/Object;
        69: checkcast     #30                 // class org/antlr/runtime/Token
        72: areturn
        73: aload_0
        74: getfield      #5                  // Field p:I
        77: istore_2
        78: iconst_1
        79: istore_3
        80: iload_3
        81: iload_1
        82: if_icmpge     99
        85: aload_0
        86: iload_2
        87: iconst_1
        88: iadd
        89: invokevirtual #27                 // Method skipOffTokenChannels:(I)I
        92: istore_2
        93: iinc          3, 1
        96: goto          80
        99: iload_2
       100: aload_0
       101: getfield      #8                  // Field tokens:Ljava/util/List;
       104: invokeinterface #28,  1           // InterfaceMethod java/util/List.size:()I
       109: if_icmplt     136
       112: aload_0
       113: getfield      #8                  // Field tokens:Ljava/util/List;
       116: aload_0
       117: getfield      #8                  // Field tokens:Ljava/util/List;
       120: invokeinterface #28,  1           // InterfaceMethod java/util/List.size:()I
       125: iconst_1
       126: isub
       127: invokeinterface #29,  2           // InterfaceMethod java/util/List.get:(I)Ljava/lang/Object;
       132: checkcast     #30                 // class org/antlr/runtime/Token
       135: areturn
       136: iload_2
       137: aload_0
       138: getfield      #4                  // Field range:I
       141: if_icmple     149
       144: aload_0
       145: iload_2
       146: putfield      #4                  // Field range:I
       149: aload_0
       150: getfield      #8                  // Field tokens:Ljava/util/List;
       153: iload_2
       154: invokeinterface #29,  2           // InterfaceMethod java/util/List.get:(I)Ljava/lang/Object;
       159: checkcast     #30                 // class org/antlr/runtime/Token
       162: areturn
      LineNumberTable:
        line 240: 0
        line 241: 8
        line 243: 12
        line 244: 16
        line 246: 18
        line 247: 22
        line 250: 29
        line 251: 49
        line 254: 73
        line 255: 78
        line 257: 80
        line 259: 85
        line 260: 93
        line 262: 99
        line 263: 112
        line 266: 136
        line 267: 149
      LocalVariableTable:
        Start  Length  Slot  Name   Signature
            0     163     0  this   Lorg/antlr/runtime/LegacyCommonTokenStream;
            0     163     1     k   I
           78      85     2     i   I
           80      83     3     n   I

  protected org.antlr.runtime.Token LB(int);
    descriptor: (I)Lorg/antlr/runtime/Token;
    flags: (0x0004) ACC_PROTECTED
    Code:
      stack=3, locals=4, args_size=2
         0: aload_0
         1: getfield      #5                  // Field p:I
         4: iconst_m1
         5: if_icmpne     12
         8: aload_0
         9: invokevirtual #37                 // Method fillBuffer:()V
        12: iload_1
        13: ifne          18
        16: aconst_null
        17: areturn
        18: aload_0
        19: getfield      #5                  // Field p:I
        22: iload_1
        23: isub
        24: ifge          29
        27: aconst_null
        28: areturn
        29: aload_0
        30: getfield      #5                  // Field p:I
        33: istore_2
        34: iconst_1
        35: istore_3
        36: iload_3
        37: iload_1
        38: if_icmpgt     55
        41: aload_0
        42: iload_2
        43: iconst_1
        44: isub
        45: invokevirtual #46                 // Method skipOffTokenChannelsReverse:(I)I
        48: istore_2
        49: iinc          3, 1
        52: goto          36
        55: iload_2
        56: ifge          61
        59: aconst_null
        60: areturn
        61: aload_0
        62: getfield      #8                  // Field tokens:Ljava/util/List;
        65: iload_2
        66: invokeinterface #29,  2           // InterfaceMethod java/util/List.get:(I)Ljava/lang/Object;
        71: checkcast     #30                 // class org/antlr/runtime/Token
        74: areturn
      LineNumberTable:
        line 273: 0
        line 274: 8
        line 276: 12
        line 277: 16
        line 279: 18
        line 280: 27
        line 283: 29
        line 284: 34
        line 286: 36
        line 288: 41
        line 289: 49
        line 291: 55
        line 292: 59
        line 294: 61
      LocalVariableTable:
        Start  Length  Slot  Name   Signature
            0      75     0  this   Lorg/antlr/runtime/LegacyCommonTokenStream;
            0      75     1     k   I
           34      41     2     i   I
           36      39     3     n   I

  public org.antlr.runtime.Token get(int);
    descriptor: (I)Lorg/antlr/runtime/Token;
    flags: (0x0001) ACC_PUBLIC
    Code:
      stack=2, locals=2, args_size=2
         0: aload_0
         1: getfield      #8                  // Field tokens:Ljava/util/List;
         4: iload_1
         5: invokeinterface #29,  2           // InterfaceMethod java/util/List.get:(I)Ljava/lang/Object;
        10: checkcast     #30                 // class org/antlr/runtime/Token
        13: areturn
      LineNumberTable:
        line 302: 0
      LocalVariableTable:
        Start  Length  Slot  Name   Signature
            0      14     0  this   Lorg/antlr/runtime/LegacyCommonTokenStream;
            0      14     1     i   I

  public java.util.List<? extends org.antlr.runtime.Token> get(int, int);
    descriptor: (II)Ljava/util/List;
    flags: (0x0001) ACC_PUBLIC
    Code:
      stack=3, locals=3, args_size=3
         0: aload_0
         1: getfield      #5                  // Field p:I
         4: iconst_m1
         5: if_icmpne     12
         8: aload_0
         9: invokevirtual #37                 // Method fillBuffer:()V
        12: iload_1
        13: iflt          20
        16: iload_2
        17: ifge          22
        20: aconst_null
        21: areturn
        22: aload_0
        23: getfield      #8                  // Field tokens:Ljava/util/List;
        26: iload_1
        27: iload_2
        28: invokeinterface #47,  3           // InterfaceMethod java/util/List.subList:(II)Ljava/util/List;
        33: areturn
      LineNumberTable:
        line 307: 0
        line 308: 12
        line 309: 22
      LocalVariableTable:
        Start  Length  Slot  Name   Signature
            0      34     0  this   Lorg/antlr/runtime/LegacyCommonTokenStream;
            0      34     1 start   I
            0      34     2  stop   I
    Signature: #118                         // (II)Ljava/util/List<+Lorg/antlr/runtime/Token;>;

  public int LA(int);
    descriptor: (I)I
    flags: (0x0001) ACC_PUBLIC
    Code:
      stack=2, locals=2, args_size=2
         0: aload_0
         1: iload_1
         2: invokevirtual #48                 // Method LT:(I)Lorg/antlr/runtime/Token;
         5: invokeinterface #14,  1           // InterfaceMethod org/antlr/runtime/Token.getType:()I
        10: ireturn
      LineNumberTable:
        line 314: 0
      LocalVariableTable:
        Start  Length  Slot  Name   Signature
            0      11     0  this   Lorg/antlr/runtime/LegacyCommonTokenStream;
            0      11     1     i   I

  public int mark();
    descriptor: ()I
    flags: (0x0001) ACC_PUBLIC
    Code:
      stack=2, locals=1, args_size=1
         0: aload_0
         1: getfield      #5                  // Field p:I
         4: iconst_m1
         5: if_icmpne     12
         8: aload_0
         9: invokevirtual #37                 // Method fillBuffer:()V
        12: aload_0
        13: aload_0
        14: invokevirtual #49                 // Method index:()I
        17: putfield      #50                 // Field lastMarker:I
        20: aload_0
        21: getfield      #50                 // Field lastMarker:I
        24: ireturn
      LineNumberTable:
        line 319: 0
        line 320: 8
        line 322: 12
        line 323: 20
      LocalVariableTable:
        Start  Length  Slot  Name   Signature
            0      25     0  this   Lorg/antlr/runtime/LegacyCommonTokenStream;

  public void release(int);
    descriptor: (I)V
    flags: (0x0001) ACC_PUBLIC
    Code:
      stack=0, locals=2, args_size=2
         0: return
      LineNumberTable:
        line 329: 0
      LocalVariableTable:
        Start  Length  Slot  Name   Signature
            0       1     0  this   Lorg/antlr/runtime/LegacyCommonTokenStream;
            0       1     1 marker   I

  public int size();
    descriptor: ()I
    flags: (0x0001) ACC_PUBLIC
    Code:
      stack=1, locals=1, args_size=1
         0: aload_0
         1: getfield      #8                  // Field tokens:Ljava/util/List;
         4: invokeinterface #28,  1           // InterfaceMethod java/util/List.size:()I
         9: ireturn
      LineNumberTable:
        line 333: 0
      LocalVariableTable:
        Start  Length  Slot  Name   Signature
            0      10     0  this   Lorg/antlr/runtime/LegacyCommonTokenStream;

  public int index();
    descriptor: ()I
    flags: (0x0001) ACC_PUBLIC
    Code:
      stack=1, locals=1, args_size=1
         0: aload_0
         1: getfield      #5                  // Field p:I
         4: ireturn
      LineNumberTable:
        line 338: 0
      LocalVariableTable:
        Start  Length  Slot  Name   Signature
            0       5     0  this   Lorg/antlr/runtime/LegacyCommonTokenStream;

  public int range();
    descriptor: ()I
    flags: (0x0001) ACC_PUBLIC
    Code:
      stack=1, locals=1, args_size=1
         0: aload_0
         1: getfield      #4                  // Field range:I
         4: ireturn
      LineNumberTable:
        line 343: 0
      LocalVariableTable:
        Start  Length  Slot  Name   Signature
            0       5     0  this   Lorg/antlr/runtime/LegacyCommonTokenStream;

  public void rewind(int);
    descriptor: (I)V
    flags: (0x0001) ACC_PUBLIC
    Code:
      stack=2, locals=2, args_size=2
         0: aload_0
         1: iload_1
         2: invokevirtual #51                 // Method seek:(I)V
         5: return
      LineNumberTable:
        line 348: 0
        line 349: 5
      LocalVariableTable:
        Start  Length  Slot  Name   Signature
            0       6     0  this   Lorg/antlr/runtime/LegacyCommonTokenStream;
            0       6     1 marker   I

  public void rewind();
    descriptor: ()V
    flags: (0x0001) ACC_PUBLIC
    Code:
      stack=2, locals=1, args_size=1
         0: aload_0
         1: aload_0
         2: getfield      #50                 // Field lastMarker:I
         5: invokevirtual #51                 // Method seek:(I)V
         8: return
      LineNumberTable:
        line 353: 0
        line 354: 8
      LocalVariableTable:
        Start  Length  Slot  Name   Signature
            0       9     0  this   Lorg/antlr/runtime/LegacyCommonTokenStream;

  public void reset();
    descriptor: ()V
    flags: (0x0001) ACC_PUBLIC
    Code:
      stack=2, locals=1, args_size=1
         0: aload_0
         1: iconst_0
         2: putfield      #5                  // Field p:I
         5: aload_0
         6: iconst_0
         7: putfield      #50                 // Field lastMarker:I
        10: return
      LineNumberTable:
        line 357: 0
        line 358: 5
        line 359: 10
      LocalVariableTable:
        Start  Length  Slot  Name   Signature
            0      11     0  this   Lorg/antlr/runtime/LegacyCommonTokenStream;

  public void seek(int);
    descriptor: (I)V
    flags: (0x0001) ACC_PUBLIC
    Code:
      stack=2, locals=2, args_size=2
         0: aload_0
         1: iload_1
         2: putfield      #5                  // Field p:I
         5: return
      LineNumberTable:
        line 363: 0
        line 364: 5
      LocalVariableTable:
        Start  Length  Slot  Name   Signature
            0       6     0  this   Lorg/antlr/runtime/LegacyCommonTokenStream;
            0       6     1 index   I

  public org.antlr.runtime.TokenSource getTokenSource();
    descriptor: ()Lorg/antlr/runtime/TokenSource;
    flags: (0x0001) ACC_PUBLIC
    Code:
      stack=1, locals=1, args_size=1
         0: aload_0
         1: getfield      #10                 // Field tokenSource:Lorg/antlr/runtime/TokenSource;
         4: areturn
      LineNumberTable:
        line 368: 0
      LocalVariableTable:
        Start  Length  Slot  Name   Signature
            0       5     0  this   Lorg/antlr/runtime/LegacyCommonTokenStream;

  public java.lang.String getSourceName();
    descriptor: ()Ljava/lang/String;
    flags: (0x0001) ACC_PUBLIC
    Code:
      stack=1, locals=1, args_size=1
         0: aload_0
         1: invokevirtual #52                 // Method getTokenSource:()Lorg/antlr/runtime/TokenSource;
         4: invokeinterface #53,  1           // InterfaceMethod org/antlr/runtime/TokenSource.getSourceName:()Ljava/lang/String;
         9: areturn
      LineNumberTable:
        line 373: 0
      LocalVariableTable:
        Start  Length  Slot  Name   Signature
            0      10     0  this   Lorg/antlr/runtime/LegacyCommonTokenStream;

  public java.lang.String toString();
    descriptor: ()Ljava/lang/String;
    flags: (0x0001) ACC_PUBLIC
    Code:
      stack=4, locals=1, args_size=1
         0: aload_0
         1: getfield      #5                  // Field p:I
         4: iconst_m1
         5: if_icmpne     12
         8: aload_0
         9: invokevirtual #37                 // Method fillBuffer:()V
        12: aload_0
        13: iconst_0
        14: aload_0
        15: getfield      #8                  // Field tokens:Ljava/util/List;
        18: invokeinterface #28,  1           // InterfaceMethod java/util/List.size:()I
        23: iconst_1
        24: isub
        25: invokevirtual #54                 // Method toString:(II)Ljava/lang/String;
        28: areturn
      LineNumberTable:
        line 378: 0
        line 379: 8
        line 381: 12
      LocalVariableTable:
        Start  Length  Slot  Name   Signature
            0      29     0  this   Lorg/antlr/runtime/LegacyCommonTokenStream;

  public java.lang.String toString(int, int);
    descriptor: (II)Ljava/lang/String;
    flags: (0x0001) ACC_PUBLIC
    Code:
      stack=2, locals=6, args_size=3
         0: iload_1
         1: iflt          8
         4: iload_2
         5: ifge          10
         8: aconst_null
         9: areturn
        10: aload_0
        11: getfield      #5                  // Field p:I
        14: iconst_m1
        15: if_icmpne     22
        18: aload_0
        19: invokevirtual #37                 // Method fillBuffer:()V
        22: iload_2
        23: aload_0
        24: getfield      #8                  // Field tokens:Ljava/util/List;
        27: invokeinterface #28,  1           // InterfaceMethod java/util/List.size:()I
        32: if_icmplt     47
        35: aload_0
        36: getfield      #8                  // Field tokens:Ljava/util/List;
        39: invokeinterface #28,  1           // InterfaceMethod java/util/List.size:()I
        44: iconst_1
        45: isub
        46: istore_2
        47: new           #55                 // class java/lang/StringBuilder
        50: dup
        51: invokespecial #56                 // Method java/lang/StringBuilder."<init>":()V
        54: astore_3
        55: iload_1
        56: istore        4
        58: iload         4
        60: iload_2
        61: if_icmpgt     98
        64: aload_0
        65: getfield      #8                  // Field tokens:Ljava/util/List;
        68: iload         4
        70: invokeinterface #29,  2           // InterfaceMethod java/util/List.get:(I)Ljava/lang/Object;
        75: checkcast     #30                 // class org/antlr/runtime/Token
        78: astore        5
        80: aload_3
        81: aload         5
        83: invokeinterface #57,  1           // InterfaceMethod org/antlr/runtime/Token.getText:()Ljava/lang/String;
        88: invokevirtual #58                 // Method java/lang/StringBuilder.append:(Ljava/lang/String;)Ljava/lang/StringBuilder;
        91: pop
        92: iinc          4, 1
        95: goto          58
        98: aload_3
        99: invokevirtual #59                 // Method java/lang/StringBuilder.toString:()Ljava/lang/String;
       102: areturn
      LineNumberTable:
        line 386: 0
        line 387: 8
        line 389: 10
        line 390: 18
        line 392: 22
        line 393: 35
        line 395: 47
        line 396: 55
        line 397: 64
        line 398: 80
        line 396: 92
        line 400: 98
      LocalVariableTable:
        Start  Length  Slot  Name   Signature
           80      12     5     t   Lorg/antlr/runtime/Token;
           58      40     4     i   I
            0     103     0  this   Lorg/antlr/runtime/LegacyCommonTokenStream;
            0     103     1 start   I
            0     103     2  stop   I
           55      48     3   buf   Ljava/lang/StringBuilder;

  public java.lang.String toString(org.antlr.runtime.Token, org.antlr.runtime.Token);
    descriptor: (Lorg/antlr/runtime/Token;Lorg/antlr/runtime/Token;)Ljava/lang/String;
    flags: (0x0001) ACC_PUBLIC
    Code:
      stack=3, locals=3, args_size=3
         0: aload_1
         1: ifnull        25
         4: aload_2
         5: ifnull        25
         8: aload_0
         9: aload_1
        10: invokeinterface #60,  1           // InterfaceMethod org/antlr/runtime/Token.getTokenIndex:()I
        15: aload_2
        16: invokeinterface #60,  1           // InterfaceMethod org/antlr/runtime/Token.getTokenIndex:()I
        21: invokevirtual #54                 // Method toString:(II)Ljava/lang/String;
        24: areturn
        25: aconst_null
        26: areturn
      LineNumberTable:
        line 405: 0
        line 406: 8
        line 408: 25
      LocalVariableTable:
        Start  Length  Slot  Name   Signature
            0      27     0  this   Lorg/antlr/runtime/LegacyCommonTokenStream;
            0      27     1 start   Lorg/antlr/runtime/Token;
            0      27     2  stop   Lorg/antlr/runtime/Token;
}
SourceFile: "LegacyCommonTokenStream.java"
