Classfile /Users/mw/Projects/slang-braindump/.jar/jar11/assemble/slang-braindump/assemble/content/org/antlr/runtime/TokenRewriteStream$RewriteOperation.class
  Last modified May 29, 2022; size 1751 bytes
  SHA-256 checksum 2d86d83be55423fc11a4bf3616b4f5b0a9245da643324cf758748973b15e7343
  Compiled from "TokenRewriteStream.java"
public class org.antlr.runtime.TokenRewriteStream$RewriteOperation
  minor version: 0
  major version: 49
  flags: (0x0021) ACC_PUBLIC, ACC_SUPER
  this_class: #21                         // org/antlr/runtime/TokenRewriteStream$RewriteOperation
  super_class: #22                        // java/lang/Object
  interfaces: 0, fields: 4, methods: 4, attributes: 2
Constant pool:
   #1 = Fieldref           #21.#51        // org/antlr/runtime/TokenRewriteStream$RewriteOperation.this$0:Lorg/antlr/runtime/TokenRewriteStream;
   #2 = Methodref          #22.#52        // java/lang/Object."<init>":()V
   #3 = Fieldref           #21.#53        // org/antlr/runtime/TokenRewriteStream$RewriteOperation.index:I
   #4 = Fieldref           #21.#54        // org/antlr/runtime/TokenRewriteStream$RewriteOperation.text:Ljava/lang/Object;
   #5 = Methodref          #22.#55        // java/lang/Object.getClass:()Ljava/lang/Class;
   #6 = Methodref          #56.#57        // java/lang/Class.getName:()Ljava/lang/String;
   #7 = Methodref          #58.#59        // java/lang/String.indexOf:(I)I
   #8 = Methodref          #58.#60        // java/lang/String.length:()I
   #9 = Methodref          #58.#61        // java/lang/String.substring:(II)Ljava/lang/String;
  #10 = Class              #62            // java/lang/StringBuilder
  #11 = Methodref          #10.#52        // java/lang/StringBuilder."<init>":()V
  #12 = String             #63            // <
  #13 = Methodref          #10.#64        // java/lang/StringBuilder.append:(Ljava/lang/String;)Ljava/lang/StringBuilder;
  #14 = String             #65            // @
  #15 = Fieldref           #66.#67        // org/antlr/runtime/TokenRewriteStream.tokens:Ljava/util/List;
  #16 = InterfaceMethodref #68.#69        // java/util/List.get:(I)Ljava/lang/Object;
  #17 = Methodref          #10.#70        // java/lang/StringBuilder.append:(Ljava/lang/Object;)Ljava/lang/StringBuilder;
  #18 = String             #71            // :\"
  #19 = String             #72            // \">
  #20 = Methodref          #10.#73        // java/lang/StringBuilder.toString:()Ljava/lang/String;
  #21 = Class              #74            // org/antlr/runtime/TokenRewriteStream$RewriteOperation
  #22 = Class              #75            // java/lang/Object
  #23 = Utf8               instructionIndex
  #24 = Utf8               I
  #25 = Utf8               index
  #26 = Utf8               text
  #27 = Utf8               Ljava/lang/Object;
  #28 = Utf8               this$0
  #29 = Utf8               Lorg/antlr/runtime/TokenRewriteStream;
  #30 = Utf8               <init>
  #31 = Utf8               (Lorg/antlr/runtime/TokenRewriteStream;I)V
  #32 = Utf8               Code
  #33 = Utf8               LineNumberTable
  #34 = Utf8               LocalVariableTable
  #35 = Utf8               this
  #36 = Utf8               RewriteOperation
  #37 = Utf8               InnerClasses
  #38 = Utf8               Lorg/antlr/runtime/TokenRewriteStream$RewriteOperation;
  #39 = Utf8               (Lorg/antlr/runtime/TokenRewriteStream;ILjava/lang/Object;)V
  #40 = Utf8               execute
  #41 = Utf8               (Ljava/lang/StringBuffer;)I
  #42 = Utf8               buf
  #43 = Utf8               Ljava/lang/StringBuffer;
  #44 = Utf8               toString
  #45 = Utf8               ()Ljava/lang/String;
  #46 = Utf8               opName
  #47 = Utf8               Ljava/lang/String;
  #48 = Utf8               $index
  #49 = Utf8               SourceFile
  #50 = Utf8               TokenRewriteStream.java
  #51 = NameAndType        #28:#29        // this$0:Lorg/antlr/runtime/TokenRewriteStream;
  #52 = NameAndType        #30:#76        // "<init>":()V
  #53 = NameAndType        #25:#24        // index:I
  #54 = NameAndType        #26:#27        // text:Ljava/lang/Object;
  #55 = NameAndType        #77:#78        // getClass:()Ljava/lang/Class;
  #56 = Class              #79            // java/lang/Class
  #57 = NameAndType        #80:#45        // getName:()Ljava/lang/String;
  #58 = Class              #81            // java/lang/String
  #59 = NameAndType        #82:#83        // indexOf:(I)I
  #60 = NameAndType        #84:#85        // length:()I
  #61 = NameAndType        #86:#87        // substring:(II)Ljava/lang/String;
  #62 = Utf8               java/lang/StringBuilder
  #63 = Utf8               <
  #64 = NameAndType        #88:#89        // append:(Ljava/lang/String;)Ljava/lang/StringBuilder;
  #65 = Utf8               @
  #66 = Class              #90            // org/antlr/runtime/TokenRewriteStream
  #67 = NameAndType        #91:#92        // tokens:Ljava/util/List;
  #68 = Class              #93            // java/util/List
  #69 = NameAndType        #94:#95        // get:(I)Ljava/lang/Object;
  #70 = NameAndType        #88:#96        // append:(Ljava/lang/Object;)Ljava/lang/StringBuilder;
  #71 = Utf8               :\"
  #72 = Utf8               \">
  #73 = NameAndType        #44:#45        // toString:()Ljava/lang/String;
  #74 = Utf8               org/antlr/runtime/TokenRewriteStream$RewriteOperation
  #75 = Utf8               java/lang/Object
  #76 = Utf8               ()V
  #77 = Utf8               getClass
  #78 = Utf8               ()Ljava/lang/Class;
  #79 = Utf8               java/lang/Class
  #80 = Utf8               getName
  #81 = Utf8               java/lang/String
  #82 = Utf8               indexOf
  #83 = Utf8               (I)I
  #84 = Utf8               length
  #85 = Utf8               ()I
  #86 = Utf8               substring
  #87 = Utf8               (II)Ljava/lang/String;
  #88 = Utf8               append
  #89 = Utf8               (Ljava/lang/String;)Ljava/lang/StringBuilder;
  #90 = Utf8               org/antlr/runtime/TokenRewriteStream
  #91 = Utf8               tokens
  #92 = Utf8               Ljava/util/List;
  #93 = Utf8               java/util/List
  #94 = Utf8               get
  #95 = Utf8               (I)Ljava/lang/Object;
  #96 = Utf8               (Ljava/lang/Object;)Ljava/lang/StringBuilder;
{
  protected int instructionIndex;
    descriptor: I
    flags: (0x0004) ACC_PROTECTED

  protected int index;
    descriptor: I
    flags: (0x0004) ACC_PROTECTED

  protected java.lang.Object text;
    descriptor: Ljava/lang/Object;
    flags: (0x0004) ACC_PROTECTED

  final org.antlr.runtime.TokenRewriteStream this$0;
    descriptor: Lorg/antlr/runtime/TokenRewriteStream;
    flags: (0x1010) ACC_FINAL, ACC_SYNTHETIC

  protected org.antlr.runtime.TokenRewriteStream$RewriteOperation(org.antlr.runtime.TokenRewriteStream, int);
    descriptor: (Lorg/antlr/runtime/TokenRewriteStream;I)V
    flags: (0x0004) ACC_PROTECTED
    Code:
      stack=2, locals=3, args_size=3
         0: aload_0
         1: aload_1
         2: putfield      #1                  // Field this$0:Lorg/antlr/runtime/TokenRewriteStream;
         5: aload_0
         6: invokespecial #2                  // Method java/lang/Object."<init>":()V
         9: aload_0
        10: iload_2
        11: putfield      #3                  // Field index:I
        14: return
      LineNumberTable:
        line 97: 0
        line 98: 9
        line 99: 14
      LocalVariableTable:
        Start  Length  Slot  Name   Signature
            0      15     0  this   Lorg/antlr/runtime/TokenRewriteStream$RewriteOperation;
            0      15     2 index   I

  protected org.antlr.runtime.TokenRewriteStream$RewriteOperation(org.antlr.runtime.TokenRewriteStream, int, java.lang.Object);
    descriptor: (Lorg/antlr/runtime/TokenRewriteStream;ILjava/lang/Object;)V
    flags: (0x0004) ACC_PROTECTED
    Code:
      stack=2, locals=4, args_size=4
         0: aload_0
         1: aload_1
         2: putfield      #1                  // Field this$0:Lorg/antlr/runtime/TokenRewriteStream;
         5: aload_0
         6: invokespecial #2                  // Method java/lang/Object."<init>":()V
         9: aload_0
        10: iload_2
        11: putfield      #3                  // Field index:I
        14: aload_0
        15: aload_3
        16: putfield      #4                  // Field text:Ljava/lang/Object;
        19: return
      LineNumberTable:
        line 101: 0
        line 102: 9
        line 103: 14
        line 104: 19
      LocalVariableTable:
        Start  Length  Slot  Name   Signature
            0      20     0  this   Lorg/antlr/runtime/TokenRewriteStream$RewriteOperation;
            0      20     2 index   I
            0      20     3  text   Ljava/lang/Object;

  public int execute(java.lang.StringBuffer);
    descriptor: (Ljava/lang/StringBuffer;)I
    flags: (0x0001) ACC_PUBLIC
    Code:
      stack=1, locals=2, args_size=2
         0: aload_0
         1: getfield      #3                  // Field index:I
         4: ireturn
      LineNumberTable:
        line 109: 0
      LocalVariableTable:
        Start  Length  Slot  Name   Signature
            0       5     0  this   Lorg/antlr/runtime/TokenRewriteStream$RewriteOperation;
            0       5     1   buf   Ljava/lang/StringBuffer;

  public java.lang.String toString();
    descriptor: ()Ljava/lang/String;
    flags: (0x0001) ACC_PUBLIC
    Code:
      stack=3, locals=3, args_size=1
         0: aload_0
         1: invokevirtual #5                  // Method java/lang/Object.getClass:()Ljava/lang/Class;
         4: invokevirtual #6                  // Method java/lang/Class.getName:()Ljava/lang/String;
         7: astore_1
         8: aload_1
         9: bipush        36
        11: invokevirtual #7                  // Method java/lang/String.indexOf:(I)I
        14: istore_2
        15: aload_1
        16: iload_2
        17: iconst_1
        18: iadd
        19: aload_1
        20: invokevirtual #8                  // Method java/lang/String.length:()I
        23: invokevirtual #9                  // Method java/lang/String.substring:(II)Ljava/lang/String;
        26: astore_1
        27: new           #10                 // class java/lang/StringBuilder
        30: dup
        31: invokespecial #11                 // Method java/lang/StringBuilder."<init>":()V
        34: ldc           #12                 // String <
        36: invokevirtual #13                 // Method java/lang/StringBuilder.append:(Ljava/lang/String;)Ljava/lang/StringBuilder;
        39: aload_1
        40: invokevirtual #13                 // Method java/lang/StringBuilder.append:(Ljava/lang/String;)Ljava/lang/StringBuilder;
        43: ldc           #14                 // String @
        45: invokevirtual #13                 // Method java/lang/StringBuilder.append:(Ljava/lang/String;)Ljava/lang/StringBuilder;
        48: aload_0
        49: getfield      #1                  // Field this$0:Lorg/antlr/runtime/TokenRewriteStream;
        52: getfield      #15                 // Field org/antlr/runtime/TokenRewriteStream.tokens:Ljava/util/List;
        55: aload_0
        56: getfield      #3                  // Field index:I
        59: invokeinterface #16,  2           // InterfaceMethod java/util/List.get:(I)Ljava/lang/Object;
        64: invokevirtual #17                 // Method java/lang/StringBuilder.append:(Ljava/lang/Object;)Ljava/lang/StringBuilder;
        67: ldc           #18                 // String :\"
        69: invokevirtual #13                 // Method java/lang/StringBuilder.append:(Ljava/lang/String;)Ljava/lang/StringBuilder;
        72: aload_0
        73: getfield      #4                  // Field text:Ljava/lang/Object;
        76: invokevirtual #17                 // Method java/lang/StringBuilder.append:(Ljava/lang/Object;)Ljava/lang/StringBuilder;
        79: ldc           #19                 // String \">
        81: invokevirtual #13                 // Method java/lang/StringBuilder.append:(Ljava/lang/String;)Ljava/lang/StringBuilder;
        84: invokevirtual #20                 // Method java/lang/StringBuilder.toString:()Ljava/lang/String;
        87: areturn
      LineNumberTable:
        line 113: 0
        line 114: 8
        line 115: 15
        line 116: 27
      LocalVariableTable:
        Start  Length  Slot  Name   Signature
            0      88     0  this   Lorg/antlr/runtime/TokenRewriteStream$RewriteOperation;
            8      80     1 opName   Ljava/lang/String;
           15      73     2 $index   I
}
SourceFile: "TokenRewriteStream.java"
InnerClasses:
  public #36= #21 of #66;                 // RewriteOperation=class org/antlr/runtime/TokenRewriteStream$RewriteOperation of class org/antlr/runtime/TokenRewriteStream
