Classfile /Users/mw/Projects/slang-braindump/.jar/jar11/assemble/slang-braindump/assemble/content/scala/concurrent/BatchingExecutorStatics$.class
  Last modified May 29, 2022; size 796 bytes
  SHA-256 checksum 74d2b6ff8dba824270a60d13da67cc7251a9bae4b64d5ec8358ee10c66035f9a
  Compiled from "BatchingExecutor.scala"
public final class scala.concurrent.BatchingExecutorStatics$
  minor version: 0
  major version: 52
  flags: (0x0031) ACC_PUBLIC, ACC_FINAL, ACC_SUPER
  this_class: #2                          // scala/concurrent/BatchingExecutorStatics$
  super_class: #4                         // java/lang/Object
  interfaces: 0, fields: 2, methods: 5, attributes: 3
Constant pool:
   #1 = Utf8               scala/concurrent/BatchingExecutorStatics$
   #2 = Class              #1             // scala/concurrent/BatchingExecutorStatics$
   #3 = Utf8               java/lang/Object
   #4 = Class              #3             // java/lang/Object
   #5 = Utf8               BatchingExecutor.scala
   #6 = Utf8               MODULE$
   #7 = Utf8               Lscala/concurrent/BatchingExecutorStatics$;
   #8 = Utf8               emptyBatchArray
   #9 = Utf8               [Ljava/lang/Runnable;
  #10 = Utf8               <clinit>
  #11 = Utf8               ()V
  #12 = Utf8               <init>
  #13 = NameAndType        #12:#11        // "<init>":()V
  #14 = Methodref          #2.#13         // scala/concurrent/BatchingExecutorStatics$."<init>":()V
  #15 = NameAndType        #6:#7          // MODULE$:Lscala/concurrent/BatchingExecutorStatics$;
  #16 = Fieldref           #2.#15         // scala/concurrent/BatchingExecutorStatics$.MODULE$:Lscala/concurrent/BatchingExecutorStatics$;
  #17 = Utf8               java/lang/Runnable
  #18 = Class              #17            // java/lang/Runnable
  #19 = NameAndType        #8:#9          // emptyBatchArray:[Ljava/lang/Runnable;
  #20 = Fieldref           #2.#19         // scala/concurrent/BatchingExecutorStatics$.emptyBatchArray:[Ljava/lang/Runnable;
  #21 = Utf8               ()[Ljava/lang/Runnable;
  #22 = Utf8               this
  #23 = Utf8               syncPreBatchDepth
  #24 = Utf8               ()I
  #25 = Utf8               runLimit
  #26 = Methodref          #4.#13         // java/lang/Object."<init>":()V
  #27 = Utf8               Code
  #28 = Utf8               LineNumberTable
  #29 = Utf8               LocalVariableTable
  #30 = Utf8               SourceFile
  #31 = Utf8               ScalaInlineInfo
  #32 = Utf8               Scala
{
  public static final scala.concurrent.BatchingExecutorStatics$ MODULE$;
    descriptor: Lscala/concurrent/BatchingExecutorStatics$;
    flags: (0x0019) ACC_PUBLIC, ACC_STATIC, ACC_FINAL

  private static final java.lang.Runnable[] emptyBatchArray;
    descriptor: [Ljava/lang/Runnable;
    flags: (0x001a) ACC_PRIVATE, ACC_STATIC, ACC_FINAL

  public static {};
    descriptor: ()V
    flags: (0x0009) ACC_PUBLIC, ACC_STATIC
    Code:
      stack=2, locals=0, args_size=0
         0: new           #2                  // class scala/concurrent/BatchingExecutorStatics$
         3: dup
         4: invokespecial #14                 // Method "<init>":()V
         7: putstatic     #16                 // Field MODULE$:Lscala/concurrent/BatchingExecutorStatics$;
        10: iconst_0
        11: anewarray     #18                 // class java/lang/Runnable
        14: putstatic     #20                 // Field emptyBatchArray:[Ljava/lang/Runnable;
        17: return
      LineNumberTable:
        line 27: 0
        line 28: 10
        line 27: 17

  public final java.lang.Runnable[] emptyBatchArray();
    descriptor: ()[Ljava/lang/Runnable;
    flags: (0x0011) ACC_PUBLIC, ACC_FINAL
    Code:
      stack=1, locals=1, args_size=1
         0: getstatic     #20                 // Field emptyBatchArray:[Ljava/lang/Runnable;
         3: areturn
      LineNumberTable:
        line 28: 0
      LocalVariableTable:
        Start  Length  Slot  Name   Signature
            0       4     0  this   Lscala/concurrent/BatchingExecutorStatics$;

  public final int syncPreBatchDepth();
    descriptor: ()I
    flags: (0x0011) ACC_PUBLIC, ACC_FINAL
    Code:
      stack=1, locals=1, args_size=1
         0: bipush        16
         2: ireturn
      LocalVariableTable:
        Start  Length  Slot  Name   Signature
            0       3     0  this   Lscala/concurrent/BatchingExecutorStatics$;

  public final int runLimit();
    descriptor: ()I
    flags: (0x0011) ACC_PUBLIC, ACC_FINAL
    Code:
      stack=1, locals=1, args_size=1
         0: sipush        1024
         3: ireturn
      LocalVariableTable:
        Start  Length  Slot  Name   Signature
            0       4     0  this   Lscala/concurrent/BatchingExecutorStatics$;

  private scala.concurrent.BatchingExecutorStatics$();
    descriptor: ()V
    flags: (0x0002) ACC_PRIVATE
    Code:
      stack=1, locals=1, args_size=1
         0: aload_0
         1: invokespecial #26                 // Method java/lang/Object."<init>":()V
         4: return
      LineNumberTable:
        line 27: 0
      LocalVariableTable:
        Start  Length  Slot  Name   Signature
            0       5     0  this   Lscala/concurrent/BatchingExecutorStatics$;
}
SourceFile: "BatchingExecutor.scala"
  ScalaInlineInfo: length = 0x18 (unknown attribute)
   01 01 00 04 00 0C 00 0B 01 00 08 00 15 01 00 19
   00 18 01 00 17 00 18 01
  Scala: length = 0x0 (unknown attribute)

