Classfile /Users/mw/Projects/slang-braindump/.jar/jar11/assemble/slang-braindump/assemble/content/scala/concurrent/JavaConversions.class
  Last modified May 29, 2022; size 1483 bytes
  SHA-256 checksum 0d723540df139dc9b30bc1db8935381d70500af27b3a1ad7974e811e29570c85
  Compiled from "JavaConversions.scala"
public final class scala.concurrent.JavaConversions
  minor version: 0
  major version: 52
  flags: (0x0031) ACC_PUBLIC, ACC_FINAL, ACC_SUPER
  this_class: #2                          // scala/concurrent/JavaConversions
  super_class: #4                         // java/lang/Object
  interfaces: 0, fields: 0, methods: 2, attributes: 3
Constant pool:
   #1 = Utf8               scala/concurrent/JavaConversions
   #2 = Class              #1             // scala/concurrent/JavaConversions
   #3 = Utf8               java/lang/Object
   #4 = Class              #3             // java/lang/Object
   #5 = Utf8               JavaConversions.scala
   #6 = Utf8               Lscala/reflect/ScalaSignature;
   #7 = Utf8               bytes
   #8 = Utf8               \u0006\u0005y:Q!\u0002\u0004\t\u0002-1Q!\u0004\u0004\t\u00029AQaE\u0001\u0005\u0002QAQ!F\u0001\u0005\u0004YAQ!F\u0001\u0005\u0004=\nqBS1wC\u000e{gN^3sg&|gn\u001d\u0006\u0003\u000f!\t!bY8oGV\u0014(/\u001a8u\u0015\u0005I\u0011!B:dC2\f7\u0001\u0001\t\u0003\u0019\u0005i\u0011A\u0002\u0002\u0010\u0015\u00064\u0018mQ8om\u0016\u00148/[8ogN\u0011\u0011a\u0004\t\u0003!Ei\u0011\u0001C\u0005\u0003%!\u0011a!\u00118z%\u00164\u0017A\u0002\u001fj]&$h\bF\u0001\f\u0003I\t7/\u0012=fGV$\u0018n\u001c8D_:$X\r\u001f;\u0015\u0005]Q\u0002C\u0001\u0007\u0019\u0013\tIbAA\u0010Fq\u0016\u001cW\u000f^5p]\u000e{g\u000e^3yi\u0016CXmY;u_J\u001cVM\u001d<jG\u0016DQaG\u0002A\u0002q\tA!\u001a=fGB\u0011QdI\u0007\u0002=)\u0011qa\b\u0006\u0003A\u0005\nA!\u001e;jY*\t!%\u0001\u0003kCZ\f\u0017B\u0001\u0013\u001f\u0005=)\u00050Z2vi>\u00148+\u001a:wS\u000e,\u0007FB\u0002\'S)bS\u0006\u0005\u0002\u0011O%\u0011\u0001\u0006\u0003\u0002\u000bI\u0016\u0004(/Z2bi\u0016$\u0017aB7fgN\fw-Z\u0011\u0002W\u0005\u0011Tk]3!A\u0016CXmY;uS>t7i\u001c8uKb$hF\u001a:p[\u0016CXmY;u_J\u001cVM\u001d<jG\u0016\u0004\u0007%\u001b8ti\u0016\fG-A\u0003tS:\u001cW-I\u0001/\u0003\u0019\u0011d&M\u001a/aQ\u0011\u0001g\r\t\u0003\u0019EJ!A\r\u0004\u00031\u0015CXmY;uS>t7i\u001c8uKb$X\t_3dkR|\'\u000fC\u0003\u001c\t\u0001\u0007A\u0007\u0005\u0002\u001ek%\u0011aG\b\u0002\t\u000bb,7-\u001e;pe\"2AAJ\u00159Y5\n\u0013!O\u0001,+N,\u0007\u0005Y#yK\u000e,H/[8o\u0007>tG/\u001a=u]\u0019\u0014x.\\#yK\u000e,Ho\u001c:aA%t7\u000f^3bI\"2\u0011AJ\u0015<Y5\n\u0013\u0001P\u00016+N,\u0007\u0005\u001e5fA\u0019\f7\r^8ss\u0002jW\r\u001e5pIN\u0004\u0013N\u001c\u0011a\u000bb,7-\u001e;j_:\u001cuN\u001c;fqR\u0004\u0007%\u001b8ti\u0016\fG\r\u000b\u0004\u0001M%ZD&\f
   #9 = Utf8               asExecutionContext
  #10 = Utf8               (Ljava/util/concurrent/Executor;)Lscala/concurrent/ExecutionContextExecutor;
  #11 = Utf8               exec
  #12 = Utf8               scala/concurrent/JavaConversions$
  #13 = Class              #12            // scala/concurrent/JavaConversions$
  #14 = Utf8               MODULE$
  #15 = Utf8               Lscala/concurrent/JavaConversions$;
  #16 = NameAndType        #14:#15        // MODULE$:Lscala/concurrent/JavaConversions$;
  #17 = Fieldref           #13.#16        // scala/concurrent/JavaConversions$.MODULE$:Lscala/concurrent/JavaConversions$;
  #18 = NameAndType        #9:#10         // asExecutionContext:(Ljava/util/concurrent/Executor;)Lscala/concurrent/ExecutionContextExecutor;
  #19 = Methodref          #13.#18        // scala/concurrent/JavaConversions$.asExecutionContext:(Ljava/util/concurrent/Executor;)Lscala/concurrent/ExecutionContextExecutor;
  #20 = Utf8               Ljava/util/concurrent/Executor;
  #21 = Utf8               (Ljava/util/concurrent/ExecutorService;)Lscala/concurrent/ExecutionContextExecutorService;
  #22 = NameAndType        #9:#21         // asExecutionContext:(Ljava/util/concurrent/ExecutorService;)Lscala/concurrent/ExecutionContextExecutorService;
  #23 = Methodref          #13.#22        // scala/concurrent/JavaConversions$.asExecutionContext:(Ljava/util/concurrent/ExecutorService;)Lscala/concurrent/ExecutionContextExecutorService;
  #24 = Utf8               Ljava/util/concurrent/ExecutorService;
  #25 = Utf8               Code
  #26 = Utf8               LocalVariableTable
  #27 = Utf8               Deprecated
  #28 = Utf8               MethodParameters
  #29 = Utf8               SourceFile
  #30 = Utf8               RuntimeVisibleAnnotations
  #31 = Utf8               ScalaSig
{
  public static scala.concurrent.ExecutionContextExecutor asExecutionContext(java.util.concurrent.Executor);
    descriptor: (Ljava/util/concurrent/Executor;)Lscala/concurrent/ExecutionContextExecutor;
    flags: (0x0009) ACC_PUBLIC, ACC_STATIC
    Code:
      stack=2, locals=1, args_size=1
         0: getstatic     #17                 // Field scala/concurrent/JavaConversions$.MODULE$:Lscala/concurrent/JavaConversions$;
         3: aload_0
         4: invokevirtual #19                 // Method scala/concurrent/JavaConversions$.asExecutionContext:(Ljava/util/concurrent/Executor;)Lscala/concurrent/ExecutionContextExecutor;
         7: areturn
      LocalVariableTable:
        Start  Length  Slot  Name   Signature
            0       8     0  exec   Ljava/util/concurrent/Executor;
    Deprecated: true
    MethodParameters:
      Name                           Flags
      exec                           final

  public static scala.concurrent.ExecutionContextExecutorService asExecutionContext(java.util.concurrent.ExecutorService);
    descriptor: (Ljava/util/concurrent/ExecutorService;)Lscala/concurrent/ExecutionContextExecutorService;
    flags: (0x0009) ACC_PUBLIC, ACC_STATIC
    Code:
      stack=2, locals=1, args_size=1
         0: getstatic     #17                 // Field scala/concurrent/JavaConversions$.MODULE$:Lscala/concurrent/JavaConversions$;
         3: aload_0
         4: invokevirtual #23                 // Method scala/concurrent/JavaConversions$.asExecutionContext:(Ljava/util/concurrent/ExecutorService;)Lscala/concurrent/ExecutionContextExecutorService;
         7: areturn
      LocalVariableTable:
        Start  Length  Slot  Name   Signature
            0       8     0  exec   Ljava/util/concurrent/ExecutorService;
    Deprecated: true
    MethodParameters:
      Name                           Flags
      exec                           final
}
SourceFile: "JavaConversions.scala"
RuntimeVisibleAnnotations:
  0: #6(#7=s#8)
    scala.reflect.ScalaSignature(
      bytes="\u0006\u0005y:Q!\u0002\u0004\t\u0002-1Q!\u0004\u0004\t\u00029AQaE\u0001\u0005\u0002QAQ!F\u0001\u0005\u0004YAQ!F\u0001\u0005\u0004=\nqBS1wC\u000e{gN^3sg&|gn\u001d\u0006\u0003\u000f!\t!bY8oGV\u0014(/\u001a8u\u0015\u0005I\u0011!B:dC2\f7\u0001\u0001\t\u0003\u0019\u0005i\u0011A\u0002\u0002\u0010\u0015\u00064\u0018mQ8om\u0016\u00148/[8ogN\u0011\u0011a\u0004\t\u0003!Ei\u0011\u0001C\u0005\u0003%!\u0011a!\u00118z%\u00164\u0017A\u0002\u001fj]&$h\bF\u0001\f\u0003I\t7/\u0012=fGV$\u0018n\u001c8D_:$X\r\u001f;\u0015\u0005]Q\u0002C\u0001\u0007\u0019\u0013\tIbAA\u0010Fq\u0016\u001cW\u000f^5p]\u000e{g\u000e^3yi\u0016CXmY;u_J\u001cVM\u001d<jG\u0016DQaG\u0002A\u0002q\tA!\u001a=fGB\u0011QdI\u0007\u0002=)\u0011qa\b\u0006\u0003A\u0005\nA!\u001e;jY*\t!%\u0001\u0003kCZ\f\u0017B\u0001\u0013\u001f\u0005=)\u00050Z2vi>\u00148+\u001a:wS\u000e,\u0007FB\u0002\'S)bS\u0006\u0005\u0002\u0011O%\u0011\u0001\u0006\u0003\u0002\u000bI\u0016\u0004(/Z2bi\u0016$\u0017aB7fgN\fw-Z\u0011\u0002W\u0005\u0011Tk]3!A\u0016CXmY;uS>t7i\u001c8uKb$hF\u001a:p[\u0016CXmY;u_J\u001cVM\u001d<jG\u0016\u0004\u0007%\u001b8ti\u0016\fG-A\u0003tS:\u001cW-I\u0001/\u0003\u0019\u0011d&M\u001a/aQ\u0011\u0001g\r\t\u0003\u0019EJ!A\r\u0004\u00031\u0015CXmY;uS>t7i\u001c8uKb$X\t_3dkR|\'\u000fC\u0003\u001c\t\u0001\u0007A\u0007\u0005\u0002\u001ek%\u0011aG\b\u0002\t\u000bb,7-\u001e;pe\"2AAJ\u00159Y5\n\u0013!O\u0001,+N,\u0007\u0005Y#yK\u000e,H/[8o\u0007>tG/\u001a=u]\u0019\u0014x.\\#yK\u000e,Ho\u001c:aA%t7\u000f^3bI\"2\u0011AJ\u0015<Y5\n\u0013\u0001P\u00016+N,\u0007\u0005\u001e5fA\u0019\f7\r^8ss\u0002jW\r\u001e5pIN\u0004\u0013N\u001c\u0011a\u000bb,7-\u001e;j_:\u001cuN\u001c;fqR\u0004\u0007%\u001b8ti\u0016\fG\r\u000b\u0004\u0001M%ZD&\f"
    )
  ScalaSig: length = 0x3 (unknown attribute)
   05 02 00
