Classfile /Users/mw/Projects/slang-braindump/.jar/jar8/assemble/slang-braindump/assemble/content/coursier/core/shaded/geny/Writable.class
  Last modified May 29, 2022; size 2867 bytes
  SHA-256 checksum e9049af9d421c3856c8bc146909c09f40a2c352c2faf73b4792687532c3e2ec4
  Compiled from "Writable.scala"
public interface coursier.core.shaded.geny.Writable
  minor version: 0
  major version: 52
  flags: (0x0601) ACC_PUBLIC, ACC_INTERFACE, ACC_ABSTRACT
  this_class: #2                          // coursier/core/shaded/geny/Writable
  super_class: #4                         // java/lang/Object
  interfaces: 0, fields: 0, methods: 9, attributes: 5
Constant pool:
   #1 = Utf8               coursier/core/shaded/geny/Writable
   #2 = Class              #1             // coursier/core/shaded/geny/Writable
   #3 = Utf8               java/lang/Object
   #4 = Class              #3             // java/lang/Object
   #5 = Utf8               Writable.scala
   #6 = Utf8               Lscala/reflect/ScalaSignature;
   #7 = Utf8               bytes
   #8 = Utf8               \u0006\u0005i4qAF\f\u0011\u0002\u0007\u0005!\u0004C\u0003\"\u0001\u0011\u0005!\u0005C\u0003\'\u0001\u0019\u0005q\u0005C\u00033\u0001\u0011\u00051\u0007C\u0003C\u0001\u0011\u00051iB\u0003I/!\u0005\u0011JB\u0003\u0017/!\u00051\nC\u0003P\r\u0011\u0005\u0001K\u0002\u0003R\r\u0005\u0011\u0006\u0002\u0003+\t\u0005\u0003\u0005\u000b\u0011B\u001c\t\u000b=CA\u0011A+\t\u000b\u0019BA\u0011A-\t\u000bIBA\u0011I.\t\u000b\tCA\u0011\t3\t\u000f\u00194\u0011\u0011!C\u0002O\u001a!\u0011NB\u0001k\u0011!YwB!A!\u0002\u0013a\u0007\"B(\u0010\t\u0003\u0011\b\"\u0002\u0014\u0010\t\u0003)\b\"\u0002\u001a\u0010\t\u0003Z\u0006\"\u0002\"\u0010\t\u0003\"\u0007bB<\u0007\u0003\u0003%\u0019\u0001\u001f\u0002\t/JLG/\u00192mK*\t\u0001$\u0001\u0003hK:L8\u0001A\n\u0003\u0001m\u0001\"\u0001H\u0010\u000e\u0003uQ\u0011AH\u0001\u0006g\u000e\fG.Y\u0005\u0003Au\u0011a!\u00118z%\u00164\u0017A\u0002\u0013j]&$H\u0005F\u0001$!\taB%\u0003\u0002&;\t!QK\\5u\u000319(/\u001b;f\u0005f$Xm\u001d+p)\t\u0019\u0003\u0006C\u0003*\u0005\u0001\u0007!&A\u0002pkR\u0004\"a\u000b\u0019\u000e\u00031R!!\f\u0018\u0002\u0005%|\'\"A\u0018\u0002\t)\fg/Y\u0005\u0003c1\u0012AbT;uaV$8\u000b\u001e:fC6\fq\u0002\u001b;ua\u000e{g\u000e^3oiRK\b/Z\u000b\u0002iA\u0019A$N\u001c\n\u0005Yj\"AB(qi&|g\u000e\u0005\u00029\u007f9\u0011\u0011(\u0010\t\u0003uui\u0011a\u000f\u0006\u0003ye\ta\u0001\u0010:p_Rt\u0014B\u0001 \u001e\u0003\u0019\u0001&/\u001a3fM&\u0011\u0001)\u0011\u0002\u0007\'R\u0014\u0018N\\4\u000b\u0005yj\u0012!D2p]R,g\u000e\u001e\'f]\u001e$\b.F\u0001E!\raR\'\u0012\t\u00039\u0019K!aR\u000f\u0003\t1{gnZ\u0001\t/JLG/\u00192mKB\u0011!JB\u0007\u0002/M\u0019aa\u0007\'\u0011\u0005)k\u0015B\u0001(\u0018\u00059aun\u001e)sS^\u0013\u0018\u000e^1cY\u0016\fa\u0001P5oSRtD#A%\u0003\u001dM#(/\u001b8h/JLG/\u00192mKN\u0019\u0001bG*\u0011\u0005)\u0003\u0011!A:\u0015\u0005YC\u0006CA,\t\u001b\u00051\u0001\"\u0002+\u000b\u0001\u00049DCA\u0012[\u0011\u0015I3\u00021\u0001++\u0005a\u0006c\u0001\u000f^?&\u0011a,\b\u0002\u0005\'>lW\r\u0005\u0002aG6\t\u0011M\u0003\u0002c]\u0005!A.\u00198h\u0013\t\u0001\u0015-F\u0001f!\raR,R\u0001\u000f\'R\u0014\u0018N\\4Xe&$\u0018M\u00197f)\t1\u0006\u000eC\u0003U\u001d\u0001\u0007qGA\tCsR,\u0017I\u001d:bs^\u0013\u0018\u000e^1cY\u0016\u001c2aD\u000eT\u0003\u0005\t\u0007c\u0001\u000fn_&\u0011a.\b\u0002\u0006\u0003J\u0014\u0018-\u001f\t\u00039AL!!]\u000f\u0003\t\tKH/\u001a\u000b\u0003gR\u0004\"aV\b\t\u000b-\f\u0002\u0019\u00017\u0015\u0005\r2\b\"B\u0015\u0013\u0001\u0004Q\u0013!\u0005\"zi\u0016\f%O]1z/JLG/\u00192mKR\u00111/\u001f\u0005\u0006WV\u0001\r\u0001\u001c
   #9 = Utf8               coursier/core/shaded/geny/Writable$ByteArrayWritable
  #10 = Class              #9             // coursier/core/shaded/geny/Writable$ByteArrayWritable
  #11 = Utf8               ByteArrayWritable
  #12 = Utf8               coursier/core/shaded/geny/Writable$StringWritable
  #13 = Class              #12            // coursier/core/shaded/geny/Writable$StringWritable
  #14 = Utf8               StringWritable
  #15 = Utf8               ([B)Lcoursier/core/shaded/geny/Writable$ByteArrayWritable;
  #16 = Utf8               a
  #17 = Utf8               coursier/core/shaded/geny/Writable$
  #18 = Class              #17            // coursier/core/shaded/geny/Writable$
  #19 = Utf8               MODULE$
  #20 = Utf8               Lcoursier/core/shaded/geny/Writable$;
  #21 = NameAndType        #19:#20        // MODULE$:Lcoursier/core/shaded/geny/Writable$;
  #22 = Fieldref           #18.#21        // coursier/core/shaded/geny/Writable$.MODULE$:Lcoursier/core/shaded/geny/Writable$;
  #23 = NameAndType        #11:#15        // ByteArrayWritable:([B)Lcoursier/core/shaded/geny/Writable$ByteArrayWritable;
  #24 = Methodref          #18.#23        // coursier/core/shaded/geny/Writable$.ByteArrayWritable:([B)Lcoursier/core/shaded/geny/Writable$ByteArrayWritable;
  #25 = Utf8               (Ljava/lang/String;)Lcoursier/core/shaded/geny/Writable$StringWritable;
  #26 = Utf8               s
  #27 = NameAndType        #14:#25        // StringWritable:(Ljava/lang/String;)Lcoursier/core/shaded/geny/Writable$StringWritable;
  #28 = Methodref          #18.#27        // coursier/core/shaded/geny/Writable$.StringWritable:(Ljava/lang/String;)Lcoursier/core/shaded/geny/Writable$StringWritable;
  #29 = Utf8               readableWritable
  #30 = Utf8               (Ljava/lang/Object;Lscala/Function1;)Lcoursier/core/shaded/geny/Writable;
  #31 = Utf8               <T:Ljava/lang/Object;>(TT;Lscala/Function1<TT;Lcoursier/core/shaded/geny/Readable;>;)Lcoursier/core/shaded/geny/Writable;
  #32 = Utf8               t
  #33 = Utf8               f
  #34 = NameAndType        #29:#30        // readableWritable:(Ljava/lang/Object;Lscala/Function1;)Lcoursier/core/shaded/geny/Writable;
  #35 = Methodref          #18.#34        // coursier/core/shaded/geny/Writable$.readableWritable:(Ljava/lang/Object;Lscala/Function1;)Lcoursier/core/shaded/geny/Writable;
  #36 = Utf8               writeBytesTo
  #37 = Utf8               (Ljava/io/OutputStream;)V
  #38 = Utf8               out
  #39 = Utf8               httpContentType$
  #40 = Utf8               (Lcoursier/core/shaded/geny/Writable;)Lscala/Option;
  #41 = Utf8               $this
  #42 = Utf8               httpContentType
  #43 = Utf8               ()Lscala/Option;
  #44 = NameAndType        #42:#43        // httpContentType:()Lscala/Option;
  #45 = InterfaceMethodref #2.#44         // coursier/core/shaded/geny/Writable.httpContentType:()Lscala/Option;
  #46 = Utf8               Lcoursier/core/shaded/geny/Writable;
  #47 = Utf8               ()Lscala/Option<Ljava/lang/String;>;
  #48 = Utf8               scala/None$
  #49 = Class              #48            // scala/None$
  #50 = Utf8               Lscala/None$;
  #51 = NameAndType        #19:#50        // MODULE$:Lscala/None$;
  #52 = Fieldref           #49.#51        // scala/None$.MODULE$:Lscala/None$;
  #53 = Utf8               this
  #54 = Utf8               contentLength$
  #55 = Utf8               contentLength
  #56 = NameAndType        #55:#43        // contentLength:()Lscala/Option;
  #57 = InterfaceMethodref #2.#56         // coursier/core/shaded/geny/Writable.contentLength:()Lscala/Option;
  #58 = Utf8               ()Lscala/Option<Ljava/lang/Object;>;
  #59 = Utf8               $init$
  #60 = Utf8               (Lcoursier/core/shaded/geny/Writable;)V
  #61 = Utf8               Code
  #62 = Utf8               MethodParameters
  #63 = Utf8               Signature
  #64 = Utf8               LineNumberTable
  #65 = Utf8               LocalVariableTable
  #66 = Utf8               InnerClasses
  #67 = Utf8               SourceFile
  #68 = Utf8               RuntimeVisibleAnnotations
  #69 = Utf8               ScalaInlineInfo
  #70 = Utf8               ScalaSig
{
  public static coursier.core.shaded.geny.Writable$ByteArrayWritable ByteArrayWritable(byte[]);
    descriptor: ([B)Lcoursier/core/shaded/geny/Writable$ByteArrayWritable;
    flags: (0x0009) ACC_PUBLIC, ACC_STATIC
    Code:
      stack=2, locals=1, args_size=1
         0: getstatic     #22                 // Field coursier/core/shaded/geny/Writable$.MODULE$:Lcoursier/core/shaded/geny/Writable$;
         3: aload_0
         4: invokevirtual #24                 // Method coursier/core/shaded/geny/Writable$.ByteArrayWritable:([B)Lcoursier/core/shaded/geny/Writable$ByteArrayWritable;
         7: areturn
    MethodParameters:
      Name                           Flags
      a                              final

  public static coursier.core.shaded.geny.Writable$StringWritable StringWritable(java.lang.String);
    descriptor: (Ljava/lang/String;)Lcoursier/core/shaded/geny/Writable$StringWritable;
    flags: (0x0009) ACC_PUBLIC, ACC_STATIC
    Code:
      stack=2, locals=1, args_size=1
         0: getstatic     #22                 // Field coursier/core/shaded/geny/Writable$.MODULE$:Lcoursier/core/shaded/geny/Writable$;
         3: aload_0
         4: invokevirtual #28                 // Method coursier/core/shaded/geny/Writable$.StringWritable:(Ljava/lang/String;)Lcoursier/core/shaded/geny/Writable$StringWritable;
         7: areturn
    MethodParameters:
      Name                           Flags
      s                              final

  public static <T extends java.lang.Object> coursier.core.shaded.geny.Writable readableWritable(T, scala.Function1<T, coursier.core.shaded.geny.Readable>);
    descriptor: (Ljava/lang/Object;Lscala/Function1;)Lcoursier/core/shaded/geny/Writable;
    flags: (0x0009) ACC_PUBLIC, ACC_STATIC
    Code:
      stack=3, locals=2, args_size=2
         0: getstatic     #22                 // Field coursier/core/shaded/geny/Writable$.MODULE$:Lcoursier/core/shaded/geny/Writable$;
         3: aload_0
         4: aload_1
         5: invokevirtual #35                 // Method coursier/core/shaded/geny/Writable$.readableWritable:(Ljava/lang/Object;Lscala/Function1;)Lcoursier/core/shaded/geny/Writable;
         8: areturn
    Signature: #31                          // <T:Ljava/lang/Object;>(TT;Lscala/Function1<TT;Lcoursier/core/shaded/geny/Readable;>;)Lcoursier/core/shaded/geny/Writable;
    MethodParameters:
      Name                           Flags
      t                              final
      f                              final

  public abstract void writeBytesTo(java.io.OutputStream);
    descriptor: (Ljava/io/OutputStream;)V
    flags: (0x0401) ACC_PUBLIC, ACC_ABSTRACT
    MethodParameters:
      Name                           Flags
      out                            final

  public static scala.Option httpContentType$(coursier.core.shaded.geny.Writable);
    descriptor: (Lcoursier/core/shaded/geny/Writable;)Lscala/Option;
    flags: (0x1009) ACC_PUBLIC, ACC_STATIC, ACC_SYNTHETIC
    Code:
      stack=1, locals=1, args_size=1
         0: aload_0
         1: invokespecial #45                 // InterfaceMethod httpContentType:()Lscala/Option;
         4: areturn
      LineNumberTable:
        line 25: 0
      LocalVariableTable:
        Start  Length  Slot  Name   Signature
            0       5     0 $this   Lcoursier/core/shaded/geny/Writable;
    MethodParameters:
      Name                           Flags
      $this                          final synthetic

  public default scala.Option<java.lang.String> httpContentType();
    descriptor: ()Lscala/Option;
    flags: (0x0001) ACC_PUBLIC
    Code:
      stack=1, locals=1, args_size=1
         0: getstatic     #52                 // Field scala/None$.MODULE$:Lscala/None$;
         3: areturn
      LineNumberTable:
        line 25: 0
      LocalVariableTable:
        Start  Length  Slot  Name   Signature
            0       4     0  this   Lcoursier/core/shaded/geny/Writable;
    Signature: #47                          // ()Lscala/Option<Ljava/lang/String;>;

  public static scala.Option contentLength$(coursier.core.shaded.geny.Writable);
    descriptor: (Lcoursier/core/shaded/geny/Writable;)Lscala/Option;
    flags: (0x1009) ACC_PUBLIC, ACC_STATIC, ACC_SYNTHETIC
    Code:
      stack=1, locals=1, args_size=1
         0: aload_0
         1: invokespecial #57                 // InterfaceMethod contentLength:()Lscala/Option;
         4: areturn
      LineNumberTable:
        line 26: 0
      LocalVariableTable:
        Start  Length  Slot  Name   Signature
            0       5     0 $this   Lcoursier/core/shaded/geny/Writable;
    MethodParameters:
      Name                           Flags
      $this                          final synthetic

  public default scala.Option<java.lang.Object> contentLength();
    descriptor: ()Lscala/Option;
    flags: (0x0001) ACC_PUBLIC
    Code:
      stack=1, locals=1, args_size=1
         0: getstatic     #52                 // Field scala/None$.MODULE$:Lscala/None$;
         3: areturn
      LineNumberTable:
        line 26: 0
      LocalVariableTable:
        Start  Length  Slot  Name   Signature
            0       4     0  this   Lcoursier/core/shaded/geny/Writable;
    Signature: #58                          // ()Lscala/Option<Ljava/lang/Object;>;

  public static void $init$(coursier.core.shaded.geny.Writable);
    descriptor: (Lcoursier/core/shaded/geny/Writable;)V
    flags: (0x0009) ACC_PUBLIC, ACC_STATIC
    Code:
      stack=0, locals=1, args_size=1
         0: return
      LineNumberTable:
        line 23: 0
      LocalVariableTable:
        Start  Length  Slot  Name   Signature
            0       1     0 $this   Lcoursier/core/shaded/geny/Writable;
    MethodParameters:
      Name                           Flags
      $this                          final synthetic
}
InnerClasses:
  public static #11= #10 of #2;           // ByteArrayWritable=class coursier/core/shaded/geny/Writable$ByteArrayWritable of class coursier/core/shaded/geny/Writable
  public static #14= #13 of #2;           // StringWritable=class coursier/core/shaded/geny/Writable$StringWritable of class coursier/core/shaded/geny/Writable
SourceFile: "Writable.scala"
RuntimeVisibleAnnotations:
  0: #6(#7=s#8)
    scala.reflect.ScalaSignature(
      bytes="\u0006\u0005i4qAF\f\u0011\u0002\u0007\u0005!\u0004C\u0003\"\u0001\u0011\u0005!\u0005C\u0003\'\u0001\u0019\u0005q\u0005C\u00033\u0001\u0011\u00051\u0007C\u0003C\u0001\u0011\u00051iB\u0003I/!\u0005\u0011JB\u0003\u0017/!\u00051\nC\u0003P\r\u0011\u0005\u0001K\u0002\u0003R\r\u0005\u0011\u0006\u0002\u0003+\t\u0005\u0003\u0005\u000b\u0011B\u001c\t\u000b=CA\u0011A+\t\u000b\u0019BA\u0011A-\t\u000bIBA\u0011I.\t\u000b\tCA\u0011\t3\t\u000f\u00194\u0011\u0011!C\u0002O\u001a!\u0011NB\u0001k\u0011!YwB!A!\u0002\u0013a\u0007\"B(\u0010\t\u0003\u0011\b\"\u0002\u0014\u0010\t\u0003)\b\"\u0002\u001a\u0010\t\u0003Z\u0006\"\u0002\"\u0010\t\u0003\"\u0007bB<\u0007\u0003\u0003%\u0019\u0001\u001f\u0002\t/JLG/\u00192mK*\t\u0001$\u0001\u0003hK:L8\u0001A\n\u0003\u0001m\u0001\"\u0001H\u0010\u000e\u0003uQ\u0011AH\u0001\u0006g\u000e\fG.Y\u0005\u0003Au\u0011a!\u00118z%\u00164\u0017A\u0002\u0013j]&$H\u0005F\u0001$!\taB%\u0003\u0002&;\t!QK\\5u\u000319(/\u001b;f\u0005f$Xm\u001d+p)\t\u0019\u0003\u0006C\u0003*\u0005\u0001\u0007!&A\u0002pkR\u0004\"a\u000b\u0019\u000e\u00031R!!\f\u0018\u0002\u0005%|\'\"A\u0018\u0002\t)\fg/Y\u0005\u0003c1\u0012AbT;uaV$8\u000b\u001e:fC6\fq\u0002\u001b;ua\u000e{g\u000e^3oiRK\b/Z\u000b\u0002iA\u0019A$N\u001c\n\u0005Yj\"AB(qi&|g\u000e\u0005\u00029\u007f9\u0011\u0011(\u0010\t\u0003uui\u0011a\u000f\u0006\u0003ye\ta\u0001\u0010:p_Rt\u0014B\u0001 \u001e\u0003\u0019\u0001&/\u001a3fM&\u0011\u0001)\u0011\u0002\u0007\'R\u0014\u0018N\\4\u000b\u0005yj\u0012!D2p]R,g\u000e\u001e\'f]\u001e$\b.F\u0001E!\raR\'\u0012\t\u00039\u0019K!aR\u000f\u0003\t1{gnZ\u0001\t/JLG/\u00192mKB\u0011!JB\u0007\u0002/M\u0019aa\u0007\'\u0011\u0005)k\u0015B\u0001(\u0018\u00059aun\u001e)sS^\u0013\u0018\u000e^1cY\u0016\fa\u0001P5oSRtD#A%\u0003\u001dM#(/\u001b8h/JLG/\u00192mKN\u0019\u0001bG*\u0011\u0005)\u0003\u0011!A:\u0015\u0005YC\u0006CA,\t\u001b\u00051\u0001\"\u0002+\u000b\u0001\u00049DCA\u0012[\u0011\u0015I3\u00021\u0001++\u0005a\u0006c\u0001\u000f^?&\u0011a,\b\u0002\u0005\'>lW\r\u0005\u0002aG6\t\u0011M\u0003\u0002c]\u0005!A.\u00198h\u0013\t\u0001\u0015-F\u0001f!\raR,R\u0001\u000f\'R\u0014\u0018N\\4Xe&$\u0018M\u00197f)\t1\u0006\u000eC\u0003U\u001d\u0001\u0007qGA\tCsR,\u0017I\u001d:bs^\u0013\u0018\u000e^1cY\u0016\u001c2aD\u000eT\u0003\u0005\t\u0007c\u0001\u000fn_&\u0011a.\b\u0002\u0006\u0003J\u0014\u0018-\u001f\t\u00039AL!!]\u000f\u0003\t\tKH/\u001a\u000b\u0003gR\u0004\"aV\b\t\u000b-\f\u0002\u0019\u00017\u0015\u0005\r2\b\"B\u0015\u0013\u0001\u0004Q\u0013!\u0005\"zi\u0016\f%O]1z/JLG/\u00192mKR\u00111/\u001f\u0005\u0006WV\u0001\r\u0001\u001c"
    )
  ScalaInlineInfo: length = 0x22 (unknown attribute)
   01 00 00 06 00 3B 00 3C 01 00 36 00 28 01 00 37
   00 2B 00 00 27 00 28 01 00 2A 00 2B 00 00 24 00
   25 00
  ScalaSig: length = 0x3 (unknown attribute)
   05 02 00
