Classfile /Users/mw/Projects/slang-braindump/.jar/jar11/assemble/slang-braindump/assemble/content/org/sireum/ops/ISZBOps.class
  Last modified May 29, 2022; size 15891 bytes
  SHA-256 checksum 44b8df66cbcc3c717e55620ab6abfb70bb71e4bf77202570c0b9a95ebc20e30a
  Compiled from "SOps.scala"
public final class org.sireum.ops.ISZBOps extends java.lang.Object implements org.sireum.ops.SBOps<org.sireum.Z>, org.sireum.DatatypeSig
  minor version: 0
  major version: 52
  flags: (0x0031) ACC_PUBLIC, ACC_FINAL, ACC_SUPER
  this_class: #2                          // org/sireum/ops/ISZBOps
  super_class: #5                         // java/lang/Object
  interfaces: 2, fields: 4, methods: 36, attributes: 7
Constant pool:
    #1 = Utf8               org/sireum/ops/ISZBOps
    #2 = Class              #1            // org/sireum/ops/ISZBOps
    #3 = Utf8               Ljava/lang/Object;Lorg/sireum/ops/SBOps<Lorg/sireum/Z;>;Lorg/sireum/DatatypeSig;
    #4 = Utf8               java/lang/Object
    #5 = Class              #4            // java/lang/Object
    #6 = Utf8               org/sireum/ops/SBOps
    #7 = Class              #6            // org/sireum/ops/SBOps
    #8 = Utf8               org/sireum/DatatypeSig
    #9 = Class              #8            // org/sireum/DatatypeSig
   #10 = Utf8               SOps.scala
   #11 = Utf8               Lscala/reflect/ScalaSignature;
   #12 = Utf8               bytes
   #13 = Utf8               \u0006\u0005\u0005ut!\u0002\u000e\u001c\u0011\u0003\u0011c!\u0002\u0013\u001c\u0011\u0003)\u0003\"\u0002\u0017\u0002\t\u0003i\u0003\"\u0002\u0018\u0002\t\u0003y\u0003\"B\"\u0002\t\u0003!\u0005\"\u0002&\u0002\t\u0003Y\u0005\"B*\u0002\t\u0003!\u0006\"B.\u0002\t\u0003a\u0006bBA9\u0003\u0011\u0005\u00111\u000f\u0004\u0005Im\u0011a\f\u0003\u0005f\u0013\t\u0005\t\u0015!\u00031\u0011\u0015a\u0013\u0002\"\u0001g\u0011\u0019A\u0017\u0002)A\u0005a!)Q*\u0003C\u0001S\")!.\u0003C\u0001S\")1.\u0003C!Y\")Q/\u0003C!m\"A\u00110\u0003EC\u0002\u0013\u0005#\u0010C\u0003\u007f\u0013\u0011\u0005s\u0010\u0003\u0004\\\u0013\u0011\u0005\u0011\u0011\u0003\u0005\n\u0003+I\u0011\u0013!C\u0001\u0003/A!\"!\f\n\u0011\u000b\u0007I\u0011IA\u0018\u0011\u001d\ty%\u0003C\u0001\u0003#Bq!!\u0016\n\t\u0003\t9\u0006C\u0004\u0002\\%!\t!!\u0018\t\u000f\u0005\u0005\u0014\u0002\"\u0001\u0002d\u00059\u0011j\u0015.C\u001fB\u001c(B\u0001\u000f\u001e\u0003\ry\u0007o\u001d\u0006\u0003=}\taa]5sKVl\'\"\u0001\u0011\u0002\u0007=\u0014xm\u0001\u0001\u0011\u0005\r\nQ\"A\u000e\u0003\u000f%\u001b&LQ(qgN\u0011\u0011A\n\t\u0003O)j\u0011\u0001\u000b\u0006\u0002S\u0005)1oY1mC&\u00111\u0006\u000b\u0002\u0007\u0003:L(+\u001a4\u0002\rqJg.\u001b;?)\u0005\u0011\u0013A\u00024s_6,\u0006\b\u0006\u00021uA!\u0011G\r\u001b8\u001b\u0005i\u0012BA\u001a\u001e\u0005\tI5\u000b\u0005\u00022k%\u0011a\'\b\u0002\u00025B\u0011\u0011\u0007O\u0005\u0003su\u0011\u0011A\u0011\u0005\u0006w\r\u0001\r\u0001P\u0001\u0002]B\u0011\u0011\'P\u0005\u0003}u\u0011!!\u0016\u001d)\u0005\r\u0001\u0005CA\u0019B\u0013\t\u0011UD\u0001\u0003qkJ,\u0017a\u00024s_6,\u0016G\u000e\u000b\u0003a\u0015CQa\u000f\u0003A\u0002\u0019\u0003\"!M$\n\u0005!k\"aA+2m!\u0012A\u0001Q\u0001\bMJ|W.V\u001a3)\r\u0001DJ\u0014\u0005\u0006\u001b\u0016\u0001\r\u0001M\u0001\u0002g\")1(\u0002a\u0001\u001fB\u0011\u0011\u0007U\u0005\u0003#v\u00111!V\u001a3Q\t)\u0001)A\u0004ge>lWK\u000e\u001b\u0015\u0007A*f\u000bC\u0003N\r\u0001\u0007\u0001\u0007C\u0003<\r\u0001\u0007q\u000b\u0005\u000221&\u0011\u0011,\b\u0002\u0004+Z\"\u0004F\u0001\u0004A\u0003\u0015\t\u0007\u000f\u001d7z)\ri\u0016q\u000e\t\u0003G%\u0019B!\u0003\u0014`EB\u00191\u0005\u0019\u001b\n\u0005\u0005\\\"!B*C\u001fB\u001c\bCA\u0019d\u0013\t!WDA\u0006ECR\fG/\u001f9f\'&<\u0017aA0`gR\u0011Ql\u001a\u0005\u0006K.\u0001\r\u0001M\u0001\u0003?N,\u0012\u0001M\u0001\u0005O\u0016$8+\u0001\u0005u_N#(/\u001b8h)\u0005i\u0007C\u00018t\u001b\u0005y\'B\u00019r\u0003\u0011a\u0017M\\4\u000b\u0003I\fAA[1wC&\u0011Ao\u001c\u0002\u0007\'R\u0014\u0018N\\4\u0002\rM$(/\u001b8h+\u00059\bCA\u0019y\u0013\t!X$\u0001\u0005iCND7i\u001c3f+\u0005Y\bCA\u0014}\u0013\ti\bFA\u0002J]R\fa!Z9vC2\u001cH\u0003BA\u0001\u0003\u000f\u00012aJA\u0002\u0013\r\t)\u0001\u000b\u0002\b\u0005>|G.Z1o\u0011\u001d\tIA\u0005a\u0001\u0003\u0017\t\u0011a\u001c\t\u0004O\u00055\u0011bAA\bQ\t\u0019\u0011I\\=\u0015\u0007u\u000b\u0019\u0002C\u0004N\'A\u0005\t\u0019\u0001\u0019\u0002\u001f\u0005\u0004\b\u000f\\=%I\u00164\u0017-\u001e7uIE*\"!!\u0007+\u0007A\nYb\u000b\u0002\u0002\u001eA!\u0011qDA\u0015\u001b\t\t\tC\u0003\u0003\u0002$\u0005\u0015\u0012!C;oG\",7m[3e\u0015\r\t9\u0003K\u0001\u000bC:tw\u000e^1uS>t\u0017\u0002BA\u0016\u0003C\u0011\u0011#\u001e8dQ\u0016\u001c7.\u001a3WCJL\u0017M\\2f\u0003!!3m\u001c8uK:$XCAA\u0019!\u0019\t\u0019$a\u0011\u0002J9!\u0011QGA \u001d\u0011\t9$!\u0010\u000e\u0005\u0005e\"bAA\u001eC\u00051AH]8pizJ\u0011!K\u0005\u0004\u0003\u0003B\u0013a\u00029bG.\fw-Z\u0005\u0005\u0003\u000b\n9EA\u0002TKFT1!!\u0011)!\u00199\u00131J7\u0002\f%\u0019\u0011Q\n\u0015\u0003\rQ+\b\u000f\\33\u0003\u0011!x.\u0016\u001d\u0016\u0003qB#A\u0006!\u0002\u000bQ|W+\r\u001c\u0016\u0003\u0019C#a\u0006!\u0002\u000bQ|Wk\r\u001a\u0016\u0003=C#\u0001\u0007!\u0002\u000bQ|WK\u000e\u001b\u0016\u0003]C#!\u0007!)\u0007%\tI\u0007E\u00022\u0003WJ1!!\u001c\u001e\u0005!!\u0017\r^1usB,\u0007\"B\'\b\u0001\u0004\u0001\u0014aB;oCB\u0004H.\u001f\u000b\u0005\u0003k\nY\b\u0005\u0003(\u0003o\u0002\u0014bAA=Q\t!1k\\7f\u0011\u0019\tI\u0001\u0003a\u0001;\u0002
   #14 = Utf8               java/lang/invoke/MethodHandles$Lookup
   #15 = Class              #14           // java/lang/invoke/MethodHandles$Lookup
   #16 = Utf8               java/lang/invoke/MethodHandles
   #17 = Class              #16           // java/lang/invoke/MethodHandles
   #18 = Utf8               Lookup
   #19 = Utf8               org/sireum/U16$U16$Slang
   #20 = Class              #19           // org/sireum/U16$U16$Slang
   #21 = Utf8               org/sireum/U16
   #22 = Class              #21           // org/sireum/U16
   #23 = Utf8               U16$Slang
   #24 = Utf8               org/sireum/U16$U16$Slang$u16$
   #25 = Class              #24           // org/sireum/U16$U16$Slang$u16$
   #26 = Utf8               u16$
   #27 = Utf8               org/sireum/U32$U32$Slang
   #28 = Class              #27           // org/sireum/U32$U32$Slang
   #29 = Utf8               org/sireum/U32
   #30 = Class              #29           // org/sireum/U32
   #31 = Utf8               U32$Slang
   #32 = Utf8               org/sireum/U32$U32$Slang$u32$
   #33 = Class              #32           // org/sireum/U32$U32$Slang$u32$
   #34 = Utf8               u32$
   #35 = Utf8               org/sireum/U64$U64$Slang
   #36 = Class              #35           // org/sireum/U64$U64$Slang
   #37 = Utf8               org/sireum/U64
   #38 = Class              #37           // org/sireum/U64
   #39 = Utf8               U64$Slang
   #40 = Utf8               org/sireum/U64$U64$Slang$u64$
   #41 = Class              #40           // org/sireum/U64$U64$Slang$u64$
   #42 = Utf8               u64$
   #43 = Utf8               org/sireum/U8$U8$Slang
   #44 = Class              #43           // org/sireum/U8$U8$Slang
   #45 = Utf8               org/sireum/U8
   #46 = Class              #45           // org/sireum/U8
   #47 = Utf8               U8$Slang
   #48 = Utf8               org/sireum/U8$U8$Slang$u8$
   #49 = Class              #48           // org/sireum/U8$U8$Slang$u8$
   #50 = Utf8               u8$
   #51 = Utf8               org/sireum/Z$BV$
   #52 = Class              #51           // org/sireum/Z$BV$
   #53 = Utf8               org/sireum/Z
   #54 = Class              #53           // org/sireum/Z
   #55 = Utf8               BV$
   #56 = Utf8               org/sireum/Z$BV$Byte
   #57 = Class              #56           // org/sireum/Z$BV$Byte
   #58 = Utf8               Byte
   #59 = Utf8               org/sireum/Z$BV$Int
   #60 = Class              #59           // org/sireum/Z$BV$Int
   #61 = Utf8               Int
   #62 = Utf8               org/sireum/Z$BV$Long
   #63 = Class              #62           // org/sireum/Z$BV$Long
   #64 = Utf8               Long
   #65 = Utf8               org/sireum/Z$BV$Short
   #66 = Class              #65           // org/sireum/Z$BV$Short
   #67 = Utf8               Short
   #68 = Utf8               hashCode
   #69 = Utf8               I
   #70 = Utf8               $content
   #71 = Utf8               Lscala/collection/immutable/Seq;
   #72 = Utf8               Lscala/collection/immutable/Seq<Lscala/Tuple2<Ljava/lang/String;Ljava/lang/Object;>;>;
   #73 = Utf8               _s
   #74 = Utf8               Lorg/sireum/IS;
   #75 = Utf8               Lorg/sireum/IS<Lorg/sireum/Z;Lorg/sireum/B;>;
   #76 = Utf8               bitmap$0
   #77 = Utf8               B
   #78 = Utf8               unapply
   #79 = Utf8               (Lorg/sireum/ops/ISZBOps;)Lscala/Some;
   #80 = Utf8               (Lorg/sireum/ops/ISZBOps;)Lscala/Some<Lorg/sireum/IS<Lorg/sireum/Z;Lorg/sireum/B;>;>;
   #81 = Utf8               o
   #82 = Utf8               org/sireum/ops/ISZBOps$
   #83 = Class              #82           // org/sireum/ops/ISZBOps$
   #84 = Utf8               MODULE$
   #85 = Utf8               Lorg/sireum/ops/ISZBOps$;
   #86 = NameAndType        #84:#85       // MODULE$:Lorg/sireum/ops/ISZBOps$;
   #87 = Fieldref           #83.#86       // org/sireum/ops/ISZBOps$.MODULE$:Lorg/sireum/ops/ISZBOps$;
   #88 = NameAndType        #78:#79       // unapply:(Lorg/sireum/ops/ISZBOps;)Lscala/Some;
   #89 = Methodref          #83.#88       // org/sireum/ops/ISZBOps$.unapply:(Lorg/sireum/ops/ISZBOps;)Lscala/Some;
   #90 = Utf8               Lorg/sireum/ops/ISZBOps;
   #91 = Utf8               fromU64
   #92 = Utf8               (Lorg/sireum/IS;J)Lorg/sireum/IS;
   #93 = Utf8               (Lorg/sireum/IS<Lorg/sireum/Z;Lorg/sireum/B;>;J)Lorg/sireum/IS<Lorg/sireum/Z;Lorg/sireum/B;>;
   #94 = Utf8               s
   #95 = Utf8               n
   #96 = NameAndType        #91:#92       // fromU64:(Lorg/sireum/IS;J)Lorg/sireum/IS;
   #97 = Methodref          #83.#96       // org/sireum/ops/ISZBOps$.fromU64:(Lorg/sireum/IS;J)Lorg/sireum/IS;
   #98 = Utf8               J
   #99 = Utf8               fromU32
  #100 = Utf8               (Lorg/sireum/IS;I)Lorg/sireum/IS;
  #101 = Utf8               (Lorg/sireum/IS<Lorg/sireum/Z;Lorg/sireum/B;>;I)Lorg/sireum/IS<Lorg/sireum/Z;Lorg/sireum/B;>;
  #102 = NameAndType        #99:#100      // fromU32:(Lorg/sireum/IS;I)Lorg/sireum/IS;
  #103 = Methodref          #83.#102      // org/sireum/ops/ISZBOps$.fromU32:(Lorg/sireum/IS;I)Lorg/sireum/IS;
  #104 = Utf8               fromU16
  #105 = Utf8               (S)Lorg/sireum/IS;
  #106 = Utf8               (S)Lorg/sireum/IS<Lorg/sireum/Z;Lorg/sireum/B;>;
  #107 = NameAndType        #104:#105     // fromU16:(S)Lorg/sireum/IS;
  #108 = Methodref          #83.#107      // org/sireum/ops/ISZBOps$.fromU16:(S)Lorg/sireum/IS;
  #109 = Utf8               S
  #110 = Utf8               fromU8
  #111 = Utf8               (B)Lorg/sireum/IS;
  #112 = Utf8               (B)Lorg/sireum/IS<Lorg/sireum/Z;Lorg/sireum/B;>;
  #113 = NameAndType        #110:#111     // fromU8:(B)Lorg/sireum/IS;
  #114 = Methodref          #83.#113      // org/sireum/ops/ISZBOps$.fromU8:(B)Lorg/sireum/IS;
  #115 = Utf8               hash
  #116 = Utf8               ()Lorg/sireum/Z;
  #117 = Utf8               hash$
  #118 = Utf8               (Lorg/sireum/DatatypeSig;)Lorg/sireum/Z;
  #119 = NameAndType        #117:#118     // hash$:(Lorg/sireum/DatatypeSig;)Lorg/sireum/Z;
  #120 = InterfaceMethodref #9.#119       // org/sireum/DatatypeSig.hash$:(Lorg/sireum/DatatypeSig;)Lorg/sireum/Z;
  #121 = Utf8               this
  #122 = Utf8               $cannotMixImmutableAndMutable
  #123 = Utf8               ()Lscala/runtime/Nothing$;
  #124 = Utf8               org/sireum/Immutable
  #125 = Class              #124          // org/sireum/Immutable
  #126 = Utf8               $cannotMixImmutableAndMutable$
  #127 = Utf8               (Lorg/sireum/Immutable;)Lscala/runtime/Nothing$;
  #128 = NameAndType        #126:#127     // $cannotMixImmutableAndMutable$:(Lorg/sireum/Immutable;)Lscala/runtime/Nothing$;
  #129 = InterfaceMethodref #125.#128     // org/sireum/Immutable.$cannotMixImmutableAndMutable$:(Lorg/sireum/Immutable;)Lscala/runtime/Nothing$;
  #130 = Utf8               $hasEquals
  #131 = Utf8               ()Z
  #132 = Utf8               $hasEquals$
  #133 = Utf8               (Lorg/sireum/Immutable;)Z
  #134 = NameAndType        #132:#133     // $hasEquals$:(Lorg/sireum/Immutable;)Z
  #135 = InterfaceMethodref #125.#134     // org/sireum/Immutable.$hasEquals$:(Lorg/sireum/Immutable;)Z
  #136 = Utf8               $hasString
  #137 = Utf8               $hasString$
  #138 = NameAndType        #137:#133     // $hasString$:(Lorg/sireum/Immutable;)Z
  #139 = InterfaceMethodref #125.#138     // org/sireum/Immutable.$hasString$:(Lorg/sireum/Immutable;)Z
  #140 = Utf8               $clone
  #141 = Utf8               ()Lorg/sireum/$internal/ImmutableMarker;
  #142 = Utf8               org/sireum/$internal/ImmutableMarker
  #143 = Class              #142          // org/sireum/$internal/ImmutableMarker
  #144 = Utf8               $clone$
  #145 = Utf8               (Lorg/sireum/$internal/ImmutableMarker;)Lorg/sireum/$internal/ImmutableMarker;
  #146 = NameAndType        #144:#145     // $clone$:(Lorg/sireum/$internal/ImmutableMarker;)Lorg/sireum/$internal/ImmutableMarker;
  #147 = InterfaceMethodref #143.#146     // org/sireum/$internal/ImmutableMarker.$clone$:(Lorg/sireum/$internal/ImmutableMarker;)Lorg/sireum/$internal/ImmutableMarker;
  #148 = Utf8               ()Lorg/sireum/IS;
  #149 = Utf8               ()Lorg/sireum/IS<Lorg/sireum/Z;Lorg/sireum/B;>;
  #150 = NameAndType        #73:#74       // _s:Lorg/sireum/IS;
  #151 = Fieldref           #2.#150       // org/sireum/ops/ISZBOps._s:Lorg/sireum/IS;
  #152 = Utf8               getS
  #153 = Utf8               toString
  #154 = Utf8               ()Ljava/lang/String;
  #155 = NameAndType        #136:#131     // $hasString:()Z
  #156 = Methodref          #2.#155       // org/sireum/ops/ISZBOps.$hasString:()Z
  #157 = Utf8               string$
  #158 = Utf8               (Lorg/sireum/DatatypeSig;)Ljava/lang/String;
  #159 = NameAndType        #157:#158     // string$:(Lorg/sireum/DatatypeSig;)Ljava/lang/String;
  #160 = InterfaceMethodref #9.#159       // org/sireum/DatatypeSig.string$:(Lorg/sireum/DatatypeSig;)Ljava/lang/String;
  #161 = Utf8               java/lang/StringBuilder
  #162 = Class              #161          // java/lang/StringBuilder
  #163 = Utf8               <init>
  #164 = Utf8               ()V
  #165 = NameAndType        #163:#164     // "<init>":()V
  #166 = Methodref          #162.#165     // java/lang/StringBuilder."<init>":()V
  #167 = Utf8               ISZBOps
  #168 = String             #167          // ISZBOps
  #169 = Utf8               append
  #170 = Utf8               (Ljava/lang/String;)Ljava/lang/StringBuilder;
  #171 = NameAndType        #169:#170     // append:(Ljava/lang/String;)Ljava/lang/StringBuilder;
  #172 = Methodref          #162.#171     // java/lang/StringBuilder.append:(Ljava/lang/String;)Ljava/lang/StringBuilder;
  #173 = Utf8               (C)Ljava/lang/StringBuilder;
  #174 = NameAndType        #169:#173     // append:(C)Ljava/lang/StringBuilder;
  #175 = Methodref          #162.#174     // java/lang/StringBuilder.append:(C)Ljava/lang/StringBuilder;
  #176 = Utf8               org/sireum/String$
  #177 = Class              #176          // org/sireum/String$
  #178 = Utf8               Lorg/sireum/String$;
  #179 = NameAndType        #84:#178      // MODULE$:Lorg/sireum/String$;
  #180 = Fieldref           #177.#179     // org/sireum/String$.MODULE$:Lorg/sireum/String$;
  #181 = NameAndType        #94:#148      // s:()Lorg/sireum/IS;
  #182 = Methodref          #2.#181       // org/sireum/ops/ISZBOps.s:()Lorg/sireum/IS;
  #183 = Utf8               escape
  #184 = Utf8               (Ljava/lang/Object;)Ljava/lang/String;
  #185 = NameAndType        #183:#184     // escape:(Ljava/lang/Object;)Ljava/lang/String;
  #186 = Methodref          #177.#185     // org/sireum/String$.escape:(Ljava/lang/Object;)Ljava/lang/String;
  #187 = NameAndType        #153:#154     // toString:()Ljava/lang/String;
  #188 = Methodref          #162.#187     // java/lang/StringBuilder.toString:()Ljava/lang/String;
  #189 = Utf8               sb
  #190 = Utf8               Ljava/lang/StringBuilder;
  #191 = Utf8               java/lang/String
  #192 = Class              #191          // java/lang/String
  #193 = Utf8               string
  #194 = Methodref          #2.#187       // org/sireum/ops/ISZBOps.toString:()Ljava/lang/String;
  #195 = Utf8               apply
  #196 = Utf8               (Ljava/lang/String;)Ljava/lang/String;
  #197 = NameAndType        #195:#196     // apply:(Ljava/lang/String;)Ljava/lang/String;
  #198 = Methodref          #177.#197     // org/sireum/String$.apply:(Ljava/lang/String;)Ljava/lang/String;
  #199 = Utf8               hashCode$lzycompute
  #200 = Utf8               ()I
  #201 = NameAndType        #76:#77       // bitmap$0:B
  #202 = Fieldref           #2.#201       // org/sireum/ops/ISZBOps.bitmap$0:B
  #203 = NameAndType        #130:#131     // $hasEquals:()Z
  #204 = Methodref          #2.#203       // org/sireum/ops/ISZBOps.$hasEquals:()Z
  #205 = NameAndType        #68:#200      // hashCode:()I
  #206 = Methodref          #5.#205       // java/lang/Object.hashCode:()I
  #207 = Utf8               scala/package$
  #208 = Class              #207          // scala/package$
  #209 = Utf8               Lscala/package$;
  #210 = NameAndType        #84:#209      // MODULE$:Lscala/package$;
  #211 = Fieldref           #208.#210     // scala/package$.MODULE$:Lscala/package$;
  #212 = Utf8               Seq
  #213 = Utf8               ()Lscala/collection/immutable/Seq$;
  #214 = NameAndType        #212:#213     // Seq:()Lscala/collection/immutable/Seq$;
  #215 = Methodref          #208.#214     // scala/package$.Seq:()Lscala/collection/immutable/Seq$;
  #216 = Utf8               scala/runtime/ScalaRunTime$
  #217 = Class              #216          // scala/runtime/ScalaRunTime$
  #218 = Utf8               Lscala/runtime/ScalaRunTime$;
  #219 = NameAndType        #84:#218      // MODULE$:Lscala/runtime/ScalaRunTime$;
  #220 = Fieldref           #217.#219     // scala/runtime/ScalaRunTime$.MODULE$:Lscala/runtime/ScalaRunTime$;
  #221 = Utf8               getClass
  #222 = Utf8               ()Ljava/lang/Class;
  #223 = NameAndType        #221:#222     // getClass:()Ljava/lang/Class;
  #224 = Methodref          #2.#223       // org/sireum/ops/ISZBOps.getClass:()Ljava/lang/Class;
  #225 = Utf8               java/lang/Class
  #226 = Class              #225          // java/lang/Class
  #227 = Utf8               getName
  #228 = NameAndType        #227:#154     // getName:()Ljava/lang/String;
  #229 = Methodref          #226.#228     // java/lang/Class.getName:()Ljava/lang/String;
  #230 = Utf8               wrapRefArray
  #231 = Utf8               ([Ljava/lang/Object;)Lscala/collection/immutable/ArraySeq;
  #232 = NameAndType        #230:#231     // wrapRefArray:([Ljava/lang/Object;)Lscala/collection/immutable/ArraySeq;
  #233 = Methodref          #217.#232     // scala/runtime/ScalaRunTime$.wrapRefArray:([Ljava/lang/Object;)Lscala/collection/immutable/ArraySeq;
  #234 = Utf8               scala/collection/immutable/Seq$
  #235 = Class              #234          // scala/collection/immutable/Seq$
  #236 = Utf8               (Lscala/collection/immutable/Seq;)Lscala/collection/SeqOps;
  #237 = NameAndType        #195:#236     // apply:(Lscala/collection/immutable/Seq;)Lscala/collection/SeqOps;
  #238 = Methodref          #235.#237     // scala/collection/immutable/Seq$.apply:(Lscala/collection/immutable/Seq;)Lscala/collection/SeqOps;
  #239 = Utf8               scala/collection/Seq
  #240 = Class              #239          // scala/collection/Seq
  #241 = InterfaceMethodref #240.#205     // scala/collection/Seq.hashCode:()I
  #242 = NameAndType        #68:#69       // hashCode:I
  #243 = Fieldref           #2.#242       // org/sireum/ops/ISZBOps.hashCode:I
  #244 = Utf8               java/lang/Throwable
  #245 = Class              #244          // java/lang/Throwable
  #246 = NameAndType        #199:#200     // hashCode$lzycompute:()I
  #247 = Methodref          #2.#246       // org/sireum/ops/ISZBOps.hashCode$lzycompute:()I
  #248 = Utf8               equals
  #249 = Utf8               (Ljava/lang/Object;)Z
  #250 = NameAndType        #248:#249     // equals:(Ljava/lang/Object;)Z
  #251 = Methodref          #5.#250       // java/lang/Object.equals:(Ljava/lang/Object;)Z
  #252 = Methodref          #2.#205       // org/sireum/ops/ISZBOps.hashCode:()I
  #253 = Utf8               Ljava/lang/Object;
  #254 = Utf8               org/sireum/IS
  #255 = Class              #254          // org/sireum/IS
  #256 = Utf8               (Lorg/sireum/IS;)Lorg/sireum/ops/ISZBOps;
  #257 = Utf8               (Lorg/sireum/IS<Lorg/sireum/Z;Lorg/sireum/B;>;)Lorg/sireum/ops/ISZBOps;
  #258 = Utf8               (Lorg/sireum/IS;)V
  #259 = NameAndType        #163:#258     // "<init>":(Lorg/sireum/IS;)V
  #260 = Methodref          #2.#259       // org/sireum/ops/ISZBOps."<init>":(Lorg/sireum/IS;)V
  #261 = Utf8               apply$default$1
  #262 = Utf8               $content$lzycompute
  #263 = Utf8               ()Lscala/collection/immutable/Seq;
  #264 = Utf8               ()Lscala/collection/immutable/Seq<Lscala/Tuple2<Ljava/lang/String;Ljava/lang/Object;>;>;
  #265 = Utf8               scala/Tuple2
  #266 = Class              #265          // scala/Tuple2
  #267 = Utf8               type
  #268 = String             #267          // type
  #269 = Utf8               List
  #270 = Utf8               ()Lscala/collection/immutable/List$;
  #271 = NameAndType        #269:#270     // List:()Lscala/collection/immutable/List$;
  #272 = Methodref          #208.#271     // scala/package$.List:()Lscala/collection/immutable/List$;
  #273 = Utf8               org
  #274 = String             #273          // org
  #275 = Utf8               sireum
  #276 = String             #275          // sireum
  #277 = Utf8               ops
  #278 = String             #277          // ops
  #279 = Utf8               [Ljava/lang/Object;
  #280 = Class              #279          // "[Ljava/lang/Object;"
  #281 = Utf8               scala/collection/immutable/List$
  #282 = Class              #281          // scala/collection/immutable/List$
  #283 = Utf8               (Lscala/collection/immutable/Seq;)Ljava/lang/Object;
  #284 = NameAndType        #195:#283     // apply:(Lscala/collection/immutable/Seq;)Ljava/lang/Object;
  #285 = Methodref          #282.#284     // scala/collection/immutable/List$.apply:(Lscala/collection/immutable/Seq;)Ljava/lang/Object;
  #286 = Utf8               (Ljava/lang/Object;Ljava/lang/Object;)V
  #287 = NameAndType        #163:#286     // "<init>":(Ljava/lang/Object;Ljava/lang/Object;)V
  #288 = Methodref          #266.#287     // scala/Tuple2."<init>":(Ljava/lang/Object;Ljava/lang/Object;)V
  #289 = String             #94           // s
  #290 = Utf8               scala/collection/immutable/Seq
  #291 = Class              #290          // scala/collection/immutable/Seq
  #292 = NameAndType        #70:#71       // $content:Lscala/collection/immutable/Seq;
  #293 = Fieldref           #2.#292       // org/sireum/ops/ISZBOps.$content:Lscala/collection/immutable/Seq;
  #294 = NameAndType        #262:#263     // $content$lzycompute:()Lscala/collection/immutable/Seq;
  #295 = Methodref          #2.#294       // org/sireum/ops/ISZBOps.$content$lzycompute:()Lscala/collection/immutable/Seq;
  #296 = Utf8               toU8
  #297 = Utf8               ()B
  #298 = Utf8               org/sireum/U8$
  #299 = Class              #298          // org/sireum/U8$
  #300 = Utf8               Lorg/sireum/U8$;
  #301 = NameAndType        #84:#300      // MODULE$:Lorg/sireum/U8$;
  #302 = Fieldref           #299.#301     // org/sireum/U8$.MODULE$:Lorg/sireum/U8$;
  #303 = Utf8               scala/StringContext
  #304 = Class              #303          // scala/StringContext
  #305 = Utf8               0
  #306 = String             #305          // 0
  #307 = Utf8               (Lscala/collection/immutable/Seq;)V
  #308 = NameAndType        #163:#307     // "<init>":(Lscala/collection/immutable/Seq;)V
  #309 = Methodref          #304.#308     // scala/StringContext."<init>":(Lscala/collection/immutable/Seq;)V
  #310 = Utf8               (Lscala/StringContext;)Lorg/sireum/U8$U8$Slang;
  #311 = NameAndType        #47:#310      // U8$Slang:(Lscala/StringContext;)Lorg/sireum/U8$U8$Slang;
  #312 = Methodref          #299.#311     // org/sireum/U8$.U8$Slang:(Lscala/StringContext;)Lorg/sireum/U8$U8$Slang;
  #313 = Utf8               u8
  #314 = Utf8               ()Lorg/sireum/U8$U8$Slang$u8$;
  #315 = NameAndType        #313:#314     // u8:()Lorg/sireum/U8$U8$Slang$u8$;
  #316 = Methodref          #44.#315      // org/sireum/U8$U8$Slang.u8:()Lorg/sireum/U8$U8$Slang$u8$;
  #317 = Utf8               scala/collection/immutable/Nil$
  #318 = Class              #317          // scala/collection/immutable/Nil$
  #319 = Utf8               Lscala/collection/immutable/Nil$;
  #320 = NameAndType        #84:#319      // MODULE$:Lscala/collection/immutable/Nil$;
  #321 = Fieldref           #318.#320     // scala/collection/immutable/Nil$.MODULE$:Lscala/collection/immutable/Nil$;
  #322 = Utf8               (Lscala/collection/immutable/Seq;)B
  #323 = NameAndType        #195:#322     // apply:(Lscala/collection/immutable/Seq;)B
  #324 = Methodref          #49.#323      // org/sireum/U8$U8$Slang$u8$.apply:(Lscala/collection/immutable/Seq;)B
  #325 = Utf8               scala/runtime/ByteRef
  #326 = Class              #325          // scala/runtime/ByteRef
  #327 = Utf8               create
  #328 = Utf8               (B)Lscala/runtime/ByteRef;
  #329 = NameAndType        #327:#328     // create:(B)Lscala/runtime/ByteRef;
  #330 = Methodref          #326.#329     // scala/runtime/ByteRef.create:(B)Lscala/runtime/ByteRef;
  #331 = Utf8               1
  #332 = String             #331          // 1
  #333 = Utf8               org/sireum/Z$
  #334 = Class              #333          // org/sireum/Z$
  #335 = Utf8               Lorg/sireum/Z$;
  #336 = NameAndType        #84:#335      // MODULE$:Lorg/sireum/Z$;
  #337 = Fieldref           #334.#336     // org/sireum/Z$.MODULE$:Lorg/sireum/Z$;
  #338 = Utf8               (I)Lorg/sireum/Z;
  #339 = NameAndType        #195:#338     // apply:(I)Lorg/sireum/Z;
  #340 = Methodref          #334.#339     // org/sireum/Z$.apply:(I)Lorg/sireum/Z;
  #341 = Utf8               until
  #342 = Utf8               (Lorg/sireum/ZLike;)Lorg/sireum/ZRange;
  #343 = NameAndType        #341:#342     // until:(Lorg/sireum/ZLike;)Lorg/sireum/ZRange;
  #344 = InterfaceMethodref #54.#343      // org/sireum/Z.until:(Lorg/sireum/ZLike;)Lorg/sireum/ZRange;
  #345 = Utf8               (Ljava/lang/Object;)Ljava/lang/Object;
  #346 = MethodType         #345          //  (Ljava/lang/Object;)Ljava/lang/Object;
  #347 = Utf8               $anonfun$toU8$1$adapted
  #348 = Utf8               (Lorg/sireum/ops/ISZBOps;Lscala/runtime/ByteRef;Lscala/runtime/ByteRef;Lorg/sireum/Z;)Ljava/lang/Object;
  #349 = NameAndType        #347:#348     // $anonfun$toU8$1$adapted:(Lorg/sireum/ops/ISZBOps;Lscala/runtime/ByteRef;Lscala/runtime/ByteRef;Lorg/sireum/Z;)Ljava/lang/Object;
  #350 = Methodref          #2.#349       // org/sireum/ops/ISZBOps.$anonfun$toU8$1$adapted:(Lorg/sireum/ops/ISZBOps;Lscala/runtime/ByteRef;Lscala/runtime/ByteRef;Lorg/sireum/Z;)Ljava/lang/Object;
  #351 = MethodHandle       6:#350        // REF_invokeStatic org/sireum/ops/ISZBOps.$anonfun$toU8$1$adapted:(Lorg/sireum/ops/ISZBOps;Lscala/runtime/ByteRef;Lscala/runtime/ByteRef;Lorg/sireum/Z;)Ljava/lang/Object;
  #352 = Utf8               (Lorg/sireum/Z;)Ljava/lang/Object;
  #353 = MethodType         #352          //  (Lorg/sireum/Z;)Ljava/lang/Object;
  #354 = Integer            5
  #355 = Integer            1
  #356 = Utf8               java/lang/invoke/LambdaMetafactory
  #357 = Class              #356          // java/lang/invoke/LambdaMetafactory
  #358 = Utf8               altMetafactory
  #359 = Utf8               (Ljava/lang/invoke/MethodHandles$Lookup;Ljava/lang/String;Ljava/lang/invoke/MethodType;[Ljava/lang/Object;)Ljava/lang/invoke/CallSite;
  #360 = NameAndType        #358:#359     // altMetafactory:(Ljava/lang/invoke/MethodHandles$Lookup;Ljava/lang/String;Ljava/lang/invoke/MethodType;[Ljava/lang/Object;)Ljava/lang/invoke/CallSite;
  #361 = Methodref          #357.#360     // java/lang/invoke/LambdaMetafactory.altMetafactory:(Ljava/lang/invoke/MethodHandles$Lookup;Ljava/lang/String;Ljava/lang/invoke/MethodType;[Ljava/lang/Object;)Ljava/lang/invoke/CallSite;
  #362 = MethodHandle       6:#361        // REF_invokeStatic java/lang/invoke/LambdaMetafactory.altMetafactory:(Ljava/lang/invoke/MethodHandles$Lookup;Ljava/lang/String;Ljava/lang/invoke/MethodType;[Ljava/lang/Object;)Ljava/lang/invoke/CallSite;
  #363 = Utf8               (Lorg/sireum/ops/ISZBOps;Lscala/runtime/ByteRef;Lscala/runtime/ByteRef;)Lscala/Function1;
  #364 = NameAndType        #195:#363     // apply:(Lorg/sireum/ops/ISZBOps;Lscala/runtime/ByteRef;Lscala/runtime/ByteRef;)Lscala/Function1;
  #365 = InvokeDynamic      #0:#364       // #0:apply:(Lorg/sireum/ops/ISZBOps;Lscala/runtime/ByteRef;Lscala/runtime/ByteRef;)Lscala/Function1;
  #366 = Utf8               org/sireum/ZRange
  #367 = Class              #366          // org/sireum/ZRange
  #368 = Utf8               foreach
  #369 = Utf8               (Lscala/Function1;)V
  #370 = NameAndType        #368:#369     // foreach:(Lscala/Function1;)V
  #371 = Methodref          #367.#370     // org/sireum/ZRange.foreach:(Lscala/Function1;)V
  #372 = Utf8               elem
  #373 = NameAndType        #372:#77      // elem:B
  #374 = Fieldref           #326.#373     // scala/runtime/ByteRef.elem:B
  #375 = Utf8               r
  #376 = Utf8               Lscala/runtime/ByteRef;
  #377 = Utf8               mask
  #378 = Utf8               toU16
  #379 = Utf8               ()S
  #380 = Utf8               org/sireum/U16$
  #381 = Class              #380          // org/sireum/U16$
  #382 = Utf8               Lorg/sireum/U16$;
  #383 = NameAndType        #84:#382      // MODULE$:Lorg/sireum/U16$;
  #384 = Fieldref           #381.#383     // org/sireum/U16$.MODULE$:Lorg/sireum/U16$;
  #385 = Utf8               (Lscala/StringContext;)Lorg/sireum/U16$U16$Slang;
  #386 = NameAndType        #23:#385      // U16$Slang:(Lscala/StringContext;)Lorg/sireum/U16$U16$Slang;
  #387 = Methodref          #381.#386     // org/sireum/U16$.U16$Slang:(Lscala/StringContext;)Lorg/sireum/U16$U16$Slang;
  #388 = Utf8               u16
  #389 = Utf8               ()Lorg/sireum/U16$U16$Slang$u16$;
  #390 = NameAndType        #388:#389     // u16:()Lorg/sireum/U16$U16$Slang$u16$;
  #391 = Methodref          #20.#390      // org/sireum/U16$U16$Slang.u16:()Lorg/sireum/U16$U16$Slang$u16$;
  #392 = Utf8               (Lscala/collection/immutable/Seq;)S
  #393 = NameAndType        #195:#392     // apply:(Lscala/collection/immutable/Seq;)S
  #394 = Methodref          #25.#393      // org/sireum/U16$U16$Slang$u16$.apply:(Lscala/collection/immutable/Seq;)S
  #395 = Utf8               scala/runtime/ShortRef
  #396 = Class              #395          // scala/runtime/ShortRef
  #397 = Utf8               (S)Lscala/runtime/ShortRef;
  #398 = NameAndType        #327:#397     // create:(S)Lscala/runtime/ShortRef;
  #399 = Methodref          #396.#398     // scala/runtime/ShortRef.create:(S)Lscala/runtime/ShortRef;
  #400 = Utf8               $anonfun$toU16$1$adapted
  #401 = Utf8               (Lorg/sireum/ops/ISZBOps;Lscala/runtime/ShortRef;Lscala/runtime/ShortRef;Lorg/sireum/Z;)Ljava/lang/Object;
  #402 = NameAndType        #400:#401     // $anonfun$toU16$1$adapted:(Lorg/sireum/ops/ISZBOps;Lscala/runtime/ShortRef;Lscala/runtime/ShortRef;Lorg/sireum/Z;)Ljava/lang/Object;
  #403 = Methodref          #2.#402       // org/sireum/ops/ISZBOps.$anonfun$toU16$1$adapted:(Lorg/sireum/ops/ISZBOps;Lscala/runtime/ShortRef;Lscala/runtime/ShortRef;Lorg/sireum/Z;)Ljava/lang/Object;
  #404 = MethodHandle       6:#403        // REF_invokeStatic org/sireum/ops/ISZBOps.$anonfun$toU16$1$adapted:(Lorg/sireum/ops/ISZBOps;Lscala/runtime/ShortRef;Lscala/runtime/ShortRef;Lorg/sireum/Z;)Ljava/lang/Object;
  #405 = Utf8               (Lorg/sireum/ops/ISZBOps;Lscala/runtime/ShortRef;Lscala/runtime/ShortRef;)Lscala/Function1;
  #406 = NameAndType        #195:#405     // apply:(Lorg/sireum/ops/ISZBOps;Lscala/runtime/ShortRef;Lscala/runtime/ShortRef;)Lscala/Function1;
  #407 = InvokeDynamic      #1:#406       // #1:apply:(Lorg/sireum/ops/ISZBOps;Lscala/runtime/ShortRef;Lscala/runtime/ShortRef;)Lscala/Function1;
  #408 = NameAndType        #372:#109     // elem:S
  #409 = Fieldref           #396.#408     // scala/runtime/ShortRef.elem:S
  #410 = Utf8               Lscala/runtime/ShortRef;
  #411 = Utf8               toU32
  #412 = Utf8               org/sireum/U32$
  #413 = Class              #412          // org/sireum/U32$
  #414 = Utf8               Lorg/sireum/U32$;
  #415 = NameAndType        #84:#414      // MODULE$:Lorg/sireum/U32$;
  #416 = Fieldref           #413.#415     // org/sireum/U32$.MODULE$:Lorg/sireum/U32$;
  #417 = Utf8               (Lscala/StringContext;)Lorg/sireum/U32$U32$Slang;
  #418 = NameAndType        #31:#417      // U32$Slang:(Lscala/StringContext;)Lorg/sireum/U32$U32$Slang;
  #419 = Methodref          #413.#418     // org/sireum/U32$.U32$Slang:(Lscala/StringContext;)Lorg/sireum/U32$U32$Slang;
  #420 = Utf8               u32
  #421 = Utf8               ()Lorg/sireum/U32$U32$Slang$u32$;
  #422 = NameAndType        #420:#421     // u32:()Lorg/sireum/U32$U32$Slang$u32$;
  #423 = Methodref          #28.#422      // org/sireum/U32$U32$Slang.u32:()Lorg/sireum/U32$U32$Slang$u32$;
  #424 = Utf8               (Lscala/collection/immutable/Seq;)I
  #425 = NameAndType        #195:#424     // apply:(Lscala/collection/immutable/Seq;)I
  #426 = Methodref          #33.#425      // org/sireum/U32$U32$Slang$u32$.apply:(Lscala/collection/immutable/Seq;)I
  #427 = Utf8               scala/runtime/IntRef
  #428 = Class              #427          // scala/runtime/IntRef
  #429 = Utf8               (I)Lscala/runtime/IntRef;
  #430 = NameAndType        #327:#429     // create:(I)Lscala/runtime/IntRef;
  #431 = Methodref          #428.#430     // scala/runtime/IntRef.create:(I)Lscala/runtime/IntRef;
  #432 = Utf8               $anonfun$toU32$1$adapted
  #433 = Utf8               (Lorg/sireum/ops/ISZBOps;Lscala/runtime/IntRef;Lscala/runtime/IntRef;Lorg/sireum/Z;)Ljava/lang/Object;
  #434 = NameAndType        #432:#433     // $anonfun$toU32$1$adapted:(Lorg/sireum/ops/ISZBOps;Lscala/runtime/IntRef;Lscala/runtime/IntRef;Lorg/sireum/Z;)Ljava/lang/Object;
  #435 = Methodref          #2.#434       // org/sireum/ops/ISZBOps.$anonfun$toU32$1$adapted:(Lorg/sireum/ops/ISZBOps;Lscala/runtime/IntRef;Lscala/runtime/IntRef;Lorg/sireum/Z;)Ljava/lang/Object;
  #436 = MethodHandle       6:#435        // REF_invokeStatic org/sireum/ops/ISZBOps.$anonfun$toU32$1$adapted:(Lorg/sireum/ops/ISZBOps;Lscala/runtime/IntRef;Lscala/runtime/IntRef;Lorg/sireum/Z;)Ljava/lang/Object;
  #437 = Utf8               (Lorg/sireum/ops/ISZBOps;Lscala/runtime/IntRef;Lscala/runtime/IntRef;)Lscala/Function1;
  #438 = NameAndType        #195:#437     // apply:(Lorg/sireum/ops/ISZBOps;Lscala/runtime/IntRef;Lscala/runtime/IntRef;)Lscala/Function1;
  #439 = InvokeDynamic      #2:#438       // #2:apply:(Lorg/sireum/ops/ISZBOps;Lscala/runtime/IntRef;Lscala/runtime/IntRef;)Lscala/Function1;
  #440 = NameAndType        #372:#69      // elem:I
  #441 = Fieldref           #428.#440     // scala/runtime/IntRef.elem:I
  #442 = Utf8               Lscala/runtime/IntRef;
  #443 = Utf8               toU64
  #444 = Utf8               ()J
  #445 = Utf8               org/sireum/U64$
  #446 = Class              #445          // org/sireum/U64$
  #447 = Utf8               Lorg/sireum/U64$;
  #448 = NameAndType        #84:#447      // MODULE$:Lorg/sireum/U64$;
  #449 = Fieldref           #446.#448     // org/sireum/U64$.MODULE$:Lorg/sireum/U64$;
  #450 = Utf8               (Lscala/StringContext;)Lorg/sireum/U64$U64$Slang;
  #451 = NameAndType        #39:#450      // U64$Slang:(Lscala/StringContext;)Lorg/sireum/U64$U64$Slang;
  #452 = Methodref          #446.#451     // org/sireum/U64$.U64$Slang:(Lscala/StringContext;)Lorg/sireum/U64$U64$Slang;
  #453 = Utf8               u64
  #454 = Utf8               ()Lorg/sireum/U64$U64$Slang$u64$;
  #455 = NameAndType        #453:#454     // u64:()Lorg/sireum/U64$U64$Slang$u64$;
  #456 = Methodref          #36.#455      // org/sireum/U64$U64$Slang.u64:()Lorg/sireum/U64$U64$Slang$u64$;
  #457 = Utf8               (Lscala/collection/immutable/Seq;)J
  #458 = NameAndType        #195:#457     // apply:(Lscala/collection/immutable/Seq;)J
  #459 = Methodref          #41.#458      // org/sireum/U64$U64$Slang$u64$.apply:(Lscala/collection/immutable/Seq;)J
  #460 = Utf8               scala/runtime/LongRef
  #461 = Class              #460          // scala/runtime/LongRef
  #462 = Utf8               (J)Lscala/runtime/LongRef;
  #463 = NameAndType        #327:#462     // create:(J)Lscala/runtime/LongRef;
  #464 = Methodref          #461.#463     // scala/runtime/LongRef.create:(J)Lscala/runtime/LongRef;
  #465 = Utf8               $anonfun$toU64$1$adapted
  #466 = Utf8               (Lorg/sireum/ops/ISZBOps;Lscala/runtime/LongRef;Lscala/runtime/LongRef;Lorg/sireum/Z;)Ljava/lang/Object;
  #467 = NameAndType        #465:#466     // $anonfun$toU64$1$adapted:(Lorg/sireum/ops/ISZBOps;Lscala/runtime/LongRef;Lscala/runtime/LongRef;Lorg/sireum/Z;)Ljava/lang/Object;
  #468 = Methodref          #2.#467       // org/sireum/ops/ISZBOps.$anonfun$toU64$1$adapted:(Lorg/sireum/ops/ISZBOps;Lscala/runtime/LongRef;Lscala/runtime/LongRef;Lorg/sireum/Z;)Ljava/lang/Object;
  #469 = MethodHandle       6:#468        // REF_invokeStatic org/sireum/ops/ISZBOps.$anonfun$toU64$1$adapted:(Lorg/sireum/ops/ISZBOps;Lscala/runtime/LongRef;Lscala/runtime/LongRef;Lorg/sireum/Z;)Ljava/lang/Object;
  #470 = Utf8               (Lorg/sireum/ops/ISZBOps;Lscala/runtime/LongRef;Lscala/runtime/LongRef;)Lscala/Function1;
  #471 = NameAndType        #195:#470     // apply:(Lorg/sireum/ops/ISZBOps;Lscala/runtime/LongRef;Lscala/runtime/LongRef;)Lscala/Function1;
  #472 = InvokeDynamic      #3:#471       // #3:apply:(Lorg/sireum/ops/ISZBOps;Lscala/runtime/LongRef;Lscala/runtime/LongRef;)Lscala/Function1;
  #473 = NameAndType        #372:#98      // elem:J
  #474 = Fieldref           #461.#473     // scala/runtime/LongRef.elem:J
  #475 = Utf8               Lscala/runtime/LongRef;
  #476 = Utf8               ()Ljava/lang/Object;
  #477 = NameAndType        #140:#141     // $clone:()Lorg/sireum/$internal/ImmutableMarker;
  #478 = Methodref          #2.#477       // org/sireum/ops/ISZBOps.$clone:()Lorg/sireum/$internal/ImmutableMarker;
  #479 = Utf8               $anonfun$toU8$1
  #480 = Utf8               (Lorg/sireum/ops/ISZBOps;Lscala/runtime/ByteRef;Lscala/runtime/ByteRef;Lorg/sireum/Z;)V
  #481 = Utf8               $this
  #482 = Utf8               r$17
  #483 = Utf8               mask$1
  #484 = Utf8               i
  #485 = Utf8               org/sireum/B$
  #486 = Class              #485          // org/sireum/B$
  #487 = Utf8               Lorg/sireum/B$;
  #488 = NameAndType        #84:#487      // MODULE$:Lorg/sireum/B$;
  #489 = Fieldref           #486.#488     // org/sireum/B$.MODULE$:Lorg/sireum/B$;
  #490 = NameAndType        #195:#345     // apply:(Ljava/lang/Object;)Ljava/lang/Object;
  #491 = Methodref          #255.#490     // org/sireum/IS.apply:(Ljava/lang/Object;)Ljava/lang/Object;
  #492 = Utf8               org/sireum/B
  #493 = Class              #492          // org/sireum/B
  #494 = Utf8               value
  #495 = NameAndType        #494:#131     // value:()Z
  #496 = Methodref          #493.#495     // org/sireum/B.value:()Z
  #497 = Utf8               $4B
  #498 = Utf8               (Z)Z
  #499 = NameAndType        #497:#498     // $4B:(Z)Z
  #500 = Methodref          #486.#499     // org/sireum/B$.$4B:(Z)Z
  #501 = Utf8               (B)V
  #502 = NameAndType        #163:#501     // "<init>":(B)V
  #503 = Methodref          #46.#502      // org/sireum/U8."<init>":(B)V
  #504 = Utf8               $bar
  #505 = Utf8               (Lorg/sireum/Z$BV$Byte;)Lorg/sireum/Z$BV$Byte;
  #506 = NameAndType        #504:#505     // $bar:(Lorg/sireum/Z$BV$Byte;)Lorg/sireum/Z$BV$Byte;
  #507 = Methodref          #46.#506      // org/sireum/U8.$bar:(Lorg/sireum/Z$BV$Byte;)Lorg/sireum/Z$BV$Byte;
  #508 = NameAndType        #494:#297     // value:()B
  #509 = Methodref          #46.#508      // org/sireum/U8.value:()B
  #510 = Utf8               $less$less
  #511 = NameAndType        #510:#505     // $less$less:(Lorg/sireum/Z$BV$Byte;)Lorg/sireum/Z$BV$Byte;
  #512 = Methodref          #46.#511      // org/sireum/U8.$less$less:(Lorg/sireum/Z$BV$Byte;)Lorg/sireum/Z$BV$Byte;
  #513 = Utf8               Lorg/sireum/Z;
  #514 = Utf8               $anonfun$toU16$1
  #515 = Utf8               (Lorg/sireum/ops/ISZBOps;Lscala/runtime/ShortRef;Lscala/runtime/ShortRef;Lorg/sireum/Z;)V
  #516 = Utf8               r$18
  #517 = Utf8               mask$2
  #518 = Utf8               (S)V
  #519 = NameAndType        #163:#518     // "<init>":(S)V
  #520 = Methodref          #22.#519      // org/sireum/U16."<init>":(S)V
  #521 = Utf8               (Lorg/sireum/Z$BV$Short;)Lorg/sireum/Z$BV$Short;
  #522 = NameAndType        #504:#521     // $bar:(Lorg/sireum/Z$BV$Short;)Lorg/sireum/Z$BV$Short;
  #523 = Methodref          #22.#522      // org/sireum/U16.$bar:(Lorg/sireum/Z$BV$Short;)Lorg/sireum/Z$BV$Short;
  #524 = NameAndType        #494:#379     // value:()S
  #525 = Methodref          #22.#524      // org/sireum/U16.value:()S
  #526 = NameAndType        #510:#521     // $less$less:(Lorg/sireum/Z$BV$Short;)Lorg/sireum/Z$BV$Short;
  #527 = Methodref          #22.#526      // org/sireum/U16.$less$less:(Lorg/sireum/Z$BV$Short;)Lorg/sireum/Z$BV$Short;
  #528 = Utf8               $anonfun$toU32$1
  #529 = Utf8               (Lorg/sireum/ops/ISZBOps;Lscala/runtime/IntRef;Lscala/runtime/IntRef;Lorg/sireum/Z;)V
  #530 = Utf8               r$19
  #531 = Utf8               mask$3
  #532 = Utf8               (I)V
  #533 = NameAndType        #163:#532     // "<init>":(I)V
  #534 = Methodref          #30.#533      // org/sireum/U32."<init>":(I)V
  #535 = Utf8               (Lorg/sireum/Z$BV$Int;)Lorg/sireum/Z$BV$Int;
  #536 = NameAndType        #504:#535     // $bar:(Lorg/sireum/Z$BV$Int;)Lorg/sireum/Z$BV$Int;
  #537 = Methodref          #30.#536      // org/sireum/U32.$bar:(Lorg/sireum/Z$BV$Int;)Lorg/sireum/Z$BV$Int;
  #538 = NameAndType        #494:#200     // value:()I
  #539 = Methodref          #30.#538      // org/sireum/U32.value:()I
  #540 = NameAndType        #510:#535     // $less$less:(Lorg/sireum/Z$BV$Int;)Lorg/sireum/Z$BV$Int;
  #541 = Methodref          #30.#540      // org/sireum/U32.$less$less:(Lorg/sireum/Z$BV$Int;)Lorg/sireum/Z$BV$Int;
  #542 = Utf8               $anonfun$toU64$1
  #543 = Utf8               (Lorg/sireum/ops/ISZBOps;Lscala/runtime/LongRef;Lscala/runtime/LongRef;Lorg/sireum/Z;)V
  #544 = Utf8               r$20
  #545 = Utf8               mask$4
  #546 = Utf8               (J)V
  #547 = NameAndType        #163:#546     // "<init>":(J)V
  #548 = Methodref          #38.#547      // org/sireum/U64."<init>":(J)V
  #549 = Utf8               (Lorg/sireum/Z$BV$Long;)Lorg/sireum/Z$BV$Long;
  #550 = NameAndType        #504:#549     // $bar:(Lorg/sireum/Z$BV$Long;)Lorg/sireum/Z$BV$Long;
  #551 = Methodref          #38.#550      // org/sireum/U64.$bar:(Lorg/sireum/Z$BV$Long;)Lorg/sireum/Z$BV$Long;
  #552 = NameAndType        #494:#444     // value:()J
  #553 = Methodref          #38.#552      // org/sireum/U64.value:()J
  #554 = NameAndType        #510:#549     // $less$less:(Lorg/sireum/Z$BV$Long;)Lorg/sireum/Z$BV$Long;
  #555 = Methodref          #38.#554      // org/sireum/U64.$less$less:(Lorg/sireum/Z$BV$Long;)Lorg/sireum/Z$BV$Long;
  #556 = Utf8               (Lorg/sireum/IS<Lorg/sireum/Z;Lorg/sireum/B;>;)V
  #557 = Utf8               __s
  #558 = Methodref          #5.#165       // java/lang/Object."<init>":()V
  #559 = Utf8               $init$
  #560 = Utf8               (Lorg/sireum/$internal/ImmutableMarker;)V
  #561 = NameAndType        #559:#560     // $init$:(Lorg/sireum/$internal/ImmutableMarker;)V
  #562 = InterfaceMethodref #143.#561     // org/sireum/$internal/ImmutableMarker.$init$:(Lorg/sireum/$internal/ImmutableMarker;)V
  #563 = Utf8               (Lorg/sireum/Immutable;)V
  #564 = NameAndType        #559:#563     // $init$:(Lorg/sireum/Immutable;)V
  #565 = InterfaceMethodref #125.#564     // org/sireum/Immutable.$init$:(Lorg/sireum/Immutable;)V
  #566 = Utf8               (Lorg/sireum/DatatypeSig;)V
  #567 = NameAndType        #559:#566     // $init$:(Lorg/sireum/DatatypeSig;)V
  #568 = InterfaceMethodref #9.#567       // org/sireum/DatatypeSig.$init$:(Lorg/sireum/DatatypeSig;)V
  #569 = NameAndType        #479:#480     // $anonfun$toU8$1:(Lorg/sireum/ops/ISZBOps;Lscala/runtime/ByteRef;Lscala/runtime/ByteRef;Lorg/sireum/Z;)V
  #570 = Methodref          #2.#569       // org/sireum/ops/ISZBOps.$anonfun$toU8$1:(Lorg/sireum/ops/ISZBOps;Lscala/runtime/ByteRef;Lscala/runtime/ByteRef;Lorg/sireum/Z;)V
  #571 = Utf8               scala/runtime/BoxedUnit
  #572 = Class              #571          // scala/runtime/BoxedUnit
  #573 = Utf8               UNIT
  #574 = Utf8               Lscala/runtime/BoxedUnit;
  #575 = NameAndType        #573:#574     // UNIT:Lscala/runtime/BoxedUnit;
  #576 = Fieldref           #572.#575     // scala/runtime/BoxedUnit.UNIT:Lscala/runtime/BoxedUnit;
  #577 = NameAndType        #514:#515     // $anonfun$toU16$1:(Lorg/sireum/ops/ISZBOps;Lscala/runtime/ShortRef;Lscala/runtime/ShortRef;Lorg/sireum/Z;)V
  #578 = Methodref          #2.#577       // org/sireum/ops/ISZBOps.$anonfun$toU16$1:(Lorg/sireum/ops/ISZBOps;Lscala/runtime/ShortRef;Lscala/runtime/ShortRef;Lorg/sireum/Z;)V
  #579 = NameAndType        #528:#529     // $anonfun$toU32$1:(Lorg/sireum/ops/ISZBOps;Lscala/runtime/IntRef;Lscala/runtime/IntRef;Lorg/sireum/Z;)V
  #580 = Methodref          #2.#579       // org/sireum/ops/ISZBOps.$anonfun$toU32$1:(Lorg/sireum/ops/ISZBOps;Lscala/runtime/IntRef;Lscala/runtime/IntRef;Lorg/sireum/Z;)V
  #581 = NameAndType        #542:#543     // $anonfun$toU64$1:(Lorg/sireum/ops/ISZBOps;Lscala/runtime/LongRef;Lscala/runtime/LongRef;Lorg/sireum/Z;)V
  #582 = Methodref          #2.#581       // org/sireum/ops/ISZBOps.$anonfun$toU64$1:(Lorg/sireum/ops/ISZBOps;Lscala/runtime/LongRef;Lscala/runtime/LongRef;Lorg/sireum/Z;)V
  #583 = Utf8               $deserializeLambda$
  #584 = Utf8               (Ljava/lang/invoke/SerializedLambda;)Ljava/lang/Object;
  #585 = Utf8               scala/runtime/LambdaDeserialize
  #586 = Class              #585          // scala/runtime/LambdaDeserialize
  #587 = Utf8               bootstrap
  #588 = Utf8               (Ljava/lang/invoke/MethodHandles$Lookup;Ljava/lang/String;Ljava/lang/invoke/MethodType;[Ljava/lang/invoke/MethodHandle;)Ljava/lang/invoke/CallSite;
  #589 = NameAndType        #587:#588     // bootstrap:(Ljava/lang/invoke/MethodHandles$Lookup;Ljava/lang/String;Ljava/lang/invoke/MethodType;[Ljava/lang/invoke/MethodHandle;)Ljava/lang/invoke/CallSite;
  #590 = Methodref          #586.#589     // scala/runtime/LambdaDeserialize.bootstrap:(Ljava/lang/invoke/MethodHandles$Lookup;Ljava/lang/String;Ljava/lang/invoke/MethodType;[Ljava/lang/invoke/MethodHandle;)Ljava/lang/invoke/CallSite;
  #591 = MethodHandle       6:#590        // REF_invokeStatic scala/runtime/LambdaDeserialize.bootstrap:(Ljava/lang/invoke/MethodHandles$Lookup;Ljava/lang/String;Ljava/lang/invoke/MethodType;[Ljava/lang/invoke/MethodHandle;)Ljava/lang/invoke/CallSite;
  #592 = Utf8               lambdaDeserialize
  #593 = NameAndType        #592:#584     // lambdaDeserialize:(Ljava/lang/invoke/SerializedLambda;)Ljava/lang/Object;
  #594 = InvokeDynamic      #4:#593       // #4:lambdaDeserialize:(Ljava/lang/invoke/SerializedLambda;)Ljava/lang/Object;
  #595 = Utf8               Signature
  #596 = Utf8               Code
  #597 = Utf8               LocalVariableTable
  #598 = Utf8               MethodParameters
  #599 = Utf8               LineNumberTable
  #600 = Utf8               StackMapTable
  #601 = Utf8               InnerClasses
  #602 = Utf8               SourceFile
  #603 = Utf8               RuntimeVisibleAnnotations
  #604 = Utf8               BootstrapMethods
  #605 = Utf8               ScalaInlineInfo
  #606 = Utf8               ScalaSig
{
  private int hashCode;
    descriptor: I
    flags: (0x0002) ACC_PRIVATE

  private scala.collection.immutable.Seq<scala.Tuple2<java.lang.String, java.lang.Object>> $content;
    descriptor: Lscala/collection/immutable/Seq;
    flags: (0x0002) ACC_PRIVATE
    Signature: #72                          // Lscala/collection/immutable/Seq<Lscala/Tuple2<Ljava/lang/String;Ljava/lang/Object;>;>;

  private final org.sireum.IS<org.sireum.Z, org.sireum.B> _s;
    descriptor: Lorg/sireum/IS;
    flags: (0x0012) ACC_PRIVATE, ACC_FINAL
    Signature: #75                          // Lorg/sireum/IS<Lorg/sireum/Z;Lorg/sireum/B;>;

  private volatile byte bitmap$0;
    descriptor: B
    flags: (0x0042) ACC_PRIVATE, ACC_VOLATILE

  public static scala.Some<org.sireum.IS<org.sireum.Z, org.sireum.B>> unapply(org.sireum.ops.ISZBOps);
    descriptor: (Lorg/sireum/ops/ISZBOps;)Lscala/Some;
    flags: (0x0009) ACC_PUBLIC, ACC_STATIC
    Code:
      stack=2, locals=1, args_size=1
         0: getstatic     #87                 // Field org/sireum/ops/ISZBOps$.MODULE$:Lorg/sireum/ops/ISZBOps$;
         3: aload_0
         4: invokevirtual #89                 // Method org/sireum/ops/ISZBOps$.unapply:(Lorg/sireum/ops/ISZBOps;)Lscala/Some;
         7: areturn
      LocalVariableTable:
        Start  Length  Slot  Name   Signature
            0       8     0     o   Lorg/sireum/ops/ISZBOps;
    Signature: #80                          // (Lorg/sireum/ops/ISZBOps;)Lscala/Some<Lorg/sireum/IS<Lorg/sireum/Z;Lorg/sireum/B;>;>;
    MethodParameters:
      Name                           Flags
      o                              final

  public static org.sireum.IS<org.sireum.Z, org.sireum.B> fromU64(org.sireum.IS<org.sireum.Z, org.sireum.B>, long);
    descriptor: (Lorg/sireum/IS;J)Lorg/sireum/IS;
    flags: (0x0009) ACC_PUBLIC, ACC_STATIC
    Code:
      stack=4, locals=3, args_size=2
         0: getstatic     #87                 // Field org/sireum/ops/ISZBOps$.MODULE$:Lorg/sireum/ops/ISZBOps$;
         3: aload_0
         4: lload_1
         5: invokevirtual #97                 // Method org/sireum/ops/ISZBOps$.fromU64:(Lorg/sireum/IS;J)Lorg/sireum/IS;
         8: areturn
      LocalVariableTable:
        Start  Length  Slot  Name   Signature
            0       9     0     s   Lorg/sireum/IS;
            0       9     1     n   J
    Signature: #93                          // (Lorg/sireum/IS<Lorg/sireum/Z;Lorg/sireum/B;>;J)Lorg/sireum/IS<Lorg/sireum/Z;Lorg/sireum/B;>;
    MethodParameters:
      Name                           Flags
      s                              final
      n                              final

  public static org.sireum.IS<org.sireum.Z, org.sireum.B> fromU32(org.sireum.IS<org.sireum.Z, org.sireum.B>, int);
    descriptor: (Lorg/sireum/IS;I)Lorg/sireum/IS;
    flags: (0x0009) ACC_PUBLIC, ACC_STATIC
    Code:
      stack=3, locals=2, args_size=2
         0: getstatic     #87                 // Field org/sireum/ops/ISZBOps$.MODULE$:Lorg/sireum/ops/ISZBOps$;
         3: aload_0
         4: iload_1
         5: invokevirtual #103                // Method org/sireum/ops/ISZBOps$.fromU32:(Lorg/sireum/IS;I)Lorg/sireum/IS;
         8: areturn
      LocalVariableTable:
        Start  Length  Slot  Name   Signature
            0       9     0     s   Lorg/sireum/IS;
            0       9     1     n   I
    Signature: #101                         // (Lorg/sireum/IS<Lorg/sireum/Z;Lorg/sireum/B;>;I)Lorg/sireum/IS<Lorg/sireum/Z;Lorg/sireum/B;>;
    MethodParameters:
      Name                           Flags
      s                              final
      n                              final

  public static org.sireum.IS<org.sireum.Z, org.sireum.B> fromU16(short);
    descriptor: (S)Lorg/sireum/IS;
    flags: (0x0009) ACC_PUBLIC, ACC_STATIC
    Code:
      stack=2, locals=1, args_size=1
         0: getstatic     #87                 // Field org/sireum/ops/ISZBOps$.MODULE$:Lorg/sireum/ops/ISZBOps$;
         3: iload_0
         4: invokevirtual #108                // Method org/sireum/ops/ISZBOps$.fromU16:(S)Lorg/sireum/IS;
         7: areturn
      LocalVariableTable:
        Start  Length  Slot  Name   Signature
            0       8     0     n   S
    Signature: #106                         // (S)Lorg/sireum/IS<Lorg/sireum/Z;Lorg/sireum/B;>;
    MethodParameters:
      Name                           Flags
      n                              final

  public static org.sireum.IS<org.sireum.Z, org.sireum.B> fromU8(byte);
    descriptor: (B)Lorg/sireum/IS;
    flags: (0x0009) ACC_PUBLIC, ACC_STATIC
    Code:
      stack=2, locals=1, args_size=1
         0: getstatic     #87                 // Field org/sireum/ops/ISZBOps$.MODULE$:Lorg/sireum/ops/ISZBOps$;
         3: iload_0
         4: invokevirtual #114                // Method org/sireum/ops/ISZBOps$.fromU8:(B)Lorg/sireum/IS;
         7: areturn
      LocalVariableTable:
        Start  Length  Slot  Name   Signature
            0       8     0     n   B
    Signature: #112                         // (B)Lorg/sireum/IS<Lorg/sireum/Z;Lorg/sireum/B;>;
    MethodParameters:
      Name                           Flags
      n                              final

  public org.sireum.Z hash();
    descriptor: ()Lorg/sireum/Z;
    flags: (0x0001) ACC_PUBLIC
    Code:
      stack=1, locals=1, args_size=1
         0: aload_0
         1: invokestatic  #120                // InterfaceMethod org/sireum/DatatypeSig.hash$:(Lorg/sireum/DatatypeSig;)Lorg/sireum/Z;
         4: areturn
      LineNumberTable:
        line 1188: 0
      LocalVariableTable:
        Start  Length  Slot  Name   Signature
            0       5     0  this   Lorg/sireum/ops/ISZBOps;

  public final scala.runtime.Nothing$ $cannotMixImmutableAndMutable();
    descriptor: ()Lscala/runtime/Nothing$;
    flags: (0x0011) ACC_PUBLIC, ACC_FINAL
    Code:
      stack=1, locals=1, args_size=1
         0: aload_0
         1: invokestatic  #129                // InterfaceMethod org/sireum/Immutable.$cannotMixImmutableAndMutable$:(Lorg/sireum/Immutable;)Lscala/runtime/Nothing$;
         4: areturn
      LineNumberTable:
        line 1188: 0
      LocalVariableTable:
        Start  Length  Slot  Name   Signature
            0       5     0  this   Lorg/sireum/ops/ISZBOps;

  public boolean $hasEquals();
    descriptor: ()Z
    flags: (0x0001) ACC_PUBLIC
    Code:
      stack=1, locals=1, args_size=1
         0: aload_0
         1: invokestatic  #135                // InterfaceMethod org/sireum/Immutable.$hasEquals$:(Lorg/sireum/Immutable;)Z
         4: ireturn
      LineNumberTable:
        line 1188: 0
      LocalVariableTable:
        Start  Length  Slot  Name   Signature
            0       5     0  this   Lorg/sireum/ops/ISZBOps;

  public boolean $hasString();
    descriptor: ()Z
    flags: (0x0001) ACC_PUBLIC
    Code:
      stack=1, locals=1, args_size=1
         0: aload_0
         1: invokestatic  #139                // InterfaceMethod org/sireum/Immutable.$hasString$:(Lorg/sireum/Immutable;)Z
         4: ireturn
      LineNumberTable:
        line 1188: 0
      LocalVariableTable:
        Start  Length  Slot  Name   Signature
            0       5     0  this   Lorg/sireum/ops/ISZBOps;

  public org.sireum.$internal.ImmutableMarker $clone();
    descriptor: ()Lorg/sireum/$internal/ImmutableMarker;
    flags: (0x0001) ACC_PUBLIC
    Code:
      stack=1, locals=1, args_size=1
         0: aload_0
         1: invokestatic  #147                // InterfaceMethod org/sireum/$internal/ImmutableMarker.$clone$:(Lorg/sireum/$internal/ImmutableMarker;)Lorg/sireum/$internal/ImmutableMarker;
         4: areturn
      LineNumberTable:
        line 1188: 0
      LocalVariableTable:
        Start  Length  Slot  Name   Signature
            0       5     0  this   Lorg/sireum/ops/ISZBOps;

  public org.sireum.IS<org.sireum.Z, org.sireum.B> s();
    descriptor: ()Lorg/sireum/IS;
    flags: (0x0001) ACC_PUBLIC
    Code:
      stack=1, locals=1, args_size=1
         0: aload_0
         1: getfield      #151                // Field _s:Lorg/sireum/IS;
         4: areturn
      LineNumberTable:
        line 1188: 0
      LocalVariableTable:
        Start  Length  Slot  Name   Signature
            0       5     0  this   Lorg/sireum/ops/ISZBOps;
    Signature: #149                         // ()Lorg/sireum/IS<Lorg/sireum/Z;Lorg/sireum/B;>;

  public org.sireum.IS<org.sireum.Z, org.sireum.B> getS();
    descriptor: ()Lorg/sireum/IS;
    flags: (0x0001) ACC_PUBLIC
    Code:
      stack=1, locals=1, args_size=1
         0: aload_0
         1: getfield      #151                // Field _s:Lorg/sireum/IS;
         4: areturn
      LineNumberTable:
        line 1188: 0
      LocalVariableTable:
        Start  Length  Slot  Name   Signature
            0       5     0  this   Lorg/sireum/ops/ISZBOps;
    Signature: #149                         // ()Lorg/sireum/IS<Lorg/sireum/Z;Lorg/sireum/B;>;

  public java.lang.String toString();
    descriptor: ()Ljava/lang/String;
    flags: (0x0001) ACC_PUBLIC
    Code:
      stack=3, locals=2, args_size=1
         0: aload_0
         1: invokevirtual #156                // Method $hasString:()Z
         4: ifeq          14
         7: aload_0
         8: invokestatic  #160                // InterfaceMethod org/sireum/DatatypeSig.string$:(Lorg/sireum/DatatypeSig;)Ljava/lang/String;
        11: goto          62
        14: new           #162                // class java/lang/StringBuilder
        17: dup
        18: invokespecial #166                // Method java/lang/StringBuilder."<init>":()V
        21: astore_1
        22: aload_1
        23: ldc           #168                // String ISZBOps
        25: invokevirtual #172                // Method java/lang/StringBuilder.append:(Ljava/lang/String;)Ljava/lang/StringBuilder;
        28: pop
        29: aload_1
        30: bipush        40
        32: invokevirtual #175                // Method java/lang/StringBuilder.append:(C)Ljava/lang/StringBuilder;
        35: pop
        36: aload_1
        37: getstatic     #180                // Field org/sireum/String$.MODULE$:Lorg/sireum/String$;
        40: aload_0
        41: invokevirtual #182                // Method s:()Lorg/sireum/IS;
        44: invokevirtual #186                // Method org/sireum/String$.escape:(Ljava/lang/Object;)Ljava/lang/String;
        47: invokevirtual #172                // Method java/lang/StringBuilder.append:(Ljava/lang/String;)Ljava/lang/StringBuilder;
        50: pop
        51: aload_1
        52: bipush        41
        54: invokevirtual #175                // Method java/lang/StringBuilder.append:(C)Ljava/lang/StringBuilder;
        57: pop
        58: aload_1
        59: invokevirtual #188                // Method java/lang/StringBuilder.toString:()Ljava/lang/String;
        62: areturn
      StackMapTable: number_of_entries = 2
        frame_type = 14 /* same */
        frame_type = 111 /* same_locals_1_stack_item */
          stack = [ class java/lang/String ]
      LineNumberTable:
        line 1188: 0
      LocalVariableTable:
        Start  Length  Slot  Name   Signature
           22      40     1    sb   Ljava/lang/StringBuilder;
            0      63     0  this   Lorg/sireum/ops/ISZBOps;

  public java.lang.String string();
    descriptor: ()Ljava/lang/String;
    flags: (0x0001) ACC_PUBLIC
    Code:
      stack=2, locals=1, args_size=1
         0: aload_0
         1: invokevirtual #156                // Method $hasString:()Z
         4: ifeq          14
         7: aload_0
         8: invokestatic  #160                // InterfaceMethod org/sireum/DatatypeSig.string$:(Lorg/sireum/DatatypeSig;)Ljava/lang/String;
        11: goto          24
        14: getstatic     #180                // Field org/sireum/String$.MODULE$:Lorg/sireum/String$;
        17: aload_0
        18: invokevirtual #194                // Method toString:()Ljava/lang/String;
        21: invokevirtual #198                // Method org/sireum/String$.apply:(Ljava/lang/String;)Ljava/lang/String;
        24: areturn
      StackMapTable: number_of_entries = 2
        frame_type = 14 /* same */
        frame_type = 73 /* same_locals_1_stack_item */
          stack = [ class java/lang/String ]
      LineNumberTable:
        line 1188: 0
      LocalVariableTable:
        Start  Length  Slot  Name   Signature
            0      25     0  this   Lorg/sireum/ops/ISZBOps;

  private int hashCode$lzycompute();
    descriptor: ()I
    flags: (0x0002) ACC_PRIVATE
    Code:
      stack=7, locals=2, args_size=1
         0: aload_0
         1: dup
         2: astore_1
         3: monitorenter
         4: aload_0
         5: getfield      #202                // Field bitmap$0:B
         8: iconst_1
         9: iand
        10: i2b
        11: iconst_0
        12: if_icmpne     88
        15: aload_0
        16: aload_0
        17: invokevirtual #204                // Method $hasEquals:()Z
        20: ifeq          30
        23: aload_0
        24: invokespecial #206                // Method java/lang/Object.hashCode:()I
        27: goto          74
        30: getstatic     #211                // Field scala/package$.MODULE$:Lscala/package$;
        33: invokevirtual #215                // Method scala/package$.Seq:()Lscala/collection/immutable/Seq$;
        36: getstatic     #220                // Field scala/runtime/ScalaRunTime$.MODULE$:Lscala/runtime/ScalaRunTime$;
        39: iconst_2
        40: anewarray     #5                  // class java/lang/Object
        43: dup
        44: iconst_0
        45: aload_0
        46: invokevirtual #224                // Method getClass:()Ljava/lang/Class;
        49: invokevirtual #229                // Method java/lang/Class.getName:()Ljava/lang/String;
        52: aastore
        53: dup
        54: iconst_1
        55: aload_0
        56: invokevirtual #182                // Method s:()Lorg/sireum/IS;
        59: aastore
        60: invokevirtual #233                // Method scala/runtime/ScalaRunTime$.wrapRefArray:([Ljava/lang/Object;)Lscala/collection/immutable/ArraySeq;
        63: invokevirtual #238                // Method scala/collection/immutable/Seq$.apply:(Lscala/collection/immutable/Seq;)Lscala/collection/SeqOps;
        66: checkcast     #240                // class scala/collection/Seq
        69: invokeinterface #241,  1          // InterfaceMethod scala/collection/Seq.hashCode:()I
        74: putfield      #243                // Field hashCode:I
        77: aload_0
        78: aload_0
        79: getfield      #202                // Field bitmap$0:B
        82: iconst_1
        83: ior
        84: i2b
        85: putfield      #202                // Field bitmap$0:B
        88: aload_1
        89: monitorexit
        90: goto          96
        93: aload_1
        94: monitorexit
        95: athrow
        96: aload_0
        97: getfield      #243                // Field hashCode:I
       100: ireturn
      Exception table:
         from    to  target type
             4    88    93   any
      StackMapTable: number_of_entries = 5
        frame_type = 255 /* full_frame */
          offset_delta = 30
          locals = [ class org/sireum/ops/ISZBOps, class org/sireum/ops/ISZBOps ]
          stack = [ class org/sireum/ops/ISZBOps ]
        frame_type = 255 /* full_frame */
          offset_delta = 43
          locals = [ class org/sireum/ops/ISZBOps, class org/sireum/ops/ISZBOps ]
          stack = [ class org/sireum/ops/ISZBOps, int ]
        frame_type = 13 /* same */
        frame_type = 68 /* same_locals_1_stack_item */
          stack = [ class java/lang/Throwable ]
        frame_type = 2 /* same */
      LineNumberTable:
        line 1188: 0
      LocalVariableTable:
        Start  Length  Slot  Name   Signature
            0     101     0  this   Lorg/sireum/ops/ISZBOps;

  public int hashCode();
    descriptor: ()I
    flags: (0x0001) ACC_PUBLIC
    Code:
      stack=2, locals=1, args_size=1
         0: aload_0
         1: getfield      #202                // Field bitmap$0:B
         4: iconst_1
         5: iand
         6: i2b
         7: iconst_0
         8: if_icmpne     18
        11: aload_0
        12: invokespecial #247                // Method hashCode$lzycompute:()I
        15: goto          22
        18: aload_0
        19: getfield      #243                // Field hashCode:I
        22: ireturn
      StackMapTable: number_of_entries = 2
        frame_type = 18 /* same */
        frame_type = 67 /* same_locals_1_stack_item */
          stack = [ int ]
      LineNumberTable:
        line 1188: 0
      LocalVariableTable:
        Start  Length  Slot  Name   Signature
            0      23     0  this   Lorg/sireum/ops/ISZBOps;

  public boolean equals(java.lang.Object);
    descriptor: (Ljava/lang/Object;)Z
    flags: (0x0001) ACC_PUBLIC
    Code:
      stack=2, locals=6, args_size=2
         0: aload_0
         1: invokevirtual #204                // Method $hasEquals:()Z
         4: ifeq          15
         7: aload_0
         8: aload_1
         9: invokespecial #251                // Method java/lang/Object.equals:(Ljava/lang/Object;)Z
        12: goto          105
        15: aload_0
        16: aload_1
        17: if_acmpne     24
        20: iconst_1
        21: goto          105
        24: aload_1
        25: astore_3
        26: aload_3
        27: instanceof    #2                  // class org/sireum/ops/ISZBOps
        30: ifeq          96
        33: aload_3
        34: checkcast     #2                  // class org/sireum/ops/ISZBOps
        37: astore        4
        39: aload_0
        40: invokevirtual #252                // Method hashCode:()I
        43: aload         4
        45: invokevirtual #252                // Method hashCode:()I
        48: if_icmpeq     55
        51: iconst_0
        52: goto          92
        55: aload_0
        56: invokevirtual #182                // Method s:()Lorg/sireum/IS;
        59: aload         4
        61: invokevirtual #182                // Method s:()Lorg/sireum/IS;
        64: astore        5
        66: dup
        67: ifnonnull     79
        70: pop
        71: aload         5
        73: ifnull        87
        76: goto          91
        79: aload         5
        81: invokevirtual #251                // Method java/lang/Object.equals:(Ljava/lang/Object;)Z
        84: ifeq          91
        87: iconst_1
        88: goto          92
        91: iconst_0
        92: istore_2
        93: goto          104
        96: goto          99
        99: iconst_0
       100: istore_2
       101: goto          104
       104: iload_2
       105: ireturn
      StackMapTable: number_of_entries = 11
        frame_type = 15 /* same */
        frame_type = 8 /* same */
        frame_type = 254 /* append */
          offset_delta = 30
          locals = [ top, class java/lang/Object, class org/sireum/ops/ISZBOps ]
        frame_type = 255 /* full_frame */
          offset_delta = 23
          locals = [ class org/sireum/ops/ISZBOps, class java/lang/Object, top, class java/lang/Object, class org/sireum/ops/ISZBOps, class org/sireum/IS ]
          stack = [ class org/sireum/IS ]
        frame_type = 7 /* same */
        frame_type = 3 /* same */
        frame_type = 255 /* full_frame */
          offset_delta = 0
          locals = [ class org/sireum/ops/ISZBOps, class java/lang/Object, top, class java/lang/Object, class org/sireum/ops/ISZBOps ]
          stack = [ int ]
        frame_type = 250 /* chop */
          offset_delta = 3
        frame_type = 2 /* same */
        frame_type = 255 /* full_frame */
          offset_delta = 4
          locals = [ class org/sireum/ops/ISZBOps, class java/lang/Object, int, class java/lang/Object ]
          stack = []
        frame_type = 255 /* full_frame */
          offset_delta = 0
          locals = [ class org/sireum/ops/ISZBOps, class java/lang/Object ]
          stack = [ int ]
      LineNumberTable:
        line 1188: 0
      LocalVariableTable:
        Start  Length  Slot  Name   Signature
            0     106     0  this   Lorg/sireum/ops/ISZBOps;
            0     106     1     o   Ljava/lang/Object;
    MethodParameters:
      Name                           Flags
      o                              final

  public org.sireum.ops.ISZBOps apply(org.sireum.IS<org.sireum.Z, org.sireum.B>);
    descriptor: (Lorg/sireum/IS;)Lorg/sireum/ops/ISZBOps;
    flags: (0x0001) ACC_PUBLIC
    Code:
      stack=3, locals=2, args_size=2
         0: new           #2                  // class org/sireum/ops/ISZBOps
         3: dup
         4: aload_1
         5: invokespecial #260                // Method "<init>":(Lorg/sireum/IS;)V
         8: areturn
      LineNumberTable:
        line 1188: 0
      LocalVariableTable:
        Start  Length  Slot  Name   Signature
            0       9     0  this   Lorg/sireum/ops/ISZBOps;
            0       9     1     s   Lorg/sireum/IS;
    Signature: #257                         // (Lorg/sireum/IS<Lorg/sireum/Z;Lorg/sireum/B;>;)Lorg/sireum/ops/ISZBOps;
    MethodParameters:
      Name                           Flags
      s                              final

  public org.sireum.IS<org.sireum.Z, org.sireum.B> apply$default$1();
    descriptor: ()Lorg/sireum/IS;
    flags: (0x0001) ACC_PUBLIC
    Code:
      stack=1, locals=1, args_size=1
         0: aload_0
         1: invokevirtual #182                // Method s:()Lorg/sireum/IS;
         4: areturn
      LineNumberTable:
        line 1188: 0
      LocalVariableTable:
        Start  Length  Slot  Name   Signature
            0       5     0  this   Lorg/sireum/ops/ISZBOps;
    Signature: #149                         // ()Lorg/sireum/IS<Lorg/sireum/Z;Lorg/sireum/B;>;

  private scala.collection.immutable.Seq<scala.Tuple2<java.lang.String, java.lang.Object>> $content$lzycompute();
    descriptor: ()Lscala/collection/immutable/Seq;
    flags: (0x0002) ACC_PRIVATE
    Code:
      stack=15, locals=2, args_size=1
         0: aload_0
         1: dup
         2: astore_1
         3: monitorenter
         4: aload_0
         5: getfield      #202                // Field bitmap$0:B
         8: iconst_2
         9: iand
        10: i2b
        11: iconst_0
        12: if_icmpne     130
        15: aload_0
        16: getstatic     #211                // Field scala/package$.MODULE$:Lscala/package$;
        19: invokevirtual #215                // Method scala/package$.Seq:()Lscala/collection/immutable/Seq$;
        22: getstatic     #220                // Field scala/runtime/ScalaRunTime$.MODULE$:Lscala/runtime/ScalaRunTime$;
        25: iconst_2
        26: anewarray     #266                // class scala/Tuple2
        29: dup
        30: iconst_0
        31: new           #266                // class scala/Tuple2
        34: dup
        35: ldc_w         #268                // String type
        38: getstatic     #211                // Field scala/package$.MODULE$:Lscala/package$;
        41: invokevirtual #272                // Method scala/package$.List:()Lscala/collection/immutable/List$;
        44: getstatic     #220                // Field scala/runtime/ScalaRunTime$.MODULE$:Lscala/runtime/ScalaRunTime$;
        47: iconst_4
        48: anewarray     #192                // class java/lang/String
        51: dup
        52: iconst_0
        53: ldc_w         #274                // String org
        56: aastore
        57: dup
        58: iconst_1
        59: ldc_w         #276                // String sireum
        62: aastore
        63: dup
        64: iconst_2
        65: ldc_w         #278                // String ops
        68: aastore
        69: dup
        70: iconst_3
        71: ldc           #168                // String ISZBOps
        73: aastore
        74: checkcast     #280                // class "[Ljava/lang/Object;"
        77: invokevirtual #233                // Method scala/runtime/ScalaRunTime$.wrapRefArray:([Ljava/lang/Object;)Lscala/collection/immutable/ArraySeq;
        80: invokevirtual #285                // Method scala/collection/immutable/List$.apply:(Lscala/collection/immutable/Seq;)Ljava/lang/Object;
        83: invokespecial #288                // Method scala/Tuple2."<init>":(Ljava/lang/Object;Ljava/lang/Object;)V
        86: aastore
        87: dup
        88: iconst_1
        89: new           #266                // class scala/Tuple2
        92: dup
        93: ldc_w         #289                // String s
        96: aload_0
        97: invokevirtual #182                // Method s:()Lorg/sireum/IS;
       100: invokespecial #288                // Method scala/Tuple2."<init>":(Ljava/lang/Object;Ljava/lang/Object;)V
       103: aastore
       104: checkcast     #280                // class "[Ljava/lang/Object;"
       107: invokevirtual #233                // Method scala/runtime/ScalaRunTime$.wrapRefArray:([Ljava/lang/Object;)Lscala/collection/immutable/ArraySeq;
       110: invokevirtual #238                // Method scala/collection/immutable/Seq$.apply:(Lscala/collection/immutable/Seq;)Lscala/collection/SeqOps;
       113: checkcast     #291                // class scala/collection/immutable/Seq
       116: putfield      #293                // Field $content:Lscala/collection/immutable/Seq;
       119: aload_0
       120: aload_0
       121: getfield      #202                // Field bitmap$0:B
       124: iconst_2
       125: ior
       126: i2b
       127: putfield      #202                // Field bitmap$0:B
       130: aload_1
       131: monitorexit
       132: goto          138
       135: aload_1
       136: monitorexit
       137: athrow
       138: aload_0
       139: getfield      #293                // Field $content:Lscala/collection/immutable/Seq;
       142: areturn
      Exception table:
         from    to  target type
             4   130   135   any
      StackMapTable: number_of_entries = 3
        frame_type = 252 /* append */
          offset_delta = 130
          locals = [ class org/sireum/ops/ISZBOps ]
        frame_type = 68 /* same_locals_1_stack_item */
          stack = [ class java/lang/Throwable ]
        frame_type = 2 /* same */
      LineNumberTable:
        line 1188: 0
      LocalVariableTable:
        Start  Length  Slot  Name   Signature
            0     143     0  this   Lorg/sireum/ops/ISZBOps;
    Signature: #264                         // ()Lscala/collection/immutable/Seq<Lscala/Tuple2<Ljava/lang/String;Ljava/lang/Object;>;>;

  public scala.collection.immutable.Seq<scala.Tuple2<java.lang.String, java.lang.Object>> $content();
    descriptor: ()Lscala/collection/immutable/Seq;
    flags: (0x0001) ACC_PUBLIC
    Code:
      stack=2, locals=1, args_size=1
         0: aload_0
         1: getfield      #202                // Field bitmap$0:B
         4: iconst_2
         5: iand
         6: i2b
         7: iconst_0
         8: if_icmpne     18
        11: aload_0
        12: invokespecial #295                // Method $content$lzycompute:()Lscala/collection/immutable/Seq;
        15: goto          22
        18: aload_0
        19: getfield      #293                // Field $content:Lscala/collection/immutable/Seq;
        22: areturn
      StackMapTable: number_of_entries = 2
        frame_type = 18 /* same */
        frame_type = 67 /* same_locals_1_stack_item */
          stack = [ class scala/collection/immutable/Seq ]
      LineNumberTable:
        line 1188: 0
      LocalVariableTable:
        Start  Length  Slot  Name   Signature
            0      23     0  this   Lorg/sireum/ops/ISZBOps;
    Signature: #264                         // ()Lscala/collection/immutable/Seq<Lscala/Tuple2<Ljava/lang/String;Ljava/lang/Object;>;>;

  public byte toU8();
    descriptor: ()B
    flags: (0x0001) ACC_PUBLIC
    Code:
      stack=8, locals=3, args_size=1
         0: getstatic     #302                // Field org/sireum/U8$.MODULE$:Lorg/sireum/U8$;
         3: new           #304                // class scala/StringContext
         6: dup
         7: getstatic     #220                // Field scala/runtime/ScalaRunTime$.MODULE$:Lscala/runtime/ScalaRunTime$;
        10: iconst_1
        11: anewarray     #192                // class java/lang/String
        14: dup
        15: iconst_0
        16: ldc_w         #306                // String 0
        19: aastore
        20: checkcast     #280                // class "[Ljava/lang/Object;"
        23: invokevirtual #233                // Method scala/runtime/ScalaRunTime$.wrapRefArray:([Ljava/lang/Object;)Lscala/collection/immutable/ArraySeq;
        26: invokespecial #309                // Method scala/StringContext."<init>":(Lscala/collection/immutable/Seq;)V
        29: invokevirtual #312                // Method org/sireum/U8$.U8$Slang:(Lscala/StringContext;)Lorg/sireum/U8$U8$Slang;
        32: invokevirtual #316                // Method org/sireum/U8$U8$Slang.u8:()Lorg/sireum/U8$U8$Slang$u8$;
        35: getstatic     #321                // Field scala/collection/immutable/Nil$.MODULE$:Lscala/collection/immutable/Nil$;
        38: invokevirtual #324                // Method org/sireum/U8$U8$Slang$u8$.apply:(Lscala/collection/immutable/Seq;)B
        41: invokestatic  #330                // Method scala/runtime/ByteRef.create:(B)Lscala/runtime/ByteRef;
        44: astore_1
        45: getstatic     #302                // Field org/sireum/U8$.MODULE$:Lorg/sireum/U8$;
        48: new           #304                // class scala/StringContext
        51: dup
        52: getstatic     #220                // Field scala/runtime/ScalaRunTime$.MODULE$:Lscala/runtime/ScalaRunTime$;
        55: iconst_1
        56: anewarray     #192                // class java/lang/String
        59: dup
        60: iconst_0
        61: ldc_w         #332                // String 1
        64: aastore
        65: checkcast     #280                // class "[Ljava/lang/Object;"
        68: invokevirtual #233                // Method scala/runtime/ScalaRunTime$.wrapRefArray:([Ljava/lang/Object;)Lscala/collection/immutable/ArraySeq;
        71: invokespecial #309                // Method scala/StringContext."<init>":(Lscala/collection/immutable/Seq;)V
        74: invokevirtual #312                // Method org/sireum/U8$.U8$Slang:(Lscala/StringContext;)Lorg/sireum/U8$U8$Slang;
        77: invokevirtual #316                // Method org/sireum/U8$U8$Slang.u8:()Lorg/sireum/U8$U8$Slang$u8$;
        80: getstatic     #321                // Field scala/collection/immutable/Nil$.MODULE$:Lscala/collection/immutable/Nil$;
        83: invokevirtual #324                // Method org/sireum/U8$U8$Slang$u8$.apply:(Lscala/collection/immutable/Seq;)B
        86: invokestatic  #330                // Method scala/runtime/ByteRef.create:(B)Lscala/runtime/ByteRef;
        89: astore_2
        90: getstatic     #337                // Field org/sireum/Z$.MODULE$:Lorg/sireum/Z$;
        93: iconst_0
        94: invokevirtual #340                // Method org/sireum/Z$.apply:(I)Lorg/sireum/Z;
        97: getstatic     #337                // Field org/sireum/Z$.MODULE$:Lorg/sireum/Z$;
       100: bipush        8
       102: invokevirtual #340                // Method org/sireum/Z$.apply:(I)Lorg/sireum/Z;
       105: invokeinterface #344,  2          // InterfaceMethod org/sireum/Z.until:(Lorg/sireum/ZLike;)Lorg/sireum/ZRange;
       110: aload_0
       111: aload_1
       112: aload_2
       113: invokedynamic #365,  0            // InvokeDynamic #0:apply:(Lorg/sireum/ops/ISZBOps;Lscala/runtime/ByteRef;Lscala/runtime/ByteRef;)Lscala/Function1;
       118: invokevirtual #371                // Method org/sireum/ZRange.foreach:(Lscala/Function1;)V
       121: aload_1
       122: getfield      #374                // Field scala/runtime/ByteRef.elem:B
       125: ireturn
      LineNumberTable:
        line 1194: 0
        line 1195: 45
        line 1196: 90
        line 1202: 121
      LocalVariableTable:
        Start  Length  Slot  Name   Signature
           45      81     1     r   Lscala/runtime/ByteRef;
           90      36     2  mask   Lscala/runtime/ByteRef;
            0     126     0  this   Lorg/sireum/ops/ISZBOps;

  public short toU16();
    descriptor: ()S
    flags: (0x0001) ACC_PUBLIC
    Code:
      stack=8, locals=3, args_size=1
         0: getstatic     #384                // Field org/sireum/U16$.MODULE$:Lorg/sireum/U16$;
         3: new           #304                // class scala/StringContext
         6: dup
         7: getstatic     #220                // Field scala/runtime/ScalaRunTime$.MODULE$:Lscala/runtime/ScalaRunTime$;
        10: iconst_1
        11: anewarray     #192                // class java/lang/String
        14: dup
        15: iconst_0
        16: ldc_w         #306                // String 0
        19: aastore
        20: checkcast     #280                // class "[Ljava/lang/Object;"
        23: invokevirtual #233                // Method scala/runtime/ScalaRunTime$.wrapRefArray:([Ljava/lang/Object;)Lscala/collection/immutable/ArraySeq;
        26: invokespecial #309                // Method scala/StringContext."<init>":(Lscala/collection/immutable/Seq;)V
        29: invokevirtual #387                // Method org/sireum/U16$.U16$Slang:(Lscala/StringContext;)Lorg/sireum/U16$U16$Slang;
        32: invokevirtual #391                // Method org/sireum/U16$U16$Slang.u16:()Lorg/sireum/U16$U16$Slang$u16$;
        35: getstatic     #321                // Field scala/collection/immutable/Nil$.MODULE$:Lscala/collection/immutable/Nil$;
        38: invokevirtual #394                // Method org/sireum/U16$U16$Slang$u16$.apply:(Lscala/collection/immutable/Seq;)S
        41: invokestatic  #399                // Method scala/runtime/ShortRef.create:(S)Lscala/runtime/ShortRef;
        44: astore_1
        45: getstatic     #384                // Field org/sireum/U16$.MODULE$:Lorg/sireum/U16$;
        48: new           #304                // class scala/StringContext
        51: dup
        52: getstatic     #220                // Field scala/runtime/ScalaRunTime$.MODULE$:Lscala/runtime/ScalaRunTime$;
        55: iconst_1
        56: anewarray     #192                // class java/lang/String
        59: dup
        60: iconst_0
        61: ldc_w         #332                // String 1
        64: aastore
        65: checkcast     #280                // class "[Ljava/lang/Object;"
        68: invokevirtual #233                // Method scala/runtime/ScalaRunTime$.wrapRefArray:([Ljava/lang/Object;)Lscala/collection/immutable/ArraySeq;
        71: invokespecial #309                // Method scala/StringContext."<init>":(Lscala/collection/immutable/Seq;)V
        74: invokevirtual #387                // Method org/sireum/U16$.U16$Slang:(Lscala/StringContext;)Lorg/sireum/U16$U16$Slang;
        77: invokevirtual #391                // Method org/sireum/U16$U16$Slang.u16:()Lorg/sireum/U16$U16$Slang$u16$;
        80: getstatic     #321                // Field scala/collection/immutable/Nil$.MODULE$:Lscala/collection/immutable/Nil$;
        83: invokevirtual #394                // Method org/sireum/U16$U16$Slang$u16$.apply:(Lscala/collection/immutable/Seq;)S
        86: invokestatic  #399                // Method scala/runtime/ShortRef.create:(S)Lscala/runtime/ShortRef;
        89: astore_2
        90: getstatic     #337                // Field org/sireum/Z$.MODULE$:Lorg/sireum/Z$;
        93: iconst_0
        94: invokevirtual #340                // Method org/sireum/Z$.apply:(I)Lorg/sireum/Z;
        97: getstatic     #337                // Field org/sireum/Z$.MODULE$:Lorg/sireum/Z$;
       100: bipush        16
       102: invokevirtual #340                // Method org/sireum/Z$.apply:(I)Lorg/sireum/Z;
       105: invokeinterface #344,  2          // InterfaceMethod org/sireum/Z.until:(Lorg/sireum/ZLike;)Lorg/sireum/ZRange;
       110: aload_0
       111: aload_1
       112: aload_2
       113: invokedynamic #407,  0            // InvokeDynamic #1:apply:(Lorg/sireum/ops/ISZBOps;Lscala/runtime/ShortRef;Lscala/runtime/ShortRef;)Lscala/Function1;
       118: invokevirtual #371                // Method org/sireum/ZRange.foreach:(Lscala/Function1;)V
       121: aload_1
       122: getfield      #409                // Field scala/runtime/ShortRef.elem:S
       125: ireturn
      LineNumberTable:
        line 1209: 0
        line 1210: 45
        line 1211: 90
        line 1217: 121
      LocalVariableTable:
        Start  Length  Slot  Name   Signature
           45      81     1     r   Lscala/runtime/ShortRef;
           90      36     2  mask   Lscala/runtime/ShortRef;
            0     126     0  this   Lorg/sireum/ops/ISZBOps;

  public int toU32();
    descriptor: ()I
    flags: (0x0001) ACC_PUBLIC
    Code:
      stack=8, locals=3, args_size=1
         0: getstatic     #416                // Field org/sireum/U32$.MODULE$:Lorg/sireum/U32$;
         3: new           #304                // class scala/StringContext
         6: dup
         7: getstatic     #220                // Field scala/runtime/ScalaRunTime$.MODULE$:Lscala/runtime/ScalaRunTime$;
        10: iconst_1
        11: anewarray     #192                // class java/lang/String
        14: dup
        15: iconst_0
        16: ldc_w         #306                // String 0
        19: aastore
        20: checkcast     #280                // class "[Ljava/lang/Object;"
        23: invokevirtual #233                // Method scala/runtime/ScalaRunTime$.wrapRefArray:([Ljava/lang/Object;)Lscala/collection/immutable/ArraySeq;
        26: invokespecial #309                // Method scala/StringContext."<init>":(Lscala/collection/immutable/Seq;)V
        29: invokevirtual #419                // Method org/sireum/U32$.U32$Slang:(Lscala/StringContext;)Lorg/sireum/U32$U32$Slang;
        32: invokevirtual #423                // Method org/sireum/U32$U32$Slang.u32:()Lorg/sireum/U32$U32$Slang$u32$;
        35: getstatic     #321                // Field scala/collection/immutable/Nil$.MODULE$:Lscala/collection/immutable/Nil$;
        38: invokevirtual #426                // Method org/sireum/U32$U32$Slang$u32$.apply:(Lscala/collection/immutable/Seq;)I
        41: invokestatic  #431                // Method scala/runtime/IntRef.create:(I)Lscala/runtime/IntRef;
        44: astore_1
        45: getstatic     #416                // Field org/sireum/U32$.MODULE$:Lorg/sireum/U32$;
        48: new           #304                // class scala/StringContext
        51: dup
        52: getstatic     #220                // Field scala/runtime/ScalaRunTime$.MODULE$:Lscala/runtime/ScalaRunTime$;
        55: iconst_1
        56: anewarray     #192                // class java/lang/String
        59: dup
        60: iconst_0
        61: ldc_w         #332                // String 1
        64: aastore
        65: checkcast     #280                // class "[Ljava/lang/Object;"
        68: invokevirtual #233                // Method scala/runtime/ScalaRunTime$.wrapRefArray:([Ljava/lang/Object;)Lscala/collection/immutable/ArraySeq;
        71: invokespecial #309                // Method scala/StringContext."<init>":(Lscala/collection/immutable/Seq;)V
        74: invokevirtual #419                // Method org/sireum/U32$.U32$Slang:(Lscala/StringContext;)Lorg/sireum/U32$U32$Slang;
        77: invokevirtual #423                // Method org/sireum/U32$U32$Slang.u32:()Lorg/sireum/U32$U32$Slang$u32$;
        80: getstatic     #321                // Field scala/collection/immutable/Nil$.MODULE$:Lscala/collection/immutable/Nil$;
        83: invokevirtual #426                // Method org/sireum/U32$U32$Slang$u32$.apply:(Lscala/collection/immutable/Seq;)I
        86: invokestatic  #431                // Method scala/runtime/IntRef.create:(I)Lscala/runtime/IntRef;
        89: astore_2
        90: getstatic     #337                // Field org/sireum/Z$.MODULE$:Lorg/sireum/Z$;
        93: iconst_0
        94: invokevirtual #340                // Method org/sireum/Z$.apply:(I)Lorg/sireum/Z;
        97: getstatic     #337                // Field org/sireum/Z$.MODULE$:Lorg/sireum/Z$;
       100: bipush        32
       102: invokevirtual #340                // Method org/sireum/Z$.apply:(I)Lorg/sireum/Z;
       105: invokeinterface #344,  2          // InterfaceMethod org/sireum/Z.until:(Lorg/sireum/ZLike;)Lorg/sireum/ZRange;
       110: aload_0
       111: aload_1
       112: aload_2
       113: invokedynamic #439,  0            // InvokeDynamic #2:apply:(Lorg/sireum/ops/ISZBOps;Lscala/runtime/IntRef;Lscala/runtime/IntRef;)Lscala/Function1;
       118: invokevirtual #371                // Method org/sireum/ZRange.foreach:(Lscala/Function1;)V
       121: aload_1
       122: getfield      #441                // Field scala/runtime/IntRef.elem:I
       125: ireturn
      LineNumberTable:
        line 1224: 0
        line 1225: 45
        line 1226: 90
        line 1232: 121
      LocalVariableTable:
        Start  Length  Slot  Name   Signature
           45      81     1     r   Lscala/runtime/IntRef;
           90      36     2  mask   Lscala/runtime/IntRef;
            0     126     0  this   Lorg/sireum/ops/ISZBOps;

  public long toU64();
    descriptor: ()J
    flags: (0x0001) ACC_PUBLIC
    Code:
      stack=8, locals=3, args_size=1
         0: getstatic     #449                // Field org/sireum/U64$.MODULE$:Lorg/sireum/U64$;
         3: new           #304                // class scala/StringContext
         6: dup
         7: getstatic     #220                // Field scala/runtime/ScalaRunTime$.MODULE$:Lscala/runtime/ScalaRunTime$;
        10: iconst_1
        11: anewarray     #192                // class java/lang/String
        14: dup
        15: iconst_0
        16: ldc_w         #306                // String 0
        19: aastore
        20: checkcast     #280                // class "[Ljava/lang/Object;"
        23: invokevirtual #233                // Method scala/runtime/ScalaRunTime$.wrapRefArray:([Ljava/lang/Object;)Lscala/collection/immutable/ArraySeq;
        26: invokespecial #309                // Method scala/StringContext."<init>":(Lscala/collection/immutable/Seq;)V
        29: invokevirtual #452                // Method org/sireum/U64$.U64$Slang:(Lscala/StringContext;)Lorg/sireum/U64$U64$Slang;
        32: invokevirtual #456                // Method org/sireum/U64$U64$Slang.u64:()Lorg/sireum/U64$U64$Slang$u64$;
        35: getstatic     #321                // Field scala/collection/immutable/Nil$.MODULE$:Lscala/collection/immutable/Nil$;
        38: invokevirtual #459                // Method org/sireum/U64$U64$Slang$u64$.apply:(Lscala/collection/immutable/Seq;)J
        41: invokestatic  #464                // Method scala/runtime/LongRef.create:(J)Lscala/runtime/LongRef;
        44: astore_1
        45: getstatic     #449                // Field org/sireum/U64$.MODULE$:Lorg/sireum/U64$;
        48: new           #304                // class scala/StringContext
        51: dup
        52: getstatic     #220                // Field scala/runtime/ScalaRunTime$.MODULE$:Lscala/runtime/ScalaRunTime$;
        55: iconst_1
        56: anewarray     #192                // class java/lang/String
        59: dup
        60: iconst_0
        61: ldc_w         #332                // String 1
        64: aastore
        65: checkcast     #280                // class "[Ljava/lang/Object;"
        68: invokevirtual #233                // Method scala/runtime/ScalaRunTime$.wrapRefArray:([Ljava/lang/Object;)Lscala/collection/immutable/ArraySeq;
        71: invokespecial #309                // Method scala/StringContext."<init>":(Lscala/collection/immutable/Seq;)V
        74: invokevirtual #452                // Method org/sireum/U64$.U64$Slang:(Lscala/StringContext;)Lorg/sireum/U64$U64$Slang;
        77: invokevirtual #456                // Method org/sireum/U64$U64$Slang.u64:()Lorg/sireum/U64$U64$Slang$u64$;
        80: getstatic     #321                // Field scala/collection/immutable/Nil$.MODULE$:Lscala/collection/immutable/Nil$;
        83: invokevirtual #459                // Method org/sireum/U64$U64$Slang$u64$.apply:(Lscala/collection/immutable/Seq;)J
        86: invokestatic  #464                // Method scala/runtime/LongRef.create:(J)Lscala/runtime/LongRef;
        89: astore_2
        90: getstatic     #337                // Field org/sireum/Z$.MODULE$:Lorg/sireum/Z$;
        93: iconst_0
        94: invokevirtual #340                // Method org/sireum/Z$.apply:(I)Lorg/sireum/Z;
        97: getstatic     #337                // Field org/sireum/Z$.MODULE$:Lorg/sireum/Z$;
       100: bipush        64
       102: invokevirtual #340                // Method org/sireum/Z$.apply:(I)Lorg/sireum/Z;
       105: invokeinterface #344,  2          // InterfaceMethod org/sireum/Z.until:(Lorg/sireum/ZLike;)Lorg/sireum/ZRange;
       110: aload_0
       111: aload_1
       112: aload_2
       113: invokedynamic #472,  0            // InvokeDynamic #3:apply:(Lorg/sireum/ops/ISZBOps;Lscala/runtime/LongRef;Lscala/runtime/LongRef;)Lscala/Function1;
       118: invokevirtual #371                // Method org/sireum/ZRange.foreach:(Lscala/Function1;)V
       121: aload_1
       122: getfield      #474                // Field scala/runtime/LongRef.elem:J
       125: lreturn
      LineNumberTable:
        line 1239: 0
        line 1240: 45
        line 1241: 90
        line 1247: 121
      LocalVariableTable:
        Start  Length  Slot  Name   Signature
           45      81     1     r   Lscala/runtime/LongRef;
           90      36     2  mask   Lscala/runtime/LongRef;
            0     126     0  this   Lorg/sireum/ops/ISZBOps;

  public java.lang.Object $clone();
    descriptor: ()Ljava/lang/Object;
    flags: (0x1041) ACC_PUBLIC, ACC_BRIDGE, ACC_SYNTHETIC
    Code:
      stack=1, locals=1, args_size=1
         0: aload_0
         1: invokevirtual #478                // Method $clone:()Lorg/sireum/$internal/ImmutableMarker;
         4: areturn
      LineNumberTable:
        line 1188: 0
      LocalVariableTable:
        Start  Length  Slot  Name   Signature
            0       5     0  this   Lorg/sireum/ops/ISZBOps;

  public static final void $anonfun$toU8$1(org.sireum.ops.ISZBOps, scala.runtime.ByteRef, scala.runtime.ByteRef, org.sireum.Z);
    descriptor: (Lorg/sireum/ops/ISZBOps;Lscala/runtime/ByteRef;Lscala/runtime/ByteRef;Lorg/sireum/Z;)V
    flags: (0x1019) ACC_PUBLIC, ACC_STATIC, ACC_FINAL, ACC_SYNTHETIC
    Code:
      stack=12, locals=4, args_size=4
         0: getstatic     #489                // Field org/sireum/B$.MODULE$:Lorg/sireum/B$;
         3: aload_0
         4: invokevirtual #182                // Method s:()Lorg/sireum/IS;
         7: aload_3
         8: invokevirtual #491                // Method org/sireum/IS.apply:(Ljava/lang/Object;)Ljava/lang/Object;
        11: checkcast     #493                // class org/sireum/B
        14: invokevirtual #496                // Method org/sireum/B.value:()Z
        17: invokevirtual #500                // Method org/sireum/B$.$4B:(Z)Z
        20: ifeq          61
        23: aload_1
        24: new           #46                 // class org/sireum/U8
        27: dup
        28: aload_1
        29: getfield      #374                // Field scala/runtime/ByteRef.elem:B
        32: invokespecial #503                // Method org/sireum/U8."<init>":(B)V
        35: new           #46                 // class org/sireum/U8
        38: dup
        39: aload_2
        40: getfield      #374                // Field scala/runtime/ByteRef.elem:B
        43: invokespecial #503                // Method org/sireum/U8."<init>":(B)V
        46: invokevirtual #507                // Method org/sireum/U8.$bar:(Lorg/sireum/Z$BV$Byte;)Lorg/sireum/Z$BV$Byte;
        49: checkcast     #46                 // class org/sireum/U8
        52: invokevirtual #509                // Method org/sireum/U8.value:()B
        55: putfield      #374                // Field scala/runtime/ByteRef.elem:B
        58: goto          61
        61: aload_2
        62: new           #46                 // class org/sireum/U8
        65: dup
        66: aload_2
        67: getfield      #374                // Field scala/runtime/ByteRef.elem:B
        70: invokespecial #503                // Method org/sireum/U8."<init>":(B)V
        73: new           #46                 // class org/sireum/U8
        76: dup
        77: getstatic     #302                // Field org/sireum/U8$.MODULE$:Lorg/sireum/U8$;
        80: new           #304                // class scala/StringContext
        83: dup
        84: getstatic     #220                // Field scala/runtime/ScalaRunTime$.MODULE$:Lscala/runtime/ScalaRunTime$;
        87: iconst_1
        88: anewarray     #192                // class java/lang/String
        91: dup
        92: iconst_0
        93: ldc_w         #332                // String 1
        96: aastore
        97: checkcast     #280                // class "[Ljava/lang/Object;"
       100: invokevirtual #233                // Method scala/runtime/ScalaRunTime$.wrapRefArray:([Ljava/lang/Object;)Lscala/collection/immutable/ArraySeq;
       103: invokespecial #309                // Method scala/StringContext."<init>":(Lscala/collection/immutable/Seq;)V
       106: invokevirtual #312                // Method org/sireum/U8$.U8$Slang:(Lscala/StringContext;)Lorg/sireum/U8$U8$Slang;
       109: invokevirtual #316                // Method org/sireum/U8$U8$Slang.u8:()Lorg/sireum/U8$U8$Slang$u8$;
       112: getstatic     #321                // Field scala/collection/immutable/Nil$.MODULE$:Lscala/collection/immutable/Nil$;
       115: invokevirtual #324                // Method org/sireum/U8$U8$Slang$u8$.apply:(Lscala/collection/immutable/Seq;)B
       118: invokespecial #503                // Method org/sireum/U8."<init>":(B)V
       121: invokevirtual #512                // Method org/sireum/U8.$less$less:(Lorg/sireum/Z$BV$Byte;)Lorg/sireum/Z$BV$Byte;
       124: checkcast     #46                 // class org/sireum/U8
       127: invokevirtual #509                // Method org/sireum/U8.value:()B
       130: putfield      #374                // Field scala/runtime/ByteRef.elem:B
       133: return
      StackMapTable: number_of_entries = 1
        frame_type = 61 /* same */
      LineNumberTable:
        line 1197: 0
        line 1198: 23
        line 1200: 61
      LocalVariableTable:
        Start  Length  Slot  Name   Signature
            0     134     0 $this   Lorg/sireum/ops/ISZBOps;
            0     134     1  r$17   Lscala/runtime/ByteRef;
            0     134     2 mask$1   Lscala/runtime/ByteRef;
            0     134     3     i   Lorg/sireum/Z;
    MethodParameters:
      Name                           Flags
      $this                          final synthetic
      r$17                           final
      mask$1                         final
      i                              final

  public static final void $anonfun$toU16$1(org.sireum.ops.ISZBOps, scala.runtime.ShortRef, scala.runtime.ShortRef, org.sireum.Z);
    descriptor: (Lorg/sireum/ops/ISZBOps;Lscala/runtime/ShortRef;Lscala/runtime/ShortRef;Lorg/sireum/Z;)V
    flags: (0x1019) ACC_PUBLIC, ACC_STATIC, ACC_FINAL, ACC_SYNTHETIC
    Code:
      stack=12, locals=4, args_size=4
         0: getstatic     #489                // Field org/sireum/B$.MODULE$:Lorg/sireum/B$;
         3: aload_0
         4: invokevirtual #182                // Method s:()Lorg/sireum/IS;
         7: aload_3
         8: invokevirtual #491                // Method org/sireum/IS.apply:(Ljava/lang/Object;)Ljava/lang/Object;
        11: checkcast     #493                // class org/sireum/B
        14: invokevirtual #496                // Method org/sireum/B.value:()Z
        17: invokevirtual #500                // Method org/sireum/B$.$4B:(Z)Z
        20: ifeq          61
        23: aload_1
        24: new           #22                 // class org/sireum/U16
        27: dup
        28: aload_1
        29: getfield      #409                // Field scala/runtime/ShortRef.elem:S
        32: invokespecial #520                // Method org/sireum/U16."<init>":(S)V
        35: new           #22                 // class org/sireum/U16
        38: dup
        39: aload_2
        40: getfield      #409                // Field scala/runtime/ShortRef.elem:S
        43: invokespecial #520                // Method org/sireum/U16."<init>":(S)V
        46: invokevirtual #523                // Method org/sireum/U16.$bar:(Lorg/sireum/Z$BV$Short;)Lorg/sireum/Z$BV$Short;
        49: checkcast     #22                 // class org/sireum/U16
        52: invokevirtual #525                // Method org/sireum/U16.value:()S
        55: putfield      #409                // Field scala/runtime/ShortRef.elem:S
        58: goto          61
        61: aload_2
        62: new           #22                 // class org/sireum/U16
        65: dup
        66: aload_2
        67: getfield      #409                // Field scala/runtime/ShortRef.elem:S
        70: invokespecial #520                // Method org/sireum/U16."<init>":(S)V
        73: new           #22                 // class org/sireum/U16
        76: dup
        77: getstatic     #384                // Field org/sireum/U16$.MODULE$:Lorg/sireum/U16$;
        80: new           #304                // class scala/StringContext
        83: dup
        84: getstatic     #220                // Field scala/runtime/ScalaRunTime$.MODULE$:Lscala/runtime/ScalaRunTime$;
        87: iconst_1
        88: anewarray     #192                // class java/lang/String
        91: dup
        92: iconst_0
        93: ldc_w         #332                // String 1
        96: aastore
        97: checkcast     #280                // class "[Ljava/lang/Object;"
       100: invokevirtual #233                // Method scala/runtime/ScalaRunTime$.wrapRefArray:([Ljava/lang/Object;)Lscala/collection/immutable/ArraySeq;
       103: invokespecial #309                // Method scala/StringContext."<init>":(Lscala/collection/immutable/Seq;)V
       106: invokevirtual #387                // Method org/sireum/U16$.U16$Slang:(Lscala/StringContext;)Lorg/sireum/U16$U16$Slang;
       109: invokevirtual #391                // Method org/sireum/U16$U16$Slang.u16:()Lorg/sireum/U16$U16$Slang$u16$;
       112: getstatic     #321                // Field scala/collection/immutable/Nil$.MODULE$:Lscala/collection/immutable/Nil$;
       115: invokevirtual #394                // Method org/sireum/U16$U16$Slang$u16$.apply:(Lscala/collection/immutable/Seq;)S
       118: invokespecial #520                // Method org/sireum/U16."<init>":(S)V
       121: invokevirtual #527                // Method org/sireum/U16.$less$less:(Lorg/sireum/Z$BV$Short;)Lorg/sireum/Z$BV$Short;
       124: checkcast     #22                 // class org/sireum/U16
       127: invokevirtual #525                // Method org/sireum/U16.value:()S
       130: putfield      #409                // Field scala/runtime/ShortRef.elem:S
       133: return
      StackMapTable: number_of_entries = 1
        frame_type = 61 /* same */
      LineNumberTable:
        line 1212: 0
        line 1213: 23
        line 1215: 61
      LocalVariableTable:
        Start  Length  Slot  Name   Signature
            0     134     0 $this   Lorg/sireum/ops/ISZBOps;
            0     134     1  r$18   Lscala/runtime/ShortRef;
            0     134     2 mask$2   Lscala/runtime/ShortRef;
            0     134     3     i   Lorg/sireum/Z;
    MethodParameters:
      Name                           Flags
      $this                          final synthetic
      r$18                           final
      mask$2                         final
      i                              final

  public static final void $anonfun$toU32$1(org.sireum.ops.ISZBOps, scala.runtime.IntRef, scala.runtime.IntRef, org.sireum.Z);
    descriptor: (Lorg/sireum/ops/ISZBOps;Lscala/runtime/IntRef;Lscala/runtime/IntRef;Lorg/sireum/Z;)V
    flags: (0x1019) ACC_PUBLIC, ACC_STATIC, ACC_FINAL, ACC_SYNTHETIC
    Code:
      stack=12, locals=4, args_size=4
         0: getstatic     #489                // Field org/sireum/B$.MODULE$:Lorg/sireum/B$;
         3: aload_0
         4: invokevirtual #182                // Method s:()Lorg/sireum/IS;
         7: aload_3
         8: invokevirtual #491                // Method org/sireum/IS.apply:(Ljava/lang/Object;)Ljava/lang/Object;
        11: checkcast     #493                // class org/sireum/B
        14: invokevirtual #496                // Method org/sireum/B.value:()Z
        17: invokevirtual #500                // Method org/sireum/B$.$4B:(Z)Z
        20: ifeq          61
        23: aload_1
        24: new           #30                 // class org/sireum/U32
        27: dup
        28: aload_1
        29: getfield      #441                // Field scala/runtime/IntRef.elem:I
        32: invokespecial #534                // Method org/sireum/U32."<init>":(I)V
        35: new           #30                 // class org/sireum/U32
        38: dup
        39: aload_2
        40: getfield      #441                // Field scala/runtime/IntRef.elem:I
        43: invokespecial #534                // Method org/sireum/U32."<init>":(I)V
        46: invokevirtual #537                // Method org/sireum/U32.$bar:(Lorg/sireum/Z$BV$Int;)Lorg/sireum/Z$BV$Int;
        49: checkcast     #30                 // class org/sireum/U32
        52: invokevirtual #539                // Method org/sireum/U32.value:()I
        55: putfield      #441                // Field scala/runtime/IntRef.elem:I
        58: goto          61
        61: aload_2
        62: new           #30                 // class org/sireum/U32
        65: dup
        66: aload_2
        67: getfield      #441                // Field scala/runtime/IntRef.elem:I
        70: invokespecial #534                // Method org/sireum/U32."<init>":(I)V
        73: new           #30                 // class org/sireum/U32
        76: dup
        77: getstatic     #416                // Field org/sireum/U32$.MODULE$:Lorg/sireum/U32$;
        80: new           #304                // class scala/StringContext
        83: dup
        84: getstatic     #220                // Field scala/runtime/ScalaRunTime$.MODULE$:Lscala/runtime/ScalaRunTime$;
        87: iconst_1
        88: anewarray     #192                // class java/lang/String
        91: dup
        92: iconst_0
        93: ldc_w         #332                // String 1
        96: aastore
        97: checkcast     #280                // class "[Ljava/lang/Object;"
       100: invokevirtual #233                // Method scala/runtime/ScalaRunTime$.wrapRefArray:([Ljava/lang/Object;)Lscala/collection/immutable/ArraySeq;
       103: invokespecial #309                // Method scala/StringContext."<init>":(Lscala/collection/immutable/Seq;)V
       106: invokevirtual #419                // Method org/sireum/U32$.U32$Slang:(Lscala/StringContext;)Lorg/sireum/U32$U32$Slang;
       109: invokevirtual #423                // Method org/sireum/U32$U32$Slang.u32:()Lorg/sireum/U32$U32$Slang$u32$;
       112: getstatic     #321                // Field scala/collection/immutable/Nil$.MODULE$:Lscala/collection/immutable/Nil$;
       115: invokevirtual #426                // Method org/sireum/U32$U32$Slang$u32$.apply:(Lscala/collection/immutable/Seq;)I
       118: invokespecial #534                // Method org/sireum/U32."<init>":(I)V
       121: invokevirtual #541                // Method org/sireum/U32.$less$less:(Lorg/sireum/Z$BV$Int;)Lorg/sireum/Z$BV$Int;
       124: checkcast     #30                 // class org/sireum/U32
       127: invokevirtual #539                // Method org/sireum/U32.value:()I
       130: putfield      #441                // Field scala/runtime/IntRef.elem:I
       133: return
      StackMapTable: number_of_entries = 1
        frame_type = 61 /* same */
      LineNumberTable:
        line 1227: 0
        line 1228: 23
        line 1230: 61
      LocalVariableTable:
        Start  Length  Slot  Name   Signature
            0     134     0 $this   Lorg/sireum/ops/ISZBOps;
            0     134     1  r$19   Lscala/runtime/IntRef;
            0     134     2 mask$3   Lscala/runtime/IntRef;
            0     134     3     i   Lorg/sireum/Z;
    MethodParameters:
      Name                           Flags
      $this                          final synthetic
      r$19                           final
      mask$3                         final
      i                              final

  public static final void $anonfun$toU64$1(org.sireum.ops.ISZBOps, scala.runtime.LongRef, scala.runtime.LongRef, org.sireum.Z);
    descriptor: (Lorg/sireum/ops/ISZBOps;Lscala/runtime/LongRef;Lscala/runtime/LongRef;Lorg/sireum/Z;)V
    flags: (0x1019) ACC_PUBLIC, ACC_STATIC, ACC_FINAL, ACC_SYNTHETIC
    Code:
      stack=12, locals=4, args_size=4
         0: getstatic     #489                // Field org/sireum/B$.MODULE$:Lorg/sireum/B$;
         3: aload_0
         4: invokevirtual #182                // Method s:()Lorg/sireum/IS;
         7: aload_3
         8: invokevirtual #491                // Method org/sireum/IS.apply:(Ljava/lang/Object;)Ljava/lang/Object;
        11: checkcast     #493                // class org/sireum/B
        14: invokevirtual #496                // Method org/sireum/B.value:()Z
        17: invokevirtual #500                // Method org/sireum/B$.$4B:(Z)Z
        20: ifeq          61
        23: aload_1
        24: new           #38                 // class org/sireum/U64
        27: dup
        28: aload_1
        29: getfield      #474                // Field scala/runtime/LongRef.elem:J
        32: invokespecial #548                // Method org/sireum/U64."<init>":(J)V
        35: new           #38                 // class org/sireum/U64
        38: dup
        39: aload_2
        40: getfield      #474                // Field scala/runtime/LongRef.elem:J
        43: invokespecial #548                // Method org/sireum/U64."<init>":(J)V
        46: invokevirtual #551                // Method org/sireum/U64.$bar:(Lorg/sireum/Z$BV$Long;)Lorg/sireum/Z$BV$Long;
        49: checkcast     #38                 // class org/sireum/U64
        52: invokevirtual #553                // Method org/sireum/U64.value:()J
        55: putfield      #474                // Field scala/runtime/LongRef.elem:J
        58: goto          61
        61: aload_2
        62: new           #38                 // class org/sireum/U64
        65: dup
        66: aload_2
        67: getfield      #474                // Field scala/runtime/LongRef.elem:J
        70: invokespecial #548                // Method org/sireum/U64."<init>":(J)V
        73: new           #38                 // class org/sireum/U64
        76: dup
        77: getstatic     #449                // Field org/sireum/U64$.MODULE$:Lorg/sireum/U64$;
        80: new           #304                // class scala/StringContext
        83: dup
        84: getstatic     #220                // Field scala/runtime/ScalaRunTime$.MODULE$:Lscala/runtime/ScalaRunTime$;
        87: iconst_1
        88: anewarray     #192                // class java/lang/String
        91: dup
        92: iconst_0
        93: ldc_w         #332                // String 1
        96: aastore
        97: checkcast     #280                // class "[Ljava/lang/Object;"
       100: invokevirtual #233                // Method scala/runtime/ScalaRunTime$.wrapRefArray:([Ljava/lang/Object;)Lscala/collection/immutable/ArraySeq;
       103: invokespecial #309                // Method scala/StringContext."<init>":(Lscala/collection/immutable/Seq;)V
       106: invokevirtual #452                // Method org/sireum/U64$.U64$Slang:(Lscala/StringContext;)Lorg/sireum/U64$U64$Slang;
       109: invokevirtual #456                // Method org/sireum/U64$U64$Slang.u64:()Lorg/sireum/U64$U64$Slang$u64$;
       112: getstatic     #321                // Field scala/collection/immutable/Nil$.MODULE$:Lscala/collection/immutable/Nil$;
       115: invokevirtual #459                // Method org/sireum/U64$U64$Slang$u64$.apply:(Lscala/collection/immutable/Seq;)J
       118: invokespecial #548                // Method org/sireum/U64."<init>":(J)V
       121: invokevirtual #555                // Method org/sireum/U64.$less$less:(Lorg/sireum/Z$BV$Long;)Lorg/sireum/Z$BV$Long;
       124: checkcast     #38                 // class org/sireum/U64
       127: invokevirtual #553                // Method org/sireum/U64.value:()J
       130: putfield      #474                // Field scala/runtime/LongRef.elem:J
       133: return
      StackMapTable: number_of_entries = 1
        frame_type = 61 /* same */
      LineNumberTable:
        line 1242: 0
        line 1243: 23
        line 1245: 61
      LocalVariableTable:
        Start  Length  Slot  Name   Signature
            0     134     0 $this   Lorg/sireum/ops/ISZBOps;
            0     134     1  r$20   Lscala/runtime/LongRef;
            0     134     2 mask$4   Lscala/runtime/LongRef;
            0     134     3     i   Lorg/sireum/Z;
    MethodParameters:
      Name                           Flags
      $this                          final synthetic
      r$20                           final
      mask$4                         final
      i                              final

  public org.sireum.ops.ISZBOps(org.sireum.IS<org.sireum.Z, org.sireum.B>);
    descriptor: (Lorg/sireum/IS;)V
    flags: (0x0001) ACC_PUBLIC
    Code:
      stack=2, locals=2, args_size=2
         0: aload_0
         1: invokespecial #558                // Method java/lang/Object."<init>":()V
         4: aload_0
         5: invokestatic  #562                // InterfaceMethod org/sireum/$internal/ImmutableMarker.$init$:(Lorg/sireum/$internal/ImmutableMarker;)V
         8: aload_0
         9: invokestatic  #565                // InterfaceMethod org/sireum/Immutable.$init$:(Lorg/sireum/Immutable;)V
        12: aload_0
        13: invokestatic  #568                // InterfaceMethod org/sireum/DatatypeSig.$init$:(Lorg/sireum/DatatypeSig;)V
        16: aload_0
        17: aload_1
        18: putfield      #151                // Field _s:Lorg/sireum/IS;
        21: return
      LineNumberTable:
        line 1188: 0
      LocalVariableTable:
        Start  Length  Slot  Name   Signature
            0      22     0  this   Lorg/sireum/ops/ISZBOps;
            0      22     1   __s   Lorg/sireum/IS;
    Signature: #556                         // (Lorg/sireum/IS<Lorg/sireum/Z;Lorg/sireum/B;>;)V
    MethodParameters:
      Name                           Flags
      __s                            final

  public static final java.lang.Object $anonfun$toU8$1$adapted(org.sireum.ops.ISZBOps, scala.runtime.ByteRef, scala.runtime.ByteRef, org.sireum.Z);
    descriptor: (Lorg/sireum/ops/ISZBOps;Lscala/runtime/ByteRef;Lscala/runtime/ByteRef;Lorg/sireum/Z;)Ljava/lang/Object;
    flags: (0x1019) ACC_PUBLIC, ACC_STATIC, ACC_FINAL, ACC_SYNTHETIC
    Code:
      stack=4, locals=4, args_size=4
         0: aload_0
         1: aload_1
         2: aload_2
         3: aload_3
         4: invokestatic  #570                // Method $anonfun$toU8$1:(Lorg/sireum/ops/ISZBOps;Lscala/runtime/ByteRef;Lscala/runtime/ByteRef;Lorg/sireum/Z;)V
         7: getstatic     #576                // Field scala/runtime/BoxedUnit.UNIT:Lscala/runtime/BoxedUnit;
        10: areturn
      LineNumberTable:
        line 1196: 0
      LocalVariableTable:
        Start  Length  Slot  Name   Signature
            0      11     0 $this   Lorg/sireum/ops/ISZBOps;
            0      11     1  r$17   Lscala/runtime/ByteRef;
            0      11     2 mask$1   Lscala/runtime/ByteRef;
            0      11     3     i   Lorg/sireum/Z;
    MethodParameters:
      Name                           Flags
      $this                          final
      r$17                           final
      mask$1                         final
      i                              final

  public static final java.lang.Object $anonfun$toU16$1$adapted(org.sireum.ops.ISZBOps, scala.runtime.ShortRef, scala.runtime.ShortRef, org.sireum.Z);
    descriptor: (Lorg/sireum/ops/ISZBOps;Lscala/runtime/ShortRef;Lscala/runtime/ShortRef;Lorg/sireum/Z;)Ljava/lang/Object;
    flags: (0x1019) ACC_PUBLIC, ACC_STATIC, ACC_FINAL, ACC_SYNTHETIC
    Code:
      stack=4, locals=4, args_size=4
         0: aload_0
         1: aload_1
         2: aload_2
         3: aload_3
         4: invokestatic  #578                // Method $anonfun$toU16$1:(Lorg/sireum/ops/ISZBOps;Lscala/runtime/ShortRef;Lscala/runtime/ShortRef;Lorg/sireum/Z;)V
         7: getstatic     #576                // Field scala/runtime/BoxedUnit.UNIT:Lscala/runtime/BoxedUnit;
        10: areturn
      LineNumberTable:
        line 1211: 0
      LocalVariableTable:
        Start  Length  Slot  Name   Signature
            0      11     0 $this   Lorg/sireum/ops/ISZBOps;
            0      11     1  r$18   Lscala/runtime/ShortRef;
            0      11     2 mask$2   Lscala/runtime/ShortRef;
            0      11     3     i   Lorg/sireum/Z;
    MethodParameters:
      Name                           Flags
      $this                          final
      r$18                           final
      mask$2                         final
      i                              final

  public static final java.lang.Object $anonfun$toU32$1$adapted(org.sireum.ops.ISZBOps, scala.runtime.IntRef, scala.runtime.IntRef, org.sireum.Z);
    descriptor: (Lorg/sireum/ops/ISZBOps;Lscala/runtime/IntRef;Lscala/runtime/IntRef;Lorg/sireum/Z;)Ljava/lang/Object;
    flags: (0x1019) ACC_PUBLIC, ACC_STATIC, ACC_FINAL, ACC_SYNTHETIC
    Code:
      stack=4, locals=4, args_size=4
         0: aload_0
         1: aload_1
         2: aload_2
         3: aload_3
         4: invokestatic  #580                // Method $anonfun$toU32$1:(Lorg/sireum/ops/ISZBOps;Lscala/runtime/IntRef;Lscala/runtime/IntRef;Lorg/sireum/Z;)V
         7: getstatic     #576                // Field scala/runtime/BoxedUnit.UNIT:Lscala/runtime/BoxedUnit;
        10: areturn
      LineNumberTable:
        line 1226: 0
      LocalVariableTable:
        Start  Length  Slot  Name   Signature
            0      11     0 $this   Lorg/sireum/ops/ISZBOps;
            0      11     1  r$19   Lscala/runtime/IntRef;
            0      11     2 mask$3   Lscala/runtime/IntRef;
            0      11     3     i   Lorg/sireum/Z;
    MethodParameters:
      Name                           Flags
      $this                          final
      r$19                           final
      mask$3                         final
      i                              final

  public static final java.lang.Object $anonfun$toU64$1$adapted(org.sireum.ops.ISZBOps, scala.runtime.LongRef, scala.runtime.LongRef, org.sireum.Z);
    descriptor: (Lorg/sireum/ops/ISZBOps;Lscala/runtime/LongRef;Lscala/runtime/LongRef;Lorg/sireum/Z;)Ljava/lang/Object;
    flags: (0x1019) ACC_PUBLIC, ACC_STATIC, ACC_FINAL, ACC_SYNTHETIC
    Code:
      stack=4, locals=4, args_size=4
         0: aload_0
         1: aload_1
         2: aload_2
         3: aload_3
         4: invokestatic  #582                // Method $anonfun$toU64$1:(Lorg/sireum/ops/ISZBOps;Lscala/runtime/LongRef;Lscala/runtime/LongRef;Lorg/sireum/Z;)V
         7: getstatic     #576                // Field scala/runtime/BoxedUnit.UNIT:Lscala/runtime/BoxedUnit;
        10: areturn
      LineNumberTable:
        line 1241: 0
      LocalVariableTable:
        Start  Length  Slot  Name   Signature
            0      11     0 $this   Lorg/sireum/ops/ISZBOps;
            0      11     1  r$20   Lscala/runtime/LongRef;
            0      11     2 mask$4   Lscala/runtime/LongRef;
            0      11     3     i   Lorg/sireum/Z;
    MethodParameters:
      Name                           Flags
      $this                          final
      r$20                           final
      mask$4                         final
      i                              final

  private static java.lang.Object $deserializeLambda$(java.lang.invoke.SerializedLambda);
    descriptor: (Ljava/lang/invoke/SerializedLambda;)Ljava/lang/Object;
    flags: (0x100a) ACC_PRIVATE, ACC_STATIC, ACC_SYNTHETIC
    Code:
      stack=1, locals=1, args_size=1
         0: aload_0
         1: invokedynamic #594,  0            // InvokeDynamic #4:lambdaDeserialize:(Ljava/lang/invoke/SerializedLambda;)Ljava/lang/Object;
         6: areturn
}
InnerClasses:
  public static final #18= #15 of #17;    // Lookup=class java/lang/invoke/MethodHandles$Lookup of class java/lang/invoke/MethodHandles
  public static #23= #20 of #22;          // U16$Slang=class org/sireum/U16$U16$Slang of class org/sireum/U16
  public #26= #25 of #20;                 // u16$=class org/sireum/U16$U16$Slang$u16$ of class org/sireum/U16$U16$Slang
  public static #31= #28 of #30;          // U32$Slang=class org/sireum/U32$U32$Slang of class org/sireum/U32
  public #34= #33 of #28;                 // u32$=class org/sireum/U32$U32$Slang$u32$ of class org/sireum/U32$U32$Slang
  public static #39= #36 of #38;          // U64$Slang=class org/sireum/U64$U64$Slang of class org/sireum/U64
  public #42= #41 of #36;                 // u64$=class org/sireum/U64$U64$Slang$u64$ of class org/sireum/U64$U64$Slang
  public static #47= #44 of #46;          // U8$Slang=class org/sireum/U8$U8$Slang of class org/sireum/U8
  public #50= #49 of #44;                 // u8$=class org/sireum/U8$U8$Slang$u8$ of class org/sireum/U8$U8$Slang
  public static #55= #52 of #54;          // BV$=class org/sireum/Z$BV$ of class org/sireum/Z
  public static #58= #57 of #52;          // Byte=class org/sireum/Z$BV$Byte of class org/sireum/Z$BV$
  public static #61= #60 of #52;          // Int=class org/sireum/Z$BV$Int of class org/sireum/Z$BV$
  public static #64= #63 of #52;          // Long=class org/sireum/Z$BV$Long of class org/sireum/Z$BV$
  public static #67= #66 of #52;          // Short=class org/sireum/Z$BV$Short of class org/sireum/Z$BV$
Signature: #3                           // Ljava/lang/Object;Lorg/sireum/ops/SBOps<Lorg/sireum/Z;>;Lorg/sireum/DatatypeSig;
SourceFile: "SOps.scala"
RuntimeVisibleAnnotations:
  0: #11(#12=s#13)
    scala.reflect.ScalaSignature(
      bytes="\u0006\u0005\u0005ut!\u0002\u000e\u001c\u0011\u0003\u0011c!\u0002\u0013\u001c\u0011\u0003)\u0003\"\u0002\u0017\u0002\t\u0003i\u0003\"\u0002\u0018\u0002\t\u0003y\u0003\"B\"\u0002\t\u0003!\u0005\"\u0002&\u0002\t\u0003Y\u0005\"B*\u0002\t\u0003!\u0006\"B.\u0002\t\u0003a\u0006bBA9\u0003\u0011\u0005\u00111\u000f\u0004\u0005Im\u0011a\f\u0003\u0005f\u0013\t\u0005\t\u0015!\u00031\u0011\u0015a\u0013\u0002\"\u0001g\u0011\u0019A\u0017\u0002)A\u0005a!)Q*\u0003C\u0001S\")!.\u0003C\u0001S\")1.\u0003C!Y\")Q/\u0003C!m\"A\u00110\u0003EC\u0002\u0013\u0005#\u0010C\u0003\u007f\u0013\u0011\u0005s\u0010\u0003\u0004\\\u0013\u0011\u0005\u0011\u0011\u0003\u0005\n\u0003+I\u0011\u0013!C\u0001\u0003/A!\"!\f\n\u0011\u000b\u0007I\u0011IA\u0018\u0011\u001d\ty%\u0003C\u0001\u0003#Bq!!\u0016\n\t\u0003\t9\u0006C\u0004\u0002\\%!\t!!\u0018\t\u000f\u0005\u0005\u0014\u0002\"\u0001\u0002d\u00059\u0011j\u0015.C\u001fB\u001c(B\u0001\u000f\u001e\u0003\ry\u0007o\u001d\u0006\u0003=}\taa]5sKVl\'\"\u0001\u0011\u0002\u0007=\u0014xm\u0001\u0001\u0011\u0005\r\nQ\"A\u000e\u0003\u000f%\u001b&LQ(qgN\u0011\u0011A\n\t\u0003O)j\u0011\u0001\u000b\u0006\u0002S\u0005)1oY1mC&\u00111\u0006\u000b\u0002\u0007\u0003:L(+\u001a4\u0002\rqJg.\u001b;?)\u0005\u0011\u0013A\u00024s_6,\u0006\b\u0006\u00021uA!\u0011G\r\u001b8\u001b\u0005i\u0012BA\u001a\u001e\u0005\tI5\u000b\u0005\u00022k%\u0011a\'\b\u0002\u00025B\u0011\u0011\u0007O\u0005\u0003su\u0011\u0011A\u0011\u0005\u0006w\r\u0001\r\u0001P\u0001\u0002]B\u0011\u0011\'P\u0005\u0003}u\u0011!!\u0016\u001d)\u0005\r\u0001\u0005CA\u0019B\u0013\t\u0011UD\u0001\u0003qkJ,\u0017a\u00024s_6,\u0016G\u000e\u000b\u0003a\u0015CQa\u000f\u0003A\u0002\u0019\u0003\"!M$\n\u0005!k\"aA+2m!\u0012A\u0001Q\u0001\bMJ|W.V\u001a3)\r\u0001DJ\u0014\u0005\u0006\u001b\u0016\u0001\r\u0001M\u0001\u0002g\")1(\u0002a\u0001\u001fB\u0011\u0011\u0007U\u0005\u0003#v\u00111!V\u001a3Q\t)\u0001)A\u0004ge>lWK\u000e\u001b\u0015\u0007A*f\u000bC\u0003N\r\u0001\u0007\u0001\u0007C\u0003<\r\u0001\u0007q\u000b\u0005\u000221&\u0011\u0011,\b\u0002\u0004+Z\"\u0004F\u0001\u0004A\u0003\u0015\t\u0007\u000f\u001d7z)\ri\u0016q\u000e\t\u0003G%\u0019B!\u0003\u0014`EB\u00191\u0005\u0019\u001b\n\u0005\u0005\\\"!B*C\u001fB\u001c\bCA\u0019d\u0013\t!WDA\u0006ECR\fG/\u001f9f\'&<\u0017aA0`gR\u0011Ql\u001a\u0005\u0006K.\u0001\r\u0001M\u0001\u0003?N,\u0012\u0001M\u0001\u0005O\u0016$8+\u0001\u0005u_N#(/\u001b8h)\u0005i\u0007C\u00018t\u001b\u0005y\'B\u00019r\u0003\u0011a\u0017M\\4\u000b\u0003I\fAA[1wC&\u0011Ao\u001c\u0002\u0007\'R\u0014\u0018N\\4\u0002\rM$(/\u001b8h+\u00059\bCA\u0019y\u0013\t!X$\u0001\u0005iCND7i\u001c3f+\u0005Y\bCA\u0014}\u0013\ti\bFA\u0002J]R\fa!Z9vC2\u001cH\u0003BA\u0001\u0003\u000f\u00012aJA\u0002\u0013\r\t)\u0001\u000b\u0002\b\u0005>|G.Z1o\u0011\u001d\tIA\u0005a\u0001\u0003\u0017\t\u0011a\u001c\t\u0004O\u00055\u0011bAA\bQ\t\u0019\u0011I\\=\u0015\u0007u\u000b\u0019\u0002C\u0004N\'A\u0005\t\u0019\u0001\u0019\u0002\u001f\u0005\u0004\b\u000f\\=%I\u00164\u0017-\u001e7uIE*\"!!\u0007+\u0007A\nYb\u000b\u0002\u0002\u001eA!\u0011qDA\u0015\u001b\t\t\tC\u0003\u0003\u0002$\u0005\u0015\u0012!C;oG\",7m[3e\u0015\r\t9\u0003K\u0001\u000bC:tw\u000e^1uS>t\u0017\u0002BA\u0016\u0003C\u0011\u0011#\u001e8dQ\u0016\u001c7.\u001a3WCJL\u0017M\\2f\u0003!!3m\u001c8uK:$XCAA\u0019!\u0019\t\u0019$a\u0011\u0002J9!\u0011QGA \u001d\u0011\t9$!\u0010\u000e\u0005\u0005e\"bAA\u001eC\u00051AH]8pizJ\u0011!K\u0005\u0004\u0003\u0003B\u0013a\u00029bG.\fw-Z\u0005\u0005\u0003\u000b\n9EA\u0002TKFT1!!\u0011)!\u00199\u00131J7\u0002\f%\u0019\u0011Q\n\u0015\u0003\rQ+\b\u000f\\33\u0003\u0011!x.\u0016\u001d\u0016\u0003qB#A\u0006!\u0002\u000bQ|W+\r\u001c\u0016\u0003\u0019C#a\u0006!\u0002\u000bQ|Wk\r\u001a\u0016\u0003=C#\u0001\u0007!\u0002\u000bQ|WK\u000e\u001b\u0016\u0003]C#!\u0007!)\u0007%\tI\u0007E\u00022\u0003WJ1!!\u001c\u001e\u0005!!\u0017\r^1usB,\u0007\"B\'\b\u0001\u0004\u0001\u0014aB;oCB\u0004H.\u001f\u000b\u0005\u0003k\nY\b\u0005\u0003(\u0003o\u0002\u0014bAA=Q\t!1k\\7f\u0011\u0019\tI\u0001\u0003a\u0001;\u0002"
    )
BootstrapMethods:
  0: #362 REF_invokeStatic java/lang/invoke/LambdaMetafactory.altMetafactory:(Ljava/lang/invoke/MethodHandles$Lookup;Ljava/lang/String;Ljava/lang/invoke/MethodType;[Ljava/lang/Object;)Ljava/lang/invoke/CallSite;
    Method arguments:
      #346 (Ljava/lang/Object;)Ljava/lang/Object;
      #351 REF_invokeStatic org/sireum/ops/ISZBOps.$anonfun$toU8$1$adapted:(Lorg/sireum/ops/ISZBOps;Lscala/runtime/ByteRef;Lscala/runtime/ByteRef;Lorg/sireum/Z;)Ljava/lang/Object;
      #353 (Lorg/sireum/Z;)Ljava/lang/Object;
      #354 5
      #355 1
      #353 (Lorg/sireum/Z;)Ljava/lang/Object;
  1: #362 REF_invokeStatic java/lang/invoke/LambdaMetafactory.altMetafactory:(Ljava/lang/invoke/MethodHandles$Lookup;Ljava/lang/String;Ljava/lang/invoke/MethodType;[Ljava/lang/Object;)Ljava/lang/invoke/CallSite;
    Method arguments:
      #346 (Ljava/lang/Object;)Ljava/lang/Object;
      #404 REF_invokeStatic org/sireum/ops/ISZBOps.$anonfun$toU16$1$adapted:(Lorg/sireum/ops/ISZBOps;Lscala/runtime/ShortRef;Lscala/runtime/ShortRef;Lorg/sireum/Z;)Ljava/lang/Object;
      #353 (Lorg/sireum/Z;)Ljava/lang/Object;
      #354 5
      #355 1
      #353 (Lorg/sireum/Z;)Ljava/lang/Object;
  2: #362 REF_invokeStatic java/lang/invoke/LambdaMetafactory.altMetafactory:(Ljava/lang/invoke/MethodHandles$Lookup;Ljava/lang/String;Ljava/lang/invoke/MethodType;[Ljava/lang/Object;)Ljava/lang/invoke/CallSite;
    Method arguments:
      #346 (Ljava/lang/Object;)Ljava/lang/Object;
      #436 REF_invokeStatic org/sireum/ops/ISZBOps.$anonfun$toU32$1$adapted:(Lorg/sireum/ops/ISZBOps;Lscala/runtime/IntRef;Lscala/runtime/IntRef;Lorg/sireum/Z;)Ljava/lang/Object;
      #353 (Lorg/sireum/Z;)Ljava/lang/Object;
      #354 5
      #355 1
      #353 (Lorg/sireum/Z;)Ljava/lang/Object;
  3: #362 REF_invokeStatic java/lang/invoke/LambdaMetafactory.altMetafactory:(Ljava/lang/invoke/MethodHandles$Lookup;Ljava/lang/String;Ljava/lang/invoke/MethodType;[Ljava/lang/Object;)Ljava/lang/invoke/CallSite;
    Method arguments:
      #346 (Ljava/lang/Object;)Ljava/lang/Object;
      #469 REF_invokeStatic org/sireum/ops/ISZBOps.$anonfun$toU64$1$adapted:(Lorg/sireum/ops/ISZBOps;Lscala/runtime/LongRef;Lscala/runtime/LongRef;Lorg/sireum/Z;)Ljava/lang/Object;
      #353 (Lorg/sireum/Z;)Ljava/lang/Object;
      #354 5
      #355 1
      #353 (Lorg/sireum/Z;)Ljava/lang/Object;
  4: #591 REF_invokeStatic scala/runtime/LambdaDeserialize.bootstrap:(Ljava/lang/invoke/MethodHandles$Lookup;Ljava/lang/String;Ljava/lang/invoke/MethodType;[Ljava/lang/invoke/MethodHandle;)Ljava/lang/invoke/CallSite;
    Method arguments:
      #404 REF_invokeStatic org/sireum/ops/ISZBOps.$anonfun$toU16$1$adapted:(Lorg/sireum/ops/ISZBOps;Lscala/runtime/ShortRef;Lscala/runtime/ShortRef;Lorg/sireum/Z;)Ljava/lang/Object;
      #436 REF_invokeStatic org/sireum/ops/ISZBOps.$anonfun$toU32$1$adapted:(Lorg/sireum/ops/ISZBOps;Lscala/runtime/IntRef;Lscala/runtime/IntRef;Lorg/sireum/Z;)Ljava/lang/Object;
      #469 REF_invokeStatic org/sireum/ops/ISZBOps.$anonfun$toU64$1$adapted:(Lorg/sireum/ops/ISZBOps;Lscala/runtime/LongRef;Lscala/runtime/LongRef;Lorg/sireum/Z;)Ljava/lang/Object;
      #351 REF_invokeStatic org/sireum/ops/ISZBOps.$anonfun$toU8$1$adapted:(Lorg/sireum/ops/ISZBOps;Lscala/runtime/ByteRef;Lscala/runtime/ByteRef;Lorg/sireum/Z;)Ljava/lang/Object;
  ScalaInlineInfo: length = 0x9A (unknown attribute)
   01 01 00 1E 02 02 02 03 01 01 90 01 91 01 02 10
   02 11 01 01 B0 01 B1 01 02 1E 02 1F 01 01 D1 01
   D2 01 01 DF 01 E0 01 01 5B 01 5C 01 00 7A 00 7B
   01 00 8C 01 DC 01 00 8C 00 8D 01 00 46 01 07 01
   01 06 01 07 01 00 82 00 83 01 00 88 00 83 01 00
   A3 01 02 01 00 C3 01 00 01 01 05 00 94 01 00 F8
   00 F9 01 00 98 00 94 01 00 73 00 74 01 00 44 00
   C8 01 00 C7 00 C8 01 00 5E 00 94 01 00 C1 00 9A
   01 00 99 00 9A 01 01 7A 01 7B 01 01 9B 00 C8 01
   01 BB 01 BC 01 01 28 01 29 01
  ScalaSig: length = 0x3 (unknown attribute)
   05 02 00
