Classfile /Users/mw/Projects/slang-braindump/.jar/jar11/assemble/slang-braindump/assemble/content/org/sireum/ops/MSOps_Ext.class
  Last modified May 29, 2022; size 1928 bytes
  SHA-256 checksum 10b73313632cf561366d0543a7a96de509227d8a6c124e0c68bf321369d2da11
  Compiled from "SOps_Ext.scala"
public final class org.sireum.ops.MSOps_Ext
  minor version: 0
  major version: 52
  flags: (0x0031) ACC_PUBLIC, ACC_FINAL, ACC_SUPER
  this_class: #2                          // org/sireum/ops/MSOps_Ext
  super_class: #4                         // java/lang/Object
  interfaces: 0, fields: 0, methods: 3, attributes: 3
Constant pool:
   #1 = Utf8               org/sireum/ops/MSOps_Ext
   #2 = Class              #1             // org/sireum/ops/MSOps_Ext
   #3 = Utf8               java/lang/Object
   #4 = Class              #3             // java/lang/Object
   #5 = Utf8               SOps_Ext.scala
   #6 = Utf8               Lscala/reflect/ScalaSignature;
   #7 = Utf8               bytes
   #8 = Utf8               \u0006\u0005\u0011<QAB\u0004\t\u000291Q\u0001E\u0004\t\u0002EAQ\u0001G\u0001\u0005\u0002eAQAG\u0001\u0005\u0002mAqaP\u0001\u0012\u0002\u0013\u0005\u0001\tC\u0003P\u0003\u0011\u0005\u0001+A\u0005N\'>\u00038oX#yi*\u0011\u0001\"C\u0001\u0004_B\u001c(B\u0001\u0006\f\u0003\u0019\u0019\u0018N]3v[*\tA\"A\u0002pe\u001e\u001c\u0001\u0001\u0005\u0002\u0010\u00035\tqAA\u0005N\'>\u00038oX#yiN\u0011\u0011A\u0005\t\u0003\'Yi\u0011\u0001\u0006\u0006\u0002+\u0005)1oY1mC&\u0011q\u0003\u0006\u0002\u0007\u0003:L(+\u001a4\u0002\rqJg.\u001b;?)\u0005q\u0011aB7QCJl\u0015\r]\u000b\u00059\r\u001aT\u0006\u0006\u0003\u001e_UR\u0004\u0003\u0002\u0010 C1j\u0011!C\u0005\u0003A%\u0011!!T*\u0011\u0005\t\u001aC\u0002\u0001\u0003\u0006I\r\u0011\r!\n\u0002\u0002\u0013F\u0011a%\u000b\t\u0003\'\u001dJ!\u0001\u000b\u000b\u0003\u000f9{G\u000f[5oOB\u00111CK\u0005\u0003WQ\u00111!\u00118z!\t\u0011S\u0006B\u0003/\u0007\t\u0007QEA\u0001V\u0011\u0015\u00014\u00011\u00012\u0003\u0005\u0019\b\u0003\u0002\u0010 CI\u0002\"AI\u001a\u0005\u000bQ\u001a!\u0019A\u0013\u0003\u0003YCQAN\u0002A\u0002]\n\u0011A\u001a\t\u0005\'a\u0012D&\u0003\u0002:)\tIa)\u001e8di&|g.\r\u0005\bw\r\u0001\n\u00111\u0001=\u0003)qW/\\(g\u0007>\u0014Xm\u001d\t\u0003=uJ!AP\u0005\u0003\u0003i\u000b\u0011#\u001c)be6\u000b\u0007\u000f\n3fM\u0006,H\u000e\u001e\u00134+\u0011\tE*\u0014(\u0016\u0003\tS#\u0001P\",\u0003\u0011\u0003\"!\u0012&\u000e\u0003\u0019S!a\u0012%\u0002\u0013Ut7\r[3dW\u0016$\'BA%\u0015\u0003)\tgN\\8uCRLwN\\\u0005\u0003\u0017\u001a\u0013\u0011#\u001e8dQ\u0016\u001c7.\u001a3WCJL\u0017M\\2f\t\u0015!CA1\u0001&\t\u0015!DA1\u0001&\t\u0015qCA1\u0001&\u0003!\u0019xN\u001d;XSRDWcA)U-R\u0019!k\u0016-\u0011\tyy2+\u0016\t\u0003EQ#Q\u0001J\u0003C\u0002\u0015\u0002\"A\t,\u0005\u000bQ*!\u0019A\u0013\t\u000bA*\u0001\u0019\u0001*\t\u000be+\u0001\u0019\u0001.\u0002\u00051$\b#B\n\\+Vk\u0016B\u0001/\u0015\u0005%1UO\\2uS>t\'\u0007\u0005\u0002\u001f=&\u0011q,\u0003\u0002\u0002\u0005\"\u0012Q!\u0019\t\u0003=\tL!aY\u0005\u0003\tA,(/\u001a
   #9 = Utf8               sortWith
  #10 = Utf8               (Lorg/sireum/MS;Lscala/Function2;)Lorg/sireum/MS;
  #11 = Utf8               <I:Ljava/lang/Object;V:Ljava/lang/Object;>(Lorg/sireum/MS<TI;TV;>;Lscala/Function2<TV;TV;Lorg/sireum/B;>;)Lorg/sireum/MS<TI;TV;>;
  #12 = Utf8               s
  #13 = Utf8               lt
  #14 = Utf8               org/sireum/ops/MSOps_Ext$
  #15 = Class              #14            // org/sireum/ops/MSOps_Ext$
  #16 = Utf8               MODULE$
  #17 = Utf8               Lorg/sireum/ops/MSOps_Ext$;
  #18 = NameAndType        #16:#17        // MODULE$:Lorg/sireum/ops/MSOps_Ext$;
  #19 = Fieldref           #15.#18        // org/sireum/ops/MSOps_Ext$.MODULE$:Lorg/sireum/ops/MSOps_Ext$;
  #20 = NameAndType        #9:#10         // sortWith:(Lorg/sireum/MS;Lscala/Function2;)Lorg/sireum/MS;
  #21 = Methodref          #15.#20        // org/sireum/ops/MSOps_Ext$.sortWith:(Lorg/sireum/MS;Lscala/Function2;)Lorg/sireum/MS;
  #22 = Utf8               Lorg/sireum/MS;
  #23 = Utf8               Lscala/Function2;
  #24 = Utf8               mParMap$default$3
  #25 = Utf8               ()Lorg/sireum/Z;
  #26 = Utf8               <I:Ljava/lang/Object;V:Ljava/lang/Object;U:Ljava/lang/Object;>()Lorg/sireum/Z;
  #27 = NameAndType        #24:#25        // mParMap$default$3:()Lorg/sireum/Z;
  #28 = Methodref          #15.#27        // org/sireum/ops/MSOps_Ext$.mParMap$default$3:()Lorg/sireum/Z;
  #29 = Utf8               mParMap
  #30 = Utf8               (Lorg/sireum/MS;Lscala/Function1;Lorg/sireum/Z;)Lorg/sireum/MS;
  #31 = Utf8               <I:Ljava/lang/Object;V:Ljava/lang/Object;U:Ljava/lang/Object;>(Lorg/sireum/MS<TI;TV;>;Lscala/Function1<TV;TU;>;Lorg/sireum/Z;)Lorg/sireum/MS<TI;TU;>;
  #32 = Utf8               f
  #33 = Utf8               numOfCores
  #34 = NameAndType        #29:#30        // mParMap:(Lorg/sireum/MS;Lscala/Function1;Lorg/sireum/Z;)Lorg/sireum/MS;
  #35 = Methodref          #15.#34        // org/sireum/ops/MSOps_Ext$.mParMap:(Lorg/sireum/MS;Lscala/Function1;Lorg/sireum/Z;)Lorg/sireum/MS;
  #36 = Utf8               Lscala/Function1;
  #37 = Utf8               Lorg/sireum/Z;
  #38 = Utf8               Code
  #39 = Utf8               LocalVariableTable
  #40 = Utf8               Signature
  #41 = Utf8               MethodParameters
  #42 = Utf8               SourceFile
  #43 = Utf8               RuntimeVisibleAnnotations
  #44 = Utf8               ScalaSig
{
  public static <I extends java.lang.Object, V extends java.lang.Object> org.sireum.MS<I, V> sortWith(org.sireum.MS<I, V>, scala.Function2<V, V, org.sireum.B>);
    descriptor: (Lorg/sireum/MS;Lscala/Function2;)Lorg/sireum/MS;
    flags: (0x0009) ACC_PUBLIC, ACC_STATIC
    Code:
      stack=3, locals=2, args_size=2
         0: getstatic     #19                 // Field org/sireum/ops/MSOps_Ext$.MODULE$:Lorg/sireum/ops/MSOps_Ext$;
         3: aload_0
         4: aload_1
         5: invokevirtual #21                 // Method org/sireum/ops/MSOps_Ext$.sortWith:(Lorg/sireum/MS;Lscala/Function2;)Lorg/sireum/MS;
         8: areturn
      LocalVariableTable:
        Start  Length  Slot  Name   Signature
            0       9     0     s   Lorg/sireum/MS;
            0       9     1    lt   Lscala/Function2;
    Signature: #11                          // <I:Ljava/lang/Object;V:Ljava/lang/Object;>(Lorg/sireum/MS<TI;TV;>;Lscala/Function2<TV;TV;Lorg/sireum/B;>;)Lorg/sireum/MS<TI;TV;>;
    MethodParameters:
      Name                           Flags
      s                              final
      lt                             final

  public static <I extends java.lang.Object, V extends java.lang.Object, U extends java.lang.Object> org.sireum.Z mParMap$default$3();
    descriptor: ()Lorg/sireum/Z;
    flags: (0x0009) ACC_PUBLIC, ACC_STATIC
    Code:
      stack=1, locals=0, args_size=0
         0: getstatic     #19                 // Field org/sireum/ops/MSOps_Ext$.MODULE$:Lorg/sireum/ops/MSOps_Ext$;
         3: invokevirtual #28                 // Method org/sireum/ops/MSOps_Ext$.mParMap$default$3:()Lorg/sireum/Z;
         6: areturn
    Signature: #26                          // <I:Ljava/lang/Object;V:Ljava/lang/Object;U:Ljava/lang/Object;>()Lorg/sireum/Z;

  public static <I extends java.lang.Object, V extends java.lang.Object, U extends java.lang.Object> org.sireum.MS<I, U> mParMap(org.sireum.MS<I, V>, scala.Function1<V, U>, org.sireum.Z);
    descriptor: (Lorg/sireum/MS;Lscala/Function1;Lorg/sireum/Z;)Lorg/sireum/MS;
    flags: (0x0009) ACC_PUBLIC, ACC_STATIC
    Code:
      stack=4, locals=3, args_size=3
         0: getstatic     #19                 // Field org/sireum/ops/MSOps_Ext$.MODULE$:Lorg/sireum/ops/MSOps_Ext$;
         3: aload_0
         4: aload_1
         5: aload_2
         6: invokevirtual #35                 // Method org/sireum/ops/MSOps_Ext$.mParMap:(Lorg/sireum/MS;Lscala/Function1;Lorg/sireum/Z;)Lorg/sireum/MS;
         9: areturn
      LocalVariableTable:
        Start  Length  Slot  Name   Signature
            0      10     0     s   Lorg/sireum/MS;
            0      10     1     f   Lscala/Function1;
            0      10     2 numOfCores   Lorg/sireum/Z;
    Signature: #31                          // <I:Ljava/lang/Object;V:Ljava/lang/Object;U:Ljava/lang/Object;>(Lorg/sireum/MS<TI;TV;>;Lscala/Function1<TV;TU;>;Lorg/sireum/Z;)Lorg/sireum/MS<TI;TU;>;
    MethodParameters:
      Name                           Flags
      s                              final
      f                              final
      numOfCores                     final
}
SourceFile: "SOps_Ext.scala"
RuntimeVisibleAnnotations:
  0: #6(#7=s#8)
    scala.reflect.ScalaSignature(
      bytes="\u0006\u0005\u0011<QAB\u0004\t\u000291Q\u0001E\u0004\t\u0002EAQ\u0001G\u0001\u0005\u0002eAQAG\u0001\u0005\u0002mAqaP\u0001\u0012\u0002\u0013\u0005\u0001\tC\u0003P\u0003\u0011\u0005\u0001+A\u0005N\'>\u00038oX#yi*\u0011\u0001\"C\u0001\u0004_B\u001c(B\u0001\u0006\f\u0003\u0019\u0019\u0018N]3v[*\tA\"A\u0002pe\u001e\u001c\u0001\u0001\u0005\u0002\u0010\u00035\tqAA\u0005N\'>\u00038oX#yiN\u0011\u0011A\u0005\t\u0003\'Yi\u0011\u0001\u0006\u0006\u0002+\u0005)1oY1mC&\u0011q\u0003\u0006\u0002\u0007\u0003:L(+\u001a4\u0002\rqJg.\u001b;?)\u0005q\u0011aB7QCJl\u0015\r]\u000b\u00059\r\u001aT\u0006\u0006\u0003\u001e_UR\u0004\u0003\u0002\u0010 C1j\u0011!C\u0005\u0003A%\u0011!!T*\u0011\u0005\t\u001aC\u0002\u0001\u0003\u0006I\r\u0011\r!\n\u0002\u0002\u0013F\u0011a%\u000b\t\u0003\'\u001dJ!\u0001\u000b\u000b\u0003\u000f9{G\u000f[5oOB\u00111CK\u0005\u0003WQ\u00111!\u00118z!\t\u0011S\u0006B\u0003/\u0007\t\u0007QEA\u0001V\u0011\u0015\u00014\u00011\u00012\u0003\u0005\u0019\b\u0003\u0002\u0010 CI\u0002\"AI\u001a\u0005\u000bQ\u001a!\u0019A\u0013\u0003\u0003YCQAN\u0002A\u0002]\n\u0011A\u001a\t\u0005\'a\u0012D&\u0003\u0002:)\tIa)\u001e8di&|g.\r\u0005\bw\r\u0001\n\u00111\u0001=\u0003)qW/\\(g\u0007>\u0014Xm\u001d\t\u0003=uJ!AP\u0005\u0003\u0003i\u000b\u0011#\u001c)be6\u000b\u0007\u000f\n3fM\u0006,H\u000e\u001e\u00134+\u0011\tE*\u0014(\u0016\u0003\tS#\u0001P\",\u0003\u0011\u0003\"!\u0012&\u000e\u0003\u0019S!a\u0012%\u0002\u0013Ut7\r[3dW\u0016$\'BA%\u0015\u0003)\tgN\\8uCRLwN\\\u0005\u0003\u0017\u001a\u0013\u0011#\u001e8dQ\u0016\u001c7.\u001a3WCJL\u0017M\\2f\t\u0015!CA1\u0001&\t\u0015!DA1\u0001&\t\u0015qCA1\u0001&\u0003!\u0019xN\u001d;XSRDWcA)U-R\u0019!k\u0016-\u0011\tyy2+\u0016\t\u0003EQ#Q\u0001J\u0003C\u0002\u0015\u0002\"A\t,\u0005\u000bQ*!\u0019A\u0013\t\u000bA*\u0001\u0019\u0001*\t\u000be+\u0001\u0019\u0001.\u0002\u00051$\b#B\n\\+Vk\u0016B\u0001/\u0015\u0005%1UO\\2uS>t\'\u0007\u0005\u0002\u001f=&\u0011q,\u0003\u0002\u0002\u0005\"\u0012Q!\u0019\t\u0003=\tL!aY\u0005\u0003\tA,(/\u001a"
    )
  ScalaSig: length = 0x3 (unknown attribute)
   05 02 00
