Classfile /Users/mw/Projects/slang-braindump/.jar/jar11/assemble/slang-braindump/assemble/content/org/sireum/ops/MSZOpsUtil.class
  Last modified May 29, 2022; size 2597 bytes
  SHA-256 checksum ae185e98acdf3113c5d1fd3e478a46a3825d8db9f5057110c6b88f68cf50f013
  Compiled from "SOps.scala"
public final class org.sireum.ops.MSZOpsUtil
  minor version: 0
  major version: 52
  flags: (0x0031) ACC_PUBLIC, ACC_FINAL, ACC_SUPER
  this_class: #2                          // org/sireum/ops/MSZOpsUtil
  super_class: #4                         // java/lang/Object
  interfaces: 0, fields: 0, methods: 5, attributes: 3
Constant pool:
   #1 = Utf8               org/sireum/ops/MSZOpsUtil
   #2 = Class              #1             // org/sireum/ops/MSZOpsUtil
   #3 = Utf8               java/lang/Object
   #4 = Class              #3             // java/lang/Object
   #5 = Utf8               SOps.scala
   #6 = Utf8               Lscala/reflect/ScalaSignature;
   #7 = Utf8               bytes
   #8 = Utf8               \u0006\u0005\u0005}q!\u0002\u0005\n\u0011\u0003\u0001b!\u0002\n\n\u0011\u0003\u0019\u0002\"\u0002\u000e\u0002\t\u0003Y\u0002\"\u0002\u000f\u0002\t\u0003i\u0002\"\u0002\"\u0002\t\u0003\u0019\u0005\"\u0002(\u0002\t\u0003y\u0005\"\u00020\u0002\t\u0003y\u0006\"B6\u0002\t\u0003a\u0017AC\'T5>\u00038/\u0016;jY*\u0011!bC\u0001\u0004_B\u001c(B\u0001\u0007\u000e\u0003\u0019\u0019\u0018N]3v[*\ta\"A\u0002pe\u001e\u001c\u0001\u0001\u0005\u0002\u0012\u00035\t\u0011B\u0001\u0006N\'j{\u0005o]+uS2\u001c\"!\u0001\u000b\u0011\u0005UAR\"\u0001\f\u000b\u0003]\tQa]2bY\u0006L!!\u0007\f\u0003\r\u0005s\u0017PU3g\u0003\u0019a\u0014N\\5u}Q\t\u0001#\u0001\u0004qCJl\u0015\r]\u000b\u0004=UBCcA\u00102oA!\u0001%I\u0012\'\u001b\u0005Y\u0011B\u0001\u0012\f\u0005\ti5\u000b\u0005\u0002!I%\u0011Qe\u0003\u0002\u00025B\u0011q\u0005\u000b\u0007\u0001\t\u0015I3A1\u0001+\u0005\u0005)\u0016CA\u0016/!\t)B&\u0003\u0002.-\t9aj\u001c;iS:<\u0007CA\u000b0\u0013\t\u0001dCA\u0002B]fDQAM\u0002A\u0002M\n\u0011a\u001d\t\u0005A\u0005\u001aC\u0007\u0005\u0002(k\u0011)ag\u0001b\u0001U\t\ta\u000bC\u00039\u0007\u0001\u0007\u0011(A\u0001g!\u0011)\"\b\u000e\u001f\n\u0005m2\"!\u0003$v]\u000e$\u0018n\u001c82U\t1ShK\u0001?!\t\u0001s(\u0003\u0002A\u0017\t!\u0001/\u001e:fQ\t\u0019a(A\u0004n!\u0006\u0014X*\u00199\u0016\u0007\u0011[u\tF\u0002F\u00112\u0003B\u0001I\u0011$\rB\u0011qe\u0012\u0003\u0006S\u0011\u0011\rA\u000b\u0005\u0006e\u0011\u0001\r!\u0013\t\u0005A\u0005\u001a#\n\u0005\u0002(\u0017\u0012)a\u0007\u0002b\u0001U!)\u0001\b\u0002a\u0001\u001bB!QC\u000f&G\u0003-\u0001\u0018M]\'ba\u000e{\'/Z:\u0016\u0007A;6\u000b\u0006\u0003R)b[\u0006\u0003\u0002\u0011\"GI\u0003\"aJ*\u0005\u000b%*!\u0019\u0001\u0016\t\u000bI*\u0001\u0019A+\u0011\t\u0001\n3E\u0016\t\u0003O]#QAN\u0003C\u0002)BQ\u0001O\u0003A\u0002e\u0003B!\u0006\u001eW5*\u0012!+\u0010\u0005\u00069\u0016\u0001\raI\u0001\u000b]VlwJZ\"pe\u0016\u001c\bFA\u0003?\u00031i\u0007+\u0019:NCB\u001cuN]3t+\r\u0001wm\u0019\u000b\u0005C\u0012D\'\u000e\u0005\u0003!C\r\u0012\u0007CA\u0014d\t\u0015IcA1\u0001+\u0011\u0015\u0011d\u00011\u0001f!\u0011\u0001\u0013e\t4\u0011\u0005\u001d:G!\u0002\u001c\u0007\u0005\u0004Q\u0003\"\u0002\u001d\u0007\u0001\u0004I\u0007\u0003B\u000b;M\nDQ\u0001\u0018\u0004A\u0002\r\n\u0001b]8si^KG\u000f[\u000b\u0003[B$2A\u001c:t!\u0011\u0001\u0013eI8\u0011\u0005\u001d\u0002H!B9\b\u0005\u0004Q#!\u0001+\t\u000bI:\u0001\u0019\u00018\t\u000bQ<\u0001\u0019A;\u0002\u00051$\b#B\u000bw_>D\u0018BA<\u0017\u0005%1UO\\2uS>t\'G\u000b\u0002z{A\u0011\u0001E_\u0005\u0003w.\u0011\u0011A\u0011\u0015\u0003\u000fyBC!\u0001@\u0002\u0004A\u0011\u0001e`\u0005\u0004\u0003\u0003Y!aA3yiFJ1%!\u0002\u0002\f\u0005M\u0011Q\u0002\t\u0004A\u0005\u001d\u0011bAA\u0005\u0017\t11\u000b\u001e:j]\u001eLA!!\u0004\u0002\u0010\u0005YB\u0005\\3tg&t\u0017\u000e\u001e\u0013he\u0016\fG/\u001a:%I\u00164\u0017-\u001e7uIER1!!\u0005\f\u0003\r)\u0007\u0010^\u0019\nG\u0005U\u0011qCA\r\u0003#q1\u0001IA\f\u0013\r\t\tbC\u0019\u0006E\u0001Z\u00111\u0004\u0002\u0007g&\u0014X-^7)\t\u0001q\u00181\u0001
   #9 = Utf8               sortWith
  #10 = Utf8               (Lorg/sireum/MS;Lscala/Function2;)Lorg/sireum/MS;
  #11 = Utf8               <T:Ljava/lang/Object;>(Lorg/sireum/MS<Lorg/sireum/Z;TT;>;Lscala/Function2<TT;TT;Lorg/sireum/B;>;)Lorg/sireum/MS<Lorg/sireum/Z;TT;>;
  #12 = Utf8               s
  #13 = Utf8               lt
  #14 = Utf8               org/sireum/ops/MSZOpsUtil$
  #15 = Class              #14            // org/sireum/ops/MSZOpsUtil$
  #16 = Utf8               MODULE$
  #17 = Utf8               Lorg/sireum/ops/MSZOpsUtil$;
  #18 = NameAndType        #16:#17        // MODULE$:Lorg/sireum/ops/MSZOpsUtil$;
  #19 = Fieldref           #15.#18        // org/sireum/ops/MSZOpsUtil$.MODULE$:Lorg/sireum/ops/MSZOpsUtil$;
  #20 = NameAndType        #9:#10         // sortWith:(Lorg/sireum/MS;Lscala/Function2;)Lorg/sireum/MS;
  #21 = Methodref          #15.#20        // org/sireum/ops/MSZOpsUtil$.sortWith:(Lorg/sireum/MS;Lscala/Function2;)Lorg/sireum/MS;
  #22 = Utf8               Lorg/sireum/MS;
  #23 = Utf8               Lscala/Function2;
  #24 = Utf8               mParMapCores
  #25 = Utf8               (Lorg/sireum/MS;Lscala/Function1;Lorg/sireum/Z;)Lorg/sireum/MS;
  #26 = Utf8               <V:Ljava/lang/Object;U:Ljava/lang/Object;>(Lorg/sireum/MS<Lorg/sireum/Z;TV;>;Lscala/Function1<TV;TU;>;Lorg/sireum/Z;)Lorg/sireum/MS<Lorg/sireum/Z;TU;>;
  #27 = Utf8               f
  #28 = Utf8               numOfCores
  #29 = NameAndType        #24:#25        // mParMapCores:(Lorg/sireum/MS;Lscala/Function1;Lorg/sireum/Z;)Lorg/sireum/MS;
  #30 = Methodref          #15.#29        // org/sireum/ops/MSZOpsUtil$.mParMapCores:(Lorg/sireum/MS;Lscala/Function1;Lorg/sireum/Z;)Lorg/sireum/MS;
  #31 = Utf8               Lscala/Function1;
  #32 = Utf8               Lorg/sireum/Z;
  #33 = Utf8               parMapCores
  #34 = NameAndType        #33:#25        // parMapCores:(Lorg/sireum/MS;Lscala/Function1;Lorg/sireum/Z;)Lorg/sireum/MS;
  #35 = Methodref          #15.#34        // org/sireum/ops/MSZOpsUtil$.parMapCores:(Lorg/sireum/MS;Lscala/Function1;Lorg/sireum/Z;)Lorg/sireum/MS;
  #36 = Utf8               mParMap
  #37 = Utf8               (Lorg/sireum/MS;Lscala/Function1;)Lorg/sireum/MS;
  #38 = Utf8               <V:Ljava/lang/Object;U:Ljava/lang/Object;>(Lorg/sireum/MS<Lorg/sireum/Z;TV;>;Lscala/Function1<TV;TU;>;)Lorg/sireum/MS<Lorg/sireum/Z;TU;>;
  #39 = NameAndType        #36:#37        // mParMap:(Lorg/sireum/MS;Lscala/Function1;)Lorg/sireum/MS;
  #40 = Methodref          #15.#39        // org/sireum/ops/MSZOpsUtil$.mParMap:(Lorg/sireum/MS;Lscala/Function1;)Lorg/sireum/MS;
  #41 = Utf8               parMap
  #42 = NameAndType        #41:#37        // parMap:(Lorg/sireum/MS;Lscala/Function1;)Lorg/sireum/MS;
  #43 = Methodref          #15.#42        // org/sireum/ops/MSZOpsUtil$.parMap:(Lorg/sireum/MS;Lscala/Function1;)Lorg/sireum/MS;
  #44 = Utf8               Code
  #45 = Utf8               LocalVariableTable
  #46 = Utf8               Signature
  #47 = Utf8               MethodParameters
  #48 = Utf8               SourceFile
  #49 = Utf8               RuntimeVisibleAnnotations
  #50 = Utf8               ScalaSig
{
  public static <T extends java.lang.Object> org.sireum.MS<org.sireum.Z, T> sortWith(org.sireum.MS<org.sireum.Z, T>, scala.Function2<T, T, org.sireum.B>);
    descriptor: (Lorg/sireum/MS;Lscala/Function2;)Lorg/sireum/MS;
    flags: (0x0009) ACC_PUBLIC, ACC_STATIC
    Code:
      stack=3, locals=2, args_size=2
         0: getstatic     #19                 // Field org/sireum/ops/MSZOpsUtil$.MODULE$:Lorg/sireum/ops/MSZOpsUtil$;
         3: aload_0
         4: aload_1
         5: invokevirtual #21                 // Method org/sireum/ops/MSZOpsUtil$.sortWith:(Lorg/sireum/MS;Lscala/Function2;)Lorg/sireum/MS;
         8: areturn
      LocalVariableTable:
        Start  Length  Slot  Name   Signature
            0       9     0     s   Lorg/sireum/MS;
            0       9     1    lt   Lscala/Function2;
    Signature: #11                          // <T:Ljava/lang/Object;>(Lorg/sireum/MS<Lorg/sireum/Z;TT;>;Lscala/Function2<TT;TT;Lorg/sireum/B;>;)Lorg/sireum/MS<Lorg/sireum/Z;TT;>;
    MethodParameters:
      Name                           Flags
      s                              final
      lt                             final

  public static <V extends java.lang.Object, U extends java.lang.Object> org.sireum.MS<org.sireum.Z, U> mParMapCores(org.sireum.MS<org.sireum.Z, V>, scala.Function1<V, U>, org.sireum.Z);
    descriptor: (Lorg/sireum/MS;Lscala/Function1;Lorg/sireum/Z;)Lorg/sireum/MS;
    flags: (0x0009) ACC_PUBLIC, ACC_STATIC
    Code:
      stack=4, locals=3, args_size=3
         0: getstatic     #19                 // Field org/sireum/ops/MSZOpsUtil$.MODULE$:Lorg/sireum/ops/MSZOpsUtil$;
         3: aload_0
         4: aload_1
         5: aload_2
         6: invokevirtual #30                 // Method org/sireum/ops/MSZOpsUtil$.mParMapCores:(Lorg/sireum/MS;Lscala/Function1;Lorg/sireum/Z;)Lorg/sireum/MS;
         9: areturn
      LocalVariableTable:
        Start  Length  Slot  Name   Signature
            0      10     0     s   Lorg/sireum/MS;
            0      10     1     f   Lscala/Function1;
            0      10     2 numOfCores   Lorg/sireum/Z;
    Signature: #26                          // <V:Ljava/lang/Object;U:Ljava/lang/Object;>(Lorg/sireum/MS<Lorg/sireum/Z;TV;>;Lscala/Function1<TV;TU;>;Lorg/sireum/Z;)Lorg/sireum/MS<Lorg/sireum/Z;TU;>;
    MethodParameters:
      Name                           Flags
      s                              final
      f                              final
      numOfCores                     final

  public static <V extends java.lang.Object, U extends java.lang.Object> org.sireum.MS<org.sireum.Z, U> parMapCores(org.sireum.MS<org.sireum.Z, V>, scala.Function1<V, U>, org.sireum.Z);
    descriptor: (Lorg/sireum/MS;Lscala/Function1;Lorg/sireum/Z;)Lorg/sireum/MS;
    flags: (0x0009) ACC_PUBLIC, ACC_STATIC
    Code:
      stack=4, locals=3, args_size=3
         0: getstatic     #19                 // Field org/sireum/ops/MSZOpsUtil$.MODULE$:Lorg/sireum/ops/MSZOpsUtil$;
         3: aload_0
         4: aload_1
         5: aload_2
         6: invokevirtual #35                 // Method org/sireum/ops/MSZOpsUtil$.parMapCores:(Lorg/sireum/MS;Lscala/Function1;Lorg/sireum/Z;)Lorg/sireum/MS;
         9: areturn
      LocalVariableTable:
        Start  Length  Slot  Name   Signature
            0      10     0     s   Lorg/sireum/MS;
            0      10     1     f   Lscala/Function1;
            0      10     2 numOfCores   Lorg/sireum/Z;
    Signature: #26                          // <V:Ljava/lang/Object;U:Ljava/lang/Object;>(Lorg/sireum/MS<Lorg/sireum/Z;TV;>;Lscala/Function1<TV;TU;>;Lorg/sireum/Z;)Lorg/sireum/MS<Lorg/sireum/Z;TU;>;
    MethodParameters:
      Name                           Flags
      s                              final
      f                              final
      numOfCores                     final

  public static <V extends java.lang.Object, U extends java.lang.Object> org.sireum.MS<org.sireum.Z, U> mParMap(org.sireum.MS<org.sireum.Z, V>, scala.Function1<V, U>);
    descriptor: (Lorg/sireum/MS;Lscala/Function1;)Lorg/sireum/MS;
    flags: (0x0009) ACC_PUBLIC, ACC_STATIC
    Code:
      stack=3, locals=2, args_size=2
         0: getstatic     #19                 // Field org/sireum/ops/MSZOpsUtil$.MODULE$:Lorg/sireum/ops/MSZOpsUtil$;
         3: aload_0
         4: aload_1
         5: invokevirtual #40                 // Method org/sireum/ops/MSZOpsUtil$.mParMap:(Lorg/sireum/MS;Lscala/Function1;)Lorg/sireum/MS;
         8: areturn
      LocalVariableTable:
        Start  Length  Slot  Name   Signature
            0       9     0     s   Lorg/sireum/MS;
            0       9     1     f   Lscala/Function1;
    Signature: #38                          // <V:Ljava/lang/Object;U:Ljava/lang/Object;>(Lorg/sireum/MS<Lorg/sireum/Z;TV;>;Lscala/Function1<TV;TU;>;)Lorg/sireum/MS<Lorg/sireum/Z;TU;>;
    MethodParameters:
      Name                           Flags
      s                              final
      f                              final

  public static <V extends java.lang.Object, U extends java.lang.Object> org.sireum.MS<org.sireum.Z, U> parMap(org.sireum.MS<org.sireum.Z, V>, scala.Function1<V, U>);
    descriptor: (Lorg/sireum/MS;Lscala/Function1;)Lorg/sireum/MS;
    flags: (0x0009) ACC_PUBLIC, ACC_STATIC
    Code:
      stack=3, locals=2, args_size=2
         0: getstatic     #19                 // Field org/sireum/ops/MSZOpsUtil$.MODULE$:Lorg/sireum/ops/MSZOpsUtil$;
         3: aload_0
         4: aload_1
         5: invokevirtual #43                 // Method org/sireum/ops/MSZOpsUtil$.parMap:(Lorg/sireum/MS;Lscala/Function1;)Lorg/sireum/MS;
         8: areturn
      LocalVariableTable:
        Start  Length  Slot  Name   Signature
            0       9     0     s   Lorg/sireum/MS;
            0       9     1     f   Lscala/Function1;
    Signature: #38                          // <V:Ljava/lang/Object;U:Ljava/lang/Object;>(Lorg/sireum/MS<Lorg/sireum/Z;TV;>;Lscala/Function1<TV;TU;>;)Lorg/sireum/MS<Lorg/sireum/Z;TU;>;
    MethodParameters:
      Name                           Flags
      s                              final
      f                              final
}
SourceFile: "SOps.scala"
RuntimeVisibleAnnotations:
  0: #6(#7=s#8)
    scala.reflect.ScalaSignature(
      bytes="\u0006\u0005\u0005}q!\u0002\u0005\n\u0011\u0003\u0001b!\u0002\n\n\u0011\u0003\u0019\u0002\"\u0002\u000e\u0002\t\u0003Y\u0002\"\u0002\u000f\u0002\t\u0003i\u0002\"\u0002\"\u0002\t\u0003\u0019\u0005\"\u0002(\u0002\t\u0003y\u0005\"\u00020\u0002\t\u0003y\u0006\"B6\u0002\t\u0003a\u0017AC\'T5>\u00038/\u0016;jY*\u0011!bC\u0001\u0004_B\u001c(B\u0001\u0007\u000e\u0003\u0019\u0019\u0018N]3v[*\ta\"A\u0002pe\u001e\u001c\u0001\u0001\u0005\u0002\u0012\u00035\t\u0011B\u0001\u0006N\'j{\u0005o]+uS2\u001c\"!\u0001\u000b\u0011\u0005UAR\"\u0001\f\u000b\u0003]\tQa]2bY\u0006L!!\u0007\f\u0003\r\u0005s\u0017PU3g\u0003\u0019a\u0014N\\5u}Q\t\u0001#\u0001\u0004qCJl\u0015\r]\u000b\u0004=UBCcA\u00102oA!\u0001%I\u0012\'\u001b\u0005Y\u0011B\u0001\u0012\f\u0005\ti5\u000b\u0005\u0002!I%\u0011Qe\u0003\u0002\u00025B\u0011q\u0005\u000b\u0007\u0001\t\u0015I3A1\u0001+\u0005\u0005)\u0016CA\u0016/!\t)B&\u0003\u0002.-\t9aj\u001c;iS:<\u0007CA\u000b0\u0013\t\u0001dCA\u0002B]fDQAM\u0002A\u0002M\n\u0011a\u001d\t\u0005A\u0005\u001aC\u0007\u0005\u0002(k\u0011)ag\u0001b\u0001U\t\ta\u000bC\u00039\u0007\u0001\u0007\u0011(A\u0001g!\u0011)\"\b\u000e\u001f\n\u0005m2\"!\u0003$v]\u000e$\u0018n\u001c82U\t1ShK\u0001?!\t\u0001s(\u0003\u0002A\u0017\t!\u0001/\u001e:fQ\t\u0019a(A\u0004n!\u0006\u0014X*\u00199\u0016\u0007\u0011[u\tF\u0002F\u00112\u0003B\u0001I\u0011$\rB\u0011qe\u0012\u0003\u0006S\u0011\u0011\rA\u000b\u0005\u0006e\u0011\u0001\r!\u0013\t\u0005A\u0005\u001a#\n\u0005\u0002(\u0017\u0012)a\u0007\u0002b\u0001U!)\u0001\b\u0002a\u0001\u001bB!QC\u000f&G\u0003-\u0001\u0018M]\'ba\u000e{\'/Z:\u0016\u0007A;6\u000b\u0006\u0003R)b[\u0006\u0003\u0002\u0011\"GI\u0003\"aJ*\u0005\u000b%*!\u0019\u0001\u0016\t\u000bI*\u0001\u0019A+\u0011\t\u0001\n3E\u0016\t\u0003O]#QAN\u0003C\u0002)BQ\u0001O\u0003A\u0002e\u0003B!\u0006\u001eW5*\u0012!+\u0010\u0005\u00069\u0016\u0001\raI\u0001\u000b]VlwJZ\"pe\u0016\u001c\bFA\u0003?\u00031i\u0007+\u0019:NCB\u001cuN]3t+\r\u0001wm\u0019\u000b\u0005C\u0012D\'\u000e\u0005\u0003!C\r\u0012\u0007CA\u0014d\t\u0015IcA1\u0001+\u0011\u0015\u0011d\u00011\u0001f!\u0011\u0001\u0013e\t4\u0011\u0005\u001d:G!\u0002\u001c\u0007\u0005\u0004Q\u0003\"\u0002\u001d\u0007\u0001\u0004I\u0007\u0003B\u000b;M\nDQ\u0001\u0018\u0004A\u0002\r\n\u0001b]8si^KG\u000f[\u000b\u0003[B$2A\u001c:t!\u0011\u0001\u0013eI8\u0011\u0005\u001d\u0002H!B9\b\u0005\u0004Q#!\u0001+\t\u000bI:\u0001\u0019\u00018\t\u000bQ<\u0001\u0019A;\u0002\u00051$\b#B\u000bw_>D\u0018BA<\u0017\u0005%1UO\\2uS>t\'G\u000b\u0002z{A\u0011\u0001E_\u0005\u0003w.\u0011\u0011A\u0011\u0015\u0003\u000fyBC!\u0001@\u0002\u0004A\u0011\u0001e`\u0005\u0004\u0003\u0003Y!aA3yiFJ1%!\u0002\u0002\f\u0005M\u0011Q\u0002\t\u0004A\u0005\u001d\u0011bAA\u0005\u0017\t11\u000b\u001e:j]\u001eLA!!\u0004\u0002\u0010\u0005YB\u0005\\3tg&t\u0017\u000e\u001e\u0013he\u0016\fG/\u001a:%I\u00164\u0017-\u001e7uIER1!!\u0005\f\u0003\r)\u0007\u0010^\u0019\nG\u0005U\u0011qCA\r\u0003#q1\u0001IA\f\u0013\r\t\tbC\u0019\u0006E\u0001Z\u00111\u0004\u0002\u0007g&\u0014X-^7)\t\u0001q\u00181\u0001"
    )
  ScalaSig: length = 0x3 (unknown attribute)
   05 02 00
