Classfile /Users/mw/Projects/slang-braindump/.jar/jar8/assemble/slang-braindump/assemble/content/scala/annotation/elidable$.class
  Last modified May 29, 2022; size 3374 bytes
  SHA-256 checksum a42e0f3ddf9d15fbf8a9a186685d46e0c9688672efff1e44f39b113874d5a9be
  Compiled from "elidable.scala"
public final class scala.annotation.elidable$
  minor version: 0
  major version: 52
  flags: (0x0031) ACC_PUBLIC, ACC_FINAL, ACC_SUPER
  this_class: #2                          // scala/annotation/elidable$
  super_class: #4                         // java/lang/Object
  interfaces: 0, fields: 2, methods: 15, attributes: 4
Constant pool:
    #1 = Utf8               scala/annotation/elidable$
    #2 = Class              #1            // scala/annotation/elidable$
    #3 = Utf8               java/lang/Object
    #4 = Class              #3            // java/lang/Object
    #5 = Utf8               elidable.scala
    #6 = Utf8               scala/Predef$ArrowAssoc$
    #7 = Class              #6            // scala/Predef$ArrowAssoc$
    #8 = Utf8               scala/Predef
    #9 = Class              #8            // scala/Predef
   #10 = Utf8               ArrowAssoc$
   #11 = Utf8               MODULE$
   #12 = Utf8               Lscala/annotation/elidable$;
   #13 = Utf8               byName
   #14 = Utf8               Lscala/collection/immutable/Map;
   #15 = Utf8               Lscala/collection/immutable/Map<Ljava/lang/String;Ljava/lang/Object;>;
   #16 = Utf8               <clinit>
   #17 = Utf8               ()V
   #18 = Utf8               <init>
   #19 = NameAndType        #18:#17       // "<init>":()V
   #20 = Methodref          #2.#19        // scala/annotation/elidable$."<init>":()V
   #21 = NameAndType        #11:#12       // MODULE$:Lscala/annotation/elidable$;
   #22 = Fieldref           #2.#21        // scala/annotation/elidable$.MODULE$:Lscala/annotation/elidable$;
   #23 = Utf8               scala/Predef$
   #24 = Class              #23           // scala/Predef$
   #25 = Utf8               Lscala/Predef$;
   #26 = NameAndType        #11:#25       // MODULE$:Lscala/Predef$;
   #27 = Fieldref           #24.#26       // scala/Predef$.MODULE$:Lscala/Predef$;
   #28 = Utf8               Map
   #29 = Utf8               ()Lscala/collection/immutable/Map$;
   #30 = NameAndType        #28:#29       // Map:()Lscala/collection/immutable/Map$;
   #31 = Methodref          #24.#30       // scala/Predef$.Map:()Lscala/collection/immutable/Map$;
   #32 = Utf8               scala/runtime/ScalaRunTime$
   #33 = Class              #32           // scala/runtime/ScalaRunTime$
   #34 = Utf8               Lscala/runtime/ScalaRunTime$;
   #35 = NameAndType        #11:#34       // MODULE$:Lscala/runtime/ScalaRunTime$;
   #36 = Fieldref           #33.#35       // scala/runtime/ScalaRunTime$.MODULE$:Lscala/runtime/ScalaRunTime$;
   #37 = Utf8               scala/Tuple2
   #38 = Class              #37           // scala/Tuple2
   #39 = Utf8               Lscala/Predef$ArrowAssoc$;
   #40 = NameAndType        #11:#39       // MODULE$:Lscala/Predef$ArrowAssoc$;
   #41 = Fieldref           #7.#40        // scala/Predef$ArrowAssoc$.MODULE$:Lscala/Predef$ArrowAssoc$;
   #42 = Utf8               FINEST
   #43 = String             #42           // FINEST
   #44 = Utf8               java/lang/Integer
   #45 = Class              #44           // java/lang/Integer
   #46 = Utf8               valueOf
   #47 = Utf8               (I)Ljava/lang/Integer;
   #48 = NameAndType        #46:#47       // valueOf:(I)Ljava/lang/Integer;
   #49 = Methodref          #45.#48       // java/lang/Integer.valueOf:(I)Ljava/lang/Integer;
   #50 = Utf8               (Ljava/lang/Object;Ljava/lang/Object;)V
   #51 = NameAndType        #18:#50       // "<init>":(Ljava/lang/Object;Ljava/lang/Object;)V
   #52 = Methodref          #38.#51       // scala/Tuple2."<init>":(Ljava/lang/Object;Ljava/lang/Object;)V
   #53 = Utf8               FINER
   #54 = String             #53           // FINER
   #55 = Utf8               FINE
   #56 = String             #55           // FINE
   #57 = Utf8               CONFIG
   #58 = String             #57           // CONFIG
   #59 = Utf8               INFO
   #60 = String             #59           // INFO
   #61 = Utf8               WARNING
   #62 = String             #61           // WARNING
   #63 = Utf8               SEVERE
   #64 = String             #63           // SEVERE
   #65 = Utf8               ASSERTION
   #66 = String             #65           // ASSERTION
   #67 = Utf8               ALL
   #68 = String             #67           // ALL
   #69 = Integer            -2147483648
   #70 = Utf8               OFF
   #71 = String             #70           // OFF
   #72 = Integer            2147483647
   #73 = Utf8               MAXIMUM
   #74 = String             #73           // MAXIMUM
   #75 = Utf8               MINIMUM
   #76 = String             #75           // MINIMUM
   #77 = Utf8               wrapRefArray
   #78 = Utf8               ([Ljava/lang/Object;)Lscala/collection/immutable/ArraySeq;
   #79 = NameAndType        #77:#78       // wrapRefArray:([Ljava/lang/Object;)Lscala/collection/immutable/ArraySeq;
   #80 = Methodref          #33.#79       // scala/runtime/ScalaRunTime$.wrapRefArray:([Ljava/lang/Object;)Lscala/collection/immutable/ArraySeq;
   #81 = Utf8               scala/collection/immutable/Map$
   #82 = Class              #81           // scala/collection/immutable/Map$
   #83 = Utf8               from
   #84 = Utf8               (Lscala/collection/IterableOnce;)Lscala/collection/immutable/Map;
   #85 = NameAndType        #83:#84       // from:(Lscala/collection/IterableOnce;)Lscala/collection/immutable/Map;
   #86 = Methodref          #82.#85       // scala/collection/immutable/Map$.from:(Lscala/collection/IterableOnce;)Lscala/collection/immutable/Map;
   #87 = NameAndType        #13:#14       // byName:Lscala/collection/immutable/Map;
   #88 = Fieldref           #2.#87        // scala/annotation/elidable$.byName:Lscala/collection/immutable/Map;
   #89 = Utf8               $minus$greater$extension_$this
   #90 = Utf8               Ljava/lang/Object;
   #91 = Utf8               $minus$greater$extension_y
   #92 = Utf8               apply_this
   #93 = Utf8               Lscala/collection/immutable/Map$;
   #94 = Utf8               apply_elems
   #95 = Utf8               Lscala/collection/immutable/Seq;
   #96 = Utf8               scala/collection/immutable/ArraySeq
   #97 = Class              #96           // scala/collection/immutable/ArraySeq
   #98 = Utf8               ()I
   #99 = Utf8               this
  #100 = Utf8               ()Lscala/collection/immutable/Map;
  #101 = Utf8               ()Lscala/collection/immutable/Map<Ljava/lang/String;Ljava/lang/Object;>;
  #102 = Methodref          #4.#19        // java/lang/Object."<init>":()V
  #103 = Utf8               Signature
  #104 = Utf8               Code
  #105 = Utf8               StackMapTable
  #106 = Utf8               LineNumberTable
  #107 = Utf8               LocalVariableTable
  #108 = Utf8               InnerClasses
  #109 = Utf8               SourceFile
  #110 = Utf8               ScalaInlineInfo
  #111 = Utf8               Scala
{
  public static final scala.annotation.elidable$ MODULE$;
    descriptor: Lscala/annotation/elidable$;
    flags: (0x0019) ACC_PUBLIC, ACC_STATIC, ACC_FINAL

  private static final scala.collection.immutable.Map<java.lang.String, java.lang.Object> byName;
    descriptor: Lscala/collection/immutable/Map;
    flags: (0x001a) ACC_PRIVATE, ACC_STATIC, ACC_FINAL
    Signature: #15                          // Lscala/collection/immutable/Map<Ljava/lang/String;Ljava/lang/Object;>;

  public static {};
    descriptor: ()V
    flags: (0x0009) ACC_PUBLIC, ACC_STATIC
    Code:
      stack=9, locals=38, args_size=0
         0: new           #2                  // class scala/annotation/elidable$
         3: dup
         4: invokespecial #20                 // Method "<init>":()V
         7: putstatic     #22                 // Field MODULE$:Lscala/annotation/elidable$;
        10: getstatic     #27                 // Field scala/Predef$.MODULE$:Lscala/Predef$;
        13: invokevirtual #31                 // Method scala/Predef$.Map:()Lscala/collection/immutable/Map$;
        16: getstatic     #36                 // Field scala/runtime/ScalaRunTime$.MODULE$:Lscala/runtime/ScalaRunTime$;
        19: bipush        12
        21: anewarray     #38                 // class scala/Tuple2
        24: dup
        25: iconst_0
        26: getstatic     #41                 // Field scala/Predef$ArrowAssoc$.MODULE$:Lscala/Predef$ArrowAssoc$;
        29: pop
        30: ldc           #43                 // String FINEST
        32: sipush        300
        35: invokestatic  #49                 // Method java/lang/Integer.valueOf:(I)Ljava/lang/Integer;
        38: astore        26
        40: aload         26
        42: aconst_null
        43: astore        26
        45: astore_1
        46: astore_0
        47: new           #38                 // class scala/Tuple2
        50: dup
        51: aload_0
        52: aload_1
        53: invokespecial #52                 // Method scala/Tuple2."<init>":(Ljava/lang/Object;Ljava/lang/Object;)V
        56: aconst_null
        57: astore_0
        58: aconst_null
        59: astore_1
        60: aastore
        61: dup
        62: iconst_1
        63: getstatic     #41                 // Field scala/Predef$ArrowAssoc$.MODULE$:Lscala/Predef$ArrowAssoc$;
        66: pop
        67: ldc           #54                 // String FINER
        69: sipush        400
        72: invokestatic  #49                 // Method java/lang/Integer.valueOf:(I)Ljava/lang/Integer;
        75: astore        27
        77: aload         27
        79: aconst_null
        80: astore        27
        82: astore_3
        83: astore_2
        84: new           #38                 // class scala/Tuple2
        87: dup
        88: aload_2
        89: aload_3
        90: invokespecial #52                 // Method scala/Tuple2."<init>":(Ljava/lang/Object;Ljava/lang/Object;)V
        93: aconst_null
        94: astore_2
        95: aconst_null
        96: astore_3
        97: aastore
        98: dup
        99: iconst_2
       100: getstatic     #41                 // Field scala/Predef$ArrowAssoc$.MODULE$:Lscala/Predef$ArrowAssoc$;
       103: pop
       104: ldc           #56                 // String FINE
       106: sipush        500
       109: invokestatic  #49                 // Method java/lang/Integer.valueOf:(I)Ljava/lang/Integer;
       112: astore        28
       114: aload         28
       116: aconst_null
       117: astore        28
       119: astore        5
       121: astore        4
       123: new           #38                 // class scala/Tuple2
       126: dup
       127: aload         4
       129: aload         5
       131: invokespecial #52                 // Method scala/Tuple2."<init>":(Ljava/lang/Object;Ljava/lang/Object;)V
       134: aconst_null
       135: astore        4
       137: aconst_null
       138: astore        5
       140: aastore
       141: dup
       142: iconst_3
       143: getstatic     #41                 // Field scala/Predef$ArrowAssoc$.MODULE$:Lscala/Predef$ArrowAssoc$;
       146: pop
       147: ldc           #58                 // String CONFIG
       149: sipush        700
       152: invokestatic  #49                 // Method java/lang/Integer.valueOf:(I)Ljava/lang/Integer;
       155: astore        29
       157: aload         29
       159: aconst_null
       160: astore        29
       162: astore        7
       164: astore        6
       166: new           #38                 // class scala/Tuple2
       169: dup
       170: aload         6
       172: aload         7
       174: invokespecial #52                 // Method scala/Tuple2."<init>":(Ljava/lang/Object;Ljava/lang/Object;)V
       177: aconst_null
       178: astore        6
       180: aconst_null
       181: astore        7
       183: aastore
       184: dup
       185: iconst_4
       186: getstatic     #41                 // Field scala/Predef$ArrowAssoc$.MODULE$:Lscala/Predef$ArrowAssoc$;
       189: pop
       190: ldc           #60                 // String INFO
       192: sipush        800
       195: invokestatic  #49                 // Method java/lang/Integer.valueOf:(I)Ljava/lang/Integer;
       198: astore        30
       200: aload         30
       202: aconst_null
       203: astore        30
       205: astore        9
       207: astore        8
       209: new           #38                 // class scala/Tuple2
       212: dup
       213: aload         8
       215: aload         9
       217: invokespecial #52                 // Method scala/Tuple2."<init>":(Ljava/lang/Object;Ljava/lang/Object;)V
       220: aconst_null
       221: astore        8
       223: aconst_null
       224: astore        9
       226: aastore
       227: dup
       228: iconst_5
       229: getstatic     #41                 // Field scala/Predef$ArrowAssoc$.MODULE$:Lscala/Predef$ArrowAssoc$;
       232: pop
       233: ldc           #62                 // String WARNING
       235: sipush        900
       238: invokestatic  #49                 // Method java/lang/Integer.valueOf:(I)Ljava/lang/Integer;
       241: astore        31
       243: aload         31
       245: aconst_null
       246: astore        31
       248: astore        11
       250: astore        10
       252: new           #38                 // class scala/Tuple2
       255: dup
       256: aload         10
       258: aload         11
       260: invokespecial #52                 // Method scala/Tuple2."<init>":(Ljava/lang/Object;Ljava/lang/Object;)V
       263: aconst_null
       264: astore        10
       266: aconst_null
       267: astore        11
       269: aastore
       270: dup
       271: bipush        6
       273: getstatic     #41                 // Field scala/Predef$ArrowAssoc$.MODULE$:Lscala/Predef$ArrowAssoc$;
       276: pop
       277: ldc           #64                 // String SEVERE
       279: sipush        1000
       282: invokestatic  #49                 // Method java/lang/Integer.valueOf:(I)Ljava/lang/Integer;
       285: astore        32
       287: aload         32
       289: aconst_null
       290: astore        32
       292: astore        13
       294: astore        12
       296: new           #38                 // class scala/Tuple2
       299: dup
       300: aload         12
       302: aload         13
       304: invokespecial #52                 // Method scala/Tuple2."<init>":(Ljava/lang/Object;Ljava/lang/Object;)V
       307: aconst_null
       308: astore        12
       310: aconst_null
       311: astore        13
       313: aastore
       314: dup
       315: bipush        7
       317: getstatic     #41                 // Field scala/Predef$ArrowAssoc$.MODULE$:Lscala/Predef$ArrowAssoc$;
       320: pop
       321: ldc           #66                 // String ASSERTION
       323: sipush        2000
       326: invokestatic  #49                 // Method java/lang/Integer.valueOf:(I)Ljava/lang/Integer;
       329: astore        33
       331: aload         33
       333: aconst_null
       334: astore        33
       336: astore        15
       338: astore        14
       340: new           #38                 // class scala/Tuple2
       343: dup
       344: aload         14
       346: aload         15
       348: invokespecial #52                 // Method scala/Tuple2."<init>":(Ljava/lang/Object;Ljava/lang/Object;)V
       351: aconst_null
       352: astore        14
       354: aconst_null
       355: astore        15
       357: aastore
       358: dup
       359: bipush        8
       361: getstatic     #41                 // Field scala/Predef$ArrowAssoc$.MODULE$:Lscala/Predef$ArrowAssoc$;
       364: pop
       365: ldc           #68                 // String ALL
       367: ldc           #69                 // int -2147483648
       369: invokestatic  #49                 // Method java/lang/Integer.valueOf:(I)Ljava/lang/Integer;
       372: astore        34
       374: aload         34
       376: aconst_null
       377: astore        34
       379: astore        17
       381: astore        16
       383: new           #38                 // class scala/Tuple2
       386: dup
       387: aload         16
       389: aload         17
       391: invokespecial #52                 // Method scala/Tuple2."<init>":(Ljava/lang/Object;Ljava/lang/Object;)V
       394: aconst_null
       395: astore        16
       397: aconst_null
       398: astore        17
       400: aastore
       401: dup
       402: bipush        9
       404: getstatic     #41                 // Field scala/Predef$ArrowAssoc$.MODULE$:Lscala/Predef$ArrowAssoc$;
       407: pop
       408: ldc           #71                 // String OFF
       410: ldc           #72                 // int 2147483647
       412: invokestatic  #49                 // Method java/lang/Integer.valueOf:(I)Ljava/lang/Integer;
       415: astore        35
       417: aload         35
       419: aconst_null
       420: astore        35
       422: astore        19
       424: astore        18
       426: new           #38                 // class scala/Tuple2
       429: dup
       430: aload         18
       432: aload         19
       434: invokespecial #52                 // Method scala/Tuple2."<init>":(Ljava/lang/Object;Ljava/lang/Object;)V
       437: aconst_null
       438: astore        18
       440: aconst_null
       441: astore        19
       443: aastore
       444: dup
       445: bipush        10
       447: getstatic     #41                 // Field scala/Predef$ArrowAssoc$.MODULE$:Lscala/Predef$ArrowAssoc$;
       450: pop
       451: ldc           #74                 // String MAXIMUM
       453: ldc           #72                 // int 2147483647
       455: invokestatic  #49                 // Method java/lang/Integer.valueOf:(I)Ljava/lang/Integer;
       458: astore        36
       460: aload         36
       462: aconst_null
       463: astore        36
       465: astore        21
       467: astore        20
       469: new           #38                 // class scala/Tuple2
       472: dup
       473: aload         20
       475: aload         21
       477: invokespecial #52                 // Method scala/Tuple2."<init>":(Ljava/lang/Object;Ljava/lang/Object;)V
       480: aconst_null
       481: astore        20
       483: aconst_null
       484: astore        21
       486: aastore
       487: dup
       488: bipush        11
       490: getstatic     #41                 // Field scala/Predef$ArrowAssoc$.MODULE$:Lscala/Predef$ArrowAssoc$;
       493: pop
       494: ldc           #76                 // String MINIMUM
       496: ldc           #69                 // int -2147483648
       498: invokestatic  #49                 // Method java/lang/Integer.valueOf:(I)Ljava/lang/Integer;
       501: astore        37
       503: aload         37
       505: aconst_null
       506: astore        37
       508: astore        23
       510: astore        22
       512: new           #38                 // class scala/Tuple2
       515: dup
       516: aload         22
       518: aload         23
       520: invokespecial #52                 // Method scala/Tuple2."<init>":(Ljava/lang/Object;Ljava/lang/Object;)V
       523: aconst_null
       524: astore        22
       526: aconst_null
       527: astore        23
       529: aastore
       530: invokevirtual #80                 // Method scala/runtime/ScalaRunTime$.wrapRefArray:([Ljava/lang/Object;)Lscala/collection/immutable/ArraySeq;
       533: astore        25
       535: astore        24
       537: aload         24
       539: ifnonnull     544
       542: aconst_null
       543: athrow
       544: aload         24
       546: aload         25
       548: invokevirtual #86                 // Method scala/collection/immutable/Map$.from:(Lscala/collection/IterableOnce;)Lscala/collection/immutable/Map;
       551: putstatic     #88                 // Field byName:Lscala/collection/immutable/Map;
       554: return
      StackMapTable: number_of_entries = 1
        frame_type = 255 /* full_frame */
          offset_delta = 544
          locals = [ null, null, null, null, null, null, null, null, null, null, null, null, null, null, null, null, null, null, null, null, null, null, null, null, class scala/collection/immutable/Map$, class scala/collection/immutable/ArraySeq, null, null, null, null, null, null, null, null, null, null, null, null ]
          stack = []
      LineNumberTable:
        line 90: 0
        line 119: 10
        line 120: 30
        line 121: 67
        line 122: 104
        line 123: 147
        line 124: 190
        line 125: 233
        line 126: 277
        line 127: 321
        line 128: 365
        line 129: 408
        line 130: 451
        line 131: 494
        line 119: 551
        line 90: 554
      LocalVariableTable:
        Start  Length  Slot  Name   Signature
           47       9     0 $minus$greater$extension_$this   Ljava/lang/Object;
           47       9     1 $minus$greater$extension_y   Ljava/lang/Object;
           84       9     2 $minus$greater$extension_$this   Ljava/lang/Object;
           84       9     3 $minus$greater$extension_y   Ljava/lang/Object;
          123      11     4 $minus$greater$extension_$this   Ljava/lang/Object;
          123      11     5 $minus$greater$extension_y   Ljava/lang/Object;
          166      11     6 $minus$greater$extension_$this   Ljava/lang/Object;
          166      11     7 $minus$greater$extension_y   Ljava/lang/Object;
          209      11     8 $minus$greater$extension_$this   Ljava/lang/Object;
          209      11     9 $minus$greater$extension_y   Ljava/lang/Object;
          252      11    10 $minus$greater$extension_$this   Ljava/lang/Object;
          252      11    11 $minus$greater$extension_y   Ljava/lang/Object;
          296      11    12 $minus$greater$extension_$this   Ljava/lang/Object;
          296      11    13 $minus$greater$extension_y   Ljava/lang/Object;
          340      11    14 $minus$greater$extension_$this   Ljava/lang/Object;
          340      11    15 $minus$greater$extension_y   Ljava/lang/Object;
          383      11    16 $minus$greater$extension_$this   Ljava/lang/Object;
          383      11    17 $minus$greater$extension_y   Ljava/lang/Object;
          426      11    18 $minus$greater$extension_$this   Ljava/lang/Object;
          426      11    19 $minus$greater$extension_y   Ljava/lang/Object;
          469      11    20 $minus$greater$extension_$this   Ljava/lang/Object;
          469      11    21 $minus$greater$extension_y   Ljava/lang/Object;
          512      11    22 $minus$greater$extension_$this   Ljava/lang/Object;
          512      11    23 $minus$greater$extension_y   Ljava/lang/Object;
          537      14    24 apply_this   Lscala/collection/immutable/Map$;
          537      14    25 apply_elems   Lscala/collection/immutable/Seq;

  public final int ALL();
    descriptor: ()I
    flags: (0x0011) ACC_PUBLIC, ACC_FINAL
    Code:
      stack=1, locals=1, args_size=1
         0: ldc           #69                 // int -2147483648
         2: ireturn
      LocalVariableTable:
        Start  Length  Slot  Name   Signature
            0       3     0  this   Lscala/annotation/elidable$;

  public final int FINEST();
    descriptor: ()I
    flags: (0x0011) ACC_PUBLIC, ACC_FINAL
    Code:
      stack=1, locals=1, args_size=1
         0: sipush        300
         3: ireturn
      LocalVariableTable:
        Start  Length  Slot  Name   Signature
            0       4     0  this   Lscala/annotation/elidable$;

  public final int FINER();
    descriptor: ()I
    flags: (0x0011) ACC_PUBLIC, ACC_FINAL
    Code:
      stack=1, locals=1, args_size=1
         0: sipush        400
         3: ireturn
      LocalVariableTable:
        Start  Length  Slot  Name   Signature
            0       4     0  this   Lscala/annotation/elidable$;

  public final int FINE();
    descriptor: ()I
    flags: (0x0011) ACC_PUBLIC, ACC_FINAL
    Code:
      stack=1, locals=1, args_size=1
         0: sipush        500
         3: ireturn
      LocalVariableTable:
        Start  Length  Slot  Name   Signature
            0       4     0  this   Lscala/annotation/elidable$;

  public final int CONFIG();
    descriptor: ()I
    flags: (0x0011) ACC_PUBLIC, ACC_FINAL
    Code:
      stack=1, locals=1, args_size=1
         0: sipush        700
         3: ireturn
      LocalVariableTable:
        Start  Length  Slot  Name   Signature
            0       4     0  this   Lscala/annotation/elidable$;

  public final int INFO();
    descriptor: ()I
    flags: (0x0011) ACC_PUBLIC, ACC_FINAL
    Code:
      stack=1, locals=1, args_size=1
         0: sipush        800
         3: ireturn
      LocalVariableTable:
        Start  Length  Slot  Name   Signature
            0       4     0  this   Lscala/annotation/elidable$;

  public final int WARNING();
    descriptor: ()I
    flags: (0x0011) ACC_PUBLIC, ACC_FINAL
    Code:
      stack=1, locals=1, args_size=1
         0: sipush        900
         3: ireturn
      LocalVariableTable:
        Start  Length  Slot  Name   Signature
            0       4     0  this   Lscala/annotation/elidable$;

  public final int SEVERE();
    descriptor: ()I
    flags: (0x0011) ACC_PUBLIC, ACC_FINAL
    Code:
      stack=1, locals=1, args_size=1
         0: sipush        1000
         3: ireturn
      LocalVariableTable:
        Start  Length  Slot  Name   Signature
            0       4     0  this   Lscala/annotation/elidable$;

  public final int OFF();
    descriptor: ()I
    flags: (0x0011) ACC_PUBLIC, ACC_FINAL
    Code:
      stack=1, locals=1, args_size=1
         0: ldc           #72                 // int 2147483647
         2: ireturn
      LocalVariableTable:
        Start  Length  Slot  Name   Signature
            0       3     0  this   Lscala/annotation/elidable$;

  public final int MAXIMUM();
    descriptor: ()I
    flags: (0x0011) ACC_PUBLIC, ACC_FINAL
    Code:
      stack=1, locals=1, args_size=1
         0: ldc           #72                 // int 2147483647
         2: ireturn
      LocalVariableTable:
        Start  Length  Slot  Name   Signature
            0       3     0  this   Lscala/annotation/elidable$;

  public final int MINIMUM();
    descriptor: ()I
    flags: (0x0011) ACC_PUBLIC, ACC_FINAL
    Code:
      stack=1, locals=1, args_size=1
         0: ldc           #69                 // int -2147483648
         2: ireturn
      LocalVariableTable:
        Start  Length  Slot  Name   Signature
            0       3     0  this   Lscala/annotation/elidable$;

  public final int ASSERTION();
    descriptor: ()I
    flags: (0x0011) ACC_PUBLIC, ACC_FINAL
    Code:
      stack=1, locals=1, args_size=1
         0: sipush        2000
         3: ireturn
      LocalVariableTable:
        Start  Length  Slot  Name   Signature
            0       4     0  this   Lscala/annotation/elidable$;

  public scala.collection.immutable.Map<java.lang.String, java.lang.Object> byName();
    descriptor: ()Lscala/collection/immutable/Map;
    flags: (0x0001) ACC_PUBLIC
    Code:
      stack=1, locals=1, args_size=1
         0: getstatic     #88                 // Field byName:Lscala/collection/immutable/Map;
         3: areturn
      LineNumberTable:
        line 119: 0
      LocalVariableTable:
        Start  Length  Slot  Name   Signature
            0       4     0  this   Lscala/annotation/elidable$;
    Signature: #101                         // ()Lscala/collection/immutable/Map<Ljava/lang/String;Ljava/lang/Object;>;

  private scala.annotation.elidable$();
    descriptor: ()V
    flags: (0x0002) ACC_PRIVATE
    Code:
      stack=1, locals=1, args_size=1
         0: aload_0
         1: invokespecial #102                // Method java/lang/Object."<init>":()V
         4: return
      LineNumberTable:
        line 90: 0
      LocalVariableTable:
        Start  Length  Slot  Name   Signature
            0       5     0  this   Lscala/annotation/elidable$;
}
InnerClasses:
  public static #10= #7 of #9;            // ArrowAssoc$=class scala/Predef$ArrowAssoc$ of class scala/Predef
SourceFile: "elidable.scala"
  ScalaInlineInfo: length = 0x4A (unknown attribute)
   01 01 00 0E 00 12 00 11 01 00 43 00 62 01 00 41
   00 62 01 00 39 00 62 01 00 37 00 62 01 00 35 00
   62 01 00 2A 00 62 01 00 3B 00 62 01 00 49 00 62
   01 00 4B 00 62 01 00 46 00 62 01 00 3F 00 62 01
   00 3D 00 62 01 00 0D 00 64 01
  Scala: length = 0x0 (unknown attribute)

