Classfile /Users/mw/Projects/slang-braindump/.jar/jar8/assemble/slang-braindump/assemble/content/scala/annotation/implicitAmbiguous.class
  Last modified May 29, 2022; size 878 bytes
  SHA-256 checksum d6cd2ee7b543869dea6980e14910726ae0de74e560771959d421d577a81373e9
  Compiled from "implicitAmbiguous.scala"
public final class scala.annotation.implicitAmbiguous extends scala.annotation.Annotation implements scala.annotation.ConstantAnnotation
  minor version: 0
  major version: 52
  flags: (0x0031) ACC_PUBLIC, ACC_FINAL, ACC_SUPER
  this_class: #2                          // scala/annotation/implicitAmbiguous
  super_class: #4                         // scala/annotation/Annotation
  interfaces: 1, fields: 0, methods: 1, attributes: 4
Constant pool:
   #1 = Utf8               scala/annotation/implicitAmbiguous
   #2 = Class              #1             // scala/annotation/implicitAmbiguous
   #3 = Utf8               scala/annotation/Annotation
   #4 = Class              #3             // scala/annotation/Annotation
   #5 = Utf8               scala/annotation/ConstantAnnotation
   #6 = Class              #5             // scala/annotation/ConstantAnnotation
   #7 = Utf8               implicitAmbiguous.scala
   #8 = Utf8               Lscala/reflect/ScalaSignature;
   #9 = Utf8               bytes
  #10 = Utf8               \u0006\u0005!2Aa\u0001\u0003\u0003\u0013!A\u0011\u0003\u0001B\u0001B\u0003%!\u0003C\u0003\u001e\u0001\u0011\u0005aDA\tj[Bd\u0017nY5u\u00036\u0014\u0017nZ;pkNT!!\u0002\u0004\u0002\u0015\u0005tgn\u001c;bi&|gNC\u0001\b\u0003\u0015\u00198-\u00197b\u0007\u0001\u00192\u0001\u0001\u0006\u000f!\tYA\"D\u0001\u0005\u0013\tiAA\u0001\u0006B]:|G/\u0019;j_:\u0004\"aC\b\n\u0005A!!AE\"p]N$\u0018M\u001c;B]:|G/\u0019;j_:\f1!\\:h!\t\u0019\"D\u0004\u0002\u00151A\u0011QCB\u0007\u0002-)\u0011q\u0003C\u0001\u0007yI|w\u000e\u001e \n\u0005e1\u0011A\u0002)sK\u0012,g-\u0003\u0002\u001c9\t11\u000b\u001e:j]\u001eT!!\u0007\u0004\u0002\rqJg.\u001b;?)\ty\u0002\u0005\u0005\u0002\f\u0001!)\u0011C\u0001a\u0001%!\u0012\u0001A\t\t\u0003G\u0019j\u0011\u0001\n\u0006\u0003K\u0011\tA!\\3uC&\u0011q\u0005\n\u0002\u0007O\u0016$H/\u001a:
  #11 = Utf8               <init>
  #12 = Utf8               (Ljava/lang/String;)V
  #13 = Utf8               msg
  #14 = Utf8               ()V
  #15 = NameAndType        #11:#14        // "<init>":()V
  #16 = Methodref          #4.#15         // scala/annotation/Annotation."<init>":()V
  #17 = Utf8               this
  #18 = Utf8               Lscala/annotation/implicitAmbiguous;
  #19 = Utf8               Ljava/lang/String;
  #20 = Utf8               Code
  #21 = Utf8               LineNumberTable
  #22 = Utf8               LocalVariableTable
  #23 = Utf8               MethodParameters
  #24 = Utf8               SourceFile
  #25 = Utf8               RuntimeVisibleAnnotations
  #26 = Utf8               ScalaInlineInfo
  #27 = Utf8               ScalaSig
{
  public scala.annotation.implicitAmbiguous(java.lang.String);
    descriptor: (Ljava/lang/String;)V
    flags: (0x0001) ACC_PUBLIC
    Code:
      stack=1, locals=2, args_size=2
         0: aload_0
         1: invokespecial #16                 // Method scala/annotation/Annotation."<init>":()V
         4: return
      LineNumberTable:
        line 42: 0
      LocalVariableTable:
        Start  Length  Slot  Name   Signature
            0       5     0  this   Lscala/annotation/implicitAmbiguous;
            0       5     1   msg   Ljava/lang/String;
    MethodParameters:
      Name                           Flags
      msg                            final
}
SourceFile: "implicitAmbiguous.scala"
RuntimeVisibleAnnotations:
  0: #8(#9=s#10)
    scala.reflect.ScalaSignature(
      bytes="\u0006\u0005!2Aa\u0001\u0003\u0003\u0013!A\u0011\u0003\u0001B\u0001B\u0003%!\u0003C\u0003\u001e\u0001\u0011\u0005aDA\tj[Bd\u0017nY5u\u00036\u0014\u0017nZ;pkNT!!\u0002\u0004\u0002\u0015\u0005tgn\u001c;bi&|gNC\u0001\b\u0003\u0015\u00198-\u00197b\u0007\u0001\u00192\u0001\u0001\u0006\u000f!\tYA\"D\u0001\u0005\u0013\tiAA\u0001\u0006B]:|G/\u0019;j_:\u0004\"aC\b\n\u0005A!!AE\"p]N$\u0018M\u001c;B]:|G/\u0019;j_:\f1!\\:h!\t\u0019\"D\u0004\u0002\u00151A\u0011QCB\u0007\u0002-)\u0011q\u0003C\u0001\u0007yI|w\u000e\u001e \n\u0005e1\u0011A\u0002)sK\u0012,g-\u0003\u0002\u001c9\t11\u000b\u001e:j]\u001eT!!\u0007\u0004\u0002\rqJg.\u001b;?)\ty\u0002\u0005\u0005\u0002\f\u0001!)\u0011C\u0001a\u0001%!\u0012\u0001A\t\t\u0003G\u0019j\u0011\u0001\n\u0006\u0003K\u0011\tA!\\3uC&\u0011q\u0005\n\u0002\u0007O\u0016$H/\u001a:"
    )
  ScalaInlineInfo: length = 0x9 (unknown attribute)
   01 01 00 01 00 0B 00 0C 01
  ScalaSig: length = 0x3 (unknown attribute)
   05 02 00
