Classfile /Users/mw/Projects/slang-braindump/.jar/jar8/assemble/slang-braindump/assemble/content/scala/annotation/varargs.class
  Last modified May 29, 2022; size 615 bytes
  SHA-256 checksum 0157d9589d216e636dd61fcbb6f946607b2edccfc53c5f85fd711f54ed34fe35
  Compiled from "varargs.scala"
public final class scala.annotation.varargs extends scala.annotation.Annotation implements scala.annotation.StaticAnnotation
  minor version: 0
  major version: 52
  flags: (0x0031) ACC_PUBLIC, ACC_FINAL, ACC_SUPER
  this_class: #2                          // scala/annotation/varargs
  super_class: #4                         // scala/annotation/Annotation
  interfaces: 1, fields: 0, methods: 1, attributes: 4
Constant pool:
   #1 = Utf8               scala/annotation/varargs
   #2 = Class              #1             // scala/annotation/varargs
   #3 = Utf8               scala/annotation/Annotation
   #4 = Class              #3             // scala/annotation/Annotation
   #5 = Utf8               scala/annotation/StaticAnnotation
   #6 = Class              #5             // scala/annotation/StaticAnnotation
   #7 = Utf8               varargs.scala
   #8 = Utf8               Lscala/reflect/ScalaSignature;
   #9 = Utf8               bytes
  #10 = Utf8               \u0006\u0005M1AAA\u0002\u0003\u0011!)\u0001\u0003\u0001C\u0001#\t9a/\u0019:be\u001e\u001c(B\u0001\u0003\u0006\u0003)\tgN\\8uCRLwN\u001c\u0006\u0002\r\u0005)1oY1mC\u000e\u00011c\u0001\u0001\n\u001bA\u0011!bC\u0007\u0002\u0007%\u0011Ab\u0001\u0002\u000b\u0003:tw\u000e^1uS>t\u0007C\u0001\u0006\u000f\u0013\ty1A\u0001\tTi\u0006$\u0018nY!o]>$\u0018\r^5p]\u00061A(\u001b8jiz\"\u0012A\u0005\t\u0003\u0015\u0001\u0001
  #11 = Utf8               <init>
  #12 = Utf8               ()V
  #13 = NameAndType        #11:#12        // "<init>":()V
  #14 = Methodref          #4.#13         // scala/annotation/Annotation."<init>":()V
  #15 = Utf8               this
  #16 = Utf8               Lscala/annotation/varargs;
  #17 = Utf8               Code
  #18 = Utf8               LineNumberTable
  #19 = Utf8               LocalVariableTable
  #20 = Utf8               SourceFile
  #21 = Utf8               RuntimeVisibleAnnotations
  #22 = Utf8               ScalaInlineInfo
  #23 = Utf8               ScalaSig
{
  public scala.annotation.varargs();
    descriptor: ()V
    flags: (0x0001) ACC_PUBLIC
    Code:
      stack=1, locals=1, args_size=1
         0: aload_0
         1: invokespecial #14                 // Method scala/annotation/Annotation."<init>":()V
         4: return
      LineNumberTable:
        line 19: 0
      LocalVariableTable:
        Start  Length  Slot  Name   Signature
            0       5     0  this   Lscala/annotation/varargs;
}
SourceFile: "varargs.scala"
RuntimeVisibleAnnotations:
  0: #8(#9=s#10)
    scala.reflect.ScalaSignature(
      bytes="\u0006\u0005M1AAA\u0002\u0003\u0011!)\u0001\u0003\u0001C\u0001#\t9a/\u0019:be\u001e\u001c(B\u0001\u0003\u0006\u0003)\tgN\\8uCRLwN\u001c\u0006\u0002\r\u0005)1oY1mC\u000e\u00011c\u0001\u0001\n\u001bA\u0011!bC\u0007\u0002\u0007%\u0011Ab\u0001\u0002\u000b\u0003:tw\u000e^1uS>t\u0007C\u0001\u0006\u000f\u0013\ty1A\u0001\tTi\u0006$\u0018nY!o]>$\u0018\r^5p]\u00061A(\u001b8jiz\"\u0012A\u0005\t\u0003\u0015\u0001\u0001"
    )
  ScalaInlineInfo: length = 0x9 (unknown attribute)
   01 01 00 01 00 0B 00 0C 01
  ScalaSig: length = 0x3 (unknown attribute)
   05 02 00
