Classfile /Users/mw/Projects/slang-braindump/.jar/jar11/assemble/slang-braindump/assemble/content/scala/reflect/ClassTag.class
  Last modified May 29, 2022; size 9642 bytes
  SHA-256 checksum 986738d699e86bbbffa337bacdaa1d5f443d3c746563d12d139cda93d55c0b6c
  Compiled from "ClassTag.scala"
public interface scala.reflect.ClassTag<T extends java.lang.Object> extends scala.reflect.ClassManifestDeprecatedApis<T>, scala.Equals
  minor version: 0
  major version: 52
  flags: (0x0601) ACC_PUBLIC, ACC_INTERFACE, ACC_ABSTRACT
  this_class: #2                          // scala/reflect/ClassTag
  super_class: #5                         // java/lang/Object
  interfaces: 2, fields: 0, methods: 33, attributes: 6
Constant pool:
    #1 = Utf8               scala/reflect/ClassTag
    #2 = Class              #1            // scala/reflect/ClassTag
    #3 = Utf8               <T:Ljava/lang/Object;>Ljava/lang/Object;Lscala/reflect/ClassManifestDeprecatedApis<TT;>;Lscala/Equals;
    #4 = Utf8               java/lang/Object
    #5 = Class              #4            // java/lang/Object
    #6 = Utf8               scala/reflect/ClassManifestDeprecatedApis
    #7 = Class              #6            // scala/reflect/ClassManifestDeprecatedApis
    #8 = Utf8               scala/Equals
    #9 = Class              #8            // scala/Equals
   #10 = Utf8               ClassTag.scala
   #11 = Utf8               Lscala/reflect/ScalaSignature;
   #12 = Utf8               bytes
   #13 = Utf8               \u0006\u0005\r]ba\u0002 @!\u0003\r\t\u0001\u0012\u0005\u0006G\u0002!\t\u0001\u001a\u0005\u0006Q\u00021\t!\u001b\u0005\u0006m\u0002!\ta\u001e\u0005\u0006y\u0002!\t! \u0005\b\u0003\u000f\u0001A\u0011AA\u0005\u0011\u001d\t)\u0002\u0001C!\u0003/Aq!!\t\u0001\t\u0003\n\u0019\u0003C\u0004\u0002(\u0001!\t%!\u000b\t\u000f\u0005-\u0002\u0001\"\u0011\u0002.\u001d9\u0011\u0011L \t\u0002\u0005mcA\u0002 @\u0011\u0003\ti\u0006C\u0004\u0002j-!\t!a\u001b\t\u0011\u000554\u0002)A\u0005\u0003_B\u0001\"a\u001e\fA\u0003%\u0011\u0011\u0010\u0005\t\u0003\u000f[\u0001\u0015!\u0003\u0002\n\"I\u0011\u0011S\u0006C\u0002\u0013\u0005\u00111\u0013\u0005\t\u0003G[\u0001\u0015!\u0003\u0002\u0016\"I\u0011QU\u0006C\u0002\u0013\u0005\u0011q\u0015\u0005\t\u0003_[\u0001\u0015!\u0003\u0002*\"I\u0011\u0011W\u0006C\u0002\u0013\u0005\u00111\u0017\u0005\t\u0003w[\u0001\u0015!\u0003\u00026\"I\u0011QX\u0006C\u0002\u0013\u0005\u0011q\u0018\u0005\t\u0003\u000f\\\u0001\u0015!\u0003\u0002B\"I\u0011\u0011Z\u0006C\u0002\u0013\u0005\u00111\u001a\u0005\t\u0003\'\\\u0001\u0015!\u0003\u0002N\"I\u0011Q[\u0006C\u0002\u0013\u0005\u0011q\u001b\u0005\t\u0003?\\\u0001\u0015!\u0003\u0002Z\"I\u0011\u0011]\u0006C\u0002\u0013\u0005\u00111\u001d\u0005\t\u0003W\\\u0001\u0015!\u0003\u0002f\"I\u0011Q^\u0006C\u0002\u0013\u0005\u0011q\u001e\u0005\t\u0003o\\\u0001\u0015!\u0003\u0002r\"I\u0011\u0011`\u0006C\u0002\u0013\u0005\u00111 \u0005\t\u0005\u0007Y\u0001\u0015!\u0003\u0002~\"I!QA\u0006C\u0002\u0013\u0005!q\u0001\u0005\t\u0005\u0017Y\u0001\u0015!\u0003\u0003\n!I!QB\u0006C\u0002\u0013\u0005!q\u0002\u0005\t\u0005\'Y\u0001\u0015!\u0003\u0003\u0012!I!QC\u0006C\u0002\u0013\u0005!q\u0003\u0005\t\u0005CY\u0001\u0015!\u0003\u0003\u001a!I!1E\u0006C\u0002\u0013\u0005!Q\u0005\u0005\t\u0005SY\u0001\u0015!\u0003\u0003(!I!1F\u0006C\u0002\u0013\u0005!Q\u0006\u0005\t\u0005cY\u0001\u0015!\u0003\u00030!I!1G\u0006C\u0002\u0013\u0005!Q\u0007\u0005\t\u0005\u007fY\u0001\u0015!\u0003\u00038!I!\u0011I\u0006C\u0002\u0013%!1\t\u0005\t\u0005\u000bZ\u0001\u0015!\u0003\u0002\u001a\u001dA!qI\u0006!\u0012\u0013\u0011IE\u0002\u0005\u0003N-\u0001\u000b\u0012\u0002B(\u0011\u001d\tI\'\rC\u0001\u0005[BqAa\u001c2\t\u0003\u0012\t\bC\u0004\u0003\fF\"\tA!$\t\u000f\t\u0015\u0016\u0007\"\u0003\u0003(\u001a1!QY\u0006\u0005\u0005\u000fD\u0011\u0002\u001b\u001c\u0003\u0006\u0004%\tA!5\t\u0015\tugG!A!\u0002\u0013\u0011\u0019\u000eC\u0004\u0002jY\"\tAa8\t\rq4D\u0011\tBw\u0011\u001d\u0011yp\u0003C\u0001\u0007\u0003Aq!a\u0002\f\t\u0003\u0019I\u0002C\u0005\u00044-\t\t\u0011\"\u0003\u00046\tA1\t\\1tgR\u000bwM\u0003\u0002A\u0003\u00069!/\u001a4mK\u000e$(\"\u0001\"\u0002\u000bM\u001c\u0017\r\\1\u0004\u0001U\u0011Q\tU\n\u0006\u0001\u0019S\u0015\f\u0018\t\u0003\u000f\"k\u0011!Q\u0005\u0003\u0013\u0006\u0013a!\u00118z%\u00164\u0007cA&M\u001d6\tq(\u0003\u0002N\u007f\tY2\t\\1tg6\u000bg.\u001b4fgR$U\r\u001d:fG\u0006$X\rZ!qSN\u0004\"a\u0014)\r\u0001\u0011)\u0011\u000b\u0001b\u0001%\n\tA+\u0005\u0002T-B\u0011q\tV\u0005\u0003+\u0006\u0013qAT8uQ&tw\r\u0005\u0002H/&\u0011\u0001,\u0011\u0002\u0004\u0003:L\bCA$[\u0013\tY\u0016I\u0001\u0004FcV\fGn\u001d\t\u0003;\u0002t!a\u00120\n\u0005}\u000b\u0015a\u00029bG.\fw-Z\u0005\u0003C\n\u0014AbU3sS\u0006d\u0017N_1cY\u0016T!aX!\u0002\r\u0011Jg.\u001b;%)\u0005)\u0007CA$g\u0013\t9\u0017I\u0001\u0003V]&$\u0018\u0001\u0004:v]RLW.Z\"mCN\u001cX#\u000161\u0005-$\bc\u00017rg6\tQN\u0003\u0002o_\u0006!A.\u00198h\u0015\u0005\u0001\u0018\u0001\u00026bm\u0006L!A]7\u0003\u000b\rc\u0017m]:\u0011\u0005=#H!C;\u0003\u0003\u0003\u0005\tQ!\u0001S\u0005\ryF%M\u0001\u0005oJ\f\u0007/F\u0001y!\rY\u0005!\u001f\t\u0004\u000fjt\u0015BA>B\u0005\u0015\t%O]1z\u0003!qWm^!se\u0006LHCA=\u007f\u0011\u0019yH\u00011\u0001\u0002\u0002\u0005\u0019A.\u001a8\u0011\u0007\u001d\u000b\u0019!C\u0002\u0002\u0006\u0005\u00131!\u00138u\u0003\u001d)h.\u00199qYf$B!a\u0003\u0002\u0012A!q)!\u0004O\u0013\r\ty!\u0011\u0002\u0007\u001fB$\u0018n\u001c8\t\r\u0005MQ\u00011\u0001W\u0003\u0005A\u0018\u0001C2b]\u0016\u000bX/\u00197\u0015\t\u0005e\u0011q\u0004\t\u0004\u000f\u0006m\u0011bAA\u000f\u0003\n9!i\\8mK\u0006t\u0007BBA\n\r\u0001\u0007a+\u0001\u0004fcV\fGn\u001d\u000b\u0005\u00033\t)\u0003\u0003\u0004\u0002\u0014\u001d\u0001\rAV\u0001\tQ\u0006\u001c\bnQ8eKR\u0011\u0011\u0011A\u0001\ti>\u001cFO]5oOR\u0011\u0011q\u0006\t\u0005\u0003c\tyD\u0004\u0003\u00024\u0005m\u0002cAA\u001b\u00036\u0011\u0011q\u0007\u0006\u0004\u0003s\u0019\u0015A\u0002\u001fs_>$h(C\u0002\u0002>\u0005\u000ba\u0001\u0015:fI\u00164\u0017\u0002BA!\u0003\u0007\u0012aa\u0015;sS:<\'bAA\u001f\u0003\":\u0001!a\u0012\u0002T\u0005U\u0003\u0003BA%\u0003\u001fj!!a\u0013\u000b\u0007\u00055\u0013)\u0001\u0006b]:|G/\u0019;j_:LA!!\u0015\u0002L\t\u0001\u0012.\u001c9mS\u000eLGOT8u\r>,h\u000eZ\u0001\u0004[N<\u0017EAA,\u0003yqu\u000eI\"mCN\u001cH+Y4!CZ\f\u0017\u000e\\1cY\u0016\u0004cm\u001c:!Im$V0\u0001\u0005DY\u0006\u001c8\u000fV1h!\tY5b\u0005\u0003\f\r\u0006}\u0003\u0003BA1\u0003Oj!!a\u0019\u000b\u0007\u0005\u0015t.\u0001\u0002j_&\u0019\u0011-a\u0019\u0002\rqJg.\u001b;?)\t\tY&\u0001\u0006PE*,7\r\u001e+Z!\u0016\u0003B\u0001\\9\u0002rA\u0019A.a\u001d\n\u0007\u0005UTN\u0001\u0004PE*,7\r^\u0001\f\u001d>$\b.\u001b8h)f\u0003V\t\u0005\u0003mc\u0006m\u0004\u0003BA?\u0003\u0007k!!a \u000b\u0007\u0005\u0005\u0015)A\u0004sk:$\u0018.\\3\n\t\u0005\u0015\u0015q\u0010\u0002\t\u001d>$\b.\u001b8hI\u0005Aa*\u001e7m)f\u0003V\t\u0005\u0003mc\u0006-\u0005\u0003BA?\u0003\u001bKA!a$\u0002\u0000\t)a*\u001e7mI\u0005!!)\u001f;f+\t\t)\n\u0005\u0003\u0002\u0018\u0006uebA&\u0002\u001a&\u0019\u00111T \u0002\u001f5\u000bg.\u001b4fgR4\u0015m\u0019;pefLA!a(\u0002\"\na!)\u001f;f\u001b\u0006t\u0017NZ3ti*\u0019\u00111T \u0002\u000b\tKH/\u001a\u0011\u0002\u000bMCwN\u001d;\u0016\u0005\u0005%\u0006\u0003BAL\u0003WKA!!,\u0002\"\ni1\u000b[8si6\u000bg.\u001b4fgR\faa\u00155peR\u0004\u0013\u0001B\"iCJ,\"!!.\u0011\t\u0005]\u0015qW\u0005\u0005\u0003s\u000b\tK\u0001\u0007DQ\u0006\u0014X*\u00198jM\u0016\u001cH/A\u0003DQ\u0006\u0014\b%A\u0002J]R,\"!!1\u0011\t\u0005]\u00151Y\u0005\u0005\u0003\u000b\f\tKA\u0006J]Rl\u0015M\\5gKN$\u0018\u0001B%oi\u0002\nA\u0001T8oOV\u0011\u0011Q\u001a\t\u0005\u0003/\u000by-\u0003\u0003\u0002R\u0006\u0005&\u0001\u0004\'p]\u001el\u0015M\\5gKN$\u0018!\u0002\'p]\u001e\u0004\u0013!\u0002$m_\u0006$XCAAm!\u0011\t9*a7\n\t\u0005u\u0017\u0011\u0015\u0002\u000e\r2|\u0017\r^\'b]&4Wm\u001d;\u0002\r\u0019cw.\u0019;!\u0003\u0019!u.\u001e2mKV\u0011\u0011Q\u001d\t\u0005\u0003/\u000b9/\u0003\u0003\u0002j\u0006\u0005&A\u0004#pk\ndW-T1oS\u001a,7\u000f^\u0001\b\t>,(\r\\3!\u0003\u001d\u0011un\u001c7fC:,\"!!=\u0011\t\u0005]\u00151_\u0005\u0005\u0003k\f\tKA\bC_>dW-\u00198NC:Lg-Z:u\u0003!\u0011un\u001c7fC:\u0004\u0013\u0001B+oSR,\"!!@\u0011\t\u0005]\u0015q`\u0005\u0005\u0005\u0003\t\tK\u0001\u0007V]&$X*\u00198jM\u0016\u001cH/A\u0003V]&$\b%A\u0002B]f,\"A!\u0003\u0011\u0007-\u0003a+\u0001\u0003B]f\u0004\u0013AB(cU\u0016\u001cG/\u0006\u0002\u0003\u0012A!1\nAA9\u0003\u001dy%M[3di\u0002\na!\u00118z-\u0006dWC\u0001B\r!\u0011Y\u0005Aa\u0007\u0011\u0007\u001d\u0013i\"C\u0002\u0003 \u0005\u0013a!\u00118z-\u0006d\u0017aB!osZ\u000bG\u000eI\u0001\u0007\u0003:L(+\u001a4\u0016\u0005\t\u001d\u0002cA&\u0001\r\u00069\u0011I\\=SK\u001a\u0004\u0013a\u0002(pi\"LgnZ\u000b\u0003\u0005_\u00012a\u0013\u0001T\u0003!qu\u000e\u001e5j]\u001e\u0004\u0013\u0001\u0002(vY2,\"Aa\u000e\u0011\t-\u0003!\u0011\b\t\u0004\u000f\nm\u0012b\u0001B\u001f\u0003\n!a*\u001e7m\u0003\u0015qU\u000f\u001c7!\u00035\u0019\u0017m\u00195f\t&\u001c\u0018M\u00197fIV\u0011\u0011\u0011D\u0001\u000fG\u0006\u001c\u0007.\u001a#jg\u0006\u0014G.\u001a3!\u0003\u0015\u0019\u0017m\u00195f!\r\u0011Y%M\u0007\u0002\u0017\t)1-Y2iKN\u0019\u0011G!\u0015\u0011\r\u0005u$1\u000bB,\u0013\u0011\u0011)&a \u0003!\rc\u0017m]:WC2,XmQ8na\u0006$\bC\u0002B-\u0005?\u0012\u0019\'\u0004\u0002\u0003\\)\u0019!QL7\u0002\u0007I,g-\u0003\u0003\u0003b\tm#!D,fC.\u0014VMZ3sK:\u001cW\r\r\u0003\u0003f\t%\u0004\u0003B&\u0001\u0005O\u00022a\u0014B5\t)\u0011Y\'MA\u0001\u0002\u0003\u0015\tA\u0015\u0002\u0004?\u00122DC\u0001B%\u00031\u0019w.\u001c9vi\u00164\u0016\r\\;f)\u0011\u0011\u0019Ha \u0011\r\te#q\fB;a\u0011\u00119Ha\u001f\u0011\t-\u0003!\u0011\u0010\t\u0004\u001f\nmDA\u0003B?g\u0005\u0005\t\u0011!B\u0001%\n\u0019q\f\n\u001d\t\r!\u001c\u0004\u0019\u0001BAa\u0011\u0011\u0019Ia\"\u0011\t1\f(Q\u0011\t\u0004\u001f\n\u001dEa\u0003BE\u0005\u007f\n\t\u0011!A\u0003\u0002I\u00131a\u0018\u00138\u0003)\u0019w.\u001c9vi\u0016$\u0016m\u001a\u000b\u0005\u0005\u001f\u0013I\n\r\u0003\u0003\u0012\nU\u0005\u0003B&\u0001\u0005\'\u00032a\u0014BK\t)\u00119\nNA\u0001\u0002\u0003\u0015\tA\u0015\u0002\u0005?\u0012\n\u0004\u0007\u0003\u0004ii\u0001\u0007!1\u0014\u0019\u0005\u0005;\u0013\t\u000b\u0005\u0003mc\n}\u0005cA(\u0003\"\u0012Y!1\u0015BM\u0003\u0003\u0005\tQ!\u0001S\u0005\ryF%O\u0001\u0012aJLW.\u001b;jm\u0016\u001cE.Y:t)\u0006<W\u0003\u0002BU\u0005\u0007$BAa+\u00036B\"!Q\u0016BY!\u0011Y\u0005Aa,\u0011\u0007=\u0013\t\f\u0002\u0006\u00034V\n\t\u0011!A\u0003\u0002I\u0013Aa\u0018\u00132e!1\u0001.\u000ea\u0001\u0005o\u0003DA!/\u0003@B1\u0011\u0011\u0007B^\u0005{K1A]A\"!\ry%q\u0018\u0003\f\u0005\u0003\u0014),!A\u0001\u0002\u000b\u0005!K\u0001\u0003`IE\nD!B)6\u0005\u0004\u0011&aD$f]\u0016\u0014\u0018nY\"mCN\u001cH+Y4\u0016\t\t%\'qZ\n\u0005m\u0019\u0013Y\r\u0005\u0003L\u0001\t5\u0007cA(\u0003P\u0012)\u0011K\u000eb\u0001%V\u0011!1\u001b\u0019\u0005\u0005+\u0014I\u000e\u0005\u0003mc\n]\u0007cA(\u0003Z\u0012Q!1\u001c\u001d\u0002\u0002\u0003\u0005)\u0011\u0001*\u0003\t}#\u0013gM\u0001\u000eeVtG/[7f\u00072\f7o\u001d\u0011\u0015\t\t\u0005(1\u001d\t\u0006\u0005\u00172$Q\u001a\u0005\u0007Qf\u0002\rA!:1\t\t\u001d(1\u001e\t\u0005YF\u0014I\u000fE\u0002P\u0005W$1Ba7\u0003d\u0006\u0005\t\u0011!B\u0001%R!!q\u001eBy!\u00119%P!4\t\r}T\u0004\u0019AA\u0001Q\u001d1$Q\u001fB~\u0005{\u00042a\u0012B|\u0013\r\u0011I0\u0011\u0002\u0011\'\u0016\u0014\u0018.\u00197WKJ\u001c\u0018n\u001c8V\u0013\u0012\u000bQA^1mk\u0016t\u0012!A\u0001\u0006CB\u0004H._\u000b\u0005\u0007\u0007\u0019I\u0001\u0006\u0003\u0004\u0006\r-\u0001\u0003B&\u0001\u0007\u000f\u00012aTB\u0005\t\u0015\t6H1\u0001S\u0011\u001d\u0019ia\u000fa\u0001\u0007\u001f\tQB];oi&lWm\u00117bgN\f\u0004\u0007BB\t\u0007+\u0001B\u0001\\9\u0004\u0014A\u0019qj!\u0006\u0005\u0017\r]11BA\u0001\u0002\u0003\u0015\tA\u0015\u0002\u0005?\u0012\nD\'\u0006\u0003\u0004\u001c\rEB\u0003BB\u000f\u0007S\u0001RaRA\u0007\u0007?\u0001Da!\t\u0004&A1\u0011\u0011\u0007B^\u0007G\u00012aTB\u0013\t)\u00199\u0003PA\u0001\u0002\u0003\u0015\tA\u0015\u0002\u0005?\u0012\nT\u0007C\u0004\u0004,q\u0002\ra!\f\u0002\t\r$\u0018m\u001a\t\u0005\u0017\u0002\u0019y\u0003E\u0002P\u0007c!Q!\u0015\u001fC\u0002I\u000bAb\u001e:ji\u0016\u0014V\r\u001d7bG\u0016$\"!!\u001d
   #14 = Utf8               scala/reflect/ClassTag$GenericClassTag
   #15 = Class              #14           // scala/reflect/ClassTag$GenericClassTag
   #16 = Utf8               GenericClassTag
   #17 = Utf8               scala/reflect/ClassTag$cache$
   #18 = Class              #17           // scala/reflect/ClassTag$cache$
   #19 = Utf8               cache$
   #20 = Utf8               scala/reflect/ManifestFactory$BooleanManifest
   #21 = Class              #20           // scala/reflect/ManifestFactory$BooleanManifest
   #22 = Utf8               scala/reflect/ManifestFactory
   #23 = Class              #22           // scala/reflect/ManifestFactory
   #24 = Utf8               BooleanManifest
   #25 = Utf8               scala/reflect/ManifestFactory$ByteManifest
   #26 = Class              #25           // scala/reflect/ManifestFactory$ByteManifest
   #27 = Utf8               ByteManifest
   #28 = Utf8               scala/reflect/ManifestFactory$CharManifest
   #29 = Class              #28           // scala/reflect/ManifestFactory$CharManifest
   #30 = Utf8               CharManifest
   #31 = Utf8               scala/reflect/ManifestFactory$DoubleManifest
   #32 = Class              #31           // scala/reflect/ManifestFactory$DoubleManifest
   #33 = Utf8               DoubleManifest
   #34 = Utf8               scala/reflect/ManifestFactory$FloatManifest
   #35 = Class              #34           // scala/reflect/ManifestFactory$FloatManifest
   #36 = Utf8               FloatManifest
   #37 = Utf8               scala/reflect/ManifestFactory$IntManifest
   #38 = Class              #37           // scala/reflect/ManifestFactory$IntManifest
   #39 = Utf8               IntManifest
   #40 = Utf8               scala/reflect/ManifestFactory$LongManifest
   #41 = Class              #40           // scala/reflect/ManifestFactory$LongManifest
   #42 = Utf8               LongManifest
   #43 = Utf8               scala/reflect/ManifestFactory$ShortManifest
   #44 = Class              #43           // scala/reflect/ManifestFactory$ShortManifest
   #45 = Utf8               ShortManifest
   #46 = Utf8               scala/reflect/ManifestFactory$UnitManifest
   #47 = Class              #46           // scala/reflect/ManifestFactory$UnitManifest
   #48 = Utf8               UnitManifest
   #49 = Utf8               apply
   #50 = Utf8               (Ljava/lang/Class;)Lscala/reflect/ClassTag;
   #51 = Utf8               <T:Ljava/lang/Object;>(Ljava/lang/Class<*>;)Lscala/reflect/ClassTag<TT;>;
   #52 = Utf8               runtimeClass1
   #53 = Utf8               scala/reflect/ClassTag$
   #54 = Class              #53           // scala/reflect/ClassTag$
   #55 = Utf8               MODULE$
   #56 = Utf8               Lscala/reflect/ClassTag$;
   #57 = NameAndType        #55:#56       // MODULE$:Lscala/reflect/ClassTag$;
   #58 = Fieldref           #54.#57       // scala/reflect/ClassTag$.MODULE$:Lscala/reflect/ClassTag$;
   #59 = NameAndType        #49:#50       // apply:(Ljava/lang/Class;)Lscala/reflect/ClassTag;
   #60 = Methodref          #54.#59       // scala/reflect/ClassTag$.apply:(Ljava/lang/Class;)Lscala/reflect/ClassTag;
   #61 = Utf8               Ljava/lang/Class;
   #62 = Utf8               Null
   #63 = Utf8               ()Lscala/reflect/ClassTag;
   #64 = Utf8               ()Lscala/reflect/ClassTag<Lscala/runtime/Null$;>;
   #65 = NameAndType        #62:#63       // Null:()Lscala/reflect/ClassTag;
   #66 = Methodref          #54.#65       // scala/reflect/ClassTag$.Null:()Lscala/reflect/ClassTag;
   #67 = Utf8               Nothing
   #68 = Utf8               ()Lscala/reflect/ClassTag<Lscala/runtime/Nothing$;>;
   #69 = NameAndType        #67:#63       // Nothing:()Lscala/reflect/ClassTag;
   #70 = Methodref          #54.#69       // scala/reflect/ClassTag$.Nothing:()Lscala/reflect/ClassTag;
   #71 = Utf8               AnyRef
   #72 = Utf8               ()Lscala/reflect/ClassTag<Ljava/lang/Object;>;
   #73 = NameAndType        #71:#63       // AnyRef:()Lscala/reflect/ClassTag;
   #74 = Methodref          #54.#73       // scala/reflect/ClassTag$.AnyRef:()Lscala/reflect/ClassTag;
   #75 = Utf8               AnyVal
   #76 = NameAndType        #75:#63       // AnyVal:()Lscala/reflect/ClassTag;
   #77 = Methodref          #54.#76       // scala/reflect/ClassTag$.AnyVal:()Lscala/reflect/ClassTag;
   #78 = Utf8               Object
   #79 = NameAndType        #78:#63       // Object:()Lscala/reflect/ClassTag;
   #80 = Methodref          #54.#79       // scala/reflect/ClassTag$.Object:()Lscala/reflect/ClassTag;
   #81 = Utf8               Any
   #82 = NameAndType        #81:#63       // Any:()Lscala/reflect/ClassTag;
   #83 = Methodref          #54.#82       // scala/reflect/ClassTag$.Any:()Lscala/reflect/ClassTag;
   #84 = Utf8               Unit
   #85 = Utf8               ()Lscala/reflect/ManifestFactory$UnitManifest;
   #86 = NameAndType        #84:#85       // Unit:()Lscala/reflect/ManifestFactory$UnitManifest;
   #87 = Methodref          #54.#86       // scala/reflect/ClassTag$.Unit:()Lscala/reflect/ManifestFactory$UnitManifest;
   #88 = Utf8               Boolean
   #89 = Utf8               ()Lscala/reflect/ManifestFactory$BooleanManifest;
   #90 = NameAndType        #88:#89       // Boolean:()Lscala/reflect/ManifestFactory$BooleanManifest;
   #91 = Methodref          #54.#90       // scala/reflect/ClassTag$.Boolean:()Lscala/reflect/ManifestFactory$BooleanManifest;
   #92 = Utf8               Double
   #93 = Utf8               ()Lscala/reflect/ManifestFactory$DoubleManifest;
   #94 = NameAndType        #92:#93       // Double:()Lscala/reflect/ManifestFactory$DoubleManifest;
   #95 = Methodref          #54.#94       // scala/reflect/ClassTag$.Double:()Lscala/reflect/ManifestFactory$DoubleManifest;
   #96 = Utf8               Float
   #97 = Utf8               ()Lscala/reflect/ManifestFactory$FloatManifest;
   #98 = NameAndType        #96:#97       // Float:()Lscala/reflect/ManifestFactory$FloatManifest;
   #99 = Methodref          #54.#98       // scala/reflect/ClassTag$.Float:()Lscala/reflect/ManifestFactory$FloatManifest;
  #100 = Utf8               Long
  #101 = Utf8               ()Lscala/reflect/ManifestFactory$LongManifest;
  #102 = NameAndType        #100:#101     // Long:()Lscala/reflect/ManifestFactory$LongManifest;
  #103 = Methodref          #54.#102      // scala/reflect/ClassTag$.Long:()Lscala/reflect/ManifestFactory$LongManifest;
  #104 = Utf8               Int
  #105 = Utf8               ()Lscala/reflect/ManifestFactory$IntManifest;
  #106 = NameAndType        #104:#105     // Int:()Lscala/reflect/ManifestFactory$IntManifest;
  #107 = Methodref          #54.#106      // scala/reflect/ClassTag$.Int:()Lscala/reflect/ManifestFactory$IntManifest;
  #108 = Utf8               Char
  #109 = Utf8               ()Lscala/reflect/ManifestFactory$CharManifest;
  #110 = NameAndType        #108:#109     // Char:()Lscala/reflect/ManifestFactory$CharManifest;
  #111 = Methodref          #54.#110      // scala/reflect/ClassTag$.Char:()Lscala/reflect/ManifestFactory$CharManifest;
  #112 = Utf8               Short
  #113 = Utf8               ()Lscala/reflect/ManifestFactory$ShortManifest;
  #114 = NameAndType        #112:#113     // Short:()Lscala/reflect/ManifestFactory$ShortManifest;
  #115 = Methodref          #54.#114      // scala/reflect/ClassTag$.Short:()Lscala/reflect/ManifestFactory$ShortManifest;
  #116 = Utf8               Byte
  #117 = Utf8               ()Lscala/reflect/ManifestFactory$ByteManifest;
  #118 = NameAndType        #116:#117     // Byte:()Lscala/reflect/ManifestFactory$ByteManifest;
  #119 = Methodref          #54.#118      // scala/reflect/ClassTag$.Byte:()Lscala/reflect/ManifestFactory$ByteManifest;
  #120 = Utf8               runtimeClass
  #121 = Utf8               ()Ljava/lang/Class;
  #122 = Utf8               ()Ljava/lang/Class<*>;
  #123 = Utf8               wrap$
  #124 = Utf8               (Lscala/reflect/ClassTag;)Lscala/reflect/ClassTag;
  #125 = Utf8               $this
  #126 = Utf8               wrap
  #127 = NameAndType        #126:#63      // wrap:()Lscala/reflect/ClassTag;
  #128 = InterfaceMethodref #2.#127       // scala/reflect/ClassTag.wrap:()Lscala/reflect/ClassTag;
  #129 = Utf8               Lscala/reflect/ClassTag;
  #130 = NameAndType        #120:#121     // runtimeClass:()Ljava/lang/Class;
  #131 = InterfaceMethodref #2.#130       // scala/reflect/ClassTag.runtimeClass:()Ljava/lang/Class;
  #132 = Utf8               arrayClass
  #133 = Utf8               (Ljava/lang/Class;)Ljava/lang/Class;
  #134 = NameAndType        #132:#133     // arrayClass:(Ljava/lang/Class;)Ljava/lang/Class;
  #135 = InterfaceMethodref #2.#134       // scala/reflect/ClassTag.arrayClass:(Ljava/lang/Class;)Ljava/lang/Class;
  #136 = Utf8               this
  #137 = Utf8               newArray$
  #138 = Utf8               (Lscala/reflect/ClassTag;I)Ljava/lang/Object;
  #139 = Utf8               len
  #140 = Utf8               newArray
  #141 = Utf8               (I)Ljava/lang/Object;
  #142 = NameAndType        #140:#141     // newArray:(I)Ljava/lang/Object;
  #143 = InterfaceMethodref #2.#142       // scala/reflect/ClassTag.newArray:(I)Ljava/lang/Object;
  #144 = Utf8               I
  #145 = Utf8               java/lang/reflect/Array
  #146 = Class              #145          // java/lang/reflect/Array
  #147 = Utf8               newInstance
  #148 = Utf8               (Ljava/lang/Class;I)Ljava/lang/Object;
  #149 = NameAndType        #147:#148     // newInstance:(Ljava/lang/Class;I)Ljava/lang/Object;
  #150 = Methodref          #146.#149     // java/lang/reflect/Array.newInstance:(Ljava/lang/Class;I)Ljava/lang/Object;
  #151 = Utf8               unapply$
  #152 = Utf8               (Lscala/reflect/ClassTag;Ljava/lang/Object;)Lscala/Option;
  #153 = Utf8               x
  #154 = Utf8               unapply
  #155 = Utf8               (Ljava/lang/Object;)Lscala/Option;
  #156 = NameAndType        #154:#155     // unapply:(Ljava/lang/Object;)Lscala/Option;
  #157 = InterfaceMethodref #2.#156       // scala/reflect/ClassTag.unapply:(Ljava/lang/Object;)Lscala/Option;
  #158 = Utf8               Ljava/lang/Object;
  #159 = Utf8               (Ljava/lang/Object;)Lscala/Option<TT;>;
  #160 = Utf8               java/lang/Class
  #161 = Class              #160          // java/lang/Class
  #162 = Utf8               isInstance
  #163 = Utf8               (Ljava/lang/Object;)Z
  #164 = NameAndType        #162:#163     // isInstance:(Ljava/lang/Object;)Z
  #165 = Methodref          #161.#164     // java/lang/Class.isInstance:(Ljava/lang/Object;)Z
  #166 = Utf8               scala/Some
  #167 = Class              #166          // scala/Some
  #168 = Utf8               <init>
  #169 = Utf8               (Ljava/lang/Object;)V
  #170 = NameAndType        #168:#169     // "<init>":(Ljava/lang/Object;)V
  #171 = Methodref          #167.#170     // scala/Some."<init>":(Ljava/lang/Object;)V
  #172 = Utf8               scala/None$
  #173 = Class              #172          // scala/None$
  #174 = Utf8               Lscala/None$;
  #175 = NameAndType        #55:#174      // MODULE$:Lscala/None$;
  #176 = Fieldref           #173.#175     // scala/None$.MODULE$:Lscala/None$;
  #177 = Utf8               canEqual$
  #178 = Utf8               (Lscala/reflect/ClassTag;Ljava/lang/Object;)Z
  #179 = Utf8               canEqual
  #180 = NameAndType        #179:#163     // canEqual:(Ljava/lang/Object;)Z
  #181 = InterfaceMethodref #2.#180       // scala/reflect/ClassTag.canEqual:(Ljava/lang/Object;)Z
  #182 = Utf8               equals$
  #183 = Utf8               equals
  #184 = NameAndType        #183:#163     // equals:(Ljava/lang/Object;)Z
  #185 = InterfaceMethodref #2.#184       // scala/reflect/ClassTag.equals:(Ljava/lang/Object;)Z
  #186 = Methodref          #5.#184       // java/lang/Object.equals:(Ljava/lang/Object;)Z
  #187 = Utf8               hashCode$
  #188 = Utf8               (Lscala/reflect/ClassTag;)I
  #189 = Utf8               hashCode
  #190 = Utf8               ()I
  #191 = NameAndType        #189:#190     // hashCode:()I
  #192 = InterfaceMethodref #2.#191       // scala/reflect/ClassTag.hashCode:()I
  #193 = Utf8               scala/runtime/Statics
  #194 = Class              #193          // scala/runtime/Statics
  #195 = Utf8               anyHash
  #196 = Utf8               (Ljava/lang/Object;)I
  #197 = NameAndType        #195:#196     // anyHash:(Ljava/lang/Object;)I
  #198 = Methodref          #194.#197     // scala/runtime/Statics.anyHash:(Ljava/lang/Object;)I
  #199 = Utf8               toString$
  #200 = Utf8               (Lscala/reflect/ClassTag;)Ljava/lang/String;
  #201 = Utf8               toString
  #202 = Utf8               ()Ljava/lang/String;
  #203 = NameAndType        #201:#202     // toString:()Ljava/lang/String;
  #204 = InterfaceMethodref #2.#203       // scala/reflect/ClassTag.toString:()Ljava/lang/String;
  #205 = Utf8               prettyprint$1
  #206 = Utf8               (Ljava/lang/Class;)Ljava/lang/String;
  #207 = NameAndType        #205:#206     // prettyprint$1:(Ljava/lang/Class;)Ljava/lang/String;
  #208 = InterfaceMethodref #2.#207       // scala/reflect/ClassTag.prettyprint$1:(Ljava/lang/Class;)Ljava/lang/String;
  #209 = Utf8               clazz
  #210 = Utf8               isArray
  #211 = Utf8               ()Z
  #212 = NameAndType        #210:#211     // isArray:()Z
  #213 = Methodref          #161.#212     // java/lang/Class.isArray:()Z
  #214 = Utf8               java/lang/StringBuilder
  #215 = Class              #214          // java/lang/StringBuilder
  #216 = Integer            7
  #217 = Utf8               (I)V
  #218 = NameAndType        #168:#217     // "<init>":(I)V
  #219 = Methodref          #215.#218     // java/lang/StringBuilder."<init>":(I)V
  #220 = Utf8               Array[
  #221 = String             #220          // Array[
  #222 = Utf8               append
  #223 = Utf8               (Ljava/lang/String;)Ljava/lang/StringBuilder;
  #224 = NameAndType        #222:#223     // append:(Ljava/lang/String;)Ljava/lang/StringBuilder;
  #225 = Methodref          #215.#224     // java/lang/StringBuilder.append:(Ljava/lang/String;)Ljava/lang/StringBuilder;
  #226 = Utf8               getComponentType
  #227 = NameAndType        #226:#121     // getComponentType:()Ljava/lang/Class;
  #228 = Methodref          #161.#227     // java/lang/Class.getComponentType:()Ljava/lang/Class;
  #229 = Utf8               ]
  #230 = String             #229          // ]
  #231 = Methodref          #215.#203     // java/lang/StringBuilder.toString:()Ljava/lang/String;
  #232 = Utf8               getName
  #233 = NameAndType        #232:#202     // getName:()Ljava/lang/String;
  #234 = Methodref          #161.#233     // java/lang/Class.getName:()Ljava/lang/String;
  #235 = Utf8               $init$
  #236 = Utf8               (Lscala/reflect/ClassTag;)V
  #237 = Utf8               Code
  #238 = Utf8               LocalVariableTable
  #239 = Utf8               Signature
  #240 = Utf8               MethodParameters
  #241 = Utf8               LineNumberTable
  #242 = Utf8               StackMapTable
  #243 = Utf8               InnerClasses
  #244 = Utf8               SourceFile
  #245 = Utf8               RuntimeVisibleAnnotations
  #246 = Utf8               ScalaInlineInfo
  #247 = Utf8               ScalaSig
{
  public static <T extends java.lang.Object> scala.reflect.ClassTag<T> apply(java.lang.Class<?>);
    descriptor: (Ljava/lang/Class;)Lscala/reflect/ClassTag;
    flags: (0x0009) ACC_PUBLIC, ACC_STATIC
    Code:
      stack=2, locals=1, args_size=1
         0: getstatic     #58                 // Field scala/reflect/ClassTag$.MODULE$:Lscala/reflect/ClassTag$;
         3: aload_0
         4: invokevirtual #60                 // Method scala/reflect/ClassTag$.apply:(Ljava/lang/Class;)Lscala/reflect/ClassTag;
         7: areturn
      LocalVariableTable:
        Start  Length  Slot  Name   Signature
            0       8     0 runtimeClass1   Ljava/lang/Class;
    Signature: #51                          // <T:Ljava/lang/Object;>(Ljava/lang/Class<*>;)Lscala/reflect/ClassTag<TT;>;
    MethodParameters:
      Name                           Flags
      runtimeClass1                  final

  public static scala.reflect.ClassTag<scala.runtime.Null$> Null();
    descriptor: ()Lscala/reflect/ClassTag;
    flags: (0x0009) ACC_PUBLIC, ACC_STATIC
    Code:
      stack=1, locals=0, args_size=0
         0: getstatic     #58                 // Field scala/reflect/ClassTag$.MODULE$:Lscala/reflect/ClassTag$;
         3: invokevirtual #66                 // Method scala/reflect/ClassTag$.Null:()Lscala/reflect/ClassTag;
         6: areturn
    Signature: #64                          // ()Lscala/reflect/ClassTag<Lscala/runtime/Null$;>;

  public static scala.reflect.ClassTag<scala.runtime.Nothing$> Nothing();
    descriptor: ()Lscala/reflect/ClassTag;
    flags: (0x0009) ACC_PUBLIC, ACC_STATIC
    Code:
      stack=1, locals=0, args_size=0
         0: getstatic     #58                 // Field scala/reflect/ClassTag$.MODULE$:Lscala/reflect/ClassTag$;
         3: invokevirtual #70                 // Method scala/reflect/ClassTag$.Nothing:()Lscala/reflect/ClassTag;
         6: areturn
    Signature: #68                          // ()Lscala/reflect/ClassTag<Lscala/runtime/Nothing$;>;

  public static scala.reflect.ClassTag<java.lang.Object> AnyRef();
    descriptor: ()Lscala/reflect/ClassTag;
    flags: (0x0009) ACC_PUBLIC, ACC_STATIC
    Code:
      stack=1, locals=0, args_size=0
         0: getstatic     #58                 // Field scala/reflect/ClassTag$.MODULE$:Lscala/reflect/ClassTag$;
         3: invokevirtual #74                 // Method scala/reflect/ClassTag$.AnyRef:()Lscala/reflect/ClassTag;
         6: areturn
    Signature: #72                          // ()Lscala/reflect/ClassTag<Ljava/lang/Object;>;

  public static scala.reflect.ClassTag<java.lang.Object> AnyVal();
    descriptor: ()Lscala/reflect/ClassTag;
    flags: (0x0009) ACC_PUBLIC, ACC_STATIC
    Code:
      stack=1, locals=0, args_size=0
         0: getstatic     #58                 // Field scala/reflect/ClassTag$.MODULE$:Lscala/reflect/ClassTag$;
         3: invokevirtual #77                 // Method scala/reflect/ClassTag$.AnyVal:()Lscala/reflect/ClassTag;
         6: areturn
    Signature: #72                          // ()Lscala/reflect/ClassTag<Ljava/lang/Object;>;

  public static scala.reflect.ClassTag<java.lang.Object> Object();
    descriptor: ()Lscala/reflect/ClassTag;
    flags: (0x0009) ACC_PUBLIC, ACC_STATIC
    Code:
      stack=1, locals=0, args_size=0
         0: getstatic     #58                 // Field scala/reflect/ClassTag$.MODULE$:Lscala/reflect/ClassTag$;
         3: invokevirtual #80                 // Method scala/reflect/ClassTag$.Object:()Lscala/reflect/ClassTag;
         6: areturn
    Signature: #72                          // ()Lscala/reflect/ClassTag<Ljava/lang/Object;>;

  public static scala.reflect.ClassTag<java.lang.Object> Any();
    descriptor: ()Lscala/reflect/ClassTag;
    flags: (0x0009) ACC_PUBLIC, ACC_STATIC
    Code:
      stack=1, locals=0, args_size=0
         0: getstatic     #58                 // Field scala/reflect/ClassTag$.MODULE$:Lscala/reflect/ClassTag$;
         3: invokevirtual #83                 // Method scala/reflect/ClassTag$.Any:()Lscala/reflect/ClassTag;
         6: areturn
    Signature: #72                          // ()Lscala/reflect/ClassTag<Ljava/lang/Object;>;

  public static scala.reflect.ManifestFactory$UnitManifest Unit();
    descriptor: ()Lscala/reflect/ManifestFactory$UnitManifest;
    flags: (0x0009) ACC_PUBLIC, ACC_STATIC
    Code:
      stack=1, locals=0, args_size=0
         0: getstatic     #58                 // Field scala/reflect/ClassTag$.MODULE$:Lscala/reflect/ClassTag$;
         3: invokevirtual #87                 // Method scala/reflect/ClassTag$.Unit:()Lscala/reflect/ManifestFactory$UnitManifest;
         6: areturn

  public static scala.reflect.ManifestFactory$BooleanManifest Boolean();
    descriptor: ()Lscala/reflect/ManifestFactory$BooleanManifest;
    flags: (0x0009) ACC_PUBLIC, ACC_STATIC
    Code:
      stack=1, locals=0, args_size=0
         0: getstatic     #58                 // Field scala/reflect/ClassTag$.MODULE$:Lscala/reflect/ClassTag$;
         3: invokevirtual #91                 // Method scala/reflect/ClassTag$.Boolean:()Lscala/reflect/ManifestFactory$BooleanManifest;
         6: areturn

  public static scala.reflect.ManifestFactory$DoubleManifest Double();
    descriptor: ()Lscala/reflect/ManifestFactory$DoubleManifest;
    flags: (0x0009) ACC_PUBLIC, ACC_STATIC
    Code:
      stack=1, locals=0, args_size=0
         0: getstatic     #58                 // Field scala/reflect/ClassTag$.MODULE$:Lscala/reflect/ClassTag$;
         3: invokevirtual #95                 // Method scala/reflect/ClassTag$.Double:()Lscala/reflect/ManifestFactory$DoubleManifest;
         6: areturn

  public static scala.reflect.ManifestFactory$FloatManifest Float();
    descriptor: ()Lscala/reflect/ManifestFactory$FloatManifest;
    flags: (0x0009) ACC_PUBLIC, ACC_STATIC
    Code:
      stack=1, locals=0, args_size=0
         0: getstatic     #58                 // Field scala/reflect/ClassTag$.MODULE$:Lscala/reflect/ClassTag$;
         3: invokevirtual #99                 // Method scala/reflect/ClassTag$.Float:()Lscala/reflect/ManifestFactory$FloatManifest;
         6: areturn

  public static scala.reflect.ManifestFactory$LongManifest Long();
    descriptor: ()Lscala/reflect/ManifestFactory$LongManifest;
    flags: (0x0009) ACC_PUBLIC, ACC_STATIC
    Code:
      stack=1, locals=0, args_size=0
         0: getstatic     #58                 // Field scala/reflect/ClassTag$.MODULE$:Lscala/reflect/ClassTag$;
         3: invokevirtual #103                // Method scala/reflect/ClassTag$.Long:()Lscala/reflect/ManifestFactory$LongManifest;
         6: areturn

  public static scala.reflect.ManifestFactory$IntManifest Int();
    descriptor: ()Lscala/reflect/ManifestFactory$IntManifest;
    flags: (0x0009) ACC_PUBLIC, ACC_STATIC
    Code:
      stack=1, locals=0, args_size=0
         0: getstatic     #58                 // Field scala/reflect/ClassTag$.MODULE$:Lscala/reflect/ClassTag$;
         3: invokevirtual #107                // Method scala/reflect/ClassTag$.Int:()Lscala/reflect/ManifestFactory$IntManifest;
         6: areturn

  public static scala.reflect.ManifestFactory$CharManifest Char();
    descriptor: ()Lscala/reflect/ManifestFactory$CharManifest;
    flags: (0x0009) ACC_PUBLIC, ACC_STATIC
    Code:
      stack=1, locals=0, args_size=0
         0: getstatic     #58                 // Field scala/reflect/ClassTag$.MODULE$:Lscala/reflect/ClassTag$;
         3: invokevirtual #111                // Method scala/reflect/ClassTag$.Char:()Lscala/reflect/ManifestFactory$CharManifest;
         6: areturn

  public static scala.reflect.ManifestFactory$ShortManifest Short();
    descriptor: ()Lscala/reflect/ManifestFactory$ShortManifest;
    flags: (0x0009) ACC_PUBLIC, ACC_STATIC
    Code:
      stack=1, locals=0, args_size=0
         0: getstatic     #58                 // Field scala/reflect/ClassTag$.MODULE$:Lscala/reflect/ClassTag$;
         3: invokevirtual #115                // Method scala/reflect/ClassTag$.Short:()Lscala/reflect/ManifestFactory$ShortManifest;
         6: areturn

  public static scala.reflect.ManifestFactory$ByteManifest Byte();
    descriptor: ()Lscala/reflect/ManifestFactory$ByteManifest;
    flags: (0x0009) ACC_PUBLIC, ACC_STATIC
    Code:
      stack=1, locals=0, args_size=0
         0: getstatic     #58                 // Field scala/reflect/ClassTag$.MODULE$:Lscala/reflect/ClassTag$;
         3: invokevirtual #119                // Method scala/reflect/ClassTag$.Byte:()Lscala/reflect/ManifestFactory$ByteManifest;
         6: areturn

  public abstract java.lang.Class<?> runtimeClass();
    descriptor: ()Ljava/lang/Class;
    flags: (0x0401) ACC_PUBLIC, ACC_ABSTRACT
    Signature: #122                         // ()Ljava/lang/Class<*>;

  public static scala.reflect.ClassTag wrap$(scala.reflect.ClassTag);
    descriptor: (Lscala/reflect/ClassTag;)Lscala/reflect/ClassTag;
    flags: (0x1009) ACC_PUBLIC, ACC_STATIC, ACC_SYNTHETIC
    Code:
      stack=1, locals=1, args_size=1
         0: aload_0
         1: invokespecial #128                // InterfaceMethod wrap:()Lscala/reflect/ClassTag;
         4: areturn
      LineNumberTable:
        line 62: 0
      LocalVariableTable:
        Start  Length  Slot  Name   Signature
            0       5     0 $this   Lscala/reflect/ClassTag;
    MethodParameters:
      Name                           Flags
      $this                          final synthetic

  public default scala.reflect.ClassTag<java.lang.Object> wrap();
    descriptor: ()Lscala/reflect/ClassTag;
    flags: (0x0001) ACC_PUBLIC
    Code:
      stack=3, locals=1, args_size=1
         0: getstatic     #58                 // Field scala/reflect/ClassTag$.MODULE$:Lscala/reflect/ClassTag$;
         3: aload_0
         4: aload_0
         5: invokeinterface #131,  1          // InterfaceMethod runtimeClass:()Ljava/lang/Class;
        10: invokeinterface #135,  2          // InterfaceMethod arrayClass:(Ljava/lang/Class;)Ljava/lang/Class;
        15: invokevirtual #60                 // Method scala/reflect/ClassTag$.apply:(Ljava/lang/Class;)Lscala/reflect/ClassTag;
        18: areturn
      LineNumberTable:
        line 62: 0
      LocalVariableTable:
        Start  Length  Slot  Name   Signature
            0      19     0  this   Lscala/reflect/ClassTag;
    Signature: #72                          // ()Lscala/reflect/ClassTag<Ljava/lang/Object;>;

  public static java.lang.Object newArray$(scala.reflect.ClassTag, int);
    descriptor: (Lscala/reflect/ClassTag;I)Ljava/lang/Object;
    flags: (0x1009) ACC_PUBLIC, ACC_STATIC, ACC_SYNTHETIC
    Code:
      stack=2, locals=2, args_size=2
         0: aload_0
         1: iload_1
         2: invokespecial #143                // InterfaceMethod newArray:(I)Ljava/lang/Object;
         5: areturn
      LineNumberTable:
        line 65: 0
      LocalVariableTable:
        Start  Length  Slot  Name   Signature
            0       6     0 $this   Lscala/reflect/ClassTag;
            0       6     1   len   I
    MethodParameters:
      Name                           Flags
      $this                          final synthetic
      len                            final

  public default java.lang.Object newArray(int);
    descriptor: (I)Ljava/lang/Object;
    flags: (0x0001) ACC_PUBLIC
    Code:
      stack=2, locals=2, args_size=2
         0: aload_0
         1: invokeinterface #131,  1          // InterfaceMethod runtimeClass:()Ljava/lang/Class;
         6: iload_1
         7: invokestatic  #150                // Method java/lang/reflect/Array.newInstance:(Ljava/lang/Class;I)Ljava/lang/Object;
        10: areturn
      LineNumberTable:
        line 66: 0
      LocalVariableTable:
        Start  Length  Slot  Name   Signature
            0      11     0  this   Lscala/reflect/ClassTag;
            0      11     1   len   I
    Signature: #141                         // (I)Ljava/lang/Object;
    MethodParameters:
      Name                           Flags
      len                            final

  public static scala.Option unapply$(scala.reflect.ClassTag, java.lang.Object);
    descriptor: (Lscala/reflect/ClassTag;Ljava/lang/Object;)Lscala/Option;
    flags: (0x1009) ACC_PUBLIC, ACC_STATIC, ACC_SYNTHETIC
    Code:
      stack=2, locals=2, args_size=2
         0: aload_0
         1: aload_1
         2: invokespecial #157                // InterfaceMethod unapply:(Ljava/lang/Object;)Lscala/Option;
         5: areturn
      LineNumberTable:
        line 76: 0
      LocalVariableTable:
        Start  Length  Slot  Name   Signature
            0       6     0 $this   Lscala/reflect/ClassTag;
            0       6     1     x   Ljava/lang/Object;
    MethodParameters:
      Name                           Flags
      $this                          final synthetic
      x                              final

  public default scala.Option<T> unapply(java.lang.Object);
    descriptor: (Ljava/lang/Object;)Lscala/Option;
    flags: (0x0001) ACC_PUBLIC
    Code:
      stack=3, locals=2, args_size=2
         0: aload_0
         1: invokeinterface #131,  1          // InterfaceMethod runtimeClass:()Ljava/lang/Class;
         6: aload_1
         7: invokevirtual #165                // Method java/lang/Class.isInstance:(Ljava/lang/Object;)Z
        10: ifeq          22
        13: new           #167                // class scala/Some
        16: dup
        17: aload_1
        18: invokespecial #171                // Method scala/Some."<init>":(Ljava/lang/Object;)V
        21: areturn
        22: getstatic     #176                // Field scala/None$.MODULE$:Lscala/None$;
        25: areturn
      StackMapTable: number_of_entries = 1
        frame_type = 22 /* same */
      LineNumberTable:
        line 77: 0
        line 78: 22
      LocalVariableTable:
        Start  Length  Slot  Name   Signature
            0      26     0  this   Lscala/reflect/ClassTag;
            0      26     1     x   Ljava/lang/Object;
    Signature: #159                         // (Ljava/lang/Object;)Lscala/Option<TT;>;
    MethodParameters:
      Name                           Flags
      x                              final

  public static boolean canEqual$(scala.reflect.ClassTag, java.lang.Object);
    descriptor: (Lscala/reflect/ClassTag;Ljava/lang/Object;)Z
    flags: (0x1009) ACC_PUBLIC, ACC_STATIC, ACC_SYNTHETIC
    Code:
      stack=2, locals=2, args_size=2
         0: aload_0
         1: aload_1
         2: invokespecial #181                // InterfaceMethod canEqual:(Ljava/lang/Object;)Z
         5: ireturn
      LineNumberTable:
        line 81: 0
      LocalVariableTable:
        Start  Length  Slot  Name   Signature
            0       6     0 $this   Lscala/reflect/ClassTag;
            0       6     1     x   Ljava/lang/Object;
    MethodParameters:
      Name                           Flags
      $this                          final synthetic
      x                              final

  public default boolean canEqual(java.lang.Object);
    descriptor: (Ljava/lang/Object;)Z
    flags: (0x0001) ACC_PUBLIC
    Code:
      stack=1, locals=2, args_size=2
         0: aload_1
         1: instanceof    #2                  // class scala/reflect/ClassTag
         4: ireturn
      LineNumberTable:
        line 81: 0
      LocalVariableTable:
        Start  Length  Slot  Name   Signature
            0       5     0  this   Lscala/reflect/ClassTag;
            0       5     1     x   Ljava/lang/Object;
    MethodParameters:
      Name                           Flags
      x                              final

  public static boolean equals$(scala.reflect.ClassTag, java.lang.Object);
    descriptor: (Lscala/reflect/ClassTag;Ljava/lang/Object;)Z
    flags: (0x1009) ACC_PUBLIC, ACC_STATIC, ACC_SYNTHETIC
    Code:
      stack=2, locals=2, args_size=2
         0: aload_0
         1: aload_1
         2: invokespecial #185                // InterfaceMethod equals:(Ljava/lang/Object;)Z
         5: ireturn
      LineNumberTable:
        line 82: 0
      LocalVariableTable:
        Start  Length  Slot  Name   Signature
            0       6     0 $this   Lscala/reflect/ClassTag;
            0       6     1     x   Ljava/lang/Object;
    MethodParameters:
      Name                           Flags
      $this                          final synthetic
      x                              final

  public default boolean equals(java.lang.Object);
    descriptor: (Ljava/lang/Object;)Z
    flags: (0x0001) ACC_PUBLIC
    Code:
      stack=2, locals=3, args_size=2
         0: aload_1
         1: instanceof    #2                  // class scala/reflect/ClassTag
         4: ifeq          44
         7: aload_0
         8: invokeinterface #131,  1          // InterfaceMethod runtimeClass:()Ljava/lang/Class;
        13: aload_1
        14: checkcast     #2                  // class scala/reflect/ClassTag
        17: invokeinterface #131,  1          // InterfaceMethod runtimeClass:()Ljava/lang/Class;
        22: astore_2
        23: dup
        24: ifnonnull     35
        27: pop
        28: aload_2
        29: ifnull        42
        32: goto          44
        35: aload_2
        36: invokevirtual #186                // Method java/lang/Object.equals:(Ljava/lang/Object;)Z
        39: ifeq          44
        42: iconst_1
        43: ireturn
        44: iconst_0
        45: ireturn
      StackMapTable: number_of_entries = 3
        frame_type = 255 /* full_frame */
          offset_delta = 35
          locals = [ class scala/reflect/ClassTag, class java/lang/Object, class java/lang/Class ]
          stack = [ class java/lang/Class ]
        frame_type = 6 /* same */
        frame_type = 250 /* chop */
          offset_delta = 1
      LineNumberTable:
        line 82: 0
      LocalVariableTable:
        Start  Length  Slot  Name   Signature
            0      46     0  this   Lscala/reflect/ClassTag;
            0      46     1     x   Ljava/lang/Object;
    MethodParameters:
      Name                           Flags
      x                              final

  public static int hashCode$(scala.reflect.ClassTag);
    descriptor: (Lscala/reflect/ClassTag;)I
    flags: (0x1009) ACC_PUBLIC, ACC_STATIC, ACC_SYNTHETIC
    Code:
      stack=1, locals=1, args_size=1
         0: aload_0
         1: invokespecial #192                // InterfaceMethod hashCode:()I
         4: ireturn
      LineNumberTable:
        line 83: 0
      LocalVariableTable:
        Start  Length  Slot  Name   Signature
            0       5     0 $this   Lscala/reflect/ClassTag;
    MethodParameters:
      Name                           Flags
      $this                          final synthetic

  public default int hashCode();
    descriptor: ()I
    flags: (0x0001) ACC_PUBLIC
    Code:
      stack=1, locals=1, args_size=1
         0: aload_0
         1: invokeinterface #131,  1          // InterfaceMethod runtimeClass:()Ljava/lang/Class;
         6: invokestatic  #198                // Method scala/runtime/Statics.anyHash:(Ljava/lang/Object;)I
         9: ireturn
      LineNumberTable:
        line 83: 0
      LocalVariableTable:
        Start  Length  Slot  Name   Signature
            0      10     0  this   Lscala/reflect/ClassTag;

  public static java.lang.String toString$(scala.reflect.ClassTag);
    descriptor: (Lscala/reflect/ClassTag;)Ljava/lang/String;
    flags: (0x1009) ACC_PUBLIC, ACC_STATIC, ACC_SYNTHETIC
    Code:
      stack=1, locals=1, args_size=1
         0: aload_0
         1: invokespecial #204                // InterfaceMethod toString:()Ljava/lang/String;
         4: areturn
      LineNumberTable:
        line 84: 0
      LocalVariableTable:
        Start  Length  Slot  Name   Signature
            0       5     0 $this   Lscala/reflect/ClassTag;
    MethodParameters:
      Name                           Flags
      $this                          final synthetic

  public default java.lang.String toString();
    descriptor: ()Ljava/lang/String;
    flags: (0x0001) ACC_PUBLIC
    Code:
      stack=1, locals=1, args_size=1
         0: aload_0
         1: invokeinterface #131,  1          // InterfaceMethod runtimeClass:()Ljava/lang/Class;
         6: invokestatic  #208                // InterfaceMethod prettyprint$1:(Ljava/lang/Class;)Ljava/lang/String;
         9: areturn
      LineNumberTable:
        line 88: 0
      LocalVariableTable:
        Start  Length  Slot  Name   Signature
            0      10     0  this   Lscala/reflect/ClassTag;

  private static java.lang.String prettyprint$1(java.lang.Class);
    descriptor: (Ljava/lang/Class;)Ljava/lang/String;
    flags: (0x000a) ACC_PRIVATE, ACC_STATIC
    Code:
      stack=3, locals=1, args_size=1
         0: aload_0
         1: invokevirtual #213                // Method java/lang/Class.isArray:()Z
         4: ifeq          40
         7: new           #215                // class java/lang/StringBuilder
        10: dup
        11: ldc           #216                // int 7
        13: invokespecial #219                // Method java/lang/StringBuilder."<init>":(I)V
        16: ldc           #221                // String Array[
        18: invokevirtual #225                // Method java/lang/StringBuilder.append:(Ljava/lang/String;)Ljava/lang/StringBuilder;
        21: aload_0
        22: invokevirtual #228                // Method java/lang/Class.getComponentType:()Ljava/lang/Class;
        25: invokestatic  #208                // InterfaceMethod prettyprint$1:(Ljava/lang/Class;)Ljava/lang/String;
        28: invokevirtual #225                // Method java/lang/StringBuilder.append:(Ljava/lang/String;)Ljava/lang/StringBuilder;
        31: ldc           #230                // String ]
        33: invokevirtual #225                // Method java/lang/StringBuilder.append:(Ljava/lang/String;)Ljava/lang/StringBuilder;
        36: invokevirtual #231                // Method java/lang/StringBuilder.toString:()Ljava/lang/String;
        39: areturn
        40: aload_0
        41: invokevirtual #234                // Method java/lang/Class.getName:()Ljava/lang/String;
        44: areturn
      StackMapTable: number_of_entries = 1
        frame_type = 40 /* same */
      LineNumberTable:
        line 86: 0
        line 87: 40
      LocalVariableTable:
        Start  Length  Slot  Name   Signature
            0      45     0 clazz   Ljava/lang/Class;
    MethodParameters:
      Name                           Flags
      clazz                          final

  public static void $init$(scala.reflect.ClassTag);
    descriptor: (Lscala/reflect/ClassTag;)V
    flags: (0x0009) ACC_PUBLIC, ACC_STATIC
    Code:
      stack=0, locals=1, args_size=1
         0: return
      LineNumberTable:
        line 52: 0
      LocalVariableTable:
        Start  Length  Slot  Name   Signature
            0       1     0 $this   Lscala/reflect/ClassTag;
    MethodParameters:
      Name                           Flags
      $this                          final synthetic
}
InnerClasses:
  private static #16= #15 of #2;          // GenericClassTag=class scala/reflect/ClassTag$GenericClassTag of class scala/reflect/ClassTag
  private static #19= #18 of #2;          // cache$=class scala/reflect/ClassTag$cache$ of class scala/reflect/ClassTag
  public static final #24= #21 of #23;    // BooleanManifest=class scala/reflect/ManifestFactory$BooleanManifest of class scala/reflect/ManifestFactory
  public static final #27= #26 of #23;    // ByteManifest=class scala/reflect/ManifestFactory$ByteManifest of class scala/reflect/ManifestFactory
  public static final #30= #29 of #23;    // CharManifest=class scala/reflect/ManifestFactory$CharManifest of class scala/reflect/ManifestFactory
  public static final #33= #32 of #23;    // DoubleManifest=class scala/reflect/ManifestFactory$DoubleManifest of class scala/reflect/ManifestFactory
  public static final #36= #35 of #23;    // FloatManifest=class scala/reflect/ManifestFactory$FloatManifest of class scala/reflect/ManifestFactory
  public static final #39= #38 of #23;    // IntManifest=class scala/reflect/ManifestFactory$IntManifest of class scala/reflect/ManifestFactory
  public static final #42= #41 of #23;    // LongManifest=class scala/reflect/ManifestFactory$LongManifest of class scala/reflect/ManifestFactory
  public static final #45= #44 of #23;    // ShortManifest=class scala/reflect/ManifestFactory$ShortManifest of class scala/reflect/ManifestFactory
  public static final #48= #47 of #23;    // UnitManifest=class scala/reflect/ManifestFactory$UnitManifest of class scala/reflect/ManifestFactory
Signature: #3                           // <T:Ljava/lang/Object;>Ljava/lang/Object;Lscala/reflect/ClassManifestDeprecatedApis<TT;>;Lscala/Equals;
SourceFile: "ClassTag.scala"
RuntimeVisibleAnnotations:
  0: #11(#12=s#13)
    scala.reflect.ScalaSignature(
      bytes="\u0006\u0005\r]ba\u0002 @!\u0003\r\t\u0001\u0012\u0005\u0006G\u0002!\t\u0001\u001a\u0005\u0006Q\u00021\t!\u001b\u0005\u0006m\u0002!\ta\u001e\u0005\u0006y\u0002!\t! \u0005\b\u0003\u000f\u0001A\u0011AA\u0005\u0011\u001d\t)\u0002\u0001C!\u0003/Aq!!\t\u0001\t\u0003\n\u0019\u0003C\u0004\u0002(\u0001!\t%!\u000b\t\u000f\u0005-\u0002\u0001\"\u0011\u0002.\u001d9\u0011\u0011L \t\u0002\u0005mcA\u0002 @\u0011\u0003\ti\u0006C\u0004\u0002j-!\t!a\u001b\t\u0011\u000554\u0002)A\u0005\u0003_B\u0001\"a\u001e\fA\u0003%\u0011\u0011\u0010\u0005\t\u0003\u000f[\u0001\u0015!\u0003\u0002\n\"I\u0011\u0011S\u0006C\u0002\u0013\u0005\u00111\u0013\u0005\t\u0003G[\u0001\u0015!\u0003\u0002\u0016\"I\u0011QU\u0006C\u0002\u0013\u0005\u0011q\u0015\u0005\t\u0003_[\u0001\u0015!\u0003\u0002*\"I\u0011\u0011W\u0006C\u0002\u0013\u0005\u00111\u0017\u0005\t\u0003w[\u0001\u0015!\u0003\u00026\"I\u0011QX\u0006C\u0002\u0013\u0005\u0011q\u0018\u0005\t\u0003\u000f\\\u0001\u0015!\u0003\u0002B\"I\u0011\u0011Z\u0006C\u0002\u0013\u0005\u00111\u001a\u0005\t\u0003\'\\\u0001\u0015!\u0003\u0002N\"I\u0011Q[\u0006C\u0002\u0013\u0005\u0011q\u001b\u0005\t\u0003?\\\u0001\u0015!\u0003\u0002Z\"I\u0011\u0011]\u0006C\u0002\u0013\u0005\u00111\u001d\u0005\t\u0003W\\\u0001\u0015!\u0003\u0002f\"I\u0011Q^\u0006C\u0002\u0013\u0005\u0011q\u001e\u0005\t\u0003o\\\u0001\u0015!\u0003\u0002r\"I\u0011\u0011`\u0006C\u0002\u0013\u0005\u00111 \u0005\t\u0005\u0007Y\u0001\u0015!\u0003\u0002~\"I!QA\u0006C\u0002\u0013\u0005!q\u0001\u0005\t\u0005\u0017Y\u0001\u0015!\u0003\u0003\n!I!QB\u0006C\u0002\u0013\u0005!q\u0002\u0005\t\u0005\'Y\u0001\u0015!\u0003\u0003\u0012!I!QC\u0006C\u0002\u0013\u0005!q\u0003\u0005\t\u0005CY\u0001\u0015!\u0003\u0003\u001a!I!1E\u0006C\u0002\u0013\u0005!Q\u0005\u0005\t\u0005SY\u0001\u0015!\u0003\u0003(!I!1F\u0006C\u0002\u0013\u0005!Q\u0006\u0005\t\u0005cY\u0001\u0015!\u0003\u00030!I!1G\u0006C\u0002\u0013\u0005!Q\u0007\u0005\t\u0005\u007fY\u0001\u0015!\u0003\u00038!I!\u0011I\u0006C\u0002\u0013%!1\t\u0005\t\u0005\u000bZ\u0001\u0015!\u0003\u0002\u001a\u001dA!qI\u0006!\u0012\u0013\u0011IE\u0002\u0005\u0003N-\u0001\u000b\u0012\u0002B(\u0011\u001d\tI\'\rC\u0001\u0005[BqAa\u001c2\t\u0003\u0012\t\bC\u0004\u0003\fF\"\tA!$\t\u000f\t\u0015\u0016\u0007\"\u0003\u0003(\u001a1!QY\u0006\u0005\u0005\u000fD\u0011\u0002\u001b\u001c\u0003\u0006\u0004%\tA!5\t\u0015\tugG!A!\u0002\u0013\u0011\u0019\u000eC\u0004\u0002jY\"\tAa8\t\rq4D\u0011\tBw\u0011\u001d\u0011yp\u0003C\u0001\u0007\u0003Aq!a\u0002\f\t\u0003\u0019I\u0002C\u0005\u00044-\t\t\u0011\"\u0003\u00046\tA1\t\\1tgR\u000bwM\u0003\u0002A\u0003\u00069!/\u001a4mK\u000e$(\"\u0001\"\u0002\u000bM\u001c\u0017\r\\1\u0004\u0001U\u0011Q\tU\n\u0006\u0001\u0019S\u0015\f\u0018\t\u0003\u000f\"k\u0011!Q\u0005\u0003\u0013\u0006\u0013a!\u00118z%\u00164\u0007cA&M\u001d6\tq(\u0003\u0002N\u007f\tY2\t\\1tg6\u000bg.\u001b4fgR$U\r\u001d:fG\u0006$X\rZ!qSN\u0004\"a\u0014)\r\u0001\u0011)\u0011\u000b\u0001b\u0001%\n\tA+\u0005\u0002T-B\u0011q\tV\u0005\u0003+\u0006\u0013qAT8uQ&tw\r\u0005\u0002H/&\u0011\u0001,\u0011\u0002\u0004\u0003:L\bCA$[\u0013\tY\u0016I\u0001\u0004FcV\fGn\u001d\t\u0003;\u0002t!a\u00120\n\u0005}\u000b\u0015a\u00029bG.\fw-Z\u0005\u0003C\n\u0014AbU3sS\u0006d\u0017N_1cY\u0016T!aX!\u0002\r\u0011Jg.\u001b;%)\u0005)\u0007CA$g\u0013\t9\u0017I\u0001\u0003V]&$\u0018\u0001\u0004:v]RLW.Z\"mCN\u001cX#\u000161\u0005-$\bc\u00017rg6\tQN\u0003\u0002o_\u0006!A.\u00198h\u0015\u0005\u0001\u0018\u0001\u00026bm\u0006L!A]7\u0003\u000b\rc\u0017m]:\u0011\u0005=#H!C;\u0003\u0003\u0003\u0005\tQ!\u0001S\u0005\ryF%M\u0001\u0005oJ\f\u0007/F\u0001y!\rY\u0005!\u001f\t\u0004\u000fjt\u0015BA>B\u0005\u0015\t%O]1z\u0003!qWm^!se\u0006LHCA=\u007f\u0011\u0019yH\u00011\u0001\u0002\u0002\u0005\u0019A.\u001a8\u0011\u0007\u001d\u000b\u0019!C\u0002\u0002\u0006\u0005\u00131!\u00138u\u0003\u001d)h.\u00199qYf$B!a\u0003\u0002\u0012A!q)!\u0004O\u0013\r\ty!\u0011\u0002\u0007\u001fB$\u0018n\u001c8\t\r\u0005MQ\u00011\u0001W\u0003\u0005A\u0018\u0001C2b]\u0016\u000bX/\u00197\u0015\t\u0005e\u0011q\u0004\t\u0004\u000f\u0006m\u0011bAA\u000f\u0003\n9!i\\8mK\u0006t\u0007BBA\n\r\u0001\u0007a+\u0001\u0004fcV\fGn\u001d\u000b\u0005\u00033\t)\u0003\u0003\u0004\u0002\u0014\u001d\u0001\rAV\u0001\tQ\u0006\u001c\bnQ8eKR\u0011\u0011\u0011A\u0001\ti>\u001cFO]5oOR\u0011\u0011q\u0006\t\u0005\u0003c\tyD\u0004\u0003\u00024\u0005m\u0002cAA\u001b\u00036\u0011\u0011q\u0007\u0006\u0004\u0003s\u0019\u0015A\u0002\u001fs_>$h(C\u0002\u0002>\u0005\u000ba\u0001\u0015:fI\u00164\u0017\u0002BA!\u0003\u0007\u0012aa\u0015;sS:<\'bAA\u001f\u0003\":\u0001!a\u0012\u0002T\u0005U\u0003\u0003BA%\u0003\u001fj!!a\u0013\u000b\u0007\u00055\u0013)\u0001\u0006b]:|G/\u0019;j_:LA!!\u0015\u0002L\t\u0001\u0012.\u001c9mS\u000eLGOT8u\r>,h\u000eZ\u0001\u0004[N<\u0017EAA,\u0003yqu\u000eI\"mCN\u001cH+Y4!CZ\f\u0017\u000e\\1cY\u0016\u0004cm\u001c:!Im$V0\u0001\u0005DY\u0006\u001c8\u000fV1h!\tY5b\u0005\u0003\f\r\u0006}\u0003\u0003BA1\u0003Oj!!a\u0019\u000b\u0007\u0005\u0015t.\u0001\u0002j_&\u0019\u0011-a\u0019\u0002\rqJg.\u001b;?)\t\tY&\u0001\u0006PE*,7\r\u001e+Z!\u0016\u0003B\u0001\\9\u0002rA\u0019A.a\u001d\n\u0007\u0005UTN\u0001\u0004PE*,7\r^\u0001\f\u001d>$\b.\u001b8h)f\u0003V\t\u0005\u0003mc\u0006m\u0004\u0003BA?\u0003\u0007k!!a \u000b\u0007\u0005\u0005\u0015)A\u0004sk:$\u0018.\\3\n\t\u0005\u0015\u0015q\u0010\u0002\t\u001d>$\b.\u001b8hI\u0005Aa*\u001e7m)f\u0003V\t\u0005\u0003mc\u0006-\u0005\u0003BA?\u0003\u001bKA!a$\u0002\u0000\t)a*\u001e7mI\u0005!!)\u001f;f+\t\t)\n\u0005\u0003\u0002\u0018\u0006uebA&\u0002\u001a&\u0019\u00111T \u0002\u001f5\u000bg.\u001b4fgR4\u0015m\u0019;pefLA!a(\u0002\"\na!)\u001f;f\u001b\u0006t\u0017NZ3ti*\u0019\u00111T \u0002\u000b\tKH/\u001a\u0011\u0002\u000bMCwN\u001d;\u0016\u0005\u0005%\u0006\u0003BAL\u0003WKA!!,\u0002\"\ni1\u000b[8si6\u000bg.\u001b4fgR\faa\u00155peR\u0004\u0013\u0001B\"iCJ,\"!!.\u0011\t\u0005]\u0015qW\u0005\u0005\u0003s\u000b\tK\u0001\u0007DQ\u0006\u0014X*\u00198jM\u0016\u001cH/A\u0003DQ\u0006\u0014\b%A\u0002J]R,\"!!1\u0011\t\u0005]\u00151Y\u0005\u0005\u0003\u000b\f\tKA\u0006J]Rl\u0015M\\5gKN$\u0018\u0001B%oi\u0002\nA\u0001T8oOV\u0011\u0011Q\u001a\t\u0005\u0003/\u000by-\u0003\u0003\u0002R\u0006\u0005&\u0001\u0004\'p]\u001el\u0015M\\5gKN$\u0018!\u0002\'p]\u001e\u0004\u0013!\u0002$m_\u0006$XCAAm!\u0011\t9*a7\n\t\u0005u\u0017\u0011\u0015\u0002\u000e\r2|\u0017\r^\'b]&4Wm\u001d;\u0002\r\u0019cw.\u0019;!\u0003\u0019!u.\u001e2mKV\u0011\u0011Q\u001d\t\u0005\u0003/\u000b9/\u0003\u0003\u0002j\u0006\u0005&A\u0004#pk\ndW-T1oS\u001a,7\u000f^\u0001\b\t>,(\r\\3!\u0003\u001d\u0011un\u001c7fC:,\"!!=\u0011\t\u0005]\u00151_\u0005\u0005\u0003k\f\tKA\bC_>dW-\u00198NC:Lg-Z:u\u0003!\u0011un\u001c7fC:\u0004\u0013\u0001B+oSR,\"!!@\u0011\t\u0005]\u0015q`\u0005\u0005\u0005\u0003\t\tK\u0001\u0007V]&$X*\u00198jM\u0016\u001cH/A\u0003V]&$\b%A\u0002B]f,\"A!\u0003\u0011\u0007-\u0003a+\u0001\u0003B]f\u0004\u0013AB(cU\u0016\u001cG/\u0006\u0002\u0003\u0012A!1\nAA9\u0003\u001dy%M[3di\u0002\na!\u00118z-\u0006dWC\u0001B\r!\u0011Y\u0005Aa\u0007\u0011\u0007\u001d\u0013i\"C\u0002\u0003 \u0005\u0013a!\u00118z-\u0006d\u0017aB!osZ\u000bG\u000eI\u0001\u0007\u0003:L(+\u001a4\u0016\u0005\t\u001d\u0002cA&\u0001\r\u00069\u0011I\\=SK\u001a\u0004\u0013a\u0002(pi\"LgnZ\u000b\u0003\u0005_\u00012a\u0013\u0001T\u0003!qu\u000e\u001e5j]\u001e\u0004\u0013\u0001\u0002(vY2,\"Aa\u000e\u0011\t-\u0003!\u0011\b\t\u0004\u000f\nm\u0012b\u0001B\u001f\u0003\n!a*\u001e7m\u0003\u0015qU\u000f\u001c7!\u00035\u0019\u0017m\u00195f\t&\u001c\u0018M\u00197fIV\u0011\u0011\u0011D\u0001\u000fG\u0006\u001c\u0007.\u001a#jg\u0006\u0014G.\u001a3!\u0003\u0015\u0019\u0017m\u00195f!\r\u0011Y%M\u0007\u0002\u0017\t)1-Y2iKN\u0019\u0011G!\u0015\u0011\r\u0005u$1\u000bB,\u0013\u0011\u0011)&a \u0003!\rc\u0017m]:WC2,XmQ8na\u0006$\bC\u0002B-\u0005?\u0012\u0019\'\u0004\u0002\u0003\\)\u0019!QL7\u0002\u0007I,g-\u0003\u0003\u0003b\tm#!D,fC.\u0014VMZ3sK:\u001cW\r\r\u0003\u0003f\t%\u0004\u0003B&\u0001\u0005O\u00022a\u0014B5\t)\u0011Y\'MA\u0001\u0002\u0003\u0015\tA\u0015\u0002\u0004?\u00122DC\u0001B%\u00031\u0019w.\u001c9vi\u00164\u0016\r\\;f)\u0011\u0011\u0019Ha \u0011\r\te#q\fB;a\u0011\u00119Ha\u001f\u0011\t-\u0003!\u0011\u0010\t\u0004\u001f\nmDA\u0003B?g\u0005\u0005\t\u0011!B\u0001%\n\u0019q\f\n\u001d\t\r!\u001c\u0004\u0019\u0001BAa\u0011\u0011\u0019Ia\"\u0011\t1\f(Q\u0011\t\u0004\u001f\n\u001dEa\u0003BE\u0005\u007f\n\t\u0011!A\u0003\u0002I\u00131a\u0018\u00138\u0003)\u0019w.\u001c9vi\u0016$\u0016m\u001a\u000b\u0005\u0005\u001f\u0013I\n\r\u0003\u0003\u0012\nU\u0005\u0003B&\u0001\u0005\'\u00032a\u0014BK\t)\u00119\nNA\u0001\u0002\u0003\u0015\tA\u0015\u0002\u0005?\u0012\n\u0004\u0007\u0003\u0004ii\u0001\u0007!1\u0014\u0019\u0005\u0005;\u0013\t\u000b\u0005\u0003mc\n}\u0005cA(\u0003\"\u0012Y!1\u0015BM\u0003\u0003\u0005\tQ!\u0001S\u0005\ryF%O\u0001\u0012aJLW.\u001b;jm\u0016\u001cE.Y:t)\u0006<W\u0003\u0002BU\u0005\u0007$BAa+\u00036B\"!Q\u0016BY!\u0011Y\u0005Aa,\u0011\u0007=\u0013\t\f\u0002\u0006\u00034V\n\t\u0011!A\u0003\u0002I\u0013Aa\u0018\u00132e!1\u0001.\u000ea\u0001\u0005o\u0003DA!/\u0003@B1\u0011\u0011\u0007B^\u0005{K1A]A\"!\ry%q\u0018\u0003\f\u0005\u0003\u0014),!A\u0001\u0002\u000b\u0005!K\u0001\u0003`IE\nD!B)6\u0005\u0004\u0011&aD$f]\u0016\u0014\u0018nY\"mCN\u001cH+Y4\u0016\t\t%\'qZ\n\u0005m\u0019\u0013Y\r\u0005\u0003L\u0001\t5\u0007cA(\u0003P\u0012)\u0011K\u000eb\u0001%V\u0011!1\u001b\u0019\u0005\u0005+\u0014I\u000e\u0005\u0003mc\n]\u0007cA(\u0003Z\u0012Q!1\u001c\u001d\u0002\u0002\u0003\u0005)\u0011\u0001*\u0003\t}#\u0013gM\u0001\u000eeVtG/[7f\u00072\f7o\u001d\u0011\u0015\t\t\u0005(1\u001d\t\u0006\u0005\u00172$Q\u001a\u0005\u0007Qf\u0002\rA!:1\t\t\u001d(1\u001e\t\u0005YF\u0014I\u000fE\u0002P\u0005W$1Ba7\u0003d\u0006\u0005\t\u0011!B\u0001%R!!q\u001eBy!\u00119%P!4\t\r}T\u0004\u0019AA\u0001Q\u001d1$Q\u001fB~\u0005{\u00042a\u0012B|\u0013\r\u0011I0\u0011\u0002\u0011\'\u0016\u0014\u0018.\u00197WKJ\u001c\u0018n\u001c8V\u0013\u0012\u000bQA^1mk\u0016t\u0012!A\u0001\u0006CB\u0004H._\u000b\u0005\u0007\u0007\u0019I\u0001\u0006\u0003\u0004\u0006\r-\u0001\u0003B&\u0001\u0007\u000f\u00012aTB\u0005\t\u0015\t6H1\u0001S\u0011\u001d\u0019ia\u000fa\u0001\u0007\u001f\tQB];oi&lWm\u00117bgN\f\u0004\u0007BB\t\u0007+\u0001B\u0001\\9\u0004\u0014A\u0019qj!\u0006\u0005\u0017\r]11BA\u0001\u0002\u0003\u0015\tA\u0015\u0002\u0005?\u0012\nD\'\u0006\u0003\u0004\u001c\rEB\u0003BB\u000f\u0007S\u0001RaRA\u0007\u0007?\u0001Da!\t\u0004&A1\u0011\u0011\u0007B^\u0007G\u00012aTB\u0013\t)\u00199\u0003PA\u0001\u0002\u0003\u0015\tA\u0015\u0002\u0005?\u0012\nT\u0007C\u0004\u0004,q\u0002\ra!\f\u0002\t\r$\u0018m\u001a\t\u0005\u0017\u0002\u0019y\u0003E\u0002P\u0007c!Q!\u0015\u001fC\u0002I\u000bAb\u001e:ji\u0016\u0014V\r\u001d7bG\u0016$\"!!\u001d"
    )
  ScalaInlineInfo: length = 0x59 (unknown attribute)
   01 00 00 11 00 EB 00 EC 01 00 B3 00 A3 00 00 B1
   00 B2 01 00 B7 00 A3 00 00 B6 00 B2 01 00 BD 00
   BE 00 00 BB 00 BC 01 00 8C 00 8D 00 00 89 00 8A
   01 00 CD 00 CE 01 00 78 00 79 00 00 C9 00 CA 00
   00 C7 00 C8 01 00 9A 00 9B 00 00 97 00 98 01 00
   7E 00 3F 00 00 7B 00 7C 01
  ScalaSig: length = 0x3 (unknown attribute)
   05 02 00
