Classfile /Users/mw/Projects/slang-braindump/.jar/jar11/assemble/slang-braindump/assemble/content/scala/reflect/ManifestFactory$BooleanManifest.class
  Last modified May 29, 2022; size 2550 bytes
  SHA-256 checksum fbabe3da927c32e688e214f9b8ee2c72cb67e35c8769bf829b696f41120cc9cd
  Compiled from "Manifest.scala"
public final class scala.reflect.ManifestFactory$BooleanManifest extends scala.reflect.AnyValManifest<java.lang.Object>
  minor version: 0
  major version: 52
  flags: (0x0031) ACC_PUBLIC, ACC_FINAL, ACC_SUPER
  this_class: #2                          // scala/reflect/ManifestFactory$BooleanManifest
  super_class: #5                         // scala/reflect/AnyValManifest
  interfaces: 0, fields: 1, methods: 8, attributes: 5
Constant pool:
    #1 = Utf8               scala/reflect/ManifestFactory$BooleanManifest
    #2 = Class              #1            // scala/reflect/ManifestFactory$BooleanManifest
    #3 = Utf8               Lscala/reflect/AnyValManifest<Ljava/lang/Object;>;
    #4 = Utf8               scala/reflect/AnyValManifest
    #5 = Class              #4            // scala/reflect/AnyValManifest
    #6 = Utf8               Manifest.scala
    #7 = Utf8               scala/collection/mutable/ArrayBuilder$ofBoolean
    #8 = Class              #7            // scala/collection/mutable/ArrayBuilder$ofBoolean
    #9 = Utf8               scala/collection/mutable/ArrayBuilder
   #10 = Class              #9            // scala/collection/mutable/ArrayBuilder
   #11 = Utf8               ofBoolean
   #12 = Utf8               scala/collection/mutable/ArraySeq$ofBoolean
   #13 = Class              #12           // scala/collection/mutable/ArraySeq$ofBoolean
   #14 = Utf8               scala/collection/mutable/ArraySeq
   #15 = Class              #14           // scala/collection/mutable/ArraySeq
   #16 = Utf8               scala/reflect/ManifestFactory
   #17 = Class              #16           // scala/reflect/ManifestFactory
   #18 = Utf8               BooleanManifest
   #19 = Utf8               serialVersionUID
   #20 = Utf8               J
   #21 = Long               1l
   #23 = Utf8               runtimeClass
   #24 = Utf8               ()Ljava/lang/Class;
   #25 = Utf8               ()Ljava/lang/Class<Ljava/lang/Boolean;>;
   #26 = Utf8               java/lang/Boolean
   #27 = Class              #26           // java/lang/Boolean
   #28 = Utf8               TYPE
   #29 = Utf8               Ljava/lang/Class;
   #30 = NameAndType        #28:#29       // TYPE:Ljava/lang/Class;
   #31 = Fieldref           #27.#30       // java/lang/Boolean.TYPE:Ljava/lang/Class;
   #32 = Utf8               this
   #33 = Utf8               Lscala/reflect/ManifestFactory$BooleanManifest;
   #34 = Utf8               newArray
   #35 = Utf8               (I)[Z
   #36 = Utf8               len
   #37 = Utf8               I
   #38 = Utf8               newWrappedArray
   #39 = Utf8               (I)Lscala/collection/mutable/ArraySeq;
   #40 = Utf8               (I)Lscala/collection/mutable/ArraySeq<Ljava/lang/Object;>;
   #41 = Utf8               <init>
   #42 = Utf8               ([Z)V
   #43 = NameAndType        #41:#42       // "<init>":([Z)V
   #44 = Methodref          #13.#43       // scala/collection/mutable/ArraySeq$ofBoolean."<init>":([Z)V
   #45 = Utf8               newArrayBuilder
   #46 = Utf8               ()Lscala/collection/mutable/ArrayBuilder;
   #47 = Utf8               ()Lscala/collection/mutable/ArrayBuilder<Ljava/lang/Object;>;
   #48 = Utf8               ()V
   #49 = NameAndType        #41:#48       // "<init>":()V
   #50 = Methodref          #8.#49        // scala/collection/mutable/ArrayBuilder$ofBoolean."<init>":()V
   #51 = Utf8               unapply
   #52 = Utf8               (Ljava/lang/Object;)Lscala/Option;
   #53 = Utf8               (Ljava/lang/Object;)Lscala/Option<Ljava/lang/Object;>;
   #54 = Utf8               x
   #55 = Utf8               scala/runtime/BoxesRunTime
   #56 = Class              #55           // scala/runtime/BoxesRunTime
   #57 = Utf8               unboxToBoolean
   #58 = Utf8               (Ljava/lang/Object;)Z
   #59 = NameAndType        #57:#58       // unboxToBoolean:(Ljava/lang/Object;)Z
   #60 = Methodref          #56.#59       // scala/runtime/BoxesRunTime.unboxToBoolean:(Ljava/lang/Object;)Z
   #61 = Utf8               scala/Some
   #62 = Class              #61           // scala/Some
   #63 = Utf8               valueOf
   #64 = Utf8               (Z)Ljava/lang/Boolean;
   #65 = NameAndType        #63:#64       // valueOf:(Z)Ljava/lang/Boolean;
   #66 = Methodref          #27.#65       // java/lang/Boolean.valueOf:(Z)Ljava/lang/Boolean;
   #67 = Utf8               (Ljava/lang/Object;)V
   #68 = NameAndType        #41:#67       // "<init>":(Ljava/lang/Object;)V
   #69 = Methodref          #62.#68       // scala/Some."<init>":(Ljava/lang/Object;)V
   #70 = Utf8               scala/None$
   #71 = Class              #70           // scala/None$
   #72 = Utf8               MODULE$
   #73 = Utf8               Lscala/None$;
   #74 = NameAndType        #72:#73       // MODULE$:Lscala/None$;
   #75 = Fieldref           #71.#74       // scala/None$.MODULE$:Lscala/None$;
   #76 = Utf8               Ljava/lang/Object;
   #77 = Utf8               scala/Option
   #78 = Class              #77           // scala/Option
   #79 = Utf8               readResolve
   #80 = Utf8               ()Ljava/lang/Object;
   #81 = Utf8               scala/reflect/Manifest$
   #82 = Class              #81           // scala/reflect/Manifest$
   #83 = Utf8               Lscala/reflect/Manifest$;
   #84 = NameAndType        #72:#83       // MODULE$:Lscala/reflect/Manifest$;
   #85 = Fieldref           #82.#84       // scala/reflect/Manifest$.MODULE$:Lscala/reflect/Manifest$;
   #86 = Utf8               Boolean
   #87 = Utf8               ()Lscala/reflect/ManifestFactory$BooleanManifest;
   #88 = NameAndType        #86:#87       // Boolean:()Lscala/reflect/ManifestFactory$BooleanManifest;
   #89 = Methodref          #82.#88       // scala/reflect/Manifest$.Boolean:()Lscala/reflect/ManifestFactory$BooleanManifest;
   #90 = Utf8               (I)Ljava/lang/Object;
   #91 = NameAndType        #34:#35       // newArray:(I)[Z
   #92 = Methodref          #2.#91        // scala/reflect/ManifestFactory$BooleanManifest.newArray:(I)[Z
   #93 = String             #86           // Boolean
   #94 = Utf8               (Ljava/lang/String;)V
   #95 = NameAndType        #41:#94       // "<init>":(Ljava/lang/String;)V
   #96 = Methodref          #5.#95        // scala/reflect/AnyValManifest."<init>":(Ljava/lang/String;)V
   #97 = Utf8               ConstantValue
   #98 = Utf8               Code
   #99 = Utf8               LineNumberTable
  #100 = Utf8               LocalVariableTable
  #101 = Utf8               Signature
  #102 = Utf8               MethodParameters
  #103 = Utf8               StackMapTable
  #104 = Utf8               InnerClasses
  #105 = Utf8               SourceFile
  #106 = Utf8               ScalaInlineInfo
  #107 = Utf8               Scala
{
  private static final long serialVersionUID;
    descriptor: J
    flags: (0x001a) ACC_PRIVATE, ACC_STATIC, ACC_FINAL
    ConstantValue: long 1l

  public java.lang.Class<java.lang.Boolean> runtimeClass();
    descriptor: ()Ljava/lang/Class;
    flags: (0x0001) ACC_PUBLIC
    Code:
      stack=1, locals=1, args_size=1
         0: getstatic     #31                 // Field java/lang/Boolean.TYPE:Ljava/lang/Class;
         3: areturn
      LineNumberTable:
        line 289: 0
      LocalVariableTable:
        Start  Length  Slot  Name   Signature
            0       4     0  this   Lscala/reflect/ManifestFactory$BooleanManifest;
    Signature: #25                          // ()Ljava/lang/Class<Ljava/lang/Boolean;>;

  public boolean[] newArray(int);
    descriptor: (I)[Z
    flags: (0x0001) ACC_PUBLIC
    Code:
      stack=1, locals=2, args_size=2
         0: iload_1
         1: newarray       boolean
         3: areturn
      LineNumberTable:
        line 290: 0
      LocalVariableTable:
        Start  Length  Slot  Name   Signature
            0       4     0  this   Lscala/reflect/ManifestFactory$BooleanManifest;
            0       4     1   len   I
    MethodParameters:
      Name                           Flags
      len                            final

  public scala.collection.mutable.ArraySeq<java.lang.Object> newWrappedArray(int);
    descriptor: (I)Lscala/collection/mutable/ArraySeq;
    flags: (0x0001) ACC_PUBLIC
    Code:
      stack=3, locals=2, args_size=2
         0: new           #13                 // class scala/collection/mutable/ArraySeq$ofBoolean
         3: dup
         4: iload_1
         5: newarray       boolean
         7: invokespecial #44                 // Method scala/collection/mutable/ArraySeq$ofBoolean."<init>":([Z)V
        10: areturn
      LineNumberTable:
        line 291: 0
      LocalVariableTable:
        Start  Length  Slot  Name   Signature
            0      11     0  this   Lscala/reflect/ManifestFactory$BooleanManifest;
            0      11     1   len   I
    Signature: #40                          // (I)Lscala/collection/mutable/ArraySeq<Ljava/lang/Object;>;
    MethodParameters:
      Name                           Flags
      len                            final

  public scala.collection.mutable.ArrayBuilder<java.lang.Object> newArrayBuilder();
    descriptor: ()Lscala/collection/mutable/ArrayBuilder;
    flags: (0x0001) ACC_PUBLIC
    Code:
      stack=2, locals=1, args_size=1
         0: new           #8                  // class scala/collection/mutable/ArrayBuilder$ofBoolean
         3: dup
         4: invokespecial #50                 // Method scala/collection/mutable/ArrayBuilder$ofBoolean."<init>":()V
         7: areturn
      LineNumberTable:
        line 292: 0
      LocalVariableTable:
        Start  Length  Slot  Name   Signature
            0       8     0  this   Lscala/reflect/ManifestFactory$BooleanManifest;
    Signature: #47                          // ()Lscala/collection/mutable/ArrayBuilder<Ljava/lang/Object;>;

  public scala.Option<java.lang.Object> unapply(java.lang.Object);
    descriptor: (Ljava/lang/Object;)Lscala/Option;
    flags: (0x0001) ACC_PUBLIC
    Code:
      stack=3, locals=4, args_size=2
         0: aload_1
         1: instanceof    #27                 // class java/lang/Boolean
         4: ifeq          27
         7: aload_1
         8: invokestatic  #60                 // Method scala/runtime/BoxesRunTime.unboxToBoolean:(Ljava/lang/Object;)Z
        11: istore_3
        12: new           #62                 // class scala/Some
        15: dup
        16: iload_3
        17: invokestatic  #66                 // Method java/lang/Boolean.valueOf:(Z)Ljava/lang/Boolean;
        20: invokespecial #69                 // Method scala/Some."<init>":(Ljava/lang/Object;)V
        23: astore_2
        24: goto          31
        27: getstatic     #75                 // Field scala/None$.MODULE$:Lscala/None$;
        30: astore_2
        31: aload_2
        32: areturn
      StackMapTable: number_of_entries = 2
        frame_type = 27 /* same */
        frame_type = 252 /* append */
          offset_delta = 3
          locals = [ class scala/Option ]
      LineNumberTable:
        line 295: 0
        line 296: 27
        line 294: 31
      LocalVariableTable:
        Start  Length  Slot  Name   Signature
            0      33     0  this   Lscala/reflect/ManifestFactory$BooleanManifest;
            0      33     1     x   Ljava/lang/Object;
    Signature: #53                          // (Ljava/lang/Object;)Lscala/Option<Ljava/lang/Object;>;
    MethodParameters:
      Name                           Flags
      x                              final

  private java.lang.Object readResolve();
    descriptor: ()Ljava/lang/Object;
    flags: (0x0002) ACC_PRIVATE
    Code:
      stack=1, locals=1, args_size=1
         0: getstatic     #85                 // Field scala/reflect/Manifest$.MODULE$:Lscala/reflect/Manifest$;
         3: invokevirtual #89                 // Method scala/reflect/Manifest$.Boolean:()Lscala/reflect/ManifestFactory$BooleanManifest;
         6: areturn
      LineNumberTable:
        line 299: 0
      LocalVariableTable:
        Start  Length  Slot  Name   Signature
            0       7     0  this   Lscala/reflect/ManifestFactory$BooleanManifest;

  public java.lang.Object newArray(int);
    descriptor: (I)Ljava/lang/Object;
    flags: (0x1041) ACC_PUBLIC, ACC_BRIDGE, ACC_SYNTHETIC
    Code:
      stack=2, locals=2, args_size=2
         0: aload_0
         1: iload_1
         2: invokevirtual #92                 // Method newArray:(I)[Z
         5: areturn
      LineNumberTable:
        line 288: 0
      LocalVariableTable:
        Start  Length  Slot  Name   Signature
            0       6     0  this   Lscala/reflect/ManifestFactory$BooleanManifest;
            0       6     1   len   I
    MethodParameters:
      Name                           Flags
      len                            final

  public scala.reflect.ManifestFactory$BooleanManifest();
    descriptor: ()V
    flags: (0x0001) ACC_PUBLIC
    Code:
      stack=2, locals=1, args_size=1
         0: aload_0
         1: ldc           #93                 // String Boolean
         3: invokespecial #96                 // Method scala/reflect/AnyValManifest."<init>":(Ljava/lang/String;)V
         6: return
      LineNumberTable:
        line 288: 0
      LocalVariableTable:
        Start  Length  Slot  Name   Signature
            0       7     0  this   Lscala/reflect/ManifestFactory$BooleanManifest;
}
InnerClasses:
  public static #11= #8 of #10;           // ofBoolean=class scala/collection/mutable/ArrayBuilder$ofBoolean of class scala/collection/mutable/ArrayBuilder
  public static final #11= #13 of #15;    // ofBoolean=class scala/collection/mutable/ArraySeq$ofBoolean of class scala/collection/mutable/ArraySeq
  public static final #18= #2 of #17;     // BooleanManifest=class scala/reflect/ManifestFactory$BooleanManifest of class scala/reflect/ManifestFactory
Signature: #3                           // Lscala/reflect/AnyValManifest<Ljava/lang/Object;>;
SourceFile: "Manifest.scala"
  ScalaInlineInfo: length = 0x2C (unknown attribute)
   01 01 00 08 00 29 00 30 01 00 22 00 5A 05 00 22
   00 23 05 00 2D 00 2E 01 00 26 00 27 01 00 4F 00
   50 01 00 17 00 18 01 00 33 00 34 01
  Scala: length = 0x0 (unknown attribute)

