Classfile /Users/mw/Projects/slang-braindump/.jar/jar11/assemble/slang-braindump/assemble/content/scala/reflect/ManifestFactory$UnitManifest.class
  Last modified May 29, 2022; size 2993 bytes
  SHA-256 checksum f8fbdea6a78a23563d608fb8395fd18efb20608c06a4d79a41a1db24b08865be
  Compiled from "Manifest.scala"
public final class scala.reflect.ManifestFactory$UnitManifest extends scala.reflect.AnyValManifest<scala.runtime.BoxedUnit>
  minor version: 0
  major version: 52
  flags: (0x0031) ACC_PUBLIC, ACC_FINAL, ACC_SUPER
  this_class: #2                          // scala/reflect/ManifestFactory$UnitManifest
  super_class: #5                         // scala/reflect/AnyValManifest
  interfaces: 0, fields: 1, methods: 9, attributes: 5
Constant pool:
    #1 = Utf8               scala/reflect/ManifestFactory$UnitManifest
    #2 = Class              #1            // scala/reflect/ManifestFactory$UnitManifest
    #3 = Utf8               Lscala/reflect/AnyValManifest<Lscala/runtime/BoxedUnit;>;
    #4 = Utf8               scala/reflect/AnyValManifest
    #5 = Class              #4            // scala/reflect/AnyValManifest
    #6 = Utf8               Manifest.scala
    #7 = Utf8               scala/collection/mutable/ArrayBuilder$ofUnit
    #8 = Class              #7            // scala/collection/mutable/ArrayBuilder$ofUnit
    #9 = Utf8               scala/collection/mutable/ArrayBuilder
   #10 = Class              #9            // scala/collection/mutable/ArrayBuilder
   #11 = Utf8               ofUnit
   #12 = Utf8               scala/collection/mutable/ArraySeq$ofUnit
   #13 = Class              #12           // scala/collection/mutable/ArraySeq$ofUnit
   #14 = Utf8               scala/collection/mutable/ArraySeq
   #15 = Class              #14           // scala/collection/mutable/ArraySeq
   #16 = Utf8               scala/reflect/ManifestFactory
   #17 = Class              #16           // scala/reflect/ManifestFactory
   #18 = Utf8               UnitManifest
   #19 = Utf8               serialVersionUID
   #20 = Utf8               J
   #21 = Long               1l
   #23 = Utf8               runtimeClass
   #24 = Utf8               ()Ljava/lang/Class;
   #25 = Utf8               ()Ljava/lang/Class<Ljava/lang/Void;>;
   #26 = Utf8               java/lang/Void
   #27 = Class              #26           // java/lang/Void
   #28 = Utf8               TYPE
   #29 = Utf8               Ljava/lang/Class;
   #30 = NameAndType        #28:#29       // TYPE:Ljava/lang/Class;
   #31 = Fieldref           #27.#30       // java/lang/Void.TYPE:Ljava/lang/Class;
   #32 = Utf8               this
   #33 = Utf8               Lscala/reflect/ManifestFactory$UnitManifest;
   #34 = Utf8               newArray
   #35 = Utf8               (I)[Lscala/runtime/BoxedUnit;
   #36 = Utf8               len
   #37 = Utf8               scala/runtime/BoxedUnit
   #38 = Class              #37           // scala/runtime/BoxedUnit
   #39 = Utf8               I
   #40 = Utf8               newWrappedArray
   #41 = Utf8               (I)Lscala/collection/mutable/ArraySeq;
   #42 = Utf8               (I)Lscala/collection/mutable/ArraySeq<Lscala/runtime/BoxedUnit;>;
   #43 = Utf8               <init>
   #44 = Utf8               ([Lscala/runtime/BoxedUnit;)V
   #45 = NameAndType        #43:#44       // "<init>":([Lscala/runtime/BoxedUnit;)V
   #46 = Methodref          #13.#45       // scala/collection/mutable/ArraySeq$ofUnit."<init>":([Lscala/runtime/BoxedUnit;)V
   #47 = Utf8               newArrayBuilder
   #48 = Utf8               ()Lscala/collection/mutable/ArrayBuilder;
   #49 = Utf8               ()Lscala/collection/mutable/ArrayBuilder<Lscala/runtime/BoxedUnit;>;
   #50 = Utf8               ()V
   #51 = NameAndType        #43:#50       // "<init>":()V
   #52 = Methodref          #8.#51        // scala/collection/mutable/ArrayBuilder$ofUnit."<init>":()V
   #53 = Utf8               arrayClass
   #54 = Utf8               (Ljava/lang/Class;)Ljava/lang/Class;
   #55 = Utf8               <T:Ljava/lang/Object;>(Ljava/lang/Class<*>;)Ljava/lang/Class<Ljava/lang/Object;>;
   #56 = Utf8               tp
   #57 = Utf8               [Lscala/runtime/BoxedUnit;
   #58 = Class              #57           // "[Lscala/runtime/BoxedUnit;"
   #59 = Utf8               scala/reflect/ClassManifestDeprecatedApis
   #60 = Class              #59           // scala/reflect/ClassManifestDeprecatedApis
   #61 = Utf8               arrayClass$
   #62 = Utf8               (Lscala/reflect/ClassManifestDeprecatedApis;Ljava/lang/Class;)Ljava/lang/Class;
   #63 = NameAndType        #61:#62       // arrayClass$:(Lscala/reflect/ClassManifestDeprecatedApis;Ljava/lang/Class;)Ljava/lang/Class;
   #64 = InterfaceMethodref #60.#63       // scala/reflect/ClassManifestDeprecatedApis.arrayClass$:(Lscala/reflect/ClassManifestDeprecatedApis;Ljava/lang/Class;)Ljava/lang/Class;
   #65 = Utf8               unapply
   #66 = Utf8               (Ljava/lang/Object;)Lscala/Option;
   #67 = Utf8               (Ljava/lang/Object;)Lscala/Option<Lscala/runtime/BoxedUnit;>;
   #68 = Utf8               x
   #69 = Utf8               UNIT
   #70 = Utf8               Lscala/runtime/BoxedUnit;
   #71 = NameAndType        #69:#70       // UNIT:Lscala/runtime/BoxedUnit;
   #72 = Fieldref           #38.#71       // scala/runtime/BoxedUnit.UNIT:Lscala/runtime/BoxedUnit;
   #73 = Utf8               scala/Some
   #74 = Class              #73           // scala/Some
   #75 = Utf8               (Ljava/lang/Object;)V
   #76 = NameAndType        #43:#75       // "<init>":(Ljava/lang/Object;)V
   #77 = Methodref          #74.#76       // scala/Some."<init>":(Ljava/lang/Object;)V
   #78 = Utf8               scala/None$
   #79 = Class              #78           // scala/None$
   #80 = Utf8               MODULE$
   #81 = Utf8               Lscala/None$;
   #82 = NameAndType        #80:#81       // MODULE$:Lscala/None$;
   #83 = Fieldref           #79.#82       // scala/None$.MODULE$:Lscala/None$;
   #84 = Utf8               Ljava/lang/Object;
   #85 = Utf8               scala/Option
   #86 = Class              #85           // scala/Option
   #87 = Utf8               readResolve
   #88 = Utf8               ()Ljava/lang/Object;
   #89 = Utf8               scala/reflect/Manifest$
   #90 = Class              #89           // scala/reflect/Manifest$
   #91 = Utf8               Lscala/reflect/Manifest$;
   #92 = NameAndType        #80:#91       // MODULE$:Lscala/reflect/Manifest$;
   #93 = Fieldref           #90.#92       // scala/reflect/Manifest$.MODULE$:Lscala/reflect/Manifest$;
   #94 = Utf8               Unit
   #95 = Utf8               ()Lscala/reflect/ManifestFactory$UnitManifest;
   #96 = NameAndType        #94:#95       // Unit:()Lscala/reflect/ManifestFactory$UnitManifest;
   #97 = Methodref          #90.#96       // scala/reflect/Manifest$.Unit:()Lscala/reflect/ManifestFactory$UnitManifest;
   #98 = Utf8               (I)Ljava/lang/Object;
   #99 = NameAndType        #34:#35       // newArray:(I)[Lscala/runtime/BoxedUnit;
  #100 = Methodref          #2.#99        // scala/reflect/ManifestFactory$UnitManifest.newArray:(I)[Lscala/runtime/BoxedUnit;
  #101 = String             #94           // Unit
  #102 = Utf8               (Ljava/lang/String;)V
  #103 = NameAndType        #43:#102      // "<init>":(Ljava/lang/String;)V
  #104 = Methodref          #5.#103       // scala/reflect/AnyValManifest."<init>":(Ljava/lang/String;)V
  #105 = Utf8               ConstantValue
  #106 = Utf8               Code
  #107 = Utf8               LineNumberTable
  #108 = Utf8               LocalVariableTable
  #109 = Utf8               Signature
  #110 = Utf8               MethodParameters
  #111 = Utf8               StackMapTable
  #112 = Utf8               InnerClasses
  #113 = Utf8               SourceFile
  #114 = Utf8               ScalaInlineInfo
  #115 = Utf8               Scala
{
  private static final long serialVersionUID;
    descriptor: J
    flags: (0x001a) ACC_PRIVATE, ACC_STATIC, ACC_FINAL
    ConstantValue: long 1l

  public java.lang.Class<java.lang.Void> runtimeClass();
    descriptor: ()Ljava/lang/Class;
    flags: (0x0001) ACC_PUBLIC
    Code:
      stack=1, locals=1, args_size=1
         0: getstatic     #31                 // Field java/lang/Void.TYPE:Ljava/lang/Class;
         3: areturn
      LineNumberTable:
        line 305: 0
      LocalVariableTable:
        Start  Length  Slot  Name   Signature
            0       4     0  this   Lscala/reflect/ManifestFactory$UnitManifest;
    Signature: #25                          // ()Ljava/lang/Class<Ljava/lang/Void;>;

  public scala.runtime.BoxedUnit[] newArray(int);
    descriptor: (I)[Lscala/runtime/BoxedUnit;
    flags: (0x0001) ACC_PUBLIC
    Code:
      stack=1, locals=2, args_size=2
         0: iload_1
         1: anewarray     #38                 // class scala/runtime/BoxedUnit
         4: areturn
      LineNumberTable:
        line 306: 0
      LocalVariableTable:
        Start  Length  Slot  Name   Signature
            0       5     0  this   Lscala/reflect/ManifestFactory$UnitManifest;
            0       5     1   len   I
    MethodParameters:
      Name                           Flags
      len                            final

  public scala.collection.mutable.ArraySeq<scala.runtime.BoxedUnit> newWrappedArray(int);
    descriptor: (I)Lscala/collection/mutable/ArraySeq;
    flags: (0x0001) ACC_PUBLIC
    Code:
      stack=3, locals=2, args_size=2
         0: new           #13                 // class scala/collection/mutable/ArraySeq$ofUnit
         3: dup
         4: iload_1
         5: anewarray     #38                 // class scala/runtime/BoxedUnit
         8: invokespecial #46                 // Method scala/collection/mutable/ArraySeq$ofUnit."<init>":([Lscala/runtime/BoxedUnit;)V
        11: areturn
      LineNumberTable:
        line 307: 0
      LocalVariableTable:
        Start  Length  Slot  Name   Signature
            0      12     0  this   Lscala/reflect/ManifestFactory$UnitManifest;
            0      12     1   len   I
    Signature: #42                          // (I)Lscala/collection/mutable/ArraySeq<Lscala/runtime/BoxedUnit;>;
    MethodParameters:
      Name                           Flags
      len                            final

  public scala.collection.mutable.ArrayBuilder<scala.runtime.BoxedUnit> newArrayBuilder();
    descriptor: ()Lscala/collection/mutable/ArrayBuilder;
    flags: (0x0001) ACC_PUBLIC
    Code:
      stack=2, locals=1, args_size=1
         0: new           #8                  // class scala/collection/mutable/ArrayBuilder$ofUnit
         3: dup
         4: invokespecial #52                 // Method scala/collection/mutable/ArrayBuilder$ofUnit."<init>":()V
         7: areturn
      LineNumberTable:
        line 308: 0
      LocalVariableTable:
        Start  Length  Slot  Name   Signature
            0       8     0  this   Lscala/reflect/ManifestFactory$UnitManifest;
    Signature: #49                          // ()Lscala/collection/mutable/ArrayBuilder<Lscala/runtime/BoxedUnit;>;

  public <T extends java.lang.Object> java.lang.Class<java.lang.Object> arrayClass(java.lang.Class<?>);
    descriptor: (Ljava/lang/Class;)Ljava/lang/Class;
    flags: (0x0001) ACC_PUBLIC
    Code:
      stack=2, locals=2, args_size=2
         0: aload_1
         1: getstatic     #31                 // Field java/lang/Void.TYPE:Ljava/lang/Class;
         4: if_acmpne     10
         7: ldc           #58                 // class "[Lscala/runtime/BoxedUnit;"
         9: areturn
        10: aload_0
        11: aload_1
        12: invokestatic  #64                 // InterfaceMethod scala/reflect/ClassManifestDeprecatedApis.arrayClass$:(Lscala/reflect/ClassManifestDeprecatedApis;Ljava/lang/Class;)Ljava/lang/Class;
        15: areturn
      StackMapTable: number_of_entries = 1
        frame_type = 10 /* same */
      LineNumberTable:
        line 310: 0
        line 305: 1
        line 310: 4
        line 311: 10
      LocalVariableTable:
        Start  Length  Slot  Name   Signature
            0      16     0  this   Lscala/reflect/ManifestFactory$UnitManifest;
            0      16     1    tp   Ljava/lang/Class;
    Signature: #55                          // <T:Ljava/lang/Object;>(Ljava/lang/Class<*>;)Ljava/lang/Class<Ljava/lang/Object;>;
    MethodParameters:
      Name                           Flags
      tp                             final

  public scala.Option<scala.runtime.BoxedUnit> unapply(java.lang.Object);
    descriptor: (Ljava/lang/Object;)Lscala/Option;
    flags: (0x0001) ACC_PUBLIC
    Code:
      stack=3, locals=4, args_size=2
         0: aload_1
         1: instanceof    #38                 // class scala/runtime/BoxedUnit
         4: ifeq          23
         7: getstatic     #72                 // Field scala/runtime/BoxedUnit.UNIT:Lscala/runtime/BoxedUnit;
        10: astore_3
        11: new           #74                 // class scala/Some
        14: dup
        15: aload_3
        16: invokespecial #77                 // Method scala/Some."<init>":(Ljava/lang/Object;)V
        19: astore_2
        20: goto          27
        23: getstatic     #83                 // Field scala/None$.MODULE$:Lscala/None$;
        26: astore_2
        27: aload_2
        28: areturn
      StackMapTable: number_of_entries = 2
        frame_type = 23 /* same */
        frame_type = 252 /* append */
          offset_delta = 3
          locals = [ class scala/Option ]
      LineNumberTable:
        line 314: 0
        line 315: 23
        line 313: 27
      LocalVariableTable:
        Start  Length  Slot  Name   Signature
            0      29     0  this   Lscala/reflect/ManifestFactory$UnitManifest;
            0      29     1     x   Ljava/lang/Object;
    Signature: #67                          // (Ljava/lang/Object;)Lscala/Option<Lscala/runtime/BoxedUnit;>;
    MethodParameters:
      Name                           Flags
      x                              final

  private java.lang.Object readResolve();
    descriptor: ()Ljava/lang/Object;
    flags: (0x0002) ACC_PRIVATE
    Code:
      stack=1, locals=1, args_size=1
         0: getstatic     #93                 // Field scala/reflect/Manifest$.MODULE$:Lscala/reflect/Manifest$;
         3: invokevirtual #97                 // Method scala/reflect/Manifest$.Unit:()Lscala/reflect/ManifestFactory$UnitManifest;
         6: areturn
      LineNumberTable:
        line 318: 0
      LocalVariableTable:
        Start  Length  Slot  Name   Signature
            0       7     0  this   Lscala/reflect/ManifestFactory$UnitManifest;

  public java.lang.Object newArray(int);
    descriptor: (I)Ljava/lang/Object;
    flags: (0x1041) ACC_PUBLIC, ACC_BRIDGE, ACC_SYNTHETIC
    Code:
      stack=2, locals=2, args_size=2
         0: aload_0
         1: iload_1
         2: invokevirtual #100                // Method newArray:(I)[Lscala/runtime/BoxedUnit;
         5: areturn
      LineNumberTable:
        line 304: 0
      LocalVariableTable:
        Start  Length  Slot  Name   Signature
            0       6     0  this   Lscala/reflect/ManifestFactory$UnitManifest;
            0       6     1   len   I
    MethodParameters:
      Name                           Flags
      len                            final

  public scala.reflect.ManifestFactory$UnitManifest();
    descriptor: ()V
    flags: (0x0001) ACC_PUBLIC
    Code:
      stack=2, locals=1, args_size=1
         0: aload_0
         1: ldc           #101                // String Unit
         3: invokespecial #104                // Method scala/reflect/AnyValManifest."<init>":(Ljava/lang/String;)V
         6: return
      LineNumberTable:
        line 304: 0
      LocalVariableTable:
        Start  Length  Slot  Name   Signature
            0       7     0  this   Lscala/reflect/ManifestFactory$UnitManifest;
}
InnerClasses:
  public static final #11= #8 of #10;     // ofUnit=class scala/collection/mutable/ArrayBuilder$ofUnit of class scala/collection/mutable/ArrayBuilder
  public static final #11= #13 of #15;    // ofUnit=class scala/collection/mutable/ArraySeq$ofUnit of class scala/collection/mutable/ArraySeq
  public static final #18= #2 of #17;     // UnitManifest=class scala/reflect/ManifestFactory$UnitManifest of class scala/reflect/ManifestFactory
Signature: #3                           // Lscala/reflect/AnyValManifest<Lscala/runtime/BoxedUnit;>;
SourceFile: "Manifest.scala"
  ScalaInlineInfo: length = 0x31 (unknown attribute)
   01 01 00 09 00 2B 00 32 01 00 35 00 36 01 00 22
   00 62 05 00 22 00 23 05 00 2F 00 30 01 00 28 00
   29 01 00 57 00 58 01 00 17 00 18 01 00 41 00 42
   01
  Scala: length = 0x0 (unknown attribute)

