Classfile /Users/mw/Projects/slang-braindump/.jar/jar11/assemble/slang-braindump/assemble/content/scala/reflect/Manifest.class
  Last modified May 29, 2022; size 11697 bytes
  SHA-256 checksum 558fbeeff002dc92ccf240d5a08375974fd8f3e8914903228c7d033e0eb09b59
  Compiled from "Manifest.scala"
public interface scala.reflect.Manifest<T extends java.lang.Object> extends scala.reflect.ClassTag<T>
  minor version: 0
  major version: 52
  flags: (0x0601) ACC_PUBLIC, ACC_INTERFACE, ACC_ABSTRACT
  this_class: #2                          // scala/reflect/Manifest
  super_class: #5                         // java/lang/Object
  interfaces: 1, fields: 0, methods: 35, attributes: 6
Constant pool:
    #1 = Utf8               scala/reflect/Manifest
    #2 = Class              #1            // scala/reflect/Manifest
    #3 = Utf8               <T:Ljava/lang/Object;>Ljava/lang/Object;Lscala/reflect/ClassTag<TT;>;
    #4 = Utf8               java/lang/Object
    #5 = Class              #4            // java/lang/Object
    #6 = Utf8               scala/reflect/ClassTag
    #7 = Class              #6            // scala/reflect/ClassTag
    #8 = Utf8               Manifest.scala
    #9 = Utf8               Lscala/reflect/ScalaSignature;
   #10 = Utf8               bytes
   #11 = Utf8               \u0006\u0005\rmba\u0002\u001a4!\u0003\r\t\u0001\u000f\u0005\u0006)\u0002!\t!\u0016\u0005\u00063\u0002!\tE\u0017\u0005\u0006M\u0002!\te\u001a\u0005\u0006Y\u0002!\t%\u001c\u0005\u0006g\u0002!\t\u0005\u001e\u0005\u0006m\u0002!\te^\u0004\b\u0003\u0017\u0019\u0004\u0012AA\u0007\r\u0019\u00114\u0007#\u0001\u0002\u0010!9\u0011\u0011\u0005\u0005\u0005\u0002\u0005\r\u0002bBA\u0013\u0011\u0011\u0005\u0011q\u0005\u0005\n\u0003sA!\u0019!C\u0001\u0003wA\u0001\"a\u0013\tA\u0003%\u0011Q\b\u0005\n\u0003\u001bB!\u0019!C\u0001\u0003\u001fB\u0001\"a\u0016\tA\u0003%\u0011\u0011\u000b\u0005\n\u00033B!\u0019!C\u0001\u00037B\u0001\"a\u0019\tA\u0003%\u0011Q\f\u0005\n\u0003KB!\u0019!C\u0001\u0003OB\u0001\"a\u001c\tA\u0003%\u0011\u0011\u000e\u0005\n\u0003cB!\u0019!C\u0001\u0003gB\u0001\"a\u001f\tA\u0003%\u0011Q\u000f\u0005\n\u0003{B!\u0019!C\u0001\u0003\u007fB\u0001\"a\"\tA\u0003%\u0011\u0011\u0011\u0005\n\u0003\u0013C!\u0019!C\u0001\u0003\u0017C\u0001\"a%\tA\u0003%\u0011Q\u0012\u0005\n\u0003+C!\u0019!C\u0001\u0003/C\u0001\"a(\tA\u0003%\u0011\u0011\u0014\u0005\n\u0003CC!\u0019!C\u0001\u0003GC\u0001\"a+\tA\u0003%\u0011Q\u0015\u0005\n\u0003[C!\u0019!C\u0001\u0003_C\u0001\"a-\tA\u0003%\u0011\u0011\u0017\u0005\n\u0003kC!\u0019!C\u0001\u0003oC\u0001\"a2\tA\u0003%\u0011\u0011\u0018\u0005\n\u0003\u0013D!\u0019!C\u0001\u0003\u0017D\u0001\"a4\tA\u0003%\u0011Q\u001a\u0005\n\u0003#D!\u0019!C\u0001\u0003\'D\u0001\"!8\tA\u0003%\u0011Q\u001b\u0005\n\u0003?D!\u0019!C\u0001\u0003CD\u0001\"a;\tA\u0003%\u00111\u001d\u0005\n\u0003[D!\u0019!C\u0001\u0003_D\u0001\"a=\tA\u0003%\u0011\u0011\u001f\u0005\b\u0003kDA\u0011AA|\u0011\u001d\u00119\u0001\u0003C\u0001\u0005\u0013AqAa\u0002\t\t\u0003\u0011i\u0003C\u0004\u0003\b!!\tAa\u0018\t\u000f\tE\u0005\u0002\"\u0001\u0003\u0014\"9!Q\u0016\u0005\u0005\u0002\t=\u0006b\u0002B{\u0011\u0011\u0005!q\u001f\u0005\b\u00077AA\u0011AB\u000f\u0011%\u00199\u0004CA\u0001\n\u0013\u0019ID\u0001\u0005NC:Lg-Z:u\u0015\t!T\'A\u0004sK\u001adWm\u0019;\u000b\u0003Y\nQa]2bY\u0006\u001c\u0001!\u0006\u0002:\u0011N!\u0001A\u000f R!\tYD(D\u00016\u0013\tiTG\u0001\u0004B]f\u0014VM\u001a\t\u0004\u007f\r3eB\u0001!B\u001b\u0005\u0019\u0014B\u0001\"4\u0003\u001d\u0001\u0018mY6bO\u0016L!\u0001R#\u0003\u001b\rc\u0017m]:NC:Lg-Z:u\u0015\t\u00115\u0007\u0005\u0002H\u00112\u0001A!B%\u0001\u0005\u0004Q%!\u0001+\u0012\u0005-s\u0005CA\u001eM\u0013\tiUGA\u0004O_RD\u0017N\\4\u0011\u0005mz\u0015B\u0001)6\u0005\r\te.\u001f\t\u0003wIK!aU\u001b\u0003\r\u0015\u000bX/\u00197t\u0003\u0019!\u0013N\\5uIQ\ta\u000b\u0005\u0002</&\u0011\u0001,\u000e\u0002\u0005+:LG/A\u0007usB,\u0017I]4v[\u0016tGo]\u000b\u00027B\u0019ALX1\u000f\u0005mj\u0016B\u0001\"6\u0013\ty\u0006M\u0001\u0003MSN$(B\u0001\"6a\t\u0011G\rE\u0002A\u0001\r\u0004\"a\u00123\u0005\u0013\u0015\u0014\u0011\u0011!A\u0001\u0006\u0003Q%aA0%c\u0005i\u0011M\u001d:bs6\u000bg.\u001b4fgR,\u0012\u0001\u001b\t\u0004\u0001\u0002I\u0007cA\u001ek\r&\u00111.\u000e\u0002\u0006\u0003J\u0014\u0018-_\u0001\tG\u0006tW)];bYR\u0011a.\u001d\t\u0003w=L!\u0001]\u001b\u0003\u000f\t{w\u000e\\3b]\")!\u000f\u0002a\u0001\u001d\u0006!A\u000f[1u\u0003\u0019)\u0017/^1mgR\u0011a.\u001e\u0005\u0006e\u0016\u0001\rAT\u0001\tQ\u0006\u001c\bnQ8eKR\t\u0001\u0010\u0005\u0002<s&\u0011!0\u000e\u0002\u0004\u0013:$\bF\u0002\u0001}\u0003\u000b\t9\u0001E\u0002~\u0003\u0003i\u0011A \u0006\u0003\u007fV\n!\"\u00198o_R\fG/[8o\u0013\r\t\u0019A \u0002\u0011S6\u0004H.[2ji:{GOR8v]\u0012\f1!\\:hC\t\tI!A\u0010O_\u0002j\u0015M\\5gKN$\b%\u0019<bS2\f\'\r\\3!M>\u0014\b\u0005J>U{:\n\u0001\"T1oS\u001a,7\u000f\u001e\t\u0003\u0001\"\u0019B\u0001\u0003\u001e\u0002\u0012A!\u00111CA\u000f\u001b\t\t)B\u0003\u0003\u0002\u0018\u0005e\u0011AA5p\u0015\t\tY\"\u0001\u0003kCZ\f\u0017\u0002BA\u0010\u0003+\u0011AbU3sS\u0006d\u0017N_1cY\u0016\fa\u0001P5oSRtDCAA\u0007\u000391\u0018\r\\;f\u001b\u0006t\u0017NZ3tiN,\"!!\u000b\u0011\tqs\u00161\u0006\u0019\u0005\u0003[\t)\u0004E\u0003A\u0003_\t\u0019$C\u0002\u00022M\u0012a\"\u00118z-\u0006dW*\u00198jM\u0016\u001cH\u000fE\u0002H\u0003k!!\"a\u000e\u000b\u0003\u0003\u0005\tQ!\u0001K\u0005\ryFEM\u0001\u0005\u0005f$X-\u0006\u0002\u0002>A!\u0011qHA#\u001d\r\u0001\u0015\u0011I\u0005\u0004\u0003\u0007\u001a\u0014aD\'b]&4Wm\u001d;GC\u000e$xN]=\n\t\u0005\u001d\u0013\u0011\n\u0002\r\u0005f$X-T1oS\u001a,7\u000f\u001e\u0006\u0004\u0003\u0007\u001a\u0014!\u0002\"zi\u0016\u0004\u0013!B*i_J$XCAA)!\u0011\ty$a\u0015\n\t\u0005U\u0013\u0011\n\u0002\u000e\'\"|\'\u000f^\'b]&4Wm\u001d;\u0002\rMCwN\u001d;!\u0003\u0011\u0019\u0005.\u0019:\u0016\u0005\u0005u\u0003\u0003BA \u0003?JA!!\u0019\u0002J\ta1\t[1s\u001b\u0006t\u0017NZ3ti\u0006)1\t[1sA\u0005\u0019\u0011J\u001c;\u0016\u0005\u0005%\u0004\u0003BA \u0003WJA!!\u001c\u0002J\tY\u0011J\u001c;NC:Lg-Z:u\u0003\u0011Ie\u000e\u001e\u0011\u0002\t1{gnZ\u000b\u0003\u0003k\u0002B!a\u0010\u0002x%!\u0011\u0011PA%\u00051auN\\4NC:Lg-Z:u\u0003\u0015auN\\4!\u0003\u00151En\\1u+\t\t\t\t\u0005\u0003\u0002@\u0005\r\u0015\u0002BAC\u0003\u0013\u0012QB\u00127pCRl\u0015M\\5gKN$\u0018A\u0002$m_\u0006$\b%\u0001\u0004E_V\u0014G.Z\u000b\u0003\u0003\u001b\u0003B!a\u0010\u0002\u0010&!\u0011\u0011SA%\u00059!u.\u001e2mK6\u000bg.\u001b4fgR\fq\u0001R8vE2,\u0007%A\u0004C_>dW-\u00198\u0016\u0005\u0005e\u0005\u0003BA \u00037KA!!(\u0002J\ty!i\\8mK\u0006tW*\u00198jM\u0016\u001cH/\u0001\u0005C_>dW-\u00198!\u0003\u0011)f.\u001b;\u0016\u0005\u0005\u0015\u0006\u0003BA \u0003OKA!!+\u0002J\taQK\\5u\u001b\u0006t\u0017NZ3ti\u0006)QK\\5uA\u0005\u0019\u0011I\\=\u0016\u0005\u0005E\u0006c\u0001!\u0001\u001d\u0006!\u0011I\\=!\u0003\u0019y%M[3diV\u0011\u0011\u0011\u0018\t\u0005\u0001\u0002\tY\f\u0005\u0003\u0002>\u0006\rWBAA`\u0015\u0011\t\t-!\u0007\u0002\t1\fgnZ\u0005\u0005\u0003\u000b\fyL\u0001\u0004PE*,7\r^\u0001\b\u001f\nTWm\u0019;!\u0003\u0019\te.\u001f*fMV\u0011\u0011Q\u001a\t\u0004\u0001\u0002Q\u0014aB!osJ+g\rI\u0001\u0007\u0003:Lh+\u00197\u0016\u0005\u0005U\u0007\u0003\u0002!\u0001\u0003/\u00042aOAm\u0013\r\tY.\u000e\u0002\u0007\u0003:Lh+\u00197\u0002\u000f\u0005s\u0017PV1mA\u0005!a*\u001e7m+\t\t\u0019\u000f\u0005\u0003A\u0001\u0005\u0015\bcA\u001e\u0002h&\u0019\u0011\u0011^\u001b\u0003\t9+H\u000e\\\u0001\u0006\u001dVdG\u000eI\u0001\b\u001d>$\b.\u001b8h+\t\t\t\u0010E\u0002A\u0001-\u000b\u0001BT8uQ&tw\rI\u0001\u000bg&tw\r\\3UsB,W\u0003BA}\u0003\u007f$B!a?\u0003\u0004A!\u0001\tAA\u007f!\r9\u0015q \u0003\u0007\u0013&\u0012\rA!\u0001\u0012\u0005-S\u0004B\u0002B\u0003S\u0001\u0007!(A\u0003wC2,X-A\u0005dY\u0006\u001c8\u000fV=qKV!!1\u0002B\t)\u0011\u0011iAa\u0005\u0011\t\u0001\u0003!q\u0002\t\u0004\u000f\nEA!B%+\u0005\u0004Q\u0005b\u0002B\u000bU\u0001\u0007!qC\u0001\u0006G2\f\'P\u001f\u0019\u0005\u00053\u0011I\u0003\u0005\u0004\u0003\u001c\t\u0005\"q\u0005\b\u0004w\tu\u0011b\u0001B\u0010k\u00051\u0001K]3eK\u001aLAAa\t\u0003&\t)1\t\\1tg*\u0019!qD\u001b\u0011\u0007\u001d\u0013I\u0003B\u0006\u0003,\tM\u0011\u0011!A\u0001\u0006\u0003Q%aA0%gU!!q\u0006B\u001b)!\u0011\tDa\u000e\u0003<\t%\u0003\u0003\u0002!\u0001\u0005g\u00012a\u0012B\u001b\t\u0015I5F1\u0001K\u0011\u001d\u0011)b\u000ba\u0001\u0005s\u0001bAa\u0007\u0003\"\tM\u0002b\u0002B\u001fW\u0001\u0007!qH\u0001\u0005CJ<\u0017\u0007\r\u0003\u0003B\t\u0015\u0003\u0003\u0002!\u0001\u0005\u0007\u00022a\u0012B#\t-\u00119Ea\u000f\u0002\u0002\u0003\u0005)\u0011\u0001&\u0003\u0007}#C\u0007C\u0004\u0003L-\u0002\rA!\u0014\u0002\t\u0005\u0014xm\u001d\t\u0006w\t=#1K\u0005\u0004\u0005#*$A\u0003\u001fsKB,\u0017\r^3e}A\"!Q\u000bB-!\u0011\u0001\u0005Aa\u0016\u0011\u0007\u001d\u0013I\u0006B\u0006\u0003\\\tu\u0013\u0011!A\u0001\u0006\u0003Q%aA0%k!9!1J\u0016A\u0002\t5S\u0003\u0002B1\u0005O\"\u0002Ba\u0019\u0003j\t]$1\u0011\t\u0005\u0001\u0002\u0011)\u0007E\u0002H\u0005O\"Q!\u0013\u0017C\u0002)CqAa\u001b-\u0001\u0004\u0011i\'\u0001\u0004qe\u00164\u0017\u000e\u001f\u0019\u0005\u0005_\u0012\u0019\b\u0005\u0003A\u0001\tE\u0004cA$\u0003t\u0011Y!Q\u000fB5\u0003\u0003\u0005\tQ!\u0001K\u0005\ryFE\u000e\u0005\b\u0005+a\u0003\u0019\u0001B=a\u0011\u0011YHa \u0011\r\tm!\u0011\u0005B?!\r9%q\u0010\u0003\f\u0005\u0003\u00139(!A\u0001\u0002\u000b\u0005!JA\u0002`I]BqAa\u0013-\u0001\u0004\u0011)\tE\u0003<\u0005\u001f\u00129\t\r\u0003\u0003\n\n5\u0005\u0003\u0002!\u0001\u0005\u0017\u00032a\u0012BG\t-\u0011yIa!\u0002\u0002\u0003\u0005)\u0011\u0001&\u0003\u0007}#\u0003(A\u0005beJ\f\u0017\u0010V=qKV!!Q\u0013BO)\u0011\u00119Ja(\u0011\t\u0001\u0003!\u0011\u0014\t\u0005w)\u0014Y\nE\u0002H\u0005;#Q!S\u0017C\u0002)CqA!).\u0001\u0004\u0011\u0019+A\u0002be\u001e\u0004DA!*\u0003*B!\u0001\t\u0001BT!\r9%\u0011\u0016\u0003\f\u0005W\u0013y*!A\u0001\u0002\u000b\u0005!JA\u0002`Ie\nA\"\u00192tiJ\f7\r\u001e+za\u0016,BA!-\u00038RQ!1\u0017B]\u0005\u000b\u0014INa:\u0011\t\u0001\u0003!Q\u0017\t\u0004\u000f\n]F!B%/\u0005\u0004Q\u0005b\u0002B6]\u0001\u0007!1\u0018\u0019\u0005\u0005{\u0013\t\r\u0005\u0003A\u0001\t}\u0006cA$\u0003B\u0012Y!1\u0019B]\u0003\u0003\u0005\tQ!\u0001K\u0005\u0011yF%\r\u0019\t\u000f\t\u001dg\u00061\u0001\u0003J\u0006!a.Y7f!\u0011\u0011YM!6\u000f\t\t5\'Q\u0004\t\u0004\u0005\u001f,TB\u0001Bi\u0015\r\u0011\u0019nN\u0001\u0007yI|w\u000e\u001e \n\t\t]\'Q\u0005\u0002\u0007\'R\u0014\u0018N\\4\t\u000f\tmg\u00061\u0001\u0003^\u0006QQ\u000f\u001d9fe\n{WO\u001c31\t\t}\'1\u001d\t\u0007\u00057\u0011\tC!9\u0011\u0007\u001d\u0013\u0019\u000fB\u0006\u0003f\ne\u0017\u0011!A\u0001\u0006\u0003Q%\u0001B0%cEBqAa\u0013/\u0001\u0004\u0011I\u000fE\u0003<\u0005\u001f\u0012Y\u000f\r\u0003\u0003n\nE\b\u0003\u0002!\u0001\u0005_\u00042a\u0012By\t-\u0011\u0019Pa:\u0002\u0002\u0003\u0005)\u0011\u0001&\u0003\t}#\u0013GM\u0001\ro&dGmY1sIRK\b/Z\u000b\u0005\u0005s\u0014y\u0010\u0006\u0004\u0003|\u000e\u00051q\u0002\t\u0005\u0001\u0002\u0011i\u0010E\u0002H\u0005\u007f$Q!S\u0018C\u0002)Cqaa\u00010\u0001\u0004\u0019)!\u0001\u0006m_^,\'OQ8v]\u0012\u0004Daa\u0002\u0004\fA!\u0001\tAB\u0005!\r951\u0002\u0003\f\u0007\u001b\u0019\t!!A\u0001\u0002\u000b\u0005!J\u0001\u0003`IE\u001a\u0004b\u0002Bn_\u0001\u00071\u0011\u0003\u0019\u0005\u0007\'\u00199\u0002\u0005\u0003A\u0001\rU\u0001cA$\u0004\u0018\u0011Y1\u0011DB\b\u0003\u0003\u0005\tQ!\u0001K\u0005\u0011yF%\r\u001b\u0002!%tG/\u001a:tK\u000e$\u0018n\u001c8UsB,W\u0003BB\u0010\u0007K!Ba!\t\u0004(A!\u0001\tAB\u0012!\r95Q\u0005\u0003\u0006\u0013B\u0012\rA\u0013\u0005\b\u0007S\u0001\u0004\u0019AB\u0016\u0003\u001d\u0001\u0018M]3oiN\u0004Ra\u000fB(\u0007[\u0001Daa\f\u00044A!\u0001\tAB\u0019!\r951\u0007\u0003\f\u0007k\u00199#!A\u0001\u0002\u000b\u0005!J\u0001\u0003`IE*\u0014\u0001D<sSR,\'+\u001a9mC\u000e,GCAA^\u0001
   #12 = Utf8               scala/reflect/ManifestFactory$AbstractTypeManifest
   #13 = Class              #12           // scala/reflect/ManifestFactory$AbstractTypeManifest
   #14 = Utf8               scala/reflect/ManifestFactory
   #15 = Class              #14           // scala/reflect/ManifestFactory
   #16 = Utf8               AbstractTypeManifest
   #17 = Utf8               scala/reflect/ManifestFactory$BooleanManifest
   #18 = Class              #17           // scala/reflect/ManifestFactory$BooleanManifest
   #19 = Utf8               BooleanManifest
   #20 = Utf8               scala/reflect/ManifestFactory$ByteManifest
   #21 = Class              #20           // scala/reflect/ManifestFactory$ByteManifest
   #22 = Utf8               ByteManifest
   #23 = Utf8               scala/reflect/ManifestFactory$CharManifest
   #24 = Class              #23           // scala/reflect/ManifestFactory$CharManifest
   #25 = Utf8               CharManifest
   #26 = Utf8               scala/reflect/ManifestFactory$DoubleManifest
   #27 = Class              #26           // scala/reflect/ManifestFactory$DoubleManifest
   #28 = Utf8               DoubleManifest
   #29 = Utf8               scala/reflect/ManifestFactory$FloatManifest
   #30 = Class              #29           // scala/reflect/ManifestFactory$FloatManifest
   #31 = Utf8               FloatManifest
   #32 = Utf8               scala/reflect/ManifestFactory$IntManifest
   #33 = Class              #32           // scala/reflect/ManifestFactory$IntManifest
   #34 = Utf8               IntManifest
   #35 = Utf8               scala/reflect/ManifestFactory$LongManifest
   #36 = Class              #35           // scala/reflect/ManifestFactory$LongManifest
   #37 = Utf8               LongManifest
   #38 = Utf8               scala/reflect/ManifestFactory$ShortManifest
   #39 = Class              #38           // scala/reflect/ManifestFactory$ShortManifest
   #40 = Utf8               ShortManifest
   #41 = Utf8               scala/reflect/ManifestFactory$SingletonTypeManifest
   #42 = Class              #41           // scala/reflect/ManifestFactory$SingletonTypeManifest
   #43 = Utf8               SingletonTypeManifest
   #44 = Utf8               scala/reflect/ManifestFactory$UnitManifest
   #45 = Class              #44           // scala/reflect/ManifestFactory$UnitManifest
   #46 = Utf8               UnitManifest
   #47 = Utf8               scala/reflect/ManifestFactory$WildcardManifest
   #48 = Class              #47           // scala/reflect/ManifestFactory$WildcardManifest
   #49 = Utf8               WildcardManifest
   #50 = Utf8               intersectionType
   #51 = Utf8               (Lscala/collection/immutable/Seq;)Lscala/reflect/Manifest;
   #52 = Utf8               <T:Ljava/lang/Object;>(Lscala/collection/immutable/Seq<Lscala/reflect/Manifest<*>;>;)Lscala/reflect/Manifest<TT;>;
   #53 = Utf8               parents
   #54 = Utf8               scala/reflect/Manifest$
   #55 = Class              #54           // scala/reflect/Manifest$
   #56 = Utf8               MODULE$
   #57 = Utf8               Lscala/reflect/Manifest$;
   #58 = NameAndType        #56:#57       // MODULE$:Lscala/reflect/Manifest$;
   #59 = Fieldref           #55.#58       // scala/reflect/Manifest$.MODULE$:Lscala/reflect/Manifest$;
   #60 = Utf8               scala/reflect/ManifestFactory$
   #61 = Class              #60           // scala/reflect/ManifestFactory$
   #62 = Utf8               Lscala/reflect/ManifestFactory$;
   #63 = NameAndType        #56:#62       // MODULE$:Lscala/reflect/ManifestFactory$;
   #64 = Fieldref           #61.#63       // scala/reflect/ManifestFactory$.MODULE$:Lscala/reflect/ManifestFactory$;
   #65 = NameAndType        #50:#51       // intersectionType:(Lscala/collection/immutable/Seq;)Lscala/reflect/Manifest;
   #66 = Methodref          #61.#65       // scala/reflect/ManifestFactory$.intersectionType:(Lscala/collection/immutable/Seq;)Lscala/reflect/Manifest;
   #67 = Utf8               Lscala/collection/immutable/Seq;
   #68 = Utf8               wildcardType
   #69 = Utf8               (Lscala/reflect/Manifest;Lscala/reflect/Manifest;)Lscala/reflect/Manifest;
   #70 = Utf8               <T:Ljava/lang/Object;>(Lscala/reflect/Manifest<*>;Lscala/reflect/Manifest<*>;)Lscala/reflect/Manifest<TT;>;
   #71 = Utf8               lowerBound
   #72 = Utf8               upperBound
   #73 = Utf8               <init>
   #74 = Utf8               (Lscala/reflect/Manifest;Lscala/reflect/Manifest;)V
   #75 = NameAndType        #73:#74       // "<init>":(Lscala/reflect/Manifest;Lscala/reflect/Manifest;)V
   #76 = Methodref          #48.#75       // scala/reflect/ManifestFactory$WildcardManifest."<init>":(Lscala/reflect/Manifest;Lscala/reflect/Manifest;)V
   #77 = Utf8               Lscala/reflect/Manifest;
   #78 = Utf8               abstractType
   #79 = Utf8               (Lscala/reflect/Manifest;Ljava/lang/String;Ljava/lang/Class;Lscala/collection/immutable/Seq;)Lscala/reflect/Manifest;
   #80 = Utf8               <T:Ljava/lang/Object;>(Lscala/reflect/Manifest<*>;Ljava/lang/String;Ljava/lang/Class<*>;Lscala/collection/immutable/Seq<Lscala/reflect/Manifest<*>;>;)Lscala/reflect/Manifest<TT;>;
   #81 = Utf8               prefix
   #82 = Utf8               name
   #83 = Utf8               args
   #84 = Utf8               (Lscala/reflect/Manifest;Ljava/lang/String;Ljava/lang/Class;Lscala/collection/Seq;)V
   #85 = NameAndType        #73:#84       // "<init>":(Lscala/reflect/Manifest;Ljava/lang/String;Ljava/lang/Class;Lscala/collection/Seq;)V
   #86 = Methodref          #13.#85       // scala/reflect/ManifestFactory$AbstractTypeManifest."<init>":(Lscala/reflect/Manifest;Ljava/lang/String;Ljava/lang/Class;Lscala/collection/Seq;)V
   #87 = Utf8               Ljava/lang/String;
   #88 = Utf8               Ljava/lang/Class;
   #89 = Utf8               arrayType
   #90 = Utf8               (Lscala/reflect/Manifest;)Lscala/reflect/Manifest;
   #91 = Utf8               <T:Ljava/lang/Object;>(Lscala/reflect/Manifest<*>;)Lscala/reflect/Manifest<Ljava/lang/Object;>;
   #92 = Utf8               arg
   #93 = Utf8               arrayManifest
   #94 = Utf8               ()Lscala/reflect/Manifest;
   #95 = NameAndType        #93:#94       // arrayManifest:()Lscala/reflect/Manifest;
   #96 = InterfaceMethodref #2.#95        // scala/reflect/Manifest.arrayManifest:()Lscala/reflect/Manifest;
   #97 = Utf8               classType
   #98 = Utf8               (Lscala/reflect/Manifest;Ljava/lang/Class;Lscala/collection/immutable/Seq;)Lscala/reflect/Manifest;
   #99 = Utf8               <T:Ljava/lang/Object;>(Lscala/reflect/Manifest<*>;Ljava/lang/Class<*>;Lscala/collection/immutable/Seq<Lscala/reflect/Manifest<*>;>;)Lscala/reflect/Manifest<TT;>;
  #100 = Utf8               clazz
  #101 = NameAndType        #97:#98       // classType:(Lscala/reflect/Manifest;Ljava/lang/Class;Lscala/collection/immutable/Seq;)Lscala/reflect/Manifest;
  #102 = Methodref          #61.#101      // scala/reflect/ManifestFactory$.classType:(Lscala/reflect/Manifest;Ljava/lang/Class;Lscala/collection/immutable/Seq;)Lscala/reflect/Manifest;
  #103 = Utf8               (Ljava/lang/Class;Lscala/reflect/Manifest;Lscala/collection/immutable/Seq;)Lscala/reflect/Manifest;
  #104 = Utf8               <T:Ljava/lang/Object;>(Ljava/lang/Class<TT;>;Lscala/reflect/Manifest<*>;Lscala/collection/immutable/Seq<Lscala/reflect/Manifest<*>;>;)Lscala/reflect/Manifest<TT;>;
  #105 = Utf8               arg1
  #106 = NameAndType        #97:#103      // classType:(Ljava/lang/Class;Lscala/reflect/Manifest;Lscala/collection/immutable/Seq;)Lscala/reflect/Manifest;
  #107 = Methodref          #61.#106      // scala/reflect/ManifestFactory$.classType:(Ljava/lang/Class;Lscala/reflect/Manifest;Lscala/collection/immutable/Seq;)Lscala/reflect/Manifest;
  #108 = Utf8               (Ljava/lang/Class;)Lscala/reflect/Manifest;
  #109 = Utf8               <T:Ljava/lang/Object;>(Ljava/lang/Class<*>;)Lscala/reflect/Manifest<TT;>;
  #110 = NameAndType        #97:#108      // classType:(Ljava/lang/Class;)Lscala/reflect/Manifest;
  #111 = Methodref          #61.#110      // scala/reflect/ManifestFactory$.classType:(Ljava/lang/Class;)Lscala/reflect/Manifest;
  #112 = Utf8               singleType
  #113 = Utf8               (Ljava/lang/Object;)Lscala/reflect/Manifest;
  #114 = Utf8               <T:Ljava/lang/Object;>(Ljava/lang/Object;)Lscala/reflect/Manifest<TT;>;
  #115 = Utf8               value
  #116 = Utf8               (Ljava/lang/Object;)V
  #117 = NameAndType        #73:#116      // "<init>":(Ljava/lang/Object;)V
  #118 = Methodref          #42.#117      // scala/reflect/ManifestFactory$SingletonTypeManifest."<init>":(Ljava/lang/Object;)V
  #119 = Utf8               Ljava/lang/Object;
  #120 = Utf8               Nothing
  #121 = Utf8               ()Lscala/reflect/Manifest<Lscala/runtime/Nothing$;>;
  #122 = NameAndType        #120:#94      // Nothing:()Lscala/reflect/Manifest;
  #123 = Methodref          #55.#122      // scala/reflect/Manifest$.Nothing:()Lscala/reflect/Manifest;
  #124 = Utf8               Null
  #125 = Utf8               ()Lscala/reflect/Manifest<Lscala/runtime/Null$;>;
  #126 = NameAndType        #124:#94      // Null:()Lscala/reflect/Manifest;
  #127 = Methodref          #55.#126      // scala/reflect/Manifest$.Null:()Lscala/reflect/Manifest;
  #128 = Utf8               AnyVal
  #129 = Utf8               ()Lscala/reflect/Manifest<Ljava/lang/Object;>;
  #130 = NameAndType        #128:#94      // AnyVal:()Lscala/reflect/Manifest;
  #131 = Methodref          #55.#130      // scala/reflect/Manifest$.AnyVal:()Lscala/reflect/Manifest;
  #132 = Utf8               AnyRef
  #133 = NameAndType        #132:#94      // AnyRef:()Lscala/reflect/Manifest;
  #134 = Methodref          #55.#133      // scala/reflect/Manifest$.AnyRef:()Lscala/reflect/Manifest;
  #135 = Utf8               Object
  #136 = NameAndType        #135:#94      // Object:()Lscala/reflect/Manifest;
  #137 = Methodref          #55.#136      // scala/reflect/Manifest$.Object:()Lscala/reflect/Manifest;
  #138 = Utf8               Any
  #139 = NameAndType        #138:#94      // Any:()Lscala/reflect/Manifest;
  #140 = Methodref          #55.#139      // scala/reflect/Manifest$.Any:()Lscala/reflect/Manifest;
  #141 = Utf8               Unit
  #142 = Utf8               ()Lscala/reflect/ManifestFactory$UnitManifest;
  #143 = NameAndType        #141:#142     // Unit:()Lscala/reflect/ManifestFactory$UnitManifest;
  #144 = Methodref          #55.#143      // scala/reflect/Manifest$.Unit:()Lscala/reflect/ManifestFactory$UnitManifest;
  #145 = Utf8               Boolean
  #146 = Utf8               ()Lscala/reflect/ManifestFactory$BooleanManifest;
  #147 = NameAndType        #145:#146     // Boolean:()Lscala/reflect/ManifestFactory$BooleanManifest;
  #148 = Methodref          #55.#147      // scala/reflect/Manifest$.Boolean:()Lscala/reflect/ManifestFactory$BooleanManifest;
  #149 = Utf8               Double
  #150 = Utf8               ()Lscala/reflect/ManifestFactory$DoubleManifest;
  #151 = NameAndType        #149:#150     // Double:()Lscala/reflect/ManifestFactory$DoubleManifest;
  #152 = Methodref          #55.#151      // scala/reflect/Manifest$.Double:()Lscala/reflect/ManifestFactory$DoubleManifest;
  #153 = Utf8               Float
  #154 = Utf8               ()Lscala/reflect/ManifestFactory$FloatManifest;
  #155 = NameAndType        #153:#154     // Float:()Lscala/reflect/ManifestFactory$FloatManifest;
  #156 = Methodref          #55.#155      // scala/reflect/Manifest$.Float:()Lscala/reflect/ManifestFactory$FloatManifest;
  #157 = Utf8               Long
  #158 = Utf8               ()Lscala/reflect/ManifestFactory$LongManifest;
  #159 = NameAndType        #157:#158     // Long:()Lscala/reflect/ManifestFactory$LongManifest;
  #160 = Methodref          #55.#159      // scala/reflect/Manifest$.Long:()Lscala/reflect/ManifestFactory$LongManifest;
  #161 = Utf8               Int
  #162 = Utf8               ()Lscala/reflect/ManifestFactory$IntManifest;
  #163 = NameAndType        #161:#162     // Int:()Lscala/reflect/ManifestFactory$IntManifest;
  #164 = Methodref          #55.#163      // scala/reflect/Manifest$.Int:()Lscala/reflect/ManifestFactory$IntManifest;
  #165 = Utf8               Char
  #166 = Utf8               ()Lscala/reflect/ManifestFactory$CharManifest;
  #167 = NameAndType        #165:#166     // Char:()Lscala/reflect/ManifestFactory$CharManifest;
  #168 = Methodref          #55.#167      // scala/reflect/Manifest$.Char:()Lscala/reflect/ManifestFactory$CharManifest;
  #169 = Utf8               Short
  #170 = Utf8               ()Lscala/reflect/ManifestFactory$ShortManifest;
  #171 = NameAndType        #169:#170     // Short:()Lscala/reflect/ManifestFactory$ShortManifest;
  #172 = Methodref          #55.#171      // scala/reflect/Manifest$.Short:()Lscala/reflect/ManifestFactory$ShortManifest;
  #173 = Utf8               Byte
  #174 = Utf8               ()Lscala/reflect/ManifestFactory$ByteManifest;
  #175 = NameAndType        #173:#174     // Byte:()Lscala/reflect/ManifestFactory$ByteManifest;
  #176 = Methodref          #55.#175      // scala/reflect/Manifest$.Byte:()Lscala/reflect/ManifestFactory$ByteManifest;
  #177 = Utf8               valueManifests
  #178 = Utf8               ()Lscala/collection/immutable/List;
  #179 = Utf8               ()Lscala/collection/immutable/List<Lscala/reflect/AnyValManifest<*>;>;
  #180 = NameAndType        #177:#178     // valueManifests:()Lscala/collection/immutable/List;
  #181 = Methodref          #61.#180      // scala/reflect/ManifestFactory$.valueManifests:()Lscala/collection/immutable/List;
  #182 = Utf8               typeArguments$
  #183 = Utf8               (Lscala/reflect/Manifest;)Lscala/collection/immutable/List;
  #184 = Utf8               $this
  #185 = Utf8               typeArguments
  #186 = NameAndType        #185:#178     // typeArguments:()Lscala/collection/immutable/List;
  #187 = InterfaceMethodref #2.#186       // scala/reflect/Manifest.typeArguments:()Lscala/collection/immutable/List;
  #188 = Utf8               ()Lscala/collection/immutable/List<Lscala/reflect/Manifest<*>;>;
  #189 = Utf8               scala/package$
  #190 = Class              #189          // scala/package$
  #191 = Utf8               Lscala/package$;
  #192 = NameAndType        #56:#191      // MODULE$:Lscala/package$;
  #193 = Fieldref           #190.#192     // scala/package$.MODULE$:Lscala/package$;
  #194 = Utf8               Nil
  #195 = Utf8               ()Lscala/collection/immutable/Nil$;
  #196 = NameAndType        #194:#195     // Nil:()Lscala/collection/immutable/Nil$;
  #197 = Methodref          #190.#196     // scala/package$.Nil:()Lscala/collection/immutable/Nil$;
  #198 = Utf8               this
  #199 = Utf8               arrayManifest$
  #200 = Utf8               runtimeClass
  #201 = Utf8               ()Ljava/lang/Class;
  #202 = NameAndType        #200:#201     // runtimeClass:()Ljava/lang/Class;
  #203 = InterfaceMethodref #2.#202       // scala/reflect/Manifest.runtimeClass:()Ljava/lang/Class;
  #204 = Utf8               arrayClass
  #205 = Utf8               (Ljava/lang/Class;)Ljava/lang/Class;
  #206 = NameAndType        #204:#205     // arrayClass:(Ljava/lang/Class;)Ljava/lang/Class;
  #207 = InterfaceMethodref #2.#206       // scala/reflect/Manifest.arrayClass:(Ljava/lang/Class;)Ljava/lang/Class;
  #208 = Utf8               scala/collection/immutable/Nil$
  #209 = Class              #208          // scala/collection/immutable/Nil$
  #210 = Utf8               Lscala/collection/immutable/Nil$;
  #211 = NameAndType        #56:#210      // MODULE$:Lscala/collection/immutable/Nil$;
  #212 = Fieldref           #209.#211     // scala/collection/immutable/Nil$.MODULE$:Lscala/collection/immutable/Nil$;
  #213 = Utf8               classType_clazz
  #214 = Utf8               classType_args
  #215 = Utf8               canEqual$
  #216 = Utf8               (Lscala/reflect/Manifest;Ljava/lang/Object;)Z
  #217 = Utf8               that
  #218 = Utf8               canEqual
  #219 = Utf8               (Ljava/lang/Object;)Z
  #220 = NameAndType        #218:#219     // canEqual:(Ljava/lang/Object;)Z
  #221 = InterfaceMethodref #2.#220       // scala/reflect/Manifest.canEqual:(Ljava/lang/Object;)Z
  #222 = Utf8               equals$
  #223 = Utf8               equals
  #224 = NameAndType        #223:#219     // equals:(Ljava/lang/Object;)Z
  #225 = InterfaceMethodref #2.#224       // scala/reflect/Manifest.equals:(Ljava/lang/Object;)Z
  #226 = Methodref          #5.#224       // java/lang/Object.equals:(Ljava/lang/Object;)Z
  #227 = Utf8               $less$colon$less
  #228 = Utf8               (Lscala/reflect/ClassTag;)Z
  #229 = NameAndType        #227:#228     // $less$colon$less:(Lscala/reflect/ClassTag;)Z
  #230 = InterfaceMethodref #2.#229       // scala/reflect/Manifest.$less$colon$less:(Lscala/reflect/ClassTag;)Z
  #231 = Utf8               java/lang/Class
  #232 = Class              #231          // java/lang/Class
  #233 = Utf8               hashCode$
  #234 = Utf8               (Lscala/reflect/Manifest;)I
  #235 = Utf8               hashCode
  #236 = Utf8               ()I
  #237 = NameAndType        #235:#236     // hashCode:()I
  #238 = InterfaceMethodref #2.#237       // scala/reflect/Manifest.hashCode:()I
  #239 = Utf8               scala/runtime/Statics
  #240 = Class              #239          // scala/runtime/Statics
  #241 = Utf8               anyHash
  #242 = Utf8               (Ljava/lang/Object;)I
  #243 = NameAndType        #241:#242     // anyHash:(Ljava/lang/Object;)I
  #244 = Methodref          #240.#243     // scala/runtime/Statics.anyHash:(Ljava/lang/Object;)I
  #245 = Utf8               $init$
  #246 = Utf8               (Lscala/reflect/Manifest;)V
  #247 = Utf8               Code
  #248 = Utf8               LineNumberTable
  #249 = Utf8               LocalVariableTable
  #250 = Utf8               Signature
  #251 = Utf8               MethodParameters
  #252 = Utf8               StackMapTable
  #253 = Utf8               InnerClasses
  #254 = Utf8               SourceFile
  #255 = Utf8               RuntimeVisibleAnnotations
  #256 = Utf8               ScalaInlineInfo
  #257 = Utf8               ScalaSig
{
  public static <T extends java.lang.Object> scala.reflect.Manifest<T> intersectionType(scala.collection.immutable.Seq<scala.reflect.Manifest<?>>);
    descriptor: (Lscala/collection/immutable/Seq;)Lscala/reflect/Manifest;
    flags: (0x0009) ACC_PUBLIC, ACC_STATIC
    Code:
      stack=2, locals=1, args_size=1
         0: getstatic     #59                 // Field scala/reflect/Manifest$.MODULE$:Lscala/reflect/Manifest$;
         3: pop
         4: getstatic     #64                 // Field scala/reflect/ManifestFactory$.MODULE$:Lscala/reflect/ManifestFactory$;
         7: aload_0
         8: invokevirtual #66                 // Method scala/reflect/ManifestFactory$.intersectionType:(Lscala/collection/immutable/Seq;)Lscala/reflect/Manifest;
        11: areturn
      LineNumberTable:
        line 142: 4
      LocalVariableTable:
        Start  Length  Slot  Name   Signature
            0      12     0 parents   Lscala/collection/immutable/Seq;
    Signature: #52                          // <T:Ljava/lang/Object;>(Lscala/collection/immutable/Seq<Lscala/reflect/Manifest<*>;>;)Lscala/reflect/Manifest<TT;>;
    MethodParameters:
      Name                           Flags
      parents                        final

  public static <T extends java.lang.Object> scala.reflect.Manifest<T> wildcardType(scala.reflect.Manifest<?>, scala.reflect.Manifest<?>);
    descriptor: (Lscala/reflect/Manifest;Lscala/reflect/Manifest;)Lscala/reflect/Manifest;
    flags: (0x0009) ACC_PUBLIC, ACC_STATIC
    Code:
      stack=4, locals=2, args_size=2
         0: getstatic     #59                 // Field scala/reflect/Manifest$.MODULE$:Lscala/reflect/Manifest$;
         3: pop
         4: new           #48                 // class scala/reflect/ManifestFactory$WildcardManifest
         7: dup
         8: aload_0
         9: aload_1
        10: invokespecial #76                 // Method scala/reflect/ManifestFactory$WildcardManifest."<init>":(Lscala/reflect/Manifest;Lscala/reflect/Manifest;)V
        13: areturn
      LineNumberTable:
        line 448: 4
        line 138: 13
      LocalVariableTable:
        Start  Length  Slot  Name   Signature
            0      14     0 lowerBound   Lscala/reflect/Manifest;
            0      14     1 upperBound   Lscala/reflect/Manifest;
    Signature: #70                          // <T:Ljava/lang/Object;>(Lscala/reflect/Manifest<*>;Lscala/reflect/Manifest<*>;)Lscala/reflect/Manifest<TT;>;
    MethodParameters:
      Name                           Flags
      lowerBound                     final
      upperBound                     final

  public static <T extends java.lang.Object> scala.reflect.Manifest<T> abstractType(scala.reflect.Manifest<?>, java.lang.String, java.lang.Class<?>, scala.collection.immutable.Seq<scala.reflect.Manifest<?>>);
    descriptor: (Lscala/reflect/Manifest;Ljava/lang/String;Ljava/lang/Class;Lscala/collection/immutable/Seq;)Lscala/reflect/Manifest;
    flags: (0x0009) ACC_PUBLIC, ACC_STATIC
    Code:
      stack=6, locals=4, args_size=4
         0: getstatic     #59                 // Field scala/reflect/Manifest$.MODULE$:Lscala/reflect/Manifest$;
         3: pop
         4: new           #13                 // class scala/reflect/ManifestFactory$AbstractTypeManifest
         7: dup
         8: aload_0
         9: aload_1
        10: aload_2
        11: aload_3
        12: invokespecial #86                 // Method scala/reflect/ManifestFactory$AbstractTypeManifest."<init>":(Lscala/reflect/Manifest;Ljava/lang/String;Ljava/lang/Class;Lscala/collection/Seq;)V
        15: areturn
      LineNumberTable:
        line 434: 4
        line 134: 15
      LocalVariableTable:
        Start  Length  Slot  Name   Signature
            0      16     0 prefix   Lscala/reflect/Manifest;
            0      16     1  name   Ljava/lang/String;
            0      16     2 upperBound   Ljava/lang/Class;
            0      16     3  args   Lscala/collection/immutable/Seq;
    Signature: #80                          // <T:Ljava/lang/Object;>(Lscala/reflect/Manifest<*>;Ljava/lang/String;Ljava/lang/Class<*>;Lscala/collection/immutable/Seq<Lscala/reflect/Manifest<*>;>;)Lscala/reflect/Manifest<TT;>;
    MethodParameters:
      Name                           Flags
      prefix                         final
      name                           final
      upperBound                     final
      args                           final

  public static <T extends java.lang.Object> scala.reflect.Manifest<java.lang.Object> arrayType(scala.reflect.Manifest<?>);
    descriptor: (Lscala/reflect/Manifest;)Lscala/reflect/Manifest;
    flags: (0x0009) ACC_PUBLIC, ACC_STATIC
    Code:
      stack=1, locals=1, args_size=1
         0: getstatic     #59                 // Field scala/reflect/Manifest$.MODULE$:Lscala/reflect/Manifest$;
         3: pop
         4: aload_0
         5: invokeinterface #96,  1           // InterfaceMethod arrayManifest:()Lscala/reflect/Manifest;
        10: areturn
      LineNumberTable:
        line 421: 4
        line 128: 10
      LocalVariableTable:
        Start  Length  Slot  Name   Signature
            0      11     0   arg   Lscala/reflect/Manifest;
    Signature: #91                          // <T:Ljava/lang/Object;>(Lscala/reflect/Manifest<*>;)Lscala/reflect/Manifest<Ljava/lang/Object;>;
    MethodParameters:
      Name                           Flags
      arg                            final

  public static <T extends java.lang.Object> scala.reflect.Manifest<T> classType(scala.reflect.Manifest<?>, java.lang.Class<?>, scala.collection.immutable.Seq<scala.reflect.Manifest<?>>);
    descriptor: (Lscala/reflect/Manifest;Ljava/lang/Class;Lscala/collection/immutable/Seq;)Lscala/reflect/Manifest;
    flags: (0x0009) ACC_PUBLIC, ACC_STATIC
    Code:
      stack=4, locals=3, args_size=3
         0: getstatic     #59                 // Field scala/reflect/Manifest$.MODULE$:Lscala/reflect/Manifest$;
         3: pop
         4: getstatic     #64                 // Field scala/reflect/ManifestFactory$.MODULE$:Lscala/reflect/ManifestFactory$;
         7: aload_0
         8: aload_1
         9: aload_2
        10: invokevirtual #102                // Method scala/reflect/ManifestFactory$.classType:(Lscala/reflect/Manifest;Ljava/lang/Class;Lscala/collection/immutable/Seq;)Lscala/reflect/Manifest;
        13: areturn
      LineNumberTable:
        line 125: 4
      LocalVariableTable:
        Start  Length  Slot  Name   Signature
            0      14     0 prefix   Lscala/reflect/Manifest;
            0      14     1 clazz   Ljava/lang/Class;
            0      14     2  args   Lscala/collection/immutable/Seq;
    Signature: #99                          // <T:Ljava/lang/Object;>(Lscala/reflect/Manifest<*>;Ljava/lang/Class<*>;Lscala/collection/immutable/Seq<Lscala/reflect/Manifest<*>;>;)Lscala/reflect/Manifest<TT;>;
    MethodParameters:
      Name                           Flags
      prefix                         final
      clazz                          final
      args                           final

  public static <T extends java.lang.Object> scala.reflect.Manifest<T> classType(java.lang.Class<T>, scala.reflect.Manifest<?>, scala.collection.immutable.Seq<scala.reflect.Manifest<?>>);
    descriptor: (Ljava/lang/Class;Lscala/reflect/Manifest;Lscala/collection/immutable/Seq;)Lscala/reflect/Manifest;
    flags: (0x0009) ACC_PUBLIC, ACC_STATIC
    Code:
      stack=4, locals=3, args_size=3
         0: getstatic     #59                 // Field scala/reflect/Manifest$.MODULE$:Lscala/reflect/Manifest$;
         3: pop
         4: getstatic     #64                 // Field scala/reflect/ManifestFactory$.MODULE$:Lscala/reflect/ManifestFactory$;
         7: aload_0
         8: aload_1
         9: aload_2
        10: invokevirtual #107                // Method scala/reflect/ManifestFactory$.classType:(Ljava/lang/Class;Lscala/reflect/Manifest;Lscala/collection/immutable/Seq;)Lscala/reflect/Manifest;
        13: areturn
      LineNumberTable:
        line 119: 4
      LocalVariableTable:
        Start  Length  Slot  Name   Signature
            0      14     0 clazz   Ljava/lang/Class;
            0      14     1  arg1   Lscala/reflect/Manifest;
            0      14     2  args   Lscala/collection/immutable/Seq;
    Signature: #104                         // <T:Ljava/lang/Object;>(Ljava/lang/Class<TT;>;Lscala/reflect/Manifest<*>;Lscala/collection/immutable/Seq<Lscala/reflect/Manifest<*>;>;)Lscala/reflect/Manifest<TT;>;
    MethodParameters:
      Name                           Flags
      clazz                          final
      arg1                           final
      args                           final

  public static <T extends java.lang.Object> scala.reflect.Manifest<T> classType(java.lang.Class<?>);
    descriptor: (Ljava/lang/Class;)Lscala/reflect/Manifest;
    flags: (0x0009) ACC_PUBLIC, ACC_STATIC
    Code:
      stack=2, locals=1, args_size=1
         0: getstatic     #59                 // Field scala/reflect/Manifest$.MODULE$:Lscala/reflect/Manifest$;
         3: pop
         4: getstatic     #64                 // Field scala/reflect/ManifestFactory$.MODULE$:Lscala/reflect/ManifestFactory$;
         7: aload_0
         8: invokevirtual #111                // Method scala/reflect/ManifestFactory$.classType:(Ljava/lang/Class;)Lscala/reflect/Manifest;
        11: areturn
      LineNumberTable:
        line 114: 4
      LocalVariableTable:
        Start  Length  Slot  Name   Signature
            0      12     0 clazz   Ljava/lang/Class;
    Signature: #109                         // <T:Ljava/lang/Object;>(Ljava/lang/Class<*>;)Lscala/reflect/Manifest<TT;>;
    MethodParameters:
      Name                           Flags
      clazz                          final

  public static <T extends java.lang.Object> scala.reflect.Manifest<T> singleType(java.lang.Object);
    descriptor: (Ljava/lang/Object;)Lscala/reflect/Manifest;
    flags: (0x0009) ACC_PUBLIC, ACC_STATIC
    Code:
      stack=3, locals=1, args_size=1
         0: getstatic     #59                 // Field scala/reflect/Manifest$.MODULE$:Lscala/reflect/Manifest$;
         3: pop
         4: new           #42                 // class scala/reflect/ManifestFactory$SingletonTypeManifest
         7: dup
         8: aload_0
         9: invokespecial #118                // Method scala/reflect/ManifestFactory$SingletonTypeManifest."<init>":(Ljava/lang/Object;)V
        12: areturn
      LineNumberTable:
        line 377: 4
        line 104: 12
      LocalVariableTable:
        Start  Length  Slot  Name   Signature
            0      13     0 value   Ljava/lang/Object;
    Signature: #114                         // <T:Ljava/lang/Object;>(Ljava/lang/Object;)Lscala/reflect/Manifest<TT;>;
    MethodParameters:
      Name                           Flags
      value                          final

  public static scala.reflect.Manifest<scala.runtime.Nothing$> Nothing();
    descriptor: ()Lscala/reflect/Manifest;
    flags: (0x0009) ACC_PUBLIC, ACC_STATIC
    Code:
      stack=1, locals=0, args_size=0
         0: getstatic     #59                 // Field scala/reflect/Manifest$.MODULE$:Lscala/reflect/Manifest$;
         3: invokevirtual #123                // Method scala/reflect/Manifest$.Nothing:()Lscala/reflect/Manifest;
         6: areturn
    Signature: #121                         // ()Lscala/reflect/Manifest<Lscala/runtime/Nothing$;>;

  public static scala.reflect.Manifest<scala.runtime.Null$> Null();
    descriptor: ()Lscala/reflect/Manifest;
    flags: (0x0009) ACC_PUBLIC, ACC_STATIC
    Code:
      stack=1, locals=0, args_size=0
         0: getstatic     #59                 // Field scala/reflect/Manifest$.MODULE$:Lscala/reflect/Manifest$;
         3: invokevirtual #127                // Method scala/reflect/Manifest$.Null:()Lscala/reflect/Manifest;
         6: areturn
    Signature: #125                         // ()Lscala/reflect/Manifest<Lscala/runtime/Null$;>;

  public static scala.reflect.Manifest<java.lang.Object> AnyVal();
    descriptor: ()Lscala/reflect/Manifest;
    flags: (0x0009) ACC_PUBLIC, ACC_STATIC
    Code:
      stack=1, locals=0, args_size=0
         0: getstatic     #59                 // Field scala/reflect/Manifest$.MODULE$:Lscala/reflect/Manifest$;
         3: invokevirtual #131                // Method scala/reflect/Manifest$.AnyVal:()Lscala/reflect/Manifest;
         6: areturn
    Signature: #129                         // ()Lscala/reflect/Manifest<Ljava/lang/Object;>;

  public static scala.reflect.Manifest<java.lang.Object> AnyRef();
    descriptor: ()Lscala/reflect/Manifest;
    flags: (0x0009) ACC_PUBLIC, ACC_STATIC
    Code:
      stack=1, locals=0, args_size=0
         0: getstatic     #59                 // Field scala/reflect/Manifest$.MODULE$:Lscala/reflect/Manifest$;
         3: invokevirtual #134                // Method scala/reflect/Manifest$.AnyRef:()Lscala/reflect/Manifest;
         6: areturn
    Signature: #129                         // ()Lscala/reflect/Manifest<Ljava/lang/Object;>;

  public static scala.reflect.Manifest<java.lang.Object> Object();
    descriptor: ()Lscala/reflect/Manifest;
    flags: (0x0009) ACC_PUBLIC, ACC_STATIC
    Code:
      stack=1, locals=0, args_size=0
         0: getstatic     #59                 // Field scala/reflect/Manifest$.MODULE$:Lscala/reflect/Manifest$;
         3: invokevirtual #137                // Method scala/reflect/Manifest$.Object:()Lscala/reflect/Manifest;
         6: areturn
    Signature: #129                         // ()Lscala/reflect/Manifest<Ljava/lang/Object;>;

  public static scala.reflect.Manifest<java.lang.Object> Any();
    descriptor: ()Lscala/reflect/Manifest;
    flags: (0x0009) ACC_PUBLIC, ACC_STATIC
    Code:
      stack=1, locals=0, args_size=0
         0: getstatic     #59                 // Field scala/reflect/Manifest$.MODULE$:Lscala/reflect/Manifest$;
         3: invokevirtual #140                // Method scala/reflect/Manifest$.Any:()Lscala/reflect/Manifest;
         6: areturn
    Signature: #129                         // ()Lscala/reflect/Manifest<Ljava/lang/Object;>;

  public static scala.reflect.ManifestFactory$UnitManifest Unit();
    descriptor: ()Lscala/reflect/ManifestFactory$UnitManifest;
    flags: (0x0009) ACC_PUBLIC, ACC_STATIC
    Code:
      stack=1, locals=0, args_size=0
         0: getstatic     #59                 // Field scala/reflect/Manifest$.MODULE$:Lscala/reflect/Manifest$;
         3: invokevirtual #144                // Method scala/reflect/Manifest$.Unit:()Lscala/reflect/ManifestFactory$UnitManifest;
         6: areturn

  public static scala.reflect.ManifestFactory$BooleanManifest Boolean();
    descriptor: ()Lscala/reflect/ManifestFactory$BooleanManifest;
    flags: (0x0009) ACC_PUBLIC, ACC_STATIC
    Code:
      stack=1, locals=0, args_size=0
         0: getstatic     #59                 // Field scala/reflect/Manifest$.MODULE$:Lscala/reflect/Manifest$;
         3: invokevirtual #148                // Method scala/reflect/Manifest$.Boolean:()Lscala/reflect/ManifestFactory$BooleanManifest;
         6: areturn

  public static scala.reflect.ManifestFactory$DoubleManifest Double();
    descriptor: ()Lscala/reflect/ManifestFactory$DoubleManifest;
    flags: (0x0009) ACC_PUBLIC, ACC_STATIC
    Code:
      stack=1, locals=0, args_size=0
         0: getstatic     #59                 // Field scala/reflect/Manifest$.MODULE$:Lscala/reflect/Manifest$;
         3: invokevirtual #152                // Method scala/reflect/Manifest$.Double:()Lscala/reflect/ManifestFactory$DoubleManifest;
         6: areturn

  public static scala.reflect.ManifestFactory$FloatManifest Float();
    descriptor: ()Lscala/reflect/ManifestFactory$FloatManifest;
    flags: (0x0009) ACC_PUBLIC, ACC_STATIC
    Code:
      stack=1, locals=0, args_size=0
         0: getstatic     #59                 // Field scala/reflect/Manifest$.MODULE$:Lscala/reflect/Manifest$;
         3: invokevirtual #156                // Method scala/reflect/Manifest$.Float:()Lscala/reflect/ManifestFactory$FloatManifest;
         6: areturn

  public static scala.reflect.ManifestFactory$LongManifest Long();
    descriptor: ()Lscala/reflect/ManifestFactory$LongManifest;
    flags: (0x0009) ACC_PUBLIC, ACC_STATIC
    Code:
      stack=1, locals=0, args_size=0
         0: getstatic     #59                 // Field scala/reflect/Manifest$.MODULE$:Lscala/reflect/Manifest$;
         3: invokevirtual #160                // Method scala/reflect/Manifest$.Long:()Lscala/reflect/ManifestFactory$LongManifest;
         6: areturn

  public static scala.reflect.ManifestFactory$IntManifest Int();
    descriptor: ()Lscala/reflect/ManifestFactory$IntManifest;
    flags: (0x0009) ACC_PUBLIC, ACC_STATIC
    Code:
      stack=1, locals=0, args_size=0
         0: getstatic     #59                 // Field scala/reflect/Manifest$.MODULE$:Lscala/reflect/Manifest$;
         3: invokevirtual #164                // Method scala/reflect/Manifest$.Int:()Lscala/reflect/ManifestFactory$IntManifest;
         6: areturn

  public static scala.reflect.ManifestFactory$CharManifest Char();
    descriptor: ()Lscala/reflect/ManifestFactory$CharManifest;
    flags: (0x0009) ACC_PUBLIC, ACC_STATIC
    Code:
      stack=1, locals=0, args_size=0
         0: getstatic     #59                 // Field scala/reflect/Manifest$.MODULE$:Lscala/reflect/Manifest$;
         3: invokevirtual #168                // Method scala/reflect/Manifest$.Char:()Lscala/reflect/ManifestFactory$CharManifest;
         6: areturn

  public static scala.reflect.ManifestFactory$ShortManifest Short();
    descriptor: ()Lscala/reflect/ManifestFactory$ShortManifest;
    flags: (0x0009) ACC_PUBLIC, ACC_STATIC
    Code:
      stack=1, locals=0, args_size=0
         0: getstatic     #59                 // Field scala/reflect/Manifest$.MODULE$:Lscala/reflect/Manifest$;
         3: invokevirtual #172                // Method scala/reflect/Manifest$.Short:()Lscala/reflect/ManifestFactory$ShortManifest;
         6: areturn

  public static scala.reflect.ManifestFactory$ByteManifest Byte();
    descriptor: ()Lscala/reflect/ManifestFactory$ByteManifest;
    flags: (0x0009) ACC_PUBLIC, ACC_STATIC
    Code:
      stack=1, locals=0, args_size=0
         0: getstatic     #59                 // Field scala/reflect/Manifest$.MODULE$:Lscala/reflect/Manifest$;
         3: invokevirtual #176                // Method scala/reflect/Manifest$.Byte:()Lscala/reflect/ManifestFactory$ByteManifest;
         6: areturn

  public static scala.collection.immutable.List<scala.reflect.AnyValManifest<?>> valueManifests();
    descriptor: ()Lscala/collection/immutable/List;
    flags: (0x0009) ACC_PUBLIC, ACC_STATIC
    Code:
      stack=1, locals=0, args_size=0
         0: getstatic     #59                 // Field scala/reflect/Manifest$.MODULE$:Lscala/reflect/Manifest$;
         3: pop
         4: getstatic     #64                 // Field scala/reflect/ManifestFactory$.MODULE$:Lscala/reflect/ManifestFactory$;
         7: invokevirtual #181                // Method scala/reflect/ManifestFactory$.valueManifests:()Lscala/collection/immutable/List;
        10: areturn
      LineNumberTable:
        line 83: 4
    Signature: #179                         // ()Lscala/collection/immutable/List<Lscala/reflect/AnyValManifest<*>;>;

  public static scala.collection.immutable.List typeArguments$(scala.reflect.Manifest);
    descriptor: (Lscala/reflect/Manifest;)Lscala/collection/immutable/List;
    flags: (0x1009) ACC_PUBLIC, ACC_STATIC, ACC_SYNTHETIC
    Code:
      stack=1, locals=1, args_size=1
         0: aload_0
         1: invokespecial #187                // InterfaceMethod typeArguments:()Lscala/collection/immutable/List;
         4: areturn
      LineNumberTable:
        line 51: 0
      LocalVariableTable:
        Start  Length  Slot  Name   Signature
            0       5     0 $this   Lscala/reflect/Manifest;
    MethodParameters:
      Name                           Flags
      $this                          final synthetic

  public default scala.collection.immutable.List<scala.reflect.Manifest<?>> typeArguments();
    descriptor: ()Lscala/collection/immutable/List;
    flags: (0x0001) ACC_PUBLIC
    Code:
      stack=1, locals=1, args_size=1
         0: getstatic     #193                // Field scala/package$.MODULE$:Lscala/package$;
         3: invokevirtual #197                // Method scala/package$.Nil:()Lscala/collection/immutable/Nil$;
         6: areturn
      LineNumberTable:
        line 51: 0
      LocalVariableTable:
        Start  Length  Slot  Name   Signature
            0       7     0  this   Lscala/reflect/Manifest;
    Signature: #188                         // ()Lscala/collection/immutable/List<Lscala/reflect/Manifest<*>;>;

  public static scala.reflect.Manifest arrayManifest$(scala.reflect.Manifest);
    descriptor: (Lscala/reflect/Manifest;)Lscala/reflect/Manifest;
    flags: (0x1009) ACC_PUBLIC, ACC_STATIC, ACC_SYNTHETIC
    Code:
      stack=1, locals=1, args_size=1
         0: aload_0
         1: invokespecial #96                 // InterfaceMethod arrayManifest:()Lscala/reflect/Manifest;
         4: areturn
      LineNumberTable:
        line 53: 0
      LocalVariableTable:
        Start  Length  Slot  Name   Signature
            0       5     0 $this   Lscala/reflect/Manifest;
    MethodParameters:
      Name                           Flags
      $this                          final synthetic

  public default scala.reflect.Manifest<java.lang.Object> arrayManifest();
    descriptor: ()Lscala/reflect/Manifest;
    flags: (0x0001) ACC_PUBLIC
    Code:
      stack=4, locals=3, args_size=1
         0: getstatic     #59                 // Field scala/reflect/Manifest$.MODULE$:Lscala/reflect/Manifest$;
         3: pop
         4: aload_0
         5: aload_0
         6: invokeinterface #203,  1          // InterfaceMethod runtimeClass:()Ljava/lang/Class;
        11: invokeinterface #207,  2          // InterfaceMethod arrayClass:(Ljava/lang/Class;)Ljava/lang/Class;
        16: getstatic     #212                // Field scala/collection/immutable/Nil$.MODULE$:Lscala/collection/immutable/Nil$;
        19: astore_2
        20: astore_1
        21: getstatic     #64                 // Field scala/reflect/ManifestFactory$.MODULE$:Lscala/reflect/ManifestFactory$;
        24: aload_1
        25: aload_0
        26: aload_2
        27: invokevirtual #107                // Method scala/reflect/ManifestFactory$.classType:(Ljava/lang/Class;Lscala/reflect/Manifest;Lscala/collection/immutable/Seq;)Lscala/reflect/Manifest;
        30: areturn
      LineNumberTable:
        line 54: 0
        line 119: 21
        line 54: 30
      LocalVariableTable:
        Start  Length  Slot  Name   Signature
            0      31     0  this   Lscala/reflect/Manifest;
           21       9     1 classType_clazz   Ljava/lang/Class;
           21       9     2 classType_args   Lscala/collection/immutable/Seq;
    Signature: #129                         // ()Lscala/reflect/Manifest<Ljava/lang/Object;>;

  public static boolean canEqual$(scala.reflect.Manifest, java.lang.Object);
    descriptor: (Lscala/reflect/Manifest;Ljava/lang/Object;)Z
    flags: (0x1009) ACC_PUBLIC, ACC_STATIC, ACC_SYNTHETIC
    Code:
      stack=2, locals=2, args_size=2
         0: aload_0
         1: aload_1
         2: invokespecial #221                // InterfaceMethod canEqual:(Ljava/lang/Object;)Z
         5: ireturn
      LineNumberTable:
        line 56: 0
      LocalVariableTable:
        Start  Length  Slot  Name   Signature
            0       6     0 $this   Lscala/reflect/Manifest;
            0       6     1  that   Ljava/lang/Object;
    MethodParameters:
      Name                           Flags
      $this                          final synthetic
      that                           final

  public default boolean canEqual(java.lang.Object);
    descriptor: (Ljava/lang/Object;)Z
    flags: (0x0001) ACC_PUBLIC
    Code:
      stack=1, locals=3, args_size=2
         0: aload_1
         1: instanceof    #2                  // class scala/reflect/Manifest
         4: ifeq          12
         7: iconst_1
         8: istore_2
         9: goto          14
        12: iconst_0
        13: istore_2
        14: iload_2
        15: ireturn
      StackMapTable: number_of_entries = 2
        frame_type = 12 /* same */
        frame_type = 252 /* append */
          offset_delta = 1
          locals = [ int ]
      LineNumberTable:
        line 57: 0
        line 58: 12
        line 56: 14
      LocalVariableTable:
        Start  Length  Slot  Name   Signature
            0      16     0  this   Lscala/reflect/Manifest;
            0      16     1  that   Ljava/lang/Object;
    MethodParameters:
      Name                           Flags
      that                           final

  public static boolean equals$(scala.reflect.Manifest, java.lang.Object);
    descriptor: (Lscala/reflect/Manifest;Ljava/lang/Object;)Z
    flags: (0x1009) ACC_PUBLIC, ACC_STATIC, ACC_SYNTHETIC
    Code:
      stack=2, locals=2, args_size=2
         0: aload_0
         1: aload_1
         2: invokespecial #225                // InterfaceMethod equals:(Ljava/lang/Object;)Z
         5: ireturn
      LineNumberTable:
        line 63: 0
      LocalVariableTable:
        Start  Length  Slot  Name   Signature
            0       6     0 $this   Lscala/reflect/Manifest;
            0       6     1  that   Ljava/lang/Object;
    MethodParameters:
      Name                           Flags
      $this                          final synthetic
      that                           final

  public default boolean equals(java.lang.Object);
    descriptor: (Ljava/lang/Object;)Z
    flags: (0x0001) ACC_PUBLIC
    Code:
      stack=2, locals=5, args_size=2
         0: aload_1
         1: instanceof    #2                  // class scala/reflect/Manifest
         4: ifeq          86
         7: aload_1
         8: checkcast     #2                  // class scala/reflect/Manifest
        11: astore_3
        12: aload_3
        13: aload_0
        14: invokeinterface #221,  2          // InterfaceMethod canEqual:(Ljava/lang/Object;)Z
        19: ifeq          81
        22: aload_0
        23: invokeinterface #203,  1          // InterfaceMethod runtimeClass:()Ljava/lang/Class;
        28: aload_3
        29: invokeinterface #203,  1          // InterfaceMethod runtimeClass:()Ljava/lang/Class;
        34: astore        4
        36: dup
        37: ifnonnull     49
        40: pop
        41: aload         4
        43: ifnull        57
        46: goto          81
        49: aload         4
        51: invokevirtual #226                // Method java/lang/Object.equals:(Ljava/lang/Object;)Z
        54: ifeq          81
        57: aload_0
        58: aload_3
        59: invokeinterface #230,  2          // InterfaceMethod $less$colon$less:(Lscala/reflect/ClassTag;)Z
        64: ifeq          81
        67: aload_3
        68: aload_0
        69: invokeinterface #230,  2          // InterfaceMethod $less$colon$less:(Lscala/reflect/ClassTag;)Z
        74: ifeq          81
        77: iconst_1
        78: goto          82
        81: iconst_0
        82: istore_2
        83: goto          88
        86: iconst_0
        87: istore_2
        88: iload_2
        89: ireturn
      StackMapTable: number_of_entries = 6
        frame_type = 255 /* full_frame */
          offset_delta = 49
          locals = [ class scala/reflect/Manifest, class java/lang/Object, top, class scala/reflect/Manifest, class java/lang/Class ]
          stack = [ class java/lang/Class ]
        frame_type = 7 /* same */
        frame_type = 250 /* chop */
          offset_delta = 23
        frame_type = 64 /* same_locals_1_stack_item */
          stack = [ int ]
        frame_type = 249 /* chop */
          offset_delta = 3
        frame_type = 252 /* append */
          offset_delta = 1
          locals = [ int ]
      LineNumberTable:
        line 64: 0
        line 65: 86
        line 63: 88
      LocalVariableTable:
        Start  Length  Slot  Name   Signature
            0      90     0  this   Lscala/reflect/Manifest;
            0      90     1  that   Ljava/lang/Object;
    MethodParameters:
      Name                           Flags
      that                           final

  public static int hashCode$(scala.reflect.Manifest);
    descriptor: (Lscala/reflect/Manifest;)I
    flags: (0x1009) ACC_PUBLIC, ACC_STATIC, ACC_SYNTHETIC
    Code:
      stack=1, locals=1, args_size=1
         0: aload_0
         1: invokespecial #238                // InterfaceMethod hashCode:()I
         4: ireturn
      LineNumberTable:
        line 67: 0
      LocalVariableTable:
        Start  Length  Slot  Name   Signature
            0       5     0 $this   Lscala/reflect/Manifest;
    MethodParameters:
      Name                           Flags
      $this                          final synthetic

  public default int hashCode();
    descriptor: ()I
    flags: (0x0001) ACC_PUBLIC
    Code:
      stack=1, locals=1, args_size=1
         0: aload_0
         1: invokeinterface #203,  1          // InterfaceMethod runtimeClass:()Ljava/lang/Class;
         6: invokestatic  #244                // Method scala/runtime/Statics.anyHash:(Ljava/lang/Object;)I
         9: ireturn
      LineNumberTable:
        line 67: 0
      LocalVariableTable:
        Start  Length  Slot  Name   Signature
            0      10     0  this   Lscala/reflect/Manifest;

  public static void $init$(scala.reflect.Manifest);
    descriptor: (Lscala/reflect/Manifest;)V
    flags: (0x0009) ACC_PUBLIC, ACC_STATIC
    Code:
      stack=0, locals=1, args_size=1
         0: return
      LineNumberTable:
        line 50: 0
      LocalVariableTable:
        Start  Length  Slot  Name   Signature
            0       1     0 $this   Lscala/reflect/Manifest;
    MethodParameters:
      Name                           Flags
      $this                          final synthetic
}
InnerClasses:
  private static #16= #13 of #15;         // AbstractTypeManifest=class scala/reflect/ManifestFactory$AbstractTypeManifest of class scala/reflect/ManifestFactory
  public static final #19= #18 of #15;    // BooleanManifest=class scala/reflect/ManifestFactory$BooleanManifest of class scala/reflect/ManifestFactory
  public static final #22= #21 of #15;    // ByteManifest=class scala/reflect/ManifestFactory$ByteManifest of class scala/reflect/ManifestFactory
  public static final #25= #24 of #15;    // CharManifest=class scala/reflect/ManifestFactory$CharManifest of class scala/reflect/ManifestFactory
  public static final #28= #27 of #15;    // DoubleManifest=class scala/reflect/ManifestFactory$DoubleManifest of class scala/reflect/ManifestFactory
  public static final #31= #30 of #15;    // FloatManifest=class scala/reflect/ManifestFactory$FloatManifest of class scala/reflect/ManifestFactory
  public static final #34= #33 of #15;    // IntManifest=class scala/reflect/ManifestFactory$IntManifest of class scala/reflect/ManifestFactory
  public static final #37= #36 of #15;    // LongManifest=class scala/reflect/ManifestFactory$LongManifest of class scala/reflect/ManifestFactory
  public static final #40= #39 of #15;    // ShortManifest=class scala/reflect/ManifestFactory$ShortManifest of class scala/reflect/ManifestFactory
  private static final #43= #42 of #15;   // SingletonTypeManifest=class scala/reflect/ManifestFactory$SingletonTypeManifest of class scala/reflect/ManifestFactory
  public static final #46= #45 of #15;    // UnitManifest=class scala/reflect/ManifestFactory$UnitManifest of class scala/reflect/ManifestFactory
  private static #49= #48 of #15;         // WildcardManifest=class scala/reflect/ManifestFactory$WildcardManifest of class scala/reflect/ManifestFactory
Signature: #3                           // <T:Ljava/lang/Object;>Ljava/lang/Object;Lscala/reflect/ClassTag<TT;>;
SourceFile: "Manifest.scala"
RuntimeVisibleAnnotations:
  0: #9(#10=s#11)
    scala.reflect.ScalaSignature(
      bytes="\u0006\u0005\rmba\u0002\u001a4!\u0003\r\t\u0001\u000f\u0005\u0006)\u0002!\t!\u0016\u0005\u00063\u0002!\tE\u0017\u0005\u0006M\u0002!\te\u001a\u0005\u0006Y\u0002!\t%\u001c\u0005\u0006g\u0002!\t\u0005\u001e\u0005\u0006m\u0002!\te^\u0004\b\u0003\u0017\u0019\u0004\u0012AA\u0007\r\u0019\u00114\u0007#\u0001\u0002\u0010!9\u0011\u0011\u0005\u0005\u0005\u0002\u0005\r\u0002bBA\u0013\u0011\u0011\u0005\u0011q\u0005\u0005\n\u0003sA!\u0019!C\u0001\u0003wA\u0001\"a\u0013\tA\u0003%\u0011Q\b\u0005\n\u0003\u001bB!\u0019!C\u0001\u0003\u001fB\u0001\"a\u0016\tA\u0003%\u0011\u0011\u000b\u0005\n\u00033B!\u0019!C\u0001\u00037B\u0001\"a\u0019\tA\u0003%\u0011Q\f\u0005\n\u0003KB!\u0019!C\u0001\u0003OB\u0001\"a\u001c\tA\u0003%\u0011\u0011\u000e\u0005\n\u0003cB!\u0019!C\u0001\u0003gB\u0001\"a\u001f\tA\u0003%\u0011Q\u000f\u0005\n\u0003{B!\u0019!C\u0001\u0003\u007fB\u0001\"a\"\tA\u0003%\u0011\u0011\u0011\u0005\n\u0003\u0013C!\u0019!C\u0001\u0003\u0017C\u0001\"a%\tA\u0003%\u0011Q\u0012\u0005\n\u0003+C!\u0019!C\u0001\u0003/C\u0001\"a(\tA\u0003%\u0011\u0011\u0014\u0005\n\u0003CC!\u0019!C\u0001\u0003GC\u0001\"a+\tA\u0003%\u0011Q\u0015\u0005\n\u0003[C!\u0019!C\u0001\u0003_C\u0001\"a-\tA\u0003%\u0011\u0011\u0017\u0005\n\u0003kC!\u0019!C\u0001\u0003oC\u0001\"a2\tA\u0003%\u0011\u0011\u0018\u0005\n\u0003\u0013D!\u0019!C\u0001\u0003\u0017D\u0001\"a4\tA\u0003%\u0011Q\u001a\u0005\n\u0003#D!\u0019!C\u0001\u0003\'D\u0001\"!8\tA\u0003%\u0011Q\u001b\u0005\n\u0003?D!\u0019!C\u0001\u0003CD\u0001\"a;\tA\u0003%\u00111\u001d\u0005\n\u0003[D!\u0019!C\u0001\u0003_D\u0001\"a=\tA\u0003%\u0011\u0011\u001f\u0005\b\u0003kDA\u0011AA|\u0011\u001d\u00119\u0001\u0003C\u0001\u0005\u0013AqAa\u0002\t\t\u0003\u0011i\u0003C\u0004\u0003\b!!\tAa\u0018\t\u000f\tE\u0005\u0002\"\u0001\u0003\u0014\"9!Q\u0016\u0005\u0005\u0002\t=\u0006b\u0002B{\u0011\u0011\u0005!q\u001f\u0005\b\u00077AA\u0011AB\u000f\u0011%\u00199\u0004CA\u0001\n\u0013\u0019ID\u0001\u0005NC:Lg-Z:u\u0015\t!T\'A\u0004sK\u001adWm\u0019;\u000b\u0003Y\nQa]2bY\u0006\u001c\u0001!\u0006\u0002:\u0011N!\u0001A\u000f R!\tYD(D\u00016\u0013\tiTG\u0001\u0004B]f\u0014VM\u001a\t\u0004\u007f\r3eB\u0001!B\u001b\u0005\u0019\u0014B\u0001\"4\u0003\u001d\u0001\u0018mY6bO\u0016L!\u0001R#\u0003\u001b\rc\u0017m]:NC:Lg-Z:u\u0015\t\u00115\u0007\u0005\u0002H\u00112\u0001A!B%\u0001\u0005\u0004Q%!\u0001+\u0012\u0005-s\u0005CA\u001eM\u0013\tiUGA\u0004O_RD\u0017N\\4\u0011\u0005mz\u0015B\u0001)6\u0005\r\te.\u001f\t\u0003wIK!aU\u001b\u0003\r\u0015\u000bX/\u00197t\u0003\u0019!\u0013N\\5uIQ\ta\u000b\u0005\u0002</&\u0011\u0001,\u000e\u0002\u0005+:LG/A\u0007usB,\u0017I]4v[\u0016tGo]\u000b\u00027B\u0019ALX1\u000f\u0005mj\u0016B\u0001\"6\u0013\ty\u0006M\u0001\u0003MSN$(B\u0001\"6a\t\u0011G\rE\u0002A\u0001\r\u0004\"a\u00123\u0005\u0013\u0015\u0014\u0011\u0011!A\u0001\u0006\u0003Q%aA0%c\u0005i\u0011M\u001d:bs6\u000bg.\u001b4fgR,\u0012\u0001\u001b\t\u0004\u0001\u0002I\u0007cA\u001ek\r&\u00111.\u000e\u0002\u0006\u0003J\u0014\u0018-_\u0001\tG\u0006tW)];bYR\u0011a.\u001d\t\u0003w=L!\u0001]\u001b\u0003\u000f\t{w\u000e\\3b]\")!\u000f\u0002a\u0001\u001d\u0006!A\u000f[1u\u0003\u0019)\u0017/^1mgR\u0011a.\u001e\u0005\u0006e\u0016\u0001\rAT\u0001\tQ\u0006\u001c\bnQ8eKR\t\u0001\u0010\u0005\u0002<s&\u0011!0\u000e\u0002\u0004\u0013:$\bF\u0002\u0001}\u0003\u000b\t9\u0001E\u0002~\u0003\u0003i\u0011A \u0006\u0003\u007fV\n!\"\u00198o_R\fG/[8o\u0013\r\t\u0019A \u0002\u0011S6\u0004H.[2ji:{GOR8v]\u0012\f1!\\:hC\t\tI!A\u0010O_\u0002j\u0015M\\5gKN$\b%\u0019<bS2\f\'\r\\3!M>\u0014\b\u0005J>U{:\n\u0001\"T1oS\u001a,7\u000f\u001e\t\u0003\u0001\"\u0019B\u0001\u0003\u001e\u0002\u0012A!\u00111CA\u000f\u001b\t\t)B\u0003\u0003\u0002\u0018\u0005e\u0011AA5p\u0015\t\tY\"\u0001\u0003kCZ\f\u0017\u0002BA\u0010\u0003+\u0011AbU3sS\u0006d\u0017N_1cY\u0016\fa\u0001P5oSRtDCAA\u0007\u000391\u0018\r\\;f\u001b\u0006t\u0017NZ3tiN,\"!!\u000b\u0011\tqs\u00161\u0006\u0019\u0005\u0003[\t)\u0004E\u0003A\u0003_\t\u0019$C\u0002\u00022M\u0012a\"\u00118z-\u0006dW*\u00198jM\u0016\u001cH\u000fE\u0002H\u0003k!!\"a\u000e\u000b\u0003\u0003\u0005\tQ!\u0001K\u0005\ryFEM\u0001\u0005\u0005f$X-\u0006\u0002\u0002>A!\u0011qHA#\u001d\r\u0001\u0015\u0011I\u0005\u0004\u0003\u0007\u001a\u0014aD\'b]&4Wm\u001d;GC\u000e$xN]=\n\t\u0005\u001d\u0013\u0011\n\u0002\r\u0005f$X-T1oS\u001a,7\u000f\u001e\u0006\u0004\u0003\u0007\u001a\u0014!\u0002\"zi\u0016\u0004\u0013!B*i_J$XCAA)!\u0011\ty$a\u0015\n\t\u0005U\u0013\u0011\n\u0002\u000e\'\"|\'\u000f^\'b]&4Wm\u001d;\u0002\rMCwN\u001d;!\u0003\u0011\u0019\u0005.\u0019:\u0016\u0005\u0005u\u0003\u0003BA \u0003?JA!!\u0019\u0002J\ta1\t[1s\u001b\u0006t\u0017NZ3ti\u0006)1\t[1sA\u0005\u0019\u0011J\u001c;\u0016\u0005\u0005%\u0004\u0003BA \u0003WJA!!\u001c\u0002J\tY\u0011J\u001c;NC:Lg-Z:u\u0003\u0011Ie\u000e\u001e\u0011\u0002\t1{gnZ\u000b\u0003\u0003k\u0002B!a\u0010\u0002x%!\u0011\u0011PA%\u00051auN\\4NC:Lg-Z:u\u0003\u0015auN\\4!\u0003\u00151En\\1u+\t\t\t\t\u0005\u0003\u0002@\u0005\r\u0015\u0002BAC\u0003\u0013\u0012QB\u00127pCRl\u0015M\\5gKN$\u0018A\u0002$m_\u0006$\b%\u0001\u0004E_V\u0014G.Z\u000b\u0003\u0003\u001b\u0003B!a\u0010\u0002\u0010&!\u0011\u0011SA%\u00059!u.\u001e2mK6\u000bg.\u001b4fgR\fq\u0001R8vE2,\u0007%A\u0004C_>dW-\u00198\u0016\u0005\u0005e\u0005\u0003BA \u00037KA!!(\u0002J\ty!i\\8mK\u0006tW*\u00198jM\u0016\u001cH/\u0001\u0005C_>dW-\u00198!\u0003\u0011)f.\u001b;\u0016\u0005\u0005\u0015\u0006\u0003BA \u0003OKA!!+\u0002J\taQK\\5u\u001b\u0006t\u0017NZ3ti\u0006)QK\\5uA\u0005\u0019\u0011I\\=\u0016\u0005\u0005E\u0006c\u0001!\u0001\u001d\u0006!\u0011I\\=!\u0003\u0019y%M[3diV\u0011\u0011\u0011\u0018\t\u0005\u0001\u0002\tY\f\u0005\u0003\u0002>\u0006\rWBAA`\u0015\u0011\t\t-!\u0007\u0002\t1\fgnZ\u0005\u0005\u0003\u000b\fyL\u0001\u0004PE*,7\r^\u0001\b\u001f\nTWm\u0019;!\u0003\u0019\te.\u001f*fMV\u0011\u0011Q\u001a\t\u0004\u0001\u0002Q\u0014aB!osJ+g\rI\u0001\u0007\u0003:Lh+\u00197\u0016\u0005\u0005U\u0007\u0003\u0002!\u0001\u0003/\u00042aOAm\u0013\r\tY.\u000e\u0002\u0007\u0003:Lh+\u00197\u0002\u000f\u0005s\u0017PV1mA\u0005!a*\u001e7m+\t\t\u0019\u000f\u0005\u0003A\u0001\u0005\u0015\bcA\u001e\u0002h&\u0019\u0011\u0011^\u001b\u0003\t9+H\u000e\\\u0001\u0006\u001dVdG\u000eI\u0001\b\u001d>$\b.\u001b8h+\t\t\t\u0010E\u0002A\u0001-\u000b\u0001BT8uQ&tw\rI\u0001\u000bg&tw\r\\3UsB,W\u0003BA}\u0003\u007f$B!a?\u0003\u0004A!\u0001\tAA\u007f!\r9\u0015q \u0003\u0007\u0013&\u0012\rA!\u0001\u0012\u0005-S\u0004B\u0002B\u0003S\u0001\u0007!(A\u0003wC2,X-A\u0005dY\u0006\u001c8\u000fV=qKV!!1\u0002B\t)\u0011\u0011iAa\u0005\u0011\t\u0001\u0003!q\u0002\t\u0004\u000f\nEA!B%+\u0005\u0004Q\u0005b\u0002B\u000bU\u0001\u0007!qC\u0001\u0006G2\f\'P\u001f\u0019\u0005\u00053\u0011I\u0003\u0005\u0004\u0003\u001c\t\u0005\"q\u0005\b\u0004w\tu\u0011b\u0001B\u0010k\u00051\u0001K]3eK\u001aLAAa\t\u0003&\t)1\t\\1tg*\u0019!qD\u001b\u0011\u0007\u001d\u0013I\u0003B\u0006\u0003,\tM\u0011\u0011!A\u0001\u0006\u0003Q%aA0%gU!!q\u0006B\u001b)!\u0011\tDa\u000e\u0003<\t%\u0003\u0003\u0002!\u0001\u0005g\u00012a\u0012B\u001b\t\u0015I5F1\u0001K\u0011\u001d\u0011)b\u000ba\u0001\u0005s\u0001bAa\u0007\u0003\"\tM\u0002b\u0002B\u001fW\u0001\u0007!qH\u0001\u0005CJ<\u0017\u0007\r\u0003\u0003B\t\u0015\u0003\u0003\u0002!\u0001\u0005\u0007\u00022a\u0012B#\t-\u00119Ea\u000f\u0002\u0002\u0003\u0005)\u0011\u0001&\u0003\u0007}#C\u0007C\u0004\u0003L-\u0002\rA!\u0014\u0002\t\u0005\u0014xm\u001d\t\u0006w\t=#1K\u0005\u0004\u0005#*$A\u0003\u001fsKB,\u0017\r^3e}A\"!Q\u000bB-!\u0011\u0001\u0005Aa\u0016\u0011\u0007\u001d\u0013I\u0006B\u0006\u0003\\\tu\u0013\u0011!A\u0001\u0006\u0003Q%aA0%k!9!1J\u0016A\u0002\t5S\u0003\u0002B1\u0005O\"\u0002Ba\u0019\u0003j\t]$1\u0011\t\u0005\u0001\u0002\u0011)\u0007E\u0002H\u0005O\"Q!\u0013\u0017C\u0002)CqAa\u001b-\u0001\u0004\u0011i\'\u0001\u0004qe\u00164\u0017\u000e\u001f\u0019\u0005\u0005_\u0012\u0019\b\u0005\u0003A\u0001\tE\u0004cA$\u0003t\u0011Y!Q\u000fB5\u0003\u0003\u0005\tQ!\u0001K\u0005\ryFE\u000e\u0005\b\u0005+a\u0003\u0019\u0001B=a\u0011\u0011YHa \u0011\r\tm!\u0011\u0005B?!\r9%q\u0010\u0003\f\u0005\u0003\u00139(!A\u0001\u0002\u000b\u0005!JA\u0002`I]BqAa\u0013-\u0001\u0004\u0011)\tE\u0003<\u0005\u001f\u00129\t\r\u0003\u0003\n\n5\u0005\u0003\u0002!\u0001\u0005\u0017\u00032a\u0012BG\t-\u0011yIa!\u0002\u0002\u0003\u0005)\u0011\u0001&\u0003\u0007}#\u0003(A\u0005beJ\f\u0017\u0010V=qKV!!Q\u0013BO)\u0011\u00119Ja(\u0011\t\u0001\u0003!\u0011\u0014\t\u0005w)\u0014Y\nE\u0002H\u0005;#Q!S\u0017C\u0002)CqA!).\u0001\u0004\u0011\u0019+A\u0002be\u001e\u0004DA!*\u0003*B!\u0001\t\u0001BT!\r9%\u0011\u0016\u0003\f\u0005W\u0013y*!A\u0001\u0002\u000b\u0005!JA\u0002`Ie\nA\"\u00192tiJ\f7\r\u001e+za\u0016,BA!-\u00038RQ!1\u0017B]\u0005\u000b\u0014INa:\u0011\t\u0001\u0003!Q\u0017\t\u0004\u000f\n]F!B%/\u0005\u0004Q\u0005b\u0002B6]\u0001\u0007!1\u0018\u0019\u0005\u0005{\u0013\t\r\u0005\u0003A\u0001\t}\u0006cA$\u0003B\u0012Y!1\u0019B]\u0003\u0003\u0005\tQ!\u0001K\u0005\u0011yF%\r\u0019\t\u000f\t\u001dg\u00061\u0001\u0003J\u0006!a.Y7f!\u0011\u0011YM!6\u000f\t\t5\'Q\u0004\t\u0004\u0005\u001f,TB\u0001Bi\u0015\r\u0011\u0019nN\u0001\u0007yI|w\u000e\u001e \n\t\t]\'Q\u0005\u0002\u0007\'R\u0014\u0018N\\4\t\u000f\tmg\u00061\u0001\u0003^\u0006QQ\u000f\u001d9fe\n{WO\u001c31\t\t}\'1\u001d\t\u0007\u00057\u0011\tC!9\u0011\u0007\u001d\u0013\u0019\u000fB\u0006\u0003f\ne\u0017\u0011!A\u0001\u0006\u0003Q%\u0001B0%cEBqAa\u0013/\u0001\u0004\u0011I\u000fE\u0003<\u0005\u001f\u0012Y\u000f\r\u0003\u0003n\nE\b\u0003\u0002!\u0001\u0005_\u00042a\u0012By\t-\u0011\u0019Pa:\u0002\u0002\u0003\u0005)\u0011\u0001&\u0003\t}#\u0013GM\u0001\ro&dGmY1sIRK\b/Z\u000b\u0005\u0005s\u0014y\u0010\u0006\u0004\u0003|\u000e\u00051q\u0002\t\u0005\u0001\u0002\u0011i\u0010E\u0002H\u0005\u007f$Q!S\u0018C\u0002)Cqaa\u00010\u0001\u0004\u0019)!\u0001\u0006m_^,\'OQ8v]\u0012\u0004Daa\u0002\u0004\fA!\u0001\tAB\u0005!\r951\u0002\u0003\f\u0007\u001b\u0019\t!!A\u0001\u0002\u000b\u0005!J\u0001\u0003`IE\u001a\u0004b\u0002Bn_\u0001\u00071\u0011\u0003\u0019\u0005\u0007\'\u00199\u0002\u0005\u0003A\u0001\rU\u0001cA$\u0004\u0018\u0011Y1\u0011DB\b\u0003\u0003\u0005\tQ!\u0001K\u0005\u0011yF%\r\u001b\u0002!%tG/\u001a:tK\u000e$\u0018n\u001c8UsB,W\u0003BB\u0010\u0007K!Ba!\t\u0004(A!\u0001\tAB\u0012!\r95Q\u0005\u0003\u0006\u0013B\u0012\rA\u0013\u0005\b\u0007S\u0001\u0004\u0019AB\u0016\u0003\u001d\u0001\u0018M]3oiN\u0004Ra\u000fB(\u0007[\u0001Daa\f\u00044A!\u0001\tAB\u0019!\r951\u0007\u0003\f\u0007k\u00199#!A\u0001\u0002\u000b\u0005!J\u0001\u0003`IE*\u0014\u0001D<sSR,\'+\u001a9mC\u000e,GCAA^\u0001"
    )
  ScalaInlineInfo: length = 0x3B (unknown attribute)
   01 00 00 0B 00 F5 00 F6 01 00 5D 00 5E 00 00 C7
   00 5A 01 00 DA 00 DB 00 00 D7 00 D8 01 00 DF 00
   DB 00 00 DE 00 D8 01 00 EB 00 EC 00 00 E9 00 EA
   01 00 B9 00 B2 00 00 B6 00 B7 01
  ScalaSig: length = 0x3 (unknown attribute)
   05 02 00
