Classfile /Users/mw/Projects/slang-braindump/.jar/jar11/assemble/slang-braindump/assemble/content/scala/reflect/NoManifest.class
  Last modified May 29, 2022; size 731 bytes
  SHA-256 checksum 4df5039555403c365e726bbe62b118f3a175b0a6feb6193bea21a0c4c6a14781
  Compiled from "NoManifest.scala"
public final class scala.reflect.NoManifest
  minor version: 0
  major version: 52
  flags: (0x0031) ACC_PUBLIC, ACC_FINAL, ACC_SUPER
  this_class: #2                          // scala/reflect/NoManifest
  super_class: #4                         // java/lang/Object
  interfaces: 0, fields: 0, methods: 1, attributes: 3
Constant pool:
   #1 = Utf8               scala/reflect/NoManifest
   #2 = Class              #1             // scala/reflect/NoManifest
   #3 = Utf8               java/lang/Object
   #4 = Class              #3             // java/lang/Object
   #5 = Utf8               NoManifest.scala
   #6 = Utf8               Lscala/reflect/ScalaSignature;
   #7 = Utf8               bytes
   #8 = Utf8               \u0006\u0005E:Q!\u0002\u0004\t\u0002-1Q!\u0004\u0004\t\u00029AQ\u0001I\u0001\u0005\u0002\u0005BQAI\u0001\u0005B\rBq\u0001L\u0001\u0002\u0002\u0013%Q&\u0001\u0006O_6\u000bg.\u001b4fgRT!a\u0002\u0005\u0002\u000fI,g\r\\3di*\t\u0011\"A\u0003tG\u0006d\u0017m\u0001\u0001\u0011\u00051\tQ\"\u0001\u0004\u0003\u00159{W*\u00198jM\u0016\u001cHo\u0005\u0003\u0002\u001fMI\u0002C\u0001\t\u0012\u001b\u0005A\u0011B\u0001\n\t\u0005\u0019\te.\u001f*fMB\u0019A\u0002\u0006\f\n\u0005U1!aC(qi6\u000bg.\u001b4fgR\u0004\"\u0001E\f\n\u0005aA!a\u0002(pi\"Lgn\u001a\t\u00035uq!\u0001E\u000e\n\u0005qA\u0011a\u00029bG.\fw-Z\u0005\u0003=}\u0011AbU3sS\u0006d\u0017N_1cY\u0016T!\u0001\b\u0005\u0002\rqJg.\u001b;?)\u0005Y\u0011\u0001\u0003;p\'R\u0014\u0018N\\4\u0015\u0003\u0011\u0002\"!\n\u0016\u000e\u0003\u0019R!a\n\u0015\u0002\t1\fgn\u001a\u0006\u0002S\u0005!!.\u0019<b\u0013\tYcE\u0001\u0004TiJLgnZ\u0001\roJLG/\u001a*fa2\f7-\u001a\u000b\u0002]A\u0011QeL\u0005\u0003a\u0019\u0012aa\u00142kK\u000e$\b
   #9 = Utf8               toString
  #10 = Utf8               ()Ljava/lang/String;
  #11 = Utf8               scala/reflect/NoManifest$
  #12 = Class              #11            // scala/reflect/NoManifest$
  #13 = Utf8               MODULE$
  #14 = Utf8               Lscala/reflect/NoManifest$;
  #15 = NameAndType        #13:#14        // MODULE$:Lscala/reflect/NoManifest$;
  #16 = Fieldref           #12.#15        // scala/reflect/NoManifest$.MODULE$:Lscala/reflect/NoManifest$;
  #17 = NameAndType        #9:#10         // toString:()Ljava/lang/String;
  #18 = Methodref          #12.#17        // scala/reflect/NoManifest$.toString:()Ljava/lang/String;
  #19 = Utf8               Code
  #20 = Utf8               SourceFile
  #21 = Utf8               RuntimeVisibleAnnotations
  #22 = Utf8               ScalaSig
{
  public static java.lang.String toString();
    descriptor: ()Ljava/lang/String;
    flags: (0x0009) ACC_PUBLIC, ACC_STATIC
    Code:
      stack=1, locals=0, args_size=0
         0: getstatic     #16                 // Field scala/reflect/NoManifest$.MODULE$:Lscala/reflect/NoManifest$;
         3: invokevirtual #18                 // Method scala/reflect/NoManifest$.toString:()Ljava/lang/String;
         6: areturn
}
SourceFile: "NoManifest.scala"
RuntimeVisibleAnnotations:
  0: #6(#7=s#8)
    scala.reflect.ScalaSignature(
      bytes="\u0006\u0005E:Q!\u0002\u0004\t\u0002-1Q!\u0004\u0004\t\u00029AQ\u0001I\u0001\u0005\u0002\u0005BQAI\u0001\u0005B\rBq\u0001L\u0001\u0002\u0002\u0013%Q&\u0001\u0006O_6\u000bg.\u001b4fgRT!a\u0002\u0005\u0002\u000fI,g\r\\3di*\t\u0011\"A\u0003tG\u0006d\u0017m\u0001\u0001\u0011\u00051\tQ\"\u0001\u0004\u0003\u00159{W*\u00198jM\u0016\u001cHo\u0005\u0003\u0002\u001fMI\u0002C\u0001\t\u0012\u001b\u0005A\u0011B\u0001\n\t\u0005\u0019\te.\u001f*fMB\u0019A\u0002\u0006\f\n\u0005U1!aC(qi6\u000bg.\u001b4fgR\u0004\"\u0001E\f\n\u0005aA!a\u0002(pi\"Lgn\u001a\t\u00035uq!\u0001E\u000e\n\u0005qA\u0011a\u00029bG.\fw-Z\u0005\u0003=}\u0011AbU3sS\u0006d\u0017N_1cY\u0016T!\u0001\b\u0005\u0002\rqJg.\u001b;?)\u0005Y\u0011\u0001\u0003;p\'R\u0014\u0018N\\4\u0015\u0003\u0011\u0002\"!\n\u0016\u000e\u0003\u0019R!a\n\u0015\u0002\t1\fgn\u001a\u0006\u0002S\u0005!!.\u0019<b\u0013\tYcE\u0001\u0004TiJLgnZ\u0001\roJLG/\u001a*fa2\f7-\u001a\u000b\u0002]A\u0011QeL\u0005\u0003a\u0019\u0012aa\u00142kK\u000e$\b"
    )
  ScalaSig: length = 0x3 (unknown attribute)
   05 02 00
