Classfile /Users/mw/Projects/slang-braindump/.jar/jar11/assemble/slang-braindump/assemble/content/org/sireum/$internal/$hash$hash$hash$.class
  Last modified May 29, 2022; size 809 bytes
  SHA-256 checksum d59caa26326d2948ce761da7028cdd9cf4359e724c36d94ae57a463ea3f7b9b7
  Compiled from "CC.scala"
public final class org.sireum.$internal.$hash$hash$hash$
  minor version: 0
  major version: 52
  flags: (0x0031) ACC_PUBLIC, ACC_FINAL, ACC_SUPER
  this_class: #2                          // org/sireum/$internal/$hash$hash$hash$
  super_class: #4                         // java/lang/Object
  interfaces: 0, fields: 1, methods: 3, attributes: 3
Constant pool:
   #1 = Utf8               org/sireum/$internal/$hash$hash$hash$
   #2 = Class              #1             // org/sireum/$internal/$hash$hash$hash$
   #3 = Utf8               java/lang/Object
   #4 = Class              #3             // java/lang/Object
   #5 = Utf8               CC.scala
   #6 = Utf8               MODULE$
   #7 = Utf8               Lorg/sireum/$internal/$hash$hash$hash$;
   #8 = Utf8               <clinit>
   #9 = Utf8               ()V
  #10 = Utf8               <init>
  #11 = NameAndType        #10:#9         // "<init>":()V
  #12 = Methodref          #2.#11         // org/sireum/$internal/$hash$hash$hash$."<init>":()V
  #13 = NameAndType        #6:#7          // MODULE$:Lorg/sireum/$internal/$hash$hash$hash$;
  #14 = Fieldref           #2.#13         // org/sireum/$internal/$hash$hash$hash$.MODULE$:Lorg/sireum/$internal/$hash$hash$hash$;
  #15 = Utf8               apply
  #16 = Utf8               (ZLscala/Function0;)V
  #17 = Utf8               (ZLscala/Function0<Lscala/runtime/BoxedUnit;>;)V
  #18 = Utf8               cond
  #19 = Utf8               f
  #20 = Utf8               scala/Predef$
  #21 = Class              #20            // scala/Predef$
  #22 = Utf8               Lscala/Predef$;
  #23 = NameAndType        #6:#22         // MODULE$:Lscala/Predef$;
  #24 = Fieldref           #21.#23        // scala/Predef$.MODULE$:Lscala/Predef$;
  #25 = Utf8               $qmark$qmark$qmark
  #26 = Utf8               ()Lscala/runtime/Nothing$;
  #27 = NameAndType        #25:#26        // $qmark$qmark$qmark:()Lscala/runtime/Nothing$;
  #28 = Methodref          #21.#27        // scala/Predef$.$qmark$qmark$qmark:()Lscala/runtime/Nothing$;
  #29 = Utf8               this
  #30 = Utf8               Z
  #31 = Utf8               Lscala/Function0;
  #32 = Methodref          #4.#11         // java/lang/Object."<init>":()V
  #33 = Utf8               Code
  #34 = Utf8               LineNumberTable
  #35 = Utf8               LocalVariableTable
  #36 = Utf8               Signature
  #37 = Utf8               MethodParameters
  #38 = Utf8               SourceFile
  #39 = Utf8               ScalaInlineInfo
  #40 = Utf8               Scala
{
  public static final org.sireum.$internal.$hash$hash$hash$ MODULE$;
    descriptor: Lorg/sireum/$internal/$hash$hash$hash$;
    flags: (0x0019) ACC_PUBLIC, ACC_STATIC, ACC_FINAL

  public static {};
    descriptor: ()V
    flags: (0x0009) ACC_PUBLIC, ACC_STATIC
    Code:
      stack=2, locals=0, args_size=0
         0: new           #2                  // class org/sireum/$internal/$hash$hash$hash$
         3: dup
         4: invokespecial #12                 // Method "<init>":()V
         7: putstatic     #14                 // Field MODULE$:Lorg/sireum/$internal/$hash$hash$hash$;
        10: return
      LineNumberTable:
        line 28: 0

  public void apply(boolean, scala.Function0<scala.runtime.BoxedUnit>);
    descriptor: (ZLscala/Function0;)V
    flags: (0x0001) ACC_PUBLIC
    Code:
      stack=1, locals=3, args_size=3
         0: getstatic     #24                 // Field scala/Predef$.MODULE$:Lscala/Predef$;
         3: invokevirtual #28                 // Method scala/Predef$.$qmark$qmark$qmark:()Lscala/runtime/Nothing$;
         6: athrow
      LineNumberTable:
        line 29: 0
      LocalVariableTable:
        Start  Length  Slot  Name   Signature
            0       7     0  this   Lorg/sireum/$internal/$hash$hash$hash$;
            0       7     1  cond   Z
            0       7     2     f   Lscala/Function0;
    Signature: #17                          // (ZLscala/Function0<Lscala/runtime/BoxedUnit;>;)V
    MethodParameters:
      Name                           Flags
      cond                           final
      f                              final

  private org.sireum.$internal.$hash$hash$hash$();
    descriptor: ()V
    flags: (0x0002) ACC_PRIVATE
    Code:
      stack=1, locals=1, args_size=1
         0: aload_0
         1: invokespecial #32                 // Method java/lang/Object."<init>":()V
         4: return
      LineNumberTable:
        line 28: 0
      LocalVariableTable:
        Start  Length  Slot  Name   Signature
            0       5     0  this   Lorg/sireum/$internal/$hash$hash$hash$;
}
SourceFile: "CC.scala"
  ScalaInlineInfo: length = 0xE (unknown attribute)
   01 01 00 02 00 0A 00 09 01 00 0F 00 10 01
  Scala: length = 0x0 (unknown attribute)

