Classfile /Users/mw/Projects/slang-braindump/.jar/jar11/assemble/slang-braindump/assemble/content/org/sireum/$internal/Macro$$anon$1.class
  Last modified May 29, 2022; size 6706 bytes
  SHA-256 checksum 8f3d551446c6f8dc7667240511371895eb4218e5119cf0c2fd24b12fac8bc1a5
  Compiled from "Macro.scala"
public final class org.sireum.$internal.Macro$$anon$1
  minor version: 0
  major version: 52
  flags: (0x0031) ACC_PUBLIC, ACC_FINAL, ACC_SUPER
  this_class: #2                          // org/sireum/$internal/Macro$$anon$1
  super_class: #4                         // java/lang/Object
  interfaces: 0, fields: 1, methods: 2, attributes: 5
Constant pool:
    #1 = Utf8               org/sireum/$internal/Macro$$anon$1
    #2 = Class              #1            // org/sireum/$internal/Macro$$anon$1
    #3 = Utf8               java/lang/Object
    #4 = Class              #3            // java/lang/Object
    #5 = Utf8               Macro.scala
    #6 = Utf8               org/sireum/$internal/Macro
    #7 = Class              #6            // org/sireum/$internal/Macro
    #8 = Utf8               extractParts
    #9 = Utf8               ()Lscala/collection/immutable/Seq;
   #10 = NameAndType        #8:#9         // extractParts:()Lscala/collection/immutable/Seq;
   #11 = Utf8               scala/reflect/api/Internals$InternalApi
   #12 = Class              #11           // scala/reflect/api/Internals$InternalApi
   #13 = Utf8               scala/reflect/api/Internals
   #14 = Class              #13           // scala/reflect/api/Internals
   #15 = Utf8               InternalApi
   #16 = Utf8               scala/reflect/api/Internals$ReificationSupportApi
   #17 = Class              #16           // scala/reflect/api/Internals$ReificationSupportApi
   #18 = Utf8               ReificationSupportApi
   #19 = Utf8               scala/reflect/api/Internals$ReificationSupportApi$SyntacticAppliedExtractor
   #20 = Class              #19           // scala/reflect/api/Internals$ReificationSupportApi$SyntacticAppliedExtractor
   #21 = Utf8               SyntacticAppliedExtractor
   #22 = Utf8               scala/reflect/api/Internals$ReificationSupportApi$SyntacticSelectTermExtractor
   #23 = Class              #22           // scala/reflect/api/Internals$ReificationSupportApi$SyntacticSelectTermExtractor
   #24 = Utf8               SyntacticSelectTermExtractor
   #25 = Utf8               scala/reflect/api/Internals$ReificationSupportApi$SyntacticTermIdentExtractor
   #26 = Class              #25           // scala/reflect/api/Internals$ReificationSupportApi$SyntacticTermIdentExtractor
   #27 = Utf8               SyntacticTermIdentExtractor
   #28 = Utf8               scala/reflect/api/Names$TermNameApi
   #29 = Class              #28           // scala/reflect/api/Names$TermNameApi
   #30 = Utf8               scala/reflect/api/Names
   #31 = Class              #30           // scala/reflect/api/Names
   #32 = Utf8               TermNameApi
   #33 = Utf8               scala/reflect/api/Names$TermNameExtractor
   #34 = Class              #33           // scala/reflect/api/Names$TermNameExtractor
   #35 = Utf8               TermNameExtractor
   #36 = Utf8               scala/reflect/api/Trees$IdentApi
   #37 = Class              #36           // scala/reflect/api/Trees$IdentApi
   #38 = Utf8               scala/reflect/api/Trees
   #39 = Class              #38           // scala/reflect/api/Trees
   #40 = Utf8               IdentApi
   #41 = Utf8               scala/reflect/api/Trees$TreeApi
   #42 = Class              #41           // scala/reflect/api/Trees$TreeApi
   #43 = Utf8               TreeApi
   #44 = Utf8               $outer
   #45 = Utf8               Lorg/sireum/$internal/Macro;
   #46 = Utf8               unapply
   #47 = Utf8               (Ljava/lang/Object;)Lscala/Option;
   #48 = Utf8               (Ljava/lang/Object;)Lscala/Option<Lscala/Tuple2<Lscala/collection/immutable/List<Lscala/reflect/api/Trees$TreeApi;>;Lscala/reflect/api/Names$TermNameApi;>;>;
   #49 = Utf8               tree
   #50 = NameAndType        #44:#45       // $outer:Lorg/sireum/$internal/Macro;
   #51 = Fieldref           #2.#50        // org/sireum/$internal/Macro$$anon$1.$outer:Lorg/sireum/$internal/Macro;
   #52 = Utf8               c
   #53 = Utf8               ()Lscala/reflect/macros/blackbox/Context;
   #54 = NameAndType        #52:#53       // c:()Lscala/reflect/macros/blackbox/Context;
   #55 = Methodref          #7.#54        // org/sireum/$internal/Macro.c:()Lscala/reflect/macros/blackbox/Context;
   #56 = Utf8               scala/reflect/macros/blackbox/Context
   #57 = Class              #56           // scala/reflect/macros/blackbox/Context
   #58 = Utf8               universe
   #59 = Utf8               ()Lscala/reflect/macros/Universe;
   #60 = NameAndType        #58:#59       // universe:()Lscala/reflect/macros/Universe;
   #61 = InterfaceMethodref #57.#60       // scala/reflect/macros/blackbox/Context.universe:()Lscala/reflect/macros/Universe;
   #62 = Utf8               scala/reflect/macros/Universe
   #63 = Class              #62           // scala/reflect/macros/Universe
   #64 = Utf8               TreeTag
   #65 = Utf8               ()Lscala/reflect/ClassTag;
   #66 = NameAndType        #64:#65       // TreeTag:()Lscala/reflect/ClassTag;
   #67 = Methodref          #63.#66       // scala/reflect/macros/Universe.TreeTag:()Lscala/reflect/ClassTag;
   #68 = Utf8               scala/reflect/ClassTag
   #69 = Class              #68           // scala/reflect/ClassTag
   #70 = NameAndType        #46:#47       // unapply:(Ljava/lang/Object;)Lscala/Option;
   #71 = InterfaceMethodref #69.#70       // scala/reflect/ClassTag.unapply:(Ljava/lang/Object;)Lscala/Option;
   #72 = Utf8               scala/Option
   #73 = Class              #72           // scala/Option
   #74 = Utf8               isEmpty
   #75 = Utf8               ()Z
   #76 = NameAndType        #74:#75       // isEmpty:()Z
   #77 = Methodref          #73.#76       // scala/Option.isEmpty:()Z
   #78 = Utf8               get
   #79 = Utf8               ()Ljava/lang/Object;
   #80 = NameAndType        #78:#79       // get:()Ljava/lang/Object;
   #81 = Methodref          #73.#80       // scala/Option.get:()Ljava/lang/Object;
   #82 = Utf8               internal
   #83 = Utf8               ()Lscala/reflect/api/Internals$InternalApi;
   #84 = NameAndType        #82:#83       // internal:()Lscala/reflect/api/Internals$InternalApi;
   #85 = Methodref          #63.#84       // scala/reflect/macros/Universe.internal:()Lscala/reflect/api/Internals$InternalApi;
   #86 = Utf8               reificationSupport
   #87 = Utf8               ()Lscala/reflect/api/Internals$ReificationSupportApi;
   #88 = NameAndType        #86:#87       // reificationSupport:()Lscala/reflect/api/Internals$ReificationSupportApi;
   #89 = InterfaceMethodref #12.#88       // scala/reflect/api/Internals$InternalApi.reificationSupport:()Lscala/reflect/api/Internals$ReificationSupportApi;
   #90 = Utf8               SyntacticSelectTerm
   #91 = Utf8               ()Lscala/reflect/api/Internals$ReificationSupportApi$SyntacticSelectTermExtractor;
   #92 = NameAndType        #90:#91       // SyntacticSelectTerm:()Lscala/reflect/api/Internals$ReificationSupportApi$SyntacticSelectTermExtractor;
   #93 = InterfaceMethodref #17.#92       // scala/reflect/api/Internals$ReificationSupportApi.SyntacticSelectTerm:()Lscala/reflect/api/Internals$ReificationSupportApi$SyntacticSelectTermExtractor;
   #94 = Utf8               (Lscala/reflect/api/Trees$TreeApi;)Lscala/Option;
   #95 = NameAndType        #46:#94       // unapply:(Lscala/reflect/api/Trees$TreeApi;)Lscala/Option;
   #96 = InterfaceMethodref #23.#95       // scala/reflect/api/Internals$ReificationSupportApi$SyntacticSelectTermExtractor.unapply:(Lscala/reflect/api/Trees$TreeApi;)Lscala/Option;
   #97 = Utf8               scala/Tuple2
   #98 = Class              #97           // scala/Tuple2
   #99 = Utf8               _1
  #100 = NameAndType        #99:#79       // _1:()Ljava/lang/Object;
  #101 = Methodref          #98.#100      // scala/Tuple2._1:()Ljava/lang/Object;
  #102 = Utf8               _2
  #103 = NameAndType        #102:#79      // _2:()Ljava/lang/Object;
  #104 = Methodref          #98.#103      // scala/Tuple2._2:()Ljava/lang/Object;
  #105 = Utf8               SyntacticApplied
  #106 = Utf8               ()Lscala/reflect/api/Internals$ReificationSupportApi$SyntacticAppliedExtractor;
  #107 = NameAndType        #105:#106     // SyntacticApplied:()Lscala/reflect/api/Internals$ReificationSupportApi$SyntacticAppliedExtractor;
  #108 = InterfaceMethodref #17.#107      // scala/reflect/api/Internals$ReificationSupportApi.SyntacticApplied:()Lscala/reflect/api/Internals$ReificationSupportApi$SyntacticAppliedExtractor;
  #109 = Utf8               (Lscala/reflect/api/Trees$TreeApi;)Lscala/Some;
  #110 = NameAndType        #46:#109      // unapply:(Lscala/reflect/api/Trees$TreeApi;)Lscala/Some;
  #111 = InterfaceMethodref #20.#110      // scala/reflect/api/Internals$ReificationSupportApi$SyntacticAppliedExtractor.unapply:(Lscala/reflect/api/Trees$TreeApi;)Lscala/Some;
  #112 = Utf8               scala/Some
  #113 = Class              #112          // scala/Some
  #114 = Methodref          #113.#76      // scala/Some.isEmpty:()Z
  #115 = Methodref          #113.#80      // scala/Some.get:()Ljava/lang/Object;
  #116 = Utf8               scala/collection/immutable/List
  #117 = Class              #116          // scala/collection/immutable/List
  #118 = Utf8               IdentTag
  #119 = NameAndType        #118:#65      // IdentTag:()Lscala/reflect/ClassTag;
  #120 = Methodref          #63.#119      // scala/reflect/macros/Universe.IdentTag:()Lscala/reflect/ClassTag;
  #121 = Utf8               SyntacticTermIdent
  #122 = Utf8               ()Lscala/reflect/api/Internals$ReificationSupportApi$SyntacticTermIdentExtractor;
  #123 = NameAndType        #121:#122     // SyntacticTermIdent:()Lscala/reflect/api/Internals$ReificationSupportApi$SyntacticTermIdentExtractor;
  #124 = InterfaceMethodref #17.#123      // scala/reflect/api/Internals$ReificationSupportApi.SyntacticTermIdent:()Lscala/reflect/api/Internals$ReificationSupportApi$SyntacticTermIdentExtractor;
  #125 = Utf8               (Lscala/reflect/api/Trees$IdentApi;)Lscala/Option;
  #126 = NameAndType        #46:#125      // unapply:(Lscala/reflect/api/Trees$IdentApi;)Lscala/Option;
  #127 = InterfaceMethodref #26.#126      // scala/reflect/api/Internals$ReificationSupportApi$SyntacticTermIdentExtractor.unapply:(Lscala/reflect/api/Trees$IdentApi;)Lscala/Option;
  #128 = Utf8               _2$mcZ$sp
  #129 = NameAndType        #128:#75      // _2$mcZ$sp:()Z
  #130 = Methodref          #98.#129      // scala/Tuple2._2$mcZ$sp:()Z
  #131 = Utf8               TermNameTag
  #132 = NameAndType        #131:#65      // TermNameTag:()Lscala/reflect/ClassTag;
  #133 = Methodref          #63.#132      // scala/reflect/macros/Universe.TermNameTag:()Lscala/reflect/ClassTag;
  #134 = Utf8               TermName
  #135 = Utf8               ()Lscala/reflect/api/Names$TermNameExtractor;
  #136 = NameAndType        #134:#135     // TermName:()Lscala/reflect/api/Names$TermNameExtractor;
  #137 = Methodref          #63.#136      // scala/reflect/macros/Universe.TermName:()Lscala/reflect/api/Names$TermNameExtractor;
  #138 = Utf8               (Lscala/reflect/api/Names$TermNameApi;)Lscala/Option;
  #139 = NameAndType        #46:#138      // unapply:(Lscala/reflect/api/Names$TermNameApi;)Lscala/Option;
  #140 = Methodref          #34.#139      // scala/reflect/api/Names$TermNameExtractor.unapply:(Lscala/reflect/api/Names$TermNameApi;)Lscala/Option;
  #141 = Utf8               java/lang/String
  #142 = Class              #141          // java/lang/String
  #143 = Utf8               org
  #144 = String             #143          // org
  #145 = Utf8               equals
  #146 = Utf8               (Ljava/lang/Object;)Z
  #147 = NameAndType        #145:#146     // equals:(Ljava/lang/Object;)Z
  #148 = Methodref          #4.#147       // java/lang/Object.equals:(Ljava/lang/Object;)Z
  #149 = Utf8               sireum
  #150 = String             #149          // sireum
  #151 = Utf8               package
  #152 = String             #151          // package
  #153 = Utf8               $Slang
  #154 = String             #153          // $Slang
  #155 = Utf8               scala/collection/immutable/$colon$colon
  #156 = Class              #155          // scala/collection/immutable/$colon$colon
  #157 = Utf8               head
  #158 = NameAndType        #157:#79      // head:()Ljava/lang/Object;
  #159 = Methodref          #156.#158     // scala/collection/immutable/$colon$colon.head:()Ljava/lang/Object;
  #160 = Utf8               next$access$1
  #161 = Utf8               ()Lscala/collection/immutable/List;
  #162 = NameAndType        #160:#161     // next$access$1:()Lscala/collection/immutable/List;
  #163 = Methodref          #156.#162     // scala/collection/immutable/$colon$colon.next$access$1:()Lscala/collection/immutable/List;
  #164 = Utf8               scala
  #165 = String             #164          // scala
  #166 = Utf8               StringContext
  #167 = String             #166          // StringContext
  #168 = Utf8               apply
  #169 = String             #168          // apply
  #170 = Utf8               scala/collection/immutable/Nil$
  #171 = Class              #170          // scala/collection/immutable/Nil$
  #172 = Utf8               MODULE$
  #173 = Utf8               Lscala/collection/immutable/Nil$;
  #174 = NameAndType        #172:#173     // MODULE$:Lscala/collection/immutable/Nil$;
  #175 = Fieldref           #171.#174     // scala/collection/immutable/Nil$.MODULE$:Lscala/collection/immutable/Nil$;
  #176 = Utf8               <init>
  #177 = Utf8               (Ljava/lang/Object;Ljava/lang/Object;)V
  #178 = NameAndType        #176:#177     // "<init>":(Ljava/lang/Object;Ljava/lang/Object;)V
  #179 = Methodref          #98.#178      // scala/Tuple2."<init>":(Ljava/lang/Object;Ljava/lang/Object;)V
  #180 = Utf8               (Ljava/lang/Object;)V
  #181 = NameAndType        #176:#180     // "<init>":(Ljava/lang/Object;)V
  #182 = Methodref          #113.#181     // scala/Some."<init>":(Ljava/lang/Object;)V
  #183 = Utf8               scala/None$
  #184 = Class              #183          // scala/None$
  #185 = Utf8               Lscala/None$;
  #186 = NameAndType        #172:#185     // MODULE$:Lscala/None$;
  #187 = Fieldref           #184.#186     // scala/None$.MODULE$:Lscala/None$;
  #188 = Utf8               qq$macro$1
  #189 = Utf8               Lscala/collection/immutable/List;
  #190 = Utf8               qq$macro$2
  #191 = Utf8               Lscala/reflect/api/Names$TermNameApi;
  #192 = Utf8               this
  #193 = Utf8               Lorg/sireum/$internal/Macro$$anon$1;
  #194 = Utf8               Ljava/lang/Object;
  #195 = Utf8               (Lorg/sireum/$internal/Macro;)V
  #196 = Utf8               ()V
  #197 = NameAndType        #176:#196     // "<init>":()V
  #198 = Methodref          #4.#197       // java/lang/Object."<init>":()V
  #199 = Utf8               Code
  #200 = Utf8               StackMapTable
  #201 = Utf8               LineNumberTable
  #202 = Utf8               LocalVariableTable
  #203 = Utf8               Signature
  #204 = Utf8               MethodParameters
  #205 = Utf8               InnerClasses
  #206 = Utf8               EnclosingMethod
  #207 = Utf8               SourceFile
  #208 = Utf8               ScalaInlineInfo
  #209 = Utf8               Scala
{
  private final org.sireum.$internal.Macro $outer;
    descriptor: Lorg/sireum/$internal/Macro;
    flags: (0x1012) ACC_PRIVATE, ACC_FINAL, ACC_SYNTHETIC

  public scala.Option<scala.Tuple2<scala.collection.immutable.List<scala.reflect.api.Trees$TreeApi>, scala.reflect.api.Names$TermNameApi>> unapply(java.lang.Object);
    descriptor: (Ljava/lang/Object;)Lscala/Option;
    flags: (0x0001) ACC_PUBLIC
    Code:
      stack=6, locals=91, args_size=2
         0: aload_1
         1: astore_3
         2: aload_3
         3: ifnull        2344
         6: aload_0
         7: getfield      #51                 // Field $outer:Lorg/sireum/$internal/Macro;
        10: invokevirtual #55                 // Method org/sireum/$internal/Macro.c:()Lscala/reflect/macros/blackbox/Context;
        13: invokeinterface #61,  1           // InterfaceMethod scala/reflect/macros/blackbox/Context.universe:()Lscala/reflect/macros/Universe;
        18: invokevirtual #67                 // Method scala/reflect/macros/Universe.TreeTag:()Lscala/reflect/ClassTag;
        21: aload_3
        22: invokeinterface #71,  2           // InterfaceMethod scala/reflect/ClassTag.unapply:(Ljava/lang/Object;)Lscala/Option;
        27: astore        4
        29: aload         4
        31: invokevirtual #77                 // Method scala/Option.isEmpty:()Z
        34: ifne          2341
        37: aload         4
        39: invokevirtual #81                 // Method scala/Option.get:()Ljava/lang/Object;
        42: checkcast     #42                 // class scala/reflect/api/Trees$TreeApi
        45: astore        5
        47: aload         5
        49: ifnull        2338
        52: aload_0
        53: getfield      #51                 // Field $outer:Lorg/sireum/$internal/Macro;
        56: invokevirtual #55                 // Method org/sireum/$internal/Macro.c:()Lscala/reflect/macros/blackbox/Context;
        59: invokeinterface #61,  1           // InterfaceMethod scala/reflect/macros/blackbox/Context.universe:()Lscala/reflect/macros/Universe;
        64: invokevirtual #85                 // Method scala/reflect/macros/Universe.internal:()Lscala/reflect/api/Internals$InternalApi;
        67: invokeinterface #89,  1           // InterfaceMethod scala/reflect/api/Internals$InternalApi.reificationSupport:()Lscala/reflect/api/Internals$ReificationSupportApi;
        72: invokeinterface #93,  1           // InterfaceMethod scala/reflect/api/Internals$ReificationSupportApi.SyntacticSelectTerm:()Lscala/reflect/api/Internals$ReificationSupportApi$SyntacticSelectTermExtractor;
        77: aload         5
        79: invokeinterface #96,  2           // InterfaceMethod scala/reflect/api/Internals$ReificationSupportApi$SyntacticSelectTermExtractor.unapply:(Lscala/reflect/api/Trees$TreeApi;)Lscala/Option;
        84: astore        6
        86: aload         6
        88: invokevirtual #77                 // Method scala/Option.isEmpty:()Z
        91: ifne          2335
        94: aload         6
        96: invokevirtual #81                 // Method scala/Option.get:()Ljava/lang/Object;
        99: checkcast     #98                 // class scala/Tuple2
       102: invokevirtual #101                // Method scala/Tuple2._1:()Ljava/lang/Object;
       105: checkcast     #42                 // class scala/reflect/api/Trees$TreeApi
       108: astore        7
       110: aload         6
       112: invokevirtual #81                 // Method scala/Option.get:()Ljava/lang/Object;
       115: checkcast     #98                 // class scala/Tuple2
       118: invokevirtual #104                // Method scala/Tuple2._2:()Ljava/lang/Object;
       121: checkcast     #29                 // class scala/reflect/api/Names$TermNameApi
       124: astore        8
       126: aload         7
       128: ifnull        2332
       131: aload_0
       132: getfield      #51                 // Field $outer:Lorg/sireum/$internal/Macro;
       135: invokevirtual #55                 // Method org/sireum/$internal/Macro.c:()Lscala/reflect/macros/blackbox/Context;
       138: invokeinterface #61,  1           // InterfaceMethod scala/reflect/macros/blackbox/Context.universe:()Lscala/reflect/macros/Universe;
       143: invokevirtual #67                 // Method scala/reflect/macros/Universe.TreeTag:()Lscala/reflect/ClassTag;
       146: aload         7
       148: invokeinterface #71,  2           // InterfaceMethod scala/reflect/ClassTag.unapply:(Ljava/lang/Object;)Lscala/Option;
       153: astore        9
       155: aload         9
       157: invokevirtual #77                 // Method scala/Option.isEmpty:()Z
       160: ifne          2329
       163: aload         9
       165: invokevirtual #81                 // Method scala/Option.get:()Ljava/lang/Object;
       168: checkcast     #42                 // class scala/reflect/api/Trees$TreeApi
       171: astore        10
       173: aload         10
       175: ifnull        2326
       178: aload_0
       179: getfield      #51                 // Field $outer:Lorg/sireum/$internal/Macro;
       182: invokevirtual #55                 // Method org/sireum/$internal/Macro.c:()Lscala/reflect/macros/blackbox/Context;
       185: invokeinterface #61,  1           // InterfaceMethod scala/reflect/macros/blackbox/Context.universe:()Lscala/reflect/macros/Universe;
       190: invokevirtual #85                 // Method scala/reflect/macros/Universe.internal:()Lscala/reflect/api/Internals$InternalApi;
       193: invokeinterface #89,  1           // InterfaceMethod scala/reflect/api/Internals$InternalApi.reificationSupport:()Lscala/reflect/api/Internals$ReificationSupportApi;
       198: invokeinterface #108,  1          // InterfaceMethod scala/reflect/api/Internals$ReificationSupportApi.SyntacticApplied:()Lscala/reflect/api/Internals$ReificationSupportApi$SyntacticAppliedExtractor;
       203: aload         10
       205: invokeinterface #111,  2          // InterfaceMethod scala/reflect/api/Internals$ReificationSupportApi$SyntacticAppliedExtractor.unapply:(Lscala/reflect/api/Trees$TreeApi;)Lscala/Some;
       210: astore        11
       212: aload         11
       214: invokevirtual #114                // Method scala/Some.isEmpty:()Z
       217: ifne          2323
       220: aload         11
       222: invokevirtual #115                // Method scala/Some.get:()Ljava/lang/Object;
       225: checkcast     #98                 // class scala/Tuple2
       228: invokevirtual #101                // Method scala/Tuple2._1:()Ljava/lang/Object;
       231: checkcast     #42                 // class scala/reflect/api/Trees$TreeApi
       234: astore        12
       236: aload         11
       238: invokevirtual #115                // Method scala/Some.get:()Ljava/lang/Object;
       241: checkcast     #98                 // class scala/Tuple2
       244: invokevirtual #104                // Method scala/Tuple2._2:()Ljava/lang/Object;
       247: checkcast     #117                // class scala/collection/immutable/List
       250: astore        13
       252: aload         12
       254: ifnull        2320
       257: aload_0
       258: getfield      #51                 // Field $outer:Lorg/sireum/$internal/Macro;
       261: invokevirtual #55                 // Method org/sireum/$internal/Macro.c:()Lscala/reflect/macros/blackbox/Context;
       264: invokeinterface #61,  1           // InterfaceMethod scala/reflect/macros/blackbox/Context.universe:()Lscala/reflect/macros/Universe;
       269: invokevirtual #67                 // Method scala/reflect/macros/Universe.TreeTag:()Lscala/reflect/ClassTag;
       272: aload         12
       274: invokeinterface #71,  2           // InterfaceMethod scala/reflect/ClassTag.unapply:(Ljava/lang/Object;)Lscala/Option;
       279: astore        14
       281: aload         14
       283: invokevirtual #77                 // Method scala/Option.isEmpty:()Z
       286: ifne          2317
       289: aload         14
       291: invokevirtual #81                 // Method scala/Option.get:()Ljava/lang/Object;
       294: checkcast     #42                 // class scala/reflect/api/Trees$TreeApi
       297: astore        15
       299: aload         15
       301: ifnull        2314
       304: aload_0
       305: getfield      #51                 // Field $outer:Lorg/sireum/$internal/Macro;
       308: invokevirtual #55                 // Method org/sireum/$internal/Macro.c:()Lscala/reflect/macros/blackbox/Context;
       311: invokeinterface #61,  1           // InterfaceMethod scala/reflect/macros/blackbox/Context.universe:()Lscala/reflect/macros/Universe;
       316: invokevirtual #85                 // Method scala/reflect/macros/Universe.internal:()Lscala/reflect/api/Internals$InternalApi;
       319: invokeinterface #89,  1           // InterfaceMethod scala/reflect/api/Internals$InternalApi.reificationSupport:()Lscala/reflect/api/Internals$ReificationSupportApi;
       324: invokeinterface #93,  1           // InterfaceMethod scala/reflect/api/Internals$ReificationSupportApi.SyntacticSelectTerm:()Lscala/reflect/api/Internals$ReificationSupportApi$SyntacticSelectTermExtractor;
       329: aload         15
       331: invokeinterface #96,  2           // InterfaceMethod scala/reflect/api/Internals$ReificationSupportApi$SyntacticSelectTermExtractor.unapply:(Lscala/reflect/api/Trees$TreeApi;)Lscala/Option;
       336: astore        16
       338: aload         16
       340: invokevirtual #77                 // Method scala/Option.isEmpty:()Z
       343: ifne          2311
       346: aload         16
       348: invokevirtual #81                 // Method scala/Option.get:()Ljava/lang/Object;
       351: checkcast     #98                 // class scala/Tuple2
       354: invokevirtual #101                // Method scala/Tuple2._1:()Ljava/lang/Object;
       357: checkcast     #42                 // class scala/reflect/api/Trees$TreeApi
       360: astore        17
       362: aload         16
       364: invokevirtual #81                 // Method scala/Option.get:()Ljava/lang/Object;
       367: checkcast     #98                 // class scala/Tuple2
       370: invokevirtual #104                // Method scala/Tuple2._2:()Ljava/lang/Object;
       373: checkcast     #29                 // class scala/reflect/api/Names$TermNameApi
       376: astore        18
       378: aload         17
       380: ifnull        2308
       383: aload_0
       384: getfield      #51                 // Field $outer:Lorg/sireum/$internal/Macro;
       387: invokevirtual #55                 // Method org/sireum/$internal/Macro.c:()Lscala/reflect/macros/blackbox/Context;
       390: invokeinterface #61,  1           // InterfaceMethod scala/reflect/macros/blackbox/Context.universe:()Lscala/reflect/macros/Universe;
       395: invokevirtual #67                 // Method scala/reflect/macros/Universe.TreeTag:()Lscala/reflect/ClassTag;
       398: aload         17
       400: invokeinterface #71,  2           // InterfaceMethod scala/reflect/ClassTag.unapply:(Ljava/lang/Object;)Lscala/Option;
       405: astore        19
       407: aload         19
       409: invokevirtual #77                 // Method scala/Option.isEmpty:()Z
       412: ifne          2305
       415: aload         19
       417: invokevirtual #81                 // Method scala/Option.get:()Ljava/lang/Object;
       420: checkcast     #42                 // class scala/reflect/api/Trees$TreeApi
       423: astore        20
       425: aload         20
       427: ifnull        2302
       430: aload_0
       431: getfield      #51                 // Field $outer:Lorg/sireum/$internal/Macro;
       434: invokevirtual #55                 // Method org/sireum/$internal/Macro.c:()Lscala/reflect/macros/blackbox/Context;
       437: invokeinterface #61,  1           // InterfaceMethod scala/reflect/macros/blackbox/Context.universe:()Lscala/reflect/macros/Universe;
       442: invokevirtual #85                 // Method scala/reflect/macros/Universe.internal:()Lscala/reflect/api/Internals$InternalApi;
       445: invokeinterface #89,  1           // InterfaceMethod scala/reflect/api/Internals$InternalApi.reificationSupport:()Lscala/reflect/api/Internals$ReificationSupportApi;
       450: invokeinterface #93,  1           // InterfaceMethod scala/reflect/api/Internals$ReificationSupportApi.SyntacticSelectTerm:()Lscala/reflect/api/Internals$ReificationSupportApi$SyntacticSelectTermExtractor;
       455: aload         20
       457: invokeinterface #96,  2           // InterfaceMethod scala/reflect/api/Internals$ReificationSupportApi$SyntacticSelectTermExtractor.unapply:(Lscala/reflect/api/Trees$TreeApi;)Lscala/Option;
       462: astore        21
       464: aload         21
       466: invokevirtual #77                 // Method scala/Option.isEmpty:()Z
       469: ifne          2299
       472: aload         21
       474: invokevirtual #81                 // Method scala/Option.get:()Ljava/lang/Object;
       477: checkcast     #98                 // class scala/Tuple2
       480: invokevirtual #101                // Method scala/Tuple2._1:()Ljava/lang/Object;
       483: checkcast     #42                 // class scala/reflect/api/Trees$TreeApi
       486: astore        22
       488: aload         21
       490: invokevirtual #81                 // Method scala/Option.get:()Ljava/lang/Object;
       493: checkcast     #98                 // class scala/Tuple2
       496: invokevirtual #104                // Method scala/Tuple2._2:()Ljava/lang/Object;
       499: checkcast     #29                 // class scala/reflect/api/Names$TermNameApi
       502: astore        23
       504: aload         22
       506: ifnull        2296
       509: aload_0
       510: getfield      #51                 // Field $outer:Lorg/sireum/$internal/Macro;
       513: invokevirtual #55                 // Method org/sireum/$internal/Macro.c:()Lscala/reflect/macros/blackbox/Context;
       516: invokeinterface #61,  1           // InterfaceMethod scala/reflect/macros/blackbox/Context.universe:()Lscala/reflect/macros/Universe;
       521: invokevirtual #67                 // Method scala/reflect/macros/Universe.TreeTag:()Lscala/reflect/ClassTag;
       524: aload         22
       526: invokeinterface #71,  2           // InterfaceMethod scala/reflect/ClassTag.unapply:(Ljava/lang/Object;)Lscala/Option;
       531: astore        24
       533: aload         24
       535: invokevirtual #77                 // Method scala/Option.isEmpty:()Z
       538: ifne          2293
       541: aload         24
       543: invokevirtual #81                 // Method scala/Option.get:()Ljava/lang/Object;
       546: checkcast     #42                 // class scala/reflect/api/Trees$TreeApi
       549: astore        25
       551: aload         25
       553: ifnull        2290
       556: aload_0
       557: getfield      #51                 // Field $outer:Lorg/sireum/$internal/Macro;
       560: invokevirtual #55                 // Method org/sireum/$internal/Macro.c:()Lscala/reflect/macros/blackbox/Context;
       563: invokeinterface #61,  1           // InterfaceMethod scala/reflect/macros/blackbox/Context.universe:()Lscala/reflect/macros/Universe;
       568: invokevirtual #85                 // Method scala/reflect/macros/Universe.internal:()Lscala/reflect/api/Internals$InternalApi;
       571: invokeinterface #89,  1           // InterfaceMethod scala/reflect/api/Internals$InternalApi.reificationSupport:()Lscala/reflect/api/Internals$ReificationSupportApi;
       576: invokeinterface #93,  1           // InterfaceMethod scala/reflect/api/Internals$ReificationSupportApi.SyntacticSelectTerm:()Lscala/reflect/api/Internals$ReificationSupportApi$SyntacticSelectTermExtractor;
       581: aload         25
       583: invokeinterface #96,  2           // InterfaceMethod scala/reflect/api/Internals$ReificationSupportApi$SyntacticSelectTermExtractor.unapply:(Lscala/reflect/api/Trees$TreeApi;)Lscala/Option;
       588: astore        26
       590: aload         26
       592: invokevirtual #77                 // Method scala/Option.isEmpty:()Z
       595: ifne          2287
       598: aload         26
       600: invokevirtual #81                 // Method scala/Option.get:()Ljava/lang/Object;
       603: checkcast     #98                 // class scala/Tuple2
       606: invokevirtual #101                // Method scala/Tuple2._1:()Ljava/lang/Object;
       609: checkcast     #42                 // class scala/reflect/api/Trees$TreeApi
       612: astore        27
       614: aload         26
       616: invokevirtual #81                 // Method scala/Option.get:()Ljava/lang/Object;
       619: checkcast     #98                 // class scala/Tuple2
       622: invokevirtual #104                // Method scala/Tuple2._2:()Ljava/lang/Object;
       625: checkcast     #29                 // class scala/reflect/api/Names$TermNameApi
       628: astore        28
       630: aload         27
       632: ifnull        2284
       635: aload_0
       636: getfield      #51                 // Field $outer:Lorg/sireum/$internal/Macro;
       639: invokevirtual #55                 // Method org/sireum/$internal/Macro.c:()Lscala/reflect/macros/blackbox/Context;
       642: invokeinterface #61,  1           // InterfaceMethod scala/reflect/macros/blackbox/Context.universe:()Lscala/reflect/macros/Universe;
       647: invokevirtual #120                // Method scala/reflect/macros/Universe.IdentTag:()Lscala/reflect/ClassTag;
       650: aload         27
       652: invokeinterface #71,  2           // InterfaceMethod scala/reflect/ClassTag.unapply:(Ljava/lang/Object;)Lscala/Option;
       657: astore        29
       659: aload         29
       661: invokevirtual #77                 // Method scala/Option.isEmpty:()Z
       664: ifne          2281
       667: aload         29
       669: invokevirtual #81                 // Method scala/Option.get:()Ljava/lang/Object;
       672: checkcast     #37                 // class scala/reflect/api/Trees$IdentApi
       675: astore        30
       677: aload         30
       679: ifnull        2278
       682: aload_0
       683: getfield      #51                 // Field $outer:Lorg/sireum/$internal/Macro;
       686: invokevirtual #55                 // Method org/sireum/$internal/Macro.c:()Lscala/reflect/macros/blackbox/Context;
       689: invokeinterface #61,  1           // InterfaceMethod scala/reflect/macros/blackbox/Context.universe:()Lscala/reflect/macros/Universe;
       694: invokevirtual #85                 // Method scala/reflect/macros/Universe.internal:()Lscala/reflect/api/Internals$InternalApi;
       697: invokeinterface #89,  1           // InterfaceMethod scala/reflect/api/Internals$InternalApi.reificationSupport:()Lscala/reflect/api/Internals$ReificationSupportApi;
       702: invokeinterface #124,  1          // InterfaceMethod scala/reflect/api/Internals$ReificationSupportApi.SyntacticTermIdent:()Lscala/reflect/api/Internals$ReificationSupportApi$SyntacticTermIdentExtractor;
       707: aload         30
       709: invokeinterface #127,  2          // InterfaceMethod scala/reflect/api/Internals$ReificationSupportApi$SyntacticTermIdentExtractor.unapply:(Lscala/reflect/api/Trees$IdentApi;)Lscala/Option;
       714: astore        31
       716: aload         31
       718: invokevirtual #77                 // Method scala/Option.isEmpty:()Z
       721: ifne          2275
       724: aload         31
       726: invokevirtual #81                 // Method scala/Option.get:()Ljava/lang/Object;
       729: checkcast     #98                 // class scala/Tuple2
       732: invokevirtual #101                // Method scala/Tuple2._1:()Ljava/lang/Object;
       735: checkcast     #29                 // class scala/reflect/api/Names$TermNameApi
       738: astore        32
       740: aload         31
       742: invokevirtual #81                 // Method scala/Option.get:()Ljava/lang/Object;
       745: checkcast     #98                 // class scala/Tuple2
       748: invokevirtual #130                // Method scala/Tuple2._2$mcZ$sp:()Z
       751: istore        33
       753: aload         32
       755: ifnull        2272
       758: aload_0
       759: getfield      #51                 // Field $outer:Lorg/sireum/$internal/Macro;
       762: invokevirtual #55                 // Method org/sireum/$internal/Macro.c:()Lscala/reflect/macros/blackbox/Context;
       765: invokeinterface #61,  1           // InterfaceMethod scala/reflect/macros/blackbox/Context.universe:()Lscala/reflect/macros/Universe;
       770: invokevirtual #133                // Method scala/reflect/macros/Universe.TermNameTag:()Lscala/reflect/ClassTag;
       773: aload         32
       775: invokeinterface #71,  2           // InterfaceMethod scala/reflect/ClassTag.unapply:(Ljava/lang/Object;)Lscala/Option;
       780: astore        34
       782: aload         34
       784: invokevirtual #77                 // Method scala/Option.isEmpty:()Z
       787: ifne          2269
       790: aload         34
       792: invokevirtual #81                 // Method scala/Option.get:()Ljava/lang/Object;
       795: checkcast     #29                 // class scala/reflect/api/Names$TermNameApi
       798: astore        35
       800: aload         35
       802: ifnull        2266
       805: aload_0
       806: getfield      #51                 // Field $outer:Lorg/sireum/$internal/Macro;
       809: invokevirtual #55                 // Method org/sireum/$internal/Macro.c:()Lscala/reflect/macros/blackbox/Context;
       812: invokeinterface #61,  1           // InterfaceMethod scala/reflect/macros/blackbox/Context.universe:()Lscala/reflect/macros/Universe;
       817: invokevirtual #137                // Method scala/reflect/macros/Universe.TermName:()Lscala/reflect/api/Names$TermNameExtractor;
       820: aload         35
       822: invokevirtual #140                // Method scala/reflect/api/Names$TermNameExtractor.unapply:(Lscala/reflect/api/Names$TermNameApi;)Lscala/Option;
       825: astore        36
       827: aload         36
       829: invokevirtual #77                 // Method scala/Option.isEmpty:()Z
       832: ifne          2263
       835: aload         36
       837: invokevirtual #81                 // Method scala/Option.get:()Ljava/lang/Object;
       840: checkcast     #142                // class java/lang/String
       843: astore        37
       845: ldc           #144                // String org
       847: aload         37
       849: invokevirtual #148                // Method java/lang/Object.equals:(Ljava/lang/Object;)Z
       852: ifeq          2260
       855: iconst_0
       856: iload         33
       858: if_icmpne     2260
       861: aload         28
       863: ifnull        2260
       866: aload_0
       867: getfield      #51                 // Field $outer:Lorg/sireum/$internal/Macro;
       870: invokevirtual #55                 // Method org/sireum/$internal/Macro.c:()Lscala/reflect/macros/blackbox/Context;
       873: invokeinterface #61,  1           // InterfaceMethod scala/reflect/macros/blackbox/Context.universe:()Lscala/reflect/macros/Universe;
       878: invokevirtual #133                // Method scala/reflect/macros/Universe.TermNameTag:()Lscala/reflect/ClassTag;
       881: aload         28
       883: invokeinterface #71,  2           // InterfaceMethod scala/reflect/ClassTag.unapply:(Ljava/lang/Object;)Lscala/Option;
       888: astore        38
       890: aload         38
       892: invokevirtual #77                 // Method scala/Option.isEmpty:()Z
       895: ifne          2257
       898: aload         38
       900: invokevirtual #81                 // Method scala/Option.get:()Ljava/lang/Object;
       903: checkcast     #29                 // class scala/reflect/api/Names$TermNameApi
       906: astore        39
       908: aload         39
       910: ifnull        2254
       913: aload_0
       914: getfield      #51                 // Field $outer:Lorg/sireum/$internal/Macro;
       917: invokevirtual #55                 // Method org/sireum/$internal/Macro.c:()Lscala/reflect/macros/blackbox/Context;
       920: invokeinterface #61,  1           // InterfaceMethod scala/reflect/macros/blackbox/Context.universe:()Lscala/reflect/macros/Universe;
       925: invokevirtual #137                // Method scala/reflect/macros/Universe.TermName:()Lscala/reflect/api/Names$TermNameExtractor;
       928: aload         39
       930: invokevirtual #140                // Method scala/reflect/api/Names$TermNameExtractor.unapply:(Lscala/reflect/api/Names$TermNameApi;)Lscala/Option;
       933: astore        40
       935: aload         40
       937: invokevirtual #77                 // Method scala/Option.isEmpty:()Z
       940: ifne          2251
       943: aload         40
       945: invokevirtual #81                 // Method scala/Option.get:()Ljava/lang/Object;
       948: checkcast     #142                // class java/lang/String
       951: astore        41
       953: ldc           #150                // String sireum
       955: aload         41
       957: invokevirtual #148                // Method java/lang/Object.equals:(Ljava/lang/Object;)Z
       960: ifeq          2248
       963: aload         23
       965: ifnull        2248
       968: aload_0
       969: getfield      #51                 // Field $outer:Lorg/sireum/$internal/Macro;
       972: invokevirtual #55                 // Method org/sireum/$internal/Macro.c:()Lscala/reflect/macros/blackbox/Context;
       975: invokeinterface #61,  1           // InterfaceMethod scala/reflect/macros/blackbox/Context.universe:()Lscala/reflect/macros/Universe;
       980: invokevirtual #133                // Method scala/reflect/macros/Universe.TermNameTag:()Lscala/reflect/ClassTag;
       983: aload         23
       985: invokeinterface #71,  2           // InterfaceMethod scala/reflect/ClassTag.unapply:(Ljava/lang/Object;)Lscala/Option;
       990: astore        42
       992: aload         42
       994: invokevirtual #77                 // Method scala/Option.isEmpty:()Z
       997: ifne          2245
      1000: aload         42
      1002: invokevirtual #81                 // Method scala/Option.get:()Ljava/lang/Object;
      1005: checkcast     #29                 // class scala/reflect/api/Names$TermNameApi
      1008: astore        43
      1010: aload         43
      1012: ifnull        2242
      1015: aload_0
      1016: getfield      #51                 // Field $outer:Lorg/sireum/$internal/Macro;
      1019: invokevirtual #55                 // Method org/sireum/$internal/Macro.c:()Lscala/reflect/macros/blackbox/Context;
      1022: invokeinterface #61,  1           // InterfaceMethod scala/reflect/macros/blackbox/Context.universe:()Lscala/reflect/macros/Universe;
      1027: invokevirtual #137                // Method scala/reflect/macros/Universe.TermName:()Lscala/reflect/api/Names$TermNameExtractor;
      1030: aload         43
      1032: invokevirtual #140                // Method scala/reflect/api/Names$TermNameExtractor.unapply:(Lscala/reflect/api/Names$TermNameApi;)Lscala/Option;
      1035: astore        44
      1037: aload         44
      1039: invokevirtual #77                 // Method scala/Option.isEmpty:()Z
      1042: ifne          2239
      1045: aload         44
      1047: invokevirtual #81                 // Method scala/Option.get:()Ljava/lang/Object;
      1050: checkcast     #142                // class java/lang/String
      1053: astore        45
      1055: ldc           #152                // String package
      1057: aload         45
      1059: invokevirtual #148                // Method java/lang/Object.equals:(Ljava/lang/Object;)Z
      1062: ifeq          2236
      1065: aload         18
      1067: ifnull        2236
      1070: aload_0
      1071: getfield      #51                 // Field $outer:Lorg/sireum/$internal/Macro;
      1074: invokevirtual #55                 // Method org/sireum/$internal/Macro.c:()Lscala/reflect/macros/blackbox/Context;
      1077: invokeinterface #61,  1           // InterfaceMethod scala/reflect/macros/blackbox/Context.universe:()Lscala/reflect/macros/Universe;
      1082: invokevirtual #133                // Method scala/reflect/macros/Universe.TermNameTag:()Lscala/reflect/ClassTag;
      1085: aload         18
      1087: invokeinterface #71,  2           // InterfaceMethod scala/reflect/ClassTag.unapply:(Ljava/lang/Object;)Lscala/Option;
      1092: astore        46
      1094: aload         46
      1096: invokevirtual #77                 // Method scala/Option.isEmpty:()Z
      1099: ifne          2233
      1102: aload         46
      1104: invokevirtual #81                 // Method scala/Option.get:()Ljava/lang/Object;
      1107: checkcast     #29                 // class scala/reflect/api/Names$TermNameApi
      1110: astore        47
      1112: aload         47
      1114: ifnull        2230
      1117: aload_0
      1118: getfield      #51                 // Field $outer:Lorg/sireum/$internal/Macro;
      1121: invokevirtual #55                 // Method org/sireum/$internal/Macro.c:()Lscala/reflect/macros/blackbox/Context;
      1124: invokeinterface #61,  1           // InterfaceMethod scala/reflect/macros/blackbox/Context.universe:()Lscala/reflect/macros/Universe;
      1129: invokevirtual #137                // Method scala/reflect/macros/Universe.TermName:()Lscala/reflect/api/Names$TermNameExtractor;
      1132: aload         47
      1134: invokevirtual #140                // Method scala/reflect/api/Names$TermNameExtractor.unapply:(Lscala/reflect/api/Names$TermNameApi;)Lscala/Option;
      1137: astore        48
      1139: aload         48
      1141: invokevirtual #77                 // Method scala/Option.isEmpty:()Z
      1144: ifne          2227
      1147: aload         48
      1149: invokevirtual #81                 // Method scala/Option.get:()Ljava/lang/Object;
      1152: checkcast     #142                // class java/lang/String
      1155: astore        49
      1157: ldc           #154                // String $Slang
      1159: aload         49
      1161: invokevirtual #148                // Method java/lang/Object.equals:(Ljava/lang/Object;)Z
      1164: ifeq          2224
      1167: aload         13
      1169: instanceof    #156                // class scala/collection/immutable/$colon$colon
      1172: ifeq          2224
      1175: aload         13
      1177: checkcast     #156                // class scala/collection/immutable/$colon$colon
      1180: astore        50
      1182: aload         50
      1184: invokevirtual #159                // Method scala/collection/immutable/$colon$colon.head:()Ljava/lang/Object;
      1187: checkcast     #117                // class scala/collection/immutable/List
      1190: astore        51
      1192: aload         50
      1194: invokevirtual #163                // Method scala/collection/immutable/$colon$colon.next$access$1:()Lscala/collection/immutable/List;
      1197: astore        52
      1199: aload         51
      1201: instanceof    #156                // class scala/collection/immutable/$colon$colon
      1204: ifeq          2221
      1207: aload         51
      1209: checkcast     #156                // class scala/collection/immutable/$colon$colon
      1212: astore        53
      1214: aload         53
      1216: invokevirtual #159                // Method scala/collection/immutable/$colon$colon.head:()Ljava/lang/Object;
      1219: checkcast     #42                 // class scala/reflect/api/Trees$TreeApi
      1222: astore        54
      1224: aload         53
      1226: invokevirtual #163                // Method scala/collection/immutable/$colon$colon.next$access$1:()Lscala/collection/immutable/List;
      1229: astore        55
      1231: aload         54
      1233: ifnull        2218
      1236: aload_0
      1237: getfield      #51                 // Field $outer:Lorg/sireum/$internal/Macro;
      1240: invokevirtual #55                 // Method org/sireum/$internal/Macro.c:()Lscala/reflect/macros/blackbox/Context;
      1243: invokeinterface #61,  1           // InterfaceMethod scala/reflect/macros/blackbox/Context.universe:()Lscala/reflect/macros/Universe;
      1248: invokevirtual #67                 // Method scala/reflect/macros/Universe.TreeTag:()Lscala/reflect/ClassTag;
      1251: aload         54
      1253: invokeinterface #71,  2           // InterfaceMethod scala/reflect/ClassTag.unapply:(Ljava/lang/Object;)Lscala/Option;
      1258: astore        56
      1260: aload         56
      1262: invokevirtual #77                 // Method scala/Option.isEmpty:()Z
      1265: ifne          2215
      1268: aload         56
      1270: invokevirtual #81                 // Method scala/Option.get:()Ljava/lang/Object;
      1273: checkcast     #42                 // class scala/reflect/api/Trees$TreeApi
      1276: astore        57
      1278: aload         57
      1280: ifnull        2212
      1283: aload_0
      1284: getfield      #51                 // Field $outer:Lorg/sireum/$internal/Macro;
      1287: invokevirtual #55                 // Method org/sireum/$internal/Macro.c:()Lscala/reflect/macros/blackbox/Context;
      1290: invokeinterface #61,  1           // InterfaceMethod scala/reflect/macros/blackbox/Context.universe:()Lscala/reflect/macros/Universe;
      1295: invokevirtual #85                 // Method scala/reflect/macros/Universe.internal:()Lscala/reflect/api/Internals$InternalApi;
      1298: invokeinterface #89,  1           // InterfaceMethod scala/reflect/api/Internals$InternalApi.reificationSupport:()Lscala/reflect/api/Internals$ReificationSupportApi;
      1303: invokeinterface #108,  1          // InterfaceMethod scala/reflect/api/Internals$ReificationSupportApi.SyntacticApplied:()Lscala/reflect/api/Internals$ReificationSupportApi$SyntacticAppliedExtractor;
      1308: aload         57
      1310: invokeinterface #111,  2          // InterfaceMethod scala/reflect/api/Internals$ReificationSupportApi$SyntacticAppliedExtractor.unapply:(Lscala/reflect/api/Trees$TreeApi;)Lscala/Some;
      1315: astore        58
      1317: aload         58
      1319: invokevirtual #114                // Method scala/Some.isEmpty:()Z
      1322: ifne          2209
      1325: aload         58
      1327: invokevirtual #115                // Method scala/Some.get:()Ljava/lang/Object;
      1330: checkcast     #98                 // class scala/Tuple2
      1333: invokevirtual #101                // Method scala/Tuple2._1:()Ljava/lang/Object;
      1336: checkcast     #42                 // class scala/reflect/api/Trees$TreeApi
      1339: astore        59
      1341: aload         58
      1343: invokevirtual #115                // Method scala/Some.get:()Ljava/lang/Object;
      1346: checkcast     #98                 // class scala/Tuple2
      1349: invokevirtual #104                // Method scala/Tuple2._2:()Ljava/lang/Object;
      1352: checkcast     #117                // class scala/collection/immutable/List
      1355: astore        60
      1357: aload         59
      1359: ifnull        2206
      1362: aload_0
      1363: getfield      #51                 // Field $outer:Lorg/sireum/$internal/Macro;
      1366: invokevirtual #55                 // Method org/sireum/$internal/Macro.c:()Lscala/reflect/macros/blackbox/Context;
      1369: invokeinterface #61,  1           // InterfaceMethod scala/reflect/macros/blackbox/Context.universe:()Lscala/reflect/macros/Universe;
      1374: invokevirtual #67                 // Method scala/reflect/macros/Universe.TreeTag:()Lscala/reflect/ClassTag;
      1377: aload         59
      1379: invokeinterface #71,  2           // InterfaceMethod scala/reflect/ClassTag.unapply:(Ljava/lang/Object;)Lscala/Option;
      1384: astore        61
      1386: aload         61
      1388: invokevirtual #77                 // Method scala/Option.isEmpty:()Z
      1391: ifne          2203
      1394: aload         61
      1396: invokevirtual #81                 // Method scala/Option.get:()Ljava/lang/Object;
      1399: checkcast     #42                 // class scala/reflect/api/Trees$TreeApi
      1402: astore        62
      1404: aload         62
      1406: ifnull        2200
      1409: aload_0
      1410: getfield      #51                 // Field $outer:Lorg/sireum/$internal/Macro;
      1413: invokevirtual #55                 // Method org/sireum/$internal/Macro.c:()Lscala/reflect/macros/blackbox/Context;
      1416: invokeinterface #61,  1           // InterfaceMethod scala/reflect/macros/blackbox/Context.universe:()Lscala/reflect/macros/Universe;
      1421: invokevirtual #85                 // Method scala/reflect/macros/Universe.internal:()Lscala/reflect/api/Internals$InternalApi;
      1424: invokeinterface #89,  1           // InterfaceMethod scala/reflect/api/Internals$InternalApi.reificationSupport:()Lscala/reflect/api/Internals$ReificationSupportApi;
      1429: invokeinterface #93,  1           // InterfaceMethod scala/reflect/api/Internals$ReificationSupportApi.SyntacticSelectTerm:()Lscala/reflect/api/Internals$ReificationSupportApi$SyntacticSelectTermExtractor;
      1434: aload         62
      1436: invokeinterface #96,  2           // InterfaceMethod scala/reflect/api/Internals$ReificationSupportApi$SyntacticSelectTermExtractor.unapply:(Lscala/reflect/api/Trees$TreeApi;)Lscala/Option;
      1441: astore        63
      1443: aload         63
      1445: invokevirtual #77                 // Method scala/Option.isEmpty:()Z
      1448: ifne          2197
      1451: aload         63
      1453: invokevirtual #81                 // Method scala/Option.get:()Ljava/lang/Object;
      1456: checkcast     #98                 // class scala/Tuple2
      1459: invokevirtual #101                // Method scala/Tuple2._1:()Ljava/lang/Object;
      1462: checkcast     #42                 // class scala/reflect/api/Trees$TreeApi
      1465: astore        64
      1467: aload         63
      1469: invokevirtual #81                 // Method scala/Option.get:()Ljava/lang/Object;
      1472: checkcast     #98                 // class scala/Tuple2
      1475: invokevirtual #104                // Method scala/Tuple2._2:()Ljava/lang/Object;
      1478: checkcast     #29                 // class scala/reflect/api/Names$TermNameApi
      1481: astore        65
      1483: aload         64
      1485: ifnull        2194
      1488: aload_0
      1489: getfield      #51                 // Field $outer:Lorg/sireum/$internal/Macro;
      1492: invokevirtual #55                 // Method org/sireum/$internal/Macro.c:()Lscala/reflect/macros/blackbox/Context;
      1495: invokeinterface #61,  1           // InterfaceMethod scala/reflect/macros/blackbox/Context.universe:()Lscala/reflect/macros/Universe;
      1500: invokevirtual #67                 // Method scala/reflect/macros/Universe.TreeTag:()Lscala/reflect/ClassTag;
      1503: aload         64
      1505: invokeinterface #71,  2           // InterfaceMethod scala/reflect/ClassTag.unapply:(Ljava/lang/Object;)Lscala/Option;
      1510: astore        66
      1512: aload         66
      1514: invokevirtual #77                 // Method scala/Option.isEmpty:()Z
      1517: ifne          2191
      1520: aload         66
      1522: invokevirtual #81                 // Method scala/Option.get:()Ljava/lang/Object;
      1525: checkcast     #42                 // class scala/reflect/api/Trees$TreeApi
      1528: astore        67
      1530: aload         67
      1532: ifnull        2188
      1535: aload_0
      1536: getfield      #51                 // Field $outer:Lorg/sireum/$internal/Macro;
      1539: invokevirtual #55                 // Method org/sireum/$internal/Macro.c:()Lscala/reflect/macros/blackbox/Context;
      1542: invokeinterface #61,  1           // InterfaceMethod scala/reflect/macros/blackbox/Context.universe:()Lscala/reflect/macros/Universe;
      1547: invokevirtual #85                 // Method scala/reflect/macros/Universe.internal:()Lscala/reflect/api/Internals$InternalApi;
      1550: invokeinterface #89,  1           // InterfaceMethod scala/reflect/api/Internals$InternalApi.reificationSupport:()Lscala/reflect/api/Internals$ReificationSupportApi;
      1555: invokeinterface #93,  1           // InterfaceMethod scala/reflect/api/Internals$ReificationSupportApi.SyntacticSelectTerm:()Lscala/reflect/api/Internals$ReificationSupportApi$SyntacticSelectTermExtractor;
      1560: aload         67
      1562: invokeinterface #96,  2           // InterfaceMethod scala/reflect/api/Internals$ReificationSupportApi$SyntacticSelectTermExtractor.unapply:(Lscala/reflect/api/Trees$TreeApi;)Lscala/Option;
      1567: astore        68
      1569: aload         68
      1571: invokevirtual #77                 // Method scala/Option.isEmpty:()Z
      1574: ifne          2185
      1577: aload         68
      1579: invokevirtual #81                 // Method scala/Option.get:()Ljava/lang/Object;
      1582: checkcast     #98                 // class scala/Tuple2
      1585: invokevirtual #101                // Method scala/Tuple2._1:()Ljava/lang/Object;
      1588: checkcast     #42                 // class scala/reflect/api/Trees$TreeApi
      1591: astore        69
      1593: aload         68
      1595: invokevirtual #81                 // Method scala/Option.get:()Ljava/lang/Object;
      1598: checkcast     #98                 // class scala/Tuple2
      1601: invokevirtual #104                // Method scala/Tuple2._2:()Ljava/lang/Object;
      1604: checkcast     #29                 // class scala/reflect/api/Names$TermNameApi
      1607: astore        70
      1609: aload         69
      1611: ifnull        2182
      1614: aload_0
      1615: getfield      #51                 // Field $outer:Lorg/sireum/$internal/Macro;
      1618: invokevirtual #55                 // Method org/sireum/$internal/Macro.c:()Lscala/reflect/macros/blackbox/Context;
      1621: invokeinterface #61,  1           // InterfaceMethod scala/reflect/macros/blackbox/Context.universe:()Lscala/reflect/macros/Universe;
      1626: invokevirtual #120                // Method scala/reflect/macros/Universe.IdentTag:()Lscala/reflect/ClassTag;
      1629: aload         69
      1631: invokeinterface #71,  2           // InterfaceMethod scala/reflect/ClassTag.unapply:(Ljava/lang/Object;)Lscala/Option;
      1636: astore        71
      1638: aload         71
      1640: invokevirtual #77                 // Method scala/Option.isEmpty:()Z
      1643: ifne          2179
      1646: aload         71
      1648: invokevirtual #81                 // Method scala/Option.get:()Ljava/lang/Object;
      1651: checkcast     #37                 // class scala/reflect/api/Trees$IdentApi
      1654: astore        72
      1656: aload         72
      1658: ifnull        2176
      1661: aload_0
      1662: getfield      #51                 // Field $outer:Lorg/sireum/$internal/Macro;
      1665: invokevirtual #55                 // Method org/sireum/$internal/Macro.c:()Lscala/reflect/macros/blackbox/Context;
      1668: invokeinterface #61,  1           // InterfaceMethod scala/reflect/macros/blackbox/Context.universe:()Lscala/reflect/macros/Universe;
      1673: invokevirtual #85                 // Method scala/reflect/macros/Universe.internal:()Lscala/reflect/api/Internals$InternalApi;
      1676: invokeinterface #89,  1           // InterfaceMethod scala/reflect/api/Internals$InternalApi.reificationSupport:()Lscala/reflect/api/Internals$ReificationSupportApi;
      1681: invokeinterface #124,  1          // InterfaceMethod scala/reflect/api/Internals$ReificationSupportApi.SyntacticTermIdent:()Lscala/reflect/api/Internals$ReificationSupportApi$SyntacticTermIdentExtractor;
      1686: aload         72
      1688: invokeinterface #127,  2          // InterfaceMethod scala/reflect/api/Internals$ReificationSupportApi$SyntacticTermIdentExtractor.unapply:(Lscala/reflect/api/Trees$IdentApi;)Lscala/Option;
      1693: astore        73
      1695: aload         73
      1697: invokevirtual #77                 // Method scala/Option.isEmpty:()Z
      1700: ifne          2173
      1703: aload         73
      1705: invokevirtual #81                 // Method scala/Option.get:()Ljava/lang/Object;
      1708: checkcast     #98                 // class scala/Tuple2
      1711: invokevirtual #101                // Method scala/Tuple2._1:()Ljava/lang/Object;
      1714: checkcast     #29                 // class scala/reflect/api/Names$TermNameApi
      1717: astore        74
      1719: aload         73
      1721: invokevirtual #81                 // Method scala/Option.get:()Ljava/lang/Object;
      1724: checkcast     #98                 // class scala/Tuple2
      1727: invokevirtual #130                // Method scala/Tuple2._2$mcZ$sp:()Z
      1730: istore        75
      1732: aload         74
      1734: ifnull        2170
      1737: aload_0
      1738: getfield      #51                 // Field $outer:Lorg/sireum/$internal/Macro;
      1741: invokevirtual #55                 // Method org/sireum/$internal/Macro.c:()Lscala/reflect/macros/blackbox/Context;
      1744: invokeinterface #61,  1           // InterfaceMethod scala/reflect/macros/blackbox/Context.universe:()Lscala/reflect/macros/Universe;
      1749: invokevirtual #133                // Method scala/reflect/macros/Universe.TermNameTag:()Lscala/reflect/ClassTag;
      1752: aload         74
      1754: invokeinterface #71,  2           // InterfaceMethod scala/reflect/ClassTag.unapply:(Ljava/lang/Object;)Lscala/Option;
      1759: astore        76
      1761: aload         76
      1763: invokevirtual #77                 // Method scala/Option.isEmpty:()Z
      1766: ifne          2167
      1769: aload         76
      1771: invokevirtual #81                 // Method scala/Option.get:()Ljava/lang/Object;
      1774: checkcast     #29                 // class scala/reflect/api/Names$TermNameApi
      1777: astore        77
      1779: aload         77
      1781: ifnull        2164
      1784: aload_0
      1785: getfield      #51                 // Field $outer:Lorg/sireum/$internal/Macro;
      1788: invokevirtual #55                 // Method org/sireum/$internal/Macro.c:()Lscala/reflect/macros/blackbox/Context;
      1791: invokeinterface #61,  1           // InterfaceMethod scala/reflect/macros/blackbox/Context.universe:()Lscala/reflect/macros/Universe;
      1796: invokevirtual #137                // Method scala/reflect/macros/Universe.TermName:()Lscala/reflect/api/Names$TermNameExtractor;
      1799: aload         77
      1801: invokevirtual #140                // Method scala/reflect/api/Names$TermNameExtractor.unapply:(Lscala/reflect/api/Names$TermNameApi;)Lscala/Option;
      1804: astore        78
      1806: aload         78
      1808: invokevirtual #77                 // Method scala/Option.isEmpty:()Z
      1811: ifne          2161
      1814: aload         78
      1816: invokevirtual #81                 // Method scala/Option.get:()Ljava/lang/Object;
      1819: checkcast     #142                // class java/lang/String
      1822: astore        79
      1824: ldc           #165                // String scala
      1826: aload         79
      1828: invokevirtual #148                // Method java/lang/Object.equals:(Ljava/lang/Object;)Z
      1831: ifeq          2158
      1834: iconst_0
      1835: iload         75
      1837: if_icmpne     2158
      1840: aload         70
      1842: ifnull        2158
      1845: aload_0
      1846: getfield      #51                 // Field $outer:Lorg/sireum/$internal/Macro;
      1849: invokevirtual #55                 // Method org/sireum/$internal/Macro.c:()Lscala/reflect/macros/blackbox/Context;
      1852: invokeinterface #61,  1           // InterfaceMethod scala/reflect/macros/blackbox/Context.universe:()Lscala/reflect/macros/Universe;
      1857: invokevirtual #133                // Method scala/reflect/macros/Universe.TermNameTag:()Lscala/reflect/ClassTag;
      1860: aload         70
      1862: invokeinterface #71,  2           // InterfaceMethod scala/reflect/ClassTag.unapply:(Ljava/lang/Object;)Lscala/Option;
      1867: astore        80
      1869: aload         80
      1871: invokevirtual #77                 // Method scala/Option.isEmpty:()Z
      1874: ifne          2155
      1877: aload         80
      1879: invokevirtual #81                 // Method scala/Option.get:()Ljava/lang/Object;
      1882: checkcast     #29                 // class scala/reflect/api/Names$TermNameApi
      1885: astore        81
      1887: aload         81
      1889: ifnull        2152
      1892: aload_0
      1893: getfield      #51                 // Field $outer:Lorg/sireum/$internal/Macro;
      1896: invokevirtual #55                 // Method org/sireum/$internal/Macro.c:()Lscala/reflect/macros/blackbox/Context;
      1899: invokeinterface #61,  1           // InterfaceMethod scala/reflect/macros/blackbox/Context.universe:()Lscala/reflect/macros/Universe;
      1904: invokevirtual #137                // Method scala/reflect/macros/Universe.TermName:()Lscala/reflect/api/Names$TermNameExtractor;
      1907: aload         81
      1909: invokevirtual #140                // Method scala/reflect/api/Names$TermNameExtractor.unapply:(Lscala/reflect/api/Names$TermNameApi;)Lscala/Option;
      1912: astore        82
      1914: aload         82
      1916: invokevirtual #77                 // Method scala/Option.isEmpty:()Z
      1919: ifne          2149
      1922: aload         82
      1924: invokevirtual #81                 // Method scala/Option.get:()Ljava/lang/Object;
      1927: checkcast     #142                // class java/lang/String
      1930: astore        83
      1932: ldc           #167                // String StringContext
      1934: aload         83
      1936: invokevirtual #148                // Method java/lang/Object.equals:(Ljava/lang/Object;)Z
      1939: ifeq          2146
      1942: aload         65
      1944: ifnull        2146
      1947: aload_0
      1948: getfield      #51                 // Field $outer:Lorg/sireum/$internal/Macro;
      1951: invokevirtual #55                 // Method org/sireum/$internal/Macro.c:()Lscala/reflect/macros/blackbox/Context;
      1954: invokeinterface #61,  1           // InterfaceMethod scala/reflect/macros/blackbox/Context.universe:()Lscala/reflect/macros/Universe;
      1959: invokevirtual #133                // Method scala/reflect/macros/Universe.TermNameTag:()Lscala/reflect/ClassTag;
      1962: aload         65
      1964: invokeinterface #71,  2           // InterfaceMethod scala/reflect/ClassTag.unapply:(Ljava/lang/Object;)Lscala/Option;
      1969: astore        84
      1971: aload         84
      1973: invokevirtual #77                 // Method scala/Option.isEmpty:()Z
      1976: ifne          2143
      1979: aload         84
      1981: invokevirtual #81                 // Method scala/Option.get:()Ljava/lang/Object;
      1984: checkcast     #29                 // class scala/reflect/api/Names$TermNameApi
      1987: astore        85
      1989: aload         85
      1991: ifnull        2140
      1994: aload_0
      1995: getfield      #51                 // Field $outer:Lorg/sireum/$internal/Macro;
      1998: invokevirtual #55                 // Method org/sireum/$internal/Macro.c:()Lscala/reflect/macros/blackbox/Context;
      2001: invokeinterface #61,  1           // InterfaceMethod scala/reflect/macros/blackbox/Context.universe:()Lscala/reflect/macros/Universe;
      2006: invokevirtual #137                // Method scala/reflect/macros/Universe.TermName:()Lscala/reflect/api/Names$TermNameExtractor;
      2009: aload         85
      2011: invokevirtual #140                // Method scala/reflect/api/Names$TermNameExtractor.unapply:(Lscala/reflect/api/Names$TermNameApi;)Lscala/Option;
      2014: astore        86
      2016: aload         86
      2018: invokevirtual #77                 // Method scala/Option.isEmpty:()Z
      2021: ifne          2137
      2024: aload         86
      2026: invokevirtual #81                 // Method scala/Option.get:()Ljava/lang/Object;
      2029: checkcast     #142                // class java/lang/String
      2032: astore        87
      2034: ldc           #169                // String apply
      2036: aload         87
      2038: invokevirtual #148                // Method java/lang/Object.equals:(Ljava/lang/Object;)Z
      2041: ifeq          2134
      2044: aload         60
      2046: instanceof    #156                // class scala/collection/immutable/$colon$colon
      2049: ifeq          2134
      2052: aload         60
      2054: checkcast     #156                // class scala/collection/immutable/$colon$colon
      2057: astore        88
      2059: aload         88
      2061: invokevirtual #159                // Method scala/collection/immutable/$colon$colon.head:()Ljava/lang/Object;
      2064: checkcast     #117                // class scala/collection/immutable/List
      2067: astore        89
      2069: aload         88
      2071: invokevirtual #163                // Method scala/collection/immutable/$colon$colon.next$access$1:()Lscala/collection/immutable/List;
      2074: astore        90
      2076: getstatic     #175                // Field scala/collection/immutable/Nil$.MODULE$:Lscala/collection/immutable/Nil$;
      2079: aload         90
      2081: invokevirtual #148                // Method java/lang/Object.equals:(Ljava/lang/Object;)Z
      2084: ifeq          2131
      2087: getstatic     #175                // Field scala/collection/immutable/Nil$.MODULE$:Lscala/collection/immutable/Nil$;
      2090: aload         55
      2092: invokevirtual #148                // Method java/lang/Object.equals:(Ljava/lang/Object;)Z
      2095: ifeq          2131
      2098: getstatic     #175                // Field scala/collection/immutable/Nil$.MODULE$:Lscala/collection/immutable/Nil$;
      2101: aload         52
      2103: invokevirtual #148                // Method java/lang/Object.equals:(Ljava/lang/Object;)Z
      2106: ifeq          2131
      2109: new           #113                // class scala/Some
      2112: dup
      2113: new           #98                 // class scala/Tuple2
      2116: dup
      2117: aload         89
      2119: aload         8
      2121: invokespecial #179                // Method scala/Tuple2."<init>":(Ljava/lang/Object;Ljava/lang/Object;)V
      2124: invokespecial #182                // Method scala/Some."<init>":(Ljava/lang/Object;)V
      2127: astore_2
      2128: goto          2354
      2131: goto          2347
      2134: goto          2347
      2137: goto          2347
      2140: goto          2347
      2143: goto          2347
      2146: goto          2347
      2149: goto          2347
      2152: goto          2347
      2155: goto          2347
      2158: goto          2347
      2161: goto          2347
      2164: goto          2347
      2167: goto          2347
      2170: goto          2347
      2173: goto          2347
      2176: goto          2347
      2179: goto          2347
      2182: goto          2347
      2185: goto          2347
      2188: goto          2347
      2191: goto          2347
      2194: goto          2347
      2197: goto          2347
      2200: goto          2347
      2203: goto          2347
      2206: goto          2347
      2209: goto          2347
      2212: goto          2347
      2215: goto          2347
      2218: goto          2347
      2221: goto          2347
      2224: goto          2347
      2227: goto          2347
      2230: goto          2347
      2233: goto          2347
      2236: goto          2347
      2239: goto          2347
      2242: goto          2347
      2245: goto          2347
      2248: goto          2347
      2251: goto          2347
      2254: goto          2347
      2257: goto          2347
      2260: goto          2347
      2263: goto          2347
      2266: goto          2347
      2269: goto          2347
      2272: goto          2347
      2275: goto          2347
      2278: goto          2347
      2281: goto          2347
      2284: goto          2347
      2287: goto          2347
      2290: goto          2347
      2293: goto          2347
      2296: goto          2347
      2299: goto          2347
      2302: goto          2347
      2305: goto          2347
      2308: goto          2347
      2311: goto          2347
      2314: goto          2347
      2317: goto          2347
      2320: goto          2347
      2323: goto          2347
      2326: goto          2347
      2329: goto          2347
      2332: goto          2347
      2335: goto          2347
      2338: goto          2347
      2341: goto          2347
      2344: goto          2347
      2347: getstatic     #187                // Field scala/None$.MODULE$:Lscala/None$;
      2350: astore_2
      2351: goto          2354
      2354: aload_2
      2355: areturn
      StackMapTable: number_of_entries = 74
        frame_type = 255 /* full_frame */
          offset_delta = 2131
          locals = [ class org/sireum/$internal/Macro$$anon$1, class java/lang/Object, top, class java/lang/Object, class scala/Option, class scala/reflect/api/Trees$TreeApi, class scala/Option, class scala/reflect/api/Trees$TreeApi, class scala/reflect/api/Names$TermNameApi, class scala/Option, class scala/reflect/api/Trees$TreeApi, class scala/Some, class scala/reflect/api/Trees$TreeApi, class scala/collection/immutable/List, class scala/Option, class scala/reflect/api/Trees$TreeApi, class scala/Option, class scala/reflect/api/Trees$TreeApi, class scala/reflect/api/Names$TermNameApi, class scala/Option, class scala/reflect/api/Trees$TreeApi, class scala/Option, class scala/reflect/api/Trees$TreeApi, class scala/reflect/api/Names$TermNameApi, class scala/Option, class scala/reflect/api/Trees$TreeApi, class scala/Option, class scala/reflect/api/Trees$TreeApi, class scala/reflect/api/Names$TermNameApi, class scala/Option, class scala/reflect/api/Trees$IdentApi, class scala/Option, class scala/reflect/api/Names$TermNameApi, int, class scala/Option, class scala/reflect/api/Names$TermNameApi, class scala/Option, class java/lang/String, class scala/Option, class scala/reflect/api/Names$TermNameApi, class scala/Option, class java/lang/String, class scala/Option, class scala/reflect/api/Names$TermNameApi, class scala/Option, class java/lang/String, class scala/Option, class scala/reflect/api/Names$TermNameApi, class scala/Option, class java/lang/String, class scala/collection/immutable/$colon$colon, class scala/collection/immutable/List, class scala/collection/immutable/List, class scala/collection/immutable/$colon$colon, class scala/reflect/api/Trees$TreeApi, class scala/collection/immutable/List, class scala/Option, class scala/reflect/api/Trees$TreeApi, class scala/Some, class scala/reflect/api/Trees$TreeApi, class scala/collection/immutable/List, class scala/Option, class scala/reflect/api/Trees$TreeApi, class scala/Option, class scala/reflect/api/Trees$TreeApi, class scala/reflect/api/Names$TermNameApi, class scala/Option, class scala/reflect/api/Trees$TreeApi, class scala/Option, class scala/reflect/api/Trees$TreeApi, class scala/reflect/api/Names$TermNameApi, class scala/Option, class scala/reflect/api/Trees$IdentApi, class scala/Option, class scala/reflect/api/Names$TermNameApi, int, class scala/Option, class scala/reflect/api/Names$TermNameApi, class scala/Option, class java/lang/String, class scala/Option, class scala/reflect/api/Names$TermNameApi, class scala/Option, class java/lang/String, class scala/Option, class scala/reflect/api/Names$TermNameApi, class scala/Option, class java/lang/String, class scala/collection/immutable/$colon$colon, class scala/collection/immutable/List, class scala/collection/immutable/List ]
          stack = []
        frame_type = 248 /* chop */
          offset_delta = 2
        frame_type = 250 /* chop */
          offset_delta = 2
        frame_type = 250 /* chop */
          offset_delta = 2
        frame_type = 250 /* chop */
          offset_delta = 2
        frame_type = 250 /* chop */
          offset_delta = 2
        frame_type = 250 /* chop */
          offset_delta = 2
        frame_type = 250 /* chop */
          offset_delta = 2
        frame_type = 250 /* chop */
          offset_delta = 2
        frame_type = 250 /* chop */
          offset_delta = 2
        frame_type = 250 /* chop */
          offset_delta = 2
        frame_type = 250 /* chop */
          offset_delta = 2
        frame_type = 250 /* chop */
          offset_delta = 2
        frame_type = 250 /* chop */
          offset_delta = 2
        frame_type = 249 /* chop */
          offset_delta = 2
        frame_type = 250 /* chop */
          offset_delta = 2
        frame_type = 250 /* chop */
          offset_delta = 2
        frame_type = 250 /* chop */
          offset_delta = 2
        frame_type = 249 /* chop */
          offset_delta = 2
        frame_type = 250 /* chop */
          offset_delta = 2
        frame_type = 250 /* chop */
          offset_delta = 2
        frame_type = 250 /* chop */
          offset_delta = 2
        frame_type = 249 /* chop */
          offset_delta = 2
        frame_type = 250 /* chop */
          offset_delta = 2
        frame_type = 250 /* chop */
          offset_delta = 2
        frame_type = 250 /* chop */
          offset_delta = 2
        frame_type = 249 /* chop */
          offset_delta = 2
        frame_type = 250 /* chop */
          offset_delta = 2
        frame_type = 250 /* chop */
          offset_delta = 2
        frame_type = 250 /* chop */
          offset_delta = 2
        frame_type = 248 /* chop */
          offset_delta = 2
        frame_type = 248 /* chop */
          offset_delta = 2
        frame_type = 250 /* chop */
          offset_delta = 2
        frame_type = 250 /* chop */
          offset_delta = 2
        frame_type = 250 /* chop */
          offset_delta = 2
        frame_type = 250 /* chop */
          offset_delta = 2
        frame_type = 250 /* chop */
          offset_delta = 2
        frame_type = 250 /* chop */
          offset_delta = 2
        frame_type = 250 /* chop */
          offset_delta = 2
        frame_type = 250 /* chop */
          offset_delta = 2
        frame_type = 250 /* chop */
          offset_delta = 2
        frame_type = 250 /* chop */
          offset_delta = 2
        frame_type = 250 /* chop */
          offset_delta = 2
        frame_type = 250 /* chop */
          offset_delta = 2
        frame_type = 250 /* chop */
          offset_delta = 2
        frame_type = 250 /* chop */
          offset_delta = 2
        frame_type = 250 /* chop */
          offset_delta = 2
        frame_type = 250 /* chop */
          offset_delta = 2
        frame_type = 249 /* chop */
          offset_delta = 2
        frame_type = 250 /* chop */
          offset_delta = 2
        frame_type = 250 /* chop */
          offset_delta = 2
        frame_type = 250 /* chop */
          offset_delta = 2
        frame_type = 249 /* chop */
          offset_delta = 2
        frame_type = 250 /* chop */
          offset_delta = 2
        frame_type = 250 /* chop */
          offset_delta = 2
        frame_type = 250 /* chop */
          offset_delta = 2
        frame_type = 249 /* chop */
          offset_delta = 2
        frame_type = 250 /* chop */
          offset_delta = 2
        frame_type = 250 /* chop */
          offset_delta = 2
        frame_type = 250 /* chop */
          offset_delta = 2
        frame_type = 249 /* chop */
          offset_delta = 2
        frame_type = 250 /* chop */
          offset_delta = 2
        frame_type = 250 /* chop */
          offset_delta = 2
        frame_type = 250 /* chop */
          offset_delta = 2
        frame_type = 249 /* chop */
          offset_delta = 2
        frame_type = 250 /* chop */
          offset_delta = 2
        frame_type = 250 /* chop */
          offset_delta = 2
        frame_type = 250 /* chop */
          offset_delta = 2
        frame_type = 249 /* chop */
          offset_delta = 2
        frame_type = 250 /* chop */
          offset_delta = 2
        frame_type = 250 /* chop */
          offset_delta = 2
        frame_type = 250 /* chop */
          offset_delta = 2
        frame_type = 2 /* same */
        frame_type = 255 /* full_frame */
          offset_delta = 6
          locals = [ class org/sireum/$internal/Macro$$anon$1, class java/lang/Object, class scala/Option, class java/lang/Object ]
          stack = []
      LineNumberTable:
        line 95: 0
      LocalVariableTable:
        Start  Length  Slot  Name   Signature
         2069      65    89 qq$macro$1   Lscala/collection/immutable/List;
          126    2209     8 qq$macro$2   Lscala/reflect/api/Names$TermNameApi;
            0    2356     0  this   Lorg/sireum/$internal/Macro$$anon$1;
            0    2356     1  tree   Ljava/lang/Object;
    Signature: #48                          // (Ljava/lang/Object;)Lscala/Option<Lscala/Tuple2<Lscala/collection/immutable/List<Lscala/reflect/api/Trees$TreeApi;>;Lscala/reflect/api/Names$TermNameApi;>;>;
    MethodParameters:
      Name                           Flags
      tree                           final

  public org.sireum.$internal.Macro$$anon$1(org.sireum.$internal.Macro);
    descriptor: (Lorg/sireum/$internal/Macro;)V
    flags: (0x0001) ACC_PUBLIC
    Code:
      stack=2, locals=2, args_size=2
         0: aload_1
         1: ifnonnull     6
         4: aconst_null
         5: athrow
         6: aload_0
         7: aload_1
         8: putfield      #51                 // Field $outer:Lorg/sireum/$internal/Macro;
        11: aload_0
        12: invokespecial #198                // Method java/lang/Object."<init>":()V
        15: return
      StackMapTable: number_of_entries = 1
        frame_type = 6 /* same */
      LineNumberTable:
        line 95: 0
      LocalVariableTable:
        Start  Length  Slot  Name   Signature
            0      16     0  this   Lorg/sireum/$internal/Macro$$anon$1;
            0      16     1 $outer   Lorg/sireum/$internal/Macro;
    MethodParameters:
      Name                           Flags
      $outer                         final synthetic
}
InnerClasses:
  public final #2;                        // class org/sireum/$internal/Macro$$anon$1
  public #15= #12 of #14;                 // InternalApi=class scala/reflect/api/Internals$InternalApi of class scala/reflect/api/Internals
  public #18= #17 of #14;                 // ReificationSupportApi=class scala/reflect/api/Internals$ReificationSupportApi of class scala/reflect/api/Internals
  public #21= #20 of #17;                 // SyntacticAppliedExtractor=class scala/reflect/api/Internals$ReificationSupportApi$SyntacticAppliedExtractor of class scala/reflect/api/Internals$ReificationSupportApi
  public #24= #23 of #17;                 // SyntacticSelectTermExtractor=class scala/reflect/api/Internals$ReificationSupportApi$SyntacticSelectTermExtractor of class scala/reflect/api/Internals$ReificationSupportApi
  public #27= #26 of #17;                 // SyntacticTermIdentExtractor=class scala/reflect/api/Internals$ReificationSupportApi$SyntacticTermIdentExtractor of class scala/reflect/api/Internals$ReificationSupportApi
  public #32= #29 of #31;                 // TermNameApi=class scala/reflect/api/Names$TermNameApi of class scala/reflect/api/Names
  public abstract #35= #34 of #31;        // TermNameExtractor=class scala/reflect/api/Names$TermNameExtractor of class scala/reflect/api/Names
  public #40= #37 of #39;                 // IdentApi=class scala/reflect/api/Trees$IdentApi of class scala/reflect/api/Trees
  public #43= #42 of #39;                 // TreeApi=class scala/reflect/api/Trees$TreeApi of class scala/reflect/api/Trees
EnclosingMethod: #7.#10                 // org.sireum.$internal.Macro.extractParts
SourceFile: "Macro.scala"
  ScalaInlineInfo: length = 0xE (unknown attribute)
   01 01 00 02 00 B0 00 C3 01 00 2E 00 2F 01
  Scala: length = 0x0 (unknown attribute)

