Classfile /Users/mw/Projects/slang-braindump/.jar/jar11/assemble/slang-braindump/assemble/content/org/apache/commons/io/input/buffer/CircularByteBuffer.class
  Last modified May 29, 2022; size 3562 bytes
  SHA-256 checksum 4ad788a4a67a98b269420e4755e634ef3745e6c14113e83609dbb7f9046663f1
  Compiled from "CircularByteBuffer.java"
public class org.apache.commons.io.input.buffer.CircularByteBuffer
  minor version: 0
  major version: 52
  flags: (0x0021) ACC_PUBLIC, ACC_SUPER
  this_class: #28                         // org/apache/commons/io/input/buffer/CircularByteBuffer
  super_class: #29                        // java/lang/Object
  interfaces: 0, fields: 4, methods: 13, attributes: 1
Constant pool:
    #1 = Methodref          #29.#74       // java/lang/Object."<init>":()V
    #2 = Fieldref           #28.#75       // org/apache/commons/io/input/buffer/CircularByteBuffer.buffer:[B
    #3 = Fieldref           #28.#76       // org/apache/commons/io/input/buffer/CircularByteBuffer.startOffset:I
    #4 = Fieldref           #28.#77       // org/apache/commons/io/input/buffer/CircularByteBuffer.endOffset:I
    #5 = Fieldref           #28.#78       // org/apache/commons/io/input/buffer/CircularByteBuffer.currentNumberOfBytes:I
    #6 = Class              #79           // org/apache/commons/io/IOUtils
    #7 = Methodref          #28.#80       // org/apache/commons/io/input/buffer/CircularByteBuffer."<init>":(I)V
    #8 = Class              #81           // java/lang/IllegalStateException
    #9 = String             #82           // No bytes available.
   #10 = Methodref          #8.#83        // java/lang/IllegalStateException."<init>":(Ljava/lang/String;)V
   #11 = Methodref          #84.#85       // java/util/Objects.requireNonNull:(Ljava/lang/Object;)Ljava/lang/Object;
   #12 = Class              #86           // java/lang/IllegalArgumentException
   #13 = Class              #87           // java/lang/StringBuilder
   #14 = Methodref          #13.#74       // java/lang/StringBuilder."<init>":()V
   #15 = String             #88           // Invalid offset:
   #16 = Methodref          #13.#89       // java/lang/StringBuilder.append:(Ljava/lang/String;)Ljava/lang/StringBuilder;
   #17 = Methodref          #13.#90       // java/lang/StringBuilder.append:(I)Ljava/lang/StringBuilder;
   #18 = Methodref          #13.#91       // java/lang/StringBuilder.toString:()Ljava/lang/String;
   #19 = Methodref          #12.#83       // java/lang/IllegalArgumentException."<init>":(Ljava/lang/String;)V
   #20 = String             #92           // Invalid length:
   #21 = String             #93           // The supplied byte array contains only
   #22 = String             #94           //  bytes, but offset, and length would require
   #23 = String             #95           // Currently, there are only
   #24 = String             #96           // in the buffer, not
   #25 = String             #97           // No space available
   #26 = String             #98           // Buffer
   #27 = Methodref          #84.#99       // java/util/Objects.requireNonNull:(Ljava/lang/Object;Ljava/lang/String;)Ljava/lang/Object;
   #28 = Class              #100          // org/apache/commons/io/input/buffer/CircularByteBuffer
   #29 = Class              #101          // java/lang/Object
   #30 = Utf8               buffer
   #31 = Utf8               [B
   #32 = Utf8               startOffset
   #33 = Utf8               I
   #34 = Utf8               endOffset
   #35 = Utf8               currentNumberOfBytes
   #36 = Utf8               <init>
   #37 = Utf8               (I)V
   #38 = Utf8               Code
   #39 = Utf8               LineNumberTable
   #40 = Utf8               LocalVariableTable
   #41 = Utf8               this
   #42 = Utf8               Lorg/apache/commons/io/input/buffer/CircularByteBuffer;
   #43 = Utf8               pSize
   #44 = Utf8               ()V
   #45 = Utf8               read
   #46 = Utf8               ()B
   #47 = Utf8               b
   #48 = Utf8               B
   #49 = Utf8               StackMapTable
   #50 = Utf8               ([BII)V
   #51 = Utf8               i
   #52 = Utf8               targetBuffer
   #53 = Utf8               targetOffset
   #54 = Utf8               length
   #55 = Utf8               offset
   #56 = Utf8               add
   #57 = Utf8               (B)V
   #58 = Utf8               value
   #59 = Utf8               peek
   #60 = Utf8               ([BII)Z
   #61 = Utf8               sourceBuffer
   #62 = Utf8               localOffset
   #63 = Utf8               hasSpace
   #64 = Utf8               ()Z
   #65 = Utf8               (I)Z
   #66 = Utf8               count
   #67 = Utf8               hasBytes
   #68 = Utf8               getSpace
   #69 = Utf8               ()I
   #70 = Utf8               getCurrentNumberOfBytes
   #71 = Utf8               clear
   #72 = Utf8               SourceFile
   #73 = Utf8               CircularByteBuffer.java
   #74 = NameAndType        #36:#44       // "<init>":()V
   #75 = NameAndType        #30:#31       // buffer:[B
   #76 = NameAndType        #32:#33       // startOffset:I
   #77 = NameAndType        #34:#33       // endOffset:I
   #78 = NameAndType        #35:#33       // currentNumberOfBytes:I
   #79 = Utf8               org/apache/commons/io/IOUtils
   #80 = NameAndType        #36:#37       // "<init>":(I)V
   #81 = Utf8               java/lang/IllegalStateException
   #82 = Utf8               No bytes available.
   #83 = NameAndType        #36:#102      // "<init>":(Ljava/lang/String;)V
   #84 = Class              #103          // java/util/Objects
   #85 = NameAndType        #104:#105     // requireNonNull:(Ljava/lang/Object;)Ljava/lang/Object;
   #86 = Utf8               java/lang/IllegalArgumentException
   #87 = Utf8               java/lang/StringBuilder
   #88 = Utf8               Invalid offset:
   #89 = NameAndType        #106:#107     // append:(Ljava/lang/String;)Ljava/lang/StringBuilder;
   #90 = NameAndType        #106:#108     // append:(I)Ljava/lang/StringBuilder;
   #91 = NameAndType        #109:#110     // toString:()Ljava/lang/String;
   #92 = Utf8               Invalid length:
   #93 = Utf8               The supplied byte array contains only
   #94 = Utf8                bytes, but offset, and length would require
   #95 = Utf8               Currently, there are only
   #96 = Utf8               in the buffer, not
   #97 = Utf8               No space available
   #98 = Utf8               Buffer
   #99 = NameAndType        #104:#111     // requireNonNull:(Ljava/lang/Object;Ljava/lang/String;)Ljava/lang/Object;
  #100 = Utf8               org/apache/commons/io/input/buffer/CircularByteBuffer
  #101 = Utf8               java/lang/Object
  #102 = Utf8               (Ljava/lang/String;)V
  #103 = Utf8               java/util/Objects
  #104 = Utf8               requireNonNull
  #105 = Utf8               (Ljava/lang/Object;)Ljava/lang/Object;
  #106 = Utf8               append
  #107 = Utf8               (Ljava/lang/String;)Ljava/lang/StringBuilder;
  #108 = Utf8               (I)Ljava/lang/StringBuilder;
  #109 = Utf8               toString
  #110 = Utf8               ()Ljava/lang/String;
  #111 = Utf8               (Ljava/lang/Object;Ljava/lang/String;)Ljava/lang/Object;
{
  private final byte[] buffer;
    descriptor: [B
    flags: (0x0012) ACC_PRIVATE, ACC_FINAL

  private int startOffset;
    descriptor: I
    flags: (0x0002) ACC_PRIVATE

  private int endOffset;
    descriptor: I
    flags: (0x0002) ACC_PRIVATE

  private int currentNumberOfBytes;
    descriptor: I
    flags: (0x0002) ACC_PRIVATE

  public org.apache.commons.io.input.buffer.CircularByteBuffer(int);
    descriptor: (I)V
    flags: (0x0001) ACC_PUBLIC
    Code:
      stack=2, locals=2, args_size=2
         0: aload_0
         1: invokespecial #1                  // Method java/lang/Object."<init>":()V
         4: aload_0
         5: iload_1
         6: newarray       byte
         8: putfield      #2                  // Field buffer:[B
        11: aload_0
        12: iconst_0
        13: putfield      #3                  // Field startOffset:I
        16: aload_0
        17: iconst_0
        18: putfield      #4                  // Field endOffset:I
        21: aload_0
        22: iconst_0
        23: putfield      #5                  // Field currentNumberOfBytes:I
        26: return
      LineNumberTable:
        line 41: 0
        line 42: 4
        line 43: 11
        line 44: 16
        line 45: 21
        line 46: 26
      LocalVariableTable:
        Start  Length  Slot  Name   Signature
            0      27     0  this   Lorg/apache/commons/io/input/buffer/CircularByteBuffer;
            0      27     1 pSize   I

  public org.apache.commons.io.input.buffer.CircularByteBuffer();
    descriptor: ()V
    flags: (0x0001) ACC_PUBLIC
    Code:
      stack=2, locals=1, args_size=1
         0: aload_0
         1: sipush        8192
         4: invokespecial #7                  // Method "<init>":(I)V
         7: return
      LineNumberTable:
        line 52: 0
        line 53: 7
      LocalVariableTable:
        Start  Length  Slot  Name   Signature
            0       8     0  this   Lorg/apache/commons/io/input/buffer/CircularByteBuffer;

  public byte read();
    descriptor: ()B
    flags: (0x0001) ACC_PUBLIC
    Code:
      stack=3, locals=2, args_size=1
         0: aload_0
         1: getfield      #5                  // Field currentNumberOfBytes:I
         4: ifgt          17
         7: new           #8                  // class java/lang/IllegalStateException
        10: dup
        11: ldc           #9                  // String No bytes available.
        13: invokespecial #10                 // Method java/lang/IllegalStateException."<init>":(Ljava/lang/String;)V
        16: athrow
        17: aload_0
        18: getfield      #2                  // Field buffer:[B
        21: aload_0
        22: getfield      #3                  // Field startOffset:I
        25: baload
        26: istore_1
        27: aload_0
        28: dup
        29: getfield      #5                  // Field currentNumberOfBytes:I
        32: iconst_1
        33: isub
        34: putfield      #5                  // Field currentNumberOfBytes:I
        37: aload_0
        38: dup
        39: getfield      #3                  // Field startOffset:I
        42: iconst_1
        43: iadd
        44: dup_x1
        45: putfield      #3                  // Field startOffset:I
        48: aload_0
        49: getfield      #2                  // Field buffer:[B
        52: arraylength
        53: if_icmpne     61
        56: aload_0
        57: iconst_0
        58: putfield      #3                  // Field startOffset:I
        61: iload_1
        62: ireturn
      LineNumberTable:
        line 64: 0
        line 65: 7
        line 67: 17
        line 68: 27
        line 69: 37
        line 70: 56
        line 72: 61
      LocalVariableTable:
        Start  Length  Slot  Name   Signature
            0      63     0  this   Lorg/apache/commons/io/input/buffer/CircularByteBuffer;
           27      36     1     b   B
      StackMapTable: number_of_entries = 2
        frame_type = 17 /* same */
        frame_type = 252 /* append */
          offset_delta = 43
          locals = [ int ]

  public void read(byte[], int, int);
    descriptor: ([BII)V
    flags: (0x0001) ACC_PUBLIC
    Code:
      stack=5, locals=6, args_size=4
         0: aload_1
         1: invokestatic  #11                 // Method java/util/Objects.requireNonNull:(Ljava/lang/Object;)Ljava/lang/Object;
         4: pop
         5: iload_2
         6: iflt          15
         9: iload_2
        10: aload_1
        11: arraylength
        12: if_icmplt     42
        15: new           #12                 // class java/lang/IllegalArgumentException
        18: dup
        19: new           #13                 // class java/lang/StringBuilder
        22: dup
        23: invokespecial #14                 // Method java/lang/StringBuilder."<init>":()V
        26: ldc           #15                 // String Invalid offset:
        28: invokevirtual #16                 // Method java/lang/StringBuilder.append:(Ljava/lang/String;)Ljava/lang/StringBuilder;
        31: iload_2
        32: invokevirtual #17                 // Method java/lang/StringBuilder.append:(I)Ljava/lang/StringBuilder;
        35: invokevirtual #18                 // Method java/lang/StringBuilder.toString:()Ljava/lang/String;
        38: invokespecial #19                 // Method java/lang/IllegalArgumentException."<init>":(Ljava/lang/String;)V
        41: athrow
        42: iload_3
        43: iflt          55
        46: iload_3
        47: aload_0
        48: getfield      #2                  // Field buffer:[B
        51: arraylength
        52: if_icmple     82
        55: new           #12                 // class java/lang/IllegalArgumentException
        58: dup
        59: new           #13                 // class java/lang/StringBuilder
        62: dup
        63: invokespecial #14                 // Method java/lang/StringBuilder."<init>":()V
        66: ldc           #20                 // String Invalid length:
        68: invokevirtual #16                 // Method java/lang/StringBuilder.append:(Ljava/lang/String;)Ljava/lang/StringBuilder;
        71: iload_3
        72: invokevirtual #17                 // Method java/lang/StringBuilder.append:(I)Ljava/lang/StringBuilder;
        75: invokevirtual #18                 // Method java/lang/StringBuilder.toString:()Ljava/lang/String;
        78: invokespecial #19                 // Method java/lang/IllegalArgumentException."<init>":(Ljava/lang/String;)V
        81: athrow
        82: iload_2
        83: iload_3
        84: iadd
        85: aload_1
        86: arraylength
        87: if_icmple     131
        90: new           #12                 // class java/lang/IllegalArgumentException
        93: dup
        94: new           #13                 // class java/lang/StringBuilder
        97: dup
        98: invokespecial #14                 // Method java/lang/StringBuilder."<init>":()V
       101: ldc           #21                 // String The supplied byte array contains only
       103: invokevirtual #16                 // Method java/lang/StringBuilder.append:(Ljava/lang/String;)Ljava/lang/StringBuilder;
       106: aload_1
       107: arraylength
       108: invokevirtual #17                 // Method java/lang/StringBuilder.append:(I)Ljava/lang/StringBuilder;
       111: ldc           #22                 // String  bytes, but offset, and length would require
       113: invokevirtual #16                 // Method java/lang/StringBuilder.append:(Ljava/lang/String;)Ljava/lang/StringBuilder;
       116: iload_2
       117: iload_3
       118: iadd
       119: iconst_1
       120: isub
       121: invokevirtual #17                 // Method java/lang/StringBuilder.append:(I)Ljava/lang/StringBuilder;
       124: invokevirtual #18                 // Method java/lang/StringBuilder.toString:()Ljava/lang/String;
       127: invokespecial #19                 // Method java/lang/IllegalArgumentException."<init>":(Ljava/lang/String;)V
       130: athrow
       131: aload_0
       132: getfield      #5                  // Field currentNumberOfBytes:I
       135: iload_3
       136: if_icmpge     178
       139: new           #8                  // class java/lang/IllegalStateException
       142: dup
       143: new           #13                 // class java/lang/StringBuilder
       146: dup
       147: invokespecial #14                 // Method java/lang/StringBuilder."<init>":()V
       150: ldc           #23                 // String Currently, there are only
       152: invokevirtual #16                 // Method java/lang/StringBuilder.append:(Ljava/lang/String;)Ljava/lang/StringBuilder;
       155: aload_0
       156: getfield      #5                  // Field currentNumberOfBytes:I
       159: invokevirtual #17                 // Method java/lang/StringBuilder.append:(I)Ljava/lang/StringBuilder;
       162: ldc           #24                 // String in the buffer, not
       164: invokevirtual #16                 // Method java/lang/StringBuilder.append:(Ljava/lang/String;)Ljava/lang/StringBuilder;
       167: iload_3
       168: invokevirtual #17                 // Method java/lang/StringBuilder.append:(I)Ljava/lang/StringBuilder;
       171: invokevirtual #18                 // Method java/lang/StringBuilder.toString:()Ljava/lang/String;
       174: invokespecial #10                 // Method java/lang/IllegalStateException."<init>":(Ljava/lang/String;)V
       177: athrow
       178: iload_2
       179: istore        4
       181: iconst_0
       182: istore        5
       184: iload         5
       186: iload_3
       187: if_icmpge     246
       190: aload_1
       191: iload         4
       193: iinc          4, 1
       196: aload_0
       197: getfield      #2                  // Field buffer:[B
       200: aload_0
       201: getfield      #3                  // Field startOffset:I
       204: baload
       205: bastore
       206: aload_0
       207: dup
       208: getfield      #5                  // Field currentNumberOfBytes:I
       211: iconst_1
       212: isub
       213: putfield      #5                  // Field currentNumberOfBytes:I
       216: aload_0
       217: dup
       218: getfield      #3                  // Field startOffset:I
       221: iconst_1
       222: iadd
       223: dup_x1
       224: putfield      #3                  // Field startOffset:I
       227: aload_0
       228: getfield      #2                  // Field buffer:[B
       231: arraylength
       232: if_icmpne     240
       235: aload_0
       236: iconst_0
       237: putfield      #3                  // Field startOffset:I
       240: iinc          5, 1
       243: goto          184
       246: return
      LineNumberTable:
        line 90: 0
        line 91: 5
        line 92: 15
        line 94: 42
        line 95: 55
        line 97: 82
        line 98: 90
        line 102: 131
        line 103: 139
        line 106: 178
        line 107: 181
        line 108: 190
        line 109: 206
        line 110: 216
        line 111: 235
        line 107: 240
        line 114: 246
      LocalVariableTable:
        Start  Length  Slot  Name   Signature
          184      62     5     i   I
            0     247     0  this   Lorg/apache/commons/io/input/buffer/CircularByteBuffer;
            0     247     1 targetBuffer   [B
            0     247     2 targetOffset   I
            0     247     3 length   I
          181      66     4 offset   I
      StackMapTable: number_of_entries = 9
        frame_type = 15 /* same */
        frame_type = 26 /* same */
        frame_type = 12 /* same */
        frame_type = 26 /* same */
        frame_type = 48 /* same */
        frame_type = 46 /* same */
        frame_type = 253 /* append */
          offset_delta = 5
          locals = [ int, int ]
        frame_type = 55 /* same */
        frame_type = 250 /* chop */
          offset_delta = 5

  public void add(byte);
    descriptor: (B)V
    flags: (0x0001) ACC_PUBLIC
    Code:
      stack=3, locals=2, args_size=2
         0: aload_0
         1: getfield      #5                  // Field currentNumberOfBytes:I
         4: aload_0
         5: getfield      #2                  // Field buffer:[B
         8: arraylength
         9: if_icmplt     22
        12: new           #8                  // class java/lang/IllegalStateException
        15: dup
        16: ldc           #25                 // String No space available
        18: invokespecial #10                 // Method java/lang/IllegalStateException."<init>":(Ljava/lang/String;)V
        21: athrow
        22: aload_0
        23: getfield      #2                  // Field buffer:[B
        26: aload_0
        27: getfield      #4                  // Field endOffset:I
        30: iload_1
        31: bastore
        32: aload_0
        33: dup
        34: getfield      #5                  // Field currentNumberOfBytes:I
        37: iconst_1
        38: iadd
        39: putfield      #5                  // Field currentNumberOfBytes:I
        42: aload_0
        43: dup
        44: getfield      #4                  // Field endOffset:I
        47: iconst_1
        48: iadd
        49: dup_x1
        50: putfield      #4                  // Field endOffset:I
        53: aload_0
        54: getfield      #2                  // Field buffer:[B
        57: arraylength
        58: if_icmpne     66
        61: aload_0
        62: iconst_0
        63: putfield      #4                  // Field endOffset:I
        66: return
      LineNumberTable:
        line 125: 0
        line 126: 12
        line 128: 22
        line 129: 32
        line 130: 42
        line 131: 61
        line 133: 66
      LocalVariableTable:
        Start  Length  Slot  Name   Signature
            0      67     0  this   Lorg/apache/commons/io/input/buffer/CircularByteBuffer;
            0      67     1 value   B
      StackMapTable: number_of_entries = 2
        frame_type = 22 /* same */
        frame_type = 43 /* same */

  public boolean peek(byte[], int, int);
    descriptor: ([BII)Z
    flags: (0x0001) ACC_PUBLIC
    Code:
      stack=4, locals=6, args_size=4
         0: aload_1
         1: ldc           #26                 // String Buffer
         3: invokestatic  #27                 // Method java/util/Objects.requireNonNull:(Ljava/lang/Object;Ljava/lang/String;)Ljava/lang/Object;
         6: pop
         7: iload_2
         8: iflt          17
        11: iload_2
        12: aload_1
        13: arraylength
        14: if_icmplt     44
        17: new           #12                 // class java/lang/IllegalArgumentException
        20: dup
        21: new           #13                 // class java/lang/StringBuilder
        24: dup
        25: invokespecial #14                 // Method java/lang/StringBuilder."<init>":()V
        28: ldc           #15                 // String Invalid offset:
        30: invokevirtual #16                 // Method java/lang/StringBuilder.append:(Ljava/lang/String;)Ljava/lang/StringBuilder;
        33: iload_2
        34: invokevirtual #17                 // Method java/lang/StringBuilder.append:(I)Ljava/lang/StringBuilder;
        37: invokevirtual #18                 // Method java/lang/StringBuilder.toString:()Ljava/lang/String;
        40: invokespecial #19                 // Method java/lang/IllegalArgumentException."<init>":(Ljava/lang/String;)V
        43: athrow
        44: iload_3
        45: iflt          57
        48: iload_3
        49: aload_0
        50: getfield      #2                  // Field buffer:[B
        53: arraylength
        54: if_icmple     84
        57: new           #12                 // class java/lang/IllegalArgumentException
        60: dup
        61: new           #13                 // class java/lang/StringBuilder
        64: dup
        65: invokespecial #14                 // Method java/lang/StringBuilder."<init>":()V
        68: ldc           #20                 // String Invalid length:
        70: invokevirtual #16                 // Method java/lang/StringBuilder.append:(Ljava/lang/String;)Ljava/lang/StringBuilder;
        73: iload_3
        74: invokevirtual #17                 // Method java/lang/StringBuilder.append:(I)Ljava/lang/StringBuilder;
        77: invokevirtual #18                 // Method java/lang/StringBuilder.toString:()Ljava/lang/String;
        80: invokespecial #19                 // Method java/lang/IllegalArgumentException."<init>":(Ljava/lang/String;)V
        83: athrow
        84: iload_3
        85: aload_0
        86: getfield      #5                  // Field currentNumberOfBytes:I
        89: if_icmpge     94
        92: iconst_0
        93: ireturn
        94: aload_0
        95: getfield      #3                  // Field startOffset:I
        98: istore        4
       100: iconst_0
       101: istore        5
       103: iload         5
       105: iload_3
       106: if_icmpge     149
       109: aload_0
       110: getfield      #2                  // Field buffer:[B
       113: iload         4
       115: baload
       116: aload_1
       117: iload         5
       119: iload_2
       120: iadd
       121: baload
       122: if_icmpeq     127
       125: iconst_0
       126: ireturn
       127: iinc          4, 1
       130: iload         4
       132: aload_0
       133: getfield      #2                  // Field buffer:[B
       136: arraylength
       137: if_icmpne     143
       140: iconst_0
       141: istore        4
       143: iinc          5, 1
       146: goto          103
       149: iconst_1
       150: ireturn
      LineNumberTable:
        line 151: 0
        line 152: 7
        line 153: 17
        line 155: 44
        line 156: 57
        line 158: 84
        line 159: 92
        line 161: 94
        line 162: 100
        line 163: 109
        line 164: 125
        line 166: 127
        line 167: 140
        line 162: 143
        line 170: 149
      LocalVariableTable:
        Start  Length  Slot  Name   Signature
          103      46     5     i   I
            0     151     0  this   Lorg/apache/commons/io/input/buffer/CircularByteBuffer;
            0     151     1 sourceBuffer   [B
            0     151     2 offset   I
            0     151     3 length   I
          100      51     4 localOffset   I
      StackMapTable: number_of_entries = 9
        frame_type = 17 /* same */
        frame_type = 26 /* same */
        frame_type = 12 /* same */
        frame_type = 26 /* same */
        frame_type = 9 /* same */
        frame_type = 253 /* append */
          offset_delta = 8
          locals = [ int, int ]
        frame_type = 23 /* same */
        frame_type = 15 /* same */
        frame_type = 250 /* chop */
          offset_delta = 5

  public void add(byte[], int, int);
    descriptor: ([BII)V
    flags: (0x0001) ACC_PUBLIC
    Code:
      stack=5, locals=5, args_size=4
         0: aload_1
         1: ldc           #26                 // String Buffer
         3: invokestatic  #27                 // Method java/util/Objects.requireNonNull:(Ljava/lang/Object;Ljava/lang/String;)Ljava/lang/Object;
         6: pop
         7: iload_2
         8: iflt          17
        11: iload_2
        12: aload_1
        13: arraylength
        14: if_icmplt     44
        17: new           #12                 // class java/lang/IllegalArgumentException
        20: dup
        21: new           #13                 // class java/lang/StringBuilder
        24: dup
        25: invokespecial #14                 // Method java/lang/StringBuilder."<init>":()V
        28: ldc           #15                 // String Invalid offset:
        30: invokevirtual #16                 // Method java/lang/StringBuilder.append:(Ljava/lang/String;)Ljava/lang/StringBuilder;
        33: iload_2
        34: invokevirtual #17                 // Method java/lang/StringBuilder.append:(I)Ljava/lang/StringBuilder;
        37: invokevirtual #18                 // Method java/lang/StringBuilder.toString:()Ljava/lang/String;
        40: invokespecial #19                 // Method java/lang/IllegalArgumentException."<init>":(Ljava/lang/String;)V
        43: athrow
        44: iload_3
        45: ifge          75
        48: new           #12                 // class java/lang/IllegalArgumentException
        51: dup
        52: new           #13                 // class java/lang/StringBuilder
        55: dup
        56: invokespecial #14                 // Method java/lang/StringBuilder."<init>":()V
        59: ldc           #20                 // String Invalid length:
        61: invokevirtual #16                 // Method java/lang/StringBuilder.append:(Ljava/lang/String;)Ljava/lang/StringBuilder;
        64: iload_3
        65: invokevirtual #17                 // Method java/lang/StringBuilder.append:(I)Ljava/lang/StringBuilder;
        68: invokevirtual #18                 // Method java/lang/StringBuilder.toString:()Ljava/lang/String;
        71: invokespecial #19                 // Method java/lang/IllegalArgumentException."<init>":(Ljava/lang/String;)V
        74: athrow
        75: aload_0
        76: getfield      #5                  // Field currentNumberOfBytes:I
        79: iload_3
        80: iadd
        81: aload_0
        82: getfield      #2                  // Field buffer:[B
        85: arraylength
        86: if_icmple     99
        89: new           #8                  // class java/lang/IllegalStateException
        92: dup
        93: ldc           #25                 // String No space available
        95: invokespecial #10                 // Method java/lang/IllegalStateException."<init>":(Ljava/lang/String;)V
        98: athrow
        99: iconst_0
       100: istore        4
       102: iload         4
       104: iload_3
       105: if_icmpge     153
       108: aload_0
       109: getfield      #2                  // Field buffer:[B
       112: aload_0
       113: getfield      #4                  // Field endOffset:I
       116: aload_1
       117: iload_2
       118: iload         4
       120: iadd
       121: baload
       122: bastore
       123: aload_0
       124: dup
       125: getfield      #4                  // Field endOffset:I
       128: iconst_1
       129: iadd
       130: dup_x1
       131: putfield      #4                  // Field endOffset:I
       134: aload_0
       135: getfield      #2                  // Field buffer:[B
       138: arraylength
       139: if_icmpne     147
       142: aload_0
       143: iconst_0
       144: putfield      #4                  // Field endOffset:I
       147: iinc          4, 1
       150: goto          102
       153: aload_0
       154: dup
       155: getfield      #5                  // Field currentNumberOfBytes:I
       158: iload_3
       159: iadd
       160: putfield      #5                  // Field currentNumberOfBytes:I
       163: return
      LineNumberTable:
        line 187: 0
        line 188: 7
        line 189: 17
        line 191: 44
        line 192: 48
        line 194: 75
        line 195: 89
        line 197: 99
        line 198: 108
        line 199: 123
        line 200: 142
        line 197: 147
        line 203: 153
        line 204: 163
      LocalVariableTable:
        Start  Length  Slot  Name   Signature
          102      51     4     i   I
            0     164     0  this   Lorg/apache/commons/io/input/buffer/CircularByteBuffer;
            0     164     1 targetBuffer   [B
            0     164     2 offset   I
            0     164     3 length   I
      StackMapTable: number_of_entries = 7
        frame_type = 17 /* same */
        frame_type = 26 /* same */
        frame_type = 30 /* same */
        frame_type = 23 /* same */
        frame_type = 252 /* append */
          offset_delta = 2
          locals = [ int ]
        frame_type = 44 /* same */
        frame_type = 250 /* chop */
          offset_delta = 5

  public boolean hasSpace();
    descriptor: ()Z
    flags: (0x0001) ACC_PUBLIC
    Code:
      stack=2, locals=1, args_size=1
         0: aload_0
         1: getfield      #5                  // Field currentNumberOfBytes:I
         4: aload_0
         5: getfield      #2                  // Field buffer:[B
         8: arraylength
         9: if_icmpge     16
        12: iconst_1
        13: goto          17
        16: iconst_0
        17: ireturn
      LineNumberTable:
        line 215: 0
      LocalVariableTable:
        Start  Length  Slot  Name   Signature
            0      18     0  this   Lorg/apache/commons/io/input/buffer/CircularByteBuffer;
      StackMapTable: number_of_entries = 2
        frame_type = 16 /* same */
        frame_type = 64 /* same_locals_1_stack_item */
          stack = [ int ]

  public boolean hasSpace(int);
    descriptor: (I)Z
    flags: (0x0001) ACC_PUBLIC
    Code:
      stack=2, locals=2, args_size=2
         0: aload_0
         1: getfield      #5                  // Field currentNumberOfBytes:I
         4: iload_1
         5: iadd
         6: aload_0
         7: getfield      #2                  // Field buffer:[B
        10: arraylength
        11: if_icmpgt     18
        14: iconst_1
        15: goto          19
        18: iconst_0
        19: ireturn
      LineNumberTable:
        line 227: 0
      LocalVariableTable:
        Start  Length  Slot  Name   Signature
            0      20     0  this   Lorg/apache/commons/io/input/buffer/CircularByteBuffer;
            0      20     1 count   I
      StackMapTable: number_of_entries = 2
        frame_type = 18 /* same */
        frame_type = 64 /* same_locals_1_stack_item */
          stack = [ int ]

  public boolean hasBytes();
    descriptor: ()Z
    flags: (0x0001) ACC_PUBLIC
    Code:
      stack=1, locals=1, args_size=1
         0: aload_0
         1: getfield      #5                  // Field currentNumberOfBytes:I
         4: ifle          11
         7: iconst_1
         8: goto          12
        11: iconst_0
        12: ireturn
      LineNumberTable:
        line 236: 0
      LocalVariableTable:
        Start  Length  Slot  Name   Signature
            0      13     0  this   Lorg/apache/commons/io/input/buffer/CircularByteBuffer;
      StackMapTable: number_of_entries = 2
        frame_type = 11 /* same */
        frame_type = 64 /* same_locals_1_stack_item */
          stack = [ int ]

  public int getSpace();
    descriptor: ()I
    flags: (0x0001) ACC_PUBLIC
    Code:
      stack=2, locals=1, args_size=1
         0: aload_0
         1: getfield      #2                  // Field buffer:[B
         4: arraylength
         5: aload_0
         6: getfield      #5                  // Field currentNumberOfBytes:I
         9: isub
        10: ireturn
      LineNumberTable:
        line 245: 0
      LocalVariableTable:
        Start  Length  Slot  Name   Signature
            0      11     0  this   Lorg/apache/commons/io/input/buffer/CircularByteBuffer;

  public int getCurrentNumberOfBytes();
    descriptor: ()I
    flags: (0x0001) ACC_PUBLIC
    Code:
      stack=1, locals=1, args_size=1
         0: aload_0
         1: getfield      #5                  // Field currentNumberOfBytes:I
         4: ireturn
      LineNumberTable:
        line 254: 0
      LocalVariableTable:
        Start  Length  Slot  Name   Signature
            0       5     0  this   Lorg/apache/commons/io/input/buffer/CircularByteBuffer;

  public void clear();
    descriptor: ()V
    flags: (0x0001) ACC_PUBLIC
    Code:
      stack=2, locals=1, args_size=1
         0: aload_0
         1: iconst_0
         2: putfield      #3                  // Field startOffset:I
         5: aload_0
         6: iconst_0
         7: putfield      #4                  // Field endOffset:I
        10: aload_0
        11: iconst_0
        12: putfield      #5                  // Field currentNumberOfBytes:I
        15: return
      LineNumberTable:
        line 261: 0
        line 262: 5
        line 263: 10
        line 264: 15
      LocalVariableTable:
        Start  Length  Slot  Name   Signature
            0      16     0  this   Lorg/apache/commons/io/input/buffer/CircularByteBuffer;
}
SourceFile: "CircularByteBuffer.java"
