Classfile /Users/mw/Projects/slang-braindump/.jar/jar11/assemble/slang-braindump/assemble/content/scala/annotation/unused.class
  Last modified May 29, 2022; size 955 bytes
  SHA-256 checksum 7214b1cfc2300354b431e717b524cbfff1ecc72ca7d9c6cb36f736926612a95a
  Compiled from "unused.scala"
public class scala.annotation.unused extends scala.annotation.Annotation implements scala.annotation.StaticAnnotation
  minor version: 0
  major version: 52
  flags: (0x0021) ACC_PUBLIC, ACC_SUPER
  this_class: #2                          // scala/annotation/unused
  super_class: #4                         // scala/annotation/Annotation
  interfaces: 1, fields: 0, methods: 2, attributes: 4
Constant pool:
   #1 = Utf8               scala/annotation/unused
   #2 = Class              #1             // scala/annotation/unused
   #3 = Utf8               scala/annotation/Annotation
   #4 = Class              #3             // scala/annotation/Annotation
   #5 = Utf8               scala/annotation/StaticAnnotation
   #6 = Class              #5             // scala/annotation/StaticAnnotation
   #7 = Utf8               unused.scala
   #8 = Utf8               Lscala/reflect/ScalaSignature;
   #9 = Utf8               bytes
  #10 = Utf8               \u0006\u000592A\u0001B\u0003\u0001\u0015!A!\u0003\u0001B\u0001B\u0003%1\u0003C\u0003\u001f\u0001\u0011\u0005q\u0004C\u0003\u001f\u0001\u0011\u0005!E\u0001\u0004v]V\u001cX\r\u001a\u0006\u0003\r\u001d\t!\"\u00198o_R\fG/[8o\u0015\u0005A\u0011!B:dC2\f7\u0001A\n\u0004\u0001-y\u0001C\u0001\u0007\u000e\u001b\u0005)\u0011B\u0001\b\u0006\u0005)\teN\\8uCRLwN\u001c\t\u0003\u0019AI!!E\u0003\u0003!M#\u0018\r^5d\u0003:tw\u000e^1uS>t\u0017aB7fgN\fw-\u001a\t\u0003)mq!!F\r\u0011\u0005Y9Q\"A\f\u000b\u0005aI\u0011A\u0002\u001fs_>$h(\u0003\u0002\u001b\u000f\u00051\u0001K]3eK\u001aL!\u0001H\u000f\u0003\rM#(/\u001b8h\u0015\tQr!\u0001\u0004=S:LGO\u0010\u000b\u0003A\u0005\u0002\"\u0001\u0004\u0001\t\u000bI\u0011\u0001\u0019A\n\u0015\u0003\u0001B#\u0001\u0001\u0013\u0011\u0005\u0015BS\"\u0001\u0014\u000b\u0005\u001d*\u0011\u0001B7fi\u0006L!!\u000b\u0014\u0003\rM,G\u000f^3sQ\t\u00011\u0006\u0005\u0002&Y%\u0011QF\n\u0002\u0007O\u0016$H/\u001a:
  #11 = Utf8               <init>
  #12 = Utf8               (Ljava/lang/String;)V
  #13 = Utf8               message
  #14 = Utf8               ()V
  #15 = NameAndType        #11:#14        // "<init>":()V
  #16 = Methodref          #4.#15         // scala/annotation/Annotation."<init>":()V
  #17 = Utf8               this
  #18 = Utf8               Lscala/annotation/unused;
  #19 = Utf8               Ljava/lang/String;
  #20 = Utf8
  #21 = String             #20            //
  #22 = NameAndType        #11:#12        // "<init>":(Ljava/lang/String;)V
  #23 = Methodref          #2.#22         // scala/annotation/unused."<init>":(Ljava/lang/String;)V
  #24 = Utf8               Code
  #25 = Utf8               LineNumberTable
  #26 = Utf8               LocalVariableTable
  #27 = Utf8               MethodParameters
  #28 = Utf8               SourceFile
  #29 = Utf8               RuntimeVisibleAnnotations
  #30 = Utf8               ScalaInlineInfo
  #31 = Utf8               ScalaSig
{
  public scala.annotation.unused(java.lang.String);
    descriptor: (Ljava/lang/String;)V
    flags: (0x0001) ACC_PUBLIC
    Code:
      stack=1, locals=2, args_size=2
         0: aload_0
         1: invokespecial #16                 // Method scala/annotation/Annotation."<init>":()V
         4: return
      LineNumberTable:
        line 24: 0
      LocalVariableTable:
        Start  Length  Slot  Name   Signature
            0       5     0  this   Lscala/annotation/unused;
            0       5     1 message   Ljava/lang/String;
    MethodParameters:
      Name                           Flags
      message                        final

  public scala.annotation.unused();
    descriptor: ()V
    flags: (0x0001) ACC_PUBLIC
    Code:
      stack=2, locals=1, args_size=1
         0: aload_0
         1: ldc           #21                 // String
         3: invokespecial #23                 // Method "<init>":(Ljava/lang/String;)V
         6: return
      LineNumberTable:
        line 25: 0
      LocalVariableTable:
        Start  Length  Slot  Name   Signature
            0       7     0  this   Lscala/annotation/unused;
}
SourceFile: "unused.scala"
RuntimeVisibleAnnotations:
  0: #8(#9=s#10)
    scala.reflect.ScalaSignature(
      bytes="\u0006\u000592A\u0001B\u0003\u0001\u0015!A!\u0003\u0001B\u0001B\u0003%1\u0003C\u0003\u001f\u0001\u0011\u0005q\u0004C\u0003\u001f\u0001\u0011\u0005!E\u0001\u0004v]V\u001cX\r\u001a\u0006\u0003\r\u001d\t!\"\u00198o_R\fG/[8o\u0015\u0005A\u0011!B:dC2\f7\u0001A\n\u0004\u0001-y\u0001C\u0001\u0007\u000e\u001b\u0005)\u0011B\u0001\b\u0006\u0005)\teN\\8uCRLwN\u001c\t\u0003\u0019AI!!E\u0003\u0003!M#\u0018\r^5d\u0003:tw\u000e^1uS>t\u0017aB7fgN\fw-\u001a\t\u0003)mq!!F\r\u0011\u0005Y9Q\"A\f\u000b\u0005aI\u0011A\u0002\u001fs_>$h(\u0003\u0002\u001b\u000f\u00051\u0001K]3eK\u001aL!\u0001H\u000f\u0003\rM#(/\u001b8h\u0015\tQr!\u0001\u0004=S:LGO\u0010\u000b\u0003A\u0005\u0002\"\u0001\u0004\u0001\t\u000bI\u0011\u0001\u0019A\n\u0015\u0003\u0001B#\u0001\u0001\u0013\u0011\u0005\u0015BS\"\u0001\u0014\u000b\u0005\u001d*\u0011\u0001B7fi\u0006L!!\u000b\u0014\u0003\rM,G\u000f^3sQ\t\u00011\u0006\u0005\u0002&Y%\u0011QF\n\u0002\u0007O\u0016$H/\u001a:"
    )
  ScalaInlineInfo: length = 0xE (unknown attribute)
   01 00 00 02 00 0B 00 0E 00 00 0B 00 0C 00
  ScalaSig: length = 0x3 (unknown attribute)
   05 02 00
