Classfile /Users/mw/Projects/slang-braindump/.jar/jar11/assemble/slang-braindump/assemble/content/scala/sys/process/package$.class
  Last modified May 29, 2022; size 3418 bytes
  SHA-256 checksum 4b0066ac8cb9cfd4f1363abf1b795d28116fc80542cf580c82fdaf1ab653b669
  Compiled from "package.scala"
public final class scala.sys.process.package$ implements scala.sys.process.ProcessImplicits
  minor version: 0
  major version: 52
  flags: (0x0031) ACC_PUBLIC, ACC_FINAL, ACC_SUPER
  this_class: #2                          // scala/sys/process/package$
  super_class: #4                         // java/lang/Object
  interfaces: 1, fields: 1, methods: 11, attributes: 4
Constant pool:
    #1 = Utf8               scala/sys/process/package$
    #2 = Class              #1            // scala/sys/process/package$
    #3 = Utf8               java/lang/Object
    #4 = Class              #3            // java/lang/Object
    #5 = Utf8               scala/sys/process/ProcessImplicits
    #6 = Class              #5            // scala/sys/process/ProcessImplicits
    #7 = Utf8               package.scala
    #8 = Utf8               scala/sys/process/ProcessBuilder$FileBuilder
    #9 = Class              #8            // scala/sys/process/ProcessBuilder$FileBuilder
   #10 = Utf8               scala/sys/process/ProcessBuilder
   #11 = Class              #10           // scala/sys/process/ProcessBuilder
   #12 = Utf8               FileBuilder
   #13 = Utf8               scala/sys/process/ProcessBuilder$Source
   #14 = Class              #13           // scala/sys/process/ProcessBuilder$Source
   #15 = Utf8               Source
   #16 = Utf8               scala/sys/process/ProcessBuilder$URLBuilder
   #17 = Class              #16           // scala/sys/process/ProcessBuilder$URLBuilder
   #18 = Utf8               URLBuilder
   #19 = Utf8               MODULE$
   #20 = Utf8               Lscala/sys/process/package$;
   #21 = Utf8               <clinit>
   #22 = Utf8               ()V
   #23 = Utf8               <init>
   #24 = NameAndType        #23:#22       // "<init>":()V
   #25 = Methodref          #2.#24        // scala/sys/process/package$."<init>":()V
   #26 = NameAndType        #19:#20       // MODULE$:Lscala/sys/process/package$;
   #27 = Fieldref           #2.#26        // scala/sys/process/package$.MODULE$:Lscala/sys/process/package$;
   #28 = Utf8               buildersToProcess
   #29 = Utf8               (Lscala/collection/Seq;Lscala/Function1;)Lscala/collection/Seq;
   #30 = Utf8               <T:Ljava/lang/Object;>(Lscala/collection/Seq<TT;>;Lscala/Function1<TT;Lscala/sys/process/ProcessBuilder$Source;>;)Lscala/collection/Seq<Lscala/sys/process/ProcessBuilder$Source;>;
   #31 = Utf8               builders
   #32 = Utf8               convert
   #33 = Utf8               buildersToProcess$
   #34 = Utf8               (Lscala/sys/process/ProcessImplicits;Lscala/collection/Seq;Lscala/Function1;)Lscala/collection/Seq;
   #35 = NameAndType        #33:#34       // buildersToProcess$:(Lscala/sys/process/ProcessImplicits;Lscala/collection/Seq;Lscala/Function1;)Lscala/collection/Seq;
   #36 = InterfaceMethodref #6.#35        // scala/sys/process/ProcessImplicits.buildersToProcess$:(Lscala/sys/process/ProcessImplicits;Lscala/collection/Seq;Lscala/Function1;)Lscala/collection/Seq;
   #37 = Utf8               this
   #38 = Utf8               Lscala/collection/Seq;
   #39 = Utf8               Lscala/Function1;
   #40 = Utf8               builderToProcess
   #41 = Utf8               (Ljava/lang/ProcessBuilder;)Lscala/sys/process/ProcessBuilder;
   #42 = Utf8               builder
   #43 = Utf8               builderToProcess$
   #44 = Utf8               (Lscala/sys/process/ProcessImplicits;Ljava/lang/ProcessBuilder;)Lscala/sys/process/ProcessBuilder;
   #45 = NameAndType        #43:#44       // builderToProcess$:(Lscala/sys/process/ProcessImplicits;Ljava/lang/ProcessBuilder;)Lscala/sys/process/ProcessBuilder;
   #46 = InterfaceMethodref #6.#45        // scala/sys/process/ProcessImplicits.builderToProcess$:(Lscala/sys/process/ProcessImplicits;Ljava/lang/ProcessBuilder;)Lscala/sys/process/ProcessBuilder;
   #47 = Utf8               Ljava/lang/ProcessBuilder;
   #48 = Utf8               fileToProcess
   #49 = Utf8               (Ljava/io/File;)Lscala/sys/process/ProcessBuilder$FileBuilder;
   #50 = Utf8               file
   #51 = Utf8               fileToProcess$
   #52 = Utf8               (Lscala/sys/process/ProcessImplicits;Ljava/io/File;)Lscala/sys/process/ProcessBuilder$FileBuilder;
   #53 = NameAndType        #51:#52       // fileToProcess$:(Lscala/sys/process/ProcessImplicits;Ljava/io/File;)Lscala/sys/process/ProcessBuilder$FileBuilder;
   #54 = InterfaceMethodref #6.#53        // scala/sys/process/ProcessImplicits.fileToProcess$:(Lscala/sys/process/ProcessImplicits;Ljava/io/File;)Lscala/sys/process/ProcessBuilder$FileBuilder;
   #55 = Utf8               Ljava/io/File;
   #56 = Utf8               urlToProcess
   #57 = Utf8               (Ljava/net/URL;)Lscala/sys/process/ProcessBuilder$URLBuilder;
   #58 = Utf8               url
   #59 = Utf8               urlToProcess$
   #60 = Utf8               (Lscala/sys/process/ProcessImplicits;Ljava/net/URL;)Lscala/sys/process/ProcessBuilder$URLBuilder;
   #61 = NameAndType        #59:#60       // urlToProcess$:(Lscala/sys/process/ProcessImplicits;Ljava/net/URL;)Lscala/sys/process/ProcessBuilder$URLBuilder;
   #62 = InterfaceMethodref #6.#61        // scala/sys/process/ProcessImplicits.urlToProcess$:(Lscala/sys/process/ProcessImplicits;Ljava/net/URL;)Lscala/sys/process/ProcessBuilder$URLBuilder;
   #63 = Utf8               Ljava/net/URL;
   #64 = Utf8               stringToProcess
   #65 = Utf8               (Ljava/lang/String;)Lscala/sys/process/ProcessBuilder;
   #66 = Utf8               command
   #67 = Utf8               stringToProcess$
   #68 = Utf8               (Lscala/sys/process/ProcessImplicits;Ljava/lang/String;)Lscala/sys/process/ProcessBuilder;
   #69 = NameAndType        #67:#68       // stringToProcess$:(Lscala/sys/process/ProcessImplicits;Ljava/lang/String;)Lscala/sys/process/ProcessBuilder;
   #70 = InterfaceMethodref #6.#69        // scala/sys/process/ProcessImplicits.stringToProcess$:(Lscala/sys/process/ProcessImplicits;Ljava/lang/String;)Lscala/sys/process/ProcessBuilder;
   #71 = Utf8               Ljava/lang/String;
   #72 = Utf8               stringSeqToProcess
   #73 = Utf8               (Lscala/collection/Seq;)Lscala/sys/process/ProcessBuilder;
   #74 = Utf8               (Lscala/collection/Seq<Ljava/lang/String;>;)Lscala/sys/process/ProcessBuilder;
   #75 = Utf8               stringSeqToProcess$
   #76 = Utf8               (Lscala/sys/process/ProcessImplicits;Lscala/collection/Seq;)Lscala/sys/process/ProcessBuilder;
   #77 = NameAndType        #75:#76       // stringSeqToProcess$:(Lscala/sys/process/ProcessImplicits;Lscala/collection/Seq;)Lscala/sys/process/ProcessBuilder;
   #78 = InterfaceMethodref #6.#77        // scala/sys/process/ProcessImplicits.stringSeqToProcess$:(Lscala/sys/process/ProcessImplicits;Lscala/collection/Seq;)Lscala/sys/process/ProcessBuilder;
   #79 = Utf8               stdin
   #80 = Utf8               ()Ljava/io/InputStream;
   #81 = Utf8               java/lang/System
   #82 = Class              #81           // java/lang/System
   #83 = Utf8               in
   #84 = Utf8               Ljava/io/InputStream;
   #85 = NameAndType        #83:#84       // in:Ljava/io/InputStream;
   #86 = Fieldref           #82.#85       // java/lang/System.in:Ljava/io/InputStream;
   #87 = Utf8               stdout
   #88 = Utf8               ()Ljava/io/PrintStream;
   #89 = Utf8               out
   #90 = Utf8               Ljava/io/PrintStream;
   #91 = NameAndType        #89:#90       // out:Ljava/io/PrintStream;
   #92 = Fieldref           #82.#91       // java/lang/System.out:Ljava/io/PrintStream;
   #93 = Utf8               stderr
   #94 = Utf8               err
   #95 = NameAndType        #94:#90       // err:Ljava/io/PrintStream;
   #96 = Fieldref           #82.#95       // java/lang/System.err:Ljava/io/PrintStream;
   #97 = Methodref          #4.#24        // java/lang/Object."<init>":()V
   #98 = Utf8               Code
   #99 = Utf8               LineNumberTable
  #100 = Utf8               LocalVariableTable
  #101 = Utf8               Signature
  #102 = Utf8               MethodParameters
  #103 = Utf8               InnerClasses
  #104 = Utf8               SourceFile
  #105 = Utf8               ScalaInlineInfo
  #106 = Utf8               Scala
{
  public static final scala.sys.process.package$ MODULE$;
    descriptor: Lscala/sys/process/package$;
    flags: (0x0019) ACC_PUBLIC, ACC_STATIC, ACC_FINAL

  public static {};
    descriptor: ()V
    flags: (0x0009) ACC_PUBLIC, ACC_STATIC
    Code:
      stack=2, locals=0, args_size=0
         0: new           #2                  // class scala/sys/process/package$
         3: dup
         4: invokespecial #25                 // Method "<init>":()V
         7: putstatic     #27                 // Field MODULE$:Lscala/sys/process/package$;
        10: getstatic     #27                 // Field MODULE$:Lscala/sys/process/package$;
        13: pop
        14: return
      LineNumberTable:
        line 207: 0

  public <T extends java.lang.Object> scala.collection.Seq<scala.sys.process.ProcessBuilder$Source> buildersToProcess(scala.collection.Seq<T>, scala.Function1<T, scala.sys.process.ProcessBuilder$Source>);
    descriptor: (Lscala/collection/Seq;Lscala/Function1;)Lscala/collection/Seq;
    flags: (0x0001) ACC_PUBLIC
    Code:
      stack=3, locals=3, args_size=3
         0: aload_0
         1: aload_1
         2: aload_2
         3: invokestatic  #36                 // InterfaceMethod scala/sys/process/ProcessImplicits.buildersToProcess$:(Lscala/sys/process/ProcessImplicits;Lscala/collection/Seq;Lscala/Function1;)Lscala/collection/Seq;
         6: areturn
      LineNumberTable:
        line 207: 0
      LocalVariableTable:
        Start  Length  Slot  Name   Signature
            0       7     0  this   Lscala/sys/process/package$;
            0       7     1 builders   Lscala/collection/Seq;
            0       7     2 convert   Lscala/Function1;
    Signature: #30                          // <T:Ljava/lang/Object;>(Lscala/collection/Seq<TT;>;Lscala/Function1<TT;Lscala/sys/process/ProcessBuilder$Source;>;)Lscala/collection/Seq<Lscala/sys/process/ProcessBuilder$Source;>;
    MethodParameters:
      Name                           Flags
      builders                       final
      convert                        final

  public scala.sys.process.ProcessBuilder builderToProcess(java.lang.ProcessBuilder);
    descriptor: (Ljava/lang/ProcessBuilder;)Lscala/sys/process/ProcessBuilder;
    flags: (0x0001) ACC_PUBLIC
    Code:
      stack=2, locals=2, args_size=2
         0: aload_0
         1: aload_1
         2: invokestatic  #46                 // InterfaceMethod scala/sys/process/ProcessImplicits.builderToProcess$:(Lscala/sys/process/ProcessImplicits;Ljava/lang/ProcessBuilder;)Lscala/sys/process/ProcessBuilder;
         5: areturn
      LineNumberTable:
        line 207: 0
      LocalVariableTable:
        Start  Length  Slot  Name   Signature
            0       6     0  this   Lscala/sys/process/package$;
            0       6     1 builder   Ljava/lang/ProcessBuilder;
    MethodParameters:
      Name                           Flags
      builder                        final

  public scala.sys.process.ProcessBuilder$FileBuilder fileToProcess(java.io.File);
    descriptor: (Ljava/io/File;)Lscala/sys/process/ProcessBuilder$FileBuilder;
    flags: (0x0001) ACC_PUBLIC
    Code:
      stack=2, locals=2, args_size=2
         0: aload_0
         1: aload_1
         2: invokestatic  #54                 // InterfaceMethod scala/sys/process/ProcessImplicits.fileToProcess$:(Lscala/sys/process/ProcessImplicits;Ljava/io/File;)Lscala/sys/process/ProcessBuilder$FileBuilder;
         5: areturn
      LineNumberTable:
        line 207: 0
      LocalVariableTable:
        Start  Length  Slot  Name   Signature
            0       6     0  this   Lscala/sys/process/package$;
            0       6     1  file   Ljava/io/File;
    MethodParameters:
      Name                           Flags
      file                           final

  public scala.sys.process.ProcessBuilder$URLBuilder urlToProcess(java.net.URL);
    descriptor: (Ljava/net/URL;)Lscala/sys/process/ProcessBuilder$URLBuilder;
    flags: (0x0001) ACC_PUBLIC
    Code:
      stack=2, locals=2, args_size=2
         0: aload_0
         1: aload_1
         2: invokestatic  #62                 // InterfaceMethod scala/sys/process/ProcessImplicits.urlToProcess$:(Lscala/sys/process/ProcessImplicits;Ljava/net/URL;)Lscala/sys/process/ProcessBuilder$URLBuilder;
         5: areturn
      LineNumberTable:
        line 207: 0
      LocalVariableTable:
        Start  Length  Slot  Name   Signature
            0       6     0  this   Lscala/sys/process/package$;
            0       6     1   url   Ljava/net/URL;
    MethodParameters:
      Name                           Flags
      url                            final

  public scala.sys.process.ProcessBuilder stringToProcess(java.lang.String);
    descriptor: (Ljava/lang/String;)Lscala/sys/process/ProcessBuilder;
    flags: (0x0001) ACC_PUBLIC
    Code:
      stack=2, locals=2, args_size=2
         0: aload_0
         1: aload_1
         2: invokestatic  #70                 // InterfaceMethod scala/sys/process/ProcessImplicits.stringToProcess$:(Lscala/sys/process/ProcessImplicits;Ljava/lang/String;)Lscala/sys/process/ProcessBuilder;
         5: areturn
      LineNumberTable:
        line 207: 0
      LocalVariableTable:
        Start  Length  Slot  Name   Signature
            0       6     0  this   Lscala/sys/process/package$;
            0       6     1 command   Ljava/lang/String;
    MethodParameters:
      Name                           Flags
      command                        final

  public scala.sys.process.ProcessBuilder stringSeqToProcess(scala.collection.Seq<java.lang.String>);
    descriptor: (Lscala/collection/Seq;)Lscala/sys/process/ProcessBuilder;
    flags: (0x0001) ACC_PUBLIC
    Code:
      stack=2, locals=2, args_size=2
         0: aload_0
         1: aload_1
         2: invokestatic  #78                 // InterfaceMethod scala/sys/process/ProcessImplicits.stringSeqToProcess$:(Lscala/sys/process/ProcessImplicits;Lscala/collection/Seq;)Lscala/sys/process/ProcessBuilder;
         5: areturn
      LineNumberTable:
        line 207: 0
      LocalVariableTable:
        Start  Length  Slot  Name   Signature
            0       6     0  this   Lscala/sys/process/package$;
            0       6     1 command   Lscala/collection/Seq;
    Signature: #74                          // (Lscala/collection/Seq<Ljava/lang/String;>;)Lscala/sys/process/ProcessBuilder;
    MethodParameters:
      Name                           Flags
      command                        final

  public java.io.InputStream stdin();
    descriptor: ()Ljava/io/InputStream;
    flags: (0x0001) ACC_PUBLIC
    Code:
      stack=1, locals=1, args_size=1
         0: getstatic     #86                 // Field java/lang/System.in:Ljava/io/InputStream;
         3: areturn
      LineNumberTable:
        line 209: 0
      LocalVariableTable:
        Start  Length  Slot  Name   Signature
            0       4     0  this   Lscala/sys/process/package$;

  public java.io.PrintStream stdout();
    descriptor: ()Ljava/io/PrintStream;
    flags: (0x0001) ACC_PUBLIC
    Code:
      stack=1, locals=1, args_size=1
         0: getstatic     #92                 // Field java/lang/System.out:Ljava/io/PrintStream;
         3: areturn
      LineNumberTable:
        line 211: 0
      LocalVariableTable:
        Start  Length  Slot  Name   Signature
            0       4     0  this   Lscala/sys/process/package$;

  public java.io.PrintStream stderr();
    descriptor: ()Ljava/io/PrintStream;
    flags: (0x0001) ACC_PUBLIC
    Code:
      stack=1, locals=1, args_size=1
         0: getstatic     #96                 // Field java/lang/System.err:Ljava/io/PrintStream;
         3: areturn
      LineNumberTable:
        line 213: 0
      LocalVariableTable:
        Start  Length  Slot  Name   Signature
            0       4     0  this   Lscala/sys/process/package$;

  private scala.sys.process.package$();
    descriptor: ()V
    flags: (0x0002) ACC_PRIVATE
    Code:
      stack=1, locals=1, args_size=1
         0: aload_0
         1: invokespecial #97                 // Method java/lang/Object."<init>":()V
         4: return
      LineNumberTable:
        line 207: 0
      LocalVariableTable:
        Start  Length  Slot  Name   Signature
            0       5     0  this   Lscala/sys/process/package$;
}
InnerClasses:
  public static #12= #9 of #11;           // FileBuilder=class scala/sys/process/ProcessBuilder$FileBuilder of class scala/sys/process/ProcessBuilder
  public static #15= #14 of #11;          // Source=class scala/sys/process/ProcessBuilder$Source of class scala/sys/process/ProcessBuilder
  public static #18= #17 of #11;          // URLBuilder=class scala/sys/process/ProcessBuilder$URLBuilder of class scala/sys/process/ProcessBuilder
SourceFile: "package.scala"
  ScalaInlineInfo: length = 0x36 (unknown attribute)
   01 01 00 0A 00 17 00 16 01 00 28 00 29 01 00 1C
   00 1D 01 00 30 00 31 01 00 5D 00 58 01 00 4F 00
   50 01 00 57 00 58 01 00 48 00 49 01 00 40 00 41
   01 00 38 00 39 01
  Scala: length = 0x0 (unknown attribute)

