Classfile /Users/mw/Projects/slang-braindump/.jar/jar11/assemble/slang-braindump/assemble/content/scala/sys/process/Parser.class
  Last modified May 29, 2022; size 1648 bytes
  SHA-256 checksum c80c3db28f0a10686363c748ee486391597cde509464b5b910cd36fdd3c0b923
  Compiled from "Parser.scala"
public final class scala.sys.process.Parser
  minor version: 0
  major version: 52
  flags: (0x0031) ACC_PUBLIC, ACC_FINAL, ACC_SUPER
  this_class: #2                          // scala/sys/process/Parser
  super_class: #4                         // java/lang/Object
  interfaces: 0, fields: 0, methods: 2, attributes: 4
Constant pool:
   #1 = Utf8               scala/sys/process/Parser
   #2 = Class              #1             // scala/sys/process/Parser
   #3 = Utf8               java/lang/Object
   #4 = Class              #3             // java/lang/Object
   #5 = Utf8               Parser.scala
   #6 = Utf8               Lscala/reflect/ScalaSignature;
   #7 = Utf8               bytes
   #8 = Utf8               \u0006\u0005q;a!\u0004\b\t\u0002I!bA\u0002\f\u000f\u0011\u0003\u0011r\u0003C\u0003\u001d\u0003\u0011\u0005a\u0004C\u0004 \u0003\t\u0007IQ\u0002\u0011\t\r\r\n\u0001\u0015!\u0004\"\u0011\u001d!\u0013A1A\u0005\u000e\u0015Ba\u0001K\u0001!\u0002\u001b1\u0003\"B\u0015\u0002\t\u0013Qc\u0001\u0002#\u0002\u0001\u0015C\u0001\"\u0013\u0005\u0003\u0002\u0003\u0006Ia\u000e\u0005\u00069!!\tA\u0013\u0005\u0006\u001d\u0006!\ta\u0014\u0005\u0006\u001d\u0006!\tAW\u0001\u0007!\u0006\u00148/\u001a:\u000b\u0005=\u0001\u0012a\u00029s_\u000e,7o\u001d\u0006\u0003#I\t1a]=t\u0015\u0005\u0019\u0012!B:dC2\f\u0007CA\u000b\u0002\u001b\u0005q!A\u0002)beN,\'o\u0005\u0002\u00021A\u0011\u0011DG\u0007\u0002%%\u00111D\u0005\u0002\u0007\u0003:L(+\u001a4\u0002\rqJg.\u001b;?\u0007\u0001!\u0012\u0001F\u0001\u0003\tF+\u0012!I\b\u0002Eq\t!%A\u0002E#\u0002\n!aU)\u0016\u0003\u0019z\u0011a\n\u000f\u0002O\u0005\u00191+\u0015\u0011\u0002\rQ|7.\u001a8t)\tY#\t\u0005\u0003-i]zdBA\u00173\u001d\tq\u0013\'D\u00010\u0015\t\u0001T$\u0001\u0004=e>|GOP\u0005\u0002\'%\u00111GE\u0001\ba\u0006\u001c7.Y4f\u0013\t)dG\u0001\u0004FSRDWM\u001d\u0006\u0003gI\u0001\"\u0001\u000f\u001f\u000f\u0005eR\u0004C\u0001\u0018\u0013\u0013\tY$#\u0001\u0004Qe\u0016$WMZ\u0005\u0003{y\u0012aa\u0015;sS:<\'BA\u001e\u0013!\ra\u0003iN\u0005\u0003\u0003Z\u0012A\u0001T5ti\")1i\u0002a\u0001o\u0005\u0011\u0011N\u001c\u0002\u000f!\u0006\u00148/Z#yG\u0016\u0004H/[8o\'\tAa\t\u0005\u0002-\u000f&\u0011\u0001J\u000e\u0002\u0011%VtG/[7f\u000bb\u001cW\r\u001d;j_:\f1!\\:h)\tYU\n\u0005\u0002M\u00115\t\u0011\u0001C\u0003J\u0015\u0001\u0007q\'\u0001\u0005u_.,g.\u001b>f)\ry\u0004K\u0015\u0005\u0006#.\u0001\raN\u0001\u0005Y&tW\rC\u0003T\u0017\u0001\u0007A+A\u0004feJ|\'O\u00128\u0011\te)vgV\u0005\u0003-J\u0011\u0011BR;oGRLwN\\\u0019\u0011\u0005eA\u0016BA-\u0013\u0005\u0011)f.\u001b;\u0015\u0005}Z\u0006\"B)\r\u0001\u00049\u0004
   #9 = Utf8               scala/sys/process/Parser$ParseException
  #10 = Class              #9             // scala/sys/process/Parser$ParseException
  #11 = Utf8               ParseException
  #12 = Utf8               tokenize
  #13 = Utf8               (Ljava/lang/String;)Lscala/collection/immutable/List;
  #14 = Utf8               (Ljava/lang/String;)Lscala/collection/immutable/List<Ljava/lang/String;>;
  #15 = Utf8               line
  #16 = Utf8               scala/sys/process/Parser$
  #17 = Class              #16            // scala/sys/process/Parser$
  #18 = Utf8               MODULE$
  #19 = Utf8               Lscala/sys/process/Parser$;
  #20 = NameAndType        #18:#19        // MODULE$:Lscala/sys/process/Parser$;
  #21 = Fieldref           #17.#20        // scala/sys/process/Parser$.MODULE$:Lscala/sys/process/Parser$;
  #22 = NameAndType        #12:#13        // tokenize:(Ljava/lang/String;)Lscala/collection/immutable/List;
  #23 = Methodref          #17.#22        // scala/sys/process/Parser$.tokenize:(Ljava/lang/String;)Lscala/collection/immutable/List;
  #24 = Utf8               Ljava/lang/String;
  #25 = Utf8               (Ljava/lang/String;Lscala/Function1;)Lscala/collection/immutable/List;
  #26 = Utf8               (Ljava/lang/String;Lscala/Function1<Ljava/lang/String;Lscala/runtime/BoxedUnit;>;)Lscala/collection/immutable/List<Ljava/lang/String;>;
  #27 = Utf8               errorFn
  #28 = NameAndType        #12:#25        // tokenize:(Ljava/lang/String;Lscala/Function1;)Lscala/collection/immutable/List;
  #29 = Methodref          #17.#28        // scala/sys/process/Parser$.tokenize:(Ljava/lang/String;Lscala/Function1;)Lscala/collection/immutable/List;
  #30 = Utf8               Lscala/Function1;
  #31 = Utf8               Code
  #32 = Utf8               LocalVariableTable
  #33 = Utf8               Signature
  #34 = Utf8               MethodParameters
  #35 = Utf8               InnerClasses
  #36 = Utf8               SourceFile
  #37 = Utf8               RuntimeVisibleAnnotations
  #38 = Utf8               ScalaSig
{
  public static scala.collection.immutable.List<java.lang.String> tokenize(java.lang.String);
    descriptor: (Ljava/lang/String;)Lscala/collection/immutable/List;
    flags: (0x0009) ACC_PUBLIC, ACC_STATIC
    Code:
      stack=2, locals=1, args_size=1
         0: getstatic     #21                 // Field scala/sys/process/Parser$.MODULE$:Lscala/sys/process/Parser$;
         3: aload_0
         4: invokevirtual #23                 // Method scala/sys/process/Parser$.tokenize:(Ljava/lang/String;)Lscala/collection/immutable/List;
         7: areturn
      LocalVariableTable:
        Start  Length  Slot  Name   Signature
            0       8     0  line   Ljava/lang/String;
    Signature: #14                          // (Ljava/lang/String;)Lscala/collection/immutable/List<Ljava/lang/String;>;
    MethodParameters:
      Name                           Flags
      line                           final

  public static scala.collection.immutable.List<java.lang.String> tokenize(java.lang.String, scala.Function1<java.lang.String, scala.runtime.BoxedUnit>);
    descriptor: (Ljava/lang/String;Lscala/Function1;)Lscala/collection/immutable/List;
    flags: (0x0009) ACC_PUBLIC, ACC_STATIC
    Code:
      stack=3, locals=2, args_size=2
         0: getstatic     #21                 // Field scala/sys/process/Parser$.MODULE$:Lscala/sys/process/Parser$;
         3: aload_0
         4: aload_1
         5: invokevirtual #29                 // Method scala/sys/process/Parser$.tokenize:(Ljava/lang/String;Lscala/Function1;)Lscala/collection/immutable/List;
         8: areturn
      LocalVariableTable:
        Start  Length  Slot  Name   Signature
            0       9     0  line   Ljava/lang/String;
            0       9     1 errorFn   Lscala/Function1;
    Signature: #26                          // (Ljava/lang/String;Lscala/Function1<Ljava/lang/String;Lscala/runtime/BoxedUnit;>;)Lscala/collection/immutable/List<Ljava/lang/String;>;
    MethodParameters:
      Name                           Flags
      line                           final
      errorFn                        final
}
InnerClasses:
  public static #11= #10 of #2;           // ParseException=class scala/sys/process/Parser$ParseException of class scala/sys/process/Parser
SourceFile: "Parser.scala"
RuntimeVisibleAnnotations:
  0: #6(#7=s#8)
    scala.reflect.ScalaSignature(
      bytes="\u0006\u0005q;a!\u0004\b\t\u0002I!bA\u0002\f\u000f\u0011\u0003\u0011r\u0003C\u0003\u001d\u0003\u0011\u0005a\u0004C\u0004 \u0003\t\u0007IQ\u0002\u0011\t\r\r\n\u0001\u0015!\u0004\"\u0011\u001d!\u0013A1A\u0005\u000e\u0015Ba\u0001K\u0001!\u0002\u001b1\u0003\"B\u0015\u0002\t\u0013Qc\u0001\u0002#\u0002\u0001\u0015C\u0001\"\u0013\u0005\u0003\u0002\u0003\u0006Ia\u000e\u0005\u00069!!\tA\u0013\u0005\u0006\u001d\u0006!\ta\u0014\u0005\u0006\u001d\u0006!\tAW\u0001\u0007!\u0006\u00148/\u001a:\u000b\u0005=\u0001\u0012a\u00029s_\u000e,7o\u001d\u0006\u0003#I\t1a]=t\u0015\u0005\u0019\u0012!B:dC2\f\u0007CA\u000b\u0002\u001b\u0005q!A\u0002)beN,\'o\u0005\u0002\u00021A\u0011\u0011DG\u0007\u0002%%\u00111D\u0005\u0002\u0007\u0003:L(+\u001a4\u0002\rqJg.\u001b;?\u0007\u0001!\u0012\u0001F\u0001\u0003\tF+\u0012!I\b\u0002Eq\t!%A\u0002E#\u0002\n!aU)\u0016\u0003\u0019z\u0011a\n\u000f\u0002O\u0005\u00191+\u0015\u0011\u0002\rQ|7.\u001a8t)\tY#\t\u0005\u0003-i]zdBA\u00173\u001d\tq\u0013\'D\u00010\u0015\t\u0001T$\u0001\u0004=e>|GOP\u0005\u0002\'%\u00111GE\u0001\ba\u0006\u001c7.Y4f\u0013\t)dG\u0001\u0004FSRDWM\u001d\u0006\u0003gI\u0001\"\u0001\u000f\u001f\u000f\u0005eR\u0004C\u0001\u0018\u0013\u0013\tY$#\u0001\u0004Qe\u0016$WMZ\u0005\u0003{y\u0012aa\u0015;sS:<\'BA\u001e\u0013!\ra\u0003iN\u0005\u0003\u0003Z\u0012A\u0001T5ti\")1i\u0002a\u0001o\u0005\u0011\u0011N\u001c\u0002\u000f!\u0006\u00148/Z#yG\u0016\u0004H/[8o\'\tAa\t\u0005\u0002-\u000f&\u0011\u0001J\u000e\u0002\u0011%VtG/[7f\u000bb\u001cW\r\u001d;j_:\f1!\\:h)\tYU\n\u0005\u0002M\u00115\t\u0011\u0001C\u0003J\u0015\u0001\u0007q\'\u0001\u0005u_.,g.\u001b>f)\ry\u0004K\u0015\u0005\u0006#.\u0001\raN\u0001\u0005Y&tW\rC\u0003T\u0017\u0001\u0007A+A\u0004feJ|\'O\u00128\u0011\te)vgV\u0005\u0003-J\u0011\u0011BR;oGRLwN\\\u0019\u0011\u0005eA\u0016BA-\u0013\u0005\u0011)f.\u001b;\u0015\u0005}Z\u0006\"B)\r\u0001\u00049\u0004"
    )
  ScalaSig: length = 0x3 (unknown attribute)
   05 02 00
