Classfile /Users/mw/Projects/slang-braindump/.jar/jar11/assemble/slang-braindump/assemble/content/scala/sys/process/ProcessBuilder$.class
  Last modified May 29, 2022; size 494 bytes
  SHA-256 checksum 90edb76dc1b67c06e0f0ad7c601a89dadce9523c64578d16c9213bd5ee97b51a
  Compiled from "ProcessBuilder.scala"
public final class scala.sys.process.ProcessBuilder$ implements scala.sys.process.ProcessBuilderImpl
  minor version: 0
  major version: 52
  flags: (0x0031) ACC_PUBLIC, ACC_FINAL, ACC_SUPER
  this_class: #2                          // scala/sys/process/ProcessBuilder$
  super_class: #4                         // java/lang/Object
  interfaces: 1, fields: 1, methods: 2, attributes: 3
Constant pool:
   #1 = Utf8               scala/sys/process/ProcessBuilder$
   #2 = Class              #1             // scala/sys/process/ProcessBuilder$
   #3 = Utf8               java/lang/Object
   #4 = Class              #3             // java/lang/Object
   #5 = Utf8               scala/sys/process/ProcessBuilderImpl
   #6 = Class              #5             // scala/sys/process/ProcessBuilderImpl
   #7 = Utf8               ProcessBuilder.scala
   #8 = Utf8               MODULE$
   #9 = Utf8               Lscala/sys/process/ProcessBuilder$;
  #10 = Utf8               <clinit>
  #11 = Utf8               ()V
  #12 = Utf8               <init>
  #13 = NameAndType        #12:#11        // "<init>":()V
  #14 = Methodref          #2.#13         // scala/sys/process/ProcessBuilder$."<init>":()V
  #15 = NameAndType        #8:#9          // MODULE$:Lscala/sys/process/ProcessBuilder$;
  #16 = Fieldref           #2.#15         // scala/sys/process/ProcessBuilder$.MODULE$:Lscala/sys/process/ProcessBuilder$;
  #17 = Methodref          #4.#13         // java/lang/Object."<init>":()V
  #18 = Utf8               this
  #19 = Utf8               Code
  #20 = Utf8               LineNumberTable
  #21 = Utf8               LocalVariableTable
  #22 = Utf8               SourceFile
  #23 = Utf8               ScalaInlineInfo
  #24 = Utf8               Scala
{
  public static final scala.sys.process.ProcessBuilder$ MODULE$;
    descriptor: Lscala/sys/process/ProcessBuilder$;
    flags: (0x0019) ACC_PUBLIC, ACC_STATIC, ACC_FINAL

  public static {};
    descriptor: ()V
    flags: (0x0009) ACC_PUBLIC, ACC_STATIC
    Code:
      stack=2, locals=0, args_size=0
         0: new           #2                  // class scala/sys/process/ProcessBuilder$
         3: dup
         4: invokespecial #14                 // Method "<init>":()V
         7: putstatic     #16                 // Field MODULE$:Lscala/sys/process/ProcessBuilder$;
        10: getstatic     #16                 // Field MODULE$:Lscala/sys/process/ProcessBuilder$;
        13: pop
        14: return
      LineNumberTable:
        line 409: 0

  private scala.sys.process.ProcessBuilder$();
    descriptor: ()V
    flags: (0x0002) ACC_PRIVATE
    Code:
      stack=1, locals=1, args_size=1
         0: aload_0
         1: invokespecial #17                 // Method java/lang/Object."<init>":()V
         4: return
      LineNumberTable:
        line 409: 0
      LocalVariableTable:
        Start  Length  Slot  Name   Signature
            0       5     0  this   Lscala/sys/process/ProcessBuilder$;
}
SourceFile: "ProcessBuilder.scala"
  ScalaInlineInfo: length = 0x9 (unknown attribute)
   01 01 00 01 00 0C 00 0B 01
  Scala: length = 0x0 (unknown attribute)

