Classfile /Users/mw/Projects/slang-braindump/.jar/jar11/assemble/slang-braindump/assemble/content/scala/sys/process/ProcessImpl$ThreadProcess.class
  Last modified May 29, 2022; size 1505 bytes
  SHA-256 checksum 8eda7f1dd38c867433966c0e140035634bb2ba4bc244268cd2f47d133950ead3
  Compiled from "ProcessImpl.scala"
public final class scala.sys.process.ProcessImpl$ThreadProcess implements scala.sys.process.Process
  minor version: 0
  major version: 52
  flags: (0x0031) ACC_PUBLIC, ACC_FINAL, ACC_SUPER
  this_class: #2                          // scala/sys/process/ProcessImpl$ThreadProcess
  super_class: #4                         // java/lang/Object
  interfaces: 1, fields: 2, methods: 4, attributes: 4
Constant pool:
   #1 = Utf8               scala/sys/process/ProcessImpl$ThreadProcess
   #2 = Class              #1             // scala/sys/process/ProcessImpl$ThreadProcess
   #3 = Utf8               java/lang/Object
   #4 = Class              #3             // java/lang/Object
   #5 = Utf8               scala/sys/process/Process
   #6 = Class              #5             // scala/sys/process/Process
   #7 = Utf8               ProcessImpl.scala
   #8 = Utf8               scala/sys/process/ProcessImpl
   #9 = Class              #8             // scala/sys/process/ProcessImpl
  #10 = Utf8               ThreadProcess
  #11 = Utf8               thread
  #12 = Utf8               Ljava/lang/Thread;
  #13 = Utf8               success
  #14 = Utf8               Ljava/util/concurrent/LinkedBlockingQueue;
  #15 = Utf8               Ljava/util/concurrent/LinkedBlockingQueue<Ljava/lang/Object;>;
  #16 = Utf8               isAlive
  #17 = Utf8               ()Z
  #18 = NameAndType        #11:#12        // thread:Ljava/lang/Thread;
  #19 = Fieldref           #2.#18         // scala/sys/process/ProcessImpl$ThreadProcess.thread:Ljava/lang/Thread;
  #20 = Utf8               java/lang/Thread
  #21 = Class              #20            // java/lang/Thread
  #22 = NameAndType        #16:#17        // isAlive:()Z
  #23 = Methodref          #21.#22        // java/lang/Thread.isAlive:()Z
  #24 = Utf8               this
  #25 = Utf8               Lscala/sys/process/ProcessImpl$ThreadProcess;
  #26 = Utf8               exitValue
  #27 = Utf8               ()I
  #28 = NameAndType        #13:#14        // success:Ljava/util/concurrent/LinkedBlockingQueue;
  #29 = Fieldref           #2.#28         // scala/sys/process/ProcessImpl$ThreadProcess.success:Ljava/util/concurrent/LinkedBlockingQueue;
  #30 = Utf8               java/util/concurrent/LinkedBlockingQueue
  #31 = Class              #30            // java/util/concurrent/LinkedBlockingQueue
  #32 = Utf8               take
  #33 = Utf8               ()Ljava/lang/Object;
  #34 = NameAndType        #32:#33        // take:()Ljava/lang/Object;
  #35 = Methodref          #31.#34        // java/util/concurrent/LinkedBlockingQueue.take:()Ljava/lang/Object;
  #36 = Utf8               scala/runtime/BoxesRunTime
  #37 = Class              #36            // scala/runtime/BoxesRunTime
  #38 = Utf8               unboxToBoolean
  #39 = Utf8               (Ljava/lang/Object;)Z
  #40 = NameAndType        #38:#39        // unboxToBoolean:(Ljava/lang/Object;)Z
  #41 = Methodref          #37.#40        // scala/runtime/BoxesRunTime.unboxToBoolean:(Ljava/lang/Object;)Z
  #42 = Utf8               destroy
  #43 = Utf8               ()V
  #44 = Utf8               interrupt
  #45 = NameAndType        #44:#43        // interrupt:()V
  #46 = Methodref          #21.#45        // java/lang/Thread.interrupt:()V
  #47 = Utf8               <init>
  #48 = Utf8               (Lscala/sys/process/Process$;Ljava/lang/Thread;Ljava/util/concurrent/LinkedBlockingQueue;)V
  #49 = Utf8               (Ljava/lang/Thread;Ljava/util/concurrent/LinkedBlockingQueue<Ljava/lang/Object;>;)V
  #50 = Utf8               $outer
  #51 = NameAndType        #47:#43        // "<init>":()V
  #52 = Methodref          #4.#51         // java/lang/Object."<init>":()V
  #53 = Utf8               Lscala/sys/process/Process$;
  #54 = Utf8               Signature
  #55 = Utf8               Code
  #56 = Utf8               LineNumberTable
  #57 = Utf8               LocalVariableTable
  #58 = Utf8               StackMapTable
  #59 = Utf8               MethodParameters
  #60 = Utf8               InnerClasses
  #61 = Utf8               SourceFile
  #62 = Utf8               ScalaInlineInfo
  #63 = Utf8               Scala
{
  private final java.lang.Thread thread;
    descriptor: Ljava/lang/Thread;
    flags: (0x0012) ACC_PRIVATE, ACC_FINAL

  private final java.util.concurrent.LinkedBlockingQueue<java.lang.Object> success;
    descriptor: Ljava/util/concurrent/LinkedBlockingQueue;
    flags: (0x0012) ACC_PRIVATE, ACC_FINAL
    Signature: #15                          // Ljava/util/concurrent/LinkedBlockingQueue<Ljava/lang/Object;>;

  public boolean isAlive();
    descriptor: ()Z
    flags: (0x0001) ACC_PUBLIC
    Code:
      stack=1, locals=1, args_size=1
         0: aload_0
         1: getfield      #19                 // Field thread:Ljava/lang/Thread;
         4: invokevirtual #23                 // Method java/lang/Thread.isAlive:()Z
         7: ireturn
      LineNumberTable:
        line 283: 0
      LocalVariableTable:
        Start  Length  Slot  Name   Signature
            0       8     0  this   Lscala/sys/process/ProcessImpl$ThreadProcess;

  public int exitValue();
    descriptor: ()I
    flags: (0x0001) ACC_PUBLIC
    Code:
      stack=1, locals=1, args_size=1
         0: aload_0
         1: getfield      #29                 // Field success:Ljava/util/concurrent/LinkedBlockingQueue;
         4: invokevirtual #35                 // Method java/util/concurrent/LinkedBlockingQueue.take:()Ljava/lang/Object;
         7: invokestatic  #41                 // Method scala/runtime/BoxesRunTime.unboxToBoolean:(Ljava/lang/Object;)Z
        10: ifeq          15
        13: iconst_0
        14: ireturn
        15: iconst_1
        16: ireturn
      StackMapTable: number_of_entries = 1
        frame_type = 15 /* same */
      LineNumberTable:
        line 284: 0
      LocalVariableTable:
        Start  Length  Slot  Name   Signature
            0      17     0  this   Lscala/sys/process/ProcessImpl$ThreadProcess;

  public void destroy();
    descriptor: ()V
    flags: (0x0001) ACC_PUBLIC
    Code:
      stack=1, locals=1, args_size=1
         0: aload_0
         1: getfield      #19                 // Field thread:Ljava/lang/Thread;
         4: invokevirtual #46                 // Method java/lang/Thread.interrupt:()V
         7: return
      LineNumberTable:
        line 285: 0
      LocalVariableTable:
        Start  Length  Slot  Name   Signature
            0       8     0  this   Lscala/sys/process/ProcessImpl$ThreadProcess;

  public scala.sys.process.ProcessImpl$ThreadProcess(java.lang.Thread, java.util.concurrent.LinkedBlockingQueue<java.lang.Object>);
    descriptor: (Lscala/sys/process/Process$;Ljava/lang/Thread;Ljava/util/concurrent/LinkedBlockingQueue;)V
    flags: (0x0001) ACC_PUBLIC
    Code:
      stack=2, locals=4, args_size=4
         0: aload_0
         1: aload_2
         2: putfield      #19                 // Field thread:Ljava/lang/Thread;
         5: aload_0
         6: aload_3
         7: putfield      #29                 // Field success:Ljava/util/concurrent/LinkedBlockingQueue;
        10: aload_0
        11: invokespecial #52                 // Method java/lang/Object."<init>":()V
        14: return
      LineNumberTable:
        line 282: 0
      LocalVariableTable:
        Start  Length  Slot  Name   Signature
            0      15     0  this   Lscala/sys/process/ProcessImpl$ThreadProcess;
            0      15     1 $outer   Lscala/sys/process/Process$;
            0      15     2 thread   Ljava/lang/Thread;
            0      15     3 success   Ljava/util/concurrent/LinkedBlockingQueue;
    Signature: #49                          // (Ljava/lang/Thread;Ljava/util/concurrent/LinkedBlockingQueue<Ljava/lang/Object;>;)V
    MethodParameters:
      Name                           Flags
      $outer                         final synthetic
      thread                         final
      success                        final
}
InnerClasses:
  public final #10= #2 of #9;             // ThreadProcess=class scala/sys/process/ProcessImpl$ThreadProcess of class scala/sys/process/ProcessImpl
SourceFile: "ProcessImpl.scala"
  ScalaInlineInfo: length = 0x18 (unknown attribute)
   01 01 00 04 00 2F 00 30 01 00 2A 00 2B 01 00 1A
   00 1B 01 00 10 00 11 01
  Scala: length = 0x0 (unknown attribute)

