Classfile /Users/mw/Projects/slang-braindump/.jar/jar11/assemble/slang-braindump/assemble/content/scala/sys/process/Process.class
  Last modified May 29, 2022; size 7612 bytes
  SHA-256 checksum 5734e41e589fa180c1a6d8624f75d6cd815068e545a8a7b87f84063b3542bf8d
  Compiled from "Process.scala"
public interface scala.sys.process.Process
  minor version: 0
  major version: 52
  flags: (0x0601) ACC_PUBLIC, ACC_INTERFACE, ACC_ABSTRACT
  this_class: #2                          // scala/sys/process/Process
  super_class: #4                         // java/lang/Object
  interfaces: 0, fields: 0, methods: 18, attributes: 5
Constant pool:
    #1 = Utf8               scala/sys/process/Process
    #2 = Class              #1            // scala/sys/process/Process
    #3 = Utf8               java/lang/Object
    #4 = Class              #3            // java/lang/Object
    #5 = Utf8               Process.scala
    #6 = Utf8               Lscala/reflect/ScalaSignature;
    #7 = Utf8               bytes
    #8 = Utf8               \u0006\u0005=2qa\u0002\u0005\u0011\u0002G\u0005q\u0002C\u0003\u0015\u0001\u0019\u0005Q\u0003C\u0003\u001a\u0001\u0019\u0005!\u0004C\u0003\u001f\u0001\u0019\u0005qdB\u0003$\u0011!\u0005AEB\u0003\b\u0011!\u0005a\u0005C\u0003.\u000b\u0011\u0005aFA\u0004Qe>\u001cWm]:\u000b\u0005%Q\u0011a\u00029s_\u000e,7o\u001d\u0006\u0003\u00171\t1a]=t\u0015\u0005i\u0011!B:dC2\f7\u0001A\n\u0003\u0001A\u0001\"!\u0005\n\u000e\u00031I!a\u0005\u0007\u0003\r\u0005s\u0017PU3g\u0003\u001dI7/\u00117jm\u0016$\u0012A\u0006\t\u0003#]I!\u0001\u0007\u0007\u0003\u000f\t{w\u000e\\3b]\u0006IQ\r_5u-\u0006dW/\u001a\u000b\u00027A\u0011\u0011\u0003H\u0005\u0003;1\u00111!\u00138u\u0003\u001d!Wm\u001d;s_f$\u0012\u0001\t\t\u0003#\u0005J!A\t\u0007\u0003\tUs\u0017\u000e^\u0001\b!J|7-Z:t!\t)S!D\u0001\t\'\u0011)\u0001c\n\u0016\u0011\u0005\u0015B\u0013BA\u0015\t\u0005-\u0001&o\\2fgNLU\u000e\u001d7\u0011\u0005\u0015Z\u0013B\u0001\u0017\t\u0005=\u0001&o\\2fgN\u001c%/Z1uS>t\u0017A\u0002\u001fj]&$h\bF\u0001%\u0001
    #9 = Utf8               scala/sys/process/ProcessBuilder$FileBuilder
   #10 = Class              #9            // scala/sys/process/ProcessBuilder$FileBuilder
   #11 = Utf8               scala/sys/process/ProcessBuilder
   #12 = Class              #11           // scala/sys/process/ProcessBuilder
   #13 = Utf8               FileBuilder
   #14 = Utf8               scala/sys/process/ProcessBuilder$Source
   #15 = Class              #14           // scala/sys/process/ProcessBuilder$Source
   #16 = Utf8               Source
   #17 = Utf8               scala/sys/process/ProcessBuilder$URLBuilder
   #18 = Class              #17           // scala/sys/process/ProcessBuilder$URLBuilder
   #19 = Utf8               URLBuilder
   #20 = Utf8               scala/sys/process/ProcessBuilderImpl$Dummy
   #21 = Class              #20           // scala/sys/process/ProcessBuilderImpl$Dummy
   #22 = Utf8               scala/sys/process/ProcessBuilderImpl
   #23 = Class              #22           // scala/sys/process/ProcessBuilderImpl
   #24 = Utf8               Dummy
   #25 = Utf8               scala/sys/process/ProcessBuilderImpl$FileImpl
   #26 = Class              #25           // scala/sys/process/ProcessBuilderImpl$FileImpl
   #27 = Utf8               FileImpl
   #28 = Utf8               scala/sys/process/ProcessBuilderImpl$Simple
   #29 = Class              #28           // scala/sys/process/ProcessBuilderImpl$Simple
   #30 = Utf8               Simple
   #31 = Utf8               scala/sys/process/ProcessBuilderImpl$URLImpl
   #32 = Class              #31           // scala/sys/process/ProcessBuilderImpl$URLImpl
   #33 = Utf8               URLImpl
   #34 = Utf8               cat
   #35 = Utf8               (Lscala/collection/Seq;)Lscala/sys/process/ProcessBuilder;
   #36 = Utf8               (Lscala/collection/Seq<Lscala/sys/process/ProcessBuilder$Source;>;)Lscala/sys/process/ProcessBuilder;
   #37 = Utf8               files
   #38 = Utf8               scala/sys/process/Process$
   #39 = Class              #38           // scala/sys/process/Process$
   #40 = Utf8               MODULE$
   #41 = Utf8               Lscala/sys/process/Process$;
   #42 = NameAndType        #40:#41       // MODULE$:Lscala/sys/process/Process$;
   #43 = Fieldref           #39.#42       // scala/sys/process/Process$.MODULE$:Lscala/sys/process/Process$;
   #44 = Utf8               scala/sys/process/ProcessCreation
   #45 = Class              #44           // scala/sys/process/ProcessCreation
   #46 = Utf8               cat$
   #47 = Utf8               (Lscala/sys/process/ProcessCreation;Lscala/collection/Seq;)Lscala/sys/process/ProcessBuilder;
   #48 = NameAndType        #46:#47       // cat$:(Lscala/sys/process/ProcessCreation;Lscala/collection/Seq;)Lscala/sys/process/ProcessBuilder;
   #49 = InterfaceMethodref #45.#48       // scala/sys/process/ProcessCreation.cat$:(Lscala/sys/process/ProcessCreation;Lscala/collection/Seq;)Lscala/sys/process/ProcessBuilder;
   #50 = Utf8               Lscala/collection/Seq;
   #51 = Utf8               (Lscala/sys/process/ProcessBuilder$Source;Lscala/collection/immutable/Seq;)Lscala/sys/process/ProcessBuilder;
   #52 = Utf8               (Lscala/sys/process/ProcessBuilder$Source;Lscala/collection/immutable/Seq<Lscala/sys/process/ProcessBuilder$Source;>;)Lscala/sys/process/ProcessBuilder;
   #53 = Utf8               file
   #54 = Utf8               (Lscala/sys/process/ProcessCreation;Lscala/sys/process/ProcessBuilder$Source;Lscala/collection/immutable/Seq;)Lscala/sys/process/ProcessBuilder;
   #55 = NameAndType        #46:#54       // cat$:(Lscala/sys/process/ProcessCreation;Lscala/sys/process/ProcessBuilder$Source;Lscala/collection/immutable/Seq;)Lscala/sys/process/ProcessBuilder;
   #56 = InterfaceMethodref #45.#55       // scala/sys/process/ProcessCreation.cat$:(Lscala/sys/process/ProcessCreation;Lscala/sys/process/ProcessBuilder$Source;Lscala/collection/immutable/Seq;)Lscala/sys/process/ProcessBuilder;
   #57 = Utf8               Lscala/sys/process/ProcessBuilder$Source;
   #58 = Utf8               Lscala/collection/immutable/Seq;
   #59 = Utf8               applySeq
   #60 = Utf8               (Lscala/collection/Seq;Lscala/Function1;)Lscala/collection/Seq;
   #61 = Utf8               <T:Ljava/lang/Object;>(Lscala/collection/Seq<TT;>;Lscala/Function1<TT;Lscala/sys/process/ProcessBuilder$Source;>;)Lscala/collection/Seq<Lscala/sys/process/ProcessBuilder$Source;>;
   #62 = Utf8               builders
   #63 = Utf8               convert
   #64 = Utf8               scala/collection/Seq
   #65 = Class              #64           // scala/collection/Seq
   #66 = Utf8               map
   #67 = Utf8               (Lscala/Function1;)Ljava/lang/Object;
   #68 = NameAndType        #66:#67       // map:(Lscala/Function1;)Ljava/lang/Object;
   #69 = InterfaceMethodref #65.#68       // scala/collection/Seq.map:(Lscala/Function1;)Ljava/lang/Object;
   #70 = Utf8               Lscala/Function1;
   #71 = Utf8               apply
   #72 = Utf8               (Ljava/lang/String;Lscala/Function0;)Lscala/sys/process/ProcessBuilder;
   #73 = Utf8               (Ljava/lang/String;Lscala/Function0<Ljava/lang/Object;>;)Lscala/sys/process/ProcessBuilder;
   #74 = Utf8               name
   #75 = Utf8               exitValue
   #76 = Utf8               scala/sys/process/ProcessBuilder$
   #77 = Class              #76           // scala/sys/process/ProcessBuilder$
   #78 = Utf8               Lscala/sys/process/ProcessBuilder$;
   #79 = NameAndType        #40:#78       // MODULE$:Lscala/sys/process/ProcessBuilder$;
   #80 = Fieldref           #77.#79       // scala/sys/process/ProcessBuilder$.MODULE$:Lscala/sys/process/ProcessBuilder$;
   #81 = Utf8               <init>
   #82 = Utf8               (Lscala/sys/process/ProcessBuilder$;Ljava/lang/String;Lscala/Function0;)V
   #83 = NameAndType        #81:#82       // "<init>":(Lscala/sys/process/ProcessBuilder$;Ljava/lang/String;Lscala/Function0;)V
   #84 = Methodref          #21.#83       // scala/sys/process/ProcessBuilderImpl$Dummy."<init>":(Lscala/sys/process/ProcessBuilder$;Ljava/lang/String;Lscala/Function0;)V
   #85 = Utf8               Ljava/lang/String;
   #86 = Utf8               Lscala/Function0;
   #87 = Utf8               (Z)Lscala/sys/process/ProcessBuilder;
   #88 = Utf8               value
   #89 = Utf8               apply$
   #90 = Utf8               (Lscala/sys/process/ProcessCreation;Z)Lscala/sys/process/ProcessBuilder;
   #91 = NameAndType        #89:#90       // apply$:(Lscala/sys/process/ProcessCreation;Z)Lscala/sys/process/ProcessBuilder;
   #92 = InterfaceMethodref #45.#91       // scala/sys/process/ProcessCreation.apply$:(Lscala/sys/process/ProcessCreation;Z)Lscala/sys/process/ProcessBuilder;
   #93 = Utf8               Z
   #94 = Utf8               (Ljava/net/URL;)Lscala/sys/process/ProcessBuilder$URLBuilder;
   #95 = Utf8               url
   #96 = Utf8               (Lscala/sys/process/ProcessBuilder$;Ljava/net/URL;)V
   #97 = NameAndType        #81:#96       // "<init>":(Lscala/sys/process/ProcessBuilder$;Ljava/net/URL;)V
   #98 = Methodref          #32.#97       // scala/sys/process/ProcessBuilderImpl$URLImpl."<init>":(Lscala/sys/process/ProcessBuilder$;Ljava/net/URL;)V
   #99 = Utf8               Ljava/net/URL;
  #100 = Utf8               (Ljava/io/File;)Lscala/sys/process/ProcessBuilder$FileBuilder;
  #101 = Utf8               (Lscala/sys/process/ProcessBuilder$;Ljava/io/File;)V
  #102 = NameAndType        #81:#101      // "<init>":(Lscala/sys/process/ProcessBuilder$;Ljava/io/File;)V
  #103 = Methodref          #26.#102      // scala/sys/process/ProcessBuilderImpl$FileImpl."<init>":(Lscala/sys/process/ProcessBuilder$;Ljava/io/File;)V
  #104 = Utf8               Ljava/io/File;
  #105 = Utf8               (Ljava/lang/ProcessBuilder;)Lscala/sys/process/ProcessBuilder;
  #106 = Utf8               builder
  #107 = Utf8               (Lscala/sys/process/ProcessBuilder$;Ljava/lang/ProcessBuilder;)V
  #108 = NameAndType        #81:#107      // "<init>":(Lscala/sys/process/ProcessBuilder$;Ljava/lang/ProcessBuilder;)V
  #109 = Methodref          #29.#108      // scala/sys/process/ProcessBuilderImpl$Simple."<init>":(Lscala/sys/process/ProcessBuilder$;Ljava/lang/ProcessBuilder;)V
  #110 = Utf8               Ljava/lang/ProcessBuilder;
  #111 = Utf8               (Lscala/collection/Seq;Lscala/Option;Lscala/collection/immutable/Seq;)Lscala/sys/process/ProcessBuilder;
  #112 = Utf8               (Lscala/collection/Seq<Ljava/lang/String;>;Lscala/Option<Ljava/io/File;>;Lscala/collection/immutable/Seq<Lscala/Tuple2<Ljava/lang/String;Ljava/lang/String;>;>;)Lscala/sys/process/ProcessBuilder;
  #113 = Utf8               command
  #114 = Utf8               cwd
  #115 = Utf8               extraEnv
  #116 = Utf8               (Lscala/sys/process/ProcessCreation;Lscala/collection/Seq;Lscala/Option;Lscala/collection/immutable/Seq;)Lscala/sys/process/ProcessBuilder;
  #117 = NameAndType        #89:#116      // apply$:(Lscala/sys/process/ProcessCreation;Lscala/collection/Seq;Lscala/Option;Lscala/collection/immutable/Seq;)Lscala/sys/process/ProcessBuilder;
  #118 = InterfaceMethodref #45.#117      // scala/sys/process/ProcessCreation.apply$:(Lscala/sys/process/ProcessCreation;Lscala/collection/Seq;Lscala/Option;Lscala/collection/immutable/Seq;)Lscala/sys/process/ProcessBuilder;
  #119 = Utf8               Lscala/Option;
  #120 = Utf8               (Ljava/lang/String;Lscala/Option;Lscala/collection/immutable/Seq;)Lscala/sys/process/ProcessBuilder;
  #121 = Utf8               (Ljava/lang/String;Lscala/Option<Ljava/io/File;>;Lscala/collection/immutable/Seq<Lscala/Tuple2<Ljava/lang/String;Ljava/lang/String;>;>;)Lscala/sys/process/ProcessBuilder;
  #122 = Utf8               (Lscala/sys/process/ProcessCreation;Ljava/lang/String;Lscala/Option;Lscala/collection/immutable/Seq;)Lscala/sys/process/ProcessBuilder;
  #123 = NameAndType        #89:#122      // apply$:(Lscala/sys/process/ProcessCreation;Ljava/lang/String;Lscala/Option;Lscala/collection/immutable/Seq;)Lscala/sys/process/ProcessBuilder;
  #124 = InterfaceMethodref #45.#123      // scala/sys/process/ProcessCreation.apply$:(Lscala/sys/process/ProcessCreation;Ljava/lang/String;Lscala/Option;Lscala/collection/immutable/Seq;)Lscala/sys/process/ProcessBuilder;
  #125 = Utf8               (Lscala/collection/Seq;Ljava/io/File;Lscala/collection/immutable/Seq;)Lscala/sys/process/ProcessBuilder;
  #126 = Utf8               (Lscala/collection/Seq<Ljava/lang/String;>;Ljava/io/File;Lscala/collection/immutable/Seq<Lscala/Tuple2<Ljava/lang/String;Ljava/lang/String;>;>;)Lscala/sys/process/ProcessBuilder;
  #127 = Utf8               (Lscala/sys/process/ProcessCreation;Lscala/collection/Seq;Ljava/io/File;Lscala/collection/immutable/Seq;)Lscala/sys/process/ProcessBuilder;
  #128 = NameAndType        #89:#127      // apply$:(Lscala/sys/process/ProcessCreation;Lscala/collection/Seq;Ljava/io/File;Lscala/collection/immutable/Seq;)Lscala/sys/process/ProcessBuilder;
  #129 = InterfaceMethodref #45.#128      // scala/sys/process/ProcessCreation.apply$:(Lscala/sys/process/ProcessCreation;Lscala/collection/Seq;Ljava/io/File;Lscala/collection/immutable/Seq;)Lscala/sys/process/ProcessBuilder;
  #130 = Utf8               (Ljava/lang/String;Ljava/io/File;Lscala/collection/immutable/Seq;)Lscala/sys/process/ProcessBuilder;
  #131 = Utf8               (Ljava/lang/String;Ljava/io/File;Lscala/collection/immutable/Seq<Lscala/Tuple2<Ljava/lang/String;Ljava/lang/String;>;>;)Lscala/sys/process/ProcessBuilder;
  #132 = Utf8               (Lscala/sys/process/ProcessCreation;Ljava/lang/String;Ljava/io/File;Lscala/collection/immutable/Seq;)Lscala/sys/process/ProcessBuilder;
  #133 = NameAndType        #89:#132      // apply$:(Lscala/sys/process/ProcessCreation;Ljava/lang/String;Ljava/io/File;Lscala/collection/immutable/Seq;)Lscala/sys/process/ProcessBuilder;
  #134 = InterfaceMethodref #45.#133      // scala/sys/process/ProcessCreation.apply$:(Lscala/sys/process/ProcessCreation;Ljava/lang/String;Ljava/io/File;Lscala/collection/immutable/Seq;)Lscala/sys/process/ProcessBuilder;
  #135 = Utf8               (Ljava/lang/String;Lscala/collection/Seq;)Lscala/sys/process/ProcessBuilder;
  #136 = Utf8               (Ljava/lang/String;Lscala/collection/Seq<Ljava/lang/String;>;)Lscala/sys/process/ProcessBuilder;
  #137 = Utf8               arguments
  #138 = Utf8               (Lscala/sys/process/ProcessCreation;Ljava/lang/String;Lscala/collection/Seq;)Lscala/sys/process/ProcessBuilder;
  #139 = NameAndType        #89:#138      // apply$:(Lscala/sys/process/ProcessCreation;Ljava/lang/String;Lscala/collection/Seq;)Lscala/sys/process/ProcessBuilder;
  #140 = InterfaceMethodref #45.#139      // scala/sys/process/ProcessCreation.apply$:(Lscala/sys/process/ProcessCreation;Ljava/lang/String;Lscala/collection/Seq;)Lscala/sys/process/ProcessBuilder;
  #141 = Utf8               (Lscala/collection/Seq<Ljava/lang/String;>;)Lscala/sys/process/ProcessBuilder;
  #142 = Utf8               scala/None$
  #143 = Class              #142          // scala/None$
  #144 = Utf8               Lscala/None$;
  #145 = NameAndType        #40:#144      // MODULE$:Lscala/None$;
  #146 = Fieldref           #143.#145     // scala/None$.MODULE$:Lscala/None$;
  #147 = Utf8               scala/collection/immutable/Nil$
  #148 = Class              #147          // scala/collection/immutable/Nil$
  #149 = Utf8               Lscala/collection/immutable/Nil$;
  #150 = NameAndType        #40:#149      // MODULE$:Lscala/collection/immutable/Nil$;
  #151 = Fieldref           #148.#150     // scala/collection/immutable/Nil$.MODULE$:Lscala/collection/immutable/Nil$;
  #152 = Utf8               apply_this
  #153 = Utf8               apply_cwd
  #154 = Utf8               apply_extraEnv
  #155 = Utf8               (Ljava/lang/String;)Lscala/sys/process/ProcessBuilder;
  #156 = Utf8               isAlive
  #157 = Utf8               ()Z
  #158 = Utf8               ()I
  #159 = Utf8               destroy
  #160 = Utf8               ()V
  #161 = Utf8               Code
  #162 = Utf8               LineNumberTable
  #163 = Utf8               LocalVariableTable
  #164 = Utf8               Signature
  #165 = Utf8               MethodParameters
  #166 = Utf8               InnerClasses
  #167 = Utf8               SourceFile
  #168 = Utf8               RuntimeVisibleAnnotations
  #169 = Utf8               ScalaInlineInfo
  #170 = Utf8               ScalaSig
{
  public static scala.sys.process.ProcessBuilder cat(scala.collection.Seq<scala.sys.process.ProcessBuilder$Source>);
    descriptor: (Lscala/collection/Seq;)Lscala/sys/process/ProcessBuilder;
    flags: (0x0009) ACC_PUBLIC, ACC_STATIC
    Code:
      stack=2, locals=1, args_size=1
         0: getstatic     #43                 // Field scala/sys/process/Process$.MODULE$:Lscala/sys/process/Process$;
         3: aload_0
         4: invokestatic  #49                 // InterfaceMethod scala/sys/process/ProcessCreation.cat$:(Lscala/sys/process/ProcessCreation;Lscala/collection/Seq;)Lscala/sys/process/ProcessBuilder;
         7: areturn
      LineNumberTable:
        line 46: 3
      LocalVariableTable:
        Start  Length  Slot  Name   Signature
            0       8     0 files   Lscala/collection/Seq;
    Signature: #36                          // (Lscala/collection/Seq<Lscala/sys/process/ProcessBuilder$Source;>;)Lscala/sys/process/ProcessBuilder;
    MethodParameters:
      Name                           Flags
      files                          final

  public static scala.sys.process.ProcessBuilder cat(scala.sys.process.ProcessBuilder$Source, scala.collection.immutable.Seq<scala.sys.process.ProcessBuilder$Source>);
    descriptor: (Lscala/sys/process/ProcessBuilder$Source;Lscala/collection/immutable/Seq;)Lscala/sys/process/ProcessBuilder;
    flags: (0x0009) ACC_PUBLIC, ACC_STATIC
    Code:
      stack=3, locals=2, args_size=2
         0: getstatic     #43                 // Field scala/sys/process/Process$.MODULE$:Lscala/sys/process/Process$;
         3: aload_0
         4: aload_1
         5: invokestatic  #56                 // InterfaceMethod scala/sys/process/ProcessCreation.cat$:(Lscala/sys/process/ProcessCreation;Lscala/sys/process/ProcessBuilder$Source;Lscala/collection/immutable/Seq;)Lscala/sys/process/ProcessBuilder;
         8: areturn
      LineNumberTable:
        line 46: 3
      LocalVariableTable:
        Start  Length  Slot  Name   Signature
            0       9     0  file   Lscala/sys/process/ProcessBuilder$Source;
            0       9     1 files   Lscala/collection/immutable/Seq;
    Signature: #52                          // (Lscala/sys/process/ProcessBuilder$Source;Lscala/collection/immutable/Seq<Lscala/sys/process/ProcessBuilder$Source;>;)Lscala/sys/process/ProcessBuilder;
    MethodParameters:
      Name                           Flags
      file                           final
      files                          final

  public static <T extends java.lang.Object> scala.collection.Seq<scala.sys.process.ProcessBuilder$Source> applySeq(scala.collection.Seq<T>, scala.Function1<T, scala.sys.process.ProcessBuilder$Source>);
    descriptor: (Lscala/collection/Seq;Lscala/Function1;)Lscala/collection/Seq;
    flags: (0x0009) ACC_PUBLIC, ACC_STATIC
    Code:
      stack=2, locals=2, args_size=2
         0: getstatic     #43                 // Field scala/sys/process/Process$.MODULE$:Lscala/sys/process/Process$;
         3: pop
         4: aload_0
         5: aload_1
         6: invokeinterface #69,  2           // InterfaceMethod scala/collection/Seq.map:(Lscala/Function1;)Ljava/lang/Object;
        11: checkcast     #65                 // class scala/collection/Seq
        14: areturn
      LineNumberTable:
        line 143: 4
        line 46: 14
      LocalVariableTable:
        Start  Length  Slot  Name   Signature
            0      15     0 builders   Lscala/collection/Seq;
            0      15     1 convert   Lscala/Function1;
    Signature: #61                          // <T:Ljava/lang/Object;>(Lscala/collection/Seq<TT;>;Lscala/Function1<TT;Lscala/sys/process/ProcessBuilder$Source;>;)Lscala/collection/Seq<Lscala/sys/process/ProcessBuilder$Source;>;
    MethodParameters:
      Name                           Flags
      builders                       final
      convert                        final

  public static scala.sys.process.ProcessBuilder apply(java.lang.String, scala.Function0<java.lang.Object>);
    descriptor: (Ljava/lang/String;Lscala/Function0;)Lscala/sys/process/ProcessBuilder;
    flags: (0x0009) ACC_PUBLIC, ACC_STATIC
    Code:
      stack=5, locals=2, args_size=2
         0: getstatic     #43                 // Field scala/sys/process/Process$.MODULE$:Lscala/sys/process/Process$;
         3: pop
         4: new           #21                 // class scala/sys/process/ProcessBuilderImpl$Dummy
         7: dup
         8: getstatic     #80                 // Field scala/sys/process/ProcessBuilder$.MODULE$:Lscala/sys/process/ProcessBuilder$;
        11: aload_0
        12: aload_1
        13: invokespecial #84                 // Method scala/sys/process/ProcessBuilderImpl$Dummy."<init>":(Lscala/sys/process/ProcessBuilder$;Ljava/lang/String;Lscala/Function0;)V
        16: areturn
      LineNumberTable:
        line 138: 4
        line 46: 16
      LocalVariableTable:
        Start  Length  Slot  Name   Signature
            0      17     0  name   Ljava/lang/String;
            0      17     1 exitValue   Lscala/Function0;
    Signature: #73                          // (Ljava/lang/String;Lscala/Function0<Ljava/lang/Object;>;)Lscala/sys/process/ProcessBuilder;
    MethodParameters:
      Name                           Flags
      name                           final
      exitValue                      final

  public static scala.sys.process.ProcessBuilder apply(boolean);
    descriptor: (Z)Lscala/sys/process/ProcessBuilder;
    flags: (0x0009) ACC_PUBLIC, ACC_STATIC
    Code:
      stack=2, locals=1, args_size=1
         0: getstatic     #43                 // Field scala/sys/process/Process$.MODULE$:Lscala/sys/process/Process$;
         3: iload_0
         4: invokestatic  #92                 // InterfaceMethod scala/sys/process/ProcessCreation.apply$:(Lscala/sys/process/ProcessCreation;Z)Lscala/sys/process/ProcessBuilder;
         7: areturn
      LineNumberTable:
        line 46: 3
      LocalVariableTable:
        Start  Length  Slot  Name   Signature
            0       8     0 value   Z
    MethodParameters:
      Name                           Flags
      value                          final

  public static scala.sys.process.ProcessBuilder$URLBuilder apply(java.net.URL);
    descriptor: (Ljava/net/URL;)Lscala/sys/process/ProcessBuilder$URLBuilder;
    flags: (0x0009) ACC_PUBLIC, ACC_STATIC
    Code:
      stack=4, locals=1, args_size=1
         0: getstatic     #43                 // Field scala/sys/process/Process$.MODULE$:Lscala/sys/process/Process$;
         3: pop
         4: new           #32                 // class scala/sys/process/ProcessBuilderImpl$URLImpl
         7: dup
         8: getstatic     #80                 // Field scala/sys/process/ProcessBuilder$.MODULE$:Lscala/sys/process/ProcessBuilder$;
        11: aload_0
        12: invokespecial #98                 // Method scala/sys/process/ProcessBuilderImpl$URLImpl."<init>":(Lscala/sys/process/ProcessBuilder$;Ljava/net/URL;)V
        15: areturn
      LineNumberTable:
        line 127: 4
        line 46: 15
      LocalVariableTable:
        Start  Length  Slot  Name   Signature
            0      16     0   url   Ljava/net/URL;
    MethodParameters:
      Name                           Flags
      url                            final

  public static scala.sys.process.ProcessBuilder$FileBuilder apply(java.io.File);
    descriptor: (Ljava/io/File;)Lscala/sys/process/ProcessBuilder$FileBuilder;
    flags: (0x0009) ACC_PUBLIC, ACC_STATIC
    Code:
      stack=4, locals=1, args_size=1
         0: getstatic     #43                 // Field scala/sys/process/Process$.MODULE$:Lscala/sys/process/Process$;
         3: pop
         4: new           #26                 // class scala/sys/process/ProcessBuilderImpl$FileImpl
         7: dup
         8: getstatic     #80                 // Field scala/sys/process/ProcessBuilder$.MODULE$:Lscala/sys/process/ProcessBuilder$;
        11: aload_0
        12: invokespecial #103                // Method scala/sys/process/ProcessBuilderImpl$FileImpl."<init>":(Lscala/sys/process/ProcessBuilder$;Ljava/io/File;)V
        15: areturn
      LineNumberTable:
        line 121: 4
        line 46: 15
      LocalVariableTable:
        Start  Length  Slot  Name   Signature
            0      16     0  file   Ljava/io/File;
    MethodParameters:
      Name                           Flags
      file                           final

  public static scala.sys.process.ProcessBuilder apply(java.lang.ProcessBuilder);
    descriptor: (Ljava/lang/ProcessBuilder;)Lscala/sys/process/ProcessBuilder;
    flags: (0x0009) ACC_PUBLIC, ACC_STATIC
    Code:
      stack=4, locals=1, args_size=1
         0: getstatic     #43                 // Field scala/sys/process/Process$.MODULE$:Lscala/sys/process/Process$;
         3: pop
         4: new           #29                 // class scala/sys/process/ProcessBuilderImpl$Simple
         7: dup
         8: getstatic     #80                 // Field scala/sys/process/ProcessBuilder$.MODULE$:Lscala/sys/process/ProcessBuilder$;
        11: aload_0
        12: invokespecial #109                // Method scala/sys/process/ProcessBuilderImpl$Simple."<init>":(Lscala/sys/process/ProcessBuilder$;Ljava/lang/ProcessBuilder;)V
        15: areturn
      LineNumberTable:
        line 115: 4
        line 46: 15
      LocalVariableTable:
        Start  Length  Slot  Name   Signature
            0      16     0 builder   Ljava/lang/ProcessBuilder;
    MethodParameters:
      Name                           Flags
      builder                        final

  public static scala.sys.process.ProcessBuilder apply(scala.collection.Seq<java.lang.String>, scala.Option<java.io.File>, scala.collection.immutable.Seq<scala.Tuple2<java.lang.String, java.lang.String>>);
    descriptor: (Lscala/collection/Seq;Lscala/Option;Lscala/collection/immutable/Seq;)Lscala/sys/process/ProcessBuilder;
    flags: (0x0009) ACC_PUBLIC, ACC_STATIC
    Code:
      stack=4, locals=3, args_size=3
         0: getstatic     #43                 // Field scala/sys/process/Process$.MODULE$:Lscala/sys/process/Process$;
         3: aload_0
         4: aload_1
         5: aload_2
         6: invokestatic  #118                // InterfaceMethod scala/sys/process/ProcessCreation.apply$:(Lscala/sys/process/ProcessCreation;Lscala/collection/Seq;Lscala/Option;Lscala/collection/immutable/Seq;)Lscala/sys/process/ProcessBuilder;
         9: areturn
      LineNumberTable:
        line 46: 3
      LocalVariableTable:
        Start  Length  Slot  Name   Signature
            0      10     0 command   Lscala/collection/Seq;
            0      10     1   cwd   Lscala/Option;
            0      10     2 extraEnv   Lscala/collection/immutable/Seq;
    Signature: #112                         // (Lscala/collection/Seq<Ljava/lang/String;>;Lscala/Option<Ljava/io/File;>;Lscala/collection/immutable/Seq<Lscala/Tuple2<Ljava/lang/String;Ljava/lang/String;>;>;)Lscala/sys/process/ProcessBuilder;
    MethodParameters:
      Name                           Flags
      command                        final
      cwd                            final
      extraEnv                       final

  public static scala.sys.process.ProcessBuilder apply(java.lang.String, scala.Option<java.io.File>, scala.collection.immutable.Seq<scala.Tuple2<java.lang.String, java.lang.String>>);
    descriptor: (Ljava/lang/String;Lscala/Option;Lscala/collection/immutable/Seq;)Lscala/sys/process/ProcessBuilder;
    flags: (0x0009) ACC_PUBLIC, ACC_STATIC
    Code:
      stack=4, locals=3, args_size=3
         0: getstatic     #43                 // Field scala/sys/process/Process$.MODULE$:Lscala/sys/process/Process$;
         3: aload_0
         4: aload_1
         5: aload_2
         6: invokestatic  #124                // InterfaceMethod scala/sys/process/ProcessCreation.apply$:(Lscala/sys/process/ProcessCreation;Ljava/lang/String;Lscala/Option;Lscala/collection/immutable/Seq;)Lscala/sys/process/ProcessBuilder;
         9: areturn
      LineNumberTable:
        line 46: 3
      LocalVariableTable:
        Start  Length  Slot  Name   Signature
            0      10     0 command   Ljava/lang/String;
            0      10     1   cwd   Lscala/Option;
            0      10     2 extraEnv   Lscala/collection/immutable/Seq;
    Signature: #121                         // (Ljava/lang/String;Lscala/Option<Ljava/io/File;>;Lscala/collection/immutable/Seq<Lscala/Tuple2<Ljava/lang/String;Ljava/lang/String;>;>;)Lscala/sys/process/ProcessBuilder;
    MethodParameters:
      Name                           Flags
      command                        final
      cwd                            final
      extraEnv                       final

  public static scala.sys.process.ProcessBuilder apply(scala.collection.Seq<java.lang.String>, java.io.File, scala.collection.immutable.Seq<scala.Tuple2<java.lang.String, java.lang.String>>);
    descriptor: (Lscala/collection/Seq;Ljava/io/File;Lscala/collection/immutable/Seq;)Lscala/sys/process/ProcessBuilder;
    flags: (0x0009) ACC_PUBLIC, ACC_STATIC
    Code:
      stack=4, locals=3, args_size=3
         0: getstatic     #43                 // Field scala/sys/process/Process$.MODULE$:Lscala/sys/process/Process$;
         3: aload_0
         4: aload_1
         5: aload_2
         6: invokestatic  #129                // InterfaceMethod scala/sys/process/ProcessCreation.apply$:(Lscala/sys/process/ProcessCreation;Lscala/collection/Seq;Ljava/io/File;Lscala/collection/immutable/Seq;)Lscala/sys/process/ProcessBuilder;
         9: areturn
      LineNumberTable:
        line 46: 3
      LocalVariableTable:
        Start  Length  Slot  Name   Signature
            0      10     0 command   Lscala/collection/Seq;
            0      10     1   cwd   Ljava/io/File;
            0      10     2 extraEnv   Lscala/collection/immutable/Seq;
    Signature: #126                         // (Lscala/collection/Seq<Ljava/lang/String;>;Ljava/io/File;Lscala/collection/immutable/Seq<Lscala/Tuple2<Ljava/lang/String;Ljava/lang/String;>;>;)Lscala/sys/process/ProcessBuilder;
    MethodParameters:
      Name                           Flags
      command                        final
      cwd                            final
      extraEnv                       final

  public static scala.sys.process.ProcessBuilder apply(java.lang.String, java.io.File, scala.collection.immutable.Seq<scala.Tuple2<java.lang.String, java.lang.String>>);
    descriptor: (Ljava/lang/String;Ljava/io/File;Lscala/collection/immutable/Seq;)Lscala/sys/process/ProcessBuilder;
    flags: (0x0009) ACC_PUBLIC, ACC_STATIC
    Code:
      stack=4, locals=3, args_size=3
         0: getstatic     #43                 // Field scala/sys/process/Process$.MODULE$:Lscala/sys/process/Process$;
         3: aload_0
         4: aload_1
         5: aload_2
         6: invokestatic  #134                // InterfaceMethod scala/sys/process/ProcessCreation.apply$:(Lscala/sys/process/ProcessCreation;Ljava/lang/String;Ljava/io/File;Lscala/collection/immutable/Seq;)Lscala/sys/process/ProcessBuilder;
         9: areturn
      LineNumberTable:
        line 46: 3
      LocalVariableTable:
        Start  Length  Slot  Name   Signature
            0      10     0 command   Ljava/lang/String;
            0      10     1   cwd   Ljava/io/File;
            0      10     2 extraEnv   Lscala/collection/immutable/Seq;
    Signature: #131                         // (Ljava/lang/String;Ljava/io/File;Lscala/collection/immutable/Seq<Lscala/Tuple2<Ljava/lang/String;Ljava/lang/String;>;>;)Lscala/sys/process/ProcessBuilder;
    MethodParameters:
      Name                           Flags
      command                        final
      cwd                            final
      extraEnv                       final

  public static scala.sys.process.ProcessBuilder apply(java.lang.String, scala.collection.Seq<java.lang.String>);
    descriptor: (Ljava/lang/String;Lscala/collection/Seq;)Lscala/sys/process/ProcessBuilder;
    flags: (0x0009) ACC_PUBLIC, ACC_STATIC
    Code:
      stack=3, locals=2, args_size=2
         0: getstatic     #43                 // Field scala/sys/process/Process$.MODULE$:Lscala/sys/process/Process$;
         3: aload_0
         4: aload_1
         5: invokestatic  #140                // InterfaceMethod scala/sys/process/ProcessCreation.apply$:(Lscala/sys/process/ProcessCreation;Ljava/lang/String;Lscala/collection/Seq;)Lscala/sys/process/ProcessBuilder;
         8: areturn
      LineNumberTable:
        line 46: 3
      LocalVariableTable:
        Start  Length  Slot  Name   Signature
            0       9     0 command   Ljava/lang/String;
            0       9     1 arguments   Lscala/collection/Seq;
    Signature: #136                         // (Ljava/lang/String;Lscala/collection/Seq<Ljava/lang/String;>;)Lscala/sys/process/ProcessBuilder;
    MethodParameters:
      Name                           Flags
      command                        final
      arguments                      final

  public static scala.sys.process.ProcessBuilder apply(scala.collection.Seq<java.lang.String>);
    descriptor: (Lscala/collection/Seq;)Lscala/sys/process/ProcessBuilder;
    flags: (0x0009) ACC_PUBLIC, ACC_STATIC
    Code:
      stack=4, locals=4, args_size=1
         0: getstatic     #43                 // Field scala/sys/process/Process$.MODULE$:Lscala/sys/process/Process$;
         3: astore_1
         4: getstatic     #146                // Field scala/None$.MODULE$:Lscala/None$;
         7: getstatic     #151                // Field scala/collection/immutable/Nil$.MODULE$:Lscala/collection/immutable/Nil$;
        10: astore_3
        11: astore_2
        12: aload_1
        13: aload_0
        14: aload_2
        15: aload_3
        16: invokestatic  #118                // InterfaceMethod scala/sys/process/ProcessCreation.apply$:(Lscala/sys/process/ProcessCreation;Lscala/collection/Seq;Lscala/Option;Lscala/collection/immutable/Seq;)Lscala/sys/process/ProcessBuilder;
        19: areturn
      LineNumberTable:
        line 64: 4
        line 46: 12
        line 46: 19
      LocalVariableTable:
        Start  Length  Slot  Name   Signature
            0      20     0 command   Lscala/collection/Seq;
            4      15     1 apply_this   Lscala/sys/process/Process$;
           12       7     2 apply_cwd   Lscala/Option;
           12       7     3 apply_extraEnv   Lscala/collection/immutable/Seq;
    Signature: #141                         // (Lscala/collection/Seq<Ljava/lang/String;>;)Lscala/sys/process/ProcessBuilder;
    MethodParameters:
      Name                           Flags
      command                        final

  public static scala.sys.process.ProcessBuilder apply(java.lang.String);
    descriptor: (Ljava/lang/String;)Lscala/sys/process/ProcessBuilder;
    flags: (0x0009) ACC_PUBLIC, ACC_STATIC
    Code:
      stack=4, locals=4, args_size=1
         0: getstatic     #43                 // Field scala/sys/process/Process$.MODULE$:Lscala/sys/process/Process$;
         3: astore_1
         4: getstatic     #146                // Field scala/None$.MODULE$:Lscala/None$;
         7: getstatic     #151                // Field scala/collection/immutable/Nil$.MODULE$:Lscala/collection/immutable/Nil$;
        10: astore_3
        11: astore_2
        12: aload_1
        13: aload_0
        14: aload_2
        15: aload_3
        16: invokestatic  #124                // InterfaceMethod scala/sys/process/ProcessCreation.apply$:(Lscala/sys/process/ProcessCreation;Ljava/lang/String;Lscala/Option;Lscala/collection/immutable/Seq;)Lscala/sys/process/ProcessBuilder;
        19: areturn
      LineNumberTable:
        line 57: 4
        line 46: 12
        line 46: 19
      LocalVariableTable:
        Start  Length  Slot  Name   Signature
            0      20     0 command   Ljava/lang/String;
            4      15     1 apply_this   Lscala/sys/process/Process$;
           12       7     2 apply_cwd   Lscala/Option;
           12       7     3 apply_extraEnv   Lscala/collection/immutable/Seq;
    MethodParameters:
      Name                           Flags
      command                        final

  public abstract boolean isAlive();
    descriptor: ()Z
    flags: (0x0401) ACC_PUBLIC, ACC_ABSTRACT

  public abstract int exitValue();
    descriptor: ()I
    flags: (0x0401) ACC_PUBLIC, ACC_ABSTRACT

  public abstract void destroy();
    descriptor: ()V
    flags: (0x0401) ACC_PUBLIC, ACC_ABSTRACT
}
InnerClasses:
  public static #13= #10 of #12;          // FileBuilder=class scala/sys/process/ProcessBuilder$FileBuilder of class scala/sys/process/ProcessBuilder
  public static #16= #15 of #12;          // Source=class scala/sys/process/ProcessBuilder$Source of class scala/sys/process/ProcessBuilder
  public static #19= #18 of #12;          // URLBuilder=class scala/sys/process/ProcessBuilder$URLBuilder of class scala/sys/process/ProcessBuilder
  public #24= #21 of #23;                 // Dummy=class scala/sys/process/ProcessBuilderImpl$Dummy of class scala/sys/process/ProcessBuilderImpl
  public #27= #26 of #23;                 // FileImpl=class scala/sys/process/ProcessBuilderImpl$FileImpl of class scala/sys/process/ProcessBuilderImpl
  public #30= #29 of #23;                 // Simple=class scala/sys/process/ProcessBuilderImpl$Simple of class scala/sys/process/ProcessBuilderImpl
  public #33= #32 of #23;                 // URLImpl=class scala/sys/process/ProcessBuilderImpl$URLImpl of class scala/sys/process/ProcessBuilderImpl
SourceFile: "Process.scala"
RuntimeVisibleAnnotations:
  0: #6(#7=s#8)
    scala.reflect.ScalaSignature(
      bytes="\u0006\u0005=2qa\u0002\u0005\u0011\u0002G\u0005q\u0002C\u0003\u0015\u0001\u0019\u0005Q\u0003C\u0003\u001a\u0001\u0019\u0005!\u0004C\u0003\u001f\u0001\u0019\u0005qdB\u0003$\u0011!\u0005AEB\u0003\b\u0011!\u0005a\u0005C\u0003.\u000b\u0011\u0005aFA\u0004Qe>\u001cWm]:\u000b\u0005%Q\u0011a\u00029s_\u000e,7o\u001d\u0006\u0003\u00171\t1a]=t\u0015\u0005i\u0011!B:dC2\f7\u0001A\n\u0003\u0001A\u0001\"!\u0005\n\u000e\u00031I!a\u0005\u0007\u0003\r\u0005s\u0017PU3g\u0003\u001dI7/\u00117jm\u0016$\u0012A\u0006\t\u0003#]I!\u0001\u0007\u0007\u0003\u000f\t{w\u000e\\3b]\u0006IQ\r_5u-\u0006dW/\u001a\u000b\u00027A\u0011\u0011\u0003H\u0005\u0003;1\u00111!\u00138u\u0003\u001d!Wm\u001d;s_f$\u0012\u0001\t\t\u0003#\u0005J!A\t\u0007\u0003\tUs\u0017\u000e^\u0001\b!J|7-Z:t!\t)S!D\u0001\t\'\u0011)\u0001c\n\u0016\u0011\u0005\u0015B\u0013BA\u0015\t\u0005-\u0001&o\\2fgNLU\u000e\u001d7\u0011\u0005\u0015Z\u0013B\u0001\u0017\t\u0005=\u0001&o\\2fgN\u001c%/Z1uS>t\u0017A\u0002\u001fj]&$h\bF\u0001%\u0001"
    )
  ScalaInlineInfo: length = 0x13 (unknown attribute)
   01 00 00 03 00 9F 00 A0 00 00 4B 00 9E 00 00 9C
   00 9D 00
  ScalaSig: length = 0x3 (unknown attribute)
   05 02 00
