Classfile /Users/mw/Projects/slang-braindump/.jar/jar8/assemble/slang-braindump/assemble/content/org/scalatest/matchers/BePropertyMatcher.class
  Last modified May 29, 2022; size 2135 bytes
  SHA-256 checksum 427863a68ff1976b211424e570946fbe928502da0828df2c544a8d79058488bf
  Compiled from "BePropertyMatcher.scala"
public interface org.scalatest.matchers.BePropertyMatcher<T extends java.lang.Object> extends scala.Function1<T, org.scalatest.matchers.BePropertyMatchResult>
  minor version: 0
  major version: 52
  flags: (0x0601) ACC_PUBLIC, ACC_INTERFACE, ACC_ABSTRACT
  this_class: #2                          // org/scalatest/matchers/BePropertyMatcher
  super_class: #5                         // java/lang/Object
  interfaces: 1, fields: 0, methods: 4, attributes: 6
Constant pool:
   #1 = Utf8               org/scalatest/matchers/BePropertyMatcher
   #2 = Class              #1             // org/scalatest/matchers/BePropertyMatcher
   #3 = Utf8               <T:Ljava/lang/Object;>Ljava/lang/Object;Lscala/Function1<TT;Lorg/scalatest/matchers/BePropertyMatchResult;>;
   #4 = Utf8               java/lang/Object
   #5 = Class              #4             // java/lang/Object
   #6 = Utf8               scala/Function1
   #7 = Class              #6             // scala/Function1
   #8 = Utf8               BePropertyMatcher.scala
   #9 = Utf8               Lscala/reflect/ScalaSignature;
  #10 = Utf8               bytes
  #11 = Utf8               \u0006\u0005M3q\u0001C\u0005\u0011\u0002\u0007\u0005\u0001\u0003C\u0003+\u0001\u0011\u00051\u0006C\u00030\u0001\u0019\u0005\u0001\u0007C\u00034\u0001\u0011\u0005CgB\u0003>\u0013!\u0005aHB\u0003\t\u0013!\u0005q\bC\u0003A\u000b\u0011\u0005\u0011\tC\u00030\u000b\u0011\u0005!IA\tCKB\u0013x\u000e]3sifl\u0015\r^2iKJT!AC\u0006\u0002\u00115\fGo\u00195feNT!\u0001D\u0007\u0002\u0013M\u001c\u0017\r\\1uKN$(\"\u0001\b\u0002\u0007=\u0014xm\u0001\u0001\u0016\u0005Ei2c\u0001\u0001\u00131A\u00111CF\u0007\u0002))\tQ#A\u0003tG\u0006d\u0017-\u0003\u0002\u0018)\t1\u0011I\\=SK\u001a\u0004BaE\r\u001cM%\u0011!\u0004\u0006\u0002\n\rVt7\r^5p]F\u0002\"\u0001H\u000f\r\u0001\u00111a\u0004\u0001EC\u0002}\u0011\u0011\u0001V\t\u0003A\r\u0002\"aE\u0011\n\u0005\t\"\"a\u0002(pi\"Lgn\u001a\t\u0003\'\u0011J!!\n\u000b\u0003\u0007\u0005s\u0017\u0010\u0005\u0002(Q5\t\u0011\"\u0003\u0002*\u0013\t)\")\u001a)s_B,\'\u000f^=NCR\u001c\u0007NU3tk2$\u0018A\u0002\u0013j]&$H\u0005F\u0001-!\t\u0019R&\u0003\u0002/)\t!QK\\5u\u0003\u0015\t\u0007\u000f\u001d7z)\t1\u0013\u0007C\u00033\u0005\u0001\u00071$\u0001\npE*,7\r^,ji\"\u0004&o\u001c9feRL\u0018aB2p[B|7/Z\u000b\u0003ka\"\"A\u000e\u001e\u0011\u0007\u001d\u0002q\u0007\u0005\u0002\u001dq\u0011)\u0011h\u0001b\u0001?\t\tQ\u000bC\u0003<\u0007\u0001\u0007A(A\u0001h!\u0011\u0019\u0012dN\u000e\u0002#\t+\u0007K]8qKJ$\u00180T1uG\",\'\u000f\u0005\u0002(\u000bM\u0011QAE\u0001\u0007y%t\u0017\u000e\u001e \u0015\u0003y*\"aQ$\u0015\u0005\u0011\u0003FCA#I!\r9\u0003A\u0012\t\u00039\u001d#QAH\u0004C\u0002}AQ!S\u0004A\u0004)\u000b!!\u001a<\u0011\u0007-se)D\u0001M\u0015\tiE#A\u0004sK\u001adWm\u0019;\n\u0005=c%\u0001C\"mCN\u001cH+Y4\t\u000bE;\u0001\u0019\u0001*\u0002\u0007\u0019,h\u000e\u0005\u0003\u00143\u00193\u0003
  #12 = Utf8               org/scalatest/matchers/BePropertyMatcher$$anon$1
  #13 = Class              #12            // org/scalatest/matchers/BePropertyMatcher$$anon$1
  #14 = Utf8               apply
  #15 = Utf8               (Ljava/lang/Object;)Lorg/scalatest/matchers/BePropertyMatchResult;
  #16 = Utf8               (TT;)Lorg/scalatest/matchers/BePropertyMatchResult;
  #17 = Utf8               objectWithProperty
  #18 = Utf8               compose$
  #19 = Utf8               (Lorg/scalatest/matchers/BePropertyMatcher;Lscala/Function1;)Lorg/scalatest/matchers/BePropertyMatcher;
  #20 = Utf8               $this
  #21 = Utf8               g
  #22 = Utf8               compose
  #23 = Utf8               (Lscala/Function1;)Lorg/scalatest/matchers/BePropertyMatcher;
  #24 = NameAndType        #22:#23        // compose:(Lscala/Function1;)Lorg/scalatest/matchers/BePropertyMatcher;
  #25 = InterfaceMethodref #2.#24         // org/scalatest/matchers/BePropertyMatcher.compose:(Lscala/Function1;)Lorg/scalatest/matchers/BePropertyMatcher;
  #26 = Utf8               Lorg/scalatest/matchers/BePropertyMatcher;
  #27 = Utf8               Lscala/Function1;
  #28 = Utf8               <U:Ljava/lang/Object;>(Lscala/Function1<TU;TT;>;)Lorg/scalatest/matchers/BePropertyMatcher<TU;>;
  #29 = Utf8               <init>
  #30 = Utf8               (Lorg/scalatest/matchers/BePropertyMatcher;Lscala/Function1;)V
  #31 = NameAndType        #29:#30        // "<init>":(Lorg/scalatest/matchers/BePropertyMatcher;Lscala/Function1;)V
  #32 = Methodref          #13.#31        // org/scalatest/matchers/BePropertyMatcher$$anon$1."<init>":(Lorg/scalatest/matchers/BePropertyMatcher;Lscala/Function1;)V
  #33 = Utf8               this
  #34 = Utf8               $init$
  #35 = Utf8               (Lorg/scalatest/matchers/BePropertyMatcher;)V
  #36 = Utf8               Signature
  #37 = Utf8               MethodParameters
  #38 = Utf8               Code
  #39 = Utf8               LineNumberTable
  #40 = Utf8               LocalVariableTable
  #41 = Utf8               InnerClasses
  #42 = Utf8               SourceFile
  #43 = Utf8               RuntimeVisibleAnnotations
  #44 = Utf8               ScalaInlineInfo
  #45 = Utf8               ScalaSig
{
  public abstract org.scalatest.matchers.BePropertyMatchResult apply(T);
    descriptor: (Ljava/lang/Object;)Lorg/scalatest/matchers/BePropertyMatchResult;
    flags: (0x0401) ACC_PUBLIC, ACC_ABSTRACT
    Signature: #16                          // (TT;)Lorg/scalatest/matchers/BePropertyMatchResult;
    MethodParameters:
      Name                           Flags
      objectWithProperty             final

  public static org.scalatest.matchers.BePropertyMatcher compose$(org.scalatest.matchers.BePropertyMatcher, scala.Function1);
    descriptor: (Lorg/scalatest/matchers/BePropertyMatcher;Lscala/Function1;)Lorg/scalatest/matchers/BePropertyMatcher;
    flags: (0x1009) ACC_PUBLIC, ACC_STATIC, ACC_SYNTHETIC
    Code:
      stack=2, locals=2, args_size=2
         0: aload_0
         1: aload_1
         2: invokespecial #25                 // InterfaceMethod compose:(Lscala/Function1;)Lorg/scalatest/matchers/BePropertyMatcher;
         5: areturn
      LineNumberTable:
        line 146: 0
      LocalVariableTable:
        Start  Length  Slot  Name   Signature
            0       6     0 $this   Lorg/scalatest/matchers/BePropertyMatcher;
            0       6     1     g   Lscala/Function1;
    MethodParameters:
      Name                           Flags
      $this                          final synthetic
      g                              final

  public default <U extends java.lang.Object> org.scalatest.matchers.BePropertyMatcher<U> compose(scala.Function1<U, T>);
    descriptor: (Lscala/Function1;)Lorg/scalatest/matchers/BePropertyMatcher;
    flags: (0x0001) ACC_PUBLIC
    Code:
      stack=4, locals=2, args_size=2
         0: new           #13                 // class org/scalatest/matchers/BePropertyMatcher$$anon$1
         3: dup
         4: aload_0
         5: aload_1
         6: invokespecial #32                 // Method org/scalatest/matchers/BePropertyMatcher$$anon$1."<init>":(Lorg/scalatest/matchers/BePropertyMatcher;Lscala/Function1;)V
         9: areturn
      LineNumberTable:
        line 147: 0
      LocalVariableTable:
        Start  Length  Slot  Name   Signature
            0      10     0  this   Lorg/scalatest/matchers/BePropertyMatcher;
            0      10     1     g   Lscala/Function1;
    Signature: #28                          // <U:Ljava/lang/Object;>(Lscala/Function1<TU;TT;>;)Lorg/scalatest/matchers/BePropertyMatcher<TU;>;
    MethodParameters:
      Name                           Flags
      g                              final

  public static void $init$(org.scalatest.matchers.BePropertyMatcher);
    descriptor: (Lorg/scalatest/matchers/BePropertyMatcher;)V
    flags: (0x0009) ACC_PUBLIC, ACC_STATIC
    Code:
      stack=0, locals=1, args_size=1
         0: return
      LineNumberTable:
        line 118: 0
      LocalVariableTable:
        Start  Length  Slot  Name   Signature
            0       1     0 $this   Lorg/scalatest/matchers/BePropertyMatcher;
    MethodParameters:
      Name                           Flags
      $this                          final synthetic
}
InnerClasses:
  public final #13;                       // class org/scalatest/matchers/BePropertyMatcher$$anon$1
Signature: #3                           // <T:Ljava/lang/Object;>Ljava/lang/Object;Lscala/Function1<TT;Lorg/scalatest/matchers/BePropertyMatchResult;>;
SourceFile: "BePropertyMatcher.scala"
RuntimeVisibleAnnotations:
  0: #9(#10=s#11)
    scala.reflect.ScalaSignature(
      bytes="\u0006\u0005M3q\u0001C\u0005\u0011\u0002\u0007\u0005\u0001\u0003C\u0003+\u0001\u0011\u00051\u0006C\u00030\u0001\u0019\u0005\u0001\u0007C\u00034\u0001\u0011\u0005CgB\u0003>\u0013!\u0005aHB\u0003\t\u0013!\u0005q\bC\u0003A\u000b\u0011\u0005\u0011\tC\u00030\u000b\u0011\u0005!IA\tCKB\u0013x\u000e]3sifl\u0015\r^2iKJT!AC\u0006\u0002\u00115\fGo\u00195feNT!\u0001D\u0007\u0002\u0013M\u001c\u0017\r\\1uKN$(\"\u0001\b\u0002\u0007=\u0014xm\u0001\u0001\u0016\u0005Ei2c\u0001\u0001\u00131A\u00111CF\u0007\u0002))\tQ#A\u0003tG\u0006d\u0017-\u0003\u0002\u0018)\t1\u0011I\\=SK\u001a\u0004BaE\r\u001cM%\u0011!\u0004\u0006\u0002\n\rVt7\r^5p]F\u0002\"\u0001H\u000f\r\u0001\u00111a\u0004\u0001EC\u0002}\u0011\u0011\u0001V\t\u0003A\r\u0002\"aE\u0011\n\u0005\t\"\"a\u0002(pi\"Lgn\u001a\t\u0003\'\u0011J!!\n\u000b\u0003\u0007\u0005s\u0017\u0010\u0005\u0002(Q5\t\u0011\"\u0003\u0002*\u0013\t)\")\u001a)s_B,\'\u000f^=NCR\u001c\u0007NU3tk2$\u0018A\u0002\u0013j]&$H\u0005F\u0001-!\t\u0019R&\u0003\u0002/)\t!QK\\5u\u0003\u0015\t\u0007\u000f\u001d7z)\t1\u0013\u0007C\u00033\u0005\u0001\u00071$\u0001\npE*,7\r^,ji\"\u0004&o\u001c9feRL\u0018aB2p[B|7/Z\u000b\u0003ka\"\"A\u000e\u001e\u0011\u0007\u001d\u0002q\u0007\u0005\u0002\u001dq\u0011)\u0011h\u0001b\u0001?\t\tQ\u000bC\u0003<\u0007\u0001\u0007A(A\u0001h!\u0011\u0019\u0012dN\u000e\u0002#\t+\u0007K]8qKJ$\u00180T1uG\",\'\u000f\u0005\u0002(\u000bM\u0011QAE\u0001\u0007y%t\u0017\u000e\u001e \u0015\u0003y*\"aQ$\u0015\u0005\u0011\u0003FCA#I!\r9\u0003A\u0012\t\u00039\u001d#QAH\u0004C\u0002}AQ!S\u0004A\u0004)\u000b!!\u001a<\u0011\u0007-se)D\u0001M\u0015\tiE#A\u0004sK\u001adWm\u0019;\n\u0005=c%\u0001C\"mCN\u001cH+Y4\t\u000bE;\u0001\u0019\u0001*\u0002\u0007\u0019,h\u000e\u0005\u0003\u00143\u00193\u0003"
    )
  ScalaInlineInfo: length = 0x18 (unknown attribute)
   01 00 00 04 00 22 00 23 01 00 0E 00 0F 00 00 16
   00 17 00 00 12 00 13 01
  ScalaSig: length = 0x3 (unknown attribute)
   05 02 00
