Classfile /Users/mw/Projects/slang-braindump/.jar/jar8/assemble/slang-braindump/assemble/content/org/scalatest/matchers/BePropertyMatchResult.class
  Last modified May 29, 2022; size 5269 bytes
  SHA-256 checksum 9285205b56300307f37454dd06688cdaef6c852baf4c2f637d884ac59b608137
  Compiled from "BePropertyMatchResult.scala"
public final class org.scalatest.matchers.BePropertyMatchResult implements scala.Product,java.io.Serializable
  minor version: 0
  major version: 52
  flags: (0x0031) ACC_PUBLIC, ACC_FINAL, ACC_SUPER
  this_class: #2                          // org/scalatest/matchers/BePropertyMatchResult
  super_class: #4                         // java/lang/Object
  interfaces: 2, fields: 2, methods: 18, attributes: 4
Constant pool:
    #1 = Utf8               org/scalatest/matchers/BePropertyMatchResult
    #2 = Class              #1            // org/scalatest/matchers/BePropertyMatchResult
    #3 = Utf8               java/lang/Object
    #4 = Class              #3            // java/lang/Object
    #5 = Utf8               scala/Product
    #6 = Class              #5            // scala/Product
    #7 = Utf8               java/io/Serializable
    #8 = Class              #7            // java/io/Serializable
    #9 = Utf8               BePropertyMatchResult.scala
   #10 = Utf8               Lscala/reflect/ScalaSignature;
   #11 = Utf8               bytes
   #12 = Utf8               \u0006\u0005\u00055c\u0001\u0002\r\u001a\u0005\u0002B\u0001B\u000e\u0001\u0003\u0016\u0004%\ta\u000e\u0005\tw\u0001\u0011\t\u0012)A\u0005q!AA\b\u0001BK\u0002\u0013\u0005Q\b\u0003\u0005G\u0001\tE\t\u0015!\u0003?\u0011\u00159\u0005\u0001\"\u0001I\u0011\u001di\u0005!!A\u0005\u00029Cq!\u0015\u0001\u0012\u0002\u0013\u0005!\u000bC\u0004^\u0001E\u0005I\u0011\u00010\t\u000f\u0001\u0004\u0011\u0011!C!C\"9\u0011\u000eAA\u0001\n\u0003Q\u0007b\u00028\u0001\u0003\u0003%\ta\u001c\u0005\bk\u0002\t\t\u0011\"\u0011w\u0011\u001di\b!!A\u0005\u0002yD\u0011\"!\u0001\u0001\u0003\u0003%\t%a\u0001\t\u0013\u0005\u001d\u0001!!A\u0005B\u0005%\u0001\"CA\u0006\u0001\u0005\u0005I\u0011IA\u0007\u0011%\ty\u0001AA\u0001\n\u0003\n\tbB\u0004\u0002\u0016eA\t!a\u0006\u0007\raI\u0002\u0012AA\r\u0011\u001995\u0003\"\u0001\u0002&!I\u0011qE\n\u0002\u0002\u0013\u0005\u0015\u0011\u0006\u0005\n\u0003_\u0019\u0012\u0011!CA\u0003cA\u0011\"a\u0011\u0014\u0003\u0003%I!!\u0012\u0003+\t+\u0007K]8qKJ$\u00180T1uG\"\u0014Vm];mi*\u0011!dG\u0001\t[\u0006$8\r[3sg*\u0011A$H\u0001\ng\u000e\fG.\u0019;fgRT\u0011AH\u0001\u0004_J<7\u0001A\n\u0005\u0001\u0005:#\u0006\u0005\u0002#K5\t1EC\u0001%\u0003\u0015\u00198-\u00197b\u0013\t13E\u0001\u0004B]f\u0014VM\u001a\t\u0003E!J!!K\u0012\u0003\u000fA\u0013x\u000eZ;diB\u00111f\r\b\u0003YEr!!\f\u0019\u000e\u00039R!aL\u0010\u0002\rq\u0012xn\u001c;?\u0013\u0005!\u0013B\u0001\u001a$\u0003\u001d\u0001\u0018mY6bO\u0016L!\u0001N\u001b\u0003\u0019M+\'/[1mSj\f\'\r\\3\u000b\u0005I\u001a\u0013aB7bi\u000eDWm]\u000b\u0002qA\u0011!%O\u0005\u0003u\r\u0012qAQ8pY\u0016\fg.\u0001\u0005nCR\u001c\u0007.Z:!\u00031\u0001(o\u001c9feRLh*Y7f+\u0005q\u0004CA D\u001d\t\u0001\u0015\t\u0005\u0002.G%\u0011!iI\u0001\u0007!J,G-\u001a4\n\u0005\u0011+%AB*ue&twM\u0003\u0002CG\u0005i\u0001O]8qKJ$\u0018PT1nK\u0002\na\u0001P5oSRtDcA%L\u0019B\u0011!\nA\u0007\u00023!)a\'\u0002a\u0001q!)A(\u0002a\u0001}\u0005!1m\u001c9z)\rIu\n\u0015\u0005\bm\u0019\u0001\n\u00111\u00019\u0011\u001dad\u0001%AA\u0002y\nabY8qs\u0012\"WMZ1vYR$\u0013\'F\u0001TU\tADkK\u0001V!\t16,D\u0001X\u0015\tA\u0016,A\u0005v]\u000eDWmY6fI*\u0011!lI\u0001\u000bC:tw\u000e^1uS>t\u0017B\u0001/X\u0005E)hn\u00195fG.,GMV1sS\u0006t7-Z\u0001\u000fG>\u0004\u0018\u0010\n3fM\u0006,H\u000e\u001e\u00133+\u0005y&F\u0001 U\u00035\u0001(o\u001c3vGR\u0004&/\u001a4jqV\t!\r\u0005\u0002dQ6\tAM\u0003\u0002fM\u0006!A.\u00198h\u0015\u00059\u0017\u0001\u00026bm\u0006L!\u0001\u00123\u0002\u0019A\u0014x\u000eZ;di\u0006\u0013\u0018\u000e^=\u0016\u0003-\u0004\"A\t7\n\u00055\u001c#aA%oi\u0006q\u0001O]8ek\u000e$X\t\\3nK:$HC\u00019t!\t\u0011\u0013/\u0003\u0002sG\t\u0019\u0011I\\=\t\u000fQ\\\u0011\u0011!a\u0001W\u0006\u0019\u0001\u0010J\u0019\u0002\u001fA\u0014x\u000eZ;di&#XM]1u_J,\u0012a\u001e\t\u0004qn\u0004X\"A=\u000b\u0005i\u001c\u0013AC2pY2,7\r^5p]&\u0011A0\u001f\u0002\t\u0013R,\'/\u0019;pe\u0006A1-\u00198FcV\fG\u000e\u0006\u00029\u007f\"9A/DA\u0001\u0002\u0004\u0001\u0018A\u00059s_\u0012,8\r^#mK6,g\u000e\u001e(b[\u0016$2AYA\u0003\u0011\u001d!h\"!AA\u0002-\f\u0001\u0002[1tQ\u000e{G-\u001a\u000b\u0002W\u0006AAo\\*ue&tw\rF\u0001c\u0003\u0019)\u0017/^1mgR\u0019\u0001(a\u0005\t\u000fQ\f\u0012\u0011!a\u0001a\u0006)\")\u001a)s_B,\'\u000f^=NCR\u001c\u0007NU3tk2$\bC\u0001&\u0014\'\u0011\u0019\u0012%a\u0007\u0011\t\u0005u\u00111E\u0007\u0003\u0003?Q1!!\tg\u0003\tIw.C\u00025\u0003?!\"!a\u0006\u0002\u000b\u0005\u0004\b\u000f\\=\u0015\u000b%\u000bY#!\f\t\u000bY*\u0002\u0019\u0001\u001d\t\u000bq*\u0002\u0019\u0001 \u0002\u000fUt\u0017\r\u001d9msR!\u00111GA !\u0015\u0011\u0013QGA\u001d\u0013\r\t9d\t\u0002\u0007\u001fB$\u0018n\u001c8\u0011\u000b\t\nY\u0004\u000f \n\u0007\u0005u2E\u0001\u0004UkBdWM\r\u0005\t\u0003\u00032\u0012\u0011!a\u0001\u0013\u0006\u0019\u0001\u0010\n\u0019\u0002\u0019]\u0014\u0018\u000e^3SKBd\u0017mY3\u0015\u0005\u0005\u001d\u0003cA2\u0002J%\u0019\u00111\n3\u0003\r=\u0013\'.Z2u\u0001
   #13 = Utf8               matches
   #14 = Utf8               Z
   #15 = Utf8               propertyName
   #16 = Utf8               Ljava/lang/String;
   #17 = Utf8               unapply
   #18 = Utf8               (Lorg/scalatest/matchers/BePropertyMatchResult;)Lscala/Option;
   #19 = Utf8               (Lorg/scalatest/matchers/BePropertyMatchResult;)Lscala/Option<Lscala/Tuple2<Ljava/lang/Object;Ljava/lang/String;>;>;
   #20 = Utf8               x$0
   #21 = Utf8               org/scalatest/matchers/BePropertyMatchResult$
   #22 = Class              #21           // org/scalatest/matchers/BePropertyMatchResult$
   #23 = Utf8               MODULE$
   #24 = Utf8               Lorg/scalatest/matchers/BePropertyMatchResult$;
   #25 = NameAndType        #23:#24       // MODULE$:Lorg/scalatest/matchers/BePropertyMatchResult$;
   #26 = Fieldref           #22.#25       // org/scalatest/matchers/BePropertyMatchResult$.MODULE$:Lorg/scalatest/matchers/BePropertyMatchResult$;
   #27 = NameAndType        #17:#18       // unapply:(Lorg/scalatest/matchers/BePropertyMatchResult;)Lscala/Option;
   #28 = Methodref          #22.#27       // org/scalatest/matchers/BePropertyMatchResult$.unapply:(Lorg/scalatest/matchers/BePropertyMatchResult;)Lscala/Option;
   #29 = Utf8               Lorg/scalatest/matchers/BePropertyMatchResult;
   #30 = Utf8               apply
   #31 = Utf8               (ZLjava/lang/String;)Lorg/scalatest/matchers/BePropertyMatchResult;
   #32 = NameAndType        #30:#31       // apply:(ZLjava/lang/String;)Lorg/scalatest/matchers/BePropertyMatchResult;
   #33 = Methodref          #22.#32       // org/scalatest/matchers/BePropertyMatchResult$.apply:(ZLjava/lang/String;)Lorg/scalatest/matchers/BePropertyMatchResult;
   #34 = Utf8               productElementNames
   #35 = Utf8               ()Lscala/collection/Iterator;
   #36 = Utf8               ()Lscala/collection/Iterator<Ljava/lang/String;>;
   #37 = Utf8               productElementNames$
   #38 = Utf8               (Lscala/Product;)Lscala/collection/Iterator;
   #39 = NameAndType        #37:#38       // productElementNames$:(Lscala/Product;)Lscala/collection/Iterator;
   #40 = InterfaceMethodref #6.#39        // scala/Product.productElementNames$:(Lscala/Product;)Lscala/collection/Iterator;
   #41 = Utf8               this
   #42 = Utf8               ()Z
   #43 = NameAndType        #13:#14       // matches:Z
   #44 = Fieldref           #2.#43        // org/scalatest/matchers/BePropertyMatchResult.matches:Z
   #45 = Utf8               ()Ljava/lang/String;
   #46 = NameAndType        #15:#16       // propertyName:Ljava/lang/String;
   #47 = Fieldref           #2.#46        // org/scalatest/matchers/BePropertyMatchResult.propertyName:Ljava/lang/String;
   #48 = Utf8               copy
   #49 = Utf8               <init>
   #50 = Utf8               (ZLjava/lang/String;)V
   #51 = NameAndType        #49:#50       // "<init>":(ZLjava/lang/String;)V
   #52 = Methodref          #2.#51        // org/scalatest/matchers/BePropertyMatchResult."<init>":(ZLjava/lang/String;)V
   #53 = Utf8               copy$default$1
   #54 = NameAndType        #13:#42       // matches:()Z
   #55 = Methodref          #2.#54        // org/scalatest/matchers/BePropertyMatchResult.matches:()Z
   #56 = Utf8               copy$default$2
   #57 = NameAndType        #15:#45       // propertyName:()Ljava/lang/String;
   #58 = Methodref          #2.#57        // org/scalatest/matchers/BePropertyMatchResult.propertyName:()Ljava/lang/String;
   #59 = Utf8               productPrefix
   #60 = Utf8               BePropertyMatchResult
   #61 = String             #60           // BePropertyMatchResult
   #62 = Utf8               productArity
   #63 = Utf8               ()I
   #64 = Utf8               productElement
   #65 = Utf8               (I)Ljava/lang/Object;
   #66 = Utf8               x$1
   #67 = Utf8               scala/runtime/BoxesRunTime
   #68 = Class              #67           // scala/runtime/BoxesRunTime
   #69 = Utf8               boxToBoolean
   #70 = Utf8               (Z)Ljava/lang/Boolean;
   #71 = NameAndType        #69:#70       // boxToBoolean:(Z)Ljava/lang/Boolean;
   #72 = Methodref          #68.#71       // scala/runtime/BoxesRunTime.boxToBoolean:(Z)Ljava/lang/Boolean;
   #73 = Utf8               scala/runtime/Statics
   #74 = Class              #73           // scala/runtime/Statics
   #75 = Utf8               ioobe
   #76 = NameAndType        #75:#65       // ioobe:(I)Ljava/lang/Object;
   #77 = Methodref          #74.#76       // scala/runtime/Statics.ioobe:(I)Ljava/lang/Object;
   #78 = Utf8               I
   #79 = Utf8               productIterator
   #80 = Utf8               ()Lscala/collection/Iterator<Ljava/lang/Object;>;
   #81 = Utf8               scala/runtime/ScalaRunTime$
   #82 = Class              #81           // scala/runtime/ScalaRunTime$
   #83 = Utf8               Lscala/runtime/ScalaRunTime$;
   #84 = NameAndType        #23:#83       // MODULE$:Lscala/runtime/ScalaRunTime$;
   #85 = Fieldref           #82.#84       // scala/runtime/ScalaRunTime$.MODULE$:Lscala/runtime/ScalaRunTime$;
   #86 = Utf8               typedProductIterator
   #87 = NameAndType        #86:#38       // typedProductIterator:(Lscala/Product;)Lscala/collection/Iterator;
   #88 = Methodref          #82.#87       // scala/runtime/ScalaRunTime$.typedProductIterator:(Lscala/Product;)Lscala/collection/Iterator;
   #89 = Utf8               canEqual
   #90 = Utf8               (Ljava/lang/Object;)Z
   #91 = Utf8               Ljava/lang/Object;
   #92 = Utf8               productElementName
   #93 = Utf8               (I)Ljava/lang/String;
   #94 = String             #13           // matches
   #95 = String             #15           // propertyName
   #96 = Utf8               java/lang/String
   #97 = Class              #96           // java/lang/String
   #98 = Utf8               hashCode
   #99 = Integer            -889275714
  #100 = NameAndType        #59:#45       // productPrefix:()Ljava/lang/String;
  #101 = Methodref          #2.#100       // org/scalatest/matchers/BePropertyMatchResult.productPrefix:()Ljava/lang/String;
  #102 = NameAndType        #98:#63       // hashCode:()I
  #103 = Methodref          #97.#102      // java/lang/String.hashCode:()I
  #104 = Utf8               mix
  #105 = Utf8               (II)I
  #106 = NameAndType        #104:#105     // mix:(II)I
  #107 = Methodref          #74.#106      // scala/runtime/Statics.mix:(II)I
  #108 = Utf8               anyHash
  #109 = Utf8               (Ljava/lang/Object;)I
  #110 = NameAndType        #108:#109     // anyHash:(Ljava/lang/Object;)I
  #111 = Methodref          #74.#110      // scala/runtime/Statics.anyHash:(Ljava/lang/Object;)I
  #112 = Utf8               finalizeHash
  #113 = NameAndType        #112:#105     // finalizeHash:(II)I
  #114 = Methodref          #74.#113      // scala/runtime/Statics.finalizeHash:(II)I
  #115 = Utf8               toString
  #116 = Utf8               _toString
  #117 = Utf8               (Lscala/Product;)Ljava/lang/String;
  #118 = NameAndType        #116:#117     // _toString:(Lscala/Product;)Ljava/lang/String;
  #119 = Methodref          #82.#118      // scala/runtime/ScalaRunTime$._toString:(Lscala/Product;)Ljava/lang/String;
  #120 = Utf8               equals
  #121 = NameAndType        #120:#90      // equals:(Ljava/lang/Object;)Z
  #122 = Methodref          #4.#121       // java/lang/Object.equals:(Ljava/lang/Object;)Z
  #123 = Utf8               ()V
  #124 = NameAndType        #49:#123      // "<init>":()V
  #125 = Methodref          #4.#124       // java/lang/Object."<init>":()V
  #126 = Utf8               $init$
  #127 = Utf8               (Lscala/Product;)V
  #128 = NameAndType        #126:#127     // $init$:(Lscala/Product;)V
  #129 = InterfaceMethodref #6.#128       // scala/Product.$init$:(Lscala/Product;)V
  #130 = Utf8               Code
  #131 = Utf8               LocalVariableTable
  #132 = Utf8               Signature
  #133 = Utf8               MethodParameters
  #134 = Utf8               LineNumberTable
  #135 = Utf8               StackMapTable
  #136 = Utf8               SourceFile
  #137 = Utf8               RuntimeVisibleAnnotations
  #138 = Utf8               ScalaInlineInfo
  #139 = Utf8               ScalaSig
{
  private final boolean matches;
    descriptor: Z
    flags: (0x0012) ACC_PRIVATE, ACC_FINAL

  private final java.lang.String propertyName;
    descriptor: Ljava/lang/String;
    flags: (0x0012) ACC_PRIVATE, ACC_FINAL

  public static scala.Option<scala.Tuple2<java.lang.Object, java.lang.String>> unapply(org.scalatest.matchers.BePropertyMatchResult);
    descriptor: (Lorg/scalatest/matchers/BePropertyMatchResult;)Lscala/Option;
    flags: (0x0009) ACC_PUBLIC, ACC_STATIC
    Code:
      stack=2, locals=1, args_size=1
         0: getstatic     #26                 // Field org/scalatest/matchers/BePropertyMatchResult$.MODULE$:Lorg/scalatest/matchers/BePropertyMatchResult$;
         3: aload_0
         4: invokevirtual #28                 // Method org/scalatest/matchers/BePropertyMatchResult$.unapply:(Lorg/scalatest/matchers/BePropertyMatchResult;)Lscala/Option;
         7: areturn
      LocalVariableTable:
        Start  Length  Slot  Name   Signature
            0       8     0   x$0   Lorg/scalatest/matchers/BePropertyMatchResult;
    Signature: #19                          // (Lorg/scalatest/matchers/BePropertyMatchResult;)Lscala/Option<Lscala/Tuple2<Ljava/lang/Object;Ljava/lang/String;>;>;
    MethodParameters:
      Name                           Flags
      x$0                            final

  public static org.scalatest.matchers.BePropertyMatchResult apply(boolean, java.lang.String);
    descriptor: (ZLjava/lang/String;)Lorg/scalatest/matchers/BePropertyMatchResult;
    flags: (0x0009) ACC_PUBLIC, ACC_STATIC
    Code:
      stack=3, locals=2, args_size=2
         0: getstatic     #26                 // Field org/scalatest/matchers/BePropertyMatchResult$.MODULE$:Lorg/scalatest/matchers/BePropertyMatchResult$;
         3: iload_0
         4: aload_1
         5: invokevirtual #33                 // Method org/scalatest/matchers/BePropertyMatchResult$.apply:(ZLjava/lang/String;)Lorg/scalatest/matchers/BePropertyMatchResult;
         8: areturn
      LocalVariableTable:
        Start  Length  Slot  Name   Signature
            0       9     0 matches   Z
            0       9     1 propertyName   Ljava/lang/String;
    MethodParameters:
      Name                           Flags
      matches                        final
      propertyName                   final

  public scala.collection.Iterator<java.lang.String> productElementNames();
    descriptor: ()Lscala/collection/Iterator;
    flags: (0x0001) ACC_PUBLIC
    Code:
      stack=1, locals=1, args_size=1
         0: aload_0
         1: invokestatic  #40                 // InterfaceMethod scala/Product.productElementNames$:(Lscala/Product;)Lscala/collection/Iterator;
         4: areturn
      LineNumberTable:
        line 35: 0
      LocalVariableTable:
        Start  Length  Slot  Name   Signature
            0       5     0  this   Lorg/scalatest/matchers/BePropertyMatchResult;
    Signature: #36                          // ()Lscala/collection/Iterator<Ljava/lang/String;>;

  public boolean matches();
    descriptor: ()Z
    flags: (0x0001) ACC_PUBLIC
    Code:
      stack=1, locals=1, args_size=1
         0: aload_0
         1: getfield      #44                 // Field matches:Z
         4: ireturn
      LineNumberTable:
        line 36: 0
      LocalVariableTable:
        Start  Length  Slot  Name   Signature
            0       5     0  this   Lorg/scalatest/matchers/BePropertyMatchResult;

  public java.lang.String propertyName();
    descriptor: ()Ljava/lang/String;
    flags: (0x0001) ACC_PUBLIC
    Code:
      stack=1, locals=1, args_size=1
         0: aload_0
         1: getfield      #47                 // Field propertyName:Ljava/lang/String;
         4: areturn
      LineNumberTable:
        line 37: 0
      LocalVariableTable:
        Start  Length  Slot  Name   Signature
            0       5     0  this   Lorg/scalatest/matchers/BePropertyMatchResult;

  public org.scalatest.matchers.BePropertyMatchResult copy(boolean, java.lang.String);
    descriptor: (ZLjava/lang/String;)Lorg/scalatest/matchers/BePropertyMatchResult;
    flags: (0x0001) ACC_PUBLIC
    Code:
      stack=4, locals=3, args_size=3
         0: new           #2                  // class org/scalatest/matchers/BePropertyMatchResult
         3: dup
         4: iload_1
         5: aload_2
         6: invokespecial #52                 // Method "<init>":(ZLjava/lang/String;)V
         9: areturn
      LineNumberTable:
        line 35: 0
        line 36: 4
        line 37: 5
      LocalVariableTable:
        Start  Length  Slot  Name   Signature
            0      10     0  this   Lorg/scalatest/matchers/BePropertyMatchResult;
            0      10     1 matches   Z
            0      10     2 propertyName   Ljava/lang/String;
    MethodParameters:
      Name                           Flags
      matches                        final
      propertyName                   final

  public boolean copy$default$1();
    descriptor: ()Z
    flags: (0x0001) ACC_PUBLIC
    Code:
      stack=1, locals=1, args_size=1
         0: aload_0
         1: invokevirtual #55                 // Method matches:()Z
         4: ireturn
      LineNumberTable:
        line 36: 0
      LocalVariableTable:
        Start  Length  Slot  Name   Signature
            0       5     0  this   Lorg/scalatest/matchers/BePropertyMatchResult;

  public java.lang.String copy$default$2();
    descriptor: ()Ljava/lang/String;
    flags: (0x0001) ACC_PUBLIC
    Code:
      stack=1, locals=1, args_size=1
         0: aload_0
         1: invokevirtual #58                 // Method propertyName:()Ljava/lang/String;
         4: areturn
      LineNumberTable:
        line 37: 0
      LocalVariableTable:
        Start  Length  Slot  Name   Signature
            0       5     0  this   Lorg/scalatest/matchers/BePropertyMatchResult;

  public java.lang.String productPrefix();
    descriptor: ()Ljava/lang/String;
    flags: (0x0001) ACC_PUBLIC
    Code:
      stack=1, locals=1, args_size=1
         0: ldc           #61                 // String BePropertyMatchResult
         2: areturn
      LineNumberTable:
        line 35: 0
      LocalVariableTable:
        Start  Length  Slot  Name   Signature
            0       3     0  this   Lorg/scalatest/matchers/BePropertyMatchResult;

  public int productArity();
    descriptor: ()I
    flags: (0x0001) ACC_PUBLIC
    Code:
      stack=1, locals=1, args_size=1
         0: iconst_2
         1: ireturn
      LineNumberTable:
        line 35: 0
      LocalVariableTable:
        Start  Length  Slot  Name   Signature
            0       2     0  this   Lorg/scalatest/matchers/BePropertyMatchResult;

  public java.lang.Object productElement(int);
    descriptor: (I)Ljava/lang/Object;
    flags: (0x0001) ACC_PUBLIC
    Code:
      stack=1, locals=3, args_size=2
         0: iload_1
         1: istore_2
         2: iload_2
         3: tableswitch   { // 0 to 1
                       0: 24
                       1: 34
                 default: 41
            }
        24: aload_0
        25: invokevirtual #55                 // Method matches:()Z
        28: invokestatic  #72                 // Method scala/runtime/BoxesRunTime.boxToBoolean:(Z)Ljava/lang/Boolean;
        31: goto          48
        34: aload_0
        35: invokevirtual #58                 // Method propertyName:()Ljava/lang/String;
        38: goto          48
        41: iload_1
        42: invokestatic  #77                 // Method scala/runtime/Statics.ioobe:(I)Ljava/lang/Object;
        45: goto          48
        48: areturn
      StackMapTable: number_of_entries = 4
        frame_type = 252 /* append */
          offset_delta = 24
          locals = [ int ]
        frame_type = 9 /* same */
        frame_type = 6 /* same */
        frame_type = 70 /* same_locals_1_stack_item */
          stack = [ class java/lang/Object ]
      LineNumberTable:
        line 35: 0
      LocalVariableTable:
        Start  Length  Slot  Name   Signature
            0      49     0  this   Lorg/scalatest/matchers/BePropertyMatchResult;
            0      49     1   x$1   I
    MethodParameters:
      Name                           Flags
      x$1                            final

  public scala.collection.Iterator<java.lang.Object> productIterator();
    descriptor: ()Lscala/collection/Iterator;
    flags: (0x0001) ACC_PUBLIC
    Code:
      stack=2, locals=1, args_size=1
         0: getstatic     #85                 // Field scala/runtime/ScalaRunTime$.MODULE$:Lscala/runtime/ScalaRunTime$;
         3: aload_0
         4: invokevirtual #88                 // Method scala/runtime/ScalaRunTime$.typedProductIterator:(Lscala/Product;)Lscala/collection/Iterator;
         7: areturn
      LineNumberTable:
        line 35: 0
      LocalVariableTable:
        Start  Length  Slot  Name   Signature
            0       8     0  this   Lorg/scalatest/matchers/BePropertyMatchResult;
    Signature: #80                          // ()Lscala/collection/Iterator<Ljava/lang/Object;>;

  public boolean canEqual(java.lang.Object);
    descriptor: (Ljava/lang/Object;)Z
    flags: (0x0001) ACC_PUBLIC
    Code:
      stack=1, locals=2, args_size=2
         0: aload_1
         1: instanceof    #2                  // class org/scalatest/matchers/BePropertyMatchResult
         4: ireturn
      LineNumberTable:
        line 35: 0
      LocalVariableTable:
        Start  Length  Slot  Name   Signature
            0       5     0  this   Lorg/scalatest/matchers/BePropertyMatchResult;
            0       5     1   x$1   Ljava/lang/Object;
    MethodParameters:
      Name                           Flags
      x$1                            final

  public java.lang.String productElementName(int);
    descriptor: (I)Ljava/lang/String;
    flags: (0x0001) ACC_PUBLIC
    Code:
      stack=1, locals=3, args_size=2
         0: iload_1
         1: istore_2
         2: iload_2
         3: tableswitch   { // 0 to 1
                       0: 24
                       1: 29
                 default: 34
            }
        24: ldc           #94                 // String matches
        26: goto          44
        29: ldc           #95                 // String propertyName
        31: goto          44
        34: iload_1
        35: invokestatic  #77                 // Method scala/runtime/Statics.ioobe:(I)Ljava/lang/Object;
        38: checkcast     #97                 // class java/lang/String
        41: goto          44
        44: areturn
      StackMapTable: number_of_entries = 4
        frame_type = 252 /* append */
          offset_delta = 24
          locals = [ int ]
        frame_type = 4 /* same */
        frame_type = 4 /* same */
        frame_type = 73 /* same_locals_1_stack_item */
          stack = [ class java/lang/String ]
      LineNumberTable:
        line 35: 0
      LocalVariableTable:
        Start  Length  Slot  Name   Signature
            0      45     0  this   Lorg/scalatest/matchers/BePropertyMatchResult;
            0      45     1   x$1   I
    MethodParameters:
      Name                           Flags
      x$1                            final

  public int hashCode();
    descriptor: ()I
    flags: (0x0001) ACC_PUBLIC
    Code:
      stack=2, locals=2, args_size=1
         0: ldc           #99                 // int -889275714
         2: istore_1
         3: iload_1
         4: aload_0
         5: invokevirtual #101                // Method productPrefix:()Ljava/lang/String;
         8: invokevirtual #103                // Method java/lang/String.hashCode:()I
        11: invokestatic  #107                // Method scala/runtime/Statics.mix:(II)I
        14: istore_1
        15: iload_1
        16: aload_0
        17: invokevirtual #55                 // Method matches:()Z
        20: ifeq          29
        23: sipush        1231
        26: goto          32
        29: sipush        1237
        32: invokestatic  #107                // Method scala/runtime/Statics.mix:(II)I
        35: istore_1
        36: iload_1
        37: aload_0
        38: invokevirtual #58                 // Method propertyName:()Ljava/lang/String;
        41: invokestatic  #111                // Method scala/runtime/Statics.anyHash:(Ljava/lang/Object;)I
        44: invokestatic  #107                // Method scala/runtime/Statics.mix:(II)I
        47: istore_1
        48: iload_1
        49: iconst_2
        50: invokestatic  #114                // Method scala/runtime/Statics.finalizeHash:(II)I
        53: ireturn
      StackMapTable: number_of_entries = 2
        frame_type = 255 /* full_frame */
          offset_delta = 29
          locals = [ class org/scalatest/matchers/BePropertyMatchResult, int ]
          stack = [ int ]
        frame_type = 255 /* full_frame */
          offset_delta = 2
          locals = [ class org/scalatest/matchers/BePropertyMatchResult, int ]
          stack = [ int, int ]
      LineNumberTable:
        line 35: 0
      LocalVariableTable:
        Start  Length  Slot  Name   Signature
            0      54     0  this   Lorg/scalatest/matchers/BePropertyMatchResult;

  public java.lang.String toString();
    descriptor: ()Ljava/lang/String;
    flags: (0x0001) ACC_PUBLIC
    Code:
      stack=2, locals=1, args_size=1
         0: getstatic     #85                 // Field scala/runtime/ScalaRunTime$.MODULE$:Lscala/runtime/ScalaRunTime$;
         3: aload_0
         4: invokevirtual #119                // Method scala/runtime/ScalaRunTime$._toString:(Lscala/Product;)Ljava/lang/String;
         7: areturn
      LineNumberTable:
        line 35: 0
      LocalVariableTable:
        Start  Length  Slot  Name   Signature
            0       8     0  this   Lorg/scalatest/matchers/BePropertyMatchResult;

  public boolean equals(java.lang.Object);
    descriptor: (Ljava/lang/Object;)Z
    flags: (0x0001) ACC_PUBLIC
    Code:
      stack=2, locals=6, args_size=2
         0: aload_0
         1: aload_1
         2: if_acmpeq     89
         5: aload_1
         6: astore_3
         7: aload_3
         8: instanceof    #2                  // class org/scalatest/matchers/BePropertyMatchResult
        11: ifeq          19
        14: iconst_1
        15: istore_2
        16: goto          27
        19: goto          22
        22: iconst_0
        23: istore_2
        24: goto          27
        27: iload_2
        28: ifeq          93
        31: aload_1
        32: checkcast     #2                  // class org/scalatest/matchers/BePropertyMatchResult
        35: astore        4
        37: aload_0
        38: invokevirtual #55                 // Method matches:()Z
        41: aload         4
        43: invokevirtual #55                 // Method matches:()Z
        46: if_icmpne     85
        49: aload_0
        50: invokevirtual #58                 // Method propertyName:()Ljava/lang/String;
        53: aload         4
        55: invokevirtual #58                 // Method propertyName:()Ljava/lang/String;
        58: astore        5
        60: dup
        61: ifnonnull     73
        64: pop
        65: aload         5
        67: ifnull        81
        70: goto          85
        73: aload         5
        75: invokevirtual #122                // Method java/lang/Object.equals:(Ljava/lang/Object;)Z
        78: ifeq          85
        81: iconst_1
        82: goto          86
        85: iconst_0
        86: ifeq          93
        89: iconst_1
        90: goto          94
        93: iconst_0
        94: ireturn
      StackMapTable: number_of_entries = 10
        frame_type = 253 /* append */
          offset_delta = 19
          locals = [ top, class java/lang/Object ]
        frame_type = 2 /* same */
        frame_type = 255 /* full_frame */
          offset_delta = 4
          locals = [ class org/scalatest/matchers/BePropertyMatchResult, class java/lang/Object, int, class java/lang/Object ]
          stack = []
        frame_type = 255 /* full_frame */
          offset_delta = 45
          locals = [ class org/scalatest/matchers/BePropertyMatchResult, class java/lang/Object, int, class java/lang/Object, class org/scalatest/matchers/BePropertyMatchResult, class java/lang/String ]
          stack = [ class java/lang/String ]
        frame_type = 7 /* same */
        frame_type = 250 /* chop */
          offset_delta = 3
        frame_type = 64 /* same_locals_1_stack_item */
          stack = [ int ]
        frame_type = 248 /* chop */
          offset_delta = 2
        frame_type = 253 /* append */
          offset_delta = 3
          locals = [ int, class java/lang/Object ]
        frame_type = 255 /* full_frame */
          offset_delta = 0
          locals = [ class org/scalatest/matchers/BePropertyMatchResult, class java/lang/Object ]
          stack = [ int ]
      LineNumberTable:
        line 35: 0
      LocalVariableTable:
        Start  Length  Slot  Name   Signature
            0      95     0  this   Lorg/scalatest/matchers/BePropertyMatchResult;
            0      95     1   x$1   Ljava/lang/Object;
    MethodParameters:
      Name                           Flags
      x$1                            final

  public org.scalatest.matchers.BePropertyMatchResult(boolean, java.lang.String);
    descriptor: (ZLjava/lang/String;)V
    flags: (0x0001) ACC_PUBLIC
    Code:
      stack=2, locals=3, args_size=3
         0: aload_0
         1: iload_1
         2: putfield      #44                 // Field matches:Z
         5: aload_0
         6: aload_2
         7: putfield      #47                 // Field propertyName:Ljava/lang/String;
        10: aload_0
        11: invokespecial #125                // Method java/lang/Object."<init>":()V
        14: aload_0
        15: invokestatic  #129                // InterfaceMethod scala/Product.$init$:(Lscala/Product;)V
        18: return
      LineNumberTable:
        line 36: 0
        line 37: 5
        line 35: 10
      LocalVariableTable:
        Start  Length  Slot  Name   Signature
            0      19     0  this   Lorg/scalatest/matchers/BePropertyMatchResult;
            0      19     1 matches   Z
            0      19     2 propertyName   Ljava/lang/String;
    MethodParameters:
      Name                           Flags
      matches                        final
      propertyName                   final
}
SourceFile: "BePropertyMatchResult.scala"
RuntimeVisibleAnnotations:
  0: #10(#11=s#12)
    scala.reflect.ScalaSignature(
      bytes="\u0006\u0005\u00055c\u0001\u0002\r\u001a\u0005\u0002B\u0001B\u000e\u0001\u0003\u0016\u0004%\ta\u000e\u0005\tw\u0001\u0011\t\u0012)A\u0005q!AA\b\u0001BK\u0002\u0013\u0005Q\b\u0003\u0005G\u0001\tE\t\u0015!\u0003?\u0011\u00159\u0005\u0001\"\u0001I\u0011\u001di\u0005!!A\u0005\u00029Cq!\u0015\u0001\u0012\u0002\u0013\u0005!\u000bC\u0004^\u0001E\u0005I\u0011\u00010\t\u000f\u0001\u0004\u0011\u0011!C!C\"9\u0011\u000eAA\u0001\n\u0003Q\u0007b\u00028\u0001\u0003\u0003%\ta\u001c\u0005\bk\u0002\t\t\u0011\"\u0011w\u0011\u001di\b!!A\u0005\u0002yD\u0011\"!\u0001\u0001\u0003\u0003%\t%a\u0001\t\u0013\u0005\u001d\u0001!!A\u0005B\u0005%\u0001\"CA\u0006\u0001\u0005\u0005I\u0011IA\u0007\u0011%\ty\u0001AA\u0001\n\u0003\n\tbB\u0004\u0002\u0016eA\t!a\u0006\u0007\raI\u0002\u0012AA\r\u0011\u001995\u0003\"\u0001\u0002&!I\u0011qE\n\u0002\u0002\u0013\u0005\u0015\u0011\u0006\u0005\n\u0003_\u0019\u0012\u0011!CA\u0003cA\u0011\"a\u0011\u0014\u0003\u0003%I!!\u0012\u0003+\t+\u0007K]8qKJ$\u00180T1uG\"\u0014Vm];mi*\u0011!dG\u0001\t[\u0006$8\r[3sg*\u0011A$H\u0001\ng\u000e\fG.\u0019;fgRT\u0011AH\u0001\u0004_J<7\u0001A\n\u0005\u0001\u0005:#\u0006\u0005\u0002#K5\t1EC\u0001%\u0003\u0015\u00198-\u00197b\u0013\t13E\u0001\u0004B]f\u0014VM\u001a\t\u0003E!J!!K\u0012\u0003\u000fA\u0013x\u000eZ;diB\u00111f\r\b\u0003YEr!!\f\u0019\u000e\u00039R!aL\u0010\u0002\rq\u0012xn\u001c;?\u0013\u0005!\u0013B\u0001\u001a$\u0003\u001d\u0001\u0018mY6bO\u0016L!\u0001N\u001b\u0003\u0019M+\'/[1mSj\f\'\r\\3\u000b\u0005I\u001a\u0013aB7bi\u000eDWm]\u000b\u0002qA\u0011!%O\u0005\u0003u\r\u0012qAQ8pY\u0016\fg.\u0001\u0005nCR\u001c\u0007.Z:!\u00031\u0001(o\u001c9feRLh*Y7f+\u0005q\u0004CA D\u001d\t\u0001\u0015\t\u0005\u0002.G%\u0011!iI\u0001\u0007!J,G-\u001a4\n\u0005\u0011+%AB*ue&twM\u0003\u0002CG\u0005i\u0001O]8qKJ$\u0018PT1nK\u0002\na\u0001P5oSRtDcA%L\u0019B\u0011!\nA\u0007\u00023!)a\'\u0002a\u0001q!)A(\u0002a\u0001}\u0005!1m\u001c9z)\rIu\n\u0015\u0005\bm\u0019\u0001\n\u00111\u00019\u0011\u001dad\u0001%AA\u0002y\nabY8qs\u0012\"WMZ1vYR$\u0013\'F\u0001TU\tADkK\u0001V!\t16,D\u0001X\u0015\tA\u0016,A\u0005v]\u000eDWmY6fI*\u0011!lI\u0001\u000bC:tw\u000e^1uS>t\u0017B\u0001/X\u0005E)hn\u00195fG.,GMV1sS\u0006t7-Z\u0001\u000fG>\u0004\u0018\u0010\n3fM\u0006,H\u000e\u001e\u00133+\u0005y&F\u0001 U\u00035\u0001(o\u001c3vGR\u0004&/\u001a4jqV\t!\r\u0005\u0002dQ6\tAM\u0003\u0002fM\u0006!A.\u00198h\u0015\u00059\u0017\u0001\u00026bm\u0006L!\u0001\u00123\u0002\u0019A\u0014x\u000eZ;di\u0006\u0013\u0018\u000e^=\u0016\u0003-\u0004\"A\t7\n\u00055\u001c#aA%oi\u0006q\u0001O]8ek\u000e$X\t\\3nK:$HC\u00019t!\t\u0011\u0013/\u0003\u0002sG\t\u0019\u0011I\\=\t\u000fQ\\\u0011\u0011!a\u0001W\u0006\u0019\u0001\u0010J\u0019\u0002\u001fA\u0014x\u000eZ;di&#XM]1u_J,\u0012a\u001e\t\u0004qn\u0004X\"A=\u000b\u0005i\u001c\u0013AC2pY2,7\r^5p]&\u0011A0\u001f\u0002\t\u0013R,\'/\u0019;pe\u0006A1-\u00198FcV\fG\u000e\u0006\u00029\u007f\"9A/DA\u0001\u0002\u0004\u0001\u0018A\u00059s_\u0012,8\r^#mK6,g\u000e\u001e(b[\u0016$2AYA\u0003\u0011\u001d!h\"!AA\u0002-\f\u0001\u0002[1tQ\u000e{G-\u001a\u000b\u0002W\u0006AAo\\*ue&tw\rF\u0001c\u0003\u0019)\u0017/^1mgR\u0019\u0001(a\u0005\t\u000fQ\f\u0012\u0011!a\u0001a\u0006)\")\u001a)s_B,\'\u000f^=NCR\u001c\u0007NU3tk2$\bC\u0001&\u0014\'\u0011\u0019\u0012%a\u0007\u0011\t\u0005u\u00111E\u0007\u0003\u0003?Q1!!\tg\u0003\tIw.C\u00025\u0003?!\"!a\u0006\u0002\u000b\u0005\u0004\b\u000f\\=\u0015\u000b%\u000bY#!\f\t\u000bY*\u0002\u0019\u0001\u001d\t\u000bq*\u0002\u0019\u0001 \u0002\u000fUt\u0017\r\u001d9msR!\u00111GA !\u0015\u0011\u0013QGA\u001d\u0013\r\t9d\t\u0002\u0007\u001fB$\u0018n\u001c8\u0011\u000b\t\nY\u0004\u000f \n\u0007\u0005u2E\u0001\u0004UkBdWM\r\u0005\t\u0003\u00032\u0012\u0011!a\u0001\u0013\u0006\u0019\u0001\u0010\n\u0019\u0002\u0019]\u0014\u0018\u000e^3SKBd\u0017mY3\u0015\u0005\u0005\u001d\u0003cA2\u0002J%\u0019\u00111\n3\u0003\r=\u0013\'.Z2u\u0001"
    )
  ScalaInlineInfo: length = 0x54 (unknown attribute)
   01 01 00 10 00 31 00 32 01 00 59 00 5A 01 00 30
   00 1F 01 00 35 00 2A 01 00 38 00 2D 01 00 78 00
   5A 01 00 62 00 3F 01 00 0D 00 2A 01 00 3E 00 3F
   01 00 40 00 41 01 00 5C 00 5D 01 00 22 00 23 01
   00 4F 00 23 01 00 3B 00 2D 01 00 0F 00 2D 01 00
   73 00 2D 01
  ScalaSig: length = 0x3 (unknown attribute)
   05 02 00
