Classfile /Users/mw/Projects/slang-braindump/.jar/jar8/assemble/slang-braindump/assemble/content/org/scalatest/matchers/LazyArg$.class
  Last modified May 29, 2022; size 1668 bytes
  SHA-256 checksum 730580dae3c1d35e102750c4b1ffa75309787d8480112cfb6a8a00dbf58bf7f7
  Compiled from "LazyArg.scala"
public final class org.scalatest.matchers.LazyArg$ implements java.io.Serializable
  minor version: 0
  major version: 52
  flags: (0x0031) ACC_PUBLIC, ACC_FINAL, ACC_SUPER
  this_class: #2                          // org/scalatest/matchers/LazyArg$
  super_class: #4                         // java/lang/Object
  interfaces: 1, fields: 1, methods: 6, attributes: 3
Constant pool:
   #1 = Utf8               org/scalatest/matchers/LazyArg$
   #2 = Class              #1             // org/scalatest/matchers/LazyArg$
   #3 = Utf8               java/lang/Object
   #4 = Class              #3             // java/lang/Object
   #5 = Utf8               java/io/Serializable
   #6 = Class              #5             // java/io/Serializable
   #7 = Utf8               LazyArg.scala
   #8 = Utf8               MODULE$
   #9 = Utf8               Lorg/scalatest/matchers/LazyArg$;
  #10 = Utf8               <clinit>
  #11 = Utf8               ()V
  #12 = Utf8               <init>
  #13 = NameAndType        #12:#11        // "<init>":()V
  #14 = Methodref          #2.#13         // org/scalatest/matchers/LazyArg$."<init>":()V
  #15 = NameAndType        #8:#9          // MODULE$:Lorg/scalatest/matchers/LazyArg$;
  #16 = Fieldref           #2.#15         // org/scalatest/matchers/LazyArg$.MODULE$:Lorg/scalatest/matchers/LazyArg$;
  #17 = Utf8               toString
  #18 = Utf8               ()Ljava/lang/String;
  #19 = Utf8               LazyArg
  #20 = String             #19            // LazyArg
  #21 = Utf8               this
  #22 = Utf8               apply
  #23 = Utf8               (Ljava/lang/Object;Lscala/Function1;)Lorg/scalatest/matchers/LazyArg;
  #24 = Utf8               (Ljava/lang/Object;Lscala/Function1<Ljava/lang/Object;Ljava/lang/String;>;)Lorg/scalatest/matchers/LazyArg;
  #25 = Utf8               arg
  #26 = Utf8               f
  #27 = Utf8               org/scalatest/matchers/LazyArg
  #28 = Class              #27            // org/scalatest/matchers/LazyArg
  #29 = Utf8               (Ljava/lang/Object;Lscala/Function1;)V
  #30 = NameAndType        #12:#29        // "<init>":(Ljava/lang/Object;Lscala/Function1;)V
  #31 = Methodref          #28.#30        // org/scalatest/matchers/LazyArg."<init>":(Ljava/lang/Object;Lscala/Function1;)V
  #32 = Utf8               Ljava/lang/Object;
  #33 = Utf8               Lscala/Function1;
  #34 = Utf8               unapply
  #35 = Utf8               (Lorg/scalatest/matchers/LazyArg;)Lscala/Option;
  #36 = Utf8               (Lorg/scalatest/matchers/LazyArg;)Lscala/Option<Ljava/lang/Object;>;
  #37 = Utf8               x$0
  #38 = Utf8               scala/None$
  #39 = Class              #38            // scala/None$
  #40 = Utf8               Lscala/None$;
  #41 = NameAndType        #8:#40         // MODULE$:Lscala/None$;
  #42 = Fieldref           #39.#41        // scala/None$.MODULE$:Lscala/None$;
  #43 = Utf8               scala/Some
  #44 = Class              #43            // scala/Some
  #45 = Utf8               ()Ljava/lang/Object;
  #46 = NameAndType        #25:#45        // arg:()Ljava/lang/Object;
  #47 = Methodref          #28.#46        // org/scalatest/matchers/LazyArg.arg:()Ljava/lang/Object;
  #48 = Utf8               (Ljava/lang/Object;)V
  #49 = NameAndType        #12:#48        // "<init>":(Ljava/lang/Object;)V
  #50 = Methodref          #44.#49        // scala/Some."<init>":(Ljava/lang/Object;)V
  #51 = Utf8               Lorg/scalatest/matchers/LazyArg;
  #52 = Utf8               scala/Option
  #53 = Class              #52            // scala/Option
  #54 = Utf8               writeReplace
  #55 = Utf8               scala/runtime/ModuleSerializationProxy
  #56 = Class              #55            // scala/runtime/ModuleSerializationProxy
  #57 = Utf8               (Ljava/lang/Class;)V
  #58 = NameAndType        #12:#57        // "<init>":(Ljava/lang/Class;)V
  #59 = Methodref          #56.#58        // scala/runtime/ModuleSerializationProxy."<init>":(Ljava/lang/Class;)V
  #60 = Methodref          #4.#13         // java/lang/Object."<init>":()V
  #61 = Utf8               Code
  #62 = Utf8               LineNumberTable
  #63 = Utf8               LocalVariableTable
  #64 = Utf8               Signature
  #65 = Utf8               MethodParameters
  #66 = Utf8               StackMapTable
  #67 = Utf8               SourceFile
  #68 = Utf8               ScalaInlineInfo
  #69 = Utf8               Scala
{
  public static final org.scalatest.matchers.LazyArg$ MODULE$;
    descriptor: Lorg/scalatest/matchers/LazyArg$;
    flags: (0x0019) ACC_PUBLIC, ACC_STATIC, ACC_FINAL

  public static {};
    descriptor: ()V
    flags: (0x0009) ACC_PUBLIC, ACC_STATIC
    Code:
      stack=2, locals=0, args_size=0
         0: new           #2                  // class org/scalatest/matchers/LazyArg$
         3: dup
         4: invokespecial #14                 // Method "<init>":()V
         7: putstatic     #16                 // Field MODULE$:Lorg/scalatest/matchers/LazyArg$;
        10: return
      LineNumberTable:
        line 50: 0

  public final java.lang.String toString();
    descriptor: ()Ljava/lang/String;
    flags: (0x0011) ACC_PUBLIC, ACC_FINAL
    Code:
      stack=1, locals=1, args_size=1
         0: ldc           #20                 // String LazyArg
         2: areturn
      LineNumberTable:
        line 50: 0
      LocalVariableTable:
        Start  Length  Slot  Name   Signature
            0       3     0  this   Lorg/scalatest/matchers/LazyArg$;

  public org.scalatest.matchers.LazyArg apply(java.lang.Object, scala.Function1<java.lang.Object, java.lang.String>);
    descriptor: (Ljava/lang/Object;Lscala/Function1;)Lorg/scalatest/matchers/LazyArg;
    flags: (0x0001) ACC_PUBLIC
    Code:
      stack=4, locals=3, args_size=3
         0: new           #28                 // class org/scalatest/matchers/LazyArg
         3: dup
         4: aload_1
         5: aload_2
         6: invokespecial #31                 // Method org/scalatest/matchers/LazyArg."<init>":(Ljava/lang/Object;Lscala/Function1;)V
         9: areturn
      LineNumberTable:
        line 50: 0
      LocalVariableTable:
        Start  Length  Slot  Name   Signature
            0      10     0  this   Lorg/scalatest/matchers/LazyArg$;
            0      10     1   arg   Ljava/lang/Object;
            0      10     2     f   Lscala/Function1;
    Signature: #24                          // (Ljava/lang/Object;Lscala/Function1<Ljava/lang/Object;Ljava/lang/String;>;)Lorg/scalatest/matchers/LazyArg;
    MethodParameters:
      Name                           Flags
      arg                            final
      f                              final

  public scala.Option<java.lang.Object> unapply(org.scalatest.matchers.LazyArg);
    descriptor: (Lorg/scalatest/matchers/LazyArg;)Lscala/Option;
    flags: (0x0001) ACC_PUBLIC
    Code:
      stack=3, locals=2, args_size=2
         0: aload_1
         1: ifnonnull     10
         4: getstatic     #42                 // Field scala/None$.MODULE$:Lscala/None$;
         7: goto          21
        10: new           #44                 // class scala/Some
        13: dup
        14: aload_1
        15: invokevirtual #47                 // Method org/scalatest/matchers/LazyArg.arg:()Ljava/lang/Object;
        18: invokespecial #50                 // Method scala/Some."<init>":(Ljava/lang/Object;)V
        21: areturn
      StackMapTable: number_of_entries = 2
        frame_type = 10 /* same */
        frame_type = 74 /* same_locals_1_stack_item */
          stack = [ class scala/Option ]
      LineNumberTable:
        line 50: 0
      LocalVariableTable:
        Start  Length  Slot  Name   Signature
            0      22     0  this   Lorg/scalatest/matchers/LazyArg$;
            0      22     1   x$0   Lorg/scalatest/matchers/LazyArg;
    Signature: #36                          // (Lorg/scalatest/matchers/LazyArg;)Lscala/Option<Ljava/lang/Object;>;
    MethodParameters:
      Name                           Flags
      x$0                            final

  private java.lang.Object writeReplace();
    descriptor: ()Ljava/lang/Object;
    flags: (0x0002) ACC_PRIVATE
    Code:
      stack=3, locals=1, args_size=1
         0: new           #56                 // class scala/runtime/ModuleSerializationProxy
         3: dup
         4: ldc           #2                  // class org/scalatest/matchers/LazyArg$
         6: invokespecial #59                 // Method scala/runtime/ModuleSerializationProxy."<init>":(Ljava/lang/Class;)V
         9: areturn
      LineNumberTable:
        line 50: 0
      LocalVariableTable:
        Start  Length  Slot  Name   Signature
            0      10     0  this   Lorg/scalatest/matchers/LazyArg$;

  private org.scalatest.matchers.LazyArg$();
    descriptor: ()V
    flags: (0x0002) ACC_PRIVATE
    Code:
      stack=1, locals=1, args_size=1
         0: aload_0
         1: invokespecial #60                 // Method java/lang/Object."<init>":()V
         4: return
      LineNumberTable:
        line 50: 0
      LocalVariableTable:
        Start  Length  Slot  Name   Signature
            0       5     0  this   Lorg/scalatest/matchers/LazyArg$;
}
SourceFile: "LazyArg.scala"
  ScalaInlineInfo: length = 0x1D (unknown attribute)
   01 01 00 05 00 0C 00 0B 01 00 16 00 17 01 00 11
   00 12 01 00 22 00 23 01 00 36 00 2D 01
  Scala: length = 0x0 (unknown attribute)

