Classfile /Users/mw/Projects/slang-braindump/.jar/jar8/assemble/slang-braindump/assemble/content/org/scalatest/matchers/MatchResult.class
  Last modified May 29, 2022; size 17016 bytes
  SHA-256 checksum f5f0998eb6ae17d6740108d7d3b2d74713bd12fe479a5db1bad2a2eb08a3629e
  Compiled from "MatchResult.scala"
public class org.scalatest.matchers.MatchResult implements scala.Product,java.io.Serializable
  minor version: 0
  major version: 52
  flags: (0x0021) ACC_PUBLIC, ACC_SUPER
  this_class: #2                          // org/scalatest/matchers/MatchResult
  super_class: #4                         // java/lang/Object
  interfaces: 2, fields: 9, methods: 46, attributes: 6
Constant pool:
    #1 = Utf8               org/scalatest/matchers/MatchResult
    #2 = Class              #1            // org/scalatest/matchers/MatchResult
    #3 = Utf8               java/lang/Object
    #4 = Class              #3            // java/lang/Object
    #5 = Utf8               scala/Product
    #6 = Class              #5            // scala/Product
    #7 = Utf8               java/io/Serializable
    #8 = Class              #7            // java/io/Serializable
    #9 = Utf8               MatchResult.scala
   #10 = Utf8               Lscala/reflect/ScalaSignature;
   #11 = Utf8               bytes
   #12 = Utf8               \u0006\u0005\tMd\u0001B\u001d;!\u0006C\u0001b\u0016\u0001\u0003\u0016\u0004%\t\u0001\u0017\u0005\t9\u0002\u0011\t\u0012)A\u00053\"AQ\f\u0001BK\u0002\u0013\u0005a\f\u0003\u0005h\u0001\tE\t\u0015!\u0003`\u0011!A\u0007A!f\u0001\n\u0003q\u0006\u0002C5\u0001\u0005#\u0005\u000b\u0011B0\t\u0011)\u0004!Q3A\u0005\u0002yC\u0001b\u001b\u0001\u0003\u0012\u0003\u0006Ia\u0018\u0005\tY\u0002\u0011)\u001a!C\u0001=\"AQ\u000e\u0001B\tB\u0003%q\f\u0003\u0005o\u0001\tU\r\u0011\"\u0001p\u0011!1\bA!E!\u0002\u0013\u0001\b\u0002C<\u0001\u0005+\u0007I\u0011A8\t\u0011a\u0004!\u0011#Q\u0001\nAD\u0001\"\u001f\u0001\u0003\u0016\u0004%\ta\u001c\u0005\tu\u0002\u0011\t\u0012)A\u0005a\"A1\u0010\u0001BK\u0002\u0013\u0005q\u000e\u0003\u0005}\u0001\tE\t\u0015!\u0003q\u0011\u0015i\b\u0001\"\u0001\u007f\u0011\u0019i\b\u0001\"\u0001\u0002\u0016!9\u0011Q\u0004\u0001\u0005\u0002\u0005}\u0001bBA\u0019\u0001\u0011\u0005\u00111\u0007\u0005\b\u0003o\u0001A\u0011AA\u001d\u0011\u001d\ti\u0004\u0001C\u0001\u0003\u007fAq!a\u0011\u0001\t\u0003\t)\u0005C\u0004\u0002H\u0001!I!!\u0013\t\u0013\u0005U\u0003!!A\u0005\u0002\u0005]\u0003\"CA6\u0001E\u0005I\u0011AA7\u0011%\t\u0019\tAI\u0001\n\u0003\t)\tC\u0005\u0002\n\u0002\t\n\u0011\"\u0001\u0002\u0006\"I\u00111\u0012\u0001\u0012\u0002\u0013\u0005\u0011Q\u0011\u0005\n\u0003\u001b\u0003\u0011\u0013!C\u0001\u0003\u000bC\u0011\"a$\u0001#\u0003%\t!!%\t\u0013\u0005U\u0005!%A\u0005\u0002\u0005E\u0005\"CAL\u0001E\u0005I\u0011AAI\u0011%\tI\nAI\u0001\n\u0003\t\t\nC\u0005\u0002\u001c\u0002\t\t\u0011\"\u0011\u0002\u001e\"I\u0011Q\u0016\u0001\u0002\u0002\u0013\u0005\u0011q\u0016\u0005\n\u0003o\u0003\u0011\u0011!C\u0001\u0003sC\u0011\"a0\u0001\u0003\u0003%\t%!1\t\u0013\u0005=\u0007!!A\u0005\u0002\u0005E\u0007\"CAk\u0001\u0005\u0005I\u0011IAl\u0011%\tY\u000eAA\u0001\n\u0003\ni\u000eC\u0005\u0002`\u0002\t\t\u0011\"\u0011\u0002b\"I\u00111\u001d\u0001\u0002\u0002\u0013\u0005\u0013Q]\u0004\b\u0003gT\u0004\u0012AA{\r\u0019I$\b#\u0001\u0002x\"1Qp\fC\u0001\u0005\u0007AqA!\u00020\t\u0003\u00119\u0001C\u0004\u0003\u0006=\"\tAa\u0006\t\u000f\t\u0015q\u0006\"\u0001\u0003$!9!QA\u0018\u0005\u0002\t-\u0002b\u0002B\u0003_\u0011\u0005!Q\u0007\u0005\n\u0005\u000by\u0013\u0011!CA\u0005\u0003B\u0011B!\u00160\u0003\u0003%\tIa\u0016\t\u0013\t%t&!A\u0005\n\t-$aC\'bi\u000eD\'+Z:vYRT!a\u000f\u001f\u0002\u00115\fGo\u00195feNT!!\u0010 \u0002\u0013M\u001c\u0017\r\\1uKN$(\"A \u0002\u0007=\u0014xm\u0001\u0001\u0014\t\u0001\u0011\u0005j\u0013\t\u0003\u0007\u001ak\u0011\u0001\u0012\u0006\u0002\u000b\u0006)1oY1mC&\u0011q\t\u0012\u0002\u0007\u0003:L(+\u001a4\u0011\u0005\rK\u0015B\u0001&E\u0005\u001d\u0001&o\u001c3vGR\u0004\"\u0001\u0014+\u000f\u00055\u0013fB\u0001(R\u001b\u0005y%B\u0001)A\u0003\u0019a$o\\8u}%\tQ)\u0003\u0002T\t\u00069\u0001/Y2lC\u001e,\u0017BA+W\u00051\u0019VM]5bY&T\u0018M\u00197f\u0015\t\u0019F)A\u0004nCR\u001c\u0007.Z:\u0016\u0003e\u0003\"a\u0011.\n\u0005m#%a\u0002\"p_2,\u0017M\\\u0001\t[\u0006$8\r[3tA\u0005\t\"/Y<GC&dWO]3NKN\u001c\u0018mZ3\u0016\u0003}\u0003\"\u0001\u00193\u000f\u0005\u0005\u0014\u0007C\u0001(E\u0013\t\u0019G)\u0001\u0004Qe\u0016$WMZ\u0005\u0003K\u001a\u0014aa\u0015;sS:<\'BA2E\u0003I\u0011\u0018m\u001e$bS2,(/Z\'fgN\fw-\u001a\u0011\u00021I\fwOT3hCR,GMR1jYV\u0014X-T3tg\u0006<W-A\rsC^tUmZ1uK\u00124\u0015-\u001b7ve\u0016lUm]:bO\u0016\u0004\u0013\u0001\b:bo6KGmU3oi\u0016t7-\u001a$bS2,(/Z\'fgN\fw-Z\u0001\u001ee\u0006<X*\u001b3TK:$XM\\2f\r\u0006LG.\u001e:f\u001b\u0016\u001c8/Y4fA\u0005\u0019#/Y<NS\u0012\u001cVM\u001c;f]\u000e,g*Z4bi\u0016$g)Y5mkJ,W*Z:tC\u001e,\u0017\u0001\n:bo6KGmU3oi\u0016t7-\u001a(fO\u0006$X\r\u001a$bS2,(/Z\'fgN\fw-\u001a\u0011\u0002%\u0019\f\u0017\u000e\\;sK6+7o]1hK\u0006\u0013xm]\u000b\u0002aB\u0019A*]:\n\u0005I4&AC%oI\u0016DX\rZ*fcB\u00111\t^\u0005\u0003k\u0012\u00131!\u00118z\u0003M1\u0017-\u001b7ve\u0016lUm]:bO\u0016\f%oZ:!\u0003eqWmZ1uK\u00124\u0015-\u001b7ve\u0016lUm]:bO\u0016\f%oZ:\u000259,w-\u0019;fI\u001a\u000b\u0017\u000e\\;sK6+7o]1hK\u0006\u0013xm\u001d\u0011\u0002;5LGmU3oi\u0016t7-\u001a$bS2,(/Z\'fgN\fw-Z!sON\fa$\\5e\'\u0016tG/\u001a8dK\u001a\u000b\u0017\u000e\\;sK6+7o]1hK\u0006\u0013xm\u001d\u0011\u0002I5LGmU3oi\u0016t7-\u001a(fO\u0006$X\r\u001a$bS2,(/Z\'fgN\fw-Z!sON\fQ%\\5e\'\u0016tG/\u001a8dK:+w-\u0019;fI\u001a\u000b\u0017\u000e\\;sK6+7o]1hK\u0006\u0013xm\u001d\u0011\u0002\rqJg.\u001b;?)My\u00181AA\u0003\u0003\u000f\tI!a\u0003\u0002\u000e\u0005=\u0011\u0011CA\n!\r\t\t\u0001A\u0007\u0002u!)qk\u0005a\u00013\")Ql\u0005a\u0001?\")\u0001n\u0005a\u0001?\")!n\u0005a\u0001?\")An\u0005a\u0001?\")an\u0005a\u0001a\")qo\u0005a\u0001a\")\u0011p\u0005a\u0001a\")1p\u0005a\u0001aR9q0a\u0006\u0002\u001a\u0005m\u0001\"B,\u0015\u0001\u0004I\u0006\"B/\u0015\u0001\u0004y\u0006\"\u00025\u0015\u0001\u0004y\u0016A\u00044bS2,(/Z\'fgN\fw-\u001a\u000b\u0004?\u0006\u0005\u0002bBA\u0012+\u0001\u000f\u0011QE\u0001\u000baJ,G\u000f^5gS\u0016\u0014\b\u0003BA\u0014\u0003[i!!!\u000b\u000b\u0007\u0005-b(A\u0005tG\u0006d\u0017m\u0019;jG&!\u0011qFA\u0015\u0005)\u0001&/\u001a;uS\u001aLWM]\u0001\u0016]\u0016<\u0017\r^3e\r\u0006LG.\u001e:f\u001b\u0016\u001c8/Y4f)\ry\u0016Q\u0007\u0005\b\u0003G1\u00029AA\u0013\u0003ei\u0017\u000eZ*f]R,gnY3GC&dWO]3NKN\u001c\u0018mZ3\u0015\u0007}\u000bY\u0004C\u0004\u0002$]\u0001\u001d!!\n\u0002A5LGmU3oi\u0016t7-\u001a(fO\u0006$X\r\u001a$bS2,(/Z\'fgN\fw-\u001a\u000b\u0004?\u0006\u0005\u0003bBA\u00121\u0001\u000f\u0011QE\u0001\b]\u0016<\u0017\r^3e+\u0005y\u0018AC7bW\u0016\u001cFO]5oOR9q,a\u0013\u0002P\u0005M\u0003BBA\'5\u0001\u0007q,A\u0005sC^\u001cFO]5oO\"1\u0011\u0011\u000b\u000eA\u0002A\fA!\u0019:hg\"9\u00111\u0005\u000eA\u0002\u0005\u0015\u0012\u0001B2paf$2c`A-\u00037\ni&a\u0018\u0002b\u0005\r\u0014QMA4\u0003SBqaV\u000e\u0011\u0002\u0003\u0007\u0011\fC\u0004^7A\u0005\t\u0019A0\t\u000f!\\\u0002\u0013!a\u0001?\"9!n\u0007I\u0001\u0002\u0004y\u0006b\u00027\u001c!\u0003\u0005\ra\u0018\u0005\b]n\u0001\n\u00111\u0001q\u0011\u001d98\u0004%AA\u0002ADq!_\u000e\u0011\u0002\u0003\u0007\u0001\u000fC\u0004|7A\u0005\t\u0019\u00019\u0002\u001d\r|\u0007/\u001f\u0013eK\u001a\fW\u000f\u001c;%cU\u0011\u0011q\u000e\u0016\u00043\u0006E4FAA:!\u0011\t)(a \u000e\u0005\u0005]$\u0002BA=\u0003w\n\u0011\"\u001e8dQ\u0016\u001c7.\u001a3\u000b\u0007\u0005uD)\u0001\u0006b]:|G/\u0019;j_:LA!!!\u0002x\t\tRO\\2iK\u000e\\W\r\u001a,be&\fgnY3\u0002\u001d\r|\u0007/\u001f\u0013eK\u001a\fW\u000f\u001c;%eU\u0011\u0011q\u0011\u0016\u0004?\u0006E\u0014AD2paf$C-\u001a4bk2$HeM\u0001\u000fG>\u0004\u0018\u0010\n3fM\u0006,H\u000e\u001e\u00135\u00039\u0019w\u000e]=%I\u00164\u0017-\u001e7uIU\nabY8qs\u0012\"WMZ1vYR$c\'\u0006\u0002\u0002\u0014*\u001a\u0001/!\u001d\u0002\u001d\r|\u0007/\u001f\u0013eK\u001a\fW\u000f\u001c;%o\u0005q1m\u001c9zI\u0011,g-Y;mi\u0012B\u0014AD2paf$C-\u001a4bk2$H%O\u0001\u000eaJ|G-^2u!J,g-\u001b=\u0016\u0005\u0005}\u0005\u0003BAQ\u0003Wk!!a)\u000b\t\u0005\u0015\u0016qU\u0001\u0005Y\u0006twM\u0003\u0002\u0002*\u0006!!.\u0019<b\u0013\r)\u00171U\u0001\raJ|G-^2u\u0003JLG/_\u000b\u0003\u0003c\u00032aQAZ\u0013\r\t)\f\u0012\u0002\u0004\u0013:$\u0018A\u00049s_\u0012,8\r^#mK6,g\u000e\u001e\u000b\u0004g\u0006m\u0006\"CA_O\u0005\u0005\t\u0019AAY\u0003\rAH%M\u0001\u0010aJ|G-^2u\u0013R,\'/\u0019;peV\u0011\u00111\u0019\t\u0006\u0003\u000b\fYm]\u0007\u0003\u0003\u000fT1!!3E\u0003)\u0019w\u000e\u001c7fGRLwN\\\u0005\u0005\u0003\u001b\f9M\u0001\u0005Ji\u0016\u0014\u0018\r^8s\u0003!\u0019\u0017M\\#rk\u0006dGcA-\u0002T\"A\u0011QX\u0015\u0002\u0002\u0003\u00071/\u0001\nqe>$Wo\u0019;FY\u0016lWM\u001c;OC6,G\u0003BAP\u00033D\u0011\"!0+\u0003\u0003\u0005\r!!-\u0002\u0011!\f7\u000f[\"pI\u0016$\"!!-\u0002\u0011Q|7\u000b\u001e:j]\u001e$\"!a(\u0002\r\u0015\fX/\u00197t)\rI\u0016q\u001d\u0005\t\u0003{k\u0013\u0011!a\u0001g&*\u0001!a;\u0002p&\u0019\u0011Q\u001e\u001e\u0003!\u0015\u000bX/\u00197NCR\u001c\u0007NU3tk2$\u0018bAAyu\t\u0019bj\u001c;FcV\fG.T1uG\"\u0014Vm];mi\u0006YQ*\u0019;dQJ+7/\u001e7u!\r\t\taL\n\u0005_\t\u000bI\u0010\u0005\u0003\u0002|\n\u0005QBAA\u007f\u0015\u0011\ty0a*\u0002\u0005%|\u0017bA+\u0002~R\u0011\u0011Q_\u0001\u0006CB\u0004H.\u001f\u000b\u0010\u007f\n%!1\u0002B\u0007\u0005\u001f\u0011\tBa\u0005\u0003\u0016!)q+\ra\u00013\")Q,\ra\u0001?\")\u0001.\ra\u0001?\")!.\ra\u0001?\")A.\ra\u0001?\")a.\ra\u0001a\")q/\ra\u0001aRYqP!\u0007\u0003\u001c\tu!q\u0004B\u0011\u0011\u00159&\u00071\u0001Z\u0011\u0015i&\u00071\u0001`\u0011\u0015A\'\u00071\u0001`\u0011\u0015Q\'\u00071\u0001`\u0011\u0015a\'\u00071\u0001`)\u001dy(Q\u0005B\u0014\u0005SAQaV\u001aA\u0002eCQ!X\u001aA\u0002}CQ\u0001[\u001aA\u0002}#\u0012b B\u0017\u0005_\u0011\tDa\r\t\u000b]#\u0004\u0019A-\t\u000bu#\u0004\u0019A0\t\u000b!$\u0004\u0019A0\t\r\u0005EC\u00071\u0001q)-y(q\u0007B\u001d\u0005w\u0011iDa\u0010\t\u000b]+\u0004\u0019A-\t\u000bu+\u0004\u0019A0\t\u000b!,\u0004\u0019A0\t\u000b9,\u0004\u0019\u00019\t\u000b],\u0004\u0019\u00019\u0015\'}\u0014\u0019E!\u0012\u0003H\t%#1\nB\'\u0005\u001f\u0012\tFa\u0015\t\u000b]3\u0004\u0019A-\t\u000bu3\u0004\u0019A0\t\u000b!4\u0004\u0019A0\t\u000b)4\u0004\u0019A0\t\u000b14\u0004\u0019A0\t\u000b94\u0004\u0019\u00019\t\u000b]4\u0004\u0019\u00019\t\u000be4\u0004\u0019\u00019\t\u000bm4\u0004\u0019\u00019\u0002\u000fUt\u0017\r\u001d9msR!!\u0011\fB3!\u0015\u0019%1\fB0\u0013\r\u0011i\u0006\u0012\u0002\u0007\u001fB$\u0018n\u001c8\u0011\u0019\r\u0013\t\'W0`?~\u0003\b\u000f\u001d9\n\u0007\t\rDI\u0001\u0004UkBdW-\u000f\u0005\t\u0005O:\u0014\u0011!a\u0001\u007f\u0006\u0019\u0001\u0010\n\u0019\u0002\u0019]\u0014\u0018\u000e^3SKBd\u0017mY3\u0015\u0005\t5\u0004\u0003BAQ\u0005_JAA!\u001d\u0002$\n1qJ\u00196fGR\u0004
   #13 = Utf8               java/lang/invoke/MethodHandles$Lookup
   #14 = Class              #13           // java/lang/invoke/MethodHandles$Lookup
   #15 = Utf8               java/lang/invoke/MethodHandles
   #16 = Class              #15           // java/lang/invoke/MethodHandles
   #17 = Utf8               Lookup
   #18 = Utf8               matches
   #19 = Utf8               Z
   #20 = Utf8               rawFailureMessage
   #21 = Utf8               Ljava/lang/String;
   #22 = Utf8               rawNegatedFailureMessage
   #23 = Utf8               rawMidSentenceFailureMessage
   #24 = Utf8               rawMidSentenceNegatedFailureMessage
   #25 = Utf8               failureMessageArgs
   #26 = Utf8               Lscala/collection/immutable/IndexedSeq;
   #27 = Utf8               Lscala/collection/immutable/IndexedSeq<Ljava/lang/Object;>;
   #28 = Utf8               negatedFailureMessageArgs
   #29 = Utf8               midSentenceFailureMessageArgs
   #30 = Utf8               midSentenceNegatedFailureMessageArgs
   #31 = Utf8               unapply
   #32 = Utf8               (Lorg/scalatest/matchers/MatchResult;)Lscala/Option;
   #33 = Utf8               (Lorg/scalatest/matchers/MatchResult;)Lscala/Option<Lscala/Tuple9<Ljava/lang/Object;Ljava/lang/String;Ljava/lang/String;Ljava/lang/String;Ljava/lang/String;Lscala/collection/immutable/IndexedSeq<Ljava/lang/Object;>;Lscala/collection/immutable/IndexedSeq<Ljava/lang/Object;>;Lscala/collection/immutable/IndexedSeq<Ljava/lang/Object;>;Lscala/collection/immutable/IndexedSeq<Ljava/lang/Object;>;>;>;
   #34 = Utf8               x$0
   #35 = Utf8               org/scalatest/matchers/MatchResult$
   #36 = Class              #35           // org/scalatest/matchers/MatchResult$
   #37 = Utf8               MODULE$
   #38 = Utf8               Lorg/scalatest/matchers/MatchResult$;
   #39 = NameAndType        #37:#38       // MODULE$:Lorg/scalatest/matchers/MatchResult$;
   #40 = Fieldref           #36.#39       // org/scalatest/matchers/MatchResult$.MODULE$:Lorg/scalatest/matchers/MatchResult$;
   #41 = NameAndType        #31:#32       // unapply:(Lorg/scalatest/matchers/MatchResult;)Lscala/Option;
   #42 = Methodref          #36.#41       // org/scalatest/matchers/MatchResult$.unapply:(Lorg/scalatest/matchers/MatchResult;)Lscala/Option;
   #43 = Utf8               Lorg/scalatest/matchers/MatchResult;
   #44 = Utf8               apply
   #45 = Utf8               (ZLjava/lang/String;Ljava/lang/String;Ljava/lang/String;Ljava/lang/String;Lscala/collection/immutable/IndexedSeq;Lscala/collection/immutable/IndexedSeq;Lscala/collection/immutable/IndexedSeq;Lscala/collection/immutable/IndexedSeq;)Lorg/scalatest/matchers/MatchResult;
   #46 = Utf8               (ZLjava/lang/String;Ljava/lang/String;Ljava/lang/String;Ljava/lang/String;Lscala/collection/immutable/IndexedSeq<Ljava/lang/Object;>;Lscala/collection/immutable/IndexedSeq<Ljava/lang/Object;>;Lscala/collection/immutable/IndexedSeq<Ljava/lang/Object;>;Lscala/collection/immutable/IndexedSeq<Ljava/lang/Object;>;)Lorg/scalatest/matchers/MatchResult;
   #47 = NameAndType        #44:#45       // apply:(ZLjava/lang/String;Ljava/lang/String;Ljava/lang/String;Ljava/lang/String;Lscala/collection/immutable/IndexedSeq;Lscala/collection/immutable/IndexedSeq;Lscala/collection/immutable/IndexedSeq;Lscala/collection/immutable/IndexedSeq;)Lorg/scalatest/matchers/MatchResult;
   #48 = Methodref          #36.#47       // org/scalatest/matchers/MatchResult$.apply:(ZLjava/lang/String;Ljava/lang/String;Ljava/lang/String;Ljava/lang/String;Lscala/collection/immutable/IndexedSeq;Lscala/collection/immutable/IndexedSeq;Lscala/collection/immutable/IndexedSeq;Lscala/collection/immutable/IndexedSeq;)Lorg/scalatest/matchers/MatchResult;
   #49 = Utf8               (ZLjava/lang/String;Ljava/lang/String;Lscala/collection/immutable/IndexedSeq;Lscala/collection/immutable/IndexedSeq;)Lorg/scalatest/matchers/MatchResult;
   #50 = Utf8               (ZLjava/lang/String;Ljava/lang/String;Lscala/collection/immutable/IndexedSeq<Ljava/lang/Object;>;Lscala/collection/immutable/IndexedSeq<Ljava/lang/Object;>;)Lorg/scalatest/matchers/MatchResult;
   #51 = NameAndType        #44:#49       // apply:(ZLjava/lang/String;Ljava/lang/String;Lscala/collection/immutable/IndexedSeq;Lscala/collection/immutable/IndexedSeq;)Lorg/scalatest/matchers/MatchResult;
   #52 = Methodref          #36.#51       // org/scalatest/matchers/MatchResult$.apply:(ZLjava/lang/String;Ljava/lang/String;Lscala/collection/immutable/IndexedSeq;Lscala/collection/immutable/IndexedSeq;)Lorg/scalatest/matchers/MatchResult;
   #53 = Utf8               (ZLjava/lang/String;Ljava/lang/String;Lscala/collection/immutable/IndexedSeq;)Lorg/scalatest/matchers/MatchResult;
   #54 = Utf8               (ZLjava/lang/String;Ljava/lang/String;Lscala/collection/immutable/IndexedSeq<Ljava/lang/Object;>;)Lorg/scalatest/matchers/MatchResult;
   #55 = Utf8               args
   #56 = NameAndType        #44:#53       // apply:(ZLjava/lang/String;Ljava/lang/String;Lscala/collection/immutable/IndexedSeq;)Lorg/scalatest/matchers/MatchResult;
   #57 = Methodref          #36.#56       // org/scalatest/matchers/MatchResult$.apply:(ZLjava/lang/String;Ljava/lang/String;Lscala/collection/immutable/IndexedSeq;)Lorg/scalatest/matchers/MatchResult;
   #58 = Utf8               (ZLjava/lang/String;Ljava/lang/String;)Lorg/scalatest/matchers/MatchResult;
   #59 = NameAndType        #44:#58       // apply:(ZLjava/lang/String;Ljava/lang/String;)Lorg/scalatest/matchers/MatchResult;
   #60 = Methodref          #36.#59       // org/scalatest/matchers/MatchResult$.apply:(ZLjava/lang/String;Ljava/lang/String;)Lorg/scalatest/matchers/MatchResult;
   #61 = Utf8               (ZLjava/lang/String;Ljava/lang/String;Ljava/lang/String;Ljava/lang/String;)Lorg/scalatest/matchers/MatchResult;
   #62 = NameAndType        #44:#61       // apply:(ZLjava/lang/String;Ljava/lang/String;Ljava/lang/String;Ljava/lang/String;)Lorg/scalatest/matchers/MatchResult;
   #63 = Methodref          #36.#62       // org/scalatest/matchers/MatchResult$.apply:(ZLjava/lang/String;Ljava/lang/String;Ljava/lang/String;Ljava/lang/String;)Lorg/scalatest/matchers/MatchResult;
   #64 = Utf8               (ZLjava/lang/String;Ljava/lang/String;Ljava/lang/String;Ljava/lang/String;Lscala/collection/immutable/IndexedSeq;Lscala/collection/immutable/IndexedSeq;)Lorg/scalatest/matchers/MatchResult;
   #65 = Utf8               (ZLjava/lang/String;Ljava/lang/String;Ljava/lang/String;Ljava/lang/String;Lscala/collection/immutable/IndexedSeq<Ljava/lang/Object;>;Lscala/collection/immutable/IndexedSeq<Ljava/lang/Object;>;)Lorg/scalatest/matchers/MatchResult;
   #66 = NameAndType        #44:#64       // apply:(ZLjava/lang/String;Ljava/lang/String;Ljava/lang/String;Ljava/lang/String;Lscala/collection/immutable/IndexedSeq;Lscala/collection/immutable/IndexedSeq;)Lorg/scalatest/matchers/MatchResult;
   #67 = Methodref          #36.#66       // org/scalatest/matchers/MatchResult$.apply:(ZLjava/lang/String;Ljava/lang/String;Ljava/lang/String;Ljava/lang/String;Lscala/collection/immutable/IndexedSeq;Lscala/collection/immutable/IndexedSeq;)Lorg/scalatest/matchers/MatchResult;
   #68 = Utf8               productElementNames
   #69 = Utf8               ()Lscala/collection/Iterator;
   #70 = Utf8               ()Lscala/collection/Iterator<Ljava/lang/String;>;
   #71 = Utf8               productElementNames$
   #72 = Utf8               (Lscala/Product;)Lscala/collection/Iterator;
   #73 = NameAndType        #71:#72       // productElementNames$:(Lscala/Product;)Lscala/collection/Iterator;
   #74 = InterfaceMethodref #6.#73        // scala/Product.productElementNames$:(Lscala/Product;)Lscala/collection/Iterator;
   #75 = Utf8               this
   #76 = Utf8               ()Z
   #77 = NameAndType        #18:#19       // matches:Z
   #78 = Fieldref           #2.#77        // org/scalatest/matchers/MatchResult.matches:Z
   #79 = Utf8               ()Ljava/lang/String;
   #80 = NameAndType        #20:#21       // rawFailureMessage:Ljava/lang/String;
   #81 = Fieldref           #2.#80        // org/scalatest/matchers/MatchResult.rawFailureMessage:Ljava/lang/String;
   #82 = NameAndType        #22:#21       // rawNegatedFailureMessage:Ljava/lang/String;
   #83 = Fieldref           #2.#82        // org/scalatest/matchers/MatchResult.rawNegatedFailureMessage:Ljava/lang/String;
   #84 = NameAndType        #23:#21       // rawMidSentenceFailureMessage:Ljava/lang/String;
   #85 = Fieldref           #2.#84        // org/scalatest/matchers/MatchResult.rawMidSentenceFailureMessage:Ljava/lang/String;
   #86 = NameAndType        #24:#21       // rawMidSentenceNegatedFailureMessage:Ljava/lang/String;
   #87 = Fieldref           #2.#86        // org/scalatest/matchers/MatchResult.rawMidSentenceNegatedFailureMessage:Ljava/lang/String;
   #88 = Utf8               ()Lscala/collection/immutable/IndexedSeq;
   #89 = Utf8               ()Lscala/collection/immutable/IndexedSeq<Ljava/lang/Object;>;
   #90 = NameAndType        #25:#26       // failureMessageArgs:Lscala/collection/immutable/IndexedSeq;
   #91 = Fieldref           #2.#90        // org/scalatest/matchers/MatchResult.failureMessageArgs:Lscala/collection/immutable/IndexedSeq;
   #92 = NameAndType        #28:#26       // negatedFailureMessageArgs:Lscala/collection/immutable/IndexedSeq;
   #93 = Fieldref           #2.#92        // org/scalatest/matchers/MatchResult.negatedFailureMessageArgs:Lscala/collection/immutable/IndexedSeq;
   #94 = NameAndType        #29:#26       // midSentenceFailureMessageArgs:Lscala/collection/immutable/IndexedSeq;
   #95 = Fieldref           #2.#94        // org/scalatest/matchers/MatchResult.midSentenceFailureMessageArgs:Lscala/collection/immutable/IndexedSeq;
   #96 = NameAndType        #30:#26       // midSentenceNegatedFailureMessageArgs:Lscala/collection/immutable/IndexedSeq;
   #97 = Fieldref           #2.#96        // org/scalatest/matchers/MatchResult.midSentenceNegatedFailureMessageArgs:Lscala/collection/immutable/IndexedSeq;
   #98 = Utf8               failureMessage
   #99 = Utf8               (Lorg/scalactic/Prettifier;)Ljava/lang/String;
  #100 = Utf8               prettifier
  #101 = NameAndType        #25:#88       // failureMessageArgs:()Lscala/collection/immutable/IndexedSeq;
  #102 = Methodref          #2.#101       // org/scalatest/matchers/MatchResult.failureMessageArgs:()Lscala/collection/immutable/IndexedSeq;
  #103 = Utf8               scala/collection/immutable/IndexedSeq
  #104 = Class              #103          // scala/collection/immutable/IndexedSeq
  #105 = Utf8               isEmpty
  #106 = NameAndType        #105:#76      // isEmpty:()Z
  #107 = InterfaceMethodref #104.#106     // scala/collection/immutable/IndexedSeq.isEmpty:()Z
  #108 = NameAndType        #20:#79       // rawFailureMessage:()Ljava/lang/String;
  #109 = Methodref          #2.#108       // org/scalatest/matchers/MatchResult.rawFailureMessage:()Ljava/lang/String;
  #110 = Utf8               makeString
  #111 = Utf8               (Ljava/lang/String;Lscala/collection/immutable/IndexedSeq;Lorg/scalactic/Prettifier;)Ljava/lang/String;
  #112 = NameAndType        #110:#111     // makeString:(Ljava/lang/String;Lscala/collection/immutable/IndexedSeq;Lorg/scalactic/Prettifier;)Ljava/lang/String;
  #113 = Methodref          #2.#112       // org/scalatest/matchers/MatchResult.makeString:(Ljava/lang/String;Lscala/collection/immutable/IndexedSeq;Lorg/scalactic/Prettifier;)Ljava/lang/String;
  #114 = Utf8               Lorg/scalactic/Prettifier;
  #115 = Utf8               java/lang/String
  #116 = Class              #115          // java/lang/String
  #117 = Utf8               negatedFailureMessage
  #118 = NameAndType        #28:#88       // negatedFailureMessageArgs:()Lscala/collection/immutable/IndexedSeq;
  #119 = Methodref          #2.#118       // org/scalatest/matchers/MatchResult.negatedFailureMessageArgs:()Lscala/collection/immutable/IndexedSeq;
  #120 = NameAndType        #22:#79       // rawNegatedFailureMessage:()Ljava/lang/String;
  #121 = Methodref          #2.#120       // org/scalatest/matchers/MatchResult.rawNegatedFailureMessage:()Ljava/lang/String;
  #122 = Utf8               midSentenceFailureMessage
  #123 = NameAndType        #29:#88       // midSentenceFailureMessageArgs:()Lscala/collection/immutable/IndexedSeq;
  #124 = Methodref          #2.#123       // org/scalatest/matchers/MatchResult.midSentenceFailureMessageArgs:()Lscala/collection/immutable/IndexedSeq;
  #125 = NameAndType        #23:#79       // rawMidSentenceFailureMessage:()Ljava/lang/String;
  #126 = Methodref          #2.#125       // org/scalatest/matchers/MatchResult.rawMidSentenceFailureMessage:()Ljava/lang/String;
  #127 = Utf8               midSentenceNegatedFailureMessage
  #128 = NameAndType        #30:#88       // midSentenceNegatedFailureMessageArgs:()Lscala/collection/immutable/IndexedSeq;
  #129 = Methodref          #2.#128       // org/scalatest/matchers/MatchResult.midSentenceNegatedFailureMessageArgs:()Lscala/collection/immutable/IndexedSeq;
  #130 = NameAndType        #24:#79       // rawMidSentenceNegatedFailureMessage:()Ljava/lang/String;
  #131 = Methodref          #2.#130       // org/scalatest/matchers/MatchResult.rawMidSentenceNegatedFailureMessage:()Ljava/lang/String;
  #132 = Utf8               negated
  #133 = Utf8               ()Lorg/scalatest/matchers/MatchResult;
  #134 = NameAndType        #18:#76       // matches:()Z
  #135 = Methodref          #2.#134       // org/scalatest/matchers/MatchResult.matches:()Z
  #136 = Utf8               <init>
  #137 = Utf8               (ZLjava/lang/String;Ljava/lang/String;Ljava/lang/String;Ljava/lang/String;Lscala/collection/immutable/IndexedSeq;Lscala/collection/immutable/IndexedSeq;Lscala/collection/immutable/IndexedSeq;Lscala/collection/immutable/IndexedSeq;)V
  #138 = NameAndType        #136:#137     // "<init>":(ZLjava/lang/String;Ljava/lang/String;Ljava/lang/String;Ljava/lang/String;Lscala/collection/immutable/IndexedSeq;Lscala/collection/immutable/IndexedSeq;Lscala/collection/immutable/IndexedSeq;Lscala/collection/immutable/IndexedSeq;)V
  #139 = Methodref          #2.#138       // org/scalatest/matchers/MatchResult."<init>":(ZLjava/lang/String;Ljava/lang/String;Ljava/lang/String;Ljava/lang/String;Lscala/collection/immutable/IndexedSeq;Lscala/collection/immutable/IndexedSeq;Lscala/collection/immutable/IndexedSeq;Lscala/collection/immutable/IndexedSeq;)V
  #140 = Utf8               (Ljava/lang/String;Lscala/collection/immutable/IndexedSeq<Ljava/lang/Object;>;Lorg/scalactic/Prettifier;)Ljava/lang/String;
  #141 = Utf8               rawString
  #142 = Utf8               org/scalatest/Resources$
  #143 = Class              #142          // org/scalatest/Resources$
  #144 = Utf8               Lorg/scalatest/Resources$;
  #145 = NameAndType        #37:#144      // MODULE$:Lorg/scalatest/Resources$;
  #146 = Fieldref           #143.#145     // org/scalatest/Resources$.MODULE$:Lorg/scalatest/Resources$;
  #147 = Utf8               (Ljava/lang/Object;)Ljava/lang/Object;
  #148 = MethodType         #147          //  (Ljava/lang/Object;)Ljava/lang/Object;
  #149 = Utf8               $anonfun$makeString$1
  #150 = Utf8               (Lorg/scalactic/Prettifier;Ljava/lang/Object;)Ljava/lang/String;
  #151 = NameAndType        #149:#150     // $anonfun$makeString$1:(Lorg/scalactic/Prettifier;Ljava/lang/Object;)Ljava/lang/String;
  #152 = Methodref          #2.#151       // org/scalatest/matchers/MatchResult.$anonfun$makeString$1:(Lorg/scalactic/Prettifier;Ljava/lang/Object;)Ljava/lang/String;
  #153 = MethodHandle       6:#152        // REF_invokeStatic org/scalatest/matchers/MatchResult.$anonfun$makeString$1:(Lorg/scalactic/Prettifier;Ljava/lang/Object;)Ljava/lang/String;
  #154 = Utf8               (Ljava/lang/Object;)Ljava/lang/String;
  #155 = MethodType         #154          //  (Ljava/lang/Object;)Ljava/lang/String;
  #156 = Integer            5
  #157 = Integer            1
  #158 = Utf8               java/lang/invoke/LambdaMetafactory
  #159 = Class              #158          // java/lang/invoke/LambdaMetafactory
  #160 = Utf8               altMetafactory
  #161 = Utf8               (Ljava/lang/invoke/MethodHandles$Lookup;Ljava/lang/String;Ljava/lang/invoke/MethodType;[Ljava/lang/Object;)Ljava/lang/invoke/CallSite;
  #162 = NameAndType        #160:#161     // altMetafactory:(Ljava/lang/invoke/MethodHandles$Lookup;Ljava/lang/String;Ljava/lang/invoke/MethodType;[Ljava/lang/Object;)Ljava/lang/invoke/CallSite;
  #163 = Methodref          #159.#162     // java/lang/invoke/LambdaMetafactory.altMetafactory:(Ljava/lang/invoke/MethodHandles$Lookup;Ljava/lang/String;Ljava/lang/invoke/MethodType;[Ljava/lang/Object;)Ljava/lang/invoke/CallSite;
  #164 = MethodHandle       6:#163        // REF_invokeStatic java/lang/invoke/LambdaMetafactory.altMetafactory:(Ljava/lang/invoke/MethodHandles$Lookup;Ljava/lang/String;Ljava/lang/invoke/MethodType;[Ljava/lang/Object;)Ljava/lang/invoke/CallSite;
  #165 = Utf8               (Lorg/scalactic/Prettifier;)Lscala/Function1;
  #166 = NameAndType        #44:#165      // apply:(Lorg/scalactic/Prettifier;)Lscala/Function1;
  #167 = InvokeDynamic      #0:#166       // #0:apply:(Lorg/scalactic/Prettifier;)Lscala/Function1;
  #168 = Utf8               map
  #169 = Utf8               (Lscala/Function1;)Ljava/lang/Object;
  #170 = NameAndType        #168:#169     // map:(Lscala/Function1;)Ljava/lang/Object;
  #171 = InterfaceMethodref #104.#170     // scala/collection/immutable/IndexedSeq.map:(Lscala/Function1;)Ljava/lang/Object;
  #172 = Utf8               scala/collection/IterableOnceOps
  #173 = Class              #172          // scala/collection/IterableOnceOps
  #174 = Utf8               scala/reflect/ClassTag$
  #175 = Class              #174          // scala/reflect/ClassTag$
  #176 = Utf8               Lscala/reflect/ClassTag$;
  #177 = NameAndType        #37:#176      // MODULE$:Lscala/reflect/ClassTag$;
  #178 = Fieldref           #175.#177     // scala/reflect/ClassTag$.MODULE$:Lscala/reflect/ClassTag$;
  #179 = Utf8               Any
  #180 = Utf8               ()Lscala/reflect/ClassTag;
  #181 = NameAndType        #179:#180     // Any:()Lscala/reflect/ClassTag;
  #182 = Methodref          #175.#181     // scala/reflect/ClassTag$.Any:()Lscala/reflect/ClassTag;
  #183 = Utf8               toArray
  #184 = Utf8               (Lscala/reflect/ClassTag;)Ljava/lang/Object;
  #185 = NameAndType        #183:#184     // toArray:(Lscala/reflect/ClassTag;)Ljava/lang/Object;
  #186 = InterfaceMethodref #173.#185     // scala/collection/IterableOnceOps.toArray:(Lscala/reflect/ClassTag;)Ljava/lang/Object;
  #187 = Utf8               [Ljava/lang/Object;
  #188 = Class              #187          // "[Ljava/lang/Object;"
  #189 = Utf8               formatString
  #190 = Utf8               (Ljava/lang/String;[Ljava/lang/Object;)Ljava/lang/String;
  #191 = NameAndType        #189:#190     // formatString:(Ljava/lang/String;[Ljava/lang/Object;)Ljava/lang/String;
  #192 = Methodref          #143.#191     // org/scalatest/Resources$.formatString:(Ljava/lang/String;[Ljava/lang/Object;)Ljava/lang/String;
  #193 = Utf8               copy
  #194 = Utf8               copy$default$1
  #195 = Utf8               copy$default$2
  #196 = Utf8               copy$default$3
  #197 = Utf8               copy$default$4
  #198 = Utf8               copy$default$5
  #199 = Utf8               copy$default$6
  #200 = Utf8               copy$default$7
  #201 = Utf8               copy$default$8
  #202 = Utf8               copy$default$9
  #203 = Utf8               productPrefix
  #204 = Utf8               MatchResult
  #205 = String             #204          // MatchResult
  #206 = Utf8               productArity
  #207 = Utf8               ()I
  #208 = Utf8               productElement
  #209 = Utf8               (I)Ljava/lang/Object;
  #210 = Utf8               x$1
  #211 = Utf8               scala/runtime/BoxesRunTime
  #212 = Class              #211          // scala/runtime/BoxesRunTime
  #213 = Utf8               boxToBoolean
  #214 = Utf8               (Z)Ljava/lang/Boolean;
  #215 = NameAndType        #213:#214     // boxToBoolean:(Z)Ljava/lang/Boolean;
  #216 = Methodref          #212.#215     // scala/runtime/BoxesRunTime.boxToBoolean:(Z)Ljava/lang/Boolean;
  #217 = Utf8               scala/runtime/Statics
  #218 = Class              #217          // scala/runtime/Statics
  #219 = Utf8               ioobe
  #220 = NameAndType        #219:#209     // ioobe:(I)Ljava/lang/Object;
  #221 = Methodref          #218.#220     // scala/runtime/Statics.ioobe:(I)Ljava/lang/Object;
  #222 = Utf8               I
  #223 = Utf8               productIterator
  #224 = Utf8               ()Lscala/collection/Iterator<Ljava/lang/Object;>;
  #225 = Utf8               scala/runtime/ScalaRunTime$
  #226 = Class              #225          // scala/runtime/ScalaRunTime$
  #227 = Utf8               Lscala/runtime/ScalaRunTime$;
  #228 = NameAndType        #37:#227      // MODULE$:Lscala/runtime/ScalaRunTime$;
  #229 = Fieldref           #226.#228     // scala/runtime/ScalaRunTime$.MODULE$:Lscala/runtime/ScalaRunTime$;
  #230 = Utf8               typedProductIterator
  #231 = NameAndType        #230:#72      // typedProductIterator:(Lscala/Product;)Lscala/collection/Iterator;
  #232 = Methodref          #226.#231     // scala/runtime/ScalaRunTime$.typedProductIterator:(Lscala/Product;)Lscala/collection/Iterator;
  #233 = Utf8               canEqual
  #234 = Utf8               (Ljava/lang/Object;)Z
  #235 = Utf8               Ljava/lang/Object;
  #236 = Utf8               productElementName
  #237 = Utf8               (I)Ljava/lang/String;
  #238 = String             #18           // matches
  #239 = String             #20           // rawFailureMessage
  #240 = String             #22           // rawNegatedFailureMessage
  #241 = String             #23           // rawMidSentenceFailureMessage
  #242 = String             #24           // rawMidSentenceNegatedFailureMessage
  #243 = String             #25           // failureMessageArgs
  #244 = String             #28           // negatedFailureMessageArgs
  #245 = String             #29           // midSentenceFailureMessageArgs
  #246 = String             #30           // midSentenceNegatedFailureMessageArgs
  #247 = Utf8               hashCode
  #248 = Integer            -889275714
  #249 = NameAndType        #203:#79      // productPrefix:()Ljava/lang/String;
  #250 = Methodref          #2.#249       // org/scalatest/matchers/MatchResult.productPrefix:()Ljava/lang/String;
  #251 = NameAndType        #247:#207     // hashCode:()I
  #252 = Methodref          #116.#251     // java/lang/String.hashCode:()I
  #253 = Utf8               mix
  #254 = Utf8               (II)I
  #255 = NameAndType        #253:#254     // mix:(II)I
  #256 = Methodref          #218.#255     // scala/runtime/Statics.mix:(II)I
  #257 = Utf8               anyHash
  #258 = Utf8               (Ljava/lang/Object;)I
  #259 = NameAndType        #257:#258     // anyHash:(Ljava/lang/Object;)I
  #260 = Methodref          #218.#259     // scala/runtime/Statics.anyHash:(Ljava/lang/Object;)I
  #261 = Utf8               finalizeHash
  #262 = NameAndType        #261:#254     // finalizeHash:(II)I
  #263 = Methodref          #218.#262     // scala/runtime/Statics.finalizeHash:(II)I
  #264 = Utf8               toString
  #265 = Utf8               _toString
  #266 = Utf8               (Lscala/Product;)Ljava/lang/String;
  #267 = NameAndType        #265:#266     // _toString:(Lscala/Product;)Ljava/lang/String;
  #268 = Methodref          #226.#267     // scala/runtime/ScalaRunTime$._toString:(Lscala/Product;)Ljava/lang/String;
  #269 = Utf8               equals
  #270 = NameAndType        #269:#234     // equals:(Ljava/lang/Object;)Z
  #271 = Methodref          #4.#270       // java/lang/Object.equals:(Ljava/lang/Object;)Z
  #272 = NameAndType        #233:#234     // canEqual:(Ljava/lang/Object;)Z
  #273 = Methodref          #2.#272       // org/scalatest/matchers/MatchResult.canEqual:(Ljava/lang/Object;)Z
  #274 = Utf8               prettifier$1
  #275 = Utf8               arg
  #276 = Utf8               org/scalatest/matchers/LazyMessage
  #277 = Class              #276          // org/scalatest/matchers/LazyMessage
  #278 = Utf8               message
  #279 = NameAndType        #278:#99      // message:(Lorg/scalactic/Prettifier;)Ljava/lang/String;
  #280 = Methodref          #277.#279     // org/scalatest/matchers/LazyMessage.message:(Lorg/scalactic/Prettifier;)Ljava/lang/String;
  #281 = Utf8               org/scalactic/Prettifier
  #282 = Class              #281          // org/scalactic/Prettifier
  #283 = NameAndType        #44:#154      // apply:(Ljava/lang/Object;)Ljava/lang/String;
  #284 = InterfaceMethodref #282.#283     // org/scalactic/Prettifier.apply:(Ljava/lang/Object;)Ljava/lang/String;
  #285 = Utf8               (ZLjava/lang/String;Ljava/lang/String;Ljava/lang/String;Ljava/lang/String;Lscala/collection/immutable/IndexedSeq<Ljava/lang/Object;>;Lscala/collection/immutable/IndexedSeq<Ljava/lang/Object;>;Lscala/collection/immutable/IndexedSeq<Ljava/lang/Object;>;Lscala/collection/immutable/IndexedSeq<Ljava/lang/Object;>;)V
  #286 = Utf8               ()V
  #287 = NameAndType        #136:#286     // "<init>":()V
  #288 = Methodref          #4.#287       // java/lang/Object."<init>":()V
  #289 = Utf8               $init$
  #290 = Utf8               (Lscala/Product;)V
  #291 = NameAndType        #289:#290     // $init$:(Lscala/Product;)V
  #292 = InterfaceMethodref #6.#291       // scala/Product.$init$:(Lscala/Product;)V
  #293 = Utf8               (ZLjava/lang/String;Ljava/lang/String;)V
  #294 = Utf8               scala/package$
  #295 = Class              #294          // scala/package$
  #296 = Utf8               Lscala/package$;
  #297 = NameAndType        #37:#296      // MODULE$:Lscala/package$;
  #298 = Fieldref           #295.#297     // scala/package$.MODULE$:Lscala/package$;
  #299 = Utf8               Vector
  #300 = Utf8               ()Lscala/collection/immutable/Vector$;
  #301 = NameAndType        #299:#300     // Vector:()Lscala/collection/immutable/Vector$;
  #302 = Methodref          #295.#301     // scala/package$.Vector:()Lscala/collection/immutable/Vector$;
  #303 = Utf8               scala/collection/immutable/Vector$
  #304 = Class              #303          // scala/collection/immutable/Vector$
  #305 = Utf8               empty
  #306 = Utf8               ()Lscala/collection/immutable/Vector;
  #307 = NameAndType        #305:#306     // empty:()Lscala/collection/immutable/Vector;
  #308 = Methodref          #304.#307     // scala/collection/immutable/Vector$.empty:()Lscala/collection/immutable/Vector;
  #309 = Utf8               $deserializeLambda$
  #310 = Utf8               (Ljava/lang/invoke/SerializedLambda;)Ljava/lang/Object;
  #311 = Utf8               scala/runtime/LambdaDeserialize
  #312 = Class              #311          // scala/runtime/LambdaDeserialize
  #313 = Utf8               bootstrap
  #314 = Utf8               (Ljava/lang/invoke/MethodHandles$Lookup;Ljava/lang/String;Ljava/lang/invoke/MethodType;[Ljava/lang/invoke/MethodHandle;)Ljava/lang/invoke/CallSite;
  #315 = NameAndType        #313:#314     // bootstrap:(Ljava/lang/invoke/MethodHandles$Lookup;Ljava/lang/String;Ljava/lang/invoke/MethodType;[Ljava/lang/invoke/MethodHandle;)Ljava/lang/invoke/CallSite;
  #316 = Methodref          #312.#315     // scala/runtime/LambdaDeserialize.bootstrap:(Ljava/lang/invoke/MethodHandles$Lookup;Ljava/lang/String;Ljava/lang/invoke/MethodType;[Ljava/lang/invoke/MethodHandle;)Ljava/lang/invoke/CallSite;
  #317 = MethodHandle       6:#316        // REF_invokeStatic scala/runtime/LambdaDeserialize.bootstrap:(Ljava/lang/invoke/MethodHandles$Lookup;Ljava/lang/String;Ljava/lang/invoke/MethodType;[Ljava/lang/invoke/MethodHandle;)Ljava/lang/invoke/CallSite;
  #318 = Utf8               lambdaDeserialize
  #319 = NameAndType        #318:#310     // lambdaDeserialize:(Ljava/lang/invoke/SerializedLambda;)Ljava/lang/Object;
  #320 = InvokeDynamic      #1:#319       // #1:lambdaDeserialize:(Ljava/lang/invoke/SerializedLambda;)Ljava/lang/Object;
  #321 = Utf8               Signature
  #322 = Utf8               Code
  #323 = Utf8               LocalVariableTable
  #324 = Utf8               MethodParameters
  #325 = Utf8               LineNumberTable
  #326 = Utf8               StackMapTable
  #327 = Utf8               InnerClasses
  #328 = Utf8               SourceFile
  #329 = Utf8               RuntimeVisibleAnnotations
  #330 = Utf8               BootstrapMethods
  #331 = Utf8               ScalaInlineInfo
  #332 = Utf8               ScalaSig
{
  private final boolean matches;
    descriptor: Z
    flags: (0x0012) ACC_PRIVATE, ACC_FINAL

  private final java.lang.String rawFailureMessage;
    descriptor: Ljava/lang/String;
    flags: (0x0012) ACC_PRIVATE, ACC_FINAL

  private final java.lang.String rawNegatedFailureMessage;
    descriptor: Ljava/lang/String;
    flags: (0x0012) ACC_PRIVATE, ACC_FINAL

  private final java.lang.String rawMidSentenceFailureMessage;
    descriptor: Ljava/lang/String;
    flags: (0x0012) ACC_PRIVATE, ACC_FINAL

  private final java.lang.String rawMidSentenceNegatedFailureMessage;
    descriptor: Ljava/lang/String;
    flags: (0x0012) ACC_PRIVATE, ACC_FINAL

  private final scala.collection.immutable.IndexedSeq<java.lang.Object> failureMessageArgs;
    descriptor: Lscala/collection/immutable/IndexedSeq;
    flags: (0x0012) ACC_PRIVATE, ACC_FINAL
    Signature: #27                          // Lscala/collection/immutable/IndexedSeq<Ljava/lang/Object;>;

  private final scala.collection.immutable.IndexedSeq<java.lang.Object> negatedFailureMessageArgs;
    descriptor: Lscala/collection/immutable/IndexedSeq;
    flags: (0x0012) ACC_PRIVATE, ACC_FINAL
    Signature: #27                          // Lscala/collection/immutable/IndexedSeq<Ljava/lang/Object;>;

  private final scala.collection.immutable.IndexedSeq<java.lang.Object> midSentenceFailureMessageArgs;
    descriptor: Lscala/collection/immutable/IndexedSeq;
    flags: (0x0012) ACC_PRIVATE, ACC_FINAL
    Signature: #27                          // Lscala/collection/immutable/IndexedSeq<Ljava/lang/Object;>;

  private final scala.collection.immutable.IndexedSeq<java.lang.Object> midSentenceNegatedFailureMessageArgs;
    descriptor: Lscala/collection/immutable/IndexedSeq;
    flags: (0x0012) ACC_PRIVATE, ACC_FINAL
    Signature: #27                          // Lscala/collection/immutable/IndexedSeq<Ljava/lang/Object;>;

  public static scala.Option<scala.Tuple9<java.lang.Object, java.lang.String, java.lang.String, java.lang.String, java.lang.String, scala.collection.immutable.IndexedSeq<java.lang.Object>, scala.collection.immutable.IndexedSeq<java.lang.Object>, scala.collection.immutable.IndexedSeq<java.lang.Object>, scala.collection.immutable.IndexedSeq<java.lang.Object>>> unapply(org.scalatest.matchers.MatchResult);
    descriptor: (Lorg/scalatest/matchers/MatchResult;)Lscala/Option;
    flags: (0x0009) ACC_PUBLIC, ACC_STATIC
    Code:
      stack=2, locals=1, args_size=1
         0: getstatic     #40                 // Field org/scalatest/matchers/MatchResult$.MODULE$:Lorg/scalatest/matchers/MatchResult$;
         3: aload_0
         4: invokevirtual #42                 // Method org/scalatest/matchers/MatchResult$.unapply:(Lorg/scalatest/matchers/MatchResult;)Lscala/Option;
         7: areturn
      LocalVariableTable:
        Start  Length  Slot  Name   Signature
            0       8     0   x$0   Lorg/scalatest/matchers/MatchResult;
    Signature: #33                          // (Lorg/scalatest/matchers/MatchResult;)Lscala/Option<Lscala/Tuple9<Ljava/lang/Object;Ljava/lang/String;Ljava/lang/String;Ljava/lang/String;Ljava/lang/String;Lscala/collection/immutable/IndexedSeq<Ljava/lang/Object;>;Lscala/collection/immutable/IndexedSeq<Ljava/lang/Object;>;Lscala/collection/immutable/IndexedSeq<Ljava/lang/Object;>;Lscala/collection/immutable/IndexedSeq<Ljava/lang/Object;>;>;>;
    MethodParameters:
      Name                           Flags
      x$0                            final

  public static org.scalatest.matchers.MatchResult apply(boolean, java.lang.String, java.lang.String, java.lang.String, java.lang.String, scala.collection.immutable.IndexedSeq<java.lang.Object>, scala.collection.immutable.IndexedSeq<java.lang.Object>, scala.collection.immutable.IndexedSeq<java.lang.Object>, scala.collection.immutable.IndexedSeq<java.lang.Object>);
    descriptor: (ZLjava/lang/String;Ljava/lang/String;Ljava/lang/String;Ljava/lang/String;Lscala/collection/immutable/IndexedSeq;Lscala/collection/immutable/IndexedSeq;Lscala/collection/immutable/IndexedSeq;Lscala/collection/immutable/IndexedSeq;)Lorg/scalatest/matchers/MatchResult;
    flags: (0x0009) ACC_PUBLIC, ACC_STATIC
    Code:
      stack=10, locals=9, args_size=9
         0: getstatic     #40                 // Field org/scalatest/matchers/MatchResult$.MODULE$:Lorg/scalatest/matchers/MatchResult$;
         3: iload_0
         4: aload_1
         5: aload_2
         6: aload_3
         7: aload         4
         9: aload         5
        11: aload         6
        13: aload         7
        15: aload         8
        17: invokevirtual #48                 // Method org/scalatest/matchers/MatchResult$.apply:(ZLjava/lang/String;Ljava/lang/String;Ljava/lang/String;Ljava/lang/String;Lscala/collection/immutable/IndexedSeq;Lscala/collection/immutable/IndexedSeq;Lscala/collection/immutable/IndexedSeq;Lscala/collection/immutable/IndexedSeq;)Lorg/scalatest/matchers/MatchResult;
        20: areturn
      LocalVariableTable:
        Start  Length  Slot  Name   Signature
            0      21     0 matches   Z
            0      21     1 rawFailureMessage   Ljava/lang/String;
            0      21     2 rawNegatedFailureMessage   Ljava/lang/String;
            0      21     3 rawMidSentenceFailureMessage   Ljava/lang/String;
            0      21     4 rawMidSentenceNegatedFailureMessage   Ljava/lang/String;
            0      21     5 failureMessageArgs   Lscala/collection/immutable/IndexedSeq;
            0      21     6 negatedFailureMessageArgs   Lscala/collection/immutable/IndexedSeq;
            0      21     7 midSentenceFailureMessageArgs   Lscala/collection/immutable/IndexedSeq;
            0      21     8 midSentenceNegatedFailureMessageArgs   Lscala/collection/immutable/IndexedSeq;
    Signature: #46                          // (ZLjava/lang/String;Ljava/lang/String;Ljava/lang/String;Ljava/lang/String;Lscala/collection/immutable/IndexedSeq<Ljava/lang/Object;>;Lscala/collection/immutable/IndexedSeq<Ljava/lang/Object;>;Lscala/collection/immutable/IndexedSeq<Ljava/lang/Object;>;Lscala/collection/immutable/IndexedSeq<Ljava/lang/Object;>;)Lorg/scalatest/matchers/MatchResult;
    MethodParameters:
      Name                           Flags
      matches                        final
      rawFailureMessage              final
      rawNegatedFailureMessage       final
      rawMidSentenceFailureMessage   final
      rawMidSentenceNegatedFailureMessagefinal
      failureMessageArgs             final
      negatedFailureMessageArgs      final
      midSentenceFailureMessageArgs  final
      midSentenceNegatedFailureMessageArgsfinal

  public static org.scalatest.matchers.MatchResult apply(boolean, java.lang.String, java.lang.String, scala.collection.immutable.IndexedSeq<java.lang.Object>, scala.collection.immutable.IndexedSeq<java.lang.Object>);
    descriptor: (ZLjava/lang/String;Ljava/lang/String;Lscala/collection/immutable/IndexedSeq;Lscala/collection/immutable/IndexedSeq;)Lorg/scalatest/matchers/MatchResult;
    flags: (0x0009) ACC_PUBLIC, ACC_STATIC
    Code:
      stack=6, locals=5, args_size=5
         0: getstatic     #40                 // Field org/scalatest/matchers/MatchResult$.MODULE$:Lorg/scalatest/matchers/MatchResult$;
         3: iload_0
         4: aload_1
         5: aload_2
         6: aload_3
         7: aload         4
         9: invokevirtual #52                 // Method org/scalatest/matchers/MatchResult$.apply:(ZLjava/lang/String;Ljava/lang/String;Lscala/collection/immutable/IndexedSeq;Lscala/collection/immutable/IndexedSeq;)Lorg/scalatest/matchers/MatchResult;
        12: areturn
      LocalVariableTable:
        Start  Length  Slot  Name   Signature
            0      13     0 matches   Z
            0      13     1 rawFailureMessage   Ljava/lang/String;
            0      13     2 rawNegatedFailureMessage   Ljava/lang/String;
            0      13     3 failureMessageArgs   Lscala/collection/immutable/IndexedSeq;
            0      13     4 negatedFailureMessageArgs   Lscala/collection/immutable/IndexedSeq;
    Signature: #50                          // (ZLjava/lang/String;Ljava/lang/String;Lscala/collection/immutable/IndexedSeq<Ljava/lang/Object;>;Lscala/collection/immutable/IndexedSeq<Ljava/lang/Object;>;)Lorg/scalatest/matchers/MatchResult;
    MethodParameters:
      Name                           Flags
      matches                        final
      rawFailureMessage              final
      rawNegatedFailureMessage       final
      failureMessageArgs             final
      negatedFailureMessageArgs      final

  public static org.scalatest.matchers.MatchResult apply(boolean, java.lang.String, java.lang.String, scala.collection.immutable.IndexedSeq<java.lang.Object>);
    descriptor: (ZLjava/lang/String;Ljava/lang/String;Lscala/collection/immutable/IndexedSeq;)Lorg/scalatest/matchers/MatchResult;
    flags: (0x0009) ACC_PUBLIC, ACC_STATIC
    Code:
      stack=5, locals=4, args_size=4
         0: getstatic     #40                 // Field org/scalatest/matchers/MatchResult$.MODULE$:Lorg/scalatest/matchers/MatchResult$;
         3: iload_0
         4: aload_1
         5: aload_2
         6: aload_3
         7: invokevirtual #57                 // Method org/scalatest/matchers/MatchResult$.apply:(ZLjava/lang/String;Ljava/lang/String;Lscala/collection/immutable/IndexedSeq;)Lorg/scalatest/matchers/MatchResult;
        10: areturn
      LocalVariableTable:
        Start  Length  Slot  Name   Signature
            0      11     0 matches   Z
            0      11     1 rawFailureMessage   Ljava/lang/String;
            0      11     2 rawNegatedFailureMessage   Ljava/lang/String;
            0      11     3  args   Lscala/collection/immutable/IndexedSeq;
    Signature: #54                          // (ZLjava/lang/String;Ljava/lang/String;Lscala/collection/immutable/IndexedSeq<Ljava/lang/Object;>;)Lorg/scalatest/matchers/MatchResult;
    MethodParameters:
      Name                           Flags
      matches                        final
      rawFailureMessage              final
      rawNegatedFailureMessage       final
      args                           final

  public static org.scalatest.matchers.MatchResult apply(boolean, java.lang.String, java.lang.String);
    descriptor: (ZLjava/lang/String;Ljava/lang/String;)Lorg/scalatest/matchers/MatchResult;
    flags: (0x0009) ACC_PUBLIC, ACC_STATIC
    Code:
      stack=4, locals=3, args_size=3
         0: getstatic     #40                 // Field org/scalatest/matchers/MatchResult$.MODULE$:Lorg/scalatest/matchers/MatchResult$;
         3: iload_0
         4: aload_1
         5: aload_2
         6: invokevirtual #60                 // Method org/scalatest/matchers/MatchResult$.apply:(ZLjava/lang/String;Ljava/lang/String;)Lorg/scalatest/matchers/MatchResult;
         9: areturn
      LocalVariableTable:
        Start  Length  Slot  Name   Signature
            0      10     0 matches   Z
            0      10     1 rawFailureMessage   Ljava/lang/String;
            0      10     2 rawNegatedFailureMessage   Ljava/lang/String;
    MethodParameters:
      Name                           Flags
      matches                        final
      rawFailureMessage              final
      rawNegatedFailureMessage       final

  public static org.scalatest.matchers.MatchResult apply(boolean, java.lang.String, java.lang.String, java.lang.String, java.lang.String);
    descriptor: (ZLjava/lang/String;Ljava/lang/String;Ljava/lang/String;Ljava/lang/String;)Lorg/scalatest/matchers/MatchResult;
    flags: (0x0009) ACC_PUBLIC, ACC_STATIC
    Code:
      stack=6, locals=5, args_size=5
         0: getstatic     #40                 // Field org/scalatest/matchers/MatchResult$.MODULE$:Lorg/scalatest/matchers/MatchResult$;
         3: iload_0
         4: aload_1
         5: aload_2
         6: aload_3
         7: aload         4
         9: invokevirtual #63                 // Method org/scalatest/matchers/MatchResult$.apply:(ZLjava/lang/String;Ljava/lang/String;Ljava/lang/String;Ljava/lang/String;)Lorg/scalatest/matchers/MatchResult;
        12: areturn
      LocalVariableTable:
        Start  Length  Slot  Name   Signature
            0      13     0 matches   Z
            0      13     1 rawFailureMessage   Ljava/lang/String;
            0      13     2 rawNegatedFailureMessage   Ljava/lang/String;
            0      13     3 rawMidSentenceFailureMessage   Ljava/lang/String;
            0      13     4 rawMidSentenceNegatedFailureMessage   Ljava/lang/String;
    MethodParameters:
      Name                           Flags
      matches                        final
      rawFailureMessage              final
      rawNegatedFailureMessage       final
      rawMidSentenceFailureMessage   final
      rawMidSentenceNegatedFailureMessagefinal

  public static org.scalatest.matchers.MatchResult apply(boolean, java.lang.String, java.lang.String, java.lang.String, java.lang.String, scala.collection.immutable.IndexedSeq<java.lang.Object>, scala.collection.immutable.IndexedSeq<java.lang.Object>);
    descriptor: (ZLjava/lang/String;Ljava/lang/String;Ljava/lang/String;Ljava/lang/String;Lscala/collection/immutable/IndexedSeq;Lscala/collection/immutable/IndexedSeq;)Lorg/scalatest/matchers/MatchResult;
    flags: (0x0009) ACC_PUBLIC, ACC_STATIC
    Code:
      stack=8, locals=7, args_size=7
         0: getstatic     #40                 // Field org/scalatest/matchers/MatchResult$.MODULE$:Lorg/scalatest/matchers/MatchResult$;
         3: iload_0
         4: aload_1
         5: aload_2
         6: aload_3
         7: aload         4
         9: aload         5
        11: aload         6
        13: invokevirtual #67                 // Method org/scalatest/matchers/MatchResult$.apply:(ZLjava/lang/String;Ljava/lang/String;Ljava/lang/String;Ljava/lang/String;Lscala/collection/immutable/IndexedSeq;Lscala/collection/immutable/IndexedSeq;)Lorg/scalatest/matchers/MatchResult;
        16: areturn
      LocalVariableTable:
        Start  Length  Slot  Name   Signature
            0      17     0 matches   Z
            0      17     1 rawFailureMessage   Ljava/lang/String;
            0      17     2 rawNegatedFailureMessage   Ljava/lang/String;
            0      17     3 rawMidSentenceFailureMessage   Ljava/lang/String;
            0      17     4 rawMidSentenceNegatedFailureMessage   Ljava/lang/String;
            0      17     5 failureMessageArgs   Lscala/collection/immutable/IndexedSeq;
            0      17     6 negatedFailureMessageArgs   Lscala/collection/immutable/IndexedSeq;
    Signature: #65                          // (ZLjava/lang/String;Ljava/lang/String;Ljava/lang/String;Ljava/lang/String;Lscala/collection/immutable/IndexedSeq<Ljava/lang/Object;>;Lscala/collection/immutable/IndexedSeq<Ljava/lang/Object;>;)Lorg/scalatest/matchers/MatchResult;
    MethodParameters:
      Name                           Flags
      matches                        final
      rawFailureMessage              final
      rawNegatedFailureMessage       final
      rawMidSentenceFailureMessage   final
      rawMidSentenceNegatedFailureMessagefinal
      failureMessageArgs             final
      negatedFailureMessageArgs      final

  public scala.collection.Iterator<java.lang.String> productElementNames();
    descriptor: ()Lscala/collection/Iterator;
    flags: (0x0001) ACC_PUBLIC
    Code:
      stack=1, locals=1, args_size=1
         0: aload_0
         1: invokestatic  #74                 // InterfaceMethod scala/Product.productElementNames$:(Lscala/Product;)Lscala/collection/Iterator;
         4: areturn
      LineNumberTable:
        line 198: 0
      LocalVariableTable:
        Start  Length  Slot  Name   Signature
            0       5     0  this   Lorg/scalatest/matchers/MatchResult;
    Signature: #70                          // ()Lscala/collection/Iterator<Ljava/lang/String;>;

  public boolean matches();
    descriptor: ()Z
    flags: (0x0001) ACC_PUBLIC
    Code:
      stack=1, locals=1, args_size=1
         0: aload_0
         1: getfield      #78                 // Field matches:Z
         4: ireturn
      LineNumberTable:
        line 199: 0
      LocalVariableTable:
        Start  Length  Slot  Name   Signature
            0       5     0  this   Lorg/scalatest/matchers/MatchResult;

  public java.lang.String rawFailureMessage();
    descriptor: ()Ljava/lang/String;
    flags: (0x0001) ACC_PUBLIC
    Code:
      stack=1, locals=1, args_size=1
         0: aload_0
         1: getfield      #81                 // Field rawFailureMessage:Ljava/lang/String;
         4: areturn
      LineNumberTable:
        line 200: 0
      LocalVariableTable:
        Start  Length  Slot  Name   Signature
            0       5     0  this   Lorg/scalatest/matchers/MatchResult;

  public java.lang.String rawNegatedFailureMessage();
    descriptor: ()Ljava/lang/String;
    flags: (0x0001) ACC_PUBLIC
    Code:
      stack=1, locals=1, args_size=1
         0: aload_0
         1: getfield      #83                 // Field rawNegatedFailureMessage:Ljava/lang/String;
         4: areturn
      LineNumberTable:
        line 201: 0
      LocalVariableTable:
        Start  Length  Slot  Name   Signature
            0       5     0  this   Lorg/scalatest/matchers/MatchResult;

  public java.lang.String rawMidSentenceFailureMessage();
    descriptor: ()Ljava/lang/String;
    flags: (0x0001) ACC_PUBLIC
    Code:
      stack=1, locals=1, args_size=1
         0: aload_0
         1: getfield      #85                 // Field rawMidSentenceFailureMessage:Ljava/lang/String;
         4: areturn
      LineNumberTable:
        line 202: 0
      LocalVariableTable:
        Start  Length  Slot  Name   Signature
            0       5     0  this   Lorg/scalatest/matchers/MatchResult;

  public java.lang.String rawMidSentenceNegatedFailureMessage();
    descriptor: ()Ljava/lang/String;
    flags: (0x0001) ACC_PUBLIC
    Code:
      stack=1, locals=1, args_size=1
         0: aload_0
         1: getfield      #87                 // Field rawMidSentenceNegatedFailureMessage:Ljava/lang/String;
         4: areturn
      LineNumberTable:
        line 203: 0
      LocalVariableTable:
        Start  Length  Slot  Name   Signature
            0       5     0  this   Lorg/scalatest/matchers/MatchResult;

  public scala.collection.immutable.IndexedSeq<java.lang.Object> failureMessageArgs();
    descriptor: ()Lscala/collection/immutable/IndexedSeq;
    flags: (0x0001) ACC_PUBLIC
    Code:
      stack=1, locals=1, args_size=1
         0: aload_0
         1: getfield      #91                 // Field failureMessageArgs:Lscala/collection/immutable/IndexedSeq;
         4: areturn
      LineNumberTable:
        line 204: 0
      LocalVariableTable:
        Start  Length  Slot  Name   Signature
            0       5     0  this   Lorg/scalatest/matchers/MatchResult;
    Signature: #89                          // ()Lscala/collection/immutable/IndexedSeq<Ljava/lang/Object;>;

  public scala.collection.immutable.IndexedSeq<java.lang.Object> negatedFailureMessageArgs();
    descriptor: ()Lscala/collection/immutable/IndexedSeq;
    flags: (0x0001) ACC_PUBLIC
    Code:
      stack=1, locals=1, args_size=1
         0: aload_0
         1: getfield      #93                 // Field negatedFailureMessageArgs:Lscala/collection/immutable/IndexedSeq;
         4: areturn
      LineNumberTable:
        line 205: 0
      LocalVariableTable:
        Start  Length  Slot  Name   Signature
            0       5     0  this   Lorg/scalatest/matchers/MatchResult;
    Signature: #89                          // ()Lscala/collection/immutable/IndexedSeq<Ljava/lang/Object;>;

  public scala.collection.immutable.IndexedSeq<java.lang.Object> midSentenceFailureMessageArgs();
    descriptor: ()Lscala/collection/immutable/IndexedSeq;
    flags: (0x0001) ACC_PUBLIC
    Code:
      stack=1, locals=1, args_size=1
         0: aload_0
         1: getfield      #95                 // Field midSentenceFailureMessageArgs:Lscala/collection/immutable/IndexedSeq;
         4: areturn
      LineNumberTable:
        line 206: 0
      LocalVariableTable:
        Start  Length  Slot  Name   Signature
            0       5     0  this   Lorg/scalatest/matchers/MatchResult;
    Signature: #89                          // ()Lscala/collection/immutable/IndexedSeq<Ljava/lang/Object;>;

  public scala.collection.immutable.IndexedSeq<java.lang.Object> midSentenceNegatedFailureMessageArgs();
    descriptor: ()Lscala/collection/immutable/IndexedSeq;
    flags: (0x0001) ACC_PUBLIC
    Code:
      stack=1, locals=1, args_size=1
         0: aload_0
         1: getfield      #97                 // Field midSentenceNegatedFailureMessageArgs:Lscala/collection/immutable/IndexedSeq;
         4: areturn
      LineNumberTable:
        line 207: 0
      LocalVariableTable:
        Start  Length  Slot  Name   Signature
            0       5     0  this   Lorg/scalatest/matchers/MatchResult;
    Signature: #89                          // ()Lscala/collection/immutable/IndexedSeq<Ljava/lang/Object;>;

  public java.lang.String failureMessage(org.scalactic.Prettifier);
    descriptor: (Lorg/scalactic/Prettifier;)Ljava/lang/String;
    flags: (0x0001) ACC_PUBLIC
    Code:
      stack=4, locals=2, args_size=2
         0: aload_0
         1: invokevirtual #102                // Method failureMessageArgs:()Lscala/collection/immutable/IndexedSeq;
         4: invokeinterface #107,  1          // InterfaceMethod scala/collection/immutable/IndexedSeq.isEmpty:()Z
         9: ifeq          19
        12: aload_0
        13: invokevirtual #109                // Method rawFailureMessage:()Ljava/lang/String;
        16: goto          32
        19: aload_0
        20: aload_0
        21: invokevirtual #109                // Method rawFailureMessage:()Ljava/lang/String;
        24: aload_0
        25: invokevirtual #102                // Method failureMessageArgs:()Lscala/collection/immutable/IndexedSeq;
        28: aload_1
        29: invokespecial #113                // Method makeString:(Ljava/lang/String;Lscala/collection/immutable/IndexedSeq;Lorg/scalactic/Prettifier;)Ljava/lang/String;
        32: areturn
      StackMapTable: number_of_entries = 2
        frame_type = 19 /* same */
        frame_type = 76 /* same_locals_1_stack_item */
          stack = [ class java/lang/String ]
      LineNumberTable:
        line 240: 0
      LocalVariableTable:
        Start  Length  Slot  Name   Signature
            0      33     0  this   Lorg/scalatest/matchers/MatchResult;
            0      33     1 prettifier   Lorg/scalactic/Prettifier;
    MethodParameters:
      Name                           Flags
      prettifier                     final

  public java.lang.String negatedFailureMessage(org.scalactic.Prettifier);
    descriptor: (Lorg/scalactic/Prettifier;)Ljava/lang/String;
    flags: (0x0001) ACC_PUBLIC
    Code:
      stack=4, locals=2, args_size=2
         0: aload_0
         1: invokevirtual #119                // Method negatedFailureMessageArgs:()Lscala/collection/immutable/IndexedSeq;
         4: invokeinterface #107,  1          // InterfaceMethod scala/collection/immutable/IndexedSeq.isEmpty:()Z
         9: ifeq          19
        12: aload_0
        13: invokevirtual #121                // Method rawNegatedFailureMessage:()Ljava/lang/String;
        16: goto          32
        19: aload_0
        20: aload_0
        21: invokevirtual #121                // Method rawNegatedFailureMessage:()Ljava/lang/String;
        24: aload_0
        25: invokevirtual #119                // Method negatedFailureMessageArgs:()Lscala/collection/immutable/IndexedSeq;
        28: aload_1
        29: invokespecial #113                // Method makeString:(Ljava/lang/String;Lscala/collection/immutable/IndexedSeq;Lorg/scalactic/Prettifier;)Ljava/lang/String;
        32: areturn
      StackMapTable: number_of_entries = 2
        frame_type = 19 /* same */
        frame_type = 76 /* same_locals_1_stack_item */
          stack = [ class java/lang/String ]
      LineNumberTable:
        line 247: 0
      LocalVariableTable:
        Start  Length  Slot  Name   Signature
            0      33     0  this   Lorg/scalatest/matchers/MatchResult;
            0      33     1 prettifier   Lorg/scalactic/Prettifier;
    MethodParameters:
      Name                           Flags
      prettifier                     final

  public java.lang.String midSentenceFailureMessage(org.scalactic.Prettifier);
    descriptor: (Lorg/scalactic/Prettifier;)Ljava/lang/String;
    flags: (0x0001) ACC_PUBLIC
    Code:
      stack=4, locals=2, args_size=2
         0: aload_0
         1: invokevirtual #124                // Method midSentenceFailureMessageArgs:()Lscala/collection/immutable/IndexedSeq;
         4: invokeinterface #107,  1          // InterfaceMethod scala/collection/immutable/IndexedSeq.isEmpty:()Z
         9: ifeq          19
        12: aload_0
        13: invokevirtual #126                // Method rawMidSentenceFailureMessage:()Ljava/lang/String;
        16: goto          32
        19: aload_0
        20: aload_0
        21: invokevirtual #126                // Method rawMidSentenceFailureMessage:()Ljava/lang/String;
        24: aload_0
        25: invokevirtual #124                // Method midSentenceFailureMessageArgs:()Lscala/collection/immutable/IndexedSeq;
        28: aload_1
        29: invokespecial #113                // Method makeString:(Ljava/lang/String;Lscala/collection/immutable/IndexedSeq;Lorg/scalactic/Prettifier;)Ljava/lang/String;
        32: areturn
      StackMapTable: number_of_entries = 2
        frame_type = 19 /* same */
        frame_type = 76 /* same_locals_1_stack_item */
          stack = [ class java/lang/String ]
      LineNumberTable:
        line 254: 0
      LocalVariableTable:
        Start  Length  Slot  Name   Signature
            0      33     0  this   Lorg/scalatest/matchers/MatchResult;
            0      33     1 prettifier   Lorg/scalactic/Prettifier;
    MethodParameters:
      Name                           Flags
      prettifier                     final

  public java.lang.String midSentenceNegatedFailureMessage(org.scalactic.Prettifier);
    descriptor: (Lorg/scalactic/Prettifier;)Ljava/lang/String;
    flags: (0x0001) ACC_PUBLIC
    Code:
      stack=4, locals=2, args_size=2
         0: aload_0
         1: invokevirtual #129                // Method midSentenceNegatedFailureMessageArgs:()Lscala/collection/immutable/IndexedSeq;
         4: invokeinterface #107,  1          // InterfaceMethod scala/collection/immutable/IndexedSeq.isEmpty:()Z
         9: ifeq          19
        12: aload_0
        13: invokevirtual #131                // Method rawMidSentenceNegatedFailureMessage:()Ljava/lang/String;
        16: goto          32
        19: aload_0
        20: aload_0
        21: invokevirtual #131                // Method rawMidSentenceNegatedFailureMessage:()Ljava/lang/String;
        24: aload_0
        25: invokevirtual #129                // Method midSentenceNegatedFailureMessageArgs:()Lscala/collection/immutable/IndexedSeq;
        28: aload_1
        29: invokespecial #113                // Method makeString:(Ljava/lang/String;Lscala/collection/immutable/IndexedSeq;Lorg/scalactic/Prettifier;)Ljava/lang/String;
        32: areturn
      StackMapTable: number_of_entries = 2
        frame_type = 19 /* same */
        frame_type = 76 /* same_locals_1_stack_item */
          stack = [ class java/lang/String ]
      LineNumberTable:
        line 261: 0
      LocalVariableTable:
        Start  Length  Slot  Name   Signature
            0      33     0  this   Lorg/scalatest/matchers/MatchResult;
            0      33     1 prettifier   Lorg/scalactic/Prettifier;
    MethodParameters:
      Name                           Flags
      prettifier                     final

  public org.scalatest.matchers.MatchResult negated();
    descriptor: ()Lorg/scalatest/matchers/MatchResult;
    flags: (0x0001) ACC_PUBLIC
    Code:
      stack=11, locals=1, args_size=1
         0: new           #2                  // class org/scalatest/matchers/MatchResult
         3: dup
         4: aload_0
         5: invokevirtual #135                // Method matches:()Z
         8: ifne          15
        11: iconst_1
        12: goto          16
        15: iconst_0
        16: aload_0
        17: invokevirtual #121                // Method rawNegatedFailureMessage:()Ljava/lang/String;
        20: aload_0
        21: invokevirtual #109                // Method rawFailureMessage:()Ljava/lang/String;
        24: aload_0
        25: invokevirtual #131                // Method rawMidSentenceNegatedFailureMessage:()Ljava/lang/String;
        28: aload_0
        29: invokevirtual #126                // Method rawMidSentenceFailureMessage:()Ljava/lang/String;
        32: aload_0
        33: invokevirtual #119                // Method negatedFailureMessageArgs:()Lscala/collection/immutable/IndexedSeq;
        36: aload_0
        37: invokevirtual #102                // Method failureMessageArgs:()Lscala/collection/immutable/IndexedSeq;
        40: aload_0
        41: invokevirtual #129                // Method midSentenceNegatedFailureMessageArgs:()Lscala/collection/immutable/IndexedSeq;
        44: aload_0
        45: invokevirtual #124                // Method midSentenceFailureMessageArgs:()Lscala/collection/immutable/IndexedSeq;
        48: invokespecial #139                // Method "<init>":(ZLjava/lang/String;Ljava/lang/String;Ljava/lang/String;Ljava/lang/String;Lscala/collection/immutable/IndexedSeq;Lscala/collection/immutable/IndexedSeq;Lscala/collection/immutable/IndexedSeq;Lscala/collection/immutable/IndexedSeq;)V
        51: areturn
      StackMapTable: number_of_entries = 2
        frame_type = 255 /* full_frame */
          offset_delta = 15
          locals = [ class org/scalatest/matchers/MatchResult ]
          stack = [ uninitialized 0, uninitialized 0 ]
        frame_type = 255 /* full_frame */
          offset_delta = 0
          locals = [ class org/scalatest/matchers/MatchResult ]
          stack = [ uninitialized 0, uninitialized 0, int ]
      LineNumberTable:
        line 268: 0
      LocalVariableTable:
        Start  Length  Slot  Name   Signature
            0      52     0  this   Lorg/scalatest/matchers/MatchResult;

  private java.lang.String makeString(java.lang.String, scala.collection.immutable.IndexedSeq<java.lang.Object>, org.scalactic.Prettifier);
    descriptor: (Ljava/lang/String;Lscala/collection/immutable/IndexedSeq;Lorg/scalactic/Prettifier;)Ljava/lang/String;
    flags: (0x0002) ACC_PRIVATE
    Code:
      stack=4, locals=4, args_size=4
         0: getstatic     #146                // Field org/scalatest/Resources$.MODULE$:Lorg/scalatest/Resources$;
         3: aload_1
         4: aload_2
         5: aload_3
         6: invokedynamic #167,  0            // InvokeDynamic #0:apply:(Lorg/scalactic/Prettifier;)Lscala/Function1;
        11: invokeinterface #171,  2          // InterfaceMethod scala/collection/immutable/IndexedSeq.map:(Lscala/Function1;)Ljava/lang/Object;
        16: checkcast     #173                // class scala/collection/IterableOnceOps
        19: getstatic     #178                // Field scala/reflect/ClassTag$.MODULE$:Lscala/reflect/ClassTag$;
        22: invokevirtual #182                // Method scala/reflect/ClassTag$.Any:()Lscala/reflect/ClassTag;
        25: invokeinterface #186,  2          // InterfaceMethod scala/collection/IterableOnceOps.toArray:(Lscala/reflect/ClassTag;)Ljava/lang/Object;
        30: checkcast     #188                // class "[Ljava/lang/Object;"
        33: invokevirtual #192                // Method org/scalatest/Resources$.formatString:(Ljava/lang/String;[Ljava/lang/Object;)Ljava/lang/String;
        36: areturn
      LineNumberTable:
        line 271: 0
      LocalVariableTable:
        Start  Length  Slot  Name   Signature
            0      37     0  this   Lorg/scalatest/matchers/MatchResult;
            0      37     1 rawString   Ljava/lang/String;
            0      37     2  args   Lscala/collection/immutable/IndexedSeq;
            0      37     3 prettifier   Lorg/scalactic/Prettifier;
    Signature: #140                         // (Ljava/lang/String;Lscala/collection/immutable/IndexedSeq<Ljava/lang/Object;>;Lorg/scalactic/Prettifier;)Ljava/lang/String;
    MethodParameters:
      Name                           Flags
      rawString                      final
      args                           final
      prettifier                     final

  public org.scalatest.matchers.MatchResult copy(boolean, java.lang.String, java.lang.String, java.lang.String, java.lang.String, scala.collection.immutable.IndexedSeq<java.lang.Object>, scala.collection.immutable.IndexedSeq<java.lang.Object>, scala.collection.immutable.IndexedSeq<java.lang.Object>, scala.collection.immutable.IndexedSeq<java.lang.Object>);
    descriptor: (ZLjava/lang/String;Ljava/lang/String;Ljava/lang/String;Ljava/lang/String;Lscala/collection/immutable/IndexedSeq;Lscala/collection/immutable/IndexedSeq;Lscala/collection/immutable/IndexedSeq;Lscala/collection/immutable/IndexedSeq;)Lorg/scalatest/matchers/MatchResult;
    flags: (0x0001) ACC_PUBLIC
    Code:
      stack=11, locals=10, args_size=10
         0: new           #2                  // class org/scalatest/matchers/MatchResult
         3: dup
         4: iload_1
         5: aload_2
         6: aload_3
         7: aload         4
         9: aload         5
        11: aload         6
        13: aload         7
        15: aload         8
        17: aload         9
        19: invokespecial #139                // Method "<init>":(ZLjava/lang/String;Ljava/lang/String;Ljava/lang/String;Ljava/lang/String;Lscala/collection/immutable/IndexedSeq;Lscala/collection/immutable/IndexedSeq;Lscala/collection/immutable/IndexedSeq;Lscala/collection/immutable/IndexedSeq;)V
        22: areturn
      LineNumberTable:
        line 198: 0
        line 199: 4
        line 200: 5
        line 201: 6
        line 202: 7
        line 203: 9
        line 204: 11
        line 205: 13
        line 206: 15
        line 207: 17
      LocalVariableTable:
        Start  Length  Slot  Name   Signature
            0      23     0  this   Lorg/scalatest/matchers/MatchResult;
            0      23     1 matches   Z
            0      23     2 rawFailureMessage   Ljava/lang/String;
            0      23     3 rawNegatedFailureMessage   Ljava/lang/String;
            0      23     4 rawMidSentenceFailureMessage   Ljava/lang/String;
            0      23     5 rawMidSentenceNegatedFailureMessage   Ljava/lang/String;
            0      23     6 failureMessageArgs   Lscala/collection/immutable/IndexedSeq;
            0      23     7 negatedFailureMessageArgs   Lscala/collection/immutable/IndexedSeq;
            0      23     8 midSentenceFailureMessageArgs   Lscala/collection/immutable/IndexedSeq;
            0      23     9 midSentenceNegatedFailureMessageArgs   Lscala/collection/immutable/IndexedSeq;
    Signature: #46                          // (ZLjava/lang/String;Ljava/lang/String;Ljava/lang/String;Ljava/lang/String;Lscala/collection/immutable/IndexedSeq<Ljava/lang/Object;>;Lscala/collection/immutable/IndexedSeq<Ljava/lang/Object;>;Lscala/collection/immutable/IndexedSeq<Ljava/lang/Object;>;Lscala/collection/immutable/IndexedSeq<Ljava/lang/Object;>;)Lorg/scalatest/matchers/MatchResult;
    MethodParameters:
      Name                           Flags
      matches                        final
      rawFailureMessage              final
      rawNegatedFailureMessage       final
      rawMidSentenceFailureMessage   final
      rawMidSentenceNegatedFailureMessagefinal
      failureMessageArgs             final
      negatedFailureMessageArgs      final
      midSentenceFailureMessageArgs  final
      midSentenceNegatedFailureMessageArgsfinal

  public boolean copy$default$1();
    descriptor: ()Z
    flags: (0x0001) ACC_PUBLIC
    Code:
      stack=1, locals=1, args_size=1
         0: aload_0
         1: invokevirtual #135                // Method matches:()Z
         4: ireturn
      LineNumberTable:
        line 199: 0
      LocalVariableTable:
        Start  Length  Slot  Name   Signature
            0       5     0  this   Lorg/scalatest/matchers/MatchResult;

  public java.lang.String copy$default$2();
    descriptor: ()Ljava/lang/String;
    flags: (0x0001) ACC_PUBLIC
    Code:
      stack=1, locals=1, args_size=1
         0: aload_0
         1: invokevirtual #109                // Method rawFailureMessage:()Ljava/lang/String;
         4: areturn
      LineNumberTable:
        line 200: 0
      LocalVariableTable:
        Start  Length  Slot  Name   Signature
            0       5     0  this   Lorg/scalatest/matchers/MatchResult;

  public java.lang.String copy$default$3();
    descriptor: ()Ljava/lang/String;
    flags: (0x0001) ACC_PUBLIC
    Code:
      stack=1, locals=1, args_size=1
         0: aload_0
         1: invokevirtual #121                // Method rawNegatedFailureMessage:()Ljava/lang/String;
         4: areturn
      LineNumberTable:
        line 201: 0
      LocalVariableTable:
        Start  Length  Slot  Name   Signature
            0       5     0  this   Lorg/scalatest/matchers/MatchResult;

  public java.lang.String copy$default$4();
    descriptor: ()Ljava/lang/String;
    flags: (0x0001) ACC_PUBLIC
    Code:
      stack=1, locals=1, args_size=1
         0: aload_0
         1: invokevirtual #126                // Method rawMidSentenceFailureMessage:()Ljava/lang/String;
         4: areturn
      LineNumberTable:
        line 202: 0
      LocalVariableTable:
        Start  Length  Slot  Name   Signature
            0       5     0  this   Lorg/scalatest/matchers/MatchResult;

  public java.lang.String copy$default$5();
    descriptor: ()Ljava/lang/String;
    flags: (0x0001) ACC_PUBLIC
    Code:
      stack=1, locals=1, args_size=1
         0: aload_0
         1: invokevirtual #131                // Method rawMidSentenceNegatedFailureMessage:()Ljava/lang/String;
         4: areturn
      LineNumberTable:
        line 203: 0
      LocalVariableTable:
        Start  Length  Slot  Name   Signature
            0       5     0  this   Lorg/scalatest/matchers/MatchResult;

  public scala.collection.immutable.IndexedSeq<java.lang.Object> copy$default$6();
    descriptor: ()Lscala/collection/immutable/IndexedSeq;
    flags: (0x0001) ACC_PUBLIC
    Code:
      stack=1, locals=1, args_size=1
         0: aload_0
         1: invokevirtual #102                // Method failureMessageArgs:()Lscala/collection/immutable/IndexedSeq;
         4: areturn
      LineNumberTable:
        line 204: 0
      LocalVariableTable:
        Start  Length  Slot  Name   Signature
            0       5     0  this   Lorg/scalatest/matchers/MatchResult;
    Signature: #89                          // ()Lscala/collection/immutable/IndexedSeq<Ljava/lang/Object;>;

  public scala.collection.immutable.IndexedSeq<java.lang.Object> copy$default$7();
    descriptor: ()Lscala/collection/immutable/IndexedSeq;
    flags: (0x0001) ACC_PUBLIC
    Code:
      stack=1, locals=1, args_size=1
         0: aload_0
         1: invokevirtual #119                // Method negatedFailureMessageArgs:()Lscala/collection/immutable/IndexedSeq;
         4: areturn
      LineNumberTable:
        line 205: 0
      LocalVariableTable:
        Start  Length  Slot  Name   Signature
            0       5     0  this   Lorg/scalatest/matchers/MatchResult;
    Signature: #89                          // ()Lscala/collection/immutable/IndexedSeq<Ljava/lang/Object;>;

  public scala.collection.immutable.IndexedSeq<java.lang.Object> copy$default$8();
    descriptor: ()Lscala/collection/immutable/IndexedSeq;
    flags: (0x0001) ACC_PUBLIC
    Code:
      stack=1, locals=1, args_size=1
         0: aload_0
         1: invokevirtual #124                // Method midSentenceFailureMessageArgs:()Lscala/collection/immutable/IndexedSeq;
         4: areturn
      LineNumberTable:
        line 206: 0
      LocalVariableTable:
        Start  Length  Slot  Name   Signature
            0       5     0  this   Lorg/scalatest/matchers/MatchResult;
    Signature: #89                          // ()Lscala/collection/immutable/IndexedSeq<Ljava/lang/Object;>;

  public scala.collection.immutable.IndexedSeq<java.lang.Object> copy$default$9();
    descriptor: ()Lscala/collection/immutable/IndexedSeq;
    flags: (0x0001) ACC_PUBLIC
    Code:
      stack=1, locals=1, args_size=1
         0: aload_0
         1: invokevirtual #129                // Method midSentenceNegatedFailureMessageArgs:()Lscala/collection/immutable/IndexedSeq;
         4: areturn
      LineNumberTable:
        line 207: 0
      LocalVariableTable:
        Start  Length  Slot  Name   Signature
            0       5     0  this   Lorg/scalatest/matchers/MatchResult;
    Signature: #89                          // ()Lscala/collection/immutable/IndexedSeq<Ljava/lang/Object;>;

  public java.lang.String productPrefix();
    descriptor: ()Ljava/lang/String;
    flags: (0x0001) ACC_PUBLIC
    Code:
      stack=1, locals=1, args_size=1
         0: ldc           #205                // String MatchResult
         2: areturn
      LineNumberTable:
        line 198: 0
      LocalVariableTable:
        Start  Length  Slot  Name   Signature
            0       3     0  this   Lorg/scalatest/matchers/MatchResult;

  public int productArity();
    descriptor: ()I
    flags: (0x0001) ACC_PUBLIC
    Code:
      stack=1, locals=1, args_size=1
         0: bipush        9
         2: ireturn
      LineNumberTable:
        line 198: 0
      LocalVariableTable:
        Start  Length  Slot  Name   Signature
            0       3     0  this   Lorg/scalatest/matchers/MatchResult;

  public java.lang.Object productElement(int);
    descriptor: (I)Ljava/lang/Object;
    flags: (0x0001) ACC_PUBLIC
    Code:
      stack=1, locals=3, args_size=2
         0: iload_1
         1: istore_2
         2: iload_2
         3: tableswitch   { // 0 to 8
                       0: 52
                       1: 62
                       2: 69
                       3: 76
                       4: 83
                       5: 90
                       6: 97
                       7: 104
                       8: 111
                 default: 118
            }
        52: aload_0
        53: invokevirtual #135                // Method matches:()Z
        56: invokestatic  #216                // Method scala/runtime/BoxesRunTime.boxToBoolean:(Z)Ljava/lang/Boolean;
        59: goto          125
        62: aload_0
        63: invokevirtual #109                // Method rawFailureMessage:()Ljava/lang/String;
        66: goto          125
        69: aload_0
        70: invokevirtual #121                // Method rawNegatedFailureMessage:()Ljava/lang/String;
        73: goto          125
        76: aload_0
        77: invokevirtual #126                // Method rawMidSentenceFailureMessage:()Ljava/lang/String;
        80: goto          125
        83: aload_0
        84: invokevirtual #131                // Method rawMidSentenceNegatedFailureMessage:()Ljava/lang/String;
        87: goto          125
        90: aload_0
        91: invokevirtual #102                // Method failureMessageArgs:()Lscala/collection/immutable/IndexedSeq;
        94: goto          125
        97: aload_0
        98: invokevirtual #119                // Method negatedFailureMessageArgs:()Lscala/collection/immutable/IndexedSeq;
       101: goto          125
       104: aload_0
       105: invokevirtual #124                // Method midSentenceFailureMessageArgs:()Lscala/collection/immutable/IndexedSeq;
       108: goto          125
       111: aload_0
       112: invokevirtual #129                // Method midSentenceNegatedFailureMessageArgs:()Lscala/collection/immutable/IndexedSeq;
       115: goto          125
       118: iload_1
       119: invokestatic  #221                // Method scala/runtime/Statics.ioobe:(I)Ljava/lang/Object;
       122: goto          125
       125: areturn
      StackMapTable: number_of_entries = 11
        frame_type = 252 /* append */
          offset_delta = 52
          locals = [ int ]
        frame_type = 9 /* same */
        frame_type = 6 /* same */
        frame_type = 6 /* same */
        frame_type = 6 /* same */
        frame_type = 6 /* same */
        frame_type = 6 /* same */
        frame_type = 6 /* same */
        frame_type = 6 /* same */
        frame_type = 6 /* same */
        frame_type = 70 /* same_locals_1_stack_item */
          stack = [ class java/lang/Object ]
      LineNumberTable:
        line 198: 0
      LocalVariableTable:
        Start  Length  Slot  Name   Signature
            0     126     0  this   Lorg/scalatest/matchers/MatchResult;
            0     126     1   x$1   I
    MethodParameters:
      Name                           Flags
      x$1                            final

  public scala.collection.Iterator<java.lang.Object> productIterator();
    descriptor: ()Lscala/collection/Iterator;
    flags: (0x0001) ACC_PUBLIC
    Code:
      stack=2, locals=1, args_size=1
         0: getstatic     #229                // Field scala/runtime/ScalaRunTime$.MODULE$:Lscala/runtime/ScalaRunTime$;
         3: aload_0
         4: invokevirtual #232                // Method scala/runtime/ScalaRunTime$.typedProductIterator:(Lscala/Product;)Lscala/collection/Iterator;
         7: areturn
      LineNumberTable:
        line 198: 0
      LocalVariableTable:
        Start  Length  Slot  Name   Signature
            0       8     0  this   Lorg/scalatest/matchers/MatchResult;
    Signature: #224                         // ()Lscala/collection/Iterator<Ljava/lang/Object;>;

  public boolean canEqual(java.lang.Object);
    descriptor: (Ljava/lang/Object;)Z
    flags: (0x0001) ACC_PUBLIC
    Code:
      stack=1, locals=2, args_size=2
         0: aload_1
         1: instanceof    #2                  // class org/scalatest/matchers/MatchResult
         4: ireturn
      LineNumberTable:
        line 198: 0
      LocalVariableTable:
        Start  Length  Slot  Name   Signature
            0       5     0  this   Lorg/scalatest/matchers/MatchResult;
            0       5     1   x$1   Ljava/lang/Object;
    MethodParameters:
      Name                           Flags
      x$1                            final

  public java.lang.String productElementName(int);
    descriptor: (I)Ljava/lang/String;
    flags: (0x0001) ACC_PUBLIC
    Code:
      stack=1, locals=3, args_size=2
         0: iload_1
         1: istore_2
         2: iload_2
         3: tableswitch   { // 0 to 8
                       0: 52
                       1: 57
                       2: 62
                       3: 67
                       4: 72
                       5: 77
                       6: 82
                       7: 87
                       8: 92
                 default: 97
            }
        52: ldc           #238                // String matches
        54: goto          107
        57: ldc           #239                // String rawFailureMessage
        59: goto          107
        62: ldc           #240                // String rawNegatedFailureMessage
        64: goto          107
        67: ldc           #241                // String rawMidSentenceFailureMessage
        69: goto          107
        72: ldc           #242                // String rawMidSentenceNegatedFailureMessage
        74: goto          107
        77: ldc           #243                // String failureMessageArgs
        79: goto          107
        82: ldc           #244                // String negatedFailureMessageArgs
        84: goto          107
        87: ldc           #245                // String midSentenceFailureMessageArgs
        89: goto          107
        92: ldc           #246                // String midSentenceNegatedFailureMessageArgs
        94: goto          107
        97: iload_1
        98: invokestatic  #221                // Method scala/runtime/Statics.ioobe:(I)Ljava/lang/Object;
       101: checkcast     #116                // class java/lang/String
       104: goto          107
       107: areturn
      StackMapTable: number_of_entries = 11
        frame_type = 252 /* append */
          offset_delta = 52
          locals = [ int ]
        frame_type = 4 /* same */
        frame_type = 4 /* same */
        frame_type = 4 /* same */
        frame_type = 4 /* same */
        frame_type = 4 /* same */
        frame_type = 4 /* same */
        frame_type = 4 /* same */
        frame_type = 4 /* same */
        frame_type = 4 /* same */
        frame_type = 73 /* same_locals_1_stack_item */
          stack = [ class java/lang/String ]
      LineNumberTable:
        line 198: 0
      LocalVariableTable:
        Start  Length  Slot  Name   Signature
            0     108     0  this   Lorg/scalatest/matchers/MatchResult;
            0     108     1   x$1   I
    MethodParameters:
      Name                           Flags
      x$1                            final

  public int hashCode();
    descriptor: ()I
    flags: (0x0001) ACC_PUBLIC
    Code:
      stack=2, locals=2, args_size=1
         0: ldc           #248                // int -889275714
         2: istore_1
         3: iload_1
         4: aload_0
         5: invokevirtual #250                // Method productPrefix:()Ljava/lang/String;
         8: invokevirtual #252                // Method java/lang/String.hashCode:()I
        11: invokestatic  #256                // Method scala/runtime/Statics.mix:(II)I
        14: istore_1
        15: iload_1
        16: aload_0
        17: invokevirtual #135                // Method matches:()Z
        20: ifeq          29
        23: sipush        1231
        26: goto          32
        29: sipush        1237
        32: invokestatic  #256                // Method scala/runtime/Statics.mix:(II)I
        35: istore_1
        36: iload_1
        37: aload_0
        38: invokevirtual #109                // Method rawFailureMessage:()Ljava/lang/String;
        41: invokestatic  #260                // Method scala/runtime/Statics.anyHash:(Ljava/lang/Object;)I
        44: invokestatic  #256                // Method scala/runtime/Statics.mix:(II)I
        47: istore_1
        48: iload_1
        49: aload_0
        50: invokevirtual #121                // Method rawNegatedFailureMessage:()Ljava/lang/String;
        53: invokestatic  #260                // Method scala/runtime/Statics.anyHash:(Ljava/lang/Object;)I
        56: invokestatic  #256                // Method scala/runtime/Statics.mix:(II)I
        59: istore_1
        60: iload_1
        61: aload_0
        62: invokevirtual #126                // Method rawMidSentenceFailureMessage:()Ljava/lang/String;
        65: invokestatic  #260                // Method scala/runtime/Statics.anyHash:(Ljava/lang/Object;)I
        68: invokestatic  #256                // Method scala/runtime/Statics.mix:(II)I
        71: istore_1
        72: iload_1
        73: aload_0
        74: invokevirtual #131                // Method rawMidSentenceNegatedFailureMessage:()Ljava/lang/String;
        77: invokestatic  #260                // Method scala/runtime/Statics.anyHash:(Ljava/lang/Object;)I
        80: invokestatic  #256                // Method scala/runtime/Statics.mix:(II)I
        83: istore_1
        84: iload_1
        85: aload_0
        86: invokevirtual #102                // Method failureMessageArgs:()Lscala/collection/immutable/IndexedSeq;
        89: invokestatic  #260                // Method scala/runtime/Statics.anyHash:(Ljava/lang/Object;)I
        92: invokestatic  #256                // Method scala/runtime/Statics.mix:(II)I
        95: istore_1
        96: iload_1
        97: aload_0
        98: invokevirtual #119                // Method negatedFailureMessageArgs:()Lscala/collection/immutable/IndexedSeq;
       101: invokestatic  #260                // Method scala/runtime/Statics.anyHash:(Ljava/lang/Object;)I
       104: invokestatic  #256                // Method scala/runtime/Statics.mix:(II)I
       107: istore_1
       108: iload_1
       109: aload_0
       110: invokevirtual #124                // Method midSentenceFailureMessageArgs:()Lscala/collection/immutable/IndexedSeq;
       113: invokestatic  #260                // Method scala/runtime/Statics.anyHash:(Ljava/lang/Object;)I
       116: invokestatic  #256                // Method scala/runtime/Statics.mix:(II)I
       119: istore_1
       120: iload_1
       121: aload_0
       122: invokevirtual #129                // Method midSentenceNegatedFailureMessageArgs:()Lscala/collection/immutable/IndexedSeq;
       125: invokestatic  #260                // Method scala/runtime/Statics.anyHash:(Ljava/lang/Object;)I
       128: invokestatic  #256                // Method scala/runtime/Statics.mix:(II)I
       131: istore_1
       132: iload_1
       133: bipush        9
       135: invokestatic  #263                // Method scala/runtime/Statics.finalizeHash:(II)I
       138: ireturn
      StackMapTable: number_of_entries = 2
        frame_type = 255 /* full_frame */
          offset_delta = 29
          locals = [ class org/scalatest/matchers/MatchResult, int ]
          stack = [ int ]
        frame_type = 255 /* full_frame */
          offset_delta = 2
          locals = [ class org/scalatest/matchers/MatchResult, int ]
          stack = [ int, int ]
      LineNumberTable:
        line 198: 0
      LocalVariableTable:
        Start  Length  Slot  Name   Signature
            0     139     0  this   Lorg/scalatest/matchers/MatchResult;

  public java.lang.String toString();
    descriptor: ()Ljava/lang/String;
    flags: (0x0001) ACC_PUBLIC
    Code:
      stack=2, locals=1, args_size=1
         0: getstatic     #229                // Field scala/runtime/ScalaRunTime$.MODULE$:Lscala/runtime/ScalaRunTime$;
         3: aload_0
         4: invokevirtual #268                // Method scala/runtime/ScalaRunTime$._toString:(Lscala/Product;)Ljava/lang/String;
         7: areturn
      LineNumberTable:
        line 198: 0
      LocalVariableTable:
        Start  Length  Slot  Name   Signature
            0       8     0  this   Lorg/scalatest/matchers/MatchResult;

  public boolean equals(java.lang.Object);
    descriptor: (Ljava/lang/Object;)Z
    flags: (0x0001) ACC_PUBLIC
    Code:
      stack=2, locals=13, args_size=2
         0: aload_0
         1: aload_1
         2: if_acmpeq     322
         5: aload_1
         6: astore_3
         7: aload_3
         8: instanceof    #2                  // class org/scalatest/matchers/MatchResult
        11: ifeq          19
        14: iconst_1
        15: istore_2
        16: goto          27
        19: goto          22
        22: iconst_0
        23: istore_2
        24: goto          27
        27: iload_2
        28: ifeq          326
        31: aload_1
        32: checkcast     #2                  // class org/scalatest/matchers/MatchResult
        35: astore        4
        37: aload_0
        38: invokevirtual #135                // Method matches:()Z
        41: aload         4
        43: invokevirtual #135                // Method matches:()Z
        46: if_icmpne     318
        49: aload_0
        50: invokevirtual #109                // Method rawFailureMessage:()Ljava/lang/String;
        53: aload         4
        55: invokevirtual #109                // Method rawFailureMessage:()Ljava/lang/String;
        58: astore        5
        60: dup
        61: ifnonnull     73
        64: pop
        65: aload         5
        67: ifnull        81
        70: goto          318
        73: aload         5
        75: invokevirtual #271                // Method java/lang/Object.equals:(Ljava/lang/Object;)Z
        78: ifeq          318
        81: aload_0
        82: invokevirtual #121                // Method rawNegatedFailureMessage:()Ljava/lang/String;
        85: aload         4
        87: invokevirtual #121                // Method rawNegatedFailureMessage:()Ljava/lang/String;
        90: astore        6
        92: dup
        93: ifnonnull     105
        96: pop
        97: aload         6
        99: ifnull        113
       102: goto          318
       105: aload         6
       107: invokevirtual #271                // Method java/lang/Object.equals:(Ljava/lang/Object;)Z
       110: ifeq          318
       113: aload_0
       114: invokevirtual #126                // Method rawMidSentenceFailureMessage:()Ljava/lang/String;
       117: aload         4
       119: invokevirtual #126                // Method rawMidSentenceFailureMessage:()Ljava/lang/String;
       122: astore        7
       124: dup
       125: ifnonnull     137
       128: pop
       129: aload         7
       131: ifnull        145
       134: goto          318
       137: aload         7
       139: invokevirtual #271                // Method java/lang/Object.equals:(Ljava/lang/Object;)Z
       142: ifeq          318
       145: aload_0
       146: invokevirtual #131                // Method rawMidSentenceNegatedFailureMessage:()Ljava/lang/String;
       149: aload         4
       151: invokevirtual #131                // Method rawMidSentenceNegatedFailureMessage:()Ljava/lang/String;
       154: astore        8
       156: dup
       157: ifnonnull     169
       160: pop
       161: aload         8
       163: ifnull        177
       166: goto          318
       169: aload         8
       171: invokevirtual #271                // Method java/lang/Object.equals:(Ljava/lang/Object;)Z
       174: ifeq          318
       177: aload_0
       178: invokevirtual #102                // Method failureMessageArgs:()Lscala/collection/immutable/IndexedSeq;
       181: aload         4
       183: invokevirtual #102                // Method failureMessageArgs:()Lscala/collection/immutable/IndexedSeq;
       186: astore        9
       188: dup
       189: ifnonnull     201
       192: pop
       193: aload         9
       195: ifnull        209
       198: goto          318
       201: aload         9
       203: invokevirtual #271                // Method java/lang/Object.equals:(Ljava/lang/Object;)Z
       206: ifeq          318
       209: aload_0
       210: invokevirtual #119                // Method negatedFailureMessageArgs:()Lscala/collection/immutable/IndexedSeq;
       213: aload         4
       215: invokevirtual #119                // Method negatedFailureMessageArgs:()Lscala/collection/immutable/IndexedSeq;
       218: astore        10
       220: dup
       221: ifnonnull     233
       224: pop
       225: aload         10
       227: ifnull        241
       230: goto          318
       233: aload         10
       235: invokevirtual #271                // Method java/lang/Object.equals:(Ljava/lang/Object;)Z
       238: ifeq          318
       241: aload_0
       242: invokevirtual #124                // Method midSentenceFailureMessageArgs:()Lscala/collection/immutable/IndexedSeq;
       245: aload         4
       247: invokevirtual #124                // Method midSentenceFailureMessageArgs:()Lscala/collection/immutable/IndexedSeq;
       250: astore        11
       252: dup
       253: ifnonnull     265
       256: pop
       257: aload         11
       259: ifnull        273
       262: goto          318
       265: aload         11
       267: invokevirtual #271                // Method java/lang/Object.equals:(Ljava/lang/Object;)Z
       270: ifeq          318
       273: aload_0
       274: invokevirtual #129                // Method midSentenceNegatedFailureMessageArgs:()Lscala/collection/immutable/IndexedSeq;
       277: aload         4
       279: invokevirtual #129                // Method midSentenceNegatedFailureMessageArgs:()Lscala/collection/immutable/IndexedSeq;
       282: astore        12
       284: dup
       285: ifnonnull     297
       288: pop
       289: aload         12
       291: ifnull        305
       294: goto          318
       297: aload         12
       299: invokevirtual #271                // Method java/lang/Object.equals:(Ljava/lang/Object;)Z
       302: ifeq          318
       305: aload         4
       307: aload_0
       308: invokevirtual #273                // Method canEqual:(Ljava/lang/Object;)Z
       311: ifeq          318
       314: iconst_1
       315: goto          319
       318: iconst_0
       319: ifeq          326
       322: iconst_1
       323: goto          327
       326: iconst_0
       327: ireturn
      StackMapTable: number_of_entries = 24
        frame_type = 253 /* append */
          offset_delta = 19
          locals = [ top, class java/lang/Object ]
        frame_type = 2 /* same */
        frame_type = 255 /* full_frame */
          offset_delta = 4
          locals = [ class org/scalatest/matchers/MatchResult, class java/lang/Object, int, class java/lang/Object ]
          stack = []
        frame_type = 255 /* full_frame */
          offset_delta = 45
          locals = [ class org/scalatest/matchers/MatchResult, class java/lang/Object, int, class java/lang/Object, class org/scalatest/matchers/MatchResult, class java/lang/String ]
          stack = [ class java/lang/String ]
        frame_type = 7 /* same */
        frame_type = 255 /* full_frame */
          offset_delta = 23
          locals = [ class org/scalatest/matchers/MatchResult, class java/lang/Object, int, class java/lang/Object, class org/scalatest/matchers/MatchResult, class java/lang/String, class java/lang/String ]
          stack = [ class java/lang/String ]
        frame_type = 7 /* same */
        frame_type = 255 /* full_frame */
          offset_delta = 23
          locals = [ class org/scalatest/matchers/MatchResult, class java/lang/Object, int, class java/lang/Object, class org/scalatest/matchers/MatchResult, class java/lang/String, class java/lang/String, class java/lang/String ]
          stack = [ class java/lang/String ]
        frame_type = 7 /* same */
        frame_type = 255 /* full_frame */
          offset_delta = 23
          locals = [ class org/scalatest/matchers/MatchResult, class java/lang/Object, int, class java/lang/Object, class org/scalatest/matchers/MatchResult, class java/lang/String, class java/lang/String, class java/lang/String, class java/lang/String ]
          stack = [ class java/lang/String ]
        frame_type = 7 /* same */
        frame_type = 255 /* full_frame */
          offset_delta = 23
          locals = [ class org/scalatest/matchers/MatchResult, class java/lang/Object, int, class java/lang/Object, class org/scalatest/matchers/MatchResult, class java/lang/String, class java/lang/String, class java/lang/String, class java/lang/String, class scala/collection/immutable/IndexedSeq ]
          stack = [ class scala/collection/immutable/IndexedSeq ]
        frame_type = 7 /* same */
        frame_type = 255 /* full_frame */
          offset_delta = 23
          locals = [ class org/scalatest/matchers/MatchResult, class java/lang/Object, int, class java/lang/Object, class org/scalatest/matchers/MatchResult, class java/lang/String, class java/lang/String, class java/lang/String, class java/lang/String, class scala/collection/immutable/IndexedSeq, class scala/collection/immutable/IndexedSeq ]
          stack = [ class scala/collection/immutable/IndexedSeq ]
        frame_type = 7 /* same */
        frame_type = 255 /* full_frame */
          offset_delta = 23
          locals = [ class org/scalatest/matchers/MatchResult, class java/lang/Object, int, class java/lang/Object, class org/scalatest/matchers/MatchResult, class java/lang/String, class java/lang/String, class java/lang/String, class java/lang/String, class scala/collection/immutable/IndexedSeq, class scala/collection/immutable/IndexedSeq, class scala/collection/immutable/IndexedSeq ]
          stack = [ class scala/collection/immutable/IndexedSeq ]
        frame_type = 7 /* same */
        frame_type = 255 /* full_frame */
          offset_delta = 23
          locals = [ class org/scalatest/matchers/MatchResult, class java/lang/Object, int, class java/lang/Object, class org/scalatest/matchers/MatchResult, class java/lang/String, class java/lang/String, class java/lang/String, class java/lang/String, class scala/collection/immutable/IndexedSeq, class scala/collection/immutable/IndexedSeq, class scala/collection/immutable/IndexedSeq, class scala/collection/immutable/IndexedSeq ]
          stack = [ class scala/collection/immutable/IndexedSeq ]
        frame_type = 7 /* same */
        frame_type = 255 /* full_frame */
          offset_delta = 12
          locals = [ class org/scalatest/matchers/MatchResult, class java/lang/Object, int, class java/lang/Object, class org/scalatest/matchers/MatchResult ]
          stack = []
        frame_type = 64 /* same_locals_1_stack_item */
          stack = [ int ]
        frame_type = 248 /* chop */
          offset_delta = 2
        frame_type = 253 /* append */
          offset_delta = 3
          locals = [ int, class java/lang/Object ]
        frame_type = 255 /* full_frame */
          offset_delta = 0
          locals = [ class org/scalatest/matchers/MatchResult, class java/lang/Object ]
          stack = [ int ]
      LineNumberTable:
        line 198: 0
      LocalVariableTable:
        Start  Length  Slot  Name   Signature
            0     328     0  this   Lorg/scalatest/matchers/MatchResult;
            0     328     1   x$1   Ljava/lang/Object;
    MethodParameters:
      Name                           Flags
      x$1                            final

  public static final java.lang.String $anonfun$makeString$1(org.scalactic.Prettifier, java.lang.Object);
    descriptor: (Lorg/scalactic/Prettifier;Ljava/lang/Object;)Ljava/lang/String;
    flags: (0x1019) ACC_PUBLIC, ACC_STATIC, ACC_FINAL, ACC_SYNTHETIC
    Code:
      stack=2, locals=2, args_size=2
         0: aload_1
         1: instanceof    #277                // class org/scalatest/matchers/LazyMessage
         4: ifeq          18
         7: aload_1
         8: checkcast     #277                // class org/scalatest/matchers/LazyMessage
        11: aload_0
        12: invokevirtual #280                // Method org/scalatest/matchers/LazyMessage.message:(Lorg/scalactic/Prettifier;)Ljava/lang/String;
        15: goto          25
        18: aload_0
        19: aload_1
        20: invokeinterface #284,  2          // InterfaceMethod org/scalactic/Prettifier.apply:(Ljava/lang/Object;)Ljava/lang/String;
        25: areturn
      StackMapTable: number_of_entries = 2
        frame_type = 18 /* same */
        frame_type = 70 /* same_locals_1_stack_item */
          stack = [ class java/lang/String ]
      LineNumberTable:
        line 271: 0
      LocalVariableTable:
        Start  Length  Slot  Name   Signature
            0      26     0 prettifier$1   Lorg/scalactic/Prettifier;
            0      26     1   arg   Ljava/lang/Object;
    MethodParameters:
      Name                           Flags
      prettifier$1                   final
      arg                            final

  public org.scalatest.matchers.MatchResult(boolean, java.lang.String, java.lang.String, java.lang.String, java.lang.String, scala.collection.immutable.IndexedSeq<java.lang.Object>, scala.collection.immutable.IndexedSeq<java.lang.Object>, scala.collection.immutable.IndexedSeq<java.lang.Object>, scala.collection.immutable.IndexedSeq<java.lang.Object>);
    descriptor: (ZLjava/lang/String;Ljava/lang/String;Ljava/lang/String;Ljava/lang/String;Lscala/collection/immutable/IndexedSeq;Lscala/collection/immutable/IndexedSeq;Lscala/collection/immutable/IndexedSeq;Lscala/collection/immutable/IndexedSeq;)V
    flags: (0x0001) ACC_PUBLIC
    Code:
      stack=2, locals=10, args_size=10
         0: aload_0
         1: iload_1
         2: putfield      #78                 // Field matches:Z
         5: aload_0
         6: aload_2
         7: putfield      #81                 // Field rawFailureMessage:Ljava/lang/String;
        10: aload_0
        11: aload_3
        12: putfield      #83                 // Field rawNegatedFailureMessage:Ljava/lang/String;
        15: aload_0
        16: aload         4
        18: putfield      #85                 // Field rawMidSentenceFailureMessage:Ljava/lang/String;
        21: aload_0
        22: aload         5
        24: putfield      #87                 // Field rawMidSentenceNegatedFailureMessage:Ljava/lang/String;
        27: aload_0
        28: aload         6
        30: putfield      #91                 // Field failureMessageArgs:Lscala/collection/immutable/IndexedSeq;
        33: aload_0
        34: aload         7
        36: putfield      #93                 // Field negatedFailureMessageArgs:Lscala/collection/immutable/IndexedSeq;
        39: aload_0
        40: aload         8
        42: putfield      #95                 // Field midSentenceFailureMessageArgs:Lscala/collection/immutable/IndexedSeq;
        45: aload_0
        46: aload         9
        48: putfield      #97                 // Field midSentenceNegatedFailureMessageArgs:Lscala/collection/immutable/IndexedSeq;
        51: aload_0
        52: invokespecial #288                // Method java/lang/Object."<init>":()V
        55: aload_0
        56: invokestatic  #292                // InterfaceMethod scala/Product.$init$:(Lscala/Product;)V
        59: return
      LineNumberTable:
        line 199: 0
        line 200: 5
        line 201: 10
        line 202: 15
        line 203: 21
        line 204: 27
        line 205: 33
        line 206: 39
        line 207: 45
        line 198: 51
      LocalVariableTable:
        Start  Length  Slot  Name   Signature
            0      60     0  this   Lorg/scalatest/matchers/MatchResult;
            0      60     1 matches   Z
            0      60     2 rawFailureMessage   Ljava/lang/String;
            0      60     3 rawNegatedFailureMessage   Ljava/lang/String;
            0      60     4 rawMidSentenceFailureMessage   Ljava/lang/String;
            0      60     5 rawMidSentenceNegatedFailureMessage   Ljava/lang/String;
            0      60     6 failureMessageArgs   Lscala/collection/immutable/IndexedSeq;
            0      60     7 negatedFailureMessageArgs   Lscala/collection/immutable/IndexedSeq;
            0      60     8 midSentenceFailureMessageArgs   Lscala/collection/immutable/IndexedSeq;
            0      60     9 midSentenceNegatedFailureMessageArgs   Lscala/collection/immutable/IndexedSeq;
    Signature: #285                         // (ZLjava/lang/String;Ljava/lang/String;Ljava/lang/String;Ljava/lang/String;Lscala/collection/immutable/IndexedSeq<Ljava/lang/Object;>;Lscala/collection/immutable/IndexedSeq<Ljava/lang/Object;>;Lscala/collection/immutable/IndexedSeq<Ljava/lang/Object;>;Lscala/collection/immutable/IndexedSeq<Ljava/lang/Object;>;)V
    MethodParameters:
      Name                           Flags
      matches                        final
      rawFailureMessage              final
      rawNegatedFailureMessage       final
      rawMidSentenceFailureMessage   final
      rawMidSentenceNegatedFailureMessagefinal
      failureMessageArgs             final
      negatedFailureMessageArgs      final
      midSentenceFailureMessageArgs  final
      midSentenceNegatedFailureMessageArgsfinal

  public org.scalatest.matchers.MatchResult(boolean, java.lang.String, java.lang.String);
    descriptor: (ZLjava/lang/String;Ljava/lang/String;)V
    flags: (0x0001) ACC_PUBLIC
    Code:
      stack=10, locals=4, args_size=4
         0: aload_0
         1: iload_1
         2: aload_2
         3: aload_3
         4: aload_2
         5: aload_3
         6: getstatic     #298                // Field scala/package$.MODULE$:Lscala/package$;
         9: invokevirtual #302                // Method scala/package$.Vector:()Lscala/collection/immutable/Vector$;
        12: invokevirtual #308                // Method scala/collection/immutable/Vector$.empty:()Lscala/collection/immutable/Vector;
        15: getstatic     #298                // Field scala/package$.MODULE$:Lscala/package$;
        18: invokevirtual #302                // Method scala/package$.Vector:()Lscala/collection/immutable/Vector$;
        21: invokevirtual #308                // Method scala/collection/immutable/Vector$.empty:()Lscala/collection/immutable/Vector;
        24: getstatic     #298                // Field scala/package$.MODULE$:Lscala/package$;
        27: invokevirtual #302                // Method scala/package$.Vector:()Lscala/collection/immutable/Vector$;
        30: invokevirtual #308                // Method scala/collection/immutable/Vector$.empty:()Lscala/collection/immutable/Vector;
        33: getstatic     #298                // Field scala/package$.MODULE$:Lscala/package$;
        36: invokevirtual #302                // Method scala/package$.Vector:()Lscala/collection/immutable/Vector$;
        39: invokevirtual #308                // Method scala/collection/immutable/Vector$.empty:()Lscala/collection/immutable/Vector;
        42: invokespecial #139                // Method "<init>":(ZLjava/lang/String;Ljava/lang/String;Ljava/lang/String;Ljava/lang/String;Lscala/collection/immutable/IndexedSeq;Lscala/collection/immutable/IndexedSeq;Lscala/collection/immutable/IndexedSeq;Lscala/collection/immutable/IndexedSeq;)V
        45: return
      LineNumberTable:
        line 223: 0
        line 224: 1
        line 225: 2
        line 226: 3
        line 227: 4
        line 228: 5
        line 229: 6
        line 230: 15
        line 231: 24
        line 232: 33
        line 223: 45
      LocalVariableTable:
        Start  Length  Slot  Name   Signature
            0      46     0  this   Lorg/scalatest/matchers/MatchResult;
            0      46     1 matches   Z
            0      46     2 rawFailureMessage   Ljava/lang/String;
            0      46     3 rawNegatedFailureMessage   Ljava/lang/String;
    MethodParameters:
      Name                           Flags
      matches                        final
      rawFailureMessage              final
      rawNegatedFailureMessage       final

  private static java.lang.Object $deserializeLambda$(java.lang.invoke.SerializedLambda);
    descriptor: (Ljava/lang/invoke/SerializedLambda;)Ljava/lang/Object;
    flags: (0x100a) ACC_PRIVATE, ACC_STATIC, ACC_SYNTHETIC
    Code:
      stack=1, locals=1, args_size=1
         0: aload_0
         1: invokedynamic #320,  0            // InvokeDynamic #1:lambdaDeserialize:(Ljava/lang/invoke/SerializedLambda;)Ljava/lang/Object;
         6: areturn
}
InnerClasses:
  public static final #17= #14 of #16;    // Lookup=class java/lang/invoke/MethodHandles$Lookup of class java/lang/invoke/MethodHandles
SourceFile: "MatchResult.scala"
RuntimeVisibleAnnotations:
  0: #10(#11=s#12)
    scala.reflect.ScalaSignature(
      bytes="\u0006\u0005\tMd\u0001B\u001d;!\u0006C\u0001b\u0016\u0001\u0003\u0016\u0004%\t\u0001\u0017\u0005\t9\u0002\u0011\t\u0012)A\u00053\"AQ\f\u0001BK\u0002\u0013\u0005a\f\u0003\u0005h\u0001\tE\t\u0015!\u0003`\u0011!A\u0007A!f\u0001\n\u0003q\u0006\u0002C5\u0001\u0005#\u0005\u000b\u0011B0\t\u0011)\u0004!Q3A\u0005\u0002yC\u0001b\u001b\u0001\u0003\u0012\u0003\u0006Ia\u0018\u0005\tY\u0002\u0011)\u001a!C\u0001=\"AQ\u000e\u0001B\tB\u0003%q\f\u0003\u0005o\u0001\tU\r\u0011\"\u0001p\u0011!1\bA!E!\u0002\u0013\u0001\b\u0002C<\u0001\u0005+\u0007I\u0011A8\t\u0011a\u0004!\u0011#Q\u0001\nAD\u0001\"\u001f\u0001\u0003\u0016\u0004%\ta\u001c\u0005\tu\u0002\u0011\t\u0012)A\u0005a\"A1\u0010\u0001BK\u0002\u0013\u0005q\u000e\u0003\u0005}\u0001\tE\t\u0015!\u0003q\u0011\u0015i\b\u0001\"\u0001\u007f\u0011\u0019i\b\u0001\"\u0001\u0002\u0016!9\u0011Q\u0004\u0001\u0005\u0002\u0005}\u0001bBA\u0019\u0001\u0011\u0005\u00111\u0007\u0005\b\u0003o\u0001A\u0011AA\u001d\u0011\u001d\ti\u0004\u0001C\u0001\u0003\u007fAq!a\u0011\u0001\t\u0003\t)\u0005C\u0004\u0002H\u0001!I!!\u0013\t\u0013\u0005U\u0003!!A\u0005\u0002\u0005]\u0003\"CA6\u0001E\u0005I\u0011AA7\u0011%\t\u0019\tAI\u0001\n\u0003\t)\tC\u0005\u0002\n\u0002\t\n\u0011\"\u0001\u0002\u0006\"I\u00111\u0012\u0001\u0012\u0002\u0013\u0005\u0011Q\u0011\u0005\n\u0003\u001b\u0003\u0011\u0013!C\u0001\u0003\u000bC\u0011\"a$\u0001#\u0003%\t!!%\t\u0013\u0005U\u0005!%A\u0005\u0002\u0005E\u0005\"CAL\u0001E\u0005I\u0011AAI\u0011%\tI\nAI\u0001\n\u0003\t\t\nC\u0005\u0002\u001c\u0002\t\t\u0011\"\u0011\u0002\u001e\"I\u0011Q\u0016\u0001\u0002\u0002\u0013\u0005\u0011q\u0016\u0005\n\u0003o\u0003\u0011\u0011!C\u0001\u0003sC\u0011\"a0\u0001\u0003\u0003%\t%!1\t\u0013\u0005=\u0007!!A\u0005\u0002\u0005E\u0007\"CAk\u0001\u0005\u0005I\u0011IAl\u0011%\tY\u000eAA\u0001\n\u0003\ni\u000eC\u0005\u0002`\u0002\t\t\u0011\"\u0011\u0002b\"I\u00111\u001d\u0001\u0002\u0002\u0013\u0005\u0013Q]\u0004\b\u0003gT\u0004\u0012AA{\r\u0019I$\b#\u0001\u0002x\"1Qp\fC\u0001\u0005\u0007AqA!\u00020\t\u0003\u00119\u0001C\u0004\u0003\u0006=\"\tAa\u0006\t\u000f\t\u0015q\u0006\"\u0001\u0003$!9!QA\u0018\u0005\u0002\t-\u0002b\u0002B\u0003_\u0011\u0005!Q\u0007\u0005\n\u0005\u000by\u0013\u0011!CA\u0005\u0003B\u0011B!\u00160\u0003\u0003%\tIa\u0016\t\u0013\t%t&!A\u0005\n\t-$aC\'bi\u000eD\'+Z:vYRT!a\u000f\u001f\u0002\u00115\fGo\u00195feNT!!\u0010 \u0002\u0013M\u001c\u0017\r\\1uKN$(\"A \u0002\u0007=\u0014xm\u0001\u0001\u0014\t\u0001\u0011\u0005j\u0013\t\u0003\u0007\u001ak\u0011\u0001\u0012\u0006\u0002\u000b\u0006)1oY1mC&\u0011q\t\u0012\u0002\u0007\u0003:L(+\u001a4\u0011\u0005\rK\u0015B\u0001&E\u0005\u001d\u0001&o\u001c3vGR\u0004\"\u0001\u0014+\u000f\u00055\u0013fB\u0001(R\u001b\u0005y%B\u0001)A\u0003\u0019a$o\\8u}%\tQ)\u0003\u0002T\t\u00069\u0001/Y2lC\u001e,\u0017BA+W\u00051\u0019VM]5bY&T\u0018M\u00197f\u0015\t\u0019F)A\u0004nCR\u001c\u0007.Z:\u0016\u0003e\u0003\"a\u0011.\n\u0005m#%a\u0002\"p_2,\u0017M\\\u0001\t[\u0006$8\r[3tA\u0005\t\"/Y<GC&dWO]3NKN\u001c\u0018mZ3\u0016\u0003}\u0003\"\u0001\u00193\u000f\u0005\u0005\u0014\u0007C\u0001(E\u0013\t\u0019G)\u0001\u0004Qe\u0016$WMZ\u0005\u0003K\u001a\u0014aa\u0015;sS:<\'BA2E\u0003I\u0011\u0018m\u001e$bS2,(/Z\'fgN\fw-\u001a\u0011\u00021I\fwOT3hCR,GMR1jYV\u0014X-T3tg\u0006<W-A\rsC^tUmZ1uK\u00124\u0015-\u001b7ve\u0016lUm]:bO\u0016\u0004\u0013\u0001\b:bo6KGmU3oi\u0016t7-\u001a$bS2,(/Z\'fgN\fw-Z\u0001\u001ee\u0006<X*\u001b3TK:$XM\\2f\r\u0006LG.\u001e:f\u001b\u0016\u001c8/Y4fA\u0005\u0019#/Y<NS\u0012\u001cVM\u001c;f]\u000e,g*Z4bi\u0016$g)Y5mkJ,W*Z:tC\u001e,\u0017\u0001\n:bo6KGmU3oi\u0016t7-\u001a(fO\u0006$X\r\u001a$bS2,(/Z\'fgN\fw-\u001a\u0011\u0002%\u0019\f\u0017\u000e\\;sK6+7o]1hK\u0006\u0013xm]\u000b\u0002aB\u0019A*]:\n\u0005I4&AC%oI\u0016DX\rZ*fcB\u00111\t^\u0005\u0003k\u0012\u00131!\u00118z\u0003M1\u0017-\u001b7ve\u0016lUm]:bO\u0016\f%oZ:!\u0003eqWmZ1uK\u00124\u0015-\u001b7ve\u0016lUm]:bO\u0016\f%oZ:\u000259,w-\u0019;fI\u001a\u000b\u0017\u000e\\;sK6+7o]1hK\u0006\u0013xm\u001d\u0011\u0002;5LGmU3oi\u0016t7-\u001a$bS2,(/Z\'fgN\fw-Z!sON\fa$\\5e\'\u0016tG/\u001a8dK\u001a\u000b\u0017\u000e\\;sK6+7o]1hK\u0006\u0013xm\u001d\u0011\u0002I5LGmU3oi\u0016t7-\u001a(fO\u0006$X\r\u001a$bS2,(/Z\'fgN\fw-Z!sON\fQ%\\5e\'\u0016tG/\u001a8dK:+w-\u0019;fI\u001a\u000b\u0017\u000e\\;sK6+7o]1hK\u0006\u0013xm\u001d\u0011\u0002\rqJg.\u001b;?)My\u00181AA\u0003\u0003\u000f\tI!a\u0003\u0002\u000e\u0005=\u0011\u0011CA\n!\r\t\t\u0001A\u0007\u0002u!)qk\u0005a\u00013\")Ql\u0005a\u0001?\")\u0001n\u0005a\u0001?\")!n\u0005a\u0001?\")An\u0005a\u0001?\")an\u0005a\u0001a\")qo\u0005a\u0001a\")\u0011p\u0005a\u0001a\")1p\u0005a\u0001aR9q0a\u0006\u0002\u001a\u0005m\u0001\"B,\u0015\u0001\u0004I\u0006\"B/\u0015\u0001\u0004y\u0006\"\u00025\u0015\u0001\u0004y\u0016A\u00044bS2,(/Z\'fgN\fw-\u001a\u000b\u0004?\u0006\u0005\u0002bBA\u0012+\u0001\u000f\u0011QE\u0001\u000baJ,G\u000f^5gS\u0016\u0014\b\u0003BA\u0014\u0003[i!!!\u000b\u000b\u0007\u0005-b(A\u0005tG\u0006d\u0017m\u0019;jG&!\u0011qFA\u0015\u0005)\u0001&/\u001a;uS\u001aLWM]\u0001\u0016]\u0016<\u0017\r^3e\r\u0006LG.\u001e:f\u001b\u0016\u001c8/Y4f)\ry\u0016Q\u0007\u0005\b\u0003G1\u00029AA\u0013\u0003ei\u0017\u000eZ*f]R,gnY3GC&dWO]3NKN\u001c\u0018mZ3\u0015\u0007}\u000bY\u0004C\u0004\u0002$]\u0001\u001d!!\n\u0002A5LGmU3oi\u0016t7-\u001a(fO\u0006$X\r\u001a$bS2,(/Z\'fgN\fw-\u001a\u000b\u0004?\u0006\u0005\u0003bBA\u00121\u0001\u000f\u0011QE\u0001\b]\u0016<\u0017\r^3e+\u0005y\u0018AC7bW\u0016\u001cFO]5oOR9q,a\u0013\u0002P\u0005M\u0003BBA\'5\u0001\u0007q,A\u0005sC^\u001cFO]5oO\"1\u0011\u0011\u000b\u000eA\u0002A\fA!\u0019:hg\"9\u00111\u0005\u000eA\u0002\u0005\u0015\u0012\u0001B2paf$2c`A-\u00037\ni&a\u0018\u0002b\u0005\r\u0014QMA4\u0003SBqaV\u000e\u0011\u0002\u0003\u0007\u0011\fC\u0004^7A\u0005\t\u0019A0\t\u000f!\\\u0002\u0013!a\u0001?\"9!n\u0007I\u0001\u0002\u0004y\u0006b\u00027\u001c!\u0003\u0005\ra\u0018\u0005\b]n\u0001\n\u00111\u0001q\u0011\u001d98\u0004%AA\u0002ADq!_\u000e\u0011\u0002\u0003\u0007\u0001\u000fC\u0004|7A\u0005\t\u0019\u00019\u0002\u001d\r|\u0007/\u001f\u0013eK\u001a\fW\u000f\u001c;%cU\u0011\u0011q\u000e\u0016\u00043\u0006E4FAA:!\u0011\t)(a \u000e\u0005\u0005]$\u0002BA=\u0003w\n\u0011\"\u001e8dQ\u0016\u001c7.\u001a3\u000b\u0007\u0005uD)\u0001\u0006b]:|G/\u0019;j_:LA!!!\u0002x\t\tRO\\2iK\u000e\\W\r\u001a,be&\fgnY3\u0002\u001d\r|\u0007/\u001f\u0013eK\u001a\fW\u000f\u001c;%eU\u0011\u0011q\u0011\u0016\u0004?\u0006E\u0014AD2paf$C-\u001a4bk2$HeM\u0001\u000fG>\u0004\u0018\u0010\n3fM\u0006,H\u000e\u001e\u00135\u00039\u0019w\u000e]=%I\u00164\u0017-\u001e7uIU\nabY8qs\u0012\"WMZ1vYR$c\'\u0006\u0002\u0002\u0014*\u001a\u0001/!\u001d\u0002\u001d\r|\u0007/\u001f\u0013eK\u001a\fW\u000f\u001c;%o\u0005q1m\u001c9zI\u0011,g-Y;mi\u0012B\u0014AD2paf$C-\u001a4bk2$H%O\u0001\u000eaJ|G-^2u!J,g-\u001b=\u0016\u0005\u0005}\u0005\u0003BAQ\u0003Wk!!a)\u000b\t\u0005\u0015\u0016qU\u0001\u0005Y\u0006twM\u0003\u0002\u0002*\u0006!!.\u0019<b\u0013\r)\u00171U\u0001\raJ|G-^2u\u0003JLG/_\u000b\u0003\u0003c\u00032aQAZ\u0013\r\t)\f\u0012\u0002\u0004\u0013:$\u0018A\u00049s_\u0012,8\r^#mK6,g\u000e\u001e\u000b\u0004g\u0006m\u0006\"CA_O\u0005\u0005\t\u0019AAY\u0003\rAH%M\u0001\u0010aJ|G-^2u\u0013R,\'/\u0019;peV\u0011\u00111\u0019\t\u0006\u0003\u000b\fYm]\u0007\u0003\u0003\u000fT1!!3E\u0003)\u0019w\u000e\u001c7fGRLwN\\\u0005\u0005\u0003\u001b\f9M\u0001\u0005Ji\u0016\u0014\u0018\r^8s\u0003!\u0019\u0017M\\#rk\u0006dGcA-\u0002T\"A\u0011QX\u0015\u0002\u0002\u0003\u00071/\u0001\nqe>$Wo\u0019;FY\u0016lWM\u001c;OC6,G\u0003BAP\u00033D\u0011\"!0+\u0003\u0003\u0005\r!!-\u0002\u0011!\f7\u000f[\"pI\u0016$\"!!-\u0002\u0011Q|7\u000b\u001e:j]\u001e$\"!a(\u0002\r\u0015\fX/\u00197t)\rI\u0016q\u001d\u0005\t\u0003{k\u0013\u0011!a\u0001g&*\u0001!a;\u0002p&\u0019\u0011Q\u001e\u001e\u0003!\u0015\u000bX/\u00197NCR\u001c\u0007NU3tk2$\u0018bAAyu\t\u0019bj\u001c;FcV\fG.T1uG\"\u0014Vm];mi\u0006YQ*\u0019;dQJ+7/\u001e7u!\r\t\taL\n\u0005_\t\u000bI\u0010\u0005\u0003\u0002|\n\u0005QBAA\u007f\u0015\u0011\ty0a*\u0002\u0005%|\u0017bA+\u0002~R\u0011\u0011Q_\u0001\u0006CB\u0004H.\u001f\u000b\u0010\u007f\n%!1\u0002B\u0007\u0005\u001f\u0011\tBa\u0005\u0003\u0016!)q+\ra\u00013\")Q,\ra\u0001?\")\u0001.\ra\u0001?\")!.\ra\u0001?\")A.\ra\u0001?\")a.\ra\u0001a\")q/\ra\u0001aRYqP!\u0007\u0003\u001c\tu!q\u0004B\u0011\u0011\u00159&\u00071\u0001Z\u0011\u0015i&\u00071\u0001`\u0011\u0015A\'\u00071\u0001`\u0011\u0015Q\'\u00071\u0001`\u0011\u0015a\'\u00071\u0001`)\u001dy(Q\u0005B\u0014\u0005SAQaV\u001aA\u0002eCQ!X\u001aA\u0002}CQ\u0001[\u001aA\u0002}#\u0012b B\u0017\u0005_\u0011\tDa\r\t\u000b]#\u0004\u0019A-\t\u000bu#\u0004\u0019A0\t\u000b!$\u0004\u0019A0\t\r\u0005EC\u00071\u0001q)-y(q\u0007B\u001d\u0005w\u0011iDa\u0010\t\u000b]+\u0004\u0019A-\t\u000bu+\u0004\u0019A0\t\u000b!,\u0004\u0019A0\t\u000b9,\u0004\u0019\u00019\t\u000b],\u0004\u0019\u00019\u0015\'}\u0014\u0019E!\u0012\u0003H\t%#1\nB\'\u0005\u001f\u0012\tFa\u0015\t\u000b]3\u0004\u0019A-\t\u000bu3\u0004\u0019A0\t\u000b!4\u0004\u0019A0\t\u000b)4\u0004\u0019A0\t\u000b14\u0004\u0019A0\t\u000b94\u0004\u0019\u00019\t\u000b]4\u0004\u0019\u00019\t\u000be4\u0004\u0019\u00019\t\u000bm4\u0004\u0019\u00019\u0002\u000fUt\u0017\r\u001d9msR!!\u0011\fB3!\u0015\u0019%1\fB0\u0013\r\u0011i\u0006\u0012\u0002\u0007\u001fB$\u0018n\u001c8\u0011\u0019\r\u0013\t\'W0`?~\u0003\b\u000f\u001d9\n\u0007\t\rDI\u0001\u0004UkBdW-\u000f\u0005\t\u0005O:\u0014\u0011!a\u0001\u007f\u0006\u0019\u0001\u0010\n\u0019\u0002\u0019]\u0014\u0018\u000e^3SKBd\u0017mY3\u0015\u0005\t5\u0004\u0003BAQ\u0005_JAA!\u001d\u0002$\n1qJ\u00196fGR\u0004"
    )
BootstrapMethods:
  0: #164 REF_invokeStatic java/lang/invoke/LambdaMetafactory.altMetafactory:(Ljava/lang/invoke/MethodHandles$Lookup;Ljava/lang/String;Ljava/lang/invoke/MethodType;[Ljava/lang/Object;)Ljava/lang/invoke/CallSite;
    Method arguments:
      #148 (Ljava/lang/Object;)Ljava/lang/Object;
      #153 REF_invokeStatic org/scalatest/matchers/MatchResult.$anonfun$makeString$1:(Lorg/scalactic/Prettifier;Ljava/lang/Object;)Ljava/lang/String;
      #155 (Ljava/lang/Object;)Ljava/lang/String;
      #156 5
      #157 1
      #155 (Ljava/lang/Object;)Ljava/lang/String;
  1: #317 REF_invokeStatic scala/runtime/LambdaDeserialize.bootstrap:(Ljava/lang/invoke/MethodHandles$Lookup;Ljava/lang/String;Ljava/lang/invoke/MethodType;[Ljava/lang/invoke/MethodHandle;)Ljava/lang/invoke/CallSite;
    Method arguments:
      #153 REF_invokeStatic org/scalatest/matchers/MatchResult.$anonfun$makeString$1:(Lorg/scalactic/Prettifier;Ljava/lang/Object;)Ljava/lang/String;
  ScalaInlineInfo: length = 0xC2 (unknown attribute)
   01 00 00 26 00 95 00 96 01 00 88 01 25 00 00 88
   00 89 00 00 E9 00 EA 00 00 C1 00 2D 00 00 C2 00
   4C 00 00 C3 00 4F 00 00 C4 00 4F 00 00 C5 00 4F
   00 00 C6 00 4F 00 00 C7 00 58 00 00 C8 00 58 00
   00 C9 00 58 00 00 CA 00 58 00 01 0D 00 EA 00 00
   62 00 63 00 00 19 00 58 00 00 F7 00 CF 00 00 6E
   00 6F 01 00 12 00 4C 00 00 7A 00 63 00 00 1D 00
   58 00 00 7F 00 63 00 00 1E 00 58 00 00 84 00 85
   00 00 75 00 63 00 00 1C 00 58 00 00 CE 00 CF 00
   00 D0 00 D1 00 00 EC 00 ED 00 00 44 00 45 00 00
   DF 00 45 00 00 CB 00 4F 00 00 14 00 4F 00 00 17
   00 4F 00 00 18 00 4F 00 00 16 00 4F 00 01 08 00
   4F 00
  ScalaSig: length = 0x3 (unknown attribute)
   05 02 00
