Classfile /Users/mw/Projects/slang-braindump/.jar/jar8/assemble/slang-braindump/assemble/content/org/scalatest/matchers/MatchResult$.class
  Last modified May 29, 2022; size 5764 bytes
  SHA-256 checksum 6a1bc752cc62520bfe1d22d594410801241659dc639bef165f3089dde43344e7
  Compiled from "MatchResult.scala"
public final class org.scalatest.matchers.MatchResult$ implements java.io.Serializable
  minor version: 0
  major version: 52
  flags: (0x0031) ACC_PUBLIC, ACC_FINAL, ACC_SUPER
  this_class: #2                          // org/scalatest/matchers/MatchResult$
  super_class: #4                         // java/lang/Object
  interfaces: 1, fields: 1, methods: 10, attributes: 3
Constant pool:
    #1 = Utf8               org/scalatest/matchers/MatchResult$
    #2 = Class              #1            // org/scalatest/matchers/MatchResult$
    #3 = Utf8               java/lang/Object
    #4 = Class              #3            // java/lang/Object
    #5 = Utf8               java/io/Serializable
    #6 = Class              #5            // java/io/Serializable
    #7 = Utf8               MatchResult.scala
    #8 = Utf8               MODULE$
    #9 = Utf8               Lorg/scalatest/matchers/MatchResult$;
   #10 = Utf8               <clinit>
   #11 = Utf8               ()V
   #12 = Utf8               <init>
   #13 = NameAndType        #12:#11       // "<init>":()V
   #14 = Methodref          #2.#13        // org/scalatest/matchers/MatchResult$."<init>":()V
   #15 = NameAndType        #8:#9         // MODULE$:Lorg/scalatest/matchers/MatchResult$;
   #16 = Fieldref           #2.#15        // org/scalatest/matchers/MatchResult$.MODULE$:Lorg/scalatest/matchers/MatchResult$;
   #17 = Utf8               apply
   #18 = Utf8               (ZLjava/lang/String;Ljava/lang/String;Ljava/lang/String;Ljava/lang/String;Lscala/collection/immutable/IndexedSeq;Lscala/collection/immutable/IndexedSeq;)Lorg/scalatest/matchers/MatchResult;
   #19 = Utf8               (ZLjava/lang/String;Ljava/lang/String;Ljava/lang/String;Ljava/lang/String;Lscala/collection/immutable/IndexedSeq<Ljava/lang/Object;>;Lscala/collection/immutable/IndexedSeq<Ljava/lang/Object;>;)Lorg/scalatest/matchers/MatchResult;
   #20 = Utf8               matches
   #21 = Utf8               rawFailureMessage
   #22 = Utf8               rawNegatedFailureMessage
   #23 = Utf8               rawMidSentenceFailureMessage
   #24 = Utf8               rawMidSentenceNegatedFailureMessage
   #25 = Utf8               failureMessageArgs
   #26 = Utf8               negatedFailureMessageArgs
   #27 = Utf8               org/scalatest/matchers/MatchResult
   #28 = Class              #27           // org/scalatest/matchers/MatchResult
   #29 = Utf8               (ZLjava/lang/String;Ljava/lang/String;Ljava/lang/String;Ljava/lang/String;Lscala/collection/immutable/IndexedSeq;Lscala/collection/immutable/IndexedSeq;Lscala/collection/immutable/IndexedSeq;Lscala/collection/immutable/IndexedSeq;)V
   #30 = NameAndType        #12:#29       // "<init>":(ZLjava/lang/String;Ljava/lang/String;Ljava/lang/String;Ljava/lang/String;Lscala/collection/immutable/IndexedSeq;Lscala/collection/immutable/IndexedSeq;Lscala/collection/immutable/IndexedSeq;Lscala/collection/immutable/IndexedSeq;)V
   #31 = Methodref          #28.#30       // org/scalatest/matchers/MatchResult."<init>":(ZLjava/lang/String;Ljava/lang/String;Ljava/lang/String;Ljava/lang/String;Lscala/collection/immutable/IndexedSeq;Lscala/collection/immutable/IndexedSeq;Lscala/collection/immutable/IndexedSeq;Lscala/collection/immutable/IndexedSeq;)V
   #32 = Utf8               this
   #33 = Utf8               Z
   #34 = Utf8               Ljava/lang/String;
   #35 = Utf8               Lscala/collection/immutable/IndexedSeq;
   #36 = Utf8               (ZLjava/lang/String;Ljava/lang/String;Ljava/lang/String;Ljava/lang/String;)Lorg/scalatest/matchers/MatchResult;
   #37 = Utf8               scala/package$
   #38 = Class              #37           // scala/package$
   #39 = Utf8               Lscala/package$;
   #40 = NameAndType        #8:#39        // MODULE$:Lscala/package$;
   #41 = Fieldref           #38.#40       // scala/package$.MODULE$:Lscala/package$;
   #42 = Utf8               Vector
   #43 = Utf8               ()Lscala/collection/immutable/Vector$;
   #44 = NameAndType        #42:#43       // Vector:()Lscala/collection/immutable/Vector$;
   #45 = Methodref          #38.#44       // scala/package$.Vector:()Lscala/collection/immutable/Vector$;
   #46 = Utf8               scala/collection/immutable/Vector$
   #47 = Class              #46           // scala/collection/immutable/Vector$
   #48 = Utf8               empty
   #49 = Utf8               ()Lscala/collection/immutable/Vector;
   #50 = NameAndType        #48:#49       // empty:()Lscala/collection/immutable/Vector;
   #51 = Methodref          #47.#50       // scala/collection/immutable/Vector$.empty:()Lscala/collection/immutable/Vector;
   #52 = Utf8               (ZLjava/lang/String;Ljava/lang/String;)Lorg/scalatest/matchers/MatchResult;
   #53 = Utf8               (ZLjava/lang/String;Ljava/lang/String;Lscala/collection/immutable/IndexedSeq;)Lorg/scalatest/matchers/MatchResult;
   #54 = Utf8               (ZLjava/lang/String;Ljava/lang/String;Lscala/collection/immutable/IndexedSeq<Ljava/lang/Object;>;)Lorg/scalatest/matchers/MatchResult;
   #55 = Utf8               args
   #56 = Utf8               (ZLjava/lang/String;Ljava/lang/String;Lscala/collection/immutable/IndexedSeq;Lscala/collection/immutable/IndexedSeq;)Lorg/scalatest/matchers/MatchResult;
   #57 = Utf8               (ZLjava/lang/String;Ljava/lang/String;Lscala/collection/immutable/IndexedSeq<Ljava/lang/Object;>;Lscala/collection/immutable/IndexedSeq<Ljava/lang/Object;>;)Lorg/scalatest/matchers/MatchResult;
   #58 = Utf8               (ZLjava/lang/String;Ljava/lang/String;Ljava/lang/String;Ljava/lang/String;Lscala/collection/immutable/IndexedSeq;Lscala/collection/immutable/IndexedSeq;Lscala/collection/immutable/IndexedSeq;Lscala/collection/immutable/IndexedSeq;)Lorg/scalatest/matchers/MatchResult;
   #59 = Utf8               (ZLjava/lang/String;Ljava/lang/String;Ljava/lang/String;Ljava/lang/String;Lscala/collection/immutable/IndexedSeq<Ljava/lang/Object;>;Lscala/collection/immutable/IndexedSeq<Ljava/lang/Object;>;Lscala/collection/immutable/IndexedSeq<Ljava/lang/Object;>;Lscala/collection/immutable/IndexedSeq<Ljava/lang/Object;>;)Lorg/scalatest/matchers/MatchResult;
   #60 = Utf8               midSentenceFailureMessageArgs
   #61 = Utf8               midSentenceNegatedFailureMessageArgs
   #62 = Utf8               unapply
   #63 = Utf8               (Lorg/scalatest/matchers/MatchResult;)Lscala/Option;
   #64 = Utf8               (Lorg/scalatest/matchers/MatchResult;)Lscala/Option<Lscala/Tuple9<Ljava/lang/Object;Ljava/lang/String;Ljava/lang/String;Ljava/lang/String;Ljava/lang/String;Lscala/collection/immutable/IndexedSeq<Ljava/lang/Object;>;Lscala/collection/immutable/IndexedSeq<Ljava/lang/Object;>;Lscala/collection/immutable/IndexedSeq<Ljava/lang/Object;>;Lscala/collection/immutable/IndexedSeq<Ljava/lang/Object;>;>;>;
   #65 = Utf8               x$0
   #66 = Utf8               scala/None$
   #67 = Class              #66           // scala/None$
   #68 = Utf8               Lscala/None$;
   #69 = NameAndType        #8:#68        // MODULE$:Lscala/None$;
   #70 = Fieldref           #67.#69       // scala/None$.MODULE$:Lscala/None$;
   #71 = Utf8               scala/Some
   #72 = Class              #71           // scala/Some
   #73 = Utf8               scala/Tuple9
   #74 = Class              #73           // scala/Tuple9
   #75 = Utf8               ()Z
   #76 = NameAndType        #20:#75       // matches:()Z
   #77 = Methodref          #28.#76       // org/scalatest/matchers/MatchResult.matches:()Z
   #78 = Utf8               scala/runtime/BoxesRunTime
   #79 = Class              #78           // scala/runtime/BoxesRunTime
   #80 = Utf8               boxToBoolean
   #81 = Utf8               (Z)Ljava/lang/Boolean;
   #82 = NameAndType        #80:#81       // boxToBoolean:(Z)Ljava/lang/Boolean;
   #83 = Methodref          #79.#82       // scala/runtime/BoxesRunTime.boxToBoolean:(Z)Ljava/lang/Boolean;
   #84 = Utf8               ()Ljava/lang/String;
   #85 = NameAndType        #21:#84       // rawFailureMessage:()Ljava/lang/String;
   #86 = Methodref          #28.#85       // org/scalatest/matchers/MatchResult.rawFailureMessage:()Ljava/lang/String;
   #87 = NameAndType        #22:#84       // rawNegatedFailureMessage:()Ljava/lang/String;
   #88 = Methodref          #28.#87       // org/scalatest/matchers/MatchResult.rawNegatedFailureMessage:()Ljava/lang/String;
   #89 = NameAndType        #23:#84       // rawMidSentenceFailureMessage:()Ljava/lang/String;
   #90 = Methodref          #28.#89       // org/scalatest/matchers/MatchResult.rawMidSentenceFailureMessage:()Ljava/lang/String;
   #91 = NameAndType        #24:#84       // rawMidSentenceNegatedFailureMessage:()Ljava/lang/String;
   #92 = Methodref          #28.#91       // org/scalatest/matchers/MatchResult.rawMidSentenceNegatedFailureMessage:()Ljava/lang/String;
   #93 = Utf8               ()Lscala/collection/immutable/IndexedSeq;
   #94 = NameAndType        #25:#93       // failureMessageArgs:()Lscala/collection/immutable/IndexedSeq;
   #95 = Methodref          #28.#94       // org/scalatest/matchers/MatchResult.failureMessageArgs:()Lscala/collection/immutable/IndexedSeq;
   #96 = NameAndType        #26:#93       // negatedFailureMessageArgs:()Lscala/collection/immutable/IndexedSeq;
   #97 = Methodref          #28.#96       // org/scalatest/matchers/MatchResult.negatedFailureMessageArgs:()Lscala/collection/immutable/IndexedSeq;
   #98 = NameAndType        #60:#93       // midSentenceFailureMessageArgs:()Lscala/collection/immutable/IndexedSeq;
   #99 = Methodref          #28.#98       // org/scalatest/matchers/MatchResult.midSentenceFailureMessageArgs:()Lscala/collection/immutable/IndexedSeq;
  #100 = NameAndType        #61:#93       // midSentenceNegatedFailureMessageArgs:()Lscala/collection/immutable/IndexedSeq;
  #101 = Methodref          #28.#100      // org/scalatest/matchers/MatchResult.midSentenceNegatedFailureMessageArgs:()Lscala/collection/immutable/IndexedSeq;
  #102 = Utf8               (Ljava/lang/Object;Ljava/lang/Object;Ljava/lang/Object;Ljava/lang/Object;Ljava/lang/Object;Ljava/lang/Object;Ljava/lang/Object;Ljava/lang/Object;Ljava/lang/Object;)V
  #103 = NameAndType        #12:#102      // "<init>":(Ljava/lang/Object;Ljava/lang/Object;Ljava/lang/Object;Ljava/lang/Object;Ljava/lang/Object;Ljava/lang/Object;Ljava/lang/Object;Ljava/lang/Object;Ljava/lang/Object;)V
  #104 = Methodref          #74.#103      // scala/Tuple9."<init>":(Ljava/lang/Object;Ljava/lang/Object;Ljava/lang/Object;Ljava/lang/Object;Ljava/lang/Object;Ljava/lang/Object;Ljava/lang/Object;Ljava/lang/Object;Ljava/lang/Object;)V
  #105 = Utf8               (Ljava/lang/Object;)V
  #106 = NameAndType        #12:#105      // "<init>":(Ljava/lang/Object;)V
  #107 = Methodref          #72.#106      // scala/Some."<init>":(Ljava/lang/Object;)V
  #108 = Utf8               Lorg/scalatest/matchers/MatchResult;
  #109 = Utf8               scala/Option
  #110 = Class              #109          // scala/Option
  #111 = Utf8               writeReplace
  #112 = Utf8               ()Ljava/lang/Object;
  #113 = Utf8               scala/runtime/ModuleSerializationProxy
  #114 = Class              #113          // scala/runtime/ModuleSerializationProxy
  #115 = Utf8               (Ljava/lang/Class;)V
  #116 = NameAndType        #12:#115      // "<init>":(Ljava/lang/Class;)V
  #117 = Methodref          #114.#116     // scala/runtime/ModuleSerializationProxy."<init>":(Ljava/lang/Class;)V
  #118 = Methodref          #4.#13        // java/lang/Object."<init>":()V
  #119 = Utf8               Code
  #120 = Utf8               LineNumberTable
  #121 = Utf8               LocalVariableTable
  #122 = Utf8               Signature
  #123 = Utf8               MethodParameters
  #124 = Utf8               StackMapTable
  #125 = Utf8               SourceFile
  #126 = Utf8               ScalaInlineInfo
  #127 = Utf8               Scala
{
  public static final org.scalatest.matchers.MatchResult$ MODULE$;
    descriptor: Lorg/scalatest/matchers/MatchResult$;
    flags: (0x0019) ACC_PUBLIC, ACC_STATIC, ACC_FINAL

  public static {};
    descriptor: ()V
    flags: (0x0009) ACC_PUBLIC, ACC_STATIC
    Code:
      stack=2, locals=0, args_size=0
         0: new           #2                  // class org/scalatest/matchers/MatchResult$
         3: dup
         4: invokespecial #14                 // Method "<init>":()V
         7: putstatic     #16                 // Field MODULE$:Lorg/scalatest/matchers/MatchResult$;
        10: return
      LineNumberTable:
        line 279: 0

  public org.scalatest.matchers.MatchResult apply(boolean, java.lang.String, java.lang.String, java.lang.String, java.lang.String, scala.collection.immutable.IndexedSeq<java.lang.Object>, scala.collection.immutable.IndexedSeq<java.lang.Object>);
    descriptor: (ZLjava/lang/String;Ljava/lang/String;Ljava/lang/String;Ljava/lang/String;Lscala/collection/immutable/IndexedSeq;Lscala/collection/immutable/IndexedSeq;)Lorg/scalatest/matchers/MatchResult;
    flags: (0x0001) ACC_PUBLIC
    Code:
      stack=11, locals=8, args_size=8
         0: new           #28                 // class org/scalatest/matchers/MatchResult
         3: dup
         4: iload_1
         5: aload_2
         6: aload_3
         7: aload         4
         9: aload         5
        11: aload         6
        13: aload         7
        15: aload         6
        17: aload         7
        19: invokespecial #31                 // Method org/scalatest/matchers/MatchResult."<init>":(ZLjava/lang/String;Ljava/lang/String;Ljava/lang/String;Ljava/lang/String;Lscala/collection/immutable/IndexedSeq;Lscala/collection/immutable/IndexedSeq;Lscala/collection/immutable/IndexedSeq;Lscala/collection/immutable/IndexedSeq;)V
        22: areturn
      LineNumberTable:
        line 299: 0
      LocalVariableTable:
        Start  Length  Slot  Name   Signature
            0      23     0  this   Lorg/scalatest/matchers/MatchResult$;
            0      23     1 matches   Z
            0      23     2 rawFailureMessage   Ljava/lang/String;
            0      23     3 rawNegatedFailureMessage   Ljava/lang/String;
            0      23     4 rawMidSentenceFailureMessage   Ljava/lang/String;
            0      23     5 rawMidSentenceNegatedFailureMessage   Ljava/lang/String;
            0      23     6 failureMessageArgs   Lscala/collection/immutable/IndexedSeq;
            0      23     7 negatedFailureMessageArgs   Lscala/collection/immutable/IndexedSeq;
    Signature: #19                          // (ZLjava/lang/String;Ljava/lang/String;Ljava/lang/String;Ljava/lang/String;Lscala/collection/immutable/IndexedSeq<Ljava/lang/Object;>;Lscala/collection/immutable/IndexedSeq<Ljava/lang/Object;>;)Lorg/scalatest/matchers/MatchResult;
    MethodParameters:
      Name                           Flags
      matches                        final
      rawFailureMessage              final
      rawNegatedFailureMessage       final
      rawMidSentenceFailureMessage   final
      rawMidSentenceNegatedFailureMessagefinal
      failureMessageArgs             final
      negatedFailureMessageArgs      final

  public org.scalatest.matchers.MatchResult apply(boolean, java.lang.String, java.lang.String, java.lang.String, java.lang.String);
    descriptor: (ZLjava/lang/String;Ljava/lang/String;Ljava/lang/String;Ljava/lang/String;)Lorg/scalatest/matchers/MatchResult;
    flags: (0x0001) ACC_PUBLIC
    Code:
      stack=11, locals=6, args_size=6
         0: new           #28                 // class org/scalatest/matchers/MatchResult
         3: dup
         4: iload_1
         5: aload_2
         6: aload_3
         7: aload         4
         9: aload         5
        11: getstatic     #41                 // Field scala/package$.MODULE$:Lscala/package$;
        14: invokevirtual #45                 // Method scala/package$.Vector:()Lscala/collection/immutable/Vector$;
        17: invokevirtual #51                 // Method scala/collection/immutable/Vector$.empty:()Lscala/collection/immutable/Vector;
        20: getstatic     #41                 // Field scala/package$.MODULE$:Lscala/package$;
        23: invokevirtual #45                 // Method scala/package$.Vector:()Lscala/collection/immutable/Vector$;
        26: invokevirtual #51                 // Method scala/collection/immutable/Vector$.empty:()Lscala/collection/immutable/Vector;
        29: getstatic     #41                 // Field scala/package$.MODULE$:Lscala/package$;
        32: invokevirtual #45                 // Method scala/package$.Vector:()Lscala/collection/immutable/Vector$;
        35: invokevirtual #51                 // Method scala/collection/immutable/Vector$.empty:()Lscala/collection/immutable/Vector;
        38: getstatic     #41                 // Field scala/package$.MODULE$:Lscala/package$;
        41: invokevirtual #45                 // Method scala/package$.Vector:()Lscala/collection/immutable/Vector$;
        44: invokevirtual #51                 // Method scala/collection/immutable/Vector$.empty:()Lscala/collection/immutable/Vector;
        47: invokespecial #31                 // Method org/scalatest/matchers/MatchResult."<init>":(ZLjava/lang/String;Ljava/lang/String;Ljava/lang/String;Ljava/lang/String;Lscala/collection/immutable/IndexedSeq;Lscala/collection/immutable/IndexedSeq;Lscala/collection/immutable/IndexedSeq;Lscala/collection/immutable/IndexedSeq;)V
        50: areturn
      LineNumberTable:
        line 316: 0
      LocalVariableTable:
        Start  Length  Slot  Name   Signature
            0      51     0  this   Lorg/scalatest/matchers/MatchResult$;
            0      51     1 matches   Z
            0      51     2 rawFailureMessage   Ljava/lang/String;
            0      51     3 rawNegatedFailureMessage   Ljava/lang/String;
            0      51     4 rawMidSentenceFailureMessage   Ljava/lang/String;
            0      51     5 rawMidSentenceNegatedFailureMessage   Ljava/lang/String;
    MethodParameters:
      Name                           Flags
      matches                        final
      rawFailureMessage              final
      rawNegatedFailureMessage       final
      rawMidSentenceFailureMessage   final
      rawMidSentenceNegatedFailureMessagefinal

  public org.scalatest.matchers.MatchResult apply(boolean, java.lang.String, java.lang.String);
    descriptor: (ZLjava/lang/String;Ljava/lang/String;)Lorg/scalatest/matchers/MatchResult;
    flags: (0x0001) ACC_PUBLIC
    Code:
      stack=11, locals=4, args_size=4
         0: new           #28                 // class org/scalatest/matchers/MatchResult
         3: dup
         4: iload_1
         5: aload_2
         6: aload_3
         7: aload_2
         8: aload_3
         9: getstatic     #41                 // Field scala/package$.MODULE$:Lscala/package$;
        12: invokevirtual #45                 // Method scala/package$.Vector:()Lscala/collection/immutable/Vector$;
        15: invokevirtual #51                 // Method scala/collection/immutable/Vector$.empty:()Lscala/collection/immutable/Vector;
        18: getstatic     #41                 // Field scala/package$.MODULE$:Lscala/package$;
        21: invokevirtual #45                 // Method scala/package$.Vector:()Lscala/collection/immutable/Vector$;
        24: invokevirtual #51                 // Method scala/collection/immutable/Vector$.empty:()Lscala/collection/immutable/Vector;
        27: getstatic     #41                 // Field scala/package$.MODULE$:Lscala/package$;
        30: invokevirtual #45                 // Method scala/package$.Vector:()Lscala/collection/immutable/Vector$;
        33: invokevirtual #51                 // Method scala/collection/immutable/Vector$.empty:()Lscala/collection/immutable/Vector;
        36: getstatic     #41                 // Field scala/package$.MODULE$:Lscala/package$;
        39: invokevirtual #45                 // Method scala/package$.Vector:()Lscala/collection/immutable/Vector$;
        42: invokevirtual #51                 // Method scala/collection/immutable/Vector$.empty:()Lscala/collection/immutable/Vector;
        45: invokespecial #31                 // Method org/scalatest/matchers/MatchResult."<init>":(ZLjava/lang/String;Ljava/lang/String;Ljava/lang/String;Ljava/lang/String;Lscala/collection/immutable/IndexedSeq;Lscala/collection/immutable/IndexedSeq;Lscala/collection/immutable/IndexedSeq;Lscala/collection/immutable/IndexedSeq;)V
        48: areturn
      LineNumberTable:
        line 331: 0
      LocalVariableTable:
        Start  Length  Slot  Name   Signature
            0      49     0  this   Lorg/scalatest/matchers/MatchResult$;
            0      49     1 matches   Z
            0      49     2 rawFailureMessage   Ljava/lang/String;
            0      49     3 rawNegatedFailureMessage   Ljava/lang/String;
    MethodParameters:
      Name                           Flags
      matches                        final
      rawFailureMessage              final
      rawNegatedFailureMessage       final

  public org.scalatest.matchers.MatchResult apply(boolean, java.lang.String, java.lang.String, scala.collection.immutable.IndexedSeq<java.lang.Object>);
    descriptor: (ZLjava/lang/String;Ljava/lang/String;Lscala/collection/immutable/IndexedSeq;)Lorg/scalatest/matchers/MatchResult;
    flags: (0x0001) ACC_PUBLIC
    Code:
      stack=11, locals=5, args_size=5
         0: new           #28                 // class org/scalatest/matchers/MatchResult
         3: dup
         4: iload_1
         5: aload_2
         6: aload_3
         7: aload_2
         8: aload_3
         9: aload         4
        11: aload         4
        13: aload         4
        15: aload         4
        17: invokespecial #31                 // Method org/scalatest/matchers/MatchResult."<init>":(ZLjava/lang/String;Ljava/lang/String;Ljava/lang/String;Ljava/lang/String;Lscala/collection/immutable/IndexedSeq;Lscala/collection/immutable/IndexedSeq;Lscala/collection/immutable/IndexedSeq;Lscala/collection/immutable/IndexedSeq;)V
        20: areturn
      LineNumberTable:
        line 347: 0
        line 348: 4
        line 349: 5
        line 350: 6
        line 351: 7
        line 352: 8
        line 353: 9
        line 354: 11
        line 355: 13
        line 356: 15
      LocalVariableTable:
        Start  Length  Slot  Name   Signature
            0      21     0  this   Lorg/scalatest/matchers/MatchResult$;
            0      21     1 matches   Z
            0      21     2 rawFailureMessage   Ljava/lang/String;
            0      21     3 rawNegatedFailureMessage   Ljava/lang/String;
            0      21     4  args   Lscala/collection/immutable/IndexedSeq;
    Signature: #54                          // (ZLjava/lang/String;Ljava/lang/String;Lscala/collection/immutable/IndexedSeq<Ljava/lang/Object;>;)Lorg/scalatest/matchers/MatchResult;
    MethodParameters:
      Name                           Flags
      matches                        final
      rawFailureMessage              final
      rawNegatedFailureMessage       final
      args                           final

  public org.scalatest.matchers.MatchResult apply(boolean, java.lang.String, java.lang.String, scala.collection.immutable.IndexedSeq<java.lang.Object>, scala.collection.immutable.IndexedSeq<java.lang.Object>);
    descriptor: (ZLjava/lang/String;Ljava/lang/String;Lscala/collection/immutable/IndexedSeq;Lscala/collection/immutable/IndexedSeq;)Lorg/scalatest/matchers/MatchResult;
    flags: (0x0001) ACC_PUBLIC
    Code:
      stack=11, locals=6, args_size=6
         0: new           #28                 // class org/scalatest/matchers/MatchResult
         3: dup
         4: iload_1
         5: aload_2
         6: aload_3
         7: aload_2
         8: aload_3
         9: aload         4
        11: aload         5
        13: aload         4
        15: aload         5
        17: invokespecial #31                 // Method org/scalatest/matchers/MatchResult."<init>":(ZLjava/lang/String;Ljava/lang/String;Ljava/lang/String;Ljava/lang/String;Lscala/collection/immutable/IndexedSeq;Lscala/collection/immutable/IndexedSeq;Lscala/collection/immutable/IndexedSeq;Lscala/collection/immutable/IndexedSeq;)V
        20: areturn
      LineNumberTable:
        line 377: 0
        line 378: 4
        line 379: 5
        line 380: 6
        line 381: 7
        line 382: 8
        line 383: 9
        line 384: 11
        line 385: 13
        line 386: 15
      LocalVariableTable:
        Start  Length  Slot  Name   Signature
            0      21     0  this   Lorg/scalatest/matchers/MatchResult$;
            0      21     1 matches   Z
            0      21     2 rawFailureMessage   Ljava/lang/String;
            0      21     3 rawNegatedFailureMessage   Ljava/lang/String;
            0      21     4 failureMessageArgs   Lscala/collection/immutable/IndexedSeq;
            0      21     5 negatedFailureMessageArgs   Lscala/collection/immutable/IndexedSeq;
    Signature: #57                          // (ZLjava/lang/String;Ljava/lang/String;Lscala/collection/immutable/IndexedSeq<Ljava/lang/Object;>;Lscala/collection/immutable/IndexedSeq<Ljava/lang/Object;>;)Lorg/scalatest/matchers/MatchResult;
    MethodParameters:
      Name                           Flags
      matches                        final
      rawFailureMessage              final
      rawNegatedFailureMessage       final
      failureMessageArgs             final
      negatedFailureMessageArgs      final

  public org.scalatest.matchers.MatchResult apply(boolean, java.lang.String, java.lang.String, java.lang.String, java.lang.String, scala.collection.immutable.IndexedSeq<java.lang.Object>, scala.collection.immutable.IndexedSeq<java.lang.Object>, scala.collection.immutable.IndexedSeq<java.lang.Object>, scala.collection.immutable.IndexedSeq<java.lang.Object>);
    descriptor: (ZLjava/lang/String;Ljava/lang/String;Ljava/lang/String;Ljava/lang/String;Lscala/collection/immutable/IndexedSeq;Lscala/collection/immutable/IndexedSeq;Lscala/collection/immutable/IndexedSeq;Lscala/collection/immutable/IndexedSeq;)Lorg/scalatest/matchers/MatchResult;
    flags: (0x0001) ACC_PUBLIC
    Code:
      stack=11, locals=10, args_size=10
         0: new           #28                 // class org/scalatest/matchers/MatchResult
         3: dup
         4: iload_1
         5: aload_2
         6: aload_3
         7: aload         4
         9: aload         5
        11: aload         6
        13: aload         7
        15: aload         8
        17: aload         9
        19: invokespecial #31                 // Method org/scalatest/matchers/MatchResult."<init>":(ZLjava/lang/String;Ljava/lang/String;Ljava/lang/String;Ljava/lang/String;Lscala/collection/immutable/IndexedSeq;Lscala/collection/immutable/IndexedSeq;Lscala/collection/immutable/IndexedSeq;Lscala/collection/immutable/IndexedSeq;)V
        22: areturn
      LineNumberTable:
        line 198: 0
      LocalVariableTable:
        Start  Length  Slot  Name   Signature
            0      23     0  this   Lorg/scalatest/matchers/MatchResult$;
            0      23     1 matches   Z
            0      23     2 rawFailureMessage   Ljava/lang/String;
            0      23     3 rawNegatedFailureMessage   Ljava/lang/String;
            0      23     4 rawMidSentenceFailureMessage   Ljava/lang/String;
            0      23     5 rawMidSentenceNegatedFailureMessage   Ljava/lang/String;
            0      23     6 failureMessageArgs   Lscala/collection/immutable/IndexedSeq;
            0      23     7 negatedFailureMessageArgs   Lscala/collection/immutable/IndexedSeq;
            0      23     8 midSentenceFailureMessageArgs   Lscala/collection/immutable/IndexedSeq;
            0      23     9 midSentenceNegatedFailureMessageArgs   Lscala/collection/immutable/IndexedSeq;
    Signature: #59                          // (ZLjava/lang/String;Ljava/lang/String;Ljava/lang/String;Ljava/lang/String;Lscala/collection/immutable/IndexedSeq<Ljava/lang/Object;>;Lscala/collection/immutable/IndexedSeq<Ljava/lang/Object;>;Lscala/collection/immutable/IndexedSeq<Ljava/lang/Object;>;Lscala/collection/immutable/IndexedSeq<Ljava/lang/Object;>;)Lorg/scalatest/matchers/MatchResult;
    MethodParameters:
      Name                           Flags
      matches                        final
      rawFailureMessage              final
      rawNegatedFailureMessage       final
      rawMidSentenceFailureMessage   final
      rawMidSentenceNegatedFailureMessagefinal
      failureMessageArgs             final
      negatedFailureMessageArgs      final
      midSentenceFailureMessageArgs  final
      midSentenceNegatedFailureMessageArgsfinal

  public scala.Option<scala.Tuple9<java.lang.Object, java.lang.String, java.lang.String, java.lang.String, java.lang.String, scala.collection.immutable.IndexedSeq<java.lang.Object>, scala.collection.immutable.IndexedSeq<java.lang.Object>, scala.collection.immutable.IndexedSeq<java.lang.Object>, scala.collection.immutable.IndexedSeq<java.lang.Object>>> unapply(org.scalatest.matchers.MatchResult);
    descriptor: (Lorg/scalatest/matchers/MatchResult;)Lscala/Option;
    flags: (0x0001) ACC_PUBLIC
    Code:
      stack=13, locals=2, args_size=2
         0: aload_1
         1: ifnonnull     10
         4: getstatic     #70                 // Field scala/None$.MODULE$:Lscala/None$;
         7: goto          63
        10: new           #72                 // class scala/Some
        13: dup
        14: new           #74                 // class scala/Tuple9
        17: dup
        18: aload_1
        19: invokevirtual #77                 // Method org/scalatest/matchers/MatchResult.matches:()Z
        22: invokestatic  #83                 // Method scala/runtime/BoxesRunTime.boxToBoolean:(Z)Ljava/lang/Boolean;
        25: aload_1
        26: invokevirtual #86                 // Method org/scalatest/matchers/MatchResult.rawFailureMessage:()Ljava/lang/String;
        29: aload_1
        30: invokevirtual #88                 // Method org/scalatest/matchers/MatchResult.rawNegatedFailureMessage:()Ljava/lang/String;
        33: aload_1
        34: invokevirtual #90                 // Method org/scalatest/matchers/MatchResult.rawMidSentenceFailureMessage:()Ljava/lang/String;
        37: aload_1
        38: invokevirtual #92                 // Method org/scalatest/matchers/MatchResult.rawMidSentenceNegatedFailureMessage:()Ljava/lang/String;
        41: aload_1
        42: invokevirtual #95                 // Method org/scalatest/matchers/MatchResult.failureMessageArgs:()Lscala/collection/immutable/IndexedSeq;
        45: aload_1
        46: invokevirtual #97                 // Method org/scalatest/matchers/MatchResult.negatedFailureMessageArgs:()Lscala/collection/immutable/IndexedSeq;
        49: aload_1
        50: invokevirtual #99                 // Method org/scalatest/matchers/MatchResult.midSentenceFailureMessageArgs:()Lscala/collection/immutable/IndexedSeq;
        53: aload_1
        54: invokevirtual #101                // Method org/scalatest/matchers/MatchResult.midSentenceNegatedFailureMessageArgs:()Lscala/collection/immutable/IndexedSeq;
        57: invokespecial #104                // Method scala/Tuple9."<init>":(Ljava/lang/Object;Ljava/lang/Object;Ljava/lang/Object;Ljava/lang/Object;Ljava/lang/Object;Ljava/lang/Object;Ljava/lang/Object;Ljava/lang/Object;Ljava/lang/Object;)V
        60: invokespecial #107                // Method scala/Some."<init>":(Ljava/lang/Object;)V
        63: areturn
      StackMapTable: number_of_entries = 2
        frame_type = 10 /* same */
        frame_type = 116 /* same_locals_1_stack_item */
          stack = [ class scala/Option ]
      LineNumberTable:
        line 198: 0
      LocalVariableTable:
        Start  Length  Slot  Name   Signature
            0      64     0  this   Lorg/scalatest/matchers/MatchResult$;
            0      64     1   x$0   Lorg/scalatest/matchers/MatchResult;
    Signature: #64                          // (Lorg/scalatest/matchers/MatchResult;)Lscala/Option<Lscala/Tuple9<Ljava/lang/Object;Ljava/lang/String;Ljava/lang/String;Ljava/lang/String;Ljava/lang/String;Lscala/collection/immutable/IndexedSeq<Ljava/lang/Object;>;Lscala/collection/immutable/IndexedSeq<Ljava/lang/Object;>;Lscala/collection/immutable/IndexedSeq<Ljava/lang/Object;>;Lscala/collection/immutable/IndexedSeq<Ljava/lang/Object;>;>;>;
    MethodParameters:
      Name                           Flags
      x$0                            final

  private java.lang.Object writeReplace();
    descriptor: ()Ljava/lang/Object;
    flags: (0x0002) ACC_PRIVATE
    Code:
      stack=3, locals=1, args_size=1
         0: new           #114                // class scala/runtime/ModuleSerializationProxy
         3: dup
         4: ldc           #2                  // class org/scalatest/matchers/MatchResult$
         6: invokespecial #117                // Method scala/runtime/ModuleSerializationProxy."<init>":(Ljava/lang/Class;)V
         9: areturn
      LineNumberTable:
        line 279: 0
      LocalVariableTable:
        Start  Length  Slot  Name   Signature
            0      10     0  this   Lorg/scalatest/matchers/MatchResult$;

  private org.scalatest.matchers.MatchResult$();
    descriptor: ()V
    flags: (0x0002) ACC_PRIVATE
    Code:
      stack=1, locals=1, args_size=1
         0: aload_0
         1: invokespecial #118                // Method java/lang/Object."<init>":()V
         4: return
      LineNumberTable:
        line 390: 0
        line 279: 4
      LocalVariableTable:
        Start  Length  Slot  Name   Signature
            0       5     0  this   Lorg/scalatest/matchers/MatchResult$;
}
SourceFile: "MatchResult.scala"
  ScalaInlineInfo: length = 0x31 (unknown attribute)
   01 01 00 09 00 0C 00 0B 01 00 11 00 34 01 00 11
   00 24 01 00 11 00 12 01 00 11 00 3A 01 00 11 00
   35 01 00 11 00 38 01 00 3E 00 3F 01 00 6F 00 70
   01
  Scala: length = 0x0 (unknown attribute)

