Classfile /Users/mw/Projects/slang-braindump/.jar/jar8/assemble/slang-braindump/assemble/content/org/scalatest/matchers/MidSentenceFailureMessage.class
  Last modified May 29, 2022; size 5825 bytes
  SHA-256 checksum 9a04ff1b49acf5f28bbd081b37bf46ace775bb81fd0753cd3feacf8786f81769
  Compiled from "LazyMessage.scala"
public class org.scalatest.matchers.MidSentenceFailureMessage extends org.scalatest.matchers.LazyMessage
  minor version: 0
  major version: 52
  flags: (0x0021) ACC_PUBLIC, ACC_SUPER
  this_class: #2                          // org/scalatest/matchers/MidSentenceFailureMessage
  super_class: #4                         // org/scalatest/matchers/LazyMessage
  interfaces: 0, fields: 2, methods: 18, attributes: 4
Constant pool:
    #1 = Utf8               org/scalatest/matchers/MidSentenceFailureMessage
    #2 = Class              #1            // org/scalatest/matchers/MidSentenceFailureMessage
    #3 = Utf8               org/scalatest/matchers/LazyMessage
    #4 = Class              #3            // org/scalatest/matchers/LazyMessage
    #5 = Utf8               LazyMessage.scala
    #6 = Utf8               Lscala/reflect/ScalaSignature;
    #7 = Utf8               bytes
    #8 = Utf8               \u0006\u0005\u0005\u001dd!\u0002\r\u001a\u0001ny\u0002\u0002C\u001c\u0001\u0005+\u0007I\u0011\u0001\u001d\t\u0011q\u0002!\u0011#Q\u0001\neBQ!\u0010\u0001\u0005\u0002yBq!\u0011\u0001C\u0002\u0013\u0005!\t\u0003\u0004J\u0001\u0001\u0006Ia\u0011\u0005\u0006\u0015\u0002!\ta\u0013\u0005\b9\u0002\t\t\u0011\"\u0001^\u0011\u001dy\u0006!%A\u0005\u0002\u0001Dqa\u001b\u0001\u0002\u0002\u0013\u0005C\u000eC\u0004u\u0001\u0005\u0005I\u0011A;\t\u000fe\u0004\u0011\u0011!C\u0001u\"9Q\u0010AA\u0001\n\u0003r\b\"CA\u0006\u0001\u0005\u0005I\u0011AA\u0007\u0011%\t9\u0002AA\u0001\n\u0003\nI\u0002C\u0005\u0002\u001e\u0001\t\t\u0011\"\u0011\u0002 !I\u0011\u0011\u0005\u0001\u0002\u0002\u0013\u0005\u00131E\u0004\u000b\u0003OI\u0012\u0011!E\u00017\u0005%b!\u0003\r\u001a\u0003\u0003E\taGA\u0016\u0011\u0019i$\u0003\"\u0001\u0002D!I\u0011Q\t\n\u0002\u0002\u0013\u0015\u0013q\t\u0005\n\u0003\u0013\u0012\u0012\u0011!CA\u0003\u0017B\u0011\"a\u0014\u0013\u0003\u0003%\t)!\u0015\t\u0013\u0005u##!A\u0005\n\u0005}#!G\'jIN+g\u000e^3oG\u00164\u0015-\u001b7ve\u0016lUm]:bO\u0016T!AG\u000e\u0002\u00115\fGo\u00195feNT!\u0001H\u000f\u0002\u0013M\u001c\u0017\r\\1uKN$(\"\u0001\u0010\u0002\u0007=\u0014xm\u0005\u0003\u0001A\u0011R\u0003CA\u0011#\u001b\u0005I\u0012BA\u0012\u001a\u0005-a\u0015M_=NKN\u001c\u0018mZ3\u0011\u0005\u0015BS\"\u0001\u0014\u000b\u0003\u001d\nQa]2bY\u0006L!!\u000b\u0014\u0003\u000fA\u0013x\u000eZ;diB\u00111\u0006\u000e\b\u0003YIr!!L\u0019\u000e\u00039R!a\f\u0019\u0002\rq\u0012xn\u001c;?\u0007\u0001I\u0011aJ\u0005\u0003g\u0019\nq\u0001]1dW\u0006<W-\u0003\u00026m\ta1+\u001a:jC2L\'0\u00192mK*\u00111GJ\u0001\f[\u0006$8\r\u001b*fgVdG/F\u0001:!\t\t#(\u0003\u0002<3\tYQ*\u0019;dQJ+7/\u001e7u\u00031i\u0017\r^2i%\u0016\u001cX\u000f\u001c;!\u0003\u0019a\u0014N\\5u}Q\u0011q\b\u0011\t\u0003C\u0001AQaN\u0002A\u0002e\n!B\\3ti\u0016$\u0017I]4t+\u0005\u0019\u0005cA\u0016E\r&\u0011QI\u000e\u0002\u000b\u0013:$W\r_3e\'\u0016\f\bCA\u0013H\u0013\tAeEA\u0002B]f\f1B\\3ti\u0016$\u0017I]4tA\u00059Q.Z:tC\u001e,GC\u0001\'U!\ti\u0015K\u0004\u0002O\u001fB\u0011QFJ\u0005\u0003!\u001a\na\u0001\u0015:fI\u00164\u0017B\u0001*T\u0005\u0019\u0019FO]5oO*\u0011\u0001K\n\u0005\u0006+\u001a\u0001\rAV\u0001\u000baJ,G\u000f^5gS\u0016\u0014\bCA,[\u001b\u0005A&BA-\u001e\u0003%\u00198-\u00197bGRL7-\u0003\u0002\\1\nQ\u0001K]3ui&4\u0017.\u001a:\u0002\t\r|\u0007/\u001f\u000b\u0003\u007fyCqaN\u0004\u0011\u0002\u0003\u0007\u0011(\u0001\bd_BLH\u0005Z3gCVdG\u000fJ\u0019\u0016\u0003\u0005T#!\u000f2,\u0003\r\u0004\"\u0001Z5\u000e\u0003\u0015T!AZ4\u0002\u0013Ut7\r[3dW\u0016$\'B\u00015\'\u0003)\tgN\\8uCRLwN\\\u0005\u0003U\u0016\u0014\u0011#\u001e8dQ\u0016\u001c7.\u001a3WCJL\u0017M\\2f\u00035\u0001(o\u001c3vGR\u0004&/\u001a4jqV\tQ\u000e\u0005\u0002og6\tqN\u0003\u0002qc\u0006!A.\u00198h\u0015\u0005\u0011\u0018\u0001\u00026bm\u0006L!AU8\u0002\u0019A\u0014x\u000eZ;di\u0006\u0013\u0018\u000e^=\u0016\u0003Y\u0004\"!J<\n\u0005a4#aA%oi\u0006q\u0001O]8ek\u000e$X\t\\3nK:$HC\u0001$|\u0011\u001da8\"!AA\u0002Y\f1\u0001\u001f\u00132\u0003=\u0001(o\u001c3vGRLE/\u001a:bi>\u0014X#A@\u0011\u000b\u0005\u0005\u0011q\u0001$\u000e\u0005\u0005\r!bAA\u0003M\u0005Q1m\u001c7mK\u000e$\u0018n\u001c8\n\t\u0005%\u00111\u0001\u0002\t\u0013R,\'/\u0019;pe\u0006A1-\u00198FcV\fG\u000e\u0006\u0003\u0002\u0010\u0005U\u0001cA\u0013\u0002\u0012%\u0019\u00111\u0003\u0014\u0003\u000f\t{w\u000e\\3b]\"9A0DA\u0001\u0002\u00041\u0015A\u00059s_\u0012,8\r^#mK6,g\u000e\u001e(b[\u0016$2!\\A\u000e\u0011\u001dah\"!AA\u0002Y\f\u0001\u0002[1tQ\u000e{G-\u001a\u000b\u0002m\u00061Q-];bYN$B!a\u0004\u0002&!9A\u0010EA\u0001\u0002\u00041\u0015!G\'jIN+g\u000e^3oG\u00164\u0015-\u001b7ve\u0016lUm]:bO\u0016\u0004\"!\t\n\u0014\u000bI\ti#!\u000f\u0011\r\u0005=\u0012QG\u001d@\u001b\t\t\tDC\u0002\u00024\u0019\nqA];oi&lW-\u0003\u0003\u00028\u0005E\"!E!cgR\u0014\u0018m\u0019;Gk:\u001cG/[8ocA!\u00111HA!\u001b\t\tiDC\u0002\u0002@E\f!![8\n\u0007U\ni\u0004\u0006\u0002\u0002*\u0005AAo\\*ue&tw\rF\u0001n\u0003\u0015\t\u0007\u000f\u001d7z)\ry\u0014Q\n\u0005\u0006oU\u0001\r!O\u0001\bk:\f\u0007\u000f\u001d7z)\u0011\t\u0019&!\u0017\u0011\t\u0015\n)&O\u0005\u0004\u0003/2#AB(qi&|g\u000e\u0003\u0005\u0002\\Y\t\t\u00111\u0001@\u0003\rAH\u0005M\u0001\roJLG/\u001a*fa2\f7-\u001a\u000b\u0003\u0003C\u00022A\\A2\u0013\r\t)g\u001c\u0002\u0007\u001f\nTWm\u0019;
    #9 = Utf8               matchResult
   #10 = Utf8               Lorg/scalatest/matchers/MatchResult;
   #11 = Utf8               nestedArgs
   #12 = Utf8               Lscala/collection/immutable/IndexedSeq;
   #13 = Utf8               Lscala/collection/immutable/IndexedSeq<Ljava/lang/Object;>;
   #14 = Utf8               unapply
   #15 = Utf8               (Lorg/scalatest/matchers/MidSentenceFailureMessage;)Lscala/Option;
   #16 = Utf8               (Lorg/scalatest/matchers/MidSentenceFailureMessage;)Lscala/Option<Lorg/scalatest/matchers/MatchResult;>;
   #17 = Utf8               x$0
   #18 = Utf8               org/scalatest/matchers/MidSentenceFailureMessage$
   #19 = Class              #18           // org/scalatest/matchers/MidSentenceFailureMessage$
   #20 = Utf8               MODULE$
   #21 = Utf8               Lorg/scalatest/matchers/MidSentenceFailureMessage$;
   #22 = NameAndType        #20:#21       // MODULE$:Lorg/scalatest/matchers/MidSentenceFailureMessage$;
   #23 = Fieldref           #19.#22       // org/scalatest/matchers/MidSentenceFailureMessage$.MODULE$:Lorg/scalatest/matchers/MidSentenceFailureMessage$;
   #24 = NameAndType        #14:#15       // unapply:(Lorg/scalatest/matchers/MidSentenceFailureMessage;)Lscala/Option;
   #25 = Methodref          #19.#24       // org/scalatest/matchers/MidSentenceFailureMessage$.unapply:(Lorg/scalatest/matchers/MidSentenceFailureMessage;)Lscala/Option;
   #26 = Utf8               Lorg/scalatest/matchers/MidSentenceFailureMessage;
   #27 = Utf8               apply
   #28 = Utf8               (Lorg/scalatest/matchers/MatchResult;)Lorg/scalatest/matchers/MidSentenceFailureMessage;
   #29 = NameAndType        #27:#28       // apply:(Lorg/scalatest/matchers/MatchResult;)Lorg/scalatest/matchers/MidSentenceFailureMessage;
   #30 = Methodref          #19.#29       // org/scalatest/matchers/MidSentenceFailureMessage$.apply:(Lorg/scalatest/matchers/MatchResult;)Lorg/scalatest/matchers/MidSentenceFailureMessage;
   #31 = Utf8               andThen
   #32 = Utf8               (Lscala/Function1;)Lscala/Function1;
   #33 = Utf8               <A:Ljava/lang/Object;>(Lscala/Function1<Lorg/scalatest/matchers/MidSentenceFailureMessage;TA;>;)Lscala/Function1<Lorg/scalatest/matchers/MatchResult;TA;>;
   #34 = Utf8               g
   #35 = NameAndType        #31:#32       // andThen:(Lscala/Function1;)Lscala/Function1;
   #36 = Methodref          #19.#35       // org/scalatest/matchers/MidSentenceFailureMessage$.andThen:(Lscala/Function1;)Lscala/Function1;
   #37 = Utf8               Lscala/Function1;
   #38 = Utf8               compose
   #39 = Utf8               <A:Ljava/lang/Object;>(Lscala/Function1<TA;Lorg/scalatest/matchers/MatchResult;>;)Lscala/Function1<TA;Lorg/scalatest/matchers/MidSentenceFailureMessage;>;
   #40 = NameAndType        #38:#32       // compose:(Lscala/Function1;)Lscala/Function1;
   #41 = Methodref          #19.#40       // org/scalatest/matchers/MidSentenceFailureMessage$.compose:(Lscala/Function1;)Lscala/Function1;
   #42 = Utf8               ()Lorg/scalatest/matchers/MatchResult;
   #43 = NameAndType        #9:#10        // matchResult:Lorg/scalatest/matchers/MatchResult;
   #44 = Fieldref           #2.#43        // org/scalatest/matchers/MidSentenceFailureMessage.matchResult:Lorg/scalatest/matchers/MatchResult;
   #45 = Utf8               this
   #46 = Utf8               ()Lscala/collection/immutable/IndexedSeq;
   #47 = Utf8               ()Lscala/collection/immutable/IndexedSeq<Ljava/lang/Object;>;
   #48 = NameAndType        #11:#12       // nestedArgs:Lscala/collection/immutable/IndexedSeq;
   #49 = Fieldref           #2.#48        // org/scalatest/matchers/MidSentenceFailureMessage.nestedArgs:Lscala/collection/immutable/IndexedSeq;
   #50 = Utf8               message
   #51 = Utf8               (Lorg/scalactic/Prettifier;)Ljava/lang/String;
   #52 = Utf8               prettifier
   #53 = NameAndType        #9:#42        // matchResult:()Lorg/scalatest/matchers/MatchResult;
   #54 = Methodref          #2.#53        // org/scalatest/matchers/MidSentenceFailureMessage.matchResult:()Lorg/scalatest/matchers/MatchResult;
   #55 = Utf8               org/scalatest/matchers/MatchResult
   #56 = Class              #55           // org/scalatest/matchers/MatchResult
   #57 = Utf8               midSentenceFailureMessage
   #58 = NameAndType        #57:#51       // midSentenceFailureMessage:(Lorg/scalactic/Prettifier;)Ljava/lang/String;
   #59 = Methodref          #56.#58       // org/scalatest/matchers/MatchResult.midSentenceFailureMessage:(Lorg/scalactic/Prettifier;)Ljava/lang/String;
   #60 = Utf8               Lorg/scalactic/Prettifier;
   #61 = Utf8               copy
   #62 = Utf8               <init>
   #63 = Utf8               (Lorg/scalatest/matchers/MatchResult;)V
   #64 = NameAndType        #62:#63       // "<init>":(Lorg/scalatest/matchers/MatchResult;)V
   #65 = Methodref          #2.#64        // org/scalatest/matchers/MidSentenceFailureMessage."<init>":(Lorg/scalatest/matchers/MatchResult;)V
   #66 = Utf8               copy$default$1
   #67 = Utf8               productPrefix
   #68 = Utf8               ()Ljava/lang/String;
   #69 = Utf8               MidSentenceFailureMessage
   #70 = String             #69           // MidSentenceFailureMessage
   #71 = Utf8               productArity
   #72 = Utf8               ()I
   #73 = Utf8               productElement
   #74 = Utf8               (I)Ljava/lang/Object;
   #75 = Utf8               x$1
   #76 = Utf8               scala/runtime/Statics
   #77 = Class              #76           // scala/runtime/Statics
   #78 = Utf8               ioobe
   #79 = NameAndType        #78:#74       // ioobe:(I)Ljava/lang/Object;
   #80 = Methodref          #77.#79       // scala/runtime/Statics.ioobe:(I)Ljava/lang/Object;
   #81 = Utf8               I
   #82 = Utf8               java/lang/Object
   #83 = Class              #82           // java/lang/Object
   #84 = Utf8               productIterator
   #85 = Utf8               ()Lscala/collection/Iterator;
   #86 = Utf8               ()Lscala/collection/Iterator<Ljava/lang/Object;>;
   #87 = Utf8               scala/runtime/ScalaRunTime$
   #88 = Class              #87           // scala/runtime/ScalaRunTime$
   #89 = Utf8               Lscala/runtime/ScalaRunTime$;
   #90 = NameAndType        #20:#89       // MODULE$:Lscala/runtime/ScalaRunTime$;
   #91 = Fieldref           #88.#90       // scala/runtime/ScalaRunTime$.MODULE$:Lscala/runtime/ScalaRunTime$;
   #92 = Utf8               typedProductIterator
   #93 = Utf8               (Lscala/Product;)Lscala/collection/Iterator;
   #94 = NameAndType        #92:#93       // typedProductIterator:(Lscala/Product;)Lscala/collection/Iterator;
   #95 = Methodref          #88.#94       // scala/runtime/ScalaRunTime$.typedProductIterator:(Lscala/Product;)Lscala/collection/Iterator;
   #96 = Utf8               canEqual
   #97 = Utf8               (Ljava/lang/Object;)Z
   #98 = Utf8               Ljava/lang/Object;
   #99 = Utf8               productElementName
  #100 = Utf8               (I)Ljava/lang/String;
  #101 = String             #9            // matchResult
  #102 = Utf8               java/lang/String
  #103 = Class              #102          // java/lang/String
  #104 = Utf8               hashCode
  #105 = Utf8               _hashCode
  #106 = Utf8               (Lscala/Product;)I
  #107 = NameAndType        #105:#106     // _hashCode:(Lscala/Product;)I
  #108 = Methodref          #88.#107      // scala/runtime/ScalaRunTime$._hashCode:(Lscala/Product;)I
  #109 = Utf8               equals
  #110 = NameAndType        #109:#97      // equals:(Ljava/lang/Object;)Z
  #111 = Methodref          #83.#110      // java/lang/Object.equals:(Ljava/lang/Object;)Z
  #112 = NameAndType        #96:#97       // canEqual:(Ljava/lang/Object;)Z
  #113 = Methodref          #2.#112       // org/scalatest/matchers/MidSentenceFailureMessage.canEqual:(Ljava/lang/Object;)Z
  #114 = Utf8               ()V
  #115 = NameAndType        #62:#114      // "<init>":()V
  #116 = Methodref          #4.#115       // org/scalatest/matchers/LazyMessage."<init>":()V
  #117 = Utf8               failureMessageArgs
  #118 = NameAndType        #117:#46      // failureMessageArgs:()Lscala/collection/immutable/IndexedSeq;
  #119 = Methodref          #56.#118      // org/scalatest/matchers/MatchResult.failureMessageArgs:()Lscala/collection/immutable/IndexedSeq;
  #120 = Utf8               Signature
  #121 = Utf8               Code
  #122 = Utf8               LocalVariableTable
  #123 = Utf8               MethodParameters
  #124 = Utf8               LineNumberTable
  #125 = Utf8               StackMapTable
  #126 = Utf8               SourceFile
  #127 = Utf8               RuntimeVisibleAnnotations
  #128 = Utf8               ScalaInlineInfo
  #129 = Utf8               ScalaSig
{
  private final org.scalatest.matchers.MatchResult matchResult;
    descriptor: Lorg/scalatest/matchers/MatchResult;
    flags: (0x0012) ACC_PRIVATE, ACC_FINAL

  private final scala.collection.immutable.IndexedSeq<java.lang.Object> nestedArgs;
    descriptor: Lscala/collection/immutable/IndexedSeq;
    flags: (0x0012) ACC_PRIVATE, ACC_FINAL
    Signature: #13                          // Lscala/collection/immutable/IndexedSeq<Ljava/lang/Object;>;

  public static scala.Option<org.scalatest.matchers.MatchResult> unapply(org.scalatest.matchers.MidSentenceFailureMessage);
    descriptor: (Lorg/scalatest/matchers/MidSentenceFailureMessage;)Lscala/Option;
    flags: (0x0009) ACC_PUBLIC, ACC_STATIC
    Code:
      stack=2, locals=1, args_size=1
         0: getstatic     #23                 // Field org/scalatest/matchers/MidSentenceFailureMessage$.MODULE$:Lorg/scalatest/matchers/MidSentenceFailureMessage$;
         3: aload_0
         4: invokevirtual #25                 // Method org/scalatest/matchers/MidSentenceFailureMessage$.unapply:(Lorg/scalatest/matchers/MidSentenceFailureMessage;)Lscala/Option;
         7: areturn
      LocalVariableTable:
        Start  Length  Slot  Name   Signature
            0       8     0   x$0   Lorg/scalatest/matchers/MidSentenceFailureMessage;
    Signature: #16                          // (Lorg/scalatest/matchers/MidSentenceFailureMessage;)Lscala/Option<Lorg/scalatest/matchers/MatchResult;>;
    MethodParameters:
      Name                           Flags
      x$0                            final

  public static org.scalatest.matchers.MidSentenceFailureMessage apply(org.scalatest.matchers.MatchResult);
    descriptor: (Lorg/scalatest/matchers/MatchResult;)Lorg/scalatest/matchers/MidSentenceFailureMessage;
    flags: (0x0009) ACC_PUBLIC, ACC_STATIC
    Code:
      stack=2, locals=1, args_size=1
         0: getstatic     #23                 // Field org/scalatest/matchers/MidSentenceFailureMessage$.MODULE$:Lorg/scalatest/matchers/MidSentenceFailureMessage$;
         3: aload_0
         4: invokevirtual #30                 // Method org/scalatest/matchers/MidSentenceFailureMessage$.apply:(Lorg/scalatest/matchers/MatchResult;)Lorg/scalatest/matchers/MidSentenceFailureMessage;
         7: areturn
      LocalVariableTable:
        Start  Length  Slot  Name   Signature
            0       8     0 matchResult   Lorg/scalatest/matchers/MatchResult;
    MethodParameters:
      Name                           Flags
      matchResult                    final

  public static <A extends java.lang.Object> scala.Function1<org.scalatest.matchers.MatchResult, A> andThen(scala.Function1<org.scalatest.matchers.MidSentenceFailureMessage, A>);
    descriptor: (Lscala/Function1;)Lscala/Function1;
    flags: (0x0009) ACC_PUBLIC, ACC_STATIC
    Code:
      stack=2, locals=1, args_size=1
         0: getstatic     #23                 // Field org/scalatest/matchers/MidSentenceFailureMessage$.MODULE$:Lorg/scalatest/matchers/MidSentenceFailureMessage$;
         3: aload_0
         4: invokevirtual #36                 // Method org/scalatest/matchers/MidSentenceFailureMessage$.andThen:(Lscala/Function1;)Lscala/Function1;
         7: areturn
      LocalVariableTable:
        Start  Length  Slot  Name   Signature
            0       8     0     g   Lscala/Function1;
    Signature: #33                          // <A:Ljava/lang/Object;>(Lscala/Function1<Lorg/scalatest/matchers/MidSentenceFailureMessage;TA;>;)Lscala/Function1<Lorg/scalatest/matchers/MatchResult;TA;>;
    MethodParameters:
      Name                           Flags
      g                              final

  public static <A extends java.lang.Object> scala.Function1<A, org.scalatest.matchers.MidSentenceFailureMessage> compose(scala.Function1<A, org.scalatest.matchers.MatchResult>);
    descriptor: (Lscala/Function1;)Lscala/Function1;
    flags: (0x0009) ACC_PUBLIC, ACC_STATIC
    Code:
      stack=2, locals=1, args_size=1
         0: getstatic     #23                 // Field org/scalatest/matchers/MidSentenceFailureMessage$.MODULE$:Lorg/scalatest/matchers/MidSentenceFailureMessage$;
         3: aload_0
         4: invokevirtual #41                 // Method org/scalatest/matchers/MidSentenceFailureMessage$.compose:(Lscala/Function1;)Lscala/Function1;
         7: areturn
      LocalVariableTable:
        Start  Length  Slot  Name   Signature
            0       8     0     g   Lscala/Function1;
    Signature: #39                          // <A:Ljava/lang/Object;>(Lscala/Function1<TA;Lorg/scalatest/matchers/MatchResult;>;)Lscala/Function1<TA;Lorg/scalatest/matchers/MidSentenceFailureMessage;>;
    MethodParameters:
      Name                           Flags
      g                              final

  public org.scalatest.matchers.MatchResult matchResult();
    descriptor: ()Lorg/scalatest/matchers/MatchResult;
    flags: (0x0001) ACC_PUBLIC
    Code:
      stack=1, locals=1, args_size=1
         0: aload_0
         1: getfield      #44                 // Field matchResult:Lorg/scalatest/matchers/MatchResult;
         4: areturn
      LineNumberTable:
        line 37: 0
      LocalVariableTable:
        Start  Length  Slot  Name   Signature
            0       5     0  this   Lorg/scalatest/matchers/MidSentenceFailureMessage;

  public scala.collection.immutable.IndexedSeq<java.lang.Object> nestedArgs();
    descriptor: ()Lscala/collection/immutable/IndexedSeq;
    flags: (0x0001) ACC_PUBLIC
    Code:
      stack=1, locals=1, args_size=1
         0: aload_0
         1: getfield      #49                 // Field nestedArgs:Lscala/collection/immutable/IndexedSeq;
         4: areturn
      LineNumberTable:
        line 38: 0
      LocalVariableTable:
        Start  Length  Slot  Name   Signature
            0       5     0  this   Lorg/scalatest/matchers/MidSentenceFailureMessage;
    Signature: #47                          // ()Lscala/collection/immutable/IndexedSeq<Ljava/lang/Object;>;

  public java.lang.String message(org.scalactic.Prettifier);
    descriptor: (Lorg/scalactic/Prettifier;)Ljava/lang/String;
    flags: (0x0001) ACC_PUBLIC
    Code:
      stack=2, locals=2, args_size=2
         0: aload_0
         1: invokevirtual #54                 // Method matchResult:()Lorg/scalatest/matchers/MatchResult;
         4: aload_1
         5: invokevirtual #59                 // Method org/scalatest/matchers/MatchResult.midSentenceFailureMessage:(Lorg/scalactic/Prettifier;)Ljava/lang/String;
         8: areturn
      LineNumberTable:
        line 39: 0
      LocalVariableTable:
        Start  Length  Slot  Name   Signature
            0       9     0  this   Lorg/scalatest/matchers/MidSentenceFailureMessage;
            0       9     1 prettifier   Lorg/scalactic/Prettifier;
    MethodParameters:
      Name                           Flags
      prettifier                     final

  public org.scalatest.matchers.MidSentenceFailureMessage copy(org.scalatest.matchers.MatchResult);
    descriptor: (Lorg/scalatest/matchers/MatchResult;)Lorg/scalatest/matchers/MidSentenceFailureMessage;
    flags: (0x0001) ACC_PUBLIC
    Code:
      stack=3, locals=2, args_size=2
         0: new           #2                  // class org/scalatest/matchers/MidSentenceFailureMessage
         3: dup
         4: aload_1
         5: invokespecial #65                 // Method "<init>":(Lorg/scalatest/matchers/MatchResult;)V
         8: areturn
      LineNumberTable:
        line 37: 0
      LocalVariableTable:
        Start  Length  Slot  Name   Signature
            0       9     0  this   Lorg/scalatest/matchers/MidSentenceFailureMessage;
            0       9     1 matchResult   Lorg/scalatest/matchers/MatchResult;
    MethodParameters:
      Name                           Flags
      matchResult                    final

  public org.scalatest.matchers.MatchResult copy$default$1();
    descriptor: ()Lorg/scalatest/matchers/MatchResult;
    flags: (0x0001) ACC_PUBLIC
    Code:
      stack=1, locals=1, args_size=1
         0: aload_0
         1: invokevirtual #54                 // Method matchResult:()Lorg/scalatest/matchers/MatchResult;
         4: areturn
      LineNumberTable:
        line 37: 0
      LocalVariableTable:
        Start  Length  Slot  Name   Signature
            0       5     0  this   Lorg/scalatest/matchers/MidSentenceFailureMessage;

  public java.lang.String productPrefix();
    descriptor: ()Ljava/lang/String;
    flags: (0x0001) ACC_PUBLIC
    Code:
      stack=1, locals=1, args_size=1
         0: ldc           #70                 // String MidSentenceFailureMessage
         2: areturn
      LineNumberTable:
        line 37: 0
      LocalVariableTable:
        Start  Length  Slot  Name   Signature
            0       3     0  this   Lorg/scalatest/matchers/MidSentenceFailureMessage;

  public int productArity();
    descriptor: ()I
    flags: (0x0001) ACC_PUBLIC
    Code:
      stack=1, locals=1, args_size=1
         0: iconst_1
         1: ireturn
      LineNumberTable:
        line 37: 0
      LocalVariableTable:
        Start  Length  Slot  Name   Signature
            0       2     0  this   Lorg/scalatest/matchers/MidSentenceFailureMessage;

  public java.lang.Object productElement(int);
    descriptor: (I)Ljava/lang/Object;
    flags: (0x0001) ACC_PUBLIC
    Code:
      stack=1, locals=3, args_size=2
         0: iload_1
         1: istore_2
         2: iload_2
         3: tableswitch   { // 0 to 0
                       0: 20
                 default: 27
            }
        20: aload_0
        21: invokevirtual #54                 // Method matchResult:()Lorg/scalatest/matchers/MatchResult;
        24: goto          34
        27: iload_1
        28: invokestatic  #80                 // Method scala/runtime/Statics.ioobe:(I)Ljava/lang/Object;
        31: goto          34
        34: areturn
      StackMapTable: number_of_entries = 3
        frame_type = 252 /* append */
          offset_delta = 20
          locals = [ int ]
        frame_type = 6 /* same */
        frame_type = 70 /* same_locals_1_stack_item */
          stack = [ class java/lang/Object ]
      LineNumberTable:
        line 37: 0
      LocalVariableTable:
        Start  Length  Slot  Name   Signature
            0      35     0  this   Lorg/scalatest/matchers/MidSentenceFailureMessage;
            0      35     1   x$1   I
    MethodParameters:
      Name                           Flags
      x$1                            final

  public scala.collection.Iterator<java.lang.Object> productIterator();
    descriptor: ()Lscala/collection/Iterator;
    flags: (0x0001) ACC_PUBLIC
    Code:
      stack=2, locals=1, args_size=1
         0: getstatic     #91                 // Field scala/runtime/ScalaRunTime$.MODULE$:Lscala/runtime/ScalaRunTime$;
         3: aload_0
         4: invokevirtual #95                 // Method scala/runtime/ScalaRunTime$.typedProductIterator:(Lscala/Product;)Lscala/collection/Iterator;
         7: areturn
      LineNumberTable:
        line 37: 0
      LocalVariableTable:
        Start  Length  Slot  Name   Signature
            0       8     0  this   Lorg/scalatest/matchers/MidSentenceFailureMessage;
    Signature: #86                          // ()Lscala/collection/Iterator<Ljava/lang/Object;>;

  public boolean canEqual(java.lang.Object);
    descriptor: (Ljava/lang/Object;)Z
    flags: (0x0001) ACC_PUBLIC
    Code:
      stack=1, locals=2, args_size=2
         0: aload_1
         1: instanceof    #2                  // class org/scalatest/matchers/MidSentenceFailureMessage
         4: ireturn
      LineNumberTable:
        line 37: 0
      LocalVariableTable:
        Start  Length  Slot  Name   Signature
            0       5     0  this   Lorg/scalatest/matchers/MidSentenceFailureMessage;
            0       5     1   x$1   Ljava/lang/Object;
    MethodParameters:
      Name                           Flags
      x$1                            final

  public java.lang.String productElementName(int);
    descriptor: (I)Ljava/lang/String;
    flags: (0x0001) ACC_PUBLIC
    Code:
      stack=1, locals=3, args_size=2
         0: iload_1
         1: istore_2
         2: iload_2
         3: tableswitch   { // 0 to 0
                       0: 20
                 default: 25
            }
        20: ldc           #101                // String matchResult
        22: goto          35
        25: iload_1
        26: invokestatic  #80                 // Method scala/runtime/Statics.ioobe:(I)Ljava/lang/Object;
        29: checkcast     #103                // class java/lang/String
        32: goto          35
        35: areturn
      StackMapTable: number_of_entries = 3
        frame_type = 252 /* append */
          offset_delta = 20
          locals = [ int ]
        frame_type = 4 /* same */
        frame_type = 73 /* same_locals_1_stack_item */
          stack = [ class java/lang/String ]
      LineNumberTable:
        line 37: 0
      LocalVariableTable:
        Start  Length  Slot  Name   Signature
            0      36     0  this   Lorg/scalatest/matchers/MidSentenceFailureMessage;
            0      36     1   x$1   I
    MethodParameters:
      Name                           Flags
      x$1                            final

  public int hashCode();
    descriptor: ()I
    flags: (0x0001) ACC_PUBLIC
    Code:
      stack=2, locals=1, args_size=1
         0: getstatic     #91                 // Field scala/runtime/ScalaRunTime$.MODULE$:Lscala/runtime/ScalaRunTime$;
         3: aload_0
         4: invokevirtual #108                // Method scala/runtime/ScalaRunTime$._hashCode:(Lscala/Product;)I
         7: ireturn
      LineNumberTable:
        line 37: 0
      LocalVariableTable:
        Start  Length  Slot  Name   Signature
            0       8     0  this   Lorg/scalatest/matchers/MidSentenceFailureMessage;

  public boolean equals(java.lang.Object);
    descriptor: (Ljava/lang/Object;)Z
    flags: (0x0001) ACC_PUBLIC
    Code:
      stack=2, locals=6, args_size=2
         0: aload_0
         1: aload_1
         2: if_acmpeq     86
         5: aload_1
         6: astore_3
         7: aload_3
         8: instanceof    #2                  // class org/scalatest/matchers/MidSentenceFailureMessage
        11: ifeq          19
        14: iconst_1
        15: istore_2
        16: goto          27
        19: goto          22
        22: iconst_0
        23: istore_2
        24: goto          27
        27: iload_2
        28: ifeq          90
        31: aload_1
        32: checkcast     #2                  // class org/scalatest/matchers/MidSentenceFailureMessage
        35: astore        4
        37: aload_0
        38: invokevirtual #54                 // Method matchResult:()Lorg/scalatest/matchers/MatchResult;
        41: aload         4
        43: invokevirtual #54                 // Method matchResult:()Lorg/scalatest/matchers/MatchResult;
        46: astore        5
        48: dup
        49: ifnonnull     61
        52: pop
        53: aload         5
        55: ifnull        69
        58: goto          82
        61: aload         5
        63: invokevirtual #111                // Method java/lang/Object.equals:(Ljava/lang/Object;)Z
        66: ifeq          82
        69: aload         4
        71: aload_0
        72: invokevirtual #113                // Method canEqual:(Ljava/lang/Object;)Z
        75: ifeq          82
        78: iconst_1
        79: goto          83
        82: iconst_0
        83: ifeq          90
        86: iconst_1
        87: goto          91
        90: iconst_0
        91: ireturn
      StackMapTable: number_of_entries = 10
        frame_type = 253 /* append */
          offset_delta = 19
          locals = [ top, class java/lang/Object ]
        frame_type = 2 /* same */
        frame_type = 255 /* full_frame */
          offset_delta = 4
          locals = [ class org/scalatest/matchers/MidSentenceFailureMessage, class java/lang/Object, int, class java/lang/Object ]
          stack = []
        frame_type = 255 /* full_frame */
          offset_delta = 33
          locals = [ class org/scalatest/matchers/MidSentenceFailureMessage, class java/lang/Object, int, class java/lang/Object, class org/scalatest/matchers/MidSentenceFailureMessage, class org/scalatest/matchers/MatchResult ]
          stack = [ class org/scalatest/matchers/MatchResult ]
        frame_type = 7 /* same */
        frame_type = 12 /* same */
        frame_type = 64 /* same_locals_1_stack_item */
          stack = [ int ]
        frame_type = 255 /* full_frame */
          offset_delta = 2
          locals = [ class org/scalatest/matchers/MidSentenceFailureMessage, class java/lang/Object ]
          stack = []
        frame_type = 253 /* append */
          offset_delta = 3
          locals = [ int, class java/lang/Object ]
        frame_type = 255 /* full_frame */
          offset_delta = 0
          locals = [ class org/scalatest/matchers/MidSentenceFailureMessage, class java/lang/Object ]
          stack = [ int ]
      LineNumberTable:
        line 37: 0
      LocalVariableTable:
        Start  Length  Slot  Name   Signature
            0      92     0  this   Lorg/scalatest/matchers/MidSentenceFailureMessage;
            0      92     1   x$1   Ljava/lang/Object;
    MethodParameters:
      Name                           Flags
      x$1                            final

  public org.scalatest.matchers.MidSentenceFailureMessage(org.scalatest.matchers.MatchResult);
    descriptor: (Lorg/scalatest/matchers/MatchResult;)V
    flags: (0x0001) ACC_PUBLIC
    Code:
      stack=2, locals=2, args_size=2
         0: aload_0
         1: aload_1
         2: putfield      #44                 // Field matchResult:Lorg/scalatest/matchers/MatchResult;
         5: aload_0
         6: invokespecial #116                // Method org/scalatest/matchers/LazyMessage."<init>":()V
         9: aload_0
        10: aload_1
        11: invokevirtual #119                // Method org/scalatest/matchers/MatchResult.failureMessageArgs:()Lscala/collection/immutable/IndexedSeq;
        14: putfield      #49                 // Field nestedArgs:Lscala/collection/immutable/IndexedSeq;
        17: return
      LineNumberTable:
        line 37: 0
        line 38: 9
        line 37: 17
      LocalVariableTable:
        Start  Length  Slot  Name   Signature
            0      18     0  this   Lorg/scalatest/matchers/MidSentenceFailureMessage;
            0      18     1 matchResult   Lorg/scalatest/matchers/MatchResult;
    MethodParameters:
      Name                           Flags
      matchResult                    final
}
SourceFile: "LazyMessage.scala"
RuntimeVisibleAnnotations:
  0: #6(#7=s#8)
    scala.reflect.ScalaSignature(
      bytes="\u0006\u0005\u0005\u001dd!\u0002\r\u001a\u0001ny\u0002\u0002C\u001c\u0001\u0005+\u0007I\u0011\u0001\u001d\t\u0011q\u0002!\u0011#Q\u0001\neBQ!\u0010\u0001\u0005\u0002yBq!\u0011\u0001C\u0002\u0013\u0005!\t\u0003\u0004J\u0001\u0001\u0006Ia\u0011\u0005\u0006\u0015\u0002!\ta\u0013\u0005\b9\u0002\t\t\u0011\"\u0001^\u0011\u001dy\u0006!%A\u0005\u0002\u0001Dqa\u001b\u0001\u0002\u0002\u0013\u0005C\u000eC\u0004u\u0001\u0005\u0005I\u0011A;\t\u000fe\u0004\u0011\u0011!C\u0001u\"9Q\u0010AA\u0001\n\u0003r\b\"CA\u0006\u0001\u0005\u0005I\u0011AA\u0007\u0011%\t9\u0002AA\u0001\n\u0003\nI\u0002C\u0005\u0002\u001e\u0001\t\t\u0011\"\u0011\u0002 !I\u0011\u0011\u0005\u0001\u0002\u0002\u0013\u0005\u00131E\u0004\u000b\u0003OI\u0012\u0011!E\u00017\u0005%b!\u0003\r\u001a\u0003\u0003E\taGA\u0016\u0011\u0019i$\u0003\"\u0001\u0002D!I\u0011Q\t\n\u0002\u0002\u0013\u0015\u0013q\t\u0005\n\u0003\u0013\u0012\u0012\u0011!CA\u0003\u0017B\u0011\"a\u0014\u0013\u0003\u0003%\t)!\u0015\t\u0013\u0005u##!A\u0005\n\u0005}#!G\'jIN+g\u000e^3oG\u00164\u0015-\u001b7ve\u0016lUm]:bO\u0016T!AG\u000e\u0002\u00115\fGo\u00195feNT!\u0001H\u000f\u0002\u0013M\u001c\u0017\r\\1uKN$(\"\u0001\u0010\u0002\u0007=\u0014xm\u0005\u0003\u0001A\u0011R\u0003CA\u0011#\u001b\u0005I\u0012BA\u0012\u001a\u0005-a\u0015M_=NKN\u001c\u0018mZ3\u0011\u0005\u0015BS\"\u0001\u0014\u000b\u0003\u001d\nQa]2bY\u0006L!!\u000b\u0014\u0003\u000fA\u0013x\u000eZ;diB\u00111\u0006\u000e\b\u0003YIr!!L\u0019\u000e\u00039R!a\f\u0019\u0002\rq\u0012xn\u001c;?\u0007\u0001I\u0011aJ\u0005\u0003g\u0019\nq\u0001]1dW\u0006<W-\u0003\u00026m\ta1+\u001a:jC2L\'0\u00192mK*\u00111GJ\u0001\f[\u0006$8\r\u001b*fgVdG/F\u0001:!\t\t#(\u0003\u0002<3\tYQ*\u0019;dQJ+7/\u001e7u\u00031i\u0017\r^2i%\u0016\u001cX\u000f\u001c;!\u0003\u0019a\u0014N\\5u}Q\u0011q\b\u0011\t\u0003C\u0001AQaN\u0002A\u0002e\n!B\\3ti\u0016$\u0017I]4t+\u0005\u0019\u0005cA\u0016E\r&\u0011QI\u000e\u0002\u000b\u0013:$W\r_3e\'\u0016\f\bCA\u0013H\u0013\tAeEA\u0002B]f\f1B\\3ti\u0016$\u0017I]4tA\u00059Q.Z:tC\u001e,GC\u0001\'U!\ti\u0015K\u0004\u0002O\u001fB\u0011QFJ\u0005\u0003!\u001a\na\u0001\u0015:fI\u00164\u0017B\u0001*T\u0005\u0019\u0019FO]5oO*\u0011\u0001K\n\u0005\u0006+\u001a\u0001\rAV\u0001\u000baJ,G\u000f^5gS\u0016\u0014\bCA,[\u001b\u0005A&BA-\u001e\u0003%\u00198-\u00197bGRL7-\u0003\u0002\\1\nQ\u0001K]3ui&4\u0017.\u001a:\u0002\t\r|\u0007/\u001f\u000b\u0003\u007fyCqaN\u0004\u0011\u0002\u0003\u0007\u0011(\u0001\bd_BLH\u0005Z3gCVdG\u000fJ\u0019\u0016\u0003\u0005T#!\u000f2,\u0003\r\u0004\"\u0001Z5\u000e\u0003\u0015T!AZ4\u0002\u0013Ut7\r[3dW\u0016$\'B\u00015\'\u0003)\tgN\\8uCRLwN\\\u0005\u0003U\u0016\u0014\u0011#\u001e8dQ\u0016\u001c7.\u001a3WCJL\u0017M\\2f\u00035\u0001(o\u001c3vGR\u0004&/\u001a4jqV\tQ\u000e\u0005\u0002og6\tqN\u0003\u0002qc\u0006!A.\u00198h\u0015\u0005\u0011\u0018\u0001\u00026bm\u0006L!AU8\u0002\u0019A\u0014x\u000eZ;di\u0006\u0013\u0018\u000e^=\u0016\u0003Y\u0004\"!J<\n\u0005a4#aA%oi\u0006q\u0001O]8ek\u000e$X\t\\3nK:$HC\u0001$|\u0011\u001da8\"!AA\u0002Y\f1\u0001\u001f\u00132\u0003=\u0001(o\u001c3vGRLE/\u001a:bi>\u0014X#A@\u0011\u000b\u0005\u0005\u0011q\u0001$\u000e\u0005\u0005\r!bAA\u0003M\u0005Q1m\u001c7mK\u000e$\u0018n\u001c8\n\t\u0005%\u00111\u0001\u0002\t\u0013R,\'/\u0019;pe\u0006A1-\u00198FcV\fG\u000e\u0006\u0003\u0002\u0010\u0005U\u0001cA\u0013\u0002\u0012%\u0019\u00111\u0003\u0014\u0003\u000f\t{w\u000e\\3b]\"9A0DA\u0001\u0002\u00041\u0015A\u00059s_\u0012,8\r^#mK6,g\u000e\u001e(b[\u0016$2!\\A\u000e\u0011\u001dah\"!AA\u0002Y\f\u0001\u0002[1tQ\u000e{G-\u001a\u000b\u0002m\u00061Q-];bYN$B!a\u0004\u0002&!9A\u0010EA\u0001\u0002\u00041\u0015!G\'jIN+g\u000e^3oG\u00164\u0015-\u001b7ve\u0016lUm]:bO\u0016\u0004\"!\t\n\u0014\u000bI\ti#!\u000f\u0011\r\u0005=\u0012QG\u001d@\u001b\t\t\tDC\u0002\u00024\u0019\nqA];oi&lW-\u0003\u0003\u00028\u0005E\"!E!cgR\u0014\u0018m\u0019;Gk:\u001cG/[8ocA!\u00111HA!\u001b\t\tiDC\u0002\u0002@E\f!![8\n\u0007U\ni\u0004\u0006\u0002\u0002*\u0005AAo\\*ue&tw\rF\u0001n\u0003\u0015\t\u0007\u000f\u001d7z)\ry\u0014Q\n\u0005\u0006oU\u0001\r!O\u0001\bk:\f\u0007\u000f\u001d7z)\u0011\t\u0019&!\u0017\u0011\t\u0015\n)&O\u0005\u0004\u0003/2#AB(qi&|g\u000e\u0003\u0005\u0002\\Y\t\t\u00111\u0001@\u0003\rAH\u0005M\u0001\roJLG/\u001a*fa2\f7-\u001a\u000b\u0003\u0003C\u00022A\\A2\u0013\r\t)g\u001c\u0002\u0007\u001f\nTWm\u0019;"
    )
  ScalaInlineInfo: length = 0x4A (unknown attribute)
   01 00 00 0E 00 3E 00 3F 00 00 60 00 61 00 00 3D
   00 1C 00 00 42 00 2A 00 00 6D 00 61 00 00 68 00
   48 00 00 09 00 2A 00 00 32 00 33 00 00 0B 00 2E
   00 00 47 00 48 00 00 49 00 4A 00 00 63 00 64 00
   00 54 00 55 00 00 43 00 44 00
  ScalaSig: length = 0x3 (unknown attribute)
   05 02 00
