Classfile /Users/mw/Projects/slang-braindump/.jar/jar8/assemble/slang-braindump/assemble/content/org/scalatest/matchers/TypeMatcherHelper$.class
  Last modified May 29, 2022; size 8034 bytes
  SHA-256 checksum 7bc2690a2aba0dcec779cd8035fa6b7862aaef163357268a3e796b29b4a9cb0c
  Compiled from "TypeMatcherHelper.scala"
public final class org.scalatest.matchers.TypeMatcherHelper$
  minor version: 0
  major version: 52
  flags: (0x0031) ACC_PUBLIC, ACC_FINAL, ACC_SUPER
  this_class: #2                          // org/scalatest/matchers/TypeMatcherHelper$
  super_class: #4                         // java/lang/Object
  interfaces: 0, fields: 1, methods: 11, attributes: 4
Constant pool:
    #1 = Utf8               org/scalatest/matchers/TypeMatcherHelper$
    #2 = Class              #1            // org/scalatest/matchers/TypeMatcherHelper$
    #3 = Utf8               java/lang/Object
    #4 = Class              #3            // java/lang/Object
    #5 = Utf8               TypeMatcherHelper.scala
    #6 = Utf8               org/scalatest/matchers/TypeMatcherHelper$$anon$1
    #7 = Class              #6            // org/scalatest/matchers/TypeMatcherHelper$$anon$1
    #8 = Utf8               org/scalatest/matchers/TypeMatcherHelper$$anon$2
    #9 = Class              #8            // org/scalatest/matchers/TypeMatcherHelper$$anon$2
   #10 = Utf8               org/scalatest/matchers/TypeMatcherHelper$$anon$3
   #11 = Class              #10           // org/scalatest/matchers/TypeMatcherHelper$$anon$3
   #12 = Utf8               org/scalatest/matchers/TypeMatcherHelper$$anon$4
   #13 = Class              #12           // org/scalatest/matchers/TypeMatcherHelper$$anon$4
   #14 = Utf8               MODULE$
   #15 = Utf8               Lorg/scalatest/matchers/TypeMatcherHelper$;
   #16 = Utf8               <clinit>
   #17 = Utf8               ()V
   #18 = Utf8               <init>
   #19 = NameAndType        #18:#17       // "<init>":()V
   #20 = Methodref          #2.#19        // org/scalatest/matchers/TypeMatcherHelper$."<init>":()V
   #21 = NameAndType        #14:#15       // MODULE$:Lorg/scalatest/matchers/TypeMatcherHelper$;
   #22 = Fieldref           #2.#21        // org/scalatest/matchers/TypeMatcherHelper$.MODULE$:Lorg/scalatest/matchers/TypeMatcherHelper$;
   #23 = Utf8               aTypeMatcher
   #24 = Utf8               (Lorg/scalatest/matchers/dsl/ResultOfATypeInvocation;)Lorg/scalatest/matchers/Matcher;
   #25 = Utf8               (Lorg/scalatest/matchers/dsl/ResultOfATypeInvocation<*>;)Lorg/scalatest/matchers/Matcher<Ljava/lang/Object;>;
   #26 = Utf8               aType
   #27 = Utf8               (Lorg/scalatest/matchers/dsl/ResultOfATypeInvocation;)V
   #28 = NameAndType        #18:#27       // "<init>":(Lorg/scalatest/matchers/dsl/ResultOfATypeInvocation;)V
   #29 = Methodref          #7.#28        // org/scalatest/matchers/TypeMatcherHelper$$anon$1."<init>":(Lorg/scalatest/matchers/dsl/ResultOfATypeInvocation;)V
   #30 = Utf8               this
   #31 = Utf8               Lorg/scalatest/matchers/dsl/ResultOfATypeInvocation;
   #32 = Utf8               anTypeMatcher
   #33 = Utf8               (Lorg/scalatest/matchers/dsl/ResultOfAnTypeInvocation;)Lorg/scalatest/matchers/Matcher;
   #34 = Utf8               (Lorg/scalatest/matchers/dsl/ResultOfAnTypeInvocation<*>;)Lorg/scalatest/matchers/Matcher<Ljava/lang/Object;>;
   #35 = Utf8               anType
   #36 = Utf8               (Lorg/scalatest/matchers/dsl/ResultOfAnTypeInvocation;)V
   #37 = NameAndType        #18:#36       // "<init>":(Lorg/scalatest/matchers/dsl/ResultOfAnTypeInvocation;)V
   #38 = Methodref          #9.#37        // org/scalatest/matchers/TypeMatcherHelper$$anon$2."<init>":(Lorg/scalatest/matchers/dsl/ResultOfAnTypeInvocation;)V
   #39 = Utf8               Lorg/scalatest/matchers/dsl/ResultOfAnTypeInvocation;
   #40 = Utf8               notATypeMatcher
   #41 = Methodref          #11.#28       // org/scalatest/matchers/TypeMatcherHelper$$anon$3."<init>":(Lorg/scalatest/matchers/dsl/ResultOfATypeInvocation;)V
   #42 = Utf8               notAnTypeMatcher
   #43 = Methodref          #13.#37       // org/scalatest/matchers/TypeMatcherHelper$$anon$4."<init>":(Lorg/scalatest/matchers/dsl/ResultOfAnTypeInvocation;)V
   #44 = Utf8               org$scalatest$matchers$TypeMatcherHelper$$conform
   #45 = Utf8               (Lscala/reflect/ClassTag;Ljava/lang/Object;)Z
   #46 = Utf8               <T:Ljava/lang/Object;>(Lscala/reflect/ClassTag<TT;>;Ljava/lang/Object;)Z
   #47 = Utf8               classTag
   #48 = Utf8               x
   #49 = Utf8               scala/reflect/ClassTag$
   #50 = Class              #49           // scala/reflect/ClassTag$
   #51 = Utf8               Lscala/reflect/ClassTag$;
   #52 = NameAndType        #14:#51       // MODULE$:Lscala/reflect/ClassTag$;
   #53 = Fieldref           #50.#52       // scala/reflect/ClassTag$.MODULE$:Lscala/reflect/ClassTag$;
   #54 = Utf8               AnyVal
   #55 = Utf8               ()Lscala/reflect/ClassTag;
   #56 = NameAndType        #54:#55       // AnyVal:()Lscala/reflect/ClassTag;
   #57 = Methodref          #50.#56       // scala/reflect/ClassTag$.AnyVal:()Lscala/reflect/ClassTag;
   #58 = Utf8               equals
   #59 = Utf8               (Ljava/lang/Object;)Z
   #60 = NameAndType        #58:#59       // equals:(Ljava/lang/Object;)Z
   #61 = Methodref          #4.#60        // java/lang/Object.equals:(Ljava/lang/Object;)Z
   #62 = Utf8               java/lang/Byte
   #63 = Class              #62           // java/lang/Byte
   #64 = Utf8               java/lang/Short
   #65 = Class              #64           // java/lang/Short
   #66 = Utf8               java/lang/Character
   #67 = Class              #66           // java/lang/Character
   #68 = Utf8               java/lang/Integer
   #69 = Class              #68           // java/lang/Integer
   #70 = Utf8               java/lang/Long
   #71 = Class              #70           // java/lang/Long
   #72 = Utf8               java/lang/Float
   #73 = Class              #72           // java/lang/Float
   #74 = Utf8               java/lang/Double
   #75 = Class              #74           // java/lang/Double
   #76 = Utf8               java/lang/Boolean
   #77 = Class              #76           // java/lang/Boolean
   #78 = Utf8               scala/reflect/ClassTag
   #79 = Class              #78           // scala/reflect/ClassTag
   #80 = Utf8               runtimeClass
   #81 = Utf8               ()Ljava/lang/Class;
   #82 = NameAndType        #80:#81       // runtimeClass:()Ljava/lang/Class;
   #83 = InterfaceMethodref #79.#82       // scala/reflect/ClassTag.runtimeClass:()Ljava/lang/Class;
   #84 = Utf8               java/lang/Class
   #85 = Class              #84           // java/lang/Class
   #86 = Utf8               isInstance
   #87 = NameAndType        #86:#59       // isInstance:(Ljava/lang/Object;)Z
   #88 = Methodref          #85.#87       // java/lang/Class.isInstance:(Ljava/lang/Object;)Z
   #89 = Utf8               TYPE
   #90 = Utf8               Ljava/lang/Class;
   #91 = NameAndType        #89:#90       // TYPE:Ljava/lang/Class;
   #92 = Fieldref           #63.#91       // java/lang/Byte.TYPE:Ljava/lang/Class;
   #93 = Utf8               isAssignableFrom
   #94 = Utf8               (Ljava/lang/Class;)Z
   #95 = NameAndType        #93:#94       // isAssignableFrom:(Ljava/lang/Class;)Z
   #96 = Methodref          #85.#95       // java/lang/Class.isAssignableFrom:(Ljava/lang/Class;)Z
   #97 = Fieldref           #65.#91       // java/lang/Short.TYPE:Ljava/lang/Class;
   #98 = Fieldref           #67.#91       // java/lang/Character.TYPE:Ljava/lang/Class;
   #99 = Fieldref           #69.#91       // java/lang/Integer.TYPE:Ljava/lang/Class;
  #100 = Fieldref           #71.#91       // java/lang/Long.TYPE:Ljava/lang/Class;
  #101 = Fieldref           #73.#91       // java/lang/Float.TYPE:Ljava/lang/Class;
  #102 = Fieldref           #75.#91       // java/lang/Double.TYPE:Ljava/lang/Class;
  #103 = Fieldref           #77.#91       // java/lang/Boolean.TYPE:Ljava/lang/Class;
  #104 = Utf8               scala/runtime/BoxedUnit
  #105 = Class              #104          // scala/runtime/BoxedUnit
  #106 = Fieldref           #105.#91      // scala/runtime/BoxedUnit.TYPE:Ljava/lang/Class;
  #107 = Utf8               Lscala/reflect/ClassTag;
  #108 = Utf8               Ljava/lang/Object;
  #109 = Utf8               assertAType
  #110 = Utf8               (Ljava/lang/Object;Lorg/scalatest/matchers/dsl/ResultOfATypeInvocation;Lorg/scalactic/Prettifier;Lorg/scalactic/source/Position;)Lorg/scalatest/compatible/Assertion;
  #111 = Utf8               (Ljava/lang/Object;Lorg/scalatest/matchers/dsl/ResultOfATypeInvocation<*>;Lorg/scalactic/Prettifier;Lorg/scalactic/source/Position;)Lorg/scalatest/compatible/Assertion;
  #112 = Utf8               left
  #113 = Utf8               prettifier
  #114 = Utf8               pos
  #115 = Utf8               org/scalatest/matchers/dsl/ResultOfATypeInvocation
  #116 = Class              #115          // org/scalatest/matchers/dsl/ResultOfATypeInvocation
  #117 = Utf8               clazz
  #118 = NameAndType        #117:#81      // clazz:()Ljava/lang/Class;
  #119 = Methodref          #116.#118     // org/scalatest/matchers/dsl/ResultOfATypeInvocation.clazz:()Ljava/lang/Class;
  #120 = Utf8               clazzTag
  #121 = NameAndType        #120:#55      // clazzTag:()Lscala/reflect/ClassTag;
  #122 = Methodref          #116.#121     // org/scalatest/matchers/dsl/ResultOfATypeInvocation.clazzTag:()Lscala/reflect/ClassTag;
  #123 = NameAndType        #44:#45       // org$scalatest$matchers$TypeMatcherHelper$$conform:(Lscala/reflect/ClassTag;Ljava/lang/Object;)Z
  #124 = Methodref          #2.#123       // org/scalatest/matchers/TypeMatcherHelper$.org$scalatest$matchers$TypeMatcherHelper$$conform:(Lscala/reflect/ClassTag;Ljava/lang/Object;)Z
  #125 = Utf8               org/scalatest/Suite$
  #126 = Class              #125          // org/scalatest/Suite$
  #127 = Utf8               Lorg/scalatest/Suite$;
  #128 = NameAndType        #14:#127      // MODULE$:Lorg/scalatest/Suite$;
  #129 = Fieldref           #126.#128     // org/scalatest/Suite$.MODULE$:Lorg/scalatest/Suite$;
  #130 = Utf8               toString
  #131 = Utf8               ()Ljava/lang/String;
  #132 = NameAndType        #130:#131     // toString:()Ljava/lang/String;
  #133 = InterfaceMethodref #79.#132      // scala/reflect/ClassTag.toString:()Ljava/lang/String;
  #134 = Utf8               getObjectsForFailureMessage
  #135 = Utf8               (Ljava/lang/Object;Ljava/lang/Object;)Lscala/Tuple2;
  #136 = NameAndType        #134:#135     // getObjectsForFailureMessage:(Ljava/lang/Object;Ljava/lang/Object;)Lscala/Tuple2;
  #137 = Methodref          #126.#136     // org/scalatest/Suite$.getObjectsForFailureMessage:(Ljava/lang/Object;Ljava/lang/Object;)Lscala/Tuple2;
  #138 = Utf8               scala/Tuple2
  #139 = Class              #138          // scala/Tuple2
  #140 = Utf8               _1
  #141 = Utf8               ()Ljava/lang/Object;
  #142 = NameAndType        #140:#141     // _1:()Ljava/lang/Object;
  #143 = Methodref          #139.#142     // scala/Tuple2._1:()Ljava/lang/Object;
  #144 = Utf8               _2
  #145 = NameAndType        #144:#141     // _2:()Ljava/lang/Object;
  #146 = Methodref          #139.#145     // scala/Tuple2._2:()Ljava/lang/Object;
  #147 = Utf8               (Ljava/lang/Object;Ljava/lang/Object;)V
  #148 = NameAndType        #18:#147      // "<init>":(Ljava/lang/Object;Ljava/lang/Object;)V
  #149 = Methodref          #139.#148     // scala/Tuple2."<init>":(Ljava/lang/Object;Ljava/lang/Object;)V
  #150 = Utf8               scala/MatchError
  #151 = Class              #150          // scala/MatchError
  #152 = Utf8               (Ljava/lang/Object;)V
  #153 = NameAndType        #18:#152      // "<init>":(Ljava/lang/Object;)V
  #154 = Methodref          #151.#153     // scala/MatchError."<init>":(Ljava/lang/Object;)V
  #155 = Utf8               org/scalatest/matchers/MatchersHelper$
  #156 = Class              #155          // org/scalatest/matchers/MatchersHelper$
  #157 = Utf8               Lorg/scalatest/matchers/MatchersHelper$;
  #158 = NameAndType        #14:#157      // MODULE$:Lorg/scalatest/matchers/MatchersHelper$;
  #159 = Fieldref           #156.#158     // org/scalatest/matchers/MatchersHelper$.MODULE$:Lorg/scalatest/matchers/MatchersHelper$;
  #160 = Utf8               org/scalatest/FailureMessages$
  #161 = Class              #160          // org/scalatest/FailureMessages$
  #162 = Utf8               Lorg/scalatest/FailureMessages$;
  #163 = NameAndType        #14:#162      // MODULE$:Lorg/scalatest/FailureMessages$;
  #164 = Fieldref           #161.#163     // org/scalatest/FailureMessages$.MODULE$:Lorg/scalatest/FailureMessages$;
  #165 = Utf8               org/scalatest/UnquotedString$
  #166 = Class              #165          // org/scalatest/UnquotedString$
  #167 = Utf8               Lorg/scalatest/UnquotedString$;
  #168 = NameAndType        #14:#167      // MODULE$:Lorg/scalatest/UnquotedString$;
  #169 = Fieldref           #166.#168     // org/scalatest/UnquotedString$.MODULE$:Lorg/scalatest/UnquotedString$;
  #170 = Utf8               apply
  #171 = Utf8               (Ljava/lang/String;)Lorg/scalatest/UnquotedString;
  #172 = NameAndType        #170:#171     // apply:(Ljava/lang/String;)Lorg/scalatest/UnquotedString;
  #173 = Methodref          #166.#172     // org/scalatest/UnquotedString$.apply:(Ljava/lang/String;)Lorg/scalatest/UnquotedString;
  #174 = Utf8               getClass
  #175 = NameAndType        #174:#81      // getClass:()Ljava/lang/Class;
  #176 = Methodref          #4.#175       // java/lang/Object.getClass:()Ljava/lang/Class;
  #177 = Utf8               getName
  #178 = NameAndType        #177:#131     // getName:()Ljava/lang/String;
  #179 = Methodref          #85.#178      // java/lang/Class.getName:()Ljava/lang/String;
  #180 = Utf8               wasNotAnInstanceOf
  #181 = Utf8               (Lorg/scalactic/Prettifier;Ljava/lang/Object;Ljava/lang/Object;Ljava/lang/Object;)Ljava/lang/String;
  #182 = NameAndType        #180:#181     // wasNotAnInstanceOf:(Lorg/scalactic/Prettifier;Ljava/lang/Object;Ljava/lang/Object;Ljava/lang/Object;)Ljava/lang/String;
  #183 = Methodref          #161.#182     // org/scalatest/FailureMessages$.wasNotAnInstanceOf:(Lorg/scalactic/Prettifier;Ljava/lang/Object;Ljava/lang/Object;Ljava/lang/Object;)Ljava/lang/String;
  #184 = Utf8               scala/None$
  #185 = Class              #184          // scala/None$
  #186 = Utf8               Lscala/None$;
  #187 = NameAndType        #14:#186      // MODULE$:Lscala/None$;
  #188 = Fieldref           #185.#187     // scala/None$.MODULE$:Lscala/None$;
  #189 = Utf8               newTestFailedException
  #190 = Utf8               (Ljava/lang/String;Lscala/Option;Lorg/scalactic/source/Position;)Ljava/lang/Throwable;
  #191 = NameAndType        #189:#190     // newTestFailedException:(Ljava/lang/String;Lscala/Option;Lorg/scalactic/source/Position;)Ljava/lang/Throwable;
  #192 = Methodref          #156.#191     // org/scalatest/matchers/MatchersHelper$.newTestFailedException:(Ljava/lang/String;Lscala/Option;Lorg/scalactic/source/Position;)Ljava/lang/Throwable;
  #193 = Utf8               org/scalatest/Succeeded$
  #194 = Class              #193          // org/scalatest/Succeeded$
  #195 = Utf8               Lorg/scalatest/Succeeded$;
  #196 = NameAndType        #14:#195      // MODULE$:Lorg/scalatest/Succeeded$;
  #197 = Fieldref           #194.#196     // org/scalatest/Succeeded$.MODULE$:Lorg/scalatest/Succeeded$;
  #198 = Utf8               leftee
  #199 = Utf8               rightee
  #200 = Utf8               Lorg/scalactic/Prettifier;
  #201 = Utf8               Lorg/scalactic/source/Position;
  #202 = Utf8               org/scalactic/Prettifier
  #203 = Class              #202          // org/scalactic/Prettifier
  #204 = Utf8               org/scalactic/source/Position
  #205 = Class              #204          // org/scalactic/source/Position
  #206 = Utf8               assertAnType
  #207 = Utf8               (Ljava/lang/Object;Lorg/scalatest/matchers/dsl/ResultOfAnTypeInvocation;Lorg/scalactic/Prettifier;Lorg/scalactic/source/Position;)Lorg/scalatest/compatible/Assertion;
  #208 = Utf8               (Ljava/lang/Object;Lorg/scalatest/matchers/dsl/ResultOfAnTypeInvocation<*>;Lorg/scalactic/Prettifier;Lorg/scalactic/source/Position;)Lorg/scalatest/compatible/Assertion;
  #209 = Utf8               org/scalatest/matchers/dsl/ResultOfAnTypeInvocation
  #210 = Class              #209          // org/scalatest/matchers/dsl/ResultOfAnTypeInvocation
  #211 = Methodref          #210.#118     // org/scalatest/matchers/dsl/ResultOfAnTypeInvocation.clazz:()Ljava/lang/Class;
  #212 = Methodref          #210.#121     // org/scalatest/matchers/dsl/ResultOfAnTypeInvocation.clazzTag:()Lscala/reflect/ClassTag;
  #213 = Utf8               assertATypeShouldBeTrue
  #214 = Utf8               (Ljava/lang/Object;Lorg/scalatest/matchers/dsl/ResultOfATypeInvocation;ZLorg/scalactic/Prettifier;Lorg/scalactic/source/Position;)Lorg/scalatest/compatible/Assertion;
  #215 = Utf8               (Ljava/lang/Object;Lorg/scalatest/matchers/dsl/ResultOfATypeInvocation<*>;ZLorg/scalactic/Prettifier;Lorg/scalactic/source/Position;)Lorg/scalatest/compatible/Assertion;
  #216 = Utf8               shouldBeTrue
  #217 = Utf8               wasAnInstanceOf
  #218 = Utf8               (Lorg/scalactic/Prettifier;Ljava/lang/Object;Ljava/lang/Object;)Ljava/lang/String;
  #219 = NameAndType        #217:#218     // wasAnInstanceOf:(Lorg/scalactic/Prettifier;Ljava/lang/Object;Ljava/lang/Object;)Ljava/lang/String;
  #220 = Methodref          #161.#219     // org/scalatest/FailureMessages$.wasAnInstanceOf:(Lorg/scalactic/Prettifier;Ljava/lang/Object;Ljava/lang/Object;)Ljava/lang/String;
  #221 = Utf8               Z
  #222 = Utf8               java/lang/String
  #223 = Class              #222          // java/lang/String
  #224 = Utf8               assertAnTypeShouldBeTrue
  #225 = Utf8               (Ljava/lang/Object;Lorg/scalatest/matchers/dsl/ResultOfAnTypeInvocation;ZLorg/scalactic/Prettifier;Lorg/scalactic/source/Position;)Lorg/scalatest/compatible/Assertion;
  #226 = Utf8               (Ljava/lang/Object;Lorg/scalatest/matchers/dsl/ResultOfAnTypeInvocation<*>;ZLorg/scalactic/Prettifier;Lorg/scalactic/source/Position;)Lorg/scalatest/compatible/Assertion;
  #227 = Methodref          #4.#19        // java/lang/Object."<init>":()V
  #228 = Utf8               Code
  #229 = Utf8               LineNumberTable
  #230 = Utf8               LocalVariableTable
  #231 = Utf8               Signature
  #232 = Utf8               MethodParameters
  #233 = Utf8               StackMapTable
  #234 = Utf8               InnerClasses
  #235 = Utf8               SourceFile
  #236 = Utf8               ScalaInlineInfo
  #237 = Utf8               Scala
{
  public static final org.scalatest.matchers.TypeMatcherHelper$ MODULE$;
    descriptor: Lorg/scalatest/matchers/TypeMatcherHelper$;
    flags: (0x0019) ACC_PUBLIC, ACC_STATIC, ACC_FINAL

  public static {};
    descriptor: ()V
    flags: (0x0009) ACC_PUBLIC, ACC_STATIC
    Code:
      stack=2, locals=0, args_size=0
         0: new           #2                  // class org/scalatest/matchers/TypeMatcherHelper$
         3: dup
         4: invokespecial #20                 // Method "<init>":()V
         7: putstatic     #22                 // Field MODULE$:Lorg/scalatest/matchers/TypeMatcherHelper$;
        10: return
      LineNumberTable:
        line 35: 0

  public org.scalatest.matchers.Matcher<java.lang.Object> aTypeMatcher(org.scalatest.matchers.dsl.ResultOfATypeInvocation<?>);
    descriptor: (Lorg/scalatest/matchers/dsl/ResultOfATypeInvocation;)Lorg/scalatest/matchers/Matcher;
    flags: (0x0001) ACC_PUBLIC
    Code:
      stack=3, locals=2, args_size=2
         0: new           #7                  // class org/scalatest/matchers/TypeMatcherHelper$$anon$1
         3: dup
         4: aload_1
         5: invokespecial #29                 // Method org/scalatest/matchers/TypeMatcherHelper$$anon$1."<init>":(Lorg/scalatest/matchers/dsl/ResultOfATypeInvocation;)V
         8: areturn
      LineNumberTable:
        line 44: 0
      LocalVariableTable:
        Start  Length  Slot  Name   Signature
            0       9     0  this   Lorg/scalatest/matchers/TypeMatcherHelper$;
            0       9     1 aType   Lorg/scalatest/matchers/dsl/ResultOfATypeInvocation;
    Signature: #25                          // (Lorg/scalatest/matchers/dsl/ResultOfATypeInvocation<*>;)Lorg/scalatest/matchers/Matcher<Ljava/lang/Object;>;
    MethodParameters:
      Name                           Flags
      aType                          final

  public org.scalatest.matchers.Matcher<java.lang.Object> anTypeMatcher(org.scalatest.matchers.dsl.ResultOfAnTypeInvocation<?>);
    descriptor: (Lorg/scalatest/matchers/dsl/ResultOfAnTypeInvocation;)Lorg/scalatest/matchers/Matcher;
    flags: (0x0001) ACC_PUBLIC
    Code:
      stack=3, locals=2, args_size=2
         0: new           #9                  // class org/scalatest/matchers/TypeMatcherHelper$$anon$2
         3: dup
         4: aload_1
         5: invokespecial #38                 // Method org/scalatest/matchers/TypeMatcherHelper$$anon$2."<init>":(Lorg/scalatest/matchers/dsl/ResultOfAnTypeInvocation;)V
         8: areturn
      LineNumberTable:
        line 65: 0
      LocalVariableTable:
        Start  Length  Slot  Name   Signature
            0       9     0  this   Lorg/scalatest/matchers/TypeMatcherHelper$;
            0       9     1 anType   Lorg/scalatest/matchers/dsl/ResultOfAnTypeInvocation;
    Signature: #34                          // (Lorg/scalatest/matchers/dsl/ResultOfAnTypeInvocation<*>;)Lorg/scalatest/matchers/Matcher<Ljava/lang/Object;>;
    MethodParameters:
      Name                           Flags
      anType                         final

  public org.scalatest.matchers.Matcher<java.lang.Object> notATypeMatcher(org.scalatest.matchers.dsl.ResultOfATypeInvocation<?>);
    descriptor: (Lorg/scalatest/matchers/dsl/ResultOfATypeInvocation;)Lorg/scalatest/matchers/Matcher;
    flags: (0x0001) ACC_PUBLIC
    Code:
      stack=3, locals=2, args_size=2
         0: new           #11                 // class org/scalatest/matchers/TypeMatcherHelper$$anon$3
         3: dup
         4: aload_1
         5: invokespecial #41                 // Method org/scalatest/matchers/TypeMatcherHelper$$anon$3."<init>":(Lorg/scalatest/matchers/dsl/ResultOfATypeInvocation;)V
         8: areturn
      LineNumberTable:
        line 86: 0
      LocalVariableTable:
        Start  Length  Slot  Name   Signature
            0       9     0  this   Lorg/scalatest/matchers/TypeMatcherHelper$;
            0       9     1 aType   Lorg/scalatest/matchers/dsl/ResultOfATypeInvocation;
    Signature: #25                          // (Lorg/scalatest/matchers/dsl/ResultOfATypeInvocation<*>;)Lorg/scalatest/matchers/Matcher<Ljava/lang/Object;>;
    MethodParameters:
      Name                           Flags
      aType                          final

  public org.scalatest.matchers.Matcher<java.lang.Object> notAnTypeMatcher(org.scalatest.matchers.dsl.ResultOfAnTypeInvocation<?>);
    descriptor: (Lorg/scalatest/matchers/dsl/ResultOfAnTypeInvocation;)Lorg/scalatest/matchers/Matcher;
    flags: (0x0001) ACC_PUBLIC
    Code:
      stack=3, locals=2, args_size=2
         0: new           #13                 // class org/scalatest/matchers/TypeMatcherHelper$$anon$4
         3: dup
         4: aload_1
         5: invokespecial #43                 // Method org/scalatest/matchers/TypeMatcherHelper$$anon$4."<init>":(Lorg/scalatest/matchers/dsl/ResultOfAnTypeInvocation;)V
         8: areturn
      LineNumberTable:
        line 107: 0
      LocalVariableTable:
        Start  Length  Slot  Name   Signature
            0       9     0  this   Lorg/scalatest/matchers/TypeMatcherHelper$;
            0       9     1 anType   Lorg/scalatest/matchers/dsl/ResultOfAnTypeInvocation;
    Signature: #34                          // (Lorg/scalatest/matchers/dsl/ResultOfAnTypeInvocation<*>;)Lorg/scalatest/matchers/Matcher<Ljava/lang/Object;>;
    MethodParameters:
      Name                           Flags
      anType                         final

  public <T extends java.lang.Object> boolean org$scalatest$matchers$TypeMatcherHelper$$conform(scala.reflect.ClassTag<T>, java.lang.Object);
    descriptor: (Lscala/reflect/ClassTag;Ljava/lang/Object;)Z
    flags: (0x0001) ACC_PUBLIC
    Code:
      stack=2, locals=5, args_size=3
         0: aload_1
         1: getstatic     #53                 // Field scala/reflect/ClassTag$.MODULE$:Lscala/reflect/ClassTag$;
         4: invokevirtual #57                 // Method scala/reflect/ClassTag$.AnyVal:()Lscala/reflect/ClassTag;
         7: astore_3
         8: dup
         9: ifnonnull     20
        12: pop
        13: aload_3
        14: ifnull        27
        17: goto          91
        20: aload_3
        21: invokevirtual #61                 // Method java/lang/Object.equals:(Ljava/lang/Object;)Z
        24: ifeq          91
        27: aload_2
        28: instanceof    #63                 // class java/lang/Byte
        31: ifne          83
        34: aload_2
        35: instanceof    #65                 // class java/lang/Short
        38: ifne          83
        41: aload_2
        42: instanceof    #67                 // class java/lang/Character
        45: ifne          83
        48: aload_2
        49: instanceof    #69                 // class java/lang/Integer
        52: ifne          83
        55: aload_2
        56: instanceof    #71                 // class java/lang/Long
        59: ifne          83
        62: aload_2
        63: instanceof    #73                 // class java/lang/Float
        66: ifne          83
        69: aload_2
        70: instanceof    #75                 // class java/lang/Double
        73: ifne          83
        76: aload_2
        77: instanceof    #77                 // class java/lang/Boolean
        80: ifeq          87
        83: iconst_1
        84: goto          88
        87: iconst_0
        88: goto          279
        91: aload_1
        92: invokeinterface #83,  1           // InterfaceMethod scala/reflect/ClassTag.runtimeClass:()Ljava/lang/Class;
        97: astore        4
        99: aload_2
       100: ifnull        278
       103: aload         4
       105: aload_2
       106: invokevirtual #88                 // Method java/lang/Class.isInstance:(Ljava/lang/Object;)Z
       109: ifne          274
       112: aload_2
       113: instanceof    #63                 // class java/lang/Byte
       116: ifeq          130
       119: aload         4
       121: getstatic     #92                 // Field java/lang/Byte.TYPE:Ljava/lang/Class;
       124: invokevirtual #96                 // Method java/lang/Class.isAssignableFrom:(Ljava/lang/Class;)Z
       127: ifne          274
       130: aload_2
       131: instanceof    #65                 // class java/lang/Short
       134: ifeq          148
       137: aload         4
       139: getstatic     #97                 // Field java/lang/Short.TYPE:Ljava/lang/Class;
       142: invokevirtual #96                 // Method java/lang/Class.isAssignableFrom:(Ljava/lang/Class;)Z
       145: ifne          274
       148: aload_2
       149: instanceof    #67                 // class java/lang/Character
       152: ifeq          166
       155: aload         4
       157: getstatic     #98                 // Field java/lang/Character.TYPE:Ljava/lang/Class;
       160: invokevirtual #96                 // Method java/lang/Class.isAssignableFrom:(Ljava/lang/Class;)Z
       163: ifne          274
       166: aload_2
       167: instanceof    #69                 // class java/lang/Integer
       170: ifeq          184
       173: aload         4
       175: getstatic     #99                 // Field java/lang/Integer.TYPE:Ljava/lang/Class;
       178: invokevirtual #96                 // Method java/lang/Class.isAssignableFrom:(Ljava/lang/Class;)Z
       181: ifne          274
       184: aload_2
       185: instanceof    #71                 // class java/lang/Long
       188: ifeq          202
       191: aload         4
       193: getstatic     #100                // Field java/lang/Long.TYPE:Ljava/lang/Class;
       196: invokevirtual #96                 // Method java/lang/Class.isAssignableFrom:(Ljava/lang/Class;)Z
       199: ifne          274
       202: aload_2
       203: instanceof    #73                 // class java/lang/Float
       206: ifeq          220
       209: aload         4
       211: getstatic     #101                // Field java/lang/Float.TYPE:Ljava/lang/Class;
       214: invokevirtual #96                 // Method java/lang/Class.isAssignableFrom:(Ljava/lang/Class;)Z
       217: ifne          274
       220: aload_2
       221: instanceof    #75                 // class java/lang/Double
       224: ifeq          238
       227: aload         4
       229: getstatic     #102                // Field java/lang/Double.TYPE:Ljava/lang/Class;
       232: invokevirtual #96                 // Method java/lang/Class.isAssignableFrom:(Ljava/lang/Class;)Z
       235: ifne          274
       238: aload_2
       239: instanceof    #77                 // class java/lang/Boolean
       242: ifeq          256
       245: aload         4
       247: getstatic     #103                // Field java/lang/Boolean.TYPE:Ljava/lang/Class;
       250: invokevirtual #96                 // Method java/lang/Class.isAssignableFrom:(Ljava/lang/Class;)Z
       253: ifne          274
       256: aload_2
       257: instanceof    #105                // class scala/runtime/BoxedUnit
       260: ifeq          278
       263: aload         4
       265: getstatic     #106                // Field scala/runtime/BoxedUnit.TYPE:Ljava/lang/Class;
       268: invokevirtual #96                 // Method java/lang/Class.isAssignableFrom:(Ljava/lang/Class;)Z
       271: ifeq          278
       274: iconst_1
       275: goto          279
       278: iconst_0
       279: ireturn
      StackMapTable: number_of_entries = 17
        frame_type = 255 /* full_frame */
          offset_delta = 20
          locals = [ class org/scalatest/matchers/TypeMatcherHelper$, class scala/reflect/ClassTag, class java/lang/Object, class scala/reflect/ClassTag ]
          stack = [ class scala/reflect/ClassTag ]
        frame_type = 6 /* same */
        frame_type = 55 /* same */
        frame_type = 3 /* same */
        frame_type = 64 /* same_locals_1_stack_item */
          stack = [ int ]
        frame_type = 2 /* same */
        frame_type = 252 /* append */
          offset_delta = 38
          locals = [ class java/lang/Class ]
        frame_type = 17 /* same */
        frame_type = 17 /* same */
        frame_type = 17 /* same */
        frame_type = 17 /* same */
        frame_type = 17 /* same */
        frame_type = 17 /* same */
        frame_type = 17 /* same */
        frame_type = 17 /* same */
        frame_type = 3 /* same */
        frame_type = 255 /* full_frame */
          offset_delta = 0
          locals = [ class org/scalatest/matchers/TypeMatcherHelper$, class scala/reflect/ClassTag, class java/lang/Object, class scala/reflect/ClassTag ]
          stack = [ int ]
      LineNumberTable:
        line 122: 0
        line 123: 27
        line 124: 34
        line 125: 41
        line 126: 48
        line 127: 55
        line 128: 62
        line 129: 69
        line 130: 76
        line 132: 91
        line 136: 99
        line 137: 103
        line 138: 112
        line 139: 130
        line 140: 148
        line 141: 166
        line 142: 184
        line 143: 202
        line 144: 220
        line 145: 238
        line 146: 256
        line 147: 274
        line 148: 278
      LocalVariableTable:
        Start  Length  Slot  Name   Signature
           99     180     4 runtimeClass   Ljava/lang/Class;
            0     280     0  this   Lorg/scalatest/matchers/TypeMatcherHelper$;
            0     280     1 classTag   Lscala/reflect/ClassTag;
            0     280     2     x   Ljava/lang/Object;
    Signature: #46                          // <T:Ljava/lang/Object;>(Lscala/reflect/ClassTag<TT;>;Ljava/lang/Object;)Z
    MethodParameters:
      Name                           Flags
      classTag                       final
      x                              final

  public org.scalatest.compatible.Assertion assertAType(java.lang.Object, org.scalatest.matchers.dsl.ResultOfATypeInvocation<?>, org.scalactic.Prettifier, org.scalactic.source.Position);
    descriptor: (Ljava/lang/Object;Lorg/scalatest/matchers/dsl/ResultOfATypeInvocation;Lorg/scalactic/Prettifier;Lorg/scalactic/source/Position;)Lorg/scalatest/compatible/Assertion;
    flags: (0x0001) ACC_PUBLIC
    Code:
      stack=7, locals=13, args_size=5
         0: aload_2
         1: invokevirtual #119                // Method org/scalatest/matchers/dsl/ResultOfATypeInvocation.clazz:()Ljava/lang/Class;
         4: astore        6
         6: aload_0
         7: aload_2
         8: invokevirtual #122                // Method org/scalatest/matchers/dsl/ResultOfATypeInvocation.clazzTag:()Lscala/reflect/ClassTag;
        11: aload_1
        12: invokevirtual #124                // Method org$scalatest$matchers$TypeMatcherHelper$$conform:(Lscala/reflect/ClassTag;Ljava/lang/Object;)Z
        15: ifne          150
        18: getstatic     #129                // Field org/scalatest/Suite$.MODULE$:Lorg/scalatest/Suite$;
        21: aload_1
        22: aload_2
        23: invokevirtual #122                // Method org/scalatest/matchers/dsl/ResultOfATypeInvocation.clazzTag:()Lscala/reflect/ClassTag;
        26: invokeinterface #133,  1          // InterfaceMethod scala/reflect/ClassTag.toString:()Ljava/lang/String;
        31: invokevirtual #137                // Method org/scalatest/Suite$.getObjectsForFailureMessage:(Ljava/lang/Object;Ljava/lang/Object;)Lscala/Tuple2;
        34: astore        8
        36: aload         8
        38: ifnull        71
        41: aload         8
        43: invokevirtual #143                // Method scala/Tuple2._1:()Ljava/lang/Object;
        46: astore        9
        48: aload         8
        50: invokevirtual #146                // Method scala/Tuple2._2:()Ljava/lang/Object;
        53: astore        10
        55: new           #139                // class scala/Tuple2
        58: dup
        59: aload         9
        61: aload         10
        63: invokespecial #149                // Method scala/Tuple2."<init>":(Ljava/lang/Object;Ljava/lang/Object;)V
        66: astore        5
        68: goto          84
        71: goto          74
        74: new           #151                // class scala/MatchError
        77: dup
        78: aload         8
        80: invokespecial #154                // Method scala/MatchError."<init>":(Ljava/lang/Object;)V
        83: athrow
        84: aload         5
        86: astore        7
        88: aload         7
        90: invokevirtual #143                // Method scala/Tuple2._1:()Ljava/lang/Object;
        93: astore        11
        95: aload         7
        97: invokevirtual #146                // Method scala/Tuple2._2:()Ljava/lang/Object;
       100: astore        12
       102: getstatic     #159                // Field org/scalatest/matchers/MatchersHelper$.MODULE$:Lorg/scalatest/matchers/MatchersHelper$;
       105: getstatic     #164                // Field org/scalatest/FailureMessages$.MODULE$:Lorg/scalatest/FailureMessages$;
       108: aload_3
       109: aload_1
       110: getstatic     #169                // Field org/scalatest/UnquotedString$.MODULE$:Lorg/scalatest/UnquotedString$;
       113: aload_2
       114: invokevirtual #122                // Method org/scalatest/matchers/dsl/ResultOfATypeInvocation.clazzTag:()Lscala/reflect/ClassTag;
       117: invokeinterface #133,  1          // InterfaceMethod scala/reflect/ClassTag.toString:()Ljava/lang/String;
       122: invokevirtual #173                // Method org/scalatest/UnquotedString$.apply:(Ljava/lang/String;)Lorg/scalatest/UnquotedString;
       125: getstatic     #169                // Field org/scalatest/UnquotedString$.MODULE$:Lorg/scalatest/UnquotedString$;
       128: aload_1
       129: invokevirtual #176                // Method java/lang/Object.getClass:()Ljava/lang/Class;
       132: invokevirtual #179                // Method java/lang/Class.getName:()Ljava/lang/String;
       135: invokevirtual #173                // Method org/scalatest/UnquotedString$.apply:(Ljava/lang/String;)Lorg/scalatest/UnquotedString;
       138: invokevirtual #183                // Method org/scalatest/FailureMessages$.wasNotAnInstanceOf:(Lorg/scalactic/Prettifier;Ljava/lang/Object;Ljava/lang/Object;Ljava/lang/Object;)Ljava/lang/String;
       141: getstatic     #188                // Field scala/None$.MODULE$:Lscala/None$;
       144: aload         4
       146: invokevirtual #192                // Method org/scalatest/matchers/MatchersHelper$.newTestFailedException:(Ljava/lang/String;Lscala/Option;Lorg/scalactic/source/Position;)Ljava/lang/Throwable;
       149: athrow
       150: getstatic     #197                // Field org/scalatest/Succeeded$.MODULE$:Lorg/scalatest/Succeeded$;
       153: areturn
      StackMapTable: number_of_entries = 4
        frame_type = 255 /* full_frame */
          offset_delta = 71
          locals = [ class org/scalatest/matchers/TypeMatcherHelper$, class java/lang/Object, class org/scalatest/matchers/dsl/ResultOfATypeInvocation, class org/scalactic/Prettifier, class org/scalactic/source/Position, top, class java/lang/Class, top, class scala/Tuple2 ]
          stack = []
        frame_type = 2 /* same */
        frame_type = 255 /* full_frame */
          offset_delta = 9
          locals = [ class org/scalatest/matchers/TypeMatcherHelper$, class java/lang/Object, class org/scalatest/matchers/dsl/ResultOfATypeInvocation, class org/scalactic/Prettifier, class org/scalactic/source/Position, class scala/Tuple2, class java/lang/Class, top, class scala/Tuple2, class java/lang/Object, class java/lang/Object ]
          stack = []
        frame_type = 255 /* full_frame */
          offset_delta = 65
          locals = [ class org/scalatest/matchers/TypeMatcherHelper$, class java/lang/Object, class org/scalatest/matchers/dsl/ResultOfATypeInvocation, class org/scalactic/Prettifier, class org/scalactic/source/Position, top, class java/lang/Class ]
          stack = []
      LineNumberTable:
        line 159: 0
        line 160: 6
        line 161: 18
        line 162: 102
        line 164: 150
      LocalVariableTable:
        Start  Length  Slot  Name   Signature
           48      23     9 leftee   Ljava/lang/Object;
           55      16    10 rightee   Ljava/lang/Object;
           95      55    11 leftee   Ljava/lang/Object;
          102      48    12 rightee   Ljava/lang/Object;
            6     147     6 clazz   Ljava/lang/Class;
            0     154     0  this   Lorg/scalatest/matchers/TypeMatcherHelper$;
            0     154     1  left   Ljava/lang/Object;
            0     154     2 aType   Lorg/scalatest/matchers/dsl/ResultOfATypeInvocation;
            0     154     3 prettifier   Lorg/scalactic/Prettifier;
            0     154     4   pos   Lorg/scalactic/source/Position;
    Signature: #111                         // (Ljava/lang/Object;Lorg/scalatest/matchers/dsl/ResultOfATypeInvocation<*>;Lorg/scalactic/Prettifier;Lorg/scalactic/source/Position;)Lorg/scalatest/compatible/Assertion;
    MethodParameters:
      Name                           Flags
      left                           final
      aType                          final
      prettifier                     final
      pos                            final

  public org.scalatest.compatible.Assertion assertAnType(java.lang.Object, org.scalatest.matchers.dsl.ResultOfAnTypeInvocation<?>, org.scalactic.Prettifier, org.scalactic.source.Position);
    descriptor: (Ljava/lang/Object;Lorg/scalatest/matchers/dsl/ResultOfAnTypeInvocation;Lorg/scalactic/Prettifier;Lorg/scalactic/source/Position;)Lorg/scalatest/compatible/Assertion;
    flags: (0x0001) ACC_PUBLIC
    Code:
      stack=7, locals=13, args_size=5
         0: aload_2
         1: invokevirtual #211                // Method org/scalatest/matchers/dsl/ResultOfAnTypeInvocation.clazz:()Ljava/lang/Class;
         4: astore        6
         6: aload_0
         7: aload_2
         8: invokevirtual #212                // Method org/scalatest/matchers/dsl/ResultOfAnTypeInvocation.clazzTag:()Lscala/reflect/ClassTag;
        11: aload_1
        12: invokevirtual #124                // Method org$scalatest$matchers$TypeMatcherHelper$$conform:(Lscala/reflect/ClassTag;Ljava/lang/Object;)Z
        15: ifne          150
        18: getstatic     #129                // Field org/scalatest/Suite$.MODULE$:Lorg/scalatest/Suite$;
        21: aload_1
        22: aload_2
        23: invokevirtual #212                // Method org/scalatest/matchers/dsl/ResultOfAnTypeInvocation.clazzTag:()Lscala/reflect/ClassTag;
        26: invokeinterface #133,  1          // InterfaceMethod scala/reflect/ClassTag.toString:()Ljava/lang/String;
        31: invokevirtual #137                // Method org/scalatest/Suite$.getObjectsForFailureMessage:(Ljava/lang/Object;Ljava/lang/Object;)Lscala/Tuple2;
        34: astore        8
        36: aload         8
        38: ifnull        71
        41: aload         8
        43: invokevirtual #143                // Method scala/Tuple2._1:()Ljava/lang/Object;
        46: astore        9
        48: aload         8
        50: invokevirtual #146                // Method scala/Tuple2._2:()Ljava/lang/Object;
        53: astore        10
        55: new           #139                // class scala/Tuple2
        58: dup
        59: aload         9
        61: aload         10
        63: invokespecial #149                // Method scala/Tuple2."<init>":(Ljava/lang/Object;Ljava/lang/Object;)V
        66: astore        5
        68: goto          84
        71: goto          74
        74: new           #151                // class scala/MatchError
        77: dup
        78: aload         8
        80: invokespecial #154                // Method scala/MatchError."<init>":(Ljava/lang/Object;)V
        83: athrow
        84: aload         5
        86: astore        7
        88: aload         7
        90: invokevirtual #143                // Method scala/Tuple2._1:()Ljava/lang/Object;
        93: astore        11
        95: aload         7
        97: invokevirtual #146                // Method scala/Tuple2._2:()Ljava/lang/Object;
       100: astore        12
       102: getstatic     #159                // Field org/scalatest/matchers/MatchersHelper$.MODULE$:Lorg/scalatest/matchers/MatchersHelper$;
       105: getstatic     #164                // Field org/scalatest/FailureMessages$.MODULE$:Lorg/scalatest/FailureMessages$;
       108: aload_3
       109: aload_1
       110: getstatic     #169                // Field org/scalatest/UnquotedString$.MODULE$:Lorg/scalatest/UnquotedString$;
       113: aload_2
       114: invokevirtual #212                // Method org/scalatest/matchers/dsl/ResultOfAnTypeInvocation.clazzTag:()Lscala/reflect/ClassTag;
       117: invokeinterface #133,  1          // InterfaceMethod scala/reflect/ClassTag.toString:()Ljava/lang/String;
       122: invokevirtual #173                // Method org/scalatest/UnquotedString$.apply:(Ljava/lang/String;)Lorg/scalatest/UnquotedString;
       125: getstatic     #169                // Field org/scalatest/UnquotedString$.MODULE$:Lorg/scalatest/UnquotedString$;
       128: aload_1
       129: invokevirtual #176                // Method java/lang/Object.getClass:()Ljava/lang/Class;
       132: invokevirtual #179                // Method java/lang/Class.getName:()Ljava/lang/String;
       135: invokevirtual #173                // Method org/scalatest/UnquotedString$.apply:(Ljava/lang/String;)Lorg/scalatest/UnquotedString;
       138: invokevirtual #183                // Method org/scalatest/FailureMessages$.wasNotAnInstanceOf:(Lorg/scalactic/Prettifier;Ljava/lang/Object;Ljava/lang/Object;Ljava/lang/Object;)Ljava/lang/String;
       141: getstatic     #188                // Field scala/None$.MODULE$:Lscala/None$;
       144: aload         4
       146: invokevirtual #192                // Method org/scalatest/matchers/MatchersHelper$.newTestFailedException:(Ljava/lang/String;Lscala/Option;Lorg/scalactic/source/Position;)Ljava/lang/Throwable;
       149: athrow
       150: getstatic     #197                // Field org/scalatest/Succeeded$.MODULE$:Lorg/scalatest/Succeeded$;
       153: areturn
      StackMapTable: number_of_entries = 4
        frame_type = 255 /* full_frame */
          offset_delta = 71
          locals = [ class org/scalatest/matchers/TypeMatcherHelper$, class java/lang/Object, class org/scalatest/matchers/dsl/ResultOfAnTypeInvocation, class org/scalactic/Prettifier, class org/scalactic/source/Position, top, class java/lang/Class, top, class scala/Tuple2 ]
          stack = []
        frame_type = 2 /* same */
        frame_type = 255 /* full_frame */
          offset_delta = 9
          locals = [ class org/scalatest/matchers/TypeMatcherHelper$, class java/lang/Object, class org/scalatest/matchers/dsl/ResultOfAnTypeInvocation, class org/scalactic/Prettifier, class org/scalactic/source/Position, class scala/Tuple2, class java/lang/Class, top, class scala/Tuple2, class java/lang/Object, class java/lang/Object ]
          stack = []
        frame_type = 255 /* full_frame */
          offset_delta = 65
          locals = [ class org/scalatest/matchers/TypeMatcherHelper$, class java/lang/Object, class org/scalatest/matchers/dsl/ResultOfAnTypeInvocation, class org/scalactic/Prettifier, class org/scalactic/source/Position, top, class java/lang/Class ]
          stack = []
      LineNumberTable:
        line 191: 0
        line 192: 6
        line 193: 18
        line 194: 102
        line 196: 150
      LocalVariableTable:
        Start  Length  Slot  Name   Signature
           48      23     9 leftee   Ljava/lang/Object;
           55      16    10 rightee   Ljava/lang/Object;
           95      55    11 leftee   Ljava/lang/Object;
          102      48    12 rightee   Ljava/lang/Object;
            6     147     6 clazz   Ljava/lang/Class;
            0     154     0  this   Lorg/scalatest/matchers/TypeMatcherHelper$;
            0     154     1  left   Ljava/lang/Object;
            0     154     2 anType   Lorg/scalatest/matchers/dsl/ResultOfAnTypeInvocation;
            0     154     3 prettifier   Lorg/scalactic/Prettifier;
            0     154     4   pos   Lorg/scalactic/source/Position;
    Signature: #208                         // (Ljava/lang/Object;Lorg/scalatest/matchers/dsl/ResultOfAnTypeInvocation<*>;Lorg/scalactic/Prettifier;Lorg/scalactic/source/Position;)Lorg/scalatest/compatible/Assertion;
    MethodParameters:
      Name                           Flags
      left                           final
      anType                         final
      prettifier                     final
      pos                            final

  public org.scalatest.compatible.Assertion assertATypeShouldBeTrue(java.lang.Object, org.scalatest.matchers.dsl.ResultOfATypeInvocation<?>, boolean, org.scalactic.Prettifier, org.scalactic.source.Position);
    descriptor: (Ljava/lang/Object;Lorg/scalatest/matchers/dsl/ResultOfATypeInvocation;ZLorg/scalactic/Prettifier;Lorg/scalactic/source/Position;)Lorg/scalatest/compatible/Assertion;
    flags: (0x0001) ACC_PUBLIC
    Code:
      stack=7, locals=7, args_size=6
         0: aload_2
         1: invokevirtual #119                // Method org/scalatest/matchers/dsl/ResultOfATypeInvocation.clazz:()Ljava/lang/Class;
         4: astore        6
         6: aload_0
         7: aload_2
         8: invokevirtual #122                // Method org/scalatest/matchers/dsl/ResultOfATypeInvocation.clazzTag:()Lscala/reflect/ClassTag;
        11: aload_1
        12: invokevirtual #124                // Method org$scalatest$matchers$TypeMatcherHelper$$conform:(Lscala/reflect/ClassTag;Ljava/lang/Object;)Z
        15: iload_3
        16: if_icmpeq     99
        19: getstatic     #159                // Field org/scalatest/matchers/MatchersHelper$.MODULE$:Lorg/scalatest/matchers/MatchersHelper$;
        22: iload_3
        23: ifeq          66
        26: getstatic     #164                // Field org/scalatest/FailureMessages$.MODULE$:Lorg/scalatest/FailureMessages$;
        29: aload         4
        31: aload_1
        32: getstatic     #169                // Field org/scalatest/UnquotedString$.MODULE$:Lorg/scalatest/UnquotedString$;
        35: aload_2
        36: invokevirtual #122                // Method org/scalatest/matchers/dsl/ResultOfATypeInvocation.clazzTag:()Lscala/reflect/ClassTag;
        39: invokeinterface #133,  1          // InterfaceMethod scala/reflect/ClassTag.toString:()Ljava/lang/String;
        44: invokevirtual #173                // Method org/scalatest/UnquotedString$.apply:(Ljava/lang/String;)Lorg/scalatest/UnquotedString;
        47: getstatic     #169                // Field org/scalatest/UnquotedString$.MODULE$:Lorg/scalatest/UnquotedString$;
        50: aload_1
        51: invokevirtual #176                // Method java/lang/Object.getClass:()Ljava/lang/Class;
        54: invokevirtual #179                // Method java/lang/Class.getName:()Ljava/lang/String;
        57: invokevirtual #173                // Method org/scalatest/UnquotedString$.apply:(Ljava/lang/String;)Lorg/scalatest/UnquotedString;
        60: invokevirtual #183                // Method org/scalatest/FailureMessages$.wasNotAnInstanceOf:(Lorg/scalactic/Prettifier;Ljava/lang/Object;Ljava/lang/Object;Ljava/lang/Object;)Ljava/lang/String;
        63: goto          90
        66: getstatic     #164                // Field org/scalatest/FailureMessages$.MODULE$:Lorg/scalatest/FailureMessages$;
        69: aload         4
        71: aload_1
        72: getstatic     #169                // Field org/scalatest/UnquotedString$.MODULE$:Lorg/scalatest/UnquotedString$;
        75: aload_2
        76: invokevirtual #122                // Method org/scalatest/matchers/dsl/ResultOfATypeInvocation.clazzTag:()Lscala/reflect/ClassTag;
        79: invokeinterface #133,  1          // InterfaceMethod scala/reflect/ClassTag.toString:()Ljava/lang/String;
        84: invokevirtual #173                // Method org/scalatest/UnquotedString$.apply:(Ljava/lang/String;)Lorg/scalatest/UnquotedString;
        87: invokevirtual #220                // Method org/scalatest/FailureMessages$.wasAnInstanceOf:(Lorg/scalactic/Prettifier;Ljava/lang/Object;Ljava/lang/Object;)Ljava/lang/String;
        90: getstatic     #188                // Field scala/None$.MODULE$:Lscala/None$;
        93: aload         5
        95: invokevirtual #192                // Method org/scalatest/matchers/MatchersHelper$.newTestFailedException:(Ljava/lang/String;Lscala/Option;Lorg/scalactic/source/Position;)Ljava/lang/Throwable;
        98: athrow
        99: getstatic     #197                // Field org/scalatest/Succeeded$.MODULE$:Lorg/scalatest/Succeeded$;
       102: areturn
      StackMapTable: number_of_entries = 3
        frame_type = 255 /* full_frame */
          offset_delta = 66
          locals = [ class org/scalatest/matchers/TypeMatcherHelper$, class java/lang/Object, class org/scalatest/matchers/dsl/ResultOfATypeInvocation, int, class org/scalactic/Prettifier, class org/scalactic/source/Position, class java/lang/Class ]
          stack = [ class org/scalatest/matchers/MatchersHelper$ ]
        frame_type = 255 /* full_frame */
          offset_delta = 23
          locals = [ class org/scalatest/matchers/TypeMatcherHelper$, class java/lang/Object, class org/scalatest/matchers/dsl/ResultOfATypeInvocation, int, class org/scalactic/Prettifier, class org/scalactic/source/Position, class java/lang/Class ]
          stack = [ class org/scalatest/matchers/MatchersHelper$, class java/lang/String ]
        frame_type = 8 /* same */
      LineNumberTable:
        line 223: 0
        line 224: 6
        line 225: 19
        line 226: 22
        line 227: 26
        line 229: 66
        line 230: 90
        line 231: 93
        line 225: 98
        line 233: 99
      LocalVariableTable:
        Start  Length  Slot  Name   Signature
            6      96     6 clazz   Ljava/lang/Class;
            0     103     0  this   Lorg/scalatest/matchers/TypeMatcherHelper$;
            0     103     1  left   Ljava/lang/Object;
            0     103     2 aType   Lorg/scalatest/matchers/dsl/ResultOfATypeInvocation;
            0     103     3 shouldBeTrue   Z
            0     103     4 prettifier   Lorg/scalactic/Prettifier;
            0     103     5   pos   Lorg/scalactic/source/Position;
    Signature: #215                         // (Ljava/lang/Object;Lorg/scalatest/matchers/dsl/ResultOfATypeInvocation<*>;ZLorg/scalactic/Prettifier;Lorg/scalactic/source/Position;)Lorg/scalatest/compatible/Assertion;
    MethodParameters:
      Name                           Flags
      left                           final
      aType                          final
      shouldBeTrue                   final
      prettifier                     final
      pos                            final

  public org.scalatest.compatible.Assertion assertAnTypeShouldBeTrue(java.lang.Object, org.scalatest.matchers.dsl.ResultOfAnTypeInvocation<?>, boolean, org.scalactic.Prettifier, org.scalactic.source.Position);
    descriptor: (Ljava/lang/Object;Lorg/scalatest/matchers/dsl/ResultOfAnTypeInvocation;ZLorg/scalactic/Prettifier;Lorg/scalactic/source/Position;)Lorg/scalatest/compatible/Assertion;
    flags: (0x0001) ACC_PUBLIC
    Code:
      stack=7, locals=7, args_size=6
         0: aload_2
         1: invokevirtual #211                // Method org/scalatest/matchers/dsl/ResultOfAnTypeInvocation.clazz:()Ljava/lang/Class;
         4: astore        6
         6: aload_0
         7: aload_2
         8: invokevirtual #212                // Method org/scalatest/matchers/dsl/ResultOfAnTypeInvocation.clazzTag:()Lscala/reflect/ClassTag;
        11: aload_1
        12: invokevirtual #124                // Method org$scalatest$matchers$TypeMatcherHelper$$conform:(Lscala/reflect/ClassTag;Ljava/lang/Object;)Z
        15: iload_3
        16: if_icmpeq     99
        19: getstatic     #159                // Field org/scalatest/matchers/MatchersHelper$.MODULE$:Lorg/scalatest/matchers/MatchersHelper$;
        22: iload_3
        23: ifeq          66
        26: getstatic     #164                // Field org/scalatest/FailureMessages$.MODULE$:Lorg/scalatest/FailureMessages$;
        29: aload         4
        31: aload_1
        32: getstatic     #169                // Field org/scalatest/UnquotedString$.MODULE$:Lorg/scalatest/UnquotedString$;
        35: aload_2
        36: invokevirtual #212                // Method org/scalatest/matchers/dsl/ResultOfAnTypeInvocation.clazzTag:()Lscala/reflect/ClassTag;
        39: invokeinterface #133,  1          // InterfaceMethod scala/reflect/ClassTag.toString:()Ljava/lang/String;
        44: invokevirtual #173                // Method org/scalatest/UnquotedString$.apply:(Ljava/lang/String;)Lorg/scalatest/UnquotedString;
        47: getstatic     #169                // Field org/scalatest/UnquotedString$.MODULE$:Lorg/scalatest/UnquotedString$;
        50: aload_1
        51: invokevirtual #176                // Method java/lang/Object.getClass:()Ljava/lang/Class;
        54: invokevirtual #179                // Method java/lang/Class.getName:()Ljava/lang/String;
        57: invokevirtual #173                // Method org/scalatest/UnquotedString$.apply:(Ljava/lang/String;)Lorg/scalatest/UnquotedString;
        60: invokevirtual #183                // Method org/scalatest/FailureMessages$.wasNotAnInstanceOf:(Lorg/scalactic/Prettifier;Ljava/lang/Object;Ljava/lang/Object;Ljava/lang/Object;)Ljava/lang/String;
        63: goto          90
        66: getstatic     #164                // Field org/scalatest/FailureMessages$.MODULE$:Lorg/scalatest/FailureMessages$;
        69: aload         4
        71: aload_1
        72: getstatic     #169                // Field org/scalatest/UnquotedString$.MODULE$:Lorg/scalatest/UnquotedString$;
        75: aload_2
        76: invokevirtual #212                // Method org/scalatest/matchers/dsl/ResultOfAnTypeInvocation.clazzTag:()Lscala/reflect/ClassTag;
        79: invokeinterface #133,  1          // InterfaceMethod scala/reflect/ClassTag.toString:()Ljava/lang/String;
        84: invokevirtual #173                // Method org/scalatest/UnquotedString$.apply:(Ljava/lang/String;)Lorg/scalatest/UnquotedString;
        87: invokevirtual #220                // Method org/scalatest/FailureMessages$.wasAnInstanceOf:(Lorg/scalactic/Prettifier;Ljava/lang/Object;Ljava/lang/Object;)Ljava/lang/String;
        90: getstatic     #188                // Field scala/None$.MODULE$:Lscala/None$;
        93: aload         5
        95: invokevirtual #192                // Method org/scalatest/matchers/MatchersHelper$.newTestFailedException:(Ljava/lang/String;Lscala/Option;Lorg/scalactic/source/Position;)Ljava/lang/Throwable;
        98: athrow
        99: getstatic     #197                // Field org/scalatest/Succeeded$.MODULE$:Lorg/scalatest/Succeeded$;
       102: areturn
      StackMapTable: number_of_entries = 3
        frame_type = 255 /* full_frame */
          offset_delta = 66
          locals = [ class org/scalatest/matchers/TypeMatcherHelper$, class java/lang/Object, class org/scalatest/matchers/dsl/ResultOfAnTypeInvocation, int, class org/scalactic/Prettifier, class org/scalactic/source/Position, class java/lang/Class ]
          stack = [ class org/scalatest/matchers/MatchersHelper$ ]
        frame_type = 255 /* full_frame */
          offset_delta = 23
          locals = [ class org/scalatest/matchers/TypeMatcherHelper$, class java/lang/Object, class org/scalatest/matchers/dsl/ResultOfAnTypeInvocation, int, class org/scalactic/Prettifier, class org/scalactic/source/Position, class java/lang/Class ]
          stack = [ class org/scalatest/matchers/MatchersHelper$, class java/lang/String ]
        frame_type = 8 /* same */
      LineNumberTable:
        line 272: 0
        line 273: 6
        line 274: 19
        line 275: 22
        line 276: 26
        line 278: 66
        line 279: 90
        line 280: 93
        line 274: 98
        line 282: 99
      LocalVariableTable:
        Start  Length  Slot  Name   Signature
            6      96     6 clazz   Ljava/lang/Class;
            0     103     0  this   Lorg/scalatest/matchers/TypeMatcherHelper$;
            0     103     1  left   Ljava/lang/Object;
            0     103     2 anType   Lorg/scalatest/matchers/dsl/ResultOfAnTypeInvocation;
            0     103     3 shouldBeTrue   Z
            0     103     4 prettifier   Lorg/scalactic/Prettifier;
            0     103     5   pos   Lorg/scalactic/source/Position;
    Signature: #226                         // (Ljava/lang/Object;Lorg/scalatest/matchers/dsl/ResultOfAnTypeInvocation<*>;ZLorg/scalactic/Prettifier;Lorg/scalactic/source/Position;)Lorg/scalatest/compatible/Assertion;
    MethodParameters:
      Name                           Flags
      left                           final
      anType                         final
      shouldBeTrue                   final
      prettifier                     final
      pos                            final

  private org.scalatest.matchers.TypeMatcherHelper$();
    descriptor: ()V
    flags: (0x0002) ACC_PRIVATE
    Code:
      stack=1, locals=1, args_size=1
         0: aload_0
         1: invokespecial #227                // Method java/lang/Object."<init>":()V
         4: return
      LineNumberTable:
        line 312: 0
        line 35: 4
      LocalVariableTable:
        Start  Length  Slot  Name   Signature
            0       5     0  this   Lorg/scalatest/matchers/TypeMatcherHelper$;
}
InnerClasses:
  public final #7;                        // class org/scalatest/matchers/TypeMatcherHelper$$anon$1
  public final #9;                        // class org/scalatest/matchers/TypeMatcherHelper$$anon$2
  public final #11;                       // class org/scalatest/matchers/TypeMatcherHelper$$anon$3
  public final #13;                       // class org/scalatest/matchers/TypeMatcherHelper$$anon$4
SourceFile: "TypeMatcherHelper.scala"
  ScalaInlineInfo: length = 0x36 (unknown attribute)
   01 01 00 0A 00 12 00 11 01 00 17 00 18 01 00 20
   00 21 01 00 6D 00 6E 01 00 D5 00 D6 01 00 CE 00
   CF 01 00 E0 00 E1 01 00 28 00 18 01 00 2A 00 21
   01 00 2C 00 2D 01
  Scala: length = 0x0 (unknown attribute)

