Classfile /Users/mw/Projects/slang-braindump/.jar/jar8/assemble/slang-braindump/assemble/content/coursier/core/shaded/fastparse/Implicits$LowPriOptioner.class
  Last modified May 29, 2022; size 1376 bytes
  SHA-256 checksum 9968171b85c4608a461a18a9e3ceeb36bf1094bfaeb4424186f2846293cdf297
  Compiled from "Implicits.scala"
public interface coursier.core.shaded.fastparse.Implicits$LowPriOptioner
  minor version: 0
  major version: 52
  flags: (0x0601) ACC_PUBLIC, ACC_INTERFACE, ACC_ABSTRACT
  this_class: #2                          // coursier/core/shaded/fastparse/Implicits$LowPriOptioner
  super_class: #4                         // java/lang/Object
  interfaces: 0, fields: 0, methods: 4, attributes: 4
Constant pool:
   #1 = Utf8               coursier/core/shaded/fastparse/Implicits$LowPriOptioner
   #2 = Class              #1             // coursier/core/shaded/fastparse/Implicits$LowPriOptioner
   #3 = Utf8               java/lang/Object
   #4 = Class              #3             // java/lang/Object
   #5 = Utf8               Implicits.scala
   #6 = Utf8               coursier/core/shaded/fastparse/Implicits
   #7 = Class              #6             // coursier/core/shaded/fastparse/Implicits
   #8 = Utf8               LowPriOptioner
   #9 = Utf8               coursier/core/shaded/fastparse/Implicits$LowPriOptioner$GenericOptionerImplicit0$
  #10 = Class              #9             // coursier/core/shaded/fastparse/Implicits$LowPriOptioner$GenericOptionerImplicit0$
  #11 = Utf8
  #12 = Utf8               coursier/core/shaded/fastparse/Implicits$Optioner
  #13 = Class              #12            // coursier/core/shaded/fastparse/Implicits$Optioner
  #14 = Utf8               Optioner
  #15 = Utf8               GenericOptionerImplicit0
  #16 = Utf8               ()Lcoursier/core/shaded/fastparse/Implicits$LowPriOptioner$GenericOptionerImplicit0$;
  #17 = Utf8               GenericOptionerImplicit$
  #18 = Utf8               (Lcoursier/core/shaded/fastparse/Implicits$LowPriOptioner;)Lcoursier/core/shaded/fastparse/Implicits$Optioner;
  #19 = Utf8               $this
  #20 = Utf8               GenericOptionerImplicit
  #21 = Utf8               ()Lcoursier/core/shaded/fastparse/Implicits$Optioner;
  #22 = NameAndType        #20:#21        // GenericOptionerImplicit:()Lcoursier/core/shaded/fastparse/Implicits$Optioner;
  #23 = InterfaceMethodref #2.#22         // coursier/core/shaded/fastparse/Implicits$LowPriOptioner.GenericOptionerImplicit:()Lcoursier/core/shaded/fastparse/Implicits$Optioner;
  #24 = Utf8               Lcoursier/core/shaded/fastparse/Implicits$LowPriOptioner;
  #25 = Utf8               <T:Ljava/lang/Object;>()Lcoursier/core/shaded/fastparse/Implicits$Optioner<TT;Lscala/Option<TT;>;>;
  #26 = NameAndType        #15:#16        // GenericOptionerImplicit0:()Lcoursier/core/shaded/fastparse/Implicits$LowPriOptioner$GenericOptionerImplicit0$;
  #27 = InterfaceMethodref #2.#26         // coursier/core/shaded/fastparse/Implicits$LowPriOptioner.GenericOptionerImplicit0:()Lcoursier/core/shaded/fastparse/Implicits$LowPriOptioner$GenericOptionerImplicit0$;
  #28 = Utf8               this
  #29 = Utf8               $init$
  #30 = Utf8               (Lcoursier/core/shaded/fastparse/Implicits$LowPriOptioner;)V
  #31 = Utf8               Code
  #32 = Utf8               LineNumberTable
  #33 = Utf8               LocalVariableTable
  #34 = Utf8               MethodParameters
  #35 = Utf8               Signature
  #36 = Utf8               InnerClasses
  #37 = Utf8               SourceFile
  #38 = Utf8               ScalaInlineInfo
  #39 = Utf8               Scala
{
  public abstract coursier.core.shaded.fastparse.Implicits$LowPriOptioner$GenericOptionerImplicit0$ GenericOptionerImplicit0();
    descriptor: ()Lcoursier/core/shaded/fastparse/Implicits$LowPriOptioner$GenericOptionerImplicit0$;
    flags: (0x0401) ACC_PUBLIC, ACC_ABSTRACT

  public static coursier.core.shaded.fastparse.Implicits$Optioner GenericOptionerImplicit$(coursier.core.shaded.fastparse.Implicits$LowPriOptioner);
    descriptor: (Lcoursier/core/shaded/fastparse/Implicits$LowPriOptioner;)Lcoursier/core/shaded/fastparse/Implicits$Optioner;
    flags: (0x1009) ACC_PUBLIC, ACC_STATIC, ACC_SYNTHETIC
    Code:
      stack=1, locals=1, args_size=1
         0: aload_0
         1: invokespecial #23                 // InterfaceMethod GenericOptionerImplicit:()Lcoursier/core/shaded/fastparse/Implicits$Optioner;
         4: areturn
      LineNumberTable:
        line 70: 0
      LocalVariableTable:
        Start  Length  Slot  Name   Signature
            0       5     0 $this   Lcoursier/core/shaded/fastparse/Implicits$LowPriOptioner;
    MethodParameters:
      Name                           Flags
      $this                          final synthetic

  public default <T extends java.lang.Object> coursier.core.shaded.fastparse.Implicits$Optioner<T, scala.Option<T>> GenericOptionerImplicit();
    descriptor: ()Lcoursier/core/shaded/fastparse/Implicits$Optioner;
    flags: (0x0001) ACC_PUBLIC
    Code:
      stack=1, locals=1, args_size=1
         0: aload_0
         1: invokeinterface #27,  1           // InterfaceMethod GenericOptionerImplicit0:()Lcoursier/core/shaded/fastparse/Implicits$LowPriOptioner$GenericOptionerImplicit0$;
         6: areturn
      LineNumberTable:
        line 70: 0
      LocalVariableTable:
        Start  Length  Slot  Name   Signature
            0       7     0  this   Lcoursier/core/shaded/fastparse/Implicits$LowPriOptioner;
    Signature: #25                          // <T:Ljava/lang/Object;>()Lcoursier/core/shaded/fastparse/Implicits$Optioner<TT;Lscala/Option<TT;>;>;

  public static void $init$(coursier.core.shaded.fastparse.Implicits$LowPriOptioner);
    descriptor: (Lcoursier/core/shaded/fastparse/Implicits$LowPriOptioner;)V
    flags: (0x0009) ACC_PUBLIC, ACC_STATIC
    Code:
      stack=0, locals=1, args_size=1
         0: return
      LineNumberTable:
        line 69: 0
      LocalVariableTable:
        Start  Length  Slot  Name   Signature
            0       1     0 $this   Lcoursier/core/shaded/fastparse/Implicits$LowPriOptioner;
    MethodParameters:
      Name                           Flags
      $this                          final synthetic
}
InnerClasses:
  public static #8= #2 of #7;             // LowPriOptioner=class coursier/core/shaded/fastparse/Implicits$LowPriOptioner of class coursier/core/shaded/fastparse/Implicits
  public #11= #10 of #2;                  // =class coursier/core/shaded/fastparse/Implicits$LowPriOptioner$GenericOptionerImplicit0$ of class coursier/core/shaded/fastparse/Implicits$LowPriOptioner
  public static #14= #13 of #7;           // Optioner=class coursier/core/shaded/fastparse/Implicits$Optioner of class coursier/core/shaded/fastparse/Implicits
SourceFile: "Implicits.scala"
  ScalaInlineInfo: length = 0x18 (unknown attribute)
   01 00 00 04 00 1D 00 1E 01 00 14 00 15 00 00 11
   00 12 01 00 0F 00 10 00
  Scala: length = 0x0 (unknown attribute)

