Classfile /Users/mw/Projects/slang-braindump/.jar/jar8/assemble/slang-braindump/assemble/content/coursier/core/shaded/fastparse/Implicits$LowPriSequencer.class
  Last modified May 29, 2022; size 1441 bytes
  SHA-256 checksum bbce135e0f12255b6088eb4877b25be3d7f7271ce3ab9cd4608f17b5f029d686
  Compiled from "Implicits.scala"
public interface coursier.core.shaded.fastparse.Implicits$LowPriSequencer extends coursier.core.shaded.fastparse.Implicits$LowerPriSequencer
  minor version: 0
  major version: 52
  flags: (0x0601) ACC_PUBLIC, ACC_INTERFACE, ACC_ABSTRACT
  this_class: #2                          // coursier/core/shaded/fastparse/Implicits$LowPriSequencer
  super_class: #4                         // java/lang/Object
  interfaces: 1, fields: 0, methods: 4, attributes: 4
Constant pool:
   #1 = Utf8               coursier/core/shaded/fastparse/Implicits$LowPriSequencer
   #2 = Class              #1             // coursier/core/shaded/fastparse/Implicits$LowPriSequencer
   #3 = Utf8               java/lang/Object
   #4 = Class              #3             // java/lang/Object
   #5 = Utf8               coursier/core/shaded/fastparse/Implicits$LowerPriSequencer
   #6 = Class              #5             // coursier/core/shaded/fastparse/Implicits$LowerPriSequencer
   #7 = Utf8               Implicits.scala
   #8 = Utf8               coursier/core/shaded/fastparse/Implicits
   #9 = Class              #8             // coursier/core/shaded/fastparse/Implicits
  #10 = Utf8               LowPriSequencer
  #11 = Utf8               coursier/core/shaded/fastparse/Implicits$LowPriSequencer$UnitSequencer0$
  #12 = Class              #11            // coursier/core/shaded/fastparse/Implicits$LowPriSequencer$UnitSequencer0$
  #13 = Utf8
  #14 = Utf8               LowerPriSequencer
  #15 = Utf8               coursier/core/shaded/fastparse/Implicits$Sequencer
  #16 = Class              #15            // coursier/core/shaded/fastparse/Implicits$Sequencer
  #17 = Utf8               Sequencer
  #18 = Utf8               UnitSequencer0
  #19 = Utf8               ()Lcoursier/core/shaded/fastparse/Implicits$LowPriSequencer$UnitSequencer0$;
  #20 = Utf8               UnitSequencer$
  #21 = Utf8               (Lcoursier/core/shaded/fastparse/Implicits$LowPriSequencer;)Lcoursier/core/shaded/fastparse/Implicits$Sequencer;
  #22 = Utf8               $this
  #23 = Utf8               UnitSequencer
  #24 = Utf8               ()Lcoursier/core/shaded/fastparse/Implicits$Sequencer;
  #25 = NameAndType        #23:#24        // UnitSequencer:()Lcoursier/core/shaded/fastparse/Implicits$Sequencer;
  #26 = InterfaceMethodref #2.#25         // coursier/core/shaded/fastparse/Implicits$LowPriSequencer.UnitSequencer:()Lcoursier/core/shaded/fastparse/Implicits$Sequencer;
  #27 = Utf8               Lcoursier/core/shaded/fastparse/Implicits$LowPriSequencer;
  #28 = Utf8               <T:Ljava/lang/Object;>()Lcoursier/core/shaded/fastparse/Implicits$Sequencer<TT;Lscala/runtime/BoxedUnit;TT;>;
  #29 = NameAndType        #18:#19        // UnitSequencer0:()Lcoursier/core/shaded/fastparse/Implicits$LowPriSequencer$UnitSequencer0$;
  #30 = InterfaceMethodref #2.#29         // coursier/core/shaded/fastparse/Implicits$LowPriSequencer.UnitSequencer0:()Lcoursier/core/shaded/fastparse/Implicits$LowPriSequencer$UnitSequencer0$;
  #31 = Utf8               this
  #32 = Utf8               $init$
  #33 = Utf8               (Lcoursier/core/shaded/fastparse/Implicits$LowPriSequencer;)V
  #34 = Utf8               Code
  #35 = Utf8               LineNumberTable
  #36 = Utf8               LocalVariableTable
  #37 = Utf8               MethodParameters
  #38 = Utf8               Signature
  #39 = Utf8               InnerClasses
  #40 = Utf8               SourceFile
  #41 = Utf8               ScalaInlineInfo
  #42 = Utf8               Scala
{
  public abstract coursier.core.shaded.fastparse.Implicits$LowPriSequencer$UnitSequencer0$ UnitSequencer0();
    descriptor: ()Lcoursier/core/shaded/fastparse/Implicits$LowPriSequencer$UnitSequencer0$;
    flags: (0x0401) ACC_PUBLIC, ACC_ABSTRACT

  public static coursier.core.shaded.fastparse.Implicits$Sequencer UnitSequencer$(coursier.core.shaded.fastparse.Implicits$LowPriSequencer);
    descriptor: (Lcoursier/core/shaded/fastparse/Implicits$LowPriSequencer;)Lcoursier/core/shaded/fastparse/Implicits$Sequencer;
    flags: (0x1009) ACC_PUBLIC, ACC_STATIC, ACC_SYNTHETIC
    Code:
      stack=1, locals=1, args_size=1
         0: aload_0
         1: invokespecial #26                 // InterfaceMethod UnitSequencer:()Lcoursier/core/shaded/fastparse/Implicits$Sequencer;
         4: areturn
      LineNumberTable:
        line 29: 0
      LocalVariableTable:
        Start  Length  Slot  Name   Signature
            0       5     0 $this   Lcoursier/core/shaded/fastparse/Implicits$LowPriSequencer;
    MethodParameters:
      Name                           Flags
      $this                          final synthetic

  public default <T extends java.lang.Object> coursier.core.shaded.fastparse.Implicits$Sequencer<T, scala.runtime.BoxedUnit, T> UnitSequencer();
    descriptor: ()Lcoursier/core/shaded/fastparse/Implicits$Sequencer;
    flags: (0x0001) ACC_PUBLIC
    Code:
      stack=1, locals=1, args_size=1
         0: aload_0
         1: invokeinterface #30,  1           // InterfaceMethod UnitSequencer0:()Lcoursier/core/shaded/fastparse/Implicits$LowPriSequencer$UnitSequencer0$;
         6: areturn
      LineNumberTable:
        line 29: 0
      LocalVariableTable:
        Start  Length  Slot  Name   Signature
            0       7     0  this   Lcoursier/core/shaded/fastparse/Implicits$LowPriSequencer;
    Signature: #28                          // <T:Ljava/lang/Object;>()Lcoursier/core/shaded/fastparse/Implicits$Sequencer<TT;Lscala/runtime/BoxedUnit;TT;>;

  public static void $init$(coursier.core.shaded.fastparse.Implicits$LowPriSequencer);
    descriptor: (Lcoursier/core/shaded/fastparse/Implicits$LowPriSequencer;)V
    flags: (0x0009) ACC_PUBLIC, ACC_STATIC
    Code:
      stack=0, locals=1, args_size=1
         0: return
      LineNumberTable:
        line 25: 0
      LocalVariableTable:
        Start  Length  Slot  Name   Signature
            0       1     0 $this   Lcoursier/core/shaded/fastparse/Implicits$LowPriSequencer;
    MethodParameters:
      Name                           Flags
      $this                          final synthetic
}
InnerClasses:
  public static #10= #2 of #9;            // LowPriSequencer=class coursier/core/shaded/fastparse/Implicits$LowPriSequencer of class coursier/core/shaded/fastparse/Implicits
  public #13= #12 of #2;                  // =class coursier/core/shaded/fastparse/Implicits$LowPriSequencer$UnitSequencer0$ of class coursier/core/shaded/fastparse/Implicits$LowPriSequencer
  public static #14= #6 of #9;            // LowerPriSequencer=class coursier/core/shaded/fastparse/Implicits$LowerPriSequencer of class coursier/core/shaded/fastparse/Implicits
  public static #17= #16 of #9;           // Sequencer=class coursier/core/shaded/fastparse/Implicits$Sequencer of class coursier/core/shaded/fastparse/Implicits
SourceFile: "Implicits.scala"
  ScalaInlineInfo: length = 0x18 (unknown attribute)
   01 00 00 04 00 20 00 21 01 00 17 00 18 00 00 14
   00 15 01 00 12 00 13 00
  Scala: length = 0x0 (unknown attribute)

