Classfile /Users/mw/Projects/slang-braindump/.jar/jar8/assemble/slang-braindump/assemble/content/coursier/core/shaded/fastparse/Implicits$LowerPriSequencer.class
  Last modified May 29, 2022; size 1710 bytes
  SHA-256 checksum cb93845eba34a6f557ec4df21f064c7b8238f09eb8049e1df8758b3d716883e5
  Compiled from "Implicits.scala"
public interface coursier.core.shaded.fastparse.Implicits$LowerPriSequencer extends coursier.core.shaded.fastparse.SequencerGen<coursier.core.shaded.fastparse.Implicits$Sequencer>
  minor version: 0
  major version: 52
  flags: (0x0601) ACC_PUBLIC, ACC_INTERFACE, ACC_ABSTRACT
  this_class: #2                          // coursier/core/shaded/fastparse/Implicits$LowerPriSequencer
  super_class: #5                         // java/lang/Object
  interfaces: 1, fields: 0, methods: 3, attributes: 5
Constant pool:
   #1 = Utf8               coursier/core/shaded/fastparse/Implicits$LowerPriSequencer
   #2 = Class              #1             // coursier/core/shaded/fastparse/Implicits$LowerPriSequencer
   #3 = Utf8               Ljava/lang/Object;Lcoursier/core/shaded/fastparse/SequencerGen<Lcoursier/core/shaded/fastparse/Implicits$Sequencer;>;
   #4 = Utf8               java/lang/Object
   #5 = Class              #4             // java/lang/Object
   #6 = Utf8               coursier/core/shaded/fastparse/SequencerGen
   #7 = Class              #6             // coursier/core/shaded/fastparse/SequencerGen
   #8 = Utf8               Implicits.scala
   #9 = Utf8               coursier/core/shaded/fastparse/Implicits
  #10 = Class              #9             // coursier/core/shaded/fastparse/Implicits
  #11 = Utf8               LowerPriSequencer
  #12 = Utf8               coursier/core/shaded/fastparse/Implicits$Sequencer
  #13 = Class              #12            // coursier/core/shaded/fastparse/Implicits$Sequencer
  #14 = Utf8               Sequencer
  #15 = Utf8               coursier/core/shaded/fastparse/Implicits$Sequencer$
  #16 = Class              #15            // coursier/core/shaded/fastparse/Implicits$Sequencer$
  #17 = Utf8
  #18 = Utf8               coursier/core/shaded/fastparse/Implicits$Sequencer$NarySequencer
  #19 = Class              #18            // coursier/core/shaded/fastparse/Implicits$Sequencer$NarySequencer
  #20 = Utf8               NarySequencer
  #21 = Utf8               Sequencer0$
  #22 = Utf8               (Lcoursier/core/shaded/fastparse/Implicits$LowerPriSequencer;Lscala/Function2;)Lcoursier/core/shaded/fastparse/Implicits$Sequencer$NarySequencer;
  #23 = Utf8               $this
  #24 = Utf8               f
  #25 = Utf8               Sequencer0
  #26 = Utf8               (Lscala/Function2;)Lcoursier/core/shaded/fastparse/Implicits$Sequencer$NarySequencer;
  #27 = NameAndType        #25:#26        // Sequencer0:(Lscala/Function2;)Lcoursier/core/shaded/fastparse/Implicits$Sequencer$NarySequencer;
  #28 = InterfaceMethodref #2.#27         // coursier/core/shaded/fastparse/Implicits$LowerPriSequencer.Sequencer0:(Lscala/Function2;)Lcoursier/core/shaded/fastparse/Implicits$Sequencer$NarySequencer;
  #29 = Utf8               Lcoursier/core/shaded/fastparse/Implicits$LowerPriSequencer;
  #30 = Utf8               Lscala/Function2;
  #31 = Utf8               <A:Ljava/lang/Object;B:Ljava/lang/Object;C:Ljava/lang/Object;>(Lscala/Function2<TA;TB;TC;>;)Lcoursier/core/shaded/fastparse/Implicits$Sequencer$NarySequencer<TA;TB;TC;>;
  #32 = Utf8               <init>
  #33 = Utf8               (Lscala/Function2;)V
  #34 = NameAndType        #32:#33        // "<init>":(Lscala/Function2;)V
  #35 = Methodref          #19.#34        // coursier/core/shaded/fastparse/Implicits$Sequencer$NarySequencer."<init>":(Lscala/Function2;)V
  #36 = Utf8               this
  #37 = Utf8               $init$
  #38 = Utf8               (Lcoursier/core/shaded/fastparse/Implicits$LowerPriSequencer;)V
  #39 = Utf8               Code
  #40 = Utf8               LineNumberTable
  #41 = Utf8               LocalVariableTable
  #42 = Utf8               MethodParameters
  #43 = Utf8               Signature
  #44 = Utf8               InnerClasses
  #45 = Utf8               SourceFile
  #46 = Utf8               ScalaInlineInfo
  #47 = Utf8               Scala
{
  public static coursier.core.shaded.fastparse.Implicits$Sequencer$NarySequencer Sequencer0$(coursier.core.shaded.fastparse.Implicits$LowerPriSequencer, scala.Function2);
    descriptor: (Lcoursier/core/shaded/fastparse/Implicits$LowerPriSequencer;Lscala/Function2;)Lcoursier/core/shaded/fastparse/Implicits$Sequencer$NarySequencer;
    flags: (0x1009) ACC_PUBLIC, ACC_STATIC, ACC_SYNTHETIC
    Code:
      stack=2, locals=2, args_size=2
         0: aload_0
         1: aload_1
         2: invokespecial #28                 // InterfaceMethod Sequencer0:(Lscala/Function2;)Lcoursier/core/shaded/fastparse/Implicits$Sequencer$NarySequencer;
         5: areturn
      LineNumberTable:
        line 32: 0
      LocalVariableTable:
        Start  Length  Slot  Name   Signature
            0       6     0 $this   Lcoursier/core/shaded/fastparse/Implicits$LowerPriSequencer;
            0       6     1     f   Lscala/Function2;
    MethodParameters:
      Name                           Flags
      $this                          final synthetic
      f                              final

  public default <A extends java.lang.Object, B extends java.lang.Object, C extends java.lang.Object> coursier.core.shaded.fastparse.Implicits$Sequencer$NarySequencer<A, B, C> Sequencer0(scala.Function2<A, B, C>);
    descriptor: (Lscala/Function2;)Lcoursier/core/shaded/fastparse/Implicits$Sequencer$NarySequencer;
    flags: (0x0001) ACC_PUBLIC
    Code:
      stack=3, locals=2, args_size=2
         0: new           #19                 // class coursier/core/shaded/fastparse/Implicits$Sequencer$NarySequencer
         3: dup
         4: aload_1
         5: invokespecial #35                 // Method coursier/core/shaded/fastparse/Implicits$Sequencer$NarySequencer."<init>":(Lscala/Function2;)V
         8: areturn
      LineNumberTable:
        line 32: 0
      LocalVariableTable:
        Start  Length  Slot  Name   Signature
            0       9     0  this   Lcoursier/core/shaded/fastparse/Implicits$LowerPriSequencer;
            0       9     1     f   Lscala/Function2;
    Signature: #31                          // <A:Ljava/lang/Object;B:Ljava/lang/Object;C:Ljava/lang/Object;>(Lscala/Function2<TA;TB;TC;>;)Lcoursier/core/shaded/fastparse/Implicits$Sequencer$NarySequencer<TA;TB;TC;>;
    MethodParameters:
      Name                           Flags
      f                              final

  public static void $init$(coursier.core.shaded.fastparse.Implicits$LowerPriSequencer);
    descriptor: (Lcoursier/core/shaded/fastparse/Implicits$LowerPriSequencer;)V
    flags: (0x0009) ACC_PUBLIC, ACC_STATIC
    Code:
      stack=0, locals=1, args_size=1
         0: return
      LineNumberTable:
        line 31: 0
      LocalVariableTable:
        Start  Length  Slot  Name   Signature
            0       1     0 $this   Lcoursier/core/shaded/fastparse/Implicits$LowerPriSequencer;
    MethodParameters:
      Name                           Flags
      $this                          final synthetic
}
InnerClasses:
  public static #11= #2 of #10;           // LowerPriSequencer=class coursier/core/shaded/fastparse/Implicits$LowerPriSequencer of class coursier/core/shaded/fastparse/Implicits
  public static #14= #13 of #10;          // Sequencer=class coursier/core/shaded/fastparse/Implicits$Sequencer of class coursier/core/shaded/fastparse/Implicits
  public static #17= #16 of #10;          // =class coursier/core/shaded/fastparse/Implicits$Sequencer$ of class coursier/core/shaded/fastparse/Implicits
  public static #20= #19 of #16;          // NarySequencer=class coursier/core/shaded/fastparse/Implicits$Sequencer$NarySequencer of class coursier/core/shaded/fastparse/Implicits$Sequencer$
Signature: #3                           // Ljava/lang/Object;Lcoursier/core/shaded/fastparse/SequencerGen<Lcoursier/core/shaded/fastparse/Implicits$Sequencer;>;
SourceFile: "Implicits.scala"
  ScalaInlineInfo: length = 0x13 (unknown attribute)
   01 00 00 03 00 25 00 26 01 00 19 00 1A 00 00 15
   00 16 01
  Scala: length = 0x0 (unknown attribute)

