Classfile /Users/mw/Projects/slang-braindump/.jar/jar8/assemble/slang-braindump/assemble/content/coursier/core/shaded/fastparse/ParserInputSourceLowPri$FromReadable$.class
  Last modified May 29, 2022; size 2690 bytes
  SHA-256 checksum 72c4ea93b270ebbf013792c75ac377b04854e59ee3910305340caee32b50b8a5
  Compiled from "ParserInput.scala"
public class coursier.core.shaded.fastparse.ParserInputSourceLowPri$FromReadable$ extends scala.runtime.AbstractFunction2<coursier.core.shaded.geny.Readable, java.lang.Object, coursier.core.shaded.fastparse.ParserInputSourceLowPri$FromReadable> implements java.io.Serializable
  minor version: 0
  major version: 52
  flags: (0x0021) ACC_PUBLIC, ACC_SUPER
  this_class: #2                          // coursier/core/shaded/fastparse/ParserInputSourceLowPri$FromReadable$
  super_class: #5                         // scala/runtime/AbstractFunction2
  interfaces: 1, fields: 1, methods: 5, attributes: 5
Constant pool:
   #1 = Utf8               coursier/core/shaded/fastparse/ParserInputSourceLowPri$FromReadable$
   #2 = Class              #1             // coursier/core/shaded/fastparse/ParserInputSourceLowPri$FromReadable$
   #3 = Utf8               Lscala/runtime/AbstractFunction2<Lcoursier/core/shaded/geny/Readable;Ljava/lang/Object;Lcoursier/core/shaded/fastparse/ParserInputSourceLowPri$FromReadable;>;Ljava/io/Serializable;
   #4 = Utf8               scala/runtime/AbstractFunction2
   #5 = Class              #4             // scala/runtime/AbstractFunction2
   #6 = Utf8               java/io/Serializable
   #7 = Class              #6             // java/io/Serializable
   #8 = Utf8               ParserInput.scala
   #9 = Utf8               coursier/core/shaded/fastparse/ParserInputSourceLowPri$FromReadable
  #10 = Class              #9             // coursier/core/shaded/fastparse/ParserInputSourceLowPri$FromReadable
  #11 = Utf8               coursier/core/shaded/fastparse/ParserInputSourceLowPri
  #12 = Class              #11            // coursier/core/shaded/fastparse/ParserInputSourceLowPri
  #13 = Utf8               FromReadable
  #14 = Utf8
  #15 = Utf8               $outer
  #16 = Utf8               Lcoursier/core/shaded/fastparse/ParserInputSourceLowPri;
  #17 = Utf8               toString
  #18 = Utf8               ()Ljava/lang/String;
  #19 = String             #13            // FromReadable
  #20 = Utf8               this
  #21 = Utf8               Lcoursier/core/shaded/fastparse/ParserInputSourceLowPri$FromReadable$;
  #22 = Utf8               apply
  #23 = Utf8               (Lcoursier/core/shaded/geny/Readable;I)Lcoursier/core/shaded/fastparse/ParserInputSourceLowPri$FromReadable;
  #24 = Utf8               s
  #25 = Utf8               bufferSize
  #26 = NameAndType        #15:#16        // $outer:Lcoursier/core/shaded/fastparse/ParserInputSourceLowPri;
  #27 = Fieldref           #2.#26         // coursier/core/shaded/fastparse/ParserInputSourceLowPri$FromReadable$.$outer:Lcoursier/core/shaded/fastparse/ParserInputSourceLowPri;
  #28 = Utf8               <init>
  #29 = Utf8               (Lcoursier/core/shaded/fastparse/ParserInputSourceLowPri;Lcoursier/core/shaded/geny/Readable;I)V
  #30 = NameAndType        #28:#29        // "<init>":(Lcoursier/core/shaded/fastparse/ParserInputSourceLowPri;Lcoursier/core/shaded/geny/Readable;I)V
  #31 = Methodref          #10.#30        // coursier/core/shaded/fastparse/ParserInputSourceLowPri$FromReadable."<init>":(Lcoursier/core/shaded/fastparse/ParserInputSourceLowPri;Lcoursier/core/shaded/geny/Readable;I)V
  #32 = Utf8               Lcoursier/core/shaded/geny/Readable;
  #33 = Utf8               I
  #34 = Utf8               unapply
  #35 = Utf8               (Lcoursier/core/shaded/fastparse/ParserInputSourceLowPri$FromReadable;)Lscala/Option;
  #36 = Utf8               (Lcoursier/core/shaded/fastparse/ParserInputSourceLowPri$FromReadable;)Lscala/Option<Lscala/Tuple2<Lcoursier/core/shaded/geny/Readable;Ljava/lang/Object;>;>;
  #37 = Utf8               x$0
  #38 = Utf8               scala/None$
  #39 = Class              #38            // scala/None$
  #40 = Utf8               MODULE$
  #41 = Utf8               Lscala/None$;
  #42 = NameAndType        #40:#41        // MODULE$:Lscala/None$;
  #43 = Fieldref           #39.#42        // scala/None$.MODULE$:Lscala/None$;
  #44 = Utf8               scala/Some
  #45 = Class              #44            // scala/Some
  #46 = Utf8               scala/Tuple2
  #47 = Class              #46            // scala/Tuple2
  #48 = Utf8               ()Lcoursier/core/shaded/geny/Readable;
  #49 = NameAndType        #24:#48        // s:()Lcoursier/core/shaded/geny/Readable;
  #50 = Methodref          #10.#49        // coursier/core/shaded/fastparse/ParserInputSourceLowPri$FromReadable.s:()Lcoursier/core/shaded/geny/Readable;
  #51 = Utf8               ()I
  #52 = NameAndType        #25:#51        // bufferSize:()I
  #53 = Methodref          #10.#52        // coursier/core/shaded/fastparse/ParserInputSourceLowPri$FromReadable.bufferSize:()I
  #54 = Utf8               scala/runtime/BoxesRunTime
  #55 = Class              #54            // scala/runtime/BoxesRunTime
  #56 = Utf8               boxToInteger
  #57 = Utf8               (I)Ljava/lang/Integer;
  #58 = NameAndType        #56:#57        // boxToInteger:(I)Ljava/lang/Integer;
  #59 = Methodref          #55.#58        // scala/runtime/BoxesRunTime.boxToInteger:(I)Ljava/lang/Integer;
  #60 = Utf8               (Ljava/lang/Object;Ljava/lang/Object;)V
  #61 = NameAndType        #28:#60        // "<init>":(Ljava/lang/Object;Ljava/lang/Object;)V
  #62 = Methodref          #47.#61        // scala/Tuple2."<init>":(Ljava/lang/Object;Ljava/lang/Object;)V
  #63 = Utf8               (Ljava/lang/Object;)V
  #64 = NameAndType        #28:#63        // "<init>":(Ljava/lang/Object;)V
  #65 = Methodref          #45.#64        // scala/Some."<init>":(Ljava/lang/Object;)V
  #66 = Utf8               scala/Option
  #67 = Class              #66            // scala/Option
  #68 = Utf8               Lcoursier/core/shaded/fastparse/ParserInputSourceLowPri$FromReadable;
  #69 = Utf8               (Ljava/lang/Object;Ljava/lang/Object;)Ljava/lang/Object;
  #70 = Utf8               v1
  #71 = Utf8               v2
  #72 = Utf8               coursier/core/shaded/geny/Readable
  #73 = Class              #72            // coursier/core/shaded/geny/Readable
  #74 = Utf8               unboxToInt
  #75 = Utf8               (Ljava/lang/Object;)I
  #76 = NameAndType        #74:#75        // unboxToInt:(Ljava/lang/Object;)I
  #77 = Methodref          #55.#76        // scala/runtime/BoxesRunTime.unboxToInt:(Ljava/lang/Object;)I
  #78 = NameAndType        #22:#23        // apply:(Lcoursier/core/shaded/geny/Readable;I)Lcoursier/core/shaded/fastparse/ParserInputSourceLowPri$FromReadable;
  #79 = Methodref          #2.#78         // coursier/core/shaded/fastparse/ParserInputSourceLowPri$FromReadable$.apply:(Lcoursier/core/shaded/geny/Readable;I)Lcoursier/core/shaded/fastparse/ParserInputSourceLowPri$FromReadable;
  #80 = Utf8               Ljava/lang/Object;
  #81 = Utf8               (Lcoursier/core/shaded/fastparse/ParserInputSourceLowPri;)V
  #82 = Utf8               ()V
  #83 = NameAndType        #28:#82        // "<init>":()V
  #84 = Methodref          #5.#83         // scala/runtime/AbstractFunction2."<init>":()V
  #85 = Utf8               Code
  #86 = Utf8               LineNumberTable
  #87 = Utf8               LocalVariableTable
  #88 = Utf8               MethodParameters
  #89 = Utf8               StackMapTable
  #90 = Utf8               Signature
  #91 = Utf8               InnerClasses
  #92 = Utf8               SourceFile
  #93 = Utf8               ScalaInlineInfo
  #94 = Utf8               Scala
{
  private final coursier.core.shaded.fastparse.ParserInputSourceLowPri $outer;
    descriptor: Lcoursier/core/shaded/fastparse/ParserInputSourceLowPri;
    flags: (0x1012) ACC_PRIVATE, ACC_FINAL, ACC_SYNTHETIC

  public final java.lang.String toString();
    descriptor: ()Ljava/lang/String;
    flags: (0x0011) ACC_PUBLIC, ACC_FINAL
    Code:
      stack=1, locals=1, args_size=1
         0: ldc           #19                 // String FromReadable
         2: areturn
      LineNumberTable:
        line 48: 0
      LocalVariableTable:
        Start  Length  Slot  Name   Signature
            0       3     0  this   Lcoursier/core/shaded/fastparse/ParserInputSourceLowPri$FromReadable$;

  public coursier.core.shaded.fastparse.ParserInputSourceLowPri$FromReadable apply(coursier.core.shaded.geny.Readable, int);
    descriptor: (Lcoursier/core/shaded/geny/Readable;I)Lcoursier/core/shaded/fastparse/ParserInputSourceLowPri$FromReadable;
    flags: (0x0001) ACC_PUBLIC
    Code:
      stack=5, locals=3, args_size=3
         0: new           #10                 // class coursier/core/shaded/fastparse/ParserInputSourceLowPri$FromReadable
         3: dup
         4: aload_0
         5: getfield      #27                 // Field $outer:Lcoursier/core/shaded/fastparse/ParserInputSourceLowPri;
         8: aload_1
         9: iload_2
        10: invokespecial #31                 // Method coursier/core/shaded/fastparse/ParserInputSourceLowPri$FromReadable."<init>":(Lcoursier/core/shaded/fastparse/ParserInputSourceLowPri;Lcoursier/core/shaded/geny/Readable;I)V
        13: areturn
      LineNumberTable:
        line 48: 0
      LocalVariableTable:
        Start  Length  Slot  Name   Signature
            0      14     0  this   Lcoursier/core/shaded/fastparse/ParserInputSourceLowPri$FromReadable$;
            0      14     1     s   Lcoursier/core/shaded/geny/Readable;
            0      14     2 bufferSize   I
    MethodParameters:
      Name                           Flags
      s                              final
      bufferSize                     final

  public scala.Option<scala.Tuple2<coursier.core.shaded.geny.Readable, java.lang.Object>> unapply(coursier.core.shaded.fastparse.ParserInputSourceLowPri$FromReadable);
    descriptor: (Lcoursier/core/shaded/fastparse/ParserInputSourceLowPri$FromReadable;)Lscala/Option;
    flags: (0x0001) ACC_PUBLIC
    Code:
      stack=6, locals=2, args_size=2
         0: aload_1
         1: ifnonnull     10
         4: getstatic     #43                 // Field scala/None$.MODULE$:Lscala/None$;
         7: goto          35
        10: new           #45                 // class scala/Some
        13: dup
        14: new           #47                 // class scala/Tuple2
        17: dup
        18: aload_1
        19: invokevirtual #50                 // Method coursier/core/shaded/fastparse/ParserInputSourceLowPri$FromReadable.s:()Lcoursier/core/shaded/geny/Readable;
        22: aload_1
        23: invokevirtual #53                 // Method coursier/core/shaded/fastparse/ParserInputSourceLowPri$FromReadable.bufferSize:()I
        26: invokestatic  #59                 // Method scala/runtime/BoxesRunTime.boxToInteger:(I)Ljava/lang/Integer;
        29: invokespecial #62                 // Method scala/Tuple2."<init>":(Ljava/lang/Object;Ljava/lang/Object;)V
        32: invokespecial #65                 // Method scala/Some."<init>":(Ljava/lang/Object;)V
        35: areturn
      StackMapTable: number_of_entries = 2
        frame_type = 10 /* same */
        frame_type = 88 /* same_locals_1_stack_item */
          stack = [ class scala/Option ]
      LineNumberTable:
        line 48: 0
      LocalVariableTable:
        Start  Length  Slot  Name   Signature
            0      36     0  this   Lcoursier/core/shaded/fastparse/ParserInputSourceLowPri$FromReadable$;
            0      36     1   x$0   Lcoursier/core/shaded/fastparse/ParserInputSourceLowPri$FromReadable;
    Signature: #36                          // (Lcoursier/core/shaded/fastparse/ParserInputSourceLowPri$FromReadable;)Lscala/Option<Lscala/Tuple2<Lcoursier/core/shaded/geny/Readable;Ljava/lang/Object;>;>;
    MethodParameters:
      Name                           Flags
      x$0                            final

  public java.lang.Object apply(java.lang.Object, java.lang.Object);
    descriptor: (Ljava/lang/Object;Ljava/lang/Object;)Ljava/lang/Object;
    flags: (0x1041) ACC_PUBLIC, ACC_BRIDGE, ACC_SYNTHETIC
    Code:
      stack=3, locals=3, args_size=3
         0: aload_0
         1: aload_1
         2: checkcast     #73                 // class coursier/core/shaded/geny/Readable
         5: aload_2
         6: invokestatic  #77                 // Method scala/runtime/BoxesRunTime.unboxToInt:(Ljava/lang/Object;)I
         9: invokevirtual #79                 // Method apply:(Lcoursier/core/shaded/geny/Readable;I)Lcoursier/core/shaded/fastparse/ParserInputSourceLowPri$FromReadable;
        12: areturn
      LineNumberTable:
        line 48: 0
      LocalVariableTable:
        Start  Length  Slot  Name   Signature
            0      13     0  this   Lcoursier/core/shaded/fastparse/ParserInputSourceLowPri$FromReadable$;
            0      13     1    v1   Ljava/lang/Object;
            0      13     2    v2   Ljava/lang/Object;
    MethodParameters:
      Name                           Flags
      v1                             final
      v2                             final

  public coursier.core.shaded.fastparse.ParserInputSourceLowPri$FromReadable$(coursier.core.shaded.fastparse.ParserInputSourceLowPri);
    descriptor: (Lcoursier/core/shaded/fastparse/ParserInputSourceLowPri;)V
    flags: (0x0001) ACC_PUBLIC
    Code:
      stack=2, locals=2, args_size=2
         0: aload_1
         1: ifnonnull     6
         4: aconst_null
         5: athrow
         6: aload_0
         7: aload_1
         8: putfield      #27                 // Field $outer:Lcoursier/core/shaded/fastparse/ParserInputSourceLowPri;
        11: aload_0
        12: invokespecial #84                 // Method scala/runtime/AbstractFunction2."<init>":()V
        15: return
      StackMapTable: number_of_entries = 1
        frame_type = 6 /* same */
      LineNumberTable:
        line 48: 0
      LocalVariableTable:
        Start  Length  Slot  Name   Signature
            0      16     0  this   Lcoursier/core/shaded/fastparse/ParserInputSourceLowPri$FromReadable$;
            0      16     1 $outer   Lcoursier/core/shaded/fastparse/ParserInputSourceLowPri;
    MethodParameters:
      Name                           Flags
      $outer                         final synthetic
}
InnerClasses:
  public #13= #10 of #12;                 // FromReadable=class coursier/core/shaded/fastparse/ParserInputSourceLowPri$FromReadable of class coursier/core/shaded/fastparse/ParserInputSourceLowPri
  public #14= #2 of #12;                  // =class coursier/core/shaded/fastparse/ParserInputSourceLowPri$FromReadable$ of class coursier/core/shaded/fastparse/ParserInputSourceLowPri
Signature: #3                           // Lscala/runtime/AbstractFunction2<Lcoursier/core/shaded/geny/Readable;Ljava/lang/Object;Lcoursier/core/shaded/fastparse/ParserInputSourceLowPri$FromReadable;>;Ljava/io/Serializable;
SourceFile: "ParserInput.scala"
  ScalaInlineInfo: length = 0x1D (unknown attribute)
   01 01 00 05 00 1C 00 51 01 00 16 00 17 01 00 16
   00 45 01 00 11 00 12 01 00 22 00 23 01
  Scala: length = 0x0 (unknown attribute)

