Classfile /Users/mw/Projects/slang-braindump/.jar/jar8/assemble/slang-braindump/assemble/content/coursier/core/shaded/fastparse/ParserInputSource$fromParserInput.class
  Last modified May 29, 2022; size 1342 bytes
  SHA-256 checksum b3cbef4ea353fa3e56872c0d000ccc93d68c8ec003c7ae7f54817d203696d3ec
  Compiled from "ParserInput.scala"
public class coursier.core.shaded.fastparse.ParserInputSource$fromParserInput<T extends java.lang.Object> extends java.lang.Object implements coursier.core.shaded.fastparse.ParserInputSource
  minor version: 0
  major version: 52
  flags: (0x0021) ACC_PUBLIC, ACC_SUPER
  this_class: #2                          // coursier/core/shaded/fastparse/ParserInputSource$fromParserInput
  super_class: #5                         // java/lang/Object
  interfaces: 1, fields: 2, methods: 2, attributes: 5
Constant pool:
   #1 = Utf8               coursier/core/shaded/fastparse/ParserInputSource$fromParserInput
   #2 = Class              #1             // coursier/core/shaded/fastparse/ParserInputSource$fromParserInput
   #3 = Utf8               <T:Ljava/lang/Object;>Ljava/lang/Object;Lcoursier/core/shaded/fastparse/ParserInputSource;
   #4 = Utf8               java/lang/Object
   #5 = Class              #4             // java/lang/Object
   #6 = Utf8               coursier/core/shaded/fastparse/ParserInputSource
   #7 = Class              #6             // coursier/core/shaded/fastparse/ParserInputSource
   #8 = Utf8               ParserInput.scala
   #9 = Utf8               fromParserInput
  #10 = Utf8               t
  #11 = Utf8               Ljava/lang/Object;
  #12 = Utf8               TT;
  #13 = Utf8               conv
  #14 = Utf8               Lscala/Function1;
  #15 = Utf8               Lscala/Function1<TT;Lcoursier/core/shaded/fastparse/ParserInput;>;
  #16 = Utf8               parseThrough
  #17 = Utf8               (Lscala/Function1;)Ljava/lang/Object;
  #18 = Utf8               <T:Ljava/lang/Object;>(Lscala/Function1<Lcoursier/core/shaded/fastparse/ParserInput;TT;>;)TT;
  #19 = Utf8               f
  #20 = NameAndType        #13:#14        // conv:Lscala/Function1;
  #21 = Fieldref           #2.#20         // coursier/core/shaded/fastparse/ParserInputSource$fromParserInput.conv:Lscala/Function1;
  #22 = NameAndType        #10:#11        // t:Ljava/lang/Object;
  #23 = Fieldref           #2.#22         // coursier/core/shaded/fastparse/ParserInputSource$fromParserInput.t:Ljava/lang/Object;
  #24 = Utf8               scala/Function1
  #25 = Class              #24            // scala/Function1
  #26 = Utf8               apply
  #27 = Utf8               (Ljava/lang/Object;)Ljava/lang/Object;
  #28 = NameAndType        #26:#27        // apply:(Ljava/lang/Object;)Ljava/lang/Object;
  #29 = InterfaceMethodref #25.#28        // scala/Function1.apply:(Ljava/lang/Object;)Ljava/lang/Object;
  #30 = Utf8               this
  #31 = Utf8               Lcoursier/core/shaded/fastparse/ParserInputSource$fromParserInput;
  #32 = Utf8               <init>
  #33 = Utf8               (Ljava/lang/Object;Lscala/Function1;)V
  #34 = Utf8               (TT;Lscala/Function1<TT;Lcoursier/core/shaded/fastparse/ParserInput;>;)V
  #35 = Utf8               ()V
  #36 = NameAndType        #32:#35        // "<init>":()V
  #37 = Methodref          #5.#36         // java/lang/Object."<init>":()V
  #38 = Utf8               Signature
  #39 = Utf8               Code
  #40 = Utf8               LineNumberTable
  #41 = Utf8               LocalVariableTable
  #42 = Utf8               MethodParameters
  #43 = Utf8               InnerClasses
  #44 = Utf8               SourceFile
  #45 = Utf8               ScalaInlineInfo
  #46 = Utf8               Scala
{
  private final T t;
    descriptor: Ljava/lang/Object;
    flags: (0x0012) ACC_PRIVATE, ACC_FINAL
    Signature: #12                          // TT;

  private final scala.Function1<T, coursier.core.shaded.fastparse.ParserInput> conv;
    descriptor: Lscala/Function1;
    flags: (0x0012) ACC_PRIVATE, ACC_FINAL
    Signature: #15                          // Lscala/Function1<TT;Lcoursier/core/shaded/fastparse/ParserInput;>;

  public <T extends java.lang.Object> T parseThrough(scala.Function1<coursier.core.shaded.fastparse.ParserInput, T>);
    descriptor: (Lscala/Function1;)Ljava/lang/Object;
    flags: (0x0001) ACC_PUBLIC
    Code:
      stack=3, locals=2, args_size=2
         0: aload_1
         1: aload_0
         2: getfield      #21                 // Field conv:Lscala/Function1;
         5: aload_0
         6: getfield      #23                 // Field t:Ljava/lang/Object;
         9: invokeinterface #29,  2           // InterfaceMethod scala/Function1.apply:(Ljava/lang/Object;)Ljava/lang/Object;
        14: invokeinterface #29,  2           // InterfaceMethod scala/Function1.apply:(Ljava/lang/Object;)Ljava/lang/Object;
        19: areturn
      LineNumberTable:
        line 25: 0
      LocalVariableTable:
        Start  Length  Slot  Name   Signature
            0      20     0  this   Lcoursier/core/shaded/fastparse/ParserInputSource$fromParserInput;
            0      20     1     f   Lscala/Function1;
    Signature: #18                          // <T:Ljava/lang/Object;>(Lscala/Function1<Lcoursier/core/shaded/fastparse/ParserInput;TT;>;)TT;
    MethodParameters:
      Name                           Flags
      f                              final

  public coursier.core.shaded.fastparse.ParserInputSource$fromParserInput(T, scala.Function1<T, coursier.core.shaded.fastparse.ParserInput>);
    descriptor: (Ljava/lang/Object;Lscala/Function1;)V
    flags: (0x0001) ACC_PUBLIC
    Code:
      stack=2, locals=3, args_size=3
         0: aload_0
         1: aload_1
         2: putfield      #23                 // Field t:Ljava/lang/Object;
         5: aload_0
         6: aload_2
         7: putfield      #21                 // Field conv:Lscala/Function1;
        10: aload_0
        11: invokespecial #37                 // Method java/lang/Object."<init>":()V
        14: return
      LineNumberTable:
        line 24: 0
      LocalVariableTable:
        Start  Length  Slot  Name   Signature
            0      15     0  this   Lcoursier/core/shaded/fastparse/ParserInputSource$fromParserInput;
            0      15     1     t   Ljava/lang/Object;
            0      15     2  conv   Lscala/Function1;
    Signature: #34                          // (TT;Lscala/Function1<TT;Lcoursier/core/shaded/fastparse/ParserInput;>;)V
    MethodParameters:
      Name                           Flags
      t                              final
      conv                           final
}
InnerClasses:
  public static #9= #2 of #7;             // fromParserInput=class coursier/core/shaded/fastparse/ParserInputSource$fromParserInput of class coursier/core/shaded/fastparse/ParserInputSource
Signature: #3                           // <T:Ljava/lang/Object;>Ljava/lang/Object;Lcoursier/core/shaded/fastparse/ParserInputSource;
SourceFile: "ParserInput.scala"
  ScalaInlineInfo: length = 0xE (unknown attribute)
   01 00 00 02 00 20 00 21 00 00 10 00 11 00
  Scala: length = 0x0 (unknown attribute)

