Classfile /Users/mw/Projects/slang-braindump/.jar/jar8/assemble/slang-braindump/assemble/content/coursier/core/shaded/sourcecode/Util.class
  Last modified May 29, 2022; size 1445 bytes
  SHA-256 checksum cc3d7f2d953e95be6c69c80a5b31668ce7419b0588d7336c2f2dc5c5e7ed19bb
  Compiled from "Macros.scala"
public final class coursier.core.shaded.sourcecode.Util
  minor version: 0
  major version: 52
  flags: (0x0031) ACC_PUBLIC, ACC_FINAL, ACC_SUPER
  this_class: #2                          // coursier/core/shaded/sourcecode/Util
  super_class: #4                         // java/lang/Object
  interfaces: 0, fields: 0, methods: 3, attributes: 4
Constant pool:
   #1 = Utf8               coursier/core/shaded/sourcecode/Util
   #2 = Class              #1             // coursier/core/shaded/sourcecode/Util
   #3 = Utf8               java/lang/Object
   #4 = Class              #3             // java/lang/Object
   #5 = Utf8               Macros.scala
   #6 = Utf8               Lscala/reflect/ScalaSignature;
   #7 = Utf8               bytes
   #8 = Utf8               \u0006\u0005=;QAB\u0004\t\u0002)1Q\u0001D\u0004\t\u00025AQ\u0001F\u0001\u0005\u0002UAQAF\u0001\u0005\u0002]AQAM\u0001\u0005\u0002MBQ!Q\u0001\u0005\u0002\t\u000bA!\u0016;jY*\t\u0001\"\u0001\u0006t_V\u00148-Z2pI\u0016\u001c\u0001\u0001\u0005\u0002\f\u00035\tqA\u0001\u0003Vi&d7CA\u0001\u000f!\ty!#D\u0001\u0011\u0015\u0005\t\u0012!B:dC2\f\u0017BA\n\u0011\u0005\u0019\te.\u001f*fM\u00061A(\u001b8jiz\"\u0012AC\u0001\fSN\u001c\u0016P\u001c;iKRL7\r\u0006\u0002\u0019CQ\u0011\u0011\u0004\b\t\u0003\u001fiI!a\u0007\t\u0003\u000f\t{w\u000e\\3b]\")Qd\u0001a\u0001=\u0005\t1\u000f\u0005\u0002 U9\u0011\u0001%\t\u0007\u0001\u0011\u0015\u00113\u00011\u0001$\u0003\u0005\u0019\u0007C\u0001\u0013(\u001d\tYQ%\u0003\u0002\'\u000f\u000511i\\7qCRL!\u0001K\u0015\u0003\u000f\r{g\u000e^3yi*\u0011aeB\u0005\u0003W1\u0012aaU=nE>d\u0017BA\u0017/\u0005\u001d\tE.[1tKNT!a\f\u0019\u0002\r5\f7M]8t\u0015\t\t\u0004#A\u0004sK\u001adWm\u0019;\u0002\u001f%\u001c8+\u001f8uQ\u0016$\u0018n\u0019(b[\u0016$\"!\u0007\u001b\t\u000bU\"\u0001\u0019\u0001\u001c\u0002\t9\fW.\u001a\t\u0003oyr!\u0001\u000f\u001f\u0011\u0005e\u0002R\"\u0001\u001e\u000b\u0005mJ\u0011A\u0002\u001fs_>$h(\u0003\u0002>!\u00051\u0001K]3eK\u001aL!a\u0010!\u0003\rM#(/\u001b8h\u0015\ti\u0004#A\u0004hKRt\u0015-\\3\u0015\u0005\rsEC\u0001#L!\t)%*D\u0001G\u0015\t9\u0005*\u0001\u0003mC:<\'\"A%\u0002\t)\fg/Y\u0005\u0003\u007f\u0019CQ!H\u0003A\u00021\u0003\"!\u0014\u0016\u000f\u0005\u0001r\u0005\"\u0002\u0012\u0006\u0001\u0004\u0019\u0003
   #9 = Utf8               scala/reflect/api/Symbols$SymbolApi
  #10 = Class              #9             // scala/reflect/api/Symbols$SymbolApi
  #11 = Utf8               scala/reflect/api/Symbols
  #12 = Class              #11            // scala/reflect/api/Symbols
  #13 = Utf8               SymbolApi
  #14 = Utf8               getName
  #15 = Utf8               (Lscala/reflect/macros/blackbox/Context;Lscala/reflect/api/Symbols$SymbolApi;)Ljava/lang/String;
  #16 = Utf8               c
  #17 = Utf8               s
  #18 = Utf8               coursier/core/shaded/sourcecode/Util$
  #19 = Class              #18            // coursier/core/shaded/sourcecode/Util$
  #20 = Utf8               MODULE$
  #21 = Utf8               Lcoursier/core/shaded/sourcecode/Util$;
  #22 = NameAndType        #20:#21        // MODULE$:Lcoursier/core/shaded/sourcecode/Util$;
  #23 = Fieldref           #19.#22        // coursier/core/shaded/sourcecode/Util$.MODULE$:Lcoursier/core/shaded/sourcecode/Util$;
  #24 = NameAndType        #14:#15        // getName:(Lscala/reflect/macros/blackbox/Context;Lscala/reflect/api/Symbols$SymbolApi;)Ljava/lang/String;
  #25 = Methodref          #19.#24        // coursier/core/shaded/sourcecode/Util$.getName:(Lscala/reflect/macros/blackbox/Context;Lscala/reflect/api/Symbols$SymbolApi;)Ljava/lang/String;
  #26 = Utf8               isSyntheticName
  #27 = Utf8               (Ljava/lang/String;)Z
  #28 = Utf8               name
  #29 = NameAndType        #26:#27        // isSyntheticName:(Ljava/lang/String;)Z
  #30 = Methodref          #19.#29        // coursier/core/shaded/sourcecode/Util$.isSyntheticName:(Ljava/lang/String;)Z
  #31 = Utf8               isSynthetic
  #32 = Utf8               (Lscala/reflect/macros/blackbox/Context;Lscala/reflect/api/Symbols$SymbolApi;)Z
  #33 = NameAndType        #31:#32        // isSynthetic:(Lscala/reflect/macros/blackbox/Context;Lscala/reflect/api/Symbols$SymbolApi;)Z
  #34 = Methodref          #19.#33        // coursier/core/shaded/sourcecode/Util$.isSynthetic:(Lscala/reflect/macros/blackbox/Context;Lscala/reflect/api/Symbols$SymbolApi;)Z
  #35 = Utf8               Code
  #36 = Utf8               Signature
  #37 = Utf8               MethodParameters
  #38 = Utf8               InnerClasses
  #39 = Utf8               SourceFile
  #40 = Utf8               RuntimeVisibleAnnotations
  #41 = Utf8               ScalaSig
{
  public static java.lang.String getName(scala.reflect.macros.blackbox.Context, scala.reflect.api.Symbols$SymbolApi);
    descriptor: (Lscala/reflect/macros/blackbox/Context;Lscala/reflect/api/Symbols$SymbolApi;)Ljava/lang/String;
    flags: (0x0009) ACC_PUBLIC, ACC_STATIC
    Code:
      stack=3, locals=2, args_size=2
         0: getstatic     #23                 // Field coursier/core/shaded/sourcecode/Util$.MODULE$:Lcoursier/core/shaded/sourcecode/Util$;
         3: aload_0
         4: aload_1
         5: invokevirtual #25                 // Method coursier/core/shaded/sourcecode/Util$.getName:(Lscala/reflect/macros/blackbox/Context;Lscala/reflect/api/Symbols$SymbolApi;)Ljava/lang/String;
         8: areturn
    Signature: #15                          // (Lscala/reflect/macros/blackbox/Context;Lscala/reflect/api/Symbols$SymbolApi;)Ljava/lang/String;
    MethodParameters:
      Name                           Flags
      c                              final
      s                              final

  public static boolean isSyntheticName(java.lang.String);
    descriptor: (Ljava/lang/String;)Z
    flags: (0x0009) ACC_PUBLIC, ACC_STATIC
    Code:
      stack=2, locals=1, args_size=1
         0: getstatic     #23                 // Field coursier/core/shaded/sourcecode/Util$.MODULE$:Lcoursier/core/shaded/sourcecode/Util$;
         3: aload_0
         4: invokevirtual #30                 // Method coursier/core/shaded/sourcecode/Util$.isSyntheticName:(Ljava/lang/String;)Z
         7: ireturn
    MethodParameters:
      Name                           Flags
      name                           final

  public static boolean isSynthetic(scala.reflect.macros.blackbox.Context, scala.reflect.api.Symbols$SymbolApi);
    descriptor: (Lscala/reflect/macros/blackbox/Context;Lscala/reflect/api/Symbols$SymbolApi;)Z
    flags: (0x0009) ACC_PUBLIC, ACC_STATIC
    Code:
      stack=3, locals=2, args_size=2
         0: getstatic     #23                 // Field coursier/core/shaded/sourcecode/Util$.MODULE$:Lcoursier/core/shaded/sourcecode/Util$;
         3: aload_0
         4: aload_1
         5: invokevirtual #34                 // Method coursier/core/shaded/sourcecode/Util$.isSynthetic:(Lscala/reflect/macros/blackbox/Context;Lscala/reflect/api/Symbols$SymbolApi;)Z
         8: ireturn
    Signature: #32                          // (Lscala/reflect/macros/blackbox/Context;Lscala/reflect/api/Symbols$SymbolApi;)Z
    MethodParameters:
      Name                           Flags
      c                              final
      s                              final
}
InnerClasses:
  public #13= #10 of #12;                 // SymbolApi=class scala/reflect/api/Symbols$SymbolApi of class scala/reflect/api/Symbols
SourceFile: "Macros.scala"
RuntimeVisibleAnnotations:
  0: #6(#7=s#8)
    scala.reflect.ScalaSignature(
      bytes="\u0006\u0005=;QAB\u0004\t\u0002)1Q\u0001D\u0004\t\u00025AQ\u0001F\u0001\u0005\u0002UAQAF\u0001\u0005\u0002]AQAM\u0001\u0005\u0002MBQ!Q\u0001\u0005\u0002\t\u000bA!\u0016;jY*\t\u0001\"\u0001\u0006t_V\u00148-Z2pI\u0016\u001c\u0001\u0001\u0005\u0002\f\u00035\tqA\u0001\u0003Vi&d7CA\u0001\u000f!\ty!#D\u0001\u0011\u0015\u0005\t\u0012!B:dC2\f\u0017BA\n\u0011\u0005\u0019\te.\u001f*fM\u00061A(\u001b8jiz\"\u0012AC\u0001\fSN\u001c\u0016P\u001c;iKRL7\r\u0006\u0002\u0019CQ\u0011\u0011\u0004\b\t\u0003\u001fiI!a\u0007\t\u0003\u000f\t{w\u000e\\3b]\")Qd\u0001a\u0001=\u0005\t1\u000f\u0005\u0002 U9\u0011\u0001%\t\u0007\u0001\u0011\u0015\u00113\u00011\u0001$\u0003\u0005\u0019\u0007C\u0001\u0013(\u001d\tYQ%\u0003\u0002\'\u000f\u000511i\\7qCRL!\u0001K\u0015\u0003\u000f\r{g\u000e^3yi*\u0011aeB\u0005\u0003W1\u0012aaU=nE>d\u0017BA\u0017/\u0005\u001d\tE.[1tKNT!a\f\u0019\u0002\r5\f7M]8t\u0015\t\t\u0004#A\u0004sK\u001adWm\u0019;\u0002\u001f%\u001c8+\u001f8uQ\u0016$\u0018n\u0019(b[\u0016$\"!\u0007\u001b\t\u000bU\"\u0001\u0019\u0001\u001c\u0002\t9\fW.\u001a\t\u0003oyr!\u0001\u000f\u001f\u0011\u0005e\u0002R\"\u0001\u001e\u000b\u0005mJ\u0011A\u0002\u001fs_>$h(\u0003\u0002>!\u00051\u0001K]3eK\u001aL!a\u0010!\u0003\rM#(/\u001b8h\u0015\ti\u0004#A\u0004hKRt\u0015-\\3\u0015\u0005\rsEC\u0001#L!\t)%*D\u0001G\u0015\t9\u0005*\u0001\u0003mC:<\'\"A%\u0002\t)\fg/Y\u0005\u0003\u007f\u0019CQ!H\u0003A\u00021\u0003\"!\u0014\u0016\u000f\u0005\u0001r\u0005\"\u0002\u0012\u0006\u0001\u0004\u0019\u0003"
    )
  ScalaSig: length = 0x3 (unknown attribute)
   05 02 00
