Classfile /Users/mw/Projects/slang-braindump/.jar/jar8/assemble/slang-braindump/assemble/content/org/apache/commons/lang3/SystemUtils.class
  Last modified May 29, 2022; size 10374 bytes
  SHA-256 checksum 629cae4dc688f981c1f4f46e421e12d9cb63c46068cd47b7515529bc17fa6deb
  Compiled from "SystemUtils.java"
public class org.apache.commons.lang3.SystemUtils
  minor version: 0
  major version: 52
  flags: (0x0021) ACC_PUBLIC, ACC_SUPER
  this_class: #2                          // org/apache/commons/lang3/SystemUtils
  super_class: #224                       // java/lang/Object
  interfaces: 0, fields: 103, methods: 19, attributes: 1
Constant pool:
    #1 = Class              #392          // java/io/File
    #2 = Class              #393          // org/apache/commons/lang3/SystemUtils
    #3 = String             #394          // java.home
    #4 = Methodref          #395.#396     // java/lang/System.getProperty:(Ljava/lang/String;)Ljava/lang/String;
    #5 = Methodref          #1.#397       // java/io/File."<init>":(Ljava/lang/String;)V
    #6 = Fieldref           #2.#398       // org/apache/commons/lang3/SystemUtils.IS_OS_WINDOWS:Z
    #7 = String             #399          // COMPUTERNAME
    #8 = Methodref          #395.#400     // java/lang/System.getenv:(Ljava/lang/String;)Ljava/lang/String;
    #9 = String             #401          // HOSTNAME
   #10 = String             #402          // java.io.tmpdir
   #11 = Fieldref           #2.#403       // org/apache/commons/lang3/SystemUtils.JAVA_SPECIFICATION_VERSION:Ljava/lang/String;
   #12 = Methodref          #2.#404       // org/apache/commons/lang3/SystemUtils.isJavaVersionMatch:(Ljava/lang/String;Ljava/lang/String;)Z
   #13 = Fieldref           #2.#405       // org/apache/commons/lang3/SystemUtils.OS_NAME:Ljava/lang/String;
   #14 = Fieldref           #2.#406       // org/apache/commons/lang3/SystemUtils.OS_VERSION:Ljava/lang/String;
   #15 = Methodref          #2.#407       // org/apache/commons/lang3/SystemUtils.isOSMatch:(Ljava/lang/String;Ljava/lang/String;Ljava/lang/String;Ljava/lang/String;)Z
   #16 = Methodref          #2.#408       // org/apache/commons/lang3/SystemUtils.isOSNameMatch:(Ljava/lang/String;Ljava/lang/String;)Z
   #17 = Class              #409          // java/lang/SecurityException
   #18 = String             #410          // user.dir
   #19 = String             #411          // user.home
   #20 = Fieldref           #412.#413     // java/lang/Boolean.TRUE:Ljava/lang/Boolean;
   #21 = Methodref          #412.#414     // java/lang/Boolean.toString:()Ljava/lang/String;
   #22 = Fieldref           #2.#415       // org/apache/commons/lang3/SystemUtils.JAVA_AWT_HEADLESS:Ljava/lang/String;
   #23 = Methodref          #342.#416     // java/lang/String.equals:(Ljava/lang/Object;)Z
   #24 = Fieldref           #2.#417       // org/apache/commons/lang3/SystemUtils.JAVA_SPECIFICATION_VERSION_AS_ENUM:Lorg/apache/commons/lang3/JavaVersion;
   #25 = Methodref          #418.#419     // org/apache/commons/lang3/JavaVersion.atLeast:(Lorg/apache/commons/lang3/JavaVersion;)Z
   #26 = Methodref          #418.#420     // org/apache/commons/lang3/JavaVersion.atMost:(Lorg/apache/commons/lang3/JavaVersion;)Z
   #27 = Methodref          #342.#421     // java/lang/String.startsWith:(Ljava/lang/String;)Z
   #28 = Methodref          #2.#422       // org/apache/commons/lang3/SystemUtils.isOSVersionMatch:(Ljava/lang/String;Ljava/lang/String;)Z
   #29 = Methodref          #423.#424     // org/apache/commons/lang3/StringUtils.isEmpty:(Ljava/lang/CharSequence;)Z
   #30 = String             #425          // \\.
   #31 = Methodref          #342.#426     // java/lang/String.split:(Ljava/lang/String;)[Ljava/lang/String;
   #32 = Methodref          #427.#428     // java/lang/Math.min:(II)I
   #33 = Methodref          #224.#429     // java/lang/Object."<init>":()V
   #34 = String             #430          // awt.toolkit
   #35 = Methodref          #2.#431       // org/apache/commons/lang3/SystemUtils.getSystemProperty:(Ljava/lang/String;)Ljava/lang/String;
   #36 = Fieldref           #2.#432       // org/apache/commons/lang3/SystemUtils.AWT_TOOLKIT:Ljava/lang/String;
   #37 = String             #433          // file.encoding
   #38 = Fieldref           #2.#434       // org/apache/commons/lang3/SystemUtils.FILE_ENCODING:Ljava/lang/String;
   #39 = String             #435          // file.separator
   #40 = Fieldref           #2.#436       // org/apache/commons/lang3/SystemUtils.FILE_SEPARATOR:Ljava/lang/String;
   #41 = String             #437          // java.awt.fonts
   #42 = Fieldref           #2.#438       // org/apache/commons/lang3/SystemUtils.JAVA_AWT_FONTS:Ljava/lang/String;
   #43 = String             #439          // java.awt.graphicsenv
   #44 = Fieldref           #2.#440       // org/apache/commons/lang3/SystemUtils.JAVA_AWT_GRAPHICSENV:Ljava/lang/String;
   #45 = String             #441          // java.awt.headless
   #46 = String             #442          // java.awt.printerjob
   #47 = Fieldref           #2.#443       // org/apache/commons/lang3/SystemUtils.JAVA_AWT_PRINTERJOB:Ljava/lang/String;
   #48 = String             #444          // java.class.path
   #49 = Fieldref           #2.#445       // org/apache/commons/lang3/SystemUtils.JAVA_CLASS_PATH:Ljava/lang/String;
   #50 = String             #446          // java.class.version
   #51 = Fieldref           #2.#447       // org/apache/commons/lang3/SystemUtils.JAVA_CLASS_VERSION:Ljava/lang/String;
   #52 = String             #448          // java.compiler
   #53 = Fieldref           #2.#449       // org/apache/commons/lang3/SystemUtils.JAVA_COMPILER:Ljava/lang/String;
   #54 = String             #450          // java.endorsed.dirs
   #55 = Fieldref           #2.#451       // org/apache/commons/lang3/SystemUtils.JAVA_ENDORSED_DIRS:Ljava/lang/String;
   #56 = String             #452          // java.ext.dirs
   #57 = Fieldref           #2.#453       // org/apache/commons/lang3/SystemUtils.JAVA_EXT_DIRS:Ljava/lang/String;
   #58 = Fieldref           #2.#454       // org/apache/commons/lang3/SystemUtils.JAVA_HOME:Ljava/lang/String;
   #59 = Fieldref           #2.#455       // org/apache/commons/lang3/SystemUtils.JAVA_IO_TMPDIR:Ljava/lang/String;
   #60 = String             #456          // java.library.path
   #61 = Fieldref           #2.#457       // org/apache/commons/lang3/SystemUtils.JAVA_LIBRARY_PATH:Ljava/lang/String;
   #62 = String             #458          // java.runtime.name
   #63 = Fieldref           #2.#459       // org/apache/commons/lang3/SystemUtils.JAVA_RUNTIME_NAME:Ljava/lang/String;
   #64 = String             #460          // java.runtime.version
   #65 = Fieldref           #2.#461       // org/apache/commons/lang3/SystemUtils.JAVA_RUNTIME_VERSION:Ljava/lang/String;
   #66 = String             #462          // java.specification.name
   #67 = Fieldref           #2.#463       // org/apache/commons/lang3/SystemUtils.JAVA_SPECIFICATION_NAME:Ljava/lang/String;
   #68 = String             #464          // java.specification.vendor
   #69 = Fieldref           #2.#465       // org/apache/commons/lang3/SystemUtils.JAVA_SPECIFICATION_VENDOR:Ljava/lang/String;
   #70 = String             #466          // java.specification.version
   #71 = Methodref          #418.#467     // org/apache/commons/lang3/JavaVersion.get:(Ljava/lang/String;)Lorg/apache/commons/lang3/JavaVersion;
   #72 = String             #468          // java.util.prefs.PreferencesFactory
   #73 = Fieldref           #2.#469       // org/apache/commons/lang3/SystemUtils.JAVA_UTIL_PREFS_PREFERENCES_FACTORY:Ljava/lang/String;
   #74 = String             #470          // java.vendor
   #75 = Fieldref           #2.#471       // org/apache/commons/lang3/SystemUtils.JAVA_VENDOR:Ljava/lang/String;
   #76 = String             #472          // java.vendor.url
   #77 = Fieldref           #2.#473       // org/apache/commons/lang3/SystemUtils.JAVA_VENDOR_URL:Ljava/lang/String;
   #78 = String             #474          // java.version
   #79 = Fieldref           #2.#475       // org/apache/commons/lang3/SystemUtils.JAVA_VERSION:Ljava/lang/String;
   #80 = String             #476          // java.vm.info
   #81 = Fieldref           #2.#477       // org/apache/commons/lang3/SystemUtils.JAVA_VM_INFO:Ljava/lang/String;
   #82 = String             #478          // java.vm.name
   #83 = Fieldref           #2.#479       // org/apache/commons/lang3/SystemUtils.JAVA_VM_NAME:Ljava/lang/String;
   #84 = String             #480          // java.vm.specification.name
   #85 = Fieldref           #2.#481       // org/apache/commons/lang3/SystemUtils.JAVA_VM_SPECIFICATION_NAME:Ljava/lang/String;
   #86 = String             #482          // java.vm.specification.vendor
   #87 = Fieldref           #2.#483       // org/apache/commons/lang3/SystemUtils.JAVA_VM_SPECIFICATION_VENDOR:Ljava/lang/String;
   #88 = String             #484          // java.vm.specification.version
   #89 = Fieldref           #2.#485       // org/apache/commons/lang3/SystemUtils.JAVA_VM_SPECIFICATION_VERSION:Ljava/lang/String;
   #90 = String             #486          // java.vm.vendor
   #91 = Fieldref           #2.#487       // org/apache/commons/lang3/SystemUtils.JAVA_VM_VENDOR:Ljava/lang/String;
   #92 = String             #488          // java.vm.version
   #93 = Fieldref           #2.#489       // org/apache/commons/lang3/SystemUtils.JAVA_VM_VERSION:Ljava/lang/String;
   #94 = String             #490          // line.separator
   #95 = Fieldref           #2.#491       // org/apache/commons/lang3/SystemUtils.LINE_SEPARATOR:Ljava/lang/String;
   #96 = String             #492          // os.arch
   #97 = Fieldref           #2.#493       // org/apache/commons/lang3/SystemUtils.OS_ARCH:Ljava/lang/String;
   #98 = String             #494          // os.name
   #99 = String             #495          // os.version
  #100 = String             #496          // path.separator
  #101 = Fieldref           #2.#497       // org/apache/commons/lang3/SystemUtils.PATH_SEPARATOR:Ljava/lang/String;
  #102 = String             #498          // user.country
  #103 = String             #499          // user.region
  #104 = Fieldref           #2.#500       // org/apache/commons/lang3/SystemUtils.USER_COUNTRY:Ljava/lang/String;
  #105 = Fieldref           #2.#501       // org/apache/commons/lang3/SystemUtils.USER_DIR:Ljava/lang/String;
  #106 = Fieldref           #2.#502       // org/apache/commons/lang3/SystemUtils.USER_HOME:Ljava/lang/String;
  #107 = String             #503          // user.language
  #108 = Fieldref           #2.#504       // org/apache/commons/lang3/SystemUtils.USER_LANGUAGE:Ljava/lang/String;
  #109 = String             #505          // user.name
  #110 = Fieldref           #2.#506       // org/apache/commons/lang3/SystemUtils.USER_NAME:Ljava/lang/String;
  #111 = String             #507          // user.timezone
  #112 = Fieldref           #2.#508       // org/apache/commons/lang3/SystemUtils.USER_TIMEZONE:Ljava/lang/String;
  #113 = String             #509          // 1.1
  #114 = Methodref          #2.#510       // org/apache/commons/lang3/SystemUtils.getJavaVersionMatches:(Ljava/lang/String;)Z
  #115 = Fieldref           #2.#511       // org/apache/commons/lang3/SystemUtils.IS_JAVA_1_1:Z
  #116 = String             #512          // 1.2
  #117 = Fieldref           #2.#513       // org/apache/commons/lang3/SystemUtils.IS_JAVA_1_2:Z
  #118 = String             #514          // 1.3
  #119 = Fieldref           #2.#515       // org/apache/commons/lang3/SystemUtils.IS_JAVA_1_3:Z
  #120 = String             #516          // 1.4
  #121 = Fieldref           #2.#517       // org/apache/commons/lang3/SystemUtils.IS_JAVA_1_4:Z
  #122 = String             #518          // 1.5
  #123 = Fieldref           #2.#519       // org/apache/commons/lang3/SystemUtils.IS_JAVA_1_5:Z
  #124 = String             #520          // 1.6
  #125 = Fieldref           #2.#521       // org/apache/commons/lang3/SystemUtils.IS_JAVA_1_6:Z
  #126 = String             #522          // 1.7
  #127 = Fieldref           #2.#523       // org/apache/commons/lang3/SystemUtils.IS_JAVA_1_7:Z
  #128 = String             #524          // 1.8
  #129 = Fieldref           #2.#525       // org/apache/commons/lang3/SystemUtils.IS_JAVA_1_8:Z
  #130 = String             #526          // 9
  #131 = Fieldref           #2.#527       // org/apache/commons/lang3/SystemUtils.IS_JAVA_1_9:Z
  #132 = Fieldref           #2.#528       // org/apache/commons/lang3/SystemUtils.IS_JAVA_9:Z
  #133 = String             #529          // 10
  #134 = Fieldref           #2.#530       // org/apache/commons/lang3/SystemUtils.IS_JAVA_10:Z
  #135 = String             #531          // 11
  #136 = Fieldref           #2.#532       // org/apache/commons/lang3/SystemUtils.IS_JAVA_11:Z
  #137 = String             #533          // 12
  #138 = Fieldref           #2.#534       // org/apache/commons/lang3/SystemUtils.IS_JAVA_12:Z
  #139 = String             #535          // 13
  #140 = Fieldref           #2.#536       // org/apache/commons/lang3/SystemUtils.IS_JAVA_13:Z
  #141 = String             #537          // AIX
  #142 = Methodref          #2.#538       // org/apache/commons/lang3/SystemUtils.getOsMatchesName:(Ljava/lang/String;)Z
  #143 = Fieldref           #2.#539       // org/apache/commons/lang3/SystemUtils.IS_OS_AIX:Z
  #144 = String             #540          // HP-UX
  #145 = Fieldref           #2.#541       // org/apache/commons/lang3/SystemUtils.IS_OS_HP_UX:Z
  #146 = String             #542          // OS/400
  #147 = Fieldref           #2.#543       // org/apache/commons/lang3/SystemUtils.IS_OS_400:Z
  #148 = String             #544          // Irix
  #149 = Fieldref           #2.#545       // org/apache/commons/lang3/SystemUtils.IS_OS_IRIX:Z
  #150 = String             #546          // Linux
  #151 = String             #547          // LINUX
  #152 = Fieldref           #2.#548       // org/apache/commons/lang3/SystemUtils.IS_OS_LINUX:Z
  #153 = String             #549          // Mac
  #154 = Fieldref           #2.#550       // org/apache/commons/lang3/SystemUtils.IS_OS_MAC:Z
  #155 = String             #551          // Mac OS X
  #156 = Fieldref           #2.#552       // org/apache/commons/lang3/SystemUtils.IS_OS_MAC_OSX:Z
  #157 = String             #553          // 10.0
  #158 = Methodref          #2.#554       // org/apache/commons/lang3/SystemUtils.getOsMatches:(Ljava/lang/String;Ljava/lang/String;)Z
  #159 = Fieldref           #2.#555       // org/apache/commons/lang3/SystemUtils.IS_OS_MAC_OSX_CHEETAH:Z
  #160 = String             #556          // 10.1
  #161 = Fieldref           #2.#557       // org/apache/commons/lang3/SystemUtils.IS_OS_MAC_OSX_PUMA:Z
  #162 = String             #558          // 10.2
  #163 = Fieldref           #2.#559       // org/apache/commons/lang3/SystemUtils.IS_OS_MAC_OSX_JAGUAR:Z
  #164 = String             #560          // 10.3
  #165 = Fieldref           #2.#561       // org/apache/commons/lang3/SystemUtils.IS_OS_MAC_OSX_PANTHER:Z
  #166 = String             #562          // 10.4
  #167 = Fieldref           #2.#563       // org/apache/commons/lang3/SystemUtils.IS_OS_MAC_OSX_TIGER:Z
  #168 = String             #564          // 10.5
  #169 = Fieldref           #2.#565       // org/apache/commons/lang3/SystemUtils.IS_OS_MAC_OSX_LEOPARD:Z
  #170 = String             #566          // 10.6
  #171 = Fieldref           #2.#567       // org/apache/commons/lang3/SystemUtils.IS_OS_MAC_OSX_SNOW_LEOPARD:Z
  #172 = String             #568          // 10.7
  #173 = Fieldref           #2.#569       // org/apache/commons/lang3/SystemUtils.IS_OS_MAC_OSX_LION:Z
  #174 = String             #570          // 10.8
  #175 = Fieldref           #2.#571       // org/apache/commons/lang3/SystemUtils.IS_OS_MAC_OSX_MOUNTAIN_LION:Z
  #176 = String             #572          // 10.9
  #177 = Fieldref           #2.#573       // org/apache/commons/lang3/SystemUtils.IS_OS_MAC_OSX_MAVERICKS:Z
  #178 = String             #574          // 10.10
  #179 = Fieldref           #2.#575       // org/apache/commons/lang3/SystemUtils.IS_OS_MAC_OSX_YOSEMITE:Z
  #180 = String             #576          // 10.11
  #181 = Fieldref           #2.#577       // org/apache/commons/lang3/SystemUtils.IS_OS_MAC_OSX_EL_CAPITAN:Z
  #182 = String             #578          // FreeBSD
  #183 = Fieldref           #2.#579       // org/apache/commons/lang3/SystemUtils.IS_OS_FREE_BSD:Z
  #184 = String             #580          // OpenBSD
  #185 = Fieldref           #2.#581       // org/apache/commons/lang3/SystemUtils.IS_OS_OPEN_BSD:Z
  #186 = String             #582          // NetBSD
  #187 = Fieldref           #2.#583       // org/apache/commons/lang3/SystemUtils.IS_OS_NET_BSD:Z
  #188 = String             #584          // OS/2
  #189 = Fieldref           #2.#585       // org/apache/commons/lang3/SystemUtils.IS_OS_OS2:Z
  #190 = String             #586          // Solaris
  #191 = Fieldref           #2.#587       // org/apache/commons/lang3/SystemUtils.IS_OS_SOLARIS:Z
  #192 = String             #588          // SunOS
  #193 = Fieldref           #2.#589       // org/apache/commons/lang3/SystemUtils.IS_OS_SUN_OS:Z
  #194 = Fieldref           #2.#590       // org/apache/commons/lang3/SystemUtils.IS_OS_UNIX:Z
  #195 = String             #591          // Windows
  #196 = String             #592          // Windows 2000
  #197 = Fieldref           #2.#593       // org/apache/commons/lang3/SystemUtils.IS_OS_WINDOWS_2000:Z
  #198 = String             #594          // Windows 2003
  #199 = Fieldref           #2.#595       // org/apache/commons/lang3/SystemUtils.IS_OS_WINDOWS_2003:Z
  #200 = String             #596          // Windows Server 2008
  #201 = Fieldref           #2.#597       // org/apache/commons/lang3/SystemUtils.IS_OS_WINDOWS_2008:Z
  #202 = String             #598          // Windows Server 2012
  #203 = Fieldref           #2.#599       // org/apache/commons/lang3/SystemUtils.IS_OS_WINDOWS_2012:Z
  #204 = String             #600          // Windows 95
  #205 = Fieldref           #2.#601       // org/apache/commons/lang3/SystemUtils.IS_OS_WINDOWS_95:Z
  #206 = String             #602          // Windows 98
  #207 = Fieldref           #2.#603       // org/apache/commons/lang3/SystemUtils.IS_OS_WINDOWS_98:Z
  #208 = String             #604          // Windows Me
  #209 = Fieldref           #2.#605       // org/apache/commons/lang3/SystemUtils.IS_OS_WINDOWS_ME:Z
  #210 = String             #606          // Windows NT
  #211 = Fieldref           #2.#607       // org/apache/commons/lang3/SystemUtils.IS_OS_WINDOWS_NT:Z
  #212 = String             #608          // Windows XP
  #213 = Fieldref           #2.#609       // org/apache/commons/lang3/SystemUtils.IS_OS_WINDOWS_XP:Z
  #214 = String             #610          // Windows Vista
  #215 = Fieldref           #2.#611       // org/apache/commons/lang3/SystemUtils.IS_OS_WINDOWS_VISTA:Z
  #216 = String             #612          // Windows 7
  #217 = Fieldref           #2.#613       // org/apache/commons/lang3/SystemUtils.IS_OS_WINDOWS_7:Z
  #218 = String             #614          // Windows 8
  #219 = Fieldref           #2.#615       // org/apache/commons/lang3/SystemUtils.IS_OS_WINDOWS_8:Z
  #220 = String             #616          // Windows 10
  #221 = Fieldref           #2.#617       // org/apache/commons/lang3/SystemUtils.IS_OS_WINDOWS_10:Z
  #222 = String             #618          // z/OS
  #223 = Fieldref           #2.#619       // org/apache/commons/lang3/SystemUtils.IS_OS_ZOS:Z
  #224 = Class              #620          // java/lang/Object
  #225 = Utf8               OS_NAME_WINDOWS_PREFIX
  #226 = Utf8               Ljava/lang/String;
  #227 = Utf8               ConstantValue
  #228 = Utf8               USER_HOME_KEY
  #229 = Utf8               USER_DIR_KEY
  #230 = Utf8               JAVA_IO_TMPDIR_KEY
  #231 = Utf8               JAVA_HOME_KEY
  #232 = Utf8               AWT_TOOLKIT
  #233 = Utf8               FILE_ENCODING
  #234 = Utf8               FILE_SEPARATOR
  #235 = Utf8               Deprecated
  #236 = Utf8               RuntimeVisibleAnnotations
  #237 = Utf8               Ljava/lang/Deprecated;
  #238 = Utf8               JAVA_AWT_FONTS
  #239 = Utf8               JAVA_AWT_GRAPHICSENV
  #240 = Utf8               JAVA_AWT_HEADLESS
  #241 = Utf8               JAVA_AWT_PRINTERJOB
  #242 = Utf8               JAVA_CLASS_PATH
  #243 = Utf8               JAVA_CLASS_VERSION
  #244 = Utf8               JAVA_COMPILER
  #245 = Utf8               JAVA_ENDORSED_DIRS
  #246 = Utf8               JAVA_EXT_DIRS
  #247 = Utf8               JAVA_HOME
  #248 = Utf8               JAVA_IO_TMPDIR
  #249 = Utf8               JAVA_LIBRARY_PATH
  #250 = Utf8               JAVA_RUNTIME_NAME
  #251 = Utf8               JAVA_RUNTIME_VERSION
  #252 = Utf8               JAVA_SPECIFICATION_NAME
  #253 = Utf8               JAVA_SPECIFICATION_VENDOR
  #254 = Utf8               JAVA_SPECIFICATION_VERSION
  #255 = Utf8               JAVA_SPECIFICATION_VERSION_AS_ENUM
  #256 = Utf8               Lorg/apache/commons/lang3/JavaVersion;
  #257 = Utf8               JAVA_UTIL_PREFS_PREFERENCES_FACTORY
  #258 = Utf8               JAVA_VENDOR
  #259 = Utf8               JAVA_VENDOR_URL
  #260 = Utf8               JAVA_VERSION
  #261 = Utf8               JAVA_VM_INFO
  #262 = Utf8               JAVA_VM_NAME
  #263 = Utf8               JAVA_VM_SPECIFICATION_NAME
  #264 = Utf8               JAVA_VM_SPECIFICATION_VENDOR
  #265 = Utf8               JAVA_VM_SPECIFICATION_VERSION
  #266 = Utf8               JAVA_VM_VENDOR
  #267 = Utf8               JAVA_VM_VERSION
  #268 = Utf8               LINE_SEPARATOR
  #269 = Utf8               OS_ARCH
  #270 = Utf8               OS_NAME
  #271 = Utf8               OS_VERSION
  #272 = Utf8               PATH_SEPARATOR
  #273 = Utf8               USER_COUNTRY
  #274 = Utf8               USER_DIR
  #275 = Utf8               USER_HOME
  #276 = Utf8               USER_LANGUAGE
  #277 = Utf8               USER_NAME
  #278 = Utf8               USER_TIMEZONE
  #279 = Utf8               IS_JAVA_1_1
  #280 = Utf8               Z
  #281 = Utf8               IS_JAVA_1_2
  #282 = Utf8               IS_JAVA_1_3
  #283 = Utf8               IS_JAVA_1_4
  #284 = Utf8               IS_JAVA_1_5
  #285 = Utf8               IS_JAVA_1_6
  #286 = Utf8               IS_JAVA_1_7
  #287 = Utf8               IS_JAVA_1_8
  #288 = Utf8               IS_JAVA_1_9
  #289 = Utf8               IS_JAVA_9
  #290 = Utf8               IS_JAVA_10
  #291 = Utf8               IS_JAVA_11
  #292 = Utf8               IS_JAVA_12
  #293 = Utf8               IS_JAVA_13
  #294 = Utf8               IS_OS_AIX
  #295 = Utf8               IS_OS_HP_UX
  #296 = Utf8               IS_OS_400
  #297 = Utf8               IS_OS_IRIX
  #298 = Utf8               IS_OS_LINUX
  #299 = Utf8               IS_OS_MAC
  #300 = Utf8               IS_OS_MAC_OSX
  #301 = Utf8               IS_OS_MAC_OSX_CHEETAH
  #302 = Utf8               IS_OS_MAC_OSX_PUMA
  #303 = Utf8               IS_OS_MAC_OSX_JAGUAR
  #304 = Utf8               IS_OS_MAC_OSX_PANTHER
  #305 = Utf8               IS_OS_MAC_OSX_TIGER
  #306 = Utf8               IS_OS_MAC_OSX_LEOPARD
  #307 = Utf8               IS_OS_MAC_OSX_SNOW_LEOPARD
  #308 = Utf8               IS_OS_MAC_OSX_LION
  #309 = Utf8               IS_OS_MAC_OSX_MOUNTAIN_LION
  #310 = Utf8               IS_OS_MAC_OSX_MAVERICKS
  #311 = Utf8               IS_OS_MAC_OSX_YOSEMITE
  #312 = Utf8               IS_OS_MAC_OSX_EL_CAPITAN
  #313 = Utf8               IS_OS_FREE_BSD
  #314 = Utf8               IS_OS_OPEN_BSD
  #315 = Utf8               IS_OS_NET_BSD
  #316 = Utf8               IS_OS_OS2
  #317 = Utf8               IS_OS_SOLARIS
  #318 = Utf8               IS_OS_SUN_OS
  #319 = Utf8               IS_OS_UNIX
  #320 = Utf8               IS_OS_WINDOWS
  #321 = Utf8               IS_OS_WINDOWS_2000
  #322 = Utf8               IS_OS_WINDOWS_2003
  #323 = Utf8               IS_OS_WINDOWS_2008
  #324 = Utf8               IS_OS_WINDOWS_2012
  #325 = Utf8               IS_OS_WINDOWS_95
  #326 = Utf8               IS_OS_WINDOWS_98
  #327 = Utf8               IS_OS_WINDOWS_ME
  #328 = Utf8               IS_OS_WINDOWS_NT
  #329 = Utf8               IS_OS_WINDOWS_XP
  #330 = Utf8               IS_OS_WINDOWS_VISTA
  #331 = Utf8               IS_OS_WINDOWS_7
  #332 = Utf8               IS_OS_WINDOWS_8
  #333 = Utf8               IS_OS_WINDOWS_10
  #334 = Utf8               IS_OS_ZOS
  #335 = Utf8               getJavaHome
  #336 = Utf8               ()Ljava/io/File;
  #337 = Utf8               Code
  #338 = Utf8               LineNumberTable
  #339 = Utf8               getHostName
  #340 = Utf8               ()Ljava/lang/String;
  #341 = Utf8               StackMapTable
  #342 = Class              #621          // java/lang/String
  #343 = Utf8               getJavaIoTmpDir
  #344 = Utf8               getJavaVersionMatches
  #345 = Utf8               (Ljava/lang/String;)Z
  #346 = Utf8               LocalVariableTable
  #347 = Utf8               versionPrefix
  #348 = Utf8               getOsMatches
  #349 = Utf8               (Ljava/lang/String;Ljava/lang/String;)Z
  #350 = Utf8               osNamePrefix
  #351 = Utf8               osVersionPrefix
  #352 = Utf8               getOsMatchesName
  #353 = Utf8               getSystemProperty
  #354 = Utf8               (Ljava/lang/String;)Ljava/lang/String;
  #355 = Utf8               ex
  #356 = Utf8               Ljava/lang/SecurityException;
  #357 = Utf8               property
  #358 = Utf8               getEnvironmentVariable
  #359 = Utf8               (Ljava/lang/String;Ljava/lang/String;)Ljava/lang/String;
  #360 = Utf8               value
  #361 = Utf8               name
  #362 = Utf8               defaultValue
  #363 = Utf8               getUserDir
  #364 = Utf8               getUserHome
  #365 = Utf8               isJavaAwtHeadless
  #366 = Utf8               ()Z
  #367 = Utf8               isJavaVersionAtLeast
  #368 = Utf8               (Lorg/apache/commons/lang3/JavaVersion;)Z
  #369 = Utf8               requiredVersion
  #370 = Utf8               isJavaVersionAtMost
  #371 = Utf8               isJavaVersionMatch
  #372 = Utf8               version
  #373 = Utf8               isOSMatch
  #374 = Utf8               (Ljava/lang/String;Ljava/lang/String;Ljava/lang/String;Ljava/lang/String;)Z
  #375 = Utf8               osName
  #376 = Utf8               osVersion
  #377 = Utf8               isOSNameMatch
  #378 = Utf8               isOSVersionMatch
  #379 = Utf8               i
  #380 = Utf8               I
  #381 = Utf8               versionPrefixParts
  #382 = Utf8               [Ljava/lang/String;
  #383 = Utf8               versionParts
  #384 = Class              #382          // "[Ljava/lang/String;"
  #385 = Utf8               <init>
  #386 = Utf8               ()V
  #387 = Utf8               this
  #388 = Utf8               Lorg/apache/commons/lang3/SystemUtils;
  #389 = Utf8               <clinit>
  #390 = Utf8               SourceFile
  #391 = Utf8               SystemUtils.java
  #392 = Utf8               java/io/File
  #393 = Utf8               org/apache/commons/lang3/SystemUtils
  #394 = Utf8               java.home
  #395 = Class              #622          // java/lang/System
  #396 = NameAndType        #623:#354     // getProperty:(Ljava/lang/String;)Ljava/lang/String;
  #397 = NameAndType        #385:#624     // "<init>":(Ljava/lang/String;)V
  #398 = NameAndType        #320:#280     // IS_OS_WINDOWS:Z
  #399 = Utf8               COMPUTERNAME
  #400 = NameAndType        #625:#354     // getenv:(Ljava/lang/String;)Ljava/lang/String;
  #401 = Utf8               HOSTNAME
  #402 = Utf8               java.io.tmpdir
  #403 = NameAndType        #254:#226     // JAVA_SPECIFICATION_VERSION:Ljava/lang/String;
  #404 = NameAndType        #371:#349     // isJavaVersionMatch:(Ljava/lang/String;Ljava/lang/String;)Z
  #405 = NameAndType        #270:#226     // OS_NAME:Ljava/lang/String;
  #406 = NameAndType        #271:#226     // OS_VERSION:Ljava/lang/String;
  #407 = NameAndType        #373:#374     // isOSMatch:(Ljava/lang/String;Ljava/lang/String;Ljava/lang/String;Ljava/lang/String;)Z
  #408 = NameAndType        #377:#349     // isOSNameMatch:(Ljava/lang/String;Ljava/lang/String;)Z
  #409 = Utf8               java/lang/SecurityException
  #410 = Utf8               user.dir
  #411 = Utf8               user.home
  #412 = Class              #626          // java/lang/Boolean
  #413 = NameAndType        #627:#628     // TRUE:Ljava/lang/Boolean;
  #414 = NameAndType        #629:#340     // toString:()Ljava/lang/String;
  #415 = NameAndType        #240:#226     // JAVA_AWT_HEADLESS:Ljava/lang/String;
  #416 = NameAndType        #630:#631     // equals:(Ljava/lang/Object;)Z
  #417 = NameAndType        #255:#256     // JAVA_SPECIFICATION_VERSION_AS_ENUM:Lorg/apache/commons/lang3/JavaVersion;
  #418 = Class              #632          // org/apache/commons/lang3/JavaVersion
  #419 = NameAndType        #633:#368     // atLeast:(Lorg/apache/commons/lang3/JavaVersion;)Z
  #420 = NameAndType        #634:#368     // atMost:(Lorg/apache/commons/lang3/JavaVersion;)Z
  #421 = NameAndType        #635:#345     // startsWith:(Ljava/lang/String;)Z
  #422 = NameAndType        #378:#349     // isOSVersionMatch:(Ljava/lang/String;Ljava/lang/String;)Z
  #423 = Class              #636          // org/apache/commons/lang3/StringUtils
  #424 = NameAndType        #637:#638     // isEmpty:(Ljava/lang/CharSequence;)Z
  #425 = Utf8               \\.
  #426 = NameAndType        #639:#640     // split:(Ljava/lang/String;)[Ljava/lang/String;
  #427 = Class              #641          // java/lang/Math
  #428 = NameAndType        #642:#643     // min:(II)I
  #429 = NameAndType        #385:#386     // "<init>":()V
  #430 = Utf8               awt.toolkit
  #431 = NameAndType        #353:#354     // getSystemProperty:(Ljava/lang/String;)Ljava/lang/String;
  #432 = NameAndType        #232:#226     // AWT_TOOLKIT:Ljava/lang/String;
  #433 = Utf8               file.encoding
  #434 = NameAndType        #233:#226     // FILE_ENCODING:Ljava/lang/String;
  #435 = Utf8               file.separator
  #436 = NameAndType        #234:#226     // FILE_SEPARATOR:Ljava/lang/String;
  #437 = Utf8               java.awt.fonts
  #438 = NameAndType        #238:#226     // JAVA_AWT_FONTS:Ljava/lang/String;
  #439 = Utf8               java.awt.graphicsenv
  #440 = NameAndType        #239:#226     // JAVA_AWT_GRAPHICSENV:Ljava/lang/String;
  #441 = Utf8               java.awt.headless
  #442 = Utf8               java.awt.printerjob
  #443 = NameAndType        #241:#226     // JAVA_AWT_PRINTERJOB:Ljava/lang/String;
  #444 = Utf8               java.class.path
  #445 = NameAndType        #242:#226     // JAVA_CLASS_PATH:Ljava/lang/String;
  #446 = Utf8               java.class.version
  #447 = NameAndType        #243:#226     // JAVA_CLASS_VERSION:Ljava/lang/String;
  #448 = Utf8               java.compiler
  #449 = NameAndType        #244:#226     // JAVA_COMPILER:Ljava/lang/String;
  #450 = Utf8               java.endorsed.dirs
  #451 = NameAndType        #245:#226     // JAVA_ENDORSED_DIRS:Ljava/lang/String;
  #452 = Utf8               java.ext.dirs
  #453 = NameAndType        #246:#226     // JAVA_EXT_DIRS:Ljava/lang/String;
  #454 = NameAndType        #247:#226     // JAVA_HOME:Ljava/lang/String;
  #455 = NameAndType        #248:#226     // JAVA_IO_TMPDIR:Ljava/lang/String;
  #456 = Utf8               java.library.path
  #457 = NameAndType        #249:#226     // JAVA_LIBRARY_PATH:Ljava/lang/String;
  #458 = Utf8               java.runtime.name
  #459 = NameAndType        #250:#226     // JAVA_RUNTIME_NAME:Ljava/lang/String;
  #460 = Utf8               java.runtime.version
  #461 = NameAndType        #251:#226     // JAVA_RUNTIME_VERSION:Ljava/lang/String;
  #462 = Utf8               java.specification.name
  #463 = NameAndType        #252:#226     // JAVA_SPECIFICATION_NAME:Ljava/lang/String;
  #464 = Utf8               java.specification.vendor
  #465 = NameAndType        #253:#226     // JAVA_SPECIFICATION_VENDOR:Ljava/lang/String;
  #466 = Utf8               java.specification.version
  #467 = NameAndType        #644:#645     // get:(Ljava/lang/String;)Lorg/apache/commons/lang3/JavaVersion;
  #468 = Utf8               java.util.prefs.PreferencesFactory
  #469 = NameAndType        #257:#226     // JAVA_UTIL_PREFS_PREFERENCES_FACTORY:Ljava/lang/String;
  #470 = Utf8               java.vendor
  #471 = NameAndType        #258:#226     // JAVA_VENDOR:Ljava/lang/String;
  #472 = Utf8               java.vendor.url
  #473 = NameAndType        #259:#226     // JAVA_VENDOR_URL:Ljava/lang/String;
  #474 = Utf8               java.version
  #475 = NameAndType        #260:#226     // JAVA_VERSION:Ljava/lang/String;
  #476 = Utf8               java.vm.info
  #477 = NameAndType        #261:#226     // JAVA_VM_INFO:Ljava/lang/String;
  #478 = Utf8               java.vm.name
  #479 = NameAndType        #262:#226     // JAVA_VM_NAME:Ljava/lang/String;
  #480 = Utf8               java.vm.specification.name
  #481 = NameAndType        #263:#226     // JAVA_VM_SPECIFICATION_NAME:Ljava/lang/String;
  #482 = Utf8               java.vm.specification.vendor
  #483 = NameAndType        #264:#226     // JAVA_VM_SPECIFICATION_VENDOR:Ljava/lang/String;
  #484 = Utf8               java.vm.specification.version
  #485 = NameAndType        #265:#226     // JAVA_VM_SPECIFICATION_VERSION:Ljava/lang/String;
  #486 = Utf8               java.vm.vendor
  #487 = NameAndType        #266:#226     // JAVA_VM_VENDOR:Ljava/lang/String;
  #488 = Utf8               java.vm.version
  #489 = NameAndType        #267:#226     // JAVA_VM_VERSION:Ljava/lang/String;
  #490 = Utf8               line.separator
  #491 = NameAndType        #268:#226     // LINE_SEPARATOR:Ljava/lang/String;
  #492 = Utf8               os.arch
  #493 = NameAndType        #269:#226     // OS_ARCH:Ljava/lang/String;
  #494 = Utf8               os.name
  #495 = Utf8               os.version
  #496 = Utf8               path.separator
  #497 = NameAndType        #272:#226     // PATH_SEPARATOR:Ljava/lang/String;
  #498 = Utf8               user.country
  #499 = Utf8               user.region
  #500 = NameAndType        #273:#226     // USER_COUNTRY:Ljava/lang/String;
  #501 = NameAndType        #274:#226     // USER_DIR:Ljava/lang/String;
  #502 = NameAndType        #275:#226     // USER_HOME:Ljava/lang/String;
  #503 = Utf8               user.language
  #504 = NameAndType        #276:#226     // USER_LANGUAGE:Ljava/lang/String;
  #505 = Utf8               user.name
  #506 = NameAndType        #277:#226     // USER_NAME:Ljava/lang/String;
  #507 = Utf8               user.timezone
  #508 = NameAndType        #278:#226     // USER_TIMEZONE:Ljava/lang/String;
  #509 = Utf8               1.1
  #510 = NameAndType        #344:#345     // getJavaVersionMatches:(Ljava/lang/String;)Z
  #511 = NameAndType        #279:#280     // IS_JAVA_1_1:Z
  #512 = Utf8               1.2
  #513 = NameAndType        #281:#280     // IS_JAVA_1_2:Z
  #514 = Utf8               1.3
  #515 = NameAndType        #282:#280     // IS_JAVA_1_3:Z
  #516 = Utf8               1.4
  #517 = NameAndType        #283:#280     // IS_JAVA_1_4:Z
  #518 = Utf8               1.5
  #519 = NameAndType        #284:#280     // IS_JAVA_1_5:Z
  #520 = Utf8               1.6
  #521 = NameAndType        #285:#280     // IS_JAVA_1_6:Z
  #522 = Utf8               1.7
  #523 = NameAndType        #286:#280     // IS_JAVA_1_7:Z
  #524 = Utf8               1.8
  #525 = NameAndType        #287:#280     // IS_JAVA_1_8:Z
  #526 = Utf8               9
  #527 = NameAndType        #288:#280     // IS_JAVA_1_9:Z
  #528 = NameAndType        #289:#280     // IS_JAVA_9:Z
  #529 = Utf8               10
  #530 = NameAndType        #290:#280     // IS_JAVA_10:Z
  #531 = Utf8               11
  #532 = NameAndType        #291:#280     // IS_JAVA_11:Z
  #533 = Utf8               12
  #534 = NameAndType        #292:#280     // IS_JAVA_12:Z
  #535 = Utf8               13
  #536 = NameAndType        #293:#280     // IS_JAVA_13:Z
  #537 = Utf8               AIX
  #538 = NameAndType        #352:#345     // getOsMatchesName:(Ljava/lang/String;)Z
  #539 = NameAndType        #294:#280     // IS_OS_AIX:Z
  #540 = Utf8               HP-UX
  #541 = NameAndType        #295:#280     // IS_OS_HP_UX:Z
  #542 = Utf8               OS/400
  #543 = NameAndType        #296:#280     // IS_OS_400:Z
  #544 = Utf8               Irix
  #545 = NameAndType        #297:#280     // IS_OS_IRIX:Z
  #546 = Utf8               Linux
  #547 = Utf8               LINUX
  #548 = NameAndType        #298:#280     // IS_OS_LINUX:Z
  #549 = Utf8               Mac
  #550 = NameAndType        #299:#280     // IS_OS_MAC:Z
  #551 = Utf8               Mac OS X
  #552 = NameAndType        #300:#280     // IS_OS_MAC_OSX:Z
  #553 = Utf8               10.0
  #554 = NameAndType        #348:#349     // getOsMatches:(Ljava/lang/String;Ljava/lang/String;)Z
  #555 = NameAndType        #301:#280     // IS_OS_MAC_OSX_CHEETAH:Z
  #556 = Utf8               10.1
  #557 = NameAndType        #302:#280     // IS_OS_MAC_OSX_PUMA:Z
  #558 = Utf8               10.2
  #559 = NameAndType        #303:#280     // IS_OS_MAC_OSX_JAGUAR:Z
  #560 = Utf8               10.3
  #561 = NameAndType        #304:#280     // IS_OS_MAC_OSX_PANTHER:Z
  #562 = Utf8               10.4
  #563 = NameAndType        #305:#280     // IS_OS_MAC_OSX_TIGER:Z
  #564 = Utf8               10.5
  #565 = NameAndType        #306:#280     // IS_OS_MAC_OSX_LEOPARD:Z
  #566 = Utf8               10.6
  #567 = NameAndType        #307:#280     // IS_OS_MAC_OSX_SNOW_LEOPARD:Z
  #568 = Utf8               10.7
  #569 = NameAndType        #308:#280     // IS_OS_MAC_OSX_LION:Z
  #570 = Utf8               10.8
  #571 = NameAndType        #309:#280     // IS_OS_MAC_OSX_MOUNTAIN_LION:Z
  #572 = Utf8               10.9
  #573 = NameAndType        #310:#280     // IS_OS_MAC_OSX_MAVERICKS:Z
  #574 = Utf8               10.10
  #575 = NameAndType        #311:#280     // IS_OS_MAC_OSX_YOSEMITE:Z
  #576 = Utf8               10.11
  #577 = NameAndType        #312:#280     // IS_OS_MAC_OSX_EL_CAPITAN:Z
  #578 = Utf8               FreeBSD
  #579 = NameAndType        #313:#280     // IS_OS_FREE_BSD:Z
  #580 = Utf8               OpenBSD
  #581 = NameAndType        #314:#280     // IS_OS_OPEN_BSD:Z
  #582 = Utf8               NetBSD
  #583 = NameAndType        #315:#280     // IS_OS_NET_BSD:Z
  #584 = Utf8               OS/2
  #585 = NameAndType        #316:#280     // IS_OS_OS2:Z
  #586 = Utf8               Solaris
  #587 = NameAndType        #317:#280     // IS_OS_SOLARIS:Z
  #588 = Utf8               SunOS
  #589 = NameAndType        #318:#280     // IS_OS_SUN_OS:Z
  #590 = NameAndType        #319:#280     // IS_OS_UNIX:Z
  #591 = Utf8               Windows
  #592 = Utf8               Windows 2000
  #593 = NameAndType        #321:#280     // IS_OS_WINDOWS_2000:Z
  #594 = Utf8               Windows 2003
  #595 = NameAndType        #322:#280     // IS_OS_WINDOWS_2003:Z
  #596 = Utf8               Windows Server 2008
  #597 = NameAndType        #323:#280     // IS_OS_WINDOWS_2008:Z
  #598 = Utf8               Windows Server 2012
  #599 = NameAndType        #324:#280     // IS_OS_WINDOWS_2012:Z
  #600 = Utf8               Windows 95
  #601 = NameAndType        #325:#280     // IS_OS_WINDOWS_95:Z
  #602 = Utf8               Windows 98
  #603 = NameAndType        #326:#280     // IS_OS_WINDOWS_98:Z
  #604 = Utf8               Windows Me
  #605 = NameAndType        #327:#280     // IS_OS_WINDOWS_ME:Z
  #606 = Utf8               Windows NT
  #607 = NameAndType        #328:#280     // IS_OS_WINDOWS_NT:Z
  #608 = Utf8               Windows XP
  #609 = NameAndType        #329:#280     // IS_OS_WINDOWS_XP:Z
  #610 = Utf8               Windows Vista
  #611 = NameAndType        #330:#280     // IS_OS_WINDOWS_VISTA:Z
  #612 = Utf8               Windows 7
  #613 = NameAndType        #331:#280     // IS_OS_WINDOWS_7:Z
  #614 = Utf8               Windows 8
  #615 = NameAndType        #332:#280     // IS_OS_WINDOWS_8:Z
  #616 = Utf8               Windows 10
  #617 = NameAndType        #333:#280     // IS_OS_WINDOWS_10:Z
  #618 = Utf8               z/OS
  #619 = NameAndType        #334:#280     // IS_OS_ZOS:Z
  #620 = Utf8               java/lang/Object
  #621 = Utf8               java/lang/String
  #622 = Utf8               java/lang/System
  #623 = Utf8               getProperty
  #624 = Utf8               (Ljava/lang/String;)V
  #625 = Utf8               getenv
  #626 = Utf8               java/lang/Boolean
  #627 = Utf8               TRUE
  #628 = Utf8               Ljava/lang/Boolean;
  #629 = Utf8               toString
  #630 = Utf8               equals
  #631 = Utf8               (Ljava/lang/Object;)Z
  #632 = Utf8               org/apache/commons/lang3/JavaVersion
  #633 = Utf8               atLeast
  #634 = Utf8               atMost
  #635 = Utf8               startsWith
  #636 = Utf8               org/apache/commons/lang3/StringUtils
  #637 = Utf8               isEmpty
  #638 = Utf8               (Ljava/lang/CharSequence;)Z
  #639 = Utf8               split
  #640 = Utf8               (Ljava/lang/String;)[Ljava/lang/String;
  #641 = Utf8               java/lang/Math
  #642 = Utf8               min
  #643 = Utf8               (II)I
  #644 = Utf8               get
  #645 = Utf8               (Ljava/lang/String;)Lorg/apache/commons/lang3/JavaVersion;
{
  private static final java.lang.String OS_NAME_WINDOWS_PREFIX;
    descriptor: Ljava/lang/String;
    flags: (0x001a) ACC_PRIVATE, ACC_STATIC, ACC_FINAL
    ConstantValue: String Windows

  private static final java.lang.String USER_HOME_KEY;
    descriptor: Ljava/lang/String;
    flags: (0x001a) ACC_PRIVATE, ACC_STATIC, ACC_FINAL
    ConstantValue: String user.home

  private static final java.lang.String USER_DIR_KEY;
    descriptor: Ljava/lang/String;
    flags: (0x001a) ACC_PRIVATE, ACC_STATIC, ACC_FINAL
    ConstantValue: String user.dir

  private static final java.lang.String JAVA_IO_TMPDIR_KEY;
    descriptor: Ljava/lang/String;
    flags: (0x001a) ACC_PRIVATE, ACC_STATIC, ACC_FINAL
    ConstantValue: String java.io.tmpdir

  private static final java.lang.String JAVA_HOME_KEY;
    descriptor: Ljava/lang/String;
    flags: (0x001a) ACC_PRIVATE, ACC_STATIC, ACC_FINAL
    ConstantValue: String java.home

  public static final java.lang.String AWT_TOOLKIT;
    descriptor: Ljava/lang/String;
    flags: (0x0019) ACC_PUBLIC, ACC_STATIC, ACC_FINAL

  public static final java.lang.String FILE_ENCODING;
    descriptor: Ljava/lang/String;
    flags: (0x0019) ACC_PUBLIC, ACC_STATIC, ACC_FINAL

  public static final java.lang.String FILE_SEPARATOR;
    descriptor: Ljava/lang/String;
    flags: (0x0019) ACC_PUBLIC, ACC_STATIC, ACC_FINAL
    Deprecated: true
    RuntimeVisibleAnnotations:
      0: #237()
        java.lang.Deprecated

  public static final java.lang.String JAVA_AWT_FONTS;
    descriptor: Ljava/lang/String;
    flags: (0x0019) ACC_PUBLIC, ACC_STATIC, ACC_FINAL

  public static final java.lang.String JAVA_AWT_GRAPHICSENV;
    descriptor: Ljava/lang/String;
    flags: (0x0019) ACC_PUBLIC, ACC_STATIC, ACC_FINAL

  public static final java.lang.String JAVA_AWT_HEADLESS;
    descriptor: Ljava/lang/String;
    flags: (0x0019) ACC_PUBLIC, ACC_STATIC, ACC_FINAL

  public static final java.lang.String JAVA_AWT_PRINTERJOB;
    descriptor: Ljava/lang/String;
    flags: (0x0019) ACC_PUBLIC, ACC_STATIC, ACC_FINAL

  public static final java.lang.String JAVA_CLASS_PATH;
    descriptor: Ljava/lang/String;
    flags: (0x0019) ACC_PUBLIC, ACC_STATIC, ACC_FINAL

  public static final java.lang.String JAVA_CLASS_VERSION;
    descriptor: Ljava/lang/String;
    flags: (0x0019) ACC_PUBLIC, ACC_STATIC, ACC_FINAL

  public static final java.lang.String JAVA_COMPILER;
    descriptor: Ljava/lang/String;
    flags: (0x0019) ACC_PUBLIC, ACC_STATIC, ACC_FINAL

  public static final java.lang.String JAVA_ENDORSED_DIRS;
    descriptor: Ljava/lang/String;
    flags: (0x0019) ACC_PUBLIC, ACC_STATIC, ACC_FINAL

  public static final java.lang.String JAVA_EXT_DIRS;
    descriptor: Ljava/lang/String;
    flags: (0x0019) ACC_PUBLIC, ACC_STATIC, ACC_FINAL

  public static final java.lang.String JAVA_HOME;
    descriptor: Ljava/lang/String;
    flags: (0x0019) ACC_PUBLIC, ACC_STATIC, ACC_FINAL

  public static final java.lang.String JAVA_IO_TMPDIR;
    descriptor: Ljava/lang/String;
    flags: (0x0019) ACC_PUBLIC, ACC_STATIC, ACC_FINAL

  public static final java.lang.String JAVA_LIBRARY_PATH;
    descriptor: Ljava/lang/String;
    flags: (0x0019) ACC_PUBLIC, ACC_STATIC, ACC_FINAL

  public static final java.lang.String JAVA_RUNTIME_NAME;
    descriptor: Ljava/lang/String;
    flags: (0x0019) ACC_PUBLIC, ACC_STATIC, ACC_FINAL

  public static final java.lang.String JAVA_RUNTIME_VERSION;
    descriptor: Ljava/lang/String;
    flags: (0x0019) ACC_PUBLIC, ACC_STATIC, ACC_FINAL

  public static final java.lang.String JAVA_SPECIFICATION_NAME;
    descriptor: Ljava/lang/String;
    flags: (0x0019) ACC_PUBLIC, ACC_STATIC, ACC_FINAL

  public static final java.lang.String JAVA_SPECIFICATION_VENDOR;
    descriptor: Ljava/lang/String;
    flags: (0x0019) ACC_PUBLIC, ACC_STATIC, ACC_FINAL

  public static final java.lang.String JAVA_SPECIFICATION_VERSION;
    descriptor: Ljava/lang/String;
    flags: (0x0019) ACC_PUBLIC, ACC_STATIC, ACC_FINAL

  private static final org.apache.commons.lang3.JavaVersion JAVA_SPECIFICATION_VERSION_AS_ENUM;
    descriptor: Lorg/apache/commons/lang3/JavaVersion;
    flags: (0x001a) ACC_PRIVATE, ACC_STATIC, ACC_FINAL

  public static final java.lang.String JAVA_UTIL_PREFS_PREFERENCES_FACTORY;
    descriptor: Ljava/lang/String;
    flags: (0x0019) ACC_PUBLIC, ACC_STATIC, ACC_FINAL

  public static final java.lang.String JAVA_VENDOR;
    descriptor: Ljava/lang/String;
    flags: (0x0019) ACC_PUBLIC, ACC_STATIC, ACC_FINAL

  public static final java.lang.String JAVA_VENDOR_URL;
    descriptor: Ljava/lang/String;
    flags: (0x0019) ACC_PUBLIC, ACC_STATIC, ACC_FINAL

  public static final java.lang.String JAVA_VERSION;
    descriptor: Ljava/lang/String;
    flags: (0x0019) ACC_PUBLIC, ACC_STATIC, ACC_FINAL

  public static final java.lang.String JAVA_VM_INFO;
    descriptor: Ljava/lang/String;
    flags: (0x0019) ACC_PUBLIC, ACC_STATIC, ACC_FINAL

  public static final java.lang.String JAVA_VM_NAME;
    descriptor: Ljava/lang/String;
    flags: (0x0019) ACC_PUBLIC, ACC_STATIC, ACC_FINAL

  public static final java.lang.String JAVA_VM_SPECIFICATION_NAME;
    descriptor: Ljava/lang/String;
    flags: (0x0019) ACC_PUBLIC, ACC_STATIC, ACC_FINAL

  public static final java.lang.String JAVA_VM_SPECIFICATION_VENDOR;
    descriptor: Ljava/lang/String;
    flags: (0x0019) ACC_PUBLIC, ACC_STATIC, ACC_FINAL

  public static final java.lang.String JAVA_VM_SPECIFICATION_VERSION;
    descriptor: Ljava/lang/String;
    flags: (0x0019) ACC_PUBLIC, ACC_STATIC, ACC_FINAL

  public static final java.lang.String JAVA_VM_VENDOR;
    descriptor: Ljava/lang/String;
    flags: (0x0019) ACC_PUBLIC, ACC_STATIC, ACC_FINAL

  public static final java.lang.String JAVA_VM_VERSION;
    descriptor: Ljava/lang/String;
    flags: (0x0019) ACC_PUBLIC, ACC_STATIC, ACC_FINAL

  public static final java.lang.String LINE_SEPARATOR;
    descriptor: Ljava/lang/String;
    flags: (0x0019) ACC_PUBLIC, ACC_STATIC, ACC_FINAL
    Deprecated: true
    RuntimeVisibleAnnotations:
      0: #237()
        java.lang.Deprecated

  public static final java.lang.String OS_ARCH;
    descriptor: Ljava/lang/String;
    flags: (0x0019) ACC_PUBLIC, ACC_STATIC, ACC_FINAL

  public static final java.lang.String OS_NAME;
    descriptor: Ljava/lang/String;
    flags: (0x0019) ACC_PUBLIC, ACC_STATIC, ACC_FINAL

  public static final java.lang.String OS_VERSION;
    descriptor: Ljava/lang/String;
    flags: (0x0019) ACC_PUBLIC, ACC_STATIC, ACC_FINAL

  public static final java.lang.String PATH_SEPARATOR;
    descriptor: Ljava/lang/String;
    flags: (0x0019) ACC_PUBLIC, ACC_STATIC, ACC_FINAL
    Deprecated: true
    RuntimeVisibleAnnotations:
      0: #237()
        java.lang.Deprecated

  public static final java.lang.String USER_COUNTRY;
    descriptor: Ljava/lang/String;
    flags: (0x0019) ACC_PUBLIC, ACC_STATIC, ACC_FINAL

  public static final java.lang.String USER_DIR;
    descriptor: Ljava/lang/String;
    flags: (0x0019) ACC_PUBLIC, ACC_STATIC, ACC_FINAL

  public static final java.lang.String USER_HOME;
    descriptor: Ljava/lang/String;
    flags: (0x0019) ACC_PUBLIC, ACC_STATIC, ACC_FINAL

  public static final java.lang.String USER_LANGUAGE;
    descriptor: Ljava/lang/String;
    flags: (0x0019) ACC_PUBLIC, ACC_STATIC, ACC_FINAL

  public static final java.lang.String USER_NAME;
    descriptor: Ljava/lang/String;
    flags: (0x0019) ACC_PUBLIC, ACC_STATIC, ACC_FINAL

  public static final java.lang.String USER_TIMEZONE;
    descriptor: Ljava/lang/String;
    flags: (0x0019) ACC_PUBLIC, ACC_STATIC, ACC_FINAL

  public static final boolean IS_JAVA_1_1;
    descriptor: Z
    flags: (0x0019) ACC_PUBLIC, ACC_STATIC, ACC_FINAL

  public static final boolean IS_JAVA_1_2;
    descriptor: Z
    flags: (0x0019) ACC_PUBLIC, ACC_STATIC, ACC_FINAL

  public static final boolean IS_JAVA_1_3;
    descriptor: Z
    flags: (0x0019) ACC_PUBLIC, ACC_STATIC, ACC_FINAL

  public static final boolean IS_JAVA_1_4;
    descriptor: Z
    flags: (0x0019) ACC_PUBLIC, ACC_STATIC, ACC_FINAL

  public static final boolean IS_JAVA_1_5;
    descriptor: Z
    flags: (0x0019) ACC_PUBLIC, ACC_STATIC, ACC_FINAL

  public static final boolean IS_JAVA_1_6;
    descriptor: Z
    flags: (0x0019) ACC_PUBLIC, ACC_STATIC, ACC_FINAL

  public static final boolean IS_JAVA_1_7;
    descriptor: Z
    flags: (0x0019) ACC_PUBLIC, ACC_STATIC, ACC_FINAL

  public static final boolean IS_JAVA_1_8;
    descriptor: Z
    flags: (0x0019) ACC_PUBLIC, ACC_STATIC, ACC_FINAL

  public static final boolean IS_JAVA_1_9;
    descriptor: Z
    flags: (0x0019) ACC_PUBLIC, ACC_STATIC, ACC_FINAL
    Deprecated: true
    RuntimeVisibleAnnotations:
      0: #237()
        java.lang.Deprecated

  public static final boolean IS_JAVA_9;
    descriptor: Z
    flags: (0x0019) ACC_PUBLIC, ACC_STATIC, ACC_FINAL

  public static final boolean IS_JAVA_10;
    descriptor: Z
    flags: (0x0019) ACC_PUBLIC, ACC_STATIC, ACC_FINAL

  public static final boolean IS_JAVA_11;
    descriptor: Z
    flags: (0x0019) ACC_PUBLIC, ACC_STATIC, ACC_FINAL

  public static final boolean IS_JAVA_12;
    descriptor: Z
    flags: (0x0019) ACC_PUBLIC, ACC_STATIC, ACC_FINAL

  public static final boolean IS_JAVA_13;
    descriptor: Z
    flags: (0x0019) ACC_PUBLIC, ACC_STATIC, ACC_FINAL

  public static final boolean IS_OS_AIX;
    descriptor: Z
    flags: (0x0019) ACC_PUBLIC, ACC_STATIC, ACC_FINAL

  public static final boolean IS_OS_HP_UX;
    descriptor: Z
    flags: (0x0019) ACC_PUBLIC, ACC_STATIC, ACC_FINAL

  public static final boolean IS_OS_400;
    descriptor: Z
    flags: (0x0019) ACC_PUBLIC, ACC_STATIC, ACC_FINAL

  public static final boolean IS_OS_IRIX;
    descriptor: Z
    flags: (0x0019) ACC_PUBLIC, ACC_STATIC, ACC_FINAL

  public static final boolean IS_OS_LINUX;
    descriptor: Z
    flags: (0x0019) ACC_PUBLIC, ACC_STATIC, ACC_FINAL

  public static final boolean IS_OS_MAC;
    descriptor: Z
    flags: (0x0019) ACC_PUBLIC, ACC_STATIC, ACC_FINAL

  public static final boolean IS_OS_MAC_OSX;
    descriptor: Z
    flags: (0x0019) ACC_PUBLIC, ACC_STATIC, ACC_FINAL

  public static final boolean IS_OS_MAC_OSX_CHEETAH;
    descriptor: Z
    flags: (0x0019) ACC_PUBLIC, ACC_STATIC, ACC_FINAL

  public static final boolean IS_OS_MAC_OSX_PUMA;
    descriptor: Z
    flags: (0x0019) ACC_PUBLIC, ACC_STATIC, ACC_FINAL

  public static final boolean IS_OS_MAC_OSX_JAGUAR;
    descriptor: Z
    flags: (0x0019) ACC_PUBLIC, ACC_STATIC, ACC_FINAL

  public static final boolean IS_OS_MAC_OSX_PANTHER;
    descriptor: Z
    flags: (0x0019) ACC_PUBLIC, ACC_STATIC, ACC_FINAL

  public static final boolean IS_OS_MAC_OSX_TIGER;
    descriptor: Z
    flags: (0x0019) ACC_PUBLIC, ACC_STATIC, ACC_FINAL

  public static final boolean IS_OS_MAC_OSX_LEOPARD;
    descriptor: Z
    flags: (0x0019) ACC_PUBLIC, ACC_STATIC, ACC_FINAL

  public static final boolean IS_OS_MAC_OSX_SNOW_LEOPARD;
    descriptor: Z
    flags: (0x0019) ACC_PUBLIC, ACC_STATIC, ACC_FINAL

  public static final boolean IS_OS_MAC_OSX_LION;
    descriptor: Z
    flags: (0x0019) ACC_PUBLIC, ACC_STATIC, ACC_FINAL

  public static final boolean IS_OS_MAC_OSX_MOUNTAIN_LION;
    descriptor: Z
    flags: (0x0019) ACC_PUBLIC, ACC_STATIC, ACC_FINAL

  public static final boolean IS_OS_MAC_OSX_MAVERICKS;
    descriptor: Z
    flags: (0x0019) ACC_PUBLIC, ACC_STATIC, ACC_FINAL

  public static final boolean IS_OS_MAC_OSX_YOSEMITE;
    descriptor: Z
    flags: (0x0019) ACC_PUBLIC, ACC_STATIC, ACC_FINAL

  public static final boolean IS_OS_MAC_OSX_EL_CAPITAN;
    descriptor: Z
    flags: (0x0019) ACC_PUBLIC, ACC_STATIC, ACC_FINAL

  public static final boolean IS_OS_FREE_BSD;
    descriptor: Z
    flags: (0x0019) ACC_PUBLIC, ACC_STATIC, ACC_FINAL

  public static final boolean IS_OS_OPEN_BSD;
    descriptor: Z
    flags: (0x0019) ACC_PUBLIC, ACC_STATIC, ACC_FINAL

  public static final boolean IS_OS_NET_BSD;
    descriptor: Z
    flags: (0x0019) ACC_PUBLIC, ACC_STATIC, ACC_FINAL

  public static final boolean IS_OS_OS2;
    descriptor: Z
    flags: (0x0019) ACC_PUBLIC, ACC_STATIC, ACC_FINAL

  public static final boolean IS_OS_SOLARIS;
    descriptor: Z
    flags: (0x0019) ACC_PUBLIC, ACC_STATIC, ACC_FINAL

  public static final boolean IS_OS_SUN_OS;
    descriptor: Z
    flags: (0x0019) ACC_PUBLIC, ACC_STATIC, ACC_FINAL

  public static final boolean IS_OS_UNIX;
    descriptor: Z
    flags: (0x0019) ACC_PUBLIC, ACC_STATIC, ACC_FINAL

  public static final boolean IS_OS_WINDOWS;
    descriptor: Z
    flags: (0x0019) ACC_PUBLIC, ACC_STATIC, ACC_FINAL

  public static final boolean IS_OS_WINDOWS_2000;
    descriptor: Z
    flags: (0x0019) ACC_PUBLIC, ACC_STATIC, ACC_FINAL

  public static final boolean IS_OS_WINDOWS_2003;
    descriptor: Z
    flags: (0x0019) ACC_PUBLIC, ACC_STATIC, ACC_FINAL

  public static final boolean IS_OS_WINDOWS_2008;
    descriptor: Z
    flags: (0x0019) ACC_PUBLIC, ACC_STATIC, ACC_FINAL

  public static final boolean IS_OS_WINDOWS_2012;
    descriptor: Z
    flags: (0x0019) ACC_PUBLIC, ACC_STATIC, ACC_FINAL

  public static final boolean IS_OS_WINDOWS_95;
    descriptor: Z
    flags: (0x0019) ACC_PUBLIC, ACC_STATIC, ACC_FINAL

  public static final boolean IS_OS_WINDOWS_98;
    descriptor: Z
    flags: (0x0019) ACC_PUBLIC, ACC_STATIC, ACC_FINAL

  public static final boolean IS_OS_WINDOWS_ME;
    descriptor: Z
    flags: (0x0019) ACC_PUBLIC, ACC_STATIC, ACC_FINAL

  public static final boolean IS_OS_WINDOWS_NT;
    descriptor: Z
    flags: (0x0019) ACC_PUBLIC, ACC_STATIC, ACC_FINAL

  public static final boolean IS_OS_WINDOWS_XP;
    descriptor: Z
    flags: (0x0019) ACC_PUBLIC, ACC_STATIC, ACC_FINAL

  public static final boolean IS_OS_WINDOWS_VISTA;
    descriptor: Z
    flags: (0x0019) ACC_PUBLIC, ACC_STATIC, ACC_FINAL

  public static final boolean IS_OS_WINDOWS_7;
    descriptor: Z
    flags: (0x0019) ACC_PUBLIC, ACC_STATIC, ACC_FINAL

  public static final boolean IS_OS_WINDOWS_8;
    descriptor: Z
    flags: (0x0019) ACC_PUBLIC, ACC_STATIC, ACC_FINAL

  public static final boolean IS_OS_WINDOWS_10;
    descriptor: Z
    flags: (0x0019) ACC_PUBLIC, ACC_STATIC, ACC_FINAL

  public static final boolean IS_OS_ZOS;
    descriptor: Z
    flags: (0x0019) ACC_PUBLIC, ACC_STATIC, ACC_FINAL

  public static java.io.File getJavaHome();
    descriptor: ()Ljava/io/File;
    flags: (0x0009) ACC_PUBLIC, ACC_STATIC
    Code:
      stack=3, locals=0, args_size=0
         0: new           #1                  // class java/io/File
         3: dup
         4: ldc           #3                  // String java.home
         6: invokestatic  #4                  // Method java/lang/System.getProperty:(Ljava/lang/String;)Ljava/lang/String;
         9: invokespecial #5                  // Method java/io/File."<init>":(Ljava/lang/String;)V
        12: areturn
      LineNumberTable:
        line 1543: 0

  public static java.lang.String getHostName();
    descriptor: ()Ljava/lang/String;
    flags: (0x0009) ACC_PUBLIC, ACC_STATIC
    Code:
      stack=1, locals=0, args_size=0
         0: getstatic     #6                  // Field IS_OS_WINDOWS:Z
         3: ifeq          14
         6: ldc           #7                  // String COMPUTERNAME
         8: invokestatic  #8                  // Method java/lang/System.getenv:(Ljava/lang/String;)Ljava/lang/String;
        11: goto          19
        14: ldc           #9                  // String HOSTNAME
        16: invokestatic  #8                  // Method java/lang/System.getenv:(Ljava/lang/String;)Ljava/lang/String;
        19: areturn
      LineNumberTable:
        line 1557: 0
      StackMapTable: number_of_entries = 2
        frame_type = 14 /* same */
        frame_type = 68 /* same_locals_1_stack_item */
          stack = [ class java/lang/String ]

  public static java.io.File getJavaIoTmpDir();
    descriptor: ()Ljava/io/File;
    flags: (0x0009) ACC_PUBLIC, ACC_STATIC
    Code:
      stack=3, locals=0, args_size=0
         0: new           #1                  // class java/io/File
         3: dup
         4: ldc           #10                 // String java.io.tmpdir
         6: invokestatic  #4                  // Method java/lang/System.getProperty:(Ljava/lang/String;)Ljava/lang/String;
         9: invokespecial #5                  // Method java/io/File."<init>":(Ljava/lang/String;)V
        12: areturn
      LineNumberTable:
        line 1572: 0

  private static boolean getJavaVersionMatches(java.lang.String);
    descriptor: (Ljava/lang/String;)Z
    flags: (0x000a) ACC_PRIVATE, ACC_STATIC
    Code:
      stack=2, locals=1, args_size=1
         0: getstatic     #11                 // Field JAVA_SPECIFICATION_VERSION:Ljava/lang/String;
         3: aload_0
         4: invokestatic  #12                 // Method isJavaVersionMatch:(Ljava/lang/String;Ljava/lang/String;)Z
         7: ireturn
      LineNumberTable:
        line 1584: 0
      LocalVariableTable:
        Start  Length  Slot  Name   Signature
            0       8     0 versionPrefix   Ljava/lang/String;

  private static boolean getOsMatches(java.lang.String, java.lang.String);
    descriptor: (Ljava/lang/String;Ljava/lang/String;)Z
    flags: (0x000a) ACC_PRIVATE, ACC_STATIC
    Code:
      stack=4, locals=2, args_size=2
         0: getstatic     #13                 // Field OS_NAME:Ljava/lang/String;
         3: getstatic     #14                 // Field OS_VERSION:Ljava/lang/String;
         6: aload_0
         7: aload_1
         8: invokestatic  #15                 // Method isOSMatch:(Ljava/lang/String;Ljava/lang/String;Ljava/lang/String;Ljava/lang/String;)Z
        11: ireturn
      LineNumberTable:
        line 1595: 0
      LocalVariableTable:
        Start  Length  Slot  Name   Signature
            0      12     0 osNamePrefix   Ljava/lang/String;
            0      12     1 osVersionPrefix   Ljava/lang/String;

  private static boolean getOsMatchesName(java.lang.String);
    descriptor: (Ljava/lang/String;)Z
    flags: (0x000a) ACC_PRIVATE, ACC_STATIC
    Code:
      stack=2, locals=1, args_size=1
         0: getstatic     #13                 // Field OS_NAME:Ljava/lang/String;
         3: aload_0
         4: invokestatic  #16                 // Method isOSNameMatch:(Ljava/lang/String;Ljava/lang/String;)Z
         7: ireturn
      LineNumberTable:
        line 1605: 0
      LocalVariableTable:
        Start  Length  Slot  Name   Signature
            0       8     0 osNamePrefix   Ljava/lang/String;

  private static java.lang.String getSystemProperty(java.lang.String);
    descriptor: (Ljava/lang/String;)Ljava/lang/String;
    flags: (0x000a) ACC_PRIVATE, ACC_STATIC
    Code:
      stack=1, locals=2, args_size=1
         0: aload_0
         1: invokestatic  #4                  // Method java/lang/System.getProperty:(Ljava/lang/String;)Ljava/lang/String;
         4: areturn
         5: astore_1
         6: aconst_null
         7: areturn
      Exception table:
         from    to  target type
             0     4     5   Class java/lang/SecurityException
      LineNumberTable:
        line 1623: 0
        line 1624: 5
        line 1628: 6
      LocalVariableTable:
        Start  Length  Slot  Name   Signature
            6       2     1    ex   Ljava/lang/SecurityException;
            0       8     0 property   Ljava/lang/String;
      StackMapTable: number_of_entries = 1
        frame_type = 69 /* same_locals_1_stack_item */
          stack = [ class java/lang/SecurityException ]

  public static java.lang.String getEnvironmentVariable(java.lang.String, java.lang.String);
    descriptor: (Ljava/lang/String;Ljava/lang/String;)Ljava/lang/String;
    flags: (0x0009) ACC_PUBLIC, ACC_STATIC
    Code:
      stack=1, locals=3, args_size=2
         0: aload_0
         1: invokestatic  #8                  // Method java/lang/System.getenv:(Ljava/lang/String;)Ljava/lang/String;
         4: astore_2
         5: aload_2
         6: ifnonnull     13
         9: aload_1
        10: goto          14
        13: aload_2
        14: areturn
        15: astore_2
        16: aload_1
        17: areturn
      Exception table:
         from    to  target type
             0    14    15   Class java/lang/SecurityException
      LineNumberTable:
        line 1650: 0
        line 1651: 5
        line 1652: 15
        line 1655: 16
      LocalVariableTable:
        Start  Length  Slot  Name   Signature
            5      10     2 value   Ljava/lang/String;
           16       2     2    ex   Ljava/lang/SecurityException;
            0      18     0  name   Ljava/lang/String;
            0      18     1 defaultValue   Ljava/lang/String;
      StackMapTable: number_of_entries = 3
        frame_type = 252 /* append */
          offset_delta = 13
          locals = [ class java/lang/String ]
        frame_type = 64 /* same_locals_1_stack_item */
          stack = [ class java/lang/String ]
        frame_type = 255 /* full_frame */
          offset_delta = 0
          locals = [ class java/lang/String, class java/lang/String ]
          stack = [ class java/lang/SecurityException ]

  public static java.io.File getUserDir();
    descriptor: ()Ljava/io/File;
    flags: (0x0009) ACC_PUBLIC, ACC_STATIC
    Code:
      stack=3, locals=0, args_size=0
         0: new           #1                  // class java/io/File
         3: dup
         4: ldc           #18                 // String user.dir
         6: invokestatic  #4                  // Method java/lang/System.getProperty:(Ljava/lang/String;)Ljava/lang/String;
         9: invokespecial #5                  // Method java/io/File."<init>":(Ljava/lang/String;)V
        12: areturn
      LineNumberTable:
        line 1671: 0

  public static java.io.File getUserHome();
    descriptor: ()Ljava/io/File;
    flags: (0x0009) ACC_PUBLIC, ACC_STATIC
    Code:
      stack=3, locals=0, args_size=0
         0: new           #1                  // class java/io/File
         3: dup
         4: ldc           #19                 // String user.home
         6: invokestatic  #4                  // Method java/lang/System.getProperty:(Ljava/lang/String;)Ljava/lang/String;
         9: invokespecial #5                  // Method java/io/File."<init>":(Ljava/lang/String;)V
        12: areturn
      LineNumberTable:
        line 1686: 0

  public static boolean isJavaAwtHeadless();
    descriptor: ()Z
    flags: (0x0009) ACC_PUBLIC, ACC_STATIC
    Code:
      stack=2, locals=0, args_size=0
         0: getstatic     #20                 // Field java/lang/Boolean.TRUE:Ljava/lang/Boolean;
         3: invokevirtual #21                 // Method java/lang/Boolean.toString:()Ljava/lang/String;
         6: getstatic     #22                 // Field JAVA_AWT_HEADLESS:Ljava/lang/String;
         9: invokevirtual #23                 // Method java/lang/String.equals:(Ljava/lang/Object;)Z
        12: ireturn
      LineNumberTable:
        line 1698: 0

  public static boolean isJavaVersionAtLeast(org.apache.commons.lang3.JavaVersion);
    descriptor: (Lorg/apache/commons/lang3/JavaVersion;)Z
    flags: (0x0009) ACC_PUBLIC, ACC_STATIC
    Code:
      stack=2, locals=1, args_size=1
         0: getstatic     #24                 // Field JAVA_SPECIFICATION_VERSION_AS_ENUM:Lorg/apache/commons/lang3/JavaVersion;
         3: aload_0
         4: invokevirtual #25                 // Method org/apache/commons/lang3/JavaVersion.atLeast:(Lorg/apache/commons/lang3/JavaVersion;)Z
         7: ireturn
      LineNumberTable:
        line 1711: 0
      LocalVariableTable:
        Start  Length  Slot  Name   Signature
            0       8     0 requiredVersion   Lorg/apache/commons/lang3/JavaVersion;

  public static boolean isJavaVersionAtMost(org.apache.commons.lang3.JavaVersion);
    descriptor: (Lorg/apache/commons/lang3/JavaVersion;)Z
    flags: (0x0009) ACC_PUBLIC, ACC_STATIC
    Code:
      stack=2, locals=1, args_size=1
         0: getstatic     #24                 // Field JAVA_SPECIFICATION_VERSION_AS_ENUM:Lorg/apache/commons/lang3/JavaVersion;
         3: aload_0
         4: invokevirtual #26                 // Method org/apache/commons/lang3/JavaVersion.atMost:(Lorg/apache/commons/lang3/JavaVersion;)Z
         7: ireturn
      LineNumberTable:
        line 1727: 0
      LocalVariableTable:
        Start  Length  Slot  Name   Signature
            0       8     0 requiredVersion   Lorg/apache/commons/lang3/JavaVersion;

  static boolean isJavaVersionMatch(java.lang.String, java.lang.String);
    descriptor: (Ljava/lang/String;Ljava/lang/String;)Z
    flags: (0x0008) ACC_STATIC
    Code:
      stack=2, locals=2, args_size=2
         0: aload_0
         1: ifnonnull     6
         4: iconst_0
         5: ireturn
         6: aload_0
         7: aload_1
         8: invokevirtual #27                 // Method java/lang/String.startsWith:(Ljava/lang/String;)Z
        11: ireturn
      LineNumberTable:
        line 1743: 0
        line 1744: 4
        line 1746: 6
      LocalVariableTable:
        Start  Length  Slot  Name   Signature
            0      12     0 version   Ljava/lang/String;
            0      12     1 versionPrefix   Ljava/lang/String;
      StackMapTable: number_of_entries = 1
        frame_type = 6 /* same */

  static boolean isOSMatch(java.lang.String, java.lang.String, java.lang.String, java.lang.String);
    descriptor: (Ljava/lang/String;Ljava/lang/String;Ljava/lang/String;Ljava/lang/String;)Z
    flags: (0x0008) ACC_STATIC
    Code:
      stack=2, locals=4, args_size=4
         0: aload_0
         1: ifnull        8
         4: aload_1
         5: ifnonnull     10
         8: iconst_0
         9: ireturn
        10: aload_0
        11: aload_2
        12: invokestatic  #16                 // Method isOSNameMatch:(Ljava/lang/String;Ljava/lang/String;)Z
        15: ifeq          30
        18: aload_1
        19: aload_3
        20: invokestatic  #28                 // Method isOSVersionMatch:(Ljava/lang/String;Ljava/lang/String;)Z
        23: ifeq          30
        26: iconst_1
        27: goto          31
        30: iconst_0
        31: ireturn
      LineNumberTable:
        line 1762: 0
        line 1763: 8
        line 1765: 10
      LocalVariableTable:
        Start  Length  Slot  Name   Signature
            0      32     0 osName   Ljava/lang/String;
            0      32     1 osVersion   Ljava/lang/String;
            0      32     2 osNamePrefix   Ljava/lang/String;
            0      32     3 osVersionPrefix   Ljava/lang/String;
      StackMapTable: number_of_entries = 4
        frame_type = 8 /* same */
        frame_type = 1 /* same */
        frame_type = 19 /* same */
        frame_type = 64 /* same_locals_1_stack_item */
          stack = [ int ]

  static boolean isOSNameMatch(java.lang.String, java.lang.String);
    descriptor: (Ljava/lang/String;Ljava/lang/String;)Z
    flags: (0x0008) ACC_STATIC
    Code:
      stack=2, locals=2, args_size=2
         0: aload_0
         1: ifnonnull     6
         4: iconst_0
         5: ireturn
         6: aload_0
         7: aload_1
         8: invokevirtual #27                 // Method java/lang/String.startsWith:(Ljava/lang/String;)Z
        11: ireturn
      LineNumberTable:
        line 1779: 0
        line 1780: 4
        line 1782: 6
      LocalVariableTable:
        Start  Length  Slot  Name   Signature
            0      12     0 osName   Ljava/lang/String;
            0      12     1 osNamePrefix   Ljava/lang/String;
      StackMapTable: number_of_entries = 1
        frame_type = 6 /* same */

  static boolean isOSVersionMatch(java.lang.String, java.lang.String);
    descriptor: (Ljava/lang/String;Ljava/lang/String;)Z
    flags: (0x0008) ACC_STATIC
    Code:
      stack=3, locals=5, args_size=2
         0: aload_0
         1: invokestatic  #29                 // Method org/apache/commons/lang3/StringUtils.isEmpty:(Ljava/lang/CharSequence;)Z
         4: ifeq          9
         7: iconst_0
         8: ireturn
         9: aload_1
        10: ldc           #30                 // String \\.
        12: invokevirtual #31                 // Method java/lang/String.split:(Ljava/lang/String;)[Ljava/lang/String;
        15: astore_2
        16: aload_0
        17: ldc           #30                 // String \\.
        19: invokevirtual #31                 // Method java/lang/String.split:(Ljava/lang/String;)[Ljava/lang/String;
        22: astore_3
        23: iconst_0
        24: istore        4
        26: iload         4
        28: aload_2
        29: arraylength
        30: aload_3
        31: arraylength
        32: invokestatic  #32                 // Method java/lang/Math.min:(II)I
        35: if_icmpge     60
        38: aload_2
        39: iload         4
        41: aaload
        42: aload_3
        43: iload         4
        45: aaload
        46: invokevirtual #23                 // Method java/lang/String.equals:(Ljava/lang/Object;)Z
        49: ifne          54
        52: iconst_0
        53: ireturn
        54: iinc          4, 1
        57: goto          26
        60: iconst_1
        61: ireturn
      LineNumberTable:
        line 1796: 0
        line 1797: 7
        line 1801: 9
        line 1802: 16
        line 1803: 23
        line 1804: 38
        line 1805: 52
        line 1803: 54
        line 1808: 60
      LocalVariableTable:
        Start  Length  Slot  Name   Signature
           26      34     4     i   I
            0      62     0 osVersion   Ljava/lang/String;
            0      62     1 osVersionPrefix   Ljava/lang/String;
           16      46     2 versionPrefixParts   [Ljava/lang/String;
           23      39     3 versionParts   [Ljava/lang/String;
      StackMapTable: number_of_entries = 4
        frame_type = 9 /* same */
        frame_type = 254 /* append */
          offset_delta = 16
          locals = [ class "[Ljava/lang/String;", class "[Ljava/lang/String;", int ]
        frame_type = 27 /* same */
        frame_type = 250 /* chop */
          offset_delta = 5

  public org.apache.commons.lang3.SystemUtils();
    descriptor: ()V
    flags: (0x0001) ACC_PUBLIC
    Code:
      stack=1, locals=1, args_size=1
         0: aload_0
         1: invokespecial #33                 // Method java/lang/Object."<init>":()V
         4: return
      LineNumberTable:
        line 1822: 0
        line 1823: 4
      LocalVariableTable:
        Start  Length  Slot  Name   Signature
            0       5     0  this   Lorg/apache/commons/lang3/SystemUtils;

  static {};
    descriptor: ()V
    flags: (0x0008) ACC_STATIC
    Code:
      stack=2, locals=0, args_size=0
         0: ldc           #34                 // String awt.toolkit
         2: invokestatic  #35                 // Method getSystemProperty:(Ljava/lang/String;)Ljava/lang/String;
         5: putstatic     #36                 // Field AWT_TOOLKIT:Ljava/lang/String;
         8: ldc           #37                 // String file.encoding
        10: invokestatic  #35                 // Method getSystemProperty:(Ljava/lang/String;)Ljava/lang/String;
        13: putstatic     #38                 // Field FILE_ENCODING:Ljava/lang/String;
        16: ldc           #39                 // String file.separator
        18: invokestatic  #35                 // Method getSystemProperty:(Ljava/lang/String;)Ljava/lang/String;
        21: putstatic     #40                 // Field FILE_SEPARATOR:Ljava/lang/String;
        24: ldc           #41                 // String java.awt.fonts
        26: invokestatic  #35                 // Method getSystemProperty:(Ljava/lang/String;)Ljava/lang/String;
        29: putstatic     #42                 // Field JAVA_AWT_FONTS:Ljava/lang/String;
        32: ldc           #43                 // String java.awt.graphicsenv
        34: invokestatic  #35                 // Method getSystemProperty:(Ljava/lang/String;)Ljava/lang/String;
        37: putstatic     #44                 // Field JAVA_AWT_GRAPHICSENV:Ljava/lang/String;
        40: ldc           #45                 // String java.awt.headless
        42: invokestatic  #35                 // Method getSystemProperty:(Ljava/lang/String;)Ljava/lang/String;
        45: putstatic     #22                 // Field JAVA_AWT_HEADLESS:Ljava/lang/String;
        48: ldc           #46                 // String java.awt.printerjob
        50: invokestatic  #35                 // Method getSystemProperty:(Ljava/lang/String;)Ljava/lang/String;
        53: putstatic     #47                 // Field JAVA_AWT_PRINTERJOB:Ljava/lang/String;
        56: ldc           #48                 // String java.class.path
        58: invokestatic  #35                 // Method getSystemProperty:(Ljava/lang/String;)Ljava/lang/String;
        61: putstatic     #49                 // Field JAVA_CLASS_PATH:Ljava/lang/String;
        64: ldc           #50                 // String java.class.version
        66: invokestatic  #35                 // Method getSystemProperty:(Ljava/lang/String;)Ljava/lang/String;
        69: putstatic     #51                 // Field JAVA_CLASS_VERSION:Ljava/lang/String;
        72: ldc           #52                 // String java.compiler
        74: invokestatic  #35                 // Method getSystemProperty:(Ljava/lang/String;)Ljava/lang/String;
        77: putstatic     #53                 // Field JAVA_COMPILER:Ljava/lang/String;
        80: ldc           #54                 // String java.endorsed.dirs
        82: invokestatic  #35                 // Method getSystemProperty:(Ljava/lang/String;)Ljava/lang/String;
        85: putstatic     #55                 // Field JAVA_ENDORSED_DIRS:Ljava/lang/String;
        88: ldc           #56                 // String java.ext.dirs
        90: invokestatic  #35                 // Method getSystemProperty:(Ljava/lang/String;)Ljava/lang/String;
        93: putstatic     #57                 // Field JAVA_EXT_DIRS:Ljava/lang/String;
        96: ldc           #3                  // String java.home
        98: invokestatic  #35                 // Method getSystemProperty:(Ljava/lang/String;)Ljava/lang/String;
       101: putstatic     #58                 // Field JAVA_HOME:Ljava/lang/String;
       104: ldc           #10                 // String java.io.tmpdir
       106: invokestatic  #35                 // Method getSystemProperty:(Ljava/lang/String;)Ljava/lang/String;
       109: putstatic     #59                 // Field JAVA_IO_TMPDIR:Ljava/lang/String;
       112: ldc           #60                 // String java.library.path
       114: invokestatic  #35                 // Method getSystemProperty:(Ljava/lang/String;)Ljava/lang/String;
       117: putstatic     #61                 // Field JAVA_LIBRARY_PATH:Ljava/lang/String;
       120: ldc           #62                 // String java.runtime.name
       122: invokestatic  #35                 // Method getSystemProperty:(Ljava/lang/String;)Ljava/lang/String;
       125: putstatic     #63                 // Field JAVA_RUNTIME_NAME:Ljava/lang/String;
       128: ldc           #64                 // String java.runtime.version
       130: invokestatic  #35                 // Method getSystemProperty:(Ljava/lang/String;)Ljava/lang/String;
       133: putstatic     #65                 // Field JAVA_RUNTIME_VERSION:Ljava/lang/String;
       136: ldc           #66                 // String java.specification.name
       138: invokestatic  #35                 // Method getSystemProperty:(Ljava/lang/String;)Ljava/lang/String;
       141: putstatic     #67                 // Field JAVA_SPECIFICATION_NAME:Ljava/lang/String;
       144: ldc           #68                 // String java.specification.vendor
       146: invokestatic  #35                 // Method getSystemProperty:(Ljava/lang/String;)Ljava/lang/String;
       149: putstatic     #69                 // Field JAVA_SPECIFICATION_VENDOR:Ljava/lang/String;
       152: ldc           #70                 // String java.specification.version
       154: invokestatic  #35                 // Method getSystemProperty:(Ljava/lang/String;)Ljava/lang/String;
       157: putstatic     #11                 // Field JAVA_SPECIFICATION_VERSION:Ljava/lang/String;
       160: getstatic     #11                 // Field JAVA_SPECIFICATION_VERSION:Ljava/lang/String;
       163: invokestatic  #71                 // Method org/apache/commons/lang3/JavaVersion.get:(Ljava/lang/String;)Lorg/apache/commons/lang3/JavaVersion;
       166: putstatic     #24                 // Field JAVA_SPECIFICATION_VERSION_AS_ENUM:Lorg/apache/commons/lang3/JavaVersion;
       169: ldc           #72                 // String java.util.prefs.PreferencesFactory
       171: invokestatic  #35                 // Method getSystemProperty:(Ljava/lang/String;)Ljava/lang/String;
       174: putstatic     #73                 // Field JAVA_UTIL_PREFS_PREFERENCES_FACTORY:Ljava/lang/String;
       177: ldc           #74                 // String java.vendor
       179: invokestatic  #35                 // Method getSystemProperty:(Ljava/lang/String;)Ljava/lang/String;
       182: putstatic     #75                 // Field JAVA_VENDOR:Ljava/lang/String;
       185: ldc           #76                 // String java.vendor.url
       187: invokestatic  #35                 // Method getSystemProperty:(Ljava/lang/String;)Ljava/lang/String;
       190: putstatic     #77                 // Field JAVA_VENDOR_URL:Ljava/lang/String;
       193: ldc           #78                 // String java.version
       195: invokestatic  #35                 // Method getSystemProperty:(Ljava/lang/String;)Ljava/lang/String;
       198: putstatic     #79                 // Field JAVA_VERSION:Ljava/lang/String;
       201: ldc           #80                 // String java.vm.info
       203: invokestatic  #35                 // Method getSystemProperty:(Ljava/lang/String;)Ljava/lang/String;
       206: putstatic     #81                 // Field JAVA_VM_INFO:Ljava/lang/String;
       209: ldc           #82                 // String java.vm.name
       211: invokestatic  #35                 // Method getSystemProperty:(Ljava/lang/String;)Ljava/lang/String;
       214: putstatic     #83                 // Field JAVA_VM_NAME:Ljava/lang/String;
       217: ldc           #84                 // String java.vm.specification.name
       219: invokestatic  #35                 // Method getSystemProperty:(Ljava/lang/String;)Ljava/lang/String;
       222: putstatic     #85                 // Field JAVA_VM_SPECIFICATION_NAME:Ljava/lang/String;
       225: ldc           #86                 // String java.vm.specification.vendor
       227: invokestatic  #35                 // Method getSystemProperty:(Ljava/lang/String;)Ljava/lang/String;
       230: putstatic     #87                 // Field JAVA_VM_SPECIFICATION_VENDOR:Ljava/lang/String;
       233: ldc           #88                 // String java.vm.specification.version
       235: invokestatic  #35                 // Method getSystemProperty:(Ljava/lang/String;)Ljava/lang/String;
       238: putstatic     #89                 // Field JAVA_VM_SPECIFICATION_VERSION:Ljava/lang/String;
       241: ldc           #90                 // String java.vm.vendor
       243: invokestatic  #35                 // Method getSystemProperty:(Ljava/lang/String;)Ljava/lang/String;
       246: putstatic     #91                 // Field JAVA_VM_VENDOR:Ljava/lang/String;
       249: ldc           #92                 // String java.vm.version
       251: invokestatic  #35                 // Method getSystemProperty:(Ljava/lang/String;)Ljava/lang/String;
       254: putstatic     #93                 // Field JAVA_VM_VERSION:Ljava/lang/String;
       257: ldc           #94                 // String line.separator
       259: invokestatic  #35                 // Method getSystemProperty:(Ljava/lang/String;)Ljava/lang/String;
       262: putstatic     #95                 // Field LINE_SEPARATOR:Ljava/lang/String;
       265: ldc           #96                 // String os.arch
       267: invokestatic  #35                 // Method getSystemProperty:(Ljava/lang/String;)Ljava/lang/String;
       270: putstatic     #97                 // Field OS_ARCH:Ljava/lang/String;
       273: ldc           #98                 // String os.name
       275: invokestatic  #35                 // Method getSystemProperty:(Ljava/lang/String;)Ljava/lang/String;
       278: putstatic     #13                 // Field OS_NAME:Ljava/lang/String;
       281: ldc           #99                 // String os.version
       283: invokestatic  #35                 // Method getSystemProperty:(Ljava/lang/String;)Ljava/lang/String;
       286: putstatic     #14                 // Field OS_VERSION:Ljava/lang/String;
       289: ldc           #100                // String path.separator
       291: invokestatic  #35                 // Method getSystemProperty:(Ljava/lang/String;)Ljava/lang/String;
       294: putstatic     #101                // Field PATH_SEPARATOR:Ljava/lang/String;
       297: ldc           #102                // String user.country
       299: invokestatic  #35                 // Method getSystemProperty:(Ljava/lang/String;)Ljava/lang/String;
       302: ifnonnull     313
       305: ldc           #103                // String user.region
       307: invokestatic  #35                 // Method getSystemProperty:(Ljava/lang/String;)Ljava/lang/String;
       310: goto          318
       313: ldc           #102                // String user.country
       315: invokestatic  #35                 // Method getSystemProperty:(Ljava/lang/String;)Ljava/lang/String;
       318: putstatic     #104                // Field USER_COUNTRY:Ljava/lang/String;
       321: ldc           #18                 // String user.dir
       323: invokestatic  #35                 // Method getSystemProperty:(Ljava/lang/String;)Ljava/lang/String;
       326: putstatic     #105                // Field USER_DIR:Ljava/lang/String;
       329: ldc           #19                 // String user.home
       331: invokestatic  #35                 // Method getSystemProperty:(Ljava/lang/String;)Ljava/lang/String;
       334: putstatic     #106                // Field USER_HOME:Ljava/lang/String;
       337: ldc           #107                // String user.language
       339: invokestatic  #35                 // Method getSystemProperty:(Ljava/lang/String;)Ljava/lang/String;
       342: putstatic     #108                // Field USER_LANGUAGE:Ljava/lang/String;
       345: ldc           #109                // String user.name
       347: invokestatic  #35                 // Method getSystemProperty:(Ljava/lang/String;)Ljava/lang/String;
       350: putstatic     #110                // Field USER_NAME:Ljava/lang/String;
       353: ldc           #111                // String user.timezone
       355: invokestatic  #35                 // Method getSystemProperty:(Ljava/lang/String;)Ljava/lang/String;
       358: putstatic     #112                // Field USER_TIMEZONE:Ljava/lang/String;
       361: ldc           #113                // String 1.1
       363: invokestatic  #114                // Method getJavaVersionMatches:(Ljava/lang/String;)Z
       366: putstatic     #115                // Field IS_JAVA_1_1:Z
       369: ldc           #116                // String 1.2
       371: invokestatic  #114                // Method getJavaVersionMatches:(Ljava/lang/String;)Z
       374: putstatic     #117                // Field IS_JAVA_1_2:Z
       377: ldc           #118                // String 1.3
       379: invokestatic  #114                // Method getJavaVersionMatches:(Ljava/lang/String;)Z
       382: putstatic     #119                // Field IS_JAVA_1_3:Z
       385: ldc           #120                // String 1.4
       387: invokestatic  #114                // Method getJavaVersionMatches:(Ljava/lang/String;)Z
       390: putstatic     #121                // Field IS_JAVA_1_4:Z
       393: ldc           #122                // String 1.5
       395: invokestatic  #114                // Method getJavaVersionMatches:(Ljava/lang/String;)Z
       398: putstatic     #123                // Field IS_JAVA_1_5:Z
       401: ldc           #124                // String 1.6
       403: invokestatic  #114                // Method getJavaVersionMatches:(Ljava/lang/String;)Z
       406: putstatic     #125                // Field IS_JAVA_1_6:Z
       409: ldc           #126                // String 1.7
       411: invokestatic  #114                // Method getJavaVersionMatches:(Ljava/lang/String;)Z
       414: putstatic     #127                // Field IS_JAVA_1_7:Z
       417: ldc           #128                // String 1.8
       419: invokestatic  #114                // Method getJavaVersionMatches:(Ljava/lang/String;)Z
       422: putstatic     #129                // Field IS_JAVA_1_8:Z
       425: ldc           #130                // String 9
       427: invokestatic  #114                // Method getJavaVersionMatches:(Ljava/lang/String;)Z
       430: putstatic     #131                // Field IS_JAVA_1_9:Z
       433: ldc           #130                // String 9
       435: invokestatic  #114                // Method getJavaVersionMatches:(Ljava/lang/String;)Z
       438: putstatic     #132                // Field IS_JAVA_9:Z
       441: ldc           #133                // String 10
       443: invokestatic  #114                // Method getJavaVersionMatches:(Ljava/lang/String;)Z
       446: putstatic     #134                // Field IS_JAVA_10:Z
       449: ldc           #135                // String 11
       451: invokestatic  #114                // Method getJavaVersionMatches:(Ljava/lang/String;)Z
       454: putstatic     #136                // Field IS_JAVA_11:Z
       457: ldc           #137                // String 12
       459: invokestatic  #114                // Method getJavaVersionMatches:(Ljava/lang/String;)Z
       462: putstatic     #138                // Field IS_JAVA_12:Z
       465: ldc           #139                // String 13
       467: invokestatic  #114                // Method getJavaVersionMatches:(Ljava/lang/String;)Z
       470: putstatic     #140                // Field IS_JAVA_13:Z
       473: ldc           #141                // String AIX
       475: invokestatic  #142                // Method getOsMatchesName:(Ljava/lang/String;)Z
       478: putstatic     #143                // Field IS_OS_AIX:Z
       481: ldc           #144                // String HP-UX
       483: invokestatic  #142                // Method getOsMatchesName:(Ljava/lang/String;)Z
       486: putstatic     #145                // Field IS_OS_HP_UX:Z
       489: ldc           #146                // String OS/400
       491: invokestatic  #142                // Method getOsMatchesName:(Ljava/lang/String;)Z
       494: putstatic     #147                // Field IS_OS_400:Z
       497: ldc           #148                // String Irix
       499: invokestatic  #142                // Method getOsMatchesName:(Ljava/lang/String;)Z
       502: putstatic     #149                // Field IS_OS_IRIX:Z
       505: ldc           #150                // String Linux
       507: invokestatic  #142                // Method getOsMatchesName:(Ljava/lang/String;)Z
       510: ifne          521
       513: ldc           #151                // String LINUX
       515: invokestatic  #142                // Method getOsMatchesName:(Ljava/lang/String;)Z
       518: ifeq          525
       521: iconst_1
       522: goto          526
       525: iconst_0
       526: putstatic     #152                // Field IS_OS_LINUX:Z
       529: ldc           #153                // String Mac
       531: invokestatic  #142                // Method getOsMatchesName:(Ljava/lang/String;)Z
       534: putstatic     #154                // Field IS_OS_MAC:Z
       537: ldc           #155                // String Mac OS X
       539: invokestatic  #142                // Method getOsMatchesName:(Ljava/lang/String;)Z
       542: putstatic     #156                // Field IS_OS_MAC_OSX:Z
       545: ldc           #155                // String Mac OS X
       547: ldc           #157                // String 10.0
       549: invokestatic  #158                // Method getOsMatches:(Ljava/lang/String;Ljava/lang/String;)Z
       552: putstatic     #159                // Field IS_OS_MAC_OSX_CHEETAH:Z
       555: ldc           #155                // String Mac OS X
       557: ldc           #160                // String 10.1
       559: invokestatic  #158                // Method getOsMatches:(Ljava/lang/String;Ljava/lang/String;)Z
       562: putstatic     #161                // Field IS_OS_MAC_OSX_PUMA:Z
       565: ldc           #155                // String Mac OS X
       567: ldc           #162                // String 10.2
       569: invokestatic  #158                // Method getOsMatches:(Ljava/lang/String;Ljava/lang/String;)Z
       572: putstatic     #163                // Field IS_OS_MAC_OSX_JAGUAR:Z
       575: ldc           #155                // String Mac OS X
       577: ldc           #164                // String 10.3
       579: invokestatic  #158                // Method getOsMatches:(Ljava/lang/String;Ljava/lang/String;)Z
       582: putstatic     #165                // Field IS_OS_MAC_OSX_PANTHER:Z
       585: ldc           #155                // String Mac OS X
       587: ldc           #166                // String 10.4
       589: invokestatic  #158                // Method getOsMatches:(Ljava/lang/String;Ljava/lang/String;)Z
       592: putstatic     #167                // Field IS_OS_MAC_OSX_TIGER:Z
       595: ldc           #155                // String Mac OS X
       597: ldc           #168                // String 10.5
       599: invokestatic  #158                // Method getOsMatches:(Ljava/lang/String;Ljava/lang/String;)Z
       602: putstatic     #169                // Field IS_OS_MAC_OSX_LEOPARD:Z
       605: ldc           #155                // String Mac OS X
       607: ldc           #170                // String 10.6
       609: invokestatic  #158                // Method getOsMatches:(Ljava/lang/String;Ljava/lang/String;)Z
       612: putstatic     #171                // Field IS_OS_MAC_OSX_SNOW_LEOPARD:Z
       615: ldc           #155                // String Mac OS X
       617: ldc           #172                // String 10.7
       619: invokestatic  #158                // Method getOsMatches:(Ljava/lang/String;Ljava/lang/String;)Z
       622: putstatic     #173                // Field IS_OS_MAC_OSX_LION:Z
       625: ldc           #155                // String Mac OS X
       627: ldc           #174                // String 10.8
       629: invokestatic  #158                // Method getOsMatches:(Ljava/lang/String;Ljava/lang/String;)Z
       632: putstatic     #175                // Field IS_OS_MAC_OSX_MOUNTAIN_LION:Z
       635: ldc           #155                // String Mac OS X
       637: ldc           #176                // String 10.9
       639: invokestatic  #158                // Method getOsMatches:(Ljava/lang/String;Ljava/lang/String;)Z
       642: putstatic     #177                // Field IS_OS_MAC_OSX_MAVERICKS:Z
       645: ldc           #155                // String Mac OS X
       647: ldc           #178                // String 10.10
       649: invokestatic  #158                // Method getOsMatches:(Ljava/lang/String;Ljava/lang/String;)Z
       652: putstatic     #179                // Field IS_OS_MAC_OSX_YOSEMITE:Z
       655: ldc           #155                // String Mac OS X
       657: ldc           #180                // String 10.11
       659: invokestatic  #158                // Method getOsMatches:(Ljava/lang/String;Ljava/lang/String;)Z
       662: putstatic     #181                // Field IS_OS_MAC_OSX_EL_CAPITAN:Z
       665: ldc           #182                // String FreeBSD
       667: invokestatic  #142                // Method getOsMatchesName:(Ljava/lang/String;)Z
       670: putstatic     #183                // Field IS_OS_FREE_BSD:Z
       673: ldc           #184                // String OpenBSD
       675: invokestatic  #142                // Method getOsMatchesName:(Ljava/lang/String;)Z
       678: putstatic     #185                // Field IS_OS_OPEN_BSD:Z
       681: ldc           #186                // String NetBSD
       683: invokestatic  #142                // Method getOsMatchesName:(Ljava/lang/String;)Z
       686: putstatic     #187                // Field IS_OS_NET_BSD:Z
       689: ldc           #188                // String OS/2
       691: invokestatic  #142                // Method getOsMatchesName:(Ljava/lang/String;)Z
       694: putstatic     #189                // Field IS_OS_OS2:Z
       697: ldc           #190                // String Solaris
       699: invokestatic  #142                // Method getOsMatchesName:(Ljava/lang/String;)Z
       702: putstatic     #191                // Field IS_OS_SOLARIS:Z
       705: ldc           #192                // String SunOS
       707: invokestatic  #142                // Method getOsMatchesName:(Ljava/lang/String;)Z
       710: putstatic     #193                // Field IS_OS_SUN_OS:Z
       713: getstatic     #143                // Field IS_OS_AIX:Z
       716: ifne          773
       719: getstatic     #145                // Field IS_OS_HP_UX:Z
       722: ifne          773
       725: getstatic     #149                // Field IS_OS_IRIX:Z
       728: ifne          773
       731: getstatic     #152                // Field IS_OS_LINUX:Z
       734: ifne          773
       737: getstatic     #156                // Field IS_OS_MAC_OSX:Z
       740: ifne          773
       743: getstatic     #191                // Field IS_OS_SOLARIS:Z
       746: ifne          773
       749: getstatic     #193                // Field IS_OS_SUN_OS:Z
       752: ifne          773
       755: getstatic     #183                // Field IS_OS_FREE_BSD:Z
       758: ifne          773
       761: getstatic     #185                // Field IS_OS_OPEN_BSD:Z
       764: ifne          773
       767: getstatic     #187                // Field IS_OS_NET_BSD:Z
       770: ifeq          777
       773: iconst_1
       774: goto          778
       777: iconst_0
       778: putstatic     #194                // Field IS_OS_UNIX:Z
       781: ldc           #195                // String Windows
       783: invokestatic  #142                // Method getOsMatchesName:(Ljava/lang/String;)Z
       786: putstatic     #6                  // Field IS_OS_WINDOWS:Z
       789: ldc           #196                // String Windows 2000
       791: invokestatic  #142                // Method getOsMatchesName:(Ljava/lang/String;)Z
       794: putstatic     #197                // Field IS_OS_WINDOWS_2000:Z
       797: ldc           #198                // String Windows 2003
       799: invokestatic  #142                // Method getOsMatchesName:(Ljava/lang/String;)Z
       802: putstatic     #199                // Field IS_OS_WINDOWS_2003:Z
       805: ldc           #200                // String Windows Server 2008
       807: invokestatic  #142                // Method getOsMatchesName:(Ljava/lang/String;)Z
       810: putstatic     #201                // Field IS_OS_WINDOWS_2008:Z
       813: ldc           #202                // String Windows Server 2012
       815: invokestatic  #142                // Method getOsMatchesName:(Ljava/lang/String;)Z
       818: putstatic     #203                // Field IS_OS_WINDOWS_2012:Z
       821: ldc           #204                // String Windows 95
       823: invokestatic  #142                // Method getOsMatchesName:(Ljava/lang/String;)Z
       826: putstatic     #205                // Field IS_OS_WINDOWS_95:Z
       829: ldc           #206                // String Windows 98
       831: invokestatic  #142                // Method getOsMatchesName:(Ljava/lang/String;)Z
       834: putstatic     #207                // Field IS_OS_WINDOWS_98:Z
       837: ldc           #208                // String Windows Me
       839: invokestatic  #142                // Method getOsMatchesName:(Ljava/lang/String;)Z
       842: putstatic     #209                // Field IS_OS_WINDOWS_ME:Z
       845: ldc           #210                // String Windows NT
       847: invokestatic  #142                // Method getOsMatchesName:(Ljava/lang/String;)Z
       850: putstatic     #211                // Field IS_OS_WINDOWS_NT:Z
       853: ldc           #212                // String Windows XP
       855: invokestatic  #142                // Method getOsMatchesName:(Ljava/lang/String;)Z
       858: putstatic     #213                // Field IS_OS_WINDOWS_XP:Z
       861: ldc           #214                // String Windows Vista
       863: invokestatic  #142                // Method getOsMatchesName:(Ljava/lang/String;)Z
       866: putstatic     #215                // Field IS_OS_WINDOWS_VISTA:Z
       869: ldc           #216                // String Windows 7
       871: invokestatic  #142                // Method getOsMatchesName:(Ljava/lang/String;)Z
       874: putstatic     #217                // Field IS_OS_WINDOWS_7:Z
       877: ldc           #218                // String Windows 8
       879: invokestatic  #142                // Method getOsMatchesName:(Ljava/lang/String;)Z
       882: putstatic     #219                // Field IS_OS_WINDOWS_8:Z
       885: ldc           #220                // String Windows 10
       887: invokestatic  #142                // Method getOsMatchesName:(Ljava/lang/String;)Z
       890: putstatic     #221                // Field IS_OS_WINDOWS_10:Z
       893: ldc           #222                // String z/OS
       895: invokestatic  #142                // Method getOsMatchesName:(Ljava/lang/String;)Z
       898: putstatic     #223                // Field IS_OS_ZOS:Z
       901: return
      LineNumberTable:
        line 88: 0
        line 110: 8
        line 137: 16
        line 155: 24
        line 173: 32
        line 194: 40
        line 212: 48
        line 230: 56
        line 248: 64
        line 267: 72
        line 285: 80
        line 303: 88
        line 321: 96
        line 339: 104
        line 357: 112
        line 376: 120
        line 395: 128
        line 413: 136
        line 431: 144
        line 449: 152
        line 450: 160
        line 469: 169
        line 470: 171
        line 488: 177
        line 506: 185
        line 524: 193
        line 543: 201
        line 561: 209
        line 579: 217
        line 597: 225
        line 615: 233
        line 633: 241
        line 651: 249
        line 671: 257
        line 689: 265
        line 707: 273
        line 725: 281
        line 746: 289
        line 766: 297
        line 767: 305
        line 785: 321
        line 803: 329
        line 822: 337
        line 840: 345
        line 858: 353
        line 873: 361
        line 883: 369
        line 893: 377
        line 903: 385
        line 913: 393
        line 923: 401
        line 935: 409
        line 947: 417
        line 962: 425
        line 974: 433
        line 986: 441
        line 998: 449
        line 1010: 457
        line 1022: 465
        line 1042: 473
        line 1054: 481
        line 1066: 489
        line 1078: 497
        line 1090: 505
        line 1102: 529
        line 1114: 537
        line 1126: 545
        line 1138: 555
        line 1150: 565
        line 1162: 575
        line 1174: 585
        line 1186: 595
        line 1198: 605
        line 1210: 615
        line 1222: 625
        line 1234: 635
        line 1246: 645
        line 1258: 655
        line 1270: 665
        line 1282: 673
        line 1294: 681
        line 1306: 689
        line 1318: 697
        line 1330: 705
        line 1342: 713
        line 1355: 781
        line 1367: 789
        line 1379: 797
        line 1391: 805
        line 1403: 813
        line 1415: 821
        line 1427: 829
        line 1439: 837
        line 1451: 845
        line 1463: 853
        line 1476: 861
        line 1488: 869
        line 1500: 877
        line 1512: 885
        line 1529: 893
      StackMapTable: number_of_entries = 8
        frame_type = 251 /* same_frame_extended */
          offset_delta = 313
        frame_type = 68 /* same_locals_1_stack_item */
          stack = [ class java/lang/String ]
        frame_type = 251 /* same_frame_extended */
          offset_delta = 202
        frame_type = 3 /* same */
        frame_type = 64 /* same_locals_1_stack_item */
          stack = [ int ]
        frame_type = 251 /* same_frame_extended */
          offset_delta = 246
        frame_type = 3 /* same */
        frame_type = 64 /* same_locals_1_stack_item */
          stack = [ int ]
}
SourceFile: "SystemUtils.java"
