Classfile /Users/mw/Projects/slang-braindump/.jar/jar11/assemble/slang-braindump/assemble/content/concurrentrefhashmap/ConcurrentReferenceHashMap$Segment.class
  Last modified May 29, 2022; size 7550 bytes
  SHA-256 checksum cbffeae8447f25ca17bd1e5c224f97980bb79c824bf7bbcf793af737528c2f09
  Compiled from "ConcurrentReferenceHashMap.java"
final class concurrentrefhashmap.ConcurrentReferenceHashMap$Segment<K extends java.lang.Object, V extends java.lang.Object> extends java.util.concurrent.locks.ReentrantLock implements java.io.Serializable
  minor version: 0
  major version: 52
  flags: (0x0030) ACC_FINAL, ACC_SUPER
  this_class: #9                          // concurrentrefhashmap/ConcurrentReferenceHashMap$Segment
  super_class: #42                        // java/util/concurrent/locks/ReentrantLock
  interfaces: 1, fields: 10, methods: 17, attributes: 3
Constant pool:
    #1 = Class              #122          // concurrentrefhashmap/ConcurrentReferenceHashMap
    #2 = Methodref          #42.#123      // java/util/concurrent/locks/ReentrantLock."<init>":()V
    #3 = Fieldref           #9.#124       // concurrentrefhashmap/ConcurrentReferenceHashMap$Segment.loadFactor:F
    #4 = Fieldref           #9.#125       // concurrentrefhashmap/ConcurrentReferenceHashMap$Segment.keyType:Lconcurrentrefhashmap/ConcurrentReferenceHashMap$ReferenceType;
    #5 = Fieldref           #9.#126       // concurrentrefhashmap/ConcurrentReferenceHashMap$Segment.valueType:Lconcurrentrefhashmap/ConcurrentReferenceHashMap$ReferenceType;
    #6 = Fieldref           #9.#127       // concurrentrefhashmap/ConcurrentReferenceHashMap$Segment.identityComparisons:Z
    #7 = Methodref          #16.#128      // concurrentrefhashmap/ConcurrentReferenceHashMap$HashEntry.newArray:(I)[Lconcurrentrefhashmap/ConcurrentReferenceHashMap$HashEntry;
    #8 = Methodref          #9.#129       // concurrentrefhashmap/ConcurrentReferenceHashMap$Segment.setTable:([Lconcurrentrefhashmap/ConcurrentReferenceHashMap$HashEntry;)V
    #9 = Class              #130          // concurrentrefhashmap/ConcurrentReferenceHashMap$Segment
   #10 = Methodref          #97.#131      // java/lang/Object.equals:(Ljava/lang/Object;)Z
   #11 = Fieldref           #9.#132       // concurrentrefhashmap/ConcurrentReferenceHashMap$Segment.threshold:I
   #12 = Fieldref           #9.#133       // concurrentrefhashmap/ConcurrentReferenceHashMap$Segment.table:[Lconcurrentrefhashmap/ConcurrentReferenceHashMap$HashEntry;
   #13 = Class              #134          // java/lang/ref/ReferenceQueue
   #14 = Methodref          #13.#123      // java/lang/ref/ReferenceQueue."<init>":()V
   #15 = Fieldref           #9.#135       // concurrentrefhashmap/ConcurrentReferenceHashMap$Segment.refQueue:Ljava/lang/ref/ReferenceQueue;
   #16 = Class              #136          // concurrentrefhashmap/ConcurrentReferenceHashMap$HashEntry
   #17 = Methodref          #16.#137      // concurrentrefhashmap/ConcurrentReferenceHashMap$HashEntry."<init>":(Ljava/lang/Object;ILconcurrentrefhashmap/ConcurrentReferenceHashMap$HashEntry;Ljava/lang/Object;Lconcurrentrefhashmap/ConcurrentReferenceHashMap$ReferenceType;Lconcurrentrefhashmap/ConcurrentReferenceHashMap$ReferenceType;Ljava/lang/ref/ReferenceQueue;)V
   #18 = Methodref          #9.#138       // concurrentrefhashmap/ConcurrentReferenceHashMap$Segment.lock:()V
   #19 = Methodref          #9.#139       // concurrentrefhashmap/ConcurrentReferenceHashMap$Segment.removeStale:()V
   #20 = Methodref          #16.#140      // concurrentrefhashmap/ConcurrentReferenceHashMap$HashEntry.value:()Ljava/lang/Object;
   #21 = Methodref          #9.#141       // concurrentrefhashmap/ConcurrentReferenceHashMap$Segment.unlock:()V
   #22 = Fieldref           #9.#142       // concurrentrefhashmap/ConcurrentReferenceHashMap$Segment.count:I
   #23 = Methodref          #9.#143       // concurrentrefhashmap/ConcurrentReferenceHashMap$Segment.getFirst:(I)Lconcurrentrefhashmap/ConcurrentReferenceHashMap$HashEntry;
   #24 = Fieldref           #16.#144      // concurrentrefhashmap/ConcurrentReferenceHashMap$HashEntry.hash:I
   #25 = Methodref          #16.#145      // concurrentrefhashmap/ConcurrentReferenceHashMap$HashEntry.key:()Ljava/lang/Object;
   #26 = Methodref          #9.#146       // concurrentrefhashmap/ConcurrentReferenceHashMap$Segment.keyEq:(Ljava/lang/Object;Ljava/lang/Object;)Z
   #27 = Fieldref           #16.#147      // concurrentrefhashmap/ConcurrentReferenceHashMap$HashEntry.valueRef:Ljava/lang/Object;
   #28 = Methodref          #16.#148      // concurrentrefhashmap/ConcurrentReferenceHashMap$HashEntry.dereferenceValue:(Ljava/lang/Object;)Ljava/lang/Object;
   #29 = Methodref          #9.#149       // concurrentrefhashmap/ConcurrentReferenceHashMap$Segment.readValueUnderLock:(Lconcurrentrefhashmap/ConcurrentReferenceHashMap$HashEntry;)Ljava/lang/Object;
   #30 = Fieldref           #16.#150      // concurrentrefhashmap/ConcurrentReferenceHashMap$HashEntry.next:Lconcurrentrefhashmap/ConcurrentReferenceHashMap$HashEntry;
   #31 = Methodref          #16.#151      // concurrentrefhashmap/ConcurrentReferenceHashMap$HashEntry.setValue:(Ljava/lang/Object;Lconcurrentrefhashmap/ConcurrentReferenceHashMap$ReferenceType;Ljava/lang/ref/ReferenceQueue;)V
   #32 = Methodref          #9.#152       // concurrentrefhashmap/ConcurrentReferenceHashMap$Segment.rehash:()I
   #33 = Fieldref           #9.#153       // concurrentrefhashmap/ConcurrentReferenceHashMap$Segment.modCount:I
   #34 = Methodref          #9.#154       // concurrentrefhashmap/ConcurrentReferenceHashMap$Segment.newHashEntry:(Ljava/lang/Object;ILconcurrentrefhashmap/ConcurrentReferenceHashMap$HashEntry;Ljava/lang/Object;)Lconcurrentrefhashmap/ConcurrentReferenceHashMap$HashEntry;
   #35 = Integer            1073741824
   #36 = Fieldref           #16.#155      // concurrentrefhashmap/ConcurrentReferenceHashMap$HashEntry.keyRef:Ljava/lang/Object;
   #37 = Methodref          #13.#156      // java/lang/ref/ReferenceQueue.poll:()Ljava/lang/ref/Reference;
   #38 = Class              #157          // concurrentrefhashmap/ConcurrentReferenceHashMap$KeyReference
   #39 = InterfaceMethodref #38.#159      // concurrentrefhashmap/ConcurrentReferenceHashMap$KeyReference.keyRef:()Ljava/lang/Object;
   #40 = InterfaceMethodref #38.#160      // concurrentrefhashmap/ConcurrentReferenceHashMap$KeyReference.keyHash:()I
   #41 = Methodref          #9.#161       // concurrentrefhashmap/ConcurrentReferenceHashMap$Segment.remove:(Ljava/lang/Object;ILjava/lang/Object;Z)Ljava/lang/Object;
   #42 = Class              #162          // java/util/concurrent/locks/ReentrantLock
   #43 = Class              #163          // java/io/Serializable
   #44 = Utf8               serialVersionUID
   #45 = Utf8               J
   #46 = Utf8               ConstantValue
   #47 = Long               2249069246763182397l
   #49 = Utf8               count
   #50 = Utf8               I
   #51 = Utf8               modCount
   #52 = Utf8               threshold
   #53 = Utf8               table
   #54 = Utf8               HashEntry
   #55 = Utf8               InnerClasses
   #56 = Utf8               [Lconcurrentrefhashmap/ConcurrentReferenceHashMap$HashEntry;
   #57 = Utf8               Signature
   #58 = Utf8               [Lconcurrentrefhashmap/ConcurrentReferenceHashMap$HashEntry<TK;TV;>;
   #59 = Utf8               loadFactor
   #60 = Utf8               F
   #61 = Utf8               refQueue
   #62 = Utf8               Ljava/lang/ref/ReferenceQueue;
   #63 = Utf8               Ljava/lang/ref/ReferenceQueue<Ljava/lang/Object;>;
   #64 = Utf8               keyType
   #65 = Class              #164          // concurrentrefhashmap/ConcurrentReferenceHashMap$ReferenceType
   #66 = Utf8               ReferenceType
   #67 = Utf8               Lconcurrentrefhashmap/ConcurrentReferenceHashMap$ReferenceType;
   #68 = Utf8               valueType
   #69 = Utf8               identityComparisons
   #70 = Utf8               Z
   #71 = Utf8               <init>
   #72 = Utf8               (IFLconcurrentrefhashmap/ConcurrentReferenceHashMap$ReferenceType;Lconcurrentrefhashmap/ConcurrentReferenceHashMap$ReferenceType;Z)V
   #73 = Utf8               Code
   #74 = Utf8               LineNumberTable
   #75 = Utf8               newArray
   #76 = Utf8               Segment
   #77 = Utf8               (I)[Lconcurrentrefhashmap/ConcurrentReferenceHashMap$Segment;
   #78 = Utf8               <K:Ljava/lang/Object;V:Ljava/lang/Object;>(I)[Lconcurrentrefhashmap/ConcurrentReferenceHashMap$Segment<TK;TV;>;
   #79 = Utf8               keyEq
   #80 = Utf8               (Ljava/lang/Object;Ljava/lang/Object;)Z
   #81 = Utf8               StackMapTable
   #82 = Utf8               setTable
   #83 = Utf8               ([Lconcurrentrefhashmap/ConcurrentReferenceHashMap$HashEntry;)V
   #84 = Utf8               ([Lconcurrentrefhashmap/ConcurrentReferenceHashMap$HashEntry<TK;TV;>;)V
   #85 = Utf8               getFirst
   #86 = Utf8               (I)Lconcurrentrefhashmap/ConcurrentReferenceHashMap$HashEntry;
   #87 = Utf8               (I)Lconcurrentrefhashmap/ConcurrentReferenceHashMap$HashEntry<TK;TV;>;
   #88 = Utf8               newHashEntry
   #89 = Utf8               (Ljava/lang/Object;ILconcurrentrefhashmap/ConcurrentReferenceHashMap$HashEntry;Ljava/lang/Object;)Lconcurrentrefhashmap/ConcurrentReferenceHashMap$HashEntry;
   #90 = Utf8               (TK;ILconcurrentrefhashmap/ConcurrentReferenceHashMap$HashEntry<TK;TV;>;TV;)Lconcurrentrefhashmap/ConcurrentReferenceHashMap$HashEntry<TK;TV;>;
   #91 = Utf8               readValueUnderLock
   #92 = Utf8               (Lconcurrentrefhashmap/ConcurrentReferenceHashMap$HashEntry;)Ljava/lang/Object;
   #93 = Class              #165          // java/lang/Throwable
   #94 = Utf8               (Lconcurrentrefhashmap/ConcurrentReferenceHashMap$HashEntry<TK;TV;>;)TV;
   #95 = Utf8               get
   #96 = Utf8               (Ljava/lang/Object;I)Ljava/lang/Object;
   #97 = Class              #166          // java/lang/Object
   #98 = Utf8               (Ljava/lang/Object;I)TV;
   #99 = Utf8               containsKey
  #100 = Utf8               (Ljava/lang/Object;I)Z
  #101 = Utf8               containsValue
  #102 = Utf8               (Ljava/lang/Object;)Z
  #103 = Class              #56           // "[Lconcurrentrefhashmap/ConcurrentReferenceHashMap$HashEntry;"
  #104 = Utf8               replace
  #105 = Utf8               (Ljava/lang/Object;ILjava/lang/Object;Ljava/lang/Object;)Z
  #106 = Utf8               (TK;ITV;TV;)Z
  #107 = Utf8               (Ljava/lang/Object;ILjava/lang/Object;)Ljava/lang/Object;
  #108 = Utf8               (TK;ITV;)TV;
  #109 = Utf8               put
  #110 = Utf8               (Ljava/lang/Object;ILjava/lang/Object;Z)Ljava/lang/Object;
  #111 = Utf8               (TK;ITV;Z)TV;
  #112 = Utf8               rehash
  #113 = Utf8               ()I
  #114 = Utf8               remove
  #115 = Utf8               (Ljava/lang/Object;ILjava/lang/Object;Z)TV;
  #116 = Utf8               removeStale
  #117 = Utf8               ()V
  #118 = Utf8               clear
  #119 = Utf8               <K:Ljava/lang/Object;V:Ljava/lang/Object;>Ljava/util/concurrent/locks/ReentrantLock;Ljava/io/Serializable;
  #120 = Utf8               SourceFile
  #121 = Utf8               ConcurrentReferenceHashMap.java
  #122 = Utf8               concurrentrefhashmap/ConcurrentReferenceHashMap
  #123 = NameAndType        #71:#117      // "<init>":()V
  #124 = NameAndType        #59:#60       // loadFactor:F
  #125 = NameAndType        #64:#67       // keyType:Lconcurrentrefhashmap/ConcurrentReferenceHashMap$ReferenceType;
  #126 = NameAndType        #68:#67       // valueType:Lconcurrentrefhashmap/ConcurrentReferenceHashMap$ReferenceType;
  #127 = NameAndType        #69:#70       // identityComparisons:Z
  #128 = NameAndType        #75:#167      // newArray:(I)[Lconcurrentrefhashmap/ConcurrentReferenceHashMap$HashEntry;
  #129 = NameAndType        #82:#83       // setTable:([Lconcurrentrefhashmap/ConcurrentReferenceHashMap$HashEntry;)V
  #130 = Utf8               concurrentrefhashmap/ConcurrentReferenceHashMap$Segment
  #131 = NameAndType        #168:#102     // equals:(Ljava/lang/Object;)Z
  #132 = NameAndType        #52:#50       // threshold:I
  #133 = NameAndType        #53:#56       // table:[Lconcurrentrefhashmap/ConcurrentReferenceHashMap$HashEntry;
  #134 = Utf8               java/lang/ref/ReferenceQueue
  #135 = NameAndType        #61:#62       // refQueue:Ljava/lang/ref/ReferenceQueue;
  #136 = Utf8               concurrentrefhashmap/ConcurrentReferenceHashMap$HashEntry
  #137 = NameAndType        #71:#169      // "<init>":(Ljava/lang/Object;ILconcurrentrefhashmap/ConcurrentReferenceHashMap$HashEntry;Ljava/lang/Object;Lconcurrentrefhashmap/ConcurrentReferenceHashMap$ReferenceType;Lconcurrentrefhashmap/ConcurrentReferenceHashMap$ReferenceType;Ljava/lang/ref/ReferenceQueue;)V
  #138 = NameAndType        #170:#117     // lock:()V
  #139 = NameAndType        #116:#117     // removeStale:()V
  #140 = NameAndType        #171:#172     // value:()Ljava/lang/Object;
  #141 = NameAndType        #173:#117     // unlock:()V
  #142 = NameAndType        #49:#50       // count:I
  #143 = NameAndType        #85:#86       // getFirst:(I)Lconcurrentrefhashmap/ConcurrentReferenceHashMap$HashEntry;
  #144 = NameAndType        #174:#50      // hash:I
  #145 = NameAndType        #175:#172     // key:()Ljava/lang/Object;
  #146 = NameAndType        #79:#80       // keyEq:(Ljava/lang/Object;Ljava/lang/Object;)Z
  #147 = NameAndType        #176:#177     // valueRef:Ljava/lang/Object;
  #148 = NameAndType        #178:#179     // dereferenceValue:(Ljava/lang/Object;)Ljava/lang/Object;
  #149 = NameAndType        #91:#92       // readValueUnderLock:(Lconcurrentrefhashmap/ConcurrentReferenceHashMap$HashEntry;)Ljava/lang/Object;
  #150 = NameAndType        #180:#181     // next:Lconcurrentrefhashmap/ConcurrentReferenceHashMap$HashEntry;
  #151 = NameAndType        #182:#183     // setValue:(Ljava/lang/Object;Lconcurrentrefhashmap/ConcurrentReferenceHashMap$ReferenceType;Ljava/lang/ref/ReferenceQueue;)V
  #152 = NameAndType        #112:#113     // rehash:()I
  #153 = NameAndType        #51:#50       // modCount:I
  #154 = NameAndType        #88:#89       // newHashEntry:(Ljava/lang/Object;ILconcurrentrefhashmap/ConcurrentReferenceHashMap$HashEntry;Ljava/lang/Object;)Lconcurrentrefhashmap/ConcurrentReferenceHashMap$HashEntry;
  #155 = NameAndType        #184:#177     // keyRef:Ljava/lang/Object;
  #156 = NameAndType        #185:#186     // poll:()Ljava/lang/ref/Reference;
  #157 = Utf8               concurrentrefhashmap/ConcurrentReferenceHashMap$KeyReference
  #158 = Utf8               KeyReference
  #159 = NameAndType        #184:#172     // keyRef:()Ljava/lang/Object;
  #160 = NameAndType        #187:#113     // keyHash:()I
  #161 = NameAndType        #114:#110     // remove:(Ljava/lang/Object;ILjava/lang/Object;Z)Ljava/lang/Object;
  #162 = Utf8               java/util/concurrent/locks/ReentrantLock
  #163 = Utf8               java/io/Serializable
  #164 = Utf8               concurrentrefhashmap/ConcurrentReferenceHashMap$ReferenceType
  #165 = Utf8               java/lang/Throwable
  #166 = Utf8               java/lang/Object
  #167 = Utf8               (I)[Lconcurrentrefhashmap/ConcurrentReferenceHashMap$HashEntry;
  #168 = Utf8               equals
  #169 = Utf8               (Ljava/lang/Object;ILconcurrentrefhashmap/ConcurrentReferenceHashMap$HashEntry;Ljava/lang/Object;Lconcurrentrefhashmap/ConcurrentReferenceHashMap$ReferenceType;Lconcurrentrefhashmap/ConcurrentReferenceHashMap$ReferenceType;Ljava/lang/ref/ReferenceQueue;)V
  #170 = Utf8               lock
  #171 = Utf8               value
  #172 = Utf8               ()Ljava/lang/Object;
  #173 = Utf8               unlock
  #174 = Utf8               hash
  #175 = Utf8               key
  #176 = Utf8               valueRef
  #177 = Utf8               Ljava/lang/Object;
  #178 = Utf8               dereferenceValue
  #179 = Utf8               (Ljava/lang/Object;)Ljava/lang/Object;
  #180 = Utf8               next
  #181 = Utf8               Lconcurrentrefhashmap/ConcurrentReferenceHashMap$HashEntry;
  #182 = Utf8               setValue
  #183 = Utf8               (Ljava/lang/Object;Lconcurrentrefhashmap/ConcurrentReferenceHashMap$ReferenceType;Ljava/lang/ref/ReferenceQueue;)V
  #184 = Utf8               keyRef
  #185 = Utf8               poll
  #186 = Utf8               ()Ljava/lang/ref/Reference;
  #187 = Utf8               keyHash
{
  private static final long serialVersionUID;
    descriptor: J
    flags: (0x001a) ACC_PRIVATE, ACC_STATIC, ACC_FINAL
    ConstantValue: long 2249069246763182397l

  volatile transient int count;
    descriptor: I
    flags: (0x00c0) ACC_VOLATILE, ACC_TRANSIENT

  transient int modCount;
    descriptor: I
    flags: (0x0080) ACC_TRANSIENT

  transient int threshold;
    descriptor: I
    flags: (0x0080) ACC_TRANSIENT

  volatile transient concurrentrefhashmap.ConcurrentReferenceHashMap$HashEntry<K, V>[] table;
    descriptor: [Lconcurrentrefhashmap/ConcurrentReferenceHashMap$HashEntry;
    flags: (0x00c0) ACC_VOLATILE, ACC_TRANSIENT
    Signature: #58                          // [Lconcurrentrefhashmap/ConcurrentReferenceHashMap$HashEntry<TK;TV;>;

  final float loadFactor;
    descriptor: F
    flags: (0x0010) ACC_FINAL

  volatile transient java.lang.ref.ReferenceQueue<java.lang.Object> refQueue;
    descriptor: Ljava/lang/ref/ReferenceQueue;
    flags: (0x00c0) ACC_VOLATILE, ACC_TRANSIENT
    Signature: #63                          // Ljava/lang/ref/ReferenceQueue<Ljava/lang/Object;>;

  final concurrentrefhashmap.ConcurrentReferenceHashMap$ReferenceType keyType;
    descriptor: Lconcurrentrefhashmap/ConcurrentReferenceHashMap$ReferenceType;
    flags: (0x0010) ACC_FINAL

  final concurrentrefhashmap.ConcurrentReferenceHashMap$ReferenceType valueType;
    descriptor: Lconcurrentrefhashmap/ConcurrentReferenceHashMap$ReferenceType;
    flags: (0x0010) ACC_FINAL

  final boolean identityComparisons;
    descriptor: Z
    flags: (0x0010) ACC_FINAL

  concurrentrefhashmap.ConcurrentReferenceHashMap$Segment(int, float, concurrentrefhashmap.ConcurrentReferenceHashMap$ReferenceType, concurrentrefhashmap.ConcurrentReferenceHashMap$ReferenceType, boolean);
    descriptor: (IFLconcurrentrefhashmap/ConcurrentReferenceHashMap$ReferenceType;Lconcurrentrefhashmap/ConcurrentReferenceHashMap$ReferenceType;Z)V
    flags: (0x0000)
    Code:
      stack=2, locals=6, args_size=6
         0: aload_0
         1: invokespecial #2                  // Method java/util/concurrent/locks/ReentrantLock."<init>":()V
         4: aload_0
         5: fload_2
         6: putfield      #3                  // Field loadFactor:F
         9: aload_0
        10: aload_3
        11: putfield      #4                  // Field keyType:Lconcurrentrefhashmap/ConcurrentReferenceHashMap$ReferenceType;
        14: aload_0
        15: aload         4
        17: putfield      #5                  // Field valueType:Lconcurrentrefhashmap/ConcurrentReferenceHashMap$ReferenceType;
        20: aload_0
        21: iload         5
        23: putfield      #6                  // Field identityComparisons:Z
        26: aload_0
        27: iload_1
        28: invokestatic  #7                  // Method concurrentrefhashmap/ConcurrentReferenceHashMap$HashEntry.newArray:(I)[Lconcurrentrefhashmap/ConcurrentReferenceHashMap$HashEntry;
        31: invokevirtual #8                  // Method setTable:([Lconcurrentrefhashmap/ConcurrentReferenceHashMap$HashEntry;)V
        34: return
      LineNumberTable:
        line 559: 0
        line 560: 4
        line 561: 9
        line 562: 14
        line 563: 20
        line 564: 26
        line 565: 34

  static final <K extends java.lang.Object, V extends java.lang.Object> concurrentrefhashmap.ConcurrentReferenceHashMap$Segment<K, V>[] newArray(int);
    descriptor: (I)[Lconcurrentrefhashmap/ConcurrentReferenceHashMap$Segment;
    flags: (0x0018) ACC_STATIC, ACC_FINAL
    Code:
      stack=1, locals=1, args_size=1
         0: iload_0
         1: anewarray     #9                  // class concurrentrefhashmap/ConcurrentReferenceHashMap$Segment
         4: areturn
      LineNumberTable:
        line 569: 0
    Signature: #78                          // <K:Ljava/lang/Object;V:Ljava/lang/Object;>(I)[Lconcurrentrefhashmap/ConcurrentReferenceHashMap$Segment<TK;TV;>;

  private boolean keyEq(java.lang.Object, java.lang.Object);
    descriptor: (Ljava/lang/Object;Ljava/lang/Object;)Z
    flags: (0x0002) ACC_PRIVATE
    Code:
      stack=2, locals=3, args_size=3
         0: aload_0
         1: getfield      #6                  // Field identityComparisons:Z
         4: ifeq          20
         7: aload_1
         8: aload_2
         9: if_acmpne     16
        12: iconst_1
        13: goto          25
        16: iconst_0
        17: goto          25
        20: aload_1
        21: aload_2
        22: invokevirtual #10                 // Method java/lang/Object.equals:(Ljava/lang/Object;)Z
        25: ireturn
      LineNumberTable:
        line 573: 0
      StackMapTable: number_of_entries = 3
        frame_type = 16 /* same */
        frame_type = 3 /* same */
        frame_type = 68 /* same_locals_1_stack_item */
          stack = [ int ]

  void setTable(concurrentrefhashmap.ConcurrentReferenceHashMap$HashEntry<K, V>[]);
    descriptor: ([Lconcurrentrefhashmap/ConcurrentReferenceHashMap$HashEntry;)V
    flags: (0x0000)
    Code:
      stack=3, locals=2, args_size=2
         0: aload_0
         1: aload_1
         2: arraylength
         3: i2f
         4: aload_0
         5: getfield      #3                  // Field loadFactor:F
         8: fmul
         9: f2i
        10: putfield      #11                 // Field threshold:I
        13: aload_0
        14: aload_1
        15: putfield      #12                 // Field table:[Lconcurrentrefhashmap/ConcurrentReferenceHashMap$HashEntry;
        18: aload_0
        19: new           #13                 // class java/lang/ref/ReferenceQueue
        22: dup
        23: invokespecial #14                 // Method java/lang/ref/ReferenceQueue."<init>":()V
        26: putfield      #15                 // Field refQueue:Ljava/lang/ref/ReferenceQueue;
        29: return
      LineNumberTable:
        line 581: 0
        line 582: 13
        line 583: 18
        line 584: 29
    Signature: #84                          // ([Lconcurrentrefhashmap/ConcurrentReferenceHashMap$HashEntry<TK;TV;>;)V

  concurrentrefhashmap.ConcurrentReferenceHashMap$HashEntry<K, V> getFirst(int);
    descriptor: (I)Lconcurrentrefhashmap/ConcurrentReferenceHashMap$HashEntry;
    flags: (0x0000)
    Code:
      stack=4, locals=3, args_size=2
         0: aload_0
         1: getfield      #12                 // Field table:[Lconcurrentrefhashmap/ConcurrentReferenceHashMap$HashEntry;
         4: astore_2
         5: aload_2
         6: iload_1
         7: aload_2
         8: arraylength
         9: iconst_1
        10: isub
        11: iand
        12: aaload
        13: areturn
      LineNumberTable:
        line 590: 0
        line 591: 5
    Signature: #87                          // (I)Lconcurrentrefhashmap/ConcurrentReferenceHashMap$HashEntry<TK;TV;>;

  concurrentrefhashmap.ConcurrentReferenceHashMap$HashEntry<K, V> newHashEntry(K, int, concurrentrefhashmap.ConcurrentReferenceHashMap$HashEntry<K, V>, V);
    descriptor: (Ljava/lang/Object;ILconcurrentrefhashmap/ConcurrentReferenceHashMap$HashEntry;Ljava/lang/Object;)Lconcurrentrefhashmap/ConcurrentReferenceHashMap$HashEntry;
    flags: (0x0000)
    Code:
      stack=9, locals=5, args_size=5
         0: new           #16                 // class concurrentrefhashmap/ConcurrentReferenceHashMap$HashEntry
         3: dup
         4: aload_1
         5: iload_2
         6: aload_3
         7: aload         4
         9: aload_0
        10: getfield      #4                  // Field keyType:Lconcurrentrefhashmap/ConcurrentReferenceHashMap$ReferenceType;
        13: aload_0
        14: getfield      #5                  // Field valueType:Lconcurrentrefhashmap/ConcurrentReferenceHashMap$ReferenceType;
        17: aload_0
        18: getfield      #15                 // Field refQueue:Ljava/lang/ref/ReferenceQueue;
        21: invokespecial #17                 // Method concurrentrefhashmap/ConcurrentReferenceHashMap$HashEntry."<init>":(Ljava/lang/Object;ILconcurrentrefhashmap/ConcurrentReferenceHashMap$HashEntry;Ljava/lang/Object;Lconcurrentrefhashmap/ConcurrentReferenceHashMap$ReferenceType;Lconcurrentrefhashmap/ConcurrentReferenceHashMap$ReferenceType;Ljava/lang/ref/ReferenceQueue;)V
        24: areturn
      LineNumberTable:
        line 595: 0
    Signature: #90                          // (TK;ILconcurrentrefhashmap/ConcurrentReferenceHashMap$HashEntry<TK;TV;>;TV;)Lconcurrentrefhashmap/ConcurrentReferenceHashMap$HashEntry<TK;TV;>;

  V readValueUnderLock(concurrentrefhashmap.ConcurrentReferenceHashMap$HashEntry<K, V>);
    descriptor: (Lconcurrentrefhashmap/ConcurrentReferenceHashMap$HashEntry;)Ljava/lang/Object;
    flags: (0x0000)
    Code:
      stack=1, locals=4, args_size=2
         0: aload_0
         1: invokevirtual #18                 // Method lock:()V
         4: aload_0
         5: invokevirtual #19                 // Method removeStale:()V
         8: aload_1
         9: invokevirtual #20                 // Method concurrentrefhashmap/ConcurrentReferenceHashMap$HashEntry.value:()Ljava/lang/Object;
        12: astore_2
        13: aload_0
        14: invokevirtual #21                 // Method unlock:()V
        17: aload_2
        18: areturn
        19: astore_3
        20: aload_0
        21: invokevirtual #21                 // Method unlock:()V
        24: aload_3
        25: athrow
      Exception table:
         from    to  target type
             4    13    19   any
      LineNumberTable:
        line 606: 0
        line 608: 4
        line 609: 8
        line 612: 13
        line 609: 17
        line 612: 19
        line 613: 24
      StackMapTable: number_of_entries = 1
        frame_type = 83 /* same_locals_1_stack_item */
          stack = [ class java/lang/Throwable ]
    Signature: #94                          // (Lconcurrentrefhashmap/ConcurrentReferenceHashMap$HashEntry<TK;TV;>;)TV;

  V get(java.lang.Object, int);
    descriptor: (Ljava/lang/Object;I)Ljava/lang/Object;
    flags: (0x0000)
    Code:
      stack=3, locals=5, args_size=3
         0: aload_0
         1: getfield      #22                 // Field count:I
         4: ifeq          69
         7: aload_0
         8: iload_2
         9: invokevirtual #23                 // Method getFirst:(I)Lconcurrentrefhashmap/ConcurrentReferenceHashMap$HashEntry;
        12: astore_3
        13: aload_3
        14: ifnull        69
        17: aload_3
        18: getfield      #24                 // Field concurrentrefhashmap/ConcurrentReferenceHashMap$HashEntry.hash:I
        21: iload_2
        22: if_icmpne     61
        25: aload_0
        26: aload_1
        27: aload_3
        28: invokevirtual #25                 // Method concurrentrefhashmap/ConcurrentReferenceHashMap$HashEntry.key:()Ljava/lang/Object;
        31: invokespecial #26                 // Method keyEq:(Ljava/lang/Object;Ljava/lang/Object;)Z
        34: ifeq          61
        37: aload_3
        38: getfield      #27                 // Field concurrentrefhashmap/ConcurrentReferenceHashMap$HashEntry.valueRef:Ljava/lang/Object;
        41: astore        4
        43: aload         4
        45: ifnull        55
        48: aload_3
        49: aload         4
        51: invokevirtual #28                 // Method concurrentrefhashmap/ConcurrentReferenceHashMap$HashEntry.dereferenceValue:(Ljava/lang/Object;)Ljava/lang/Object;
        54: areturn
        55: aload_0
        56: aload_3
        57: invokevirtual #29                 // Method readValueUnderLock:(Lconcurrentrefhashmap/ConcurrentReferenceHashMap$HashEntry;)Ljava/lang/Object;
        60: areturn
        61: aload_3
        62: getfield      #30                 // Field concurrentrefhashmap/ConcurrentReferenceHashMap$HashEntry.next:Lconcurrentrefhashmap/ConcurrentReferenceHashMap$HashEntry;
        65: astore_3
        66: goto          13
        69: aconst_null
        70: areturn
      LineNumberTable:
        line 619: 0
        line 620: 7
        line 621: 13
        line 622: 17
        line 623: 37
        line 624: 43
        line 625: 48
        line 628: 55
        line 630: 61
        line 633: 69
      StackMapTable: number_of_entries = 4
        frame_type = 252 /* append */
          offset_delta = 13
          locals = [ class concurrentrefhashmap/ConcurrentReferenceHashMap$HashEntry ]
        frame_type = 252 /* append */
          offset_delta = 41
          locals = [ class java/lang/Object ]
        frame_type = 250 /* chop */
          offset_delta = 5
        frame_type = 250 /* chop */
          offset_delta = 7
    Signature: #98                          // (Ljava/lang/Object;I)TV;

  boolean containsKey(java.lang.Object, int);
    descriptor: (Ljava/lang/Object;I)Z
    flags: (0x0000)
    Code:
      stack=3, locals=4, args_size=3
         0: aload_0
         1: getfield      #22                 // Field count:I
         4: ifeq          47
         7: aload_0
         8: iload_2
         9: invokevirtual #23                 // Method getFirst:(I)Lconcurrentrefhashmap/ConcurrentReferenceHashMap$HashEntry;
        12: astore_3
        13: aload_3
        14: ifnull        47
        17: aload_3
        18: getfield      #24                 // Field concurrentrefhashmap/ConcurrentReferenceHashMap$HashEntry.hash:I
        21: iload_2
        22: if_icmpne     39
        25: aload_0
        26: aload_1
        27: aload_3
        28: invokevirtual #25                 // Method concurrentrefhashmap/ConcurrentReferenceHashMap$HashEntry.key:()Ljava/lang/Object;
        31: invokespecial #26                 // Method keyEq:(Ljava/lang/Object;Ljava/lang/Object;)Z
        34: ifeq          39
        37: iconst_1
        38: ireturn
        39: aload_3
        40: getfield      #30                 // Field concurrentrefhashmap/ConcurrentReferenceHashMap$HashEntry.next:Lconcurrentrefhashmap/ConcurrentReferenceHashMap$HashEntry;
        43: astore_3
        44: goto          13
        47: iconst_0
        48: ireturn
      LineNumberTable:
        line 637: 0
        line 638: 7
        line 639: 13
        line 640: 17
        line 641: 37
        line 643: 39
        line 646: 47
      StackMapTable: number_of_entries = 3
        frame_type = 252 /* append */
          offset_delta = 13
          locals = [ class concurrentrefhashmap/ConcurrentReferenceHashMap$HashEntry ]
        frame_type = 25 /* same */
        frame_type = 250 /* chop */
          offset_delta = 7

  boolean containsValue(java.lang.Object);
    descriptor: (Ljava/lang/Object;)Z
    flags: (0x0000)
    Code:
      stack=2, locals=8, args_size=2
         0: aload_0
         1: getfield      #22                 // Field count:I
         4: ifeq          94
         7: aload_0
         8: getfield      #12                 // Field table:[Lconcurrentrefhashmap/ConcurrentReferenceHashMap$HashEntry;
        11: astore_2
        12: aload_2
        13: arraylength
        14: istore_3
        15: iconst_0
        16: istore        4
        18: iload         4
        20: iload_3
        21: if_icmpge     94
        24: aload_2
        25: iload         4
        27: aaload
        28: astore        5
        30: aload         5
        32: ifnull        88
        35: aload         5
        37: getfield      #27                 // Field concurrentrefhashmap/ConcurrentReferenceHashMap$HashEntry.valueRef:Ljava/lang/Object;
        40: astore        6
        42: aload         6
        44: ifnonnull     58
        47: aload_0
        48: aload         5
        50: invokevirtual #29                 // Method readValueUnderLock:(Lconcurrentrefhashmap/ConcurrentReferenceHashMap$HashEntry;)Ljava/lang/Object;
        53: astore        7
        55: goto          67
        58: aload         5
        60: aload         6
        62: invokevirtual #28                 // Method concurrentrefhashmap/ConcurrentReferenceHashMap$HashEntry.dereferenceValue:(Ljava/lang/Object;)Ljava/lang/Object;
        65: astore        7
        67: aload_1
        68: aload         7
        70: invokevirtual #10                 // Method java/lang/Object.equals:(Ljava/lang/Object;)Z
        73: ifeq          78
        76: iconst_1
        77: ireturn
        78: aload         5
        80: getfield      #30                 // Field concurrentrefhashmap/ConcurrentReferenceHashMap$HashEntry.next:Lconcurrentrefhashmap/ConcurrentReferenceHashMap$HashEntry;
        83: astore        5
        85: goto          30
        88: iinc          4, 1
        91: goto          18
        94: iconst_0
        95: ireturn
      LineNumberTable:
        line 650: 0
        line 651: 7
        line 652: 12
        line 653: 15
        line 654: 24
        line 655: 35
        line 658: 42
        line 659: 47
        line 662: 58
        line 665: 67
        line 666: 76
        line 654: 78
        line 653: 88
        line 671: 94
      StackMapTable: number_of_entries = 7
        frame_type = 254 /* append */
          offset_delta = 18
          locals = [ class "[Lconcurrentrefhashmap/ConcurrentReferenceHashMap$HashEntry;", int, int ]
        frame_type = 252 /* append */
          offset_delta = 11
          locals = [ class concurrentrefhashmap/ConcurrentReferenceHashMap$HashEntry ]
        frame_type = 252 /* append */
          offset_delta = 27
          locals = [ class java/lang/Object ]
        frame_type = 252 /* append */
          offset_delta = 8
          locals = [ class java/lang/Object ]
        frame_type = 249 /* chop */
          offset_delta = 10
        frame_type = 250 /* chop */
          offset_delta = 9
        frame_type = 248 /* chop */
          offset_delta = 5

  boolean replace(K, int, V, V);
    descriptor: (Ljava/lang/Object;ILjava/lang/Object;Ljava/lang/Object;)Z
    flags: (0x0000)
    Code:
      stack=4, locals=9, args_size=5
         0: aload_0
         1: invokevirtual #18                 // Method lock:()V
         4: aload_0
         5: invokevirtual #19                 // Method removeStale:()V
         8: aload_0
         9: iload_2
        10: invokevirtual #23                 // Method getFirst:(I)Lconcurrentrefhashmap/ConcurrentReferenceHashMap$HashEntry;
        13: astore        5
        15: aload         5
        17: ifnull        52
        20: aload         5
        22: getfield      #24                 // Field concurrentrefhashmap/ConcurrentReferenceHashMap$HashEntry.hash:I
        25: iload_2
        26: if_icmpne     42
        29: aload_0
        30: aload_1
        31: aload         5
        33: invokevirtual #25                 // Method concurrentrefhashmap/ConcurrentReferenceHashMap$HashEntry.key:()Ljava/lang/Object;
        36: invokespecial #26                 // Method keyEq:(Ljava/lang/Object;Ljava/lang/Object;)Z
        39: ifne          52
        42: aload         5
        44: getfield      #30                 // Field concurrentrefhashmap/ConcurrentReferenceHashMap$HashEntry.next:Lconcurrentrefhashmap/ConcurrentReferenceHashMap$HashEntry;
        47: astore        5
        49: goto          15
        52: iconst_0
        53: istore        6
        55: aload         5
        57: ifnull        90
        60: aload_3
        61: aload         5
        63: invokevirtual #20                 // Method concurrentrefhashmap/ConcurrentReferenceHashMap$HashEntry.value:()Ljava/lang/Object;
        66: invokevirtual #10                 // Method java/lang/Object.equals:(Ljava/lang/Object;)Z
        69: ifeq          90
        72: iconst_1
        73: istore        6
        75: aload         5
        77: aload         4
        79: aload_0
        80: getfield      #5                  // Field valueType:Lconcurrentrefhashmap/ConcurrentReferenceHashMap$ReferenceType;
        83: aload_0
        84: getfield      #15                 // Field refQueue:Ljava/lang/ref/ReferenceQueue;
        87: invokevirtual #31                 // Method concurrentrefhashmap/ConcurrentReferenceHashMap$HashEntry.setValue:(Ljava/lang/Object;Lconcurrentrefhashmap/ConcurrentReferenceHashMap$ReferenceType;Ljava/lang/ref/ReferenceQueue;)V
        90: iload         6
        92: istore        7
        94: aload_0
        95: invokevirtual #21                 // Method unlock:()V
        98: iload         7
       100: ireturn
       101: astore        8
       103: aload_0
       104: invokevirtual #21                 // Method unlock:()V
       107: aload         8
       109: athrow
      Exception table:
         from    to  target type
             4    94   101   any
           101   103   101   any
      LineNumberTable:
        line 675: 0
        line 677: 4
        line 678: 8
        line 679: 15
        line 680: 42
        line 683: 52
        line 684: 55
        line 685: 72
        line 686: 75
        line 688: 90
        line 691: 94
        line 688: 98
        line 691: 101
        line 692: 107
      StackMapTable: number_of_entries = 5
        frame_type = 252 /* append */
          offset_delta = 15
          locals = [ class concurrentrefhashmap/ConcurrentReferenceHashMap$HashEntry ]
        frame_type = 26 /* same */
        frame_type = 9 /* same */
        frame_type = 252 /* append */
          offset_delta = 37
          locals = [ int ]
        frame_type = 255 /* full_frame */
          offset_delta = 10
          locals = [ class concurrentrefhashmap/ConcurrentReferenceHashMap$Segment, class java/lang/Object, int, class java/lang/Object, class java/lang/Object ]
          stack = [ class java/lang/Throwable ]
    Signature: #106                         // (TK;ITV;TV;)Z

  V replace(K, int, V);
    descriptor: (Ljava/lang/Object;ILjava/lang/Object;)Ljava/lang/Object;
    flags: (0x0000)
    Code:
      stack=4, locals=8, args_size=4
         0: aload_0
         1: invokevirtual #18                 // Method lock:()V
         4: aload_0
         5: invokevirtual #19                 // Method removeStale:()V
         8: aload_0
         9: iload_2
        10: invokevirtual #23                 // Method getFirst:(I)Lconcurrentrefhashmap/ConcurrentReferenceHashMap$HashEntry;
        13: astore        4
        15: aload         4
        17: ifnull        52
        20: aload         4
        22: getfield      #24                 // Field concurrentrefhashmap/ConcurrentReferenceHashMap$HashEntry.hash:I
        25: iload_2
        26: if_icmpne     42
        29: aload_0
        30: aload_1
        31: aload         4
        33: invokevirtual #25                 // Method concurrentrefhashmap/ConcurrentReferenceHashMap$HashEntry.key:()Ljava/lang/Object;
        36: invokespecial #26                 // Method keyEq:(Ljava/lang/Object;Ljava/lang/Object;)Z
        39: ifne          52
        42: aload         4
        44: getfield      #30                 // Field concurrentrefhashmap/ConcurrentReferenceHashMap$HashEntry.next:Lconcurrentrefhashmap/ConcurrentReferenceHashMap$HashEntry;
        47: astore        4
        49: goto          15
        52: aconst_null
        53: astore        5
        55: aload         4
        57: ifnull        81
        60: aload         4
        62: invokevirtual #20                 // Method concurrentrefhashmap/ConcurrentReferenceHashMap$HashEntry.value:()Ljava/lang/Object;
        65: astore        5
        67: aload         4
        69: aload_3
        70: aload_0
        71: getfield      #5                  // Field valueType:Lconcurrentrefhashmap/ConcurrentReferenceHashMap$ReferenceType;
        74: aload_0
        75: getfield      #15                 // Field refQueue:Ljava/lang/ref/ReferenceQueue;
        78: invokevirtual #31                 // Method concurrentrefhashmap/ConcurrentReferenceHashMap$HashEntry.setValue:(Ljava/lang/Object;Lconcurrentrefhashmap/ConcurrentReferenceHashMap$ReferenceType;Ljava/lang/ref/ReferenceQueue;)V
        81: aload         5
        83: astore        6
        85: aload_0
        86: invokevirtual #21                 // Method unlock:()V
        89: aload         6
        91: areturn
        92: astore        7
        94: aload_0
        95: invokevirtual #21                 // Method unlock:()V
        98: aload         7
       100: athrow
      Exception table:
         from    to  target type
             4    85    92   any
            92    94    92   any
      LineNumberTable:
        line 696: 0
        line 698: 4
        line 699: 8
        line 700: 15
        line 701: 42
        line 704: 52
        line 705: 55
        line 706: 60
        line 707: 67
        line 709: 81
        line 712: 85
        line 709: 89
        line 712: 92
        line 713: 98
      StackMapTable: number_of_entries = 5
        frame_type = 252 /* append */
          offset_delta = 15
          locals = [ class concurrentrefhashmap/ConcurrentReferenceHashMap$HashEntry ]
        frame_type = 26 /* same */
        frame_type = 9 /* same */
        frame_type = 252 /* append */
          offset_delta = 28
          locals = [ class java/lang/Object ]
        frame_type = 255 /* full_frame */
          offset_delta = 10
          locals = [ class concurrentrefhashmap/ConcurrentReferenceHashMap$Segment, class java/lang/Object, int, class java/lang/Object ]
          stack = [ class java/lang/Throwable ]
    Signature: #108                         // (TK;ITV;)TV;

  V put(K, int, V, boolean);
    descriptor: (Ljava/lang/Object;ILjava/lang/Object;Z)Ljava/lang/Object;
    flags: (0x0000)
    Code:
      stack=7, locals=13, args_size=5
         0: aload_0
         1: invokevirtual #18                 // Method lock:()V
         4: aload_0
         5: invokevirtual #19                 // Method removeStale:()V
         8: aload_0
         9: getfield      #22                 // Field count:I
        12: istore        5
        14: iload         5
        16: iinc          5, 1
        19: aload_0
        20: getfield      #11                 // Field threshold:I
        23: if_icmple     51
        26: aload_0
        27: invokevirtual #32                 // Method rehash:()I
        30: istore        6
        32: iload         6
        34: ifle          51
        37: aload_0
        38: iload         5
        40: iload         6
        42: isub
        43: dup
        44: istore        5
        46: iconst_1
        47: isub
        48: putfield      #22                 // Field count:I
        51: aload_0
        52: getfield      #12                 // Field table:[Lconcurrentrefhashmap/ConcurrentReferenceHashMap$HashEntry;
        55: astore        6
        57: iload_2
        58: aload         6
        60: arraylength
        61: iconst_1
        62: isub
        63: iand
        64: istore        7
        66: aload         6
        68: iload         7
        70: aaload
        71: astore        8
        73: aload         8
        75: astore        9
        77: aload         9
        79: ifnull        114
        82: aload         9
        84: getfield      #24                 // Field concurrentrefhashmap/ConcurrentReferenceHashMap$HashEntry.hash:I
        87: iload_2
        88: if_icmpne     104
        91: aload_0
        92: aload_1
        93: aload         9
        95: invokevirtual #25                 // Method concurrentrefhashmap/ConcurrentReferenceHashMap$HashEntry.key:()Ljava/lang/Object;
        98: invokespecial #26                 // Method keyEq:(Ljava/lang/Object;Ljava/lang/Object;)Z
       101: ifne          114
       104: aload         9
       106: getfield      #30                 // Field concurrentrefhashmap/ConcurrentReferenceHashMap$HashEntry.next:Lconcurrentrefhashmap/ConcurrentReferenceHashMap$HashEntry;
       109: astore        9
       111: goto          77
       114: aload         9
       116: ifnull        148
       119: aload         9
       121: invokevirtual #20                 // Method concurrentrefhashmap/ConcurrentReferenceHashMap$HashEntry.value:()Ljava/lang/Object;
       124: astore        10
       126: iload         4
       128: ifne          181
       131: aload         9
       133: aload_3
       134: aload_0
       135: getfield      #5                  // Field valueType:Lconcurrentrefhashmap/ConcurrentReferenceHashMap$ReferenceType;
       138: aload_0
       139: getfield      #15                 // Field refQueue:Ljava/lang/ref/ReferenceQueue;
       142: invokevirtual #31                 // Method concurrentrefhashmap/ConcurrentReferenceHashMap$HashEntry.setValue:(Ljava/lang/Object;Lconcurrentrefhashmap/ConcurrentReferenceHashMap$ReferenceType;Ljava/lang/ref/ReferenceQueue;)V
       145: goto          181
       148: aconst_null
       149: astore        10
       151: aload_0
       152: dup
       153: getfield      #33                 // Field modCount:I
       156: iconst_1
       157: iadd
       158: putfield      #33                 // Field modCount:I
       161: aload         6
       163: iload         7
       165: aload_0
       166: aload_1
       167: iload_2
       168: aload         8
       170: aload_3
       171: invokevirtual #34                 // Method newHashEntry:(Ljava/lang/Object;ILconcurrentrefhashmap/ConcurrentReferenceHashMap$HashEntry;Ljava/lang/Object;)Lconcurrentrefhashmap/ConcurrentReferenceHashMap$HashEntry;
       174: aastore
       175: aload_0
       176: iload         5
       178: putfield      #22                 // Field count:I
       181: aload         10
       183: astore        11
       185: aload_0
       186: invokevirtual #21                 // Method unlock:()V
       189: aload         11
       191: areturn
       192: astore        12
       194: aload_0
       195: invokevirtual #21                 // Method unlock:()V
       198: aload         12
       200: athrow
      Exception table:
         from    to  target type
             4   185   192   any
           192   194   192   any
      LineNumberTable:
        line 718: 0
        line 720: 4
        line 721: 8
        line 722: 14
        line 723: 26
        line 724: 32
        line 726: 37
        line 730: 51
        line 731: 57
        line 732: 66
        line 733: 73
        line 734: 77
        line 735: 104
        line 739: 114
        line 740: 119
        line 741: 126
        line 742: 131
        line 746: 148
        line 747: 151
        line 748: 161
        line 749: 175
        line 751: 181
        line 754: 185
        line 751: 189
        line 754: 192
        line 755: 198
      StackMapTable: number_of_entries = 7
        frame_type = 252 /* append */
          offset_delta = 51
          locals = [ int ]
        frame_type = 255 /* full_frame */
          offset_delta = 25
          locals = [ class concurrentrefhashmap/ConcurrentReferenceHashMap$Segment, class java/lang/Object, int, class java/lang/Object, int, int, class "[Lconcurrentrefhashmap/ConcurrentReferenceHashMap$HashEntry;", int, class concurrentrefhashmap/ConcurrentReferenceHashMap$HashEntry, class concurrentrefhashmap/ConcurrentReferenceHashMap$HashEntry ]
          stack = []
        frame_type = 26 /* same */
        frame_type = 9 /* same */
        frame_type = 33 /* same */
        frame_type = 252 /* append */
          offset_delta = 32
          locals = [ class java/lang/Object ]
        frame_type = 255 /* full_frame */
          offset_delta = 10
          locals = [ class concurrentrefhashmap/ConcurrentReferenceHashMap$Segment, class java/lang/Object, int, class java/lang/Object, int ]
          stack = [ class java/lang/Throwable ]
    Signature: #111                         // (TK;ITV;Z)TV;

  int rehash();
    descriptor: ()I
    flags: (0x0000)
    Code:
      stack=7, locals=16, args_size=1
         0: aload_0
         1: getfield      #12                 // Field table:[Lconcurrentrefhashmap/ConcurrentReferenceHashMap$HashEntry;
         4: astore_1
         5: aload_1
         6: arraylength
         7: istore_2
         8: iload_2
         9: ldc           #35                 // int 1073741824
        11: if_icmplt     16
        14: iconst_0
        15: ireturn
        16: iload_2
        17: iconst_1
        18: ishl
        19: invokestatic  #7                  // Method concurrentrefhashmap/ConcurrentReferenceHashMap$HashEntry.newArray:(I)[Lconcurrentrefhashmap/ConcurrentReferenceHashMap$HashEntry;
        22: astore_3
        23: aload_0
        24: aload_3
        25: arraylength
        26: i2f
        27: aload_0
        28: getfield      #3                  // Field loadFactor:F
        31: fmul
        32: f2i
        33: putfield      #11                 // Field threshold:I
        36: aload_3
        37: arraylength
        38: iconst_1
        39: isub
        40: istore        4
        42: iconst_0
        43: istore        5
        45: iconst_0
        46: istore        6
        48: iload         6
        50: iload_2
        51: if_icmpge     237
        54: aload_1
        55: iload         6
        57: aaload
        58: astore        7
        60: aload         7
        62: ifnull        231
        65: aload         7
        67: getfield      #30                 // Field concurrentrefhashmap/ConcurrentReferenceHashMap$HashEntry.next:Lconcurrentrefhashmap/ConcurrentReferenceHashMap$HashEntry;
        70: astore        8
        72: aload         7
        74: getfield      #24                 // Field concurrentrefhashmap/ConcurrentReferenceHashMap$HashEntry.hash:I
        77: iload         4
        79: iand
        80: istore        9
        82: aload         8
        84: ifnonnull     96
        87: aload_3
        88: iload         9
        90: aload         7
        92: aastore
        93: goto          231
        96: aload         7
        98: astore        10
       100: iload         9
       102: istore        11
       104: aload         8
       106: astore        12
       108: aload         12
       110: ifnull        148
       113: aload         12
       115: getfield      #24                 // Field concurrentrefhashmap/ConcurrentReferenceHashMap$HashEntry.hash:I
       118: iload         4
       120: iand
       121: istore        13
       123: iload         13
       125: iload         11
       127: if_icmpeq     138
       130: iload         13
       132: istore        11
       134: aload         12
       136: astore        10
       138: aload         12
       140: getfield      #30                 // Field concurrentrefhashmap/ConcurrentReferenceHashMap$HashEntry.next:Lconcurrentrefhashmap/ConcurrentReferenceHashMap$HashEntry;
       143: astore        12
       145: goto          108
       148: aload_3
       149: iload         11
       151: aload         10
       153: aastore
       154: aload         7
       156: astore        12
       158: aload         12
       160: aload         10
       162: if_acmpeq     231
       165: aload         12
       167: invokevirtual #25                 // Method concurrentrefhashmap/ConcurrentReferenceHashMap$HashEntry.key:()Ljava/lang/Object;
       170: astore        13
       172: aload         13
       174: ifnonnull     183
       177: iinc          5, 1
       180: goto          221
       183: aload         12
       185: getfield      #24                 // Field concurrentrefhashmap/ConcurrentReferenceHashMap$HashEntry.hash:I
       188: iload         4
       190: iand
       191: istore        14
       193: aload_3
       194: iload         14
       196: aaload
       197: astore        15
       199: aload_3
       200: iload         14
       202: aload_0
       203: aload         13
       205: aload         12
       207: getfield      #24                 // Field concurrentrefhashmap/ConcurrentReferenceHashMap$HashEntry.hash:I
       210: aload         15
       212: aload         12
       214: invokevirtual #20                 // Method concurrentrefhashmap/ConcurrentReferenceHashMap$HashEntry.value:()Ljava/lang/Object;
       217: invokevirtual #34                 // Method newHashEntry:(Ljava/lang/Object;ILconcurrentrefhashmap/ConcurrentReferenceHashMap$HashEntry;Ljava/lang/Object;)Lconcurrentrefhashmap/ConcurrentReferenceHashMap$HashEntry;
       220: aastore
       221: aload         12
       223: getfield      #30                 // Field concurrentrefhashmap/ConcurrentReferenceHashMap$HashEntry.next:Lconcurrentrefhashmap/ConcurrentReferenceHashMap$HashEntry;
       226: astore        12
       228: goto          158
       231: iinc          6, 1
       234: goto          48
       237: aload_0
       238: aload_3
       239: putfield      #12                 // Field table:[Lconcurrentrefhashmap/ConcurrentReferenceHashMap$HashEntry;
       242: iload         5
       244: ireturn
      LineNumberTable:
        line 759: 0
        line 760: 5
        line 761: 8
        line 762: 14
        line 779: 16
        line 780: 23
        line 781: 36
        line 782: 42
        line 783: 45
        line 786: 54
        line 788: 60
        line 789: 65
        line 790: 72
        line 793: 82
        line 794: 87
        line 799: 96
        line 800: 100
        line 801: 104
        line 802: 113
        line 803: 123
        line 804: 130
        line 805: 134
        line 801: 138
        line 808: 148
        line 810: 154
        line 812: 165
        line 813: 172
        line 814: 177
        line 815: 180
        line 817: 183
        line 818: 193
        line 819: 199
        line 810: 221
        line 783: 231
        line 824: 237
        line 825: 242
      StackMapTable: number_of_entries = 11
        frame_type = 253 /* append */
          offset_delta = 16
          locals = [ class "[Lconcurrentrefhashmap/ConcurrentReferenceHashMap$HashEntry;", int ]
        frame_type = 255 /* full_frame */
          offset_delta = 31
          locals = [ class concurrentrefhashmap/ConcurrentReferenceHashMap$Segment, class "[Lconcurrentrefhashmap/ConcurrentReferenceHashMap$HashEntry;", int, class "[Lconcurrentrefhashmap/ConcurrentReferenceHashMap$HashEntry;", int, int, int ]
          stack = []
        frame_type = 254 /* append */
          offset_delta = 47
          locals = [ class concurrentrefhashmap/ConcurrentReferenceHashMap$HashEntry, class concurrentrefhashmap/ConcurrentReferenceHashMap$HashEntry, int ]
        frame_type = 254 /* append */
          offset_delta = 11
          locals = [ class concurrentrefhashmap/ConcurrentReferenceHashMap$HashEntry, int, class concurrentrefhashmap/ConcurrentReferenceHashMap$HashEntry ]
        frame_type = 29 /* same */
        frame_type = 250 /* chop */
          offset_delta = 9
        frame_type = 252 /* append */
          offset_delta = 9
          locals = [ class concurrentrefhashmap/ConcurrentReferenceHashMap$HashEntry ]
        frame_type = 252 /* append */
          offset_delta = 24
          locals = [ class java/lang/Object ]
        frame_type = 250 /* chop */
          offset_delta = 37
        frame_type = 255 /* full_frame */
          offset_delta = 9
          locals = [ class concurrentrefhashmap/ConcurrentReferenceHashMap$Segment, class "[Lconcurrentrefhashmap/ConcurrentReferenceHashMap$HashEntry;", int, class "[Lconcurrentrefhashmap/ConcurrentReferenceHashMap$HashEntry;", int, int, int ]
          stack = []
        frame_type = 250 /* chop */
          offset_delta = 5

  V remove(java.lang.Object, int, java.lang.Object, boolean);
    descriptor: (Ljava/lang/Object;ILjava/lang/Object;Z)Ljava/lang/Object;
    flags: (0x0000)
    Code:
      stack=5, locals=16, args_size=5
         0: aload_0
         1: invokevirtual #18                 // Method lock:()V
         4: iload         4
         6: ifne          13
         9: aload_0
        10: invokevirtual #19                 // Method removeStale:()V
        13: aload_0
        14: getfield      #22                 // Field count:I
        17: iconst_1
        18: isub
        19: istore        5
        21: aload_0
        22: getfield      #12                 // Field table:[Lconcurrentrefhashmap/ConcurrentReferenceHashMap$HashEntry;
        25: astore        6
        27: iload_2
        28: aload         6
        30: arraylength
        31: iconst_1
        32: isub
        33: iand
        34: istore        7
        36: aload         6
        38: iload         7
        40: aaload
        41: astore        8
        43: aload         8
        45: astore        9
        47: aload         9
        49: ifnull        98
        52: aload_1
        53: aload         9
        55: getfield      #36                 // Field concurrentrefhashmap/ConcurrentReferenceHashMap$HashEntry.keyRef:Ljava/lang/Object;
        58: if_acmpeq     98
        61: iload         4
        63: ifne          88
        66: iload_2
        67: aload         9
        69: getfield      #24                 // Field concurrentrefhashmap/ConcurrentReferenceHashMap$HashEntry.hash:I
        72: if_icmpne     88
        75: aload_0
        76: aload_1
        77: aload         9
        79: invokevirtual #25                 // Method concurrentrefhashmap/ConcurrentReferenceHashMap$HashEntry.key:()Ljava/lang/Object;
        82: invokespecial #26                 // Method keyEq:(Ljava/lang/Object;Ljava/lang/Object;)Z
        85: ifne          98
        88: aload         9
        90: getfield      #30                 // Field concurrentrefhashmap/ConcurrentReferenceHashMap$HashEntry.next:Lconcurrentrefhashmap/ConcurrentReferenceHashMap$HashEntry;
        93: astore        9
        95: goto          47
        98: aconst_null
        99: astore        10
       101: aload         9
       103: ifnull        219
       106: aload         9
       108: invokevirtual #20                 // Method concurrentrefhashmap/ConcurrentReferenceHashMap$HashEntry.value:()Ljava/lang/Object;
       111: astore        11
       113: aload_3
       114: ifnull        126
       117: aload_3
       118: aload         11
       120: invokevirtual #10                 // Method java/lang/Object.equals:(Ljava/lang/Object;)Z
       123: ifeq          219
       126: aload         11
       128: astore        10
       130: aload_0
       131: dup
       132: getfield      #33                 // Field modCount:I
       135: iconst_1
       136: iadd
       137: putfield      #33                 // Field modCount:I
       140: aload         9
       142: getfield      #30                 // Field concurrentrefhashmap/ConcurrentReferenceHashMap$HashEntry.next:Lconcurrentrefhashmap/ConcurrentReferenceHashMap$HashEntry;
       145: astore        12
       147: aload         8
       149: astore        13
       151: aload         13
       153: aload         9
       155: if_acmpeq     206
       158: aload         13
       160: invokevirtual #25                 // Method concurrentrefhashmap/ConcurrentReferenceHashMap$HashEntry.key:()Ljava/lang/Object;
       163: astore        14
       165: aload         14
       167: ifnonnull     176
       170: iinc          5, -1
       173: goto          196
       176: aload_0
       177: aload         14
       179: aload         13
       181: getfield      #24                 // Field concurrentrefhashmap/ConcurrentReferenceHashMap$HashEntry.hash:I
       184: aload         12
       186: aload         13
       188: invokevirtual #20                 // Method concurrentrefhashmap/ConcurrentReferenceHashMap$HashEntry.value:()Ljava/lang/Object;
       191: invokevirtual #34                 // Method newHashEntry:(Ljava/lang/Object;ILconcurrentrefhashmap/ConcurrentReferenceHashMap$HashEntry;Ljava/lang/Object;)Lconcurrentrefhashmap/ConcurrentReferenceHashMap$HashEntry;
       194: astore        12
       196: aload         13
       198: getfield      #30                 // Field concurrentrefhashmap/ConcurrentReferenceHashMap$HashEntry.next:Lconcurrentrefhashmap/ConcurrentReferenceHashMap$HashEntry;
       201: astore        13
       203: goto          151
       206: aload         6
       208: iload         7
       210: aload         12
       212: aastore
       213: aload_0
       214: iload         5
       216: putfield      #22                 // Field count:I
       219: aload         10
       221: astore        11
       223: aload_0
       224: invokevirtual #21                 // Method unlock:()V
       227: aload         11
       229: areturn
       230: astore        15
       232: aload_0
       233: invokevirtual #21                 // Method unlock:()V
       236: aload         15
       238: athrow
      Exception table:
         from    to  target type
             4   223   230   any
           230   232   230   any
      LineNumberTable:
        line 832: 0
        line 834: 4
        line 835: 9
        line 837: 13
        line 838: 21
        line 839: 27
        line 840: 36
        line 841: 43
        line 843: 47
        line 844: 79
        line 845: 88
        line 848: 98
        line 849: 101
        line 850: 106
        line 851: 113
        line 852: 126
        line 856: 130
        line 857: 140
        line 858: 147
        line 859: 158
        line 860: 165
        line 861: 170
        line 862: 173
        line 865: 176
        line 858: 196
        line 867: 206
        line 868: 213
        line 871: 219
        line 874: 223
        line 871: 227
        line 874: 230
        line 875: 236
      StackMapTable: number_of_entries = 11
        frame_type = 13 /* same */
        frame_type = 255 /* full_frame */
          offset_delta = 33
          locals = [ class concurrentrefhashmap/ConcurrentReferenceHashMap$Segment, class java/lang/Object, int, class java/lang/Object, int, int, class "[Lconcurrentrefhashmap/ConcurrentReferenceHashMap$HashEntry;", int, class concurrentrefhashmap/ConcurrentReferenceHashMap$HashEntry, class concurrentrefhashmap/ConcurrentReferenceHashMap$HashEntry ]
          stack = []
        frame_type = 40 /* same */
        frame_type = 9 /* same */
        frame_type = 253 /* append */
          offset_delta = 27
          locals = [ class java/lang/Object, class java/lang/Object ]
        frame_type = 253 /* append */
          offset_delta = 24
          locals = [ class concurrentrefhashmap/ConcurrentReferenceHashMap$HashEntry, class concurrentrefhashmap/ConcurrentReferenceHashMap$HashEntry ]
        frame_type = 252 /* append */
          offset_delta = 24
          locals = [ class java/lang/Object ]
        frame_type = 250 /* chop */
          offset_delta = 19
        frame_type = 250 /* chop */
          offset_delta = 9
        frame_type = 249 /* chop */
          offset_delta = 12
        frame_type = 255 /* full_frame */
          offset_delta = 10
          locals = [ class concurrentrefhashmap/ConcurrentReferenceHashMap$Segment, class java/lang/Object, int, class java/lang/Object, int ]
          stack = [ class java/lang/Throwable ]
    Signature: #115                         // (Ljava/lang/Object;ILjava/lang/Object;Z)TV;

  final void removeStale();
    descriptor: ()V
    flags: (0x0010) ACC_FINAL
    Code:
      stack=5, locals=2, args_size=1
         0: aload_0
         1: getfield      #15                 // Field refQueue:Ljava/lang/ref/ReferenceQueue;
         4: invokevirtual #37                 // Method java/lang/ref/ReferenceQueue.poll:()Ljava/lang/ref/Reference;
         7: checkcast     #38                 // class concurrentrefhashmap/ConcurrentReferenceHashMap$KeyReference
        10: dup
        11: astore_1
        12: ifnull        37
        15: aload_0
        16: aload_1
        17: invokeinterface #39,  1           // InterfaceMethod concurrentrefhashmap/ConcurrentReferenceHashMap$KeyReference.keyRef:()Ljava/lang/Object;
        22: aload_1
        23: invokeinterface #40,  1           // InterfaceMethod concurrentrefhashmap/ConcurrentReferenceHashMap$KeyReference.keyHash:()I
        28: aconst_null
        29: iconst_1
        30: invokevirtual #41                 // Method remove:(Ljava/lang/Object;ILjava/lang/Object;Z)Ljava/lang/Object;
        33: pop
        34: goto          0
        37: return
      LineNumberTable:
        line 880: 0
        line 881: 15
        line 883: 37
      StackMapTable: number_of_entries = 2
        frame_type = 0 /* same */
        frame_type = 252 /* append */
          offset_delta = 36
          locals = [ class concurrentrefhashmap/ConcurrentReferenceHashMap$KeyReference ]

  void clear();
    descriptor: ()V
    flags: (0x0000)
    Code:
      stack=3, locals=4, args_size=1
         0: aload_0
         1: getfield      #22                 // Field count:I
         4: ifeq          74
         7: aload_0
         8: invokevirtual #18                 // Method lock:()V
        11: aload_0
        12: getfield      #12                 // Field table:[Lconcurrentrefhashmap/ConcurrentReferenceHashMap$HashEntry;
        15: astore_1
        16: iconst_0
        17: istore_2
        18: iload_2
        19: aload_1
        20: arraylength
        21: if_icmpge     34
        24: aload_1
        25: iload_2
        26: aconst_null
        27: aastore
        28: iinc          2, 1
        31: goto          18
        34: aload_0
        35: dup
        36: getfield      #33                 // Field modCount:I
        39: iconst_1
        40: iadd
        41: putfield      #33                 // Field modCount:I
        44: aload_0
        45: new           #13                 // class java/lang/ref/ReferenceQueue
        48: dup
        49: invokespecial #14                 // Method java/lang/ref/ReferenceQueue."<init>":()V
        52: putfield      #15                 // Field refQueue:Ljava/lang/ref/ReferenceQueue;
        55: aload_0
        56: iconst_0
        57: putfield      #22                 // Field count:I
        60: aload_0
        61: invokevirtual #21                 // Method unlock:()V
        64: goto          74
        67: astore_3
        68: aload_0
        69: invokevirtual #21                 // Method unlock:()V
        72: aload_3
        73: athrow
        74: return
      Exception table:
         from    to  target type
            11    60    67   any
      LineNumberTable:
        line 886: 0
        line 887: 7
        line 889: 11
        line 890: 16
        line 891: 24
        line 890: 28
        line 893: 34
        line 895: 44
        line 896: 55
        line 899: 60
        line 900: 64
        line 899: 67
        line 900: 72
        line 902: 74
      StackMapTable: number_of_entries = 4
        frame_type = 253 /* append */
          offset_delta = 18
          locals = [ class "[Lconcurrentrefhashmap/ConcurrentReferenceHashMap$HashEntry;", int ]
        frame_type = 250 /* chop */
          offset_delta = 15
        frame_type = 255 /* full_frame */
          offset_delta = 32
          locals = [ class concurrentrefhashmap/ConcurrentReferenceHashMap$Segment ]
          stack = [ class java/lang/Throwable ]
        frame_type = 6 /* same */
}
Signature: #119                         // <K:Ljava/lang/Object;V:Ljava/lang/Object;>Ljava/util/concurrent/locks/ReentrantLock;Ljava/io/Serializable;
SourceFile: "ConcurrentReferenceHashMap.java"
InnerClasses:
  static final #54= #16 of #1;            // HashEntry=class concurrentrefhashmap/ConcurrentReferenceHashMap$HashEntry of class concurrentrefhashmap/ConcurrentReferenceHashMap
  public static final #66= #65 of #1;     // ReferenceType=class concurrentrefhashmap/ConcurrentReferenceHashMap$ReferenceType of class concurrentrefhashmap/ConcurrentReferenceHashMap
  static final #76= #9 of #1;             // Segment=class concurrentrefhashmap/ConcurrentReferenceHashMap$Segment of class concurrentrefhashmap/ConcurrentReferenceHashMap
  static #158= #38 of #1;                 // KeyReference=class concurrentrefhashmap/ConcurrentReferenceHashMap$KeyReference of class concurrentrefhashmap/ConcurrentReferenceHashMap
