Classfile /Users/mw/Projects/slang-braindump/.jar/jar11/assemble/slang-braindump/assemble/content/org/scalactic/exceptions/NullArgumentException.class
  Last modified May 29, 2022; size 882 bytes
  SHA-256 checksum cd2cad737286274be7bb9eaab9cf878a590e6b5ea918ee14fd7ce37117946899
  Compiled from "NullArgumentException.scala"
public class org.scalactic.exceptions.NullArgumentException extends java.lang.IllegalArgumentException
  minor version: 0
  major version: 52
  flags: (0x0021) ACC_PUBLIC, ACC_SUPER
  this_class: #2                          // org/scalactic/exceptions/NullArgumentException
  super_class: #4                         // java/lang/IllegalArgumentException
  interfaces: 0, fields: 0, methods: 1, attributes: 4
Constant pool:
   #1 = Utf8               org/scalactic/exceptions/NullArgumentException
   #2 = Class              #1             // org/scalactic/exceptions/NullArgumentException
   #3 = Utf8               java/lang/IllegalArgumentException
   #4 = Class              #3             // java/lang/IllegalArgumentException
   #5 = Utf8               NullArgumentException.scala
   #6 = Utf8               Lscala/reflect/ScalaSignature;
   #7 = Utf8               bytes
   #8 = Utf8               \u0006\u0005!2Aa\u0001\u0003\u0001\u0017!A!\u0004\u0001B\u0001B\u0003%1\u0004C\u0003$\u0001\u0011\u0005AEA\u000bOk2d\u0017I]4v[\u0016tG/\u0012=dKB$\u0018n\u001c8\u000b\u0005\u00151\u0011AC3yG\u0016\u0004H/[8og*\u0011q\u0001C\u0001\ng\u000e\fG.Y2uS\u000eT\u0011!C\u0001\u0004_J<7\u0001A\n\u0003\u00011\u0001\"!D\f\u000f\u00059!bBA\b\u0013\u001b\u0005\u0001\"BA\t\u000b\u0003\u0019a$o\\8u}%\t1#A\u0003tG\u0006d\u0017-\u0003\u0002\u0016-\u00059\u0001/Y2lC\u001e,\'\"A\n\n\u0005aI\"\u0001G%mY\u0016<\u0017\r\\!sOVlWM\u001c;Fq\u000e,\u0007\u000f^5p]*\u0011QCF\u0001\b[\u0016\u001c8/Y4f!\ta\u0002E\u0004\u0002\u001e=A\u0011qBF\u0005\u0003?Y\ta\u0001\u0015:fI\u00164\u0017BA\u0011#\u0005\u0019\u0019FO]5oO*\u0011qDF\u0001\u0007y%t\u0017\u000e\u001e \u0015\u0005\u0015:\u0003C\u0001\u0014\u0001\u001b\u0005!\u0001\"\u0002\u000e\u0003\u0001\u0004Y\u0002
   #9 = Utf8               <init>
  #10 = Utf8               (Ljava/lang/String;)V
  #11 = Utf8               message
  #12 = NameAndType        #9:#10         // "<init>":(Ljava/lang/String;)V
  #13 = Methodref          #4.#12         // java/lang/IllegalArgumentException."<init>":(Ljava/lang/String;)V
  #14 = Utf8               this
  #15 = Utf8               Lorg/scalactic/exceptions/NullArgumentException;
  #16 = Utf8               Ljava/lang/String;
  #17 = Utf8               Code
  #18 = Utf8               LineNumberTable
  #19 = Utf8               LocalVariableTable
  #20 = Utf8               MethodParameters
  #21 = Utf8               SourceFile
  #22 = Utf8               RuntimeVisibleAnnotations
  #23 = Utf8               ScalaInlineInfo
  #24 = Utf8               ScalaSig
{
  public org.scalactic.exceptions.NullArgumentException(java.lang.String);
    descriptor: (Ljava/lang/String;)V
    flags: (0x0001) ACC_PUBLIC
    Code:
      stack=2, locals=2, args_size=2
         0: aload_0
         1: aload_1
         2: invokespecial #13                 // Method java/lang/IllegalArgumentException."<init>":(Ljava/lang/String;)V
         5: return
      LineNumberTable:
        line 31: 0
      LocalVariableTable:
        Start  Length  Slot  Name   Signature
            0       6     0  this   Lorg/scalactic/exceptions/NullArgumentException;
            0       6     1 message   Ljava/lang/String;
    MethodParameters:
      Name                           Flags
      message                        final
}
SourceFile: "NullArgumentException.scala"
RuntimeVisibleAnnotations:
  0: #6(#7=s#8)
    scala.reflect.ScalaSignature(
      bytes="\u0006\u0005!2Aa\u0001\u0003\u0001\u0017!A!\u0004\u0001B\u0001B\u0003%1\u0004C\u0003$\u0001\u0011\u0005AEA\u000bOk2d\u0017I]4v[\u0016tG/\u0012=dKB$\u0018n\u001c8\u000b\u0005\u00151\u0011AC3yG\u0016\u0004H/[8og*\u0011q\u0001C\u0001\ng\u000e\fG.Y2uS\u000eT\u0011!C\u0001\u0004_J<7\u0001A\n\u0003\u00011\u0001\"!D\f\u000f\u00059!bBA\b\u0013\u001b\u0005\u0001\"BA\t\u000b\u0003\u0019a$o\\8u}%\t1#A\u0003tG\u0006d\u0017-\u0003\u0002\u0016-\u00059\u0001/Y2lC\u001e,\'\"A\n\n\u0005aI\"\u0001G%mY\u0016<\u0017\r\\!sOVlWM\u001c;Fq\u000e,\u0007\u000f^5p]*\u0011QCF\u0001\b[\u0016\u001c8/Y4f!\ta\u0002E\u0004\u0002\u001e=A\u0011qBF\u0005\u0003?Y\ta\u0001\u0015:fI\u00164\u0017BA\u0011#\u0005\u0019\u0019FO]5oO*\u0011qDF\u0001\u0007y%t\u0017\u000e\u001e \u0015\u0005\u0015:\u0003C\u0001\u0014\u0001\u001b\u0005!\u0001\"\u0002\u000e\u0003\u0001\u0004Y\u0002"
    )
  ScalaInlineInfo: length = 0x9 (unknown attribute)
   01 00 00 01 00 09 00 0A 00
  ScalaSig: length = 0x3 (unknown attribute)
   05 02 00
