Classfile /Users/mw/Projects/slang-braindump/.jar/jar8/assemble/slang-braindump/assemble/content/com/zaxxer/nuprocess/windows/NuWinNT$PROCESS_INFORMATION.class
  Last modified May 29, 2022; size 1046 bytes
  SHA-256 checksum f794c9fb2b7de20cff68050bafe586653f0e5a677a568534f1de889b9b62d631
  Compiled from "NuWinNT.java"
public class com.zaxxer.nuprocess.windows.NuWinNT$PROCESS_INFORMATION extends com.sun.jna.Structure
  minor version: 0
  major version: 51
  flags: (0x0021) ACC_PUBLIC, ACC_SUPER
  this_class: #8                          // com/zaxxer/nuprocess/windows/NuWinNT$PROCESS_INFORMATION
  super_class: #9                         // com/sun/jna/Structure
  interfaces: 0, fields: 4, methods: 2, attributes: 2
Constant pool:
   #1 = Methodref          #9.#35         // com/sun/jna/Structure."<init>":()V
   #2 = Class              #36            // java/lang/String
   #3 = String             #10            // hProcess
   #4 = String             #15            // hThread
   #5 = String             #16            // dwProcessId
   #6 = String             #20            // dwThreadId
   #7 = Methodref          #37.#38        // java/util/Arrays.asList:([Ljava/lang/Object;)Ljava/util/List;
   #8 = Class              #40            // com/zaxxer/nuprocess/windows/NuWinNT$PROCESS_INFORMATION
   #9 = Class              #41            // com/sun/jna/Structure
  #10 = Utf8               hProcess
  #11 = Class              #42            // com/zaxxer/nuprocess/windows/NuWinNT$HANDLE
  #12 = Utf8               HANDLE
  #13 = Utf8               InnerClasses
  #14 = Utf8               Lcom/zaxxer/nuprocess/windows/NuWinNT$HANDLE;
  #15 = Utf8               hThread
  #16 = Utf8               dwProcessId
  #17 = Class              #43            // com/zaxxer/nuprocess/windows/NuWinNT$DWORD
  #18 = Utf8               DWORD
  #19 = Utf8               Lcom/zaxxer/nuprocess/windows/NuWinNT$DWORD;
  #20 = Utf8               dwThreadId
  #21 = Utf8               <init>
  #22 = Utf8               ()V
  #23 = Utf8               Code
  #24 = Utf8               LineNumberTable
  #25 = Utf8               LocalVariableTable
  #26 = Utf8               this
  #27 = Utf8               PROCESS_INFORMATION
  #28 = Utf8               Lcom/zaxxer/nuprocess/windows/NuWinNT$PROCESS_INFORMATION;
  #29 = Utf8               getFieldOrder
  #30 = Utf8               ()Ljava/util/List;
  #31 = Utf8               Signature
  #32 = Utf8               ()Ljava/util/List<Ljava/lang/String;>;
  #33 = Utf8               SourceFile
  #34 = Utf8               NuWinNT.java
  #35 = NameAndType        #21:#22        // "<init>":()V
  #36 = Utf8               java/lang/String
  #37 = Class              #44            // java/util/Arrays
  #38 = NameAndType        #45:#46        // asList:([Ljava/lang/Object;)Ljava/util/List;
  #39 = Class              #47            // com/zaxxer/nuprocess/windows/NuWinNT
  #40 = Utf8               com/zaxxer/nuprocess/windows/NuWinNT$PROCESS_INFORMATION
  #41 = Utf8               com/sun/jna/Structure
  #42 = Utf8               com/zaxxer/nuprocess/windows/NuWinNT$HANDLE
  #43 = Utf8               com/zaxxer/nuprocess/windows/NuWinNT$DWORD
  #44 = Utf8               java/util/Arrays
  #45 = Utf8               asList
  #46 = Utf8               ([Ljava/lang/Object;)Ljava/util/List;
  #47 = Utf8               com/zaxxer/nuprocess/windows/NuWinNT
{
  public com.zaxxer.nuprocess.windows.NuWinNT$HANDLE hProcess;
    descriptor: Lcom/zaxxer/nuprocess/windows/NuWinNT$HANDLE;
    flags: (0x0001) ACC_PUBLIC

  public com.zaxxer.nuprocess.windows.NuWinNT$HANDLE hThread;
    descriptor: Lcom/zaxxer/nuprocess/windows/NuWinNT$HANDLE;
    flags: (0x0001) ACC_PUBLIC

  public com.zaxxer.nuprocess.windows.NuWinNT$DWORD dwProcessId;
    descriptor: Lcom/zaxxer/nuprocess/windows/NuWinNT$DWORD;
    flags: (0x0001) ACC_PUBLIC

  public com.zaxxer.nuprocess.windows.NuWinNT$DWORD dwThreadId;
    descriptor: Lcom/zaxxer/nuprocess/windows/NuWinNT$DWORD;
    flags: (0x0001) ACC_PUBLIC

  public com.zaxxer.nuprocess.windows.NuWinNT$PROCESS_INFORMATION();
    descriptor: ()V
    flags: (0x0001) ACC_PUBLIC
    Code:
      stack=1, locals=1, args_size=1
         0: aload_0
         1: invokespecial #1                  // Method com/sun/jna/Structure."<init>":()V
         4: return
      LineNumberTable:
        line 211: 0
      LocalVariableTable:
        Start  Length  Slot  Name   Signature
            0       5     0  this   Lcom/zaxxer/nuprocess/windows/NuWinNT$PROCESS_INFORMATION;

  protected java.util.List<java.lang.String> getFieldOrder();
    descriptor: ()Ljava/util/List;
    flags: (0x0004) ACC_PROTECTED
    Code:
      stack=4, locals=1, args_size=1
         0: iconst_4
         1: anewarray     #2                  // class java/lang/String
         4: dup
         5: iconst_0
         6: ldc           #3                  // String hProcess
         8: aastore
         9: dup
        10: iconst_1
        11: ldc           #4                  // String hThread
        13: aastore
        14: dup
        15: iconst_2
        16: ldc           #5                  // String dwProcessId
        18: aastore
        19: dup
        20: iconst_3
        21: ldc           #6                  // String dwThreadId
        23: aastore
        24: invokestatic  #7                  // Method java/util/Arrays.asList:([Ljava/lang/Object;)Ljava/util/List;
        27: areturn
      LineNumberTable:
        line 221: 0
      LocalVariableTable:
        Start  Length  Slot  Name   Signature
            0      28     0  this   Lcom/zaxxer/nuprocess/windows/NuWinNT$PROCESS_INFORMATION;
    Signature: #32                          // ()Ljava/util/List<Ljava/lang/String;>;
}
SourceFile: "NuWinNT.java"
InnerClasses:
  public static #12= #11 of #39;          // HANDLE=class com/zaxxer/nuprocess/windows/NuWinNT$HANDLE of class com/zaxxer/nuprocess/windows/NuWinNT
  public static #18= #17 of #39;          // DWORD=class com/zaxxer/nuprocess/windows/NuWinNT$DWORD of class com/zaxxer/nuprocess/windows/NuWinNT
  public static #27= #8 of #39;           // PROCESS_INFORMATION=class com/zaxxer/nuprocess/windows/NuWinNT$PROCESS_INFORMATION of class com/zaxxer/nuprocess/windows/NuWinNT
