Classfile /Users/mw/Projects/slang-braindump/.jar/jar8/assemble/slang-braindump/assemble/content/org/scalatest/flatspec/AnyFlatSpecLike.class
  Last modified May 29, 2022; size 26040 bytes
  SHA-256 checksum 4273871bb931abd8539e3e06c9e086c8a37dc5291e053b73a4fae11110d267d9
  Compiled from "AnyFlatSpecLike.scala"
public interface org.scalatest.flatspec.AnyFlatSpecLike extends org.scalatest.TestSuite,org.scalatest.TestRegistration,org.scalatest.verbs.ShouldVerb,org.scalatest.verbs.MustVerb,org.scalatest.verbs.CanVerb,org.scalatest.Informing,org.scalatest.Notifying,org.scalatest.Alerting,org.scalatest.Documenting
  minor version: 0
  major version: 52
  flags: (0x0601) ACC_PUBLIC, ACC_INTERFACE, ACC_ABSTRACT
  this_class: #2                          // org/scalatest/flatspec/AnyFlatSpecLike
  super_class: #4                         // java/lang/Object
  interfaces: 9, fields: 0, methods: 67, attributes: 6
Constant pool:
    #1 = Utf8               org/scalatest/flatspec/AnyFlatSpecLike
    #2 = Class              #1            // org/scalatest/flatspec/AnyFlatSpecLike
    #3 = Utf8               java/lang/Object
    #4 = Class              #3            // java/lang/Object
    #5 = Utf8               org/scalatest/TestSuite
    #6 = Class              #5            // org/scalatest/TestSuite
    #7 = Utf8               org/scalatest/TestRegistration
    #8 = Class              #7            // org/scalatest/TestRegistration
    #9 = Utf8               org/scalatest/verbs/ShouldVerb
   #10 = Class              #9            // org/scalatest/verbs/ShouldVerb
   #11 = Utf8               org/scalatest/verbs/MustVerb
   #12 = Class              #11           // org/scalatest/verbs/MustVerb
   #13 = Utf8               org/scalatest/verbs/CanVerb
   #14 = Class              #13           // org/scalatest/verbs/CanVerb
   #15 = Utf8               org/scalatest/Informing
   #16 = Class              #15           // org/scalatest/Informing
   #17 = Utf8               org/scalatest/Notifying
   #18 = Class              #17           // org/scalatest/Notifying
   #19 = Utf8               org/scalatest/Alerting
   #20 = Class              #19           // org/scalatest/Alerting
   #21 = Utf8               org/scalatest/Documenting
   #22 = Class              #21           // org/scalatest/Documenting
   #23 = Utf8               AnyFlatSpecLike.scala
   #24 = Utf8               Lorg/scalatest/Finders;
   #25 = Utf8               value
   #26 = Utf8               org.scalatest.finders.FlatSpecFinder
   #27 = Utf8               Lscala/reflect/ScalaSignature;
   #28 = Utf8               bytes
   #29 = Utf8               \u0006\u0005\u0011-ga\u00029r!\u0003\r\t\u0001\u001f\u0005\b\u0003{\u0001A\u0011AA \u0011%\t9\u0005\u0001b\u0001\n\u001b\tI\u0005C\u0004\u0002R\u0001!\t\"a\u0015\t\u000f\u0005m\u0003\u0001\"\u0005\u0002^!9\u0011Q\r\u0001\u0005\u0012\u0005\u001d\u0004bBA8\u0001\u0011E\u0011\u0011\u000f\u0005\b\u0003s\u0002AQBA>\u0011\u001d\ti\r\u0001C\u0003\u0003\u001fDq!!8\u0001\t\u001b\ty\u000eC\u0004\u0002l\u0002!)!!<\t\u000f\u0005m\b\u0001\"\u0003\u0002~\u001a1!Q\u0005\u0001\u000b\u0005OAqA!\u000b\r\t\u0003\u0011Y\u0003C\u0004\u000321!iAa\r\t\u000f\tmB\u0002\"\u0001\u0003>!I!Q\t\u0001C\u0002\u0013E!q\t\u0004\u0007\u0005\u0013\u0002!Ba\u0013\t\u0015\t5\u0013C!A!\u0002\u0013\t9\u000b\u0003\u0006\u0003PE\u0011\t\u0011)A\u0005\u0003OC!B!\u0015\u0012\u0005\u0003\u0005\u000b\u0011\u0002B\u0005\u0011\u001d\u0011I#\u0005C\u0001\u0005\'BqA!\u0018\u0012\t\u0003\u0011y\u0006C\u0004\u0003hE!\tA!\u001b\t\u000f\te\u0014\u0003\"\u0001\u0003|\u00191!1\u0011\u0001\u000b\u0005\u000bC!B!\u0014\u001a\u0005\u0003\u0005\u000b\u0011BAT\u0011)\u0011y%\u0007B\u0001B\u0003%\u0011q\u0015\u0005\b\u0005SIB\u0011\u0001BD\u0011\u001d\u0011i&\u0007C\u0001\u0005\u001fCqAa\u001a\u001a\t\u0003\u00119\nC\u0004\u0003ze!\tAa(\t\u000f\t\u001d\u0016\u0004\"\u0001\u0003*\u001a1!1\u0017\u0001\u000b\u0005kCqA!\u000b\"\t\u0003\u00119\fC\u0004\u0003<\u0006\"\tA!0\t\u000f\t\r\u0017\u0005\"\u0001\u0003F\"9!\u0011Z\u0011\u0005\u0002\t-\u0007b\u0002B^C\u0011\u0005!q\u001a\u0005\b\u0005\u0007\fC\u0011\u0001Bn\u0011\u001d\u0011I-\tC\u0001\u0005?D\u0011Ba9\u0001\u0005\u0004%\tB!:\u0007\r\t\u001d\bA\u0003Bu\u0011)\u0011iE\u000bB\u0001B\u0003%\u0011q\u0015\u0005\u000b\u0005\u001fR#\u0011!Q\u0001\n\u0005\u001d\u0006B\u0003B)U\t\u0005\t\u0015!\u0003\u0003\n!9!\u0011\u0006\u0016\u0005\u0002\t-\bb\u0002B/U\u0011\u0005!Q\u001f\u0005\b\u0005ORC\u0011\u0001B\u007f\r\u0019\u0019)\u0001\u0001\u0006\u0004\b!Q!QJ\u0019\u0003\u0002\u0003\u0006I!a*\t\u0015\t=\u0013G!A!\u0002\u0013\t9\u000bC\u0004\u0003*E\"\ta!\u0003\t\u000f\tu\u0013\u0007\"\u0001\u0004\u0012!9!qM\u0019\u0005\u0002\re\u0001b\u0002BTc\u0011\u00051\u0011\u0005\u0004\u0007\u0007O\u0001!b!\u000b\t\u000f\t%\u0002\b\"\u0001\u0004,!9!1\u0018\u001d\u0005\u0002\r=\u0002b\u0002Bbq\u0011\u000511\u0007\u0005\b\u0005\u0013DD\u0011AB\u001c\u0011%\u0011I\b\u0001b\u0001\n#\u0019YD\u0002\u0004\u0004>\u0001Q1q\b\u0005\u000b\u0005\u001br$\u0011!Q\u0001\n\u0005\u001d\u0006B\u0003B(}\t\u0005\t\u0015!\u0003\u0002(\"Q!\u0011\u000b \u0003\u0002\u0003\u0006IA!\u0003\t\u000f\t%b\b\"\u0001\u0004B!9!Q\f \u0005\u0002\r-\u0003b\u0002B4}\u0011\u000511\u000b\u0005\b\u0005srD\u0011AB.\r\u0019\u0019\u0019\u0007\u0001\u0006\u0004f!Q!Q\n$\u0003\u0002\u0003\u0006I!a*\t\u0015\t=cI!A!\u0002\u0013\t9\u000bC\u0004\u0003*\u0019#\taa\u001a\t\u000f\tuc\t\"\u0001\u0004p!9!q\r$\u0005\u0002\r]\u0004b\u0002B=\r\u0012\u00051q\u0010\u0005\b\u0005O3E\u0011ABD\r\u0019\u0019i\t\u0001\u0006\u0004\u0010\"9!\u0011\u0006(\u0005\u0002\rE\u0005b\u0002B^\u001d\u0012\u00051Q\u0013\u0005\b\u0005\u0007tE\u0011ABM\u0011\u001d\u0011IM\u0014C\u0001\u0007;CqAa/O\t\u0003\u0019\t\u000bC\u0004\u0003D:#\ta!*\t\u000f\t%g\n\"\u0001\u0004*\"I1Q\u0016\u0001C\u0002\u0013E1q\u0016\u0004\u0007\u0007c\u0003!ba-\t\u0015\rUvK!A!\u0002\u0013\u00199\fC\u0004\u0003*]#\ta!0\t\u000f\tus\u000b\"\u0001\u0004D\"9!\u0011P,\u0005\u0002\r-\u0007bBBj\u0001\u0011M1Q\u001b\u0004\u0007\u00073\u0004!ba7\t\u0015\ruWL!A!\u0002\u0013\u0019y\u000eC\u0004\u0003*u#\ta!:\t\u000f\tuS\f\"\u0001\u0004l\"9!\u0011P/\u0005\u0002\rM\bbBB~\u0001\u0011M1Q \u0005\n\t\u0003\u0001!\u0019!C\n\t\u0007A\u0011\u0002b\u0003\u0001\u0005\u0004%\u0019\u0002\"\u0004\t\u000f\u0011U\u0001\u0001\"\u0003\u0005\u0018!9!\u0011\u000b\u0001\u0005B\u0011\r\u0002b\u0002C\u0019\u0001\u0011EC1\u0007\u0005\b\t\u0013\u0002A\u0011\u000bC&\u0011\u001d!9\u0006\u0001C!\t3Bq\u0001b\u0017\u0001\t\u0003\"i\u0006C\u0005\u0005d\u0001\u0011\r\u0011\"\u0005\u0005f!IAq\r\u0001C\u0002\u0013\u0015C\u0011\u000e\u0005\b\t\u007f\u0002A\u0011\tCA\u0011%!)\nAI\u0001\n\u0003!9\n\u0003\b\u0005.\u0002\u0001\n1!A\u0001\n\u0013!y\u000b\".\u0003\u001f\u0005s\u0017P\u00127biN\u0003Xm\u0019\'jW\u0016T!A]:\u0002\u0011\u0019d\u0017\r^:qK\u000eT!\u0001^;\u0002\u0013M\u001c\u0017\r\\1uKN$(\"\u0001<\u0002\u0007=\u0014xm\u0001\u0001\u0014\'\u0001Ix0a\u0002\u0002\u000e\u0005e\u0011qDA\u0013\u0003W\t\t$a\u000e\u0011\u0005ilX\"A>\u000b\u0003q\fQa]2bY\u0006L!A`>\u0003\r\u0005s\u0017PU3g!\u0011\t\t!a\u0001\u000e\u0003ML1!!\u0002t\u0005%!Vm\u001d;Tk&$X\r\u0005\u0003\u0002\u0002\u0005%\u0011bAA\u0006g\n\u0001B+Z:u%\u0016<\u0017n\u001d;sCRLwN\u001c\t\u0005\u0003\u001f\t)\"\u0004\u0002\u0002\u0012)\u0019\u00111C:\u0002\u000bY,\'OY:\n\t\u0005]\u0011\u0011\u0003\u0002\u000b\'\"|W\u000f\u001c3WKJ\u0014\u0007\u0003BA\b\u00037IA!!\b\u0002\u0012\tAQ*^:u-\u0016\u0014(\r\u0005\u0003\u0002\u0010\u0005\u0005\u0012\u0002BA\u0012\u0003#\u0011qaQ1o-\u0016\u0014(\r\u0005\u0003\u0002\u0002\u0005\u001d\u0012bAA\u0015g\nI\u0011J\u001c4pe6Lgn\u001a\t\u0005\u0003\u0003\ti#C\u0002\u00020M\u0014\u0011BT8uS\u001aL\u0018N\\4\u0011\t\u0005\u0005\u00111G\u0005\u0004\u0003k\u0019(\u0001C!mKJ$\u0018N\\4\u0011\t\u0005\u0005\u0011\u0011H\u0005\u0004\u0003w\u0019(a\u0003#pGVlWM\u001c;j]\u001e\fa\u0001J5oSR$CCAA!!\rQ\u00181I\u0005\u0004\u0003\u000bZ(\u0001B+oSR\fa!\u001a8hS:,WCAA&!\u0011\t\t!!\u0014\n\u0007\u0005=3O\u0001\u0004F]\u001eLg.Z\u0001\u0005S:4w.\u0006\u0002\u0002VA!\u0011\u0011AA,\u0013\r\tIf\u001d\u0002\t\u0013:4wN]7fe\u0006!an\u001c;f+\t\ty\u0006\u0005\u0003\u0002\u0002\u0005\u0005\u0014bAA2g\nAaj\u001c;jM&,\'/A\u0003bY\u0016\u0014H/\u0006\u0002\u0002jA!\u0011\u0011AA6\u0013\r\tig\u001d\u0002\b\u00032,\'\u000f^3s\u0003\u0019i\u0017M]6vaV\u0011\u00111\u000f\t\u0005\u0003\u0003\t)(C\u0002\u0002xM\u0014!\u0002R8dk6,g\u000e^3s\u0003A\u0011XmZ5ti\u0016\u0014H+Z:u\u00136\u0004H\u000e\u0006\u0004\u0002~\u0005\r\u0016Q\u0018\u000b\u0007\u0003\u0003\ny(a$\t\u0011\u0005\u0005u\u0001\"a\u0001\u0003\u0007\u000bq\u0001^3ti\u001a+h\u000eE\u0003{\u0003\u000b\u000bI)C\u0002\u0002\bn\u0014\u0001\u0002\u00102z]\u0006lWM\u0010\t\u0004u\u0006-\u0015bAAGw\n\u0019\u0011I\\=\t\u000f\u0005Eu\u00011\u0001\u0002\u0014\u0006\u0019\u0001o\\:\u0011\t\u0005U\u0015qT\u0007\u0003\u0003/SA!!\'\u0002\u001c\u000611o\\;sG\u0016T1!!(v\u0003%\u00198-\u00197bGRL7-\u0003\u0003\u0002\"\u0006]%\u0001\u0003)pg&$\u0018n\u001c8\t\u000f\u0005\u0015v\u00011\u0001\u0002(\u0006AA/Z:u)\u0016DH\u000f\u0005\u0003\u0002*\u0006]f\u0002BAV\u0003g\u00032!!,|\u001b\t\tyKC\u0002\u00022^\fa\u0001\u0010:p_Rt\u0014bAA[w\u00061\u0001K]3eK\u001aLA!!/\u0002<\n11\u000b\u001e:j]\u001eT1!!.|\u0011\u001d\tyl\u0002a\u0001\u0003\u0003\f\u0001\u0002^3tiR\u000bwm\u001d\t\u0006u\u0006\r\u0017qY\u0005\u0004\u0003\u000b\\(A\u0003\u001fsKB,\u0017\r^3e}A!\u0011\u0011AAe\u0013\r\tYm\u001d\u0002\u0004)\u0006<\u0017\u0001\u0004:fO&\u001cH/\u001a:UKN$HCBAi\u00033\fY\u000e\u0006\u0003\u0002T\u0006]G\u0003BA!\u0003+Dq!!%\t\u0001\b\t\u0019\n\u0003\u0005\u0002\u0002\"!\t\u0019AAB\u0011\u001d\t)\u000b\u0003a\u0001\u0003OCq!a0\t\u0001\u0004\t\t-A\fsK\u001eL7\u000f^3s\u0013\u001etwN]3e)\u0016\u001cH/S7qYR1\u0011\u0011]At\u0003S$b!!\u0011\u0002d\u0006\u0015\b\u0002CAA\u0013\u0011\u0005\r!a!\t\u000f\u0005E\u0015\u00021\u0001\u0002\u0014\"9\u0011QU\u0005A\u0002\u0005\u001d\u0006bBA`\u0013\u0001\u0007\u0011\u0011Y\u0001\u0014e\u0016<\u0017n\u001d;fe&;gn\u001c:fIR+7\u000f\u001e\u000b\u0007\u0003_\f90!?\u0015\t\u0005E\u0018Q\u001f\u000b\u0005\u0003\u0003\n\u0019\u0010C\u0004\u0002\u0012*\u0001\u001d!a%\t\u0011\u0005\u0005%\u0002\"a\u0001\u0003\u0007Cq!!*\u000b\u0001\u0004\t9\u000bC\u0004\u0002@*\u0001\r!!1\u0002#I,w-[:uKJ$Vm\u001d;U_J+h\u000e\u0006\u0007\u0002B\u0005}(1\u0001B\u0004\u00057\u0011\u0019\u0003C\u0004\u0003\u0002-\u0001\r!a*\u0002\u0011M\u0004Xm\u0019+fqRDqA!\u0002\f\u0001\u0004\t9+\u0001\u0006nKRDw\u000e\u001a(b[\u0016Dq!a0\f\u0001\u0004\u0011I\u0001\u0005\u0004\u0003\f\tU\u0011q\u0019\b\u0005\u0005\u001b\u0011\tB\u0004\u0003\u0002.\n=\u0011\"\u0001?\n\u0007\tM10A\u0004qC\u000e\\\u0017mZ3\n\t\t]!\u0011\u0004\u0002\u0005\u0019&\u001cHOC\u0002\u0003\u0014mDq!!!\f\u0001\u0004\u0011i\u0002E\u0003{\u0005?\tI)C\u0002\u0003\"m\u0014\u0011BR;oGRLwN\u001c\u0019\t\u000f\u0005E5\u00021\u0001\u0002\u0014\na!)\u001a5bm&|\'oV8sIN\u0011A\"_\u0001\u0007y%t\u0017\u000e\u001e \u0015\u0005\t5\u0002c\u0001B\u0018\u00195\t\u0001!\u0001\u0004pM&k\u0007\u000f\u001c\u000b\u0007\u0003\u0003\u0012)D!\u000f\t\u000f\t]b\u00021\u0001\u0002(\u0006YA-Z:de&\u0004H/[8o\u0011\u001d\t\tJ\u0004a\u0001\u0003\'\u000b!a\u001c4\u0015\t\t}\"1\t\u000b\u0005\u0003\u0003\u0012\t\u0005C\u0004\u0002\u0012>\u0001\u001d!a%\t\u000f\t]r\u00021\u0001\u0002(\u0006A!-\u001a5bm&|\'/\u0006\u0002\u0003.\t!\u0012\n\u001e,fe\n\u001cFO]5oOR\u000bwmZ3e\u0003N\u001c\"!E=\u0002\tY,\'OY\u0001\u0005]\u0006lW-\u0001\u0003uC\u001e\u001cH\u0003\u0003B+\u0005/\u0012IFa\u0017\u0011\u0007\t=\u0012\u0003C\u0004\u0003NU\u0001\r!a*\t\u000f\t=S\u00031\u0001\u0002(\"9!\u0011K\u000bA\u0002\t%\u0011AA5o)\u0011\u0011\tG!\u001a\u0015\t\u0005\u0005#1\r\u0005\b\u0003#3\u00029AAJ\u0011!\t\tI\u0006CA\u0002\u0005\r\u0015AA5t)\u0011\u0011YGa\u001c\u0015\t\u0005\u0005#Q\u000e\u0005\b\u0003#;\u00029AAJ\u0011!\t\ti\u0006CA\u0002\tE\u0004#\u0002>\u0002\u0006\nM\u0004\u0003BA\u0001\u0005kJ1Aa\u001et\u0005A\u0001VM\u001c3j]\u001e\u001cF/\u0019;f[\u0016tG/\u0001\u0004jO:|\'/\u001a\u000b\u0005\u0005{\u0012\t\t\u0006\u0003\u0002B\t}\u0004bBAI1\u0001\u000f\u00111\u0013\u0005\t\u0003\u0003CB\u00111\u0001\u0002\u0004\na\u0011\n\u001e,fe\n\u001cFO]5oON\u0011\u0011$\u001f\u000b\u0007\u0005\u0013\u0013YI!$\u0011\u0007\t=\u0012\u0004C\u0004\u0003Nq\u0001\r!a*\t\u000f\t=C\u00041\u0001\u0002(R!!\u0011\u0013BK)\u0011\t\tEa%\t\u000f\u0005EU\u0004q\u0001\u0002\u0014\"A\u0011\u0011Q\u000f\u0005\u0002\u0004\t\u0019\t\u0006\u0003\u0003\u001a\nuE\u0003BA!\u00057Cq!!%\u001f\u0001\b\t\u0019\n\u0003\u0005\u0002\u0002z!\t\u0019\u0001B9)\u0011\u0011\tK!*\u0015\t\u0005\u0005#1\u0015\u0005\b\u0003#{\u00029AAJ\u0011!\t\ti\bCA\u0002\u0005\r\u0015\u0001\u0003;bO\u001e,G-Q:\u0015\r\tU#1\u0016BX\u0011\u001d\u0011i\u000b\ta\u0001\u0003\u000f\fABZ5sgR$Vm\u001d;UC\u001eDqA!-!\u0001\u0004\t\t-A\u0007pi\",\'\u000fV3tiR\u000bwm\u001d\u0002\u0007\u0013R<vN\u001d3\u0014\u0005\u0005JHC\u0001B]!\r\u0011y#I\u0001\u0007g\"|W\u000f\u001c3\u0015\t\t%%q\u0018\u0005\b\u0005\u0003\u001c\u0003\u0019AAT\u0003\u0019\u0019HO]5oO\u0006!Q.^:u)\u0011\u0011IIa2\t\u000f\t\u0005G\u00051\u0001\u0002(\u0006\u00191-\u00198\u0015\t\t%%Q\u001a\u0005\b\u0005\u0003,\u0003\u0019AAT)\u0011\u0011\tNa6\u0011\t\u0005=!1[\u0005\u0005\u0005+\f\tB\u0001\u0006CK\"\fg/Z,pe\u0012DqA!7\'\u0001\u0004\u0011\t.\u0001\u0006cK\"\fg/Z,pe\u0012$BA!5\u0003^\"9!\u0011\\\u0014A\u0002\tEG\u0003\u0002Bi\u0005CDqA!7)\u0001\u0004\u0011\t.\u0001\u0002jiV\u0011!\u0011\u0018\u0002\u0019\u0013\u001etwN]3WKJ\u00147\u000b\u001e:j]\u001e$\u0016mZ4fI\u0006\u001b8C\u0001\u0016z)!\u0011iOa<\u0003r\nM\bc\u0001B\u0018U!9!Q\n\u0018A\u0002\u0005\u001d\u0006b\u0002B(]\u0001\u0007\u0011q\u0015\u0005\b\u0005#r\u0003\u0019\u0001B\u0005)\u0011\u00119Pa?\u0015\t\u0005\u0005#\u0011 \u0005\b\u0003#{\u00039AAJ\u0011!\t\ti\fCA\u0002\u0005\rE\u0003\u0002B\u0000\u0007\u0007!B!!\u0011\u0004\u0002!9\u0011\u0011\u0013\u0019A\u0004\u0005M\u0005\u0002CAAa\u0011\u0005\rA!\u001d\u0003!%;gn\u001c:f-\u0016\u0014(m\u0015;sS:<7CA\u0019z)\u0019\u0019Ya!\u0004\u0004\u0010A\u0019!qF\u0019\t\u000f\t5C\u00071\u0001\u0002(\"9!q\n\u001bA\u0002\u0005\u001dF\u0003BB\n\u0007/!B!!\u0011\u0004\u0016!9\u0011\u0011S\u001bA\u0004\u0005M\u0005\u0002CAAk\u0011\u0005\r!a!\u0015\t\rm1q\u0004\u000b\u0005\u0003\u0003\u001ai\u0002C\u0004\u0002\u0012Z\u0002\u001d!a%\t\u0011\u0005\u0005e\u0007\"a\u0001\u0005c\"bA!<\u0004$\r\u0015\u0002b\u0002BWo\u0001\u0007\u0011q\u0019\u0005\b\u0005c;\u0004\u0019AAa\u0005)IuM\\8sK^{\'\u000fZ\n\u0003qe$\"a!\f\u0011\u0007\t=\u0002\b\u0006\u0003\u0004\f\rE\u0002b\u0002Bau\u0001\u0007\u0011q\u0015\u000b\u0005\u0007\u0017\u0019)\u0004C\u0004\u0003Bn\u0002\r!a*\u0015\t\r-1\u0011\b\u0005\b\u0005\u0003d\u0004\u0019AAT+\t\u0019iC\u0001\fUQ\u0016Lh+\u001a:c\'R\u0014\u0018N\\4UC\u001e<W\rZ!t\'\tq\u0014\u0010\u0006\u0005\u0004D\r\u00153qIB%!\r\u0011yC\u0010\u0005\b\u0005\u001b\u0012\u0005\u0019AAT\u0011\u001d\u0011yE\u0011a\u0001\u0003OCqA!\u0015C\u0001\u0004\u0011I\u0001\u0006\u0003\u0004N\rEC\u0003BA!\u0007\u001fBq!!%D\u0001\b\t\u0019\n\u0003\u0005\u0002\u0002\u000e#\t\u0019AAB)\u0011\u0019)f!\u0017\u0015\t\u0005\u00053q\u000b\u0005\b\u0003##\u00059AAJ\u0011!\t\t\t\u0012CA\u0002\tED\u0003BB/\u0007C\"B!!\u0011\u0004`!9\u0011\u0011S#A\u0004\u0005M\u0005\u0002CAA\u000b\u0012\u0005\r!a!\u0003\u001dQCW-\u001f,fe\n\u001cFO]5oON\u0011a)\u001f\u000b\u0007\u0007S\u001aYg!\u001c\u0011\u0007\t=b\tC\u0004\u0003N%\u0003\r!a*\t\u000f\t=\u0013\n1\u0001\u0002(R!1\u0011OB;)\u0011\t\tea\u001d\t\u000f\u0005E%\nq\u0001\u0002\u0014\"A\u0011\u0011\u0011&\u0005\u0002\u0004\t\u0019\t\u0006\u0003\u0004z\ruD\u0003BA!\u0007wBq!!%L\u0001\b\t\u0019\n\u0003\u0005\u0002\u0002.#\t\u0019\u0001B9)\u0011\u0019\ti!\"\u0015\t\u0005\u000531\u0011\u0005\b\u0003#c\u00059AAJ\u0011!\t\t\t\u0014CA\u0002\u0005\rEC\u0002B+\u0007\u0013\u001bY\tC\u0004\u0003.6\u0003\r!a2\t\u000f\tEV\n1\u0001\u0002B\nAA\u000b[3z/>\u0014Hm\u0005\u0002OsR\u001111\u0013\t\u0004\u0005_qE\u0003\u0002BE\u0007/CqA!1Q\u0001\u0004\t9\u000b\u0006\u0003\u0003\n\u000em\u0005b\u0002Ba#\u0002\u0007\u0011q\u0015\u000b\u0005\u0005\u0013\u001by\nC\u0004\u0003BJ\u0003\r!a*\u0015\t\tE71\u0015\u0005\b\u00053\u001c\u0006\u0019\u0001Bi)\u0011\u0011\tna*\t\u000f\teG\u000b1\u0001\u0003RR!!\u0011[BV\u0011\u001d\u0011I.\u0016a\u0001\u0005#\fA\u0001\u001e5fsV\u001111\u0013\u0002\u0013\u0013:\fe\u000eZ%h]>\u0014X-T3uQ>$7o\u0005\u0002Xs\u0006Q\"/Z:vYR|em\u0015;sS:<\u0007+Y:tK\u0012$vNV3sEB!\u0011qBB]\u0013\u0011\u0019Y,!\u0005\u00035I+7/\u001e7u\u001f\u001a\u001cFO]5oOB\u000b7o]3e)>4VM\u001d2\u0015\t\r}6\u0011\u0019\t\u0004\u0005_9\u0006bBB[3\u0002\u00071q\u0017\u000b\u0005\u0007\u000b\u001cI\r\u0006\u0003\u0002B\r\u001d\u0007bBAI5\u0002\u000f\u00111\u0013\u0005\t\u0003\u0003SF\u00111\u0001\u0002\u0004R!1QZBi)\u0011\t\tea4\t\u000f\u0005E5\fq\u0001\u0002\u0014\"A\u0011\u0011Q.\u0005\u0002\u0004\t\u0019)A\u000ed_:4XM\u001d;U_&s\u0017I\u001c3JO:|\'/Z\'fi\"|Gm\u001d\u000b\u0005\u0007\u007f\u001b9\u000eC\u0004\u00046r\u0003\raa.\u0003?%s\u0017I\u001c3JO:|\'/Z\'fi\"|Gm]!gi\u0016\u0014H+Y4hK\u0012\f5o\u0005\u0002^s\u0006Q\"/Z:vYR|e\rV1hO\u0016$\u0017i]%om>\u001c\u0017\r^5p]B!\u0011qBBq\u0013\u0011\u0019\u0019/!\u0005\u00035I+7/\u001e7u\u001f\u001a$\u0016mZ4fI\u0006\u001b\u0018J\u001c<pG\u0006$\u0018n\u001c8\u0015\t\r\u001d8\u0011\u001e\t\u0004\u0005_i\u0006bBBo?\u0002\u00071q\u001c\u000b\u0005\u0007[\u001c\t\u0010\u0006\u0003\u0002B\r=\bbBAIA\u0002\u000f\u00111\u0013\u0005\t\u0003\u0003\u0003G\u00111\u0001\u0002\u0004R!1Q_B})\u0011\t\tea>\t\u000f\u0005E\u0015\rq\u0001\u0002\u0014\"A\u0011\u0011Q1\u0005\u0002\u0004\t\u0019)\u0001\u0015d_:4XM\u001d;U_&s\u0017I\u001c3JO:|\'/Z\'fi\"|Gm]!gi\u0016\u0014H+Y4hK\u0012\f5\u000f\u0006\u0003\u0004h\u000e}\bbBBoE\u0002\u00071q\\\u0001\"g\"|\'\u000f\u001e5b]\u0012$Vm\u001d;SK\u001eL7\u000f\u001e:bi&|gNR;oGRLwN\\\u000b\u0003\t\u000b\u0001B!a\u0004\u0005\b%!A\u0011BA\t\u0005i\u0019FO]5oOZ+\'OY*ue&tw-\u00138w_\u000e\fG/[8o\u0003\u001d\u001a\bn\u001c:uQ\u0006tGm\u00155be\u0016$G+Z:u%\u0016<\u0017n\u001d;sCRLwN\u001c$v]\u000e$\u0018n\u001c8\u0016\u0005\u0011=\u0001\u0003BA\b\t#IA\u0001b\u0005\u0002\u0012\tq2\u000b\u001e:j]\u001e4VM\u001d2CK\"\fg/\u001a\'jW\u0016LeN^8dCRLwN\\\u0001\u0015e\u0016<\u0017n\u001d;feR+7\u000f\u001e+p\u0013\u001etwN]3\u0015\u0019\u0005\u0005C\u0011\u0004C\u000e\t;!y\u0002\"\t\t\u000f\t\u0005Q\r1\u0001\u0002(\"9\u0011qX3A\u0002\t%\u0001b\u0002B\u0003K\u0002\u0007\u0011q\u0015\u0005\b\u0003\u0003+\u0007\u0019\u0001B\u000f\u0011\u001d\t\t*\u001aa\u0001\u0003\'+\"\u0001\"\n\u0011\u0011\u0005%FqEAT\tWIA\u0001\"\u000b\u0002<\n\u0019Q*\u00199\u0011\r\u0005%FQFAT\u0013\u0011!y#a/\u0003\u0007M+G/A\u0004sk:$Vm\u001d;\u0015\r\u0011UB1\bC !\u0011\t\t\u0001b\u000e\n\u0007\u0011e2O\u0001\u0004Ti\u0006$Xo\u001d\u0005\b\t{9\u0007\u0019AAT\u0003!!Xm\u001d;OC6,\u0007b\u0002C!O\u0002\u0007A1I\u0001\u0005CJ<7\u000f\u0005\u0003\u0002\u0002\u0011\u0015\u0013b\u0001C$g\n!\u0011I]4t\u0003!\u0011XO\u001c+fgR\u001cHC\u0002C\u001b\t\u001b\")\u0006C\u0004\u0005>!\u0004\r\u0001b\u0014\u0011\u000bi$\t&a*\n\u0007\u0011M3P\u0001\u0004PaRLwN\u001c\u0005\b\t\u0003B\u0007\u0019\u0001C\"\u0003%!Xm\u001d;OC6,7/\u0006\u0002\u0005,\u0005\u0019!/\u001e8\u0015\r\u0011UBq\fC1\u0011\u001d!iD\u001ba\u0001\t\u001fBq\u0001\"\u0011k\u0001\u0004!\u0019%\u0001\u0004cK\"\fg/Z\u000b\u0003\u0005#\f\u0011b\u001d;zY\u0016t\u0015-\\3\u0016\u0005\u0005\u001d\u0006f\u00037\u0005n\u0011MDQ\u000fC=\tw\u00022A\u001fC8\u0013\r!\th\u001f\u0002\u000bI\u0016\u0004(/Z2bi\u0016$\u0017aB7fgN\fw-Z\u0011\u0003\to\nA\u0010\u00165fAM$\u0018\u0010\\3OC6,\u0007\u0005\\5gK\u000eL8\r\\3![\u0016$\bn\u001c3!Q\u0006\u001c\bEY3f]\u0002\"W\r\u001d:fG\u0006$X\r\u001a\u0011b]\u0012\u0004s/\u001b7mA\t,\u0007E]3n_Z,G\rI5oA\u0005\u0004c-\u001e;ve\u0016\u0004c/\u001a:tS>t\u0007e\u001c4!\'\u000e\fG.\u0019+fgR\u0004s/\u001b;iA9|\u0007E]3qY\u0006\u001cW-\\3oi:\nQa]5oG\u0016\f#\u0001\" \u0002\u000bMr\u0013G\f\u0019\u0002\u0017Q,7\u000f\u001e#bi\u00064uN\u001d\u000b\u0007\t\u0007#I\tb#\u0011\t\u0005\u0005AQQ\u0005\u0004\t\u000f\u001b(\u0001\u0003+fgR$\u0015\r^1\t\u000f\u0011uR\u000e1\u0001\u0002(\"IAQR7\u0011\u0002\u0003\u0007AqR\u0001\ri\",7i\u001c8gS\u001el\u0015\r\u001d\t\u0005\u0003\u0003!\t*C\u0002\u0005\u0014N\u0014\u0011bQ8oM&<W*\u00199\u0002+Q,7\u000f\u001e#bi\u00064uN\u001d\u0013eK\u001a\fW\u000f\u001c;%eU\u0011A\u0011\u0014\u0016\u0005\t\u001f#Yj\u000b\u0002\u0005\u001eB!Aq\u0014CU\u001b\t!\tK\u0003\u0003\u0005$\u0012\u0015\u0016!C;oG\",7m[3e\u0015\r!9k_\u0001\u000bC:tw\u000e^1uS>t\u0017\u0002\u0002CV\tC\u0013\u0011#\u001e8dQ\u0016\u001c7.\u001a3WCJL\u0017M\\2f\u0003%\u0019X\u000f]3sII,h\u000e\u0006\u0004\u00056\u0011EF1\u0017\u0005\b\t{y\u0007\u0019\u0001C(\u0011\u001d!\te\u001ca\u0001\t\u0007JA\u0001b\u0017\u00058&\u0019A\u0011X:\u0003\u000bM+\u0018\u000e^3)\u000f\u0001!i\fb1\u0005FB!\u0011\u0011\u0001C`\u0013\r!\tm\u001d\u0002\b\r&tG-\u001a:t\u0003\u00151\u0018\r\\;fY\t!9-\t\u0002\u0005J\u0006!sN]4/g\u000e\fG.\u0019;fgRtc-\u001b8eKJ\u001chF\u00127biN\u0003Xm\u0019$j]\u0012,\'\u000f
   #30 = Utf8               java/lang/invoke/MethodHandles$Lookup
   #31 = Class              #30           // java/lang/invoke/MethodHandles$Lookup
   #32 = Utf8               java/lang/invoke/MethodHandles
   #33 = Class              #32           // java/lang/invoke/MethodHandles
   #34 = Utf8               Lookup
   #35 = Utf8               org/scalatest/SuperEngine$Bundle
   #36 = Class              #35           // org/scalatest/SuperEngine$Bundle
   #37 = Utf8               org/scalatest/SuperEngine
   #38 = Class              #37           // org/scalatest/SuperEngine
   #39 = Utf8               Bundle
   #40 = Utf8               org/scalatest/SuperEngine$TestLeaf
   #41 = Class              #40           // org/scalatest/SuperEngine$TestLeaf
   #42 = Utf8               TestLeaf
   #43 = Utf8               org/scalatest/TestSuite$NoArgTest
   #44 = Class              #43           // org/scalatest/TestSuite$NoArgTest
   #45 = Utf8               NoArgTest
   #46 = Utf8               org/scalatest/flatspec/AnyFlatSpecLike$$anon$1
   #47 = Class              #46           // org/scalatest/flatspec/AnyFlatSpecLike$$anon$1
   #48 = Utf8               org/scalatest/flatspec/AnyFlatSpecLike$$anon$4
   #49 = Class              #48           // org/scalatest/flatspec/AnyFlatSpecLike$$anon$4
   #50 = Utf8               org/scalatest/flatspec/AnyFlatSpecLike$$anon$5
   #51 = Class              #50           // org/scalatest/flatspec/AnyFlatSpecLike$$anon$5
   #52 = Utf8               org/scalatest/flatspec/AnyFlatSpecLike$BehaviorWord
   #53 = Class              #52           // org/scalatest/flatspec/AnyFlatSpecLike$BehaviorWord
   #54 = Utf8               BehaviorWord
   #55 = Utf8               org/scalatest/flatspec/AnyFlatSpecLike$IgnoreVerbString
   #56 = Class              #55           // org/scalatest/flatspec/AnyFlatSpecLike$IgnoreVerbString
   #57 = Utf8               IgnoreVerbString
   #58 = Utf8               org/scalatest/flatspec/AnyFlatSpecLike$IgnoreVerbStringTaggedAs
   #59 = Class              #58           // org/scalatest/flatspec/AnyFlatSpecLike$IgnoreVerbStringTaggedAs
   #60 = Utf8               IgnoreVerbStringTaggedAs
   #61 = Utf8               org/scalatest/flatspec/AnyFlatSpecLike$IgnoreWord
   #62 = Class              #61           // org/scalatest/flatspec/AnyFlatSpecLike$IgnoreWord
   #63 = Utf8               IgnoreWord
   #64 = Utf8               org/scalatest/flatspec/AnyFlatSpecLike$InAndIgnoreMethods
   #65 = Class              #64           // org/scalatest/flatspec/AnyFlatSpecLike$InAndIgnoreMethods
   #66 = Utf8               InAndIgnoreMethods
   #67 = Utf8               org/scalatest/flatspec/AnyFlatSpecLike$InAndIgnoreMethodsAfterTaggedAs
   #68 = Class              #67           // org/scalatest/flatspec/AnyFlatSpecLike$InAndIgnoreMethodsAfterTaggedAs
   #69 = Utf8               InAndIgnoreMethodsAfterTaggedAs
   #70 = Utf8               org/scalatest/flatspec/AnyFlatSpecLike$ItVerbString
   #71 = Class              #70           // org/scalatest/flatspec/AnyFlatSpecLike$ItVerbString
   #72 = Utf8               ItVerbString
   #73 = Utf8               org/scalatest/flatspec/AnyFlatSpecLike$ItVerbStringTaggedAs
   #74 = Class              #73           // org/scalatest/flatspec/AnyFlatSpecLike$ItVerbStringTaggedAs
   #75 = Utf8               ItVerbStringTaggedAs
   #76 = Utf8               org/scalatest/flatspec/AnyFlatSpecLike$ItWord
   #77 = Class              #76           // org/scalatest/flatspec/AnyFlatSpecLike$ItWord
   #78 = Utf8               ItWord
   #79 = Utf8               org/scalatest/flatspec/AnyFlatSpecLike$TheyVerbString
   #80 = Class              #79           // org/scalatest/flatspec/AnyFlatSpecLike$TheyVerbString
   #81 = Utf8               TheyVerbString
   #82 = Utf8               org/scalatest/flatspec/AnyFlatSpecLike$TheyVerbStringTaggedAs
   #83 = Class              #82           // org/scalatest/flatspec/AnyFlatSpecLike$TheyVerbStringTaggedAs
   #84 = Utf8               TheyVerbStringTaggedAs
   #85 = Utf8               org/scalatest/flatspec/AnyFlatSpecLike$TheyWord
   #86 = Class              #85           // org/scalatest/flatspec/AnyFlatSpecLike$TheyWord
   #87 = Utf8               TheyWord
   #88 = Utf8               org$scalatest$flatspec$AnyFlatSpecLike$_setter_$org$scalatest$flatspec$AnyFlatSpecLike$$engine_$eq
   #89 = Utf8               (Lorg/scalatest/Engine;)V
   #90 = Utf8               x$1
   #91 = Utf8               org$scalatest$flatspec$AnyFlatSpecLike$_setter_$behavior_$eq
   #92 = Utf8               (Lorg/scalatest/flatspec/AnyFlatSpecLike$BehaviorWord;)V
   #93 = Utf8               org$scalatest$flatspec$AnyFlatSpecLike$_setter_$it_$eq
   #94 = Utf8               (Lorg/scalatest/flatspec/AnyFlatSpecLike$ItWord;)V
   #95 = Utf8               org$scalatest$flatspec$AnyFlatSpecLike$_setter_$ignore_$eq
   #96 = Utf8               (Lorg/scalatest/flatspec/AnyFlatSpecLike$IgnoreWord;)V
   #97 = Utf8               org$scalatest$flatspec$AnyFlatSpecLike$_setter_$they_$eq
   #98 = Utf8               (Lorg/scalatest/flatspec/AnyFlatSpecLike$TheyWord;)V
   #99 = Utf8               org$scalatest$flatspec$AnyFlatSpecLike$_setter_$shorthandTestRegistrationFunction_$eq
  #100 = Utf8               (Lorg/scalatest/verbs/StringVerbStringInvocation;)V
  #101 = Utf8               org$scalatest$flatspec$AnyFlatSpecLike$_setter_$shorthandSharedTestRegistrationFunction_$eq
  #102 = Utf8               (Lorg/scalatest/verbs/StringVerbBehaveLikeInvocation;)V
  #103 = Utf8               org$scalatest$flatspec$AnyFlatSpecLike$_setter_$behave_$eq
  #104 = Utf8               (Lorg/scalatest/verbs/BehaveWord;)V
  #105 = Utf8               org$scalatest$flatspec$AnyFlatSpecLike$_setter_$styleName_$eq
  #106 = Utf8               (Ljava/lang/String;)V
  #107 = Utf8               org$scalatest$flatspec$AnyFlatSpecLike$$super$run
  #108 = Utf8               (Lscala/Option;Lorg/scalatest/Args;)Lorg/scalatest/Status;
  #109 = Utf8               testName
  #110 = Utf8               args
  #111 = Utf8               org$scalatest$flatspec$AnyFlatSpecLike$$engine
  #112 = Utf8               ()Lorg/scalatest/Engine;
  #113 = Utf8               info$
  #114 = Utf8               (Lorg/scalatest/flatspec/AnyFlatSpecLike;)Lorg/scalatest/Informer;
  #115 = Utf8               $this
  #116 = Utf8               info
  #117 = Utf8               ()Lorg/scalatest/Informer;
  #118 = NameAndType        #116:#117     // info:()Lorg/scalatest/Informer;
  #119 = InterfaceMethodref #2.#118       // org/scalatest/flatspec/AnyFlatSpecLike.info:()Lorg/scalatest/Informer;
  #120 = Utf8               Lorg/scalatest/flatspec/AnyFlatSpecLike;
  #121 = NameAndType        #111:#112     // org$scalatest$flatspec$AnyFlatSpecLike$$engine:()Lorg/scalatest/Engine;
  #122 = InterfaceMethodref #2.#121       // org/scalatest/flatspec/AnyFlatSpecLike.org$scalatest$flatspec$AnyFlatSpecLike$$engine:()Lorg/scalatest/Engine;
  #123 = Utf8               org/scalatest/Engine
  #124 = Class              #123          // org/scalatest/Engine
  #125 = Utf8               atomicInformer
  #126 = Utf8               ()Ljava/util/concurrent/atomic/AtomicReference;
  #127 = NameAndType        #125:#126     // atomicInformer:()Ljava/util/concurrent/atomic/AtomicReference;
  #128 = Methodref          #124.#127     // org/scalatest/Engine.atomicInformer:()Ljava/util/concurrent/atomic/AtomicReference;
  #129 = Utf8               java/util/concurrent/atomic/AtomicReference
  #130 = Class              #129          // java/util/concurrent/atomic/AtomicReference
  #131 = Utf8               get
  #132 = Utf8               ()Ljava/lang/Object;
  #133 = NameAndType        #131:#132     // get:()Ljava/lang/Object;
  #134 = Methodref          #130.#133     // java/util/concurrent/atomic/AtomicReference.get:()Ljava/lang/Object;
  #135 = Utf8               org/scalatest/Informer
  #136 = Class              #135          // org/scalatest/Informer
  #137 = Utf8               this
  #138 = Utf8               note$
  #139 = Utf8               (Lorg/scalatest/flatspec/AnyFlatSpecLike;)Lorg/scalatest/Notifier;
  #140 = Utf8               note
  #141 = Utf8               ()Lorg/scalatest/Notifier;
  #142 = NameAndType        #140:#141     // note:()Lorg/scalatest/Notifier;
  #143 = InterfaceMethodref #2.#142       // org/scalatest/flatspec/AnyFlatSpecLike.note:()Lorg/scalatest/Notifier;
  #144 = Utf8               atomicNotifier
  #145 = NameAndType        #144:#126     // atomicNotifier:()Ljava/util/concurrent/atomic/AtomicReference;
  #146 = Methodref          #124.#145     // org/scalatest/Engine.atomicNotifier:()Ljava/util/concurrent/atomic/AtomicReference;
  #147 = Utf8               org/scalatest/Notifier
  #148 = Class              #147          // org/scalatest/Notifier
  #149 = Utf8               alert$
  #150 = Utf8               (Lorg/scalatest/flatspec/AnyFlatSpecLike;)Lorg/scalatest/Alerter;
  #151 = Utf8               alert
  #152 = Utf8               ()Lorg/scalatest/Alerter;
  #153 = NameAndType        #151:#152     // alert:()Lorg/scalatest/Alerter;
  #154 = InterfaceMethodref #2.#153       // org/scalatest/flatspec/AnyFlatSpecLike.alert:()Lorg/scalatest/Alerter;
  #155 = Utf8               atomicAlerter
  #156 = NameAndType        #155:#126     // atomicAlerter:()Ljava/util/concurrent/atomic/AtomicReference;
  #157 = Methodref          #124.#156     // org/scalatest/Engine.atomicAlerter:()Ljava/util/concurrent/atomic/AtomicReference;
  #158 = Utf8               org/scalatest/Alerter
  #159 = Class              #158          // org/scalatest/Alerter
  #160 = Utf8               markup$
  #161 = Utf8               (Lorg/scalatest/flatspec/AnyFlatSpecLike;)Lorg/scalatest/Documenter;
  #162 = Utf8               markup
  #163 = Utf8               ()Lorg/scalatest/Documenter;
  #164 = NameAndType        #162:#163     // markup:()Lorg/scalatest/Documenter;
  #165 = InterfaceMethodref #2.#164       // org/scalatest/flatspec/AnyFlatSpecLike.markup:()Lorg/scalatest/Documenter;
  #166 = Utf8               atomicDocumenter
  #167 = NameAndType        #166:#126     // atomicDocumenter:()Ljava/util/concurrent/atomic/AtomicReference;
  #168 = Methodref          #124.#167     // org/scalatest/Engine.atomicDocumenter:()Ljava/util/concurrent/atomic/AtomicReference;
  #169 = Utf8               org/scalatest/Documenter
  #170 = Class              #169          // org/scalatest/Documenter
  #171 = Utf8               registerTestImpl
  #172 = Utf8               (Ljava/lang/String;Lscala/collection/immutable/Seq;Lscala/Function0;Lorg/scalactic/source/Position;)V
  #173 = Utf8               (Ljava/lang/String;Lscala/collection/immutable/Seq<Lorg/scalatest/Tag;>;Lscala/Function0<Ljava/lang/Object;>;Lorg/scalactic/source/Position;)V
  #174 = Utf8               testText
  #175 = Utf8               testTags
  #176 = Utf8               testFun
  #177 = Utf8               pos
  #178 = Utf8               org/scalatest/Transformer
  #179 = Class              #178          // org/scalatest/Transformer
  #180 = Utf8               <init>
  #181 = Utf8               (Lscala/Function0;)V
  #182 = NameAndType        #180:#181     // "<init>":(Lscala/Function0;)V
  #183 = Methodref          #179.#182     // org/scalatest/Transformer."<init>":(Lscala/Function0;)V
  #184 = MethodType         #132          //  ()Ljava/lang/Object;
  #185 = Utf8               $anonfun$registerTestImpl$1
  #186 = Utf8               ()Ljava/lang/String;
  #187 = NameAndType        #185:#186     // $anonfun$registerTestImpl$1:()Ljava/lang/String;
  #188 = InterfaceMethodref #2.#187       // org/scalatest/flatspec/AnyFlatSpecLike.$anonfun$registerTestImpl$1:()Ljava/lang/String;
  #189 = MethodHandle       6:#188        // REF_invokeStatic org/scalatest/flatspec/AnyFlatSpecLike.$anonfun$registerTestImpl$1:()Ljava/lang/String;
  #190 = MethodType         #186          //  ()Ljava/lang/String;
  #191 = Integer            5
  #192 = Integer            1
  #193 = Utf8               java/lang/invoke/LambdaMetafactory
  #194 = Class              #193          // java/lang/invoke/LambdaMetafactory
  #195 = Utf8               altMetafactory
  #196 = Utf8               (Ljava/lang/invoke/MethodHandles$Lookup;Ljava/lang/String;Ljava/lang/invoke/MethodType;[Ljava/lang/Object;)Ljava/lang/invoke/CallSite;
  #197 = NameAndType        #195:#196     // altMetafactory:(Ljava/lang/invoke/MethodHandles$Lookup;Ljava/lang/String;Ljava/lang/invoke/MethodType;[Ljava/lang/Object;)Ljava/lang/invoke/CallSite;
  #198 = Methodref          #194.#197     // java/lang/invoke/LambdaMetafactory.altMetafactory:(Ljava/lang/invoke/MethodHandles$Lookup;Ljava/lang/String;Ljava/lang/invoke/MethodType;[Ljava/lang/Object;)Ljava/lang/invoke/CallSite;
  #199 = MethodHandle       6:#198        // REF_invokeStatic java/lang/invoke/LambdaMetafactory.altMetafactory:(Ljava/lang/invoke/MethodHandles$Lookup;Ljava/lang/String;Ljava/lang/invoke/MethodType;[Ljava/lang/Object;)Ljava/lang/invoke/CallSite;
  #200 = Utf8               apply
  #201 = Utf8               ()Lscala/Function0;
  #202 = NameAndType        #200:#201     // apply:()Lscala/Function0;
  #203 = InvokeDynamic      #0:#202       // #0:apply:()Lscala/Function0;
  #204 = String             #23           // AnyFlatSpecLike.scala
  #205 = Utf8               registerTest
  #206 = String             #205          // registerTest
  #207 = Utf8               scala/None$
  #208 = Class              #207          // scala/None$
  #209 = Utf8               MODULE$
  #210 = Utf8               Lscala/None$;
  #211 = NameAndType        #209:#210     // MODULE$:Lscala/None$;
  #212 = Fieldref           #208.#211     // scala/None$.MODULE$:Lscala/None$;
  #213 = Utf8               scala/Some
  #214 = Class              #213          // scala/Some
  #215 = Utf8               (Ljava/lang/Object;)V
  #216 = NameAndType        #180:#215     // "<init>":(Ljava/lang/Object;)V
  #217 = Methodref          #214.#216     // scala/Some."<init>":(Ljava/lang/Object;)V
  #218 = Utf8               (Ljava/lang/String;Ljava/lang/Object;Lscala/Function0;Ljava/lang/String;Ljava/lang/String;IILscala/Option;Lscala/Option;Lscala/Option;Lscala/Option;Lscala/collection/immutable/Seq;)Ljava/lang/String;
  #219 = NameAndType        #205:#218     // registerTest:(Ljava/lang/String;Ljava/lang/Object;Lscala/Function0;Ljava/lang/String;Ljava/lang/String;IILscala/Option;Lscala/Option;Lscala/Option;Lscala/Option;Lscala/collection/immutable/Seq;)Ljava/lang/String;
  #220 = Methodref          #124.#219     // org/scalatest/Engine.registerTest:(Ljava/lang/String;Ljava/lang/Object;Lscala/Function0;Ljava/lang/String;Ljava/lang/String;IILscala/Option;Lscala/Option;Lscala/Option;Lscala/Option;Lscala/collection/immutable/Seq;)Ljava/lang/String;
  #221 = Utf8               stackDepthAdjustment
  #222 = Utf8               I
  #223 = Utf8               Ljava/lang/String;
  #224 = Utf8               Lscala/collection/immutable/Seq;
  #225 = Utf8               Lscala/Function0;
  #226 = Utf8               Lorg/scalactic/source/Position;
  #227 = Utf8               registerTest$
  #228 = Utf8               (Lorg/scalatest/flatspec/AnyFlatSpecLike;Ljava/lang/String;Lscala/collection/immutable/Seq;Lscala/Function0;Lorg/scalactic/source/Position;)V
  #229 = NameAndType        #205:#172     // registerTest:(Ljava/lang/String;Lscala/collection/immutable/Seq;Lscala/Function0;Lorg/scalactic/source/Position;)V
  #230 = InterfaceMethodref #2.#229       // org/scalatest/flatspec/AnyFlatSpecLike.registerTest:(Ljava/lang/String;Lscala/collection/immutable/Seq;Lscala/Function0;Lorg/scalactic/source/Position;)V
  #231 = NameAndType        #171:#172     // registerTestImpl:(Ljava/lang/String;Lscala/collection/immutable/Seq;Lscala/Function0;Lorg/scalactic/source/Position;)V
  #232 = InterfaceMethodref #2.#231       // org/scalatest/flatspec/AnyFlatSpecLike.registerTestImpl:(Ljava/lang/String;Lscala/collection/immutable/Seq;Lscala/Function0;Lorg/scalactic/source/Position;)V
  #233 = Utf8               registerIgnoredTestImpl
  #234 = Utf8               $anonfun$registerIgnoredTestImpl$1
  #235 = NameAndType        #234:#186     // $anonfun$registerIgnoredTestImpl$1:()Ljava/lang/String;
  #236 = InterfaceMethodref #2.#235       // org/scalatest/flatspec/AnyFlatSpecLike.$anonfun$registerIgnoredTestImpl$1:()Ljava/lang/String;
  #237 = MethodHandle       6:#236        // REF_invokeStatic org/scalatest/flatspec/AnyFlatSpecLike.$anonfun$registerIgnoredTestImpl$1:()Ljava/lang/String;
  #238 = InvokeDynamic      #1:#202       // #1:apply:()Lscala/Function0;
  #239 = Utf8               registerIgnoredTest
  #240 = String             #239          // registerIgnoredTest
  #241 = Utf8               (Ljava/lang/String;Ljava/lang/Object;Lscala/Function0;Ljava/lang/String;Ljava/lang/String;IILscala/Option;Lscala/Option;Lscala/collection/immutable/Seq;)V
  #242 = NameAndType        #239:#241     // registerIgnoredTest:(Ljava/lang/String;Ljava/lang/Object;Lscala/Function0;Ljava/lang/String;Ljava/lang/String;IILscala/Option;Lscala/Option;Lscala/collection/immutable/Seq;)V
  #243 = Methodref          #124.#242     // org/scalatest/Engine.registerIgnoredTest:(Ljava/lang/String;Ljava/lang/Object;Lscala/Function0;Ljava/lang/String;Ljava/lang/String;IILscala/Option;Lscala/Option;Lscala/collection/immutable/Seq;)V
  #244 = Utf8               registerIgnoredTest$
  #245 = NameAndType        #239:#172     // registerIgnoredTest:(Ljava/lang/String;Lscala/collection/immutable/Seq;Lscala/Function0;Lorg/scalactic/source/Position;)V
  #246 = InterfaceMethodref #2.#245       // org/scalatest/flatspec/AnyFlatSpecLike.registerIgnoredTest:(Ljava/lang/String;Lscala/collection/immutable/Seq;Lscala/Function0;Lorg/scalactic/source/Position;)V
  #247 = NameAndType        #233:#172     // registerIgnoredTestImpl:(Ljava/lang/String;Lscala/collection/immutable/Seq;Lscala/Function0;Lorg/scalactic/source/Position;)V
  #248 = InterfaceMethodref #2.#247       // org/scalatest/flatspec/AnyFlatSpecLike.registerIgnoredTestImpl:(Ljava/lang/String;Lscala/collection/immutable/Seq;Lscala/Function0;Lorg/scalactic/source/Position;)V
  #249 = Utf8               org$scalatest$flatspec$AnyFlatSpecLike$$registerTestToRun$
  #250 = Utf8               (Lorg/scalatest/flatspec/AnyFlatSpecLike;Ljava/lang/String;Ljava/lang/String;Lscala/collection/immutable/List;Lscala/Function0;Lorg/scalactic/source/Position;)V
  #251 = Utf8               specText
  #252 = Utf8               methodName
  #253 = Utf8               org$scalatest$flatspec$AnyFlatSpecLike$$registerTestToRun
  #254 = Utf8               (Ljava/lang/String;Ljava/lang/String;Lscala/collection/immutable/List;Lscala/Function0;Lorg/scalactic/source/Position;)V
  #255 = NameAndType        #253:#254     // org$scalatest$flatspec$AnyFlatSpecLike$$registerTestToRun:(Ljava/lang/String;Ljava/lang/String;Lscala/collection/immutable/List;Lscala/Function0;Lorg/scalactic/source/Position;)V
  #256 = InterfaceMethodref #2.#255       // org/scalatest/flatspec/AnyFlatSpecLike.org$scalatest$flatspec$AnyFlatSpecLike$$registerTestToRun:(Ljava/lang/String;Ljava/lang/String;Lscala/collection/immutable/List;Lscala/Function0;Lorg/scalactic/source/Position;)V
  #257 = Utf8               Lscala/collection/immutable/List;
  #258 = Utf8               (Ljava/lang/String;Ljava/lang/String;Lscala/collection/immutable/List<Lorg/scalatest/Tag;>;Lscala/Function0<Ljava/lang/Object;>;Lorg/scalactic/source/Position;)V
  #259 = Utf8               $anonfun$registerTestToRun$1
  #260 = Utf8               (Ljava/lang/String;)Ljava/lang/String;
  #261 = NameAndType        #259:#260     // $anonfun$registerTestToRun$1:(Ljava/lang/String;)Ljava/lang/String;
  #262 = InterfaceMethodref #2.#261       // org/scalatest/flatspec/AnyFlatSpecLike.$anonfun$registerTestToRun$1:(Ljava/lang/String;)Ljava/lang/String;
  #263 = MethodHandle       6:#262        // REF_invokeStatic org/scalatest/flatspec/AnyFlatSpecLike.$anonfun$registerTestToRun$1:(Ljava/lang/String;)Ljava/lang/String;
  #264 = Utf8               (Ljava/lang/String;)Lscala/Function0;
  #265 = NameAndType        #200:#264     // apply:(Ljava/lang/String;)Lscala/Function0;
  #266 = InvokeDynamic      #2:#265       // #2:apply:(Ljava/lang/String;)Lscala/Function0;
  #267 = Utf8               stackDepth
  #268 = Utf8               behavior
  #269 = Utf8               ()Lorg/scalatest/flatspec/AnyFlatSpecLike$BehaviorWord;
  #270 = Utf8               it
  #271 = Utf8               ()Lorg/scalatest/flatspec/AnyFlatSpecLike$ItWord;
  #272 = Utf8               ignore
  #273 = Utf8               ()Lorg/scalatest/flatspec/AnyFlatSpecLike$IgnoreWord;
  #274 = Utf8               they
  #275 = Utf8               ()Lorg/scalatest/flatspec/AnyFlatSpecLike$TheyWord;
  #276 = Utf8               convertToInAndIgnoreMethods$
  #277 = Utf8               (Lorg/scalatest/flatspec/AnyFlatSpecLike;Lorg/scalatest/verbs/ResultOfStringPassedToVerb;)Lorg/scalatest/flatspec/AnyFlatSpecLike$InAndIgnoreMethods;
  #278 = Utf8               resultOfStringPassedToVerb
  #279 = Utf8               convertToInAndIgnoreMethods
  #280 = Utf8               (Lorg/scalatest/verbs/ResultOfStringPassedToVerb;)Lorg/scalatest/flatspec/AnyFlatSpecLike$InAndIgnoreMethods;
  #281 = NameAndType        #279:#280     // convertToInAndIgnoreMethods:(Lorg/scalatest/verbs/ResultOfStringPassedToVerb;)Lorg/scalatest/flatspec/AnyFlatSpecLike$InAndIgnoreMethods;
  #282 = InterfaceMethodref #2.#281       // org/scalatest/flatspec/AnyFlatSpecLike.convertToInAndIgnoreMethods:(Lorg/scalatest/verbs/ResultOfStringPassedToVerb;)Lorg/scalatest/flatspec/AnyFlatSpecLike$InAndIgnoreMethods;
  #283 = Utf8               Lorg/scalatest/verbs/ResultOfStringPassedToVerb;
  #284 = Utf8               (Lorg/scalatest/flatspec/AnyFlatSpecLike;Lorg/scalatest/verbs/ResultOfStringPassedToVerb;)V
  #285 = NameAndType        #180:#284     // "<init>":(Lorg/scalatest/flatspec/AnyFlatSpecLike;Lorg/scalatest/verbs/ResultOfStringPassedToVerb;)V
  #286 = Methodref          #65.#285      // org/scalatest/flatspec/AnyFlatSpecLike$InAndIgnoreMethods."<init>":(Lorg/scalatest/flatspec/AnyFlatSpecLike;Lorg/scalatest/verbs/ResultOfStringPassedToVerb;)V
  #287 = Utf8               convertToInAndIgnoreMethodsAfterTaggedAs$
  #288 = Utf8               (Lorg/scalatest/flatspec/AnyFlatSpecLike;Lorg/scalatest/verbs/ResultOfTaggedAsInvocation;)Lorg/scalatest/flatspec/AnyFlatSpecLike$InAndIgnoreMethodsAfterTaggedAs;
  #289 = Utf8               resultOfTaggedAsInvocation
  #290 = Utf8               convertToInAndIgnoreMethodsAfterTaggedAs
  #291 = Utf8               (Lorg/scalatest/verbs/ResultOfTaggedAsInvocation;)Lorg/scalatest/flatspec/AnyFlatSpecLike$InAndIgnoreMethodsAfterTaggedAs;
  #292 = NameAndType        #290:#291     // convertToInAndIgnoreMethodsAfterTaggedAs:(Lorg/scalatest/verbs/ResultOfTaggedAsInvocation;)Lorg/scalatest/flatspec/AnyFlatSpecLike$InAndIgnoreMethodsAfterTaggedAs;
  #293 = InterfaceMethodref #2.#292       // org/scalatest/flatspec/AnyFlatSpecLike.convertToInAndIgnoreMethodsAfterTaggedAs:(Lorg/scalatest/verbs/ResultOfTaggedAsInvocation;)Lorg/scalatest/flatspec/AnyFlatSpecLike$InAndIgnoreMethodsAfterTaggedAs;
  #294 = Utf8               Lorg/scalatest/verbs/ResultOfTaggedAsInvocation;
  #295 = Utf8               (Lorg/scalatest/flatspec/AnyFlatSpecLike;Lorg/scalatest/verbs/ResultOfTaggedAsInvocation;)V
  #296 = NameAndType        #180:#295     // "<init>":(Lorg/scalatest/flatspec/AnyFlatSpecLike;Lorg/scalatest/verbs/ResultOfTaggedAsInvocation;)V
  #297 = Methodref          #68.#296      // org/scalatest/flatspec/AnyFlatSpecLike$InAndIgnoreMethodsAfterTaggedAs."<init>":(Lorg/scalatest/flatspec/AnyFlatSpecLike;Lorg/scalatest/verbs/ResultOfTaggedAsInvocation;)V
  #298 = Utf8               shorthandTestRegistrationFunction
  #299 = Utf8               ()Lorg/scalatest/verbs/StringVerbStringInvocation;
  #300 = Utf8               shorthandSharedTestRegistrationFunction
  #301 = Utf8               ()Lorg/scalatest/verbs/StringVerbBehaveLikeInvocation;
  #302 = Utf8               org$scalatest$flatspec$AnyFlatSpecLike$$registerTestToIgnore$
  #303 = Utf8               (Lorg/scalatest/flatspec/AnyFlatSpecLike;Ljava/lang/String;Lscala/collection/immutable/List;Ljava/lang/String;Lscala/Function0;Lorg/scalactic/source/Position;)V
  #304 = Utf8               org$scalatest$flatspec$AnyFlatSpecLike$$registerTestToIgnore
  #305 = Utf8               (Ljava/lang/String;Lscala/collection/immutable/List;Ljava/lang/String;Lscala/Function0;Lorg/scalactic/source/Position;)V
  #306 = NameAndType        #304:#305     // org$scalatest$flatspec$AnyFlatSpecLike$$registerTestToIgnore:(Ljava/lang/String;Lscala/collection/immutable/List;Ljava/lang/String;Lscala/Function0;Lorg/scalactic/source/Position;)V
  #307 = InterfaceMethodref #2.#306       // org/scalatest/flatspec/AnyFlatSpecLike.org$scalatest$flatspec$AnyFlatSpecLike$$registerTestToIgnore:(Ljava/lang/String;Lscala/collection/immutable/List;Ljava/lang/String;Lscala/Function0;Lorg/scalactic/source/Position;)V
  #308 = Utf8               (Ljava/lang/String;Lscala/collection/immutable/List<Lorg/scalatest/Tag;>;Ljava/lang/String;Lscala/Function0<Ljava/lang/Object;>;Lorg/scalactic/source/Position;)V
  #309 = Utf8               $anonfun$registerTestToIgnore$1
  #310 = NameAndType        #309:#186     // $anonfun$registerTestToIgnore$1:()Ljava/lang/String;
  #311 = InterfaceMethodref #2.#310       // org/scalatest/flatspec/AnyFlatSpecLike.$anonfun$registerTestToIgnore$1:()Ljava/lang/String;
  #312 = MethodHandle       6:#311        // REF_invokeStatic org/scalatest/flatspec/AnyFlatSpecLike.$anonfun$registerTestToIgnore$1:()Ljava/lang/String;
  #313 = InvokeDynamic      #3:#202       // #3:apply:()Lscala/Function0;
  #314 = Utf8               tags$
  #315 = Utf8               (Lorg/scalatest/flatspec/AnyFlatSpecLike;)Lscala/collection/immutable/Map;
  #316 = Utf8               tags
  #317 = Utf8               ()Lscala/collection/immutable/Map;
  #318 = NameAndType        #316:#317     // tags:()Lscala/collection/immutable/Map;
  #319 = InterfaceMethodref #2.#318       // org/scalatest/flatspec/AnyFlatSpecLike.tags:()Lscala/collection/immutable/Map;
  #320 = Utf8               ()Lscala/collection/immutable/Map<Ljava/lang/String;Lscala/collection/immutable/Set<Ljava/lang/String;>;>;
  #321 = Utf8               org/scalatest/Suite$
  #322 = Class              #321          // org/scalatest/Suite$
  #323 = Utf8               Lorg/scalatest/Suite$;
  #324 = NameAndType        #209:#323     // MODULE$:Lorg/scalatest/Suite$;
  #325 = Fieldref           #322.#324     // org/scalatest/Suite$.MODULE$:Lorg/scalatest/Suite$;
  #326 = Utf8               atomic
  #327 = NameAndType        #326:#126     // atomic:()Ljava/util/concurrent/atomic/AtomicReference;
  #328 = Methodref          #124.#327     // org/scalatest/Engine.atomic:()Ljava/util/concurrent/atomic/AtomicReference;
  #329 = Utf8               tagsMap
  #330 = NameAndType        #329:#317     // tagsMap:()Lscala/collection/immutable/Map;
  #331 = Methodref          #36.#330      // org/scalatest/SuperEngine$Bundle.tagsMap:()Lscala/collection/immutable/Map;
  #332 = Utf8               autoTagClassAnnotations
  #333 = Utf8               (Lscala/collection/immutable/Map;Lorg/scalatest/Suite;)Lscala/collection/immutable/Map;
  #334 = NameAndType        #332:#333     // autoTagClassAnnotations:(Lscala/collection/immutable/Map;Lorg/scalatest/Suite;)Lscala/collection/immutable/Map;
  #335 = Methodref          #322.#334     // org/scalatest/Suite$.autoTagClassAnnotations:(Lscala/collection/immutable/Map;Lorg/scalatest/Suite;)Lscala/collection/immutable/Map;
  #336 = Utf8               runTest$
  #337 = Utf8               (Lorg/scalatest/flatspec/AnyFlatSpecLike;Ljava/lang/String;Lorg/scalatest/Args;)Lorg/scalatest/Status;
  #338 = Utf8               runTest
  #339 = Utf8               (Ljava/lang/String;Lorg/scalatest/Args;)Lorg/scalatest/Status;
  #340 = NameAndType        #338:#339     // runTest:(Ljava/lang/String;Lorg/scalatest/Args;)Lorg/scalatest/Status;
  #341 = InterfaceMethodref #2.#340       // org/scalatest/flatspec/AnyFlatSpecLike.runTest:(Ljava/lang/String;Lorg/scalatest/Args;)Lorg/scalatest/Status;
  #342 = Utf8               Lorg/scalatest/Args;
  #343 = Utf8               (Ljava/lang/Object;)Ljava/lang/Object;
  #344 = MethodType         #343          //  (Ljava/lang/Object;)Ljava/lang/Object;
  #345 = Utf8               $anonfun$runTest$1
  #346 = Utf8               (Lorg/scalatest/flatspec/AnyFlatSpecLike;Lorg/scalatest/Args;Ljava/lang/String;Lorg/scalatest/SuperEngine$TestLeaf;)Lorg/scalatest/Outcome;
  #347 = NameAndType        #345:#346     // $anonfun$runTest$1:(Lorg/scalatest/flatspec/AnyFlatSpecLike;Lorg/scalatest/Args;Ljava/lang/String;Lorg/scalatest/SuperEngine$TestLeaf;)Lorg/scalatest/Outcome;
  #348 = InterfaceMethodref #2.#347       // org/scalatest/flatspec/AnyFlatSpecLike.$anonfun$runTest$1:(Lorg/scalatest/flatspec/AnyFlatSpecLike;Lorg/scalatest/Args;Ljava/lang/String;Lorg/scalatest/SuperEngine$TestLeaf;)Lorg/scalatest/Outcome;
  #349 = MethodHandle       6:#348        // REF_invokeStatic org/scalatest/flatspec/AnyFlatSpecLike.$anonfun$runTest$1:(Lorg/scalatest/flatspec/AnyFlatSpecLike;Lorg/scalatest/Args;Ljava/lang/String;Lorg/scalatest/SuperEngine$TestLeaf;)Lorg/scalatest/Outcome;
  #350 = Utf8               (Lorg/scalatest/SuperEngine$TestLeaf;)Lorg/scalatest/Outcome;
  #351 = MethodType         #350          //  (Lorg/scalatest/SuperEngine$TestLeaf;)Lorg/scalatest/Outcome;
  #352 = Utf8               (Lorg/scalatest/flatspec/AnyFlatSpecLike;Lorg/scalatest/Args;Ljava/lang/String;)Lscala/Function1;
  #353 = NameAndType        #200:#352     // apply:(Lorg/scalatest/flatspec/AnyFlatSpecLike;Lorg/scalatest/Args;Ljava/lang/String;)Lscala/Function1;
  #354 = InvokeDynamic      #4:#353       // #4:apply:(Lorg/scalatest/flatspec/AnyFlatSpecLike;Lorg/scalatest/Args;Ljava/lang/String;)Lscala/Function1;
  #355 = Utf8               runTestImpl
  #356 = Utf8               (Lorg/scalatest/Suite;Ljava/lang/String;Lorg/scalatest/Args;ZLscala/Function1;)Lorg/scalatest/Status;
  #357 = NameAndType        #355:#356     // runTestImpl:(Lorg/scalatest/Suite;Ljava/lang/String;Lorg/scalatest/Args;ZLscala/Function1;)Lorg/scalatest/Status;
  #358 = Methodref          #124.#357     // org/scalatest/Engine.runTestImpl:(Lorg/scalatest/Suite;Ljava/lang/String;Lorg/scalatest/Args;ZLscala/Function1;)Lorg/scalatest/Status;
  #359 = Utf8               runTests$
  #360 = Utf8               (Lorg/scalatest/flatspec/AnyFlatSpecLike;Lscala/Option;Lorg/scalatest/Args;)Lorg/scalatest/Status;
  #361 = Utf8               runTests
  #362 = NameAndType        #361:#108     // runTests:(Lscala/Option;Lorg/scalatest/Args;)Lorg/scalatest/Status;
  #363 = InterfaceMethodref #2.#362       // org/scalatest/flatspec/AnyFlatSpecLike.runTests:(Lscala/Option;Lorg/scalatest/Args;)Lorg/scalatest/Status;
  #364 = Utf8               Lscala/Option;
  #365 = Utf8               (Lscala/Option<Ljava/lang/String;>;Lorg/scalatest/Args;)Lorg/scalatest/Status;
  #366 = Utf8               (Ljava/lang/Object;Ljava/lang/Object;)Ljava/lang/Object;
  #367 = MethodType         #366          //  (Ljava/lang/Object;Ljava/lang/Object;)Ljava/lang/Object;
  #368 = Utf8               $anonfun$runTests$1
  #369 = NameAndType        #368:#337     // $anonfun$runTests$1:(Lorg/scalatest/flatspec/AnyFlatSpecLike;Ljava/lang/String;Lorg/scalatest/Args;)Lorg/scalatest/Status;
  #370 = InterfaceMethodref #2.#369       // org/scalatest/flatspec/AnyFlatSpecLike.$anonfun$runTests$1:(Lorg/scalatest/flatspec/AnyFlatSpecLike;Ljava/lang/String;Lorg/scalatest/Args;)Lorg/scalatest/Status;
  #371 = MethodHandle       6:#370        // REF_invokeStatic org/scalatest/flatspec/AnyFlatSpecLike.$anonfun$runTests$1:(Lorg/scalatest/flatspec/AnyFlatSpecLike;Ljava/lang/String;Lorg/scalatest/Args;)Lorg/scalatest/Status;
  #372 = MethodType         #339          //  (Ljava/lang/String;Lorg/scalatest/Args;)Lorg/scalatest/Status;
  #373 = Utf8               (Lorg/scalatest/flatspec/AnyFlatSpecLike;)Lscala/Function2;
  #374 = NameAndType        #200:#373     // apply:(Lorg/scalatest/flatspec/AnyFlatSpecLike;)Lscala/Function2;
  #375 = InvokeDynamic      #5:#374       // #5:apply:(Lorg/scalatest/flatspec/AnyFlatSpecLike;)Lscala/Function2;
  #376 = Utf8               runTestsImpl
  #377 = Utf8               (Lorg/scalatest/Suite;Lscala/Option;Lorg/scalatest/Args;Lorg/scalatest/Informer;ZLscala/Function2;)Lorg/scalatest/Status;
  #378 = NameAndType        #376:#377     // runTestsImpl:(Lorg/scalatest/Suite;Lscala/Option;Lorg/scalatest/Args;Lorg/scalatest/Informer;ZLscala/Function2;)Lorg/scalatest/Status;
  #379 = Methodref          #124.#378     // org/scalatest/Engine.runTestsImpl:(Lorg/scalatest/Suite;Lscala/Option;Lorg/scalatest/Args;Lorg/scalatest/Informer;ZLscala/Function2;)Lorg/scalatest/Status;
  #380 = Utf8               testNames$
  #381 = Utf8               (Lorg/scalatest/flatspec/AnyFlatSpecLike;)Lscala/collection/immutable/Set;
  #382 = Utf8               testNames
  #383 = Utf8               ()Lscala/collection/immutable/Set;
  #384 = NameAndType        #382:#383     // testNames:()Lscala/collection/immutable/Set;
  #385 = InterfaceMethodref #2.#384       // org/scalatest/flatspec/AnyFlatSpecLike.testNames:()Lscala/collection/immutable/Set;
  #386 = Utf8               ()Lscala/collection/immutable/Set<Ljava/lang/String;>;
  #387 = Utf8               org/scalatest/InsertionOrderSet$
  #388 = Class              #387          // org/scalatest/InsertionOrderSet$
  #389 = Utf8               Lorg/scalatest/InsertionOrderSet$;
  #390 = NameAndType        #209:#389     // MODULE$:Lorg/scalatest/InsertionOrderSet$;
  #391 = Fieldref           #388.#390     // org/scalatest/InsertionOrderSet$.MODULE$:Lorg/scalatest/InsertionOrderSet$;
  #392 = Utf8               testNamesList
  #393 = Utf8               ()Lscala/collection/immutable/List;
  #394 = NameAndType        #392:#393     // testNamesList:()Lscala/collection/immutable/List;
  #395 = Methodref          #36.#394      // org/scalatest/SuperEngine$Bundle.testNamesList:()Lscala/collection/immutable/List;
  #396 = Utf8               (Lscala/collection/immutable/List;)Lscala/collection/immutable/Set;
  #397 = NameAndType        #200:#396     // apply:(Lscala/collection/immutable/List;)Lscala/collection/immutable/Set;
  #398 = Methodref          #388.#397     // org/scalatest/InsertionOrderSet$.apply:(Lscala/collection/immutable/List;)Lscala/collection/immutable/Set;
  #399 = Utf8               run$
  #400 = Utf8               run
  #401 = NameAndType        #400:#108     // run:(Lscala/Option;Lorg/scalatest/Args;)Lorg/scalatest/Status;
  #402 = InterfaceMethodref #2.#401       // org/scalatest/flatspec/AnyFlatSpecLike.run:(Lscala/Option;Lorg/scalatest/Args;)Lorg/scalatest/Status;
  #403 = Utf8               $anonfun$run$1
  #404 = NameAndType        #403:#360     // $anonfun$run$1:(Lorg/scalatest/flatspec/AnyFlatSpecLike;Lscala/Option;Lorg/scalatest/Args;)Lorg/scalatest/Status;
  #405 = InterfaceMethodref #2.#404       // org/scalatest/flatspec/AnyFlatSpecLike.$anonfun$run$1:(Lorg/scalatest/flatspec/AnyFlatSpecLike;Lscala/Option;Lorg/scalatest/Args;)Lorg/scalatest/Status;
  #406 = MethodHandle       6:#405        // REF_invokeStatic org/scalatest/flatspec/AnyFlatSpecLike.$anonfun$run$1:(Lorg/scalatest/flatspec/AnyFlatSpecLike;Lscala/Option;Lorg/scalatest/Args;)Lorg/scalatest/Status;
  #407 = MethodType         #108          //  (Lscala/Option;Lorg/scalatest/Args;)Lorg/scalatest/Status;
  #408 = InvokeDynamic      #6:#374       // #6:apply:(Lorg/scalatest/flatspec/AnyFlatSpecLike;)Lscala/Function2;
  #409 = Utf8               runImpl
  #410 = Utf8               (Lorg/scalatest/Suite;Lscala/Option;Lorg/scalatest/Args;Lscala/Function2;)Lorg/scalatest/Status;
  #411 = NameAndType        #409:#410     // runImpl:(Lorg/scalatest/Suite;Lscala/Option;Lorg/scalatest/Args;Lscala/Function2;)Lorg/scalatest/Status;
  #412 = Methodref          #124.#411     // org/scalatest/Engine.runImpl:(Lorg/scalatest/Suite;Lscala/Option;Lorg/scalatest/Args;Lscala/Function2;)Lorg/scalatest/Status;
  #413 = Utf8               behave
  #414 = Utf8               ()Lorg/scalatest/verbs/BehaveWord;
  #415 = Utf8               styleName
  #416 = Utf8               testDataFor$
  #417 = Utf8               (Lorg/scalatest/flatspec/AnyFlatSpecLike;Ljava/lang/String;Lorg/scalatest/ConfigMap;)Lorg/scalatest/TestData;
  #418 = Utf8               theConfigMap
  #419 = Utf8               testDataFor
  #420 = Utf8               (Ljava/lang/String;Lorg/scalatest/ConfigMap;)Lorg/scalatest/TestData;
  #421 = NameAndType        #419:#420     // testDataFor:(Ljava/lang/String;Lorg/scalatest/ConfigMap;)Lorg/scalatest/TestData;
  #422 = InterfaceMethodref #2.#421       // org/scalatest/flatspec/AnyFlatSpecLike.testDataFor:(Ljava/lang/String;Lorg/scalatest/ConfigMap;)Lorg/scalatest/TestData;
  #423 = Utf8               Lorg/scalatest/ConfigMap;
  #424 = Utf8               createTestDataFor
  #425 = Utf8               (Ljava/lang/String;Lorg/scalatest/ConfigMap;Lorg/scalatest/Suite;)Lorg/scalatest/TestData;
  #426 = NameAndType        #424:#425     // createTestDataFor:(Ljava/lang/String;Lorg/scalatest/ConfigMap;Lorg/scalatest/Suite;)Lorg/scalatest/TestData;
  #427 = Methodref          #124.#426     // org/scalatest/Engine.createTestDataFor:(Ljava/lang/String;Lorg/scalatest/ConfigMap;Lorg/scalatest/Suite;)Lorg/scalatest/TestData;
  #428 = Utf8               testDataFor$default$2$
  #429 = Utf8               (Lorg/scalatest/flatspec/AnyFlatSpecLike;)Lorg/scalatest/ConfigMap;
  #430 = Utf8               testDataFor$default$2
  #431 = Utf8               ()Lorg/scalatest/ConfigMap;
  #432 = NameAndType        #430:#431     // testDataFor$default$2:()Lorg/scalatest/ConfigMap;
  #433 = InterfaceMethodref #2.#432       // org/scalatest/flatspec/AnyFlatSpecLike.testDataFor$default$2:()Lorg/scalatest/ConfigMap;
  #434 = Utf8               org/scalatest/ConfigMap$
  #435 = Class              #434          // org/scalatest/ConfigMap$
  #436 = Utf8               Lorg/scalatest/ConfigMap$;
  #437 = NameAndType        #209:#436     // MODULE$:Lorg/scalatest/ConfigMap$;
  #438 = Fieldref           #435.#437     // org/scalatest/ConfigMap$.MODULE$:Lorg/scalatest/ConfigMap$;
  #439 = Utf8               empty
  #440 = NameAndType        #439:#431     // empty:()Lorg/scalatest/ConfigMap;
  #441 = Methodref          #435.#440     // org/scalatest/ConfigMap$.empty:()Lorg/scalatest/ConfigMap;
  #442 = Utf8               $anonfun$engine$1
  #443 = Utf8               org/scalatest/Resources$
  #444 = Class              #443          // org/scalatest/Resources$
  #445 = Utf8               Lorg/scalatest/Resources$;
  #446 = NameAndType        #209:#445     // MODULE$:Lorg/scalatest/Resources$;
  #447 = Fieldref           #444.#446     // org/scalatest/Resources$.MODULE$:Lorg/scalatest/Resources$;
  #448 = Utf8               concurrentSpecMod
  #449 = NameAndType        #448:#186     // concurrentSpecMod:()Ljava/lang/String;
  #450 = Methodref          #444.#449     // org/scalatest/Resources$.concurrentSpecMod:()Ljava/lang/String;
  #451 = Utf8               testCannotBeNestedInsideAnotherTest
  #452 = NameAndType        #451:#186     // testCannotBeNestedInsideAnotherTest:()Ljava/lang/String;
  #453 = Methodref          #444.#452     // org/scalatest/Resources$.testCannotBeNestedInsideAnotherTest:()Ljava/lang/String;
  #454 = Utf8               testRegistrationClosedMessageFun$1
  #455 = Utf8               methodName$1
  #456 = Utf8               java/lang/String
  #457 = Class              #456          // java/lang/String
  #458 = Utf8               hashCode
  #459 = Utf8               ()I
  #460 = NameAndType        #458:#459     // hashCode:()I
  #461 = Methodref          #457.#460     // java/lang/String.hashCode:()I
  #462 = Utf8               in
  #463 = String             #462          // in
  #464 = Utf8               equals
  #465 = Utf8               (Ljava/lang/Object;)Z
  #466 = NameAndType        #464:#465     // equals:(Ljava/lang/Object;)Z
  #467 = Methodref          #457.#466     // java/lang/String.equals:(Ljava/lang/Object;)Z
  #468 = Utf8               inCannotAppearInsideAnotherInOrIs
  #469 = NameAndType        #468:#186     // inCannotAppearInsideAnotherInOrIs:()Ljava/lang/String;
  #470 = Methodref          #444.#469     // org/scalatest/Resources$.inCannotAppearInsideAnotherInOrIs:()Ljava/lang/String;
  #471 = Utf8               is
  #472 = String             #471          // is
  #473 = Utf8               isCannotAppearInsideAnotherInOrIs
  #474 = NameAndType        #473:#186     // isCannotAppearInsideAnotherInOrIs:()Ljava/lang/String;
  #475 = Methodref          #444.#474     // org/scalatest/Resources$.isCannotAppearInsideAnotherInOrIs:()Ljava/lang/String;
  #476 = Utf8               scala/MatchError
  #477 = Class              #476          // scala/MatchError
  #478 = Methodref          #477.#216     // scala/MatchError."<init>":(Ljava/lang/Object;)V
  #479 = NameAndType        #454:#260     // testRegistrationClosedMessageFun$1:(Ljava/lang/String;)Ljava/lang/String;
  #480 = InterfaceMethodref #2.#479       // org/scalatest/flatspec/AnyFlatSpecLike.testRegistrationClosedMessageFun$1:(Ljava/lang/String;)Ljava/lang/String;
  #481 = Utf8               ignoreCannotAppearInsideAnInOrAnIs
  #482 = NameAndType        #481:#186     // ignoreCannotAppearInsideAnInOrAnIs:()Ljava/lang/String;
  #483 = Methodref          #444.#482     // org/scalatest/Resources$.ignoreCannotAppearInsideAnInOrAnIs:()Ljava/lang/String;
  #484 = Utf8               invokeWithFixture$1
  #485 = Utf8               (Lorg/scalatest/SuperEngine$TestLeaf;Lorg/scalatest/Args;Ljava/lang/String;)Lorg/scalatest/Outcome;
  #486 = Utf8               theTest
  #487 = Utf8               args$1
  #488 = Utf8               testName$1
  #489 = Utf8               org/scalatest/Args
  #490 = Class              #489          // org/scalatest/Args
  #491 = Utf8               configMap
  #492 = NameAndType        #491:#431     // configMap:()Lorg/scalatest/ConfigMap;
  #493 = Methodref          #490.#492     // org/scalatest/Args.configMap:()Lorg/scalatest/ConfigMap;
  #494 = Utf8               (Lorg/scalatest/flatspec/AnyFlatSpecLike;Lorg/scalatest/TestData;Lorg/scalatest/SuperEngine$TestLeaf;)V
  #495 = NameAndType        #180:#494     // "<init>":(Lorg/scalatest/flatspec/AnyFlatSpecLike;Lorg/scalatest/TestData;Lorg/scalatest/SuperEngine$TestLeaf;)V
  #496 = Methodref          #51.#495      // org/scalatest/flatspec/AnyFlatSpecLike$$anon$5."<init>":(Lorg/scalatest/flatspec/AnyFlatSpecLike;Lorg/scalatest/TestData;Lorg/scalatest/SuperEngine$TestLeaf;)V
  #497 = Utf8               withFixture
  #498 = Utf8               (Lorg/scalatest/TestSuite$NoArgTest;)Lorg/scalatest/Outcome;
  #499 = NameAndType        #497:#498     // withFixture:(Lorg/scalatest/TestSuite$NoArgTest;)Lorg/scalatest/Outcome;
  #500 = InterfaceMethodref #2.#499       // org/scalatest/flatspec/AnyFlatSpecLike.withFixture:(Lorg/scalatest/TestSuite$NoArgTest;)Lorg/scalatest/Outcome;
  #501 = Utf8               testData
  #502 = Utf8               Lorg/scalatest/TestData;
  #503 = Utf8               Lorg/scalatest/SuperEngine$TestLeaf;
  #504 = NameAndType        #484:#485     // invokeWithFixture$1:(Lorg/scalatest/SuperEngine$TestLeaf;Lorg/scalatest/Args;Ljava/lang/String;)Lorg/scalatest/Outcome;
  #505 = InterfaceMethodref #2.#504       // org/scalatest/flatspec/AnyFlatSpecLike.invokeWithFixture$1:(Lorg/scalatest/SuperEngine$TestLeaf;Lorg/scalatest/Args;Ljava/lang/String;)Lorg/scalatest/Outcome;
  #506 = NameAndType        #107:#108     // org$scalatest$flatspec$AnyFlatSpecLike$$super$run:(Lscala/Option;Lorg/scalatest/Args;)Lorg/scalatest/Status;
  #507 = InterfaceMethodref #2.#506       // org/scalatest/flatspec/AnyFlatSpecLike.org$scalatest$flatspec$AnyFlatSpecLike$$super$run:(Lscala/Option;Lorg/scalatest/Args;)Lorg/scalatest/Status;
  #508 = Utf8               $init$
  #509 = Utf8               (Lorg/scalatest/flatspec/AnyFlatSpecLike;)V
  #510 = NameAndType        #442:#186     // $anonfun$engine$1:()Ljava/lang/String;
  #511 = InterfaceMethodref #2.#510       // org/scalatest/flatspec/AnyFlatSpecLike.$anonfun$engine$1:()Ljava/lang/String;
  #512 = MethodHandle       6:#511        // REF_invokeStatic org/scalatest/flatspec/AnyFlatSpecLike.$anonfun$engine$1:()Ljava/lang/String;
  #513 = InvokeDynamic      #7:#202       // #7:apply:()Lscala/Function0;
  #514 = Utf8               Spec
  #515 = String             #514          // Spec
  #516 = Utf8               (Lscala/Function0;Ljava/lang/String;)V
  #517 = NameAndType        #180:#516     // "<init>":(Lscala/Function0;Ljava/lang/String;)V
  #518 = Methodref          #124.#517     // org/scalatest/Engine."<init>":(Lscala/Function0;Ljava/lang/String;)V
  #519 = NameAndType        #88:#89       // org$scalatest$flatspec$AnyFlatSpecLike$_setter_$org$scalatest$flatspec$AnyFlatSpecLike$$engine_$eq:(Lorg/scalatest/Engine;)V
  #520 = InterfaceMethodref #2.#519       // org/scalatest/flatspec/AnyFlatSpecLike.org$scalatest$flatspec$AnyFlatSpecLike$_setter_$org$scalatest$flatspec$AnyFlatSpecLike$$engine_$eq:(Lorg/scalatest/Engine;)V
  #521 = NameAndType        #180:#509     // "<init>":(Lorg/scalatest/flatspec/AnyFlatSpecLike;)V
  #522 = Methodref          #53.#521      // org/scalatest/flatspec/AnyFlatSpecLike$BehaviorWord."<init>":(Lorg/scalatest/flatspec/AnyFlatSpecLike;)V
  #523 = NameAndType        #91:#92       // org$scalatest$flatspec$AnyFlatSpecLike$_setter_$behavior_$eq:(Lorg/scalatest/flatspec/AnyFlatSpecLike$BehaviorWord;)V
  #524 = InterfaceMethodref #2.#523       // org/scalatest/flatspec/AnyFlatSpecLike.org$scalatest$flatspec$AnyFlatSpecLike$_setter_$behavior_$eq:(Lorg/scalatest/flatspec/AnyFlatSpecLike$BehaviorWord;)V
  #525 = Methodref          #77.#521      // org/scalatest/flatspec/AnyFlatSpecLike$ItWord."<init>":(Lorg/scalatest/flatspec/AnyFlatSpecLike;)V
  #526 = NameAndType        #93:#94       // org$scalatest$flatspec$AnyFlatSpecLike$_setter_$it_$eq:(Lorg/scalatest/flatspec/AnyFlatSpecLike$ItWord;)V
  #527 = InterfaceMethodref #2.#526       // org/scalatest/flatspec/AnyFlatSpecLike.org$scalatest$flatspec$AnyFlatSpecLike$_setter_$it_$eq:(Lorg/scalatest/flatspec/AnyFlatSpecLike$ItWord;)V
  #528 = Methodref          #62.#521      // org/scalatest/flatspec/AnyFlatSpecLike$IgnoreWord."<init>":(Lorg/scalatest/flatspec/AnyFlatSpecLike;)V
  #529 = NameAndType        #95:#96       // org$scalatest$flatspec$AnyFlatSpecLike$_setter_$ignore_$eq:(Lorg/scalatest/flatspec/AnyFlatSpecLike$IgnoreWord;)V
  #530 = InterfaceMethodref #2.#529       // org/scalatest/flatspec/AnyFlatSpecLike.org$scalatest$flatspec$AnyFlatSpecLike$_setter_$ignore_$eq:(Lorg/scalatest/flatspec/AnyFlatSpecLike$IgnoreWord;)V
  #531 = Methodref          #86.#521      // org/scalatest/flatspec/AnyFlatSpecLike$TheyWord."<init>":(Lorg/scalatest/flatspec/AnyFlatSpecLike;)V
  #532 = NameAndType        #97:#98       // org$scalatest$flatspec$AnyFlatSpecLike$_setter_$they_$eq:(Lorg/scalatest/flatspec/AnyFlatSpecLike$TheyWord;)V
  #533 = InterfaceMethodref #2.#532       // org/scalatest/flatspec/AnyFlatSpecLike.org$scalatest$flatspec$AnyFlatSpecLike$_setter_$they_$eq:(Lorg/scalatest/flatspec/AnyFlatSpecLike$TheyWord;)V
  #534 = Methodref          #47.#521      // org/scalatest/flatspec/AnyFlatSpecLike$$anon$1."<init>":(Lorg/scalatest/flatspec/AnyFlatSpecLike;)V
  #535 = NameAndType        #99:#100      // org$scalatest$flatspec$AnyFlatSpecLike$_setter_$shorthandTestRegistrationFunction_$eq:(Lorg/scalatest/verbs/StringVerbStringInvocation;)V
  #536 = InterfaceMethodref #2.#535       // org/scalatest/flatspec/AnyFlatSpecLike.org$scalatest$flatspec$AnyFlatSpecLike$_setter_$shorthandTestRegistrationFunction_$eq:(Lorg/scalatest/verbs/StringVerbStringInvocation;)V
  #537 = Methodref          #49.#521      // org/scalatest/flatspec/AnyFlatSpecLike$$anon$4."<init>":(Lorg/scalatest/flatspec/AnyFlatSpecLike;)V
  #538 = NameAndType        #101:#102     // org$scalatest$flatspec$AnyFlatSpecLike$_setter_$shorthandSharedTestRegistrationFunction_$eq:(Lorg/scalatest/verbs/StringVerbBehaveLikeInvocation;)V
  #539 = InterfaceMethodref #2.#538       // org/scalatest/flatspec/AnyFlatSpecLike.org$scalatest$flatspec$AnyFlatSpecLike$_setter_$shorthandSharedTestRegistrationFunction_$eq:(Lorg/scalatest/verbs/StringVerbBehaveLikeInvocation;)V
  #540 = Utf8               org/scalatest/verbs/BehaveWord
  #541 = Class              #540          // org/scalatest/verbs/BehaveWord
  #542 = Utf8               ()V
  #543 = NameAndType        #180:#542     // "<init>":()V
  #544 = Methodref          #541.#543     // org/scalatest/verbs/BehaveWord."<init>":()V
  #545 = NameAndType        #103:#104     // org$scalatest$flatspec$AnyFlatSpecLike$_setter_$behave_$eq:(Lorg/scalatest/verbs/BehaveWord;)V
  #546 = InterfaceMethodref #2.#545       // org/scalatest/flatspec/AnyFlatSpecLike.org$scalatest$flatspec$AnyFlatSpecLike$_setter_$behave_$eq:(Lorg/scalatest/verbs/BehaveWord;)V
  #547 = Utf8               org.scalatest.FlatSpec
  #548 = String             #547          // org.scalatest.FlatSpec
  #549 = NameAndType        #105:#106     // org$scalatest$flatspec$AnyFlatSpecLike$_setter_$styleName_$eq:(Ljava/lang/String;)V
  #550 = InterfaceMethodref #2.#549       // org/scalatest/flatspec/AnyFlatSpecLike.org$scalatest$flatspec$AnyFlatSpecLike$_setter_$styleName_$eq:(Ljava/lang/String;)V
  #551 = Utf8               $deserializeLambda$
  #552 = Utf8               (Ljava/lang/invoke/SerializedLambda;)Ljava/lang/Object;
  #553 = Utf8               scala/runtime/LambdaDeserialize
  #554 = Class              #553          // scala/runtime/LambdaDeserialize
  #555 = Utf8               bootstrap
  #556 = Utf8               (Ljava/lang/invoke/MethodHandles$Lookup;Ljava/lang/String;Ljava/lang/invoke/MethodType;[Ljava/lang/invoke/MethodHandle;)Ljava/lang/invoke/CallSite;
  #557 = NameAndType        #555:#556     // bootstrap:(Ljava/lang/invoke/MethodHandles$Lookup;Ljava/lang/String;Ljava/lang/invoke/MethodType;[Ljava/lang/invoke/MethodHandle;)Ljava/lang/invoke/CallSite;
  #558 = Methodref          #554.#557     // scala/runtime/LambdaDeserialize.bootstrap:(Ljava/lang/invoke/MethodHandles$Lookup;Ljava/lang/String;Ljava/lang/invoke/MethodType;[Ljava/lang/invoke/MethodHandle;)Ljava/lang/invoke/CallSite;
  #559 = MethodHandle       6:#558        // REF_invokeStatic scala/runtime/LambdaDeserialize.bootstrap:(Ljava/lang/invoke/MethodHandles$Lookup;Ljava/lang/String;Ljava/lang/invoke/MethodType;[Ljava/lang/invoke/MethodHandle;)Ljava/lang/invoke/CallSite;
  #560 = Utf8               lambdaDeserialize
  #561 = NameAndType        #560:#552     // lambdaDeserialize:(Ljava/lang/invoke/SerializedLambda;)Ljava/lang/Object;
  #562 = InvokeDynamic      #8:#561       // #8:lambdaDeserialize:(Ljava/lang/invoke/SerializedLambda;)Ljava/lang/Object;
  #563 = Utf8               MethodParameters
  #564 = Utf8               Code
  #565 = Utf8               LineNumberTable
  #566 = Utf8               LocalVariableTable
  #567 = Utf8               Signature
  #568 = Utf8               Deprecated
  #569 = Utf8               StackMapTable
  #570 = Utf8               InnerClasses
  #571 = Utf8               SourceFile
  #572 = Utf8               RuntimeVisibleAnnotations
  #573 = Utf8               BootstrapMethods
  #574 = Utf8               ScalaInlineInfo
  #575 = Utf8               ScalaSig
{
  public abstract void org$scalatest$flatspec$AnyFlatSpecLike$_setter_$org$scalatest$flatspec$AnyFlatSpecLike$$engine_$eq(org.scalatest.Engine);
    descriptor: (Lorg/scalatest/Engine;)V
    flags: (0x0401) ACC_PUBLIC, ACC_ABSTRACT
    MethodParameters:
      Name                           Flags
      x$1                            final

  public abstract void org$scalatest$flatspec$AnyFlatSpecLike$_setter_$behavior_$eq(org.scalatest.flatspec.AnyFlatSpecLike$BehaviorWord);
    descriptor: (Lorg/scalatest/flatspec/AnyFlatSpecLike$BehaviorWord;)V
    flags: (0x0401) ACC_PUBLIC, ACC_ABSTRACT
    MethodParameters:
      Name                           Flags
      x$1                            final

  public abstract void org$scalatest$flatspec$AnyFlatSpecLike$_setter_$it_$eq(org.scalatest.flatspec.AnyFlatSpecLike$ItWord);
    descriptor: (Lorg/scalatest/flatspec/AnyFlatSpecLike$ItWord;)V
    flags: (0x0401) ACC_PUBLIC, ACC_ABSTRACT
    MethodParameters:
      Name                           Flags
      x$1                            final

  public abstract void org$scalatest$flatspec$AnyFlatSpecLike$_setter_$ignore_$eq(org.scalatest.flatspec.AnyFlatSpecLike$IgnoreWord);
    descriptor: (Lorg/scalatest/flatspec/AnyFlatSpecLike$IgnoreWord;)V
    flags: (0x0401) ACC_PUBLIC, ACC_ABSTRACT
    MethodParameters:
      Name                           Flags
      x$1                            final

  public abstract void org$scalatest$flatspec$AnyFlatSpecLike$_setter_$they_$eq(org.scalatest.flatspec.AnyFlatSpecLike$TheyWord);
    descriptor: (Lorg/scalatest/flatspec/AnyFlatSpecLike$TheyWord;)V
    flags: (0x0401) ACC_PUBLIC, ACC_ABSTRACT
    MethodParameters:
      Name                           Flags
      x$1                            final

  public abstract void org$scalatest$flatspec$AnyFlatSpecLike$_setter_$shorthandTestRegistrationFunction_$eq(org.scalatest.verbs.StringVerbStringInvocation);
    descriptor: (Lorg/scalatest/verbs/StringVerbStringInvocation;)V
    flags: (0x0401) ACC_PUBLIC, ACC_ABSTRACT
    MethodParameters:
      Name                           Flags
      x$1                            final

  public abstract void org$scalatest$flatspec$AnyFlatSpecLike$_setter_$shorthandSharedTestRegistrationFunction_$eq(org.scalatest.verbs.StringVerbBehaveLikeInvocation);
    descriptor: (Lorg/scalatest/verbs/StringVerbBehaveLikeInvocation;)V
    flags: (0x0401) ACC_PUBLIC, ACC_ABSTRACT
    MethodParameters:
      Name                           Flags
      x$1                            final

  public abstract void org$scalatest$flatspec$AnyFlatSpecLike$_setter_$behave_$eq(org.scalatest.verbs.BehaveWord);
    descriptor: (Lorg/scalatest/verbs/BehaveWord;)V
    flags: (0x0401) ACC_PUBLIC, ACC_ABSTRACT
    MethodParameters:
      Name                           Flags
      x$1                            final

  public abstract void org$scalatest$flatspec$AnyFlatSpecLike$_setter_$styleName_$eq(java.lang.String);
    descriptor: (Ljava/lang/String;)V
    flags: (0x0401) ACC_PUBLIC, ACC_ABSTRACT
    MethodParameters:
      Name                           Flags
      x$1                            final

  public abstract org.scalatest.Status org$scalatest$flatspec$AnyFlatSpecLike$$super$run(scala.Option, org.scalatest.Args);
    descriptor: (Lscala/Option;Lorg/scalatest/Args;)Lorg/scalatest/Status;
    flags: (0x1401) ACC_PUBLIC, ACC_ABSTRACT, ACC_SYNTHETIC
    MethodParameters:
      Name                           Flags
      testName                       final
      args                           final

  public abstract org.scalatest.Engine org$scalatest$flatspec$AnyFlatSpecLike$$engine();
    descriptor: ()Lorg/scalatest/Engine;
    flags: (0x0401) ACC_PUBLIC, ACC_ABSTRACT

  public static org.scalatest.Informer info$(org.scalatest.flatspec.AnyFlatSpecLike);
    descriptor: (Lorg/scalatest/flatspec/AnyFlatSpecLike;)Lorg/scalatest/Informer;
    flags: (0x1009) ACC_PUBLIC, ACC_STATIC, ACC_SYNTHETIC
    Code:
      stack=1, locals=1, args_size=1
         0: aload_0
         1: invokespecial #119                // InterfaceMethod info:()Lorg/scalatest/Informer;
         4: areturn
      LineNumberTable:
        line 65: 0
      LocalVariableTable:
        Start  Length  Slot  Name   Signature
            0       5     0 $this   Lorg/scalatest/flatspec/AnyFlatSpecLike;
    MethodParameters:
      Name                           Flags
      $this                          final synthetic

  public default org.scalatest.Informer info();
    descriptor: ()Lorg/scalatest/Informer;
    flags: (0x0001) ACC_PUBLIC
    Code:
      stack=1, locals=1, args_size=1
         0: aload_0
         1: invokeinterface #122,  1          // InterfaceMethod org$scalatest$flatspec$AnyFlatSpecLike$$engine:()Lorg/scalatest/Engine;
         6: invokevirtual #128                // Method org/scalatest/Engine.atomicInformer:()Ljava/util/concurrent/atomic/AtomicReference;
         9: invokevirtual #134                // Method java/util/concurrent/atomic/AtomicReference.get:()Ljava/lang/Object;
        12: checkcast     #136                // class org/scalatest/Informer
        15: areturn
      LineNumberTable:
        line 65: 0
      LocalVariableTable:
        Start  Length  Slot  Name   Signature
            0      16     0  this   Lorg/scalatest/flatspec/AnyFlatSpecLike;

  public static org.scalatest.Notifier note$(org.scalatest.flatspec.AnyFlatSpecLike);
    descriptor: (Lorg/scalatest/flatspec/AnyFlatSpecLike;)Lorg/scalatest/Notifier;
    flags: (0x1009) ACC_PUBLIC, ACC_STATIC, ACC_SYNTHETIC
    Code:
      stack=1, locals=1, args_size=1
         0: aload_0
         1: invokespecial #143                // InterfaceMethod note:()Lorg/scalatest/Notifier;
         4: areturn
      LineNumberTable:
        line 75: 0
      LocalVariableTable:
        Start  Length  Slot  Name   Signature
            0       5     0 $this   Lorg/scalatest/flatspec/AnyFlatSpecLike;
    MethodParameters:
      Name                           Flags
      $this                          final synthetic

  public default org.scalatest.Notifier note();
    descriptor: ()Lorg/scalatest/Notifier;
    flags: (0x0001) ACC_PUBLIC
    Code:
      stack=1, locals=1, args_size=1
         0: aload_0
         1: invokeinterface #122,  1          // InterfaceMethod org$scalatest$flatspec$AnyFlatSpecLike$$engine:()Lorg/scalatest/Engine;
         6: invokevirtual #146                // Method org/scalatest/Engine.atomicNotifier:()Ljava/util/concurrent/atomic/AtomicReference;
         9: invokevirtual #134                // Method java/util/concurrent/atomic/AtomicReference.get:()Ljava/lang/Object;
        12: checkcast     #148                // class org/scalatest/Notifier
        15: areturn
      LineNumberTable:
        line 75: 0
      LocalVariableTable:
        Start  Length  Slot  Name   Signature
            0      16     0  this   Lorg/scalatest/flatspec/AnyFlatSpecLike;

  public static org.scalatest.Alerter alert$(org.scalatest.flatspec.AnyFlatSpecLike);
    descriptor: (Lorg/scalatest/flatspec/AnyFlatSpecLike;)Lorg/scalatest/Alerter;
    flags: (0x1009) ACC_PUBLIC, ACC_STATIC, ACC_SYNTHETIC
    Code:
      stack=1, locals=1, args_size=1
         0: aload_0
         1: invokespecial #154                // InterfaceMethod alert:()Lorg/scalatest/Alerter;
         4: areturn
      LineNumberTable:
        line 85: 0
      LocalVariableTable:
        Start  Length  Slot  Name   Signature
            0       5     0 $this   Lorg/scalatest/flatspec/AnyFlatSpecLike;
    MethodParameters:
      Name                           Flags
      $this                          final synthetic

  public default org.scalatest.Alerter alert();
    descriptor: ()Lorg/scalatest/Alerter;
    flags: (0x0001) ACC_PUBLIC
    Code:
      stack=1, locals=1, args_size=1
         0: aload_0
         1: invokeinterface #122,  1          // InterfaceMethod org$scalatest$flatspec$AnyFlatSpecLike$$engine:()Lorg/scalatest/Engine;
         6: invokevirtual #157                // Method org/scalatest/Engine.atomicAlerter:()Ljava/util/concurrent/atomic/AtomicReference;
         9: invokevirtual #134                // Method java/util/concurrent/atomic/AtomicReference.get:()Ljava/lang/Object;
        12: checkcast     #159                // class org/scalatest/Alerter
        15: areturn
      LineNumberTable:
        line 85: 0
      LocalVariableTable:
        Start  Length  Slot  Name   Signature
            0      16     0  this   Lorg/scalatest/flatspec/AnyFlatSpecLike;

  public static org.scalatest.Documenter markup$(org.scalatest.flatspec.AnyFlatSpecLike);
    descriptor: (Lorg/scalatest/flatspec/AnyFlatSpecLike;)Lorg/scalatest/Documenter;
    flags: (0x1009) ACC_PUBLIC, ACC_STATIC, ACC_SYNTHETIC
    Code:
      stack=1, locals=1, args_size=1
         0: aload_0
         1: invokespecial #165                // InterfaceMethod markup:()Lorg/scalatest/Documenter;
         4: areturn
      LineNumberTable:
        line 96: 0
      LocalVariableTable:
        Start  Length  Slot  Name   Signature
            0       5     0 $this   Lorg/scalatest/flatspec/AnyFlatSpecLike;
    MethodParameters:
      Name                           Flags
      $this                          final synthetic

  public default org.scalatest.Documenter markup();
    descriptor: ()Lorg/scalatest/Documenter;
    flags: (0x0001) ACC_PUBLIC
    Code:
      stack=1, locals=1, args_size=1
         0: aload_0
         1: invokeinterface #122,  1          // InterfaceMethod org$scalatest$flatspec$AnyFlatSpecLike$$engine:()Lorg/scalatest/Engine;
         6: invokevirtual #168                // Method org/scalatest/Engine.atomicDocumenter:()Ljava/util/concurrent/atomic/AtomicReference;
         9: invokevirtual #134                // Method java/util/concurrent/atomic/AtomicReference.get:()Ljava/lang/Object;
        12: checkcast     #170                // class org/scalatest/Documenter
        15: areturn
      LineNumberTable:
        line 96: 0
      LocalVariableTable:
        Start  Length  Slot  Name   Signature
            0      16     0  this   Lorg/scalatest/flatspec/AnyFlatSpecLike;

  private void registerTestImpl(java.lang.String, scala.collection.immutable.Seq<org.scalatest.Tag>, scala.Function0<java.lang.Object>, org.scalactic.source.Position);
    descriptor: (Ljava/lang/String;Lscala/collection/immutable/Seq;Lscala/Function0;Lorg/scalactic/source/Position;)V
    flags: (0x0002) ACC_PRIVATE
    Code:
      stack=13, locals=6, args_size=5
         0: iconst_m1
         1: istore        5
         3: aload_0
         4: invokeinterface #122,  1          // InterfaceMethod org$scalatest$flatspec$AnyFlatSpecLike$$engine:()Lorg/scalatest/Engine;
         9: aload_1
        10: new           #179                // class org/scalatest/Transformer
        13: dup
        14: aload_3
        15: invokespecial #183                // Method org/scalatest/Transformer."<init>":(Lscala/Function0;)V
        18: invokedynamic #203,  0            // InvokeDynamic #0:apply:()Lscala/Function0;
        23: ldc           #204                // String AnyFlatSpecLike.scala
        25: ldc           #206                // String registerTest
        27: iconst_4
        28: iload         5
        30: getstatic     #212                // Field scala/None$.MODULE$:Lscala/None$;
        33: getstatic     #212                // Field scala/None$.MODULE$:Lscala/None$;
        36: new           #214                // class scala/Some
        39: dup
        40: aload         4
        42: invokespecial #217                // Method scala/Some."<init>":(Ljava/lang/Object;)V
        45: getstatic     #212                // Field scala/None$.MODULE$:Lscala/None$;
        48: aload_2
        49: invokevirtual #220                // Method org/scalatest/Engine.registerTest:(Ljava/lang/String;Ljava/lang/Object;Lscala/Function0;Ljava/lang/String;Ljava/lang/String;IILscala/Option;Lscala/Option;Lscala/Option;Lscala/Option;Lscala/collection/immutable/Seq;)Ljava/lang/String;
        52: pop
        53: return
      LineNumberTable:
        line 100: 0
        line 103: 3
      LocalVariableTable:
        Start  Length  Slot  Name   Signature
            3      50     5 stackDepthAdjustment   I
            0      54     0  this   Lorg/scalatest/flatspec/AnyFlatSpecLike;
            0      54     1 testText   Ljava/lang/String;
            0      54     2 testTags   Lscala/collection/immutable/Seq;
            0      54     3 testFun   Lscala/Function0;
            0      54     4   pos   Lorg/scalactic/source/Position;
    Signature: #173                         // (Ljava/lang/String;Lscala/collection/immutable/Seq<Lorg/scalatest/Tag;>;Lscala/Function0<Ljava/lang/Object;>;Lorg/scalactic/source/Position;)V
    MethodParameters:
      Name                           Flags
      testText                       final
      testTags                       final
      testFun                        final
      pos                            final

  public static void registerTest$(org.scalatest.flatspec.AnyFlatSpecLike, java.lang.String, scala.collection.immutable.Seq, scala.Function0, org.scalactic.source.Position);
    descriptor: (Lorg/scalatest/flatspec/AnyFlatSpecLike;Ljava/lang/String;Lscala/collection/immutable/Seq;Lscala/Function0;Lorg/scalactic/source/Position;)V
    flags: (0x1009) ACC_PUBLIC, ACC_STATIC, ACC_SYNTHETIC
    Code:
      stack=5, locals=5, args_size=5
         0: aload_0
         1: aload_1
         2: aload_2
         3: aload_3
         4: aload         4
         6: invokespecial #230                // InterfaceMethod registerTest:(Ljava/lang/String;Lscala/collection/immutable/Seq;Lscala/Function0;Lorg/scalactic/source/Position;)V
         9: return
      LineNumberTable:
        line 107: 0
      LocalVariableTable:
        Start  Length  Slot  Name   Signature
            0      10     0 $this   Lorg/scalatest/flatspec/AnyFlatSpecLike;
            0      10     1 testText   Ljava/lang/String;
            0      10     2 testTags   Lscala/collection/immutable/Seq;
            0      10     3 testFun   Lscala/Function0;
            0      10     4   pos   Lorg/scalactic/source/Position;
    MethodParameters:
      Name                           Flags
      $this                          final synthetic
      testText                       final
      testTags                       final
      testFun                        final
      pos                            final

  public default void registerTest(java.lang.String, scala.collection.immutable.Seq<org.scalatest.Tag>, scala.Function0<java.lang.Object>, org.scalactic.source.Position);
    descriptor: (Ljava/lang/String;Lscala/collection/immutable/Seq;Lscala/Function0;Lorg/scalactic/source/Position;)V
    flags: (0x0001) ACC_PUBLIC
    Code:
      stack=5, locals=5, args_size=5
         0: aload_0
         1: aload_1
         2: aload_2
         3: aload_3
         4: aload         4
         6: invokespecial #232                // InterfaceMethod registerTestImpl:(Ljava/lang/String;Lscala/collection/immutable/Seq;Lscala/Function0;Lorg/scalactic/source/Position;)V
         9: return
      LineNumberTable:
        line 108: 0
      LocalVariableTable:
        Start  Length  Slot  Name   Signature
            0      10     0  this   Lorg/scalatest/flatspec/AnyFlatSpecLike;
            0      10     1 testText   Ljava/lang/String;
            0      10     2 testTags   Lscala/collection/immutable/Seq;
            0      10     3 testFun   Lscala/Function0;
            0      10     4   pos   Lorg/scalactic/source/Position;
    Signature: #173                         // (Ljava/lang/String;Lscala/collection/immutable/Seq<Lorg/scalatest/Tag;>;Lscala/Function0<Ljava/lang/Object;>;Lorg/scalactic/source/Position;)V
    MethodParameters:
      Name                           Flags
      testText                       final
      testTags                       final
      testFun                        final
      pos                            final

  private void registerIgnoredTestImpl(java.lang.String, scala.collection.immutable.Seq<org.scalatest.Tag>, scala.Function0<java.lang.Object>, org.scalactic.source.Position);
    descriptor: (Ljava/lang/String;Lscala/collection/immutable/Seq;Lscala/Function0;Lorg/scalactic/source/Position;)V
    flags: (0x0002) ACC_PRIVATE
    Code:
      stack=12, locals=6, args_size=5
         0: bipush        -3
         2: istore        5
         4: aload_0
         5: invokeinterface #122,  1          // InterfaceMethod org$scalatest$flatspec$AnyFlatSpecLike$$engine:()Lorg/scalatest/Engine;
        10: aload_1
        11: new           #179                // class org/scalatest/Transformer
        14: dup
        15: aload_3
        16: invokespecial #183                // Method org/scalatest/Transformer."<init>":(Lscala/Function0;)V
        19: invokedynamic #238,  0            // InvokeDynamic #1:apply:()Lscala/Function0;
        24: ldc           #204                // String AnyFlatSpecLike.scala
        26: ldc           #240                // String registerIgnoredTest
        28: iconst_4
        29: iload         5
        31: getstatic     #212                // Field scala/None$.MODULE$:Lscala/None$;
        34: new           #214                // class scala/Some
        37: dup
        38: aload         4
        40: invokespecial #217                // Method scala/Some."<init>":(Ljava/lang/Object;)V
        43: aload_2
        44: invokevirtual #243                // Method org/scalatest/Engine.registerIgnoredTest:(Ljava/lang/String;Ljava/lang/Object;Lscala/Function0;Ljava/lang/String;Ljava/lang/String;IILscala/Option;Lscala/Option;Lscala/collection/immutable/Seq;)V
        47: return
      LineNumberTable:
        line 117: 0
        line 120: 4
      LocalVariableTable:
        Start  Length  Slot  Name   Signature
            4      43     5 stackDepthAdjustment   I
            0      48     0  this   Lorg/scalatest/flatspec/AnyFlatSpecLike;
            0      48     1 testText   Ljava/lang/String;
            0      48     2 testTags   Lscala/collection/immutable/Seq;
            0      48     3 testFun   Lscala/Function0;
            0      48     4   pos   Lorg/scalactic/source/Position;
    Signature: #173                         // (Ljava/lang/String;Lscala/collection/immutable/Seq<Lorg/scalatest/Tag;>;Lscala/Function0<Ljava/lang/Object;>;Lorg/scalactic/source/Position;)V
    MethodParameters:
      Name                           Flags
      testText                       final
      testTags                       final
      testFun                        final
      pos                            final

  public static void registerIgnoredTest$(org.scalatest.flatspec.AnyFlatSpecLike, java.lang.String, scala.collection.immutable.Seq, scala.Function0, org.scalactic.source.Position);
    descriptor: (Lorg/scalatest/flatspec/AnyFlatSpecLike;Ljava/lang/String;Lscala/collection/immutable/Seq;Lscala/Function0;Lorg/scalactic/source/Position;)V
    flags: (0x1009) ACC_PUBLIC, ACC_STATIC, ACC_SYNTHETIC
    Code:
      stack=5, locals=5, args_size=5
         0: aload_0
         1: aload_1
         2: aload_2
         3: aload_3
         4: aload         4
         6: invokespecial #246                // InterfaceMethod registerIgnoredTest:(Ljava/lang/String;Lscala/collection/immutable/Seq;Lscala/Function0;Lorg/scalactic/source/Position;)V
         9: return
      LineNumberTable:
        line 124: 0
      LocalVariableTable:
        Start  Length  Slot  Name   Signature
            0      10     0 $this   Lorg/scalatest/flatspec/AnyFlatSpecLike;
            0      10     1 testText   Ljava/lang/String;
            0      10     2 testTags   Lscala/collection/immutable/Seq;
            0      10     3 testFun   Lscala/Function0;
            0      10     4   pos   Lorg/scalactic/source/Position;
    MethodParameters:
      Name                           Flags
      $this                          final synthetic
      testText                       final
      testTags                       final
      testFun                        final
      pos                            final

  public default void registerIgnoredTest(java.lang.String, scala.collection.immutable.Seq<org.scalatest.Tag>, scala.Function0<java.lang.Object>, org.scalactic.source.Position);
    descriptor: (Ljava/lang/String;Lscala/collection/immutable/Seq;Lscala/Function0;Lorg/scalactic/source/Position;)V
    flags: (0x0001) ACC_PUBLIC
    Code:
      stack=5, locals=5, args_size=5
         0: aload_0
         1: aload_1
         2: aload_2
         3: aload_3
         4: aload         4
         6: invokespecial #248                // InterfaceMethod registerIgnoredTestImpl:(Ljava/lang/String;Lscala/collection/immutable/Seq;Lscala/Function0;Lorg/scalactic/source/Position;)V
         9: return
      LineNumberTable:
        line 125: 0
      LocalVariableTable:
        Start  Length  Slot  Name   Signature
            0      10     0  this   Lorg/scalatest/flatspec/AnyFlatSpecLike;
            0      10     1 testText   Ljava/lang/String;
            0      10     2 testTags   Lscala/collection/immutable/Seq;
            0      10     3 testFun   Lscala/Function0;
            0      10     4   pos   Lorg/scalactic/source/Position;
    Signature: #173                         // (Ljava/lang/String;Lscala/collection/immutable/Seq<Lorg/scalatest/Tag;>;Lscala/Function0<Ljava/lang/Object;>;Lorg/scalactic/source/Position;)V
    MethodParameters:
      Name                           Flags
      testText                       final
      testTags                       final
      testFun                        final
      pos                            final

  public static void org$scalatest$flatspec$AnyFlatSpecLike$$registerTestToRun$(org.scalatest.flatspec.AnyFlatSpecLike, java.lang.String, java.lang.String, scala.collection.immutable.List, scala.Function0, org.scalactic.source.Position);
    descriptor: (Lorg/scalatest/flatspec/AnyFlatSpecLike;Ljava/lang/String;Ljava/lang/String;Lscala/collection/immutable/List;Lscala/Function0;Lorg/scalactic/source/Position;)V
    flags: (0x1009) ACC_PUBLIC, ACC_STATIC, ACC_SYNTHETIC
    Code:
      stack=6, locals=6, args_size=6
         0: aload_0
         1: aload_1
         2: aload_2
         3: aload_3
         4: aload         4
         6: aload         5
         8: invokespecial #256                // InterfaceMethod org$scalatest$flatspec$AnyFlatSpecLike$$registerTestToRun:(Ljava/lang/String;Ljava/lang/String;Lscala/collection/immutable/List;Lscala/Function0;Lorg/scalactic/source/Position;)V
        11: return
      LineNumberTable:
        line 151: 0
      LocalVariableTable:
        Start  Length  Slot  Name   Signature
            0      12     0 $this   Lorg/scalatest/flatspec/AnyFlatSpecLike;
            0      12     1 specText   Ljava/lang/String;
            0      12     2 methodName   Ljava/lang/String;
            0      12     3 testTags   Lscala/collection/immutable/List;
            0      12     4 testFun   Lscala/Function0;
            0      12     5   pos   Lorg/scalactic/source/Position;
    MethodParameters:
      Name                           Flags
      $this                          final synthetic
      specText                       final
      methodName                     final
      testTags                       final
      testFun                        final
      pos                            final

  public default void org$scalatest$flatspec$AnyFlatSpecLike$$registerTestToRun(java.lang.String, java.lang.String, scala.collection.immutable.List<org.scalatest.Tag>, scala.Function0<java.lang.Object>, org.scalactic.source.Position);
    descriptor: (Ljava/lang/String;Ljava/lang/String;Lscala/collection/immutable/List;Lscala/Function0;Lorg/scalactic/source/Position;)V
    flags: (0x0001) ACC_PUBLIC
    Code:
      stack=13, locals=8, args_size=6
         0: iconst_4
         1: istore        6
         3: bipush        -3
         5: istore        7
         7: aload_0
         8: invokeinterface #122,  1          // InterfaceMethod org$scalatest$flatspec$AnyFlatSpecLike$$engine:()Lorg/scalatest/Engine;
        13: aload_1
        14: new           #179                // class org/scalatest/Transformer
        17: dup
        18: aload         4
        20: invokespecial #183                // Method org/scalatest/Transformer."<init>":(Lscala/Function0;)V
        23: aload_2
        24: invokedynamic #266,  0            // InvokeDynamic #2:apply:(Ljava/lang/String;)Lscala/Function0;
        29: ldc           #204                // String AnyFlatSpecLike.scala
        31: aload_2
        32: iload         6
        34: iload         7
        36: getstatic     #212                // Field scala/None$.MODULE$:Lscala/None$;
        39: getstatic     #212                // Field scala/None$.MODULE$:Lscala/None$;
        42: new           #214                // class scala/Some
        45: dup
        46: aload         5
        48: invokespecial #217                // Method scala/Some."<init>":(Ljava/lang/Object;)V
        51: getstatic     #212                // Field scala/None$.MODULE$:Lscala/None$;
        54: aload_3
        55: invokevirtual #220                // Method org/scalatest/Engine.registerTest:(Ljava/lang/String;Ljava/lang/Object;Lscala/Function0;Ljava/lang/String;Ljava/lang/String;IILscala/Option;Lscala/Option;Lscala/Option;Lscala/Option;Lscala/collection/immutable/Seq;)Ljava/lang/String;
        58: pop
        59: return
      LineNumberTable:
        line 153: 0
        line 154: 3
        line 163: 7
      LocalVariableTable:
        Start  Length  Slot  Name   Signature
            3      56     6 stackDepth   I
            7      52     7 stackDepthAdjustment   I
            0      60     0  this   Lorg/scalatest/flatspec/AnyFlatSpecLike;
            0      60     1 specText   Ljava/lang/String;
            0      60     2 methodName   Ljava/lang/String;
            0      60     3 testTags   Lscala/collection/immutable/List;
            0      60     4 testFun   Lscala/Function0;
            0      60     5   pos   Lorg/scalactic/source/Position;
    Signature: #258                         // (Ljava/lang/String;Ljava/lang/String;Lscala/collection/immutable/List<Lorg/scalatest/Tag;>;Lscala/Function0<Ljava/lang/Object;>;Lorg/scalactic/source/Position;)V
    MethodParameters:
      Name                           Flags
      specText                       final
      methodName                     final
      testTags                       final
      testFun                        final
      pos                            final

  public abstract org.scalatest.flatspec.AnyFlatSpecLike$BehaviorWord behavior();
    descriptor: ()Lorg/scalatest/flatspec/AnyFlatSpecLike$BehaviorWord;
    flags: (0x0401) ACC_PUBLIC, ACC_ABSTRACT

  public abstract org.scalatest.flatspec.AnyFlatSpecLike$ItWord it();
    descriptor: ()Lorg/scalatest/flatspec/AnyFlatSpecLike$ItWord;
    flags: (0x0401) ACC_PUBLIC, ACC_ABSTRACT

  public abstract org.scalatest.flatspec.AnyFlatSpecLike$IgnoreWord ignore();
    descriptor: ()Lorg/scalatest/flatspec/AnyFlatSpecLike$IgnoreWord;
    flags: (0x0401) ACC_PUBLIC, ACC_ABSTRACT

  public abstract org.scalatest.flatspec.AnyFlatSpecLike$TheyWord they();
    descriptor: ()Lorg/scalatest/flatspec/AnyFlatSpecLike$TheyWord;
    flags: (0x0401) ACC_PUBLIC, ACC_ABSTRACT

  public static org.scalatest.flatspec.AnyFlatSpecLike$InAndIgnoreMethods convertToInAndIgnoreMethods$(org.scalatest.flatspec.AnyFlatSpecLike, org.scalatest.verbs.ResultOfStringPassedToVerb);
    descriptor: (Lorg/scalatest/flatspec/AnyFlatSpecLike;Lorg/scalatest/verbs/ResultOfStringPassedToVerb;)Lorg/scalatest/flatspec/AnyFlatSpecLike$InAndIgnoreMethods;
    flags: (0x1009) ACC_PUBLIC, ACC_STATIC, ACC_SYNTHETIC
    Code:
      stack=2, locals=2, args_size=2
         0: aload_0
         1: aload_1
         2: invokespecial #282                // InterfaceMethod convertToInAndIgnoreMethods:(Lorg/scalatest/verbs/ResultOfStringPassedToVerb;)Lorg/scalatest/flatspec/AnyFlatSpecLike$InAndIgnoreMethods;
         5: areturn
      LineNumberTable:
        line 1550: 0
      LocalVariableTable:
        Start  Length  Slot  Name   Signature
            0       6     0 $this   Lorg/scalatest/flatspec/AnyFlatSpecLike;
            0       6     1 resultOfStringPassedToVerb   Lorg/scalatest/verbs/ResultOfStringPassedToVerb;
    MethodParameters:
      Name                           Flags
      $this                          final synthetic
      resultOfStringPassedToVerb     final

  public default org.scalatest.flatspec.AnyFlatSpecLike$InAndIgnoreMethods convertToInAndIgnoreMethods(org.scalatest.verbs.ResultOfStringPassedToVerb);
    descriptor: (Lorg/scalatest/verbs/ResultOfStringPassedToVerb;)Lorg/scalatest/flatspec/AnyFlatSpecLike$InAndIgnoreMethods;
    flags: (0x0001) ACC_PUBLIC
    Code:
      stack=4, locals=2, args_size=2
         0: new           #65                 // class org/scalatest/flatspec/AnyFlatSpecLike$InAndIgnoreMethods
         3: dup
         4: aload_0
         5: aload_1
         6: invokespecial #286                // Method org/scalatest/flatspec/AnyFlatSpecLike$InAndIgnoreMethods."<init>":(Lorg/scalatest/flatspec/AnyFlatSpecLike;Lorg/scalatest/verbs/ResultOfStringPassedToVerb;)V
         9: areturn
      LineNumberTable:
        line 1551: 0
      LocalVariableTable:
        Start  Length  Slot  Name   Signature
            0      10     0  this   Lorg/scalatest/flatspec/AnyFlatSpecLike;
            0      10     1 resultOfStringPassedToVerb   Lorg/scalatest/verbs/ResultOfStringPassedToVerb;
    MethodParameters:
      Name                           Flags
      resultOfStringPassedToVerb     final

  public static org.scalatest.flatspec.AnyFlatSpecLike$InAndIgnoreMethodsAfterTaggedAs convertToInAndIgnoreMethodsAfterTaggedAs$(org.scalatest.flatspec.AnyFlatSpecLike, org.scalatest.verbs.ResultOfTaggedAsInvocation);
    descriptor: (Lorg/scalatest/flatspec/AnyFlatSpecLike;Lorg/scalatest/verbs/ResultOfTaggedAsInvocation;)Lorg/scalatest/flatspec/AnyFlatSpecLike$InAndIgnoreMethodsAfterTaggedAs;
    flags: (0x1009) ACC_PUBLIC, ACC_STATIC, ACC_SYNTHETIC
    Code:
      stack=2, locals=2, args_size=2
         0: aload_0
         1: aload_1
         2: invokespecial #293                // InterfaceMethod convertToInAndIgnoreMethodsAfterTaggedAs:(Lorg/scalatest/verbs/ResultOfTaggedAsInvocation;)Lorg/scalatest/flatspec/AnyFlatSpecLike$InAndIgnoreMethodsAfterTaggedAs;
         5: areturn
      LineNumberTable:
        line 1658: 0
      LocalVariableTable:
        Start  Length  Slot  Name   Signature
            0       6     0 $this   Lorg/scalatest/flatspec/AnyFlatSpecLike;
            0       6     1 resultOfTaggedAsInvocation   Lorg/scalatest/verbs/ResultOfTaggedAsInvocation;
    MethodParameters:
      Name                           Flags
      $this                          final synthetic
      resultOfTaggedAsInvocation     final

  public default org.scalatest.flatspec.AnyFlatSpecLike$InAndIgnoreMethodsAfterTaggedAs convertToInAndIgnoreMethodsAfterTaggedAs(org.scalatest.verbs.ResultOfTaggedAsInvocation);
    descriptor: (Lorg/scalatest/verbs/ResultOfTaggedAsInvocation;)Lorg/scalatest/flatspec/AnyFlatSpecLike$InAndIgnoreMethodsAfterTaggedAs;
    flags: (0x0001) ACC_PUBLIC
    Code:
      stack=4, locals=2, args_size=2
         0: new           #68                 // class org/scalatest/flatspec/AnyFlatSpecLike$InAndIgnoreMethodsAfterTaggedAs
         3: dup
         4: aload_0
         5: aload_1
         6: invokespecial #297                // Method org/scalatest/flatspec/AnyFlatSpecLike$InAndIgnoreMethodsAfterTaggedAs."<init>":(Lorg/scalatest/flatspec/AnyFlatSpecLike;Lorg/scalatest/verbs/ResultOfTaggedAsInvocation;)V
         9: areturn
      LineNumberTable:
        line 1659: 0
      LocalVariableTable:
        Start  Length  Slot  Name   Signature
            0      10     0  this   Lorg/scalatest/flatspec/AnyFlatSpecLike;
            0      10     1 resultOfTaggedAsInvocation   Lorg/scalatest/verbs/ResultOfTaggedAsInvocation;
    MethodParameters:
      Name                           Flags
      resultOfTaggedAsInvocation     final

  public abstract org.scalatest.verbs.StringVerbStringInvocation shorthandTestRegistrationFunction();
    descriptor: ()Lorg/scalatest/verbs/StringVerbStringInvocation;
    flags: (0x0401) ACC_PUBLIC, ACC_ABSTRACT

  public abstract org.scalatest.verbs.StringVerbBehaveLikeInvocation shorthandSharedTestRegistrationFunction();
    descriptor: ()Lorg/scalatest/verbs/StringVerbBehaveLikeInvocation;
    flags: (0x0401) ACC_PUBLIC, ACC_ABSTRACT

  public static void org$scalatest$flatspec$AnyFlatSpecLike$$registerTestToIgnore$(org.scalatest.flatspec.AnyFlatSpecLike, java.lang.String, scala.collection.immutable.List, java.lang.String, scala.Function0, org.scalactic.source.Position);
    descriptor: (Lorg/scalatest/flatspec/AnyFlatSpecLike;Ljava/lang/String;Lscala/collection/immutable/List;Ljava/lang/String;Lscala/Function0;Lorg/scalactic/source/Position;)V
    flags: (0x1009) ACC_PUBLIC, ACC_STATIC, ACC_SYNTHETIC
    Code:
      stack=6, locals=6, args_size=6
         0: aload_0
         1: aload_1
         2: aload_2
         3: aload_3
         4: aload         4
         6: aload         5
         8: invokespecial #307                // InterfaceMethod org$scalatest$flatspec$AnyFlatSpecLike$$registerTestToIgnore:(Ljava/lang/String;Lscala/collection/immutable/List;Ljava/lang/String;Lscala/Function0;Lorg/scalactic/source/Position;)V
        11: return
      LineNumberTable:
        line 1764: 0
      LocalVariableTable:
        Start  Length  Slot  Name   Signature
            0      12     0 $this   Lorg/scalatest/flatspec/AnyFlatSpecLike;
            0      12     1 specText   Ljava/lang/String;
            0      12     2 testTags   Lscala/collection/immutable/List;
            0      12     3 methodName   Ljava/lang/String;
            0      12     4 testFun   Lscala/Function0;
            0      12     5   pos   Lorg/scalactic/source/Position;
    MethodParameters:
      Name                           Flags
      $this                          final synthetic
      specText                       final
      testTags                       final
      methodName                     final
      testFun                        final
      pos                            final

  public default void org$scalatest$flatspec$AnyFlatSpecLike$$registerTestToIgnore(java.lang.String, scala.collection.immutable.List<org.scalatest.Tag>, java.lang.String, scala.Function0<java.lang.Object>, org.scalactic.source.Position);
    descriptor: (Ljava/lang/String;Lscala/collection/immutable/List;Ljava/lang/String;Lscala/Function0;Lorg/scalactic/source/Position;)V
    flags: (0x0001) ACC_PUBLIC
    Code:
      stack=12, locals=8, args_size=6
         0: iconst_4
         1: istore        6
         3: bipush        -4
         5: istore        7
         7: aload_0
         8: invokeinterface #122,  1          // InterfaceMethod org$scalatest$flatspec$AnyFlatSpecLike$$engine:()Lorg/scalatest/Engine;
        13: aload_1
        14: new           #179                // class org/scalatest/Transformer
        17: dup
        18: aload         4
        20: invokespecial #183                // Method org/scalatest/Transformer."<init>":(Lscala/Function0;)V
        23: invokedynamic #313,  0            // InvokeDynamic #3:apply:()Lscala/Function0;
        28: ldc           #204                // String AnyFlatSpecLike.scala
        30: aload_3
        31: iload         6
        33: iload         7
        35: getstatic     #212                // Field scala/None$.MODULE$:Lscala/None$;
        38: new           #214                // class scala/Some
        41: dup
        42: aload         5
        44: invokespecial #217                // Method scala/Some."<init>":(Ljava/lang/Object;)V
        47: aload_2
        48: invokevirtual #243                // Method org/scalatest/Engine.registerIgnoredTest:(Ljava/lang/String;Ljava/lang/Object;Lscala/Function0;Ljava/lang/String;Ljava/lang/String;IILscala/Option;Lscala/Option;Lscala/collection/immutable/Seq;)V
        51: return
      LineNumberTable:
        line 1766: 0
        line 1767: 3
        line 1771: 7
      LocalVariableTable:
        Start  Length  Slot  Name   Signature
            3      48     6 stackDepth   I
            7      44     7 stackDepthAdjustment   I
            0      52     0  this   Lorg/scalatest/flatspec/AnyFlatSpecLike;
            0      52     1 specText   Ljava/lang/String;
            0      52     2 testTags   Lscala/collection/immutable/List;
            0      52     3 methodName   Ljava/lang/String;
            0      52     4 testFun   Lscala/Function0;
            0      52     5   pos   Lorg/scalactic/source/Position;
    Signature: #308                         // (Ljava/lang/String;Lscala/collection/immutable/List<Lorg/scalatest/Tag;>;Ljava/lang/String;Lscala/Function0<Ljava/lang/Object;>;Lorg/scalactic/source/Position;)V
    MethodParameters:
      Name                           Flags
      specText                       final
      testTags                       final
      methodName                     final
      testFun                        final
      pos                            final

  public static scala.collection.immutable.Map tags$(org.scalatest.flatspec.AnyFlatSpecLike);
    descriptor: (Lorg/scalatest/flatspec/AnyFlatSpecLike;)Lscala/collection/immutable/Map;
    flags: (0x1009) ACC_PUBLIC, ACC_STATIC, ACC_SYNTHETIC
    Code:
      stack=1, locals=1, args_size=1
         0: aload_0
         1: invokespecial #319                // InterfaceMethod tags:()Lscala/collection/immutable/Map;
         4: areturn
      LineNumberTable:
        line 1789: 0
      LocalVariableTable:
        Start  Length  Slot  Name   Signature
            0       5     0 $this   Lorg/scalatest/flatspec/AnyFlatSpecLike;
    MethodParameters:
      Name                           Flags
      $this                          final synthetic

  public default scala.collection.immutable.Map<java.lang.String, scala.collection.immutable.Set<java.lang.String>> tags();
    descriptor: ()Lscala/collection/immutable/Map;
    flags: (0x0001) ACC_PUBLIC
    Code:
      stack=3, locals=1, args_size=1
         0: getstatic     #325                // Field org/scalatest/Suite$.MODULE$:Lorg/scalatest/Suite$;
         3: aload_0
         4: invokeinterface #122,  1          // InterfaceMethod org$scalatest$flatspec$AnyFlatSpecLike$$engine:()Lorg/scalatest/Engine;
         9: invokevirtual #328                // Method org/scalatest/Engine.atomic:()Ljava/util/concurrent/atomic/AtomicReference;
        12: invokevirtual #134                // Method java/util/concurrent/atomic/AtomicReference.get:()Ljava/lang/Object;
        15: checkcast     #36                 // class org/scalatest/SuperEngine$Bundle
        18: invokevirtual #331                // Method org/scalatest/SuperEngine$Bundle.tagsMap:()Lscala/collection/immutable/Map;
        21: aload_0
        22: invokevirtual #335                // Method org/scalatest/Suite$.autoTagClassAnnotations:(Lscala/collection/immutable/Map;Lorg/scalatest/Suite;)Lscala/collection/immutable/Map;
        25: areturn
      LineNumberTable:
        line 1789: 0
      LocalVariableTable:
        Start  Length  Slot  Name   Signature
            0      26     0  this   Lorg/scalatest/flatspec/AnyFlatSpecLike;
    Signature: #320                         // ()Lscala/collection/immutable/Map<Ljava/lang/String;Lscala/collection/immutable/Set<Ljava/lang/String;>;>;

  public static org.scalatest.Status runTest$(org.scalatest.flatspec.AnyFlatSpecLike, java.lang.String, org.scalatest.Args);
    descriptor: (Lorg/scalatest/flatspec/AnyFlatSpecLike;Ljava/lang/String;Lorg/scalatest/Args;)Lorg/scalatest/Status;
    flags: (0x1009) ACC_PUBLIC, ACC_STATIC, ACC_SYNTHETIC
    Code:
      stack=3, locals=3, args_size=3
         0: aload_0
         1: aload_1
         2: aload_2
         3: invokespecial #341                // InterfaceMethod runTest:(Ljava/lang/String;Lorg/scalatest/Args;)Lorg/scalatest/Status;
         6: areturn
      LineNumberTable:
        line 1804: 0
      LocalVariableTable:
        Start  Length  Slot  Name   Signature
            0       7     0 $this   Lorg/scalatest/flatspec/AnyFlatSpecLike;
            0       7     1 testName   Ljava/lang/String;
            0       7     2  args   Lorg/scalatest/Args;
    MethodParameters:
      Name                           Flags
      $this                          final synthetic
      testName                       final
      args                           final

  public default org.scalatest.Status runTest(java.lang.String, org.scalatest.Args);
    descriptor: (Ljava/lang/String;Lorg/scalatest/Args;)Lorg/scalatest/Status;
    flags: (0x0001) ACC_PUBLIC
    Code:
      stack=8, locals=3, args_size=3
         0: aload_0
         1: invokeinterface #122,  1          // InterfaceMethod org$scalatest$flatspec$AnyFlatSpecLike$$engine:()Lorg/scalatest/Engine;
         6: aload_0
         7: aload_1
         8: aload_2
         9: iconst_1
        10: aload_0
        11: aload_2
        12: aload_1
        13: invokedynamic #354,  0            // InvokeDynamic #4:apply:(Lorg/scalatest/flatspec/AnyFlatSpecLike;Lorg/scalatest/Args;Ljava/lang/String;)Lscala/Function1;
        18: invokevirtual #358                // Method org/scalatest/Engine.runTestImpl:(Lorg/scalatest/Suite;Ljava/lang/String;Lorg/scalatest/Args;ZLscala/Function1;)Lorg/scalatest/Status;
        21: areturn
      LineNumberTable:
        line 1822: 0
      LocalVariableTable:
        Start  Length  Slot  Name   Signature
            0      22     0  this   Lorg/scalatest/flatspec/AnyFlatSpecLike;
            0      22     1 testName   Ljava/lang/String;
            0      22     2  args   Lorg/scalatest/Args;
    MethodParameters:
      Name                           Flags
      testName                       final
      args                           final

  public static org.scalatest.Status runTests$(org.scalatest.flatspec.AnyFlatSpecLike, scala.Option, org.scalatest.Args);
    descriptor: (Lorg/scalatest/flatspec/AnyFlatSpecLike;Lscala/Option;Lorg/scalatest/Args;)Lorg/scalatest/Status;
    flags: (0x1009) ACC_PUBLIC, ACC_STATIC, ACC_SYNTHETIC
    Code:
      stack=3, locals=3, args_size=3
         0: aload_0
         1: aload_1
         2: aload_2
         3: invokespecial #363                // InterfaceMethod runTests:(Lscala/Option;Lorg/scalatest/Args;)Lorg/scalatest/Status;
         6: areturn
      LineNumberTable:
        line 1879: 0
      LocalVariableTable:
        Start  Length  Slot  Name   Signature
            0       7     0 $this   Lorg/scalatest/flatspec/AnyFlatSpecLike;
            0       7     1 testName   Lscala/Option;
            0       7     2  args   Lorg/scalatest/Args;
    MethodParameters:
      Name                           Flags
      $this                          final synthetic
      testName                       final
      args                           final

  public default org.scalatest.Status runTests(scala.Option<java.lang.String>, org.scalatest.Args);
    descriptor: (Lscala/Option;Lorg/scalatest/Args;)Lorg/scalatest/Status;
    flags: (0x0001) ACC_PUBLIC
    Code:
      stack=7, locals=3, args_size=3
         0: aload_0
         1: invokeinterface #122,  1          // InterfaceMethod org$scalatest$flatspec$AnyFlatSpecLike$$engine:()Lorg/scalatest/Engine;
         6: aload_0
         7: aload_1
         8: aload_2
         9: aload_0
        10: invokeinterface #119,  1          // InterfaceMethod info:()Lorg/scalatest/Informer;
        15: iconst_1
        16: aload_0
        17: invokedynamic #375,  0            // InvokeDynamic #5:apply:(Lorg/scalatest/flatspec/AnyFlatSpecLike;)Lscala/Function2;
        22: invokevirtual #379                // Method org/scalatest/Engine.runTestsImpl:(Lorg/scalatest/Suite;Lscala/Option;Lorg/scalatest/Args;Lorg/scalatest/Informer;ZLscala/Function2;)Lorg/scalatest/Status;
        25: areturn
      LineNumberTable:
        line 1880: 0
      LocalVariableTable:
        Start  Length  Slot  Name   Signature
            0      26     0  this   Lorg/scalatest/flatspec/AnyFlatSpecLike;
            0      26     1 testName   Lscala/Option;
            0      26     2  args   Lorg/scalatest/Args;
    Signature: #365                         // (Lscala/Option<Ljava/lang/String;>;Lorg/scalatest/Args;)Lorg/scalatest/Status;
    MethodParameters:
      Name                           Flags
      testName                       final
      args                           final

  public static scala.collection.immutable.Set testNames$(org.scalatest.flatspec.AnyFlatSpecLike);
    descriptor: (Lorg/scalatest/flatspec/AnyFlatSpecLike;)Lscala/collection/immutable/Set;
    flags: (0x1009) ACC_PUBLIC, ACC_STATIC, ACC_SYNTHETIC
    Code:
      stack=1, locals=1, args_size=1
         0: aload_0
         1: invokespecial #385                // InterfaceMethod testNames:()Lscala/collection/immutable/Set;
         4: areturn
      LineNumberTable:
        line 1919: 0
      LocalVariableTable:
        Start  Length  Slot  Name   Signature
            0       5     0 $this   Lorg/scalatest/flatspec/AnyFlatSpecLike;
    MethodParameters:
      Name                           Flags
      $this                          final synthetic

  public default scala.collection.immutable.Set<java.lang.String> testNames();
    descriptor: ()Lscala/collection/immutable/Set;
    flags: (0x0001) ACC_PUBLIC
    Code:
      stack=2, locals=1, args_size=1
         0: getstatic     #391                // Field org/scalatest/InsertionOrderSet$.MODULE$:Lorg/scalatest/InsertionOrderSet$;
         3: aload_0
         4: invokeinterface #122,  1          // InterfaceMethod org$scalatest$flatspec$AnyFlatSpecLike$$engine:()Lorg/scalatest/Engine;
         9: invokevirtual #328                // Method org/scalatest/Engine.atomic:()Ljava/util/concurrent/atomic/AtomicReference;
        12: invokevirtual #134                // Method java/util/concurrent/atomic/AtomicReference.get:()Ljava/lang/Object;
        15: checkcast     #36                 // class org/scalatest/SuperEngine$Bundle
        18: invokevirtual #395                // Method org/scalatest/SuperEngine$Bundle.testNamesList:()Lscala/collection/immutable/List;
        21: invokevirtual #398                // Method org/scalatest/InsertionOrderSet$.apply:(Lscala/collection/immutable/List;)Lscala/collection/immutable/Set;
        24: areturn
      LineNumberTable:
        line 1920: 0
      LocalVariableTable:
        Start  Length  Slot  Name   Signature
            0      25     0  this   Lorg/scalatest/flatspec/AnyFlatSpecLike;
    Signature: #386                         // ()Lscala/collection/immutable/Set<Ljava/lang/String;>;

  public static org.scalatest.Status run$(org.scalatest.flatspec.AnyFlatSpecLike, scala.Option, org.scalatest.Args);
    descriptor: (Lorg/scalatest/flatspec/AnyFlatSpecLike;Lscala/Option;Lorg/scalatest/Args;)Lorg/scalatest/Status;
    flags: (0x1009) ACC_PUBLIC, ACC_STATIC, ACC_SYNTHETIC
    Code:
      stack=3, locals=3, args_size=3
         0: aload_0
         1: aload_1
         2: aload_2
         3: invokespecial #402                // InterfaceMethod run:(Lscala/Option;Lorg/scalatest/Args;)Lorg/scalatest/Status;
         6: areturn
      LineNumberTable:
        line 1923: 0
      LocalVariableTable:
        Start  Length  Slot  Name   Signature
            0       7     0 $this   Lorg/scalatest/flatspec/AnyFlatSpecLike;
            0       7     1 testName   Lscala/Option;
            0       7     2  args   Lorg/scalatest/Args;
    MethodParameters:
      Name                           Flags
      $this                          final synthetic
      testName                       final
      args                           final

  public default org.scalatest.Status run(scala.Option<java.lang.String>, org.scalatest.Args);
    descriptor: (Lscala/Option;Lorg/scalatest/Args;)Lorg/scalatest/Status;
    flags: (0x0001) ACC_PUBLIC
    Code:
      stack=5, locals=3, args_size=3
         0: aload_0
         1: invokeinterface #122,  1          // InterfaceMethod org$scalatest$flatspec$AnyFlatSpecLike$$engine:()Lorg/scalatest/Engine;
         6: aload_0
         7: aload_1
         8: aload_2
         9: aload_0
        10: invokedynamic #408,  0            // InvokeDynamic #6:apply:(Lorg/scalatest/flatspec/AnyFlatSpecLike;)Lscala/Function2;
        15: invokevirtual #412                // Method org/scalatest/Engine.runImpl:(Lorg/scalatest/Suite;Lscala/Option;Lorg/scalatest/Args;Lscala/Function2;)Lorg/scalatest/Status;
        18: areturn
      LineNumberTable:
        line 1925: 0
      LocalVariableTable:
        Start  Length  Slot  Name   Signature
            0      19     0  this   Lorg/scalatest/flatspec/AnyFlatSpecLike;
            0      19     1 testName   Lscala/Option;
            0      19     2  args   Lorg/scalatest/Args;
    Signature: #365                         // (Lscala/Option<Ljava/lang/String;>;Lorg/scalatest/Args;)Lorg/scalatest/Status;
    MethodParameters:
      Name                           Flags
      testName                       final
      args                           final

  public abstract org.scalatest.verbs.BehaveWord behave();
    descriptor: ()Lorg/scalatest/verbs/BehaveWord;
    flags: (0x0401) ACC_PUBLIC, ACC_ABSTRACT

  public abstract java.lang.String styleName();
    descriptor: ()Ljava/lang/String;
    flags: (0x0401) ACC_PUBLIC, ACC_ABSTRACT
    Deprecated: true

  public static org.scalatest.TestData testDataFor$(org.scalatest.flatspec.AnyFlatSpecLike, java.lang.String, org.scalatest.ConfigMap);
    descriptor: (Lorg/scalatest/flatspec/AnyFlatSpecLike;Ljava/lang/String;Lorg/scalatest/ConfigMap;)Lorg/scalatest/TestData;
    flags: (0x1009) ACC_PUBLIC, ACC_STATIC, ACC_SYNTHETIC
    Code:
      stack=3, locals=3, args_size=3
         0: aload_0
         1: aload_1
         2: aload_2
         3: invokespecial #422                // InterfaceMethod testDataFor:(Ljava/lang/String;Lorg/scalatest/ConfigMap;)Lorg/scalatest/TestData;
         6: areturn
      LineNumberTable:
        line 1956: 0
      LocalVariableTable:
        Start  Length  Slot  Name   Signature
            0       7     0 $this   Lorg/scalatest/flatspec/AnyFlatSpecLike;
            0       7     1 testName   Ljava/lang/String;
            0       7     2 theConfigMap   Lorg/scalatest/ConfigMap;
    MethodParameters:
      Name                           Flags
      $this                          final synthetic
      testName                       final
      theConfigMap                   final

  public default org.scalatest.TestData testDataFor(java.lang.String, org.scalatest.ConfigMap);
    descriptor: (Ljava/lang/String;Lorg/scalatest/ConfigMap;)Lorg/scalatest/TestData;
    flags: (0x0001) ACC_PUBLIC
    Code:
      stack=4, locals=3, args_size=3
         0: aload_0
         1: invokeinterface #122,  1          // InterfaceMethod org$scalatest$flatspec$AnyFlatSpecLike$$engine:()Lorg/scalatest/Engine;
         6: aload_1
         7: aload_2
         8: aload_0
         9: invokevirtual #427                // Method org/scalatest/Engine.createTestDataFor:(Ljava/lang/String;Lorg/scalatest/ConfigMap;Lorg/scalatest/Suite;)Lorg/scalatest/TestData;
        12: areturn
      LineNumberTable:
        line 1956: 0
      LocalVariableTable:
        Start  Length  Slot  Name   Signature
            0      13     0  this   Lorg/scalatest/flatspec/AnyFlatSpecLike;
            0      13     1 testName   Ljava/lang/String;
            0      13     2 theConfigMap   Lorg/scalatest/ConfigMap;
    MethodParameters:
      Name                           Flags
      testName                       final
      theConfigMap                   final

  public static org.scalatest.ConfigMap testDataFor$default$2$(org.scalatest.flatspec.AnyFlatSpecLike);
    descriptor: (Lorg/scalatest/flatspec/AnyFlatSpecLike;)Lorg/scalatest/ConfigMap;
    flags: (0x1009) ACC_PUBLIC, ACC_STATIC, ACC_SYNTHETIC
    Code:
      stack=1, locals=1, args_size=1
         0: aload_0
         1: invokespecial #433                // InterfaceMethod testDataFor$default$2:()Lorg/scalatest/ConfigMap;
         4: areturn
      LineNumberTable:
        line 1956: 0
      LocalVariableTable:
        Start  Length  Slot  Name   Signature
            0       5     0 $this   Lorg/scalatest/flatspec/AnyFlatSpecLike;
    MethodParameters:
      Name                           Flags
      $this                          final synthetic

  public default org.scalatest.ConfigMap testDataFor$default$2();
    descriptor: ()Lorg/scalatest/ConfigMap;
    flags: (0x0001) ACC_PUBLIC
    Code:
      stack=1, locals=1, args_size=1
         0: getstatic     #438                // Field org/scalatest/ConfigMap$.MODULE$:Lorg/scalatest/ConfigMap$;
         3: invokevirtual #441                // Method org/scalatest/ConfigMap$.empty:()Lorg/scalatest/ConfigMap;
         6: areturn
      LineNumberTable:
        line 1956: 0
      LocalVariableTable:
        Start  Length  Slot  Name   Signature
            0       7     0  this   Lorg/scalatest/flatspec/AnyFlatSpecLike;

  public static java.lang.String $anonfun$engine$1();
    descriptor: ()Ljava/lang/String;
    flags: (0x1009) ACC_PUBLIC, ACC_STATIC, ACC_SYNTHETIC
    Code:
      stack=1, locals=0, args_size=0
         0: getstatic     #447                // Field org/scalatest/Resources$.MODULE$:Lorg/scalatest/Resources$;
         3: invokevirtual #450                // Method org/scalatest/Resources$.concurrentSpecMod:()Ljava/lang/String;
         6: areturn
      LineNumberTable:
        line 53: 0

  public static java.lang.String $anonfun$registerTestImpl$1();
    descriptor: ()Ljava/lang/String;
    flags: (0x1009) ACC_PUBLIC, ACC_STATIC, ACC_SYNTHETIC
    Code:
      stack=1, locals=0, args_size=0
         0: getstatic     #447                // Field org/scalatest/Resources$.MODULE$:Lorg/scalatest/Resources$;
         3: invokevirtual #453                // Method org/scalatest/Resources$.testCannotBeNestedInsideAnotherTest:()Ljava/lang/String;
         6: areturn
      LineNumberTable:
        line 103: 0

  public static java.lang.String $anonfun$registerIgnoredTestImpl$1();
    descriptor: ()Ljava/lang/String;
    flags: (0x1009) ACC_PUBLIC, ACC_STATIC, ACC_SYNTHETIC
    Code:
      stack=1, locals=0, args_size=0
         0: getstatic     #447                // Field org/scalatest/Resources$.MODULE$:Lorg/scalatest/Resources$;
         3: invokevirtual #453                // Method org/scalatest/Resources$.testCannotBeNestedInsideAnotherTest:()Ljava/lang/String;
         6: areturn
      LineNumberTable:
        line 120: 0

  private static java.lang.String testRegistrationClosedMessageFun$1(java.lang.String);
    descriptor: (Ljava/lang/String;)Ljava/lang/String;
    flags: (0x000a) ACC_PRIVATE, ACC_STATIC
    Code:
      stack=3, locals=3, args_size=1
         0: aload_0
         1: astore_2
         2: aload_2
         3: ifnonnull     10
         6: iconst_0
         7: goto          14
        10: aload_2
        11: invokevirtual #461                // Method java/lang/String.hashCode:()I
        14: lookupswitch  { // 2
                    3365: 40
                    3370: 63
                 default: 86
            }
        40: ldc_w         #463                // String in
        43: aload_2
        44: invokevirtual #467                // Method java/lang/String.equals:(Ljava/lang/Object;)Z
        47: ifeq          60
        50: getstatic     #447                // Field org/scalatest/Resources$.MODULE$:Lorg/scalatest/Resources$;
        53: invokevirtual #470                // Method org/scalatest/Resources$.inCannotAppearInsideAnotherInOrIs:()Ljava/lang/String;
        56: astore_1
        57: goto          98
        60: goto          89
        63: ldc_w         #472                // String is
        66: aload_2
        67: invokevirtual #467                // Method java/lang/String.equals:(Ljava/lang/Object;)Z
        70: ifeq          83
        73: getstatic     #447                // Field org/scalatest/Resources$.MODULE$:Lorg/scalatest/Resources$;
        76: invokevirtual #475                // Method org/scalatest/Resources$.isCannotAppearInsideAnotherInOrIs:()Ljava/lang/String;
        79: astore_1
        80: goto          98
        83: goto          89
        86: goto          89
        89: new           #477                // class scala/MatchError
        92: dup
        93: aload_2
        94: invokespecial #478                // Method scala/MatchError."<init>":(Ljava/lang/Object;)V
        97: athrow
        98: aload_1
        99: areturn
      StackMapTable: number_of_entries = 9
        frame_type = 253 /* append */
          offset_delta = 10
          locals = [ top, class java/lang/String ]
        frame_type = 67 /* same_locals_1_stack_item */
          stack = [ int ]
        frame_type = 25 /* same */
        frame_type = 19 /* same */
        frame_type = 2 /* same */
        frame_type = 19 /* same */
        frame_type = 2 /* same */
        frame_type = 2 /* same */
        frame_type = 255 /* full_frame */
          offset_delta = 8
          locals = [ class java/lang/String, class java/lang/String, class java/lang/String ]
          stack = []
      LineNumberTable:
        line 159: 0
        line 160: 40
        line 159: 60
        line 161: 63
        line 159: 83
      LocalVariableTable:
        Start  Length  Slot  Name   Signature
            0     100     0 methodName$1   Ljava/lang/String;
    MethodParameters:
      Name                           Flags
      methodName$1                   final

  public static java.lang.String $anonfun$registerTestToRun$1(java.lang.String);
    descriptor: (Ljava/lang/String;)Ljava/lang/String;
    flags: (0x1009) ACC_PUBLIC, ACC_STATIC, ACC_SYNTHETIC
    Code:
      stack=1, locals=1, args_size=1
         0: aload_0
         1: invokestatic  #480                // InterfaceMethod testRegistrationClosedMessageFun$1:(Ljava/lang/String;)Ljava/lang/String;
         4: areturn
      LineNumberTable:
        line 163: 0
      LocalVariableTable:
        Start  Length  Slot  Name   Signature
            0       5     0 methodName$1   Ljava/lang/String;
    MethodParameters:
      Name                           Flags
      methodName$1                   final

  public static java.lang.String $anonfun$registerTestToIgnore$1();
    descriptor: ()Ljava/lang/String;
    flags: (0x1009) ACC_PUBLIC, ACC_STATIC, ACC_SYNTHETIC
    Code:
      stack=1, locals=0, args_size=0
         0: getstatic     #447                // Field org/scalatest/Resources$.MODULE$:Lorg/scalatest/Resources$;
         3: invokevirtual #483                // Method org/scalatest/Resources$.ignoreCannotAppearInsideAnInOrAnIs:()Ljava/lang/String;
         6: areturn
      LineNumberTable:
        line 1771: 0

  private org.scalatest.Outcome invokeWithFixture$1(org.scalatest.SuperEngine$TestLeaf, org.scalatest.Args, java.lang.String);
    descriptor: (Lorg/scalatest/SuperEngine$TestLeaf;Lorg/scalatest/Args;Ljava/lang/String;)Lorg/scalatest/Outcome;
    flags: (0x0002) ACC_PRIVATE
    Code:
      stack=6, locals=6, args_size=4
         0: aload_2
         1: invokevirtual #493                // Method org/scalatest/Args.configMap:()Lorg/scalatest/ConfigMap;
         4: astore        4
         6: aload_0
         7: aload_3
         8: aload         4
        10: invokeinterface #422,  3          // InterfaceMethod testDataFor:(Ljava/lang/String;Lorg/scalatest/ConfigMap;)Lorg/scalatest/TestData;
        15: astore        5
        17: aload_0
        18: new           #51                 // class org/scalatest/flatspec/AnyFlatSpecLike$$anon$5
        21: dup
        22: aconst_null
        23: aload         5
        25: aload_1
        26: invokespecial #496                // Method org/scalatest/flatspec/AnyFlatSpecLike$$anon$5."<init>":(Lorg/scalatest/flatspec/AnyFlatSpecLike;Lorg/scalatest/TestData;Lorg/scalatest/SuperEngine$TestLeaf;)V
        29: invokeinterface #500,  2          // InterfaceMethod withFixture:(Lorg/scalatest/TestSuite$NoArgTest;)Lorg/scalatest/Outcome;
        34: areturn
      LineNumberTable:
        line 1807: 0
        line 1808: 6
        line 1809: 17
        line 1810: 18
      LocalVariableTable:
        Start  Length  Slot  Name   Signature
            6      28     4 theConfigMap   Lorg/scalatest/ConfigMap;
           17      17     5 testData   Lorg/scalatest/TestData;
            0      35     0  this   Lorg/scalatest/flatspec/AnyFlatSpecLike;
            0      35     1 theTest   Lorg/scalatest/SuperEngine$TestLeaf;
            0      35     2 args$1   Lorg/scalatest/Args;
            0      35     3 testName$1   Ljava/lang/String;
    MethodParameters:
      Name                           Flags
      theTest                        final
      args$1                         final
      testName$1                     final

  public static org.scalatest.Outcome $anonfun$runTest$1(org.scalatest.flatspec.AnyFlatSpecLike, org.scalatest.Args, java.lang.String, org.scalatest.SuperEngine$TestLeaf);
    descriptor: (Lorg/scalatest/flatspec/AnyFlatSpecLike;Lorg/scalatest/Args;Ljava/lang/String;Lorg/scalatest/SuperEngine$TestLeaf;)Lorg/scalatest/Outcome;
    flags: (0x1009) ACC_PUBLIC, ACC_STATIC, ACC_SYNTHETIC
    Code:
      stack=4, locals=4, args_size=4
         0: aload_0
         1: aload_3
         2: aload_1
         3: aload_2
         4: invokespecial #505                // InterfaceMethod invokeWithFixture$1:(Lorg/scalatest/SuperEngine$TestLeaf;Lorg/scalatest/Args;Ljava/lang/String;)Lorg/scalatest/Outcome;
         7: areturn
      LineNumberTable:
        line 1822: 0
      LocalVariableTable:
        Start  Length  Slot  Name   Signature
            0       8     0 $this   Lorg/scalatest/flatspec/AnyFlatSpecLike;
            0       8     1 args$1   Lorg/scalatest/Args;
            0       8     2 testName$1   Ljava/lang/String;
            0       8     3 theTest   Lorg/scalatest/SuperEngine$TestLeaf;
    MethodParameters:
      Name                           Flags
      $this                          final synthetic
      args$1                         final
      testName$1                     final
      theTest                        final

  public static org.scalatest.Status $anonfun$runTests$1(org.scalatest.flatspec.AnyFlatSpecLike, java.lang.String, org.scalatest.Args);
    descriptor: (Lorg/scalatest/flatspec/AnyFlatSpecLike;Ljava/lang/String;Lorg/scalatest/Args;)Lorg/scalatest/Status;
    flags: (0x1009) ACC_PUBLIC, ACC_STATIC, ACC_SYNTHETIC
    Code:
      stack=3, locals=3, args_size=3
         0: aload_0
         1: aload_1
         2: aload_2
         3: invokeinterface #341,  3          // InterfaceMethod runTest:(Ljava/lang/String;Lorg/scalatest/Args;)Lorg/scalatest/Status;
         8: areturn
      LineNumberTable:
        line 1880: 0
      LocalVariableTable:
        Start  Length  Slot  Name   Signature
            0       9     0 $this   Lorg/scalatest/flatspec/AnyFlatSpecLike;
            0       9     1 testName   Ljava/lang/String;
            0       9     2  args   Lorg/scalatest/Args;
    MethodParameters:
      Name                           Flags
      $this                          final synthetic
      testName                       final
      args                           final

  public static org.scalatest.Status $anonfun$run$1(org.scalatest.flatspec.AnyFlatSpecLike, scala.Option, org.scalatest.Args);
    descriptor: (Lorg/scalatest/flatspec/AnyFlatSpecLike;Lscala/Option;Lorg/scalatest/Args;)Lorg/scalatest/Status;
    flags: (0x1009) ACC_PUBLIC, ACC_STATIC, ACC_SYNTHETIC
    Code:
      stack=3, locals=3, args_size=3
         0: aload_0
         1: aload_1
         2: aload_2
         3: invokeinterface #507,  3          // InterfaceMethod org$scalatest$flatspec$AnyFlatSpecLike$$super$run:(Lscala/Option;Lorg/scalatest/Args;)Lorg/scalatest/Status;
         8: areturn
      LineNumberTable:
        line 1925: 0
      LocalVariableTable:
        Start  Length  Slot  Name   Signature
            0       9     0 $this   Lorg/scalatest/flatspec/AnyFlatSpecLike;
            0       9     1 testName   Lscala/Option;
            0       9     2  args   Lorg/scalatest/Args;
    MethodParameters:
      Name                           Flags
      $this                          final synthetic
      testName                       final
      args                           final

  public static void $init$(org.scalatest.flatspec.AnyFlatSpecLike);
    descriptor: (Lorg/scalatest/flatspec/AnyFlatSpecLike;)V
    flags: (0x0009) ACC_PUBLIC, ACC_STATIC
    Code:
      stack=5, locals=1, args_size=1
         0: aload_0
         1: new           #124                // class org/scalatest/Engine
         4: dup
         5: invokedynamic #513,  0            // InvokeDynamic #7:apply:()Lscala/Function0;
        10: ldc_w         #515                // String Spec
        13: invokespecial #518                // Method org/scalatest/Engine."<init>":(Lscala/Function0;Ljava/lang/String;)V
        16: invokeinterface #520,  2          // InterfaceMethod org$scalatest$flatspec$AnyFlatSpecLike$_setter_$org$scalatest$flatspec$AnyFlatSpecLike$$engine_$eq:(Lorg/scalatest/Engine;)V
        21: aload_0
        22: new           #53                 // class org/scalatest/flatspec/AnyFlatSpecLike$BehaviorWord
        25: dup
        26: aload_0
        27: invokespecial #522                // Method org/scalatest/flatspec/AnyFlatSpecLike$BehaviorWord."<init>":(Lorg/scalatest/flatspec/AnyFlatSpecLike;)V
        30: invokeinterface #524,  2          // InterfaceMethod org$scalatest$flatspec$AnyFlatSpecLike$_setter_$behavior_$eq:(Lorg/scalatest/flatspec/AnyFlatSpecLike$BehaviorWord;)V
        35: aload_0
        36: new           #77                 // class org/scalatest/flatspec/AnyFlatSpecLike$ItWord
        39: dup
        40: aload_0
        41: invokespecial #525                // Method org/scalatest/flatspec/AnyFlatSpecLike$ItWord."<init>":(Lorg/scalatest/flatspec/AnyFlatSpecLike;)V
        44: invokeinterface #527,  2          // InterfaceMethod org$scalatest$flatspec$AnyFlatSpecLike$_setter_$it_$eq:(Lorg/scalatest/flatspec/AnyFlatSpecLike$ItWord;)V
        49: aload_0
        50: new           #62                 // class org/scalatest/flatspec/AnyFlatSpecLike$IgnoreWord
        53: dup
        54: aload_0
        55: invokespecial #528                // Method org/scalatest/flatspec/AnyFlatSpecLike$IgnoreWord."<init>":(Lorg/scalatest/flatspec/AnyFlatSpecLike;)V
        58: invokeinterface #530,  2          // InterfaceMethod org$scalatest$flatspec$AnyFlatSpecLike$_setter_$ignore_$eq:(Lorg/scalatest/flatspec/AnyFlatSpecLike$IgnoreWord;)V
        63: aload_0
        64: new           #86                 // class org/scalatest/flatspec/AnyFlatSpecLike$TheyWord
        67: dup
        68: aload_0
        69: invokespecial #531                // Method org/scalatest/flatspec/AnyFlatSpecLike$TheyWord."<init>":(Lorg/scalatest/flatspec/AnyFlatSpecLike;)V
        72: invokeinterface #533,  2          // InterfaceMethod org$scalatest$flatspec$AnyFlatSpecLike$_setter_$they_$eq:(Lorg/scalatest/flatspec/AnyFlatSpecLike$TheyWord;)V
        77: aload_0
        78: new           #47                 // class org/scalatest/flatspec/AnyFlatSpecLike$$anon$1
        81: dup
        82: aload_0
        83: invokespecial #534                // Method org/scalatest/flatspec/AnyFlatSpecLike$$anon$1."<init>":(Lorg/scalatest/flatspec/AnyFlatSpecLike;)V
        86: invokeinterface #536,  2          // InterfaceMethod org$scalatest$flatspec$AnyFlatSpecLike$_setter_$shorthandTestRegistrationFunction_$eq:(Lorg/scalatest/verbs/StringVerbStringInvocation;)V
        91: aload_0
        92: new           #49                 // class org/scalatest/flatspec/AnyFlatSpecLike$$anon$4
        95: dup
        96: aload_0
        97: invokespecial #537                // Method org/scalatest/flatspec/AnyFlatSpecLike$$anon$4."<init>":(Lorg/scalatest/flatspec/AnyFlatSpecLike;)V
       100: invokeinterface #539,  2          // InterfaceMethod org$scalatest$flatspec$AnyFlatSpecLike$_setter_$shorthandSharedTestRegistrationFunction_$eq:(Lorg/scalatest/verbs/StringVerbBehaveLikeInvocation;)V
       105: aload_0
       106: new           #541                // class org/scalatest/verbs/BehaveWord
       109: dup
       110: invokespecial #544                // Method org/scalatest/verbs/BehaveWord."<init>":()V
       113: invokeinterface #546,  2          // InterfaceMethod org$scalatest$flatspec$AnyFlatSpecLike$_setter_$behave_$eq:(Lorg/scalatest/verbs/BehaveWord;)V
       118: aload_0
       119: ldc_w         #548                // String org.scalatest.FlatSpec
       122: invokeinterface #550,  2          // InterfaceMethod org$scalatest$flatspec$AnyFlatSpecLike$_setter_$styleName_$eq:(Ljava/lang/String;)V
       127: return
      LineNumberTable:
        line 53: 0
        line 239: 21
        line 678: 35
        line 1005: 49
        line 1444: 63
        line 1683: 77
        line 1684: 78
        line 1732: 91
        line 1733: 92
        line 1945: 105
        line 1954: 118
        line 51: 127
      LocalVariableTable:
        Start  Length  Slot  Name   Signature
            0     128     0 $this   Lorg/scalatest/flatspec/AnyFlatSpecLike;
    MethodParameters:
      Name                           Flags
      $this                          final synthetic

  private static java.lang.Object $deserializeLambda$(java.lang.invoke.SerializedLambda);
    descriptor: (Ljava/lang/invoke/SerializedLambda;)Ljava/lang/Object;
    flags: (0x100a) ACC_PRIVATE, ACC_STATIC, ACC_SYNTHETIC
    Code:
      stack=1, locals=1, args_size=1
         0: aload_0
         1: invokedynamic #562,  0            // InvokeDynamic #8:lambdaDeserialize:(Ljava/lang/invoke/SerializedLambda;)Ljava/lang/Object;
         6: areturn
}
InnerClasses:
  public static final #34= #31 of #33;    // Lookup=class java/lang/invoke/MethodHandles$Lookup of class java/lang/invoke/MethodHandles
  public #39= #36 of #38;                 // Bundle=class org/scalatest/SuperEngine$Bundle of class org/scalatest/SuperEngine
  public #42= #41 of #38;                 // TestLeaf=class org/scalatest/SuperEngine$TestLeaf of class org/scalatest/SuperEngine
  public #45= #44 of #6;                  // NoArgTest=class org/scalatest/TestSuite$NoArgTest of class org/scalatest/TestSuite
  public final #47;                       // class org/scalatest/flatspec/AnyFlatSpecLike$$anon$1
  public final #49;                       // class org/scalatest/flatspec/AnyFlatSpecLike$$anon$4
  public final #51;                       // class org/scalatest/flatspec/AnyFlatSpecLike$$anon$5
  public final #54= #53 of #2;            // BehaviorWord=class org/scalatest/flatspec/AnyFlatSpecLike$BehaviorWord of class org/scalatest/flatspec/AnyFlatSpecLike
  public final #57= #56 of #2;            // IgnoreVerbString=class org/scalatest/flatspec/AnyFlatSpecLike$IgnoreVerbString of class org/scalatest/flatspec/AnyFlatSpecLike
  public final #60= #59 of #2;            // IgnoreVerbStringTaggedAs=class org/scalatest/flatspec/AnyFlatSpecLike$IgnoreVerbStringTaggedAs of class org/scalatest/flatspec/AnyFlatSpecLike
  public final #63= #62 of #2;            // IgnoreWord=class org/scalatest/flatspec/AnyFlatSpecLike$IgnoreWord of class org/scalatest/flatspec/AnyFlatSpecLike
  public final #66= #65 of #2;            // InAndIgnoreMethods=class org/scalatest/flatspec/AnyFlatSpecLike$InAndIgnoreMethods of class org/scalatest/flatspec/AnyFlatSpecLike
  public final #69= #68 of #2;            // InAndIgnoreMethodsAfterTaggedAs=class org/scalatest/flatspec/AnyFlatSpecLike$InAndIgnoreMethodsAfterTaggedAs of class org/scalatest/flatspec/AnyFlatSpecLike
  public final #72= #71 of #2;            // ItVerbString=class org/scalatest/flatspec/AnyFlatSpecLike$ItVerbString of class org/scalatest/flatspec/AnyFlatSpecLike
  public final #75= #74 of #2;            // ItVerbStringTaggedAs=class org/scalatest/flatspec/AnyFlatSpecLike$ItVerbStringTaggedAs of class org/scalatest/flatspec/AnyFlatSpecLike
  public final #78= #77 of #2;            // ItWord=class org/scalatest/flatspec/AnyFlatSpecLike$ItWord of class org/scalatest/flatspec/AnyFlatSpecLike
  public final #81= #80 of #2;            // TheyVerbString=class org/scalatest/flatspec/AnyFlatSpecLike$TheyVerbString of class org/scalatest/flatspec/AnyFlatSpecLike
  public final #84= #83 of #2;            // TheyVerbStringTaggedAs=class org/scalatest/flatspec/AnyFlatSpecLike$TheyVerbStringTaggedAs of class org/scalatest/flatspec/AnyFlatSpecLike
  public final #87= #86 of #2;            // TheyWord=class org/scalatest/flatspec/AnyFlatSpecLike$TheyWord of class org/scalatest/flatspec/AnyFlatSpecLike
SourceFile: "AnyFlatSpecLike.scala"
RuntimeVisibleAnnotations:
  0: #24(#25=[s#26])
    org.scalatest.Finders(
      value=["org.scalatest.finders.FlatSpecFinder"]
    )
  1: #27(#28=s#29)
    scala.reflect.ScalaSignature(
      bytes="\u0006\u0005\u0011-ga\u00029r!\u0003\r\t\u0001\u001f\u0005\b\u0003{\u0001A\u0011AA \u0011%\t9\u0005\u0001b\u0001\n\u001b\tI\u0005C\u0004\u0002R\u0001!\t\"a\u0015\t\u000f\u0005m\u0003\u0001\"\u0005\u0002^!9\u0011Q\r\u0001\u0005\u0012\u0005\u001d\u0004bBA8\u0001\u0011E\u0011\u0011\u000f\u0005\b\u0003s\u0002AQBA>\u0011\u001d\ti\r\u0001C\u0003\u0003\u001fDq!!8\u0001\t\u001b\ty\u000eC\u0004\u0002l\u0002!)!!<\t\u000f\u0005m\b\u0001\"\u0003\u0002~\u001a1!Q\u0005\u0001\u000b\u0005OAqA!\u000b\r\t\u0003\u0011Y\u0003C\u0004\u000321!iAa\r\t\u000f\tmB\u0002\"\u0001\u0003>!I!Q\t\u0001C\u0002\u0013E!q\t\u0004\u0007\u0005\u0013\u0002!Ba\u0013\t\u0015\t5\u0013C!A!\u0002\u0013\t9\u000b\u0003\u0006\u0003PE\u0011\t\u0011)A\u0005\u0003OC!B!\u0015\u0012\u0005\u0003\u0005\u000b\u0011\u0002B\u0005\u0011\u001d\u0011I#\u0005C\u0001\u0005\'BqA!\u0018\u0012\t\u0003\u0011y\u0006C\u0004\u0003hE!\tA!\u001b\t\u000f\te\u0014\u0003\"\u0001\u0003|\u00191!1\u0011\u0001\u000b\u0005\u000bC!B!\u0014\u001a\u0005\u0003\u0005\u000b\u0011BAT\u0011)\u0011y%\u0007B\u0001B\u0003%\u0011q\u0015\u0005\b\u0005SIB\u0011\u0001BD\u0011\u001d\u0011i&\u0007C\u0001\u0005\u001fCqAa\u001a\u001a\t\u0003\u00119\nC\u0004\u0003ze!\tAa(\t\u000f\t\u001d\u0016\u0004\"\u0001\u0003*\u001a1!1\u0017\u0001\u000b\u0005kCqA!\u000b\"\t\u0003\u00119\fC\u0004\u0003<\u0006\"\tA!0\t\u000f\t\r\u0017\u0005\"\u0001\u0003F\"9!\u0011Z\u0011\u0005\u0002\t-\u0007b\u0002B^C\u0011\u0005!q\u001a\u0005\b\u0005\u0007\fC\u0011\u0001Bn\u0011\u001d\u0011I-\tC\u0001\u0005?D\u0011Ba9\u0001\u0005\u0004%\tB!:\u0007\r\t\u001d\bA\u0003Bu\u0011)\u0011iE\u000bB\u0001B\u0003%\u0011q\u0015\u0005\u000b\u0005\u001fR#\u0011!Q\u0001\n\u0005\u001d\u0006B\u0003B)U\t\u0005\t\u0015!\u0003\u0003\n!9!\u0011\u0006\u0016\u0005\u0002\t-\bb\u0002B/U\u0011\u0005!Q\u001f\u0005\b\u0005ORC\u0011\u0001B\u007f\r\u0019\u0019)\u0001\u0001\u0006\u0004\b!Q!QJ\u0019\u0003\u0002\u0003\u0006I!a*\t\u0015\t=\u0013G!A!\u0002\u0013\t9\u000bC\u0004\u0003*E\"\ta!\u0003\t\u000f\tu\u0013\u0007\"\u0001\u0004\u0012!9!qM\u0019\u0005\u0002\re\u0001b\u0002BTc\u0011\u00051\u0011\u0005\u0004\u0007\u0007O\u0001!b!\u000b\t\u000f\t%\u0002\b\"\u0001\u0004,!9!1\u0018\u001d\u0005\u0002\r=\u0002b\u0002Bbq\u0011\u000511\u0007\u0005\b\u0005\u0013DD\u0011AB\u001c\u0011%\u0011I\b\u0001b\u0001\n#\u0019YD\u0002\u0004\u0004>\u0001Q1q\b\u0005\u000b\u0005\u001br$\u0011!Q\u0001\n\u0005\u001d\u0006B\u0003B(}\t\u0005\t\u0015!\u0003\u0002(\"Q!\u0011\u000b \u0003\u0002\u0003\u0006IA!\u0003\t\u000f\t%b\b\"\u0001\u0004B!9!Q\f \u0005\u0002\r-\u0003b\u0002B4}\u0011\u000511\u000b\u0005\b\u0005srD\u0011AB.\r\u0019\u0019\u0019\u0007\u0001\u0006\u0004f!Q!Q\n$\u0003\u0002\u0003\u0006I!a*\t\u0015\t=cI!A!\u0002\u0013\t9\u000bC\u0004\u0003*\u0019#\taa\u001a\t\u000f\tuc\t\"\u0001\u0004p!9!q\r$\u0005\u0002\r]\u0004b\u0002B=\r\u0012\u00051q\u0010\u0005\b\u0005O3E\u0011ABD\r\u0019\u0019i\t\u0001\u0006\u0004\u0010\"9!\u0011\u0006(\u0005\u0002\rE\u0005b\u0002B^\u001d\u0012\u00051Q\u0013\u0005\b\u0005\u0007tE\u0011ABM\u0011\u001d\u0011IM\u0014C\u0001\u0007;CqAa/O\t\u0003\u0019\t\u000bC\u0004\u0003D:#\ta!*\t\u000f\t%g\n\"\u0001\u0004*\"I1Q\u0016\u0001C\u0002\u0013E1q\u0016\u0004\u0007\u0007c\u0003!ba-\t\u0015\rUvK!A!\u0002\u0013\u00199\fC\u0004\u0003*]#\ta!0\t\u000f\tus\u000b\"\u0001\u0004D\"9!\u0011P,\u0005\u0002\r-\u0007bBBj\u0001\u0011M1Q\u001b\u0004\u0007\u00073\u0004!ba7\t\u0015\ruWL!A!\u0002\u0013\u0019y\u000eC\u0004\u0003*u#\ta!:\t\u000f\tuS\f\"\u0001\u0004l\"9!\u0011P/\u0005\u0002\rM\bbBB~\u0001\u0011M1Q \u0005\n\t\u0003\u0001!\u0019!C\n\t\u0007A\u0011\u0002b\u0003\u0001\u0005\u0004%\u0019\u0002\"\u0004\t\u000f\u0011U\u0001\u0001\"\u0003\u0005\u0018!9!\u0011\u000b\u0001\u0005B\u0011\r\u0002b\u0002C\u0019\u0001\u0011EC1\u0007\u0005\b\t\u0013\u0002A\u0011\u000bC&\u0011\u001d!9\u0006\u0001C!\t3Bq\u0001b\u0017\u0001\t\u0003\"i\u0006C\u0005\u0005d\u0001\u0011\r\u0011\"\u0005\u0005f!IAq\r\u0001C\u0002\u0013\u0015C\u0011\u000e\u0005\b\t\u007f\u0002A\u0011\tCA\u0011%!)\nAI\u0001\n\u0003!9\n\u0003\b\u0005.\u0002\u0001\n1!A\u0001\n\u0013!y\u000b\".\u0003\u001f\u0005s\u0017P\u00127biN\u0003Xm\u0019\'jW\u0016T!A]:\u0002\u0011\u0019d\u0017\r^:qK\u000eT!\u0001^;\u0002\u0013M\u001c\u0017\r\\1uKN$(\"\u0001<\u0002\u0007=\u0014xm\u0001\u0001\u0014\'\u0001Ix0a\u0002\u0002\u000e\u0005e\u0011qDA\u0013\u0003W\t\t$a\u000e\u0011\u0005ilX\"A>\u000b\u0003q\fQa]2bY\u0006L!A`>\u0003\r\u0005s\u0017PU3g!\u0011\t\t!a\u0001\u000e\u0003ML1!!\u0002t\u0005%!Vm\u001d;Tk&$X\r\u0005\u0003\u0002\u0002\u0005%\u0011bAA\u0006g\n\u0001B+Z:u%\u0016<\u0017n\u001d;sCRLwN\u001c\t\u0005\u0003\u001f\t)\"\u0004\u0002\u0002\u0012)\u0019\u00111C:\u0002\u000bY,\'OY:\n\t\u0005]\u0011\u0011\u0003\u0002\u000b\'\"|W\u000f\u001c3WKJ\u0014\u0007\u0003BA\b\u00037IA!!\b\u0002\u0012\tAQ*^:u-\u0016\u0014(\r\u0005\u0003\u0002\u0010\u0005\u0005\u0012\u0002BA\u0012\u0003#\u0011qaQ1o-\u0016\u0014(\r\u0005\u0003\u0002\u0002\u0005\u001d\u0012bAA\u0015g\nI\u0011J\u001c4pe6Lgn\u001a\t\u0005\u0003\u0003\ti#C\u0002\u00020M\u0014\u0011BT8uS\u001aL\u0018N\\4\u0011\t\u0005\u0005\u00111G\u0005\u0004\u0003k\u0019(\u0001C!mKJ$\u0018N\\4\u0011\t\u0005\u0005\u0011\u0011H\u0005\u0004\u0003w\u0019(a\u0003#pGVlWM\u001c;j]\u001e\fa\u0001J5oSR$CCAA!!\rQ\u00181I\u0005\u0004\u0003\u000bZ(\u0001B+oSR\fa!\u001a8hS:,WCAA&!\u0011\t\t!!\u0014\n\u0007\u0005=3O\u0001\u0004F]\u001eLg.Z\u0001\u0005S:4w.\u0006\u0002\u0002VA!\u0011\u0011AA,\u0013\r\tIf\u001d\u0002\t\u0013:4wN]7fe\u0006!an\u001c;f+\t\ty\u0006\u0005\u0003\u0002\u0002\u0005\u0005\u0014bAA2g\nAaj\u001c;jM&,\'/A\u0003bY\u0016\u0014H/\u0006\u0002\u0002jA!\u0011\u0011AA6\u0013\r\tig\u001d\u0002\b\u00032,\'\u000f^3s\u0003\u0019i\u0017M]6vaV\u0011\u00111\u000f\t\u0005\u0003\u0003\t)(C\u0002\u0002xM\u0014!\u0002R8dk6,g\u000e^3s\u0003A\u0011XmZ5ti\u0016\u0014H+Z:u\u00136\u0004H\u000e\u0006\u0004\u0002~\u0005\r\u0016Q\u0018\u000b\u0007\u0003\u0003\ny(a$\t\u0011\u0005\u0005u\u0001\"a\u0001\u0003\u0007\u000bq\u0001^3ti\u001a+h\u000eE\u0003{\u0003\u000b\u000bI)C\u0002\u0002\bn\u0014\u0001\u0002\u00102z]\u0006lWM\u0010\t\u0004u\u0006-\u0015bAAGw\n\u0019\u0011I\\=\t\u000f\u0005Eu\u00011\u0001\u0002\u0014\u0006\u0019\u0001o\\:\u0011\t\u0005U\u0015qT\u0007\u0003\u0003/SA!!\'\u0002\u001c\u000611o\\;sG\u0016T1!!(v\u0003%\u00198-\u00197bGRL7-\u0003\u0003\u0002\"\u0006]%\u0001\u0003)pg&$\u0018n\u001c8\t\u000f\u0005\u0015v\u00011\u0001\u0002(\u0006AA/Z:u)\u0016DH\u000f\u0005\u0003\u0002*\u0006]f\u0002BAV\u0003g\u00032!!,|\u001b\t\tyKC\u0002\u00022^\fa\u0001\u0010:p_Rt\u0014bAA[w\u00061\u0001K]3eK\u001aLA!!/\u0002<\n11\u000b\u001e:j]\u001eT1!!.|\u0011\u001d\tyl\u0002a\u0001\u0003\u0003\f\u0001\u0002^3tiR\u000bwm\u001d\t\u0006u\u0006\r\u0017qY\u0005\u0004\u0003\u000b\\(A\u0003\u001fsKB,\u0017\r^3e}A!\u0011\u0011AAe\u0013\r\tYm\u001d\u0002\u0004)\u0006<\u0017\u0001\u0004:fO&\u001cH/\u001a:UKN$HCBAi\u00033\fY\u000e\u0006\u0003\u0002T\u0006]G\u0003BA!\u0003+Dq!!%\t\u0001\b\t\u0019\n\u0003\u0005\u0002\u0002\"!\t\u0019AAB\u0011\u001d\t)\u000b\u0003a\u0001\u0003OCq!a0\t\u0001\u0004\t\t-A\fsK\u001eL7\u000f^3s\u0013\u001etwN]3e)\u0016\u001cH/S7qYR1\u0011\u0011]At\u0003S$b!!\u0011\u0002d\u0006\u0015\b\u0002CAA\u0013\u0011\u0005\r!a!\t\u000f\u0005E\u0015\u00021\u0001\u0002\u0014\"9\u0011QU\u0005A\u0002\u0005\u001d\u0006bBA`\u0013\u0001\u0007\u0011\u0011Y\u0001\u0014e\u0016<\u0017n\u001d;fe&;gn\u001c:fIR+7\u000f\u001e\u000b\u0007\u0003_\f90!?\u0015\t\u0005E\u0018Q\u001f\u000b\u0005\u0003\u0003\n\u0019\u0010C\u0004\u0002\u0012*\u0001\u001d!a%\t\u0011\u0005\u0005%\u0002\"a\u0001\u0003\u0007Cq!!*\u000b\u0001\u0004\t9\u000bC\u0004\u0002@*\u0001\r!!1\u0002#I,w-[:uKJ$Vm\u001d;U_J+h\u000e\u0006\u0007\u0002B\u0005}(1\u0001B\u0004\u00057\u0011\u0019\u0003C\u0004\u0003\u0002-\u0001\r!a*\u0002\u0011M\u0004Xm\u0019+fqRDqA!\u0002\f\u0001\u0004\t9+\u0001\u0006nKRDw\u000e\u001a(b[\u0016Dq!a0\f\u0001\u0004\u0011I\u0001\u0005\u0004\u0003\f\tU\u0011q\u0019\b\u0005\u0005\u001b\u0011\tB\u0004\u0003\u0002.\n=\u0011\"\u0001?\n\u0007\tM10A\u0004qC\u000e\\\u0017mZ3\n\t\t]!\u0011\u0004\u0002\u0005\u0019&\u001cHOC\u0002\u0003\u0014mDq!!!\f\u0001\u0004\u0011i\u0002E\u0003{\u0005?\tI)C\u0002\u0003\"m\u0014\u0011BR;oGRLwN\u001c\u0019\t\u000f\u0005E5\u00021\u0001\u0002\u0014\na!)\u001a5bm&|\'oV8sIN\u0011A\"_\u0001\u0007y%t\u0017\u000e\u001e \u0015\u0005\t5\u0002c\u0001B\u0018\u00195\t\u0001!\u0001\u0004pM&k\u0007\u000f\u001c\u000b\u0007\u0003\u0003\u0012)D!\u000f\t\u000f\t]b\u00021\u0001\u0002(\u0006YA-Z:de&\u0004H/[8o\u0011\u001d\t\tJ\u0004a\u0001\u0003\'\u000b!a\u001c4\u0015\t\t}\"1\t\u000b\u0005\u0003\u0003\u0012\t\u0005C\u0004\u0002\u0012>\u0001\u001d!a%\t\u000f\t]r\u00021\u0001\u0002(\u0006A!-\u001a5bm&|\'/\u0006\u0002\u0003.\t!\u0012\n\u001e,fe\n\u001cFO]5oOR\u000bwmZ3e\u0003N\u001c\"!E=\u0002\tY,\'OY\u0001\u0005]\u0006lW-\u0001\u0003uC\u001e\u001cH\u0003\u0003B+\u0005/\u0012IFa\u0017\u0011\u0007\t=\u0012\u0003C\u0004\u0003NU\u0001\r!a*\t\u000f\t=S\u00031\u0001\u0002(\"9!\u0011K\u000bA\u0002\t%\u0011AA5o)\u0011\u0011\tG!\u001a\u0015\t\u0005\u0005#1\r\u0005\b\u0003#3\u00029AAJ\u0011!\t\tI\u0006CA\u0002\u0005\r\u0015AA5t)\u0011\u0011YGa\u001c\u0015\t\u0005\u0005#Q\u000e\u0005\b\u0003#;\u00029AAJ\u0011!\t\ti\u0006CA\u0002\tE\u0004#\u0002>\u0002\u0006\nM\u0004\u0003BA\u0001\u0005kJ1Aa\u001et\u0005A\u0001VM\u001c3j]\u001e\u001cF/\u0019;f[\u0016tG/\u0001\u0004jO:|\'/\u001a\u000b\u0005\u0005{\u0012\t\t\u0006\u0003\u0002B\t}\u0004bBAI1\u0001\u000f\u00111\u0013\u0005\t\u0003\u0003CB\u00111\u0001\u0002\u0004\na\u0011\n\u001e,fe\n\u001cFO]5oON\u0011\u0011$\u001f\u000b\u0007\u0005\u0013\u0013YI!$\u0011\u0007\t=\u0012\u0004C\u0004\u0003Nq\u0001\r!a*\t\u000f\t=C\u00041\u0001\u0002(R!!\u0011\u0013BK)\u0011\t\tEa%\t\u000f\u0005EU\u0004q\u0001\u0002\u0014\"A\u0011\u0011Q\u000f\u0005\u0002\u0004\t\u0019\t\u0006\u0003\u0003\u001a\nuE\u0003BA!\u00057Cq!!%\u001f\u0001\b\t\u0019\n\u0003\u0005\u0002\u0002z!\t\u0019\u0001B9)\u0011\u0011\tK!*\u0015\t\u0005\u0005#1\u0015\u0005\b\u0003#{\u00029AAJ\u0011!\t\ti\bCA\u0002\u0005\r\u0015\u0001\u0003;bO\u001e,G-Q:\u0015\r\tU#1\u0016BX\u0011\u001d\u0011i\u000b\ta\u0001\u0003\u000f\fABZ5sgR$Vm\u001d;UC\u001eDqA!-!\u0001\u0004\t\t-A\u0007pi\",\'\u000fV3tiR\u000bwm\u001d\u0002\u0007\u0013R<vN\u001d3\u0014\u0005\u0005JHC\u0001B]!\r\u0011y#I\u0001\u0007g\"|W\u000f\u001c3\u0015\t\t%%q\u0018\u0005\b\u0005\u0003\u001c\u0003\u0019AAT\u0003\u0019\u0019HO]5oO\u0006!Q.^:u)\u0011\u0011IIa2\t\u000f\t\u0005G\u00051\u0001\u0002(\u0006\u00191-\u00198\u0015\t\t%%Q\u001a\u0005\b\u0005\u0003,\u0003\u0019AAT)\u0011\u0011\tNa6\u0011\t\u0005=!1[\u0005\u0005\u0005+\f\tB\u0001\u0006CK\"\fg/Z,pe\u0012DqA!7\'\u0001\u0004\u0011\t.\u0001\u0006cK\"\fg/Z,pe\u0012$BA!5\u0003^\"9!\u0011\\\u0014A\u0002\tEG\u0003\u0002Bi\u0005CDqA!7)\u0001\u0004\u0011\t.\u0001\u0002jiV\u0011!\u0011\u0018\u0002\u0019\u0013\u001etwN]3WKJ\u00147\u000b\u001e:j]\u001e$\u0016mZ4fI\u0006\u001b8C\u0001\u0016z)!\u0011iOa<\u0003r\nM\bc\u0001B\u0018U!9!Q\n\u0018A\u0002\u0005\u001d\u0006b\u0002B(]\u0001\u0007\u0011q\u0015\u0005\b\u0005#r\u0003\u0019\u0001B\u0005)\u0011\u00119Pa?\u0015\t\u0005\u0005#\u0011 \u0005\b\u0003#{\u00039AAJ\u0011!\t\ti\fCA\u0002\u0005\rE\u0003\u0002B\u0000\u0007\u0007!B!!\u0011\u0004\u0002!9\u0011\u0011\u0013\u0019A\u0004\u0005M\u0005\u0002CAAa\u0011\u0005\rA!\u001d\u0003!%;gn\u001c:f-\u0016\u0014(m\u0015;sS:<7CA\u0019z)\u0019\u0019Ya!\u0004\u0004\u0010A\u0019!qF\u0019\t\u000f\t5C\u00071\u0001\u0002(\"9!q\n\u001bA\u0002\u0005\u001dF\u0003BB\n\u0007/!B!!\u0011\u0004\u0016!9\u0011\u0011S\u001bA\u0004\u0005M\u0005\u0002CAAk\u0011\u0005\r!a!\u0015\t\rm1q\u0004\u000b\u0005\u0003\u0003\u001ai\u0002C\u0004\u0002\u0012Z\u0002\u001d!a%\t\u0011\u0005\u0005e\u0007\"a\u0001\u0005c\"bA!<\u0004$\r\u0015\u0002b\u0002BWo\u0001\u0007\u0011q\u0019\u0005\b\u0005c;\u0004\u0019AAa\u0005)IuM\\8sK^{\'\u000fZ\n\u0003qe$\"a!\f\u0011\u0007\t=\u0002\b\u0006\u0003\u0004\f\rE\u0002b\u0002Bau\u0001\u0007\u0011q\u0015\u000b\u0005\u0007\u0017\u0019)\u0004C\u0004\u0003Bn\u0002\r!a*\u0015\t\r-1\u0011\b\u0005\b\u0005\u0003d\u0004\u0019AAT+\t\u0019iC\u0001\fUQ\u0016Lh+\u001a:c\'R\u0014\u0018N\\4UC\u001e<W\rZ!t\'\tq\u0014\u0010\u0006\u0005\u0004D\r\u00153qIB%!\r\u0011yC\u0010\u0005\b\u0005\u001b\u0012\u0005\u0019AAT\u0011\u001d\u0011yE\u0011a\u0001\u0003OCqA!\u0015C\u0001\u0004\u0011I\u0001\u0006\u0003\u0004N\rEC\u0003BA!\u0007\u001fBq!!%D\u0001\b\t\u0019\n\u0003\u0005\u0002\u0002\u000e#\t\u0019AAB)\u0011\u0019)f!\u0017\u0015\t\u0005\u00053q\u000b\u0005\b\u0003##\u00059AAJ\u0011!\t\t\t\u0012CA\u0002\tED\u0003BB/\u0007C\"B!!\u0011\u0004`!9\u0011\u0011S#A\u0004\u0005M\u0005\u0002CAA\u000b\u0012\u0005\r!a!\u0003\u001dQCW-\u001f,fe\n\u001cFO]5oON\u0011a)\u001f\u000b\u0007\u0007S\u001aYg!\u001c\u0011\u0007\t=b\tC\u0004\u0003N%\u0003\r!a*\t\u000f\t=\u0013\n1\u0001\u0002(R!1\u0011OB;)\u0011\t\tea\u001d\t\u000f\u0005E%\nq\u0001\u0002\u0014\"A\u0011\u0011\u0011&\u0005\u0002\u0004\t\u0019\t\u0006\u0003\u0004z\ruD\u0003BA!\u0007wBq!!%L\u0001\b\t\u0019\n\u0003\u0005\u0002\u0002.#\t\u0019\u0001B9)\u0011\u0019\ti!\"\u0015\t\u0005\u000531\u0011\u0005\b\u0003#c\u00059AAJ\u0011!\t\t\t\u0014CA\u0002\u0005\rEC\u0002B+\u0007\u0013\u001bY\tC\u0004\u0003.6\u0003\r!a2\t\u000f\tEV\n1\u0001\u0002B\nAA\u000b[3z/>\u0014Hm\u0005\u0002OsR\u001111\u0013\t\u0004\u0005_qE\u0003\u0002BE\u0007/CqA!1Q\u0001\u0004\t9\u000b\u0006\u0003\u0003\n\u000em\u0005b\u0002Ba#\u0002\u0007\u0011q\u0015\u000b\u0005\u0005\u0013\u001by\nC\u0004\u0003BJ\u0003\r!a*\u0015\t\tE71\u0015\u0005\b\u00053\u001c\u0006\u0019\u0001Bi)\u0011\u0011\tna*\t\u000f\teG\u000b1\u0001\u0003RR!!\u0011[BV\u0011\u001d\u0011I.\u0016a\u0001\u0005#\fA\u0001\u001e5fsV\u001111\u0013\u0002\u0013\u0013:\fe\u000eZ%h]>\u0014X-T3uQ>$7o\u0005\u0002Xs\u0006Q\"/Z:vYR|em\u0015;sS:<\u0007+Y:tK\u0012$vNV3sEB!\u0011qBB]\u0013\u0011\u0019Y,!\u0005\u00035I+7/\u001e7u\u001f\u001a\u001cFO]5oOB\u000b7o]3e)>4VM\u001d2\u0015\t\r}6\u0011\u0019\t\u0004\u0005_9\u0006bBB[3\u0002\u00071q\u0017\u000b\u0005\u0007\u000b\u001cI\r\u0006\u0003\u0002B\r\u001d\u0007bBAI5\u0002\u000f\u00111\u0013\u0005\t\u0003\u0003SF\u00111\u0001\u0002\u0004R!1QZBi)\u0011\t\tea4\t\u000f\u0005E5\fq\u0001\u0002\u0014\"A\u0011\u0011Q.\u0005\u0002\u0004\t\u0019)A\u000ed_:4XM\u001d;U_&s\u0017I\u001c3JO:|\'/Z\'fi\"|Gm\u001d\u000b\u0005\u0007\u007f\u001b9\u000eC\u0004\u00046r\u0003\raa.\u0003?%s\u0017I\u001c3JO:|\'/Z\'fi\"|Gm]!gi\u0016\u0014H+Y4hK\u0012\f5o\u0005\u0002^s\u0006Q\"/Z:vYR|e\rV1hO\u0016$\u0017i]%om>\u001c\u0017\r^5p]B!\u0011qBBq\u0013\u0011\u0019\u0019/!\u0005\u00035I+7/\u001e7u\u001f\u001a$\u0016mZ4fI\u0006\u001b\u0018J\u001c<pG\u0006$\u0018n\u001c8\u0015\t\r\u001d8\u0011\u001e\t\u0004\u0005_i\u0006bBBo?\u0002\u00071q\u001c\u000b\u0005\u0007[\u001c\t\u0010\u0006\u0003\u0002B\r=\bbBAIA\u0002\u000f\u00111\u0013\u0005\t\u0003\u0003\u0003G\u00111\u0001\u0002\u0004R!1Q_B})\u0011\t\tea>\t\u000f\u0005E\u0015\rq\u0001\u0002\u0014\"A\u0011\u0011Q1\u0005\u0002\u0004\t\u0019)\u0001\u0015d_:4XM\u001d;U_&s\u0017I\u001c3JO:|\'/Z\'fi\"|Gm]!gi\u0016\u0014H+Y4hK\u0012\f5\u000f\u0006\u0003\u0004h\u000e}\bbBBoE\u0002\u00071q\\\u0001\"g\"|\'\u000f\u001e5b]\u0012$Vm\u001d;SK\u001eL7\u000f\u001e:bi&|gNR;oGRLwN\\\u000b\u0003\t\u000b\u0001B!a\u0004\u0005\b%!A\u0011BA\t\u0005i\u0019FO]5oOZ+\'OY*ue&tw-\u00138w_\u000e\fG/[8o\u0003\u001d\u001a\bn\u001c:uQ\u0006tGm\u00155be\u0016$G+Z:u%\u0016<\u0017n\u001d;sCRLwN\u001c$v]\u000e$\u0018n\u001c8\u0016\u0005\u0011=\u0001\u0003BA\b\t#IA\u0001b\u0005\u0002\u0012\tq2\u000b\u001e:j]\u001e4VM\u001d2CK\"\fg/\u001a\'jW\u0016LeN^8dCRLwN\\\u0001\u0015e\u0016<\u0017n\u001d;feR+7\u000f\u001e+p\u0013\u001etwN]3\u0015\u0019\u0005\u0005C\u0011\u0004C\u000e\t;!y\u0002\"\t\t\u000f\t\u0005Q\r1\u0001\u0002(\"9\u0011qX3A\u0002\t%\u0001b\u0002B\u0003K\u0002\u0007\u0011q\u0015\u0005\b\u0003\u0003+\u0007\u0019\u0001B\u000f\u0011\u001d\t\t*\u001aa\u0001\u0003\'+\"\u0001\"\n\u0011\u0011\u0005%FqEAT\tWIA\u0001\"\u000b\u0002<\n\u0019Q*\u00199\u0011\r\u0005%FQFAT\u0013\u0011!y#a/\u0003\u0007M+G/A\u0004sk:$Vm\u001d;\u0015\r\u0011UB1\bC !\u0011\t\t\u0001b\u000e\n\u0007\u0011e2O\u0001\u0004Ti\u0006$Xo\u001d\u0005\b\t{9\u0007\u0019AAT\u0003!!Xm\u001d;OC6,\u0007b\u0002C!O\u0002\u0007A1I\u0001\u0005CJ<7\u000f\u0005\u0003\u0002\u0002\u0011\u0015\u0013b\u0001C$g\n!\u0011I]4t\u0003!\u0011XO\u001c+fgR\u001cHC\u0002C\u001b\t\u001b\")\u0006C\u0004\u0005>!\u0004\r\u0001b\u0014\u0011\u000bi$\t&a*\n\u0007\u0011M3P\u0001\u0004PaRLwN\u001c\u0005\b\t\u0003B\u0007\u0019\u0001C\"\u0003%!Xm\u001d;OC6,7/\u0006\u0002\u0005,\u0005\u0019!/\u001e8\u0015\r\u0011UBq\fC1\u0011\u001d!iD\u001ba\u0001\t\u001fBq\u0001\"\u0011k\u0001\u0004!\u0019%\u0001\u0004cK\"\fg/Z\u000b\u0003\u0005#\f\u0011b\u001d;zY\u0016t\u0015-\\3\u0016\u0005\u0005\u001d\u0006f\u00037\u0005n\u0011MDQ\u000fC=\tw\u00022A\u001fC8\u0013\r!\th\u001f\u0002\u000bI\u0016\u0004(/Z2bi\u0016$\u0017aB7fgN\fw-Z\u0011\u0003\to\nA\u0010\u00165fAM$\u0018\u0010\\3OC6,\u0007\u0005\\5gK\u000eL8\r\\3![\u0016$\bn\u001c3!Q\u0006\u001c\bEY3f]\u0002\"W\r\u001d:fG\u0006$X\r\u001a\u0011b]\u0012\u0004s/\u001b7mA\t,\u0007E]3n_Z,G\rI5oA\u0005\u0004c-\u001e;ve\u0016\u0004c/\u001a:tS>t\u0007e\u001c4!\'\u000e\fG.\u0019+fgR\u0004s/\u001b;iA9|\u0007E]3qY\u0006\u001cW-\\3oi:\nQa]5oG\u0016\f#\u0001\" \u0002\u000bMr\u0013G\f\u0019\u0002\u0017Q,7\u000f\u001e#bi\u00064uN\u001d\u000b\u0007\t\u0007#I\tb#\u0011\t\u0005\u0005AQQ\u0005\u0004\t\u000f\u001b(\u0001\u0003+fgR$\u0015\r^1\t\u000f\u0011uR\u000e1\u0001\u0002(\"IAQR7\u0011\u0002\u0003\u0007AqR\u0001\ri\",7i\u001c8gS\u001el\u0015\r\u001d\t\u0005\u0003\u0003!\t*C\u0002\u0005\u0014N\u0014\u0011bQ8oM&<W*\u00199\u0002+Q,7\u000f\u001e#bi\u00064uN\u001d\u0013eK\u001a\fW\u000f\u001c;%eU\u0011A\u0011\u0014\u0016\u0005\t\u001f#Yj\u000b\u0002\u0005\u001eB!Aq\u0014CU\u001b\t!\tK\u0003\u0003\u0005$\u0012\u0015\u0016!C;oG\",7m[3e\u0015\r!9k_\u0001\u000bC:tw\u000e^1uS>t\u0017\u0002\u0002CV\tC\u0013\u0011#\u001e8dQ\u0016\u001c7.\u001a3WCJL\u0017M\\2f\u0003%\u0019X\u000f]3sII,h\u000e\u0006\u0004\u00056\u0011EF1\u0017\u0005\b\t{y\u0007\u0019\u0001C(\u0011\u001d!\te\u001ca\u0001\t\u0007JA\u0001b\u0017\u00058&\u0019A\u0011X:\u0003\u000bM+\u0018\u000e^3)\u000f\u0001!i\fb1\u0005FB!\u0011\u0011\u0001C`\u0013\r!\tm\u001d\u0002\b\r&tG-\u001a:t\u0003\u00151\u0018\r\\;fY\t!9-\t\u0002\u0005J\u0006!sN]4/g\u000e\fG.\u0019;fgRtc-\u001b8eKJ\u001chF\u00127biN\u0003Xm\u0019$j]\u0012,\'\u000f"
    )
BootstrapMethods:
  0: #199 REF_invokeStatic java/lang/invoke/LambdaMetafactory.altMetafactory:(Ljava/lang/invoke/MethodHandles$Lookup;Ljava/lang/String;Ljava/lang/invoke/MethodType;[Ljava/lang/Object;)Ljava/lang/invoke/CallSite;
    Method arguments:
      #184 ()Ljava/lang/Object;
      #189 REF_invokeStatic org/scalatest/flatspec/AnyFlatSpecLike.$anonfun$registerTestImpl$1:()Ljava/lang/String;
      #190 ()Ljava/lang/String;
      #191 5
      #192 1
      #190 ()Ljava/lang/String;
  1: #199 REF_invokeStatic java/lang/invoke/LambdaMetafactory.altMetafactory:(Ljava/lang/invoke/MethodHandles$Lookup;Ljava/lang/String;Ljava/lang/invoke/MethodType;[Ljava/lang/Object;)Ljava/lang/invoke/CallSite;
    Method arguments:
      #184 ()Ljava/lang/Object;
      #237 REF_invokeStatic org/scalatest/flatspec/AnyFlatSpecLike.$anonfun$registerIgnoredTestImpl$1:()Ljava/lang/String;
      #190 ()Ljava/lang/String;
      #191 5
      #192 1
      #190 ()Ljava/lang/String;
  2: #199 REF_invokeStatic java/lang/invoke/LambdaMetafactory.altMetafactory:(Ljava/lang/invoke/MethodHandles$Lookup;Ljava/lang/String;Ljava/lang/invoke/MethodType;[Ljava/lang/Object;)Ljava/lang/invoke/CallSite;
    Method arguments:
      #184 ()Ljava/lang/Object;
      #263 REF_invokeStatic org/scalatest/flatspec/AnyFlatSpecLike.$anonfun$registerTestToRun$1:(Ljava/lang/String;)Ljava/lang/String;
      #190 ()Ljava/lang/String;
      #191 5
      #192 1
      #190 ()Ljava/lang/String;
  3: #199 REF_invokeStatic java/lang/invoke/LambdaMetafactory.altMetafactory:(Ljava/lang/invoke/MethodHandles$Lookup;Ljava/lang/String;Ljava/lang/invoke/MethodType;[Ljava/lang/Object;)Ljava/lang/invoke/CallSite;
    Method arguments:
      #184 ()Ljava/lang/Object;
      #312 REF_invokeStatic org/scalatest/flatspec/AnyFlatSpecLike.$anonfun$registerTestToIgnore$1:()Ljava/lang/String;
      #190 ()Ljava/lang/String;
      #191 5
      #192 1
      #190 ()Ljava/lang/String;
  4: #199 REF_invokeStatic java/lang/invoke/LambdaMetafactory.altMetafactory:(Ljava/lang/invoke/MethodHandles$Lookup;Ljava/lang/String;Ljava/lang/invoke/MethodType;[Ljava/lang/Object;)Ljava/lang/invoke/CallSite;
    Method arguments:
      #344 (Ljava/lang/Object;)Ljava/lang/Object;
      #349 REF_invokeStatic org/scalatest/flatspec/AnyFlatSpecLike.$anonfun$runTest$1:(Lorg/scalatest/flatspec/AnyFlatSpecLike;Lorg/scalatest/Args;Ljava/lang/String;Lorg/scalatest/SuperEngine$TestLeaf;)Lorg/scalatest/Outcome;
      #351 (Lorg/scalatest/SuperEngine$TestLeaf;)Lorg/scalatest/Outcome;
      #191 5
      #192 1
      #351 (Lorg/scalatest/SuperEngine$TestLeaf;)Lorg/scalatest/Outcome;
  5: #199 REF_invokeStatic java/lang/invoke/LambdaMetafactory.altMetafactory:(Ljava/lang/invoke/MethodHandles$Lookup;Ljava/lang/String;Ljava/lang/invoke/MethodType;[Ljava/lang/Object;)Ljava/lang/invoke/CallSite;
    Method arguments:
      #367 (Ljava/lang/Object;Ljava/lang/Object;)Ljava/lang/Object;
      #371 REF_invokeStatic org/scalatest/flatspec/AnyFlatSpecLike.$anonfun$runTests$1:(Lorg/scalatest/flatspec/AnyFlatSpecLike;Ljava/lang/String;Lorg/scalatest/Args;)Lorg/scalatest/Status;
      #372 (Ljava/lang/String;Lorg/scalatest/Args;)Lorg/scalatest/Status;
      #191 5
      #192 1
      #372 (Ljava/lang/String;Lorg/scalatest/Args;)Lorg/scalatest/Status;
  6: #199 REF_invokeStatic java/lang/invoke/LambdaMetafactory.altMetafactory:(Ljava/lang/invoke/MethodHandles$Lookup;Ljava/lang/String;Ljava/lang/invoke/MethodType;[Ljava/lang/Object;)Ljava/lang/invoke/CallSite;
    Method arguments:
      #367 (Ljava/lang/Object;Ljava/lang/Object;)Ljava/lang/Object;
      #406 REF_invokeStatic org/scalatest/flatspec/AnyFlatSpecLike.$anonfun$run$1:(Lorg/scalatest/flatspec/AnyFlatSpecLike;Lscala/Option;Lorg/scalatest/Args;)Lorg/scalatest/Status;
      #407 (Lscala/Option;Lorg/scalatest/Args;)Lorg/scalatest/Status;
      #191 5
      #192 1
      #407 (Lscala/Option;Lorg/scalatest/Args;)Lorg/scalatest/Status;
  7: #199 REF_invokeStatic java/lang/invoke/LambdaMetafactory.altMetafactory:(Ljava/lang/invoke/MethodHandles$Lookup;Ljava/lang/String;Ljava/lang/invoke/MethodType;[Ljava/lang/Object;)Ljava/lang/invoke/CallSite;
    Method arguments:
      #184 ()Ljava/lang/Object;
      #512 REF_invokeStatic org/scalatest/flatspec/AnyFlatSpecLike.$anonfun$engine$1:()Ljava/lang/String;
      #190 ()Ljava/lang/String;
      #191 5
      #192 1
      #190 ()Ljava/lang/String;
  8: #559 REF_invokeStatic scala/runtime/LambdaDeserialize.bootstrap:(Ljava/lang/invoke/MethodHandles$Lookup;Ljava/lang/String;Ljava/lang/invoke/MethodType;[Ljava/lang/invoke/MethodHandle;)Ljava/lang/invoke/CallSite;
    Method arguments:
      #512 REF_invokeStatic org/scalatest/flatspec/AnyFlatSpecLike.$anonfun$engine$1:()Ljava/lang/String;
      #237 REF_invokeStatic org/scalatest/flatspec/AnyFlatSpecLike.$anonfun$registerIgnoredTestImpl$1:()Ljava/lang/String;
      #189 REF_invokeStatic org/scalatest/flatspec/AnyFlatSpecLike.$anonfun$registerTestImpl$1:()Ljava/lang/String;
      #312 REF_invokeStatic org/scalatest/flatspec/AnyFlatSpecLike.$anonfun$registerTestToIgnore$1:()Ljava/lang/String;
      #263 REF_invokeStatic org/scalatest/flatspec/AnyFlatSpecLike.$anonfun$registerTestToRun$1:(Ljava/lang/String;)Ljava/lang/String;
      #406 REF_invokeStatic org/scalatest/flatspec/AnyFlatSpecLike.$anonfun$run$1:(Lorg/scalatest/flatspec/AnyFlatSpecLike;Lscala/Option;Lorg/scalatest/Args;)Lorg/scalatest/Status;
      #349 REF_invokeStatic org/scalatest/flatspec/AnyFlatSpecLike.$anonfun$runTest$1:(Lorg/scalatest/flatspec/AnyFlatSpecLike;Lorg/scalatest/Args;Ljava/lang/String;Lorg/scalatest/SuperEngine$TestLeaf;)Lorg/scalatest/Outcome;
      #371 REF_invokeStatic org/scalatest/flatspec/AnyFlatSpecLike.$anonfun$runTests$1:(Lorg/scalatest/flatspec/AnyFlatSpecLike;Ljava/lang/String;Lorg/scalatest/Args;)Lorg/scalatest/Status;
  ScalaInlineInfo: length = 0x14E (unknown attribute)
   01 00 00 42 01 BA 00 BA 01 00 EA 00 BA 01 00 B9
   00 BA 01 01 35 00 BA 01 01 03 01 04 01 01 93 01
   68 01 01 59 01 5A 01 01 70 01 51 01 01 FC 01 FD
   01 00 97 00 98 00 00 95 00 96 01 01 9D 01 9E 00
   01 0C 01 0D 00 01 17 01 18 00 01 14 01 15 01 01
   22 01 23 00 01 1F 01 20 01 01 10 01 11 00 00 74
   00 75 00 00 71 00 72 01 01 E4 01 E5 01 01 0E 01
   0F 00 00 A2 00 A3 00 00 A0 00 A1 01 00 8C 00 8D
   00 00 8A 00 8B 01 00 6F 00 70 00 01 30 01 31 01
   01 2E 01 2F 01 00 FD 00 FE 01 00 F9 00 FA 01 00
   6B 00 6C 01 00 67 00 68 00 00 5B 00 5C 00 00 5F
   00 60 00 00 5D 00 5E 00 00 58 00 59 00 00 65 00
   66 00 00 63 00 64 00 00 69 00 6A 00 00 61 00 62
   00 00 EF 00 AC 01 00 F4 00 E4 01 00 E9 00 AC 01
   00 CD 00 AC 01 00 E3 00 E4 01 00 AB 00 AC 01 01
   90 00 6C 00 01 8F 01 68 01 01 52 01 53 00 01 50
   01 51 01 01 69 00 6C 00 01 67 01 68 01 01 2C 01
   2D 00 01 2A 01 2B 00 01 9F 00 BA 00 01 3C 01 3D
   00 01 3A 01 3B 01 01 A3 01 A4 00 01 A0 01 A1 01
   01 AE 01 AF 00 01 AC 01 AD 01 01 7E 01 7F 00 01
   7C 01 7D 01 01 C6 01 04 01 01 12 01 13 00
  ScalaSig: length = 0x3 (unknown attribute)
   05 02 00
