Classfile /Users/mw/Projects/slang-braindump/.jar/jar11/assemble/slang-braindump/assemble/content/scala/compat/java8/FutureConverters$.class
  Last modified May 29, 2022; size 7515 bytes
  SHA-256 checksum 331b653784029afbc8daa2d36a24a0dfe4a2dc64d12eaa6d98de81f2dc083354
  Compiled from "FutureConverters.scala"
public final class scala.compat.java8.FutureConverters$
  minor version: 0
  major version: 52
  flags: (0x0031) ACC_PUBLIC, ACC_FINAL, ACC_SUPER
  this_class: #2                          // scala/compat/java8/FutureConverters$
  super_class: #4                         // java/lang/Object
  interfaces: 0, fields: 1, methods: 19, attributes: 5
Constant pool:
    #1 = Utf8               scala/compat/java8/FutureConverters$
    #2 = Class              #1            // scala/compat/java8/FutureConverters$
    #3 = Utf8               java/lang/Object
    #4 = Class              #3            // java/lang/Object
    #5 = Utf8               FutureConverters.scala
    #6 = Utf8               java/lang/invoke/MethodHandles$Lookup
    #7 = Class              #6            // java/lang/invoke/MethodHandles$Lookup
    #8 = Utf8               java/lang/invoke/MethodHandles
    #9 = Class              #8            // java/lang/invoke/MethodHandles
   #10 = Utf8               Lookup
   #11 = Utf8               scala/concurrent/ExecutionContext$parasitic$
   #12 = Class              #11           // scala/concurrent/ExecutionContext$parasitic$
   #13 = Utf8               scala/concurrent/ExecutionContext
   #14 = Class              #13           // scala/concurrent/ExecutionContext
   #15 = Utf8               parasitic$
   #16 = Utf8               scala/concurrent/java8/FuturesConvertersImpl$CF
   #17 = Class              #16           // scala/concurrent/java8/FuturesConvertersImpl$CF
   #18 = Utf8               scala/concurrent/java8/FuturesConvertersImpl
   #19 = Class              #18           // scala/concurrent/java8/FuturesConvertersImpl
   #20 = Utf8               CF
   #21 = Utf8               scala/concurrent/java8/FuturesConvertersImpl$P
   #22 = Class              #21           // scala/concurrent/java8/FuturesConvertersImpl$P
   #23 = Utf8               P
   #24 = Utf8               MODULE$
   #25 = Utf8               Lscala/compat/java8/FutureConverters$;
   #26 = Utf8               <clinit>
   #27 = Utf8               ()V
   #28 = Utf8               <init>
   #29 = NameAndType        #28:#27       // "<init>":()V
   #30 = Methodref          #2.#29        // scala/compat/java8/FutureConverters$."<init>":()V
   #31 = NameAndType        #24:#25       // MODULE$:Lscala/compat/java8/FutureConverters$;
   #32 = Fieldref           #2.#31        // scala/compat/java8/FutureConverters$.MODULE$:Lscala/compat/java8/FutureConverters$;
   #33 = Utf8               toJava
   #34 = Utf8               (Lscala/concurrent/Future;)Ljava/util/concurrent/CompletionStage;
   #35 = Utf8               <T:Ljava/lang/Object;>(Lscala/concurrent/Future<TT;>;)Ljava/util/concurrent/CompletionStage<TT;>;
   #36 = Utf8               f
   #37 = Utf8               wrapped
   #38 = Utf8               ()Ljava/util/concurrent/CompletionStage;
   #39 = NameAndType        #37:#38       // wrapped:()Ljava/util/concurrent/CompletionStage;
   #40 = Methodref          #22.#39       // scala/concurrent/java8/FuturesConvertersImpl$P.wrapped:()Ljava/util/concurrent/CompletionStage;
   #41 = Utf8               (Lscala/concurrent/Future;)V
   #42 = NameAndType        #28:#41       // "<init>":(Lscala/concurrent/Future;)V
   #43 = Methodref          #17.#42       // scala/concurrent/java8/FuturesConvertersImpl$CF."<init>":(Lscala/concurrent/Future;)V
   #44 = Utf8               scala/concurrent/java8/FuturesConvertersImplCompat$
   #45 = Class              #44           // scala/concurrent/java8/FuturesConvertersImplCompat$
   #46 = Utf8               Lscala/concurrent/java8/FuturesConvertersImplCompat$;
   #47 = NameAndType        #24:#46       // MODULE$:Lscala/concurrent/java8/FuturesConvertersImplCompat$;
   #48 = Fieldref           #45.#47       // scala/concurrent/java8/FuturesConvertersImplCompat$.MODULE$:Lscala/concurrent/java8/FuturesConvertersImplCompat$;
   #49 = Utf8               InternalCallbackExecutor
   #50 = Utf8               ()Lscala/concurrent/ExecutionContext$parasitic$;
   #51 = NameAndType        #49:#50       // InternalCallbackExecutor:()Lscala/concurrent/ExecutionContext$parasitic$;
   #52 = Methodref          #45.#51       // scala/concurrent/java8/FuturesConvertersImplCompat$.InternalCallbackExecutor:()Lscala/concurrent/ExecutionContext$parasitic$;
   #53 = Utf8               scala/concurrent/Future
   #54 = Class              #53           // scala/concurrent/Future
   #55 = Utf8               onComplete
   #56 = Utf8               (Lscala/Function1;Lscala/concurrent/ExecutionContext;)V
   #57 = NameAndType        #55:#56       // onComplete:(Lscala/Function1;Lscala/concurrent/ExecutionContext;)V
   #58 = InterfaceMethodref #54.#57       // scala/concurrent/Future.onComplete:(Lscala/Function1;Lscala/concurrent/ExecutionContext;)V
   #59 = Utf8               cf
   #60 = Utf8               Lscala/concurrent/java8/FuturesConvertersImpl$CF;
   #61 = Utf8               ec
   #62 = Utf8               Lscala/concurrent/ExecutionContext$parasitic$;
   #63 = Utf8               this
   #64 = Utf8               Lscala/concurrent/Future;
   #65 = Utf8               java/util/concurrent/CompletionStage
   #66 = Class              #65           // java/util/concurrent/CompletionStage
   #67 = Utf8               toScala
   #68 = Utf8               (Ljava/util/concurrent/CompletionStage;)Lscala/concurrent/Future;
   #69 = Utf8               <T:Ljava/lang/Object;>(Ljava/util/concurrent/CompletionStage<TT;>;)Lscala/concurrent/Future<TT;>;
   #70 = Utf8               cs
   #71 = Utf8               ()Lscala/concurrent/Future;
   #72 = NameAndType        #37:#71       // wrapped:()Lscala/concurrent/Future;
   #73 = Methodref          #17.#72       // scala/concurrent/java8/FuturesConvertersImpl$CF.wrapped:()Lscala/concurrent/Future;
   #74 = Utf8               (Ljava/util/concurrent/CompletionStage;)V
   #75 = NameAndType        #28:#74       // "<init>":(Ljava/util/concurrent/CompletionStage;)V
   #76 = Methodref          #22.#75       // scala/concurrent/java8/FuturesConvertersImpl$P."<init>":(Ljava/util/concurrent/CompletionStage;)V
   #77 = Utf8               whenComplete
   #78 = Utf8               (Ljava/util/function/BiConsumer;)Ljava/util/concurrent/CompletionStage;
   #79 = NameAndType        #77:#78       // whenComplete:(Ljava/util/function/BiConsumer;)Ljava/util/concurrent/CompletionStage;
   #80 = InterfaceMethodref #66.#79       // java/util/concurrent/CompletionStage.whenComplete:(Ljava/util/function/BiConsumer;)Ljava/util/concurrent/CompletionStage;
   #81 = Utf8               future
   #82 = NameAndType        #81:#71       // future:()Lscala/concurrent/Future;
   #83 = Methodref          #22.#82       // scala/concurrent/java8/FuturesConvertersImpl$P.future:()Lscala/concurrent/Future;
   #84 = Utf8               p
   #85 = Utf8               Lscala/concurrent/java8/FuturesConvertersImpl$P;
   #86 = Utf8               Ljava/util/concurrent/CompletionStage;
   #87 = Utf8               fromExecutorService
   #88 = Utf8               (Ljava/util/concurrent/ExecutorService;Ljava/util/function/Consumer;)Lscala/concurrent/ExecutionContextExecutorService;
   #89 = Utf8               (Ljava/util/concurrent/ExecutorService;Ljava/util/function/Consumer<Ljava/lang/Throwable;>;)Lscala/concurrent/ExecutionContextExecutorService;
   #90 = Utf8               e
   #91 = Utf8               reporter
   #92 = Utf8               scala/concurrent/ExecutionContext$
   #93 = Class              #92           // scala/concurrent/ExecutionContext$
   #94 = Utf8               Lscala/concurrent/ExecutionContext$;
   #95 = NameAndType        #24:#94       // MODULE$:Lscala/concurrent/ExecutionContext$;
   #96 = Fieldref           #93.#95       // scala/concurrent/ExecutionContext$.MODULE$:Lscala/concurrent/ExecutionContext$;
   #97 = Utf8               (Ljava/lang/Object;)Ljava/lang/Object;
   #98 = MethodType         #97           //  (Ljava/lang/Object;)Ljava/lang/Object;
   #99 = Utf8               $anonfun$fromExecutorService$1$adapted
  #100 = Utf8               (Ljava/util/function/Consumer;Ljava/lang/Throwable;)Ljava/lang/Object;
  #101 = NameAndType        #99:#100      // $anonfun$fromExecutorService$1$adapted:(Ljava/util/function/Consumer;Ljava/lang/Throwable;)Ljava/lang/Object;
  #102 = Methodref          #2.#101       // scala/compat/java8/FutureConverters$.$anonfun$fromExecutorService$1$adapted:(Ljava/util/function/Consumer;Ljava/lang/Throwable;)Ljava/lang/Object;
  #103 = MethodHandle       6:#102        // REF_invokeStatic scala/compat/java8/FutureConverters$.$anonfun$fromExecutorService$1$adapted:(Ljava/util/function/Consumer;Ljava/lang/Throwable;)Ljava/lang/Object;
  #104 = Utf8               (Ljava/lang/Throwable;)Ljava/lang/Object;
  #105 = MethodType         #104          //  (Ljava/lang/Throwable;)Ljava/lang/Object;
  #106 = Integer            5
  #107 = Integer            1
  #108 = Utf8               java/lang/invoke/LambdaMetafactory
  #109 = Class              #108          // java/lang/invoke/LambdaMetafactory
  #110 = Utf8               altMetafactory
  #111 = Utf8               (Ljava/lang/invoke/MethodHandles$Lookup;Ljava/lang/String;Ljava/lang/invoke/MethodType;[Ljava/lang/Object;)Ljava/lang/invoke/CallSite;
  #112 = NameAndType        #110:#111     // altMetafactory:(Ljava/lang/invoke/MethodHandles$Lookup;Ljava/lang/String;Ljava/lang/invoke/MethodType;[Ljava/lang/Object;)Ljava/lang/invoke/CallSite;
  #113 = Methodref          #109.#112     // java/lang/invoke/LambdaMetafactory.altMetafactory:(Ljava/lang/invoke/MethodHandles$Lookup;Ljava/lang/String;Ljava/lang/invoke/MethodType;[Ljava/lang/Object;)Ljava/lang/invoke/CallSite;
  #114 = MethodHandle       6:#113        // REF_invokeStatic java/lang/invoke/LambdaMetafactory.altMetafactory:(Ljava/lang/invoke/MethodHandles$Lookup;Ljava/lang/String;Ljava/lang/invoke/MethodType;[Ljava/lang/Object;)Ljava/lang/invoke/CallSite;
  #115 = Utf8               apply
  #116 = Utf8               (Ljava/util/function/Consumer;)Lscala/Function1;
  #117 = NameAndType        #115:#116     // apply:(Ljava/util/function/Consumer;)Lscala/Function1;
  #118 = InvokeDynamic      #0:#117       // #0:apply:(Ljava/util/function/Consumer;)Lscala/Function1;
  #119 = Utf8               (Ljava/util/concurrent/ExecutorService;Lscala/Function1;)Lscala/concurrent/ExecutionContextExecutorService;
  #120 = NameAndType        #87:#119      // fromExecutorService:(Ljava/util/concurrent/ExecutorService;Lscala/Function1;)Lscala/concurrent/ExecutionContextExecutorService;
  #121 = Methodref          #93.#120      // scala/concurrent/ExecutionContext$.fromExecutorService:(Ljava/util/concurrent/ExecutorService;Lscala/Function1;)Lscala/concurrent/ExecutionContextExecutorService;
  #122 = Utf8               Ljava/util/concurrent/ExecutorService;
  #123 = Utf8               Ljava/util/function/Consumer;
  #124 = Utf8               (Ljava/util/concurrent/ExecutorService;)Lscala/concurrent/ExecutionContextExecutorService;
  #125 = Utf8               defaultReporter
  #126 = Utf8               ()Lscala/Function1;
  #127 = NameAndType        #125:#126     // defaultReporter:()Lscala/Function1;
  #128 = Methodref          #93.#127      // scala/concurrent/ExecutionContext$.defaultReporter:()Lscala/Function1;
  #129 = Utf8               fromExecutor
  #130 = Utf8               (Ljava/util/concurrent/Executor;Ljava/util/function/Consumer;)Lscala/concurrent/ExecutionContextExecutor;
  #131 = Utf8               (Ljava/util/concurrent/Executor;Ljava/util/function/Consumer<Ljava/lang/Throwable;>;)Lscala/concurrent/ExecutionContextExecutor;
  #132 = Utf8               $anonfun$fromExecutor$1$adapted
  #133 = NameAndType        #132:#100     // $anonfun$fromExecutor$1$adapted:(Ljava/util/function/Consumer;Ljava/lang/Throwable;)Ljava/lang/Object;
  #134 = Methodref          #2.#133       // scala/compat/java8/FutureConverters$.$anonfun$fromExecutor$1$adapted:(Ljava/util/function/Consumer;Ljava/lang/Throwable;)Ljava/lang/Object;
  #135 = MethodHandle       6:#134        // REF_invokeStatic scala/compat/java8/FutureConverters$.$anonfun$fromExecutor$1$adapted:(Ljava/util/function/Consumer;Ljava/lang/Throwable;)Ljava/lang/Object;
  #136 = InvokeDynamic      #1:#117       // #1:apply:(Ljava/util/function/Consumer;)Lscala/Function1;
  #137 = Utf8               (Ljava/util/concurrent/Executor;Lscala/Function1;)Lscala/concurrent/ExecutionContextExecutor;
  #138 = NameAndType        #129:#137     // fromExecutor:(Ljava/util/concurrent/Executor;Lscala/Function1;)Lscala/concurrent/ExecutionContextExecutor;
  #139 = Methodref          #93.#138      // scala/concurrent/ExecutionContext$.fromExecutor:(Ljava/util/concurrent/Executor;Lscala/Function1;)Lscala/concurrent/ExecutionContextExecutor;
  #140 = Utf8               Ljava/util/concurrent/Executor;
  #141 = Utf8               (Ljava/util/concurrent/Executor;)Lscala/concurrent/ExecutionContextExecutor;
  #142 = Utf8               globalExecutionContext
  #143 = Utf8               ()Lscala/concurrent/ExecutionContext;
  #144 = Utf8               global
  #145 = Utf8               ()Lscala/concurrent/ExecutionContextExecutor;
  #146 = NameAndType        #144:#145     // global:()Lscala/concurrent/ExecutionContextExecutor;
  #147 = Methodref          #93.#146      // scala/concurrent/ExecutionContext$.global:()Lscala/concurrent/ExecutionContextExecutor;
  #148 = Utf8               promise
  #149 = Utf8               ()Lscala/concurrent/Promise;
  #150 = Utf8               <T:Ljava/lang/Object;>()Lscala/concurrent/Promise<TT;>;
  #151 = Utf8               scala/concurrent/Promise$
  #152 = Class              #151          // scala/concurrent/Promise$
  #153 = Utf8               Lscala/concurrent/Promise$;
  #154 = NameAndType        #24:#153      // MODULE$:Lscala/concurrent/Promise$;
  #155 = Fieldref           #152.#154     // scala/concurrent/Promise$.MODULE$:Lscala/concurrent/Promise$;
  #156 = NameAndType        #115:#149     // apply:()Lscala/concurrent/Promise;
  #157 = Methodref          #152.#156     // scala/concurrent/Promise$.apply:()Lscala/concurrent/Promise;
  #158 = Utf8               keptPromise
  #159 = Utf8               (Ljava/lang/Object;)Lscala/concurrent/Promise;
  #160 = Utf8               <T:Ljava/lang/Object;>(TT;)Lscala/concurrent/Promise<TT;>;
  #161 = Utf8               v
  #162 = Utf8               successful
  #163 = NameAndType        #162:#159     // successful:(Ljava/lang/Object;)Lscala/concurrent/Promise;
  #164 = Methodref          #152.#163     // scala/concurrent/Promise$.successful:(Ljava/lang/Object;)Lscala/concurrent/Promise;
  #165 = Utf8               Ljava/lang/Object;
  #166 = Utf8               failedPromise
  #167 = Utf8               (Ljava/lang/Throwable;)Lscala/concurrent/Promise;
  #168 = Utf8               <T:Ljava/lang/Object;>(Ljava/lang/Throwable;)Lscala/concurrent/Promise<TT;>;
  #169 = Utf8               ex
  #170 = Utf8               failed
  #171 = NameAndType        #170:#167     // failed:(Ljava/lang/Throwable;)Lscala/concurrent/Promise;
  #172 = Methodref          #152.#171     // scala/concurrent/Promise$.failed:(Ljava/lang/Throwable;)Lscala/concurrent/Promise;
  #173 = Utf8               Ljava/lang/Throwable;
  #174 = Utf8               FutureOps
  #175 = Utf8               (Lscala/concurrent/Future;)Lscala/concurrent/Future;
  #176 = Utf8               <T:Ljava/lang/Object;>(Lscala/concurrent/Future<TT;>;)Lscala/concurrent/Future<TT;>;
  #177 = Utf8               CompletionStageOps
  #178 = Utf8               (Ljava/util/concurrent/CompletionStage;)Ljava/util/concurrent/CompletionStage;
  #179 = Utf8               <T:Ljava/lang/Object;>(Ljava/util/concurrent/CompletionStage<TT;>;)Ljava/util/concurrent/CompletionStage<TT;>;
  #180 = Utf8               $anonfun$fromExecutorService$1
  #181 = Utf8               (Ljava/util/function/Consumer;Ljava/lang/Throwable;)V
  #182 = Utf8               reporter$1
  #183 = Utf8               x$1
  #184 = Utf8               java/util/function/Consumer
  #185 = Class              #184          // java/util/function/Consumer
  #186 = Utf8               accept
  #187 = Utf8               (Ljava/lang/Object;)V
  #188 = NameAndType        #186:#187     // accept:(Ljava/lang/Object;)V
  #189 = InterfaceMethodref #185.#188     // java/util/function/Consumer.accept:(Ljava/lang/Object;)V
  #190 = Utf8               $anonfun$fromExecutor$1
  #191 = Utf8               reporter$2
  #192 = Methodref          #4.#29        // java/lang/Object."<init>":()V
  #193 = NameAndType        #180:#181     // $anonfun$fromExecutorService$1:(Ljava/util/function/Consumer;Ljava/lang/Throwable;)V
  #194 = Methodref          #2.#193       // scala/compat/java8/FutureConverters$.$anonfun$fromExecutorService$1:(Ljava/util/function/Consumer;Ljava/lang/Throwable;)V
  #195 = Utf8               scala/runtime/BoxedUnit
  #196 = Class              #195          // scala/runtime/BoxedUnit
  #197 = Utf8               UNIT
  #198 = Utf8               Lscala/runtime/BoxedUnit;
  #199 = NameAndType        #197:#198     // UNIT:Lscala/runtime/BoxedUnit;
  #200 = Fieldref           #196.#199     // scala/runtime/BoxedUnit.UNIT:Lscala/runtime/BoxedUnit;
  #201 = NameAndType        #190:#181     // $anonfun$fromExecutor$1:(Ljava/util/function/Consumer;Ljava/lang/Throwable;)V
  #202 = Methodref          #2.#201       // scala/compat/java8/FutureConverters$.$anonfun$fromExecutor$1:(Ljava/util/function/Consumer;Ljava/lang/Throwable;)V
  #203 = Utf8               $deserializeLambda$
  #204 = Utf8               (Ljava/lang/invoke/SerializedLambda;)Ljava/lang/Object;
  #205 = Utf8               scala/runtime/LambdaDeserialize
  #206 = Class              #205          // scala/runtime/LambdaDeserialize
  #207 = Utf8               bootstrap
  #208 = Utf8               (Ljava/lang/invoke/MethodHandles$Lookup;Ljava/lang/String;Ljava/lang/invoke/MethodType;[Ljava/lang/invoke/MethodHandle;)Ljava/lang/invoke/CallSite;
  #209 = NameAndType        #207:#208     // bootstrap:(Ljava/lang/invoke/MethodHandles$Lookup;Ljava/lang/String;Ljava/lang/invoke/MethodType;[Ljava/lang/invoke/MethodHandle;)Ljava/lang/invoke/CallSite;
  #210 = Methodref          #206.#209     // scala/runtime/LambdaDeserialize.bootstrap:(Ljava/lang/invoke/MethodHandles$Lookup;Ljava/lang/String;Ljava/lang/invoke/MethodType;[Ljava/lang/invoke/MethodHandle;)Ljava/lang/invoke/CallSite;
  #211 = MethodHandle       6:#210        // REF_invokeStatic scala/runtime/LambdaDeserialize.bootstrap:(Ljava/lang/invoke/MethodHandles$Lookup;Ljava/lang/String;Ljava/lang/invoke/MethodType;[Ljava/lang/invoke/MethodHandle;)Ljava/lang/invoke/CallSite;
  #212 = Utf8               lambdaDeserialize
  #213 = NameAndType        #212:#204     // lambdaDeserialize:(Ljava/lang/invoke/SerializedLambda;)Ljava/lang/Object;
  #214 = InvokeDynamic      #2:#213       // #2:lambdaDeserialize:(Ljava/lang/invoke/SerializedLambda;)Ljava/lang/Object;
  #215 = Utf8               Code
  #216 = Utf8               LineNumberTable
  #217 = Utf8               StackMapTable
  #218 = Utf8               LocalVariableTable
  #219 = Utf8               Signature
  #220 = Utf8               MethodParameters
  #221 = Utf8               InnerClasses
  #222 = Utf8               SourceFile
  #223 = Utf8               BootstrapMethods
  #224 = Utf8               ScalaInlineInfo
  #225 = Utf8               Scala
{
  public static final scala.compat.java8.FutureConverters$ MODULE$;
    descriptor: Lscala/compat/java8/FutureConverters$;
    flags: (0x0019) ACC_PUBLIC, ACC_STATIC, ACC_FINAL

  public static {};
    descriptor: ()V
    flags: (0x0009) ACC_PUBLIC, ACC_STATIC
    Code:
      stack=2, locals=0, args_size=0
         0: new           #2                  // class scala/compat/java8/FutureConverters$
         3: dup
         4: invokespecial #30                 // Method "<init>":()V
         7: putstatic     #32                 // Field MODULE$:Lscala/compat/java8/FutureConverters$;
        10: return
      LineNumberTable:
        line 51: 0

  public <T extends java.lang.Object> java.util.concurrent.CompletionStage<T> toJava(scala.concurrent.Future<T>);
    descriptor: (Lscala/concurrent/Future;)Ljava/util/concurrent/CompletionStage;
    flags: (0x0001) ACC_PUBLIC
    Code:
      stack=3, locals=7, args_size=2
         0: aload_1
         1: astore_3
         2: aload_3
         3: instanceof    #22                 // class scala/concurrent/java8/FuturesConvertersImpl$P
         6: ifeq          24
         9: aload_3
        10: checkcast     #22                 // class scala/concurrent/java8/FuturesConvertersImpl$P
        13: astore        4
        15: aload         4
        17: invokevirtual #40                 // Method scala/concurrent/java8/FuturesConvertersImpl$P.wrapped:()Ljava/util/concurrent/CompletionStage;
        20: astore_2
        21: goto          61
        24: goto          27
        27: new           #17                 // class scala/concurrent/java8/FuturesConvertersImpl$CF
        30: dup
        31: aload_1
        32: invokespecial #43                 // Method scala/concurrent/java8/FuturesConvertersImpl$CF."<init>":(Lscala/concurrent/Future;)V
        35: astore        5
        37: getstatic     #48                 // Field scala/concurrent/java8/FuturesConvertersImplCompat$.MODULE$:Lscala/concurrent/java8/FuturesConvertersImplCompat$;
        40: invokevirtual #52                 // Method scala/concurrent/java8/FuturesConvertersImplCompat$.InternalCallbackExecutor:()Lscala/concurrent/ExecutionContext$parasitic$;
        43: astore        6
        45: aload_1
        46: aload         5
        48: aload         6
        50: invokeinterface #58,  3           // InterfaceMethod scala/concurrent/Future.onComplete:(Lscala/Function1;Lscala/concurrent/ExecutionContext;)V
        55: aload         5
        57: astore_2
        58: goto          61
        61: aload_2
        62: areturn
      StackMapTable: number_of_entries = 3
        frame_type = 253 /* append */
          offset_delta = 24
          locals = [ top, class scala/concurrent/Future ]
        frame_type = 2 /* same */
        frame_type = 255 /* full_frame */
          offset_delta = 33
          locals = [ class scala/compat/java8/FutureConverters$, class scala/concurrent/Future, class java/util/concurrent/CompletionStage, class scala/concurrent/Future ]
          stack = []
      LineNumberTable:
        line 68: 0
        line 69: 2
        line 71: 27
        line 72: 37
        line 73: 45
        line 74: 55
        line 68: 61
      LocalVariableTable:
        Start  Length  Slot  Name   Signature
           37      20     5    cf   Lscala/concurrent/java8/FuturesConvertersImpl$CF;
           45      12     6    ec   Lscala/concurrent/ExecutionContext$parasitic$;
            0      63     0  this   Lscala/compat/java8/FutureConverters$;
            0      63     1     f   Lscala/concurrent/Future;
    Signature: #35                          // <T:Ljava/lang/Object;>(Lscala/concurrent/Future<TT;>;)Ljava/util/concurrent/CompletionStage<TT;>;
    MethodParameters:
      Name                           Flags
      f                              final

  public <T extends java.lang.Object> scala.concurrent.Future<T> toScala(java.util.concurrent.CompletionStage<T>);
    descriptor: (Ljava/util/concurrent/CompletionStage;)Lscala/concurrent/Future;
    flags: (0x0001) ACC_PUBLIC
    Code:
      stack=3, locals=6, args_size=2
         0: aload_1
         1: astore_3
         2: aload_3
         3: instanceof    #17                 // class scala/concurrent/java8/FuturesConvertersImpl$CF
         6: ifeq          24
         9: aload_3
        10: checkcast     #17                 // class scala/concurrent/java8/FuturesConvertersImpl$CF
        13: astore        4
        15: aload         4
        17: invokevirtual #73                 // Method scala/concurrent/java8/FuturesConvertersImpl$CF.wrapped:()Lscala/concurrent/Future;
        20: astore_2
        21: goto          55
        24: goto          27
        27: new           #22                 // class scala/concurrent/java8/FuturesConvertersImpl$P
        30: dup
        31: aload_1
        32: invokespecial #76                 // Method scala/concurrent/java8/FuturesConvertersImpl$P."<init>":(Ljava/util/concurrent/CompletionStage;)V
        35: astore        5
        37: aload_1
        38: aload         5
        40: invokeinterface #80,  2           // InterfaceMethod java/util/concurrent/CompletionStage.whenComplete:(Ljava/util/function/BiConsumer;)Ljava/util/concurrent/CompletionStage;
        45: pop
        46: aload         5
        48: invokevirtual #83                 // Method scala/concurrent/java8/FuturesConvertersImpl$P.future:()Lscala/concurrent/Future;
        51: astore_2
        52: goto          55
        55: aload_2
        56: areturn
      StackMapTable: number_of_entries = 3
        frame_type = 253 /* append */
          offset_delta = 24
          locals = [ top, class java/util/concurrent/CompletionStage ]
        frame_type = 2 /* same */
        frame_type = 255 /* full_frame */
          offset_delta = 27
          locals = [ class scala/compat/java8/FutureConverters$, class java/util/concurrent/CompletionStage, class scala/concurrent/Future, class java/util/concurrent/CompletionStage ]
          stack = []
      LineNumberTable:
        line 89: 0
        line 90: 2
        line 92: 27
        line 93: 37
        line 94: 46
        line 89: 55
      LocalVariableTable:
        Start  Length  Slot  Name   Signature
           37      14     5     p   Lscala/concurrent/java8/FuturesConvertersImpl$P;
            0      57     0  this   Lscala/compat/java8/FutureConverters$;
            0      57     1    cs   Ljava/util/concurrent/CompletionStage;
    Signature: #69                          // <T:Ljava/lang/Object;>(Ljava/util/concurrent/CompletionStage<TT;>;)Lscala/concurrent/Future<TT;>;
    MethodParameters:
      Name                           Flags
      cs                             final

  public scala.concurrent.ExecutionContextExecutorService fromExecutorService(java.util.concurrent.ExecutorService, java.util.function.Consumer<java.lang.Throwable>);
    descriptor: (Ljava/util/concurrent/ExecutorService;Ljava/util/function/Consumer;)Lscala/concurrent/ExecutionContextExecutorService;
    flags: (0x0001) ACC_PUBLIC
    Code:
      stack=3, locals=3, args_size=3
         0: getstatic     #96                 // Field scala/concurrent/ExecutionContext$.MODULE$:Lscala/concurrent/ExecutionContext$;
         3: aload_1
         4: aload_2
         5: invokedynamic #118,  0            // InvokeDynamic #0:apply:(Ljava/util/function/Consumer;)Lscala/Function1;
        10: invokevirtual #121                // Method scala/concurrent/ExecutionContext$.fromExecutorService:(Ljava/util/concurrent/ExecutorService;Lscala/Function1;)Lscala/concurrent/ExecutionContextExecutorService;
        13: areturn
      LineNumberTable:
        line 112: 0
      LocalVariableTable:
        Start  Length  Slot  Name   Signature
            0      14     0  this   Lscala/compat/java8/FutureConverters$;
            0      14     1     e   Ljava/util/concurrent/ExecutorService;
            0      14     2 reporter   Ljava/util/function/Consumer;
    Signature: #89                          // (Ljava/util/concurrent/ExecutorService;Ljava/util/function/Consumer<Ljava/lang/Throwable;>;)Lscala/concurrent/ExecutionContextExecutorService;
    MethodParameters:
      Name                           Flags
      e                              final
      reporter                       final

  public scala.concurrent.ExecutionContextExecutorService fromExecutorService(java.util.concurrent.ExecutorService);
    descriptor: (Ljava/util/concurrent/ExecutorService;)Lscala/concurrent/ExecutionContextExecutorService;
    flags: (0x0001) ACC_PUBLIC
    Code:
      stack=3, locals=2, args_size=2
         0: getstatic     #96                 // Field scala/concurrent/ExecutionContext$.MODULE$:Lscala/concurrent/ExecutionContext$;
         3: aload_1
         4: getstatic     #96                 // Field scala/concurrent/ExecutionContext$.MODULE$:Lscala/concurrent/ExecutionContext$;
         7: invokevirtual #128                // Method scala/concurrent/ExecutionContext$.defaultReporter:()Lscala/Function1;
        10: invokevirtual #121                // Method scala/concurrent/ExecutionContext$.fromExecutorService:(Ljava/util/concurrent/ExecutorService;Lscala/Function1;)Lscala/concurrent/ExecutionContextExecutorService;
        13: areturn
      LineNumberTable:
        line 123: 0
      LocalVariableTable:
        Start  Length  Slot  Name   Signature
            0      14     0  this   Lscala/compat/java8/FutureConverters$;
            0      14     1     e   Ljava/util/concurrent/ExecutorService;
    MethodParameters:
      Name                           Flags
      e                              final

  public scala.concurrent.ExecutionContextExecutor fromExecutor(java.util.concurrent.Executor, java.util.function.Consumer<java.lang.Throwable>);
    descriptor: (Ljava/util/concurrent/Executor;Ljava/util/function/Consumer;)Lscala/concurrent/ExecutionContextExecutor;
    flags: (0x0001) ACC_PUBLIC
    Code:
      stack=3, locals=3, args_size=3
         0: getstatic     #96                 // Field scala/concurrent/ExecutionContext$.MODULE$:Lscala/concurrent/ExecutionContext$;
         3: aload_1
         4: aload_2
         5: invokedynamic #136,  0            // InvokeDynamic #1:apply:(Ljava/util/function/Consumer;)Lscala/Function1;
        10: invokevirtual #139                // Method scala/concurrent/ExecutionContext$.fromExecutor:(Ljava/util/concurrent/Executor;Lscala/Function1;)Lscala/concurrent/ExecutionContextExecutor;
        13: areturn
      LineNumberTable:
        line 139: 0
      LocalVariableTable:
        Start  Length  Slot  Name   Signature
            0      14     0  this   Lscala/compat/java8/FutureConverters$;
            0      14     1     e   Ljava/util/concurrent/Executor;
            0      14     2 reporter   Ljava/util/function/Consumer;
    Signature: #131                         // (Ljava/util/concurrent/Executor;Ljava/util/function/Consumer<Ljava/lang/Throwable;>;)Lscala/concurrent/ExecutionContextExecutor;
    MethodParameters:
      Name                           Flags
      e                              final
      reporter                       final

  public scala.concurrent.ExecutionContextExecutor fromExecutor(java.util.concurrent.Executor);
    descriptor: (Ljava/util/concurrent/Executor;)Lscala/concurrent/ExecutionContextExecutor;
    flags: (0x0001) ACC_PUBLIC
    Code:
      stack=3, locals=2, args_size=2
         0: getstatic     #96                 // Field scala/concurrent/ExecutionContext$.MODULE$:Lscala/concurrent/ExecutionContext$;
         3: aload_1
         4: getstatic     #96                 // Field scala/concurrent/ExecutionContext$.MODULE$:Lscala/concurrent/ExecutionContext$;
         7: invokevirtual #128                // Method scala/concurrent/ExecutionContext$.defaultReporter:()Lscala/Function1;
        10: invokevirtual #139                // Method scala/concurrent/ExecutionContext$.fromExecutor:(Ljava/util/concurrent/Executor;Lscala/Function1;)Lscala/concurrent/ExecutionContextExecutor;
        13: areturn
      LineNumberTable:
        line 150: 0
      LocalVariableTable:
        Start  Length  Slot  Name   Signature
            0      14     0  this   Lscala/compat/java8/FutureConverters$;
            0      14     1     e   Ljava/util/concurrent/Executor;
    MethodParameters:
      Name                           Flags
      e                              final

  public scala.concurrent.ExecutionContext globalExecutionContext();
    descriptor: ()Lscala/concurrent/ExecutionContext;
    flags: (0x0001) ACC_PUBLIC
    Code:
      stack=1, locals=1, args_size=1
         0: getstatic     #96                 // Field scala/concurrent/ExecutionContext$.MODULE$:Lscala/concurrent/ExecutionContext$;
         3: invokevirtual #147                // Method scala/concurrent/ExecutionContext$.global:()Lscala/concurrent/ExecutionContextExecutor;
         6: areturn
      LineNumberTable:
        line 157: 0
      LocalVariableTable:
        Start  Length  Slot  Name   Signature
            0       7     0  this   Lscala/compat/java8/FutureConverters$;

  public <T extends java.lang.Object> scala.concurrent.Promise<T> promise();
    descriptor: ()Lscala/concurrent/Promise;
    flags: (0x0001) ACC_PUBLIC
    Code:
      stack=1, locals=1, args_size=1
         0: getstatic     #155                // Field scala/concurrent/Promise$.MODULE$:Lscala/concurrent/Promise$;
         3: invokevirtual #157                // Method scala/concurrent/Promise$.apply:()Lscala/concurrent/Promise;
         6: areturn
      LineNumberTable:
        line 164: 0
      LocalVariableTable:
        Start  Length  Slot  Name   Signature
            0       7     0  this   Lscala/compat/java8/FutureConverters$;
    Signature: #150                         // <T:Ljava/lang/Object;>()Lscala/concurrent/Promise<TT;>;

  public <T extends java.lang.Object> scala.concurrent.Promise<T> keptPromise(T);
    descriptor: (Ljava/lang/Object;)Lscala/concurrent/Promise;
    flags: (0x0001) ACC_PUBLIC
    Code:
      stack=2, locals=2, args_size=2
         0: getstatic     #155                // Field scala/concurrent/Promise$.MODULE$:Lscala/concurrent/Promise$;
         3: aload_1
         4: invokevirtual #164                // Method scala/concurrent/Promise$.successful:(Ljava/lang/Object;)Lscala/concurrent/Promise;
         7: areturn
      LineNumberTable:
        line 171: 0
      LocalVariableTable:
        Start  Length  Slot  Name   Signature
            0       8     0  this   Lscala/compat/java8/FutureConverters$;
            0       8     1     v   Ljava/lang/Object;
    Signature: #160                         // <T:Ljava/lang/Object;>(TT;)Lscala/concurrent/Promise<TT;>;
    MethodParameters:
      Name                           Flags
      v                              final

  public <T extends java.lang.Object> scala.concurrent.Promise<T> failedPromise(java.lang.Throwable);
    descriptor: (Ljava/lang/Throwable;)Lscala/concurrent/Promise;
    flags: (0x0001) ACC_PUBLIC
    Code:
      stack=2, locals=2, args_size=2
         0: getstatic     #155                // Field scala/concurrent/Promise$.MODULE$:Lscala/concurrent/Promise$;
         3: aload_1
         4: invokevirtual #172                // Method scala/concurrent/Promise$.failed:(Ljava/lang/Throwable;)Lscala/concurrent/Promise;
         7: areturn
      LineNumberTable:
        line 178: 0
      LocalVariableTable:
        Start  Length  Slot  Name   Signature
            0       8     0  this   Lscala/compat/java8/FutureConverters$;
            0       8     1    ex   Ljava/lang/Throwable;
    Signature: #168                         // <T:Ljava/lang/Object;>(Ljava/lang/Throwable;)Lscala/concurrent/Promise<TT;>;
    MethodParameters:
      Name                           Flags
      ex                             final

  public <T extends java.lang.Object> scala.concurrent.Future<T> FutureOps(scala.concurrent.Future<T>);
    descriptor: (Lscala/concurrent/Future;)Lscala/concurrent/Future;
    flags: (0x0001) ACC_PUBLIC
    Code:
      stack=1, locals=2, args_size=2
         0: aload_1
         1: areturn
      LineNumberTable:
        line 180: 0
      LocalVariableTable:
        Start  Length  Slot  Name   Signature
            0       2     0  this   Lscala/compat/java8/FutureConverters$;
            0       2     1     f   Lscala/concurrent/Future;
    Signature: #176                         // <T:Ljava/lang/Object;>(Lscala/concurrent/Future<TT;>;)Lscala/concurrent/Future<TT;>;
    MethodParameters:
      Name                           Flags
      f                              final

  public <T extends java.lang.Object> java.util.concurrent.CompletionStage<T> CompletionStageOps(java.util.concurrent.CompletionStage<T>);
    descriptor: (Ljava/util/concurrent/CompletionStage;)Ljava/util/concurrent/CompletionStage;
    flags: (0x0001) ACC_PUBLIC
    Code:
      stack=1, locals=2, args_size=2
         0: aload_1
         1: areturn
      LineNumberTable:
        line 198: 0
      LocalVariableTable:
        Start  Length  Slot  Name   Signature
            0       2     0  this   Lscala/compat/java8/FutureConverters$;
            0       2     1    cs   Ljava/util/concurrent/CompletionStage;
    Signature: #179                         // <T:Ljava/lang/Object;>(Ljava/util/concurrent/CompletionStage<TT;>;)Ljava/util/concurrent/CompletionStage<TT;>;
    MethodParameters:
      Name                           Flags
      cs                             final

  public static final void $anonfun$fromExecutorService$1(java.util.function.Consumer, java.lang.Throwable);
    descriptor: (Ljava/util/function/Consumer;Ljava/lang/Throwable;)V
    flags: (0x1019) ACC_PUBLIC, ACC_STATIC, ACC_FINAL, ACC_SYNTHETIC
    Code:
      stack=2, locals=2, args_size=2
         0: aload_0
         1: aload_1
         2: invokeinterface #189,  2          // InterfaceMethod java/util/function/Consumer.accept:(Ljava/lang/Object;)V
         7: return
      LineNumberTable:
        line 112: 0
      LocalVariableTable:
        Start  Length  Slot  Name   Signature
            0       8     0 reporter$1   Ljava/util/function/Consumer;
            0       8     1   x$1   Ljava/lang/Throwable;
    MethodParameters:
      Name                           Flags
      reporter$1                     final
      x$1                            final

  public static final void $anonfun$fromExecutor$1(java.util.function.Consumer, java.lang.Throwable);
    descriptor: (Ljava/util/function/Consumer;Ljava/lang/Throwable;)V
    flags: (0x1019) ACC_PUBLIC, ACC_STATIC, ACC_FINAL, ACC_SYNTHETIC
    Code:
      stack=2, locals=2, args_size=2
         0: aload_0
         1: aload_1
         2: invokeinterface #189,  2          // InterfaceMethod java/util/function/Consumer.accept:(Ljava/lang/Object;)V
         7: return
      LineNumberTable:
        line 139: 0
      LocalVariableTable:
        Start  Length  Slot  Name   Signature
            0       8     0 reporter$2   Ljava/util/function/Consumer;
            0       8     1   x$1   Ljava/lang/Throwable;
    MethodParameters:
      Name                           Flags
      reporter$2                     final
      x$1                            final

  private scala.compat.java8.FutureConverters$();
    descriptor: ()V
    flags: (0x0002) ACC_PRIVATE
    Code:
      stack=1, locals=1, args_size=1
         0: aload_0
         1: invokespecial #192                // Method java/lang/Object."<init>":()V
         4: return
      LineNumberTable:
        line 211: 0
        line 51: 4
      LocalVariableTable:
        Start  Length  Slot  Name   Signature
            0       5     0  this   Lscala/compat/java8/FutureConverters$;

  public static final java.lang.Object $anonfun$fromExecutorService$1$adapted(java.util.function.Consumer, java.lang.Throwable);
    descriptor: (Ljava/util/function/Consumer;Ljava/lang/Throwable;)Ljava/lang/Object;
    flags: (0x1019) ACC_PUBLIC, ACC_STATIC, ACC_FINAL, ACC_SYNTHETIC
    Code:
      stack=2, locals=2, args_size=2
         0: aload_0
         1: aload_1
         2: invokestatic  #194                // Method $anonfun$fromExecutorService$1:(Ljava/util/function/Consumer;Ljava/lang/Throwable;)V
         5: getstatic     #200                // Field scala/runtime/BoxedUnit.UNIT:Lscala/runtime/BoxedUnit;
         8: areturn
      LineNumberTable:
        line 112: 0
      LocalVariableTable:
        Start  Length  Slot  Name   Signature
            0       9     0 reporter$1   Ljava/util/function/Consumer;
            0       9     1   x$1   Ljava/lang/Throwable;
    MethodParameters:
      Name                           Flags
      reporter$1                     final
      x$1                            final

  public static final java.lang.Object $anonfun$fromExecutor$1$adapted(java.util.function.Consumer, java.lang.Throwable);
    descriptor: (Ljava/util/function/Consumer;Ljava/lang/Throwable;)Ljava/lang/Object;
    flags: (0x1019) ACC_PUBLIC, ACC_STATIC, ACC_FINAL, ACC_SYNTHETIC
    Code:
      stack=2, locals=2, args_size=2
         0: aload_0
         1: aload_1
         2: invokestatic  #202                // Method $anonfun$fromExecutor$1:(Ljava/util/function/Consumer;Ljava/lang/Throwable;)V
         5: getstatic     #200                // Field scala/runtime/BoxedUnit.UNIT:Lscala/runtime/BoxedUnit;
         8: areturn
      LineNumberTable:
        line 139: 0
      LocalVariableTable:
        Start  Length  Slot  Name   Signature
            0       9     0 reporter$2   Ljava/util/function/Consumer;
            0       9     1   x$1   Ljava/lang/Throwable;
    MethodParameters:
      Name                           Flags
      reporter$2                     final
      x$1                            final

  private static java.lang.Object $deserializeLambda$(java.lang.invoke.SerializedLambda);
    descriptor: (Ljava/lang/invoke/SerializedLambda;)Ljava/lang/Object;
    flags: (0x100a) ACC_PRIVATE, ACC_STATIC, ACC_SYNTHETIC
    Code:
      stack=1, locals=1, args_size=1
         0: aload_0
         1: invokedynamic #214,  0            // InvokeDynamic #2:lambdaDeserialize:(Ljava/lang/invoke/SerializedLambda;)Ljava/lang/Object;
         6: areturn
}
InnerClasses:
  public static final #10= #7 of #9;      // Lookup=class java/lang/invoke/MethodHandles$Lookup of class java/lang/invoke/MethodHandles
  public static #15= #12 of #14;          // parasitic$=class scala/concurrent/ExecutionContext$parasitic$ of class scala/concurrent/ExecutionContext
  public static #20= #17 of #19;          // CF=class scala/concurrent/java8/FuturesConvertersImpl$CF of class scala/concurrent/java8/FuturesConvertersImpl
  public static #23= #22 of #19;          // P=class scala/concurrent/java8/FuturesConvertersImpl$P of class scala/concurrent/java8/FuturesConvertersImpl
SourceFile: "FutureConverters.scala"
BootstrapMethods:
  0: #114 REF_invokeStatic java/lang/invoke/LambdaMetafactory.altMetafactory:(Ljava/lang/invoke/MethodHandles$Lookup;Ljava/lang/String;Ljava/lang/invoke/MethodType;[Ljava/lang/Object;)Ljava/lang/invoke/CallSite;
    Method arguments:
      #98 (Ljava/lang/Object;)Ljava/lang/Object;
      #103 REF_invokeStatic scala/compat/java8/FutureConverters$.$anonfun$fromExecutorService$1$adapted:(Ljava/util/function/Consumer;Ljava/lang/Throwable;)Ljava/lang/Object;
      #105 (Ljava/lang/Throwable;)Ljava/lang/Object;
      #106 5
      #107 1
      #105 (Ljava/lang/Throwable;)Ljava/lang/Object;
  1: #114 REF_invokeStatic java/lang/invoke/LambdaMetafactory.altMetafactory:(Ljava/lang/invoke/MethodHandles$Lookup;Ljava/lang/String;Ljava/lang/invoke/MethodType;[Ljava/lang/Object;)Ljava/lang/invoke/CallSite;
    Method arguments:
      #98 (Ljava/lang/Object;)Ljava/lang/Object;
      #135 REF_invokeStatic scala/compat/java8/FutureConverters$.$anonfun$fromExecutor$1$adapted:(Ljava/util/function/Consumer;Ljava/lang/Throwable;)Ljava/lang/Object;
      #105 (Ljava/lang/Throwable;)Ljava/lang/Object;
      #106 5
      #107 1
      #105 (Ljava/lang/Throwable;)Ljava/lang/Object;
  2: #211 REF_invokeStatic scala/runtime/LambdaDeserialize.bootstrap:(Ljava/lang/invoke/MethodHandles$Lookup;Ljava/lang/String;Ljava/lang/invoke/MethodType;[Ljava/lang/invoke/MethodHandle;)Ljava/lang/invoke/CallSite;
    Method arguments:
      #135 REF_invokeStatic scala/compat/java8/FutureConverters$.$anonfun$fromExecutor$1$adapted:(Ljava/util/function/Consumer;Ljava/lang/Throwable;)Ljava/lang/Object;
      #103 REF_invokeStatic scala/compat/java8/FutureConverters$.$anonfun$fromExecutorService$1$adapted:(Ljava/util/function/Consumer;Ljava/lang/Throwable;)Ljava/lang/Object;
  ScalaInlineInfo: length = 0x59 (unknown attribute)
   01 01 00 11 00 BE 00 B5 01 00 84 00 64 01 00 B4
   00 B5 01 00 63 00 64 01 00 1C 00 1B 01 00 B1 00
   B2 01 00 AE 00 AF 01 00 A6 00 A7 01 00 81 00 8D
   01 00 81 00 82 01 00 57 00 7C 01 00 57 00 58 01
   00 8E 00 8F 01 00 9E 00 9F 01 00 94 00 95 01 00
   21 00 22 01 00 43 00 44 01
  Scala: length = 0x0 (unknown attribute)

