Classfile /Users/mw/Projects/slang-braindump/.jar/jar11/assemble/slang-braindump/assemble/content/scala/compat/java8/PrimitiveIteratorConverters$RichIteratorToPrimitives$.class
  Last modified May 29, 2022; size 2415 bytes
  SHA-256 checksum fc8db818ea323436a4ed2b5a8f826c10848a8048faad5ceaca4cc386767bf7cf
  Compiled from "PrimitiveIteratorConversions.scala"
public class scala.compat.java8.PrimitiveIteratorConverters$RichIteratorToPrimitives$
  minor version: 0
  major version: 52
  flags: (0x0021) ACC_PUBLIC, ACC_SUPER
  this_class: #2                          // scala/compat/java8/PrimitiveIteratorConverters$RichIteratorToPrimitives$
  super_class: #4                         // java/lang/Object
  interfaces: 0, fields: 1, methods: 5, attributes: 4
Constant pool:
   #1 = Utf8               scala/compat/java8/PrimitiveIteratorConverters$RichIteratorToPrimitives$
   #2 = Class              #1             // scala/compat/java8/PrimitiveIteratorConverters$RichIteratorToPrimitives$
   #3 = Utf8               java/lang/Object
   #4 = Class              #3             // java/lang/Object
   #5 = Utf8               PrimitiveIteratorConversions.scala
   #6 = Utf8               scala/compat/java8/PrimitiveIteratorConverters$RichIteratorToPrimitives
   #7 = Class              #6             // scala/compat/java8/PrimitiveIteratorConverters$RichIteratorToPrimitives
   #8 = Utf8               scala/compat/java8/PrimitiveIteratorConverters
   #9 = Class              #8             // scala/compat/java8/PrimitiveIteratorConverters
  #10 = Utf8               RichIteratorToPrimitives
  #11 = Utf8               RichIteratorToPrimitives$
  #12 = Utf8               scala/compat/java8/PrimitiveIteratorConverters$SpecializerOfIterators
  #13 = Class              #12            // scala/compat/java8/PrimitiveIteratorConverters$SpecializerOfIterators
  #14 = Utf8               SpecializerOfIterators
  #15 = Utf8               MODULE$
  #16 = Utf8               Lscala/compat/java8/PrimitiveIteratorConverters$RichIteratorToPrimitives$;
  #17 = Utf8               <clinit>
  #18 = Utf8               ()V
  #19 = Utf8               <init>
  #20 = NameAndType        #19:#18        // "<init>":()V
  #21 = Methodref          #2.#20         // scala/compat/java8/PrimitiveIteratorConverters$RichIteratorToPrimitives$."<init>":()V
  #22 = NameAndType        #15:#16        // MODULE$:Lscala/compat/java8/PrimitiveIteratorConverters$RichIteratorToPrimitives$;
  #23 = Fieldref           #2.#22         // scala/compat/java8/PrimitiveIteratorConverters$RichIteratorToPrimitives$.MODULE$:Lscala/compat/java8/PrimitiveIteratorConverters$RichIteratorToPrimitives$;
  #24 = Utf8               asPrimitive$extension
  #25 = Utf8               (Lscala/collection/Iterator;Lscala/compat/java8/PrimitiveIteratorConverters$SpecializerOfIterators;)Ljava/lang/Object;
  #26 = Utf8               <That:Ljava/lang/Object;A:Ljava/lang/Object;>(Lscala/collection/Iterator<TA;>;Lscala/compat/java8/PrimitiveIteratorConverters$SpecializerOfIterators<TA;TThat;>;)TThat;
  #27 = Utf8               $this
  #28 = Utf8               specOp
  #29 = Utf8               fromScala
  #30 = Utf8               (Lscala/collection/Iterator;)Ljava/lang/Object;
  #31 = NameAndType        #29:#30        // fromScala:(Lscala/collection/Iterator;)Ljava/lang/Object;
  #32 = Methodref          #13.#31        // scala/compat/java8/PrimitiveIteratorConverters$SpecializerOfIterators.fromScala:(Lscala/collection/Iterator;)Ljava/lang/Object;
  #33 = Utf8               this
  #34 = Utf8               Lscala/collection/Iterator;
  #35 = Utf8               Lscala/compat/java8/PrimitiveIteratorConverters$SpecializerOfIterators;
  #36 = Utf8               hashCode$extension
  #37 = Utf8               (Lscala/collection/Iterator;)I
  #38 = Utf8               <A:Ljava/lang/Object;>(Lscala/collection/Iterator<TA;>;)I
  #39 = Utf8               hashCode
  #40 = Utf8               ()I
  #41 = NameAndType        #39:#40        // hashCode:()I
  #42 = Methodref          #4.#41         // java/lang/Object.hashCode:()I
  #43 = Utf8               equals$extension
  #44 = Utf8               (Lscala/collection/Iterator;Ljava/lang/Object;)Z
  #45 = Utf8               <A:Ljava/lang/Object;>(Lscala/collection/Iterator<TA;>;Ljava/lang/Object;)Z
  #46 = Utf8               x$1
  #47 = Utf8               scala$compat$java8$PrimitiveIteratorConverters$RichIteratorToPrimitives$$underlying
  #48 = Utf8               ()Lscala/collection/Iterator;
  #49 = NameAndType        #47:#48        // scala$compat$java8$PrimitiveIteratorConverters$RichIteratorToPrimitives$$underlying:()Lscala/collection/Iterator;
  #50 = Methodref          #7.#49         // scala/compat/java8/PrimitiveIteratorConverters$RichIteratorToPrimitives.scala$compat$java8$PrimitiveIteratorConverters$RichIteratorToPrimitives$$underlying:()Lscala/collection/Iterator;
  #51 = Utf8               equals
  #52 = Utf8               (Ljava/lang/Object;)Z
  #53 = NameAndType        #51:#52        // equals:(Ljava/lang/Object;)Z
  #54 = Methodref          #4.#53         // java/lang/Object.equals:(Ljava/lang/Object;)Z
  #55 = Utf8               Ljava/lang/Object;
  #56 = Utf8               scala/collection/Iterator
  #57 = Class              #56            // scala/collection/Iterator
  #58 = Methodref          #4.#20         // java/lang/Object."<init>":()V
  #59 = Utf8               Code
  #60 = Utf8               LineNumberTable
  #61 = Utf8               LocalVariableTable
  #62 = Utf8               Signature
  #63 = Utf8               MethodParameters
  #64 = Utf8               StackMapTable
  #65 = Utf8               InnerClasses
  #66 = Utf8               SourceFile
  #67 = Utf8               ScalaInlineInfo
  #68 = Utf8               Scala
{
  public static final scala.compat.java8.PrimitiveIteratorConverters$RichIteratorToPrimitives$ MODULE$;
    descriptor: Lscala/compat/java8/PrimitiveIteratorConverters$RichIteratorToPrimitives$;
    flags: (0x0019) ACC_PUBLIC, ACC_STATIC, ACC_FINAL

  public static {};
    descriptor: ()V
    flags: (0x0009) ACC_PUBLIC, ACC_STATIC
    Code:
      stack=2, locals=0, args_size=0
         0: new           #2                  // class scala/compat/java8/PrimitiveIteratorConverters$RichIteratorToPrimitives$
         3: dup
         4: invokespecial #21                 // Method "<init>":()V
         7: putstatic     #23                 // Field MODULE$:Lscala/compat/java8/PrimitiveIteratorConverters$RichIteratorToPrimitives$;
        10: return
      LineNumberTable:
        line 116: 0

  public final <That extends java.lang.Object, A extends java.lang.Object> That asPrimitive$extension(scala.collection.Iterator<A>, scala.compat.java8.PrimitiveIteratorConverters$SpecializerOfIterators<A, That>);
    descriptor: (Lscala/collection/Iterator;Lscala/compat/java8/PrimitiveIteratorConverters$SpecializerOfIterators;)Ljava/lang/Object;
    flags: (0x0011) ACC_PUBLIC, ACC_FINAL
    Code:
      stack=2, locals=3, args_size=3
         0: aload_2
         1: aload_1
         2: invokevirtual #32                 // Method scala/compat/java8/PrimitiveIteratorConverters$SpecializerOfIterators.fromScala:(Lscala/collection/Iterator;)Ljava/lang/Object;
         5: areturn
      LineNumberTable:
        line 118: 0
      LocalVariableTable:
        Start  Length  Slot  Name   Signature
            0       6     0  this   Lscala/compat/java8/PrimitiveIteratorConverters$RichIteratorToPrimitives$;
            0       6     1 $this   Lscala/collection/Iterator;
            0       6     2 specOp   Lscala/compat/java8/PrimitiveIteratorConverters$SpecializerOfIterators;
    Signature: #26                          // <That:Ljava/lang/Object;A:Ljava/lang/Object;>(Lscala/collection/Iterator<TA;>;Lscala/compat/java8/PrimitiveIteratorConverters$SpecializerOfIterators<TA;TThat;>;)TThat;
    MethodParameters:
      Name                           Flags
      $this                          final
      specOp                         final

  public final <A extends java.lang.Object> int hashCode$extension(scala.collection.Iterator<A>);
    descriptor: (Lscala/collection/Iterator;)I
    flags: (0x0011) ACC_PUBLIC, ACC_FINAL
    Code:
      stack=1, locals=2, args_size=2
         0: aload_1
         1: invokevirtual #42                 // Method java/lang/Object.hashCode:()I
         4: ireturn
      LineNumberTable:
        line 116: 0
      LocalVariableTable:
        Start  Length  Slot  Name   Signature
            0       5     0  this   Lscala/compat/java8/PrimitiveIteratorConverters$RichIteratorToPrimitives$;
            0       5     1 $this   Lscala/collection/Iterator;
    Signature: #38                          // <A:Ljava/lang/Object;>(Lscala/collection/Iterator<TA;>;)I
    MethodParameters:
      Name                           Flags
      $this                          final

  public final <A extends java.lang.Object> boolean equals$extension(scala.collection.Iterator<A>, java.lang.Object);
    descriptor: (Lscala/collection/Iterator;Ljava/lang/Object;)Z
    flags: (0x0011) ACC_PUBLIC, ACC_FINAL
    Code:
      stack=2, locals=7, args_size=3
         0: aload_2
         1: astore        4
         3: aload         4
         5: instanceof    #7                  // class scala/compat/java8/PrimitiveIteratorConverters$RichIteratorToPrimitives
         8: ifeq          16
        11: iconst_1
        12: istore_3
        13: goto          24
        16: goto          19
        19: iconst_0
        20: istore_3
        21: goto          24
        24: iload_3
        25: ifeq          83
        28: aload_2
        29: ifnonnull     36
        32: aconst_null
        33: goto          43
        36: aload_2
        37: checkcast     #7                  // class scala/compat/java8/PrimitiveIteratorConverters$RichIteratorToPrimitives
        40: invokevirtual #50                 // Method scala/compat/java8/PrimitiveIteratorConverters$RichIteratorToPrimitives.scala$compat$java8$PrimitiveIteratorConverters$RichIteratorToPrimitives$$underlying:()Lscala/collection/Iterator;
        43: astore        5
        45: aload_1
        46: aload         5
        48: astore        6
        50: dup
        51: ifnonnull     63
        54: pop
        55: aload         6
        57: ifnull        71
        60: goto          75
        63: aload         6
        65: invokevirtual #54                 // Method java/lang/Object.equals:(Ljava/lang/Object;)Z
        68: ifeq          75
        71: iconst_1
        72: goto          76
        75: iconst_0
        76: ifeq          83
        79: iconst_1
        80: goto          84
        83: iconst_0
        84: ireturn
      StackMapTable: number_of_entries = 11
        frame_type = 253 /* append */
          offset_delta = 16
          locals = [ top, class java/lang/Object ]
        frame_type = 2 /* same */
        frame_type = 255 /* full_frame */
          offset_delta = 4
          locals = [ class scala/compat/java8/PrimitiveIteratorConverters$RichIteratorToPrimitives$, class scala/collection/Iterator, class java/lang/Object, int, class java/lang/Object ]
          stack = []
        frame_type = 11 /* same */
        frame_type = 70 /* same_locals_1_stack_item */
          stack = [ class scala/collection/Iterator ]
        frame_type = 255 /* full_frame */
          offset_delta = 19
          locals = [ class scala/compat/java8/PrimitiveIteratorConverters$RichIteratorToPrimitives$, class scala/collection/Iterator, class java/lang/Object, int, class java/lang/Object, class scala/collection/Iterator, class scala/collection/Iterator ]
          stack = [ class scala/collection/Iterator ]
        frame_type = 7 /* same */
        frame_type = 3 /* same */
        frame_type = 64 /* same_locals_1_stack_item */
          stack = [ int ]
        frame_type = 249 /* chop */
          offset_delta = 6
        frame_type = 64 /* same_locals_1_stack_item */
          stack = [ int ]
      LineNumberTable:
        line 116: 0
      LocalVariableTable:
        Start  Length  Slot  Name   Signature
            0      85     0  this   Lscala/compat/java8/PrimitiveIteratorConverters$RichIteratorToPrimitives$;
            0      85     1 $this   Lscala/collection/Iterator;
            0      85     2   x$1   Ljava/lang/Object;
    Signature: #45                          // <A:Ljava/lang/Object;>(Lscala/collection/Iterator<TA;>;Ljava/lang/Object;)Z
    MethodParameters:
      Name                           Flags
      $this                          final
      x$1                            final

  public scala.compat.java8.PrimitiveIteratorConverters$RichIteratorToPrimitives$();
    descriptor: ()V
    flags: (0x0001) ACC_PUBLIC
    Code:
      stack=1, locals=1, args_size=1
         0: aload_0
         1: invokespecial #58                 // Method java/lang/Object."<init>":()V
         4: return
      LineNumberTable:
        line 116: 0
      LocalVariableTable:
        Start  Length  Slot  Name   Signature
            0       5     0  this   Lscala/compat/java8/PrimitiveIteratorConverters$RichIteratorToPrimitives$;
}
InnerClasses:
  public static final #10= #7 of #9;      // RichIteratorToPrimitives=class scala/compat/java8/PrimitiveIteratorConverters$RichIteratorToPrimitives of class scala/compat/java8/PrimitiveIteratorConverters
  public static #11= #2 of #9;            // RichIteratorToPrimitives$=class scala/compat/java8/PrimitiveIteratorConverters$RichIteratorToPrimitives$ of class scala/compat/java8/PrimitiveIteratorConverters
  public static abstract #14= #13 of #9;  // SpecializerOfIterators=class scala/compat/java8/PrimitiveIteratorConverters$SpecializerOfIterators of class scala/compat/java8/PrimitiveIteratorConverters
SourceFile: "PrimitiveIteratorConversions.scala"
  ScalaInlineInfo: length = 0x18 (unknown attribute)
   01 01 00 04 00 13 00 12 01 00 18 00 19 01 00 2B
   00 2C 01 00 24 00 25 01
  Scala: length = 0x0 (unknown attribute)

