Classfile /Users/mw/Projects/slang-braindump/.jar/jar11/assemble/slang-braindump/assemble/content/scala/compat/java8/Priority1FunctionConverters.class
  Last modified May 29, 2022; size 8975 bytes
  SHA-256 checksum 10824ebea1d5853c5e5e21082d49b9859533561f793675567e4e3eee90aecdd7
  Compiled from "FunctionConverters.scala"
public interface scala.compat.java8.Priority1FunctionConverters extends scala.compat.java8.Priority2FunctionConverters
  minor version: 0
  major version: 52
  flags: (0x0601) ACC_PUBLIC, ACC_INTERFACE, ACC_ABSTRACT
  this_class: #2                          // scala/compat/java8/Priority1FunctionConverters
  super_class: #4                         // java/lang/Object
  interfaces: 1, fields: 0, methods: 29, attributes: 4
Constant pool:
    #1 = Utf8               scala/compat/java8/Priority1FunctionConverters
    #2 = Class              #1            // scala/compat/java8/Priority1FunctionConverters
    #3 = Utf8               java/lang/Object
    #4 = Class              #3            // java/lang/Object
    #5 = Utf8               scala/compat/java8/Priority2FunctionConverters
    #6 = Class              #5            // scala/compat/java8/Priority2FunctionConverters
    #7 = Utf8               FunctionConverters.scala
    #8 = Utf8               Lscala/reflect/ScalaSignature;
    #9 = Utf8               bytes
   #10 = Utf8               \u0006\u0005\t=ba\u0002\t\u0012!\u0003\r\t\u0001\u0007\u0005\u0006C\u0001!\tA\t\u0005\u0006M\u0001!\u0019a\n\u0005\u0006%\u0002!\u0019a\u0015\u0005\u0006?\u0002!\u0019\u0001\u0019\u0005\u0006k\u0002!\u0019A\u001e\u0005\b\u0003#\u0001A1AA\n\u0011\u001d\t9\u0004\u0001C\u0002\u0003sAq!a\u0016\u0001\t\u0007\tI\u0006C\u0004\u0002x\u0001!\u0019!!\u001f\t\u000f\u0005]\u0005\u0001b\u0001\u0002\u001a\"9\u00111\u0017\u0001\u0005\u0004\u0005U\u0006bBAg\u0001\u0011\r\u0011q\u001a\u0005\b\u0003G\u0004A1AAs\u0011\u001d\tI\u0010\u0001C\u0002\u0003wDqAa\u0004\u0001\t\u0007\u0011\tBA\u000eQe&|\'/\u001b;zc\u0019+hn\u0019;j_:\u001cuN\u001c<feR,\'o\u001d\u0006\u0003%M\tQA[1wCbR!\u0001F\u000b\u0002\r\r|W\u000e]1u\u0015\u00051\u0012!B:dC2\f7\u0001A\n\u0004\u0001ei\u0002C\u0001\u000e\u001c\u001b\u0005)\u0012B\u0001\u000f\u0016\u0005\u0019\te.\u001f*fMB\u0011adH\u0007\u0002#%\u0011\u0001%\u0005\u0002\u001c!JLwN]5usJ2UO\\2uS>t7i\u001c8wKJ$XM]:\u0002\r\u0011Jg.\u001b;%)\u0005\u0019\u0003C\u0001\u000e%\u0013\t)SC\u0001\u0003V]&$\u0018AG3oe&\u001c\u0007.Q:KCZ\f\')\u001b8bef|\u0005/\u001a:bi>\u0014X\u0003\u0002\u00153\u0003\u001e#\"!K%\u0015\u0007)Z4\tE\u0002,]Aj\u0011\u0001\f\u0006\u0003[E\taCZ;oGRLwN\\\"p]Z,\'\u000f^3s\u00136\u0004Hn]\u0005\u0003_1\u0012QDU5dQ\u001a+hn\u0019;j_:\u0014\u0014i\u001d\"j]\u0006\u0014\u0018p\u00149fe\u0006$xN\u001d\t\u0003cIb\u0001\u0001B\u00034\u0005\t\u0007AGA\u0001U#\t)\u0004\b\u0005\u0002\u001bm%\u0011q\'\u0006\u0002\b\u001d>$\b.\u001b8h!\tQ\u0012(\u0003\u0002;+\t\u0019\u0011I\\=\t\u000bq\u0012\u00019A\u001f\u0002\t\u00154\u0018)\r\t\u00055y\u0002\u0005\'\u0003\u0002@+\taA%Z9%G>dwN\u001c\u0013fcB\u0011\u0011\'\u0011\u0003\u0006\u0005\n\u0011\r\u0001\u000e\u0002\u0003\u0003FBQ\u0001\u0012\u0002A\u0004\u0015\u000bA!\u001a<BeA!!D\u0010$1!\t\tt\tB\u0003I\u0005\t\u0007AG\u0001\u0002Be!)!J\u0001a\u0001\u0017\u0006\u00111O\u001a\t\u000651\u0003\u0004IR\u0005\u0003\u001bV\u0011\u0011BR;oGRLwN\u001c\u001a)\u0005\ty\u0005C\u0001\u000eQ\u0013\t\tVC\u0001\u0004j]2Lg.Z\u0001\u0015K:\u0014\u0018n\u00195Bg*\u000bg/Y\"p]N,X.\u001a:\u0016\u0005QKFCA+[!\rYc\u000bW\u0005\u0003/2\u0012qCU5dQ\u001a+hn\u0019;j_:\f\u0014i]\"p]N,X.\u001a:\u0011\u0005EJF!B\u001a\u0004\u0005\u0004!\u0004\"\u0002&\u0004\u0001\u0004Y\u0006\u0003\u0002\u000e]1\u000eJ!!X\u000b\u0003\u0013\u0019+hn\u0019;j_:\f\u0004FA\u0002P\u0003i)gN]5dQ\u0006\u001b(*\u0019<b\t>,(\r\\3Gk:\u001cG/[8o+\r\tWn\u001a\u000b\u0003EJ$\"aY5\u0011\u0007-\"g-\u0003\u0002fY\ti\"+[2i\rVt7\r^5p]F\n5\u000fR8vE2,g)\u001e8di&|g\u000e\u0005\u00022O\u0012)\u0001\u000e\u0002b\u0001i\t\t!\u000bC\u0003k\t\u0001\u000f1.\u0001\u0003fm\u0006\u0003\u0004\u0003\u0002\u000e?Y>\u0004\"!M7\u0005\u000b9$!\u0019\u0001\u001b\u0003\u0005\u0005\u0003\u0004C\u0001\u000eq\u0013\t\tXC\u0001\u0004E_V\u0014G.\u001a\u0005\u0006\u0015\u0012\u0001\ra\u001d\t\u00055qcg\r\u000b\u0002\u0005\u001f\u00069RM\u001c:jG\"\f5OS1wC&sGOR;oGRLwN\\\u000b\u0005o\u0006\rQ\u0010F\u0002y\u0003\u0017!\"!\u001f@\u0011\u0007-RH0\u0003\u0002|Y\tQ\"+[2i\rVt7\r^5p]F\n5/\u00138u\rVt7\r^5p]B\u0011\u0011\' \u0003\u0006Q\u0016\u0011\r\u0001\u000e\u0005\u0006U\u0016\u0001\u001da \t\u00075y\n\t!!\u0002\u0011\u0007E\n\u0019\u0001B\u0003o\u000b\t\u0007A\u0007E\u0002\u001b\u0003\u000fI1!!\u0003\u0016\u0005\rIe\u000e\u001e\u0005\u0007\u0015\u0016\u0001\r!!\u0004\u0011\u000bia\u0016\u0011\u0001?)\u0005\u0015y\u0015\u0001G3oe&\u001c\u0007.Q:KCZ\fGj\u001c8h\rVt7\r^5p]V1\u0011QCA\u0015\u0003C!B!a\u0006\u00022Q!\u0011\u0011DA\u0012!\u0015Y\u00131DA\u0010\u0013\r\ti\u0002\f\u0002\u001c%&\u001c\u0007NR;oGRLwN\\\u0019Bg2{gn\u001a$v]\u000e$\u0018n\u001c8\u0011\u0007E\n\t\u0003B\u0003i\r\t\u0007A\u0007\u0003\u0004k\r\u0001\u000f\u0011Q\u0005\t\u00075y\n9#a\u000b\u0011\u0007E\nI\u0003B\u0003o\r\t\u0007A\u0007E\u0002\u001b\u0003[I1!a\f\u0016\u0005\u0011auN\\4\t\r)3\u0001\u0019AA\u001a!\u0019QB,a\n\u0002 !\u0012aaT\u0001\u001eK:\u0014\u0018n\u00195Bg*\u000bg/Y(cU\u0012{WO\u00197f\u0007>t7/^7feV1\u00111HA$\u0003\u001f\"B!!\u0010\u0002RQ!\u0011qHA%!\u0015Y\u0013\u0011IA#\u0013\r\t\u0019\u0005\f\u0002!%&\u001c\u0007NR;oGRLwN\u001c\u001aBg>\u0013\'\u000eR8vE2,7i\u001c8tk6,\'\u000fE\u00022\u0003\u000f\"QaM\u0004C\u0002QBa\u0001P\u0004A\u0004\u0005-\u0003#\u0002\u000e?\u0003\u001bz\u0007cA\u0019\u0002P\u0011)!i\u0002b\u0001i!1!j\u0002a\u0001\u0003\'\u0002rA\u0007\'\u0002F\u000553\u0005\u000b\u0002\b\u001f\u0006QRM\u001c:jG\"\f5OS1wC>\u0013\'.\u00138u\u0007>t7/^7feV1\u00111LA4\u0003_\"B!!\u0018\u0002rQ!\u0011qLA5!\u0015Y\u0013\u0011MA3\u0013\r\t\u0019\u0007\f\u0002\u001e%&\u001c\u0007NR;oGRLwN\u001c\u001aBg>\u0013\'.\u00138u\u0007>t7/^7feB\u0019\u0011\'a\u001a\u0005\u000bMB!\u0019\u0001\u001b\t\rqB\u00019AA6!\u0019Qb(!\u001c\u0002\u0006A\u0019\u0011\'a\u001c\u0005\u000b\tC!\u0019\u0001\u001b\t\r)C\u0001\u0019AA:!\u001dQB*!\u001a\u0002n\rB#\u0001C(\u00027\u0015t\'/[2i\u0003NT\u0015M^1PE*duN\\4D_:\u001cX/\\3s+\u0019\tY(a\"\u0002\u0010R!\u0011QPAI)\u0011\ty(!#\u0011\u000b-\n\t)!\"\n\u0007\u0005\rEF\u0001\u0010SS\u000eDg)\u001e8di&|gNM!t\u001f\nTGj\u001c8h\u0007>t7/^7feB\u0019\u0011\'a\"\u0005\u000bMJ!\u0019\u0001\u001b\t\rqJ\u00019AAF!\u0019Qb(!$\u0002,A\u0019\u0011\'a$\u0005\u000b\tK!\u0019\u0001\u001b\t\r)K\u0001\u0019AAJ!\u001dQB*!\"\u0002\u000e\u000eB#!C(\u0002+\u0015t\'/[2i\u0003NT\u0015M^1Qe\u0016$\u0017nY1uKV!\u00111TAS)\u0011\ti*a*\u0011\u000b-\ny*a)\n\u0007\u0005\u0005FF\u0001\rSS\u000eDg)\u001e8di&|g.M!t!J,G-[2bi\u0016\u00042!MAS\t\u0015\u0019$B1\u00015\u0011\u0019Q%\u00021\u0001\u0002*B1!\u0004XAR\u0003W\u00032AGAW\u0013\r\ty+\u0006\u0002\b\u0005>|G.Z1oQ\tQq*\u0001\u000bf]JL7\r[!t\u0015\u00064\u0018mU;qa2LWM]\u000b\u0005\u0003o\u000b\t\r\u0006\u0003\u0002:\u0006\r\u0007#B\u0016\u0002<\u0006}\u0016bAA_Y\t9\"+[2i\rVt7\r^5p]B\n5oU;qa2LWM\u001d\t\u0004c\u0005\u0005G!B\u001a\f\u0005\u0004!\u0004B\u0002&\f\u0001\u0004\t)\rE\u0003\u001b\u0003\u000f\fy,C\u0002\u0002JV\u0011\u0011BR;oGRLwN\u001c\u0019)\u0005-y\u0015\u0001H3oe&\u001c\u0007.Q:KCZ\fGk\u001c#pk\ndWMR;oGRLwN\\\u000b\u0005\u0003#\fY\u000e\u0006\u0003\u0002T\u0006u\u0007#B\u0016\u0002V\u0006e\u0017bAAlY\ty\"+[2i\rVt7\r^5p]F\n5\u000fV8E_V\u0014G.\u001a$v]\u000e$\u0018n\u001c8\u0011\u0007E\nY\u000eB\u00034\u0019\t\u0007A\u0007\u0003\u0004K\u0019\u0001\u0007\u0011q\u001c\t\u00065q\u000bIn\u001c\u0015\u0003\u0019=\u000b\u0011$\u001a8sS\u000eD\u0017i\u001d&bm\u0006$v.\u00138u\rVt7\r^5p]V!\u0011q]Ay)\u0011\tI/a=\u0011\u000b-\nY/a<\n\u0007\u00055HF\u0001\u000fSS\u000eDg)\u001e8di&|g.M!t)>Le\u000e\u001e$v]\u000e$\u0018n\u001c8\u0011\u0007E\n\t\u0010B\u00034\u001b\t\u0007A\u0007\u0003\u0004K\u001b\u0001\u0007\u0011Q\u001f\t\u00075q\u000by/!\u0002)\u00055y\u0015AG3oe&\u001c\u0007.Q:KCZ\fGk\u001c\'p]\u001e4UO\\2uS>tW\u0003BA\u007f\u0005\u000f!B!a@\u0003\nA)1F!\u0001\u0003\u0006%\u0019!1\u0001\u0017\u0003;IK7\r\u001b$v]\u000e$\u0018n\u001c82\u0003N$v\u000eT8oO\u001a+hn\u0019;j_:\u00042!\rB\u0004\t\u0015\u0019dB1\u00015\u0011\u0019Qe\u00021\u0001\u0003\fA1!\u0004\u0018B\u0003\u0003WA#AD(\u00023\u0015t\'/[2i\u0003NT\u0015M^1V]\u0006\u0014\u0018p\u00149fe\u0006$xN]\u000b\u0007\u0005\'\u0011yBa\n\u0015\t\tU!\u0011\u0006\u000b\u0005\u0005/\u0011\t\u0003E\u0003,\u00053\u0011i\"C\u0002\u0003\u001c1\u0012ADU5dQ\u001a+hn\u0019;j_:\f\u0014i]+oCJLx\n]3sCR|\'\u000fE\u00022\u0005?!QaM\bC\u0002QBa\u0001P\bA\u0004\t\r\u0002C\u0002\u000e?\u0005K\u0011i\u0002E\u00022\u0005O!QAQ\bC\u0002QBaAS\bA\u0002\t-\u0002C\u0002\u000e]\u0005;\u0011)\u0003\u000b\u0002\u0010\u001f\u0002
   #11 = Utf8               enrichAsJavaBinaryOperator$
   #12 = Utf8               (Lscala/compat/java8/Priority1FunctionConverters;Lscala/Function2;Lscala/$eq$colon$eq;Lscala/$eq$colon$eq;)Lscala/Function2;
   #13 = Utf8               $this
   #14 = Utf8               sf
   #15 = Utf8               evA1
   #16 = Utf8               evA2
   #17 = Utf8               enrichAsJavaBinaryOperator
   #18 = Utf8               (Lscala/Function2;Lscala/$eq$colon$eq;Lscala/$eq$colon$eq;)Lscala/Function2;
   #19 = NameAndType        #17:#18       // enrichAsJavaBinaryOperator:(Lscala/Function2;Lscala/$eq$colon$eq;Lscala/$eq$colon$eq;)Lscala/Function2;
   #20 = InterfaceMethodref #2.#19        // scala/compat/java8/Priority1FunctionConverters.enrichAsJavaBinaryOperator:(Lscala/Function2;Lscala/$eq$colon$eq;Lscala/$eq$colon$eq;)Lscala/Function2;
   #21 = Utf8               Lscala/compat/java8/Priority1FunctionConverters;
   #22 = Utf8               Lscala/Function2;
   #23 = Utf8               Lscala/$eq$colon$eq;
   #24 = Utf8               <T:Ljava/lang/Object;A1:Ljava/lang/Object;A2:Ljava/lang/Object;>(Lscala/Function2<TT;TA1;TA2;>;Lscala/$eq$colon$eq<TA1;TT;>;Lscala/$eq$colon$eq<TA2;TT;>;)Lscala/Function2<TT;TT;TT;>;
   #25 = Utf8               this
   #26 = Utf8               enrichAsJavaConsumer$
   #27 = Utf8               (Lscala/compat/java8/Priority1FunctionConverters;Lscala/Function1;)Lscala/Function1;
   #28 = Utf8               enrichAsJavaConsumer
   #29 = Utf8               (Lscala/Function1;)Lscala/Function1;
   #30 = NameAndType        #28:#29       // enrichAsJavaConsumer:(Lscala/Function1;)Lscala/Function1;
   #31 = InterfaceMethodref #2.#30        // scala/compat/java8/Priority1FunctionConverters.enrichAsJavaConsumer:(Lscala/Function1;)Lscala/Function1;
   #32 = Utf8               Lscala/Function1;
   #33 = Utf8               <T:Ljava/lang/Object;>(Lscala/Function1<TT;Lscala/runtime/BoxedUnit;>;)Lscala/Function1<TT;Lscala/runtime/BoxedUnit;>;
   #34 = Utf8               enrichAsJavaDoubleFunction$
   #35 = Utf8               (Lscala/compat/java8/Priority1FunctionConverters;Lscala/Function1;Lscala/$eq$colon$eq;)Lscala/Function1;
   #36 = Utf8               evA0
   #37 = Utf8               enrichAsJavaDoubleFunction
   #38 = Utf8               (Lscala/Function1;Lscala/$eq$colon$eq;)Lscala/Function1;
   #39 = NameAndType        #37:#38       // enrichAsJavaDoubleFunction:(Lscala/Function1;Lscala/$eq$colon$eq;)Lscala/Function1;
   #40 = InterfaceMethodref #2.#39        // scala/compat/java8/Priority1FunctionConverters.enrichAsJavaDoubleFunction:(Lscala/Function1;Lscala/$eq$colon$eq;)Lscala/Function1;
   #41 = Utf8               <A0:Ljava/lang/Object;R:Ljava/lang/Object;>(Lscala/Function1<TA0;TR;>;Lscala/$eq$colon$eq<TA0;Ljava/lang/Object;>;)Lscala/Function1<Ljava/lang/Object;TR;>;
   #42 = Utf8               enrichAsJavaIntFunction$
   #43 = Utf8               enrichAsJavaIntFunction
   #44 = NameAndType        #43:#38       // enrichAsJavaIntFunction:(Lscala/Function1;Lscala/$eq$colon$eq;)Lscala/Function1;
   #45 = InterfaceMethodref #2.#44        // scala/compat/java8/Priority1FunctionConverters.enrichAsJavaIntFunction:(Lscala/Function1;Lscala/$eq$colon$eq;)Lscala/Function1;
   #46 = Utf8               enrichAsJavaLongFunction$
   #47 = Utf8               enrichAsJavaLongFunction
   #48 = NameAndType        #47:#38       // enrichAsJavaLongFunction:(Lscala/Function1;Lscala/$eq$colon$eq;)Lscala/Function1;
   #49 = InterfaceMethodref #2.#48        // scala/compat/java8/Priority1FunctionConverters.enrichAsJavaLongFunction:(Lscala/Function1;Lscala/$eq$colon$eq;)Lscala/Function1;
   #50 = Utf8               enrichAsJavaObjDoubleConsumer$
   #51 = Utf8               (Lscala/compat/java8/Priority1FunctionConverters;Lscala/Function2;Lscala/$eq$colon$eq;)Lscala/Function2;
   #52 = Utf8               enrichAsJavaObjDoubleConsumer
   #53 = Utf8               (Lscala/Function2;Lscala/$eq$colon$eq;)Lscala/Function2;
   #54 = NameAndType        #52:#53       // enrichAsJavaObjDoubleConsumer:(Lscala/Function2;Lscala/$eq$colon$eq;)Lscala/Function2;
   #55 = InterfaceMethodref #2.#54        // scala/compat/java8/Priority1FunctionConverters.enrichAsJavaObjDoubleConsumer:(Lscala/Function2;Lscala/$eq$colon$eq;)Lscala/Function2;
   #56 = Utf8               <T:Ljava/lang/Object;A1:Ljava/lang/Object;>(Lscala/Function2<TT;TA1;Lscala/runtime/BoxedUnit;>;Lscala/$eq$colon$eq<TA1;Ljava/lang/Object;>;)Lscala/Function2<TT;Ljava/lang/Object;Lscala/runtime/BoxedUnit;>;
   #57 = Utf8               enrichAsJavaObjIntConsumer$
   #58 = Utf8               enrichAsJavaObjIntConsumer
   #59 = NameAndType        #58:#53       // enrichAsJavaObjIntConsumer:(Lscala/Function2;Lscala/$eq$colon$eq;)Lscala/Function2;
   #60 = InterfaceMethodref #2.#59        // scala/compat/java8/Priority1FunctionConverters.enrichAsJavaObjIntConsumer:(Lscala/Function2;Lscala/$eq$colon$eq;)Lscala/Function2;
   #61 = Utf8               enrichAsJavaObjLongConsumer$
   #62 = Utf8               enrichAsJavaObjLongConsumer
   #63 = NameAndType        #62:#53       // enrichAsJavaObjLongConsumer:(Lscala/Function2;Lscala/$eq$colon$eq;)Lscala/Function2;
   #64 = InterfaceMethodref #2.#63        // scala/compat/java8/Priority1FunctionConverters.enrichAsJavaObjLongConsumer:(Lscala/Function2;Lscala/$eq$colon$eq;)Lscala/Function2;
   #65 = Utf8               enrichAsJavaPredicate$
   #66 = Utf8               enrichAsJavaPredicate
   #67 = NameAndType        #66:#29       // enrichAsJavaPredicate:(Lscala/Function1;)Lscala/Function1;
   #68 = InterfaceMethodref #2.#67        // scala/compat/java8/Priority1FunctionConverters.enrichAsJavaPredicate:(Lscala/Function1;)Lscala/Function1;
   #69 = Utf8               <T:Ljava/lang/Object;>(Lscala/Function1<TT;Ljava/lang/Object;>;)Lscala/Function1<TT;Ljava/lang/Object;>;
   #70 = Utf8               enrichAsJavaSupplier$
   #71 = Utf8               (Lscala/compat/java8/Priority1FunctionConverters;Lscala/Function0;)Lscala/Function0;
   #72 = Utf8               enrichAsJavaSupplier
   #73 = Utf8               (Lscala/Function0;)Lscala/Function0;
   #74 = NameAndType        #72:#73       // enrichAsJavaSupplier:(Lscala/Function0;)Lscala/Function0;
   #75 = InterfaceMethodref #2.#74        // scala/compat/java8/Priority1FunctionConverters.enrichAsJavaSupplier:(Lscala/Function0;)Lscala/Function0;
   #76 = Utf8               Lscala/Function0;
   #77 = Utf8               <T:Ljava/lang/Object;>(Lscala/Function0<TT;>;)Lscala/Function0<TT;>;
   #78 = Utf8               enrichAsJavaToDoubleFunction$
   #79 = Utf8               enrichAsJavaToDoubleFunction
   #80 = NameAndType        #79:#29       // enrichAsJavaToDoubleFunction:(Lscala/Function1;)Lscala/Function1;
   #81 = InterfaceMethodref #2.#80        // scala/compat/java8/Priority1FunctionConverters.enrichAsJavaToDoubleFunction:(Lscala/Function1;)Lscala/Function1;
   #82 = Utf8               enrichAsJavaToIntFunction$
   #83 = Utf8               enrichAsJavaToIntFunction
   #84 = NameAndType        #83:#29       // enrichAsJavaToIntFunction:(Lscala/Function1;)Lscala/Function1;
   #85 = InterfaceMethodref #2.#84        // scala/compat/java8/Priority1FunctionConverters.enrichAsJavaToIntFunction:(Lscala/Function1;)Lscala/Function1;
   #86 = Utf8               enrichAsJavaToLongFunction$
   #87 = Utf8               enrichAsJavaToLongFunction
   #88 = NameAndType        #87:#29       // enrichAsJavaToLongFunction:(Lscala/Function1;)Lscala/Function1;
   #89 = InterfaceMethodref #2.#88        // scala/compat/java8/Priority1FunctionConverters.enrichAsJavaToLongFunction:(Lscala/Function1;)Lscala/Function1;
   #90 = Utf8               enrichAsJavaUnaryOperator$
   #91 = Utf8               enrichAsJavaUnaryOperator
   #92 = NameAndType        #91:#38       // enrichAsJavaUnaryOperator:(Lscala/Function1;Lscala/$eq$colon$eq;)Lscala/Function1;
   #93 = InterfaceMethodref #2.#92        // scala/compat/java8/Priority1FunctionConverters.enrichAsJavaUnaryOperator:(Lscala/Function1;Lscala/$eq$colon$eq;)Lscala/Function1;
   #94 = Utf8               <T:Ljava/lang/Object;A1:Ljava/lang/Object;>(Lscala/Function1<TT;TA1;>;Lscala/$eq$colon$eq<TA1;TT;>;)Lscala/Function1<TT;TT;>;
   #95 = Utf8               $init$
   #96 = Utf8               (Lscala/compat/java8/Priority1FunctionConverters;)V
   #97 = Utf8               Code
   #98 = Utf8               LineNumberTable
   #99 = Utf8               LocalVariableTable
  #100 = Utf8               MethodParameters
  #101 = Utf8               Signature
  #102 = Utf8               SourceFile
  #103 = Utf8               RuntimeVisibleAnnotations
  #104 = Utf8               ScalaInlineInfo
  #105 = Utf8               ScalaSig
{
  public static scala.Function2 enrichAsJavaBinaryOperator$(scala.compat.java8.Priority1FunctionConverters, scala.Function2, scala.$eq$colon$eq, scala.$eq$colon$eq);
    descriptor: (Lscala/compat/java8/Priority1FunctionConverters;Lscala/Function2;Lscala/$eq$colon$eq;Lscala/$eq$colon$eq;)Lscala/Function2;
    flags: (0x1009) ACC_PUBLIC, ACC_STATIC, ACC_SYNTHETIC
    Code:
      stack=4, locals=4, args_size=4
         0: aload_0
         1: aload_1
         2: aload_2
         3: aload_3
         4: invokespecial #20                 // InterfaceMethod enrichAsJavaBinaryOperator:(Lscala/Function2;Lscala/$eq$colon$eq;Lscala/$eq$colon$eq;)Lscala/Function2;
         7: areturn
      LineNumberTable:
        line 774: 0
      LocalVariableTable:
        Start  Length  Slot  Name   Signature
            0       8     0 $this   Lscala/compat/java8/Priority1FunctionConverters;
            0       8     1    sf   Lscala/Function2;
            0       8     2  evA1   Lscala/$eq$colon$eq;
            0       8     3  evA2   Lscala/$eq$colon$eq;
    MethodParameters:
      Name                           Flags
      $this                          final synthetic
      sf                             final
      evA1                           final
      evA2                           final

  public default <T extends java.lang.Object, A1 extends java.lang.Object, A2 extends java.lang.Object> scala.Function2<T, T, T> enrichAsJavaBinaryOperator(scala.Function2<T, A1, A2>, scala.$eq$colon$eq<A1, T>, scala.$eq$colon$eq<A2, T>);
    descriptor: (Lscala/Function2;Lscala/$eq$colon$eq;Lscala/$eq$colon$eq;)Lscala/Function2;
    flags: (0x0001) ACC_PUBLIC
    Code:
      stack=1, locals=4, args_size=4
         0: aload_1
         1: areturn
      LineNumberTable:
        line 774: 0
      LocalVariableTable:
        Start  Length  Slot  Name   Signature
            0       2     0  this   Lscala/compat/java8/Priority1FunctionConverters;
            0       2     1    sf   Lscala/Function2;
            0       2     2  evA1   Lscala/$eq$colon$eq;
            0       2     3  evA2   Lscala/$eq$colon$eq;
    Signature: #24                          // <T:Ljava/lang/Object;A1:Ljava/lang/Object;A2:Ljava/lang/Object;>(Lscala/Function2<TT;TA1;TA2;>;Lscala/$eq$colon$eq<TA1;TT;>;Lscala/$eq$colon$eq<TA2;TT;>;)Lscala/Function2<TT;TT;TT;>;
    MethodParameters:
      Name                           Flags
      sf                             final
      evA1                           final
      evA2                           final

  public static scala.Function1 enrichAsJavaConsumer$(scala.compat.java8.Priority1FunctionConverters, scala.Function1);
    descriptor: (Lscala/compat/java8/Priority1FunctionConverters;Lscala/Function1;)Lscala/Function1;
    flags: (0x1009) ACC_PUBLIC, ACC_STATIC, ACC_SYNTHETIC
    Code:
      stack=2, locals=2, args_size=2
         0: aload_0
         1: aload_1
         2: invokespecial #31                 // InterfaceMethod enrichAsJavaConsumer:(Lscala/Function1;)Lscala/Function1;
         5: areturn
      LineNumberTable:
        line 776: 0
      LocalVariableTable:
        Start  Length  Slot  Name   Signature
            0       6     0 $this   Lscala/compat/java8/Priority1FunctionConverters;
            0       6     1    sf   Lscala/Function1;
    MethodParameters:
      Name                           Flags
      $this                          final synthetic
      sf                             final

  public default <T extends java.lang.Object> scala.Function1<T, scala.runtime.BoxedUnit> enrichAsJavaConsumer(scala.Function1<T, scala.runtime.BoxedUnit>);
    descriptor: (Lscala/Function1;)Lscala/Function1;
    flags: (0x0001) ACC_PUBLIC
    Code:
      stack=1, locals=2, args_size=2
         0: aload_1
         1: areturn
      LineNumberTable:
        line 776: 0
      LocalVariableTable:
        Start  Length  Slot  Name   Signature
            0       2     0  this   Lscala/compat/java8/Priority1FunctionConverters;
            0       2     1    sf   Lscala/Function1;
    Signature: #33                          // <T:Ljava/lang/Object;>(Lscala/Function1<TT;Lscala/runtime/BoxedUnit;>;)Lscala/Function1<TT;Lscala/runtime/BoxedUnit;>;
    MethodParameters:
      Name                           Flags
      sf                             final

  public static scala.Function1 enrichAsJavaDoubleFunction$(scala.compat.java8.Priority1FunctionConverters, scala.Function1, scala.$eq$colon$eq);
    descriptor: (Lscala/compat/java8/Priority1FunctionConverters;Lscala/Function1;Lscala/$eq$colon$eq;)Lscala/Function1;
    flags: (0x1009) ACC_PUBLIC, ACC_STATIC, ACC_SYNTHETIC
    Code:
      stack=3, locals=3, args_size=3
         0: aload_0
         1: aload_1
         2: aload_2
         3: invokespecial #40                 // InterfaceMethod enrichAsJavaDoubleFunction:(Lscala/Function1;Lscala/$eq$colon$eq;)Lscala/Function1;
         6: areturn
      LineNumberTable:
        line 778: 0
      LocalVariableTable:
        Start  Length  Slot  Name   Signature
            0       7     0 $this   Lscala/compat/java8/Priority1FunctionConverters;
            0       7     1    sf   Lscala/Function1;
            0       7     2  evA0   Lscala/$eq$colon$eq;
    MethodParameters:
      Name                           Flags
      $this                          final synthetic
      sf                             final
      evA0                           final

  public default <A0 extends java.lang.Object, R extends java.lang.Object> scala.Function1<java.lang.Object, R> enrichAsJavaDoubleFunction(scala.Function1<A0, R>, scala.$eq$colon$eq<A0, java.lang.Object>);
    descriptor: (Lscala/Function1;Lscala/$eq$colon$eq;)Lscala/Function1;
    flags: (0x0001) ACC_PUBLIC
    Code:
      stack=1, locals=3, args_size=3
         0: aload_1
         1: areturn
      LineNumberTable:
        line 778: 0
      LocalVariableTable:
        Start  Length  Slot  Name   Signature
            0       2     0  this   Lscala/compat/java8/Priority1FunctionConverters;
            0       2     1    sf   Lscala/Function1;
            0       2     2  evA0   Lscala/$eq$colon$eq;
    Signature: #41                          // <A0:Ljava/lang/Object;R:Ljava/lang/Object;>(Lscala/Function1<TA0;TR;>;Lscala/$eq$colon$eq<TA0;Ljava/lang/Object;>;)Lscala/Function1<Ljava/lang/Object;TR;>;
    MethodParameters:
      Name                           Flags
      sf                             final
      evA0                           final

  public static scala.Function1 enrichAsJavaIntFunction$(scala.compat.java8.Priority1FunctionConverters, scala.Function1, scala.$eq$colon$eq);
    descriptor: (Lscala/compat/java8/Priority1FunctionConverters;Lscala/Function1;Lscala/$eq$colon$eq;)Lscala/Function1;
    flags: (0x1009) ACC_PUBLIC, ACC_STATIC, ACC_SYNTHETIC
    Code:
      stack=3, locals=3, args_size=3
         0: aload_0
         1: aload_1
         2: aload_2
         3: invokespecial #45                 // InterfaceMethod enrichAsJavaIntFunction:(Lscala/Function1;Lscala/$eq$colon$eq;)Lscala/Function1;
         6: areturn
      LineNumberTable:
        line 780: 0
      LocalVariableTable:
        Start  Length  Slot  Name   Signature
            0       7     0 $this   Lscala/compat/java8/Priority1FunctionConverters;
            0       7     1    sf   Lscala/Function1;
            0       7     2  evA0   Lscala/$eq$colon$eq;
    MethodParameters:
      Name                           Flags
      $this                          final synthetic
      sf                             final
      evA0                           final

  public default <A0 extends java.lang.Object, R extends java.lang.Object> scala.Function1<java.lang.Object, R> enrichAsJavaIntFunction(scala.Function1<A0, R>, scala.$eq$colon$eq<A0, java.lang.Object>);
    descriptor: (Lscala/Function1;Lscala/$eq$colon$eq;)Lscala/Function1;
    flags: (0x0001) ACC_PUBLIC
    Code:
      stack=1, locals=3, args_size=3
         0: aload_1
         1: areturn
      LineNumberTable:
        line 780: 0
      LocalVariableTable:
        Start  Length  Slot  Name   Signature
            0       2     0  this   Lscala/compat/java8/Priority1FunctionConverters;
            0       2     1    sf   Lscala/Function1;
            0       2     2  evA0   Lscala/$eq$colon$eq;
    Signature: #41                          // <A0:Ljava/lang/Object;R:Ljava/lang/Object;>(Lscala/Function1<TA0;TR;>;Lscala/$eq$colon$eq<TA0;Ljava/lang/Object;>;)Lscala/Function1<Ljava/lang/Object;TR;>;
    MethodParameters:
      Name                           Flags
      sf                             final
      evA0                           final

  public static scala.Function1 enrichAsJavaLongFunction$(scala.compat.java8.Priority1FunctionConverters, scala.Function1, scala.$eq$colon$eq);
    descriptor: (Lscala/compat/java8/Priority1FunctionConverters;Lscala/Function1;Lscala/$eq$colon$eq;)Lscala/Function1;
    flags: (0x1009) ACC_PUBLIC, ACC_STATIC, ACC_SYNTHETIC
    Code:
      stack=3, locals=3, args_size=3
         0: aload_0
         1: aload_1
         2: aload_2
         3: invokespecial #49                 // InterfaceMethod enrichAsJavaLongFunction:(Lscala/Function1;Lscala/$eq$colon$eq;)Lscala/Function1;
         6: areturn
      LineNumberTable:
        line 782: 0
      LocalVariableTable:
        Start  Length  Slot  Name   Signature
            0       7     0 $this   Lscala/compat/java8/Priority1FunctionConverters;
            0       7     1    sf   Lscala/Function1;
            0       7     2  evA0   Lscala/$eq$colon$eq;
    MethodParameters:
      Name                           Flags
      $this                          final synthetic
      sf                             final
      evA0                           final

  public default <A0 extends java.lang.Object, R extends java.lang.Object> scala.Function1<java.lang.Object, R> enrichAsJavaLongFunction(scala.Function1<A0, R>, scala.$eq$colon$eq<A0, java.lang.Object>);
    descriptor: (Lscala/Function1;Lscala/$eq$colon$eq;)Lscala/Function1;
    flags: (0x0001) ACC_PUBLIC
    Code:
      stack=1, locals=3, args_size=3
         0: aload_1
         1: areturn
      LineNumberTable:
        line 782: 0
      LocalVariableTable:
        Start  Length  Slot  Name   Signature
            0       2     0  this   Lscala/compat/java8/Priority1FunctionConverters;
            0       2     1    sf   Lscala/Function1;
            0       2     2  evA0   Lscala/$eq$colon$eq;
    Signature: #41                          // <A0:Ljava/lang/Object;R:Ljava/lang/Object;>(Lscala/Function1<TA0;TR;>;Lscala/$eq$colon$eq<TA0;Ljava/lang/Object;>;)Lscala/Function1<Ljava/lang/Object;TR;>;
    MethodParameters:
      Name                           Flags
      sf                             final
      evA0                           final

  public static scala.Function2 enrichAsJavaObjDoubleConsumer$(scala.compat.java8.Priority1FunctionConverters, scala.Function2, scala.$eq$colon$eq);
    descriptor: (Lscala/compat/java8/Priority1FunctionConverters;Lscala/Function2;Lscala/$eq$colon$eq;)Lscala/Function2;
    flags: (0x1009) ACC_PUBLIC, ACC_STATIC, ACC_SYNTHETIC
    Code:
      stack=3, locals=3, args_size=3
         0: aload_0
         1: aload_1
         2: aload_2
         3: invokespecial #55                 // InterfaceMethod enrichAsJavaObjDoubleConsumer:(Lscala/Function2;Lscala/$eq$colon$eq;)Lscala/Function2;
         6: areturn
      LineNumberTable:
        line 784: 0
      LocalVariableTable:
        Start  Length  Slot  Name   Signature
            0       7     0 $this   Lscala/compat/java8/Priority1FunctionConverters;
            0       7     1    sf   Lscala/Function2;
            0       7     2  evA1   Lscala/$eq$colon$eq;
    MethodParameters:
      Name                           Flags
      $this                          final synthetic
      sf                             final
      evA1                           final

  public default <T extends java.lang.Object, A1 extends java.lang.Object> scala.Function2<T, java.lang.Object, scala.runtime.BoxedUnit> enrichAsJavaObjDoubleConsumer(scala.Function2<T, A1, scala.runtime.BoxedUnit>, scala.$eq$colon$eq<A1, java.lang.Object>);
    descriptor: (Lscala/Function2;Lscala/$eq$colon$eq;)Lscala/Function2;
    flags: (0x0001) ACC_PUBLIC
    Code:
      stack=1, locals=3, args_size=3
         0: aload_1
         1: areturn
      LineNumberTable:
        line 784: 0
      LocalVariableTable:
        Start  Length  Slot  Name   Signature
            0       2     0  this   Lscala/compat/java8/Priority1FunctionConverters;
            0       2     1    sf   Lscala/Function2;
            0       2     2  evA1   Lscala/$eq$colon$eq;
    Signature: #56                          // <T:Ljava/lang/Object;A1:Ljava/lang/Object;>(Lscala/Function2<TT;TA1;Lscala/runtime/BoxedUnit;>;Lscala/$eq$colon$eq<TA1;Ljava/lang/Object;>;)Lscala/Function2<TT;Ljava/lang/Object;Lscala/runtime/BoxedUnit;>;
    MethodParameters:
      Name                           Flags
      sf                             final
      evA1                           final

  public static scala.Function2 enrichAsJavaObjIntConsumer$(scala.compat.java8.Priority1FunctionConverters, scala.Function2, scala.$eq$colon$eq);
    descriptor: (Lscala/compat/java8/Priority1FunctionConverters;Lscala/Function2;Lscala/$eq$colon$eq;)Lscala/Function2;
    flags: (0x1009) ACC_PUBLIC, ACC_STATIC, ACC_SYNTHETIC
    Code:
      stack=3, locals=3, args_size=3
         0: aload_0
         1: aload_1
         2: aload_2
         3: invokespecial #60                 // InterfaceMethod enrichAsJavaObjIntConsumer:(Lscala/Function2;Lscala/$eq$colon$eq;)Lscala/Function2;
         6: areturn
      LineNumberTable:
        line 786: 0
      LocalVariableTable:
        Start  Length  Slot  Name   Signature
            0       7     0 $this   Lscala/compat/java8/Priority1FunctionConverters;
            0       7     1    sf   Lscala/Function2;
            0       7     2  evA1   Lscala/$eq$colon$eq;
    MethodParameters:
      Name                           Flags
      $this                          final synthetic
      sf                             final
      evA1                           final

  public default <T extends java.lang.Object, A1 extends java.lang.Object> scala.Function2<T, java.lang.Object, scala.runtime.BoxedUnit> enrichAsJavaObjIntConsumer(scala.Function2<T, A1, scala.runtime.BoxedUnit>, scala.$eq$colon$eq<A1, java.lang.Object>);
    descriptor: (Lscala/Function2;Lscala/$eq$colon$eq;)Lscala/Function2;
    flags: (0x0001) ACC_PUBLIC
    Code:
      stack=1, locals=3, args_size=3
         0: aload_1
         1: areturn
      LineNumberTable:
        line 786: 0
      LocalVariableTable:
        Start  Length  Slot  Name   Signature
            0       2     0  this   Lscala/compat/java8/Priority1FunctionConverters;
            0       2     1    sf   Lscala/Function2;
            0       2     2  evA1   Lscala/$eq$colon$eq;
    Signature: #56                          // <T:Ljava/lang/Object;A1:Ljava/lang/Object;>(Lscala/Function2<TT;TA1;Lscala/runtime/BoxedUnit;>;Lscala/$eq$colon$eq<TA1;Ljava/lang/Object;>;)Lscala/Function2<TT;Ljava/lang/Object;Lscala/runtime/BoxedUnit;>;
    MethodParameters:
      Name                           Flags
      sf                             final
      evA1                           final

  public static scala.Function2 enrichAsJavaObjLongConsumer$(scala.compat.java8.Priority1FunctionConverters, scala.Function2, scala.$eq$colon$eq);
    descriptor: (Lscala/compat/java8/Priority1FunctionConverters;Lscala/Function2;Lscala/$eq$colon$eq;)Lscala/Function2;
    flags: (0x1009) ACC_PUBLIC, ACC_STATIC, ACC_SYNTHETIC
    Code:
      stack=3, locals=3, args_size=3
         0: aload_0
         1: aload_1
         2: aload_2
         3: invokespecial #64                 // InterfaceMethod enrichAsJavaObjLongConsumer:(Lscala/Function2;Lscala/$eq$colon$eq;)Lscala/Function2;
         6: areturn
      LineNumberTable:
        line 788: 0
      LocalVariableTable:
        Start  Length  Slot  Name   Signature
            0       7     0 $this   Lscala/compat/java8/Priority1FunctionConverters;
            0       7     1    sf   Lscala/Function2;
            0       7     2  evA1   Lscala/$eq$colon$eq;
    MethodParameters:
      Name                           Flags
      $this                          final synthetic
      sf                             final
      evA1                           final

  public default <T extends java.lang.Object, A1 extends java.lang.Object> scala.Function2<T, java.lang.Object, scala.runtime.BoxedUnit> enrichAsJavaObjLongConsumer(scala.Function2<T, A1, scala.runtime.BoxedUnit>, scala.$eq$colon$eq<A1, java.lang.Object>);
    descriptor: (Lscala/Function2;Lscala/$eq$colon$eq;)Lscala/Function2;
    flags: (0x0001) ACC_PUBLIC
    Code:
      stack=1, locals=3, args_size=3
         0: aload_1
         1: areturn
      LineNumberTable:
        line 788: 0
      LocalVariableTable:
        Start  Length  Slot  Name   Signature
            0       2     0  this   Lscala/compat/java8/Priority1FunctionConverters;
            0       2     1    sf   Lscala/Function2;
            0       2     2  evA1   Lscala/$eq$colon$eq;
    Signature: #56                          // <T:Ljava/lang/Object;A1:Ljava/lang/Object;>(Lscala/Function2<TT;TA1;Lscala/runtime/BoxedUnit;>;Lscala/$eq$colon$eq<TA1;Ljava/lang/Object;>;)Lscala/Function2<TT;Ljava/lang/Object;Lscala/runtime/BoxedUnit;>;
    MethodParameters:
      Name                           Flags
      sf                             final
      evA1                           final

  public static scala.Function1 enrichAsJavaPredicate$(scala.compat.java8.Priority1FunctionConverters, scala.Function1);
    descriptor: (Lscala/compat/java8/Priority1FunctionConverters;Lscala/Function1;)Lscala/Function1;
    flags: (0x1009) ACC_PUBLIC, ACC_STATIC, ACC_SYNTHETIC
    Code:
      stack=2, locals=2, args_size=2
         0: aload_0
         1: aload_1
         2: invokespecial #68                 // InterfaceMethod enrichAsJavaPredicate:(Lscala/Function1;)Lscala/Function1;
         5: areturn
      LineNumberTable:
        line 790: 0
      LocalVariableTable:
        Start  Length  Slot  Name   Signature
            0       6     0 $this   Lscala/compat/java8/Priority1FunctionConverters;
            0       6     1    sf   Lscala/Function1;
    MethodParameters:
      Name                           Flags
      $this                          final synthetic
      sf                             final

  public default <T extends java.lang.Object> scala.Function1<T, java.lang.Object> enrichAsJavaPredicate(scala.Function1<T, java.lang.Object>);
    descriptor: (Lscala/Function1;)Lscala/Function1;
    flags: (0x0001) ACC_PUBLIC
    Code:
      stack=1, locals=2, args_size=2
         0: aload_1
         1: areturn
      LineNumberTable:
        line 790: 0
      LocalVariableTable:
        Start  Length  Slot  Name   Signature
            0       2     0  this   Lscala/compat/java8/Priority1FunctionConverters;
            0       2     1    sf   Lscala/Function1;
    Signature: #69                          // <T:Ljava/lang/Object;>(Lscala/Function1<TT;Ljava/lang/Object;>;)Lscala/Function1<TT;Ljava/lang/Object;>;
    MethodParameters:
      Name                           Flags
      sf                             final

  public static scala.Function0 enrichAsJavaSupplier$(scala.compat.java8.Priority1FunctionConverters, scala.Function0);
    descriptor: (Lscala/compat/java8/Priority1FunctionConverters;Lscala/Function0;)Lscala/Function0;
    flags: (0x1009) ACC_PUBLIC, ACC_STATIC, ACC_SYNTHETIC
    Code:
      stack=2, locals=2, args_size=2
         0: aload_0
         1: aload_1
         2: invokespecial #75                 // InterfaceMethod enrichAsJavaSupplier:(Lscala/Function0;)Lscala/Function0;
         5: areturn
      LineNumberTable:
        line 792: 0
      LocalVariableTable:
        Start  Length  Slot  Name   Signature
            0       6     0 $this   Lscala/compat/java8/Priority1FunctionConverters;
            0       6     1    sf   Lscala/Function0;
    MethodParameters:
      Name                           Flags
      $this                          final synthetic
      sf                             final

  public default <T extends java.lang.Object> scala.Function0<T> enrichAsJavaSupplier(scala.Function0<T>);
    descriptor: (Lscala/Function0;)Lscala/Function0;
    flags: (0x0001) ACC_PUBLIC
    Code:
      stack=1, locals=2, args_size=2
         0: aload_1
         1: areturn
      LineNumberTable:
        line 792: 0
      LocalVariableTable:
        Start  Length  Slot  Name   Signature
            0       2     0  this   Lscala/compat/java8/Priority1FunctionConverters;
            0       2     1    sf   Lscala/Function0;
    Signature: #77                          // <T:Ljava/lang/Object;>(Lscala/Function0<TT;>;)Lscala/Function0<TT;>;
    MethodParameters:
      Name                           Flags
      sf                             final

  public static scala.Function1 enrichAsJavaToDoubleFunction$(scala.compat.java8.Priority1FunctionConverters, scala.Function1);
    descriptor: (Lscala/compat/java8/Priority1FunctionConverters;Lscala/Function1;)Lscala/Function1;
    flags: (0x1009) ACC_PUBLIC, ACC_STATIC, ACC_SYNTHETIC
    Code:
      stack=2, locals=2, args_size=2
         0: aload_0
         1: aload_1
         2: invokespecial #81                 // InterfaceMethod enrichAsJavaToDoubleFunction:(Lscala/Function1;)Lscala/Function1;
         5: areturn
      LineNumberTable:
        line 794: 0
      LocalVariableTable:
        Start  Length  Slot  Name   Signature
            0       6     0 $this   Lscala/compat/java8/Priority1FunctionConverters;
            0       6     1    sf   Lscala/Function1;
    MethodParameters:
      Name                           Flags
      $this                          final synthetic
      sf                             final

  public default <T extends java.lang.Object> scala.Function1<T, java.lang.Object> enrichAsJavaToDoubleFunction(scala.Function1<T, java.lang.Object>);
    descriptor: (Lscala/Function1;)Lscala/Function1;
    flags: (0x0001) ACC_PUBLIC
    Code:
      stack=1, locals=2, args_size=2
         0: aload_1
         1: areturn
      LineNumberTable:
        line 794: 0
      LocalVariableTable:
        Start  Length  Slot  Name   Signature
            0       2     0  this   Lscala/compat/java8/Priority1FunctionConverters;
            0       2     1    sf   Lscala/Function1;
    Signature: #69                          // <T:Ljava/lang/Object;>(Lscala/Function1<TT;Ljava/lang/Object;>;)Lscala/Function1<TT;Ljava/lang/Object;>;
    MethodParameters:
      Name                           Flags
      sf                             final

  public static scala.Function1 enrichAsJavaToIntFunction$(scala.compat.java8.Priority1FunctionConverters, scala.Function1);
    descriptor: (Lscala/compat/java8/Priority1FunctionConverters;Lscala/Function1;)Lscala/Function1;
    flags: (0x1009) ACC_PUBLIC, ACC_STATIC, ACC_SYNTHETIC
    Code:
      stack=2, locals=2, args_size=2
         0: aload_0
         1: aload_1
         2: invokespecial #85                 // InterfaceMethod enrichAsJavaToIntFunction:(Lscala/Function1;)Lscala/Function1;
         5: areturn
      LineNumberTable:
        line 796: 0
      LocalVariableTable:
        Start  Length  Slot  Name   Signature
            0       6     0 $this   Lscala/compat/java8/Priority1FunctionConverters;
            0       6     1    sf   Lscala/Function1;
    MethodParameters:
      Name                           Flags
      $this                          final synthetic
      sf                             final

  public default <T extends java.lang.Object> scala.Function1<T, java.lang.Object> enrichAsJavaToIntFunction(scala.Function1<T, java.lang.Object>);
    descriptor: (Lscala/Function1;)Lscala/Function1;
    flags: (0x0001) ACC_PUBLIC
    Code:
      stack=1, locals=2, args_size=2
         0: aload_1
         1: areturn
      LineNumberTable:
        line 796: 0
      LocalVariableTable:
        Start  Length  Slot  Name   Signature
            0       2     0  this   Lscala/compat/java8/Priority1FunctionConverters;
            0       2     1    sf   Lscala/Function1;
    Signature: #69                          // <T:Ljava/lang/Object;>(Lscala/Function1<TT;Ljava/lang/Object;>;)Lscala/Function1<TT;Ljava/lang/Object;>;
    MethodParameters:
      Name                           Flags
      sf                             final

  public static scala.Function1 enrichAsJavaToLongFunction$(scala.compat.java8.Priority1FunctionConverters, scala.Function1);
    descriptor: (Lscala/compat/java8/Priority1FunctionConverters;Lscala/Function1;)Lscala/Function1;
    flags: (0x1009) ACC_PUBLIC, ACC_STATIC, ACC_SYNTHETIC
    Code:
      stack=2, locals=2, args_size=2
         0: aload_0
         1: aload_1
         2: invokespecial #89                 // InterfaceMethod enrichAsJavaToLongFunction:(Lscala/Function1;)Lscala/Function1;
         5: areturn
      LineNumberTable:
        line 798: 0
      LocalVariableTable:
        Start  Length  Slot  Name   Signature
            0       6     0 $this   Lscala/compat/java8/Priority1FunctionConverters;
            0       6     1    sf   Lscala/Function1;
    MethodParameters:
      Name                           Flags
      $this                          final synthetic
      sf                             final

  public default <T extends java.lang.Object> scala.Function1<T, java.lang.Object> enrichAsJavaToLongFunction(scala.Function1<T, java.lang.Object>);
    descriptor: (Lscala/Function1;)Lscala/Function1;
    flags: (0x0001) ACC_PUBLIC
    Code:
      stack=1, locals=2, args_size=2
         0: aload_1
         1: areturn
      LineNumberTable:
        line 798: 0
      LocalVariableTable:
        Start  Length  Slot  Name   Signature
            0       2     0  this   Lscala/compat/java8/Priority1FunctionConverters;
            0       2     1    sf   Lscala/Function1;
    Signature: #69                          // <T:Ljava/lang/Object;>(Lscala/Function1<TT;Ljava/lang/Object;>;)Lscala/Function1<TT;Ljava/lang/Object;>;
    MethodParameters:
      Name                           Flags
      sf                             final

  public static scala.Function1 enrichAsJavaUnaryOperator$(scala.compat.java8.Priority1FunctionConverters, scala.Function1, scala.$eq$colon$eq);
    descriptor: (Lscala/compat/java8/Priority1FunctionConverters;Lscala/Function1;Lscala/$eq$colon$eq;)Lscala/Function1;
    flags: (0x1009) ACC_PUBLIC, ACC_STATIC, ACC_SYNTHETIC
    Code:
      stack=3, locals=3, args_size=3
         0: aload_0
         1: aload_1
         2: aload_2
         3: invokespecial #93                 // InterfaceMethod enrichAsJavaUnaryOperator:(Lscala/Function1;Lscala/$eq$colon$eq;)Lscala/Function1;
         6: areturn
      LineNumberTable:
        line 800: 0
      LocalVariableTable:
        Start  Length  Slot  Name   Signature
            0       7     0 $this   Lscala/compat/java8/Priority1FunctionConverters;
            0       7     1    sf   Lscala/Function1;
            0       7     2  evA1   Lscala/$eq$colon$eq;
    MethodParameters:
      Name                           Flags
      $this                          final synthetic
      sf                             final
      evA1                           final

  public default <T extends java.lang.Object, A1 extends java.lang.Object> scala.Function1<T, T> enrichAsJavaUnaryOperator(scala.Function1<T, A1>, scala.$eq$colon$eq<A1, T>);
    descriptor: (Lscala/Function1;Lscala/$eq$colon$eq;)Lscala/Function1;
    flags: (0x0001) ACC_PUBLIC
    Code:
      stack=1, locals=3, args_size=3
         0: aload_1
         1: areturn
      LineNumberTable:
        line 800: 0
      LocalVariableTable:
        Start  Length  Slot  Name   Signature
            0       2     0  this   Lscala/compat/java8/Priority1FunctionConverters;
            0       2     1    sf   Lscala/Function1;
            0       2     2  evA1   Lscala/$eq$colon$eq;
    Signature: #94                          // <T:Ljava/lang/Object;A1:Ljava/lang/Object;>(Lscala/Function1<TT;TA1;>;Lscala/$eq$colon$eq<TA1;TT;>;)Lscala/Function1<TT;TT;>;
    MethodParameters:
      Name                           Flags
      sf                             final
      evA1                           final

  public static void $init$(scala.compat.java8.Priority1FunctionConverters);
    descriptor: (Lscala/compat/java8/Priority1FunctionConverters;)V
    flags: (0x0009) ACC_PUBLIC, ACC_STATIC
    Code:
      stack=0, locals=1, args_size=1
         0: return
      LineNumberTable:
        line 771: 0
      LocalVariableTable:
        Start  Length  Slot  Name   Signature
            0       1     0 $this   Lscala/compat/java8/Priority1FunctionConverters;
    MethodParameters:
      Name                           Flags
      $this                          final synthetic
}
SourceFile: "FunctionConverters.scala"
RuntimeVisibleAnnotations:
  0: #8(#9=s#10)
    scala.reflect.ScalaSignature(
      bytes="\u0006\u0005\t=ba\u0002\t\u0012!\u0003\r\t\u0001\u0007\u0005\u0006C\u0001!\tA\t\u0005\u0006M\u0001!\u0019a\n\u0005\u0006%\u0002!\u0019a\u0015\u0005\u0006?\u0002!\u0019\u0001\u0019\u0005\u0006k\u0002!\u0019A\u001e\u0005\b\u0003#\u0001A1AA\n\u0011\u001d\t9\u0004\u0001C\u0002\u0003sAq!a\u0016\u0001\t\u0007\tI\u0006C\u0004\u0002x\u0001!\u0019!!\u001f\t\u000f\u0005]\u0005\u0001b\u0001\u0002\u001a\"9\u00111\u0017\u0001\u0005\u0004\u0005U\u0006bBAg\u0001\u0011\r\u0011q\u001a\u0005\b\u0003G\u0004A1AAs\u0011\u001d\tI\u0010\u0001C\u0002\u0003wDqAa\u0004\u0001\t\u0007\u0011\tBA\u000eQe&|\'/\u001b;zc\u0019+hn\u0019;j_:\u001cuN\u001c<feR,\'o\u001d\u0006\u0003%M\tQA[1wCbR!\u0001F\u000b\u0002\r\r|W\u000e]1u\u0015\u00051\u0012!B:dC2\f7\u0001A\n\u0004\u0001ei\u0002C\u0001\u000e\u001c\u001b\u0005)\u0012B\u0001\u000f\u0016\u0005\u0019\te.\u001f*fMB\u0011adH\u0007\u0002#%\u0011\u0001%\u0005\u0002\u001c!JLwN]5usJ2UO\\2uS>t7i\u001c8wKJ$XM]:\u0002\r\u0011Jg.\u001b;%)\u0005\u0019\u0003C\u0001\u000e%\u0013\t)SC\u0001\u0003V]&$\u0018AG3oe&\u001c\u0007.Q:KCZ\f\')\u001b8bef|\u0005/\u001a:bi>\u0014X\u0003\u0002\u00153\u0003\u001e#\"!K%\u0015\u0007)Z4\tE\u0002,]Aj\u0011\u0001\f\u0006\u0003[E\taCZ;oGRLwN\\\"p]Z,\'\u000f^3s\u00136\u0004Hn]\u0005\u0003_1\u0012QDU5dQ\u001a+hn\u0019;j_:\u0014\u0014i\u001d\"j]\u0006\u0014\u0018p\u00149fe\u0006$xN\u001d\t\u0003cIb\u0001\u0001B\u00034\u0005\t\u0007AGA\u0001U#\t)\u0004\b\u0005\u0002\u001bm%\u0011q\'\u0006\u0002\b\u001d>$\b.\u001b8h!\tQ\u0012(\u0003\u0002;+\t\u0019\u0011I\\=\t\u000bq\u0012\u00019A\u001f\u0002\t\u00154\u0018)\r\t\u00055y\u0002\u0005\'\u0003\u0002@+\taA%Z9%G>dwN\u001c\u0013fcB\u0011\u0011\'\u0011\u0003\u0006\u0005\n\u0011\r\u0001\u000e\u0002\u0003\u0003FBQ\u0001\u0012\u0002A\u0004\u0015\u000bA!\u001a<BeA!!D\u0010$1!\t\tt\tB\u0003I\u0005\t\u0007AG\u0001\u0002Be!)!J\u0001a\u0001\u0017\u0006\u00111O\u001a\t\u000651\u0003\u0004IR\u0005\u0003\u001bV\u0011\u0011BR;oGRLwN\u001c\u001a)\u0005\ty\u0005C\u0001\u000eQ\u0013\t\tVC\u0001\u0004j]2Lg.Z\u0001\u0015K:\u0014\u0018n\u00195Bg*\u000bg/Y\"p]N,X.\u001a:\u0016\u0005QKFCA+[!\rYc\u000bW\u0005\u0003/2\u0012qCU5dQ\u001a+hn\u0019;j_:\f\u0014i]\"p]N,X.\u001a:\u0011\u0005EJF!B\u001a\u0004\u0005\u0004!\u0004\"\u0002&\u0004\u0001\u0004Y\u0006\u0003\u0002\u000e]1\u000eJ!!X\u000b\u0003\u0013\u0019+hn\u0019;j_:\f\u0004FA\u0002P\u0003i)gN]5dQ\u0006\u001b(*\u0019<b\t>,(\r\\3Gk:\u001cG/[8o+\r\tWn\u001a\u000b\u0003EJ$\"aY5\u0011\u0007-\"g-\u0003\u0002fY\ti\"+[2i\rVt7\r^5p]F\n5\u000fR8vE2,g)\u001e8di&|g\u000e\u0005\u00022O\u0012)\u0001\u000e\u0002b\u0001i\t\t!\u000bC\u0003k\t\u0001\u000f1.\u0001\u0003fm\u0006\u0003\u0004\u0003\u0002\u000e?Y>\u0004\"!M7\u0005\u000b9$!\u0019\u0001\u001b\u0003\u0005\u0005\u0003\u0004C\u0001\u000eq\u0013\t\tXC\u0001\u0004E_V\u0014G.\u001a\u0005\u0006\u0015\u0012\u0001\ra\u001d\t\u00055qcg\r\u000b\u0002\u0005\u001f\u00069RM\u001c:jG\"\f5OS1wC&sGOR;oGRLwN\\\u000b\u0005o\u0006\rQ\u0010F\u0002y\u0003\u0017!\"!\u001f@\u0011\u0007-RH0\u0003\u0002|Y\tQ\"+[2i\rVt7\r^5p]F\n5/\u00138u\rVt7\r^5p]B\u0011\u0011\' \u0003\u0006Q\u0016\u0011\r\u0001\u000e\u0005\u0006U\u0016\u0001\u001da \t\u00075y\n\t!!\u0002\u0011\u0007E\n\u0019\u0001B\u0003o\u000b\t\u0007A\u0007E\u0002\u001b\u0003\u000fI1!!\u0003\u0016\u0005\rIe\u000e\u001e\u0005\u0007\u0015\u0016\u0001\r!!\u0004\u0011\u000bia\u0016\u0011\u0001?)\u0005\u0015y\u0015\u0001G3oe&\u001c\u0007.Q:KCZ\fGj\u001c8h\rVt7\r^5p]V1\u0011QCA\u0015\u0003C!B!a\u0006\u00022Q!\u0011\u0011DA\u0012!\u0015Y\u00131DA\u0010\u0013\r\ti\u0002\f\u0002\u001c%&\u001c\u0007NR;oGRLwN\\\u0019Bg2{gn\u001a$v]\u000e$\u0018n\u001c8\u0011\u0007E\n\t\u0003B\u0003i\r\t\u0007A\u0007\u0003\u0004k\r\u0001\u000f\u0011Q\u0005\t\u00075y\n9#a\u000b\u0011\u0007E\nI\u0003B\u0003o\r\t\u0007A\u0007E\u0002\u001b\u0003[I1!a\f\u0016\u0005\u0011auN\\4\t\r)3\u0001\u0019AA\u001a!\u0019QB,a\n\u0002 !\u0012aaT\u0001\u001eK:\u0014\u0018n\u00195Bg*\u000bg/Y(cU\u0012{WO\u00197f\u0007>t7/^7feV1\u00111HA$\u0003\u001f\"B!!\u0010\u0002RQ!\u0011qHA%!\u0015Y\u0013\u0011IA#\u0013\r\t\u0019\u0005\f\u0002!%&\u001c\u0007NR;oGRLwN\u001c\u001aBg>\u0013\'\u000eR8vE2,7i\u001c8tk6,\'\u000fE\u00022\u0003\u000f\"QaM\u0004C\u0002QBa\u0001P\u0004A\u0004\u0005-\u0003#\u0002\u000e?\u0003\u001bz\u0007cA\u0019\u0002P\u0011)!i\u0002b\u0001i!1!j\u0002a\u0001\u0003\'\u0002rA\u0007\'\u0002F\u000553\u0005\u000b\u0002\b\u001f\u0006QRM\u001c:jG\"\f5OS1wC>\u0013\'.\u00138u\u0007>t7/^7feV1\u00111LA4\u0003_\"B!!\u0018\u0002rQ!\u0011qLA5!\u0015Y\u0013\u0011MA3\u0013\r\t\u0019\u0007\f\u0002\u001e%&\u001c\u0007NR;oGRLwN\u001c\u001aBg>\u0013\'.\u00138u\u0007>t7/^7feB\u0019\u0011\'a\u001a\u0005\u000bMB!\u0019\u0001\u001b\t\rqB\u00019AA6!\u0019Qb(!\u001c\u0002\u0006A\u0019\u0011\'a\u001c\u0005\u000b\tC!\u0019\u0001\u001b\t\r)C\u0001\u0019AA:!\u001dQB*!\u001a\u0002n\rB#\u0001C(\u00027\u0015t\'/[2i\u0003NT\u0015M^1PE*duN\\4D_:\u001cX/\\3s+\u0019\tY(a\"\u0002\u0010R!\u0011QPAI)\u0011\ty(!#\u0011\u000b-\n\t)!\"\n\u0007\u0005\rEF\u0001\u0010SS\u000eDg)\u001e8di&|gNM!t\u001f\nTGj\u001c8h\u0007>t7/^7feB\u0019\u0011\'a\"\u0005\u000bMJ!\u0019\u0001\u001b\t\rqJ\u00019AAF!\u0019Qb(!$\u0002,A\u0019\u0011\'a$\u0005\u000b\tK!\u0019\u0001\u001b\t\r)K\u0001\u0019AAJ!\u001dQB*!\"\u0002\u000e\u000eB#!C(\u0002+\u0015t\'/[2i\u0003NT\u0015M^1Qe\u0016$\u0017nY1uKV!\u00111TAS)\u0011\ti*a*\u0011\u000b-\ny*a)\n\u0007\u0005\u0005FF\u0001\rSS\u000eDg)\u001e8di&|g.M!t!J,G-[2bi\u0016\u00042!MAS\t\u0015\u0019$B1\u00015\u0011\u0019Q%\u00021\u0001\u0002*B1!\u0004XAR\u0003W\u00032AGAW\u0013\r\ty+\u0006\u0002\b\u0005>|G.Z1oQ\tQq*\u0001\u000bf]JL7\r[!t\u0015\u00064\u0018mU;qa2LWM]\u000b\u0005\u0003o\u000b\t\r\u0006\u0003\u0002:\u0006\r\u0007#B\u0016\u0002<\u0006}\u0016bAA_Y\t9\"+[2i\rVt7\r^5p]B\n5oU;qa2LWM\u001d\t\u0004c\u0005\u0005G!B\u001a\f\u0005\u0004!\u0004B\u0002&\f\u0001\u0004\t)\rE\u0003\u001b\u0003\u000f\fy,C\u0002\u0002JV\u0011\u0011BR;oGRLwN\u001c\u0019)\u0005-y\u0015\u0001H3oe&\u001c\u0007.Q:KCZ\fGk\u001c#pk\ndWMR;oGRLwN\\\u000b\u0005\u0003#\fY\u000e\u0006\u0003\u0002T\u0006u\u0007#B\u0016\u0002V\u0006e\u0017bAAlY\ty\"+[2i\rVt7\r^5p]F\n5\u000fV8E_V\u0014G.\u001a$v]\u000e$\u0018n\u001c8\u0011\u0007E\nY\u000eB\u00034\u0019\t\u0007A\u0007\u0003\u0004K\u0019\u0001\u0007\u0011q\u001c\t\u00065q\u000bIn\u001c\u0015\u0003\u0019=\u000b\u0011$\u001a8sS\u000eD\u0017i\u001d&bm\u0006$v.\u00138u\rVt7\r^5p]V!\u0011q]Ay)\u0011\tI/a=\u0011\u000b-\nY/a<\n\u0007\u00055HF\u0001\u000fSS\u000eDg)\u001e8di&|g.M!t)>Le\u000e\u001e$v]\u000e$\u0018n\u001c8\u0011\u0007E\n\t\u0010B\u00034\u001b\t\u0007A\u0007\u0003\u0004K\u001b\u0001\u0007\u0011Q\u001f\t\u00075q\u000by/!\u0002)\u00055y\u0015AG3oe&\u001c\u0007.Q:KCZ\fGk\u001c\'p]\u001e4UO\\2uS>tW\u0003BA\u007f\u0005\u000f!B!a@\u0003\nA)1F!\u0001\u0003\u0006%\u0019!1\u0001\u0017\u0003;IK7\r\u001b$v]\u000e$\u0018n\u001c82\u0003N$v\u000eT8oO\u001a+hn\u0019;j_:\u00042!\rB\u0004\t\u0015\u0019dB1\u00015\u0011\u0019Qe\u00021\u0001\u0003\fA1!\u0004\u0018B\u0003\u0003WA#AD(\u00023\u0015t\'/[2i\u0003NT\u0015M^1V]\u0006\u0014\u0018p\u00149fe\u0006$xN]\u000b\u0007\u0005\'\u0011yBa\n\u0015\t\tU!\u0011\u0006\u000b\u0005\u0005/\u0011\t\u0003E\u0003,\u00053\u0011i\"C\u0002\u0003\u001c1\u0012ADU5dQ\u001a+hn\u0019;j_:\f\u0014i]+oCJLx\n]3sCR|\'\u000fE\u00022\u0005?!QaM\bC\u0002QBa\u0001P\bA\u0004\t\r\u0002C\u0002\u000e?\u0005K\u0011i\u0002E\u00022\u0005O!QAQ\bC\u0002QBaAS\bA\u0002\t-\u0002C\u0002\u000e]\u0005;\u0011)\u0003\u000b\u0002\u0010\u001f\u0002"
    )
  ScalaInlineInfo: length = 0x95 (unknown attribute)
   01 00 00 1D 00 5F 00 60 01 00 11 00 12 04 00 0B
   00 0C 05 00 1C 00 1D 04 00 1A 00 1B 05 00 25 00
   26 04 00 22 00 23 05 00 2B 00 26 04 00 2A 00 23
   05 00 2F 00 26 04 00 2E 00 23 05 00 34 00 35 04
   00 32 00 33 05 00 3A 00 35 04 00 39 00 33 05 00
   3E 00 35 04 00 3D 00 33 05 00 42 00 1D 04 00 41
   00 1B 05 00 48 00 49 04 00 46 00 47 05 00 4F 00
   1D 04 00 4E 00 1B 05 00 53 00 1D 04 00 52 00 1B
   05 00 57 00 1D 04 00 56 00 1B 05 00 5B 00 26 04
   00 5A 00 23 05
  ScalaSig: length = 0x3 (unknown attribute)
   05 02 00
