Classfile /Users/mw/Projects/slang-braindump/.jar/jar11/assemble/slang-braindump/assemble/content/scala/collection/immutable/DoubleVectorStepper.class
  Last modified May 29, 2022; size 4019 bytes
  SHA-256 checksum 327d10333212faf65a5e73fe217616809c39c43ed2260578156f7b3eb2b48d5f
  Compiled from "Vector.scala"
public class scala.collection.immutable.DoubleVectorStepper extends scala.collection.immutable.VectorStepperBase<java.lang.Object, scala.collection.DoubleStepper, scala.collection.immutable.DoubleVectorStepper> implements scala.collection.DoubleStepper
  minor version: 0
  major version: 52
  flags: (0x0021) ACC_PUBLIC, ACC_SUPER
  this_class: #2                          // scala/collection/immutable/DoubleVectorStepper
  super_class: #5                         // scala/collection/immutable/VectorStepperBase
  interfaces: 1, fields: 1, methods: 13, attributes: 6
Constant pool:
    #1 = Utf8               scala/collection/immutable/DoubleVectorStepper
    #2 = Class              #1            // scala/collection/immutable/DoubleVectorStepper
    #3 = Utf8               Lscala/collection/immutable/VectorStepperBase<Ljava/lang/Object;Lscala/collection/DoubleStepper;Lscala/collection/immutable/DoubleVectorStepper;>;Lscala/collection/DoubleStepper;
    #4 = Utf8               scala/collection/immutable/VectorStepperBase
    #5 = Class              #4            // scala/collection/immutable/VectorStepperBase
    #6 = Utf8               scala/collection/DoubleStepper
    #7 = Class              #6            // scala/collection/DoubleStepper
    #8 = Utf8               Vector.scala
    #9 = Utf8               Lscala/reflect/ScalaSignature;
   #10 = Utf8               bytes
   #11 = Utf8               \u0006\u0005\u001d2A!\u0002\u0004\u0005\u001b!A1\u0004\u0001B\u0001B\u0003%A\u0004C\u0003 \u0001\u0011\u0005\u0001\u0005\u0003\u0004#\u0001\u0001&\tb\t\u0005\u0006K\u0001!\tA\n\u0002\u0014\t>,(\r\\3WK\u000e$xN]*uKB\u0004XM\u001d\u0006\u0003\u000f!\t\u0011\"[7nkR\f\'\r\\3\u000b\u0005%Q\u0011AC2pY2,7\r^5p]*\t1\"A\u0003tG\u0006d\u0017m\u0001\u0001\u0014\u0007\u0001qa\u0003E\u0003\u0010!I1\"$D\u0001\u0007\u0013\t\tbAA\tWK\u000e$xN]*uKB\u0004XM\u001d\"bg\u0016\u0004\"a\u0005\u000b\u000e\u0003)I!!\u0006\u0006\u0003\r\u0011{WO\u00197f!\t9\u0002$D\u0001\t\u0013\tI\u0002BA\u0007E_V\u0014G.Z*uKB\u0004XM\u001d\t\u0003\u001f\u0001\t!!\u001b;\u0011\u0007=i\"#\u0003\u0002\u001f\r\t\tb*Z<WK\u000e$xN]%uKJ\fGo\u001c:\u0002\rqJg.\u001b;?)\tQ\u0012\u0005C\u0003\u001c\u0005\u0001\u0007A$A\u0003ck&dG\r\u0006\u0002\u001bI!)1d\u0001a\u00019\u0005Aa.\u001a=u\'R,\u0007\u000fF\u0001\u0013\u0001
   #12 = Utf8               java/util/PrimitiveIterator$OfDouble
   #13 = Class              #12           // java/util/PrimitiveIterator$OfDouble
   #14 = Utf8               java/util/PrimitiveIterator
   #15 = Class              #14           // java/util/PrimitiveIterator
   #16 = Utf8               OfDouble
   #17 = Utf8               java/util/Spliterator$OfDouble
   #18 = Class              #17           // java/util/Spliterator$OfDouble
   #19 = Utf8               java/util/Spliterator
   #20 = Class              #19           // java/util/Spliterator
   #21 = Utf8               scala$collection$immutable$DoubleVectorStepper$$it
   #22 = Utf8               Lscala/collection/immutable/NewVectorIterator;
   #23 = Utf8               Lscala/collection/immutable/NewVectorIterator<Ljava/lang/Object;>;
   #24 = Utf8               spliterator
   #25 = Utf8               ()Ljava/util/Spliterator$OfDouble;
   #26 = Utf8               <B:Ljava/lang/Object;>()Ljava/util/Spliterator$OfDouble;
   #27 = Utf8               spliterator$
   #28 = Utf8               (Lscala/collection/DoubleStepper;)Ljava/util/Spliterator$OfDouble;
   #29 = NameAndType        #27:#28       // spliterator$:(Lscala/collection/DoubleStepper;)Ljava/util/Spliterator$OfDouble;
   #30 = InterfaceMethodref #7.#29        // scala/collection/DoubleStepper.spliterator$:(Lscala/collection/DoubleStepper;)Ljava/util/Spliterator$OfDouble;
   #31 = Utf8               this
   #32 = Utf8               Lscala/collection/immutable/DoubleVectorStepper;
   #33 = Utf8               javaIterator
   #34 = Utf8               ()Ljava/util/PrimitiveIterator$OfDouble;
   #35 = Utf8               <B:Ljava/lang/Object;>()Ljava/util/PrimitiveIterator$OfDouble;
   #36 = Utf8               javaIterator$
   #37 = Utf8               (Lscala/collection/DoubleStepper;)Ljava/util/PrimitiveIterator$OfDouble;
   #38 = NameAndType        #36:#37       // javaIterator$:(Lscala/collection/DoubleStepper;)Ljava/util/PrimitiveIterator$OfDouble;
   #39 = InterfaceMethodref #7.#38        // scala/collection/DoubleStepper.javaIterator$:(Lscala/collection/DoubleStepper;)Ljava/util/PrimitiveIterator$OfDouble;
   #40 = Utf8               spliterator$mcD$sp
   #41 = Utf8               ()Ljava/util/Spliterator;
   #42 = Utf8               <B:Ljava/lang/Object;>()Ljava/util/Spliterator<*>;
   #43 = Utf8               spliterator$mcD$sp$
   #44 = Utf8               (Lscala/collection/DoubleStepper;)Ljava/util/Spliterator;
   #45 = NameAndType        #43:#44       // spliterator$mcD$sp$:(Lscala/collection/DoubleStepper;)Ljava/util/Spliterator;
   #46 = InterfaceMethodref #7.#45        // scala/collection/DoubleStepper.spliterator$mcD$sp$:(Lscala/collection/DoubleStepper;)Ljava/util/Spliterator;
   #47 = Utf8               javaIterator$mcD$sp
   #48 = Utf8               ()Ljava/util/Iterator;
   #49 = Utf8               <B:Ljava/lang/Object;>()Ljava/util/Iterator<*>;
   #50 = Utf8               javaIterator$mcD$sp$
   #51 = Utf8               (Lscala/collection/DoubleStepper;)Ljava/util/Iterator;
   #52 = NameAndType        #50:#51       // javaIterator$mcD$sp$:(Lscala/collection/DoubleStepper;)Ljava/util/Iterator;
   #53 = InterfaceMethodref #7.#52        // scala/collection/DoubleStepper.javaIterator$mcD$sp$:(Lscala/collection/DoubleStepper;)Ljava/util/Iterator;
   #54 = Utf8               build
   #55 = Utf8               (Lscala/collection/immutable/NewVectorIterator;)Lscala/collection/immutable/DoubleVectorStepper;
   #56 = Utf8               (Lscala/collection/immutable/NewVectorIterator<Ljava/lang/Object;>;)Lscala/collection/immutable/DoubleVectorStepper;
   #57 = Utf8               it
   #58 = Utf8               <init>
   #59 = Utf8               (Lscala/collection/immutable/NewVectorIterator;)V
   #60 = NameAndType        #58:#59       // "<init>":(Lscala/collection/immutable/NewVectorIterator;)V
   #61 = Methodref          #2.#60        // scala/collection/immutable/DoubleVectorStepper."<init>":(Lscala/collection/immutable/NewVectorIterator;)V
   #62 = Utf8               nextStep
   #63 = Utf8               ()D
   #64 = Utf8               nextStep$mcD$sp
   #65 = NameAndType        #64:#63       // nextStep$mcD$sp:()D
   #66 = Methodref          #2.#65        // scala/collection/immutable/DoubleVectorStepper.nextStep$mcD$sp:()D
   #67 = NameAndType        #21:#22       // scala$collection$immutable$DoubleVectorStepper$$it:Lscala/collection/immutable/NewVectorIterator;
   #68 = Fieldref           #2.#67        // scala/collection/immutable/DoubleVectorStepper.scala$collection$immutable$DoubleVectorStepper$$it:Lscala/collection/immutable/NewVectorIterator;
   #69 = Utf8               scala/collection/immutable/NewVectorIterator
   #70 = Class              #69           // scala/collection/immutable/NewVectorIterator
   #71 = Utf8               next
   #72 = Utf8               ()Ljava/lang/Object;
   #73 = NameAndType        #71:#72       // next:()Ljava/lang/Object;
   #74 = Methodref          #70.#73       // scala/collection/immutable/NewVectorIterator.next:()Ljava/lang/Object;
   #75 = Utf8               scala/runtime/BoxesRunTime
   #76 = Class              #75           // scala/runtime/BoxesRunTime
   #77 = Utf8               unboxToDouble
   #78 = Utf8               (Ljava/lang/Object;)D
   #79 = NameAndType        #77:#78       // unboxToDouble:(Ljava/lang/Object;)D
   #80 = Methodref          #76.#79       // scala/runtime/BoxesRunTime.unboxToDouble:(Ljava/lang/Object;)D
   #81 = Utf8               trySplit
   #82 = Utf8               ()Lscala/collection/DoubleStepper;
   #83 = Utf8               ()Lscala/collection/Stepper;
   #84 = NameAndType        #81:#83       // trySplit:()Lscala/collection/Stepper;
   #85 = Methodref          #2.#84        // scala/collection/immutable/DoubleVectorStepper.trySplit:()Lscala/collection/Stepper;
   #86 = NameAndType        #33:#34       // javaIterator:()Ljava/util/PrimitiveIterator$OfDouble;
   #87 = Methodref          #2.#86        // scala/collection/immutable/DoubleVectorStepper.javaIterator:()Ljava/util/PrimitiveIterator$OfDouble;
   #88 = NameAndType        #24:#25       // spliterator:()Ljava/util/Spliterator$OfDouble;
   #89 = Methodref          #2.#88        // scala/collection/immutable/DoubleVectorStepper.spliterator:()Ljava/util/Spliterator$OfDouble;
   #90 = NameAndType        #62:#63       // nextStep:()D
   #91 = Methodref          #2.#90        // scala/collection/immutable/DoubleVectorStepper.nextStep:()D
   #92 = Utf8               boxToDouble
   #93 = Utf8               (D)Ljava/lang/Double;
   #94 = NameAndType        #92:#93       // boxToDouble:(D)Ljava/lang/Double;
   #95 = Methodref          #76.#94       // scala/runtime/BoxesRunTime.boxToDouble:(D)Ljava/lang/Double;
   #96 = Utf8               (Lscala/collection/immutable/NewVectorIterator;)Lscala/collection/Stepper;
   #97 = NameAndType        #54:#55       // build:(Lscala/collection/immutable/NewVectorIterator;)Lscala/collection/immutable/DoubleVectorStepper;
   #98 = Methodref          #2.#97        // scala/collection/immutable/DoubleVectorStepper.build:(Lscala/collection/immutable/NewVectorIterator;)Lscala/collection/immutable/DoubleVectorStepper;
   #99 = Utf8               (Lscala/collection/immutable/NewVectorIterator<Ljava/lang/Object;>;)V
  #100 = Methodref          #5.#60        // scala/collection/immutable/VectorStepperBase."<init>":(Lscala/collection/immutable/NewVectorIterator;)V
  #101 = Utf8               Signature
  #102 = Utf8               Code
  #103 = Utf8               LineNumberTable
  #104 = Utf8               LocalVariableTable
  #105 = Utf8               MethodParameters
  #106 = Utf8               InnerClasses
  #107 = Utf8               SourceFile
  #108 = Utf8               RuntimeVisibleAnnotations
  #109 = Utf8               ScalaInlineInfo
  #110 = Utf8               ScalaSig
{
  public final scala.collection.immutable.NewVectorIterator<java.lang.Object> scala$collection$immutable$DoubleVectorStepper$$it;
    descriptor: Lscala/collection/immutable/NewVectorIterator;
    flags: (0x0011) ACC_PUBLIC, ACC_FINAL
    Signature: #23                          // Lscala/collection/immutable/NewVectorIterator<Ljava/lang/Object;>;

  public <B extends java.lang.Object> java.util.Spliterator$OfDouble spliterator();
    descriptor: ()Ljava/util/Spliterator$OfDouble;
    flags: (0x0001) ACC_PUBLIC
    Code:
      stack=1, locals=1, args_size=1
         0: aload_0
         1: invokestatic  #30                 // InterfaceMethod scala/collection/DoubleStepper.spliterator$:(Lscala/collection/DoubleStepper;)Ljava/util/Spliterator$OfDouble;
         4: areturn
      LineNumberTable:
        line 2182: 0
      LocalVariableTable:
        Start  Length  Slot  Name   Signature
            0       5     0  this   Lscala/collection/immutable/DoubleVectorStepper;
    Signature: #26                          // <B:Ljava/lang/Object;>()Ljava/util/Spliterator$OfDouble;

  public <B extends java.lang.Object> java.util.PrimitiveIterator$OfDouble javaIterator();
    descriptor: ()Ljava/util/PrimitiveIterator$OfDouble;
    flags: (0x0001) ACC_PUBLIC
    Code:
      stack=1, locals=1, args_size=1
         0: aload_0
         1: invokestatic  #39                 // InterfaceMethod scala/collection/DoubleStepper.javaIterator$:(Lscala/collection/DoubleStepper;)Ljava/util/PrimitiveIterator$OfDouble;
         4: areturn
      LineNumberTable:
        line 2182: 0
      LocalVariableTable:
        Start  Length  Slot  Name   Signature
            0       5     0  this   Lscala/collection/immutable/DoubleVectorStepper;
    Signature: #35                          // <B:Ljava/lang/Object;>()Ljava/util/PrimitiveIterator$OfDouble;

  public <B extends java.lang.Object> java.util.Spliterator<?> spliterator$mcD$sp();
    descriptor: ()Ljava/util/Spliterator;
    flags: (0x0001) ACC_PUBLIC
    Code:
      stack=1, locals=1, args_size=1
         0: aload_0
         1: invokestatic  #46                 // InterfaceMethod scala/collection/DoubleStepper.spliterator$mcD$sp$:(Lscala/collection/DoubleStepper;)Ljava/util/Spliterator;
         4: areturn
      LineNumberTable:
        line 2182: 0
      LocalVariableTable:
        Start  Length  Slot  Name   Signature
            0       5     0  this   Lscala/collection/immutable/DoubleVectorStepper;
    Signature: #42                          // <B:Ljava/lang/Object;>()Ljava/util/Spliterator<*>;

  public <B extends java.lang.Object> java.util.Iterator<?> javaIterator$mcD$sp();
    descriptor: ()Ljava/util/Iterator;
    flags: (0x0001) ACC_PUBLIC
    Code:
      stack=1, locals=1, args_size=1
         0: aload_0
         1: invokestatic  #53                 // InterfaceMethod scala/collection/DoubleStepper.javaIterator$mcD$sp$:(Lscala/collection/DoubleStepper;)Ljava/util/Iterator;
         4: areturn
      LineNumberTable:
        line 2182: 0
      LocalVariableTable:
        Start  Length  Slot  Name   Signature
            0       5     0  this   Lscala/collection/immutable/DoubleVectorStepper;
    Signature: #49                          // <B:Ljava/lang/Object;>()Ljava/util/Iterator<*>;

  public scala.collection.immutable.DoubleVectorStepper build(scala.collection.immutable.NewVectorIterator<java.lang.Object>);
    descriptor: (Lscala/collection/immutable/NewVectorIterator;)Lscala/collection/immutable/DoubleVectorStepper;
    flags: (0x0001) ACC_PUBLIC
    Code:
      stack=3, locals=2, args_size=2
         0: new           #2                  // class scala/collection/immutable/DoubleVectorStepper
         3: dup
         4: aload_1
         5: invokespecial #61                 // Method "<init>":(Lscala/collection/immutable/NewVectorIterator;)V
         8: areturn
      LineNumberTable:
        line 2184: 0
      LocalVariableTable:
        Start  Length  Slot  Name   Signature
            0       9     0  this   Lscala/collection/immutable/DoubleVectorStepper;
            0       9     1    it   Lscala/collection/immutable/NewVectorIterator;
    Signature: #56                          // (Lscala/collection/immutable/NewVectorIterator<Ljava/lang/Object;>;)Lscala/collection/immutable/DoubleVectorStepper;
    MethodParameters:
      Name                           Flags
      it                             final

  public double nextStep();
    descriptor: ()D
    flags: (0x0001) ACC_PUBLIC
    Code:
      stack=2, locals=1, args_size=1
         0: aload_0
         1: invokevirtual #66                 // Method nextStep$mcD$sp:()D
         4: dreturn
      LineNumberTable:
        line 2185: 0
      LocalVariableTable:
        Start  Length  Slot  Name   Signature
            0       5     0  this   Lscala/collection/immutable/DoubleVectorStepper;

  public double nextStep$mcD$sp();
    descriptor: ()D
    flags: (0x0001) ACC_PUBLIC
    Code:
      stack=2, locals=1, args_size=1
         0: aload_0
         1: getfield      #68                 // Field scala$collection$immutable$DoubleVectorStepper$$it:Lscala/collection/immutable/NewVectorIterator;
         4: invokevirtual #74                 // Method scala/collection/immutable/NewVectorIterator.next:()Ljava/lang/Object;
         7: invokestatic  #80                 // Method scala/runtime/BoxesRunTime.unboxToDouble:(Ljava/lang/Object;)D
        10: dreturn
      LineNumberTable:
        line 2185: 0
      LocalVariableTable:
        Start  Length  Slot  Name   Signature
            0      11     0  this   Lscala/collection/immutable/DoubleVectorStepper;

  public scala.collection.DoubleStepper trySplit();
    descriptor: ()Lscala/collection/DoubleStepper;
    flags: (0x1041) ACC_PUBLIC, ACC_BRIDGE, ACC_SYNTHETIC
    Code:
      stack=1, locals=1, args_size=1
         0: aload_0
         1: invokevirtual #85                 // Method trySplit:()Lscala/collection/Stepper;
         4: checkcast     #7                  // class scala/collection/DoubleStepper
         7: areturn
      LineNumberTable:
        line 2182: 0
      LocalVariableTable:
        Start  Length  Slot  Name   Signature
            0       8     0  this   Lscala/collection/immutable/DoubleVectorStepper;

  public java.util.Iterator javaIterator();
    descriptor: ()Ljava/util/Iterator;
    flags: (0x1041) ACC_PUBLIC, ACC_BRIDGE, ACC_SYNTHETIC
    Code:
      stack=1, locals=1, args_size=1
         0: aload_0
         1: invokevirtual #87                 // Method javaIterator:()Ljava/util/PrimitiveIterator$OfDouble;
         4: areturn
      LineNumberTable:
        line 2182: 0
      LocalVariableTable:
        Start  Length  Slot  Name   Signature
            0       5     0  this   Lscala/collection/immutable/DoubleVectorStepper;

  public java.util.Spliterator spliterator();
    descriptor: ()Ljava/util/Spliterator;
    flags: (0x1041) ACC_PUBLIC, ACC_BRIDGE, ACC_SYNTHETIC
    Code:
      stack=1, locals=1, args_size=1
         0: aload_0
         1: invokevirtual #89                 // Method spliterator:()Ljava/util/Spliterator$OfDouble;
         4: areturn
      LineNumberTable:
        line 2182: 0
      LocalVariableTable:
        Start  Length  Slot  Name   Signature
            0       5     0  this   Lscala/collection/immutable/DoubleVectorStepper;

  public java.lang.Object nextStep();
    descriptor: ()Ljava/lang/Object;
    flags: (0x1041) ACC_PUBLIC, ACC_BRIDGE, ACC_SYNTHETIC
    Code:
      stack=2, locals=1, args_size=1
         0: aload_0
         1: invokevirtual #91                 // Method nextStep:()D
         4: invokestatic  #95                 // Method scala/runtime/BoxesRunTime.boxToDouble:(D)Ljava/lang/Double;
         7: areturn
      LineNumberTable:
        line 2182: 0
      LocalVariableTable:
        Start  Length  Slot  Name   Signature
            0       8     0  this   Lscala/collection/immutable/DoubleVectorStepper;

  public scala.collection.Stepper build(scala.collection.immutable.NewVectorIterator);
    descriptor: (Lscala/collection/immutable/NewVectorIterator;)Lscala/collection/Stepper;
    flags: (0x1041) ACC_PUBLIC, ACC_BRIDGE, ACC_SYNTHETIC
    Code:
      stack=2, locals=2, args_size=2
         0: aload_0
         1: aload_1
         2: invokevirtual #98                 // Method build:(Lscala/collection/immutable/NewVectorIterator;)Lscala/collection/immutable/DoubleVectorStepper;
         5: areturn
      LineNumberTable:
        line 2182: 0
      LocalVariableTable:
        Start  Length  Slot  Name   Signature
            0       6     0  this   Lscala/collection/immutable/DoubleVectorStepper;
            0       6     1    it   Lscala/collection/immutable/NewVectorIterator;
    MethodParameters:
      Name                           Flags
      it                             final

  public scala.collection.immutable.DoubleVectorStepper(scala.collection.immutable.NewVectorIterator<java.lang.Object>);
    descriptor: (Lscala/collection/immutable/NewVectorIterator;)V
    flags: (0x0001) ACC_PUBLIC
    Code:
      stack=2, locals=2, args_size=2
         0: aload_0
         1: aload_1
         2: putfield      #68                 // Field scala$collection$immutable$DoubleVectorStepper$$it:Lscala/collection/immutable/NewVectorIterator;
         5: aload_0
         6: aload_1
         7: invokespecial #100                // Method scala/collection/immutable/VectorStepperBase."<init>":(Lscala/collection/immutable/NewVectorIterator;)V
        10: return
      LineNumberTable:
        line 2182: 0
        line 2183: 5
        line 2182: 10
      LocalVariableTable:
        Start  Length  Slot  Name   Signature
            0      11     0  this   Lscala/collection/immutable/DoubleVectorStepper;
            0      11     1    it   Lscala/collection/immutable/NewVectorIterator;
    Signature: #99                          // (Lscala/collection/immutable/NewVectorIterator<Ljava/lang/Object;>;)V
    MethodParameters:
      Name                           Flags
      it                             final
}
InnerClasses:
  public static #16= #13 of #15;          // OfDouble=class java/util/PrimitiveIterator$OfDouble of class java/util/PrimitiveIterator
  public static #16= #18 of #20;          // OfDouble=class java/util/Spliterator$OfDouble of class java/util/Spliterator
Signature: #3                           // Lscala/collection/immutable/VectorStepperBase<Ljava/lang/Object;Lscala/collection/DoubleStepper;Lscala/collection/immutable/DoubleVectorStepper;>;Lscala/collection/DoubleStepper;
SourceFile: "Vector.scala"
RuntimeVisibleAnnotations:
  0: #9(#10=s#11)
    scala.reflect.ScalaSignature(
      bytes="\u0006\u0005\u001d2A!\u0002\u0004\u0005\u001b!A1\u0004\u0001B\u0001B\u0003%A\u0004C\u0003 \u0001\u0011\u0005\u0001\u0005\u0003\u0004#\u0001\u0001&\tb\t\u0005\u0006K\u0001!\tA\n\u0002\u0014\t>,(\r\\3WK\u000e$xN]*uKB\u0004XM\u001d\u0006\u0003\u000f!\t\u0011\"[7nkR\f\'\r\\3\u000b\u0005%Q\u0011AC2pY2,7\r^5p]*\t1\"A\u0003tG\u0006d\u0017m\u0001\u0001\u0014\u0007\u0001qa\u0003E\u0003\u0010!I1\"$D\u0001\u0007\u0013\t\tbAA\tWK\u000e$xN]*uKB\u0004XM\u001d\"bg\u0016\u0004\"a\u0005\u000b\u000e\u0003)I!!\u0006\u0006\u0003\r\u0011{WO\u00197f!\t9\u0002$D\u0001\t\u0013\tI\u0002BA\u0007E_V\u0014G.Z*uKB\u0004XM\u001d\t\u0003\u001f\u0001\t!!\u001b;\u0011\u0007=i\"#\u0003\u0002\u001f\r\t\tb*Z<WK\u000e$xN]%uKJ\fGo\u001c:\u0002\rqJg.\u001b;?)\tQ\u0012\u0005C\u0003\u001c\u0005\u0001\u0007A$A\u0003ck&dG\r\u0006\u0002\u001bI!)1d\u0001a\u00019\u0005Aa.\u001a=u\'R,\u0007\u000fF\u0001\u0013\u0001"
    )
  ScalaInlineInfo: length = 0x45 (unknown attribute)
   01 00 00 0D 00 3A 00 3B 00 00 36 00 60 00 00 36
   00 37 00 00 21 00 30 00 00 21 00 22 00 00 2F 00
   30 00 00 3E 00 3F 00 00 3E 00 48 00 00 40 00 3F
   00 00 18 00 19 00 00 18 00 29 00 00 28 00 29 00
   00 51 00 52 00
  ScalaSig: length = 0x3 (unknown attribute)
   05 02 00
