Classfile /Users/mw/Projects/slang-braindump/.jar/jar11/assemble/slang-braindump/assemble/content/scala/collection/immutable/HashSet$.class
  Last modified May 29, 2022; size 7917 bytes
  SHA-256 checksum 45f3034157c6410c971abe6ce7e72eb603b7561839f68254899b5443fcc7c6b4
  Compiled from "HashSet.scala"
public final class scala.collection.immutable.HashSet$ extends java.lang.Object implements scala.collection.IterableFactory<scala.collection.immutable.HashSet>
  minor version: 0
  major version: 52
  flags: (0x0031) ACC_PUBLIC, ACC_FINAL, ACC_SUPER
  this_class: #2                          // scala/collection/immutable/HashSet$
  super_class: #5                         // java/lang/Object
  interfaces: 1, fields: 3, methods: 27, attributes: 4
Constant pool:
    #1 = Utf8               scala/collection/immutable/HashSet$
    #2 = Class              #1            // scala/collection/immutable/HashSet$
    #3 = Utf8               Ljava/lang/Object;Lscala/collection/IterableFactory<Lscala/collection/immutable/HashSet;>;
    #4 = Utf8               java/lang/Object
    #5 = Class              #4            // java/lang/Object
    #6 = Utf8               scala/collection/IterableFactory
    #7 = Class              #6            // scala/collection/IterableFactory
    #8 = Utf8               HashSet.scala
    #9 = Utf8               MODULE$
   #10 = Utf8               Lscala/collection/immutable/HashSet$;
   #11 = Utf8               serialVersionUID
   #12 = Utf8               J
   #13 = Long               3l
   #15 = Utf8               EmptySet
   #16 = Utf8               Lscala/collection/immutable/HashSet;
   #17 = Utf8               Lscala/collection/immutable/HashSet<Lscala/runtime/Nothing$;>;
   #18 = Utf8               <clinit>
   #19 = Utf8               ()V
   #20 = Utf8               <init>
   #21 = NameAndType        #20:#19       // "<init>":()V
   #22 = Methodref          #2.#21        // scala/collection/immutable/HashSet$."<init>":()V
   #23 = NameAndType        #9:#10        // MODULE$:Lscala/collection/immutable/HashSet$;
   #24 = Fieldref           #2.#23        // scala/collection/immutable/HashSet$.MODULE$:Lscala/collection/immutable/HashSet$;
   #25 = Utf8               scala/collection/immutable/HashSet
   #26 = Class              #25           // scala/collection/immutable/HashSet
   #27 = Utf8               scala/collection/immutable/SetNode$
   #28 = Class              #27           // scala/collection/immutable/SetNode$
   #29 = Utf8               Lscala/collection/immutable/SetNode$;
   #30 = NameAndType        #9:#29        // MODULE$:Lscala/collection/immutable/SetNode$;
   #31 = Fieldref           #28.#30       // scala/collection/immutable/SetNode$.MODULE$:Lscala/collection/immutable/SetNode$;
   #32 = Utf8               empty
   #33 = Utf8               ()Lscala/collection/immutable/BitmapIndexedSetNode;
   #34 = NameAndType        #32:#33       // empty:()Lscala/collection/immutable/BitmapIndexedSetNode;
   #35 = Methodref          #28.#34       // scala/collection/immutable/SetNode$.empty:()Lscala/collection/immutable/BitmapIndexedSetNode;
   #36 = Utf8               (Lscala/collection/immutable/BitmapIndexedSetNode;)V
   #37 = NameAndType        #20:#36       // "<init>":(Lscala/collection/immutable/BitmapIndexedSetNode;)V
   #38 = Methodref          #26.#37       // scala/collection/immutable/HashSet."<init>":(Lscala/collection/immutable/BitmapIndexedSetNode;)V
   #39 = NameAndType        #15:#16       // EmptySet:Lscala/collection/immutable/HashSet;
   #40 = Fieldref           #2.#39        // scala/collection/immutable/HashSet$.EmptySet:Lscala/collection/immutable/HashSet;
   #41 = Utf8               apply
   #42 = Utf8               (Lscala/collection/immutable/Seq;)Ljava/lang/Object;
   #43 = Utf8               elems
   #44 = Utf8               apply$
   #45 = Utf8               (Lscala/collection/IterableFactory;Lscala/collection/immutable/Seq;)Ljava/lang/Object;
   #46 = NameAndType        #44:#45       // apply$:(Lscala/collection/IterableFactory;Lscala/collection/immutable/Seq;)Ljava/lang/Object;
   #47 = InterfaceMethodref #7.#46        // scala/collection/IterableFactory.apply$:(Lscala/collection/IterableFactory;Lscala/collection/immutable/Seq;)Ljava/lang/Object;
   #48 = Utf8               this
   #49 = Utf8               Lscala/collection/immutable/Seq;
   #50 = Utf8               iterate
   #51 = Utf8               (Ljava/lang/Object;ILscala/Function1;)Ljava/lang/Object;
   #52 = Utf8               start
   #53 = Utf8               len
   #54 = Utf8               f
   #55 = Utf8               iterate$
   #56 = Utf8               (Lscala/collection/IterableFactory;Ljava/lang/Object;ILscala/Function1;)Ljava/lang/Object;
   #57 = NameAndType        #55:#56       // iterate$:(Lscala/collection/IterableFactory;Ljava/lang/Object;ILscala/Function1;)Ljava/lang/Object;
   #58 = InterfaceMethodref #7.#57        // scala/collection/IterableFactory.iterate$:(Lscala/collection/IterableFactory;Ljava/lang/Object;ILscala/Function1;)Ljava/lang/Object;
   #59 = Utf8               Ljava/lang/Object;
   #60 = Utf8               I
   #61 = Utf8               Lscala/Function1;
   #62 = Utf8               unfold
   #63 = Utf8               (Ljava/lang/Object;Lscala/Function1;)Ljava/lang/Object;
   #64 = Utf8               init
   #65 = Utf8               unfold$
   #66 = Utf8               (Lscala/collection/IterableFactory;Ljava/lang/Object;Lscala/Function1;)Ljava/lang/Object;
   #67 = NameAndType        #65:#66       // unfold$:(Lscala/collection/IterableFactory;Ljava/lang/Object;Lscala/Function1;)Ljava/lang/Object;
   #68 = InterfaceMethodref #7.#67        // scala/collection/IterableFactory.unfold$:(Lscala/collection/IterableFactory;Ljava/lang/Object;Lscala/Function1;)Ljava/lang/Object;
   #69 = Utf8               range
   #70 = Utf8               (Ljava/lang/Object;Ljava/lang/Object;Lscala/math/Integral;)Ljava/lang/Object;
   #71 = Utf8               end
   #72 = Utf8               evidence$3
   #73 = Utf8               range$
   #74 = Utf8               (Lscala/collection/IterableFactory;Ljava/lang/Object;Ljava/lang/Object;Lscala/math/Integral;)Ljava/lang/Object;
   #75 = NameAndType        #73:#74       // range$:(Lscala/collection/IterableFactory;Ljava/lang/Object;Ljava/lang/Object;Lscala/math/Integral;)Ljava/lang/Object;
   #76 = InterfaceMethodref #7.#75        // scala/collection/IterableFactory.range$:(Lscala/collection/IterableFactory;Ljava/lang/Object;Ljava/lang/Object;Lscala/math/Integral;)Ljava/lang/Object;
   #77 = Utf8               Lscala/math/Integral;
   #78 = Utf8               (Ljava/lang/Object;Ljava/lang/Object;Ljava/lang/Object;Lscala/math/Integral;)Ljava/lang/Object;
   #79 = Utf8               step
   #80 = Utf8               evidence$4
   #81 = Utf8               (Lscala/collection/IterableFactory;Ljava/lang/Object;Ljava/lang/Object;Ljava/lang/Object;Lscala/math/Integral;)Ljava/lang/Object;
   #82 = NameAndType        #73:#81       // range$:(Lscala/collection/IterableFactory;Ljava/lang/Object;Ljava/lang/Object;Ljava/lang/Object;Lscala/math/Integral;)Ljava/lang/Object;
   #83 = InterfaceMethodref #7.#82        // scala/collection/IterableFactory.range$:(Lscala/collection/IterableFactory;Ljava/lang/Object;Ljava/lang/Object;Ljava/lang/Object;Lscala/math/Integral;)Ljava/lang/Object;
   #84 = Utf8               fill
   #85 = Utf8               (ILscala/Function0;)Ljava/lang/Object;
   #86 = Utf8               n
   #87 = Utf8               elem
   #88 = Utf8               fill$
   #89 = Utf8               (Lscala/collection/IterableFactory;ILscala/Function0;)Ljava/lang/Object;
   #90 = NameAndType        #88:#89       // fill$:(Lscala/collection/IterableFactory;ILscala/Function0;)Ljava/lang/Object;
   #91 = InterfaceMethodref #7.#90        // scala/collection/IterableFactory.fill$:(Lscala/collection/IterableFactory;ILscala/Function0;)Ljava/lang/Object;
   #92 = Utf8               Lscala/Function0;
   #93 = Utf8               (IILscala/Function0;)Ljava/lang/Object;
   #94 = Utf8               n1
   #95 = Utf8               n2
   #96 = Utf8               (Lscala/collection/IterableFactory;IILscala/Function0;)Ljava/lang/Object;
   #97 = NameAndType        #88:#96       // fill$:(Lscala/collection/IterableFactory;IILscala/Function0;)Ljava/lang/Object;
   #98 = InterfaceMethodref #7.#97        // scala/collection/IterableFactory.fill$:(Lscala/collection/IterableFactory;IILscala/Function0;)Ljava/lang/Object;
   #99 = Utf8               (IIILscala/Function0;)Ljava/lang/Object;
  #100 = Utf8               n3
  #101 = Utf8               (Lscala/collection/IterableFactory;IIILscala/Function0;)Ljava/lang/Object;
  #102 = NameAndType        #88:#101      // fill$:(Lscala/collection/IterableFactory;IIILscala/Function0;)Ljava/lang/Object;
  #103 = InterfaceMethodref #7.#102       // scala/collection/IterableFactory.fill$:(Lscala/collection/IterableFactory;IIILscala/Function0;)Ljava/lang/Object;
  #104 = Utf8               (IIIILscala/Function0;)Ljava/lang/Object;
  #105 = Utf8               n4
  #106 = Utf8               (Lscala/collection/IterableFactory;IIIILscala/Function0;)Ljava/lang/Object;
  #107 = NameAndType        #88:#106      // fill$:(Lscala/collection/IterableFactory;IIIILscala/Function0;)Ljava/lang/Object;
  #108 = InterfaceMethodref #7.#107       // scala/collection/IterableFactory.fill$:(Lscala/collection/IterableFactory;IIIILscala/Function0;)Ljava/lang/Object;
  #109 = Utf8               (IIIIILscala/Function0;)Ljava/lang/Object;
  #110 = Utf8               n5
  #111 = Utf8               (Lscala/collection/IterableFactory;IIIIILscala/Function0;)Ljava/lang/Object;
  #112 = NameAndType        #88:#111      // fill$:(Lscala/collection/IterableFactory;IIIIILscala/Function0;)Ljava/lang/Object;
  #113 = InterfaceMethodref #7.#112       // scala/collection/IterableFactory.fill$:(Lscala/collection/IterableFactory;IIIIILscala/Function0;)Ljava/lang/Object;
  #114 = Utf8               tabulate
  #115 = Utf8               (ILscala/Function1;)Ljava/lang/Object;
  #116 = Utf8               tabulate$
  #117 = Utf8               (Lscala/collection/IterableFactory;ILscala/Function1;)Ljava/lang/Object;
  #118 = NameAndType        #116:#117     // tabulate$:(Lscala/collection/IterableFactory;ILscala/Function1;)Ljava/lang/Object;
  #119 = InterfaceMethodref #7.#118       // scala/collection/IterableFactory.tabulate$:(Lscala/collection/IterableFactory;ILscala/Function1;)Ljava/lang/Object;
  #120 = Utf8               (IILscala/Function2;)Ljava/lang/Object;
  #121 = Utf8               (Lscala/collection/IterableFactory;IILscala/Function2;)Ljava/lang/Object;
  #122 = NameAndType        #116:#121     // tabulate$:(Lscala/collection/IterableFactory;IILscala/Function2;)Ljava/lang/Object;
  #123 = InterfaceMethodref #7.#122       // scala/collection/IterableFactory.tabulate$:(Lscala/collection/IterableFactory;IILscala/Function2;)Ljava/lang/Object;
  #124 = Utf8               Lscala/Function2;
  #125 = Utf8               (IIILscala/Function3;)Ljava/lang/Object;
  #126 = Utf8               (Lscala/collection/IterableFactory;IIILscala/Function3;)Ljava/lang/Object;
  #127 = NameAndType        #116:#126     // tabulate$:(Lscala/collection/IterableFactory;IIILscala/Function3;)Ljava/lang/Object;
  #128 = InterfaceMethodref #7.#127       // scala/collection/IterableFactory.tabulate$:(Lscala/collection/IterableFactory;IIILscala/Function3;)Ljava/lang/Object;
  #129 = Utf8               Lscala/Function3;
  #130 = Utf8               (IIIILscala/Function4;)Ljava/lang/Object;
  #131 = Utf8               (Lscala/collection/IterableFactory;IIIILscala/Function4;)Ljava/lang/Object;
  #132 = NameAndType        #116:#131     // tabulate$:(Lscala/collection/IterableFactory;IIIILscala/Function4;)Ljava/lang/Object;
  #133 = InterfaceMethodref #7.#132       // scala/collection/IterableFactory.tabulate$:(Lscala/collection/IterableFactory;IIIILscala/Function4;)Ljava/lang/Object;
  #134 = Utf8               Lscala/Function4;
  #135 = Utf8               (IIIIILscala/Function5;)Ljava/lang/Object;
  #136 = Utf8               (Lscala/collection/IterableFactory;IIIIILscala/Function5;)Ljava/lang/Object;
  #137 = NameAndType        #116:#136     // tabulate$:(Lscala/collection/IterableFactory;IIIIILscala/Function5;)Ljava/lang/Object;
  #138 = InterfaceMethodref #7.#137       // scala/collection/IterableFactory.tabulate$:(Lscala/collection/IterableFactory;IIIIILscala/Function5;)Ljava/lang/Object;
  #139 = Utf8               Lscala/Function5;
  #140 = Utf8               concat
  #141 = Utf8               xss
  #142 = Utf8               concat$
  #143 = NameAndType        #142:#45      // concat$:(Lscala/collection/IterableFactory;Lscala/collection/immutable/Seq;)Ljava/lang/Object;
  #144 = InterfaceMethodref #7.#143       // scala/collection/IterableFactory.concat$:(Lscala/collection/IterableFactory;Lscala/collection/immutable/Seq;)Ljava/lang/Object;
  #145 = Utf8               iterableFactory
  #146 = Utf8               ()Lscala/collection/Factory;
  #147 = Utf8               <A:Ljava/lang/Object;>()Lscala/collection/Factory<TA;Lscala/collection/immutable/HashSet<TA;>;>;
  #148 = Utf8               iterableFactory$
  #149 = Utf8               (Lscala/collection/IterableFactory;)Lscala/collection/Factory;
  #150 = NameAndType        #148:#149     // iterableFactory$:(Lscala/collection/IterableFactory;)Lscala/collection/Factory;
  #151 = InterfaceMethodref #7.#150       // scala/collection/IterableFactory.iterableFactory$:(Lscala/collection/IterableFactory;)Lscala/collection/Factory;
  #152 = Utf8               ()Lscala/collection/immutable/HashSet;
  #153 = Utf8               ()Lscala/collection/immutable/HashSet<Lscala/runtime/Nothing$;>;
  #154 = Utf8               <A:Ljava/lang/Object;>()Lscala/collection/immutable/HashSet<TA;>;
  #155 = NameAndType        #15:#152      // EmptySet:()Lscala/collection/immutable/HashSet;
  #156 = Methodref          #2.#155       // scala/collection/immutable/HashSet$.EmptySet:()Lscala/collection/immutable/HashSet;
  #157 = Utf8               from
  #158 = Utf8               (Lscala/collection/IterableOnce;)Lscala/collection/immutable/HashSet;
  #159 = Utf8               <A:Ljava/lang/Object;>(Lscala/collection/IterableOnce<TA;>;)Lscala/collection/immutable/HashSet<TA;>;
  #160 = Utf8               source
  #161 = Utf8               scala/collection/IterableOnce
  #162 = Class              #161          // scala/collection/IterableOnce
  #163 = Utf8               knownSize
  #164 = Utf8               ()I
  #165 = NameAndType        #163:#164     // knownSize:()I
  #166 = InterfaceMethodref #162.#165     // scala/collection/IterableOnce.knownSize:()I
  #167 = NameAndType        #32:#152      // empty:()Lscala/collection/immutable/HashSet;
  #168 = Methodref          #2.#167       // scala/collection/immutable/HashSet$.empty:()Lscala/collection/immutable/HashSet;
  #169 = Utf8               scala/collection/immutable/HashSetBuilder
  #170 = Class              #169          // scala/collection/immutable/HashSetBuilder
  #171 = Methodref          #170.#21      // scala/collection/immutable/HashSetBuilder."<init>":()V
  #172 = Utf8               addAll
  #173 = Utf8               (Lscala/collection/IterableOnce;)Lscala/collection/immutable/HashSetBuilder;
  #174 = NameAndType        #172:#173     // addAll:(Lscala/collection/IterableOnce;)Lscala/collection/immutable/HashSetBuilder;
  #175 = Methodref          #170.#174     // scala/collection/immutable/HashSetBuilder.addAll:(Lscala/collection/IterableOnce;)Lscala/collection/immutable/HashSetBuilder;
  #176 = Utf8               scala/collection/mutable/ReusableBuilder
  #177 = Class              #176          // scala/collection/mutable/ReusableBuilder
  #178 = Utf8               result
  #179 = Utf8               ()Ljava/lang/Object;
  #180 = NameAndType        #178:#179     // result:()Ljava/lang/Object;
  #181 = InterfaceMethodref #177.#180     // scala/collection/mutable/ReusableBuilder.result:()Ljava/lang/Object;
  #182 = Utf8               Lscala/collection/IterableOnce;
  #183 = Utf8               newBuilder
  #184 = Utf8               ()Lscala/collection/mutable/ReusableBuilder;
  #185 = Utf8               <A:Ljava/lang/Object;>()Lscala/collection/mutable/ReusableBuilder<TA;Lscala/collection/immutable/HashSet<TA;>;>;
  #186 = Utf8               writeReplace
  #187 = Utf8               scala/runtime/ModuleSerializationProxy
  #188 = Class              #187          // scala/runtime/ModuleSerializationProxy
  #189 = Utf8               (Ljava/lang/Class;)V
  #190 = NameAndType        #20:#189      // "<init>":(Ljava/lang/Class;)V
  #191 = Methodref          #188.#190     // scala/runtime/ModuleSerializationProxy."<init>":(Ljava/lang/Class;)V
  #192 = Utf8               ()Lscala/collection/mutable/Builder;
  #193 = NameAndType        #183:#184     // newBuilder:()Lscala/collection/mutable/ReusableBuilder;
  #194 = Methodref          #2.#193       // scala/collection/immutable/HashSet$.newBuilder:()Lscala/collection/mutable/ReusableBuilder;
  #195 = Utf8               (Lscala/collection/IterableOnce;)Ljava/lang/Object;
  #196 = NameAndType        #157:#158     // from:(Lscala/collection/IterableOnce;)Lscala/collection/immutable/HashSet;
  #197 = Methodref          #2.#196       // scala/collection/immutable/HashSet$.from:(Lscala/collection/IterableOnce;)Lscala/collection/immutable/HashSet;
  #198 = Methodref          #5.#21        // java/lang/Object."<init>":()V
  #199 = Utf8               ConstantValue
  #200 = Utf8               Signature
  #201 = Utf8               Code
  #202 = Utf8               LineNumberTable
  #203 = Utf8               LocalVariableTable
  #204 = Utf8               MethodParameters
  #205 = Utf8               StackMapTable
  #206 = Utf8               SourceFile
  #207 = Utf8               ScalaInlineInfo
  #208 = Utf8               Scala
{
  public static final scala.collection.immutable.HashSet$ MODULE$;
    descriptor: Lscala/collection/immutable/HashSet$;
    flags: (0x0019) ACC_PUBLIC, ACC_STATIC, ACC_FINAL

  private static final long serialVersionUID;
    descriptor: J
    flags: (0x001a) ACC_PRIVATE, ACC_STATIC, ACC_FINAL
    ConstantValue: long 3l

  private static final transient scala.collection.immutable.HashSet<scala.runtime.Nothing$> EmptySet;
    descriptor: Lscala/collection/immutable/HashSet;
    flags: (0x009a) ACC_PRIVATE, ACC_STATIC, ACC_FINAL, ACC_TRANSIENT
    Signature: #17                          // Lscala/collection/immutable/HashSet<Lscala/runtime/Nothing$;>;

  public static {};
    descriptor: ()V
    flags: (0x0009) ACC_PUBLIC, ACC_STATIC
    Code:
      stack=3, locals=0, args_size=0
         0: new           #2                  // class scala/collection/immutable/HashSet$
         3: dup
         4: invokespecial #22                 // Method "<init>":()V
         7: putstatic     #24                 // Field MODULE$:Lscala/collection/immutable/HashSet$;
        10: getstatic     #24                 // Field MODULE$:Lscala/collection/immutable/HashSet$;
        13: pop
        14: new           #26                 // class scala/collection/immutable/HashSet
        17: dup
        18: getstatic     #31                 // Field scala/collection/immutable/SetNode$.MODULE$:Lscala/collection/immutable/SetNode$;
        21: invokevirtual #35                 // Method scala/collection/immutable/SetNode$.empty:()Lscala/collection/immutable/BitmapIndexedSetNode;
        24: invokespecial #38                 // Method scala/collection/immutable/HashSet."<init>":(Lscala/collection/immutable/BitmapIndexedSetNode;)V
        27: putstatic     #40                 // Field EmptySet:Lscala/collection/immutable/HashSet;
        30: return
      LineNumberTable:
        line 1918: 0
        line 1921: 14
        line 1918: 30

  public java.lang.Object apply(scala.collection.immutable.Seq);
    descriptor: (Lscala/collection/immutable/Seq;)Ljava/lang/Object;
    flags: (0x0001) ACC_PUBLIC
    Code:
      stack=2, locals=2, args_size=2
         0: aload_0
         1: aload_1
         2: invokestatic  #47                 // InterfaceMethod scala/collection/IterableFactory.apply$:(Lscala/collection/IterableFactory;Lscala/collection/immutable/Seq;)Ljava/lang/Object;
         5: areturn
      LineNumberTable:
        line 1918: 0
      LocalVariableTable:
        Start  Length  Slot  Name   Signature
            0       6     0  this   Lscala/collection/immutable/HashSet$;
            0       6     1 elems   Lscala/collection/immutable/Seq;
    MethodParameters:
      Name                           Flags
      elems                          final

  public java.lang.Object iterate(java.lang.Object, int, scala.Function1);
    descriptor: (Ljava/lang/Object;ILscala/Function1;)Ljava/lang/Object;
    flags: (0x0001) ACC_PUBLIC
    Code:
      stack=4, locals=4, args_size=4
         0: aload_0
         1: aload_1
         2: iload_2
         3: aload_3
         4: invokestatic  #58                 // InterfaceMethod scala/collection/IterableFactory.iterate$:(Lscala/collection/IterableFactory;Ljava/lang/Object;ILscala/Function1;)Ljava/lang/Object;
         7: areturn
      LineNumberTable:
        line 1918: 0
      LocalVariableTable:
        Start  Length  Slot  Name   Signature
            0       8     0  this   Lscala/collection/immutable/HashSet$;
            0       8     1 start   Ljava/lang/Object;
            0       8     2   len   I
            0       8     3     f   Lscala/Function1;
    MethodParameters:
      Name                           Flags
      start                          final
      len                            final
      f                              final

  public java.lang.Object unfold(java.lang.Object, scala.Function1);
    descriptor: (Ljava/lang/Object;Lscala/Function1;)Ljava/lang/Object;
    flags: (0x0001) ACC_PUBLIC
    Code:
      stack=3, locals=3, args_size=3
         0: aload_0
         1: aload_1
         2: aload_2
         3: invokestatic  #68                 // InterfaceMethod scala/collection/IterableFactory.unfold$:(Lscala/collection/IterableFactory;Ljava/lang/Object;Lscala/Function1;)Ljava/lang/Object;
         6: areturn
      LineNumberTable:
        line 1918: 0
      LocalVariableTable:
        Start  Length  Slot  Name   Signature
            0       7     0  this   Lscala/collection/immutable/HashSet$;
            0       7     1  init   Ljava/lang/Object;
            0       7     2     f   Lscala/Function1;
    MethodParameters:
      Name                           Flags
      init                           final
      f                              final

  public java.lang.Object range(java.lang.Object, java.lang.Object, scala.math.Integral);
    descriptor: (Ljava/lang/Object;Ljava/lang/Object;Lscala/math/Integral;)Ljava/lang/Object;
    flags: (0x0001) ACC_PUBLIC
    Code:
      stack=4, locals=4, args_size=4
         0: aload_0
         1: aload_1
         2: aload_2
         3: aload_3
         4: invokestatic  #76                 // InterfaceMethod scala/collection/IterableFactory.range$:(Lscala/collection/IterableFactory;Ljava/lang/Object;Ljava/lang/Object;Lscala/math/Integral;)Ljava/lang/Object;
         7: areturn
      LineNumberTable:
        line 1918: 0
      LocalVariableTable:
        Start  Length  Slot  Name   Signature
            0       8     0  this   Lscala/collection/immutable/HashSet$;
            0       8     1 start   Ljava/lang/Object;
            0       8     2   end   Ljava/lang/Object;
            0       8     3 evidence$3   Lscala/math/Integral;
    MethodParameters:
      Name                           Flags
      start                          final
      end                            final
      evidence$3                     final

  public java.lang.Object range(java.lang.Object, java.lang.Object, java.lang.Object, scala.math.Integral);
    descriptor: (Ljava/lang/Object;Ljava/lang/Object;Ljava/lang/Object;Lscala/math/Integral;)Ljava/lang/Object;
    flags: (0x0001) ACC_PUBLIC
    Code:
      stack=5, locals=5, args_size=5
         0: aload_0
         1: aload_1
         2: aload_2
         3: aload_3
         4: aload         4
         6: invokestatic  #83                 // InterfaceMethod scala/collection/IterableFactory.range$:(Lscala/collection/IterableFactory;Ljava/lang/Object;Ljava/lang/Object;Ljava/lang/Object;Lscala/math/Integral;)Ljava/lang/Object;
         9: areturn
      LineNumberTable:
        line 1918: 0
      LocalVariableTable:
        Start  Length  Slot  Name   Signature
            0      10     0  this   Lscala/collection/immutable/HashSet$;
            0      10     1 start   Ljava/lang/Object;
            0      10     2   end   Ljava/lang/Object;
            0      10     3  step   Ljava/lang/Object;
            0      10     4 evidence$4   Lscala/math/Integral;
    MethodParameters:
      Name                           Flags
      start                          final
      end                            final
      step                           final
      evidence$4                     final

  public java.lang.Object fill(int, scala.Function0);
    descriptor: (ILscala/Function0;)Ljava/lang/Object;
    flags: (0x0001) ACC_PUBLIC
    Code:
      stack=3, locals=3, args_size=3
         0: aload_0
         1: iload_1
         2: aload_2
         3: invokestatic  #91                 // InterfaceMethod scala/collection/IterableFactory.fill$:(Lscala/collection/IterableFactory;ILscala/Function0;)Ljava/lang/Object;
         6: areturn
      LineNumberTable:
        line 1918: 0
      LocalVariableTable:
        Start  Length  Slot  Name   Signature
            0       7     0  this   Lscala/collection/immutable/HashSet$;
            0       7     1     n   I
            0       7     2  elem   Lscala/Function0;
    MethodParameters:
      Name                           Flags
      n                              final
      elem                           final

  public java.lang.Object fill(int, int, scala.Function0);
    descriptor: (IILscala/Function0;)Ljava/lang/Object;
    flags: (0x0001) ACC_PUBLIC
    Code:
      stack=4, locals=4, args_size=4
         0: aload_0
         1: iload_1
         2: iload_2
         3: aload_3
         4: invokestatic  #98                 // InterfaceMethod scala/collection/IterableFactory.fill$:(Lscala/collection/IterableFactory;IILscala/Function0;)Ljava/lang/Object;
         7: areturn
      LineNumberTable:
        line 1918: 0
      LocalVariableTable:
        Start  Length  Slot  Name   Signature
            0       8     0  this   Lscala/collection/immutable/HashSet$;
            0       8     1    n1   I
            0       8     2    n2   I
            0       8     3  elem   Lscala/Function0;
    MethodParameters:
      Name                           Flags
      n1                             final
      n2                             final
      elem                           final

  public java.lang.Object fill(int, int, int, scala.Function0);
    descriptor: (IIILscala/Function0;)Ljava/lang/Object;
    flags: (0x0001) ACC_PUBLIC
    Code:
      stack=5, locals=5, args_size=5
         0: aload_0
         1: iload_1
         2: iload_2
         3: iload_3
         4: aload         4
         6: invokestatic  #103                // InterfaceMethod scala/collection/IterableFactory.fill$:(Lscala/collection/IterableFactory;IIILscala/Function0;)Ljava/lang/Object;
         9: areturn
      LineNumberTable:
        line 1918: 0
      LocalVariableTable:
        Start  Length  Slot  Name   Signature
            0      10     0  this   Lscala/collection/immutable/HashSet$;
            0      10     1    n1   I
            0      10     2    n2   I
            0      10     3    n3   I
            0      10     4  elem   Lscala/Function0;
    MethodParameters:
      Name                           Flags
      n1                             final
      n2                             final
      n3                             final
      elem                           final

  public java.lang.Object fill(int, int, int, int, scala.Function0);
    descriptor: (IIIILscala/Function0;)Ljava/lang/Object;
    flags: (0x0001) ACC_PUBLIC
    Code:
      stack=6, locals=6, args_size=6
         0: aload_0
         1: iload_1
         2: iload_2
         3: iload_3
         4: iload         4
         6: aload         5
         8: invokestatic  #108                // InterfaceMethod scala/collection/IterableFactory.fill$:(Lscala/collection/IterableFactory;IIIILscala/Function0;)Ljava/lang/Object;
        11: areturn
      LineNumberTable:
        line 1918: 0
      LocalVariableTable:
        Start  Length  Slot  Name   Signature
            0      12     0  this   Lscala/collection/immutable/HashSet$;
            0      12     1    n1   I
            0      12     2    n2   I
            0      12     3    n3   I
            0      12     4    n4   I
            0      12     5  elem   Lscala/Function0;
    MethodParameters:
      Name                           Flags
      n1                             final
      n2                             final
      n3                             final
      n4                             final
      elem                           final

  public java.lang.Object fill(int, int, int, int, int, scala.Function0);
    descriptor: (IIIIILscala/Function0;)Ljava/lang/Object;
    flags: (0x0001) ACC_PUBLIC
    Code:
      stack=7, locals=7, args_size=7
         0: aload_0
         1: iload_1
         2: iload_2
         3: iload_3
         4: iload         4
         6: iload         5
         8: aload         6
        10: invokestatic  #113                // InterfaceMethod scala/collection/IterableFactory.fill$:(Lscala/collection/IterableFactory;IIIIILscala/Function0;)Ljava/lang/Object;
        13: areturn
      LineNumberTable:
        line 1918: 0
      LocalVariableTable:
        Start  Length  Slot  Name   Signature
            0      14     0  this   Lscala/collection/immutable/HashSet$;
            0      14     1    n1   I
            0      14     2    n2   I
            0      14     3    n3   I
            0      14     4    n4   I
            0      14     5    n5   I
            0      14     6  elem   Lscala/Function0;
    MethodParameters:
      Name                           Flags
      n1                             final
      n2                             final
      n3                             final
      n4                             final
      n5                             final
      elem                           final

  public java.lang.Object tabulate(int, scala.Function1);
    descriptor: (ILscala/Function1;)Ljava/lang/Object;
    flags: (0x0001) ACC_PUBLIC
    Code:
      stack=3, locals=3, args_size=3
         0: aload_0
         1: iload_1
         2: aload_2
         3: invokestatic  #119                // InterfaceMethod scala/collection/IterableFactory.tabulate$:(Lscala/collection/IterableFactory;ILscala/Function1;)Ljava/lang/Object;
         6: areturn
      LineNumberTable:
        line 1918: 0
      LocalVariableTable:
        Start  Length  Slot  Name   Signature
            0       7     0  this   Lscala/collection/immutable/HashSet$;
            0       7     1     n   I
            0       7     2     f   Lscala/Function1;
    MethodParameters:
      Name                           Flags
      n                              final
      f                              final

  public java.lang.Object tabulate(int, int, scala.Function2);
    descriptor: (IILscala/Function2;)Ljava/lang/Object;
    flags: (0x0001) ACC_PUBLIC
    Code:
      stack=4, locals=4, args_size=4
         0: aload_0
         1: iload_1
         2: iload_2
         3: aload_3
         4: invokestatic  #123                // InterfaceMethod scala/collection/IterableFactory.tabulate$:(Lscala/collection/IterableFactory;IILscala/Function2;)Ljava/lang/Object;
         7: areturn
      LineNumberTable:
        line 1918: 0
      LocalVariableTable:
        Start  Length  Slot  Name   Signature
            0       8     0  this   Lscala/collection/immutable/HashSet$;
            0       8     1    n1   I
            0       8     2    n2   I
            0       8     3     f   Lscala/Function2;
    MethodParameters:
      Name                           Flags
      n1                             final
      n2                             final
      f                              final

  public java.lang.Object tabulate(int, int, int, scala.Function3);
    descriptor: (IIILscala/Function3;)Ljava/lang/Object;
    flags: (0x0001) ACC_PUBLIC
    Code:
      stack=5, locals=5, args_size=5
         0: aload_0
         1: iload_1
         2: iload_2
         3: iload_3
         4: aload         4
         6: invokestatic  #128                // InterfaceMethod scala/collection/IterableFactory.tabulate$:(Lscala/collection/IterableFactory;IIILscala/Function3;)Ljava/lang/Object;
         9: areturn
      LineNumberTable:
        line 1918: 0
      LocalVariableTable:
        Start  Length  Slot  Name   Signature
            0      10     0  this   Lscala/collection/immutable/HashSet$;
            0      10     1    n1   I
            0      10     2    n2   I
            0      10     3    n3   I
            0      10     4     f   Lscala/Function3;
    MethodParameters:
      Name                           Flags
      n1                             final
      n2                             final
      n3                             final
      f                              final

  public java.lang.Object tabulate(int, int, int, int, scala.Function4);
    descriptor: (IIIILscala/Function4;)Ljava/lang/Object;
    flags: (0x0001) ACC_PUBLIC
    Code:
      stack=6, locals=6, args_size=6
         0: aload_0
         1: iload_1
         2: iload_2
         3: iload_3
         4: iload         4
         6: aload         5
         8: invokestatic  #133                // InterfaceMethod scala/collection/IterableFactory.tabulate$:(Lscala/collection/IterableFactory;IIIILscala/Function4;)Ljava/lang/Object;
        11: areturn
      LineNumberTable:
        line 1918: 0
      LocalVariableTable:
        Start  Length  Slot  Name   Signature
            0      12     0  this   Lscala/collection/immutable/HashSet$;
            0      12     1    n1   I
            0      12     2    n2   I
            0      12     3    n3   I
            0      12     4    n4   I
            0      12     5     f   Lscala/Function4;
    MethodParameters:
      Name                           Flags
      n1                             final
      n2                             final
      n3                             final
      n4                             final
      f                              final

  public java.lang.Object tabulate(int, int, int, int, int, scala.Function5);
    descriptor: (IIIIILscala/Function5;)Ljava/lang/Object;
    flags: (0x0001) ACC_PUBLIC
    Code:
      stack=7, locals=7, args_size=7
         0: aload_0
         1: iload_1
         2: iload_2
         3: iload_3
         4: iload         4
         6: iload         5
         8: aload         6
        10: invokestatic  #138                // InterfaceMethod scala/collection/IterableFactory.tabulate$:(Lscala/collection/IterableFactory;IIIIILscala/Function5;)Ljava/lang/Object;
        13: areturn
      LineNumberTable:
        line 1918: 0
      LocalVariableTable:
        Start  Length  Slot  Name   Signature
            0      14     0  this   Lscala/collection/immutable/HashSet$;
            0      14     1    n1   I
            0      14     2    n2   I
            0      14     3    n3   I
            0      14     4    n4   I
            0      14     5    n5   I
            0      14     6     f   Lscala/Function5;
    MethodParameters:
      Name                           Flags
      n1                             final
      n2                             final
      n3                             final
      n4                             final
      n5                             final
      f                              final

  public java.lang.Object concat(scala.collection.immutable.Seq);
    descriptor: (Lscala/collection/immutable/Seq;)Ljava/lang/Object;
    flags: (0x0001) ACC_PUBLIC
    Code:
      stack=2, locals=2, args_size=2
         0: aload_0
         1: aload_1
         2: invokestatic  #144                // InterfaceMethod scala/collection/IterableFactory.concat$:(Lscala/collection/IterableFactory;Lscala/collection/immutable/Seq;)Ljava/lang/Object;
         5: areturn
      LineNumberTable:
        line 1918: 0
      LocalVariableTable:
        Start  Length  Slot  Name   Signature
            0       6     0  this   Lscala/collection/immutable/HashSet$;
            0       6     1   xss   Lscala/collection/immutable/Seq;
    MethodParameters:
      Name                           Flags
      xss                            final

  public <A extends java.lang.Object> scala.collection.Factory<A, scala.collection.immutable.HashSet<A>> iterableFactory();
    descriptor: ()Lscala/collection/Factory;
    flags: (0x0001) ACC_PUBLIC
    Code:
      stack=1, locals=1, args_size=1
         0: aload_0
         1: invokestatic  #151                // InterfaceMethod scala/collection/IterableFactory.iterableFactory$:(Lscala/collection/IterableFactory;)Lscala/collection/Factory;
         4: areturn
      LineNumberTable:
        line 1918: 0
      LocalVariableTable:
        Start  Length  Slot  Name   Signature
            0       5     0  this   Lscala/collection/immutable/HashSet$;
    Signature: #147                         // <A:Ljava/lang/Object;>()Lscala/collection/Factory<TA;Lscala/collection/immutable/HashSet<TA;>;>;

  private final scala.collection.immutable.HashSet<scala.runtime.Nothing$> EmptySet();
    descriptor: ()Lscala/collection/immutable/HashSet;
    flags: (0x0012) ACC_PRIVATE, ACC_FINAL
    Code:
      stack=1, locals=1, args_size=1
         0: getstatic     #40                 // Field EmptySet:Lscala/collection/immutable/HashSet;
         3: areturn
      LineNumberTable:
        line 1921: 0
      LocalVariableTable:
        Start  Length  Slot  Name   Signature
            0       4     0  this   Lscala/collection/immutable/HashSet$;
    Signature: #153                         // ()Lscala/collection/immutable/HashSet<Lscala/runtime/Nothing$;>;

  public <A extends java.lang.Object> scala.collection.immutable.HashSet<A> empty();
    descriptor: ()Lscala/collection/immutable/HashSet;
    flags: (0x0001) ACC_PUBLIC
    Code:
      stack=1, locals=1, args_size=1
         0: aload_0
         1: invokespecial #156                // Method EmptySet:()Lscala/collection/immutable/HashSet;
         4: areturn
      LineNumberTable:
        line 1924: 0
      LocalVariableTable:
        Start  Length  Slot  Name   Signature
            0       5     0  this   Lscala/collection/immutable/HashSet$;
    Signature: #154                         // <A:Ljava/lang/Object;>()Lscala/collection/immutable/HashSet<TA;>;

  public <A extends java.lang.Object> scala.collection.immutable.HashSet<A> from(scala.collection.IterableOnce<A>);
    descriptor: (Lscala/collection/IterableOnce;)Lscala/collection/immutable/HashSet;
    flags: (0x0001) ACC_PUBLIC
    Code:
      stack=2, locals=3, args_size=2
         0: aload_1
         1: instanceof    #26                 // class scala/collection/immutable/HashSet
         4: ifeq          15
         7: aload_1
         8: checkcast     #26                 // class scala/collection/immutable/HashSet
        11: astore_2
        12: goto          53
        15: aload_1
        16: invokeinterface #166,  1          // InterfaceMethod scala/collection/IterableOnce.knownSize:()I
        21: iconst_0
        22: if_icmpne     33
        25: aload_0
        26: invokevirtual #168                // Method empty:()Lscala/collection/immutable/HashSet;
        29: astore_2
        30: goto          53
        33: new           #170                // class scala/collection/immutable/HashSetBuilder
        36: dup
        37: invokespecial #171                // Method scala/collection/immutable/HashSetBuilder."<init>":()V
        40: aload_1
        41: invokevirtual #175                // Method scala/collection/immutable/HashSetBuilder.addAll:(Lscala/collection/IterableOnce;)Lscala/collection/immutable/HashSetBuilder;
        44: invokeinterface #181,  1          // InterfaceMethod scala/collection/mutable/ReusableBuilder.result:()Ljava/lang/Object;
        49: checkcast     #26                 // class scala/collection/immutable/HashSet
        52: astore_2
        53: aload_2
        54: areturn
      StackMapTable: number_of_entries = 3
        frame_type = 15 /* same */
        frame_type = 17 /* same */
        frame_type = 252 /* append */
          offset_delta = 19
          locals = [ class scala/collection/immutable/HashSet ]
      LineNumberTable:
        line 1928: 0
        line 1929: 15
        line 1936: 33
        line 1942: 40
        line 1930: 44
        line 1927: 53
      LocalVariableTable:
        Start  Length  Slot  Name   Signature
            0      55     0  this   Lscala/collection/immutable/HashSet$;
            0      55     1 source   Lscala/collection/IterableOnce;
    Signature: #159                         // <A:Ljava/lang/Object;>(Lscala/collection/IterableOnce<TA;>;)Lscala/collection/immutable/HashSet<TA;>;
    MethodParameters:
      Name                           Flags
      source                         final

  public <A extends java.lang.Object> scala.collection.mutable.ReusableBuilder<A, scala.collection.immutable.HashSet<A>> newBuilder();
    descriptor: ()Lscala/collection/mutable/ReusableBuilder;
    flags: (0x0001) ACC_PUBLIC
    Code:
      stack=2, locals=1, args_size=1
         0: new           #170                // class scala/collection/immutable/HashSetBuilder
         3: dup
         4: invokespecial #171                // Method scala/collection/immutable/HashSetBuilder."<init>":()V
         7: areturn
      LineNumberTable:
        line 1936: 0
      LocalVariableTable:
        Start  Length  Slot  Name   Signature
            0       8     0  this   Lscala/collection/immutable/HashSet$;
    Signature: #185                         // <A:Ljava/lang/Object;>()Lscala/collection/mutable/ReusableBuilder<TA;Lscala/collection/immutable/HashSet<TA;>;>;

  private java.lang.Object writeReplace();
    descriptor: ()Ljava/lang/Object;
    flags: (0x0002) ACC_PRIVATE
    Code:
      stack=3, locals=1, args_size=1
         0: new           #188                // class scala/runtime/ModuleSerializationProxy
         3: dup
         4: ldc           #2                  // class scala/collection/immutable/HashSet$
         6: invokespecial #191                // Method scala/runtime/ModuleSerializationProxy."<init>":(Ljava/lang/Class;)V
         9: areturn
      LineNumberTable:
        line 1918: 0
      LocalVariableTable:
        Start  Length  Slot  Name   Signature
            0      10     0  this   Lscala/collection/immutable/HashSet$;

  public scala.collection.mutable.Builder newBuilder();
    descriptor: ()Lscala/collection/mutable/Builder;
    flags: (0x1041) ACC_PUBLIC, ACC_BRIDGE, ACC_SYNTHETIC
    Code:
      stack=1, locals=1, args_size=1
         0: aload_0
         1: invokevirtual #194                // Method newBuilder:()Lscala/collection/mutable/ReusableBuilder;
         4: areturn
      LineNumberTable:
        line 1918: 0
      LocalVariableTable:
        Start  Length  Slot  Name   Signature
            0       5     0  this   Lscala/collection/immutable/HashSet$;

  public java.lang.Object from(scala.collection.IterableOnce);
    descriptor: (Lscala/collection/IterableOnce;)Ljava/lang/Object;
    flags: (0x1041) ACC_PUBLIC, ACC_BRIDGE, ACC_SYNTHETIC
    Code:
      stack=2, locals=2, args_size=2
         0: aload_0
         1: aload_1
         2: invokevirtual #197                // Method from:(Lscala/collection/IterableOnce;)Lscala/collection/immutable/HashSet;
         5: areturn
      LineNumberTable:
        line 1918: 0
      LocalVariableTable:
        Start  Length  Slot  Name   Signature
            0       6     0  this   Lscala/collection/immutable/HashSet$;
            0       6     1 source   Lscala/collection/IterableOnce;
    MethodParameters:
      Name                           Flags
      source                         final

  public java.lang.Object empty();
    descriptor: ()Ljava/lang/Object;
    flags: (0x1041) ACC_PUBLIC, ACC_BRIDGE, ACC_SYNTHETIC
    Code:
      stack=1, locals=1, args_size=1
         0: aload_0
         1: invokevirtual #168                // Method empty:()Lscala/collection/immutable/HashSet;
         4: areturn
      LineNumberTable:
        line 1918: 0
      LocalVariableTable:
        Start  Length  Slot  Name   Signature
            0       5     0  this   Lscala/collection/immutable/HashSet$;

  private scala.collection.immutable.HashSet$();
    descriptor: ()V
    flags: (0x0002) ACC_PRIVATE
    Code:
      stack=1, locals=1, args_size=1
         0: aload_0
         1: invokespecial #198                // Method java/lang/Object."<init>":()V
         4: return
      LineNumberTable:
        line 1918: 0
      LocalVariableTable:
        Start  Length  Slot  Name   Signature
            0       5     0  this   Lscala/collection/immutable/HashSet$;
}
Signature: #3                           // Ljava/lang/Object;Lscala/collection/IterableFactory<Lscala/collection/immutable/HashSet;>;
SourceFile: "HashSet.scala"
  ScalaInlineInfo: length = 0x86 (unknown attribute)
   01 01 00 1A 00 14 00 13 01 00 0F 00 98 01 00 29
   00 2A 01 00 8C 00 2A 01 00 20 00 B3 01 00 20 00
   98 01 00 54 00 6D 01 00 54 00 68 01 00 54 00 63
   01 00 54 00 5D 01 00 54 00 55 01 00 9D 00 C3 01
   00 9D 00 9E 01 00 91 00 92 01 00 32 00 33 01 00
   B7 00 C0 01 00 B7 00 B8 01 00 45 00 4E 01 00 45
   00 46 01 00 72 00 87 01 00 72 00 82 01 00 72 00
   7D 01 00 72 00 78 01 00 72 00 73 01 00 3E 00 3F
   01 00 BA 00 B3 01
  Scala: length = 0x0 (unknown attribute)

