Classfile /Users/mw/Projects/slang-braindump/.jar/jar11/assemble/slang-braindump/assemble/content/scala/collection/immutable/HashMap$HashKeySet.class
  Last modified May 29, 2022; size 16520 bytes
  SHA-256 checksum 3ad6c1c58259152ae2a2baea2b08d7f60950d7356d63480752d61f651a2dfcc6
  Compiled from "HashMap.scala"
public final class scala.collection.immutable.HashMap$HashKeySet extends scala.collection.immutable.MapOps<K, V, ?, scala.collection.immutable.HashMap<K, V>>.ImmutableKeySet
  minor version: 0
  major version: 52
  flags: (0x0031) ACC_PUBLIC, ACC_FINAL, ACC_SUPER
  this_class: #2                          // scala/collection/immutable/HashMap$HashKeySet
  super_class: #5                         // scala/collection/immutable/MapOps$ImmutableKeySet
  interfaces: 0, fields: 0, methods: 17, attributes: 6
Constant pool:
    #1 = Utf8               scala/collection/immutable/HashMap$HashKeySet
    #2 = Class              #1            // scala/collection/immutable/HashMap$HashKeySet
    #3 = Utf8               Lscala/collection/immutable/MapOps<TK;TV;*Lscala/collection/immutable/HashMap<TK;TV;>;>.ImmutableKeySet;
    #4 = Utf8               scala/collection/immutable/MapOps$ImmutableKeySet
    #5 = Class              #4            // scala/collection/immutable/MapOps$ImmutableKeySet
    #6 = Utf8               HashMap.scala
    #7 = Utf8               java/lang/invoke/MethodHandles$Lookup
    #8 = Class              #7            // java/lang/invoke/MethodHandles$Lookup
    #9 = Utf8               java/lang/invoke/MethodHandles
   #10 = Class              #9            // java/lang/invoke/MethodHandles
   #11 = Utf8               Lookup
   #12 = Utf8               scala/collection/immutable/HashMap
   #13 = Class              #12           // scala/collection/immutable/HashMap
   #14 = Utf8               HashKeySet
   #15 = Utf8               scala/collection/immutable/MapOps
   #16 = Class              #15           // scala/collection/immutable/MapOps
   #17 = Utf8               ImmutableKeySet
   #18 = Utf8               newKeySetOrThis
   #19 = Utf8               (Lscala/collection/immutable/HashMap;)Lscala/collection/immutable/Set;
   #20 = Utf8               (Lscala/collection/immutable/HashMap<TK;*>;)Lscala/collection/immutable/Set<TK;>;
   #21 = Utf8               newHashMap
   #22 = Utf8               scala$collection$immutable$HashMap$HashKeySet$$$outer
   #23 = Utf8               ()Lscala/collection/immutable/HashMap;
   #24 = NameAndType        #22:#23       // scala$collection$immutable$HashMap$HashKeySet$$$outer:()Lscala/collection/immutable/HashMap;
   #25 = Methodref          #2.#24        // scala/collection/immutable/HashMap$HashKeySet.scala$collection$immutable$HashMap$HashKeySet$$$outer:()Lscala/collection/immutable/HashMap;
   #26 = Utf8               keySet
   #27 = Utf8               ()Lscala/collection/immutable/Set;
   #28 = NameAndType        #26:#27       // keySet:()Lscala/collection/immutable/Set;
   #29 = Methodref          #13.#28       // scala/collection/immutable/HashMap.keySet:()Lscala/collection/immutable/Set;
   #30 = Utf8               this
   #31 = Utf8               Lscala/collection/immutable/HashMap$HashKeySet;
   #32 = Utf8               Lscala/collection/immutable/HashMap;
   #33 = Utf8               (Lscala/collection/immutable/BitmapIndexedMapNode;)Lscala/collection/immutable/Set;
   #34 = Utf8               (Lscala/collection/immutable/BitmapIndexedMapNode<TK;*>;)Lscala/collection/immutable/Set<TK;>;
   #35 = Utf8               newRootNode
   #36 = Utf8               rootNode
   #37 = Utf8               ()Lscala/collection/immutable/BitmapIndexedMapNode;
   #38 = NameAndType        #36:#37       // rootNode:()Lscala/collection/immutable/BitmapIndexedMapNode;
   #39 = Methodref          #13.#38       // scala/collection/immutable/HashMap.rootNode:()Lscala/collection/immutable/BitmapIndexedMapNode;
   #40 = Utf8               <init>
   #41 = Utf8               (Lscala/collection/immutable/BitmapIndexedMapNode;)V
   #42 = NameAndType        #40:#41       // "<init>":(Lscala/collection/immutable/BitmapIndexedMapNode;)V
   #43 = Methodref          #13.#42       // scala/collection/immutable/HashMap."<init>":(Lscala/collection/immutable/BitmapIndexedMapNode;)V
   #44 = Utf8               Lscala/collection/immutable/BitmapIndexedMapNode;
   #45 = Utf8               incl
   #46 = Utf8               (Ljava/lang/Object;)Lscala/collection/immutable/Set;
   #47 = Utf8               (TK;)Lscala/collection/immutable/Set<TK;>;
   #48 = Utf8               elem
   #49 = Utf8               scala/runtime/Statics
   #50 = Class              #49           // scala/runtime/Statics
   #51 = Utf8               anyHash
   #52 = Utf8               (Ljava/lang/Object;)I
   #53 = NameAndType        #51:#52       // anyHash:(Ljava/lang/Object;)I
   #54 = Methodref          #50.#53       // scala/runtime/Statics.anyHash:(Ljava/lang/Object;)I
   #55 = Utf8               scala/collection/Hashing$
   #56 = Class              #55           // scala/collection/Hashing$
   #57 = Utf8               MODULE$
   #58 = Utf8               Lscala/collection/Hashing$;
   #59 = NameAndType        #57:#58       // MODULE$:Lscala/collection/Hashing$;
   #60 = Fieldref           #56.#59       // scala/collection/Hashing$.MODULE$:Lscala/collection/Hashing$;
   #61 = Utf8               improve
   #62 = Utf8               (I)I
   #63 = NameAndType        #61:#62       // improve:(I)I
   #64 = Methodref          #56.#63       // scala/collection/Hashing$.improve:(I)I
   #65 = Utf8               scala/collection/immutable/BitmapIndexedMapNode
   #66 = Class              #65           // scala/collection/immutable/BitmapIndexedMapNode
   #67 = Utf8               updated
   #68 = Utf8               (Ljava/lang/Object;Ljava/lang/Object;IIIZ)Lscala/collection/immutable/BitmapIndexedMapNode;
   #69 = NameAndType        #67:#68       // updated:(Ljava/lang/Object;Ljava/lang/Object;IIIZ)Lscala/collection/immutable/BitmapIndexedMapNode;
   #70 = Methodref          #66.#69       // scala/collection/immutable/BitmapIndexedMapNode.updated:(Ljava/lang/Object;Ljava/lang/Object;IIIZ)Lscala/collection/immutable/BitmapIndexedMapNode;
   #71 = NameAndType        #18:#33       // newKeySetOrThis:(Lscala/collection/immutable/BitmapIndexedMapNode;)Lscala/collection/immutable/Set;
   #72 = Methodref          #2.#71        // scala/collection/immutable/HashMap$HashKeySet.newKeySetOrThis:(Lscala/collection/immutable/BitmapIndexedMapNode;)Lscala/collection/immutable/Set;
   #73 = Utf8               originalHash
   #74 = Utf8               I
   #75 = Utf8               improvedHash
   #76 = Utf8               newNode
   #77 = Utf8               Ljava/lang/Object;
   #78 = Utf8               excl
   #79 = Utf8               removed
   #80 = Utf8               (Ljava/lang/Object;)Lscala/collection/immutable/HashMap;
   #81 = NameAndType        #79:#80       // removed:(Ljava/lang/Object;)Lscala/collection/immutable/HashMap;
   #82 = Methodref          #13.#81       // scala/collection/immutable/HashMap.removed:(Ljava/lang/Object;)Lscala/collection/immutable/HashMap;
   #83 = NameAndType        #18:#19       // newKeySetOrThis:(Lscala/collection/immutable/HashMap;)Lscala/collection/immutable/Set;
   #84 = Methodref          #2.#83        // scala/collection/immutable/HashMap$HashKeySet.newKeySetOrThis:(Lscala/collection/immutable/HashMap;)Lscala/collection/immutable/Set;
   #85 = Utf8               java/lang/Object
   #86 = Class              #85           // java/lang/Object
   #87 = Utf8               filter
   #88 = Utf8               (Lscala/Function1;)Lscala/collection/immutable/Set;
   #89 = Utf8               (Lscala/Function1<TK;Ljava/lang/Object;>;)Lscala/collection/immutable/Set<TK;>;
   #90 = Utf8               pred
   #91 = Utf8               (Ljava/lang/Object;)Ljava/lang/Object;
   #92 = MethodType         #91           //  (Ljava/lang/Object;)Ljava/lang/Object;
   #93 = Utf8               $anonfun$filter$1$adapted
   #94 = Utf8               (Lscala/Function1;Lscala/Tuple2;)Ljava/lang/Object;
   #95 = NameAndType        #93:#94       // $anonfun$filter$1$adapted:(Lscala/Function1;Lscala/Tuple2;)Ljava/lang/Object;
   #96 = Methodref          #2.#95        // scala/collection/immutable/HashMap$HashKeySet.$anonfun$filter$1$adapted:(Lscala/Function1;Lscala/Tuple2;)Ljava/lang/Object;
   #97 = MethodHandle       6:#96         // REF_invokeStatic scala/collection/immutable/HashMap$HashKeySet.$anonfun$filter$1$adapted:(Lscala/Function1;Lscala/Tuple2;)Ljava/lang/Object;
   #98 = Utf8               (Lscala/Tuple2;)Ljava/lang/Object;
   #99 = MethodType         #98           //  (Lscala/Tuple2;)Ljava/lang/Object;
  #100 = Integer            5
  #101 = Integer            1
  #102 = Utf8               java/lang/invoke/LambdaMetafactory
  #103 = Class              #102          // java/lang/invoke/LambdaMetafactory
  #104 = Utf8               altMetafactory
  #105 = Utf8               (Ljava/lang/invoke/MethodHandles$Lookup;Ljava/lang/String;Ljava/lang/invoke/MethodType;[Ljava/lang/Object;)Ljava/lang/invoke/CallSite;
  #106 = NameAndType        #104:#105     // altMetafactory:(Ljava/lang/invoke/MethodHandles$Lookup;Ljava/lang/String;Ljava/lang/invoke/MethodType;[Ljava/lang/Object;)Ljava/lang/invoke/CallSite;
  #107 = Methodref          #103.#106     // java/lang/invoke/LambdaMetafactory.altMetafactory:(Ljava/lang/invoke/MethodHandles$Lookup;Ljava/lang/String;Ljava/lang/invoke/MethodType;[Ljava/lang/Object;)Ljava/lang/invoke/CallSite;
  #108 = MethodHandle       6:#107        // REF_invokeStatic java/lang/invoke/LambdaMetafactory.altMetafactory:(Ljava/lang/invoke/MethodHandles$Lookup;Ljava/lang/String;Ljava/lang/invoke/MethodType;[Ljava/lang/Object;)Ljava/lang/invoke/CallSite;
  #109 = Utf8               apply
  #110 = Utf8               (Lscala/Function1;)Lscala/Function1;
  #111 = NameAndType        #109:#110     // apply:(Lscala/Function1;)Lscala/Function1;
  #112 = InvokeDynamic      #0:#111       // #0:apply:(Lscala/Function1;)Lscala/Function1;
  #113 = Utf8               size
  #114 = Utf8               ()I
  #115 = NameAndType        #113:#114     // size:()I
  #116 = Methodref          #66.#115      // scala/collection/immutable/BitmapIndexedMapNode.size:()I
  #117 = Utf8               getPayload
  #118 = Utf8               (I)Lscala/Tuple2;
  #119 = NameAndType        #117:#118     // getPayload:(I)Lscala/Tuple2;
  #120 = Methodref          #66.#119      // scala/collection/immutable/BitmapIndexedMapNode.getPayload:(I)Lscala/Tuple2;
  #121 = Utf8               scala/Tuple2
  #122 = Class              #121          // scala/Tuple2
  #123 = Utf8               _1
  #124 = Utf8               ()Ljava/lang/Object;
  #125 = NameAndType        #123:#124     // _1:()Ljava/lang/Object;
  #126 = Methodref          #122.#125     // scala/Tuple2._1:()Ljava/lang/Object;
  #127 = Utf8               scala/Function1
  #128 = Class              #127          // scala/Function1
  #129 = NameAndType        #109:#91      // apply:(Ljava/lang/Object;)Ljava/lang/Object;
  #130 = InterfaceMethodref #128.#129     // scala/Function1.apply:(Ljava/lang/Object;)Ljava/lang/Object;
  #131 = Utf8               scala/runtime/BoxesRunTime
  #132 = Class              #131          // scala/runtime/BoxesRunTime
  #133 = Utf8               unboxToBoolean
  #134 = Utf8               (Ljava/lang/Object;)Z
  #135 = NameAndType        #133:#134     // unboxToBoolean:(Ljava/lang/Object;)Z
  #136 = Methodref          #132.#135     // scala/runtime/BoxesRunTime.unboxToBoolean:(Ljava/lang/Object;)Z
  #137 = Utf8               scala/collection/immutable/MapNode$
  #138 = Class              #137          // scala/collection/immutable/MapNode$
  #139 = Utf8               Lscala/collection/immutable/MapNode$;
  #140 = NameAndType        #57:#139      // MODULE$:Lscala/collection/immutable/MapNode$;
  #141 = Fieldref           #138.#140     // scala/collection/immutable/MapNode$.MODULE$:Lscala/collection/immutable/MapNode$;
  #142 = Utf8               empty
  #143 = NameAndType        #142:#37      // empty:()Lscala/collection/immutable/BitmapIndexedMapNode;
  #144 = Methodref          #138.#143     // scala/collection/immutable/MapNode$.empty:()Lscala/collection/immutable/BitmapIndexedMapNode;
  #145 = Utf8               nodeMap
  #146 = NameAndType        #145:#114     // nodeMap:()I
  #147 = Methodref          #66.#146      // scala/collection/immutable/BitmapIndexedMapNode.nodeMap:()I
  #148 = Utf8               dataMap
  #149 = NameAndType        #148:#114     // dataMap:()I
  #150 = Methodref          #66.#149      // scala/collection/immutable/BitmapIndexedMapNode.dataMap:()I
  #151 = Utf8               java/lang/Integer
  #152 = Class              #151          // java/lang/Integer
  #153 = Utf8               numberOfTrailingZeros
  #154 = NameAndType        #153:#62      // numberOfTrailingZeros:(I)I
  #155 = Methodref          #152.#154     // java/lang/Integer.numberOfTrailingZeros:(I)I
  #156 = Utf8               numberOfLeadingZeros
  #157 = NameAndType        #156:#62      // numberOfLeadingZeros:(I)I
  #158 = Methodref          #152.#157     // java/lang/Integer.numberOfLeadingZeros:(I)I
  #159 = Utf8               scala/collection/immutable/Node$
  #160 = Class              #159          // scala/collection/immutable/Node$
  #161 = Utf8               Lscala/collection/immutable/Node$;
  #162 = NameAndType        #57:#161      // MODULE$:Lscala/collection/immutable/Node$;
  #163 = Fieldref           #160.#162     // scala/collection/immutable/Node$.MODULE$:Lscala/collection/immutable/Node$;
  #164 = Utf8               originalHashes
  #165 = Utf8               ()[I
  #166 = NameAndType        #164:#165     // originalHashes:()[I
  #167 = Methodref          #66.#166      // scala/collection/immutable/BitmapIndexedMapNode.originalHashes:()[I
  #168 = Utf8               bitCount
  #169 = NameAndType        #168:#62      // bitCount:(I)I
  #170 = Methodref          #152.#169     // java/lang/Integer.bitCount:(I)I
  #171 = Utf8               content
  #172 = Utf8               ()[Ljava/lang/Object;
  #173 = NameAndType        #171:#172     // content:()[Ljava/lang/Object;
  #174 = Methodref          #66.#173      // scala/collection/immutable/BitmapIndexedMapNode.content:()[Ljava/lang/Object;
  #175 = Utf8               (II[Ljava/lang/Object;[III)V
  #176 = NameAndType        #40:#175      // "<init>":(II[Ljava/lang/Object;[III)V
  #177 = Methodref          #66.#176      // scala/collection/immutable/BitmapIndexedMapNode."<init>":(II[Ljava/lang/Object;[III)V
  #178 = Utf8               getNode
  #179 = Utf8               (I)Lscala/collection/immutable/MapNode;
  #180 = NameAndType        #178:#179     // getNode:(I)Lscala/collection/immutable/MapNode;
  #181 = Methodref          #66.#180      // scala/collection/immutable/BitmapIndexedMapNode.getNode:(I)Lscala/collection/immutable/MapNode;
  #182 = Utf8               scala/collection/immutable/MapNode
  #183 = Class              #182          // scala/collection/immutable/MapNode
  #184 = Utf8               filterImpl
  #185 = Utf8               (Lscala/Function1;Z)Lscala/collection/immutable/MapNode;
  #186 = NameAndType        #184:#185     // filterImpl:(Lscala/Function1;Z)Lscala/collection/immutable/MapNode;
  #187 = Methodref          #183.#186     // scala/collection/immutable/MapNode.filterImpl:(Lscala/Function1;Z)Lscala/collection/immutable/MapNode;
  #188 = Methodref          #183.#115     // scala/collection/immutable/MapNode.size:()I
  #189 = Utf8               cachedJavaKeySetHashCode
  #190 = NameAndType        #189:#114     // cachedJavaKeySetHashCode:()I
  #191 = Methodref          #183.#190     // scala/collection/immutable/MapNode.cachedJavaKeySetHashCode:()I
  #192 = Utf8               scala/collection/mutable/Queue$
  #193 = Class              #192          // scala/collection/mutable/Queue$
  #194 = Utf8               Lscala/collection/mutable/Queue$;
  #195 = NameAndType        #57:#194      // MODULE$:Lscala/collection/mutable/Queue$;
  #196 = Fieldref           #193.#195     // scala/collection/mutable/Queue$.MODULE$:Lscala/collection/mutable/Queue$;
  #197 = Utf8               ()Lscala/collection/mutable/Queue;
  #198 = NameAndType        #142:#197     // empty:()Lscala/collection/mutable/Queue;
  #199 = Methodref          #193.#198     // scala/collection/mutable/Queue$.empty:()Lscala/collection/mutable/Queue;
  #200 = Utf8               scala/collection/mutable/Queue
  #201 = Class              #200          // scala/collection/mutable/Queue
  #202 = Utf8               $plus$eq
  #203 = Utf8               (Ljava/lang/Object;)Lscala/collection/mutable/Growable;
  #204 = NameAndType        #202:#203     // $plus$eq:(Ljava/lang/Object;)Lscala/collection/mutable/Growable;
  #205 = Methodref          #201.#204     // scala/collection/mutable/Queue.$plus$eq:(Ljava/lang/Object;)Lscala/collection/mutable/Growable;
  #206 = Utf8               scala/collection/immutable/Nil$
  #207 = Class              #206          // scala/collection/immutable/Nil$
  #208 = Utf8               Lscala/collection/immutable/Nil$;
  #209 = NameAndType        #57:#208      // MODULE$:Lscala/collection/immutable/Nil$;
  #210 = Fieldref           #207.#209     // scala/collection/immutable/Nil$.MODULE$:Lscala/collection/immutable/Nil$;
  #211 = Utf8               scala/collection/IterableFactory
  #212 = Class              #211          // scala/collection/IterableFactory
  #213 = Utf8               apply$
  #214 = Utf8               (Lscala/collection/IterableFactory;Lscala/collection/immutable/Seq;)Ljava/lang/Object;
  #215 = NameAndType        #213:#214     // apply$:(Lscala/collection/IterableFactory;Lscala/collection/immutable/Seq;)Ljava/lang/Object;
  #216 = InterfaceMethodref #212.#215     // scala/collection/IterableFactory.apply$:(Lscala/collection/IterableFactory;Lscala/collection/immutable/Seq;)Ljava/lang/Object;
  #217 = Utf8               bitposFrom
  #218 = NameAndType        #217:#62      // bitposFrom:(I)I
  #219 = Methodref          #160.#218     // scala/collection/immutable/Node$.bitposFrom:(I)I
  #220 = Utf8               dequeue
  #221 = NameAndType        #220:#124     // dequeue:()Ljava/lang/Object;
  #222 = Methodref          #201.#221     // scala/collection/mutable/Queue.dequeue:()Ljava/lang/Object;
  #223 = Utf8               getKey
  #224 = Utf8               (I)Ljava/lang/Object;
  #225 = NameAndType        #223:#224     // getKey:(I)Ljava/lang/Object;
  #226 = Methodref          #183.#225     // scala/collection/immutable/MapNode.getKey:(I)Ljava/lang/Object;
  #227 = Utf8               getValue
  #228 = NameAndType        #227:#224     // getValue:(I)Ljava/lang/Object;
  #229 = Methodref          #183.#228     // scala/collection/immutable/MapNode.getValue:(I)Ljava/lang/Object;
  #230 = Utf8               getHash
  #231 = NameAndType        #230:#62      // getHash:(I)I
  #232 = Methodref          #183.#231     // scala/collection/immutable/MapNode.getHash:(I)I
  #233 = Utf8               scala/collection/immutable/HashMap$
  #234 = Class              #233          // scala/collection/immutable/HashMap$
  #235 = Utf8               Lscala/collection/immutable/HashMap$;
  #236 = NameAndType        #57:#235      // MODULE$:Lscala/collection/immutable/HashMap$;
  #237 = Fieldref           #234.#236     // scala/collection/immutable/HashMap$.MODULE$:Lscala/collection/immutable/HashMap$;
  #238 = NameAndType        #142:#23      // empty:()Lscala/collection/immutable/HashMap;
  #239 = Methodref          #234.#238     // scala/collection/immutable/HashMap$.empty:()Lscala/collection/immutable/HashMap;
  #240 = Utf8               Lscala/Function1;
  #241 = Utf8               filter_this
  #242 = Utf8               filter_pred
  #243 = Utf8               filterImpl_isFlipped
  #244 = Utf8               Z
  #245 = Utf8               filterImpl_newRootNode
  #246 = Utf8               filterImpl_filterImpl_newSize
  #247 = Utf8               filterImpl_filterImpl_newContent
  #248 = Utf8               [Ljava/lang/Object;
  #249 = Utf8               filterImpl_filterImpl_newOriginalHashCodes
  #250 = Utf8               [I
  #251 = Utf8               filterImpl_filterImpl_newMaximumIndex
  #252 = Utf8               filterImpl_filterImpl_j
  #253 = Utf8               filterImpl_filterImpl_newDataIndex
  #254 = Utf8               filterImpl_filterImpl_minimumIndex
  #255 = Utf8               filterImpl_filterImpl_maximumIndex
  #256 = Utf8               filterImpl_filterImpl_newDataMap
  #257 = Utf8               filterImpl_filterImpl_newCachedHashCode
  #258 = Utf8               filterImpl_filterImpl_dataIndex
  #259 = Utf8               filterImpl_filterImpl_i
  #260 = Utf8               filterImpl_filterImpl_oldSubNode
  #261 = Utf8               Lscala/collection/immutable/MapNode;
  #262 = Utf8               filterImpl_filterImpl_newSubNode
  #263 = Utf8               filterImpl_filterImpl_node
  #264 = Utf8               filterImpl_filterImpl_bitpos
  #265 = Utf8               filterImpl_filterImpl_newDataSize
  #266 = Utf8               filterImpl_filterImpl_newContentSize
  #267 = Utf8               filterImpl_filterImpl_newOriginalHashes
  #268 = Utf8               filterImpl_filterImpl_newAllMap
  #269 = Utf8               filterImpl_filterImpl_maxIndex
  #270 = Utf8               filterImpl_filterImpl_oldDataIndex
  #271 = Utf8               filterImpl_filterImpl_oldNodeIndex
  #272 = Utf8               filterImpl_filterImpl_newNodeIndex
  #273 = Utf8               filterImpl_filterImpl_allMap
  #274 = Utf8               filterImpl_filterImpl_oldDataPassThrough
  #275 = Utf8               filterImpl_filterImpl_nodeMigrateToDataTargetMap
  #276 = Utf8               filterImpl_filterImpl_nodesToMigrateToData
  #277 = Utf8               Lscala/collection/mutable/Queue;
  #278 = Utf8               filterImpl_filterImpl_nodesToPassThroughMap
  #279 = Utf8               filterImpl_filterImpl_mapOfNewNodes
  #280 = Utf8               filterImpl_filterImpl_newNodes
  #281 = Utf8               filterImpl_filterImpl_newNodeMap
  #282 = Utf8               filterImpl_filterImpl_nodeIndex
  #283 = Utf8               filterImpl_filterImpl_this
  #284 = Class              #248          // "[Ljava/lang/Object;"
  #285 = Class              #250          // "[I"
  #286 = Utf8               filterNot
  #287 = Utf8               $anonfun$filterNot$1$adapted
  #288 = NameAndType        #287:#94      // $anonfun$filterNot$1$adapted:(Lscala/Function1;Lscala/Tuple2;)Ljava/lang/Object;
  #289 = Methodref          #2.#288       // scala/collection/immutable/HashMap$HashKeySet.$anonfun$filterNot$1$adapted:(Lscala/Function1;Lscala/Tuple2;)Ljava/lang/Object;
  #290 = MethodHandle       6:#289        // REF_invokeStatic scala/collection/immutable/HashMap$HashKeySet.$anonfun$filterNot$1$adapted:(Lscala/Function1;Lscala/Tuple2;)Ljava/lang/Object;
  #291 = InvokeDynamic      #1:#111       // #1:apply:(Lscala/Function1;)Lscala/Function1;
  #292 = Utf8               filterNot_this
  #293 = Utf8               filterNot_pred
  #294 = Utf8               $outer
  #295 = Utf8               Lscala/collection/immutable/MapOps;
  #296 = NameAndType        #294:#295     // $outer:Lscala/collection/immutable/MapOps;
  #297 = Fieldref           #2.#296       // scala/collection/immutable/HashMap$HashKeySet.$outer:Lscala/collection/immutable/MapOps;
  #298 = Utf8               (Lscala/Function1;)Ljava/lang/Object;
  #299 = NameAndType        #286:#88      // filterNot:(Lscala/Function1;)Lscala/collection/immutable/Set;
  #300 = Methodref          #2.#299       // scala/collection/immutable/HashMap$HashKeySet.filterNot:(Lscala/Function1;)Lscala/collection/immutable/Set;
  #301 = NameAndType        #87:#88       // filter:(Lscala/Function1;)Lscala/collection/immutable/Set;
  #302 = Methodref          #2.#301       // scala/collection/immutable/HashMap$HashKeySet.filter:(Lscala/Function1;)Lscala/collection/immutable/Set;
  #303 = Utf8               (Ljava/lang/Object;)Lscala/collection/immutable/SetOps;
  #304 = NameAndType        #78:#46       // excl:(Ljava/lang/Object;)Lscala/collection/immutable/Set;
  #305 = Methodref          #2.#304       // scala/collection/immutable/HashMap$HashKeySet.excl:(Ljava/lang/Object;)Lscala/collection/immutable/Set;
  #306 = NameAndType        #45:#46       // incl:(Ljava/lang/Object;)Lscala/collection/immutable/Set;
  #307 = Methodref          #2.#306       // scala/collection/immutable/HashMap$HashKeySet.incl:(Ljava/lang/Object;)Lscala/collection/immutable/Set;
  #308 = Utf8               $anonfun$filter$1
  #309 = Utf8               (Lscala/Function1;Lscala/Tuple2;)Z
  #310 = Utf8               pred$1
  #311 = Utf8               kv
  #312 = Utf8               Lscala/Tuple2;
  #313 = Utf8               $anonfun$filterNot$1
  #314 = Utf8               pred$2
  #315 = Utf8               (Lscala/collection/immutable/HashMap;)V
  #316 = Utf8               (Lscala/collection/immutable/MapOps;)V
  #317 = NameAndType        #40:#316      // "<init>":(Lscala/collection/immutable/MapOps;)V
  #318 = Methodref          #5.#317       // scala/collection/immutable/MapOps$ImmutableKeySet."<init>":(Lscala/collection/immutable/MapOps;)V
  #319 = NameAndType        #308:#309     // $anonfun$filter$1:(Lscala/Function1;Lscala/Tuple2;)Z
  #320 = Methodref          #2.#319       // scala/collection/immutable/HashMap$HashKeySet.$anonfun$filter$1:(Lscala/Function1;Lscala/Tuple2;)Z
  #321 = Utf8               boxToBoolean
  #322 = Utf8               (Z)Ljava/lang/Boolean;
  #323 = NameAndType        #321:#322     // boxToBoolean:(Z)Ljava/lang/Boolean;
  #324 = Methodref          #132.#323     // scala/runtime/BoxesRunTime.boxToBoolean:(Z)Ljava/lang/Boolean;
  #325 = NameAndType        #313:#309     // $anonfun$filterNot$1:(Lscala/Function1;Lscala/Tuple2;)Z
  #326 = Methodref          #2.#325       // scala/collection/immutable/HashMap$HashKeySet.$anonfun$filterNot$1:(Lscala/Function1;Lscala/Tuple2;)Z
  #327 = Utf8               $deserializeLambda$
  #328 = Utf8               (Ljava/lang/invoke/SerializedLambda;)Ljava/lang/Object;
  #329 = Utf8               scala/runtime/LambdaDeserialize
  #330 = Class              #329          // scala/runtime/LambdaDeserialize
  #331 = Utf8               bootstrap
  #332 = Utf8               (Ljava/lang/invoke/MethodHandles$Lookup;Ljava/lang/String;Ljava/lang/invoke/MethodType;[Ljava/lang/invoke/MethodHandle;)Ljava/lang/invoke/CallSite;
  #333 = NameAndType        #331:#332     // bootstrap:(Ljava/lang/invoke/MethodHandles$Lookup;Ljava/lang/String;Ljava/lang/invoke/MethodType;[Ljava/lang/invoke/MethodHandle;)Ljava/lang/invoke/CallSite;
  #334 = Methodref          #330.#333     // scala/runtime/LambdaDeserialize.bootstrap:(Ljava/lang/invoke/MethodHandles$Lookup;Ljava/lang/String;Ljava/lang/invoke/MethodType;[Ljava/lang/invoke/MethodHandle;)Ljava/lang/invoke/CallSite;
  #335 = MethodHandle       6:#334        // REF_invokeStatic scala/runtime/LambdaDeserialize.bootstrap:(Ljava/lang/invoke/MethodHandles$Lookup;Ljava/lang/String;Ljava/lang/invoke/MethodType;[Ljava/lang/invoke/MethodHandle;)Ljava/lang/invoke/CallSite;
  #336 = Utf8               lambdaDeserialize
  #337 = NameAndType        #336:#328     // lambdaDeserialize:(Ljava/lang/invoke/SerializedLambda;)Ljava/lang/Object;
  #338 = InvokeDynamic      #2:#337       // #2:lambdaDeserialize:(Ljava/lang/invoke/SerializedLambda;)Ljava/lang/Object;
  #339 = Utf8               Code
  #340 = Utf8               StackMapTable
  #341 = Utf8               LineNumberTable
  #342 = Utf8               LocalVariableTable
  #343 = Utf8               Signature
  #344 = Utf8               MethodParameters
  #345 = Utf8               InnerClasses
  #346 = Utf8               SourceFile
  #347 = Utf8               BootstrapMethods
  #348 = Utf8               ScalaInlineInfo
  #349 = Utf8               Scala
{
  private scala.collection.immutable.Set<K> newKeySetOrThis(scala.collection.immutable.HashMap<K, ?>);
    descriptor: (Lscala/collection/immutable/HashMap;)Lscala/collection/immutable/Set;
    flags: (0x0002) ACC_PRIVATE
    Code:
      stack=2, locals=2, args_size=2
         0: aload_1
         1: aload_0
         2: invokevirtual #25                 // Method scala$collection$immutable$HashMap$HashKeySet$$$outer:()Lscala/collection/immutable/HashMap;
         5: if_acmpne     10
         8: aload_0
         9: areturn
        10: aload_1
        11: invokevirtual #29                 // Method scala/collection/immutable/HashMap.keySet:()Lscala/collection/immutable/Set;
        14: areturn
      StackMapTable: number_of_entries = 1
        frame_type = 10 /* same */
      LineNumberTable:
        line 63: 0
      LocalVariableTable:
        Start  Length  Slot  Name   Signature
            0      15     0  this   Lscala/collection/immutable/HashMap$HashKeySet;
            0      15     1 newHashMap   Lscala/collection/immutable/HashMap;
    Signature: #20                          // (Lscala/collection/immutable/HashMap<TK;*>;)Lscala/collection/immutable/Set<TK;>;
    MethodParameters:
      Name                           Flags
      newHashMap                     final

  private scala.collection.immutable.Set<K> newKeySetOrThis(scala.collection.immutable.BitmapIndexedMapNode<K, ?>);
    descriptor: (Lscala/collection/immutable/BitmapIndexedMapNode;)Lscala/collection/immutable/Set;
    flags: (0x0002) ACC_PRIVATE
    Code:
      stack=3, locals=2, args_size=2
         0: aload_1
         1: aload_0
         2: invokevirtual #25                 // Method scala$collection$immutable$HashMap$HashKeySet$$$outer:()Lscala/collection/immutable/HashMap;
         5: invokevirtual #39                 // Method scala/collection/immutable/HashMap.rootNode:()Lscala/collection/immutable/BitmapIndexedMapNode;
         8: if_acmpne     13
        11: aload_0
        12: areturn
        13: new           #13                 // class scala/collection/immutable/HashMap
        16: dup
        17: aload_1
        18: invokespecial #43                 // Method scala/collection/immutable/HashMap."<init>":(Lscala/collection/immutable/BitmapIndexedMapNode;)V
        21: invokevirtual #29                 // Method scala/collection/immutable/HashMap.keySet:()Lscala/collection/immutable/Set;
        24: areturn
      StackMapTable: number_of_entries = 1
        frame_type = 13 /* same */
      LineNumberTable:
        line 65: 0
      LocalVariableTable:
        Start  Length  Slot  Name   Signature
            0      25     0  this   Lscala/collection/immutable/HashMap$HashKeySet;
            0      25     1 newRootNode   Lscala/collection/immutable/BitmapIndexedMapNode;
    Signature: #34                          // (Lscala/collection/immutable/BitmapIndexedMapNode<TK;*>;)Lscala/collection/immutable/Set<TK;>;
    MethodParameters:
      Name                           Flags
      newRootNode                    final

  public scala.collection.immutable.Set<K> incl(K);
    descriptor: (Ljava/lang/Object;)Lscala/collection/immutable/Set;
    flags: (0x0001) ACC_PUBLIC
    Code:
      stack=7, locals=5, args_size=2
         0: aload_1
         1: invokestatic  #54                 // Method scala/runtime/Statics.anyHash:(Ljava/lang/Object;)I
         4: istore_2
         5: getstatic     #60                 // Field scala/collection/Hashing$.MODULE$:Lscala/collection/Hashing$;
         8: iload_2
         9: invokevirtual #64                 // Method scala/collection/Hashing$.improve:(I)I
        12: istore_3
        13: aload_0
        14: invokevirtual #25                 // Method scala$collection$immutable$HashMap$HashKeySet$$$outer:()Lscala/collection/immutable/HashMap;
        17: invokevirtual #39                 // Method scala/collection/immutable/HashMap.rootNode:()Lscala/collection/immutable/BitmapIndexedMapNode;
        20: aload_1
        21: aconst_null
        22: iload_2
        23: iload_3
        24: iconst_0
        25: iconst_0
        26: invokevirtual #70                 // Method scala/collection/immutable/BitmapIndexedMapNode.updated:(Ljava/lang/Object;Ljava/lang/Object;IIIZ)Lscala/collection/immutable/BitmapIndexedMapNode;
        29: astore        4
        31: aload_0
        32: aload         4
        34: invokespecial #72                 // Method newKeySetOrThis:(Lscala/collection/immutable/BitmapIndexedMapNode;)Lscala/collection/immutable/Set;
        37: areturn
      LineNumberTable:
        line 68: 0
        line 69: 5
        line 70: 13
        line 71: 31
      LocalVariableTable:
        Start  Length  Slot  Name   Signature
            5      32     2 originalHash   I
           13      24     3 improvedHash   I
           31       6     4 newNode   Lscala/collection/immutable/BitmapIndexedMapNode;
            0      38     0  this   Lscala/collection/immutable/HashMap$HashKeySet;
            0      38     1  elem   Ljava/lang/Object;
    Signature: #47                          // (TK;)Lscala/collection/immutable/Set<TK;>;
    MethodParameters:
      Name                           Flags
      elem                           final

  public scala.collection.immutable.Set<K> excl(K);
    descriptor: (Ljava/lang/Object;)Lscala/collection/immutable/Set;
    flags: (0x0001) ACC_PUBLIC
    Code:
      stack=3, locals=2, args_size=2
         0: aload_0
         1: aload_0
         2: invokevirtual #25                 // Method scala$collection$immutable$HashMap$HashKeySet$$$outer:()Lscala/collection/immutable/HashMap;
         5: dup
         6: ifnonnull     11
         9: aconst_null
        10: athrow
        11: aload_1
        12: invokevirtual #82                 // Method scala/collection/immutable/HashMap.removed:(Ljava/lang/Object;)Lscala/collection/immutable/HashMap;
        15: invokespecial #84                 // Method newKeySetOrThis:(Lscala/collection/immutable/HashMap;)Lscala/collection/immutable/Set;
        18: areturn
      StackMapTable: number_of_entries = 1
        frame_type = 255 /* full_frame */
          offset_delta = 11
          locals = [ class scala/collection/immutable/HashMap$HashKeySet, class java/lang/Object ]
          stack = [ class scala/collection/immutable/HashMap$HashKeySet, class scala/collection/immutable/HashMap ]
      LineNumberTable:
        line 73: 0
        line 39: 11
        line 73: 15
      LocalVariableTable:
        Start  Length  Slot  Name   Signature
            0      19     0  this   Lscala/collection/immutable/HashMap$HashKeySet;
            0      19     1  elem   Ljava/lang/Object;
    Signature: #47                          // (TK;)Lscala/collection/immutable/Set<TK;>;
    MethodParameters:
      Name                           Flags
      elem                           final

  public scala.collection.immutable.Set<K> filter(scala.Function1<K, java.lang.Object>);
    descriptor: (Lscala/Function1;)Lscala/collection/immutable/Set;
    flags: (0x0001) ACC_PUBLIC
    Code:
      stack=9, locals=55, args_size=2
         0: aload_0
         1: aload_0
         2: invokevirtual #25                 // Method scala$collection$immutable$HashMap$HashKeySet$$$outer:()Lscala/collection/immutable/HashMap;
         5: aload_1
         6: invokedynamic #112,  0            // InvokeDynamic #0:apply:(Lscala/Function1;)Lscala/Function1;
        11: astore_3
        12: dup
        13: ifnonnull     18
        16: aconst_null
        17: athrow
        18: astore_2
        19: iconst_0
        20: istore        4
        22: aload_2
        23: invokevirtual #39                 // Method scala/collection/immutable/HashMap.rootNode:()Lscala/collection/immutable/BitmapIndexedMapNode;
        26: dup
        27: ifnonnull     32
        30: aconst_null
        31: athrow
        32: astore        6
        34: aload         6
        36: invokevirtual #116                // Method scala/collection/immutable/BitmapIndexedMapNode.size:()I
        39: iconst_0
        40: if_icmpne     48
        43: aload         6
        45: goto          1166
        48: aload         6
        50: invokevirtual #116                // Method scala/collection/immutable/BitmapIndexedMapNode.size:()I
        53: iconst_1
        54: if_icmpne     98
        57: aload         6
        59: iconst_0
        60: invokevirtual #120                // Method scala/collection/immutable/BitmapIndexedMapNode.getPayload:(I)Lscala/Tuple2;
        63: astore        54
        65: aload_1
        66: aload         54
        68: invokevirtual #126                // Method scala/Tuple2._1:()Ljava/lang/Object;
        71: invokeinterface #130,  2          // InterfaceMethod scala/Function1.apply:(Ljava/lang/Object;)Ljava/lang/Object;
        76: invokestatic  #136                // Method scala/runtime/BoxesRunTime.unboxToBoolean:(Ljava/lang/Object;)Z
        79: iload         4
        81: if_icmpeq     89
        84: aload         6
        86: goto          1166
        89: getstatic     #141                // Field scala/collection/immutable/MapNode$.MODULE$:Lscala/collection/immutable/MapNode$;
        92: invokevirtual #144                // Method scala/collection/immutable/MapNode$.empty:()Lscala/collection/immutable/BitmapIndexedMapNode;
        95: goto          1166
        98: aload         6
       100: invokevirtual #147                // Method scala/collection/immutable/BitmapIndexedMapNode.nodeMap:()I
       103: iconst_0
       104: if_icmpne     441
       107: aload         6
       109: invokevirtual #150                // Method scala/collection/immutable/BitmapIndexedMapNode.dataMap:()I
       112: invokestatic  #155                // Method java/lang/Integer.numberOfTrailingZeros:(I)I
       115: istore        7
       117: bipush        32
       119: aload         6
       121: invokevirtual #150                // Method scala/collection/immutable/BitmapIndexedMapNode.dataMap:()I
       124: invokestatic  #158                // Method java/lang/Integer.numberOfLeadingZeros:(I)I
       127: isub
       128: istore        8
       130: iconst_0
       131: istore        9
       133: iconst_0
       134: istore        10
       136: iconst_0
       137: istore        11
       139: iload         7
       141: istore        12
       143: iload         12
       145: iload         8
       147: if_icmpge     243
       150: getstatic     #163                // Field scala/collection/immutable/Node$.MODULE$:Lscala/collection/immutable/Node$;
       153: pop
       154: iconst_1
       155: iload         12
       157: ishl
       158: istore        51
       160: iload         51
       162: aload         6
       164: invokevirtual #150                // Method scala/collection/immutable/BitmapIndexedMapNode.dataMap:()I
       167: iand
       168: iconst_0
       169: if_icmpeq     237
       172: aload         6
       174: iload         11
       176: invokevirtual #120                // Method scala/collection/immutable/BitmapIndexedMapNode.getPayload:(I)Lscala/Tuple2;
       179: astore        54
       181: aload_1
       182: aload         54
       184: invokevirtual #126                // Method scala/Tuple2._1:()Ljava/lang/Object;
       187: invokeinterface #130,  2          // InterfaceMethod scala/Function1.apply:(Ljava/lang/Object;)Ljava/lang/Object;
       192: invokestatic  #136                // Method scala/runtime/BoxesRunTime.unboxToBoolean:(Ljava/lang/Object;)Z
       195: iload         4
       197: if_icmpeq     204
       200: iconst_1
       201: goto          205
       204: iconst_0
       205: ifeq          234
       208: iload         9
       210: iload         51
       212: ior
       213: istore        9
       215: iload         10
       217: getstatic     #60                 // Field scala/collection/Hashing$.MODULE$:Lscala/collection/Hashing$;
       220: aload         6
       222: invokevirtual #167                // Method scala/collection/immutable/BitmapIndexedMapNode.originalHashes:()[I
       225: iload         11
       227: iaload
       228: invokevirtual #64                 // Method scala/collection/Hashing$.improve:(I)I
       231: iadd
       232: istore        10
       234: iinc          11, 1
       237: iinc          12, 1
       240: goto          143
       243: iload         9
       245: iconst_0
       246: if_icmpne     258
       249: getstatic     #141                // Field scala/collection/immutable/MapNode$.MODULE$:Lscala/collection/immutable/MapNode$;
       252: invokevirtual #144                // Method scala/collection/immutable/MapNode$.empty:()Lscala/collection/immutable/BitmapIndexedMapNode;
       255: goto          1166
       258: iload         9
       260: aload         6
       262: invokevirtual #150                // Method scala/collection/immutable/BitmapIndexedMapNode.dataMap:()I
       265: if_icmpne     273
       268: aload         6
       270: goto          1166
       273: iload         9
       275: invokestatic  #170                // Method java/lang/Integer.bitCount:(I)I
       278: istore        13
       280: iload         13
       282: iconst_2
       283: imul
       284: anewarray     #86                 // class java/lang/Object
       287: astore        14
       289: iload         13
       291: newarray       int
       293: astore        15
       295: bipush        32
       297: iload         9
       299: invokestatic  #158                // Method java/lang/Integer.numberOfLeadingZeros:(I)I
       302: isub
       303: istore        16
       305: iload         9
       307: invokestatic  #155                // Method java/lang/Integer.numberOfTrailingZeros:(I)I
       310: istore        17
       312: iconst_0
       313: istore        18
       315: iload         17
       317: iload         16
       319: if_icmpge     420
       322: getstatic     #163                // Field scala/collection/immutable/Node$.MODULE$:Lscala/collection/immutable/Node$;
       325: pop
       326: iconst_1
       327: iload         17
       329: ishl
       330: istore        52
       332: iload         52
       334: iload         9
       336: iand
       337: iconst_0
       338: if_icmpeq     414
       341: getstatic     #163                // Field scala/collection/immutable/Node$.MODULE$:Lscala/collection/immutable/Node$;
       344: pop
       345: aload         6
       347: invokevirtual #150                // Method scala/collection/immutable/BitmapIndexedMapNode.dataMap:()I
       350: iload         52
       352: iconst_1
       353: isub
       354: iand
       355: invokestatic  #170                // Method java/lang/Integer.bitCount:(I)I
       358: istore        50
       360: aload         14
       362: iload         18
       364: iconst_2
       365: imul
       366: aload         6
       368: invokevirtual #174                // Method scala/collection/immutable/BitmapIndexedMapNode.content:()[Ljava/lang/Object;
       371: iload         50
       373: iconst_2
       374: imul
       375: aaload
       376: aastore
       377: aload         14
       379: iload         18
       381: iconst_2
       382: imul
       383: iconst_1
       384: iadd
       385: aload         6
       387: invokevirtual #174                // Method scala/collection/immutable/BitmapIndexedMapNode.content:()[Ljava/lang/Object;
       390: iload         50
       392: iconst_2
       393: imul
       394: iconst_1
       395: iadd
       396: aaload
       397: aastore
       398: aload         15
       400: iload         18
       402: aload         6
       404: invokevirtual #167                // Method scala/collection/immutable/BitmapIndexedMapNode.originalHashes:()[I
       407: iload         50
       409: iaload
       410: iastore
       411: iinc          18, 1
       414: iinc          17, 1
       417: goto          315
       420: new           #66                 // class scala/collection/immutable/BitmapIndexedMapNode
       423: dup
       424: iload         9
       426: iconst_0
       427: aload         14
       429: aload         15
       431: iload         13
       433: iload         10
       435: invokespecial #177                // Method scala/collection/immutable/BitmapIndexedMapNode."<init>":(II[Ljava/lang/Object;[III)V
       438: goto          1166
       441: aload         6
       443: invokevirtual #150                // Method scala/collection/immutable/BitmapIndexedMapNode.dataMap:()I
       446: aload         6
       448: invokevirtual #147                // Method scala/collection/immutable/BitmapIndexedMapNode.nodeMap:()I
       451: ior
       452: istore        19
       454: iload         19
       456: invokestatic  #155                // Method java/lang/Integer.numberOfTrailingZeros:(I)I
       459: istore        20
       461: bipush        32
       463: iload         19
       465: invokestatic  #158                // Method java/lang/Integer.numberOfLeadingZeros:(I)I
       468: isub
       469: istore        21
       471: iconst_0
       472: istore        22
       474: iconst_0
       475: istore        23
       477: aconst_null
       478: astore        24
       480: iconst_0
       481: istore        25
       483: iconst_0
       484: istore        26
       486: aconst_null
       487: astore        27
       489: iconst_0
       490: istore        28
       492: iconst_0
       493: istore        29
       495: iconst_0
       496: istore        30
       498: iconst_0
       499: istore        31
       501: iconst_0
       502: istore        32
       504: iconst_0
       505: istore        33
       507: iload         20
       509: istore        34
       511: iload         34
       513: iload         21
       515: if_icmpge     792
       518: getstatic     #163                // Field scala/collection/immutable/Node$.MODULE$:Lscala/collection/immutable/Node$;
       521: pop
       522: iconst_1
       523: iload         34
       525: ishl
       526: istore        53
       528: iload         53
       530: aload         6
       532: invokevirtual #150                // Method scala/collection/immutable/BitmapIndexedMapNode.dataMap:()I
       535: iand
       536: iconst_0
       537: if_icmpeq     618
       540: aload         6
       542: iload         32
       544: invokevirtual #120                // Method scala/collection/immutable/BitmapIndexedMapNode.getPayload:(I)Lscala/Tuple2;
       547: astore        54
       549: aload_1
       550: aload         54
       552: invokevirtual #126                // Method scala/Tuple2._1:()Ljava/lang/Object;
       555: invokeinterface #130,  2          // InterfaceMethod scala/Function1.apply:(Ljava/lang/Object;)Ljava/lang/Object;
       560: invokestatic  #136                // Method scala/runtime/BoxesRunTime.unboxToBoolean:(Ljava/lang/Object;)Z
       563: iload         4
       565: if_icmpeq     572
       568: iconst_1
       569: goto          573
       572: iconst_0
       573: ifeq          612
       576: iload         28
       578: iload         53
       580: ior
       581: istore        28
       583: iload         22
       585: iload         53
       587: ior
       588: istore        22
       590: iinc          30, 1
       593: iload         31
       595: getstatic     #60                 // Field scala/collection/Hashing$.MODULE$:Lscala/collection/Hashing$;
       598: aload         6
       600: invokevirtual #167                // Method scala/collection/immutable/BitmapIndexedMapNode.originalHashes:()[I
       603: iload         32
       605: iaload
       606: invokevirtual #64                 // Method scala/collection/Hashing$.improve:(I)I
       609: iadd
       610: istore        31
       612: iinc          32, 1
       615: goto          786
       618: iload         53
       620: aload         6
       622: invokevirtual #147                // Method scala/collection/immutable/BitmapIndexedMapNode.nodeMap:()I
       625: iand
       626: iconst_0
       627: if_icmpeq     786
       630: aload         6
       632: iload         33
       634: invokevirtual #181                // Method scala/collection/immutable/BitmapIndexedMapNode.getNode:(I)Lscala/collection/immutable/MapNode;
       637: astore        35
       639: aload         35
       641: aload_3
       642: iload         4
       644: invokevirtual #187                // Method scala/collection/immutable/MapNode.filterImpl:(Lscala/Function1;Z)Lscala/collection/immutable/MapNode;
       647: astore        36
       649: iload         30
       651: aload         36
       653: invokevirtual #188                // Method scala/collection/immutable/MapNode.size:()I
       656: iadd
       657: istore        30
       659: iload         31
       661: aload         36
       663: invokevirtual #191                // Method scala/collection/immutable/MapNode.cachedJavaKeySetHashCode:()I
       666: iadd
       667: istore        31
       669: aload         36
       671: invokevirtual #188                // Method scala/collection/immutable/MapNode.size:()I
       674: iconst_1
       675: if_icmple     733
       678: iload         29
       680: iload         53
       682: ior
       683: istore        29
       685: aload         35
       687: aload         36
       689: if_acmpne     702
       692: iload         25
       694: iload         53
       696: ior
       697: istore        25
       699: goto          783
       702: iload         26
       704: iload         53
       706: ior
       707: istore        26
       709: aload         27
       711: ifnonnull     722
       714: getstatic     #196                // Field scala/collection/mutable/Queue$.MODULE$:Lscala/collection/mutable/Queue$;
       717: invokevirtual #199                // Method scala/collection/mutable/Queue$.empty:()Lscala/collection/mutable/Queue;
       720: astore        27
       722: aload         27
       724: aload         36
       726: invokevirtual #205                // Method scala/collection/mutable/Queue.$plus$eq:(Ljava/lang/Object;)Lscala/collection/mutable/Growable;
       729: pop
       730: goto          783
       733: aload         36
       735: invokevirtual #188                // Method scala/collection/immutable/MapNode.size:()I
       738: iconst_1
       739: if_icmpne     783
       742: iload         28
       744: iload         53
       746: ior
       747: istore        28
       749: iload         23
       751: iload         53
       753: ior
       754: istore        23
       756: aload         24
       758: ifnonnull     775
       761: getstatic     #196                // Field scala/collection/mutable/Queue$.MODULE$:Lscala/collection/mutable/Queue$;
       764: getstatic     #210                // Field scala/collection/immutable/Nil$.MODULE$:Lscala/collection/immutable/Nil$;
       767: invokestatic  #216                // InterfaceMethod scala/collection/IterableFactory.apply$:(Lscala/collection/IterableFactory;Lscala/collection/immutable/Seq;)Ljava/lang/Object;
       770: checkcast     #201                // class scala/collection/mutable/Queue
       773: astore        24
       775: aload         24
       777: aload         36
       779: invokevirtual #205                // Method scala/collection/mutable/Queue.$plus$eq:(Ljava/lang/Object;)Lscala/collection/mutable/Growable;
       782: pop
       783: iinc          33, 1
       786: iinc          34, 1
       789: goto          511
       792: iload         30
       794: iconst_0
       795: if_icmpne     807
       798: getstatic     #141                // Field scala/collection/immutable/MapNode$.MODULE$:Lscala/collection/immutable/MapNode$;
       801: invokevirtual #144                // Method scala/collection/immutable/MapNode$.empty:()Lscala/collection/immutable/BitmapIndexedMapNode;
       804: goto          1166
       807: iload         30
       809: aload         6
       811: invokevirtual #116                // Method scala/collection/immutable/BitmapIndexedMapNode.size:()I
       814: if_icmpne     822
       817: aload         6
       819: goto          1166
       822: iload         28
       824: invokestatic  #170                // Method java/lang/Integer.bitCount:(I)I
       827: istore        37
       829: iconst_2
       830: iload         37
       832: imul
       833: iload         29
       835: invokestatic  #170                // Method java/lang/Integer.bitCount:(I)I
       838: iadd
       839: istore        38
       841: iload         38
       843: anewarray     #86                 // class java/lang/Object
       846: astore        39
       848: iload         37
       850: newarray       int
       852: astore        40
       854: iload         28
       856: iload         29
       858: ior
       859: istore        41
       861: bipush        32
       863: iload         41
       865: invokestatic  #158                // Method java/lang/Integer.numberOfLeadingZeros:(I)I
       868: isub
       869: istore        42
       871: iload         20
       873: istore        43
       875: iconst_0
       876: istore        44
       878: iconst_0
       879: istore        45
       881: iconst_0
       882: istore        46
       884: iconst_0
       885: istore        47
       887: iload         43
       889: iload         42
       891: if_icmpge     1147
       894: getstatic     #163                // Field scala/collection/immutable/Node$.MODULE$:Lscala/collection/immutable/Node$;
       897: iload         43
       899: invokevirtual #219                // Method scala/collection/immutable/Node$.bitposFrom:(I)I
       902: istore        48
       904: iload         48
       906: iload         22
       908: iand
       909: iconst_0
       910: if_icmpeq     973
       913: aload         39
       915: iload         46
       917: iconst_2
       918: imul
       919: aload         6
       921: invokevirtual #174                // Method scala/collection/immutable/BitmapIndexedMapNode.content:()[Ljava/lang/Object;
       924: iconst_2
       925: iload         44
       927: imul
       928: aaload
       929: aastore
       930: aload         39
       932: iload         46
       934: iconst_2
       935: imul
       936: iconst_1
       937: iadd
       938: aload         6
       940: invokevirtual #174                // Method scala/collection/immutable/BitmapIndexedMapNode.content:()[Ljava/lang/Object;
       943: iconst_2
       944: iload         44
       946: imul
       947: iconst_1
       948: iadd
       949: aaload
       950: aastore
       951: aload         40
       953: iload         46
       955: aload         6
       957: invokevirtual #167                // Method scala/collection/immutable/BitmapIndexedMapNode.originalHashes:()[I
       960: iload         44
       962: iaload
       963: iastore
       964: iinc          46, 1
       967: iinc          44, 1
       970: goto          1141
       973: iload         48
       975: iload         25
       977: iand
       978: iconst_0
       979: if_icmpeq     1008
       982: aload         39
       984: iload         38
       986: iload         47
       988: isub
       989: iconst_1
       990: isub
       991: aload         6
       993: iload         45
       995: invokevirtual #181                // Method scala/collection/immutable/BitmapIndexedMapNode.getNode:(I)Lscala/collection/immutable/MapNode;
       998: aastore
       999: iinc          47, 1
      1002: iinc          45, 1
      1005: goto          1141
      1008: iload         48
      1010: iload         23
      1012: iand
      1013: iconst_0
      1014: if_icmpeq     1075
      1017: aload         24
      1019: invokevirtual #222                // Method scala/collection/mutable/Queue.dequeue:()Ljava/lang/Object;
      1022: checkcast     #183                // class scala/collection/immutable/MapNode
      1025: astore        49
      1027: aload         39
      1029: iconst_2
      1030: iload         46
      1032: imul
      1033: aload         49
      1035: iconst_0
      1036: invokevirtual #226                // Method scala/collection/immutable/MapNode.getKey:(I)Ljava/lang/Object;
      1039: aastore
      1040: aload         39
      1042: iconst_2
      1043: iload         46
      1045: imul
      1046: iconst_1
      1047: iadd
      1048: aload         49
      1050: iconst_0
      1051: invokevirtual #229                // Method scala/collection/immutable/MapNode.getValue:(I)Ljava/lang/Object;
      1054: aastore
      1055: aload         40
      1057: iload         46
      1059: aload         49
      1061: iconst_0
      1062: invokevirtual #232                // Method scala/collection/immutable/MapNode.getHash:(I)I
      1065: iastore
      1066: iinc          46, 1
      1069: iinc          45, 1
      1072: goto          1141
      1075: iload         48
      1077: iload         26
      1079: iand
      1080: iconst_0
      1081: if_icmpeq     1108
      1084: aload         39
      1086: iload         38
      1088: iload         47
      1090: isub
      1091: iconst_1
      1092: isub
      1093: aload         27
      1095: invokevirtual #222                // Method scala/collection/mutable/Queue.dequeue:()Ljava/lang/Object;
      1098: aastore
      1099: iinc          47, 1
      1102: iinc          45, 1
      1105: goto          1141
      1108: iload         48
      1110: aload         6
      1112: invokevirtual #150                // Method scala/collection/immutable/BitmapIndexedMapNode.dataMap:()I
      1115: iand
      1116: iconst_0
      1117: if_icmpeq     1126
      1120: iinc          44, 1
      1123: goto          1141
      1126: iload         48
      1128: aload         6
      1130: invokevirtual #147                // Method scala/collection/immutable/BitmapIndexedMapNode.nodeMap:()I
      1133: iand
      1134: iconst_0
      1135: if_icmpeq     1141
      1138: iinc          45, 1
      1141: iinc          43, 1
      1144: goto          887
      1147: new           #66                 // class scala/collection/immutable/BitmapIndexedMapNode
      1150: dup
      1151: iload         28
      1153: iload         29
      1155: aload         39
      1157: aload         40
      1159: iload         30
      1161: iload         31
      1163: invokespecial #177                // Method scala/collection/immutable/BitmapIndexedMapNode."<init>":(II[Ljava/lang/Object;[III)V
      1166: aconst_null
      1167: astore        6
      1169: aconst_null
      1170: astore        14
      1172: aconst_null
      1173: astore        15
      1175: aconst_null
      1176: astore        24
      1178: aconst_null
      1179: astore        27
      1181: aconst_null
      1182: astore        35
      1184: aconst_null
      1185: astore        36
      1187: aconst_null
      1188: astore        39
      1190: aconst_null
      1191: astore        40
      1193: aconst_null
      1194: astore        49
      1196: astore        5
      1198: aload         5
      1200: aload_2
      1201: invokevirtual #39                 // Method scala/collection/immutable/HashMap.rootNode:()Lscala/collection/immutable/BitmapIndexedMapNode;
      1204: if_acmpne     1211
      1207: aload_2
      1208: goto          1238
      1211: aload         5
      1213: invokevirtual #116                // Method scala/collection/immutable/BitmapIndexedMapNode.size:()I
      1216: iconst_0
      1217: if_icmpne     1229
      1220: getstatic     #237                // Field scala/collection/immutable/HashMap$.MODULE$:Lscala/collection/immutable/HashMap$;
      1223: invokevirtual #239                // Method scala/collection/immutable/HashMap$.empty:()Lscala/collection/immutable/HashMap;
      1226: goto          1238
      1229: new           #13                 // class scala/collection/immutable/HashMap
      1232: dup
      1233: aload         5
      1235: invokespecial #43                 // Method scala/collection/immutable/HashMap."<init>":(Lscala/collection/immutable/BitmapIndexedMapNode;)V
      1238: aconst_null
      1239: astore        5
      1241: aconst_null
      1242: astore_2
      1243: aconst_null
      1244: astore_3
      1245: invokespecial #84                 // Method newKeySetOrThis:(Lscala/collection/immutable/HashMap;)Lscala/collection/immutable/Set;
      1248: areturn
      StackMapTable: number_of_entries = 43
        frame_type = 255 /* full_frame */
          offset_delta = 18
          locals = [ class scala/collection/immutable/HashMap$HashKeySet, class scala/Function1, top, class scala/Function1 ]
          stack = [ class scala/collection/immutable/HashMap$HashKeySet, class scala/collection/immutable/HashMap ]
        frame_type = 255 /* full_frame */
          offset_delta = 13
          locals = [ class scala/collection/immutable/HashMap$HashKeySet, class scala/Function1, class scala/collection/immutable/HashMap, class scala/Function1, int ]
          stack = [ class scala/collection/immutable/HashMap$HashKeySet, class scala/collection/immutable/BitmapIndexedMapNode ]
        frame_type = 255 /* full_frame */
          offset_delta = 15
          locals = [ class scala/collection/immutable/HashMap$HashKeySet, class scala/Function1, class scala/collection/immutable/HashMap, class scala/Function1, int, top, class scala/collection/immutable/BitmapIndexedMapNode ]
          stack = [ class scala/collection/immutable/HashMap$HashKeySet ]
        frame_type = 255 /* full_frame */
          offset_delta = 40
          locals = [ class scala/collection/immutable/HashMap$HashKeySet, class scala/Function1, class scala/collection/immutable/HashMap, class scala/Function1, int, top, class scala/collection/immutable/BitmapIndexedMapNode, top, top, top, top, top, top, top, top, top, top, top, top, top, top, top, top, top, top, top, top, top, top, top, top, top, top, top, top, top, top, top, top, top, top, top, top, top, top, top, top, top, top, top, top, top, top, top, class scala/Tuple2 ]
          stack = [ class scala/collection/immutable/HashMap$HashKeySet ]
        frame_type = 255 /* full_frame */
          offset_delta = 8
          locals = [ class scala/collection/immutable/HashMap$HashKeySet, class scala/Function1, class scala/collection/immutable/HashMap, class scala/Function1, int, top, class scala/collection/immutable/BitmapIndexedMapNode ]
          stack = [ class scala/collection/immutable/HashMap$HashKeySet ]
        frame_type = 255 /* full_frame */
          offset_delta = 44
          locals = [ class scala/collection/immutable/HashMap$HashKeySet, class scala/Function1, class scala/collection/immutable/HashMap, class scala/Function1, int, top, class scala/collection/immutable/BitmapIndexedMapNode, int, int, int, int, int, int ]
          stack = [ class scala/collection/immutable/HashMap$HashKeySet ]
        frame_type = 255 /* full_frame */
          offset_delta = 60
          locals = [ class scala/collection/immutable/HashMap$HashKeySet, class scala/Function1, class scala/collection/immutable/HashMap, class scala/Function1, int, top, class scala/collection/immutable/BitmapIndexedMapNode, int, int, int, int, int, int, top, top, top, top, top, top, top, top, top, top, top, top, top, top, top, top, top, top, top, top, top, top, top, top, top, top, top, top, top, top, top, top, top, top, top, top, top, top, int, top, top, class scala/Tuple2 ]
          stack = [ class scala/collection/immutable/HashMap$HashKeySet ]
        frame_type = 255 /* full_frame */
          offset_delta = 0
          locals = [ class scala/collection/immutable/HashMap$HashKeySet, class scala/Function1, class scala/collection/immutable/HashMap, class scala/Function1, int, top, class scala/collection/immutable/BitmapIndexedMapNode, int, int, int, int, int, int, top, top, top, top, top, top, top, top, top, top, top, top, top, top, top, top, top, top, top, top, top, top, top, top, top, top, top, top, top, top, top, top, top, top, top, top, top, top, int, top, top, class scala/Tuple2 ]
          stack = [ class scala/collection/immutable/HashMap$HashKeySet, int ]
        frame_type = 92 /* same_locals_1_stack_item */
          stack = [ class scala/collection/immutable/HashMap$HashKeySet ]
        frame_type = 255 /* full_frame */
          offset_delta = 2
          locals = [ class scala/collection/immutable/HashMap$HashKeySet, class scala/Function1, class scala/collection/immutable/HashMap, class scala/Function1, int, top, class scala/collection/immutable/BitmapIndexedMapNode, int, int, int, int, int, int, top, top, top, top, top, top, top, top, top, top, top, top, top, top, top, top, top, top, top, top, top, top, top, top, top, top, top, top, top, top, top, top, top, top, top, top, top, top, int ]
          stack = [ class scala/collection/immutable/HashMap$HashKeySet ]
        frame_type = 255 /* full_frame */
          offset_delta = 5
          locals = [ class scala/collection/immutable/HashMap$HashKeySet, class scala/Function1, class scala/collection/immutable/HashMap, class scala/Function1, int, top, class scala/collection/immutable/BitmapIndexedMapNode, int, int, int, int, int, int ]
          stack = [ class scala/collection/immutable/HashMap$HashKeySet ]
        frame_type = 78 /* same_locals_1_stack_item */
          stack = [ class scala/collection/immutable/HashMap$HashKeySet ]
        frame_type = 78 /* same_locals_1_stack_item */
          stack = [ class scala/collection/immutable/HashMap$HashKeySet ]
        frame_type = 255 /* full_frame */
          offset_delta = 41
          locals = [ class scala/collection/immutable/HashMap$HashKeySet, class scala/Function1, class scala/collection/immutable/HashMap, class scala/Function1, int, top, class scala/collection/immutable/BitmapIndexedMapNode, int, int, int, int, int, int, int, class "[Ljava/lang/Object;", class "[I", int, int, int ]
          stack = [ class scala/collection/immutable/HashMap$HashKeySet ]
        frame_type = 255 /* full_frame */
          offset_delta = 98
          locals = [ class scala/collection/immutable/HashMap$HashKeySet, class scala/Function1, class scala/collection/immutable/HashMap, class scala/Function1, int, top, class scala/collection/immutable/BitmapIndexedMapNode, int, int, int, int, int, int, int, class "[Ljava/lang/Object;", class "[I", int, int, int, top, top, top, top, top, top, top, top, top, top, top, top, top, top, top, top, top, top, top, top, top, top, top, top, top, top, top, top, top, top, top, top, top, int ]
          stack = [ class scala/collection/immutable/HashMap$HashKeySet ]
        frame_type = 255 /* full_frame */
          offset_delta = 5
          locals = [ class scala/collection/immutable/HashMap$HashKeySet, class scala/Function1, class scala/collection/immutable/HashMap, class scala/Function1, int, top, class scala/collection/immutable/BitmapIndexedMapNode, int, int, int, int, int, int, int, class "[Ljava/lang/Object;", class "[I", int, int, int ]
          stack = [ class scala/collection/immutable/HashMap$HashKeySet ]
        frame_type = 255 /* full_frame */
          offset_delta = 20
          locals = [ class scala/collection/immutable/HashMap$HashKeySet, class scala/Function1, class scala/collection/immutable/HashMap, class scala/Function1, int, top, class scala/collection/immutable/BitmapIndexedMapNode ]
          stack = [ class scala/collection/immutable/HashMap$HashKeySet ]
        frame_type = 255 /* full_frame */
          offset_delta = 69
          locals = [ class scala/collection/immutable/HashMap$HashKeySet, class scala/Function1, class scala/collection/immutable/HashMap, class scala/Function1, int, top, class scala/collection/immutable/BitmapIndexedMapNode, top, top, top, top, top, top, top, top, top, top, top, top, int, int, int, int, int, class scala/collection/mutable/Queue, int, int, class scala/collection/mutable/Queue, int, int, int, int, int, int, int ]
          stack = [ class scala/collection/immutable/HashMap$HashKeySet ]
        frame_type = 255 /* full_frame */
          offset_delta = 60
          locals = [ class scala/collection/immutable/HashMap$HashKeySet, class scala/Function1, class scala/collection/immutable/HashMap, class scala/Function1, int, top, class scala/collection/immutable/BitmapIndexedMapNode, top, top, top, top, top, top, top, top, top, top, top, top, int, int, int, int, int, class scala/collection/mutable/Queue, int, int, class scala/collection/mutable/Queue, int, int, int, int, int, int, int, top, top, top, top, top, top, top, top, top, top, top, top, top, top, top, top, top, top, int, class scala/Tuple2 ]
          stack = [ class scala/collection/immutable/HashMap$HashKeySet ]
        frame_type = 255 /* full_frame */
          offset_delta = 0
          locals = [ class scala/collection/immutable/HashMap$HashKeySet, class scala/Function1, class scala/collection/immutable/HashMap, class scala/Function1, int, top, class scala/collection/immutable/BitmapIndexedMapNode, top, top, top, top, top, top, top, top, top, top, top, top, int, int, int, int, int, class scala/collection/mutable/Queue, int, int, class scala/collection/mutable/Queue, int, int, int, int, int, int, int, top, top, top, top, top, top, top, top, top, top, top, top, top, top, top, top, top, top, int, class scala/Tuple2 ]
          stack = [ class scala/collection/immutable/HashMap$HashKeySet, int ]
        frame_type = 102 /* same_locals_1_stack_item */
          stack = [ class scala/collection/immutable/HashMap$HashKeySet ]
        frame_type = 255 /* full_frame */
          offset_delta = 5
          locals = [ class scala/collection/immutable/HashMap$HashKeySet, class scala/Function1, class scala/collection/immutable/HashMap, class scala/Function1, int, top, class scala/collection/immutable/BitmapIndexedMapNode, top, top, top, top, top, top, top, top, top, top, top, top, int, int, int, int, int, class scala/collection/mutable/Queue, int, int, class scala/collection/mutable/Queue, int, int, int, int, int, int, int, top, top, top, top, top, top, top, top, top, top, top, top, top, top, top, top, top, top, int ]
          stack = [ class scala/collection/immutable/HashMap$HashKeySet ]
        frame_type = 255 /* full_frame */
          offset_delta = 83
          locals = [ class scala/collection/immutable/HashMap$HashKeySet, class scala/Function1, class scala/collection/immutable/HashMap, class scala/Function1, int, top, class scala/collection/immutable/BitmapIndexedMapNode, top, top, top, top, top, top, top, top, top, top, top, top, int, int, int, int, int, class scala/collection/mutable/Queue, int, int, class scala/collection/mutable/Queue, int, int, int, int, int, int, int, class scala/collection/immutable/MapNode, class scala/collection/immutable/MapNode, top, top, top, top, top, top, top, top, top, top, top, top, top, top, top, top, int ]
          stack = [ class scala/collection/immutable/HashMap$HashKeySet ]
        frame_type = 83 /* same_locals_1_stack_item */
          stack = [ class scala/collection/immutable/HashMap$HashKeySet ]
        frame_type = 74 /* same_locals_1_stack_item */
          stack = [ class scala/collection/immutable/HashMap$HashKeySet ]
        frame_type = 105 /* same_locals_1_stack_item */
          stack = [ class scala/collection/immutable/HashMap$HashKeySet ]
        frame_type = 71 /* same_locals_1_stack_item */
          stack = [ class scala/collection/immutable/HashMap$HashKeySet ]
        frame_type = 255 /* full_frame */
          offset_delta = 2
          locals = [ class scala/collection/immutable/HashMap$HashKeySet, class scala/Function1, class scala/collection/immutable/HashMap, class scala/Function1, int, top, class scala/collection/immutable/BitmapIndexedMapNode, top, top, top, top, top, top, top, top, top, top, top, top, int, int, int, int, int, class scala/collection/mutable/Queue, int, int, class scala/collection/mutable/Queue, int, int, int, int, int, int, int, top, top, top, top, top, top, top, top, top, top, top, top, top, top, top, top, top, top, int ]
          stack = [ class scala/collection/immutable/HashMap$HashKeySet ]
        frame_type = 255 /* full_frame */
          offset_delta = 5
          locals = [ class scala/collection/immutable/HashMap$HashKeySet, class scala/Function1, class scala/collection/immutable/HashMap, class scala/Function1, int, top, class scala/collection/immutable/BitmapIndexedMapNode, top, top, top, top, top, top, top, top, top, top, top, top, int, int, int, int, int, class scala/collection/mutable/Queue, int, int, class scala/collection/mutable/Queue, int, int, int, int, int, int, int ]
          stack = [ class scala/collection/immutable/HashMap$HashKeySet ]
        frame_type = 78 /* same_locals_1_stack_item */
          stack = [ class scala/collection/immutable/HashMap$HashKeySet ]
        frame_type = 78 /* same_locals_1_stack_item */
          stack = [ class scala/collection/immutable/HashMap$HashKeySet ]
        frame_type = 255 /* full_frame */
          offset_delta = 64
          locals = [ class scala/collection/immutable/HashMap$HashKeySet, class scala/Function1, class scala/collection/immutable/HashMap, class scala/Function1, int, top, class scala/collection/immutable/BitmapIndexedMapNode, top, top, top, top, top, top, top, top, top, top, top, top, int, int, int, int, int, class scala/collection/mutable/Queue, int, int, class scala/collection/mutable/Queue, int, int, int, int, int, int, int, top, top, int, int, class "[Ljava/lang/Object;", class "[I", int, int, int, int, int, int, int ]
          stack = [ class scala/collection/immutable/HashMap$HashKeySet ]
        frame_type = 255 /* full_frame */
          offset_delta = 85
          locals = [ class scala/collection/immutable/HashMap$HashKeySet, class scala/Function1, class scala/collection/immutable/HashMap, class scala/Function1, int, top, class scala/collection/immutable/BitmapIndexedMapNode, top, top, top, top, top, top, top, top, top, top, top, top, int, int, int, int, int, class scala/collection/mutable/Queue, int, int, class scala/collection/mutable/Queue, int, int, int, int, int, int, int, top, top, int, int, class "[Ljava/lang/Object;", class "[I", int, int, int, int, int, int, int, int ]
          stack = [ class scala/collection/immutable/HashMap$HashKeySet ]
        frame_type = 98 /* same_locals_1_stack_item */
          stack = [ class scala/collection/immutable/HashMap$HashKeySet ]
        frame_type = 247 /* same_locals_1_stack_item_frame_extended */
          offset_delta = 66
          stack = [ class scala/collection/immutable/HashMap$HashKeySet ]
        frame_type = 96 /* same_locals_1_stack_item */
          stack = [ class scala/collection/immutable/HashMap$HashKeySet ]
        frame_type = 81 /* same_locals_1_stack_item */
          stack = [ class scala/collection/immutable/HashMap$HashKeySet ]
        frame_type = 78 /* same_locals_1_stack_item */
          stack = [ class scala/collection/immutable/HashMap$HashKeySet ]
        frame_type = 255 /* full_frame */
          offset_delta = 5
          locals = [ class scala/collection/immutable/HashMap$HashKeySet, class scala/Function1, class scala/collection/immutable/HashMap, class scala/Function1, int, top, class scala/collection/immutable/BitmapIndexedMapNode, top, top, top, top, top, top, top, top, top, top, top, top, int, int, int, int, int, class scala/collection/mutable/Queue, int, int, class scala/collection/mutable/Queue, int, int, int, int, int, int, int, top, top, int, int, class "[Ljava/lang/Object;", class "[I", int, int, int, int, int, int, int ]
          stack = [ class scala/collection/immutable/HashMap$HashKeySet ]
        frame_type = 255 /* full_frame */
          offset_delta = 18
          locals = [ class scala/collection/immutable/HashMap$HashKeySet, class scala/Function1, class scala/collection/immutable/HashMap, class scala/Function1, int, top, class scala/collection/immutable/BitmapIndexedMapNode ]
          stack = [ class scala/collection/immutable/HashMap$HashKeySet, class scala/collection/immutable/BitmapIndexedMapNode ]
        frame_type = 255 /* full_frame */
          offset_delta = 44
          locals = [ class scala/collection/immutable/HashMap$HashKeySet, class scala/Function1, class scala/collection/immutable/HashMap, class scala/Function1, int, class scala/collection/immutable/BitmapIndexedMapNode, null, top, top, top, top, top, top, top, null, null, top, top, top, top, top, top, top, top, null, top, top, null, top, top, top, top, top, top, top, null, null, top, top, null, null, top, top, top, top, top, top, top, top, null ]
          stack = [ class scala/collection/immutable/HashMap$HashKeySet ]
        frame_type = 81 /* same_locals_1_stack_item */
          stack = [ class scala/collection/immutable/HashMap$HashKeySet ]
        frame_type = 255 /* full_frame */
          offset_delta = 8
          locals = [ class scala/collection/immutable/HashMap$HashKeySet, class scala/Function1, class scala/collection/immutable/HashMap, class scala/Function1, int, class scala/collection/immutable/BitmapIndexedMapNode, null, top, top, top, top, top, top, top, null, null, top, top, top, top, top, top, top, top, null, top, top, null, top, top, top, top, top, top, top, null, null, top, top, null, null, top, top, top, top, top, top, top, top, null ]
          stack = [ class scala/collection/immutable/HashMap$HashKeySet, class scala/collection/immutable/HashMap ]
      LineNumberTable:
        line 74: 0
        line 39: 19
        line 360: 22
        line 1594: 34
        line 1595: 48
        line 1596: 57
        line 74: 65
        line 1596: 79
        line 1597: 98
        line 1611: 107
        line 1612: 117
        line 1614: 130
        line 1615: 133
        line 1616: 136
        line 1618: 139
        line 1620: 143
        line 1621: 150
        line 1623: 160
        line 1624: 172
        line 1625: 179
        line 74: 181
        line 1625: 195
        line 1627: 205
        line 1628: 208
        line 1629: 215
        line 620: 220
        line 1629: 228
        line 1632: 234
        line 1635: 237
        line 1620: 240
        line 1638: 243
        line 1639: 249
        line 1640: 258
        line 1641: 268
        line 1643: 273
        line 1644: 280
        line 1645: 289
        line 1646: 295
        line 1648: 305
        line 1650: 312
        line 1653: 315
        line 1654: 322
        line 1655: 332
        line 1656: 341
        line 1657: 360
        line 1658: 377
        line 1659: 398
        line 1660: 411
        line 1662: 414
        line 1653: 417
        line 1665: 420
        line 1670: 441
        line 1671: 454
        line 1672: 461
        line 1674: 471
        line 1677: 474
        line 1679: 477
        line 1682: 480
        line 1687: 483
        line 1689: 486
        line 1691: 489
        line 1692: 492
        line 1693: 495
        line 1694: 498
        line 1696: 501
        line 1697: 504
        line 1699: 507
        line 1700: 511
        line 1701: 518
        line 1703: 528
        line 1704: 540
        line 1705: 547
        line 74: 549
        line 1705: 563
        line 1707: 573
        line 1708: 576
        line 1709: 583
        line 1710: 590
        line 1711: 593
        line 620: 598
        line 1711: 606
        line 1714: 612
        line 1715: 618
        line 1716: 630
        line 1717: 639
        line 1719: 649
        line 1720: 659
        line 1723: 669
        line 1724: 678
        line 1725: 685
        line 1726: 692
        line 1728: 702
        line 1729: 709
        line 1730: 714
        line 1732: 722
        line 1734: 733
        line 1735: 742
        line 1736: 749
        line 1737: 756
        line 1738: 761
        line 1740: 775
        line 1743: 783
        line 1746: 786
        line 1700: 789
        line 1749: 792
        line 1750: 798
        line 1751: 807
        line 1752: 817
        line 1754: 822
        line 1755: 829
        line 1756: 841
        line 1757: 848
        line 1759: 854
        line 1760: 861
        line 1764: 871
        line 1766: 875
        line 1767: 878
        line 1769: 881
        line 1770: 884
        line 1772: 887
        line 1773: 894
        line 1775: 904
        line 1776: 913
        line 613: 919
        line 1776: 929
        line 1777: 930
        line 614: 938
        line 1777: 950
        line 1778: 951
        line 620: 955
        line 1778: 963
        line 1779: 964
        line 1780: 967
        line 1781: 973
        line 1782: 982
        line 1783: 999
        line 1784: 1002
        line 1785: 1008
        line 1787: 1017
        line 1788: 1027
        line 1789: 1040
        line 1790: 1055
        line 1791: 1066
        line 1792: 1069
        line 1793: 1075
        line 1794: 1084
        line 1795: 1099
        line 1796: 1102
        line 1797: 1108
        line 1798: 1120
        line 1799: 1126
        line 1800: 1138
        line 1803: 1141
        line 1772: 1144
        line 1806: 1147
        line 360: 1166
        line 361: 1198
        line 362: 1211
        line 363: 1229
        line 39: 1238
        line 74: 1241
      LocalVariableTable:
        Start  Length  Slot  Name   Signature
            0    1249     0  this   Lscala/collection/immutable/HashMap$HashKeySet;
            0    1249     1  pred   Lscala/Function1;
           19    1222     2 filter_this   Lscala/collection/immutable/HashMap;
           19    1222     3 filter_pred   Lscala/Function1;
           22    1219     4 filterImpl_isFlipped   Z
         1198      40     5 filterImpl_newRootNode   Lscala/collection/immutable/BitmapIndexedMapNode;
          280     158    13 filterImpl_filterImpl_newSize   I
          289     149    14 filterImpl_filterImpl_newContent   [Ljava/lang/Object;
          295     143    15 filterImpl_filterImpl_newOriginalHashCodes   [I
          305     133    16 filterImpl_filterImpl_newMaximumIndex   I
          312     126    17 filterImpl_filterImpl_j   I
          315     123    18 filterImpl_filterImpl_newDataIndex   I
          117     321     7 filterImpl_filterImpl_minimumIndex   I
          130     308     8 filterImpl_filterImpl_maximumIndex   I
          133     305     9 filterImpl_filterImpl_newDataMap   I
          136     302    10 filterImpl_filterImpl_newCachedHashCode   I
          139     299    11 filterImpl_filterImpl_dataIndex   I
          143     295    12 filterImpl_filterImpl_i   I
          639     147    35 filterImpl_filterImpl_oldSubNode   Lscala/collection/immutable/MapNode;
          649     137    36 filterImpl_filterImpl_newSubNode   Lscala/collection/immutable/MapNode;
         1027      45    49 filterImpl_filterImpl_node   Lscala/collection/immutable/MapNode;
          904     240    48 filterImpl_filterImpl_bitpos   I
          829     337    37 filterImpl_filterImpl_newDataSize   I
          841     325    38 filterImpl_filterImpl_newContentSize   I
          848     318    39 filterImpl_filterImpl_newContent   [Ljava/lang/Object;
          854     312    40 filterImpl_filterImpl_newOriginalHashes   [I
          861     305    41 filterImpl_filterImpl_newAllMap   I
          871     295    42 filterImpl_filterImpl_maxIndex   I
          875     291    43 filterImpl_filterImpl_i   I
          878     288    44 filterImpl_filterImpl_oldDataIndex   I
          881     285    45 filterImpl_filterImpl_oldNodeIndex   I
          884     282    46 filterImpl_filterImpl_newDataIndex   I
          887     279    47 filterImpl_filterImpl_newNodeIndex   I
          454     712    19 filterImpl_filterImpl_allMap   I
          461     705    20 filterImpl_filterImpl_minimumIndex   I
          471     695    21 filterImpl_filterImpl_maximumIndex   I
          474     692    22 filterImpl_filterImpl_oldDataPassThrough   I
          477     689    23 filterImpl_filterImpl_nodeMigrateToDataTargetMap   I
          480     686    24 filterImpl_filterImpl_nodesToMigrateToData   Lscala/collection/mutable/Queue;
          483     683    25 filterImpl_filterImpl_nodesToPassThroughMap   I
          486     680    26 filterImpl_filterImpl_mapOfNewNodes   I
          489     677    27 filterImpl_filterImpl_newNodes   Lscala/collection/mutable/Queue;
          492     674    28 filterImpl_filterImpl_newDataMap   I
          495     671    29 filterImpl_filterImpl_newNodeMap   I
          498     668    30 filterImpl_filterImpl_newSize   I
          501     665    31 filterImpl_filterImpl_newCachedHashCode   I
          504     662    32 filterImpl_filterImpl_dataIndex   I
          507     659    33 filterImpl_filterImpl_nodeIndex   I
          511     655    34 filterImpl_filterImpl_i   I
           34    1132     6 filterImpl_filterImpl_this   Lscala/collection/immutable/BitmapIndexedMapNode;
    Signature: #89                          // (Lscala/Function1<TK;Ljava/lang/Object;>;)Lscala/collection/immutable/Set<TK;>;
    MethodParameters:
      Name                           Flags
      pred                           final

  public scala.collection.immutable.Set<K> filterNot(scala.Function1<K, java.lang.Object>);
    descriptor: (Lscala/Function1;)Lscala/collection/immutable/Set;
    flags: (0x0001) ACC_PUBLIC
    Code:
      stack=9, locals=55, args_size=2
         0: aload_0
         1: aload_0
         2: invokevirtual #25                 // Method scala$collection$immutable$HashMap$HashKeySet$$$outer:()Lscala/collection/immutable/HashMap;
         5: aload_1
         6: invokedynamic #291,  0            // InvokeDynamic #1:apply:(Lscala/Function1;)Lscala/Function1;
        11: astore_3
        12: dup
        13: ifnonnull     18
        16: aconst_null
        17: athrow
        18: astore_2
        19: iconst_1
        20: istore        4
        22: aload_2
        23: invokevirtual #39                 // Method scala/collection/immutable/HashMap.rootNode:()Lscala/collection/immutable/BitmapIndexedMapNode;
        26: dup
        27: ifnonnull     32
        30: aconst_null
        31: athrow
        32: astore        6
        34: aload         6
        36: invokevirtual #116                // Method scala/collection/immutable/BitmapIndexedMapNode.size:()I
        39: iconst_0
        40: if_icmpne     48
        43: aload         6
        45: goto          1166
        48: aload         6
        50: invokevirtual #116                // Method scala/collection/immutable/BitmapIndexedMapNode.size:()I
        53: iconst_1
        54: if_icmpne     98
        57: aload         6
        59: iconst_0
        60: invokevirtual #120                // Method scala/collection/immutable/BitmapIndexedMapNode.getPayload:(I)Lscala/Tuple2;
        63: astore        54
        65: aload_1
        66: aload         54
        68: invokevirtual #126                // Method scala/Tuple2._1:()Ljava/lang/Object;
        71: invokeinterface #130,  2          // InterfaceMethod scala/Function1.apply:(Ljava/lang/Object;)Ljava/lang/Object;
        76: invokestatic  #136                // Method scala/runtime/BoxesRunTime.unboxToBoolean:(Ljava/lang/Object;)Z
        79: iload         4
        81: if_icmpeq     89
        84: aload         6
        86: goto          1166
        89: getstatic     #141                // Field scala/collection/immutable/MapNode$.MODULE$:Lscala/collection/immutable/MapNode$;
        92: invokevirtual #144                // Method scala/collection/immutable/MapNode$.empty:()Lscala/collection/immutable/BitmapIndexedMapNode;
        95: goto          1166
        98: aload         6
       100: invokevirtual #147                // Method scala/collection/immutable/BitmapIndexedMapNode.nodeMap:()I
       103: iconst_0
       104: if_icmpne     441
       107: aload         6
       109: invokevirtual #150                // Method scala/collection/immutable/BitmapIndexedMapNode.dataMap:()I
       112: invokestatic  #155                // Method java/lang/Integer.numberOfTrailingZeros:(I)I
       115: istore        7
       117: bipush        32
       119: aload         6
       121: invokevirtual #150                // Method scala/collection/immutable/BitmapIndexedMapNode.dataMap:()I
       124: invokestatic  #158                // Method java/lang/Integer.numberOfLeadingZeros:(I)I
       127: isub
       128: istore        8
       130: iconst_0
       131: istore        9
       133: iconst_0
       134: istore        10
       136: iconst_0
       137: istore        11
       139: iload         7
       141: istore        12
       143: iload         12
       145: iload         8
       147: if_icmpge     243
       150: getstatic     #163                // Field scala/collection/immutable/Node$.MODULE$:Lscala/collection/immutable/Node$;
       153: pop
       154: iconst_1
       155: iload         12
       157: ishl
       158: istore        51
       160: iload         51
       162: aload         6
       164: invokevirtual #150                // Method scala/collection/immutable/BitmapIndexedMapNode.dataMap:()I
       167: iand
       168: iconst_0
       169: if_icmpeq     237
       172: aload         6
       174: iload         11
       176: invokevirtual #120                // Method scala/collection/immutable/BitmapIndexedMapNode.getPayload:(I)Lscala/Tuple2;
       179: astore        54
       181: aload_1
       182: aload         54
       184: invokevirtual #126                // Method scala/Tuple2._1:()Ljava/lang/Object;
       187: invokeinterface #130,  2          // InterfaceMethod scala/Function1.apply:(Ljava/lang/Object;)Ljava/lang/Object;
       192: invokestatic  #136                // Method scala/runtime/BoxesRunTime.unboxToBoolean:(Ljava/lang/Object;)Z
       195: iload         4
       197: if_icmpeq     204
       200: iconst_1
       201: goto          205
       204: iconst_0
       205: ifeq          234
       208: iload         9
       210: iload         51
       212: ior
       213: istore        9
       215: iload         10
       217: getstatic     #60                 // Field scala/collection/Hashing$.MODULE$:Lscala/collection/Hashing$;
       220: aload         6
       222: invokevirtual #167                // Method scala/collection/immutable/BitmapIndexedMapNode.originalHashes:()[I
       225: iload         11
       227: iaload
       228: invokevirtual #64                 // Method scala/collection/Hashing$.improve:(I)I
       231: iadd
       232: istore        10
       234: iinc          11, 1
       237: iinc          12, 1
       240: goto          143
       243: iload         9
       245: iconst_0
       246: if_icmpne     258
       249: getstatic     #141                // Field scala/collection/immutable/MapNode$.MODULE$:Lscala/collection/immutable/MapNode$;
       252: invokevirtual #144                // Method scala/collection/immutable/MapNode$.empty:()Lscala/collection/immutable/BitmapIndexedMapNode;
       255: goto          1166
       258: iload         9
       260: aload         6
       262: invokevirtual #150                // Method scala/collection/immutable/BitmapIndexedMapNode.dataMap:()I
       265: if_icmpne     273
       268: aload         6
       270: goto          1166
       273: iload         9
       275: invokestatic  #170                // Method java/lang/Integer.bitCount:(I)I
       278: istore        13
       280: iload         13
       282: iconst_2
       283: imul
       284: anewarray     #86                 // class java/lang/Object
       287: astore        14
       289: iload         13
       291: newarray       int
       293: astore        15
       295: bipush        32
       297: iload         9
       299: invokestatic  #158                // Method java/lang/Integer.numberOfLeadingZeros:(I)I
       302: isub
       303: istore        16
       305: iload         9
       307: invokestatic  #155                // Method java/lang/Integer.numberOfTrailingZeros:(I)I
       310: istore        17
       312: iconst_0
       313: istore        18
       315: iload         17
       317: iload         16
       319: if_icmpge     420
       322: getstatic     #163                // Field scala/collection/immutable/Node$.MODULE$:Lscala/collection/immutable/Node$;
       325: pop
       326: iconst_1
       327: iload         17
       329: ishl
       330: istore        52
       332: iload         52
       334: iload         9
       336: iand
       337: iconst_0
       338: if_icmpeq     414
       341: getstatic     #163                // Field scala/collection/immutable/Node$.MODULE$:Lscala/collection/immutable/Node$;
       344: pop
       345: aload         6
       347: invokevirtual #150                // Method scala/collection/immutable/BitmapIndexedMapNode.dataMap:()I
       350: iload         52
       352: iconst_1
       353: isub
       354: iand
       355: invokestatic  #170                // Method java/lang/Integer.bitCount:(I)I
       358: istore        50
       360: aload         14
       362: iload         18
       364: iconst_2
       365: imul
       366: aload         6
       368: invokevirtual #174                // Method scala/collection/immutable/BitmapIndexedMapNode.content:()[Ljava/lang/Object;
       371: iload         50
       373: iconst_2
       374: imul
       375: aaload
       376: aastore
       377: aload         14
       379: iload         18
       381: iconst_2
       382: imul
       383: iconst_1
       384: iadd
       385: aload         6
       387: invokevirtual #174                // Method scala/collection/immutable/BitmapIndexedMapNode.content:()[Ljava/lang/Object;
       390: iload         50
       392: iconst_2
       393: imul
       394: iconst_1
       395: iadd
       396: aaload
       397: aastore
       398: aload         15
       400: iload         18
       402: aload         6
       404: invokevirtual #167                // Method scala/collection/immutable/BitmapIndexedMapNode.originalHashes:()[I
       407: iload         50
       409: iaload
       410: iastore
       411: iinc          18, 1
       414: iinc          17, 1
       417: goto          315
       420: new           #66                 // class scala/collection/immutable/BitmapIndexedMapNode
       423: dup
       424: iload         9
       426: iconst_0
       427: aload         14
       429: aload         15
       431: iload         13
       433: iload         10
       435: invokespecial #177                // Method scala/collection/immutable/BitmapIndexedMapNode."<init>":(II[Ljava/lang/Object;[III)V
       438: goto          1166
       441: aload         6
       443: invokevirtual #150                // Method scala/collection/immutable/BitmapIndexedMapNode.dataMap:()I
       446: aload         6
       448: invokevirtual #147                // Method scala/collection/immutable/BitmapIndexedMapNode.nodeMap:()I
       451: ior
       452: istore        19
       454: iload         19
       456: invokestatic  #155                // Method java/lang/Integer.numberOfTrailingZeros:(I)I
       459: istore        20
       461: bipush        32
       463: iload         19
       465: invokestatic  #158                // Method java/lang/Integer.numberOfLeadingZeros:(I)I
       468: isub
       469: istore        21
       471: iconst_0
       472: istore        22
       474: iconst_0
       475: istore        23
       477: aconst_null
       478: astore        24
       480: iconst_0
       481: istore        25
       483: iconst_0
       484: istore        26
       486: aconst_null
       487: astore        27
       489: iconst_0
       490: istore        28
       492: iconst_0
       493: istore        29
       495: iconst_0
       496: istore        30
       498: iconst_0
       499: istore        31
       501: iconst_0
       502: istore        32
       504: iconst_0
       505: istore        33
       507: iload         20
       509: istore        34
       511: iload         34
       513: iload         21
       515: if_icmpge     792
       518: getstatic     #163                // Field scala/collection/immutable/Node$.MODULE$:Lscala/collection/immutable/Node$;
       521: pop
       522: iconst_1
       523: iload         34
       525: ishl
       526: istore        53
       528: iload         53
       530: aload         6
       532: invokevirtual #150                // Method scala/collection/immutable/BitmapIndexedMapNode.dataMap:()I
       535: iand
       536: iconst_0
       537: if_icmpeq     618
       540: aload         6
       542: iload         32
       544: invokevirtual #120                // Method scala/collection/immutable/BitmapIndexedMapNode.getPayload:(I)Lscala/Tuple2;
       547: astore        54
       549: aload_1
       550: aload         54
       552: invokevirtual #126                // Method scala/Tuple2._1:()Ljava/lang/Object;
       555: invokeinterface #130,  2          // InterfaceMethod scala/Function1.apply:(Ljava/lang/Object;)Ljava/lang/Object;
       560: invokestatic  #136                // Method scala/runtime/BoxesRunTime.unboxToBoolean:(Ljava/lang/Object;)Z
       563: iload         4
       565: if_icmpeq     572
       568: iconst_1
       569: goto          573
       572: iconst_0
       573: ifeq          612
       576: iload         28
       578: iload         53
       580: ior
       581: istore        28
       583: iload         22
       585: iload         53
       587: ior
       588: istore        22
       590: iinc          30, 1
       593: iload         31
       595: getstatic     #60                 // Field scala/collection/Hashing$.MODULE$:Lscala/collection/Hashing$;
       598: aload         6
       600: invokevirtual #167                // Method scala/collection/immutable/BitmapIndexedMapNode.originalHashes:()[I
       603: iload         32
       605: iaload
       606: invokevirtual #64                 // Method scala/collection/Hashing$.improve:(I)I
       609: iadd
       610: istore        31
       612: iinc          32, 1
       615: goto          786
       618: iload         53
       620: aload         6
       622: invokevirtual #147                // Method scala/collection/immutable/BitmapIndexedMapNode.nodeMap:()I
       625: iand
       626: iconst_0
       627: if_icmpeq     786
       630: aload         6
       632: iload         33
       634: invokevirtual #181                // Method scala/collection/immutable/BitmapIndexedMapNode.getNode:(I)Lscala/collection/immutable/MapNode;
       637: astore        35
       639: aload         35
       641: aload_3
       642: iload         4
       644: invokevirtual #187                // Method scala/collection/immutable/MapNode.filterImpl:(Lscala/Function1;Z)Lscala/collection/immutable/MapNode;
       647: astore        36
       649: iload         30
       651: aload         36
       653: invokevirtual #188                // Method scala/collection/immutable/MapNode.size:()I
       656: iadd
       657: istore        30
       659: iload         31
       661: aload         36
       663: invokevirtual #191                // Method scala/collection/immutable/MapNode.cachedJavaKeySetHashCode:()I
       666: iadd
       667: istore        31
       669: aload         36
       671: invokevirtual #188                // Method scala/collection/immutable/MapNode.size:()I
       674: iconst_1
       675: if_icmple     733
       678: iload         29
       680: iload         53
       682: ior
       683: istore        29
       685: aload         35
       687: aload         36
       689: if_acmpne     702
       692: iload         25
       694: iload         53
       696: ior
       697: istore        25
       699: goto          783
       702: iload         26
       704: iload         53
       706: ior
       707: istore        26
       709: aload         27
       711: ifnonnull     722
       714: getstatic     #196                // Field scala/collection/mutable/Queue$.MODULE$:Lscala/collection/mutable/Queue$;
       717: invokevirtual #199                // Method scala/collection/mutable/Queue$.empty:()Lscala/collection/mutable/Queue;
       720: astore        27
       722: aload         27
       724: aload         36
       726: invokevirtual #205                // Method scala/collection/mutable/Queue.$plus$eq:(Ljava/lang/Object;)Lscala/collection/mutable/Growable;
       729: pop
       730: goto          783
       733: aload         36
       735: invokevirtual #188                // Method scala/collection/immutable/MapNode.size:()I
       738: iconst_1
       739: if_icmpne     783
       742: iload         28
       744: iload         53
       746: ior
       747: istore        28
       749: iload         23
       751: iload         53
       753: ior
       754: istore        23
       756: aload         24
       758: ifnonnull     775
       761: getstatic     #196                // Field scala/collection/mutable/Queue$.MODULE$:Lscala/collection/mutable/Queue$;
       764: getstatic     #210                // Field scala/collection/immutable/Nil$.MODULE$:Lscala/collection/immutable/Nil$;
       767: invokestatic  #216                // InterfaceMethod scala/collection/IterableFactory.apply$:(Lscala/collection/IterableFactory;Lscala/collection/immutable/Seq;)Ljava/lang/Object;
       770: checkcast     #201                // class scala/collection/mutable/Queue
       773: astore        24
       775: aload         24
       777: aload         36
       779: invokevirtual #205                // Method scala/collection/mutable/Queue.$plus$eq:(Ljava/lang/Object;)Lscala/collection/mutable/Growable;
       782: pop
       783: iinc          33, 1
       786: iinc          34, 1
       789: goto          511
       792: iload         30
       794: iconst_0
       795: if_icmpne     807
       798: getstatic     #141                // Field scala/collection/immutable/MapNode$.MODULE$:Lscala/collection/immutable/MapNode$;
       801: invokevirtual #144                // Method scala/collection/immutable/MapNode$.empty:()Lscala/collection/immutable/BitmapIndexedMapNode;
       804: goto          1166
       807: iload         30
       809: aload         6
       811: invokevirtual #116                // Method scala/collection/immutable/BitmapIndexedMapNode.size:()I
       814: if_icmpne     822
       817: aload         6
       819: goto          1166
       822: iload         28
       824: invokestatic  #170                // Method java/lang/Integer.bitCount:(I)I
       827: istore        37
       829: iconst_2
       830: iload         37
       832: imul
       833: iload         29
       835: invokestatic  #170                // Method java/lang/Integer.bitCount:(I)I
       838: iadd
       839: istore        38
       841: iload         38
       843: anewarray     #86                 // class java/lang/Object
       846: astore        39
       848: iload         37
       850: newarray       int
       852: astore        40
       854: iload         28
       856: iload         29
       858: ior
       859: istore        41
       861: bipush        32
       863: iload         41
       865: invokestatic  #158                // Method java/lang/Integer.numberOfLeadingZeros:(I)I
       868: isub
       869: istore        42
       871: iload         20
       873: istore        43
       875: iconst_0
       876: istore        44
       878: iconst_0
       879: istore        45
       881: iconst_0
       882: istore        46
       884: iconst_0
       885: istore        47
       887: iload         43
       889: iload         42
       891: if_icmpge     1147
       894: getstatic     #163                // Field scala/collection/immutable/Node$.MODULE$:Lscala/collection/immutable/Node$;
       897: iload         43
       899: invokevirtual #219                // Method scala/collection/immutable/Node$.bitposFrom:(I)I
       902: istore        48
       904: iload         48
       906: iload         22
       908: iand
       909: iconst_0
       910: if_icmpeq     973
       913: aload         39
       915: iload         46
       917: iconst_2
       918: imul
       919: aload         6
       921: invokevirtual #174                // Method scala/collection/immutable/BitmapIndexedMapNode.content:()[Ljava/lang/Object;
       924: iconst_2
       925: iload         44
       927: imul
       928: aaload
       929: aastore
       930: aload         39
       932: iload         46
       934: iconst_2
       935: imul
       936: iconst_1
       937: iadd
       938: aload         6
       940: invokevirtual #174                // Method scala/collection/immutable/BitmapIndexedMapNode.content:()[Ljava/lang/Object;
       943: iconst_2
       944: iload         44
       946: imul
       947: iconst_1
       948: iadd
       949: aaload
       950: aastore
       951: aload         40
       953: iload         46
       955: aload         6
       957: invokevirtual #167                // Method scala/collection/immutable/BitmapIndexedMapNode.originalHashes:()[I
       960: iload         44
       962: iaload
       963: iastore
       964: iinc          46, 1
       967: iinc          44, 1
       970: goto          1141
       973: iload         48
       975: iload         25
       977: iand
       978: iconst_0
       979: if_icmpeq     1008
       982: aload         39
       984: iload         38
       986: iload         47
       988: isub
       989: iconst_1
       990: isub
       991: aload         6
       993: iload         45
       995: invokevirtual #181                // Method scala/collection/immutable/BitmapIndexedMapNode.getNode:(I)Lscala/collection/immutable/MapNode;
       998: aastore
       999: iinc          47, 1
      1002: iinc          45, 1
      1005: goto          1141
      1008: iload         48
      1010: iload         23
      1012: iand
      1013: iconst_0
      1014: if_icmpeq     1075
      1017: aload         24
      1019: invokevirtual #222                // Method scala/collection/mutable/Queue.dequeue:()Ljava/lang/Object;
      1022: checkcast     #183                // class scala/collection/immutable/MapNode
      1025: astore        49
      1027: aload         39
      1029: iconst_2
      1030: iload         46
      1032: imul
      1033: aload         49
      1035: iconst_0
      1036: invokevirtual #226                // Method scala/collection/immutable/MapNode.getKey:(I)Ljava/lang/Object;
      1039: aastore
      1040: aload         39
      1042: iconst_2
      1043: iload         46
      1045: imul
      1046: iconst_1
      1047: iadd
      1048: aload         49
      1050: iconst_0
      1051: invokevirtual #229                // Method scala/collection/immutable/MapNode.getValue:(I)Ljava/lang/Object;
      1054: aastore
      1055: aload         40
      1057: iload         46
      1059: aload         49
      1061: iconst_0
      1062: invokevirtual #232                // Method scala/collection/immutable/MapNode.getHash:(I)I
      1065: iastore
      1066: iinc          46, 1
      1069: iinc          45, 1
      1072: goto          1141
      1075: iload         48
      1077: iload         26
      1079: iand
      1080: iconst_0
      1081: if_icmpeq     1108
      1084: aload         39
      1086: iload         38
      1088: iload         47
      1090: isub
      1091: iconst_1
      1092: isub
      1093: aload         27
      1095: invokevirtual #222                // Method scala/collection/mutable/Queue.dequeue:()Ljava/lang/Object;
      1098: aastore
      1099: iinc          47, 1
      1102: iinc          45, 1
      1105: goto          1141
      1108: iload         48
      1110: aload         6
      1112: invokevirtual #150                // Method scala/collection/immutable/BitmapIndexedMapNode.dataMap:()I
      1115: iand
      1116: iconst_0
      1117: if_icmpeq     1126
      1120: iinc          44, 1
      1123: goto          1141
      1126: iload         48
      1128: aload         6
      1130: invokevirtual #147                // Method scala/collection/immutable/BitmapIndexedMapNode.nodeMap:()I
      1133: iand
      1134: iconst_0
      1135: if_icmpeq     1141
      1138: iinc          45, 1
      1141: iinc          43, 1
      1144: goto          887
      1147: new           #66                 // class scala/collection/immutable/BitmapIndexedMapNode
      1150: dup
      1151: iload         28
      1153: iload         29
      1155: aload         39
      1157: aload         40
      1159: iload         30
      1161: iload         31
      1163: invokespecial #177                // Method scala/collection/immutable/BitmapIndexedMapNode."<init>":(II[Ljava/lang/Object;[III)V
      1166: aconst_null
      1167: astore        6
      1169: aconst_null
      1170: astore        14
      1172: aconst_null
      1173: astore        15
      1175: aconst_null
      1176: astore        24
      1178: aconst_null
      1179: astore        27
      1181: aconst_null
      1182: astore        35
      1184: aconst_null
      1185: astore        36
      1187: aconst_null
      1188: astore        39
      1190: aconst_null
      1191: astore        40
      1193: aconst_null
      1194: astore        49
      1196: astore        5
      1198: aload         5
      1200: aload_2
      1201: invokevirtual #39                 // Method scala/collection/immutable/HashMap.rootNode:()Lscala/collection/immutable/BitmapIndexedMapNode;
      1204: if_acmpne     1211
      1207: aload_2
      1208: goto          1238
      1211: aload         5
      1213: invokevirtual #116                // Method scala/collection/immutable/BitmapIndexedMapNode.size:()I
      1216: iconst_0
      1217: if_icmpne     1229
      1220: getstatic     #237                // Field scala/collection/immutable/HashMap$.MODULE$:Lscala/collection/immutable/HashMap$;
      1223: invokevirtual #239                // Method scala/collection/immutable/HashMap$.empty:()Lscala/collection/immutable/HashMap;
      1226: goto          1238
      1229: new           #13                 // class scala/collection/immutable/HashMap
      1232: dup
      1233: aload         5
      1235: invokespecial #43                 // Method scala/collection/immutable/HashMap."<init>":(Lscala/collection/immutable/BitmapIndexedMapNode;)V
      1238: aconst_null
      1239: astore        5
      1241: aconst_null
      1242: astore_2
      1243: aconst_null
      1244: astore_3
      1245: invokespecial #84                 // Method newKeySetOrThis:(Lscala/collection/immutable/HashMap;)Lscala/collection/immutable/Set;
      1248: areturn
      StackMapTable: number_of_entries = 43
        frame_type = 255 /* full_frame */
          offset_delta = 18
          locals = [ class scala/collection/immutable/HashMap$HashKeySet, class scala/Function1, top, class scala/Function1 ]
          stack = [ class scala/collection/immutable/HashMap$HashKeySet, class scala/collection/immutable/HashMap ]
        frame_type = 255 /* full_frame */
          offset_delta = 13
          locals = [ class scala/collection/immutable/HashMap$HashKeySet, class scala/Function1, class scala/collection/immutable/HashMap, class scala/Function1, int ]
          stack = [ class scala/collection/immutable/HashMap$HashKeySet, class scala/collection/immutable/BitmapIndexedMapNode ]
        frame_type = 255 /* full_frame */
          offset_delta = 15
          locals = [ class scala/collection/immutable/HashMap$HashKeySet, class scala/Function1, class scala/collection/immutable/HashMap, class scala/Function1, int, top, class scala/collection/immutable/BitmapIndexedMapNode ]
          stack = [ class scala/collection/immutable/HashMap$HashKeySet ]
        frame_type = 255 /* full_frame */
          offset_delta = 40
          locals = [ class scala/collection/immutable/HashMap$HashKeySet, class scala/Function1, class scala/collection/immutable/HashMap, class scala/Function1, int, top, class scala/collection/immutable/BitmapIndexedMapNode, top, top, top, top, top, top, top, top, top, top, top, top, top, top, top, top, top, top, top, top, top, top, top, top, top, top, top, top, top, top, top, top, top, top, top, top, top, top, top, top, top, top, top, top, top, top, top, class scala/Tuple2 ]
          stack = [ class scala/collection/immutable/HashMap$HashKeySet ]
        frame_type = 255 /* full_frame */
          offset_delta = 8
          locals = [ class scala/collection/immutable/HashMap$HashKeySet, class scala/Function1, class scala/collection/immutable/HashMap, class scala/Function1, int, top, class scala/collection/immutable/BitmapIndexedMapNode ]
          stack = [ class scala/collection/immutable/HashMap$HashKeySet ]
        frame_type = 255 /* full_frame */
          offset_delta = 44
          locals = [ class scala/collection/immutable/HashMap$HashKeySet, class scala/Function1, class scala/collection/immutable/HashMap, class scala/Function1, int, top, class scala/collection/immutable/BitmapIndexedMapNode, int, int, int, int, int, int ]
          stack = [ class scala/collection/immutable/HashMap$HashKeySet ]
        frame_type = 255 /* full_frame */
          offset_delta = 60
          locals = [ class scala/collection/immutable/HashMap$HashKeySet, class scala/Function1, class scala/collection/immutable/HashMap, class scala/Function1, int, top, class scala/collection/immutable/BitmapIndexedMapNode, int, int, int, int, int, int, top, top, top, top, top, top, top, top, top, top, top, top, top, top, top, top, top, top, top, top, top, top, top, top, top, top, top, top, top, top, top, top, top, top, top, top, top, top, int, top, top, class scala/Tuple2 ]
          stack = [ class scala/collection/immutable/HashMap$HashKeySet ]
        frame_type = 255 /* full_frame */
          offset_delta = 0
          locals = [ class scala/collection/immutable/HashMap$HashKeySet, class scala/Function1, class scala/collection/immutable/HashMap, class scala/Function1, int, top, class scala/collection/immutable/BitmapIndexedMapNode, int, int, int, int, int, int, top, top, top, top, top, top, top, top, top, top, top, top, top, top, top, top, top, top, top, top, top, top, top, top, top, top, top, top, top, top, top, top, top, top, top, top, top, top, int, top, top, class scala/Tuple2 ]
          stack = [ class scala/collection/immutable/HashMap$HashKeySet, int ]
        frame_type = 92 /* same_locals_1_stack_item */
          stack = [ class scala/collection/immutable/HashMap$HashKeySet ]
        frame_type = 255 /* full_frame */
          offset_delta = 2
          locals = [ class scala/collection/immutable/HashMap$HashKeySet, class scala/Function1, class scala/collection/immutable/HashMap, class scala/Function1, int, top, class scala/collection/immutable/BitmapIndexedMapNode, int, int, int, int, int, int, top, top, top, top, top, top, top, top, top, top, top, top, top, top, top, top, top, top, top, top, top, top, top, top, top, top, top, top, top, top, top, top, top, top, top, top, top, top, int ]
          stack = [ class scala/collection/immutable/HashMap$HashKeySet ]
        frame_type = 255 /* full_frame */
          offset_delta = 5
          locals = [ class scala/collection/immutable/HashMap$HashKeySet, class scala/Function1, class scala/collection/immutable/HashMap, class scala/Function1, int, top, class scala/collection/immutable/BitmapIndexedMapNode, int, int, int, int, int, int ]
          stack = [ class scala/collection/immutable/HashMap$HashKeySet ]
        frame_type = 78 /* same_locals_1_stack_item */
          stack = [ class scala/collection/immutable/HashMap$HashKeySet ]
        frame_type = 78 /* same_locals_1_stack_item */
          stack = [ class scala/collection/immutable/HashMap$HashKeySet ]
        frame_type = 255 /* full_frame */
          offset_delta = 41
          locals = [ class scala/collection/immutable/HashMap$HashKeySet, class scala/Function1, class scala/collection/immutable/HashMap, class scala/Function1, int, top, class scala/collection/immutable/BitmapIndexedMapNode, int, int, int, int, int, int, int, class "[Ljava/lang/Object;", class "[I", int, int, int ]
          stack = [ class scala/collection/immutable/HashMap$HashKeySet ]
        frame_type = 255 /* full_frame */
          offset_delta = 98
          locals = [ class scala/collection/immutable/HashMap$HashKeySet, class scala/Function1, class scala/collection/immutable/HashMap, class scala/Function1, int, top, class scala/collection/immutable/BitmapIndexedMapNode, int, int, int, int, int, int, int, class "[Ljava/lang/Object;", class "[I", int, int, int, top, top, top, top, top, top, top, top, top, top, top, top, top, top, top, top, top, top, top, top, top, top, top, top, top, top, top, top, top, top, top, top, top, int ]
          stack = [ class scala/collection/immutable/HashMap$HashKeySet ]
        frame_type = 255 /* full_frame */
          offset_delta = 5
          locals = [ class scala/collection/immutable/HashMap$HashKeySet, class scala/Function1, class scala/collection/immutable/HashMap, class scala/Function1, int, top, class scala/collection/immutable/BitmapIndexedMapNode, int, int, int, int, int, int, int, class "[Ljava/lang/Object;", class "[I", int, int, int ]
          stack = [ class scala/collection/immutable/HashMap$HashKeySet ]
        frame_type = 255 /* full_frame */
          offset_delta = 20
          locals = [ class scala/collection/immutable/HashMap$HashKeySet, class scala/Function1, class scala/collection/immutable/HashMap, class scala/Function1, int, top, class scala/collection/immutable/BitmapIndexedMapNode ]
          stack = [ class scala/collection/immutable/HashMap$HashKeySet ]
        frame_type = 255 /* full_frame */
          offset_delta = 69
          locals = [ class scala/collection/immutable/HashMap$HashKeySet, class scala/Function1, class scala/collection/immutable/HashMap, class scala/Function1, int, top, class scala/collection/immutable/BitmapIndexedMapNode, top, top, top, top, top, top, top, top, top, top, top, top, int, int, int, int, int, class scala/collection/mutable/Queue, int, int, class scala/collection/mutable/Queue, int, int, int, int, int, int, int ]
          stack = [ class scala/collection/immutable/HashMap$HashKeySet ]
        frame_type = 255 /* full_frame */
          offset_delta = 60
          locals = [ class scala/collection/immutable/HashMap$HashKeySet, class scala/Function1, class scala/collection/immutable/HashMap, class scala/Function1, int, top, class scala/collection/immutable/BitmapIndexedMapNode, top, top, top, top, top, top, top, top, top, top, top, top, int, int, int, int, int, class scala/collection/mutable/Queue, int, int, class scala/collection/mutable/Queue, int, int, int, int, int, int, int, top, top, top, top, top, top, top, top, top, top, top, top, top, top, top, top, top, top, int, class scala/Tuple2 ]
          stack = [ class scala/collection/immutable/HashMap$HashKeySet ]
        frame_type = 255 /* full_frame */
          offset_delta = 0
          locals = [ class scala/collection/immutable/HashMap$HashKeySet, class scala/Function1, class scala/collection/immutable/HashMap, class scala/Function1, int, top, class scala/collection/immutable/BitmapIndexedMapNode, top, top, top, top, top, top, top, top, top, top, top, top, int, int, int, int, int, class scala/collection/mutable/Queue, int, int, class scala/collection/mutable/Queue, int, int, int, int, int, int, int, top, top, top, top, top, top, top, top, top, top, top, top, top, top, top, top, top, top, int, class scala/Tuple2 ]
          stack = [ class scala/collection/immutable/HashMap$HashKeySet, int ]
        frame_type = 102 /* same_locals_1_stack_item */
          stack = [ class scala/collection/immutable/HashMap$HashKeySet ]
        frame_type = 255 /* full_frame */
          offset_delta = 5
          locals = [ class scala/collection/immutable/HashMap$HashKeySet, class scala/Function1, class scala/collection/immutable/HashMap, class scala/Function1, int, top, class scala/collection/immutable/BitmapIndexedMapNode, top, top, top, top, top, top, top, top, top, top, top, top, int, int, int, int, int, class scala/collection/mutable/Queue, int, int, class scala/collection/mutable/Queue, int, int, int, int, int, int, int, top, top, top, top, top, top, top, top, top, top, top, top, top, top, top, top, top, top, int ]
          stack = [ class scala/collection/immutable/HashMap$HashKeySet ]
        frame_type = 255 /* full_frame */
          offset_delta = 83
          locals = [ class scala/collection/immutable/HashMap$HashKeySet, class scala/Function1, class scala/collection/immutable/HashMap, class scala/Function1, int, top, class scala/collection/immutable/BitmapIndexedMapNode, top, top, top, top, top, top, top, top, top, top, top, top, int, int, int, int, int, class scala/collection/mutable/Queue, int, int, class scala/collection/mutable/Queue, int, int, int, int, int, int, int, class scala/collection/immutable/MapNode, class scala/collection/immutable/MapNode, top, top, top, top, top, top, top, top, top, top, top, top, top, top, top, top, int ]
          stack = [ class scala/collection/immutable/HashMap$HashKeySet ]
        frame_type = 83 /* same_locals_1_stack_item */
          stack = [ class scala/collection/immutable/HashMap$HashKeySet ]
        frame_type = 74 /* same_locals_1_stack_item */
          stack = [ class scala/collection/immutable/HashMap$HashKeySet ]
        frame_type = 105 /* same_locals_1_stack_item */
          stack = [ class scala/collection/immutable/HashMap$HashKeySet ]
        frame_type = 71 /* same_locals_1_stack_item */
          stack = [ class scala/collection/immutable/HashMap$HashKeySet ]
        frame_type = 255 /* full_frame */
          offset_delta = 2
          locals = [ class scala/collection/immutable/HashMap$HashKeySet, class scala/Function1, class scala/collection/immutable/HashMap, class scala/Function1, int, top, class scala/collection/immutable/BitmapIndexedMapNode, top, top, top, top, top, top, top, top, top, top, top, top, int, int, int, int, int, class scala/collection/mutable/Queue, int, int, class scala/collection/mutable/Queue, int, int, int, int, int, int, int, top, top, top, top, top, top, top, top, top, top, top, top, top, top, top, top, top, top, int ]
          stack = [ class scala/collection/immutable/HashMap$HashKeySet ]
        frame_type = 255 /* full_frame */
          offset_delta = 5
          locals = [ class scala/collection/immutable/HashMap$HashKeySet, class scala/Function1, class scala/collection/immutable/HashMap, class scala/Function1, int, top, class scala/collection/immutable/BitmapIndexedMapNode, top, top, top, top, top, top, top, top, top, top, top, top, int, int, int, int, int, class scala/collection/mutable/Queue, int, int, class scala/collection/mutable/Queue, int, int, int, int, int, int, int ]
          stack = [ class scala/collection/immutable/HashMap$HashKeySet ]
        frame_type = 78 /* same_locals_1_stack_item */
          stack = [ class scala/collection/immutable/HashMap$HashKeySet ]
        frame_type = 78 /* same_locals_1_stack_item */
          stack = [ class scala/collection/immutable/HashMap$HashKeySet ]
        frame_type = 255 /* full_frame */
          offset_delta = 64
          locals = [ class scala/collection/immutable/HashMap$HashKeySet, class scala/Function1, class scala/collection/immutable/HashMap, class scala/Function1, int, top, class scala/collection/immutable/BitmapIndexedMapNode, top, top, top, top, top, top, top, top, top, top, top, top, int, int, int, int, int, class scala/collection/mutable/Queue, int, int, class scala/collection/mutable/Queue, int, int, int, int, int, int, int, top, top, int, int, class "[Ljava/lang/Object;", class "[I", int, int, int, int, int, int, int ]
          stack = [ class scala/collection/immutable/HashMap$HashKeySet ]
        frame_type = 255 /* full_frame */
          offset_delta = 85
          locals = [ class scala/collection/immutable/HashMap$HashKeySet, class scala/Function1, class scala/collection/immutable/HashMap, class scala/Function1, int, top, class scala/collection/immutable/BitmapIndexedMapNode, top, top, top, top, top, top, top, top, top, top, top, top, int, int, int, int, int, class scala/collection/mutable/Queue, int, int, class scala/collection/mutable/Queue, int, int, int, int, int, int, int, top, top, int, int, class "[Ljava/lang/Object;", class "[I", int, int, int, int, int, int, int, int ]
          stack = [ class scala/collection/immutable/HashMap$HashKeySet ]
        frame_type = 98 /* same_locals_1_stack_item */
          stack = [ class scala/collection/immutable/HashMap$HashKeySet ]
        frame_type = 247 /* same_locals_1_stack_item_frame_extended */
          offset_delta = 66
          stack = [ class scala/collection/immutable/HashMap$HashKeySet ]
        frame_type = 96 /* same_locals_1_stack_item */
          stack = [ class scala/collection/immutable/HashMap$HashKeySet ]
        frame_type = 81 /* same_locals_1_stack_item */
          stack = [ class scala/collection/immutable/HashMap$HashKeySet ]
        frame_type = 78 /* same_locals_1_stack_item */
          stack = [ class scala/collection/immutable/HashMap$HashKeySet ]
        frame_type = 255 /* full_frame */
          offset_delta = 5
          locals = [ class scala/collection/immutable/HashMap$HashKeySet, class scala/Function1, class scala/collection/immutable/HashMap, class scala/Function1, int, top, class scala/collection/immutable/BitmapIndexedMapNode, top, top, top, top, top, top, top, top, top, top, top, top, int, int, int, int, int, class scala/collection/mutable/Queue, int, int, class scala/collection/mutable/Queue, int, int, int, int, int, int, int, top, top, int, int, class "[Ljava/lang/Object;", class "[I", int, int, int, int, int, int, int ]
          stack = [ class scala/collection/immutable/HashMap$HashKeySet ]
        frame_type = 255 /* full_frame */
          offset_delta = 18
          locals = [ class scala/collection/immutable/HashMap$HashKeySet, class scala/Function1, class scala/collection/immutable/HashMap, class scala/Function1, int, top, class scala/collection/immutable/BitmapIndexedMapNode ]
          stack = [ class scala/collection/immutable/HashMap$HashKeySet, class scala/collection/immutable/BitmapIndexedMapNode ]
        frame_type = 255 /* full_frame */
          offset_delta = 44
          locals = [ class scala/collection/immutable/HashMap$HashKeySet, class scala/Function1, class scala/collection/immutable/HashMap, class scala/Function1, int, class scala/collection/immutable/BitmapIndexedMapNode, null, top, top, top, top, top, top, top, null, null, top, top, top, top, top, top, top, top, null, top, top, null, top, top, top, top, top, top, top, null, null, top, top, null, null, top, top, top, top, top, top, top, top, null ]
          stack = [ class scala/collection/immutable/HashMap$HashKeySet ]
        frame_type = 81 /* same_locals_1_stack_item */
          stack = [ class scala/collection/immutable/HashMap$HashKeySet ]
        frame_type = 255 /* full_frame */
          offset_delta = 8
          locals = [ class scala/collection/immutable/HashMap$HashKeySet, class scala/Function1, class scala/collection/immutable/HashMap, class scala/Function1, int, class scala/collection/immutable/BitmapIndexedMapNode, null, top, top, top, top, top, top, top, null, null, top, top, top, top, top, top, top, top, null, top, top, null, top, top, top, top, top, top, top, null, null, top, top, null, null, top, top, top, top, top, top, top, top, null ]
          stack = [ class scala/collection/immutable/HashMap$HashKeySet, class scala/collection/immutable/HashMap ]
      LineNumberTable:
        line 75: 0
        line 39: 19
        line 360: 22
        line 1594: 34
        line 1595: 48
        line 1596: 57
        line 75: 65
        line 1596: 79
        line 1597: 98
        line 1611: 107
        line 1612: 117
        line 1614: 130
        line 1615: 133
        line 1616: 136
        line 1618: 139
        line 1620: 143
        line 1621: 150
        line 1623: 160
        line 1624: 172
        line 1625: 179
        line 75: 181
        line 1625: 195
        line 1627: 205
        line 1628: 208
        line 1629: 215
        line 620: 220
        line 1629: 228
        line 1632: 234
        line 1635: 237
        line 1620: 240
        line 1638: 243
        line 1639: 249
        line 1640: 258
        line 1641: 268
        line 1643: 273
        line 1644: 280
        line 1645: 289
        line 1646: 295
        line 1648: 305
        line 1650: 312
        line 1653: 315
        line 1654: 322
        line 1655: 332
        line 1656: 341
        line 1657: 360
        line 1658: 377
        line 1659: 398
        line 1660: 411
        line 1662: 414
        line 1653: 417
        line 1665: 420
        line 1670: 441
        line 1671: 454
        line 1672: 461
        line 1674: 471
        line 1677: 474
        line 1679: 477
        line 1682: 480
        line 1687: 483
        line 1689: 486
        line 1691: 489
        line 1692: 492
        line 1693: 495
        line 1694: 498
        line 1696: 501
        line 1697: 504
        line 1699: 507
        line 1700: 511
        line 1701: 518
        line 1703: 528
        line 1704: 540
        line 1705: 547
        line 75: 549
        line 1705: 563
        line 1707: 573
        line 1708: 576
        line 1709: 583
        line 1710: 590
        line 1711: 593
        line 620: 598
        line 1711: 606
        line 1714: 612
        line 1715: 618
        line 1716: 630
        line 1717: 639
        line 1719: 649
        line 1720: 659
        line 1723: 669
        line 1724: 678
        line 1725: 685
        line 1726: 692
        line 1728: 702
        line 1729: 709
        line 1730: 714
        line 1732: 722
        line 1734: 733
        line 1735: 742
        line 1736: 749
        line 1737: 756
        line 1738: 761
        line 1740: 775
        line 1743: 783
        line 1746: 786
        line 1700: 789
        line 1749: 792
        line 1750: 798
        line 1751: 807
        line 1752: 817
        line 1754: 822
        line 1755: 829
        line 1756: 841
        line 1757: 848
        line 1759: 854
        line 1760: 861
        line 1764: 871
        line 1766: 875
        line 1767: 878
        line 1769: 881
        line 1770: 884
        line 1772: 887
        line 1773: 894
        line 1775: 904
        line 1776: 913
        line 613: 919
        line 1776: 929
        line 1777: 930
        line 614: 938
        line 1777: 950
        line 1778: 951
        line 620: 955
        line 1778: 963
        line 1779: 964
        line 1780: 967
        line 1781: 973
        line 1782: 982
        line 1783: 999
        line 1784: 1002
        line 1785: 1008
        line 1787: 1017
        line 1788: 1027
        line 1789: 1040
        line 1790: 1055
        line 1791: 1066
        line 1792: 1069
        line 1793: 1075
        line 1794: 1084
        line 1795: 1099
        line 1796: 1102
        line 1797: 1108
        line 1798: 1120
        line 1799: 1126
        line 1800: 1138
        line 1803: 1141
        line 1772: 1144
        line 1806: 1147
        line 360: 1166
        line 361: 1198
        line 362: 1211
        line 363: 1229
        line 39: 1238
        line 75: 1241
      LocalVariableTable:
        Start  Length  Slot  Name   Signature
            0    1249     0  this   Lscala/collection/immutable/HashMap$HashKeySet;
            0    1249     1  pred   Lscala/Function1;
           19    1222     2 filterNot_this   Lscala/collection/immutable/HashMap;
           19    1222     3 filterNot_pred   Lscala/Function1;
           22    1219     4 filterImpl_isFlipped   Z
         1198      40     5 filterImpl_newRootNode   Lscala/collection/immutable/BitmapIndexedMapNode;
          280     158    13 filterImpl_filterImpl_newSize   I
          289     149    14 filterImpl_filterImpl_newContent   [Ljava/lang/Object;
          295     143    15 filterImpl_filterImpl_newOriginalHashCodes   [I
          305     133    16 filterImpl_filterImpl_newMaximumIndex   I
          312     126    17 filterImpl_filterImpl_j   I
          315     123    18 filterImpl_filterImpl_newDataIndex   I
          117     321     7 filterImpl_filterImpl_minimumIndex   I
          130     308     8 filterImpl_filterImpl_maximumIndex   I
          133     305     9 filterImpl_filterImpl_newDataMap   I
          136     302    10 filterImpl_filterImpl_newCachedHashCode   I
          139     299    11 filterImpl_filterImpl_dataIndex   I
          143     295    12 filterImpl_filterImpl_i   I
          639     147    35 filterImpl_filterImpl_oldSubNode   Lscala/collection/immutable/MapNode;
          649     137    36 filterImpl_filterImpl_newSubNode   Lscala/collection/immutable/MapNode;
         1027      45    49 filterImpl_filterImpl_node   Lscala/collection/immutable/MapNode;
          904     240    48 filterImpl_filterImpl_bitpos   I
          829     337    37 filterImpl_filterImpl_newDataSize   I
          841     325    38 filterImpl_filterImpl_newContentSize   I
          848     318    39 filterImpl_filterImpl_newContent   [Ljava/lang/Object;
          854     312    40 filterImpl_filterImpl_newOriginalHashes   [I
          861     305    41 filterImpl_filterImpl_newAllMap   I
          871     295    42 filterImpl_filterImpl_maxIndex   I
          875     291    43 filterImpl_filterImpl_i   I
          878     288    44 filterImpl_filterImpl_oldDataIndex   I
          881     285    45 filterImpl_filterImpl_oldNodeIndex   I
          884     282    46 filterImpl_filterImpl_newDataIndex   I
          887     279    47 filterImpl_filterImpl_newNodeIndex   I
          454     712    19 filterImpl_filterImpl_allMap   I
          461     705    20 filterImpl_filterImpl_minimumIndex   I
          471     695    21 filterImpl_filterImpl_maximumIndex   I
          474     692    22 filterImpl_filterImpl_oldDataPassThrough   I
          477     689    23 filterImpl_filterImpl_nodeMigrateToDataTargetMap   I
          480     686    24 filterImpl_filterImpl_nodesToMigrateToData   Lscala/collection/mutable/Queue;
          483     683    25 filterImpl_filterImpl_nodesToPassThroughMap   I
          486     680    26 filterImpl_filterImpl_mapOfNewNodes   I
          489     677    27 filterImpl_filterImpl_newNodes   Lscala/collection/mutable/Queue;
          492     674    28 filterImpl_filterImpl_newDataMap   I
          495     671    29 filterImpl_filterImpl_newNodeMap   I
          498     668    30 filterImpl_filterImpl_newSize   I
          501     665    31 filterImpl_filterImpl_newCachedHashCode   I
          504     662    32 filterImpl_filterImpl_dataIndex   I
          507     659    33 filterImpl_filterImpl_nodeIndex   I
          511     655    34 filterImpl_filterImpl_i   I
           34    1132     6 filterImpl_filterImpl_this   Lscala/collection/immutable/BitmapIndexedMapNode;
    Signature: #89                          // (Lscala/Function1<TK;Ljava/lang/Object;>;)Lscala/collection/immutable/Set<TK;>;
    MethodParameters:
      Name                           Flags
      pred                           final

  public scala.collection.immutable.HashMap scala$collection$immutable$HashMap$HashKeySet$$$outer();
    descriptor: ()Lscala/collection/immutable/HashMap;
    flags: (0x1001) ACC_PUBLIC, ACC_SYNTHETIC
    Code:
      stack=1, locals=1, args_size=1
         0: aload_0
         1: getfield      #297                // Field $outer:Lscala/collection/immutable/MapOps;
         4: checkcast     #13                 // class scala/collection/immutable/HashMap
         7: areturn
      LineNumberTable:
        line 60: 0
      LocalVariableTable:
        Start  Length  Slot  Name   Signature
            0       8     0  this   Lscala/collection/immutable/HashMap$HashKeySet;

  public java.lang.Object filterNot(scala.Function1);
    descriptor: (Lscala/Function1;)Ljava/lang/Object;
    flags: (0x1041) ACC_PUBLIC, ACC_BRIDGE, ACC_SYNTHETIC
    Code:
      stack=2, locals=2, args_size=2
         0: aload_0
         1: aload_1
         2: invokevirtual #300                // Method filterNot:(Lscala/Function1;)Lscala/collection/immutable/Set;
         5: areturn
      LineNumberTable:
        line 60: 0
      LocalVariableTable:
        Start  Length  Slot  Name   Signature
            0       6     0  this   Lscala/collection/immutable/HashMap$HashKeySet;
            0       6     1  pred   Lscala/Function1;
    MethodParameters:
      Name                           Flags
      pred                           final

  public java.lang.Object filter(scala.Function1);
    descriptor: (Lscala/Function1;)Ljava/lang/Object;
    flags: (0x1041) ACC_PUBLIC, ACC_BRIDGE, ACC_SYNTHETIC
    Code:
      stack=2, locals=2, args_size=2
         0: aload_0
         1: aload_1
         2: invokevirtual #302                // Method filter:(Lscala/Function1;)Lscala/collection/immutable/Set;
         5: areturn
      LineNumberTable:
        line 60: 0
      LocalVariableTable:
        Start  Length  Slot  Name   Signature
            0       6     0  this   Lscala/collection/immutable/HashMap$HashKeySet;
            0       6     1  pred   Lscala/Function1;
    MethodParameters:
      Name                           Flags
      pred                           final

  public scala.collection.immutable.SetOps excl(java.lang.Object);
    descriptor: (Ljava/lang/Object;)Lscala/collection/immutable/SetOps;
    flags: (0x1041) ACC_PUBLIC, ACC_BRIDGE, ACC_SYNTHETIC
    Code:
      stack=2, locals=2, args_size=2
         0: aload_0
         1: aload_1
         2: invokevirtual #305                // Method excl:(Ljava/lang/Object;)Lscala/collection/immutable/Set;
         5: areturn
      LineNumberTable:
        line 60: 0
      LocalVariableTable:
        Start  Length  Slot  Name   Signature
            0       6     0  this   Lscala/collection/immutable/HashMap$HashKeySet;
            0       6     1  elem   Ljava/lang/Object;
    MethodParameters:
      Name                           Flags
      elem                           final

  public scala.collection.immutable.SetOps incl(java.lang.Object);
    descriptor: (Ljava/lang/Object;)Lscala/collection/immutable/SetOps;
    flags: (0x1041) ACC_PUBLIC, ACC_BRIDGE, ACC_SYNTHETIC
    Code:
      stack=2, locals=2, args_size=2
         0: aload_0
         1: aload_1
         2: invokevirtual #307                // Method incl:(Ljava/lang/Object;)Lscala/collection/immutable/Set;
         5: areturn
      LineNumberTable:
        line 60: 0
      LocalVariableTable:
        Start  Length  Slot  Name   Signature
            0       6     0  this   Lscala/collection/immutable/HashMap$HashKeySet;
            0       6     1  elem   Ljava/lang/Object;
    MethodParameters:
      Name                           Flags
      elem                           final

  public static final boolean $anonfun$filter$1(scala.Function1, scala.Tuple2);
    descriptor: (Lscala/Function1;Lscala/Tuple2;)Z
    flags: (0x1019) ACC_PUBLIC, ACC_STATIC, ACC_FINAL, ACC_SYNTHETIC
    Code:
      stack=2, locals=2, args_size=2
         0: aload_0
         1: aload_1
         2: invokevirtual #126                // Method scala/Tuple2._1:()Ljava/lang/Object;
         5: invokeinterface #130,  2          // InterfaceMethod scala/Function1.apply:(Ljava/lang/Object;)Ljava/lang/Object;
        10: invokestatic  #136                // Method scala/runtime/BoxesRunTime.unboxToBoolean:(Ljava/lang/Object;)Z
        13: ireturn
      LineNumberTable:
        line 74: 0
      LocalVariableTable:
        Start  Length  Slot  Name   Signature
            0      14     0 pred$1   Lscala/Function1;
            0      14     1    kv   Lscala/Tuple2;
    MethodParameters:
      Name                           Flags
      pred$1                         final
      kv                             final

  public static final boolean $anonfun$filterNot$1(scala.Function1, scala.Tuple2);
    descriptor: (Lscala/Function1;Lscala/Tuple2;)Z
    flags: (0x1019) ACC_PUBLIC, ACC_STATIC, ACC_FINAL, ACC_SYNTHETIC
    Code:
      stack=2, locals=2, args_size=2
         0: aload_0
         1: aload_1
         2: invokevirtual #126                // Method scala/Tuple2._1:()Ljava/lang/Object;
         5: invokeinterface #130,  2          // InterfaceMethod scala/Function1.apply:(Ljava/lang/Object;)Ljava/lang/Object;
        10: invokestatic  #136                // Method scala/runtime/BoxesRunTime.unboxToBoolean:(Ljava/lang/Object;)Z
        13: ireturn
      LineNumberTable:
        line 75: 0
      LocalVariableTable:
        Start  Length  Slot  Name   Signature
            0      14     0 pred$2   Lscala/Function1;
            0      14     1    kv   Lscala/Tuple2;
    MethodParameters:
      Name                           Flags
      pred$2                         final
      kv                             final

  public scala.collection.immutable.HashMap$HashKeySet(scala.collection.immutable.HashMap);
    descriptor: (Lscala/collection/immutable/HashMap;)V
    flags: (0x0001) ACC_PUBLIC
    Code:
      stack=2, locals=2, args_size=2
         0: aload_0
         1: aload_1
         2: invokespecial #318                // Method scala/collection/immutable/MapOps$ImmutableKeySet."<init>":(Lscala/collection/immutable/MapOps;)V
         5: return
      LineNumberTable:
        line 60: 0
      LocalVariableTable:
        Start  Length  Slot  Name   Signature
            0       6     0  this   Lscala/collection/immutable/HashMap$HashKeySet;
            0       6     1 $outer   Lscala/collection/immutable/HashMap;
    MethodParameters:
      Name                           Flags
      $outer                         final synthetic

  public static final java.lang.Object $anonfun$filter$1$adapted(scala.Function1, scala.Tuple2);
    descriptor: (Lscala/Function1;Lscala/Tuple2;)Ljava/lang/Object;
    flags: (0x1019) ACC_PUBLIC, ACC_STATIC, ACC_FINAL, ACC_SYNTHETIC
    Code:
      stack=2, locals=2, args_size=2
         0: aload_0
         1: aload_1
         2: invokestatic  #320                // Method $anonfun$filter$1:(Lscala/Function1;Lscala/Tuple2;)Z
         5: invokestatic  #324                // Method scala/runtime/BoxesRunTime.boxToBoolean:(Z)Ljava/lang/Boolean;
         8: areturn
      LineNumberTable:
        line 74: 0
      LocalVariableTable:
        Start  Length  Slot  Name   Signature
            0       9     0 pred$1   Lscala/Function1;
            0       9     1    kv   Lscala/Tuple2;
    MethodParameters:
      Name                           Flags
      pred$1                         final
      kv                             final

  public static final java.lang.Object $anonfun$filterNot$1$adapted(scala.Function1, scala.Tuple2);
    descriptor: (Lscala/Function1;Lscala/Tuple2;)Ljava/lang/Object;
    flags: (0x1019) ACC_PUBLIC, ACC_STATIC, ACC_FINAL, ACC_SYNTHETIC
    Code:
      stack=2, locals=2, args_size=2
         0: aload_0
         1: aload_1
         2: invokestatic  #326                // Method $anonfun$filterNot$1:(Lscala/Function1;Lscala/Tuple2;)Z
         5: invokestatic  #324                // Method scala/runtime/BoxesRunTime.boxToBoolean:(Z)Ljava/lang/Boolean;
         8: areturn
      LineNumberTable:
        line 75: 0
      LocalVariableTable:
        Start  Length  Slot  Name   Signature
            0       9     0 pred$2   Lscala/Function1;
            0       9     1    kv   Lscala/Tuple2;
    MethodParameters:
      Name                           Flags
      pred$2                         final
      kv                             final

  private static java.lang.Object $deserializeLambda$(java.lang.invoke.SerializedLambda);
    descriptor: (Ljava/lang/invoke/SerializedLambda;)Ljava/lang/Object;
    flags: (0x100a) ACC_PRIVATE, ACC_STATIC, ACC_SYNTHETIC
    Code:
      stack=1, locals=1, args_size=1
         0: aload_0
         1: invokedynamic #338,  0            // InvokeDynamic #2:lambdaDeserialize:(Ljava/lang/invoke/SerializedLambda;)Ljava/lang/Object;
         6: areturn
}
InnerClasses:
  public static final #11= #8 of #10;     // Lookup=class java/lang/invoke/MethodHandles$Lookup of class java/lang/invoke/MethodHandles
  private final #14= #2 of #13;           // HashKeySet=class scala/collection/immutable/HashMap$HashKeySet of class scala/collection/immutable/HashMap
  public #17= #5 of #16;                  // ImmutableKeySet=class scala/collection/immutable/MapOps$ImmutableKeySet of class scala/collection/immutable/MapOps
Signature: #3                           // Lscala/collection/immutable/MapOps<TK;TV;*Lscala/collection/immutable/HashMap<TK;TV;>;>.ImmutableKeySet;
SourceFile: "HashMap.scala"
BootstrapMethods:
  0: #108 REF_invokeStatic java/lang/invoke/LambdaMetafactory.altMetafactory:(Ljava/lang/invoke/MethodHandles$Lookup;Ljava/lang/String;Ljava/lang/invoke/MethodType;[Ljava/lang/Object;)Ljava/lang/invoke/CallSite;
    Method arguments:
      #92 (Ljava/lang/Object;)Ljava/lang/Object;
      #97 REF_invokeStatic scala/collection/immutable/HashMap$HashKeySet.$anonfun$filter$1$adapted:(Lscala/Function1;Lscala/Tuple2;)Ljava/lang/Object;
      #99 (Lscala/Tuple2;)Ljava/lang/Object;
      #100 5
      #101 1
      #99 (Lscala/Tuple2;)Ljava/lang/Object;
  1: #108 REF_invokeStatic java/lang/invoke/LambdaMetafactory.altMetafactory:(Ljava/lang/invoke/MethodHandles$Lookup;Ljava/lang/String;Ljava/lang/invoke/MethodType;[Ljava/lang/Object;)Ljava/lang/invoke/CallSite;
    Method arguments:
      #92 (Ljava/lang/Object;)Ljava/lang/Object;
      #290 REF_invokeStatic scala/collection/immutable/HashMap$HashKeySet.$anonfun$filterNot$1$adapted:(Lscala/Function1;Lscala/Tuple2;)Ljava/lang/Object;
      #99 (Lscala/Tuple2;)Ljava/lang/Object;
      #100 5
      #101 1
      #99 (Lscala/Tuple2;)Ljava/lang/Object;
  2: #335 REF_invokeStatic scala/runtime/LambdaDeserialize.bootstrap:(Ljava/lang/invoke/MethodHandles$Lookup;Ljava/lang/String;Ljava/lang/invoke/MethodType;[Ljava/lang/invoke/MethodHandle;)Ljava/lang/invoke/CallSite;
    Method arguments:
      #97 REF_invokeStatic scala/collection/immutable/HashMap$HashKeySet.$anonfun$filter$1$adapted:(Lscala/Function1;Lscala/Tuple2;)Ljava/lang/Object;
      #290 REF_invokeStatic scala/collection/immutable/HashMap$HashKeySet.$anonfun$filterNot$1$adapted:(Lscala/Function1;Lscala/Tuple2;)Ljava/lang/Object;
  ScalaInlineInfo: length = 0x54 (unknown attribute)
   01 01 00 10 01 34 01 35 01 00 5D 00 5E 01 01 39
   01 35 01 01 1F 00 5E 01 00 28 01 3B 01 00 4E 00
   2E 01 00 4E 01 2F 01 00 57 01 2A 01 00 57 00 58
   01 01 1E 01 2A 01 01 1E 00 58 01 00 2D 00 2E 01
   00 2D 01 2F 01 00 12 00 21 01 00 12 00 13 01 00
   16 00 17 01
  Scala: length = 0x0 (unknown attribute)

