Classfile /Users/mw/Projects/slang-braindump/.jar/jar11/assemble/slang-braindump/assemble/content/scala/collection/immutable/HashMapBuilder$$anon$1.class
  Last modified May 29, 2022; size 1914 bytes
  SHA-256 checksum 0f4b29d324683f4ef51c68e0b2e6f02fe1946b2a574706610248620367cbfafd
  Compiled from "HashMap.scala"
public final class scala.collection.immutable.HashMapBuilder$$anon$1 extends scala.collection.immutable.ChampBaseIterator<scala.collection.immutable.MapNode<K, V>>
  minor version: 0
  major version: 52
  flags: (0x0031) ACC_PUBLIC, ACC_FINAL, ACC_SUPER
  this_class: #2                          // scala/collection/immutable/HashMapBuilder$$anon$1
  super_class: #5                         // scala/collection/immutable/ChampBaseIterator
  interfaces: 0, fields: 0, methods: 1, attributes: 6
Constant pool:
   #1 = Utf8               scala/collection/immutable/HashMapBuilder$$anon$1
   #2 = Class              #1             // scala/collection/immutable/HashMapBuilder$$anon$1
   #3 = Utf8               Lscala/collection/immutable/ChampBaseIterator<Lscala/collection/immutable/MapNode<TK;TV;>;>;
   #4 = Utf8               scala/collection/immutable/ChampBaseIterator
   #5 = Class              #4             // scala/collection/immutable/ChampBaseIterator
   #6 = Utf8               HashMap.scala
   #7 = Utf8               scala/collection/immutable/HashMapBuilder
   #8 = Class              #7             // scala/collection/immutable/HashMapBuilder
   #9 = Utf8               addAll
  #10 = Utf8               (Lscala/collection/IterableOnce;)Lscala/collection/immutable/HashMapBuilder;
  #11 = NameAndType        #9:#10         // addAll:(Lscala/collection/IterableOnce;)Lscala/collection/immutable/HashMapBuilder;
  #12 = Utf8               <init>
  #13 = Utf8               (Lscala/collection/immutable/HashMapBuilder;Lscala/collection/immutable/HashMap;)V
  #14 = Utf8               $outer
  #15 = Utf8               x2$1
  #16 = Utf8               scala/collection/immutable/HashMap
  #17 = Class              #16            // scala/collection/immutable/HashMap
  #18 = Utf8               rootNode
  #19 = Utf8               ()Lscala/collection/immutable/BitmapIndexedMapNode;
  #20 = NameAndType        #18:#19        // rootNode:()Lscala/collection/immutable/BitmapIndexedMapNode;
  #21 = Methodref          #17.#20        // scala/collection/immutable/HashMap.rootNode:()Lscala/collection/immutable/BitmapIndexedMapNode;
  #22 = Utf8               (Lscala/collection/immutable/Node;)V
  #23 = NameAndType        #12:#22        // "<init>":(Lscala/collection/immutable/Node;)V
  #24 = Methodref          #5.#23         // scala/collection/immutable/ChampBaseIterator."<init>":(Lscala/collection/immutable/Node;)V
  #25 = Utf8               hasNext
  #26 = Utf8               ()Z
  #27 = NameAndType        #25:#26        // hasNext:()Z
  #28 = Methodref          #2.#27         // scala/collection/immutable/HashMapBuilder$$anon$1.hasNext:()Z
  #29 = Utf8               currentValueNode
  #30 = Utf8               ()Lscala/collection/immutable/Node;
  #31 = NameAndType        #29:#30        // currentValueNode:()Lscala/collection/immutable/Node;
  #32 = Methodref          #2.#31         // scala/collection/immutable/HashMapBuilder$$anon$1.currentValueNode:()Lscala/collection/immutable/Node;
  #33 = Utf8               currentValueCursor
  #34 = Utf8               ()I
  #35 = NameAndType        #33:#34        // currentValueCursor:()I
  #36 = Methodref          #2.#35         // scala/collection/immutable/HashMapBuilder$$anon$1.currentValueCursor:()I
  #37 = Utf8               scala/collection/immutable/Node
  #38 = Class              #37            // scala/collection/immutable/Node
  #39 = Utf8               getHash
  #40 = Utf8               (I)I
  #41 = NameAndType        #39:#40        // getHash:(I)I
  #42 = Methodref          #38.#41        // scala/collection/immutable/Node.getHash:(I)I
  #43 = Utf8               scala$collection$immutable$HashMapBuilder$$rootNode
  #44 = NameAndType        #43:#19        // scala$collection$immutable$HashMapBuilder$$rootNode:()Lscala/collection/immutable/BitmapIndexedMapNode;
  #45 = Methodref          #8.#44         // scala/collection/immutable/HashMapBuilder.scala$collection$immutable$HashMapBuilder$$rootNode:()Lscala/collection/immutable/BitmapIndexedMapNode;
  #46 = Utf8               scala/collection/immutable/MapNode
  #47 = Class              #46            // scala/collection/immutable/MapNode
  #48 = Utf8               getKey
  #49 = Utf8               (I)Ljava/lang/Object;
  #50 = NameAndType        #48:#49        // getKey:(I)Ljava/lang/Object;
  #51 = Methodref          #47.#50        // scala/collection/immutable/MapNode.getKey:(I)Ljava/lang/Object;
  #52 = Utf8               getValue
  #53 = NameAndType        #52:#49        // getValue:(I)Ljava/lang/Object;
  #54 = Methodref          #47.#53        // scala/collection/immutable/MapNode.getValue:(I)Ljava/lang/Object;
  #55 = Utf8               scala/collection/Hashing$
  #56 = Class              #55            // scala/collection/Hashing$
  #57 = Utf8               MODULE$
  #58 = Utf8               Lscala/collection/Hashing$;
  #59 = NameAndType        #57:#58        // MODULE$:Lscala/collection/Hashing$;
  #60 = Fieldref           #56.#59        // scala/collection/Hashing$.MODULE$:Lscala/collection/Hashing$;
  #61 = Utf8               improve
  #62 = NameAndType        #61:#40        // improve:(I)I
  #63 = Methodref          #56.#62        // scala/collection/Hashing$.improve:(I)I
  #64 = Utf8               update
  #65 = Utf8               (Lscala/collection/immutable/MapNode;Ljava/lang/Object;Ljava/lang/Object;III)V
  #66 = NameAndType        #64:#65        // update:(Lscala/collection/immutable/MapNode;Ljava/lang/Object;Ljava/lang/Object;III)V
  #67 = Methodref          #8.#66         // scala/collection/immutable/HashMapBuilder.update:(Lscala/collection/immutable/MapNode;Ljava/lang/Object;Ljava/lang/Object;III)V
  #68 = Utf8               currentValueCursor_$eq
  #69 = Utf8               (I)V
  #70 = NameAndType        #68:#69        // currentValueCursor_$eq:(I)V
  #71 = Methodref          #2.#70         // scala/collection/immutable/HashMapBuilder$$anon$1.currentValueCursor_$eq:(I)V
  #72 = Utf8               originalHash
  #73 = Utf8               I
  #74 = Utf8               this
  #75 = Utf8               Lscala/collection/immutable/HashMapBuilder$$anon$1;
  #76 = Utf8               Lscala/collection/immutable/HashMapBuilder;
  #77 = Utf8               Lscala/collection/immutable/HashMap;
  #78 = Utf8               Code
  #79 = Utf8               StackMapTable
  #80 = Utf8               LineNumberTable
  #81 = Utf8               LocalVariableTable
  #82 = Utf8               MethodParameters
  #83 = Utf8               InnerClasses
  #84 = Utf8               EnclosingMethod
  #85 = Utf8               Signature
  #86 = Utf8               SourceFile
  #87 = Utf8               ScalaInlineInfo
  #88 = Utf8               Scala
{
  public scala.collection.immutable.HashMapBuilder$$anon$1(scala.collection.immutable.HashMapBuilder, scala.collection.immutable.HashMap);
    descriptor: (Lscala/collection/immutable/HashMapBuilder;Lscala/collection/immutable/HashMap;)V
    flags: (0x0001) ACC_PUBLIC
    Code:
      stack=7, locals=4, args_size=3
         0: aload_0
         1: aload_2
         2: invokevirtual #21                 // Method scala/collection/immutable/HashMap.rootNode:()Lscala/collection/immutable/BitmapIndexedMapNode;
         5: invokespecial #24                 // Method scala/collection/immutable/ChampBaseIterator."<init>":(Lscala/collection/immutable/Node;)V
         8: aload_0
         9: invokevirtual #28                 // Method hasNext:()Z
        12: ifeq          85
        15: aload_0
        16: invokevirtual #32                 // Method currentValueNode:()Lscala/collection/immutable/Node;
        19: aload_0
        20: invokevirtual #36                 // Method currentValueCursor:()I
        23: invokevirtual #42                 // Method scala/collection/immutable/Node.getHash:(I)I
        26: istore_3
        27: aload_1
        28: aload_1
        29: invokevirtual #45                 // Method scala/collection/immutable/HashMapBuilder.scala$collection$immutable$HashMapBuilder$$rootNode:()Lscala/collection/immutable/BitmapIndexedMapNode;
        32: aload_0
        33: invokevirtual #32                 // Method currentValueNode:()Lscala/collection/immutable/Node;
        36: checkcast     #47                 // class scala/collection/immutable/MapNode
        39: aload_0
        40: invokevirtual #36                 // Method currentValueCursor:()I
        43: invokevirtual #51                 // Method scala/collection/immutable/MapNode.getKey:(I)Ljava/lang/Object;
        46: aload_0
        47: invokevirtual #32                 // Method currentValueNode:()Lscala/collection/immutable/Node;
        50: checkcast     #47                 // class scala/collection/immutable/MapNode
        53: aload_0
        54: invokevirtual #36                 // Method currentValueCursor:()I
        57: invokevirtual #54                 // Method scala/collection/immutable/MapNode.getValue:(I)Ljava/lang/Object;
        60: iload_3
        61: getstatic     #60                 // Field scala/collection/Hashing$.MODULE$:Lscala/collection/Hashing$;
        64: iload_3
        65: invokevirtual #63                 // Method scala/collection/Hashing$.improve:(I)I
        68: iconst_0
        69: invokevirtual #67                 // Method scala/collection/immutable/HashMapBuilder.update:(Lscala/collection/immutable/MapNode;Ljava/lang/Object;Ljava/lang/Object;III)V
        72: aload_0
        73: aload_0
        74: invokevirtual #36                 // Method currentValueCursor:()I
        77: iconst_1
        78: iadd
        79: invokevirtual #71                 // Method currentValueCursor_$eq:(I)V
        82: goto          8
        85: return
      StackMapTable: number_of_entries = 2
        frame_type = 255 /* full_frame */
          offset_delta = 8
          locals = [ class scala/collection/immutable/HashMapBuilder$$anon$1, class scala/collection/immutable/HashMapBuilder, class scala/collection/immutable/HashMap ]
          stack = []
        frame_type = 251 /* same_frame_extended */
          offset_delta = 76
      LineNumberTable:
        line 2334: 0
        line 2335: 8
        line 2336: 15
        line 2337: 27
        line 2338: 28
        line 2339: 32
        line 2340: 46
        line 2341: 60
        line 2342: 61
        line 2343: 68
        line 2345: 72
        line 2335: 82
        line 2334: 85
      LocalVariableTable:
        Start  Length  Slot  Name   Signature
           27      55     3 originalHash   I
            0      86     0  this   Lscala/collection/immutable/HashMapBuilder$$anon$1;
            0      86     1 $outer   Lscala/collection/immutable/HashMapBuilder;
            0      86     2  x2$1   Lscala/collection/immutable/HashMap;
    MethodParameters:
      Name                           Flags
      $outer                         final synthetic
      x2$1                           final
}
InnerClasses:
  public final #2;                        // class scala/collection/immutable/HashMapBuilder$$anon$1
EnclosingMethod: #8.#11                 // scala.collection.immutable.HashMapBuilder.addAll
Signature: #3                           // Lscala/collection/immutable/ChampBaseIterator<Lscala/collection/immutable/MapNode<TK;TV;>;>;
SourceFile: "HashMap.scala"
  ScalaInlineInfo: length = 0x9 (unknown attribute)
   01 01 00 01 00 0C 00 0D 01
  Scala: length = 0x0 (unknown attribute)

