Classfile /Users/mw/Projects/slang-braindump/.jar/jar11/assemble/slang-braindump/assemble/content/scala/collection/immutable/IndexedSeqOps.class
  Last modified May 29, 2022; size 1799 bytes
  SHA-256 checksum fc04283d7545dc61db50bd2d0f89a7e8fc412aa6c68cd5ad4b29047d47a5cfd0
  Compiled from "Seq.scala"
public interface scala.collection.immutable.IndexedSeqOps<A extends java.lang.Object, CC extends java.lang.Object, C extends java.lang.Object> extends scala.collection.immutable.SeqOps<A, CC, C>, scala.collection.IndexedSeqOps<A, CC, C>
  minor version: 0
  major version: 52
  flags: (0x0601) ACC_PUBLIC, ACC_INTERFACE, ACC_ABSTRACT
  this_class: #2                          // scala/collection/immutable/IndexedSeqOps
  super_class: #5                         // java/lang/Object
  interfaces: 2, fields: 0, methods: 4, attributes: 5
Constant pool:
   #1 = Utf8               scala/collection/immutable/IndexedSeqOps
   #2 = Class              #1             // scala/collection/immutable/IndexedSeqOps
   #3 = Utf8               <A:Ljava/lang/Object;CC:Ljava/lang/Object;C:Ljava/lang/Object;>Ljava/lang/Object;Lscala/collection/immutable/SeqOps<TA;TCC;TC;>;Lscala/collection/IndexedSeqOps<TA;TCC;TC;>;
   #4 = Utf8               java/lang/Object
   #5 = Class              #4             // java/lang/Object
   #6 = Utf8               scala/collection/immutable/SeqOps
   #7 = Class              #6             // scala/collection/immutable/SeqOps
   #8 = Utf8               scala/collection/IndexedSeqOps
   #9 = Class              #8             // scala/collection/IndexedSeqOps
  #10 = Utf8               Seq.scala
  #11 = Utf8               Lscala/reflect/ScalaSignature;
  #12 = Utf8               bytes
  #13 = Utf8               \u0006\u0005\u00013q\u0001B\u0003\u0011\u0002\u0007\u0005A\u0002C\u0003.\u0001\u0011\u0005a\u0006C\u00033\u0001\u0011\u00053\u0007C\u0006<\u0001A\u0005\u0019\u0011!A\u0005\nqz$!D%oI\u0016DX\rZ*fc>\u00038O\u0003\u0002\u0007\u000f\u0005I\u0011.\\7vi\u0006\u0014G.\u001a\u0006\u0003\u0011%\t!bY8mY\u0016\u001cG/[8o\u0015\u0005Q\u0011!B:dC2\f7\u0001A\u000b\u0005\u001ba\u0011\u0003f\u0005\u0003\u0001\u001dIQ\u0003CA\b\u0011\u001b\u0005I\u0011BA\t\n\u0005\u0019\te.\u001f*fMB)1\u0003\u0006\f\"O5\tQ!\u0003\u0002\u0016\u000b\t11+Z9PaN\u0004\"a\u0006\r\r\u0001\u00111\u0011\u0004\u0001CC\u0002i\u0011\u0011!Q\t\u00037y\u0001\"a\u0004\u000f\n\u0005uI!a\u0002(pi\"Lgn\u001a\t\u0003\u001f}I!\u0001I\u0005\u0003\u0007\u0005s\u0017\u0010\u0005\u0002\u0018E\u001111\u0005\u0001CC\u0002\u0011\u0012!aQ\"\u0016\u0005i)C!\u0002\u0014#\u0005\u0004Q\"\u0001B0%II\u0002\"a\u0006\u0015\u0005\r%\u0002AQ1\u0001\u001b\u0005\u0005\u0019\u0005#B\u0016--\u0005:S\"A\u0004\n\u0005\u00119\u0011A\u0002\u0013j]&$H\u0005F\u00010!\ty\u0001\'\u0003\u00022\u0013\t!QK\\5u\u0003\u0015\u0019H.[2f)\r9C\'\u000f\u0005\u0006k\t\u0001\rAN\u0001\u0005MJ|W\u000e\u0005\u0002\u0010o%\u0011\u0001(\u0003\u0002\u0004\u0013:$\b\"\u0002\u001e\u0003\u0001\u00041\u0014!B;oi&d\u0017aC:va\u0016\u0014He\u001d7jG\u0016$2aJ\u001f?\u0011\u0015)4\u00011\u00017\u0011\u0015Q4\u00011\u00017\u0013\t\u0011D\u0006
  #14 = Utf8               scala$collection$immutable$IndexedSeqOps$$super$slice
  #15 = Utf8               (II)Ljava/lang/Object;
  #16 = Utf8               from
  #17 = Utf8               until
  #18 = Utf8               slice$
  #19 = Utf8               (Lscala/collection/immutable/IndexedSeqOps;II)Ljava/lang/Object;
  #20 = Utf8               $this
  #21 = Utf8               slice
  #22 = NameAndType        #21:#15        // slice:(II)Ljava/lang/Object;
  #23 = InterfaceMethodref #2.#22         // scala/collection/immutable/IndexedSeqOps.slice:(II)Ljava/lang/Object;
  #24 = Utf8               Lscala/collection/immutable/IndexedSeqOps;
  #25 = Utf8               I
  #26 = Utf8               (II)TC;
  #27 = Utf8               length
  #28 = Utf8               ()I
  #29 = NameAndType        #27:#28        // length:()I
  #30 = InterfaceMethodref #2.#29         // scala/collection/immutable/IndexedSeqOps.length:()I
  #31 = Utf8               coll
  #32 = Utf8               ()Ljava/lang/Object;
  #33 = NameAndType        #31:#32        // coll:()Ljava/lang/Object;
  #34 = InterfaceMethodref #2.#33         // scala/collection/immutable/IndexedSeqOps.coll:()Ljava/lang/Object;
  #35 = NameAndType        #14:#15        // scala$collection$immutable$IndexedSeqOps$$super$slice:(II)Ljava/lang/Object;
  #36 = InterfaceMethodref #2.#35         // scala/collection/immutable/IndexedSeqOps.scala$collection$immutable$IndexedSeqOps$$super$slice:(II)Ljava/lang/Object;
  #37 = Utf8               this
  #38 = Utf8               $init$
  #39 = Utf8               (Lscala/collection/immutable/IndexedSeqOps;)V
  #40 = Utf8               MethodParameters
  #41 = Utf8               Code
  #42 = Utf8               LineNumberTable
  #43 = Utf8               LocalVariableTable
  #44 = Utf8               StackMapTable
  #45 = Utf8               Signature
  #46 = Utf8               SourceFile
  #47 = Utf8               RuntimeVisibleAnnotations
  #48 = Utf8               ScalaInlineInfo
  #49 = Utf8               ScalaSig
{
  public abstract java.lang.Object scala$collection$immutable$IndexedSeqOps$$super$slice(int, int);
    descriptor: (II)Ljava/lang/Object;
    flags: (0x1401) ACC_PUBLIC, ACC_ABSTRACT, ACC_SYNTHETIC
    MethodParameters:
      Name                           Flags
      from                           final
      until                          final

  public static java.lang.Object slice$(scala.collection.immutable.IndexedSeqOps, int, int);
    descriptor: (Lscala/collection/immutable/IndexedSeqOps;II)Ljava/lang/Object;
    flags: (0x1009) ACC_PUBLIC, ACC_STATIC, ACC_SYNTHETIC
    Code:
      stack=3, locals=3, args_size=3
         0: aload_0
         1: iload_1
         2: iload_2
         3: invokespecial #23                 // InterfaceMethod slice:(II)Ljava/lang/Object;
         6: areturn
      LineNumberTable:
        line 124: 0
      LocalVariableTable:
        Start  Length  Slot  Name   Signature
            0       7     0 $this   Lscala/collection/immutable/IndexedSeqOps;
            0       7     1  from   I
            0       7     2 until   I
    MethodParameters:
      Name                           Flags
      $this                          final synthetic
      from                           final
      until                          final

  public default C slice(int, int);
    descriptor: (II)Ljava/lang/Object;
    flags: (0x0001) ACC_PUBLIC
    Code:
      stack=3, locals=3, args_size=3
         0: iload_1
         1: iconst_0
         2: if_icmpgt     22
         5: iload_2
         6: aload_0
         7: invokeinterface #30,  1           // InterfaceMethod length:()I
        12: if_icmplt     22
        15: aload_0
        16: invokeinterface #34,  1           // InterfaceMethod coll:()Ljava/lang/Object;
        21: areturn
        22: aload_0
        23: iload_1
        24: iload_2
        25: invokeinterface #36,  3           // InterfaceMethod scala$collection$immutable$IndexedSeqOps$$super$slice:(II)Ljava/lang/Object;
        30: areturn
      StackMapTable: number_of_entries = 1
        frame_type = 22 /* same */
      LineNumberTable:
        line 126: 0
        line 127: 22
      LocalVariableTable:
        Start  Length  Slot  Name   Signature
            0      31     0  this   Lscala/collection/immutable/IndexedSeqOps;
            0      31     1  from   I
            0      31     2 until   I
    Signature: #26                          // (II)TC;
    MethodParameters:
      Name                           Flags
      from                           final
      until                          final

  public static void $init$(scala.collection.immutable.IndexedSeqOps);
    descriptor: (Lscala/collection/immutable/IndexedSeqOps;)V
    flags: (0x0009) ACC_PUBLIC, ACC_STATIC
    Code:
      stack=0, locals=1, args_size=1
         0: return
      LineNumberTable:
        line 121: 0
      LocalVariableTable:
        Start  Length  Slot  Name   Signature
            0       1     0 $this   Lscala/collection/immutable/IndexedSeqOps;
    MethodParameters:
      Name                           Flags
      $this                          final synthetic
}
Signature: #3                           // <A:Ljava/lang/Object;CC:Ljava/lang/Object;C:Ljava/lang/Object;>Ljava/lang/Object;Lscala/collection/immutable/SeqOps<TA;TCC;TC;>;Lscala/collection/IndexedSeqOps<TA;TCC;TC;>;
SourceFile: "Seq.scala"
RuntimeVisibleAnnotations:
  0: #11(#12=s#13)
    scala.reflect.ScalaSignature(
      bytes="\u0006\u0005\u00013q\u0001B\u0003\u0011\u0002\u0007\u0005A\u0002C\u0003.\u0001\u0011\u0005a\u0006C\u00033\u0001\u0011\u00053\u0007C\u0006<\u0001A\u0005\u0019\u0011!A\u0005\nqz$!D%oI\u0016DX\rZ*fc>\u00038O\u0003\u0002\u0007\u000f\u0005I\u0011.\\7vi\u0006\u0014G.\u001a\u0006\u0003\u0011%\t!bY8mY\u0016\u001cG/[8o\u0015\u0005Q\u0011!B:dC2\f7\u0001A\u000b\u0005\u001ba\u0011\u0003f\u0005\u0003\u0001\u001dIQ\u0003CA\b\u0011\u001b\u0005I\u0011BA\t\n\u0005\u0019\te.\u001f*fMB)1\u0003\u0006\f\"O5\tQ!\u0003\u0002\u0016\u000b\t11+Z9PaN\u0004\"a\u0006\r\r\u0001\u00111\u0011\u0004\u0001CC\u0002i\u0011\u0011!Q\t\u00037y\u0001\"a\u0004\u000f\n\u0005uI!a\u0002(pi\"Lgn\u001a\t\u0003\u001f}I!\u0001I\u0005\u0003\u0007\u0005s\u0017\u0010\u0005\u0002\u0018E\u001111\u0005\u0001CC\u0002\u0011\u0012!aQ\"\u0016\u0005i)C!\u0002\u0014#\u0005\u0004Q\"\u0001B0%II\u0002\"a\u0006\u0015\u0005\r%\u0002AQ1\u0001\u001b\u0005\u0005\u0019\u0005#B\u0016--\u0005:S\"A\u0004\n\u0005\u00119\u0011A\u0002\u0013j]&$H\u0005F\u00010!\ty\u0001\'\u0003\u00022\u0013\t!QK\\5u\u0003\u0015\u0019H.[2f)\r9C\'\u000f\u0005\u0006k\t\u0001\rAN\u0001\u0005MJ|W\u000e\u0005\u0002\u0010o%\u0011\u0001(\u0003\u0002\u0004\u0013:$\b\"\u0002\u001e\u0003\u0001\u00041\u0014!B;oi&d\u0017aC:va\u0016\u0014He\u001d7jG\u0016$2aJ\u001f?\u0011\u0015)4\u00011\u00017\u0011\u0015Q4\u00011\u00017\u0013\t\u0011D\u0006"
    )
  ScalaInlineInfo: length = 0x18 (unknown attribute)
   01 00 00 04 00 26 00 27 01 00 0E 00 0F 01 00 15
   00 0F 00 00 12 00 13 01
  ScalaSig: length = 0x3 (unknown attribute)
   05 02 00
