Classfile /Users/mw/Projects/slang-braindump/.jar/jar11/assemble/slang-braindump/assemble/content/scala/collection/immutable/IntMap$$anon$1.class
  Last modified May 29, 2022; size 1601 bytes
  SHA-256 checksum ed82af4b03ae7612369a4baee5511590acdecb246a2b8d52d85b4445d4df4274
  Compiled from "IntMap.scala"
public final class scala.collection.immutable.IntMap$$anon$1 extends scala.collection.mutable.ImmutableBuilder<scala.Tuple2<java.lang.Object, V>, scala.collection.immutable.IntMap<V>>
  minor version: 0
  major version: 52
  flags: (0x0031) ACC_PUBLIC, ACC_FINAL, ACC_SUPER
  this_class: #2                          // scala/collection/immutable/IntMap$$anon$1
  super_class: #5                         // scala/collection/mutable/ImmutableBuilder
  interfaces: 0, fields: 0, methods: 3, attributes: 6
Constant pool:
   #1 = Utf8               scala/collection/immutable/IntMap$$anon$1
   #2 = Class              #1             // scala/collection/immutable/IntMap$$anon$1
   #3 = Utf8               Lscala/collection/mutable/ImmutableBuilder<Lscala/Tuple2<Ljava/lang/Object;TV;>;Lscala/collection/immutable/IntMap<TV;>;>;
   #4 = Utf8               scala/collection/mutable/ImmutableBuilder
   #5 = Class              #4             // scala/collection/mutable/ImmutableBuilder
   #6 = Utf8               IntMap.scala
   #7 = Utf8               scala/collection/immutable/IntMap$
   #8 = Class              #7             // scala/collection/immutable/IntMap$
   #9 = Utf8               newBuilder
  #10 = Utf8               ()Lscala/collection/mutable/Builder;
  #11 = NameAndType        #9:#10         // newBuilder:()Lscala/collection/mutable/Builder;
  #12 = Utf8               scala/collection/immutable/IntMap$Nil$
  #13 = Class              #12            // scala/collection/immutable/IntMap$Nil$
  #14 = Utf8               scala/collection/immutable/IntMap
  #15 = Class              #14            // scala/collection/immutable/IntMap
  #16 = Utf8               Nil$
  #17 = Utf8               addOne
  #18 = Utf8               (Lscala/Tuple2;)Lscala/collection/immutable/IntMap$$anon$1;
  #19 = Utf8               (Lscala/Tuple2<Ljava/lang/Object;TV;>;)Lscala/collection/immutable/IntMap$$anon$1;
  #20 = Utf8               elem
  #21 = Utf8               elems
  #22 = Utf8               ()Lscala/collection/IterableOnce;
  #23 = NameAndType        #21:#22        // elems:()Lscala/collection/IterableOnce;
  #24 = Methodref          #2.#23         // scala/collection/immutable/IntMap$$anon$1.elems:()Lscala/collection/IterableOnce;
  #25 = Utf8               $plus
  #26 = Utf8               (Lscala/Tuple2;)Lscala/collection/immutable/IntMap;
  #27 = NameAndType        #25:#26        // $plus:(Lscala/Tuple2;)Lscala/collection/immutable/IntMap;
  #28 = Methodref          #15.#27        // scala/collection/immutable/IntMap.$plus:(Lscala/Tuple2;)Lscala/collection/immutable/IntMap;
  #29 = Utf8               elems_$eq
  #30 = Utf8               (Lscala/collection/IterableOnce;)V
  #31 = NameAndType        #29:#30        // elems_$eq:(Lscala/collection/IterableOnce;)V
  #32 = Methodref          #2.#31         // scala/collection/immutable/IntMap$$anon$1.elems_$eq:(Lscala/collection/IterableOnce;)V
  #33 = Utf8               this
  #34 = Utf8               Lscala/collection/immutable/IntMap$$anon$1;
  #35 = Utf8               Lscala/Tuple2;
  #36 = Utf8               (Ljava/lang/Object;)Lscala/collection/mutable/Growable;
  #37 = Utf8               scala/Tuple2
  #38 = Class              #37            // scala/Tuple2
  #39 = NameAndType        #17:#18        // addOne:(Lscala/Tuple2;)Lscala/collection/immutable/IntMap$$anon$1;
  #40 = Methodref          #2.#39         // scala/collection/immutable/IntMap$$anon$1.addOne:(Lscala/Tuple2;)Lscala/collection/immutable/IntMap$$anon$1;
  #41 = Utf8               Ljava/lang/Object;
  #42 = Utf8               <init>
  #43 = Utf8               ()V
  #44 = Utf8               MODULE$
  #45 = Utf8               Lscala/collection/immutable/IntMap$;
  #46 = NameAndType        #44:#45        // MODULE$:Lscala/collection/immutable/IntMap$;
  #47 = Fieldref           #8.#46         // scala/collection/immutable/IntMap$.MODULE$:Lscala/collection/immutable/IntMap$;
  #48 = Utf8               Lscala/collection/immutable/IntMap$Nil$;
  #49 = NameAndType        #44:#48        // MODULE$:Lscala/collection/immutable/IntMap$Nil$;
  #50 = Fieldref           #13.#49        // scala/collection/immutable/IntMap$Nil$.MODULE$:Lscala/collection/immutable/IntMap$Nil$;
  #51 = NameAndType        #42:#30        // "<init>":(Lscala/collection/IterableOnce;)V
  #52 = Methodref          #5.#51         // scala/collection/mutable/ImmutableBuilder."<init>":(Lscala/collection/IterableOnce;)V
  #53 = Utf8               Code
  #54 = Utf8               LineNumberTable
  #55 = Utf8               LocalVariableTable
  #56 = Utf8               Signature
  #57 = Utf8               MethodParameters
  #58 = Utf8               InnerClasses
  #59 = Utf8               EnclosingMethod
  #60 = Utf8               SourceFile
  #61 = Utf8               ScalaInlineInfo
  #62 = Utf8               Scala
{
  public scala.collection.immutable.IntMap$$anon$1 addOne(scala.Tuple2<java.lang.Object, V>);
    descriptor: (Lscala/Tuple2;)Lscala/collection/immutable/IntMap$$anon$1;
    flags: (0x0001) ACC_PUBLIC
    Code:
      stack=3, locals=2, args_size=2
         0: aload_0
         1: aload_0
         2: invokevirtual #24                 // Method elems:()Lscala/collection/IterableOnce;
         5: checkcast     #15                 // class scala/collection/immutable/IntMap
         8: aload_1
         9: invokevirtual #28                 // Method scala/collection/immutable/IntMap.$plus:(Lscala/Tuple2;)Lscala/collection/immutable/IntMap;
        12: invokevirtual #32                 // Method elems_$eq:(Lscala/collection/IterableOnce;)V
        15: aload_0
        16: areturn
      LineNumberTable:
        line 85: 0
      LocalVariableTable:
        Start  Length  Slot  Name   Signature
            0      17     0  this   Lscala/collection/immutable/IntMap$$anon$1;
            0      17     1  elem   Lscala/Tuple2;
    Signature: #19                          // (Lscala/Tuple2<Ljava/lang/Object;TV;>;)Lscala/collection/immutable/IntMap$$anon$1;
    MethodParameters:
      Name                           Flags
      elem                           final

  public scala.collection.mutable.Growable addOne(java.lang.Object);
    descriptor: (Ljava/lang/Object;)Lscala/collection/mutable/Growable;
    flags: (0x1041) ACC_PUBLIC, ACC_BRIDGE, ACC_SYNTHETIC
    Code:
      stack=2, locals=2, args_size=2
         0: aload_0
         1: aload_1
         2: checkcast     #38                 // class scala/Tuple2
         5: invokevirtual #40                 // Method addOne:(Lscala/Tuple2;)Lscala/collection/immutable/IntMap$$anon$1;
         8: areturn
      LineNumberTable:
        line 84: 0
      LocalVariableTable:
        Start  Length  Slot  Name   Signature
            0       9     0  this   Lscala/collection/immutable/IntMap$$anon$1;
            0       9     1  elem   Ljava/lang/Object;
    MethodParameters:
      Name                           Flags
      elem                           final

  public scala.collection.immutable.IntMap$$anon$1();
    descriptor: ()V
    flags: (0x0001) ACC_PUBLIC
    Code:
      stack=2, locals=1, args_size=1
         0: aload_0
         1: getstatic     #47                 // Field scala/collection/immutable/IntMap$.MODULE$:Lscala/collection/immutable/IntMap$;
         4: pop
         5: getstatic     #50                 // Field scala/collection/immutable/IntMap$Nil$.MODULE$:Lscala/collection/immutable/IntMap$Nil$;
         8: invokespecial #52                 // Method scala/collection/mutable/ImmutableBuilder."<init>":(Lscala/collection/IterableOnce;)V
        11: return
      LineNumberTable:
        line 84: 0
        line 48: 5
        line 84: 8
      LocalVariableTable:
        Start  Length  Slot  Name   Signature
            0      12     0  this   Lscala/collection/immutable/IntMap$$anon$1;
}
InnerClasses:
  public final #2;                        // class scala/collection/immutable/IntMap$$anon$1
  public static #16= #13 of #15;          // Nil$=class scala/collection/immutable/IntMap$Nil$ of class scala/collection/immutable/IntMap
EnclosingMethod: #8.#11                 // scala.collection.immutable.IntMap$.newBuilder
Signature: #3                           // Lscala/collection/mutable/ImmutableBuilder<Lscala/Tuple2<Ljava/lang/Object;TV;>;Lscala/collection/immutable/IntMap<TV;>;>;
SourceFile: "IntMap.scala"
  ScalaInlineInfo: length = 0x13 (unknown attribute)
   01 01 00 03 00 2A 00 2B 01 00 11 00 24 01 00 11
   00 12 01
  Scala: length = 0x0 (unknown attribute)

