Classfile /Users/mw/Projects/slang-braindump/.jar/jar11/assemble/slang-braindump/assemble/content/scala/collection/immutable/IntMapEntryIterator.class
  Last modified May 29, 2022; size 2010 bytes
  SHA-256 checksum eac237ea14a45d2dadce98a20d42d0a62445d53594ae2f0ca2be4eb597bd609c
  Compiled from "IntMap.scala"
public class scala.collection.immutable.IntMapEntryIterator<V extends java.lang.Object> extends scala.collection.immutable.IntMapIterator<V, scala.Tuple2<java.lang.Object, V>>
  minor version: 0
  major version: 52
  flags: (0x0021) ACC_PUBLIC, ACC_SUPER
  this_class: #2                          // scala/collection/immutable/IntMapEntryIterator
  super_class: #5                         // scala/collection/immutable/IntMapIterator
  interfaces: 0, fields: 0, methods: 3, attributes: 6
Constant pool:
   #1 = Utf8               scala/collection/immutable/IntMapEntryIterator
   #2 = Class              #1             // scala/collection/immutable/IntMapEntryIterator
   #3 = Utf8               <V:Ljava/lang/Object;>Lscala/collection/immutable/IntMapIterator<TV;Lscala/Tuple2<Ljava/lang/Object;TV;>;>;
   #4 = Utf8               scala/collection/immutable/IntMapIterator
   #5 = Class              #4             // scala/collection/immutable/IntMapIterator
   #6 = Utf8               IntMap.scala
   #7 = Utf8               Lscala/reflect/ScalaSignature;
   #8 = Utf8               bytes
   #9 = Utf8               \u0006\u0005}2Q\u0001B\u0003\u0001\u000b-A\u0001\u0002\f\u0001\u0003\u0002\u0003\u0006I!\f\u0005\u0006a\u0001!\t!\r\u0005\u0006i\u0001!\t!\u000e\u0002\u0014\u0013:$X*\u00199F]R\u0014\u00180\u0013;fe\u0006$xN\u001d\u0006\u0003\r\u001d\t\u0011\"[7nkR\f\'\r\\3\u000b\u0005!I\u0011AC2pY2,7\r^5p]*\t!\"A\u0003tG\u0006d\u0017-\u0006\u0002\r\'M\u0011\u0001!\u0004\t\u0005\u001d=\tb$D\u0001\u0006\u0013\t\u0001RA\u0001\bJ]Rl\u0015\r]%uKJ\fGo\u001c:\u0011\u0005I\u0019B\u0002\u0001\u0003\u0006)\u0001\u0011\rA\u0006\u0002\u0002-\u000e\u0001\u0011CA\f\u001c!\tA\u0012$D\u0001\n\u0013\tQ\u0012BA\u0004O_RD\u0017N\\4\u0011\u0005aa\u0012BA\u000f\n\u0005\r\te.\u001f\t\u00051}\t\u0013#\u0003\u0002!\u0013\t1A+\u001e9mKJ\u0002\"AI\u0013\u000f\u00059\u0019\u0013B\u0001\u0013\u0006\u0003-Ie\u000e^\'baV#\u0018\u000e\\:\n\u0005\u0019:#aA%oi&\u0011a\u0005\u000b\u0006\u0003S)\nQBQ5u\u001fB,\'/\u0019;j_:\u001c(BA\u0016\b\u0003\u001d9WM\\3sS\u000e\f!!\u001b;\u0011\u00079q\u0013#\u0003\u00020\u000b\t1\u0011J\u001c;NCB\fa\u0001P5oSRtDC\u0001\u001a4!\rq\u0001!\u0005\u0005\u0006Y\t\u0001\r!L\u0001\bm\u0006dW/Z(g)\tqb\u0007C\u00038\u0007\u0001\u0007\u0001(A\u0002uSB\u00042!\u000f\u001f\u0012\u001d\tq!(\u0003\u0002<\u000b\u00051\u0011J\u001c;NCBL!!\u0010 \u0003\u0007QK\u0007O\u0003\u0002<\u000b\u0001
  #10 = Utf8               scala/collection/immutable/IntMap$Tip
  #11 = Class              #10            // scala/collection/immutable/IntMap$Tip
  #12 = Utf8               scala/collection/immutable/IntMap
  #13 = Class              #12            // scala/collection/immutable/IntMap
  #14 = Utf8               Tip
  #15 = Utf8               valueOf
  #16 = Utf8               (Lscala/collection/immutable/IntMap$Tip;)Lscala/Tuple2;
  #17 = Utf8               (Lscala/collection/immutable/IntMap$Tip<TV;>;)Lscala/Tuple2<Ljava/lang/Object;TV;>;
  #18 = Utf8               tip
  #19 = Utf8               scala/Tuple2
  #20 = Class              #19            // scala/Tuple2
  #21 = Utf8               key
  #22 = Utf8               ()I
  #23 = NameAndType        #21:#22        // key:()I
  #24 = Methodref          #11.#23        // scala/collection/immutable/IntMap$Tip.key:()I
  #25 = Utf8               java/lang/Integer
  #26 = Class              #25            // java/lang/Integer
  #27 = Utf8               (I)Ljava/lang/Integer;
  #28 = NameAndType        #15:#27        // valueOf:(I)Ljava/lang/Integer;
  #29 = Methodref          #26.#28        // java/lang/Integer.valueOf:(I)Ljava/lang/Integer;
  #30 = Utf8               value
  #31 = Utf8               ()Ljava/lang/Object;
  #32 = NameAndType        #30:#31        // value:()Ljava/lang/Object;
  #33 = Methodref          #11.#32        // scala/collection/immutable/IntMap$Tip.value:()Ljava/lang/Object;
  #34 = Utf8               <init>
  #35 = Utf8               (Ljava/lang/Object;Ljava/lang/Object;)V
  #36 = NameAndType        #34:#35        // "<init>":(Ljava/lang/Object;Ljava/lang/Object;)V
  #37 = Methodref          #20.#36        // scala/Tuple2."<init>":(Ljava/lang/Object;Ljava/lang/Object;)V
  #38 = Utf8               this
  #39 = Utf8               Lscala/collection/immutable/IntMapEntryIterator;
  #40 = Utf8               Lscala/collection/immutable/IntMap$Tip;
  #41 = Utf8               (Lscala/collection/immutable/IntMap$Tip;)Ljava/lang/Object;
  #42 = NameAndType        #15:#16        // valueOf:(Lscala/collection/immutable/IntMap$Tip;)Lscala/Tuple2;
  #43 = Methodref          #2.#42         // scala/collection/immutable/IntMapEntryIterator.valueOf:(Lscala/collection/immutable/IntMap$Tip;)Lscala/Tuple2;
  #44 = Utf8               (Lscala/collection/immutable/IntMap;)V
  #45 = Utf8               (Lscala/collection/immutable/IntMap<TV;>;)V
  #46 = Utf8               it
  #47 = NameAndType        #34:#44        // "<init>":(Lscala/collection/immutable/IntMap;)V
  #48 = Methodref          #5.#47         // scala/collection/immutable/IntMapIterator."<init>":(Lscala/collection/immutable/IntMap;)V
  #49 = Utf8               Lscala/collection/immutable/IntMap;
  #50 = Utf8               Code
  #51 = Utf8               LineNumberTable
  #52 = Utf8               LocalVariableTable
  #53 = Utf8               Signature
  #54 = Utf8               MethodParameters
  #55 = Utf8               InnerClasses
  #56 = Utf8               SourceFile
  #57 = Utf8               RuntimeVisibleAnnotations
  #58 = Utf8               ScalaInlineInfo
  #59 = Utf8               ScalaSig
{
  public scala.Tuple2<java.lang.Object, V> valueOf(scala.collection.immutable.IntMap$Tip<V>);
    descriptor: (Lscala/collection/immutable/IntMap$Tip;)Lscala/Tuple2;
    flags: (0x0001) ACC_PUBLIC
    Code:
      stack=4, locals=2, args_size=2
         0: new           #20                 // class scala/Tuple2
         3: dup
         4: aload_1
         5: invokevirtual #24                 // Method scala/collection/immutable/IntMap$Tip.key:()I
         8: invokestatic  #29                 // Method java/lang/Integer.valueOf:(I)Ljava/lang/Integer;
        11: aload_1
        12: invokevirtual #33                 // Method scala/collection/immutable/IntMap$Tip.value:()Ljava/lang/Object;
        15: invokespecial #37                 // Method scala/Tuple2."<init>":(Ljava/lang/Object;Ljava/lang/Object;)V
        18: areturn
      LineNumberTable:
        line 153: 0
      LocalVariableTable:
        Start  Length  Slot  Name   Signature
            0      19     0  this   Lscala/collection/immutable/IntMapEntryIterator;
            0      19     1   tip   Lscala/collection/immutable/IntMap$Tip;
    Signature: #17                          // (Lscala/collection/immutable/IntMap$Tip<TV;>;)Lscala/Tuple2<Ljava/lang/Object;TV;>;
    MethodParameters:
      Name                           Flags
      tip                            final

  public java.lang.Object valueOf(scala.collection.immutable.IntMap$Tip);
    descriptor: (Lscala/collection/immutable/IntMap$Tip;)Ljava/lang/Object;
    flags: (0x1041) ACC_PUBLIC, ACC_BRIDGE, ACC_SYNTHETIC
    Code:
      stack=2, locals=2, args_size=2
         0: aload_0
         1: aload_1
         2: invokevirtual #43                 // Method valueOf:(Lscala/collection/immutable/IntMap$Tip;)Lscala/Tuple2;
         5: areturn
      LineNumberTable:
        line 152: 0
      LocalVariableTable:
        Start  Length  Slot  Name   Signature
            0       6     0  this   Lscala/collection/immutable/IntMapEntryIterator;
            0       6     1   tip   Lscala/collection/immutable/IntMap$Tip;
    MethodParameters:
      Name                           Flags
      tip                            final

  public scala.collection.immutable.IntMapEntryIterator(scala.collection.immutable.IntMap<V>);
    descriptor: (Lscala/collection/immutable/IntMap;)V
    flags: (0x0001) ACC_PUBLIC
    Code:
      stack=2, locals=2, args_size=2
         0: aload_0
         1: aload_1
         2: invokespecial #48                 // Method scala/collection/immutable/IntMapIterator."<init>":(Lscala/collection/immutable/IntMap;)V
         5: return
      LineNumberTable:
        line 152: 0
      LocalVariableTable:
        Start  Length  Slot  Name   Signature
            0       6     0  this   Lscala/collection/immutable/IntMapEntryIterator;
            0       6     1    it   Lscala/collection/immutable/IntMap;
    Signature: #45                          // (Lscala/collection/immutable/IntMap<TV;>;)V
    MethodParameters:
      Name                           Flags
      it                             final
}
InnerClasses:
  public static #14= #11 of #13;          // Tip=class scala/collection/immutable/IntMap$Tip of class scala/collection/immutable/IntMap
Signature: #3                           // <V:Ljava/lang/Object;>Lscala/collection/immutable/IntMapIterator<TV;Lscala/Tuple2<Ljava/lang/Object;TV;>;>;
SourceFile: "IntMap.scala"
RuntimeVisibleAnnotations:
  0: #7(#8=s#9)
    scala.reflect.ScalaSignature(
      bytes="\u0006\u0005}2Q\u0001B\u0003\u0001\u000b-A\u0001\u0002\f\u0001\u0003\u0002\u0003\u0006I!\f\u0005\u0006a\u0001!\t!\r\u0005\u0006i\u0001!\t!\u000e\u0002\u0014\u0013:$X*\u00199F]R\u0014\u00180\u0013;fe\u0006$xN\u001d\u0006\u0003\r\u001d\t\u0011\"[7nkR\f\'\r\\3\u000b\u0005!I\u0011AC2pY2,7\r^5p]*\t!\"A\u0003tG\u0006d\u0017-\u0006\u0002\r\'M\u0011\u0001!\u0004\t\u0005\u001d=\tb$D\u0001\u0006\u0013\t\u0001RA\u0001\bJ]Rl\u0015\r]%uKJ\fGo\u001c:\u0011\u0005I\u0019B\u0002\u0001\u0003\u0006)\u0001\u0011\rA\u0006\u0002\u0002-\u000e\u0001\u0011CA\f\u001c!\tA\u0012$D\u0001\n\u0013\tQ\u0012BA\u0004O_RD\u0017N\\4\u0011\u0005aa\u0012BA\u000f\n\u0005\r\te.\u001f\t\u00051}\t\u0013#\u0003\u0002!\u0013\t1A+\u001e9mKJ\u0002\"AI\u0013\u000f\u00059\u0019\u0013B\u0001\u0013\u0006\u0003-Ie\u000e^\'baV#\u0018\u000e\\:\n\u0005\u0019:#aA%oi&\u0011a\u0005\u000b\u0006\u0003S)\nQBQ5u\u001fB,\'/\u0019;j_:\u001c(BA\u0016\b\u0003\u001d9WM\\3sS\u000e\f!!\u001b;\u0011\u00079q\u0013#\u0003\u00020\u000b\t1\u0011J\u001c;NCB\fa\u0001P5oSRtDC\u0001\u001a4!\rq\u0001!\u0005\u0005\u0006Y\t\u0001\r!L\u0001\bm\u0006dW/Z(g)\tqb\u0007C\u00038\u0007\u0001\u0007\u0001(A\u0002uSB\u00042!\u000f\u001f\u0012\u001d\tq!(\u0003\u0002<\u000b\u00051\u0011J\u001c;NCBL!!\u0010 \u0003\u0007QK\u0007O\u0003\u0002<\u000b\u0001"
    )
  ScalaInlineInfo: length = 0x13 (unknown attribute)
   01 00 00 03 00 22 00 2C 00 00 0F 00 29 00 00 0F
   00 10 00
  ScalaSig: length = 0x3 (unknown attribute)
   05 02 00
