Classfile /Users/mw/Projects/slang-braindump/.jar/jar11/assemble/slang-braindump/assemble/content/scala/collection/immutable/IntMapValueIterator.class
  Last modified May 29, 2022; size 1521 bytes
  SHA-256 checksum 14bc7b7ea94f6ca4f6390a4ad61b9514f067acea23078b48645bbe92e25acfe3
  Compiled from "IntMap.scala"
public class scala.collection.immutable.IntMapValueIterator<V extends java.lang.Object> extends scala.collection.immutable.IntMapIterator<V, V>
  minor version: 0
  major version: 52
  flags: (0x0021) ACC_PUBLIC, ACC_SUPER
  this_class: #2                          // scala/collection/immutable/IntMapValueIterator
  super_class: #5                         // scala/collection/immutable/IntMapIterator
  interfaces: 0, fields: 0, methods: 2, attributes: 6
Constant pool:
   #1 = Utf8               scala/collection/immutable/IntMapValueIterator
   #2 = Class              #1             // scala/collection/immutable/IntMapValueIterator
   #3 = Utf8               <V:Ljava/lang/Object;>Lscala/collection/immutable/IntMapIterator<TV;TV;>;
   #4 = Utf8               scala/collection/immutable/IntMapIterator
   #5 = Class              #4             // scala/collection/immutable/IntMapIterator
   #6 = Utf8               IntMap.scala
   #7 = Utf8               Lscala/reflect/ScalaSignature;
   #8 = Utf8               bytes
   #9 = Utf8               \u0006\u0005E2Q\u0001B\u0003\u0001\u000b-A\u0001B\b\u0001\u0003\u0002\u0003\u0006Ia\b\u0005\u0006E\u0001!\ta\t\u0005\u0006M\u0001!\ta\n\u0002\u0014\u0013:$X*\u00199WC2,X-\u0013;fe\u0006$xN\u001d\u0006\u0003\r\u001d\t\u0011\"[7nkR\f\'\r\\3\u000b\u0005!I\u0011AC2pY2,7\r^5p]*\t!\"A\u0003tG\u0006d\u0017-\u0006\u0002\r\'M\u0011\u0001!\u0004\t\u0005\u001d=\t\u0012#D\u0001\u0006\u0013\t\u0001RA\u0001\bJ]Rl\u0015\r]%uKJ\fGo\u001c:\u0011\u0005I\u0019B\u0002\u0001\u0003\u0006)\u0001\u0011\rA\u0006\u0002\u0002-\u000e\u0001\u0011CA\f\u001c!\tA\u0012$D\u0001\n\u0013\tQ\u0012BA\u0004O_RD\u0017N\\4\u0011\u0005aa\u0012BA\u000f\n\u0005\r\te._\u0001\u0003SR\u00042A\u0004\u0011\u0012\u0013\t\tSA\u0001\u0004J]Rl\u0015\r]\u0001\u0007y%t\u0017\u000e\u001e \u0015\u0005\u0011*\u0003c\u0001\b\u0001#!)aD\u0001a\u0001?\u00059a/\u00197vK>3GCA\t)\u0011\u0015I3\u00011\u0001+\u0003\r!\u0018\u000e\u001d\t\u0004W9\nbB\u0001\b-\u0013\tiS!\u0001\u0004J]Rl\u0015\r]\u0005\u0003_A\u00121\u0001V5q\u0015\tiS\u0001
  #10 = Utf8               scala/collection/immutable/IntMap$Tip
  #11 = Class              #10            // scala/collection/immutable/IntMap$Tip
  #12 = Utf8               scala/collection/immutable/IntMap
  #13 = Class              #12            // scala/collection/immutable/IntMap
  #14 = Utf8               Tip
  #15 = Utf8               valueOf
  #16 = Utf8               (Lscala/collection/immutable/IntMap$Tip;)Ljava/lang/Object;
  #17 = Utf8               (Lscala/collection/immutable/IntMap$Tip<TV;>;)TV;
  #18 = Utf8               tip
  #19 = Utf8               value
  #20 = Utf8               ()Ljava/lang/Object;
  #21 = NameAndType        #19:#20        // value:()Ljava/lang/Object;
  #22 = Methodref          #11.#21        // scala/collection/immutable/IntMap$Tip.value:()Ljava/lang/Object;
  #23 = Utf8               this
  #24 = Utf8               Lscala/collection/immutable/IntMapValueIterator;
  #25 = Utf8               Lscala/collection/immutable/IntMap$Tip;
  #26 = Utf8               <init>
  #27 = Utf8               (Lscala/collection/immutable/IntMap;)V
  #28 = Utf8               (Lscala/collection/immutable/IntMap<TV;>;)V
  #29 = Utf8               it
  #30 = NameAndType        #26:#27        // "<init>":(Lscala/collection/immutable/IntMap;)V
  #31 = Methodref          #5.#30         // scala/collection/immutable/IntMapIterator."<init>":(Lscala/collection/immutable/IntMap;)V
  #32 = Utf8               Lscala/collection/immutable/IntMap;
  #33 = Utf8               Code
  #34 = Utf8               LineNumberTable
  #35 = Utf8               LocalVariableTable
  #36 = Utf8               Signature
  #37 = Utf8               MethodParameters
  #38 = Utf8               InnerClasses
  #39 = Utf8               SourceFile
  #40 = Utf8               RuntimeVisibleAnnotations
  #41 = Utf8               ScalaInlineInfo
  #42 = Utf8               ScalaSig
{
  public V valueOf(scala.collection.immutable.IntMap$Tip<V>);
    descriptor: (Lscala/collection/immutable/IntMap$Tip;)Ljava/lang/Object;
    flags: (0x0001) ACC_PUBLIC
    Code:
      stack=1, locals=2, args_size=2
         0: aload_1
         1: invokevirtual #22                 // Method scala/collection/immutable/IntMap$Tip.value:()Ljava/lang/Object;
         4: areturn
      LineNumberTable:
        line 157: 0
      LocalVariableTable:
        Start  Length  Slot  Name   Signature
            0       5     0  this   Lscala/collection/immutable/IntMapValueIterator;
            0       5     1   tip   Lscala/collection/immutable/IntMap$Tip;
    Signature: #17                          // (Lscala/collection/immutable/IntMap$Tip<TV;>;)TV;
    MethodParameters:
      Name                           Flags
      tip                            final

  public scala.collection.immutable.IntMapValueIterator(scala.collection.immutable.IntMap<V>);
    descriptor: (Lscala/collection/immutable/IntMap;)V
    flags: (0x0001) ACC_PUBLIC
    Code:
      stack=2, locals=2, args_size=2
         0: aload_0
         1: aload_1
         2: invokespecial #31                 // Method scala/collection/immutable/IntMapIterator."<init>":(Lscala/collection/immutable/IntMap;)V
         5: return
      LineNumberTable:
        line 156: 0
      LocalVariableTable:
        Start  Length  Slot  Name   Signature
            0       6     0  this   Lscala/collection/immutable/IntMapValueIterator;
            0       6     1    it   Lscala/collection/immutable/IntMap;
    Signature: #28                          // (Lscala/collection/immutable/IntMap<TV;>;)V
    MethodParameters:
      Name                           Flags
      it                             final
}
InnerClasses:
  public static #14= #11 of #13;          // Tip=class scala/collection/immutable/IntMap$Tip of class scala/collection/immutable/IntMap
Signature: #3                           // <V:Ljava/lang/Object;>Lscala/collection/immutable/IntMapIterator<TV;TV;>;
SourceFile: "IntMap.scala"
RuntimeVisibleAnnotations:
  0: #7(#8=s#9)
    scala.reflect.ScalaSignature(
      bytes="\u0006\u0005E2Q\u0001B\u0003\u0001\u000b-A\u0001B\b\u0001\u0003\u0002\u0003\u0006Ia\b\u0005\u0006E\u0001!\ta\t\u0005\u0006M\u0001!\ta\n\u0002\u0014\u0013:$X*\u00199WC2,X-\u0013;fe\u0006$xN\u001d\u0006\u0003\r\u001d\t\u0011\"[7nkR\f\'\r\\3\u000b\u0005!I\u0011AC2pY2,7\r^5p]*\t!\"A\u0003tG\u0006d\u0017-\u0006\u0002\r\'M\u0011\u0001!\u0004\t\u0005\u001d=\t\u0012#D\u0001\u0006\u0013\t\u0001RA\u0001\bJ]Rl\u0015\r]%uKJ\fGo\u001c:\u0011\u0005I\u0019B\u0002\u0001\u0003\u0006)\u0001\u0011\rA\u0006\u0002\u0002-\u000e\u0001\u0011CA\f\u001c!\tA\u0012$D\u0001\n\u0013\tQ\u0012BA\u0004O_RD\u0017N\\4\u0011\u0005aa\u0012BA\u000f\n\u0005\r\te._\u0001\u0003SR\u00042A\u0004\u0011\u0012\u0013\t\tSA\u0001\u0004J]Rl\u0015\r]\u0001\u0007y%t\u0017\u000e\u001e \u0015\u0005\u0011*\u0003c\u0001\b\u0001#!)aD\u0001a\u0001?\u00059a/\u00197vK>3GCA\t)\u0011\u0015I3\u00011\u0001+\u0003\r!\u0018\u000e\u001d\t\u0004W9\nbB\u0001\b-\u0013\tiS!\u0001\u0004J]Rl\u0015\r]\u0005\u0003_A\u00121\u0001V5q\u0015\tiS\u0001"
    )
  ScalaInlineInfo: length = 0xE (unknown attribute)
   01 00 00 02 00 1A 00 1B 00 00 0F 00 10 00
  ScalaSig: length = 0x3 (unknown attribute)
   05 02 00
