Classfile /Users/mw/Projects/slang-braindump/.jar/jar11/assemble/slang-braindump/assemble/content/scala/collection/immutable/LongVectorStepper.class
  Last modified May 29, 2022; size 3960 bytes
  SHA-256 checksum 63a31e23d0b060839612c89a479599e7696cfe8939fe97450bfa4db41387fb61
  Compiled from "Vector.scala"
public class scala.collection.immutable.LongVectorStepper extends scala.collection.immutable.VectorStepperBase<java.lang.Object, scala.collection.LongStepper, scala.collection.immutable.LongVectorStepper> implements scala.collection.LongStepper
  minor version: 0
  major version: 52
  flags: (0x0021) ACC_PUBLIC, ACC_SUPER
  this_class: #2                          // scala/collection/immutable/LongVectorStepper
  super_class: #5                         // scala/collection/immutable/VectorStepperBase
  interfaces: 1, fields: 1, methods: 13, attributes: 6
Constant pool:
    #1 = Utf8               scala/collection/immutable/LongVectorStepper
    #2 = Class              #1            // scala/collection/immutable/LongVectorStepper
    #3 = Utf8               Lscala/collection/immutable/VectorStepperBase<Ljava/lang/Object;Lscala/collection/LongStepper;Lscala/collection/immutable/LongVectorStepper;>;Lscala/collection/LongStepper;
    #4 = Utf8               scala/collection/immutable/VectorStepperBase
    #5 = Class              #4            // scala/collection/immutable/VectorStepperBase
    #6 = Utf8               scala/collection/LongStepper
    #7 = Class              #6            // scala/collection/LongStepper
    #8 = Utf8               Vector.scala
    #9 = Utf8               Lscala/reflect/ScalaSignature;
   #10 = Utf8               bytes
   #11 = Utf8               \u0006\u0005\u001d2A!\u0002\u0004\u0005\u001b!A1\u0004\u0001B\u0001B\u0003%A\u0004C\u0003 \u0001\u0011\u0005\u0001\u0005\u0003\u0004#\u0001\u0001&\tb\t\u0005\u0006K\u0001!\tA\n\u0002\u0012\u0019>twMV3di>\u00148\u000b^3qa\u0016\u0014(BA\u0004\t\u0003%IW.\\;uC\ndWM\u0003\u0002\n\u0015\u0005Q1m\u001c7mK\u000e$\u0018n\u001c8\u000b\u0003-\tQa]2bY\u0006\u001c\u0001aE\u0002\u0001\u001dY\u0001Ra\u0004\t\u0013-ii\u0011AB\u0005\u0003#\u0019\u0011\u0011CV3di>\u00148\u000b^3qa\u0016\u0014()Y:f!\t\u0019B#D\u0001\u000b\u0013\t)\"B\u0001\u0003M_:<\u0007CA\f\u0019\u001b\u0005A\u0011BA\r\t\u0005-auN\\4Ti\u0016\u0004\b/\u001a:\u0011\u0005=\u0001\u0011AA5u!\ryQDE\u0005\u0003=\u0019\u0011\u0011CT3x-\u0016\u001cGo\u001c:Ji\u0016\u0014\u0018\r^8s\u0003\u0019a\u0014N\\5u}Q\u0011!$\t\u0005\u00067\t\u0001\r\u0001H\u0001\u0006EVLG\u000e\u001a\u000b\u00035\u0011BQaG\u0002A\u0002q\t\u0001B\\3yiN#X\r\u001d\u000b\u0002%\u0001
   #12 = Utf8               java/util/PrimitiveIterator$OfLong
   #13 = Class              #12           // java/util/PrimitiveIterator$OfLong
   #14 = Utf8               java/util/PrimitiveIterator
   #15 = Class              #14           // java/util/PrimitiveIterator
   #16 = Utf8               OfLong
   #17 = Utf8               java/util/Spliterator$OfLong
   #18 = Class              #17           // java/util/Spliterator$OfLong
   #19 = Utf8               java/util/Spliterator
   #20 = Class              #19           // java/util/Spliterator
   #21 = Utf8               scala$collection$immutable$LongVectorStepper$$it
   #22 = Utf8               Lscala/collection/immutable/NewVectorIterator;
   #23 = Utf8               Lscala/collection/immutable/NewVectorIterator<Ljava/lang/Object;>;
   #24 = Utf8               spliterator
   #25 = Utf8               ()Ljava/util/Spliterator$OfLong;
   #26 = Utf8               <B:Ljava/lang/Object;>()Ljava/util/Spliterator$OfLong;
   #27 = Utf8               spliterator$
   #28 = Utf8               (Lscala/collection/LongStepper;)Ljava/util/Spliterator$OfLong;
   #29 = NameAndType        #27:#28       // spliterator$:(Lscala/collection/LongStepper;)Ljava/util/Spliterator$OfLong;
   #30 = InterfaceMethodref #7.#29        // scala/collection/LongStepper.spliterator$:(Lscala/collection/LongStepper;)Ljava/util/Spliterator$OfLong;
   #31 = Utf8               this
   #32 = Utf8               Lscala/collection/immutable/LongVectorStepper;
   #33 = Utf8               javaIterator
   #34 = Utf8               ()Ljava/util/PrimitiveIterator$OfLong;
   #35 = Utf8               <B:Ljava/lang/Object;>()Ljava/util/PrimitiveIterator$OfLong;
   #36 = Utf8               javaIterator$
   #37 = Utf8               (Lscala/collection/LongStepper;)Ljava/util/PrimitiveIterator$OfLong;
   #38 = NameAndType        #36:#37       // javaIterator$:(Lscala/collection/LongStepper;)Ljava/util/PrimitiveIterator$OfLong;
   #39 = InterfaceMethodref #7.#38        // scala/collection/LongStepper.javaIterator$:(Lscala/collection/LongStepper;)Ljava/util/PrimitiveIterator$OfLong;
   #40 = Utf8               spliterator$mcJ$sp
   #41 = Utf8               ()Ljava/util/Spliterator;
   #42 = Utf8               <B:Ljava/lang/Object;>()Ljava/util/Spliterator<*>;
   #43 = Utf8               spliterator$mcJ$sp$
   #44 = Utf8               (Lscala/collection/LongStepper;)Ljava/util/Spliterator;
   #45 = NameAndType        #43:#44       // spliterator$mcJ$sp$:(Lscala/collection/LongStepper;)Ljava/util/Spliterator;
   #46 = InterfaceMethodref #7.#45        // scala/collection/LongStepper.spliterator$mcJ$sp$:(Lscala/collection/LongStepper;)Ljava/util/Spliterator;
   #47 = Utf8               javaIterator$mcJ$sp
   #48 = Utf8               ()Ljava/util/Iterator;
   #49 = Utf8               <B:Ljava/lang/Object;>()Ljava/util/Iterator<*>;
   #50 = Utf8               javaIterator$mcJ$sp$
   #51 = Utf8               (Lscala/collection/LongStepper;)Ljava/util/Iterator;
   #52 = NameAndType        #50:#51       // javaIterator$mcJ$sp$:(Lscala/collection/LongStepper;)Ljava/util/Iterator;
   #53 = InterfaceMethodref #7.#52        // scala/collection/LongStepper.javaIterator$mcJ$sp$:(Lscala/collection/LongStepper;)Ljava/util/Iterator;
   #54 = Utf8               build
   #55 = Utf8               (Lscala/collection/immutable/NewVectorIterator;)Lscala/collection/immutable/LongVectorStepper;
   #56 = Utf8               (Lscala/collection/immutable/NewVectorIterator<Ljava/lang/Object;>;)Lscala/collection/immutable/LongVectorStepper;
   #57 = Utf8               it
   #58 = Utf8               <init>
   #59 = Utf8               (Lscala/collection/immutable/NewVectorIterator;)V
   #60 = NameAndType        #58:#59       // "<init>":(Lscala/collection/immutable/NewVectorIterator;)V
   #61 = Methodref          #2.#60        // scala/collection/immutable/LongVectorStepper."<init>":(Lscala/collection/immutable/NewVectorIterator;)V
   #62 = Utf8               nextStep
   #63 = Utf8               ()J
   #64 = Utf8               nextStep$mcJ$sp
   #65 = NameAndType        #64:#63       // nextStep$mcJ$sp:()J
   #66 = Methodref          #2.#65        // scala/collection/immutable/LongVectorStepper.nextStep$mcJ$sp:()J
   #67 = NameAndType        #21:#22       // scala$collection$immutable$LongVectorStepper$$it:Lscala/collection/immutable/NewVectorIterator;
   #68 = Fieldref           #2.#67        // scala/collection/immutable/LongVectorStepper.scala$collection$immutable$LongVectorStepper$$it:Lscala/collection/immutable/NewVectorIterator;
   #69 = Utf8               scala/collection/immutable/NewVectorIterator
   #70 = Class              #69           // scala/collection/immutable/NewVectorIterator
   #71 = Utf8               next
   #72 = Utf8               ()Ljava/lang/Object;
   #73 = NameAndType        #71:#72       // next:()Ljava/lang/Object;
   #74 = Methodref          #70.#73       // scala/collection/immutable/NewVectorIterator.next:()Ljava/lang/Object;
   #75 = Utf8               scala/runtime/BoxesRunTime
   #76 = Class              #75           // scala/runtime/BoxesRunTime
   #77 = Utf8               unboxToLong
   #78 = Utf8               (Ljava/lang/Object;)J
   #79 = NameAndType        #77:#78       // unboxToLong:(Ljava/lang/Object;)J
   #80 = Methodref          #76.#79       // scala/runtime/BoxesRunTime.unboxToLong:(Ljava/lang/Object;)J
   #81 = Utf8               trySplit
   #82 = Utf8               ()Lscala/collection/LongStepper;
   #83 = Utf8               ()Lscala/collection/Stepper;
   #84 = NameAndType        #81:#83       // trySplit:()Lscala/collection/Stepper;
   #85 = Methodref          #2.#84        // scala/collection/immutable/LongVectorStepper.trySplit:()Lscala/collection/Stepper;
   #86 = NameAndType        #33:#34       // javaIterator:()Ljava/util/PrimitiveIterator$OfLong;
   #87 = Methodref          #2.#86        // scala/collection/immutable/LongVectorStepper.javaIterator:()Ljava/util/PrimitiveIterator$OfLong;
   #88 = NameAndType        #24:#25       // spliterator:()Ljava/util/Spliterator$OfLong;
   #89 = Methodref          #2.#88        // scala/collection/immutable/LongVectorStepper.spliterator:()Ljava/util/Spliterator$OfLong;
   #90 = NameAndType        #62:#63       // nextStep:()J
   #91 = Methodref          #2.#90        // scala/collection/immutable/LongVectorStepper.nextStep:()J
   #92 = Utf8               boxToLong
   #93 = Utf8               (J)Ljava/lang/Long;
   #94 = NameAndType        #92:#93       // boxToLong:(J)Ljava/lang/Long;
   #95 = Methodref          #76.#94       // scala/runtime/BoxesRunTime.boxToLong:(J)Ljava/lang/Long;
   #96 = Utf8               (Lscala/collection/immutable/NewVectorIterator;)Lscala/collection/Stepper;
   #97 = NameAndType        #54:#55       // build:(Lscala/collection/immutable/NewVectorIterator;)Lscala/collection/immutable/LongVectorStepper;
   #98 = Methodref          #2.#97        // scala/collection/immutable/LongVectorStepper.build:(Lscala/collection/immutable/NewVectorIterator;)Lscala/collection/immutable/LongVectorStepper;
   #99 = Utf8               (Lscala/collection/immutable/NewVectorIterator<Ljava/lang/Object;>;)V
  #100 = Methodref          #5.#60        // scala/collection/immutable/VectorStepperBase."<init>":(Lscala/collection/immutable/NewVectorIterator;)V
  #101 = Utf8               Signature
  #102 = Utf8               Code
  #103 = Utf8               LineNumberTable
  #104 = Utf8               LocalVariableTable
  #105 = Utf8               MethodParameters
  #106 = Utf8               InnerClasses
  #107 = Utf8               SourceFile
  #108 = Utf8               RuntimeVisibleAnnotations
  #109 = Utf8               ScalaInlineInfo
  #110 = Utf8               ScalaSig
{
  public final scala.collection.immutable.NewVectorIterator<java.lang.Object> scala$collection$immutable$LongVectorStepper$$it;
    descriptor: Lscala/collection/immutable/NewVectorIterator;
    flags: (0x0011) ACC_PUBLIC, ACC_FINAL
    Signature: #23                          // Lscala/collection/immutable/NewVectorIterator<Ljava/lang/Object;>;

  public <B extends java.lang.Object> java.util.Spliterator$OfLong spliterator();
    descriptor: ()Ljava/util/Spliterator$OfLong;
    flags: (0x0001) ACC_PUBLIC
    Code:
      stack=1, locals=1, args_size=1
         0: aload_0
         1: invokestatic  #30                 // InterfaceMethod scala/collection/LongStepper.spliterator$:(Lscala/collection/LongStepper;)Ljava/util/Spliterator$OfLong;
         4: areturn
      LineNumberTable:
        line 2194: 0
      LocalVariableTable:
        Start  Length  Slot  Name   Signature
            0       5     0  this   Lscala/collection/immutable/LongVectorStepper;
    Signature: #26                          // <B:Ljava/lang/Object;>()Ljava/util/Spliterator$OfLong;

  public <B extends java.lang.Object> java.util.PrimitiveIterator$OfLong javaIterator();
    descriptor: ()Ljava/util/PrimitiveIterator$OfLong;
    flags: (0x0001) ACC_PUBLIC
    Code:
      stack=1, locals=1, args_size=1
         0: aload_0
         1: invokestatic  #39                 // InterfaceMethod scala/collection/LongStepper.javaIterator$:(Lscala/collection/LongStepper;)Ljava/util/PrimitiveIterator$OfLong;
         4: areturn
      LineNumberTable:
        line 2194: 0
      LocalVariableTable:
        Start  Length  Slot  Name   Signature
            0       5     0  this   Lscala/collection/immutable/LongVectorStepper;
    Signature: #35                          // <B:Ljava/lang/Object;>()Ljava/util/PrimitiveIterator$OfLong;

  public <B extends java.lang.Object> java.util.Spliterator<?> spliterator$mcJ$sp();
    descriptor: ()Ljava/util/Spliterator;
    flags: (0x0001) ACC_PUBLIC
    Code:
      stack=1, locals=1, args_size=1
         0: aload_0
         1: invokestatic  #46                 // InterfaceMethod scala/collection/LongStepper.spliterator$mcJ$sp$:(Lscala/collection/LongStepper;)Ljava/util/Spliterator;
         4: areturn
      LineNumberTable:
        line 2194: 0
      LocalVariableTable:
        Start  Length  Slot  Name   Signature
            0       5     0  this   Lscala/collection/immutable/LongVectorStepper;
    Signature: #42                          // <B:Ljava/lang/Object;>()Ljava/util/Spliterator<*>;

  public <B extends java.lang.Object> java.util.Iterator<?> javaIterator$mcJ$sp();
    descriptor: ()Ljava/util/Iterator;
    flags: (0x0001) ACC_PUBLIC
    Code:
      stack=1, locals=1, args_size=1
         0: aload_0
         1: invokestatic  #53                 // InterfaceMethod scala/collection/LongStepper.javaIterator$mcJ$sp$:(Lscala/collection/LongStepper;)Ljava/util/Iterator;
         4: areturn
      LineNumberTable:
        line 2194: 0
      LocalVariableTable:
        Start  Length  Slot  Name   Signature
            0       5     0  this   Lscala/collection/immutable/LongVectorStepper;
    Signature: #49                          // <B:Ljava/lang/Object;>()Ljava/util/Iterator<*>;

  public scala.collection.immutable.LongVectorStepper build(scala.collection.immutable.NewVectorIterator<java.lang.Object>);
    descriptor: (Lscala/collection/immutable/NewVectorIterator;)Lscala/collection/immutable/LongVectorStepper;
    flags: (0x0001) ACC_PUBLIC
    Code:
      stack=3, locals=2, args_size=2
         0: new           #2                  // class scala/collection/immutable/LongVectorStepper
         3: dup
         4: aload_1
         5: invokespecial #61                 // Method "<init>":(Lscala/collection/immutable/NewVectorIterator;)V
         8: areturn
      LineNumberTable:
        line 2196: 0
      LocalVariableTable:
        Start  Length  Slot  Name   Signature
            0       9     0  this   Lscala/collection/immutable/LongVectorStepper;
            0       9     1    it   Lscala/collection/immutable/NewVectorIterator;
    Signature: #56                          // (Lscala/collection/immutable/NewVectorIterator<Ljava/lang/Object;>;)Lscala/collection/immutable/LongVectorStepper;
    MethodParameters:
      Name                           Flags
      it                             final

  public long nextStep();
    descriptor: ()J
    flags: (0x0001) ACC_PUBLIC
    Code:
      stack=2, locals=1, args_size=1
         0: aload_0
         1: invokevirtual #66                 // Method nextStep$mcJ$sp:()J
         4: lreturn
      LineNumberTable:
        line 2197: 0
      LocalVariableTable:
        Start  Length  Slot  Name   Signature
            0       5     0  this   Lscala/collection/immutable/LongVectorStepper;

  public long nextStep$mcJ$sp();
    descriptor: ()J
    flags: (0x0001) ACC_PUBLIC
    Code:
      stack=2, locals=1, args_size=1
         0: aload_0
         1: getfield      #68                 // Field scala$collection$immutable$LongVectorStepper$$it:Lscala/collection/immutable/NewVectorIterator;
         4: invokevirtual #74                 // Method scala/collection/immutable/NewVectorIterator.next:()Ljava/lang/Object;
         7: invokestatic  #80                 // Method scala/runtime/BoxesRunTime.unboxToLong:(Ljava/lang/Object;)J
        10: lreturn
      LineNumberTable:
        line 2197: 0
      LocalVariableTable:
        Start  Length  Slot  Name   Signature
            0      11     0  this   Lscala/collection/immutable/LongVectorStepper;

  public scala.collection.LongStepper trySplit();
    descriptor: ()Lscala/collection/LongStepper;
    flags: (0x1041) ACC_PUBLIC, ACC_BRIDGE, ACC_SYNTHETIC
    Code:
      stack=1, locals=1, args_size=1
         0: aload_0
         1: invokevirtual #85                 // Method trySplit:()Lscala/collection/Stepper;
         4: checkcast     #7                  // class scala/collection/LongStepper
         7: areturn
      LineNumberTable:
        line 2194: 0
      LocalVariableTable:
        Start  Length  Slot  Name   Signature
            0       8     0  this   Lscala/collection/immutable/LongVectorStepper;

  public java.util.Iterator javaIterator();
    descriptor: ()Ljava/util/Iterator;
    flags: (0x1041) ACC_PUBLIC, ACC_BRIDGE, ACC_SYNTHETIC
    Code:
      stack=1, locals=1, args_size=1
         0: aload_0
         1: invokevirtual #87                 // Method javaIterator:()Ljava/util/PrimitiveIterator$OfLong;
         4: areturn
      LineNumberTable:
        line 2194: 0
      LocalVariableTable:
        Start  Length  Slot  Name   Signature
            0       5     0  this   Lscala/collection/immutable/LongVectorStepper;

  public java.util.Spliterator spliterator();
    descriptor: ()Ljava/util/Spliterator;
    flags: (0x1041) ACC_PUBLIC, ACC_BRIDGE, ACC_SYNTHETIC
    Code:
      stack=1, locals=1, args_size=1
         0: aload_0
         1: invokevirtual #89                 // Method spliterator:()Ljava/util/Spliterator$OfLong;
         4: areturn
      LineNumberTable:
        line 2194: 0
      LocalVariableTable:
        Start  Length  Slot  Name   Signature
            0       5     0  this   Lscala/collection/immutable/LongVectorStepper;

  public java.lang.Object nextStep();
    descriptor: ()Ljava/lang/Object;
    flags: (0x1041) ACC_PUBLIC, ACC_BRIDGE, ACC_SYNTHETIC
    Code:
      stack=2, locals=1, args_size=1
         0: aload_0
         1: invokevirtual #91                 // Method nextStep:()J
         4: invokestatic  #95                 // Method scala/runtime/BoxesRunTime.boxToLong:(J)Ljava/lang/Long;
         7: areturn
      LineNumberTable:
        line 2194: 0
      LocalVariableTable:
        Start  Length  Slot  Name   Signature
            0       8     0  this   Lscala/collection/immutable/LongVectorStepper;

  public scala.collection.Stepper build(scala.collection.immutable.NewVectorIterator);
    descriptor: (Lscala/collection/immutable/NewVectorIterator;)Lscala/collection/Stepper;
    flags: (0x1041) ACC_PUBLIC, ACC_BRIDGE, ACC_SYNTHETIC
    Code:
      stack=2, locals=2, args_size=2
         0: aload_0
         1: aload_1
         2: invokevirtual #98                 // Method build:(Lscala/collection/immutable/NewVectorIterator;)Lscala/collection/immutable/LongVectorStepper;
         5: areturn
      LineNumberTable:
        line 2194: 0
      LocalVariableTable:
        Start  Length  Slot  Name   Signature
            0       6     0  this   Lscala/collection/immutable/LongVectorStepper;
            0       6     1    it   Lscala/collection/immutable/NewVectorIterator;
    MethodParameters:
      Name                           Flags
      it                             final

  public scala.collection.immutable.LongVectorStepper(scala.collection.immutable.NewVectorIterator<java.lang.Object>);
    descriptor: (Lscala/collection/immutable/NewVectorIterator;)V
    flags: (0x0001) ACC_PUBLIC
    Code:
      stack=2, locals=2, args_size=2
         0: aload_0
         1: aload_1
         2: putfield      #68                 // Field scala$collection$immutable$LongVectorStepper$$it:Lscala/collection/immutable/NewVectorIterator;
         5: aload_0
         6: aload_1
         7: invokespecial #100                // Method scala/collection/immutable/VectorStepperBase."<init>":(Lscala/collection/immutable/NewVectorIterator;)V
        10: return
      LineNumberTable:
        line 2194: 0
        line 2195: 5
        line 2194: 10
      LocalVariableTable:
        Start  Length  Slot  Name   Signature
            0      11     0  this   Lscala/collection/immutable/LongVectorStepper;
            0      11     1    it   Lscala/collection/immutable/NewVectorIterator;
    Signature: #99                          // (Lscala/collection/immutable/NewVectorIterator<Ljava/lang/Object;>;)V
    MethodParameters:
      Name                           Flags
      it                             final
}
InnerClasses:
  public static #16= #13 of #15;          // OfLong=class java/util/PrimitiveIterator$OfLong of class java/util/PrimitiveIterator
  public static #16= #18 of #20;          // OfLong=class java/util/Spliterator$OfLong of class java/util/Spliterator
Signature: #3                           // Lscala/collection/immutable/VectorStepperBase<Ljava/lang/Object;Lscala/collection/LongStepper;Lscala/collection/immutable/LongVectorStepper;>;Lscala/collection/LongStepper;
SourceFile: "Vector.scala"
RuntimeVisibleAnnotations:
  0: #9(#10=s#11)
    scala.reflect.ScalaSignature(
      bytes="\u0006\u0005\u001d2A!\u0002\u0004\u0005\u001b!A1\u0004\u0001B\u0001B\u0003%A\u0004C\u0003 \u0001\u0011\u0005\u0001\u0005\u0003\u0004#\u0001\u0001&\tb\t\u0005\u0006K\u0001!\tA\n\u0002\u0012\u0019>twMV3di>\u00148\u000b^3qa\u0016\u0014(BA\u0004\t\u0003%IW.\\;uC\ndWM\u0003\u0002\n\u0015\u0005Q1m\u001c7mK\u000e$\u0018n\u001c8\u000b\u0003-\tQa]2bY\u0006\u001c\u0001aE\u0002\u0001\u001dY\u0001Ra\u0004\t\u0013-ii\u0011AB\u0005\u0003#\u0019\u0011\u0011CV3di>\u00148\u000b^3qa\u0016\u0014()Y:f!\t\u0019B#D\u0001\u000b\u0013\t)\"B\u0001\u0003M_:<\u0007CA\f\u0019\u001b\u0005A\u0011BA\r\t\u0005-auN\\4Ti\u0016\u0004\b/\u001a:\u0011\u0005=\u0001\u0011AA5u!\ryQDE\u0005\u0003=\u0019\u0011\u0011CT3x-\u0016\u001cGo\u001c:Ji\u0016\u0014\u0018\r^8s\u0003\u0019a\u0014N\\5u}Q\u0011!$\t\u0005\u00067\t\u0001\r\u0001H\u0001\u0006EVLG\u000e\u001a\u000b\u00035\u0011BQaG\u0002A\u0002q\t\u0001B\\3yiN#X\r\u001d\u000b\u0002%\u0001"
    )
  ScalaInlineInfo: length = 0x45 (unknown attribute)
   01 00 00 0D 00 3A 00 3B 00 00 36 00 60 00 00 36
   00 37 00 00 21 00 30 00 00 21 00 22 00 00 2F 00
   30 00 00 3E 00 3F 00 00 3E 00 48 00 00 40 00 3F
   00 00 18 00 19 00 00 18 00 29 00 00 28 00 29 00
   00 51 00 52 00
  ScalaSig: length = 0x3 (unknown attribute)
   05 02 00
