Classfile /Users/mw/Projects/slang-braindump/.jar/jar11/assemble/slang-braindump/assemble/content/scala/collection/immutable/Map$EmptyMap$.class
  Last modified May 29, 2022; size 4939 bytes
  SHA-256 checksum 9291ca6028c9116c1bff7c3ec4df86b22b6d4cd62a2f8e7f4e8134ef104af6b2
  Compiled from "Map.scala"
public class scala.collection.immutable.Map$EmptyMap$ extends scala.collection.immutable.AbstractMap<java.lang.Object, scala.runtime.Nothing$> implements java.io.Serializable
  minor version: 0
  major version: 52
  flags: (0x0021) ACC_PUBLIC, ACC_SUPER
  this_class: #2                          // scala/collection/immutable/Map$EmptyMap$
  super_class: #5                         // scala/collection/immutable/AbstractMap
  interfaces: 1, fields: 2, methods: 20, attributes: 5
Constant pool:
    #1 = Utf8               scala/collection/immutable/Map$EmptyMap$
    #2 = Class              #1            // scala/collection/immutable/Map$EmptyMap$
    #3 = Utf8               Lscala/collection/immutable/AbstractMap<Ljava/lang/Object;Lscala/runtime/Nothing$;>;Ljava/io/Serializable;
    #4 = Utf8               scala/collection/immutable/AbstractMap
    #5 = Class              #4            // scala/collection/immutable/AbstractMap
    #6 = Utf8               java/io/Serializable
    #7 = Class              #6            // java/io/Serializable
    #8 = Utf8               Map.scala
    #9 = Utf8               scala/collection/immutable/Map
   #10 = Class              #9            // scala/collection/immutable/Map
   #11 = Utf8               EmptyMap$
   #12 = Utf8               scala/collection/immutable/Map$Map1
   #13 = Class              #12           // scala/collection/immutable/Map$Map1
   #14 = Utf8               Map1
   #15 = Utf8               MODULE$
   #16 = Utf8               Lscala/collection/immutable/Map$EmptyMap$;
   #17 = Utf8               serialVersionUID
   #18 = Utf8               J
   #19 = Long               3l
   #21 = Utf8               <clinit>
   #22 = Utf8               ()V
   #23 = Utf8               <init>
   #24 = NameAndType        #23:#22       // "<init>":()V
   #25 = Methodref          #2.#24        // scala/collection/immutable/Map$EmptyMap$."<init>":()V
   #26 = NameAndType        #15:#16       // MODULE$:Lscala/collection/immutable/Map$EmptyMap$;
   #27 = Fieldref           #2.#26        // scala/collection/immutable/Map$EmptyMap$.MODULE$:Lscala/collection/immutable/Map$EmptyMap$;
   #28 = Utf8               size
   #29 = Utf8               ()I
   #30 = Utf8               this
   #31 = Utf8               knownSize
   #32 = Utf8               isEmpty
   #33 = Utf8               ()Z
   #34 = Utf8               apply
   #35 = Utf8               (Ljava/lang/Object;)Lscala/runtime/Nothing$;
   #36 = Utf8               key
   #37 = Utf8               java/util/NoSuchElementException
   #38 = Class              #37           // java/util/NoSuchElementException
   #39 = Utf8               java/lang/StringBuilder
   #40 = Class              #39           // java/lang/StringBuilder
   #41 = Integer            15
   #42 = Utf8               (I)V
   #43 = NameAndType        #23:#42       // "<init>":(I)V
   #44 = Methodref          #40.#43       // java/lang/StringBuilder."<init>":(I)V
   #45 = Utf8               key not found:
   #46 = String             #45           // key not found:
   #47 = Utf8               append
   #48 = Utf8               (Ljava/lang/String;)Ljava/lang/StringBuilder;
   #49 = NameAndType        #47:#48       // append:(Ljava/lang/String;)Ljava/lang/StringBuilder;
   #50 = Methodref          #40.#49       // java/lang/StringBuilder.append:(Ljava/lang/String;)Ljava/lang/StringBuilder;
   #51 = Utf8               (Ljava/lang/Object;)Ljava/lang/StringBuilder;
   #52 = NameAndType        #47:#51       // append:(Ljava/lang/Object;)Ljava/lang/StringBuilder;
   #53 = Methodref          #40.#52       // java/lang/StringBuilder.append:(Ljava/lang/Object;)Ljava/lang/StringBuilder;
   #54 = Utf8               toString
   #55 = Utf8               ()Ljava/lang/String;
   #56 = NameAndType        #54:#55       // toString:()Ljava/lang/String;
   #57 = Methodref          #40.#56       // java/lang/StringBuilder.toString:()Ljava/lang/String;
   #58 = Utf8               (Ljava/lang/String;)V
   #59 = NameAndType        #23:#58       // "<init>":(Ljava/lang/String;)V
   #60 = Methodref          #38.#59       // java/util/NoSuchElementException."<init>":(Ljava/lang/String;)V
   #61 = Utf8               Ljava/lang/Object;
   #62 = Utf8               contains
   #63 = Utf8               (Ljava/lang/Object;)Z
   #64 = Utf8               get
   #65 = Utf8               (Ljava/lang/Object;)Lscala/Option;
   #66 = Utf8               (Ljava/lang/Object;)Lscala/Option<Lscala/runtime/Nothing$;>;
   #67 = Utf8               scala/None$
   #68 = Class              #67           // scala/None$
   #69 = Utf8               Lscala/None$;
   #70 = NameAndType        #15:#69       // MODULE$:Lscala/None$;
   #71 = Fieldref           #68.#70       // scala/None$.MODULE$:Lscala/None$;
   #72 = Utf8               getOrElse
   #73 = Utf8               (Ljava/lang/Object;Lscala/Function0;)Ljava/lang/Object;
   #74 = Utf8               <V1:Ljava/lang/Object;>(Ljava/lang/Object;Lscala/Function0<TV1;>;)TV1;
   #75 = Utf8               default
   #76 = Utf8               scala/Function0
   #77 = Class              #76           // scala/Function0
   #78 = Utf8               ()Ljava/lang/Object;
   #79 = NameAndType        #34:#78       // apply:()Ljava/lang/Object;
   #80 = InterfaceMethodref #77.#79       // scala/Function0.apply:()Ljava/lang/Object;
   #81 = Utf8               Lscala/Function0;
   #82 = Utf8               iterator
   #83 = Utf8               ()Lscala/collection/Iterator;
   #84 = Utf8               ()Lscala/collection/Iterator<Lscala/Tuple2<Ljava/lang/Object;Lscala/runtime/Nothing$;>;>;
   #85 = Utf8               scala/collection/Iterator$
   #86 = Class              #85           // scala/collection/Iterator$
   #87 = Utf8               Lscala/collection/Iterator$;
   #88 = NameAndType        #15:#87       // MODULE$:Lscala/collection/Iterator$;
   #89 = Fieldref           #86.#88       // scala/collection/Iterator$.MODULE$:Lscala/collection/Iterator$;
   #90 = Utf8               scala$collection$Iterator$$_empty
   #91 = Utf8               Lscala/collection/Iterator;
   #92 = NameAndType        #90:#91       // scala$collection$Iterator$$_empty:Lscala/collection/Iterator;
   #93 = Fieldref           #86.#92       // scala/collection/Iterator$.scala$collection$Iterator$$_empty:Lscala/collection/Iterator;
   #94 = Utf8               keysIterator
   #95 = Utf8               ()Lscala/collection/Iterator<Ljava/lang/Object;>;
   #96 = Utf8               valuesIterator
   #97 = Utf8               ()Lscala/collection/Iterator<Lscala/runtime/Nothing$;>;
   #98 = Utf8               updated
   #99 = Utf8               (Ljava/lang/Object;Ljava/lang/Object;)Lscala/collection/immutable/Map;
  #100 = Utf8               <V1:Ljava/lang/Object;>(Ljava/lang/Object;TV1;)Lscala/collection/immutable/Map<Ljava/lang/Object;TV1;>;
  #101 = Utf8               value
  #102 = Utf8               (Ljava/lang/Object;Ljava/lang/Object;)V
  #103 = NameAndType        #23:#102      // "<init>":(Ljava/lang/Object;Ljava/lang/Object;)V
  #104 = Methodref          #13.#103      // scala/collection/immutable/Map$Map1."<init>":(Ljava/lang/Object;Ljava/lang/Object;)V
  #105 = Utf8               removed
  #106 = Utf8               (Ljava/lang/Object;)Lscala/collection/immutable/Map;
  #107 = Utf8               (Ljava/lang/Object;)Lscala/collection/immutable/Map<Ljava/lang/Object;Lscala/runtime/Nothing$;>;
  #108 = Utf8               concat
  #109 = Utf8               (Lscala/collection/IterableOnce;)Lscala/collection/immutable/Map;
  #110 = Utf8               <V2:Ljava/lang/Object;>(Lscala/collection/IterableOnce<Lscala/Tuple2<Ljava/lang/Object;TV2;>;>;)Lscala/collection/immutable/Map<Ljava/lang/Object;TV2;>;
  #111 = Utf8               suffix
  #112 = Utf8               scala/collection/MapOps
  #113 = Class              #112          // scala/collection/MapOps
  #114 = Utf8               concat$
  #115 = Utf8               (Lscala/collection/MapOps;Lscala/collection/IterableOnce;)Lscala/collection/IterableOps;
  #116 = NameAndType        #114:#115     // concat$:(Lscala/collection/MapOps;Lscala/collection/IterableOnce;)Lscala/collection/IterableOps;
  #117 = InterfaceMethodref #113.#116     // scala/collection/MapOps.concat$:(Lscala/collection/MapOps;Lscala/collection/IterableOnce;)Lscala/collection/IterableOps;
  #118 = Utf8               Lscala/collection/IterableOnce;
  #119 = Utf8               writeReplace
  #120 = Utf8               scala/runtime/ModuleSerializationProxy
  #121 = Class              #120          // scala/runtime/ModuleSerializationProxy
  #122 = Utf8               (Ljava/lang/Class;)V
  #123 = NameAndType        #23:#122      // "<init>":(Ljava/lang/Class;)V
  #124 = Methodref          #121.#123     // scala/runtime/ModuleSerializationProxy."<init>":(Ljava/lang/Class;)V
  #125 = Utf8               (Lscala/collection/IterableOnce;)Lscala/collection/IterableOps;
  #126 = NameAndType        #108:#109     // concat:(Lscala/collection/IterableOnce;)Lscala/collection/immutable/Map;
  #127 = Methodref          #2.#126       // scala/collection/immutable/Map$EmptyMap$.concat:(Lscala/collection/IterableOnce;)Lscala/collection/immutable/Map;
  #128 = Utf8               (Ljava/lang/Object;)Lscala/collection/immutable/MapOps;
  #129 = NameAndType        #105:#106     // removed:(Ljava/lang/Object;)Lscala/collection/immutable/Map;
  #130 = Methodref          #2.#129       // scala/collection/immutable/Map$EmptyMap$.removed:(Ljava/lang/Object;)Lscala/collection/immutable/Map;
  #131 = Utf8               (Ljava/lang/Object;Ljava/lang/Object;)Lscala/collection/immutable/MapOps;
  #132 = NameAndType        #98:#99       // updated:(Ljava/lang/Object;Ljava/lang/Object;)Lscala/collection/immutable/Map;
  #133 = Methodref          #2.#132       // scala/collection/immutable/Map$EmptyMap$.updated:(Ljava/lang/Object;Ljava/lang/Object;)Lscala/collection/immutable/Map;
  #134 = Utf8               (Ljava/lang/Object;)Ljava/lang/Object;
  #135 = NameAndType        #34:#35       // apply:(Ljava/lang/Object;)Lscala/runtime/Nothing$;
  #136 = Methodref          #2.#135       // scala/collection/immutable/Map$EmptyMap$.apply:(Ljava/lang/Object;)Lscala/runtime/Nothing$;
  #137 = Methodref          #5.#24        // scala/collection/immutable/AbstractMap."<init>":()V
  #138 = Utf8               ConstantValue
  #139 = Utf8               Code
  #140 = Utf8               LineNumberTable
  #141 = Utf8               LocalVariableTable
  #142 = Utf8               MethodParameters
  #143 = Utf8               Signature
  #144 = Utf8               StackMapTable
  #145 = Utf8               InnerClasses
  #146 = Utf8               SourceFile
  #147 = Utf8               ScalaInlineInfo
  #148 = Utf8               Scala
{
  public static final scala.collection.immutable.Map$EmptyMap$ MODULE$;
    descriptor: Lscala/collection/immutable/Map$EmptyMap$;
    flags: (0x0019) ACC_PUBLIC, ACC_STATIC, ACC_FINAL

  private static final long serialVersionUID;
    descriptor: J
    flags: (0x001a) ACC_PRIVATE, ACC_STATIC, ACC_FINAL
    ConstantValue: long 3l

  public static {};
    descriptor: ()V
    flags: (0x0009) ACC_PUBLIC, ACC_STATIC
    Code:
      stack=2, locals=0, args_size=0
         0: new           #2                  // class scala/collection/immutable/Map$EmptyMap$
         3: dup
         4: invokespecial #25                 // Method "<init>":()V
         7: putstatic     #27                 // Field MODULE$:Lscala/collection/immutable/Map$EmptyMap$;
        10: return
      LineNumberTable:
        line 221: 0

  public int size();
    descriptor: ()I
    flags: (0x0001) ACC_PUBLIC
    Code:
      stack=1, locals=1, args_size=1
         0: iconst_0
         1: ireturn
      LineNumberTable:
        line 222: 0
      LocalVariableTable:
        Start  Length  Slot  Name   Signature
            0       2     0  this   Lscala/collection/immutable/Map$EmptyMap$;

  public int knownSize();
    descriptor: ()I
    flags: (0x0001) ACC_PUBLIC
    Code:
      stack=1, locals=1, args_size=1
         0: iconst_0
         1: ireturn
      LineNumberTable:
        line 223: 0
      LocalVariableTable:
        Start  Length  Slot  Name   Signature
            0       2     0  this   Lscala/collection/immutable/Map$EmptyMap$;

  public boolean isEmpty();
    descriptor: ()Z
    flags: (0x0001) ACC_PUBLIC
    Code:
      stack=1, locals=1, args_size=1
         0: iconst_1
         1: ireturn
      LineNumberTable:
        line 224: 0
      LocalVariableTable:
        Start  Length  Slot  Name   Signature
            0       2     0  this   Lscala/collection/immutable/Map$EmptyMap$;

  public scala.runtime.Nothing$ apply(java.lang.Object);
    descriptor: (Ljava/lang/Object;)Lscala/runtime/Nothing$;
    flags: (0x0001) ACC_PUBLIC
    Code:
      stack=5, locals=2, args_size=2
         0: new           #38                 // class java/util/NoSuchElementException
         3: dup
         4: new           #40                 // class java/lang/StringBuilder
         7: dup
         8: ldc           #41                 // int 15
        10: invokespecial #44                 // Method java/lang/StringBuilder."<init>":(I)V
        13: ldc           #46                 // String key not found:
        15: invokevirtual #50                 // Method java/lang/StringBuilder.append:(Ljava/lang/String;)Ljava/lang/StringBuilder;
        18: aload_1
        19: invokevirtual #53                 // Method java/lang/StringBuilder.append:(Ljava/lang/Object;)Ljava/lang/StringBuilder;
        22: invokevirtual #57                 // Method java/lang/StringBuilder.toString:()Ljava/lang/String;
        25: invokespecial #60                 // Method java/util/NoSuchElementException."<init>":(Ljava/lang/String;)V
        28: athrow
      LineNumberTable:
        line 225: 0
      LocalVariableTable:
        Start  Length  Slot  Name   Signature
            0      29     0  this   Lscala/collection/immutable/Map$EmptyMap$;
            0      29     1   key   Ljava/lang/Object;
    MethodParameters:
      Name                           Flags
      key                            final

  public boolean contains(java.lang.Object);
    descriptor: (Ljava/lang/Object;)Z
    flags: (0x0001) ACC_PUBLIC
    Code:
      stack=1, locals=2, args_size=2
         0: iconst_0
         1: ireturn
      LineNumberTable:
        line 226: 0
      LocalVariableTable:
        Start  Length  Slot  Name   Signature
            0       2     0  this   Lscala/collection/immutable/Map$EmptyMap$;
            0       2     1   key   Ljava/lang/Object;
    MethodParameters:
      Name                           Flags
      key                            final

  public scala.Option<scala.runtime.Nothing$> get(java.lang.Object);
    descriptor: (Ljava/lang/Object;)Lscala/Option;
    flags: (0x0001) ACC_PUBLIC
    Code:
      stack=1, locals=2, args_size=2
         0: getstatic     #71                 // Field scala/None$.MODULE$:Lscala/None$;
         3: areturn
      LineNumberTable:
        line 227: 0
      LocalVariableTable:
        Start  Length  Slot  Name   Signature
            0       4     0  this   Lscala/collection/immutable/Map$EmptyMap$;
            0       4     1   key   Ljava/lang/Object;
    Signature: #66                          // (Ljava/lang/Object;)Lscala/Option<Lscala/runtime/Nothing$;>;
    MethodParameters:
      Name                           Flags
      key                            final

  public <V1 extends java.lang.Object> V1 getOrElse(java.lang.Object, scala.Function0<V1>);
    descriptor: (Ljava/lang/Object;Lscala/Function0;)Ljava/lang/Object;
    flags: (0x0001) ACC_PUBLIC
    Code:
      stack=1, locals=3, args_size=3
         0: aload_2
         1: invokeinterface #80,  1           // InterfaceMethod scala/Function0.apply:()Ljava/lang/Object;
         6: areturn
      LineNumberTable:
        line 228: 0
      LocalVariableTable:
        Start  Length  Slot  Name   Signature
            0       7     0  this   Lscala/collection/immutable/Map$EmptyMap$;
            0       7     1   key   Ljava/lang/Object;
            0       7     2 default   Lscala/Function0;
    Signature: #74                          // <V1:Ljava/lang/Object;>(Ljava/lang/Object;Lscala/Function0<TV1;>;)TV1;
    MethodParameters:
      Name                           Flags
      key                            final
      default                        final

  public scala.collection.Iterator<scala.Tuple2<java.lang.Object, scala.runtime.Nothing$>> iterator();
    descriptor: ()Lscala/collection/Iterator;
    flags: (0x0001) ACC_PUBLIC
    Code:
      stack=1, locals=1, args_size=1
         0: getstatic     #89                 // Field scala/collection/Iterator$.MODULE$:Lscala/collection/Iterator$;
         3: pop
         4: getstatic     #93                 // Field scala/collection/Iterator$.scala$collection$Iterator$$_empty:Lscala/collection/Iterator;
         7: areturn
      LineNumberTable:
        line 229: 0
      LocalVariableTable:
        Start  Length  Slot  Name   Signature
            0       8     0  this   Lscala/collection/immutable/Map$EmptyMap$;
    Signature: #84                          // ()Lscala/collection/Iterator<Lscala/Tuple2<Ljava/lang/Object;Lscala/runtime/Nothing$;>;>;

  public scala.collection.Iterator<java.lang.Object> keysIterator();
    descriptor: ()Lscala/collection/Iterator;
    flags: (0x0001) ACC_PUBLIC
    Code:
      stack=1, locals=1, args_size=1
         0: getstatic     #89                 // Field scala/collection/Iterator$.MODULE$:Lscala/collection/Iterator$;
         3: pop
         4: getstatic     #93                 // Field scala/collection/Iterator$.scala$collection$Iterator$$_empty:Lscala/collection/Iterator;
         7: areturn
      LineNumberTable:
        line 230: 0
      LocalVariableTable:
        Start  Length  Slot  Name   Signature
            0       8     0  this   Lscala/collection/immutable/Map$EmptyMap$;
    Signature: #95                          // ()Lscala/collection/Iterator<Ljava/lang/Object;>;

  public scala.collection.Iterator<scala.runtime.Nothing$> valuesIterator();
    descriptor: ()Lscala/collection/Iterator;
    flags: (0x0001) ACC_PUBLIC
    Code:
      stack=1, locals=1, args_size=1
         0: getstatic     #89                 // Field scala/collection/Iterator$.MODULE$:Lscala/collection/Iterator$;
         3: pop
         4: getstatic     #93                 // Field scala/collection/Iterator$.scala$collection$Iterator$$_empty:Lscala/collection/Iterator;
         7: areturn
      LineNumberTable:
        line 231: 0
      LocalVariableTable:
        Start  Length  Slot  Name   Signature
            0       8     0  this   Lscala/collection/immutable/Map$EmptyMap$;
    Signature: #97                          // ()Lscala/collection/Iterator<Lscala/runtime/Nothing$;>;

  public <V1 extends java.lang.Object> scala.collection.immutable.Map<java.lang.Object, V1> updated(java.lang.Object, V1);
    descriptor: (Ljava/lang/Object;Ljava/lang/Object;)Lscala/collection/immutable/Map;
    flags: (0x0001) ACC_PUBLIC
    Code:
      stack=4, locals=3, args_size=3
         0: new           #13                 // class scala/collection/immutable/Map$Map1
         3: dup
         4: aload_1
         5: aload_2
         6: invokespecial #104                // Method scala/collection/immutable/Map$Map1."<init>":(Ljava/lang/Object;Ljava/lang/Object;)V
         9: areturn
      LineNumberTable:
        line 232: 0
      LocalVariableTable:
        Start  Length  Slot  Name   Signature
            0      10     0  this   Lscala/collection/immutable/Map$EmptyMap$;
            0      10     1   key   Ljava/lang/Object;
            0      10     2 value   Ljava/lang/Object;
    Signature: #100                         // <V1:Ljava/lang/Object;>(Ljava/lang/Object;TV1;)Lscala/collection/immutable/Map<Ljava/lang/Object;TV1;>;
    MethodParameters:
      Name                           Flags
      key                            final
      value                          final

  public scala.collection.immutable.Map<java.lang.Object, scala.runtime.Nothing$> removed(java.lang.Object);
    descriptor: (Ljava/lang/Object;)Lscala/collection/immutable/Map;
    flags: (0x0001) ACC_PUBLIC
    Code:
      stack=1, locals=2, args_size=2
         0: aload_0
         1: areturn
      LineNumberTable:
        line 233: 0
      LocalVariableTable:
        Start  Length  Slot  Name   Signature
            0       2     0  this   Lscala/collection/immutable/Map$EmptyMap$;
            0       2     1   key   Ljava/lang/Object;
    Signature: #107                         // (Ljava/lang/Object;)Lscala/collection/immutable/Map<Ljava/lang/Object;Lscala/runtime/Nothing$;>;
    MethodParameters:
      Name                           Flags
      key                            final

  public <V2 extends java.lang.Object> scala.collection.immutable.Map<java.lang.Object, V2> concat(scala.collection.IterableOnce<scala.Tuple2<java.lang.Object, V2>>);
    descriptor: (Lscala/collection/IterableOnce;)Lscala/collection/immutable/Map;
    flags: (0x0001) ACC_PUBLIC
    Code:
      stack=2, locals=3, args_size=2
         0: aload_1
         1: instanceof    #10                 // class scala/collection/immutable/Map
         4: ifeq          15
         7: aload_1
         8: checkcast     #10                 // class scala/collection/immutable/Map
        11: astore_2
        12: goto          24
        15: aload_0
        16: aload_1
        17: invokestatic  #117                // InterfaceMethod scala/collection/MapOps.concat$:(Lscala/collection/MapOps;Lscala/collection/IterableOnce;)Lscala/collection/IterableOps;
        20: checkcast     #10                 // class scala/collection/immutable/Map
        23: astore_2
        24: aload_2
        25: areturn
      StackMapTable: number_of_entries = 2
        frame_type = 15 /* same */
        frame_type = 252 /* append */
          offset_delta = 8
          locals = [ class scala/collection/immutable/Map ]
      LineNumberTable:
        line 235: 0
        line 236: 15
        line 234: 24
      LocalVariableTable:
        Start  Length  Slot  Name   Signature
            0      26     0  this   Lscala/collection/immutable/Map$EmptyMap$;
            0      26     1 suffix   Lscala/collection/IterableOnce;
    Signature: #110                         // <V2:Ljava/lang/Object;>(Lscala/collection/IterableOnce<Lscala/Tuple2<Ljava/lang/Object;TV2;>;>;)Lscala/collection/immutable/Map<Ljava/lang/Object;TV2;>;
    MethodParameters:
      Name                           Flags
      suffix                         final

  private java.lang.Object writeReplace();
    descriptor: ()Ljava/lang/Object;
    flags: (0x0002) ACC_PRIVATE
    Code:
      stack=3, locals=1, args_size=1
         0: new           #121                // class scala/runtime/ModuleSerializationProxy
         3: dup
         4: ldc           #2                  // class scala/collection/immutable/Map$EmptyMap$
         6: invokespecial #124                // Method scala/runtime/ModuleSerializationProxy."<init>":(Ljava/lang/Class;)V
         9: areturn
      LineNumberTable:
        line 221: 0
      LocalVariableTable:
        Start  Length  Slot  Name   Signature
            0      10     0  this   Lscala/collection/immutable/Map$EmptyMap$;

  public scala.collection.IterableOps concat(scala.collection.IterableOnce);
    descriptor: (Lscala/collection/IterableOnce;)Lscala/collection/IterableOps;
    flags: (0x1041) ACC_PUBLIC, ACC_BRIDGE, ACC_SYNTHETIC
    Code:
      stack=2, locals=2, args_size=2
         0: aload_0
         1: aload_1
         2: invokevirtual #127                // Method concat:(Lscala/collection/IterableOnce;)Lscala/collection/immutable/Map;
         5: areturn
      LineNumberTable:
        line 221: 0
      LocalVariableTable:
        Start  Length  Slot  Name   Signature
            0       6     0  this   Lscala/collection/immutable/Map$EmptyMap$;
            0       6     1 suffix   Lscala/collection/IterableOnce;
    MethodParameters:
      Name                           Flags
      suffix                         final

  public scala.collection.immutable.MapOps removed(java.lang.Object);
    descriptor: (Ljava/lang/Object;)Lscala/collection/immutable/MapOps;
    flags: (0x1041) ACC_PUBLIC, ACC_BRIDGE, ACC_SYNTHETIC
    Code:
      stack=2, locals=2, args_size=2
         0: aload_0
         1: aload_1
         2: invokevirtual #130                // Method removed:(Ljava/lang/Object;)Lscala/collection/immutable/Map;
         5: areturn
      LineNumberTable:
        line 221: 0
      LocalVariableTable:
        Start  Length  Slot  Name   Signature
            0       6     0  this   Lscala/collection/immutable/Map$EmptyMap$;
            0       6     1   key   Ljava/lang/Object;
    MethodParameters:
      Name                           Flags
      key                            final

  public scala.collection.immutable.MapOps updated(java.lang.Object, java.lang.Object);
    descriptor: (Ljava/lang/Object;Ljava/lang/Object;)Lscala/collection/immutable/MapOps;
    flags: (0x1041) ACC_PUBLIC, ACC_BRIDGE, ACC_SYNTHETIC
    Code:
      stack=3, locals=3, args_size=3
         0: aload_0
         1: aload_1
         2: aload_2
         3: invokevirtual #133                // Method updated:(Ljava/lang/Object;Ljava/lang/Object;)Lscala/collection/immutable/Map;
         6: areturn
      LineNumberTable:
        line 221: 0
      LocalVariableTable:
        Start  Length  Slot  Name   Signature
            0       7     0  this   Lscala/collection/immutable/Map$EmptyMap$;
            0       7     1   key   Ljava/lang/Object;
            0       7     2 value   Ljava/lang/Object;
    MethodParameters:
      Name                           Flags
      key                            final
      value                          final

  public java.lang.Object apply(java.lang.Object);
    descriptor: (Ljava/lang/Object;)Ljava/lang/Object;
    flags: (0x1041) ACC_PUBLIC, ACC_BRIDGE, ACC_SYNTHETIC
    Code:
      stack=2, locals=2, args_size=2
         0: aload_0
         1: aload_1
         2: invokevirtual #136                // Method apply:(Ljava/lang/Object;)Lscala/runtime/Nothing$;
         5: athrow
      LineNumberTable:
        line 221: 0
      LocalVariableTable:
        Start  Length  Slot  Name   Signature
            0       6     0  this   Lscala/collection/immutable/Map$EmptyMap$;
            0       6     1   key   Ljava/lang/Object;
    MethodParameters:
      Name                           Flags
      key                            final

  public scala.collection.immutable.Map$EmptyMap$();
    descriptor: ()V
    flags: (0x0001) ACC_PUBLIC
    Code:
      stack=1, locals=1, args_size=1
         0: aload_0
         1: invokespecial #137                // Method scala/collection/immutable/AbstractMap."<init>":()V
         4: return
      LineNumberTable:
        line 221: 0
      LocalVariableTable:
        Start  Length  Slot  Name   Signature
            0       5     0  this   Lscala/collection/immutable/Map$EmptyMap$;
}
InnerClasses:
  private static #11= #2 of #10;          // EmptyMap$=class scala/collection/immutable/Map$EmptyMap$ of class scala/collection/immutable/Map
  public static final #14= #13 of #10;    // Map1=class scala/collection/immutable/Map$Map1 of class scala/collection/immutable/Map
Signature: #3                           // Lscala/collection/immutable/AbstractMap<Ljava/lang/Object;Lscala/runtime/Nothing$;>;Ljava/io/Serializable;
SourceFile: "Map.scala"
  ScalaInlineInfo: length = 0x63 (unknown attribute)
   01 01 00 13 00 17 00 16 01 00 22 00 86 01 00 22
   00 23 01 00 6C 00 7D 01 00 6C 00 6D 01 00 3E 00
   3F 01 00 40 00 41 01 00 48 00 49 01 00 20 00 21
   01 00 52 00 53 01 00 5E 00 53 01 00 1F 00 1D 01
   00 69 00 6A 01 00 69 00 80 01 00 1C 00 1D 01 00
   62 00 63 01 00 62 00 83 01 00 60 00 53 01 00 77
   00 4E 01
  Scala: length = 0x0 (unknown attribute)

