Classfile /Users/mw/Projects/slang-braindump/.jar/jar11/assemble/slang-braindump/assemble/content/scala/collection/immutable/Node$.class
  Last modified May 29, 2022; size 1506 bytes
  SHA-256 checksum 5b4b3139d78cc52ae9a31d48beb5ce500f6478597985e12b04f817bc25ee83c0
  Compiled from "ChampCommon.scala"
public final class scala.collection.immutable.Node$
  minor version: 0
  major version: 52
  flags: (0x0031) ACC_PUBLIC, ACC_FINAL, ACC_SUPER
  this_class: #2                          // scala/collection/immutable/Node$
  super_class: #4                         // java/lang/Object
  interfaces: 0, fields: 2, methods: 11, attributes: 3
Constant pool:
   #1 = Utf8               scala/collection/immutable/Node$
   #2 = Class              #1             // scala/collection/immutable/Node$
   #3 = Utf8               java/lang/Object
   #4 = Class              #3             // java/lang/Object
   #5 = Utf8               ChampCommon.scala
   #6 = Utf8               MODULE$
   #7 = Utf8               Lscala/collection/immutable/Node$;
   #8 = Utf8               MaxDepth
   #9 = Utf8               I
  #10 = Utf8               <clinit>
  #11 = Utf8               ()V
  #12 = Utf8               <init>
  #13 = NameAndType        #12:#11        // "<init>":()V
  #14 = Methodref          #2.#13         // scala/collection/immutable/Node$."<init>":()V
  #15 = NameAndType        #6:#7          // MODULE$:Lscala/collection/immutable/Node$;
  #16 = Fieldref           #2.#15         // scala/collection/immutable/Node$.MODULE$:Lscala/collection/immutable/Node$;
  #17 = Utf8               java/lang/Math
  #18 = Class              #17            // java/lang/Math
  #19 = Utf8               ceil
  #20 = Utf8               (D)D
  #21 = NameAndType        #19:#20        // ceil:(D)D
  #22 = Methodref          #18.#21        // java/lang/Math.ceil:(D)D
  #23 = NameAndType        #8:#9          // MaxDepth:I
  #24 = Fieldref           #2.#23         // scala/collection/immutable/Node$.MaxDepth:I
  #25 = Utf8               HashCodeLength
  #26 = Utf8               ()I
  #27 = Utf8               this
  #28 = Utf8               BitPartitionSize
  #29 = Utf8               BitPartitionMask
  #30 = Utf8               BranchingFactor
  #31 = Utf8               maskFrom
  #32 = Utf8               (II)I
  #33 = Utf8               hash
  #34 = Utf8               shift
  #35 = Utf8               bitposFrom
  #36 = Utf8               (I)I
  #37 = Utf8               mask
  #38 = Utf8               indexFrom
  #39 = Utf8               bitmap
  #40 = Utf8               bitpos
  #41 = Utf8               java/lang/Integer
  #42 = Class              #41            // java/lang/Integer
  #43 = Utf8               bitCount
  #44 = NameAndType        #43:#36        // bitCount:(I)I
  #45 = Methodref          #42.#44        // java/lang/Integer.bitCount:(I)I
  #46 = Utf8               (III)I
  #47 = Methodref          #4.#13         // java/lang/Object."<init>":()V
  #48 = Utf8               Code
  #49 = Utf8               LineNumberTable
  #50 = Utf8               LocalVariableTable
  #51 = Utf8               MethodParameters
  #52 = Utf8               StackMapTable
  #53 = Utf8               SourceFile
  #54 = Utf8               ScalaInlineInfo
  #55 = Utf8               Scala
{
  public static final scala.collection.immutable.Node$ MODULE$;
    descriptor: Lscala/collection/immutable/Node$;
    flags: (0x0019) ACC_PUBLIC, ACC_STATIC, ACC_FINAL

  private static final int MaxDepth;
    descriptor: I
    flags: (0x001a) ACC_PRIVATE, ACC_STATIC, ACC_FINAL

  public static {};
    descriptor: ()V
    flags: (0x0009) ACC_PUBLIC, ACC_STATIC
    Code:
      stack=4, locals=0, args_size=0
         0: new           #2                  // class scala/collection/immutable/Node$
         3: dup
         4: invokespecial #14                 // Method "<init>":()V
         7: putstatic     #16                 // Field MODULE$:Lscala/collection/immutable/Node$;
        10: bipush        32
        12: i2d
        13: iconst_5
        14: i2d
        15: ddiv
        16: invokestatic  #22                 // Method java/lang/Math.ceil:(D)D
        19: d2i
        20: putstatic     #24                 // Field MaxDepth:I
        23: return
      LineNumberTable:
        line 20: 0
        line 27: 10
        line 20: 23

  public final int HashCodeLength();
    descriptor: ()I
    flags: (0x0011) ACC_PUBLIC, ACC_FINAL
    Code:
      stack=1, locals=1, args_size=1
         0: bipush        32
         2: ireturn
      LocalVariableTable:
        Start  Length  Slot  Name   Signature
            0       3     0  this   Lscala/collection/immutable/Node$;

  public final int BitPartitionSize();
    descriptor: ()I
    flags: (0x0011) ACC_PUBLIC, ACC_FINAL
    Code:
      stack=1, locals=1, args_size=1
         0: iconst_5
         1: ireturn
      LocalVariableTable:
        Start  Length  Slot  Name   Signature
            0       2     0  this   Lscala/collection/immutable/Node$;

  public final int BitPartitionMask();
    descriptor: ()I
    flags: (0x0011) ACC_PUBLIC, ACC_FINAL
    Code:
      stack=1, locals=1, args_size=1
         0: bipush        31
         2: ireturn
      LocalVariableTable:
        Start  Length  Slot  Name   Signature
            0       3     0  this   Lscala/collection/immutable/Node$;

  public final int MaxDepth();
    descriptor: ()I
    flags: (0x0011) ACC_PUBLIC, ACC_FINAL
    Code:
      stack=1, locals=1, args_size=1
         0: getstatic     #24                 // Field MaxDepth:I
         3: ireturn
      LineNumberTable:
        line 27: 0
      LocalVariableTable:
        Start  Length  Slot  Name   Signature
            0       4     0  this   Lscala/collection/immutable/Node$;

  public final int BranchingFactor();
    descriptor: ()I
    flags: (0x0011) ACC_PUBLIC, ACC_FINAL
    Code:
      stack=1, locals=1, args_size=1
         0: bipush        32
         2: ireturn
      LocalVariableTable:
        Start  Length  Slot  Name   Signature
            0       3     0  this   Lscala/collection/immutable/Node$;

  public final int maskFrom(int, int);
    descriptor: (II)I
    flags: (0x0011) ACC_PUBLIC, ACC_FINAL
    Code:
      stack=2, locals=3, args_size=3
         0: iload_1
         1: iload_2
         2: iushr
         3: bipush        31
         5: iand
         6: ireturn
      LineNumberTable:
        line 31: 0
      LocalVariableTable:
        Start  Length  Slot  Name   Signature
            0       7     0  this   Lscala/collection/immutable/Node$;
            0       7     1  hash   I
            0       7     2 shift   I
    MethodParameters:
      Name                           Flags
      hash                           final
      shift                          final

  public final int bitposFrom(int);
    descriptor: (I)I
    flags: (0x0011) ACC_PUBLIC, ACC_FINAL
    Code:
      stack=2, locals=2, args_size=2
         0: iconst_1
         1: iload_1
         2: ishl
         3: ireturn
      LineNumberTable:
        line 33: 0
      LocalVariableTable:
        Start  Length  Slot  Name   Signature
            0       4     0  this   Lscala/collection/immutable/Node$;
            0       4     1  mask   I
    MethodParameters:
      Name                           Flags
      mask                           final

  public final int indexFrom(int, int);
    descriptor: (II)I
    flags: (0x0011) ACC_PUBLIC, ACC_FINAL
    Code:
      stack=3, locals=3, args_size=3
         0: iload_1
         1: iload_2
         2: iconst_1
         3: isub
         4: iand
         5: invokestatic  #45                 // Method java/lang/Integer.bitCount:(I)I
         8: ireturn
      LineNumberTable:
        line 35: 0
      LocalVariableTable:
        Start  Length  Slot  Name   Signature
            0       9     0  this   Lscala/collection/immutable/Node$;
            0       9     1 bitmap   I
            0       9     2 bitpos   I
    MethodParameters:
      Name                           Flags
      bitmap                         final
      bitpos                         final

  public final int indexFrom(int, int, int);
    descriptor: (III)I
    flags: (0x0011) ACC_PUBLIC, ACC_FINAL
    Code:
      stack=3, locals=4, args_size=4
         0: iload_1
         1: iconst_m1
         2: if_icmpne     7
         5: iload_2
         6: ireturn
         7: iload_1
         8: iload_3
         9: iconst_1
        10: isub
        11: iand
        12: invokestatic  #45                 // Method java/lang/Integer.bitCount:(I)I
        15: ireturn
      StackMapTable: number_of_entries = 1
        frame_type = 7 /* same */
      LineNumberTable:
        line 37: 0
        line 35: 7
        line 37: 15
      LocalVariableTable:
        Start  Length  Slot  Name   Signature
            0      16     0  this   Lscala/collection/immutable/Node$;
            0      16     1 bitmap   I
            0      16     2  mask   I
            0      16     3 bitpos   I
    MethodParameters:
      Name                           Flags
      bitmap                         final
      mask                           final
      bitpos                         final

  private scala.collection.immutable.Node$();
    descriptor: ()V
    flags: (0x0002) ACC_PRIVATE
    Code:
      stack=1, locals=1, args_size=1
         0: aload_0
         1: invokespecial #47                 // Method java/lang/Object."<init>":()V
         4: return
      LineNumberTable:
        line 20: 0
      LocalVariableTable:
        Start  Length  Slot  Name   Signature
            0       5     0  this   Lscala/collection/immutable/Node$;
}
SourceFile: "ChampCommon.scala"
  ScalaInlineInfo: length = 0x36 (unknown attribute)
   01 01 00 0A 00 0C 00 0B 01 00 1D 00 1A 01 00 1C
   00 1A 01 00 1E 00 1A 01 00 19 00 1A 01 00 08 00
   1A 01 00 23 00 24 01 00 26 00 20 01 00 26 00 2E
   01 00 1F 00 20 01
  Scala: length = 0x0 (unknown attribute)

