Classfile /Users/mw/Projects/slang-braindump/.jar/jar11/assemble/slang-braindump/assemble/content/scala/collection/immutable/OldHashSet$LeafOldHashSet.class
  Last modified May 29, 2022; size 571 bytes
  SHA-256 checksum 5961639beb4509f637a0c68e8da8c88ac98fd995b62b9019efa8d856115c827c
  Compiled from "OldHashSet.scala"
public abstract class scala.collection.immutable.OldHashSet$LeafOldHashSet<A extends java.lang.Object> extends scala.collection.immutable.OldHashSet<A>
  minor version: 0
  major version: 52
  flags: (0x0421) ACC_PUBLIC, ACC_SUPER, ACC_ABSTRACT
  this_class: #2                          // scala/collection/immutable/OldHashSet$LeafOldHashSet
  super_class: #5                         // scala/collection/immutable/OldHashSet
  interfaces: 0, fields: 0, methods: 2, attributes: 5
Constant pool:
   #1 = Utf8               scala/collection/immutable/OldHashSet$LeafOldHashSet
   #2 = Class              #1             // scala/collection/immutable/OldHashSet$LeafOldHashSet
   #3 = Utf8               <A:Ljava/lang/Object;>Lscala/collection/immutable/OldHashSet<TA;>;
   #4 = Utf8               scala/collection/immutable/OldHashSet
   #5 = Class              #4             // scala/collection/immutable/OldHashSet
   #6 = Utf8               OldHashSet.scala
   #7 = Utf8               LeafOldHashSet
   #8 = Utf8               hash
   #9 = Utf8               ()I
  #10 = Utf8               <init>
  #11 = Utf8               ()V
  #12 = NameAndType        #10:#11        // "<init>":()V
  #13 = Methodref          #5.#12         // scala/collection/immutable/OldHashSet."<init>":()V
  #14 = Utf8               this
  #15 = Utf8               Lscala/collection/immutable/OldHashSet$LeafOldHashSet;
  #16 = Utf8               Code
  #17 = Utf8               LineNumberTable
  #18 = Utf8               LocalVariableTable
  #19 = Utf8               InnerClasses
  #20 = Utf8               Signature
  #21 = Utf8               SourceFile
  #22 = Utf8               ScalaInlineInfo
  #23 = Utf8               Scala
{
  public abstract int hash();
    descriptor: ()I
    flags: (0x0401) ACC_PUBLIC, ACC_ABSTRACT

  public scala.collection.immutable.OldHashSet$LeafOldHashSet();
    descriptor: ()V
    flags: (0x0001) ACC_PUBLIC
    Code:
      stack=1, locals=1, args_size=1
         0: aload_0
         1: invokespecial #13                 // Method scala/collection/immutable/OldHashSet."<init>":()V
         4: return
      LineNumberTable:
        line 224: 0
      LocalVariableTable:
        Start  Length  Slot  Name   Signature
            0       5     0  this   Lscala/collection/immutable/OldHashSet$LeafOldHashSet;
}
InnerClasses:
  public static abstract #7= #2 of #5;    // LeafOldHashSet=class scala/collection/immutable/OldHashSet$LeafOldHashSet of class scala/collection/immutable/OldHashSet
Signature: #3                           // <A:Ljava/lang/Object;>Lscala/collection/immutable/OldHashSet<TA;>;
SourceFile: "OldHashSet.scala"
  ScalaInlineInfo: length = 0xE (unknown attribute)
   01 00 00 02 00 0A 00 0B 01 00 08 00 09 00
  Scala: length = 0x0 (unknown attribute)

