Classfile /Users/mw/Projects/slang-braindump/.jar/jar11/assemble/slang-braindump/assemble/content/scala/collection/immutable/OldHashMap$.class
  Last modified May 29, 2022; size 7350 bytes
  SHA-256 checksum 1e391e2ae64e60f61cae1eda5d09a5d618a993a20cc154dbd8422afa43ff2b24
  Compiled from "OldHashMap.scala"
public final class scala.collection.immutable.OldHashMap$ extends java.lang.Object implements scala.collection.MapFactory<scala.collection.immutable.OldHashMap>
  minor version: 0
  major version: 52
  flags: (0x0031) ACC_PUBLIC, ACC_FINAL, ACC_SUPER
  this_class: #2                          // scala/collection/immutable/OldHashMap$
  super_class: #5                         // java/lang/Object
  interfaces: 1, fields: 3, methods: 19, attributes: 6
Constant pool:
    #1 = Utf8               scala/collection/immutable/OldHashMap$
    #2 = Class              #1            // scala/collection/immutable/OldHashMap$
    #3 = Utf8               Ljava/lang/Object;Lscala/collection/MapFactory<Lscala/collection/immutable/OldHashMap;>;
    #4 = Utf8               java/lang/Object
    #5 = Class              #4            // java/lang/Object
    #6 = Utf8               scala/collection/MapFactory
    #7 = Class              #6            // scala/collection/MapFactory
    #8 = Utf8               OldHashMap.scala
    #9 = Utf8               java/lang/invoke/MethodHandles$Lookup
   #10 = Class              #9            // java/lang/invoke/MethodHandles$Lookup
   #11 = Utf8               java/lang/invoke/MethodHandles
   #12 = Class              #11           // java/lang/invoke/MethodHandles
   #13 = Utf8               Lookup
   #14 = Utf8               scala/collection/immutable/OldHashMap$$anon$1
   #15 = Class              #14           // scala/collection/immutable/OldHashMap$$anon$1
   #16 = Utf8               scala/collection/immutable/OldHashMap$$anon$2
   #17 = Class              #16           // scala/collection/immutable/OldHashMap$$anon$2
   #18 = Utf8               scala/collection/immutable/OldHashMap$EmptyOldHashMap$
   #19 = Class              #18           // scala/collection/immutable/OldHashMap$EmptyOldHashMap$
   #20 = Utf8               scala/collection/immutable/OldHashMap
   #21 = Class              #20           // scala/collection/immutable/OldHashMap
   #22 = Utf8               EmptyOldHashMap$
   #23 = Utf8               scala/collection/immutable/OldHashMap$HashTrieMap
   #24 = Class              #23           // scala/collection/immutable/OldHashMap$HashTrieMap
   #25 = Utf8               HashTrieMap
   #26 = Utf8               scala/collection/immutable/OldHashMap$Merger
   #27 = Class              #26           // scala/collection/immutable/OldHashMap$Merger
   #28 = Utf8               Merger
   #29 = Utf8               MODULE$
   #30 = Utf8               Lscala/collection/immutable/OldHashMap$;
   #31 = Utf8               serialVersionUID
   #32 = Utf8               J
   #33 = Long               3l
   #35 = Utf8               defaultMerger
   #36 = Utf8               Lscala/collection/immutable/OldHashMap$Merger;
   #37 = Utf8               Lscala/collection/immutable/OldHashMap$Merger<Ljava/lang/Object;Ljava/lang/Object;>;
   #38 = Utf8               <clinit>
   #39 = Utf8               ()V
   #40 = Utf8               <init>
   #41 = NameAndType        #40:#39       // "<init>":()V
   #42 = Methodref          #2.#41        // scala/collection/immutable/OldHashMap$."<init>":()V
   #43 = NameAndType        #29:#30       // MODULE$:Lscala/collection/immutable/OldHashMap$;
   #44 = Fieldref           #2.#43        // scala/collection/immutable/OldHashMap$.MODULE$:Lscala/collection/immutable/OldHashMap$;
   #45 = Utf8               $init$
   #46 = Utf8               (Lscala/collection/MapFactory;)V
   #47 = NameAndType        #45:#46       // $init$:(Lscala/collection/MapFactory;)V
   #48 = InterfaceMethodref #7.#47        // scala/collection/MapFactory.$init$:(Lscala/collection/MapFactory;)V
   #49 = Utf8               (Ljava/lang/Object;Ljava/lang/Object;)Ljava/lang/Object;
   #50 = MethodType         #49           //  (Ljava/lang/Object;Ljava/lang/Object;)Ljava/lang/Object;
   #51 = Utf8               $anonfun$defaultMerger$1
   #52 = Utf8               (Lscala/Tuple2;Lscala/Tuple2;)Lscala/Tuple2;
   #53 = NameAndType        #51:#52       // $anonfun$defaultMerger$1:(Lscala/Tuple2;Lscala/Tuple2;)Lscala/Tuple2;
   #54 = Methodref          #2.#53        // scala/collection/immutable/OldHashMap$.$anonfun$defaultMerger$1:(Lscala/Tuple2;Lscala/Tuple2;)Lscala/Tuple2;
   #55 = MethodHandle       6:#54         // REF_invokeStatic scala/collection/immutable/OldHashMap$.$anonfun$defaultMerger$1:(Lscala/Tuple2;Lscala/Tuple2;)Lscala/Tuple2;
   #56 = MethodType         #52           //  (Lscala/Tuple2;Lscala/Tuple2;)Lscala/Tuple2;
   #57 = Integer            5
   #58 = Integer            1
   #59 = Utf8               java/lang/invoke/LambdaMetafactory
   #60 = Class              #59           // java/lang/invoke/LambdaMetafactory
   #61 = Utf8               altMetafactory
   #62 = Utf8               (Ljava/lang/invoke/MethodHandles$Lookup;Ljava/lang/String;Ljava/lang/invoke/MethodType;[Ljava/lang/Object;)Ljava/lang/invoke/CallSite;
   #63 = NameAndType        #61:#62       // altMetafactory:(Ljava/lang/invoke/MethodHandles$Lookup;Ljava/lang/String;Ljava/lang/invoke/MethodType;[Ljava/lang/Object;)Ljava/lang/invoke/CallSite;
   #64 = Methodref          #60.#63       // java/lang/invoke/LambdaMetafactory.altMetafactory:(Ljava/lang/invoke/MethodHandles$Lookup;Ljava/lang/String;Ljava/lang/invoke/MethodType;[Ljava/lang/Object;)Ljava/lang/invoke/CallSite;
   #65 = MethodHandle       6:#64         // REF_invokeStatic java/lang/invoke/LambdaMetafactory.altMetafactory:(Ljava/lang/invoke/MethodHandles$Lookup;Ljava/lang/String;Ljava/lang/invoke/MethodType;[Ljava/lang/Object;)Ljava/lang/invoke/CallSite;
   #66 = Utf8               apply
   #67 = Utf8               ()Lscala/Function2;
   #68 = NameAndType        #66:#67       // apply:()Lscala/Function2;
   #69 = InvokeDynamic      #0:#68        // #0:apply:()Lscala/Function2;
   #70 = Utf8               liftMerger0
   #71 = Utf8               (Lscala/Function2;)Lscala/collection/immutable/OldHashMap$Merger;
   #72 = NameAndType        #70:#71       // liftMerger0:(Lscala/Function2;)Lscala/collection/immutable/OldHashMap$Merger;
   #73 = Methodref          #2.#72        // scala/collection/immutable/OldHashMap$.liftMerger0:(Lscala/Function2;)Lscala/collection/immutable/OldHashMap$Merger;
   #74 = NameAndType        #35:#36       // defaultMerger:Lscala/collection/immutable/OldHashMap$Merger;
   #75 = Fieldref           #2.#74        // scala/collection/immutable/OldHashMap$.defaultMerger:Lscala/collection/immutable/OldHashMap$Merger;
   #76 = Utf8               (Lscala/collection/immutable/Seq;)Ljava/lang/Object;
   #77 = Utf8               elems
   #78 = Utf8               apply$
   #79 = Utf8               (Lscala/collection/MapFactory;Lscala/collection/immutable/Seq;)Ljava/lang/Object;
   #80 = NameAndType        #78:#79       // apply$:(Lscala/collection/MapFactory;Lscala/collection/immutable/Seq;)Ljava/lang/Object;
   #81 = InterfaceMethodref #7.#80        // scala/collection/MapFactory.apply$:(Lscala/collection/MapFactory;Lscala/collection/immutable/Seq;)Ljava/lang/Object;
   #82 = Utf8               this
   #83 = Utf8               Lscala/collection/immutable/Seq;
   #84 = Utf8               mapFactory
   #85 = Utf8               ()Lscala/collection/Factory;
   #86 = Utf8               <K:Ljava/lang/Object;V:Ljava/lang/Object;>()Lscala/collection/Factory<Lscala/Tuple2<TK;TV;>;Lscala/collection/immutable/OldHashMap<TK;TV;>;>;
   #87 = Utf8               mapFactory$
   #88 = Utf8               (Lscala/collection/MapFactory;)Lscala/collection/Factory;
   #89 = NameAndType        #87:#88       // mapFactory$:(Lscala/collection/MapFactory;)Lscala/collection/Factory;
   #90 = InterfaceMethodref #7.#89        // scala/collection/MapFactory.mapFactory$:(Lscala/collection/MapFactory;)Lscala/collection/Factory;
   #91 = Utf8               empty
   #92 = Utf8               ()Lscala/collection/immutable/OldHashMap;
   #93 = Utf8               <K:Ljava/lang/Object;V:Ljava/lang/Object;>()Lscala/collection/immutable/OldHashMap<TK;TV;>;
   #94 = Utf8               Lscala/collection/immutable/OldHashMap$EmptyOldHashMap$;
   #95 = NameAndType        #29:#94       // MODULE$:Lscala/collection/immutable/OldHashMap$EmptyOldHashMap$;
   #96 = Fieldref           #19.#95       // scala/collection/immutable/OldHashMap$EmptyOldHashMap$.MODULE$:Lscala/collection/immutable/OldHashMap$EmptyOldHashMap$;
   #97 = Utf8               from
   #98 = Utf8               (Lscala/collection/IterableOnce;)Lscala/collection/immutable/OldHashMap;
   #99 = Utf8               <K:Ljava/lang/Object;V:Ljava/lang/Object;>(Lscala/collection/IterableOnce<Lscala/Tuple2<TK;TV;>;>;)Lscala/collection/immutable/OldHashMap<TK;TV;>;
  #100 = Utf8               it
  #101 = Utf8               newBuilder
  #102 = Utf8               ()Lscala/collection/mutable/Builder;
  #103 = NameAndType        #101:#102     // newBuilder:()Lscala/collection/mutable/Builder;
  #104 = Methodref          #2.#103       // scala/collection/immutable/OldHashMap$.newBuilder:()Lscala/collection/mutable/Builder;
  #105 = Utf8               scala/collection/mutable/Builder
  #106 = Class              #105          // scala/collection/mutable/Builder
  #107 = Utf8               $plus$plus$eq
  #108 = Utf8               (Lscala/collection/IterableOnce;)Lscala/collection/mutable/Growable;
  #109 = NameAndType        #107:#108     // $plus$plus$eq:(Lscala/collection/IterableOnce;)Lscala/collection/mutable/Growable;
  #110 = InterfaceMethodref #106.#109     // scala/collection/mutable/Builder.$plus$plus$eq:(Lscala/collection/IterableOnce;)Lscala/collection/mutable/Growable;
  #111 = Utf8               result
  #112 = Utf8               ()Ljava/lang/Object;
  #113 = NameAndType        #111:#112     // result:()Ljava/lang/Object;
  #114 = InterfaceMethodref #106.#113     // scala/collection/mutable/Builder.result:()Ljava/lang/Object;
  #115 = Utf8               Lscala/collection/IterableOnce;
  #116 = Utf8               scala/collection/IterableOnce
  #117 = Class              #116          // scala/collection/IterableOnce
  #118 = Utf8               <K:Ljava/lang/Object;V:Ljava/lang/Object;>()Lscala/collection/mutable/Builder<Lscala/Tuple2<TK;TV;>;Lscala/collection/immutable/OldHashMap<TK;TV;>;>;
  #119 = Methodref          #15.#41       // scala/collection/immutable/OldHashMap$$anon$1."<init>":()V
  #120 = Utf8               scala$collection$immutable$OldHashMap$$liftMerger
  #121 = Utf8               <A1:Ljava/lang/Object;B1:Ljava/lang/Object;>(Lscala/Function2<Lscala/Tuple2<TA1;TB1;>;Lscala/Tuple2<TA1;TB1;>;Lscala/Tuple2<TA1;TB1;>;>;)Lscala/collection/immutable/OldHashMap$Merger<TA1;TB1;>;
  #122 = Utf8               mergef
  #123 = Utf8               Lscala/Function2;
  #124 = Utf8               (Lscala/Function2;)V
  #125 = NameAndType        #40:#124      // "<init>":(Lscala/Function2;)V
  #126 = Methodref          #17.#125      // scala/collection/immutable/OldHashMap$$anon$2."<init>":(Lscala/Function2;)V
  #127 = Utf8               scala$collection$immutable$OldHashMap$$makeHashTrieMap
  #128 = Utf8               (ILscala/collection/immutable/OldHashMap;ILscala/collection/immutable/OldHashMap;II)Lscala/collection/immutable/OldHashMap$HashTrieMap;
  #129 = Utf8               <A:Ljava/lang/Object;B:Ljava/lang/Object;>(ILscala/collection/immutable/OldHashMap<TA;TB;>;ILscala/collection/immutable/OldHashMap<TA;TB;>;II)Lscala/collection/immutable/OldHashMap$HashTrieMap<TA;TB;>;
  #130 = Utf8               hash0
  #131 = Utf8               elem0
  #132 = Utf8               hash1
  #133 = Utf8               elem1
  #134 = Utf8               level
  #135 = Utf8               size
  #136 = Utf8               (I[Lscala/collection/immutable/OldHashMap;I)V
  #137 = NameAndType        #40:#136      // "<init>":(I[Lscala/collection/immutable/OldHashMap;I)V
  #138 = Methodref          #24.#137      // scala/collection/immutable/OldHashMap$HashTrieMap."<init>":(I[Lscala/collection/immutable/OldHashMap;I)V
  #139 = NameAndType        #127:#128     // scala$collection$immutable$OldHashMap$$makeHashTrieMap:(ILscala/collection/immutable/OldHashMap;ILscala/collection/immutable/OldHashMap;II)Lscala/collection/immutable/OldHashMap$HashTrieMap;
  #140 = Methodref          #2.#139       // scala/collection/immutable/OldHashMap$.scala$collection$immutable$OldHashMap$$makeHashTrieMap:(ILscala/collection/immutable/OldHashMap;ILscala/collection/immutable/OldHashMap;II)Lscala/collection/immutable/OldHashMap$HashTrieMap;
  #141 = Utf8               bitmap
  #142 = Utf8               I
  #143 = Utf8               [Lscala/collection/immutable/OldHashMap;
  #144 = Utf8               index0
  #145 = Utf8               index1
  #146 = Utf8               Lscala/collection/immutable/OldHashMap;
  #147 = Class              #143          // "[Lscala/collection/immutable/OldHashMap;"
  #148 = Utf8               scala$collection$immutable$OldHashMap$$bufferSize
  #149 = Utf8               (I)I
  #150 = Utf8               scala/math/package$
  #151 = Class              #150          // scala/math/package$
  #152 = Utf8               Lscala/math/package$;
  #153 = NameAndType        #29:#152      // MODULE$:Lscala/math/package$;
  #154 = Fieldref           #151.#153     // scala/math/package$.MODULE$:Lscala/math/package$;
  #155 = Utf8               min
  #156 = Utf8               (II)I
  #157 = NameAndType        #155:#156     // min:(II)I
  #158 = Methodref          #151.#157     // scala/math/package$.min:(II)I
  #159 = Utf8               scala$collection$immutable$OldHashMap$$nullToEmpty
  #160 = Utf8               (Lscala/collection/immutable/OldHashMap;)Lscala/collection/immutable/OldHashMap;
  #161 = Utf8               <A:Ljava/lang/Object;B:Ljava/lang/Object;>(Lscala/collection/immutable/OldHashMap<TA;TB;>;)Lscala/collection/immutable/OldHashMap<TA;TB;>;
  #162 = Utf8               m
  #163 = NameAndType        #91:#92       // empty:()Lscala/collection/immutable/OldHashMap;
  #164 = Methodref          #2.#163       // scala/collection/immutable/OldHashMap$.empty:()Lscala/collection/immutable/OldHashMap;
  #165 = Utf8               writeObject
  #166 = Utf8               (Ljava/io/ObjectOutputStream;)V
  #167 = Utf8               out
  #168 = Utf8               Ljava/io/ObjectOutputStream;
  #169 = Utf8               readObject
  #170 = Utf8               (Ljava/io/ObjectInputStream;)V
  #171 = Utf8               in
  #172 = Utf8               Ljava/io/ObjectInputStream;
  #173 = Utf8               writeReplace
  #174 = Utf8               scala/runtime/ModuleSerializationProxy
  #175 = Class              #174          // scala/runtime/ModuleSerializationProxy
  #176 = Utf8               (Ljava/lang/Class;)V
  #177 = NameAndType        #40:#176      // "<init>":(Ljava/lang/Class;)V
  #178 = Methodref          #175.#177     // scala/runtime/ModuleSerializationProxy."<init>":(Ljava/lang/Class;)V
  #179 = Utf8               (Lscala/collection/IterableOnce;)Ljava/lang/Object;
  #180 = NameAndType        #97:#98       // from:(Lscala/collection/IterableOnce;)Lscala/collection/immutable/OldHashMap;
  #181 = Methodref          #2.#180       // scala/collection/immutable/OldHashMap$.from:(Lscala/collection/IterableOnce;)Lscala/collection/immutable/OldHashMap;
  #182 = Utf8               a
  #183 = Utf8               b
  #184 = Utf8               Lscala/Tuple2;
  #185 = Methodref          #5.#41        // java/lang/Object."<init>":()V
  #186 = Utf8               $deserializeLambda$
  #187 = Utf8               (Ljava/lang/invoke/SerializedLambda;)Ljava/lang/Object;
  #188 = Utf8               scala/runtime/LambdaDeserialize
  #189 = Class              #188          // scala/runtime/LambdaDeserialize
  #190 = Utf8               bootstrap
  #191 = Utf8               (Ljava/lang/invoke/MethodHandles$Lookup;Ljava/lang/String;Ljava/lang/invoke/MethodType;[Ljava/lang/invoke/MethodHandle;)Ljava/lang/invoke/CallSite;
  #192 = NameAndType        #190:#191     // bootstrap:(Ljava/lang/invoke/MethodHandles$Lookup;Ljava/lang/String;Ljava/lang/invoke/MethodType;[Ljava/lang/invoke/MethodHandle;)Ljava/lang/invoke/CallSite;
  #193 = Methodref          #189.#192     // scala/runtime/LambdaDeserialize.bootstrap:(Ljava/lang/invoke/MethodHandles$Lookup;Ljava/lang/String;Ljava/lang/invoke/MethodType;[Ljava/lang/invoke/MethodHandle;)Ljava/lang/invoke/CallSite;
  #194 = MethodHandle       6:#193        // REF_invokeStatic scala/runtime/LambdaDeserialize.bootstrap:(Ljava/lang/invoke/MethodHandles$Lookup;Ljava/lang/String;Ljava/lang/invoke/MethodType;[Ljava/lang/invoke/MethodHandle;)Ljava/lang/invoke/CallSite;
  #195 = Utf8               lambdaDeserialize
  #196 = NameAndType        #195:#187     // lambdaDeserialize:(Ljava/lang/invoke/SerializedLambda;)Ljava/lang/Object;
  #197 = InvokeDynamic      #1:#196       // #1:lambdaDeserialize:(Ljava/lang/invoke/SerializedLambda;)Ljava/lang/Object;
  #198 = Utf8               ConstantValue
  #199 = Utf8               Signature
  #200 = Utf8               Code
  #201 = Utf8               LineNumberTable
  #202 = Utf8               LocalVariableTable
  #203 = Utf8               MethodParameters
  #204 = Utf8               StackMapTable
  #205 = Utf8               InnerClasses
  #206 = Utf8               SourceFile
  #207 = Utf8               BootstrapMethods
  #208 = Utf8               ScalaInlineInfo
  #209 = Utf8               Scala
{
  public static final scala.collection.immutable.OldHashMap$ MODULE$;
    descriptor: Lscala/collection/immutable/OldHashMap$;
    flags: (0x0019) ACC_PUBLIC, ACC_STATIC, ACC_FINAL

  private static final long serialVersionUID;
    descriptor: J
    flags: (0x001a) ACC_PRIVATE, ACC_STATIC, ACC_FINAL
    ConstantValue: long 3l

  private static final scala.collection.immutable.OldHashMap$Merger<java.lang.Object, java.lang.Object> defaultMerger;
    descriptor: Lscala/collection/immutable/OldHashMap$Merger;
    flags: (0x001a) ACC_PRIVATE, ACC_STATIC, ACC_FINAL
    Signature: #37                          // Lscala/collection/immutable/OldHashMap$Merger<Ljava/lang/Object;Ljava/lang/Object;>;

  public static {};
    descriptor: ()V
    flags: (0x0009) ACC_PUBLIC, ACC_STATIC
    Code:
      stack=2, locals=0, args_size=0
         0: new           #2                  // class scala/collection/immutable/OldHashMap$
         3: dup
         4: invokespecial #42                 // Method "<init>":()V
         7: putstatic     #44                 // Field MODULE$:Lscala/collection/immutable/OldHashMap$;
        10: getstatic     #44                 // Field MODULE$:Lscala/collection/immutable/OldHashMap$;
        13: invokestatic  #48                 // InterfaceMethod scala/collection/MapFactory.$init$:(Lscala/collection/MapFactory;)V
        16: getstatic     #44                 // Field MODULE$:Lscala/collection/immutable/OldHashMap$;
        19: invokedynamic #69,  0             // InvokeDynamic #0:apply:()Lscala/Function2;
        24: invokespecial #73                 // Method liftMerger0:(Lscala/Function2;)Lscala/collection/immutable/OldHashMap$Merger;
        27: putstatic     #75                 // Field defaultMerger:Lscala/collection/immutable/OldHashMap$Merger;
        30: return
      LineNumberTable:
        line 114: 0
        line 139: 16
        line 114: 30

  public java.lang.Object apply(scala.collection.immutable.Seq);
    descriptor: (Lscala/collection/immutable/Seq;)Ljava/lang/Object;
    flags: (0x0001) ACC_PUBLIC
    Code:
      stack=2, locals=2, args_size=2
         0: aload_0
         1: aload_1
         2: invokestatic  #81                 // InterfaceMethod scala/collection/MapFactory.apply$:(Lscala/collection/MapFactory;Lscala/collection/immutable/Seq;)Ljava/lang/Object;
         5: areturn
      LineNumberTable:
        line 114: 0
      LocalVariableTable:
        Start  Length  Slot  Name   Signature
            0       6     0  this   Lscala/collection/immutable/OldHashMap$;
            0       6     1 elems   Lscala/collection/immutable/Seq;
    MethodParameters:
      Name                           Flags
      elems                          final

  public <K extends java.lang.Object, V extends java.lang.Object> scala.collection.Factory<scala.Tuple2<K, V>, scala.collection.immutable.OldHashMap<K, V>> mapFactory();
    descriptor: ()Lscala/collection/Factory;
    flags: (0x0001) ACC_PUBLIC
    Code:
      stack=1, locals=1, args_size=1
         0: aload_0
         1: invokestatic  #90                 // InterfaceMethod scala/collection/MapFactory.mapFactory$:(Lscala/collection/MapFactory;)Lscala/collection/Factory;
         4: areturn
      LineNumberTable:
        line 114: 0
      LocalVariableTable:
        Start  Length  Slot  Name   Signature
            0       5     0  this   Lscala/collection/immutable/OldHashMap$;
    Signature: #86                          // <K:Ljava/lang/Object;V:Ljava/lang/Object;>()Lscala/collection/Factory<Lscala/Tuple2<TK;TV;>;Lscala/collection/immutable/OldHashMap<TK;TV;>;>;

  public <K extends java.lang.Object, V extends java.lang.Object> scala.collection.immutable.OldHashMap<K, V> empty();
    descriptor: ()Lscala/collection/immutable/OldHashMap;
    flags: (0x0001) ACC_PUBLIC
    Code:
      stack=1, locals=1, args_size=1
         0: getstatic     #96                 // Field scala/collection/immutable/OldHashMap$EmptyOldHashMap$.MODULE$:Lscala/collection/immutable/OldHashMap$EmptyOldHashMap$;
         3: areturn
      LineNumberTable:
        line 116: 0
      LocalVariableTable:
        Start  Length  Slot  Name   Signature
            0       4     0  this   Lscala/collection/immutable/OldHashMap$;
    Signature: #93                          // <K:Ljava/lang/Object;V:Ljava/lang/Object;>()Lscala/collection/immutable/OldHashMap<TK;TV;>;

  public <K extends java.lang.Object, V extends java.lang.Object> scala.collection.immutable.OldHashMap<K, V> from(scala.collection.IterableOnce<scala.Tuple2<K, V>>);
    descriptor: (Lscala/collection/IterableOnce;)Lscala/collection/immutable/OldHashMap;
    flags: (0x0001) ACC_PUBLIC
    Code:
      stack=2, locals=5, args_size=2
         0: aload_1
         1: astore_3
         2: aload_3
         3: instanceof    #21                 // class scala/collection/immutable/OldHashMap
         6: ifeq          21
         9: aload_3
        10: checkcast     #21                 // class scala/collection/immutable/OldHashMap
        13: astore        4
        15: aload         4
        17: astore_2
        18: goto          49
        21: goto          24
        24: aload_0
        25: invokevirtual #104                // Method newBuilder:()Lscala/collection/mutable/Builder;
        28: aload_1
        29: invokeinterface #110,  2          // InterfaceMethod scala/collection/mutable/Builder.$plus$plus$eq:(Lscala/collection/IterableOnce;)Lscala/collection/mutable/Growable;
        34: checkcast     #106                // class scala/collection/mutable/Builder
        37: invokeinterface #114,  1          // InterfaceMethod scala/collection/mutable/Builder.result:()Ljava/lang/Object;
        42: checkcast     #21                 // class scala/collection/immutable/OldHashMap
        45: astore_2
        46: goto          49
        49: aload_2
        50: areturn
      StackMapTable: number_of_entries = 3
        frame_type = 253 /* append */
          offset_delta = 21
          locals = [ top, class scala/collection/IterableOnce ]
        frame_type = 2 /* same */
        frame_type = 255 /* full_frame */
          offset_delta = 24
          locals = [ class scala/collection/immutable/OldHashMap$, class scala/collection/IterableOnce, class scala/collection/immutable/OldHashMap, class scala/collection/IterableOnce ]
          stack = []
      LineNumberTable:
        line 119: 0
        line 120: 2
        line 121: 24
        line 119: 49
      LocalVariableTable:
        Start  Length  Slot  Name   Signature
            0      51     0  this   Lscala/collection/immutable/OldHashMap$;
            0      51     1    it   Lscala/collection/IterableOnce;
    Signature: #99                          // <K:Ljava/lang/Object;V:Ljava/lang/Object;>(Lscala/collection/IterableOnce<Lscala/Tuple2<TK;TV;>;>;)Lscala/collection/immutable/OldHashMap<TK;TV;>;
    MethodParameters:
      Name                           Flags
      it                             final

  public <K extends java.lang.Object, V extends java.lang.Object> scala.collection.mutable.Builder<scala.Tuple2<K, V>, scala.collection.immutable.OldHashMap<K, V>> newBuilder();
    descriptor: ()Lscala/collection/mutable/Builder;
    flags: (0x0001) ACC_PUBLIC
    Code:
      stack=2, locals=1, args_size=1
         0: new           #15                 // class scala/collection/immutable/OldHashMap$$anon$1
         3: dup
         4: invokespecial #119                // Method scala/collection/immutable/OldHashMap$$anon$1."<init>":()V
         7: areturn
      LineNumberTable:
        line 125: 0
      LocalVariableTable:
        Start  Length  Slot  Name   Signature
            0       8     0  this   Lscala/collection/immutable/OldHashMap$;
    Signature: #118                         // <K:Ljava/lang/Object;V:Ljava/lang/Object;>()Lscala/collection/mutable/Builder<Lscala/Tuple2<TK;TV;>;Lscala/collection/immutable/OldHashMap<TK;TV;>;>;

  public <A1 extends java.lang.Object, B1 extends java.lang.Object> scala.collection.immutable.OldHashMap$Merger<A1, B1> scala$collection$immutable$OldHashMap$$liftMerger(scala.Function2<scala.Tuple2<A1, B1>, scala.Tuple2<A1, B1>, scala.Tuple2<A1, B1>>);
    descriptor: (Lscala/Function2;)Lscala/collection/immutable/OldHashMap$Merger;
    flags: (0x0001) ACC_PUBLIC
    Code:
      stack=2, locals=2, args_size=2
         0: aload_1
         1: ifnonnull     10
         4: getstatic     #75                 // Field defaultMerger:Lscala/collection/immutable/OldHashMap$Merger;
         7: goto          15
        10: aload_0
        11: aload_1
        12: invokespecial #73                 // Method liftMerger0:(Lscala/Function2;)Lscala/collection/immutable/OldHashMap$Merger;
        15: areturn
      StackMapTable: number_of_entries = 2
        frame_type = 10 /* same */
        frame_type = 68 /* same_locals_1_stack_item */
          stack = [ class scala/collection/immutable/OldHashMap$Merger ]
      LineNumberTable:
        line 137: 0
      LocalVariableTable:
        Start  Length  Slot  Name   Signature
            0      16     0  this   Lscala/collection/immutable/OldHashMap$;
            0      16     1 mergef   Lscala/Function2;
    Signature: #121                         // <A1:Ljava/lang/Object;B1:Ljava/lang/Object;>(Lscala/Function2<Lscala/Tuple2<TA1;TB1;>;Lscala/Tuple2<TA1;TB1;>;Lscala/Tuple2<TA1;TB1;>;>;)Lscala/collection/immutable/OldHashMap$Merger<TA1;TB1;>;
    MethodParameters:
      Name                           Flags
      mergef                         final

  private <A1 extends java.lang.Object, B1 extends java.lang.Object> scala.collection.immutable.OldHashMap$Merger<A1, B1> liftMerger0(scala.Function2<scala.Tuple2<A1, B1>, scala.Tuple2<A1, B1>, scala.Tuple2<A1, B1>>);
    descriptor: (Lscala/Function2;)Lscala/collection/immutable/OldHashMap$Merger;
    flags: (0x0002) ACC_PRIVATE
    Code:
      stack=3, locals=2, args_size=2
         0: new           #17                 // class scala/collection/immutable/OldHashMap$$anon$2
         3: dup
         4: aload_1
         5: invokespecial #126                // Method scala/collection/immutable/OldHashMap$$anon$2."<init>":(Lscala/Function2;)V
         8: areturn
      LineNumberTable:
        line 141: 0
      LocalVariableTable:
        Start  Length  Slot  Name   Signature
            0       9     0  this   Lscala/collection/immutable/OldHashMap$;
            0       9     1 mergef   Lscala/Function2;
    Signature: #121                         // <A1:Ljava/lang/Object;B1:Ljava/lang/Object;>(Lscala/Function2<Lscala/Tuple2<TA1;TB1;>;Lscala/Tuple2<TA1;TB1;>;Lscala/Tuple2<TA1;TB1;>;>;)Lscala/collection/immutable/OldHashMap$Merger<TA1;TB1;>;
    MethodParameters:
      Name                           Flags
      mergef                         final

  public <A extends java.lang.Object, B extends java.lang.Object> scala.collection.immutable.OldHashMap$HashTrieMap<A, B> scala$collection$immutable$OldHashMap$$makeHashTrieMap(int, scala.collection.immutable.OldHashMap<A, B>, int, scala.collection.immutable.OldHashMap<A, B>, int, int);
    descriptor: (ILscala/collection/immutable/OldHashMap;ILscala/collection/immutable/OldHashMap;II)Lscala/collection/immutable/OldHashMap$HashTrieMap;
    flags: (0x0001) ACC_PUBLIC
    Code:
      stack=9, locals=13, args_size=7
         0: iload_1
         1: iload         5
         3: iushr
         4: bipush        31
         6: iand
         7: istore        7
         9: iload_3
        10: iload         5
        12: iushr
        13: bipush        31
        15: iand
        16: istore        8
        18: iload         7
        20: iload         8
        22: if_icmpeq     90
        25: iconst_1
        26: iload         7
        28: ishl
        29: iconst_1
        30: iload         8
        32: ishl
        33: ior
        34: istore        9
        36: iconst_2
        37: anewarray     #21                 // class scala/collection/immutable/OldHashMap
        40: astore        10
        42: iload         7
        44: iload         8
        46: if_icmpge     63
        49: aload         10
        51: iconst_0
        52: aload_2
        53: aastore
        54: aload         10
        56: iconst_1
        57: aload         4
        59: aastore
        60: goto          74
        63: aload         10
        65: iconst_0
        66: aload         4
        68: aastore
        69: aload         10
        71: iconst_1
        72: aload_2
        73: aastore
        74: new           #24                 // class scala/collection/immutable/OldHashMap$HashTrieMap
        77: dup
        78: iload         9
        80: aload         10
        82: iload         6
        84: invokespecial #138                // Method scala/collection/immutable/OldHashMap$HashTrieMap."<init>":(I[Lscala/collection/immutable/OldHashMap;I)V
        87: goto          134
        90: iconst_1
        91: anewarray     #21                 // class scala/collection/immutable/OldHashMap
        94: astore        11
        96: iconst_1
        97: iload         7
        99: ishl
       100: istore        12
       102: aload         11
       104: iconst_0
       105: aload_0
       106: iload_1
       107: aload_2
       108: iload_3
       109: aload         4
       111: iload         5
       113: iconst_5
       114: iadd
       115: iload         6
       117: invokevirtual #140                // Method scala$collection$immutable$OldHashMap$$makeHashTrieMap:(ILscala/collection/immutable/OldHashMap;ILscala/collection/immutable/OldHashMap;II)Lscala/collection/immutable/OldHashMap$HashTrieMap;
       120: aastore
       121: new           #24                 // class scala/collection/immutable/OldHashMap$HashTrieMap
       124: dup
       125: iload         12
       127: aload         11
       129: iload         6
       131: invokespecial #138                // Method scala/collection/immutable/OldHashMap$HashTrieMap."<init>":(I[Lscala/collection/immutable/OldHashMap;I)V
       134: areturn
      StackMapTable: number_of_entries = 4
        frame_type = 255 /* full_frame */
          offset_delta = 63
          locals = [ class scala/collection/immutable/OldHashMap$, int, class scala/collection/immutable/OldHashMap, int, class scala/collection/immutable/OldHashMap, int, int, int, int, int, class "[Lscala/collection/immutable/OldHashMap;" ]
          stack = []
        frame_type = 10 /* same */
        frame_type = 249 /* chop */
          offset_delta = 15
        frame_type = 107 /* same_locals_1_stack_item */
          stack = [ class scala/collection/immutable/OldHashMap$HashTrieMap ]
      LineNumberTable:
        line 152: 0
        line 153: 9
        line 154: 18
        line 155: 25
        line 156: 36
        line 157: 42
        line 158: 49
        line 159: 54
        line 161: 63
        line 162: 69
        line 164: 74
        line 166: 90
        line 167: 96
        line 168: 102
        line 169: 121
      LocalVariableTable:
        Start  Length  Slot  Name   Signature
           36      51     9 bitmap   I
           42      45    10 elems   [Lscala/collection/immutable/OldHashMap;
           96      38    11 elems   [Lscala/collection/immutable/OldHashMap;
          102      32    12 bitmap   I
            9     125     7 index0   I
           18     116     8 index1   I
            0     135     0  this   Lscala/collection/immutable/OldHashMap$;
            0     135     1 hash0   I
            0     135     2 elem0   Lscala/collection/immutable/OldHashMap;
            0     135     3 hash1   I
            0     135     4 elem1   Lscala/collection/immutable/OldHashMap;
            0     135     5 level   I
            0     135     6  size   I
    Signature: #129                         // <A:Ljava/lang/Object;B:Ljava/lang/Object;>(ILscala/collection/immutable/OldHashMap<TA;TB;>;ILscala/collection/immutable/OldHashMap<TA;TB;>;II)Lscala/collection/immutable/OldHashMap$HashTrieMap<TA;TB;>;
    MethodParameters:
      Name                           Flags
      hash0                          final
      elem0                          final
      hash1                          final
      elem1                          final
      level                          final
      size                           final

  public int scala$collection$immutable$OldHashMap$$bufferSize(int);
    descriptor: (I)I
    flags: (0x0001) ACC_PUBLIC
    Code:
      stack=3, locals=2, args_size=2
         0: getstatic     #154                // Field scala/math/package$.MODULE$:Lscala/math/package$;
         3: iload_1
         4: bipush        6
         6: iadd
         7: sipush        224
        10: invokevirtual #158                // Method scala/math/package$.min:(II)I
        13: ireturn
      LineNumberTable:
        line 178: 0
      LocalVariableTable:
        Start  Length  Slot  Name   Signature
            0      14     0  this   Lscala/collection/immutable/OldHashMap$;
            0      14     1  size   I
    MethodParameters:
      Name                           Flags
      size                           final

  public <A extends java.lang.Object, B extends java.lang.Object> scala.collection.immutable.OldHashMap<A, B> scala$collection$immutable$OldHashMap$$nullToEmpty(scala.collection.immutable.OldHashMap<A, B>);
    descriptor: (Lscala/collection/immutable/OldHashMap;)Lscala/collection/immutable/OldHashMap;
    flags: (0x0001) ACC_PUBLIC
    Code:
      stack=1, locals=2, args_size=2
         0: aload_1
         1: ifnonnull     11
         4: aload_0
         5: invokevirtual #164                // Method empty:()Lscala/collection/immutable/OldHashMap;
         8: goto          12
        11: aload_1
        12: areturn
      StackMapTable: number_of_entries = 2
        frame_type = 11 /* same */
        frame_type = 64 /* same_locals_1_stack_item */
          stack = [ class scala/collection/immutable/OldHashMap ]
      LineNumberTable:
        line 184: 0
      LocalVariableTable:
        Start  Length  Slot  Name   Signature
            0      13     0  this   Lscala/collection/immutable/OldHashMap$;
            0      13     1     m   Lscala/collection/immutable/OldHashMap;
    Signature: #161                         // <A:Ljava/lang/Object;B:Ljava/lang/Object;>(Lscala/collection/immutable/OldHashMap<TA;TB;>;)Lscala/collection/immutable/OldHashMap<TA;TB;>;
    MethodParameters:
      Name                           Flags
      m                              final

  private void writeObject(java.io.ObjectOutputStream);
    descriptor: (Ljava/io/ObjectOutputStream;)V
    flags: (0x0002) ACC_PRIVATE
    Code:
      stack=0, locals=2, args_size=2
         0: return
      LineNumberTable:
        line 591: 0
      LocalVariableTable:
        Start  Length  Slot  Name   Signature
            0       1     0  this   Lscala/collection/immutable/OldHashMap$;
            0       1     1   out   Ljava/io/ObjectOutputStream;
    MethodParameters:
      Name                           Flags
      out                            final

  private void readObject(java.io.ObjectInputStream);
    descriptor: (Ljava/io/ObjectInputStream;)V
    flags: (0x0002) ACC_PRIVATE
    Code:
      stack=0, locals=2, args_size=2
         0: return
      LineNumberTable:
        line 592: 0
      LocalVariableTable:
        Start  Length  Slot  Name   Signature
            0       1     0  this   Lscala/collection/immutable/OldHashMap$;
            0       1     1    in   Ljava/io/ObjectInputStream;
    MethodParameters:
      Name                           Flags
      in                             final

  private java.lang.Object writeReplace();
    descriptor: ()Ljava/lang/Object;
    flags: (0x0002) ACC_PRIVATE
    Code:
      stack=3, locals=1, args_size=1
         0: new           #175                // class scala/runtime/ModuleSerializationProxy
         3: dup
         4: ldc           #2                  // class scala/collection/immutable/OldHashMap$
         6: invokespecial #178                // Method scala/runtime/ModuleSerializationProxy."<init>":(Ljava/lang/Class;)V
         9: areturn
      LineNumberTable:
        line 114: 0
      LocalVariableTable:
        Start  Length  Slot  Name   Signature
            0      10     0  this   Lscala/collection/immutable/OldHashMap$;

  public java.lang.Object from(scala.collection.IterableOnce);
    descriptor: (Lscala/collection/IterableOnce;)Ljava/lang/Object;
    flags: (0x1041) ACC_PUBLIC, ACC_BRIDGE, ACC_SYNTHETIC
    Code:
      stack=2, locals=2, args_size=2
         0: aload_0
         1: aload_1
         2: invokevirtual #181                // Method from:(Lscala/collection/IterableOnce;)Lscala/collection/immutable/OldHashMap;
         5: areturn
      LineNumberTable:
        line 114: 0
      LocalVariableTable:
        Start  Length  Slot  Name   Signature
            0       6     0  this   Lscala/collection/immutable/OldHashMap$;
            0       6     1    it   Lscala/collection/IterableOnce;
    MethodParameters:
      Name                           Flags
      it                             final

  public java.lang.Object empty();
    descriptor: ()Ljava/lang/Object;
    flags: (0x1041) ACC_PUBLIC, ACC_BRIDGE, ACC_SYNTHETIC
    Code:
      stack=1, locals=1, args_size=1
         0: aload_0
         1: invokevirtual #164                // Method empty:()Lscala/collection/immutable/OldHashMap;
         4: areturn
      LineNumberTable:
        line 114: 0
      LocalVariableTable:
        Start  Length  Slot  Name   Signature
            0       5     0  this   Lscala/collection/immutable/OldHashMap$;

  public static final scala.Tuple2 $anonfun$defaultMerger$1(scala.Tuple2, scala.Tuple2);
    descriptor: (Lscala/Tuple2;Lscala/Tuple2;)Lscala/Tuple2;
    flags: (0x1019) ACC_PUBLIC, ACC_STATIC, ACC_FINAL, ACC_SYNTHETIC
    Code:
      stack=1, locals=2, args_size=2
         0: aload_0
         1: areturn
      LineNumberTable:
        line 139: 0
      LocalVariableTable:
        Start  Length  Slot  Name   Signature
            0       2     0     a   Lscala/Tuple2;
            0       2     1     b   Lscala/Tuple2;
    MethodParameters:
      Name                           Flags
      a                              final
      b                              final

  private scala.collection.immutable.OldHashMap$();
    descriptor: ()V
    flags: (0x0002) ACC_PRIVATE
    Code:
      stack=1, locals=1, args_size=1
         0: aload_0
         1: invokespecial #185                // Method java/lang/Object."<init>":()V
         4: return
      LineNumberTable:
        line 114: 0
      LocalVariableTable:
        Start  Length  Slot  Name   Signature
            0       5     0  this   Lscala/collection/immutable/OldHashMap$;

  private static java.lang.Object $deserializeLambda$(java.lang.invoke.SerializedLambda);
    descriptor: (Ljava/lang/invoke/SerializedLambda;)Ljava/lang/Object;
    flags: (0x100a) ACC_PRIVATE, ACC_STATIC, ACC_SYNTHETIC
    Code:
      stack=1, locals=1, args_size=1
         0: aload_0
         1: invokedynamic #197,  0            // InvokeDynamic #1:lambdaDeserialize:(Ljava/lang/invoke/SerializedLambda;)Ljava/lang/Object;
         6: areturn
}
InnerClasses:
  public static final #13= #10 of #12;    // Lookup=class java/lang/invoke/MethodHandles$Lookup of class java/lang/invoke/MethodHandles
  public final #15;                       // class scala/collection/immutable/OldHashMap$$anon$1
  public final #17;                       // class scala/collection/immutable/OldHashMap$$anon$2
  private static #22= #19 of #21;         // EmptyOldHashMap$=class scala/collection/immutable/OldHashMap$EmptyOldHashMap$ of class scala/collection/immutable/OldHashMap
  public static final #25= #24 of #21;    // HashTrieMap=class scala/collection/immutable/OldHashMap$HashTrieMap of class scala/collection/immutable/OldHashMap
  public static abstract #28= #27 of #21; // Merger=class scala/collection/immutable/OldHashMap$Merger of class scala/collection/immutable/OldHashMap
Signature: #3                           // Ljava/lang/Object;Lscala/collection/MapFactory<Lscala/collection/immutable/OldHashMap;>;
SourceFile: "OldHashMap.scala"
BootstrapMethods:
  0: #65 REF_invokeStatic java/lang/invoke/LambdaMetafactory.altMetafactory:(Ljava/lang/invoke/MethodHandles$Lookup;Ljava/lang/String;Ljava/lang/invoke/MethodType;[Ljava/lang/Object;)Ljava/lang/invoke/CallSite;
    Method arguments:
      #50 (Ljava/lang/Object;Ljava/lang/Object;)Ljava/lang/Object;
      #55 REF_invokeStatic scala/collection/immutable/OldHashMap$.$anonfun$defaultMerger$1:(Lscala/Tuple2;Lscala/Tuple2;)Lscala/Tuple2;
      #56 (Lscala/Tuple2;Lscala/Tuple2;)Lscala/Tuple2;
      #57 5
      #58 1
      #56 (Lscala/Tuple2;Lscala/Tuple2;)Lscala/Tuple2;
  1: #194 REF_invokeStatic scala/runtime/LambdaDeserialize.bootstrap:(Ljava/lang/invoke/MethodHandles$Lookup;Ljava/lang/String;Ljava/lang/invoke/MethodType;[Ljava/lang/invoke/MethodHandle;)Ljava/lang/invoke/CallSite;
    Method arguments:
      #55 REF_invokeStatic scala/collection/immutable/OldHashMap$.$anonfun$defaultMerger$1:(Lscala/Tuple2;Lscala/Tuple2;)Lscala/Tuple2;
  ScalaInlineInfo: length = 0x59 (unknown attribute)
   01 01 00 11 00 33 00 34 01 00 28 00 27 01 00 42
   00 4C 01 00 5B 00 70 01 00 5B 00 5C 01 00 61 00
   B3 01 00 61 00 62 01 00 46 00 47 01 00 54 00 55
   01 00 65 00 66 01 00 A9 00 AA 01 00 94 00 95 05
   00 78 00 47 01 00 7F 00 80 01 00 9F 00 A0 05 00
   A5 00 A6 01 00 AD 00 70 01
  Scala: length = 0x0 (unknown attribute)

