Classfile /Users/mw/Projects/slang-braindump/.jar/jar11/assemble/slang-braindump/assemble/content/scala/collection/immutable/OldHashMap$HashTrieMap$$anon$4.class
  Last modified May 29, 2022; size 1525 bytes
  SHA-256 checksum 4659f175bd156664d93946145a68c83c4e1956166da5ba2470a3f4c186c153c1
  Compiled from "OldHashMap.scala"
public final class scala.collection.immutable.OldHashMap$HashTrieMap$$anon$4 extends scala.collection.immutable.TrieIterator<scala.Tuple2<K, V>>
  minor version: 0
  major version: 52
  flags: (0x0031) ACC_PUBLIC, ACC_FINAL, ACC_SUPER
  this_class: #2                          // scala/collection/immutable/OldHashMap$HashTrieMap$$anon$4
  super_class: #5                         // scala/collection/immutable/TrieIterator
  interfaces: 0, fields: 0, methods: 3, attributes: 6
Constant pool:
   #1 = Utf8               scala/collection/immutable/OldHashMap$HashTrieMap$$anon$4
   #2 = Class              #1             // scala/collection/immutable/OldHashMap$HashTrieMap$$anon$4
   #3 = Utf8               Lscala/collection/immutable/TrieIterator<Lscala/Tuple2<TK;TV;>;>;
   #4 = Utf8               scala/collection/immutable/TrieIterator
   #5 = Class              #4             // scala/collection/immutable/TrieIterator
   #6 = Utf8               OldHashMap.scala
   #7 = Utf8               scala/collection/immutable/OldHashMap$HashTrieMap
   #8 = Class              #7             // scala/collection/immutable/OldHashMap$HashTrieMap
   #9 = Utf8               iterator
  #10 = Utf8               ()Lscala/collection/Iterator;
  #11 = NameAndType        #9:#10         // iterator:()Lscala/collection/Iterator;
  #12 = Utf8               scala/collection/immutable/OldHashMap
  #13 = Class              #12            // scala/collection/immutable/OldHashMap
  #14 = Utf8               HashTrieMap
  #15 = Utf8               scala/collection/immutable/OldHashMap$OldHashMap1
  #16 = Class              #15            // scala/collection/immutable/OldHashMap$OldHashMap1
  #17 = Utf8               OldHashMap1
  #18 = Utf8               getElem
  #19 = Utf8               (Ljava/lang/Object;)Lscala/Tuple2;
  #20 = Utf8               (Ljava/lang/Object;)Lscala/Tuple2<TK;TV;>;
  #21 = Utf8               cc
  #22 = Utf8               ensurePair
  #23 = Utf8               ()Lscala/Tuple2;
  #24 = NameAndType        #22:#23        // ensurePair:()Lscala/Tuple2;
  #25 = Methodref          #16.#24        // scala/collection/immutable/OldHashMap$OldHashMap1.ensurePair:()Lscala/Tuple2;
  #26 = Utf8               this
  #27 = Utf8               Lscala/collection/immutable/OldHashMap$HashTrieMap$$anon$4;
  #28 = Utf8               Ljava/lang/Object;
  #29 = Utf8               (Ljava/lang/Object;)Ljava/lang/Object;
  #30 = Utf8               x
  #31 = NameAndType        #18:#19        // getElem:(Ljava/lang/Object;)Lscala/Tuple2;
  #32 = Methodref          #2.#31         // scala/collection/immutable/OldHashMap$HashTrieMap$$anon$4.getElem:(Ljava/lang/Object;)Lscala/Tuple2;
  #33 = Utf8               <init>
  #34 = Utf8               (Lscala/collection/immutable/OldHashMap$HashTrieMap;)V
  #35 = Utf8               $outer
  #36 = Utf8               elems
  #37 = Utf8               ()[Lscala/collection/immutable/OldHashMap;
  #38 = NameAndType        #36:#37        // elems:()[Lscala/collection/immutable/OldHashMap;
  #39 = Methodref          #8.#38         // scala/collection/immutable/OldHashMap$HashTrieMap.elems:()[Lscala/collection/immutable/OldHashMap;
  #40 = Utf8               [Lscala/collection/immutable/Iterable;
  #41 = Class              #40            // "[Lscala/collection/immutable/Iterable;"
  #42 = Utf8               ([Lscala/collection/immutable/Iterable;)V
  #43 = NameAndType        #33:#42        // "<init>":([Lscala/collection/immutable/Iterable;)V
  #44 = Methodref          #5.#43         // scala/collection/immutable/TrieIterator."<init>":([Lscala/collection/immutable/Iterable;)V
  #45 = Utf8               Lscala/collection/immutable/OldHashMap$HashTrieMap;
  #46 = Utf8               Code
  #47 = Utf8               LineNumberTable
  #48 = Utf8               LocalVariableTable
  #49 = Utf8               Signature
  #50 = Utf8               MethodParameters
  #51 = Utf8               InnerClasses
  #52 = Utf8               EnclosingMethod
  #53 = Utf8               SourceFile
  #54 = Utf8               ScalaInlineInfo
  #55 = Utf8               Scala
{
  public final scala.Tuple2<K, V> getElem(java.lang.Object);
    descriptor: (Ljava/lang/Object;)Lscala/Tuple2;
    flags: (0x0011) ACC_PUBLIC, ACC_FINAL
    Code:
      stack=1, locals=2, args_size=2
         0: aload_1
         1: checkcast     #16                 // class scala/collection/immutable/OldHashMap$OldHashMap1
         4: invokevirtual #25                 // Method scala/collection/immutable/OldHashMap$OldHashMap1.ensurePair:()Lscala/Tuple2;
         7: areturn
      LineNumberTable:
        line 491: 0
      LocalVariableTable:
        Start  Length  Slot  Name   Signature
            0       8     0  this   Lscala/collection/immutable/OldHashMap$HashTrieMap$$anon$4;
            0       8     1    cc   Ljava/lang/Object;
    Signature: #20                          // (Ljava/lang/Object;)Lscala/Tuple2<TK;TV;>;
    MethodParameters:
      Name                           Flags
      cc                             final

  public final java.lang.Object getElem(java.lang.Object);
    descriptor: (Ljava/lang/Object;)Ljava/lang/Object;
    flags: (0x1051) ACC_PUBLIC, ACC_FINAL, ACC_BRIDGE, ACC_SYNTHETIC
    Code:
      stack=2, locals=2, args_size=2
         0: aload_0
         1: aload_1
         2: invokevirtual #32                 // Method getElem:(Ljava/lang/Object;)Lscala/Tuple2;
         5: areturn
      LineNumberTable:
        line 490: 0
      LocalVariableTable:
        Start  Length  Slot  Name   Signature
            0       6     0  this   Lscala/collection/immutable/OldHashMap$HashTrieMap$$anon$4;
            0       6     1     x   Ljava/lang/Object;
    MethodParameters:
      Name                           Flags
      x                              final

  public scala.collection.immutable.OldHashMap$HashTrieMap$$anon$4(scala.collection.immutable.OldHashMap$HashTrieMap);
    descriptor: (Lscala/collection/immutable/OldHashMap$HashTrieMap;)V
    flags: (0x0001) ACC_PUBLIC
    Code:
      stack=2, locals=2, args_size=2
         0: aload_0
         1: aload_1
         2: invokevirtual #39                 // Method scala/collection/immutable/OldHashMap$HashTrieMap.elems:()[Lscala/collection/immutable/OldHashMap;
         5: checkcast     #41                 // class "[Lscala/collection/immutable/Iterable;"
         8: invokespecial #44                 // Method scala/collection/immutable/TrieIterator."<init>":([Lscala/collection/immutable/Iterable;)V
        11: return
      LineNumberTable:
        line 490: 0
      LocalVariableTable:
        Start  Length  Slot  Name   Signature
            0      12     0  this   Lscala/collection/immutable/OldHashMap$HashTrieMap$$anon$4;
            0      12     1 $outer   Lscala/collection/immutable/OldHashMap$HashTrieMap;
    MethodParameters:
      Name                           Flags
      $outer                         final synthetic
}
InnerClasses:
  public static final #14= #8 of #13;     // HashTrieMap=class scala/collection/immutable/OldHashMap$HashTrieMap of class scala/collection/immutable/OldHashMap
  public final #2;                        // class scala/collection/immutable/OldHashMap$HashTrieMap$$anon$4
  public static final #17= #16 of #13;    // OldHashMap1=class scala/collection/immutable/OldHashMap$OldHashMap1 of class scala/collection/immutable/OldHashMap
EnclosingMethod: #8.#11                 // scala.collection.immutable.OldHashMap$HashTrieMap.iterator
Signature: #3                           // Lscala/collection/immutable/TrieIterator<Lscala/Tuple2<TK;TV;>;>;
SourceFile: "OldHashMap.scala"
  ScalaInlineInfo: length = 0x13 (unknown attribute)
   01 01 00 03 00 21 00 22 01 00 12 00 1D 01 00 12
   00 13 01
  Scala: length = 0x0 (unknown attribute)

