Classfile /Users/mw/Projects/slang-braindump/.jar/jar11/assemble/slang-braindump/assemble/content/scala/collection/immutable/OldHashSet$OldHashSetCollision1.class
  Last modified May 29, 2022; size 9732 bytes
  SHA-256 checksum 62f665ba321a5d293771493406845149c152769085501fb474e77516694d536a
  Compiled from "OldHashSet.scala"
public final class scala.collection.immutable.OldHashSet$OldHashSetCollision1<A extends java.lang.Object> extends scala.collection.immutable.OldHashSet$LeafOldHashSet<A>
  minor version: 0
  major version: 52
  flags: (0x0031) ACC_PUBLIC, ACC_FINAL, ACC_SUPER
  this_class: #2                          // scala/collection/immutable/OldHashSet$OldHashSetCollision1
  super_class: #5                         // scala/collection/immutable/OldHashSet$LeafOldHashSet
  interfaces: 0, fields: 2, methods: 25, attributes: 6
Constant pool:
    #1 = Utf8               scala/collection/immutable/OldHashSet$OldHashSetCollision1
    #2 = Class              #1            // scala/collection/immutable/OldHashSet$OldHashSetCollision1
    #3 = Utf8               <A:Ljava/lang/Object;>Lscala/collection/immutable/OldHashSet$LeafOldHashSet<TA;>;
    #4 = Utf8               scala/collection/immutable/OldHashSet$LeafOldHashSet
    #5 = Class              #4            // scala/collection/immutable/OldHashSet$LeafOldHashSet
    #6 = Utf8               OldHashSet.scala
    #7 = Utf8               java/lang/invoke/MethodHandles$Lookup
    #8 = Class              #7            // java/lang/invoke/MethodHandles$Lookup
    #9 = Utf8               java/lang/invoke/MethodHandles
   #10 = Class              #9            // java/lang/invoke/MethodHandles
   #11 = Utf8               Lookup
   #12 = Utf8               scala/collection/immutable/OldHashSet$HashTrieSet
   #13 = Class              #12           // scala/collection/immutable/OldHashSet$HashTrieSet
   #14 = Utf8               scala/collection/immutable/OldHashSet
   #15 = Class              #14           // scala/collection/immutable/OldHashSet
   #16 = Utf8               HashTrieSet
   #17 = Utf8               LeafOldHashSet
   #18 = Utf8               scala/collection/immutable/OldHashSet$OldHashSet1
   #19 = Class              #18           // scala/collection/immutable/OldHashSet$OldHashSet1
   #20 = Utf8               OldHashSet1
   #21 = Utf8               OldHashSetCollision1
   #22 = Utf8               hash
   #23 = Utf8               I
   #24 = Utf8               ks
   #25 = Utf8               Lscala/collection/immutable/ListSet;
   #26 = Utf8               Lscala/collection/immutable/ListSet<TA;>;
   #27 = Utf8               ()I
   #28 = NameAndType        #22:#23       // hash:I
   #29 = Fieldref           #2.#28        // scala/collection/immutable/OldHashSet$OldHashSetCollision1.hash:I
   #30 = Utf8               this
   #31 = Utf8               Lscala/collection/immutable/OldHashSet$OldHashSetCollision1;
   #32 = Utf8               ()Lscala/collection/immutable/ListSet;
   #33 = Utf8               ()Lscala/collection/immutable/ListSet<TA;>;
   #34 = NameAndType        #24:#25       // ks:Lscala/collection/immutable/ListSet;
   #35 = Fieldref           #2.#34        // scala/collection/immutable/OldHashSet$OldHashSetCollision1.ks:Lscala/collection/immutable/ListSet;
   #36 = Utf8               isEmpty
   #37 = Utf8               ()Z
   #38 = Utf8               size
   #39 = NameAndType        #24:#32       // ks:()Lscala/collection/immutable/ListSet;
   #40 = Methodref          #2.#39        // scala/collection/immutable/OldHashSet$OldHashSetCollision1.ks:()Lscala/collection/immutable/ListSet;
   #41 = Utf8               scala/collection/immutable/ListSet
   #42 = Class              #41           // scala/collection/immutable/ListSet
   #43 = NameAndType        #38:#27       // size:()I
   #44 = Methodref          #42.#43       // scala/collection/immutable/ListSet.size:()I
   #45 = Utf8               iterator
   #46 = Utf8               ()Lscala/collection/Iterator;
   #47 = Utf8               ()Lscala/collection/Iterator<TA;>;
   #48 = NameAndType        #45:#46       // iterator:()Lscala/collection/Iterator;
   #49 = Methodref          #42.#48       // scala/collection/immutable/ListSet.iterator:()Lscala/collection/Iterator;
   #50 = Utf8               foreach
   #51 = Utf8               (Lscala/Function1;)V
   #52 = Utf8               <U:Ljava/lang/Object;>(Lscala/Function1<TA;TU;>;)V
   #53 = Utf8               f
   #54 = NameAndType        #50:#51       // foreach:(Lscala/Function1;)V
   #55 = Methodref          #42.#54       // scala/collection/immutable/ListSet.foreach:(Lscala/Function1;)V
   #56 = Utf8               Lscala/Function1;
   #57 = Utf8               get0
   #58 = Utf8               (Ljava/lang/Object;II)Z
   #59 = Utf8               (TA;II)Z
   #60 = Utf8               key
   #61 = Utf8               level
   #62 = NameAndType        #22:#27       // hash:()I
   #63 = Methodref          #2.#62        // scala/collection/immutable/OldHashSet$OldHashSetCollision1.hash:()I
   #64 = Utf8               contains
   #65 = Utf8               (Ljava/lang/Object;)Z
   #66 = NameAndType        #64:#65       // contains:(Ljava/lang/Object;)Z
   #67 = Methodref          #42.#66       // scala/collection/immutable/ListSet.contains:(Ljava/lang/Object;)Z
   #68 = Utf8               Ljava/lang/Object;
   #69 = Utf8               updated0
   #70 = Utf8               (Ljava/lang/Object;II)Lscala/collection/immutable/OldHashSet;
   #71 = Utf8               (TA;II)Lscala/collection/immutable/OldHashSet<TA;>;
   #72 = Utf8               $plus
   #73 = Utf8               (Ljava/lang/Object;)Lscala/collection/immutable/SetOps;
   #74 = NameAndType        #72:#73       // $plus:(Ljava/lang/Object;)Lscala/collection/immutable/SetOps;
   #75 = Methodref          #42.#74       // scala/collection/immutable/ListSet.$plus:(Ljava/lang/Object;)Lscala/collection/immutable/SetOps;
   #76 = Utf8               <init>
   #77 = Utf8               (ILscala/collection/immutable/ListSet;)V
   #78 = NameAndType        #76:#77       // "<init>":(ILscala/collection/immutable/ListSet;)V
   #79 = Methodref          #2.#78        // scala/collection/immutable/OldHashSet$OldHashSetCollision1."<init>":(ILscala/collection/immutable/ListSet;)V
   #80 = Utf8               scala/collection/immutable/OldHashSet$
   #81 = Class              #80           // scala/collection/immutable/OldHashSet$
   #82 = Utf8               MODULE$
   #83 = Utf8               Lscala/collection/immutable/OldHashSet$;
   #84 = NameAndType        #82:#83       // MODULE$:Lscala/collection/immutable/OldHashSet$;
   #85 = Fieldref           #81.#84       // scala/collection/immutable/OldHashSet$.MODULE$:Lscala/collection/immutable/OldHashSet$;
   #86 = Utf8               (Ljava/lang/Object;I)V
   #87 = NameAndType        #76:#86       // "<init>":(Ljava/lang/Object;I)V
   #88 = Methodref          #19.#87       // scala/collection/immutable/OldHashSet$OldHashSet1."<init>":(Ljava/lang/Object;I)V
   #89 = Utf8               scala$collection$immutable$OldHashSet$$makeHashTrieSet
   #90 = Utf8               (ILscala/collection/immutable/OldHashSet;ILscala/collection/immutable/OldHashSet;I)Lscala/collection/immutable/OldHashSet$HashTrieSet;
   #91 = NameAndType        #89:#90       // scala$collection$immutable$OldHashSet$$makeHashTrieSet:(ILscala/collection/immutable/OldHashSet;ILscala/collection/immutable/OldHashSet;I)Lscala/collection/immutable/OldHashSet$HashTrieSet;
   #92 = Methodref          #81.#91       // scala/collection/immutable/OldHashSet$.scala$collection$immutable$OldHashSet$$makeHashTrieSet:(ILscala/collection/immutable/OldHashSet;ILscala/collection/immutable/OldHashSet;I)Lscala/collection/immutable/OldHashSet$HashTrieSet;
   #93 = Utf8               removed0
   #94 = Utf8               $minus
   #95 = NameAndType        #94:#73       // $minus:(Ljava/lang/Object;)Lscala/collection/immutable/SetOps;
   #96 = Methodref          #42.#95       // scala/collection/immutable/ListSet.$minus:(Ljava/lang/Object;)Lscala/collection/immutable/SetOps;
   #97 = Utf8               head
   #98 = Utf8               ()Ljava/lang/Object;
   #99 = NameAndType        #97:#98       // head:()Ljava/lang/Object;
  #100 = Methodref          #42.#99       // scala/collection/immutable/ListSet.head:()Ljava/lang/Object;
  #101 = Utf8               ks1
  #102 = Utf8               writeObject
  #103 = Utf8               (Ljava/io/ObjectOutputStream;)V
  #104 = Utf8               out
  #105 = Utf8               scala/sys/package$
  #106 = Class              #105          // scala/sys/package$
  #107 = Utf8               Lscala/sys/package$;
  #108 = NameAndType        #82:#107      // MODULE$:Lscala/sys/package$;
  #109 = Fieldref           #106.#108     // scala/sys/package$.MODULE$:Lscala/sys/package$;
  #110 = Utf8               cannot serialize an immutable.OldHashSet where all items have the same 32-bit hash code
  #111 = String             #110          // cannot serialize an immutable.OldHashSet where all items have the same 32-bit hash code
  #112 = Utf8               error
  #113 = Utf8               (Ljava/lang/String;)Lscala/runtime/Nothing$;
  #114 = NameAndType        #112:#113     // error:(Ljava/lang/String;)Lscala/runtime/Nothing$;
  #115 = Methodref          #106.#114     // scala/sys/package$.error:(Ljava/lang/String;)Lscala/runtime/Nothing$;
  #116 = Utf8               Ljava/io/ObjectOutputStream;
  #117 = Utf8               readObject
  #118 = Utf8               (Ljava/io/ObjectInputStream;)V
  #119 = Utf8               in
  #120 = Utf8               cannot deserialize an immutable.OldHashSet where all items have the same 32-bit hash code
  #121 = String             #120          // cannot deserialize an immutable.OldHashSet where all items have the same 32-bit hash code
  #122 = Utf8               Ljava/io/ObjectInputStream;
  #123 = Utf8               filter0
  #124 = Utf8               (Lscala/Function1;ZI[Lscala/collection/immutable/OldHashSet;I)Lscala/collection/immutable/OldHashSet;
  #125 = Utf8               (Lscala/Function1<TA;Ljava/lang/Object;>;ZI[Lscala/collection/immutable/OldHashSet<TA;>;I)Lscala/collection/immutable/OldHashSet<TA;>;
  #126 = Utf8               p
  #127 = Utf8               negate
  #128 = Utf8               buffer
  #129 = Utf8               offset0
  #130 = Utf8               filterNot
  #131 = Utf8               (Lscala/Function1;)Ljava/lang/Object;
  #132 = NameAndType        #130:#131     // filterNot:(Lscala/Function1;)Ljava/lang/Object;
  #133 = Methodref          #42.#132      // scala/collection/immutable/ListSet.filterNot:(Lscala/Function1;)Ljava/lang/Object;
  #134 = Utf8               filter
  #135 = NameAndType        #134:#131     // filter:(Lscala/Function1;)Ljava/lang/Object;
  #136 = Methodref          #42.#135      // scala/collection/immutable/ListSet.filter:(Lscala/Function1;)Ljava/lang/Object;
  #137 = Utf8               Z
  #138 = Utf8               [Lscala/collection/immutable/OldHashSet;
  #139 = Utf8               subsetOf0
  #140 = Utf8               (Lscala/collection/immutable/OldHashSet;I)Z
  #141 = Utf8               (Lscala/collection/immutable/OldHashSet<TA;>;I)Z
  #142 = Utf8               that
  #143 = Utf8               (Ljava/lang/Object;)Ljava/lang/Object;
  #144 = MethodType         #143          //  (Ljava/lang/Object;)Ljava/lang/Object;
  #145 = Utf8               $anonfun$subsetOf0$1$adapted
  #146 = Utf8               (Lscala/collection/immutable/OldHashSet$OldHashSetCollision1;Lscala/collection/immutable/OldHashSet;ILjava/lang/Object;)Ljava/lang/Object;
  #147 = NameAndType        #145:#146     // $anonfun$subsetOf0$1$adapted:(Lscala/collection/immutable/OldHashSet$OldHashSetCollision1;Lscala/collection/immutable/OldHashSet;ILjava/lang/Object;)Ljava/lang/Object;
  #148 = Methodref          #2.#147       // scala/collection/immutable/OldHashSet$OldHashSetCollision1.$anonfun$subsetOf0$1$adapted:(Lscala/collection/immutable/OldHashSet$OldHashSetCollision1;Lscala/collection/immutable/OldHashSet;ILjava/lang/Object;)Ljava/lang/Object;
  #149 = MethodHandle       6:#148        // REF_invokeStatic scala/collection/immutable/OldHashSet$OldHashSetCollision1.$anonfun$subsetOf0$1$adapted:(Lscala/collection/immutable/OldHashSet$OldHashSetCollision1;Lscala/collection/immutable/OldHashSet;ILjava/lang/Object;)Ljava/lang/Object;
  #150 = Integer            1
  #151 = Utf8               java/lang/invoke/LambdaMetafactory
  #152 = Class              #151          // java/lang/invoke/LambdaMetafactory
  #153 = Utf8               altMetafactory
  #154 = Utf8               (Ljava/lang/invoke/MethodHandles$Lookup;Ljava/lang/String;Ljava/lang/invoke/MethodType;[Ljava/lang/Object;)Ljava/lang/invoke/CallSite;
  #155 = NameAndType        #153:#154     // altMetafactory:(Ljava/lang/invoke/MethodHandles$Lookup;Ljava/lang/String;Ljava/lang/invoke/MethodType;[Ljava/lang/Object;)Ljava/lang/invoke/CallSite;
  #156 = Methodref          #152.#155     // java/lang/invoke/LambdaMetafactory.altMetafactory:(Ljava/lang/invoke/MethodHandles$Lookup;Ljava/lang/String;Ljava/lang/invoke/MethodType;[Ljava/lang/Object;)Ljava/lang/invoke/CallSite;
  #157 = MethodHandle       6:#156        // REF_invokeStatic java/lang/invoke/LambdaMetafactory.altMetafactory:(Ljava/lang/invoke/MethodHandles$Lookup;Ljava/lang/String;Ljava/lang/invoke/MethodType;[Ljava/lang/Object;)Ljava/lang/invoke/CallSite;
  #158 = Utf8               apply
  #159 = Utf8               (Lscala/collection/immutable/OldHashSet$OldHashSetCollision1;Lscala/collection/immutable/OldHashSet;I)Lscala/Function1;
  #160 = NameAndType        #158:#159     // apply:(Lscala/collection/immutable/OldHashSet$OldHashSetCollision1;Lscala/collection/immutable/OldHashSet;I)Lscala/Function1;
  #161 = InvokeDynamic      #0:#160       // #0:apply:(Lscala/collection/immutable/OldHashSet$OldHashSetCollision1;Lscala/collection/immutable/OldHashSet;I)Lscala/Function1;
  #162 = Utf8               forall
  #163 = Utf8               (Lscala/Function1;)Z
  #164 = NameAndType        #162:#163     // forall:(Lscala/Function1;)Z
  #165 = Methodref          #42.#164      // scala/collection/immutable/ListSet.forall:(Lscala/Function1;)Z
  #166 = Utf8               Lscala/collection/immutable/OldHashSet;
  #167 = Utf8               union0
  #168 = Utf8               (Lscala/collection/immutable/OldHashSet$LeafOldHashSet;I)Lscala/collection/immutable/OldHashSet;
  #169 = Utf8               (Lscala/collection/immutable/OldHashSet$LeafOldHashSet<TA;>;I)Lscala/collection/immutable/OldHashSet<TA;>;
  #170 = Methodref          #5.#62        // scala/collection/immutable/OldHashSet$LeafOldHashSet.hash:()I
  #171 = NameAndType        #60:#98       // key:()Ljava/lang/Object;
  #172 = Methodref          #19.#171      // scala/collection/immutable/OldHashSet$OldHashSet1.key:()Ljava/lang/Object;
  #173 = Utf8               $plus$plus
  #174 = Utf8               (Lscala/collection/IterableOnce;)Lscala/collection/SetOps;
  #175 = NameAndType        #173:#174     // $plus$plus:(Lscala/collection/IterableOnce;)Lscala/collection/SetOps;
  #176 = Methodref          #42.#175      // scala/collection/immutable/ListSet.$plus$plus:(Lscala/collection/IterableOnce;)Lscala/collection/SetOps;
  #177 = Utf8               scala/MatchError
  #178 = Class              #177          // scala/MatchError
  #179 = Utf8               (Ljava/lang/Object;)V
  #180 = NameAndType        #76:#179      // "<init>":(Ljava/lang/Object;)V
  #181 = Methodref          #178.#180     // scala/MatchError."<init>":(Ljava/lang/Object;)V
  #182 = Utf8               Lscala/collection/immutable/OldHashSet$LeafOldHashSet;
  #183 = Utf8               (Lscala/collection/immutable/OldHashSet;I[Lscala/collection/immutable/OldHashSet;I)Lscala/collection/immutable/OldHashSet;
  #184 = Utf8               (Lscala/collection/immutable/OldHashSet<TA;>;I[Lscala/collection/immutable/OldHashSet<TA;>;I)Lscala/collection/immutable/OldHashSet<TA;>;
  #185 = NameAndType        #167:#168     // union0:(Lscala/collection/immutable/OldHashSet$LeafOldHashSet;I)Lscala/collection/immutable/OldHashSet;
  #186 = Methodref          #2.#185       // scala/collection/immutable/OldHashSet$OldHashSetCollision1.union0:(Lscala/collection/immutable/OldHashSet$LeafOldHashSet;I)Lscala/collection/immutable/OldHashSet;
  #187 = Methodref          #13.#185      // scala/collection/immutable/OldHashSet$HashTrieSet.union0:(Lscala/collection/immutable/OldHashSet$LeafOldHashSet;I)Lscala/collection/immutable/OldHashSet;
  #188 = Class              #138          // "[Lscala/collection/immutable/OldHashSet;"
  #189 = Utf8               intersect0
  #190 = Utf8               $anonfun$intersect0$1$adapted
  #191 = NameAndType        #190:#146     // $anonfun$intersect0$1$adapted:(Lscala/collection/immutable/OldHashSet$OldHashSetCollision1;Lscala/collection/immutable/OldHashSet;ILjava/lang/Object;)Ljava/lang/Object;
  #192 = Methodref          #2.#191       // scala/collection/immutable/OldHashSet$OldHashSetCollision1.$anonfun$intersect0$1$adapted:(Lscala/collection/immutable/OldHashSet$OldHashSetCollision1;Lscala/collection/immutable/OldHashSet;ILjava/lang/Object;)Ljava/lang/Object;
  #193 = MethodHandle       6:#192        // REF_invokeStatic scala/collection/immutable/OldHashSet$OldHashSetCollision1.$anonfun$intersect0$1$adapted:(Lscala/collection/immutable/OldHashSet$OldHashSetCollision1;Lscala/collection/immutable/OldHashSet;ILjava/lang/Object;)Ljava/lang/Object;
  #194 = InvokeDynamic      #1:#160       // #1:apply:(Lscala/collection/immutable/OldHashSet$OldHashSetCollision1;Lscala/collection/immutable/OldHashSet;I)Lscala/Function1;
  #195 = Methodref          #2.#43        // scala/collection/immutable/OldHashSet$OldHashSetCollision1.size:()I
  #196 = Methodref          #15.#43       // scala/collection/immutable/OldHashSet.size:()I
  #197 = Utf8               diff0
  #198 = Utf8               $anonfun$diff0$1$adapted
  #199 = NameAndType        #198:#146     // $anonfun$diff0$1$adapted:(Lscala/collection/immutable/OldHashSet$OldHashSetCollision1;Lscala/collection/immutable/OldHashSet;ILjava/lang/Object;)Ljava/lang/Object;
  #200 = Methodref          #2.#199       // scala/collection/immutable/OldHashSet$OldHashSetCollision1.$anonfun$diff0$1$adapted:(Lscala/collection/immutable/OldHashSet$OldHashSetCollision1;Lscala/collection/immutable/OldHashSet;ILjava/lang/Object;)Ljava/lang/Object;
  #201 = MethodHandle       6:#200        // REF_invokeStatic scala/collection/immutable/OldHashSet$OldHashSetCollision1.$anonfun$diff0$1$adapted:(Lscala/collection/immutable/OldHashSet$OldHashSetCollision1;Lscala/collection/immutable/OldHashSet;ILjava/lang/Object;)Ljava/lang/Object;
  #202 = InvokeDynamic      #2:#160       // #2:apply:(Lscala/collection/immutable/OldHashSet$OldHashSetCollision1;Lscala/collection/immutable/OldHashSet;I)Lscala/Function1;
  #203 = Utf8               $anonfun$subsetOf0$1
  #204 = Utf8               (Lscala/collection/immutable/OldHashSet$OldHashSetCollision1;Lscala/collection/immutable/OldHashSet;ILjava/lang/Object;)Z
  #205 = Utf8               $this
  #206 = Utf8               that$1
  #207 = Utf8               level$1
  #208 = NameAndType        #57:#58       // get0:(Ljava/lang/Object;II)Z
  #209 = Methodref          #15.#208      // scala/collection/immutable/OldHashSet.get0:(Ljava/lang/Object;II)Z
  #210 = Utf8               $anonfun$intersect0$1
  #211 = Utf8               that$2
  #212 = Utf8               level$2
  #213 = Utf8               x$1
  #214 = Utf8               $anonfun$diff0$1
  #215 = Utf8               that$3
  #216 = Utf8               level$3
  #217 = Utf8               x$2
  #218 = Utf8               (ILscala/collection/immutable/ListSet<TA;>;)V
  #219 = Utf8               ()V
  #220 = NameAndType        #76:#219      // "<init>":()V
  #221 = Methodref          #5.#220       // scala/collection/immutable/OldHashSet$LeafOldHashSet."<init>":()V
  #222 = NameAndType        #203:#204     // $anonfun$subsetOf0$1:(Lscala/collection/immutable/OldHashSet$OldHashSetCollision1;Lscala/collection/immutable/OldHashSet;ILjava/lang/Object;)Z
  #223 = Methodref          #2.#222       // scala/collection/immutable/OldHashSet$OldHashSetCollision1.$anonfun$subsetOf0$1:(Lscala/collection/immutable/OldHashSet$OldHashSetCollision1;Lscala/collection/immutable/OldHashSet;ILjava/lang/Object;)Z
  #224 = Utf8               scala/runtime/BoxesRunTime
  #225 = Class              #224          // scala/runtime/BoxesRunTime
  #226 = Utf8               boxToBoolean
  #227 = Utf8               (Z)Ljava/lang/Boolean;
  #228 = NameAndType        #226:#227     // boxToBoolean:(Z)Ljava/lang/Boolean;
  #229 = Methodref          #225.#228     // scala/runtime/BoxesRunTime.boxToBoolean:(Z)Ljava/lang/Boolean;
  #230 = NameAndType        #210:#204     // $anonfun$intersect0$1:(Lscala/collection/immutable/OldHashSet$OldHashSetCollision1;Lscala/collection/immutable/OldHashSet;ILjava/lang/Object;)Z
  #231 = Methodref          #2.#230       // scala/collection/immutable/OldHashSet$OldHashSetCollision1.$anonfun$intersect0$1:(Lscala/collection/immutable/OldHashSet$OldHashSetCollision1;Lscala/collection/immutable/OldHashSet;ILjava/lang/Object;)Z
  #232 = NameAndType        #214:#204     // $anonfun$diff0$1:(Lscala/collection/immutable/OldHashSet$OldHashSetCollision1;Lscala/collection/immutable/OldHashSet;ILjava/lang/Object;)Z
  #233 = Methodref          #2.#232       // scala/collection/immutable/OldHashSet$OldHashSetCollision1.$anonfun$diff0$1:(Lscala/collection/immutable/OldHashSet$OldHashSetCollision1;Lscala/collection/immutable/OldHashSet;ILjava/lang/Object;)Z
  #234 = Utf8               $deserializeLambda$
  #235 = Utf8               (Ljava/lang/invoke/SerializedLambda;)Ljava/lang/Object;
  #236 = Utf8               scala/runtime/LambdaDeserialize
  #237 = Class              #236          // scala/runtime/LambdaDeserialize
  #238 = Utf8               bootstrap
  #239 = Utf8               (Ljava/lang/invoke/MethodHandles$Lookup;Ljava/lang/String;Ljava/lang/invoke/MethodType;[Ljava/lang/invoke/MethodHandle;)Ljava/lang/invoke/CallSite;
  #240 = NameAndType        #238:#239     // bootstrap:(Ljava/lang/invoke/MethodHandles$Lookup;Ljava/lang/String;Ljava/lang/invoke/MethodType;[Ljava/lang/invoke/MethodHandle;)Ljava/lang/invoke/CallSite;
  #241 = Methodref          #237.#240     // scala/runtime/LambdaDeserialize.bootstrap:(Ljava/lang/invoke/MethodHandles$Lookup;Ljava/lang/String;Ljava/lang/invoke/MethodType;[Ljava/lang/invoke/MethodHandle;)Ljava/lang/invoke/CallSite;
  #242 = MethodHandle       6:#241        // REF_invokeStatic scala/runtime/LambdaDeserialize.bootstrap:(Ljava/lang/invoke/MethodHandles$Lookup;Ljava/lang/String;Ljava/lang/invoke/MethodType;[Ljava/lang/invoke/MethodHandle;)Ljava/lang/invoke/CallSite;
  #243 = Utf8               lambdaDeserialize
  #244 = NameAndType        #243:#235     // lambdaDeserialize:(Ljava/lang/invoke/SerializedLambda;)Ljava/lang/Object;
  #245 = InvokeDynamic      #3:#244       // #3:lambdaDeserialize:(Ljava/lang/invoke/SerializedLambda;)Ljava/lang/Object;
  #246 = Utf8               Signature
  #247 = Utf8               Code
  #248 = Utf8               LineNumberTable
  #249 = Utf8               LocalVariableTable
  #250 = Utf8               MethodParameters
  #251 = Utf8               StackMapTable
  #252 = Utf8               InnerClasses
  #253 = Utf8               SourceFile
  #254 = Utf8               BootstrapMethods
  #255 = Utf8               ScalaInlineInfo
  #256 = Utf8               Scala
{
  private final int hash;
    descriptor: I
    flags: (0x0012) ACC_PRIVATE, ACC_FINAL

  private final scala.collection.immutable.ListSet<A> ks;
    descriptor: Lscala/collection/immutable/ListSet;
    flags: (0x0012) ACC_PRIVATE, ACC_FINAL
    Signature: #26                          // Lscala/collection/immutable/ListSet<TA;>;

  public int hash();
    descriptor: ()I
    flags: (0x0001) ACC_PUBLIC
    Code:
      stack=1, locals=1, args_size=1
         0: aload_0
         1: getfield      #29                 // Field hash:I
         4: ireturn
      LineNumberTable:
        line 310: 0
      LocalVariableTable:
        Start  Length  Slot  Name   Signature
            0       5     0  this   Lscala/collection/immutable/OldHashSet$OldHashSetCollision1;

  public scala.collection.immutable.ListSet<A> ks();
    descriptor: ()Lscala/collection/immutable/ListSet;
    flags: (0x0001) ACC_PUBLIC
    Code:
      stack=1, locals=1, args_size=1
         0: aload_0
         1: getfield      #35                 // Field ks:Lscala/collection/immutable/ListSet;
         4: areturn
      LineNumberTable:
        line 310: 0
      LocalVariableTable:
        Start  Length  Slot  Name   Signature
            0       5     0  this   Lscala/collection/immutable/OldHashSet$OldHashSetCollision1;
    Signature: #33                          // ()Lscala/collection/immutable/ListSet<TA;>;

  public boolean isEmpty();
    descriptor: ()Z
    flags: (0x0001) ACC_PUBLIC
    Code:
      stack=1, locals=1, args_size=1
         0: iconst_0
         1: ireturn
      LineNumberTable:
        line 311: 0
      LocalVariableTable:
        Start  Length  Slot  Name   Signature
            0       2     0  this   Lscala/collection/immutable/OldHashSet$OldHashSetCollision1;

  public int size();
    descriptor: ()I
    flags: (0x0001) ACC_PUBLIC
    Code:
      stack=1, locals=1, args_size=1
         0: aload_0
         1: invokevirtual #40                 // Method ks:()Lscala/collection/immutable/ListSet;
         4: invokevirtual #44                 // Method scala/collection/immutable/ListSet.size:()I
         7: ireturn
      LineNumberTable:
        line 312: 0
      LocalVariableTable:
        Start  Length  Slot  Name   Signature
            0       8     0  this   Lscala/collection/immutable/OldHashSet$OldHashSetCollision1;

  public scala.collection.Iterator<A> iterator();
    descriptor: ()Lscala/collection/Iterator;
    flags: (0x0001) ACC_PUBLIC
    Code:
      stack=1, locals=1, args_size=1
         0: aload_0
         1: invokevirtual #40                 // Method ks:()Lscala/collection/immutable/ListSet;
         4: invokevirtual #49                 // Method scala/collection/immutable/ListSet.iterator:()Lscala/collection/Iterator;
         7: areturn
      LineNumberTable:
        line 314: 0
      LocalVariableTable:
        Start  Length  Slot  Name   Signature
            0       8     0  this   Lscala/collection/immutable/OldHashSet$OldHashSetCollision1;
    Signature: #47                          // ()Lscala/collection/Iterator<TA;>;

  public <U extends java.lang.Object> void foreach(scala.Function1<A, U>);
    descriptor: (Lscala/Function1;)V
    flags: (0x0001) ACC_PUBLIC
    Code:
      stack=2, locals=2, args_size=2
         0: aload_0
         1: invokevirtual #40                 // Method ks:()Lscala/collection/immutable/ListSet;
         4: aload_1
         5: invokevirtual #55                 // Method scala/collection/immutable/ListSet.foreach:(Lscala/Function1;)V
         8: return
      LineNumberTable:
        line 316: 0
      LocalVariableTable:
        Start  Length  Slot  Name   Signature
            0       9     0  this   Lscala/collection/immutable/OldHashSet$OldHashSetCollision1;
            0       9     1     f   Lscala/Function1;
    Signature: #52                          // <U:Ljava/lang/Object;>(Lscala/Function1<TA;TU;>;)V
    MethodParameters:
      Name                           Flags
      f                              final

  public boolean get0(A, int, int);
    descriptor: (Ljava/lang/Object;II)Z
    flags: (0x0001) ACC_PUBLIC
    Code:
      stack=2, locals=4, args_size=4
         0: iload_2
         1: aload_0
         2: invokevirtual #63                 // Method hash:()I
         5: if_icmpne     19
         8: aload_0
         9: invokevirtual #40                 // Method ks:()Lscala/collection/immutable/ListSet;
        12: aload_1
        13: invokevirtual #67                 // Method scala/collection/immutable/ListSet.contains:(Ljava/lang/Object;)Z
        16: goto          20
        19: iconst_0
        20: ireturn
      StackMapTable: number_of_entries = 2
        frame_type = 19 /* same */
        frame_type = 64 /* same_locals_1_stack_item */
          stack = [ int ]
      LineNumberTable:
        line 319: 0
      LocalVariableTable:
        Start  Length  Slot  Name   Signature
            0      21     0  this   Lscala/collection/immutable/OldHashSet$OldHashSetCollision1;
            0      21     1   key   Ljava/lang/Object;
            0      21     2  hash   I
            0      21     3 level   I
    Signature: #59                          // (TA;II)Z
    MethodParameters:
      Name                           Flags
      key                            final
      hash                           final
      level                          final

  public scala.collection.immutable.OldHashSet<A> updated0(A, int, int);
    descriptor: (Ljava/lang/Object;II)Lscala/collection/immutable/OldHashSet;
    flags: (0x0001) ACC_PUBLIC
    Code:
      stack=8, locals=4, args_size=4
         0: iload_2
         1: aload_0
         2: invokevirtual #63                 // Method hash:()I
         5: if_icmpne     30
         8: new           #2                  // class scala/collection/immutable/OldHashSet$OldHashSetCollision1
        11: dup
        12: iload_2
        13: aload_0
        14: invokevirtual #40                 // Method ks:()Lscala/collection/immutable/ListSet;
        17: aload_1
        18: invokevirtual #75                 // Method scala/collection/immutable/ListSet.$plus:(Ljava/lang/Object;)Lscala/collection/immutable/SetOps;
        21: checkcast     #42                 // class scala/collection/immutable/ListSet
        24: invokespecial #79                 // Method "<init>":(ILscala/collection/immutable/ListSet;)V
        27: goto          52
        30: getstatic     #85                 // Field scala/collection/immutable/OldHashSet$.MODULE$:Lscala/collection/immutable/OldHashSet$;
        33: aload_0
        34: invokevirtual #63                 // Method hash:()I
        37: aload_0
        38: iload_2
        39: new           #19                 // class scala/collection/immutable/OldHashSet$OldHashSet1
        42: dup
        43: aload_1
        44: iload_2
        45: invokespecial #88                 // Method scala/collection/immutable/OldHashSet$OldHashSet1."<init>":(Ljava/lang/Object;I)V
        48: iload_3
        49: invokevirtual #92                 // Method scala/collection/immutable/OldHashSet$.scala$collection$immutable$OldHashSet$$makeHashTrieSet:(ILscala/collection/immutable/OldHashSet;ILscala/collection/immutable/OldHashSet;I)Lscala/collection/immutable/OldHashSet$HashTrieSet;
        52: areturn
      StackMapTable: number_of_entries = 2
        frame_type = 30 /* same */
        frame_type = 85 /* same_locals_1_stack_item */
          stack = [ class scala/collection/immutable/OldHashSet ]
      LineNumberTable:
        line 322: 0
        line 323: 30
      LocalVariableTable:
        Start  Length  Slot  Name   Signature
            0      53     0  this   Lscala/collection/immutable/OldHashSet$OldHashSetCollision1;
            0      53     1   key   Ljava/lang/Object;
            0      53     2  hash   I
            0      53     3 level   I
    Signature: #71                          // (TA;II)Lscala/collection/immutable/OldHashSet<TA;>;
    MethodParameters:
      Name                           Flags
      key                            final
      hash                           final
      level                          final

  public scala.collection.immutable.OldHashSet<A> removed0(A, int, int);
    descriptor: (Ljava/lang/Object;II)Lscala/collection/immutable/OldHashSet;
    flags: (0x0001) ACC_PUBLIC
    Code:
      stack=4, locals=6, args_size=4
         0: iload_2
         1: aload_0
         2: invokevirtual #63                 // Method hash:()I
         5: if_icmpne     104
         8: aload_0
         9: invokevirtual #40                 // Method ks:()Lscala/collection/immutable/ListSet;
        12: aload_1
        13: invokevirtual #96                 // Method scala/collection/immutable/ListSet.$minus:(Ljava/lang/Object;)Lscala/collection/immutable/SetOps;
        16: checkcast     #42                 // class scala/collection/immutable/ListSet
        19: astore        4
        21: aload         4
        23: invokevirtual #44                 // Method scala/collection/immutable/ListSet.size:()I
        26: istore        5
        28: iload         5
        30: tableswitch   { // 0 to 1
                       0: 52
                       1: 56
                 default: 72
            }
        52: aconst_null
        53: goto          101
        56: new           #19                 // class scala/collection/immutable/OldHashSet$OldHashSet1
        59: dup
        60: aload         4
        62: invokevirtual #100                // Method scala/collection/immutable/ListSet.head:()Ljava/lang/Object;
        65: iload_2
        66: invokespecial #88                 // Method scala/collection/immutable/OldHashSet$OldHashSet1."<init>":(Ljava/lang/Object;I)V
        69: goto          101
        72: iload         5
        74: aload_0
        75: invokevirtual #40                 // Method ks:()Lscala/collection/immutable/ListSet;
        78: invokevirtual #44                 // Method scala/collection/immutable/ListSet.size:()I
        81: if_icmpne     88
        84: aload_0
        85: goto          98
        88: new           #2                  // class scala/collection/immutable/OldHashSet$OldHashSetCollision1
        91: dup
        92: iload_2
        93: aload         4
        95: invokespecial #79                 // Method "<init>":(ILscala/collection/immutable/ListSet;)V
        98: goto          101
       101: goto          105
       104: aload_0
       105: areturn
      StackMapTable: number_of_entries = 8
        frame_type = 253 /* append */
          offset_delta = 52
          locals = [ class scala/collection/immutable/ListSet, int ]
        frame_type = 3 /* same */
        frame_type = 15 /* same */
        frame_type = 15 /* same */
        frame_type = 73 /* same_locals_1_stack_item */
          stack = [ class scala/collection/immutable/OldHashSet$OldHashSetCollision1 ]
        frame_type = 66 /* same_locals_1_stack_item */
          stack = [ class scala/collection/immutable/OldHashSet$LeafOldHashSet ]
        frame_type = 249 /* chop */
          offset_delta = 2
        frame_type = 64 /* same_locals_1_stack_item */
          stack = [ class scala/collection/immutable/OldHashSet$LeafOldHashSet ]
      LineNumberTable:
        line 326: 0
        line 327: 8
        line 328: 21
        line 331: 52
        line 334: 56
        line 335: 72
        line 337: 84
        line 340: 88
        line 342: 104
      LocalVariableTable:
        Start  Length  Slot  Name   Signature
           21      80     4   ks1   Lscala/collection/immutable/ListSet;
            0     106     0  this   Lscala/collection/immutable/OldHashSet$OldHashSetCollision1;
            0     106     1   key   Ljava/lang/Object;
            0     106     2  hash   I
            0     106     3 level   I
    Signature: #71                          // (TA;II)Lscala/collection/immutable/OldHashSet<TA;>;
    MethodParameters:
      Name                           Flags
      key                            final
      hash                           final
      level                          final

  private void writeObject(java.io.ObjectOutputStream);
    descriptor: (Ljava/io/ObjectOutputStream;)V
    flags: (0x0002) ACC_PRIVATE
    Code:
      stack=2, locals=2, args_size=2
         0: getstatic     #109                // Field scala/sys/package$.MODULE$:Lscala/sys/package$;
         3: ldc           #111                // String cannot serialize an immutable.OldHashSet where all items have the same 32-bit hash code
         5: invokevirtual #115                // Method scala/sys/package$.error:(Ljava/lang/String;)Lscala/runtime/Nothing$;
         8: athrow
      LineNumberTable:
        line 349: 0
      LocalVariableTable:
        Start  Length  Slot  Name   Signature
            0       9     0  this   Lscala/collection/immutable/OldHashSet$OldHashSetCollision1;
            0       9     1   out   Ljava/io/ObjectOutputStream;
    MethodParameters:
      Name                           Flags
      out                            final

  private void readObject(java.io.ObjectInputStream);
    descriptor: (Ljava/io/ObjectInputStream;)V
    flags: (0x0002) ACC_PRIVATE
    Code:
      stack=2, locals=2, args_size=2
         0: getstatic     #109                // Field scala/sys/package$.MODULE$:Lscala/sys/package$;
         3: ldc           #121                // String cannot deserialize an immutable.OldHashSet where all items have the same 32-bit hash code
         5: invokevirtual #115                // Method scala/sys/package$.error:(Ljava/lang/String;)Lscala/runtime/Nothing$;
         8: athrow
      LineNumberTable:
        line 354: 0
      LocalVariableTable:
        Start  Length  Slot  Name   Signature
            0       9     0  this   Lscala/collection/immutable/OldHashSet$OldHashSetCollision1;
            0       9     1    in   Ljava/io/ObjectInputStream;
    MethodParameters:
      Name                           Flags
      in                             final

  public scala.collection.immutable.OldHashSet<A> filter0(scala.Function1<A, java.lang.Object>, boolean, int, scala.collection.immutable.OldHashSet<A>[], int);
    descriptor: (Lscala/Function1;ZI[Lscala/collection/immutable/OldHashSet;I)Lscala/collection/immutable/OldHashSet;
    flags: (0x0001) ACC_PUBLIC
    Code:
      stack=4, locals=8, args_size=6
         0: iload_2
         1: ifeq          18
         4: aload_0
         5: invokevirtual #40                 // Method ks:()Lscala/collection/immutable/ListSet;
         8: aload_1
         9: invokevirtual #133                // Method scala/collection/immutable/ListSet.filterNot:(Lscala/Function1;)Ljava/lang/Object;
        12: checkcast     #42                 // class scala/collection/immutable/ListSet
        15: goto          29
        18: aload_0
        19: invokevirtual #40                 // Method ks:()Lscala/collection/immutable/ListSet;
        22: aload_1
        23: invokevirtual #136                // Method scala/collection/immutable/ListSet.filter:(Lscala/Function1;)Ljava/lang/Object;
        26: checkcast     #42                 // class scala/collection/immutable/ListSet
        29: astore        6
        31: aload         6
        33: invokevirtual #44                 // Method scala/collection/immutable/ListSet.size:()I
        36: istore        7
        38: iload         7
        40: tableswitch   { // 0 to 1
                       0: 64
                       1: 68
                 default: 87
            }
        64: aconst_null
        65: goto          119
        68: new           #19                 // class scala/collection/immutable/OldHashSet$OldHashSet1
        71: dup
        72: aload         6
        74: invokevirtual #100                // Method scala/collection/immutable/ListSet.head:()Ljava/lang/Object;
        77: aload_0
        78: invokevirtual #63                 // Method hash:()I
        81: invokespecial #88                 // Method scala/collection/immutable/OldHashSet$OldHashSet1."<init>":(Ljava/lang/Object;I)V
        84: goto          119
        87: iload         7
        89: aload_0
        90: invokevirtual #40                 // Method ks:()Lscala/collection/immutable/ListSet;
        93: invokevirtual #44                 // Method scala/collection/immutable/ListSet.size:()I
        96: if_icmpne     103
        99: aload_0
       100: goto          116
       103: new           #2                  // class scala/collection/immutable/OldHashSet$OldHashSetCollision1
       106: dup
       107: aload_0
       108: invokevirtual #63                 // Method hash:()I
       111: aload         6
       113: invokespecial #79                 // Method "<init>":(ILscala/collection/immutable/ListSet;)V
       116: goto          119
       119: areturn
      StackMapTable: number_of_entries = 8
        frame_type = 18 /* same */
        frame_type = 74 /* same_locals_1_stack_item */
          stack = [ class scala/collection/immutable/ListSet ]
        frame_type = 253 /* append */
          offset_delta = 34
          locals = [ class scala/collection/immutable/ListSet, int ]
        frame_type = 3 /* same */
        frame_type = 18 /* same */
        frame_type = 15 /* same */
        frame_type = 76 /* same_locals_1_stack_item */
          stack = [ class scala/collection/immutable/OldHashSet$OldHashSetCollision1 ]
        frame_type = 66 /* same_locals_1_stack_item */
          stack = [ class scala/collection/immutable/OldHashSet$LeafOldHashSet ]
      LineNumberTable:
        line 360: 0
        line 361: 31
        line 363: 64
        line 365: 68
        line 366: 87
        line 367: 99
        line 369: 103
      LocalVariableTable:
        Start  Length  Slot  Name   Signature
           31      88     6   ks1   Lscala/collection/immutable/ListSet;
            0     120     0  this   Lscala/collection/immutable/OldHashSet$OldHashSetCollision1;
            0     120     1     p   Lscala/Function1;
            0     120     2 negate   Z
            0     120     3 level   I
            0     120     4 buffer   [Lscala/collection/immutable/OldHashSet;
            0     120     5 offset0   I
    Signature: #125                         // (Lscala/Function1<TA;Ljava/lang/Object;>;ZI[Lscala/collection/immutable/OldHashSet<TA;>;I)Lscala/collection/immutable/OldHashSet<TA;>;
    MethodParameters:
      Name                           Flags
      p                              final
      negate                         final
      level                          final
      buffer                         final
      offset0                        final

  public boolean subsetOf0(scala.collection.immutable.OldHashSet<A>, int);
    descriptor: (Lscala/collection/immutable/OldHashSet;I)Z
    flags: (0x0001) ACC_PUBLIC
    Code:
      stack=4, locals=3, args_size=3
         0: aload_0
         1: invokevirtual #40                 // Method ks:()Lscala/collection/immutable/ListSet;
         4: aload_0
         5: aload_1
         6: iload_2
         7: invokedynamic #161,  0            // InvokeDynamic #0:apply:(Lscala/collection/immutable/OldHashSet$OldHashSetCollision1;Lscala/collection/immutable/OldHashSet;I)Lscala/Function1;
        12: invokevirtual #165                // Method scala/collection/immutable/ListSet.forall:(Lscala/Function1;)Z
        15: ireturn
      LineNumberTable:
        line 378: 0
      LocalVariableTable:
        Start  Length  Slot  Name   Signature
            0      16     0  this   Lscala/collection/immutable/OldHashSet$OldHashSetCollision1;
            0      16     1  that   Lscala/collection/immutable/OldHashSet;
            0      16     2 level   I
    Signature: #141                         // (Lscala/collection/immutable/OldHashSet<TA;>;I)Z
    MethodParameters:
      Name                           Flags
      that                           final
      level                          final

  public scala.collection.immutable.OldHashSet<A> union0(scala.collection.immutable.OldHashSet$LeafOldHashSet<A>, int);
    descriptor: (Lscala/collection/immutable/OldHashSet$LeafOldHashSet;I)Lscala/collection/immutable/OldHashSet;
    flags: (0x0001) ACC_PUBLIC
    Code:
      stack=6, locals=10, args_size=3
         0: aload_1
         1: astore        4
         3: aload         4
         5: invokevirtual #170                // Method scala/collection/immutable/OldHashSet$LeafOldHashSet.hash:()I
         8: aload_0
         9: invokevirtual #63                 // Method hash:()I
        12: if_icmpeq     38
        15: getstatic     #85                 // Field scala/collection/immutable/OldHashSet$.MODULE$:Lscala/collection/immutable/OldHashSet$;
        18: aload_0
        19: invokevirtual #63                 // Method hash:()I
        22: aload_0
        23: aload         4
        25: invokevirtual #170                // Method scala/collection/immutable/OldHashSet$LeafOldHashSet.hash:()I
        28: aload         4
        30: iload_2
        31: invokevirtual #92                 // Method scala/collection/immutable/OldHashSet$.scala$collection$immutable$OldHashSet$$makeHashTrieSet:(ILscala/collection/immutable/OldHashSet;ILscala/collection/immutable/OldHashSet;I)Lscala/collection/immutable/OldHashSet$HashTrieSet;
        34: astore_3
        35: goto          231
        38: goto          41
        41: aload         4
        43: instanceof    #19                 // class scala/collection/immutable/OldHashSet$OldHashSet1
        46: ifeq          109
        49: aload         4
        51: checkcast     #19                 // class scala/collection/immutable/OldHashSet$OldHashSet1
        54: astore        5
        56: aload_0
        57: invokevirtual #40                 // Method ks:()Lscala/collection/immutable/ListSet;
        60: aload         5
        62: invokevirtual #172                // Method scala/collection/immutable/OldHashSet$OldHashSet1.key:()Ljava/lang/Object;
        65: invokevirtual #75                 // Method scala/collection/immutable/ListSet.$plus:(Ljava/lang/Object;)Lscala/collection/immutable/SetOps;
        68: checkcast     #42                 // class scala/collection/immutable/ListSet
        71: astore        6
        73: aload         6
        75: invokevirtual #44                 // Method scala/collection/immutable/ListSet.size:()I
        78: aload_0
        79: invokevirtual #40                 // Method ks:()Lscala/collection/immutable/ListSet;
        82: invokevirtual #44                 // Method scala/collection/immutable/ListSet.size:()I
        85: if_icmpne     92
        88: aload_0
        89: goto          105
        92: new           #2                  // class scala/collection/immutable/OldHashSet$OldHashSetCollision1
        95: dup
        96: aload_0
        97: invokevirtual #63                 // Method hash:()I
       100: aload         6
       102: invokespecial #79                 // Method "<init>":(ILscala/collection/immutable/ListSet;)V
       105: astore_3
       106: goto          231
       109: goto          112
       112: aload         4
       114: instanceof    #2                  // class scala/collection/immutable/OldHashSet$OldHashSetCollision1
       117: ifeq          218
       120: aload         4
       122: checkcast     #2                  // class scala/collection/immutable/OldHashSet$OldHashSetCollision1
       125: astore        7
       127: aload_0
       128: invokevirtual #40                 // Method ks:()Lscala/collection/immutable/ListSet;
       131: aload         7
       133: invokevirtual #40                 // Method ks:()Lscala/collection/immutable/ListSet;
       136: invokevirtual #176                // Method scala/collection/immutable/ListSet.$plus$plus:(Lscala/collection/IterableOnce;)Lscala/collection/SetOps;
       139: checkcast     #42                 // class scala/collection/immutable/ListSet
       142: astore        8
       144: aload         8
       146: invokevirtual #44                 // Method scala/collection/immutable/ListSet.size:()I
       149: istore        9
       151: iload         9
       153: lookupswitch  { // 0
                 default: 164
            }
       164: iload         9
       166: aload_0
       167: invokevirtual #40                 // Method ks:()Lscala/collection/immutable/ListSet;
       170: invokevirtual #44                 // Method scala/collection/immutable/ListSet.size:()I
       173: if_icmpne     180
       176: aload_0
       177: goto          211
       180: iload         9
       182: aload         7
       184: invokevirtual #40                 // Method ks:()Lscala/collection/immutable/ListSet;
       187: invokevirtual #44                 // Method scala/collection/immutable/ListSet.size:()I
       190: if_icmpne     198
       193: aload         7
       195: goto          211
       198: new           #2                  // class scala/collection/immutable/OldHashSet$OldHashSetCollision1
       201: dup
       202: aload_0
       203: invokevirtual #63                 // Method hash:()I
       206: aload         8
       208: invokespecial #79                 // Method "<init>":(ILscala/collection/immutable/ListSet;)V
       211: goto          214
       214: astore_3
       215: goto          231
       218: goto          221
       221: new           #178                // class scala/MatchError
       224: dup
       225: aload         4
       227: invokespecial #181                // Method scala/MatchError."<init>":(Ljava/lang/Object;)V
       230: athrow
       231: aload_3
       232: areturn
      StackMapTable: number_of_entries = 14
        frame_type = 253 /* append */
          offset_delta = 38
          locals = [ top, class scala/collection/immutable/OldHashSet$LeafOldHashSet ]
        frame_type = 2 /* same */
        frame_type = 253 /* append */
          offset_delta = 50
          locals = [ class scala/collection/immutable/OldHashSet$OldHashSet1, class scala/collection/immutable/ListSet ]
        frame_type = 76 /* same_locals_1_stack_item */
          stack = [ class scala/collection/immutable/OldHashSet$OldHashSetCollision1 ]
        frame_type = 249 /* chop */
          offset_delta = 3
        frame_type = 2 /* same */
        frame_type = 255 /* full_frame */
          offset_delta = 51
          locals = [ class scala/collection/immutable/OldHashSet$OldHashSetCollision1, class scala/collection/immutable/OldHashSet$LeafOldHashSet, int, top, class scala/collection/immutable/OldHashSet$LeafOldHashSet, top, top, class scala/collection/immutable/OldHashSet$OldHashSetCollision1, class scala/collection/immutable/ListSet, int ]
          stack = []
        frame_type = 15 /* same */
        frame_type = 17 /* same */
        frame_type = 76 /* same_locals_1_stack_item */
          stack = [ class scala/collection/immutable/OldHashSet$OldHashSetCollision1 ]
        frame_type = 66 /* same_locals_1_stack_item */
          stack = [ class scala/collection/immutable/OldHashSet$OldHashSetCollision1 ]
        frame_type = 255 /* full_frame */
          offset_delta = 3
          locals = [ class scala/collection/immutable/OldHashSet$OldHashSetCollision1, class scala/collection/immutable/OldHashSet$LeafOldHashSet, int, top, class scala/collection/immutable/OldHashSet$LeafOldHashSet ]
          stack = []
        frame_type = 2 /* same */
        frame_type = 255 /* full_frame */
          offset_delta = 9
          locals = [ class scala/collection/immutable/OldHashSet$OldHashSetCollision1, class scala/collection/immutable/OldHashSet$LeafOldHashSet, int, class scala/collection/immutable/OldHashSet, class scala/collection/immutable/OldHashSet$LeafOldHashSet ]
          stack = []
      LineNumberTable:
        line 381: 0
        line 382: 3
        line 385: 15
        line 381: 38
        line 386: 41
        line 387: 56
        line 389: 73
        line 390: 88
        line 394: 92
        line 386: 109
        line 396: 112
        line 397: 127
        line 398: 144
        line 399: 164
        line 403: 176
        line 404: 180
        line 406: 193
        line 410: 198
        line 396: 218
        line 381: 221
      LocalVariableTable:
        Start  Length  Slot  Name   Signature
           73      32     6   ks1   Lscala/collection/immutable/ListSet;
          144      70     8   ks1   Lscala/collection/immutable/ListSet;
            0     233     0  this   Lscala/collection/immutable/OldHashSet$OldHashSetCollision1;
            0     233     1  that   Lscala/collection/immutable/OldHashSet$LeafOldHashSet;
            0     233     2 level   I
    Signature: #169                         // (Lscala/collection/immutable/OldHashSet$LeafOldHashSet<TA;>;I)Lscala/collection/immutable/OldHashSet<TA;>;
    MethodParameters:
      Name                           Flags
      that                           final
      level                          final

  public scala.collection.immutable.OldHashSet<A> union0(scala.collection.immutable.OldHashSet<A>, int, scala.collection.immutable.OldHashSet<A>[], int);
    descriptor: (Lscala/collection/immutable/OldHashSet;I[Lscala/collection/immutable/OldHashSet;I)Lscala/collection/immutable/OldHashSet;
    flags: (0x0001) ACC_PUBLIC
    Code:
      stack=3, locals=9, args_size=5
         0: aload_1
         1: astore        6
         3: aload         6
         5: instanceof    #5                  // class scala/collection/immutable/OldHashSet$LeafOldHashSet
         8: ifeq          30
        11: aload         6
        13: checkcast     #5                  // class scala/collection/immutable/OldHashSet$LeafOldHashSet
        16: astore        7
        18: aload_0
        19: aload         7
        21: iload_2
        22: invokevirtual #186                // Method union0:(Lscala/collection/immutable/OldHashSet$LeafOldHashSet;I)Lscala/collection/immutable/OldHashSet;
        25: astore        5
        27: goto          69
        30: goto          33
        33: aload         6
        35: instanceof    #13                 // class scala/collection/immutable/OldHashSet$HashTrieSet
        38: ifeq          60
        41: aload         6
        43: checkcast     #13                 // class scala/collection/immutable/OldHashSet$HashTrieSet
        46: astore        8
        48: aload         8
        50: aload_0
        51: iload_2
        52: invokevirtual #187                // Method scala/collection/immutable/OldHashSet$HashTrieSet.union0:(Lscala/collection/immutable/OldHashSet$LeafOldHashSet;I)Lscala/collection/immutable/OldHashSet;
        55: astore        5
        57: goto          69
        60: goto          63
        63: aload_0
        64: astore        5
        66: goto          69
        69: aload         5
        71: areturn
      StackMapTable: number_of_entries = 5
        frame_type = 253 /* append */
          offset_delta = 30
          locals = [ top, class scala/collection/immutable/OldHashSet ]
        frame_type = 2 /* same */
        frame_type = 26 /* same */
        frame_type = 2 /* same */
        frame_type = 255 /* full_frame */
          offset_delta = 5
          locals = [ class scala/collection/immutable/OldHashSet$OldHashSetCollision1, class scala/collection/immutable/OldHashSet, int, class "[Lscala/collection/immutable/OldHashSet;", int, class scala/collection/immutable/OldHashSet, class scala/collection/immutable/OldHashSet ]
          stack = []
      LineNumberTable:
        line 414: 0
        line 415: 3
        line 417: 18
        line 415: 30
        line 418: 33
        line 421: 48
        line 418: 60
        line 422: 63
        line 414: 69
      LocalVariableTable:
        Start  Length  Slot  Name   Signature
            0      72     0  this   Lscala/collection/immutable/OldHashSet$OldHashSetCollision1;
            0      72     1  that   Lscala/collection/immutable/OldHashSet;
            0      72     2 level   I
            0      72     3 buffer   [Lscala/collection/immutable/OldHashSet;
            0      72     4 offset0   I
    Signature: #184                         // (Lscala/collection/immutable/OldHashSet<TA;>;I[Lscala/collection/immutable/OldHashSet<TA;>;I)Lscala/collection/immutable/OldHashSet<TA;>;
    MethodParameters:
      Name                           Flags
      that                           final
      level                          final
      buffer                         final
      offset0                        final

  public scala.collection.immutable.OldHashSet<A> intersect0(scala.collection.immutable.OldHashSet<A>, int, scala.collection.immutable.OldHashSet<A>[], int);
    descriptor: (Lscala/collection/immutable/OldHashSet;I[Lscala/collection/immutable/OldHashSet;I)Lscala/collection/immutable/OldHashSet;
    flags: (0x0001) ACC_PUBLIC
    Code:
      stack=4, locals=8, args_size=5
         0: aload_0
         1: invokevirtual #40                 // Method ks:()Lscala/collection/immutable/ListSet;
         4: aload_0
         5: aload_1
         6: iload_2
         7: invokedynamic #194,  0            // InvokeDynamic #1:apply:(Lscala/collection/immutable/OldHashSet$OldHashSetCollision1;Lscala/collection/immutable/OldHashSet;I)Lscala/Function1;
        12: invokevirtual #136                // Method scala/collection/immutable/ListSet.filter:(Lscala/Function1;)Ljava/lang/Object;
        15: checkcast     #42                 // class scala/collection/immutable/ListSet
        18: astore        6
        20: aload         6
        22: invokevirtual #44                 // Method scala/collection/immutable/ListSet.size:()I
        25: istore        7
        27: iconst_0
        28: iload         7
        30: if_icmpne     39
        33: aconst_null
        34: astore        5
        36: goto          126
        39: goto          42
        42: iload         7
        44: aload_0
        45: invokevirtual #195                // Method size:()I
        48: if_icmpne     57
        51: aload_0
        52: astore        5
        54: goto          126
        57: goto          60
        60: iload         7
        62: aload_1
        63: invokevirtual #196                // Method scala/collection/immutable/OldHashSet.size:()I
        66: if_icmpne     75
        69: aload_1
        70: astore        5
        72: goto          126
        75: goto          78
        78: iconst_1
        79: iload         7
        81: if_icmpne     105
        84: new           #19                 // class scala/collection/immutable/OldHashSet$OldHashSet1
        87: dup
        88: aload         6
        90: invokevirtual #100                // Method scala/collection/immutable/ListSet.head:()Ljava/lang/Object;
        93: aload_0
        94: invokevirtual #63                 // Method hash:()I
        97: invokespecial #88                 // Method scala/collection/immutable/OldHashSet$OldHashSet1."<init>":(Ljava/lang/Object;I)V
       100: astore        5
       102: goto          126
       105: goto          108
       108: new           #2                  // class scala/collection/immutable/OldHashSet$OldHashSetCollision1
       111: dup
       112: aload_0
       113: invokevirtual #63                 // Method hash:()I
       116: aload         6
       118: invokespecial #79                 // Method "<init>":(ILscala/collection/immutable/ListSet;)V
       121: astore        5
       123: goto          126
       126: aload         5
       128: areturn
      StackMapTable: number_of_entries = 9
        frame_type = 254 /* append */
          offset_delta = 39
          locals = [ top, class scala/collection/immutable/ListSet, int ]
        frame_type = 2 /* same */
        frame_type = 14 /* same */
        frame_type = 2 /* same */
        frame_type = 14 /* same */
        frame_type = 2 /* same */
        frame_type = 26 /* same */
        frame_type = 2 /* same */
        frame_type = 255 /* full_frame */
          offset_delta = 17
          locals = [ class scala/collection/immutable/OldHashSet$OldHashSetCollision1, class scala/collection/immutable/OldHashSet, int, class "[Lscala/collection/immutable/OldHashSet;", int, class scala/collection/immutable/OldHashSet, class scala/collection/immutable/ListSet, int ]
          stack = []
      LineNumberTable:
        line 427: 0
        line 428: 20
        line 429: 27
        line 431: 33
        line 429: 39
        line 432: 42
        line 436: 51
        line 428: 57
        line 437: 60
        line 441: 69
        line 428: 75
        line 442: 78
        line 444: 84
        line 442: 105
        line 447: 108
        line 428: 126
      LocalVariableTable:
        Start  Length  Slot  Name   Signature
           20     108     6   ks1   Lscala/collection/immutable/ListSet;
            0     129     0  this   Lscala/collection/immutable/OldHashSet$OldHashSetCollision1;
            0     129     1  that   Lscala/collection/immutable/OldHashSet;
            0     129     2 level   I
            0     129     3 buffer   [Lscala/collection/immutable/OldHashSet;
            0     129     4 offset0   I
    Signature: #184                         // (Lscala/collection/immutable/OldHashSet<TA;>;I[Lscala/collection/immutable/OldHashSet<TA;>;I)Lscala/collection/immutable/OldHashSet<TA;>;
    MethodParameters:
      Name                           Flags
      that                           final
      level                          final
      buffer                         final
      offset0                        final

  public scala.collection.immutable.OldHashSet<A> diff0(scala.collection.immutable.OldHashSet<A>, int, scala.collection.immutable.OldHashSet<A>[], int);
    descriptor: (Lscala/collection/immutable/OldHashSet;I[Lscala/collection/immutable/OldHashSet;I)Lscala/collection/immutable/OldHashSet;
    flags: (0x0001) ACC_PUBLIC
    Code:
      stack=4, locals=8, args_size=5
         0: aload_0
         1: invokevirtual #40                 // Method ks:()Lscala/collection/immutable/ListSet;
         4: aload_0
         5: aload_1
         6: iload_2
         7: invokedynamic #202,  0            // InvokeDynamic #2:apply:(Lscala/collection/immutable/OldHashSet$OldHashSetCollision1;Lscala/collection/immutable/OldHashSet;I)Lscala/Function1;
        12: invokevirtual #133                // Method scala/collection/immutable/ListSet.filterNot:(Lscala/Function1;)Ljava/lang/Object;
        15: checkcast     #42                 // class scala/collection/immutable/ListSet
        18: astore        6
        20: aload         6
        22: invokevirtual #44                 // Method scala/collection/immutable/ListSet.size:()I
        25: istore        7
        27: iconst_0
        28: iload         7
        30: if_icmpne     39
        33: aconst_null
        34: astore        5
        36: goto          108
        39: goto          42
        42: iload         7
        44: aload_0
        45: invokevirtual #195                // Method size:()I
        48: if_icmpne     57
        51: aload_0
        52: astore        5
        54: goto          108
        57: goto          60
        60: iconst_1
        61: iload         7
        63: if_icmpne     87
        66: new           #19                 // class scala/collection/immutable/OldHashSet$OldHashSet1
        69: dup
        70: aload         6
        72: invokevirtual #100                // Method scala/collection/immutable/ListSet.head:()Ljava/lang/Object;
        75: aload_0
        76: invokevirtual #63                 // Method hash:()I
        79: invokespecial #88                 // Method scala/collection/immutable/OldHashSet$OldHashSet1."<init>":(Ljava/lang/Object;I)V
        82: astore        5
        84: goto          108
        87: goto          90
        90: new           #2                  // class scala/collection/immutable/OldHashSet$OldHashSetCollision1
        93: dup
        94: aload_0
        95: invokevirtual #63                 // Method hash:()I
        98: aload         6
       100: invokespecial #79                 // Method "<init>":(ILscala/collection/immutable/ListSet;)V
       103: astore        5
       105: goto          108
       108: aload         5
       110: areturn
      StackMapTable: number_of_entries = 7
        frame_type = 254 /* append */
          offset_delta = 39
          locals = [ top, class scala/collection/immutable/ListSet, int ]
        frame_type = 2 /* same */
        frame_type = 14 /* same */
        frame_type = 2 /* same */
        frame_type = 26 /* same */
        frame_type = 2 /* same */
        frame_type = 255 /* full_frame */
          offset_delta = 17
          locals = [ class scala/collection/immutable/OldHashSet$OldHashSetCollision1, class scala/collection/immutable/OldHashSet, int, class "[Lscala/collection/immutable/OldHashSet;", int, class scala/collection/immutable/OldHashSet$LeafOldHashSet, class scala/collection/immutable/ListSet, int ]
          stack = []
      LineNumberTable:
        line 452: 0
        line 453: 20
        line 454: 27
        line 456: 33
        line 454: 39
        line 457: 42
        line 461: 51
        line 453: 57
        line 462: 60
        line 464: 66
        line 462: 87
        line 467: 90
        line 453: 108
      LocalVariableTable:
        Start  Length  Slot  Name   Signature
           20      90     6   ks1   Lscala/collection/immutable/ListSet;
            0     111     0  this   Lscala/collection/immutable/OldHashSet$OldHashSetCollision1;
            0     111     1  that   Lscala/collection/immutable/OldHashSet;
            0     111     2 level   I
            0     111     3 buffer   [Lscala/collection/immutable/OldHashSet;
            0     111     4 offset0   I
    Signature: #184                         // (Lscala/collection/immutable/OldHashSet<TA;>;I[Lscala/collection/immutable/OldHashSet<TA;>;I)Lscala/collection/immutable/OldHashSet<TA;>;
    MethodParameters:
      Name                           Flags
      that                           final
      level                          final
      buffer                         final
      offset0                        final

  public static final boolean $anonfun$subsetOf0$1(scala.collection.immutable.OldHashSet$OldHashSetCollision1, scala.collection.immutable.OldHashSet, int, java.lang.Object);
    descriptor: (Lscala/collection/immutable/OldHashSet$OldHashSetCollision1;Lscala/collection/immutable/OldHashSet;ILjava/lang/Object;)Z
    flags: (0x1019) ACC_PUBLIC, ACC_STATIC, ACC_FINAL, ACC_SYNTHETIC
    Code:
      stack=4, locals=4, args_size=4
         0: aload_1
         1: aload_3
         2: aload_0
         3: invokevirtual #63                 // Method hash:()I
         6: iload_2
         7: invokevirtual #209                // Method scala/collection/immutable/OldHashSet.get0:(Ljava/lang/Object;II)Z
        10: ireturn
      LineNumberTable:
        line 378: 0
      LocalVariableTable:
        Start  Length  Slot  Name   Signature
            0      11     0 $this   Lscala/collection/immutable/OldHashSet$OldHashSetCollision1;
            0      11     1 that$1   Lscala/collection/immutable/OldHashSet;
            0      11     2 level$1   I
            0      11     3   key   Ljava/lang/Object;
    MethodParameters:
      Name                           Flags
      $this                          final synthetic
      that$1                         final
      level$1                        final
      key                            final

  public static final boolean $anonfun$intersect0$1(scala.collection.immutable.OldHashSet$OldHashSetCollision1, scala.collection.immutable.OldHashSet, int, java.lang.Object);
    descriptor: (Lscala/collection/immutable/OldHashSet$OldHashSetCollision1;Lscala/collection/immutable/OldHashSet;ILjava/lang/Object;)Z
    flags: (0x1019) ACC_PUBLIC, ACC_STATIC, ACC_FINAL, ACC_SYNTHETIC
    Code:
      stack=4, locals=4, args_size=4
         0: aload_1
         1: aload_3
         2: aload_0
         3: invokevirtual #63                 // Method hash:()I
         6: iload_2
         7: invokevirtual #209                // Method scala/collection/immutable/OldHashSet.get0:(Ljava/lang/Object;II)Z
        10: ireturn
      LineNumberTable:
        line 427: 0
      LocalVariableTable:
        Start  Length  Slot  Name   Signature
            0      11     0 $this   Lscala/collection/immutable/OldHashSet$OldHashSetCollision1;
            0      11     1 that$2   Lscala/collection/immutable/OldHashSet;
            0      11     2 level$2   I
            0      11     3   x$1   Ljava/lang/Object;
    MethodParameters:
      Name                           Flags
      $this                          final synthetic
      that$2                         final
      level$2                        final
      x$1                            final

  public static final boolean $anonfun$diff0$1(scala.collection.immutable.OldHashSet$OldHashSetCollision1, scala.collection.immutable.OldHashSet, int, java.lang.Object);
    descriptor: (Lscala/collection/immutable/OldHashSet$OldHashSetCollision1;Lscala/collection/immutable/OldHashSet;ILjava/lang/Object;)Z
    flags: (0x1019) ACC_PUBLIC, ACC_STATIC, ACC_FINAL, ACC_SYNTHETIC
    Code:
      stack=4, locals=4, args_size=4
         0: aload_1
         1: aload_3
         2: aload_0
         3: invokevirtual #63                 // Method hash:()I
         6: iload_2
         7: invokevirtual #209                // Method scala/collection/immutable/OldHashSet.get0:(Ljava/lang/Object;II)Z
        10: ireturn
      LineNumberTable:
        line 452: 0
      LocalVariableTable:
        Start  Length  Slot  Name   Signature
            0      11     0 $this   Lscala/collection/immutable/OldHashSet$OldHashSetCollision1;
            0      11     1 that$3   Lscala/collection/immutable/OldHashSet;
            0      11     2 level$3   I
            0      11     3   x$2   Ljava/lang/Object;
    MethodParameters:
      Name                           Flags
      $this                          final synthetic
      that$3                         final
      level$3                        final
      x$2                            final

  public scala.collection.immutable.OldHashSet$OldHashSetCollision1(int, scala.collection.immutable.ListSet<A>);
    descriptor: (ILscala/collection/immutable/ListSet;)V
    flags: (0x0001) ACC_PUBLIC
    Code:
      stack=2, locals=3, args_size=3
         0: aload_0
         1: iload_1
         2: putfield      #29                 // Field hash:I
         5: aload_0
         6: aload_2
         7: putfield      #35                 // Field ks:Lscala/collection/immutable/ListSet;
        10: aload_0
        11: invokespecial #221                // Method scala/collection/immutable/OldHashSet$LeafOldHashSet."<init>":()V
        14: return
      LineNumberTable:
        line 310: 0
      LocalVariableTable:
        Start  Length  Slot  Name   Signature
            0      15     0  this   Lscala/collection/immutable/OldHashSet$OldHashSetCollision1;
            0      15     1  hash   I
            0      15     2    ks   Lscala/collection/immutable/ListSet;
    Signature: #218                         // (ILscala/collection/immutable/ListSet<TA;>;)V
    MethodParameters:
      Name                           Flags
      hash                           final
      ks                             final

  public static final java.lang.Object $anonfun$subsetOf0$1$adapted(scala.collection.immutable.OldHashSet$OldHashSetCollision1, scala.collection.immutable.OldHashSet, int, java.lang.Object);
    descriptor: (Lscala/collection/immutable/OldHashSet$OldHashSetCollision1;Lscala/collection/immutable/OldHashSet;ILjava/lang/Object;)Ljava/lang/Object;
    flags: (0x1019) ACC_PUBLIC, ACC_STATIC, ACC_FINAL, ACC_SYNTHETIC
    Code:
      stack=4, locals=4, args_size=4
         0: aload_0
         1: aload_1
         2: iload_2
         3: aload_3
         4: invokestatic  #223                // Method $anonfun$subsetOf0$1:(Lscala/collection/immutable/OldHashSet$OldHashSetCollision1;Lscala/collection/immutable/OldHashSet;ILjava/lang/Object;)Z
         7: invokestatic  #229                // Method scala/runtime/BoxesRunTime.boxToBoolean:(Z)Ljava/lang/Boolean;
        10: areturn
      LineNumberTable:
        line 378: 0
      LocalVariableTable:
        Start  Length  Slot  Name   Signature
            0      11     0 $this   Lscala/collection/immutable/OldHashSet$OldHashSetCollision1;
            0      11     1 that$1   Lscala/collection/immutable/OldHashSet;
            0      11     2 level$1   I
            0      11     3   key   Ljava/lang/Object;
    MethodParameters:
      Name                           Flags
      $this                          final
      that$1                         final
      level$1                        final
      key                            final

  public static final java.lang.Object $anonfun$intersect0$1$adapted(scala.collection.immutable.OldHashSet$OldHashSetCollision1, scala.collection.immutable.OldHashSet, int, java.lang.Object);
    descriptor: (Lscala/collection/immutable/OldHashSet$OldHashSetCollision1;Lscala/collection/immutable/OldHashSet;ILjava/lang/Object;)Ljava/lang/Object;
    flags: (0x1019) ACC_PUBLIC, ACC_STATIC, ACC_FINAL, ACC_SYNTHETIC
    Code:
      stack=4, locals=4, args_size=4
         0: aload_0
         1: aload_1
         2: iload_2
         3: aload_3
         4: invokestatic  #231                // Method $anonfun$intersect0$1:(Lscala/collection/immutable/OldHashSet$OldHashSetCollision1;Lscala/collection/immutable/OldHashSet;ILjava/lang/Object;)Z
         7: invokestatic  #229                // Method scala/runtime/BoxesRunTime.boxToBoolean:(Z)Ljava/lang/Boolean;
        10: areturn
      LineNumberTable:
        line 427: 0
      LocalVariableTable:
        Start  Length  Slot  Name   Signature
            0      11     0 $this   Lscala/collection/immutable/OldHashSet$OldHashSetCollision1;
            0      11     1 that$2   Lscala/collection/immutable/OldHashSet;
            0      11     2 level$2   I
            0      11     3   x$1   Ljava/lang/Object;
    MethodParameters:
      Name                           Flags
      $this                          final
      that$2                         final
      level$2                        final
      x$1                            final

  public static final java.lang.Object $anonfun$diff0$1$adapted(scala.collection.immutable.OldHashSet$OldHashSetCollision1, scala.collection.immutable.OldHashSet, int, java.lang.Object);
    descriptor: (Lscala/collection/immutable/OldHashSet$OldHashSetCollision1;Lscala/collection/immutable/OldHashSet;ILjava/lang/Object;)Ljava/lang/Object;
    flags: (0x1019) ACC_PUBLIC, ACC_STATIC, ACC_FINAL, ACC_SYNTHETIC
    Code:
      stack=4, locals=4, args_size=4
         0: aload_0
         1: aload_1
         2: iload_2
         3: aload_3
         4: invokestatic  #233                // Method $anonfun$diff0$1:(Lscala/collection/immutable/OldHashSet$OldHashSetCollision1;Lscala/collection/immutable/OldHashSet;ILjava/lang/Object;)Z
         7: invokestatic  #229                // Method scala/runtime/BoxesRunTime.boxToBoolean:(Z)Ljava/lang/Boolean;
        10: areturn
      LineNumberTable:
        line 452: 0
      LocalVariableTable:
        Start  Length  Slot  Name   Signature
            0      11     0 $this   Lscala/collection/immutable/OldHashSet$OldHashSetCollision1;
            0      11     1 that$3   Lscala/collection/immutable/OldHashSet;
            0      11     2 level$3   I
            0      11     3   x$2   Ljava/lang/Object;
    MethodParameters:
      Name                           Flags
      $this                          final
      that$3                         final
      level$3                        final
      x$2                            final

  private static java.lang.Object $deserializeLambda$(java.lang.invoke.SerializedLambda);
    descriptor: (Ljava/lang/invoke/SerializedLambda;)Ljava/lang/Object;
    flags: (0x100a) ACC_PRIVATE, ACC_STATIC, ACC_SYNTHETIC
    Code:
      stack=1, locals=1, args_size=1
         0: aload_0
         1: invokedynamic #245,  0            // InvokeDynamic #3:lambdaDeserialize:(Ljava/lang/invoke/SerializedLambda;)Ljava/lang/Object;
         6: areturn
}
InnerClasses:
  public static final #11= #8 of #10;     // Lookup=class java/lang/invoke/MethodHandles$Lookup of class java/lang/invoke/MethodHandles
  public static final #16= #13 of #15;    // HashTrieSet=class scala/collection/immutable/OldHashSet$HashTrieSet of class scala/collection/immutable/OldHashSet
  public static abstract #17= #5 of #15;  // LeafOldHashSet=class scala/collection/immutable/OldHashSet$LeafOldHashSet of class scala/collection/immutable/OldHashSet
  public static final #20= #19 of #15;    // OldHashSet1=class scala/collection/immutable/OldHashSet$OldHashSet1 of class scala/collection/immutable/OldHashSet
  public static final #21= #2 of #15;     // OldHashSetCollision1=class scala/collection/immutable/OldHashSet$OldHashSetCollision1 of class scala/collection/immutable/OldHashSet
Signature: #3                           // <A:Ljava/lang/Object;>Lscala/collection/immutable/OldHashSet$LeafOldHashSet<TA;>;
SourceFile: "OldHashSet.scala"
BootstrapMethods:
  0: #157 REF_invokeStatic java/lang/invoke/LambdaMetafactory.altMetafactory:(Ljava/lang/invoke/MethodHandles$Lookup;Ljava/lang/String;Ljava/lang/invoke/MethodType;[Ljava/lang/Object;)Ljava/lang/invoke/CallSite;
    Method arguments:
      #144 (Ljava/lang/Object;)Ljava/lang/Object;
      #149 REF_invokeStatic scala/collection/immutable/OldHashSet$OldHashSetCollision1.$anonfun$subsetOf0$1$adapted:(Lscala/collection/immutable/OldHashSet$OldHashSetCollision1;Lscala/collection/immutable/OldHashSet;ILjava/lang/Object;)Ljava/lang/Object;
      #144 (Ljava/lang/Object;)Ljava/lang/Object;
      #150 1
  1: #157 REF_invokeStatic java/lang/invoke/LambdaMetafactory.altMetafactory:(Ljava/lang/invoke/MethodHandles$Lookup;Ljava/lang/String;Ljava/lang/invoke/MethodType;[Ljava/lang/Object;)Ljava/lang/invoke/CallSite;
    Method arguments:
      #144 (Ljava/lang/Object;)Ljava/lang/Object;
      #193 REF_invokeStatic scala/collection/immutable/OldHashSet$OldHashSetCollision1.$anonfun$intersect0$1$adapted:(Lscala/collection/immutable/OldHashSet$OldHashSetCollision1;Lscala/collection/immutable/OldHashSet;ILjava/lang/Object;)Ljava/lang/Object;
      #144 (Ljava/lang/Object;)Ljava/lang/Object;
      #150 1
  2: #157 REF_invokeStatic java/lang/invoke/LambdaMetafactory.altMetafactory:(Ljava/lang/invoke/MethodHandles$Lookup;Ljava/lang/String;Ljava/lang/invoke/MethodType;[Ljava/lang/Object;)Ljava/lang/invoke/CallSite;
    Method arguments:
      #144 (Ljava/lang/Object;)Ljava/lang/Object;
      #201 REF_invokeStatic scala/collection/immutable/OldHashSet$OldHashSetCollision1.$anonfun$diff0$1$adapted:(Lscala/collection/immutable/OldHashSet$OldHashSetCollision1;Lscala/collection/immutable/OldHashSet;ILjava/lang/Object;)Ljava/lang/Object;
      #144 (Ljava/lang/Object;)Ljava/lang/Object;
      #150 1
  3: #242 REF_invokeStatic scala/runtime/LambdaDeserialize.bootstrap:(Ljava/lang/invoke/MethodHandles$Lookup;Ljava/lang/String;Ljava/lang/invoke/MethodType;[Ljava/lang/invoke/MethodHandle;)Ljava/lang/invoke/CallSite;
    Method arguments:
      #201 REF_invokeStatic scala/collection/immutable/OldHashSet$OldHashSetCollision1.$anonfun$diff0$1$adapted:(Lscala/collection/immutable/OldHashSet$OldHashSetCollision1;Lscala/collection/immutable/OldHashSet;ILjava/lang/Object;)Ljava/lang/Object;
      #193 REF_invokeStatic scala/collection/immutable/OldHashSet$OldHashSetCollision1.$anonfun$intersect0$1$adapted:(Lscala/collection/immutable/OldHashSet$OldHashSetCollision1;Lscala/collection/immutable/OldHashSet;ILjava/lang/Object;)Ljava/lang/Object;
      #149 REF_invokeStatic scala/collection/immutable/OldHashSet$OldHashSetCollision1.$anonfun$subsetOf0$1$adapted:(Lscala/collection/immutable/OldHashSet$OldHashSetCollision1;Lscala/collection/immutable/OldHashSet;ILjava/lang/Object;)Ljava/lang/Object;
  ScalaInlineInfo: length = 0x7C (unknown attribute)
   01 01 00 18 00 D6 00 CC 01 00 C6 00 92 01 00 D2
   00 CC 01 00 BE 00 92 01 00 CB 00 CC 01 00 91 00
   92 01 00 4C 00 4D 01 00 C5 00 B7 01 00 7B 00 7C
   01 00 32 00 33 01 00 39 00 3A 01 00 16 00 1B 01
   00 BD 00 B7 01 00 24 00 25 01 00 2D 00 2E 01 00
   18 00 20 01 00 75 00 76 01 00 5D 00 46 01 00 26
   00 1B 01 00 8B 00 8C 01 00 A7 00 A8 01 00 A7 00
   B7 01 00 45 00 46 01 00 66 00 67 01
  Scala: length = 0x0 (unknown attribute)

