Classfile /Users/mw/Projects/slang-braindump/.jar/jar11/assemble/slang-braindump/assemble/content/scala/collection/immutable/Range$Partial$.class
  Last modified May 29, 2022; size 2047 bytes
  SHA-256 checksum 1b74e99eee96fad2410042e6e0bfded36024979e5a5938014451c9872ffedec8
  Compiled from "Range.scala"
public class scala.collection.immutable.Range$Partial$
  minor version: 0
  major version: 52
  flags: (0x0021) ACC_PUBLIC, ACC_SUPER
  this_class: #2                          // scala/collection/immutable/Range$Partial$
  super_class: #4                         // java/lang/Object
  interfaces: 0, fields: 1, methods: 6, attributes: 4
Constant pool:
   #1 = Utf8               scala/collection/immutable/Range$Partial$
   #2 = Class              #1             // scala/collection/immutable/Range$Partial$
   #3 = Utf8               java/lang/Object
   #4 = Class              #3             // java/lang/Object
   #5 = Utf8               Range.scala
   #6 = Utf8               scala/collection/immutable/Range$Partial
   #7 = Class              #6             // scala/collection/immutable/Range$Partial
   #8 = Utf8               scala/collection/immutable/Range
   #9 = Class              #8             // scala/collection/immutable/Range
  #10 = Utf8               Partial
  #11 = Utf8               Partial$
  #12 = Utf8               MODULE$
  #13 = Utf8               Lscala/collection/immutable/Range$Partial$;
  #14 = Utf8               <clinit>
  #15 = Utf8               ()V
  #16 = Utf8               <init>
  #17 = NameAndType        #16:#15        // "<init>":()V
  #18 = Methodref          #2.#17         // scala/collection/immutable/Range$Partial$."<init>":()V
  #19 = NameAndType        #12:#13        // MODULE$:Lscala/collection/immutable/Range$Partial$;
  #20 = Fieldref           #2.#19         // scala/collection/immutable/Range$Partial$.MODULE$:Lscala/collection/immutable/Range$Partial$;
  #21 = Utf8               by$extension
  #22 = Utf8               (Lscala/Function1;Ljava/lang/Object;)Ljava/lang/Object;
  #23 = Utf8               <T:Ljava/lang/Object;U:Ljava/lang/Object;>(Lscala/Function1<TT;TU;>;TT;)TU;
  #24 = Utf8               $this
  #25 = Utf8               x
  #26 = Utf8               scala/Function1
  #27 = Class              #26            // scala/Function1
  #28 = Utf8               apply
  #29 = Utf8               (Ljava/lang/Object;)Ljava/lang/Object;
  #30 = NameAndType        #28:#29        // apply:(Ljava/lang/Object;)Ljava/lang/Object;
  #31 = InterfaceMethodref #27.#30        // scala/Function1.apply:(Ljava/lang/Object;)Ljava/lang/Object;
  #32 = Utf8               this
  #33 = Utf8               Lscala/Function1;
  #34 = Utf8               Ljava/lang/Object;
  #35 = Utf8               toString$extension
  #36 = Utf8               (Lscala/Function1;)Ljava/lang/String;
  #37 = Utf8               <T:Ljava/lang/Object;U:Ljava/lang/Object;>(Lscala/Function1<TT;TU;>;)Ljava/lang/String;
  #38 = Utf8               Range requires step
  #39 = String             #38            // Range requires step
  #40 = Utf8               hashCode$extension
  #41 = Utf8               (Lscala/Function1;)I
  #42 = Utf8               <T:Ljava/lang/Object;U:Ljava/lang/Object;>(Lscala/Function1<TT;TU;>;)I
  #43 = Utf8               hashCode
  #44 = Utf8               ()I
  #45 = NameAndType        #43:#44        // hashCode:()I
  #46 = Methodref          #4.#45         // java/lang/Object.hashCode:()I
  #47 = Utf8               equals$extension
  #48 = Utf8               (Lscala/Function1;Ljava/lang/Object;)Z
  #49 = Utf8               <T:Ljava/lang/Object;U:Ljava/lang/Object;>(Lscala/Function1<TT;TU;>;Ljava/lang/Object;)Z
  #50 = Utf8               x$1
  #51 = Utf8               scala$collection$immutable$Range$Partial$$f
  #52 = Utf8               ()Lscala/Function1;
  #53 = NameAndType        #51:#52        // scala$collection$immutable$Range$Partial$$f:()Lscala/Function1;
  #54 = Methodref          #7.#53         // scala/collection/immutable/Range$Partial.scala$collection$immutable$Range$Partial$$f:()Lscala/Function1;
  #55 = Utf8               equals
  #56 = Utf8               (Ljava/lang/Object;)Z
  #57 = NameAndType        #55:#56        // equals:(Ljava/lang/Object;)Z
  #58 = Methodref          #4.#57         // java/lang/Object.equals:(Ljava/lang/Object;)Z
  #59 = Methodref          #4.#17         // java/lang/Object."<init>":()V
  #60 = Utf8               Code
  #61 = Utf8               LineNumberTable
  #62 = Utf8               LocalVariableTable
  #63 = Utf8               Signature
  #64 = Utf8               MethodParameters
  #65 = Utf8               StackMapTable
  #66 = Utf8               InnerClasses
  #67 = Utf8               SourceFile
  #68 = Utf8               ScalaInlineInfo
  #69 = Utf8               Scala
{
  public static final scala.collection.immutable.Range$Partial$ MODULE$;
    descriptor: Lscala/collection/immutable/Range$Partial$;
    flags: (0x0019) ACC_PUBLIC, ACC_STATIC, ACC_FINAL

  public static {};
    descriptor: ()V
    flags: (0x0009) ACC_PUBLIC, ACC_STATIC
    Code:
      stack=2, locals=0, args_size=0
         0: new           #2                  // class scala/collection/immutable/Range$Partial$
         3: dup
         4: invokespecial #18                 // Method "<init>":()V
         7: putstatic     #20                 // Field MODULE$:Lscala/collection/immutable/Range$Partial$;
        10: return
      LineNumberTable:
        line 616: 0

  public final <T extends java.lang.Object, U extends java.lang.Object> U by$extension(scala.Function1<T, U>, T);
    descriptor: (Lscala/Function1;Ljava/lang/Object;)Ljava/lang/Object;
    flags: (0x0011) ACC_PUBLIC, ACC_FINAL
    Code:
      stack=2, locals=3, args_size=3
         0: aload_1
         1: aload_2
         2: invokeinterface #31,  2           // InterfaceMethod scala/Function1.apply:(Ljava/lang/Object;)Ljava/lang/Object;
         7: areturn
      LineNumberTable:
        line 617: 0
      LocalVariableTable:
        Start  Length  Slot  Name   Signature
            0       8     0  this   Lscala/collection/immutable/Range$Partial$;
            0       8     1 $this   Lscala/Function1;
            0       8     2     x   Ljava/lang/Object;
    Signature: #23                          // <T:Ljava/lang/Object;U:Ljava/lang/Object;>(Lscala/Function1<TT;TU;>;TT;)TU;
    MethodParameters:
      Name                           Flags
      $this                          final
      x                              final

  public final <T extends java.lang.Object, U extends java.lang.Object> java.lang.String toString$extension(scala.Function1<T, U>);
    descriptor: (Lscala/Function1;)Ljava/lang/String;
    flags: (0x0011) ACC_PUBLIC, ACC_FINAL
    Code:
      stack=1, locals=2, args_size=2
         0: ldc           #39                 // String Range requires step
         2: areturn
      LineNumberTable:
        line 618: 0
      LocalVariableTable:
        Start  Length  Slot  Name   Signature
            0       3     0  this   Lscala/collection/immutable/Range$Partial$;
            0       3     1 $this   Lscala/Function1;
    Signature: #37                          // <T:Ljava/lang/Object;U:Ljava/lang/Object;>(Lscala/Function1<TT;TU;>;)Ljava/lang/String;
    MethodParameters:
      Name                           Flags
      $this                          final

  public final <T extends java.lang.Object, U extends java.lang.Object> int hashCode$extension(scala.Function1<T, U>);
    descriptor: (Lscala/Function1;)I
    flags: (0x0011) ACC_PUBLIC, ACC_FINAL
    Code:
      stack=1, locals=2, args_size=2
         0: aload_1
         1: invokevirtual #46                 // Method java/lang/Object.hashCode:()I
         4: ireturn
      LineNumberTable:
        line 616: 0
      LocalVariableTable:
        Start  Length  Slot  Name   Signature
            0       5     0  this   Lscala/collection/immutable/Range$Partial$;
            0       5     1 $this   Lscala/Function1;
    Signature: #42                          // <T:Ljava/lang/Object;U:Ljava/lang/Object;>(Lscala/Function1<TT;TU;>;)I
    MethodParameters:
      Name                           Flags
      $this                          final

  public final <T extends java.lang.Object, U extends java.lang.Object> boolean equals$extension(scala.Function1<T, U>, java.lang.Object);
    descriptor: (Lscala/Function1;Ljava/lang/Object;)Z
    flags: (0x0011) ACC_PUBLIC, ACC_FINAL
    Code:
      stack=2, locals=5, args_size=3
         0: aload_2
         1: instanceof    #7                  // class scala/collection/immutable/Range$Partial
         4: ifeq          12
         7: iconst_1
         8: istore_3
         9: goto          14
        12: iconst_0
        13: istore_3
        14: iload_3
        15: ifeq          67
        18: aload_2
        19: ifnonnull     26
        22: aconst_null
        23: goto          33
        26: aload_2
        27: checkcast     #7                  // class scala/collection/immutable/Range$Partial
        30: invokevirtual #54                 // Method scala/collection/immutable/Range$Partial.scala$collection$immutable$Range$Partial$$f:()Lscala/Function1;
        33: astore        4
        35: aload_1
        36: dup
        37: ifnonnull     49
        40: pop
        41: aload         4
        43: ifnull        57
        46: goto          61
        49: aload         4
        51: invokevirtual #58                 // Method java/lang/Object.equals:(Ljava/lang/Object;)Z
        54: ifeq          61
        57: iconst_1
        58: goto          62
        61: iconst_0
        62: ifeq          67
        65: iconst_1
        66: ireturn
        67: iconst_0
        68: ireturn
      StackMapTable: number_of_entries = 9
        frame_type = 12 /* same */
        frame_type = 252 /* append */
          offset_delta = 1
          locals = [ int ]
        frame_type = 11 /* same */
        frame_type = 70 /* same_locals_1_stack_item */
          stack = [ class scala/Function1 ]
        frame_type = 255 /* full_frame */
          offset_delta = 15
          locals = [ class scala/collection/immutable/Range$Partial$, class scala/Function1, class java/lang/Object, int, class scala/Function1 ]
          stack = [ class scala/Function1 ]
        frame_type = 7 /* same */
        frame_type = 3 /* same */
        frame_type = 64 /* same_locals_1_stack_item */
          stack = [ int ]
        frame_type = 250 /* chop */
          offset_delta = 4
      LineNumberTable:
        line 616: 0
      LocalVariableTable:
        Start  Length  Slot  Name   Signature
            0      69     0  this   Lscala/collection/immutable/Range$Partial$;
            0      69     1 $this   Lscala/Function1;
            0      69     2   x$1   Ljava/lang/Object;
    Signature: #49                          // <T:Ljava/lang/Object;U:Ljava/lang/Object;>(Lscala/Function1<TT;TU;>;Ljava/lang/Object;)Z
    MethodParameters:
      Name                           Flags
      $this                          final
      x$1                            final

  public scala.collection.immutable.Range$Partial$();
    descriptor: ()V
    flags: (0x0001) ACC_PUBLIC
    Code:
      stack=1, locals=1, args_size=1
         0: aload_0
         1: invokespecial #59                 // Method java/lang/Object."<init>":()V
         4: return
      LineNumberTable:
        line 616: 0
      LocalVariableTable:
        Start  Length  Slot  Name   Signature
            0       5     0  this   Lscala/collection/immutable/Range$Partial$;
}
InnerClasses:
  public static final #10= #7 of #9;      // Partial=class scala/collection/immutable/Range$Partial of class scala/collection/immutable/Range
  public static #11= #2 of #9;            // Partial$=class scala/collection/immutable/Range$Partial$ of class scala/collection/immutable/Range
SourceFile: "Range.scala"
  ScalaInlineInfo: length = 0x1D (unknown attribute)
   01 01 00 05 00 10 00 0F 01 00 15 00 16 01 00 2F
   00 30 01 00 28 00 29 01 00 23 00 24 01
  Scala: length = 0x0 (unknown attribute)

