Classfile /Users/mw/Projects/slang-braindump/.jar/jar11/assemble/slang-braindump/assemble/content/scala/collection/immutable/SeqMap$SeqMapBuilderImpl.class
  Last modified May 29, 2022; size 6205 bytes
  SHA-256 checksum cb93bd304b200a229d048c12fd6b0ba0fb17fa7f09cfbd922600db3dfb84eb6e
  Compiled from "SeqMap.scala"
public final class scala.collection.immutable.SeqMap$SeqMapBuilderImpl<K extends java.lang.Object, V extends java.lang.Object> extends java.lang.Object implements scala.collection.mutable.ReusableBuilder<scala.Tuple2<K, V>, scala.collection.immutable.SeqMap<K, V>>
  minor version: 0
  major version: 52
  flags: (0x0031) ACC_PUBLIC, ACC_FINAL, ACC_SUPER
  this_class: #2                          // scala/collection/immutable/SeqMap$SeqMapBuilderImpl
  super_class: #5                         // java/lang/Object
  interfaces: 1, fields: 3, methods: 17, attributes: 5
Constant pool:
    #1 = Utf8               scala/collection/immutable/SeqMap$SeqMapBuilderImpl
    #2 = Class              #1            // scala/collection/immutable/SeqMap$SeqMapBuilderImpl
    #3 = Utf8               <K:Ljava/lang/Object;V:Ljava/lang/Object;>Ljava/lang/Object;Lscala/collection/mutable/ReusableBuilder<Lscala/Tuple2<TK;TV;>;Lscala/collection/immutable/SeqMap<TK;TV;>;>;
    #4 = Utf8               java/lang/Object
    #5 = Class              #4            // java/lang/Object
    #6 = Utf8               scala/collection/mutable/ReusableBuilder
    #7 = Class              #6            // scala/collection/mutable/ReusableBuilder
    #8 = Utf8               SeqMap.scala
    #9 = Utf8               scala/collection/immutable/SeqMap$EmptySeqMap$
   #10 = Class              #9            // scala/collection/immutable/SeqMap$EmptySeqMap$
   #11 = Utf8               scala/collection/immutable/SeqMap
   #12 = Class              #11           // scala/collection/immutable/SeqMap
   #13 = Utf8               EmptySeqMap$
   #14 = Utf8               scala/collection/immutable/SeqMap$SeqMap4
   #15 = Class              #14           // scala/collection/immutable/SeqMap$SeqMap4
   #16 = Utf8               SeqMap4
   #17 = Utf8               SeqMapBuilderImpl
   #18 = Utf8               elems
   #19 = Utf8               Lscala/collection/immutable/SeqMap;
   #20 = Utf8               Lscala/collection/immutable/SeqMap<TK;TV;>;
   #21 = Utf8               switchedToVectorMapBuilder
   #22 = Utf8               Z
   #23 = Utf8               vectorMapBuilder
   #24 = Utf8               Lscala/collection/immutable/VectorMapBuilder;
   #25 = Utf8               Lscala/collection/immutable/VectorMapBuilder<TK;TV;>;
   #26 = Utf8               sizeHint
   #27 = Utf8               (I)V
   #28 = Utf8               size
   #29 = Utf8               scala/collection/mutable/Builder
   #30 = Class              #29           // scala/collection/mutable/Builder
   #31 = Utf8               sizeHint$
   #32 = Utf8               (Lscala/collection/mutable/Builder;I)V
   #33 = NameAndType        #31:#32       // sizeHint$:(Lscala/collection/mutable/Builder;I)V
   #34 = InterfaceMethodref #30.#33       // scala/collection/mutable/Builder.sizeHint$:(Lscala/collection/mutable/Builder;I)V
   #35 = Utf8               this
   #36 = Utf8               Lscala/collection/immutable/SeqMap$SeqMapBuilderImpl;
   #37 = Utf8               I
   #38 = Utf8               (Lscala/collection/IterableOnce;I)V
   #39 = Utf8               (Lscala/collection/IterableOnce<*>;I)V
   #40 = Utf8               coll
   #41 = Utf8               delta
   #42 = Utf8               (Lscala/collection/mutable/Builder;Lscala/collection/IterableOnce;I)V
   #43 = NameAndType        #31:#42       // sizeHint$:(Lscala/collection/mutable/Builder;Lscala/collection/IterableOnce;I)V
   #44 = InterfaceMethodref #30.#43       // scala/collection/mutable/Builder.sizeHint$:(Lscala/collection/mutable/Builder;Lscala/collection/IterableOnce;I)V
   #45 = Utf8               Lscala/collection/IterableOnce;
   #46 = Utf8               sizeHint$default$2
   #47 = Utf8               ()I
   #48 = Utf8               sizeHint$default$2$
   #49 = Utf8               (Lscala/collection/mutable/Builder;)I
   #50 = NameAndType        #48:#49       // sizeHint$default$2$:(Lscala/collection/mutable/Builder;)I
   #51 = InterfaceMethodref #30.#50       // scala/collection/mutable/Builder.sizeHint$default$2$:(Lscala/collection/mutable/Builder;)I
   #52 = Utf8               sizeHintBounded
   #53 = Utf8               (ILscala/collection/Iterable;)V
   #54 = Utf8               (ILscala/collection/Iterable<*>;)V
   #55 = Utf8               boundingColl
   #56 = Utf8               sizeHintBounded$
   #57 = Utf8               (Lscala/collection/mutable/Builder;ILscala/collection/Iterable;)V
   #58 = NameAndType        #56:#57       // sizeHintBounded$:(Lscala/collection/mutable/Builder;ILscala/collection/Iterable;)V
   #59 = InterfaceMethodref #30.#58       // scala/collection/mutable/Builder.sizeHintBounded$:(Lscala/collection/mutable/Builder;ILscala/collection/Iterable;)V
   #60 = Utf8               Lscala/collection/Iterable;
   #61 = Utf8               mapResult
   #62 = Utf8               (Lscala/Function1;)Lscala/collection/mutable/Builder;
   #63 = Utf8               <NewTo:Ljava/lang/Object;>(Lscala/Function1<Lscala/collection/immutable/SeqMap<TK;TV;>;TNewTo;>;)Lscala/collection/mutable/Builder<Lscala/Tuple2<TK;TV;>;TNewTo;>;
   #64 = Utf8               f
   #65 = Utf8               mapResult$
   #66 = Utf8               (Lscala/collection/mutable/Builder;Lscala/Function1;)Lscala/collection/mutable/Builder;
   #67 = NameAndType        #65:#66       // mapResult$:(Lscala/collection/mutable/Builder;Lscala/Function1;)Lscala/collection/mutable/Builder;
   #68 = InterfaceMethodref #30.#67       // scala/collection/mutable/Builder.mapResult$:(Lscala/collection/mutable/Builder;Lscala/Function1;)Lscala/collection/mutable/Builder;
   #69 = Utf8               Lscala/Function1;
   #70 = Utf8               $plus$eq
   #71 = Utf8               (Ljava/lang/Object;)Lscala/collection/mutable/Growable;
   #72 = Utf8               elem
   #73 = Utf8               scala/collection/mutable/Growable
   #74 = Class              #73           // scala/collection/mutable/Growable
   #75 = Utf8               $plus$eq$
   #76 = Utf8               (Lscala/collection/mutable/Growable;Ljava/lang/Object;)Lscala/collection/mutable/Growable;
   #77 = NameAndType        #75:#76       // $plus$eq$:(Lscala/collection/mutable/Growable;Ljava/lang/Object;)Lscala/collection/mutable/Growable;
   #78 = InterfaceMethodref #74.#77       // scala/collection/mutable/Growable.$plus$eq$:(Lscala/collection/mutable/Growable;Ljava/lang/Object;)Lscala/collection/mutable/Growable;
   #79 = Utf8               Ljava/lang/Object;
   #80 = Utf8               (Ljava/lang/Object;Ljava/lang/Object;Lscala/collection/immutable/Seq;)Lscala/collection/mutable/Growable;
   #81 = Utf8               elem1
   #82 = Utf8               elem2
   #83 = Utf8               (Lscala/collection/mutable/Growable;Ljava/lang/Object;Ljava/lang/Object;Lscala/collection/immutable/Seq;)Lscala/collection/mutable/Growable;
   #84 = NameAndType        #75:#83       // $plus$eq$:(Lscala/collection/mutable/Growable;Ljava/lang/Object;Ljava/lang/Object;Lscala/collection/immutable/Seq;)Lscala/collection/mutable/Growable;
   #85 = InterfaceMethodref #74.#84       // scala/collection/mutable/Growable.$plus$eq$:(Lscala/collection/mutable/Growable;Ljava/lang/Object;Ljava/lang/Object;Lscala/collection/immutable/Seq;)Lscala/collection/mutable/Growable;
   #86 = Utf8               Lscala/collection/immutable/Seq;
   #87 = Utf8               $plus$plus$eq
   #88 = Utf8               (Lscala/collection/IterableOnce;)Lscala/collection/mutable/Growable;
   #89 = Utf8               (Lscala/collection/IterableOnce<Lscala/Tuple2<TK;TV;>;>;)Lscala/collection/mutable/Growable<Lscala/Tuple2<TK;TV;>;>;
   #90 = Utf8               xs
   #91 = Utf8               $plus$plus$eq$
   #92 = Utf8               (Lscala/collection/mutable/Growable;Lscala/collection/IterableOnce;)Lscala/collection/mutable/Growable;
   #93 = NameAndType        #91:#92       // $plus$plus$eq$:(Lscala/collection/mutable/Growable;Lscala/collection/IterableOnce;)Lscala/collection/mutable/Growable;
   #94 = InterfaceMethodref #74.#93       // scala/collection/mutable/Growable.$plus$plus$eq$:(Lscala/collection/mutable/Growable;Lscala/collection/IterableOnce;)Lscala/collection/mutable/Growable;
   #95 = Utf8               knownSize
   #96 = Utf8               knownSize$
   #97 = Utf8               (Lscala/collection/mutable/Growable;)I
   #98 = NameAndType        #96:#97       // knownSize$:(Lscala/collection/mutable/Growable;)I
   #99 = InterfaceMethodref #74.#98       // scala/collection/mutable/Growable.knownSize$:(Lscala/collection/mutable/Growable;)I
  #100 = Utf8               clear
  #101 = Utf8               ()V
  #102 = Utf8               scala/collection/immutable/SeqMap$
  #103 = Class              #102          // scala/collection/immutable/SeqMap$
  #104 = Utf8               MODULE$
  #105 = Utf8               Lscala/collection/immutable/SeqMap$;
  #106 = NameAndType        #104:#105     // MODULE$:Lscala/collection/immutable/SeqMap$;
  #107 = Fieldref           #103.#106     // scala/collection/immutable/SeqMap$.MODULE$:Lscala/collection/immutable/SeqMap$;
  #108 = Utf8               Lscala/collection/immutable/SeqMap$EmptySeqMap$;
  #109 = NameAndType        #104:#108     // MODULE$:Lscala/collection/immutable/SeqMap$EmptySeqMap$;
  #110 = Fieldref           #10.#109      // scala/collection/immutable/SeqMap$EmptySeqMap$.MODULE$:Lscala/collection/immutable/SeqMap$EmptySeqMap$;
  #111 = NameAndType        #18:#19       // elems:Lscala/collection/immutable/SeqMap;
  #112 = Fieldref           #2.#111       // scala/collection/immutable/SeqMap$SeqMapBuilderImpl.elems:Lscala/collection/immutable/SeqMap;
  #113 = NameAndType        #23:#24       // vectorMapBuilder:Lscala/collection/immutable/VectorMapBuilder;
  #114 = Fieldref           #2.#113       // scala/collection/immutable/SeqMap$SeqMapBuilderImpl.vectorMapBuilder:Lscala/collection/immutable/VectorMapBuilder;
  #115 = Utf8               scala/collection/immutable/VectorMapBuilder
  #116 = Class              #115          // scala/collection/immutable/VectorMapBuilder
  #117 = NameAndType        #100:#101     // clear:()V
  #118 = Methodref          #116.#117     // scala/collection/immutable/VectorMapBuilder.clear:()V
  #119 = NameAndType        #21:#22       // switchedToVectorMapBuilder:Z
  #120 = Fieldref           #2.#119       // scala/collection/immutable/SeqMap$SeqMapBuilderImpl.switchedToVectorMapBuilder:Z
  #121 = Utf8               result
  #122 = Utf8               ()Lscala/collection/immutable/SeqMap;
  #123 = Utf8               ()Lscala/collection/immutable/SeqMap<TK;TV;>;
  #124 = Utf8               ()Lscala/collection/immutable/VectorMap;
  #125 = NameAndType        #121:#124     // result:()Lscala/collection/immutable/VectorMap;
  #126 = Methodref          #116.#125     // scala/collection/immutable/VectorMapBuilder.result:()Lscala/collection/immutable/VectorMap;
  #127 = Utf8               addOne
  #128 = Utf8               (Lscala/Tuple2;)Lscala/collection/immutable/SeqMap$SeqMapBuilderImpl;
  #129 = Utf8               (Lscala/Tuple2<TK;TV;>;)Lscala/collection/immutable/SeqMap$SeqMapBuilderImpl<TK;TV;>;
  #130 = Utf8               (Lscala/Tuple2;)Lscala/collection/immutable/VectorMapBuilder;
  #131 = NameAndType        #127:#130     // addOne:(Lscala/Tuple2;)Lscala/collection/immutable/VectorMapBuilder;
  #132 = Methodref          #116.#131     // scala/collection/immutable/VectorMapBuilder.addOne:(Lscala/Tuple2;)Lscala/collection/immutable/VectorMapBuilder;
  #133 = NameAndType        #28:#47       // size:()I
  #134 = InterfaceMethodref #12.#133      // scala/collection/immutable/SeqMap.size:()I
  #135 = Utf8               $plus
  #136 = Utf8               (Lscala/Tuple2;)Lscala/collection/immutable/MapOps;
  #137 = NameAndType        #135:#136     // $plus:(Lscala/Tuple2;)Lscala/collection/immutable/MapOps;
  #138 = InterfaceMethodref #12.#137      // scala/collection/immutable/SeqMap.$plus:(Lscala/Tuple2;)Lscala/collection/immutable/MapOps;
  #139 = Utf8               scala/Tuple2
  #140 = Class              #139          // scala/Tuple2
  #141 = Utf8               _1
  #142 = Utf8               ()Ljava/lang/Object;
  #143 = NameAndType        #141:#142     // _1:()Ljava/lang/Object;
  #144 = Methodref          #140.#143     // scala/Tuple2._1:()Ljava/lang/Object;
  #145 = Utf8               contains
  #146 = Utf8               (Ljava/lang/Object;)Z
  #147 = NameAndType        #145:#146     // contains:(Ljava/lang/Object;)Z
  #148 = InterfaceMethodref #12.#147      // scala/collection/immutable/SeqMap.contains:(Ljava/lang/Object;)Z
  #149 = Utf8               <init>
  #150 = NameAndType        #149:#101     // "<init>":()V
  #151 = Methodref          #116.#150     // scala/collection/immutable/VectorMapBuilder."<init>":()V
  #152 = Utf8               buildTo
  #153 = Utf8               (Lscala/collection/mutable/Builder;)Lscala/collection/mutable/Builder;
  #154 = NameAndType        #152:#153     // buildTo:(Lscala/collection/mutable/Builder;)Lscala/collection/mutable/Builder;
  #155 = Methodref          #15.#154      // scala/collection/immutable/SeqMap$SeqMap4.buildTo:(Lscala/collection/mutable/Builder;)Lscala/collection/mutable/Builder;
  #156 = Utf8               Lscala/Tuple2;
  #157 = Utf8               addAll
  #158 = Utf8               (Lscala/collection/IterableOnce;)Lscala/collection/immutable/SeqMap$SeqMapBuilderImpl;
  #159 = Utf8               (Lscala/collection/IterableOnce<Lscala/Tuple2<TK;TV;>;>;)Lscala/collection/immutable/SeqMap$SeqMapBuilderImpl<TK;TV;>;
  #160 = Utf8               addAll$
  #161 = NameAndType        #160:#92      // addAll$:(Lscala/collection/mutable/Growable;Lscala/collection/IterableOnce;)Lscala/collection/mutable/Growable;
  #162 = InterfaceMethodref #74.#161      // scala/collection/mutable/Growable.addAll$:(Lscala/collection/mutable/Growable;Lscala/collection/IterableOnce;)Lscala/collection/mutable/Growable;
  #163 = NameAndType        #157:#158     // addAll:(Lscala/collection/IterableOnce;)Lscala/collection/immutable/SeqMap$SeqMapBuilderImpl;
  #164 = Methodref          #2.#163       // scala/collection/immutable/SeqMap$SeqMapBuilderImpl.addAll:(Lscala/collection/IterableOnce;)Lscala/collection/immutable/SeqMap$SeqMapBuilderImpl;
  #165 = NameAndType        #127:#128     // addOne:(Lscala/Tuple2;)Lscala/collection/immutable/SeqMap$SeqMapBuilderImpl;
  #166 = Methodref          #2.#165       // scala/collection/immutable/SeqMap$SeqMapBuilderImpl.addOne:(Lscala/Tuple2;)Lscala/collection/immutable/SeqMap$SeqMapBuilderImpl;
  #167 = NameAndType        #121:#122     // result:()Lscala/collection/immutable/SeqMap;
  #168 = Methodref          #2.#167       // scala/collection/immutable/SeqMap$SeqMapBuilderImpl.result:()Lscala/collection/immutable/SeqMap;
  #169 = Methodref          #5.#150       // java/lang/Object."<init>":()V
  #170 = Utf8               Signature
  #171 = Utf8               Code
  #172 = Utf8               LineNumberTable
  #173 = Utf8               LocalVariableTable
  #174 = Utf8               MethodParameters
  #175 = Utf8               Deprecated
  #176 = Utf8               StackMapTable
  #177 = Utf8               InnerClasses
  #178 = Utf8               SourceFile
  #179 = Utf8               ScalaInlineInfo
  #180 = Utf8               Scala
{
  private scala.collection.immutable.SeqMap<K, V> elems;
    descriptor: Lscala/collection/immutable/SeqMap;
    flags: (0x0002) ACC_PRIVATE
    Signature: #20                          // Lscala/collection/immutable/SeqMap<TK;TV;>;

  private boolean switchedToVectorMapBuilder;
    descriptor: Z
    flags: (0x0002) ACC_PRIVATE

  private scala.collection.immutable.VectorMapBuilder<K, V> vectorMapBuilder;
    descriptor: Lscala/collection/immutable/VectorMapBuilder;
    flags: (0x0002) ACC_PRIVATE
    Signature: #25                          // Lscala/collection/immutable/VectorMapBuilder<TK;TV;>;

  public void sizeHint(int);
    descriptor: (I)V
    flags: (0x0001) ACC_PUBLIC
    Code:
      stack=2, locals=2, args_size=2
         0: aload_0
         1: iload_1
         2: invokestatic  #34                 // InterfaceMethod scala/collection/mutable/Builder.sizeHint$:(Lscala/collection/mutable/Builder;I)V
         5: return
      LineNumberTable:
        line 228: 0
      LocalVariableTable:
        Start  Length  Slot  Name   Signature
            0       6     0  this   Lscala/collection/immutable/SeqMap$SeqMapBuilderImpl;
            0       6     1  size   I
    MethodParameters:
      Name                           Flags
      size                           final

  public final void sizeHint(scala.collection.IterableOnce<?>, int);
    descriptor: (Lscala/collection/IterableOnce;I)V
    flags: (0x0011) ACC_PUBLIC, ACC_FINAL
    Code:
      stack=3, locals=3, args_size=3
         0: aload_0
         1: aload_1
         2: iload_2
         3: invokestatic  #44                 // InterfaceMethod scala/collection/mutable/Builder.sizeHint$:(Lscala/collection/mutable/Builder;Lscala/collection/IterableOnce;I)V
         6: return
      LineNumberTable:
        line 228: 0
      LocalVariableTable:
        Start  Length  Slot  Name   Signature
            0       7     0  this   Lscala/collection/immutable/SeqMap$SeqMapBuilderImpl;
            0       7     1  coll   Lscala/collection/IterableOnce;
            0       7     2 delta   I
    Signature: #39                          // (Lscala/collection/IterableOnce<*>;I)V
    MethodParameters:
      Name                           Flags
      coll                           final
      delta                          final

  public final int sizeHint$default$2();
    descriptor: ()I
    flags: (0x0011) ACC_PUBLIC, ACC_FINAL
    Code:
      stack=1, locals=1, args_size=1
         0: aload_0
         1: invokestatic  #51                 // InterfaceMethod scala/collection/mutable/Builder.sizeHint$default$2$:(Lscala/collection/mutable/Builder;)I
         4: ireturn
      LineNumberTable:
        line 228: 0
      LocalVariableTable:
        Start  Length  Slot  Name   Signature
            0       5     0  this   Lscala/collection/immutable/SeqMap$SeqMapBuilderImpl;

  public final void sizeHintBounded(int, scala.collection.Iterable<?>);
    descriptor: (ILscala/collection/Iterable;)V
    flags: (0x0011) ACC_PUBLIC, ACC_FINAL
    Code:
      stack=3, locals=3, args_size=3
         0: aload_0
         1: iload_1
         2: aload_2
         3: invokestatic  #59                 // InterfaceMethod scala/collection/mutable/Builder.sizeHintBounded$:(Lscala/collection/mutable/Builder;ILscala/collection/Iterable;)V
         6: return
      LineNumberTable:
        line 228: 0
      LocalVariableTable:
        Start  Length  Slot  Name   Signature
            0       7     0  this   Lscala/collection/immutable/SeqMap$SeqMapBuilderImpl;
            0       7     1  size   I
            0       7     2 boundingColl   Lscala/collection/Iterable;
    Signature: #54                          // (ILscala/collection/Iterable<*>;)V
    MethodParameters:
      Name                           Flags
      size                           final
      boundingColl                   final

  public <NewTo extends java.lang.Object> scala.collection.mutable.Builder<scala.Tuple2<K, V>, NewTo> mapResult(scala.Function1<scala.collection.immutable.SeqMap<K, V>, NewTo>);
    descriptor: (Lscala/Function1;)Lscala/collection/mutable/Builder;
    flags: (0x0001) ACC_PUBLIC
    Code:
      stack=2, locals=2, args_size=2
         0: aload_0
         1: aload_1
         2: invokestatic  #68                 // InterfaceMethod scala/collection/mutable/Builder.mapResult$:(Lscala/collection/mutable/Builder;Lscala/Function1;)Lscala/collection/mutable/Builder;
         5: areturn
      LineNumberTable:
        line 228: 0
      LocalVariableTable:
        Start  Length  Slot  Name   Signature
            0       6     0  this   Lscala/collection/immutable/SeqMap$SeqMapBuilderImpl;
            0       6     1     f   Lscala/Function1;
    Signature: #63                          // <NewTo:Ljava/lang/Object;>(Lscala/Function1<Lscala/collection/immutable/SeqMap<TK;TV;>;TNewTo;>;)Lscala/collection/mutable/Builder<Lscala/Tuple2<TK;TV;>;TNewTo;>;
    MethodParameters:
      Name                           Flags
      f                              final

  public final scala.collection.mutable.Growable $plus$eq(java.lang.Object);
    descriptor: (Ljava/lang/Object;)Lscala/collection/mutable/Growable;
    flags: (0x0011) ACC_PUBLIC, ACC_FINAL
    Code:
      stack=2, locals=2, args_size=2
         0: aload_0
         1: aload_1
         2: invokestatic  #78                 // InterfaceMethod scala/collection/mutable/Growable.$plus$eq$:(Lscala/collection/mutable/Growable;Ljava/lang/Object;)Lscala/collection/mutable/Growable;
         5: areturn
      LineNumberTable:
        line 228: 0
      LocalVariableTable:
        Start  Length  Slot  Name   Signature
            0       6     0  this   Lscala/collection/immutable/SeqMap$SeqMapBuilderImpl;
            0       6     1  elem   Ljava/lang/Object;
    MethodParameters:
      Name                           Flags
      elem                           final

  public final scala.collection.mutable.Growable $plus$eq(java.lang.Object, java.lang.Object, scala.collection.immutable.Seq);
    descriptor: (Ljava/lang/Object;Ljava/lang/Object;Lscala/collection/immutable/Seq;)Lscala/collection/mutable/Growable;
    flags: (0x0011) ACC_PUBLIC, ACC_FINAL
    Code:
      stack=4, locals=4, args_size=4
         0: aload_0
         1: aload_1
         2: aload_2
         3: aload_3
         4: invokestatic  #85                 // InterfaceMethod scala/collection/mutable/Growable.$plus$eq$:(Lscala/collection/mutable/Growable;Ljava/lang/Object;Ljava/lang/Object;Lscala/collection/immutable/Seq;)Lscala/collection/mutable/Growable;
         7: areturn
      LineNumberTable:
        line 228: 0
      LocalVariableTable:
        Start  Length  Slot  Name   Signature
            0       8     0  this   Lscala/collection/immutable/SeqMap$SeqMapBuilderImpl;
            0       8     1 elem1   Ljava/lang/Object;
            0       8     2 elem2   Ljava/lang/Object;
            0       8     3 elems   Lscala/collection/immutable/Seq;
    Deprecated: true
    MethodParameters:
      Name                           Flags
      elem1                          final
      elem2                          final
      elems                          final

  public final scala.collection.mutable.Growable<scala.Tuple2<K, V>> $plus$plus$eq(scala.collection.IterableOnce<scala.Tuple2<K, V>>);
    descriptor: (Lscala/collection/IterableOnce;)Lscala/collection/mutable/Growable;
    flags: (0x0011) ACC_PUBLIC, ACC_FINAL
    Code:
      stack=2, locals=2, args_size=2
         0: aload_0
         1: aload_1
         2: invokestatic  #94                 // InterfaceMethod scala/collection/mutable/Growable.$plus$plus$eq$:(Lscala/collection/mutable/Growable;Lscala/collection/IterableOnce;)Lscala/collection/mutable/Growable;
         5: areturn
      LineNumberTable:
        line 228: 0
      LocalVariableTable:
        Start  Length  Slot  Name   Signature
            0       6     0  this   Lscala/collection/immutable/SeqMap$SeqMapBuilderImpl;
            0       6     1    xs   Lscala/collection/IterableOnce;
    Signature: #89                          // (Lscala/collection/IterableOnce<Lscala/Tuple2<TK;TV;>;>;)Lscala/collection/mutable/Growable<Lscala/Tuple2<TK;TV;>;>;
    MethodParameters:
      Name                           Flags
      xs                             final

  public int knownSize();
    descriptor: ()I
    flags: (0x0001) ACC_PUBLIC
    Code:
      stack=1, locals=1, args_size=1
         0: aload_0
         1: invokestatic  #99                 // InterfaceMethod scala/collection/mutable/Growable.knownSize$:(Lscala/collection/mutable/Growable;)I
         4: ireturn
      LineNumberTable:
        line 228: 0
      LocalVariableTable:
        Start  Length  Slot  Name   Signature
            0       5     0  this   Lscala/collection/immutable/SeqMap$SeqMapBuilderImpl;

  public void clear();
    descriptor: ()V
    flags: (0x0001) ACC_PUBLIC
    Code:
      stack=2, locals=1, args_size=1
         0: aload_0
         1: getstatic     #107                // Field scala/collection/immutable/SeqMap$.MODULE$:Lscala/collection/immutable/SeqMap$;
         4: pop
         5: getstatic     #110                // Field scala/collection/immutable/SeqMap$EmptySeqMap$.MODULE$:Lscala/collection/immutable/SeqMap$EmptySeqMap$;
         8: putfield      #112                // Field elems:Lscala/collection/immutable/SeqMap;
        11: aload_0
        12: getfield      #114                // Field vectorMapBuilder:Lscala/collection/immutable/VectorMapBuilder;
        15: ifnull        25
        18: aload_0
        19: getfield      #114                // Field vectorMapBuilder:Lscala/collection/immutable/VectorMapBuilder;
        22: invokevirtual #118                // Method scala/collection/immutable/VectorMapBuilder.clear:()V
        25: aload_0
        26: iconst_0
        27: putfield      #120                // Field switchedToVectorMapBuilder:Z
        30: return
      StackMapTable: number_of_entries = 1
        frame_type = 25 /* same */
      LineNumberTable:
        line 234: 0
        line 43: 5
        line 234: 8
        line 235: 11
        line 236: 18
        line 238: 25
      LocalVariableTable:
        Start  Length  Slot  Name   Signature
            0      31     0  this   Lscala/collection/immutable/SeqMap$SeqMapBuilderImpl;

  public scala.collection.immutable.SeqMap<K, V> result();
    descriptor: ()Lscala/collection/immutable/SeqMap;
    flags: (0x0001) ACC_PUBLIC
    Code:
      stack=1, locals=1, args_size=1
         0: aload_0
         1: getfield      #120                // Field switchedToVectorMapBuilder:Z
         4: ifeq          15
         7: aload_0
         8: getfield      #114                // Field vectorMapBuilder:Lscala/collection/immutable/VectorMapBuilder;
        11: invokevirtual #126                // Method scala/collection/immutable/VectorMapBuilder.result:()Lscala/collection/immutable/VectorMap;
        14: areturn
        15: aload_0
        16: getfield      #112                // Field elems:Lscala/collection/immutable/SeqMap;
        19: areturn
      StackMapTable: number_of_entries = 1
        frame_type = 15 /* same */
      LineNumberTable:
        line 242: 0
      LocalVariableTable:
        Start  Length  Slot  Name   Signature
            0      20     0  this   Lscala/collection/immutable/SeqMap$SeqMapBuilderImpl;
    Signature: #123                         // ()Lscala/collection/immutable/SeqMap<TK;TV;>;

  public scala.collection.immutable.SeqMap$SeqMapBuilderImpl<K, V> addOne(scala.Tuple2<K, V>);
    descriptor: (Lscala/Tuple2;)Lscala/collection/immutable/SeqMap$SeqMapBuilderImpl;
    flags: (0x0001) ACC_PUBLIC
    Code:
      stack=3, locals=2, args_size=2
         0: aload_0
         1: getfield      #120                // Field switchedToVectorMapBuilder:Z
         4: ifeq          19
         7: aload_0
         8: getfield      #114                // Field vectorMapBuilder:Lscala/collection/immutable/VectorMapBuilder;
        11: aload_1
        12: invokevirtual #132                // Method scala/collection/immutable/VectorMapBuilder.addOne:(Lscala/Tuple2;)Lscala/collection/immutable/VectorMapBuilder;
        15: pop
        16: goto          135
        19: aload_0
        20: getfield      #112                // Field elems:Lscala/collection/immutable/SeqMap;
        23: invokeinterface #134,  1          // InterfaceMethod scala/collection/immutable/SeqMap.size:()I
        28: iconst_4
        29: if_icmpge     52
        32: aload_0
        33: aload_0
        34: getfield      #112                // Field elems:Lscala/collection/immutable/SeqMap;
        37: aload_1
        38: invokeinterface #138,  2          // InterfaceMethod scala/collection/immutable/SeqMap.$plus:(Lscala/Tuple2;)Lscala/collection/immutable/MapOps;
        43: checkcast     #12                 // class scala/collection/immutable/SeqMap
        46: putfield      #112                // Field elems:Lscala/collection/immutable/SeqMap;
        49: goto          135
        52: aload_0
        53: getfield      #112                // Field elems:Lscala/collection/immutable/SeqMap;
        56: aload_1
        57: invokevirtual #144                // Method scala/Tuple2._1:()Ljava/lang/Object;
        60: invokeinterface #148,  2          // InterfaceMethod scala/collection/immutable/SeqMap.contains:(Ljava/lang/Object;)Z
        65: ifeq          88
        68: aload_0
        69: aload_0
        70: getfield      #112                // Field elems:Lscala/collection/immutable/SeqMap;
        73: aload_1
        74: invokeinterface #138,  2          // InterfaceMethod scala/collection/immutable/SeqMap.$plus:(Lscala/Tuple2;)Lscala/collection/immutable/MapOps;
        79: checkcast     #12                 // class scala/collection/immutable/SeqMap
        82: putfield      #112                // Field elems:Lscala/collection/immutable/SeqMap;
        85: goto          135
        88: aload_0
        89: iconst_1
        90: putfield      #120                // Field switchedToVectorMapBuilder:Z
        93: aload_0
        94: getfield      #114                // Field vectorMapBuilder:Lscala/collection/immutable/VectorMapBuilder;
        97: ifnonnull     111
       100: aload_0
       101: new           #116                // class scala/collection/immutable/VectorMapBuilder
       104: dup
       105: invokespecial #151                // Method scala/collection/immutable/VectorMapBuilder."<init>":()V
       108: putfield      #114                // Field vectorMapBuilder:Lscala/collection/immutable/VectorMapBuilder;
       111: aload_0
       112: getfield      #112                // Field elems:Lscala/collection/immutable/SeqMap;
       115: checkcast     #15                 // class scala/collection/immutable/SeqMap$SeqMap4
       118: aload_0
       119: getfield      #114                // Field vectorMapBuilder:Lscala/collection/immutable/VectorMapBuilder;
       122: invokevirtual #155                // Method scala/collection/immutable/SeqMap$SeqMap4.buildTo:(Lscala/collection/mutable/Builder;)Lscala/collection/mutable/Builder;
       125: pop
       126: aload_0
       127: getfield      #114                // Field vectorMapBuilder:Lscala/collection/immutable/VectorMapBuilder;
       130: aload_1
       131: invokevirtual #132                // Method scala/collection/immutable/VectorMapBuilder.addOne:(Lscala/Tuple2;)Lscala/collection/immutable/VectorMapBuilder;
       134: pop
       135: aload_0
       136: areturn
      StackMapTable: number_of_entries = 5
        frame_type = 19 /* same */
        frame_type = 32 /* same */
        frame_type = 35 /* same */
        frame_type = 22 /* same */
        frame_type = 23 /* same */
      LineNumberTable:
        line 245: 0
        line 246: 7
        line 247: 19
        line 248: 32
        line 251: 52
        line 252: 68
        line 254: 88
        line 255: 93
        line 256: 100
        line 258: 111
        line 259: 126
        line 263: 135
      LocalVariableTable:
        Start  Length  Slot  Name   Signature
            0     137     0  this   Lscala/collection/immutable/SeqMap$SeqMapBuilderImpl;
            0     137     1  elem   Lscala/Tuple2;
    Signature: #129                         // (Lscala/Tuple2<TK;TV;>;)Lscala/collection/immutable/SeqMap$SeqMapBuilderImpl<TK;TV;>;
    MethodParameters:
      Name                           Flags
      elem                           final

  public scala.collection.immutable.SeqMap$SeqMapBuilderImpl<K, V> addAll(scala.collection.IterableOnce<scala.Tuple2<K, V>>);
    descriptor: (Lscala/collection/IterableOnce;)Lscala/collection/immutable/SeqMap$SeqMapBuilderImpl;
    flags: (0x0001) ACC_PUBLIC
    Code:
      stack=2, locals=2, args_size=2
         0: aload_0
         1: getfield      #120                // Field switchedToVectorMapBuilder:Z
         4: ifeq          24
         7: aload_0
         8: getfield      #114                // Field vectorMapBuilder:Lscala/collection/immutable/VectorMapBuilder;
        11: dup
        12: ifnonnull     17
        15: aconst_null
        16: athrow
        17: aload_1
        18: invokestatic  #162                // InterfaceMethod scala/collection/mutable/Growable.addAll$:(Lscala/collection/mutable/Growable;Lscala/collection/IterableOnce;)Lscala/collection/mutable/Growable;
        21: pop
        22: aload_0
        23: areturn
        24: aload_0
        25: aload_1
        26: invokestatic  #162                // InterfaceMethod scala/collection/mutable/Growable.addAll$:(Lscala/collection/mutable/Growable;Lscala/collection/IterableOnce;)Lscala/collection/mutable/Growable;
        29: checkcast     #2                  // class scala/collection/immutable/SeqMap$SeqMapBuilderImpl
        32: areturn
      StackMapTable: number_of_entries = 2
        frame_type = 81 /* same_locals_1_stack_item */
          stack = [ class scala/collection/immutable/VectorMapBuilder ]
        frame_type = 6 /* same */
      LineNumberTable:
        line 267: 0
        line 268: 7
        line 269: 22
        line 271: 24
      LocalVariableTable:
        Start  Length  Slot  Name   Signature
            0      33     0  this   Lscala/collection/immutable/SeqMap$SeqMapBuilderImpl;
            0      33     1    xs   Lscala/collection/IterableOnce;
    Signature: #159                         // (Lscala/collection/IterableOnce<Lscala/Tuple2<TK;TV;>;>;)Lscala/collection/immutable/SeqMap$SeqMapBuilderImpl<TK;TV;>;
    MethodParameters:
      Name                           Flags
      xs                             final

  public scala.collection.mutable.Growable addAll(scala.collection.IterableOnce);
    descriptor: (Lscala/collection/IterableOnce;)Lscala/collection/mutable/Growable;
    flags: (0x1041) ACC_PUBLIC, ACC_BRIDGE, ACC_SYNTHETIC
    Code:
      stack=2, locals=2, args_size=2
         0: aload_0
         1: aload_1
         2: invokevirtual #164                // Method addAll:(Lscala/collection/IterableOnce;)Lscala/collection/immutable/SeqMap$SeqMapBuilderImpl;
         5: areturn
      LineNumberTable:
        line 228: 0
      LocalVariableTable:
        Start  Length  Slot  Name   Signature
            0       6     0  this   Lscala/collection/immutable/SeqMap$SeqMapBuilderImpl;
            0       6     1    xs   Lscala/collection/IterableOnce;
    MethodParameters:
      Name                           Flags
      xs                             final

  public scala.collection.mutable.Growable addOne(java.lang.Object);
    descriptor: (Ljava/lang/Object;)Lscala/collection/mutable/Growable;
    flags: (0x1041) ACC_PUBLIC, ACC_BRIDGE, ACC_SYNTHETIC
    Code:
      stack=2, locals=2, args_size=2
         0: aload_0
         1: aload_1
         2: checkcast     #140                // class scala/Tuple2
         5: invokevirtual #166                // Method addOne:(Lscala/Tuple2;)Lscala/collection/immutable/SeqMap$SeqMapBuilderImpl;
         8: areturn
      LineNumberTable:
        line 228: 0
      LocalVariableTable:
        Start  Length  Slot  Name   Signature
            0       9     0  this   Lscala/collection/immutable/SeqMap$SeqMapBuilderImpl;
            0       9     1  elem   Ljava/lang/Object;
    MethodParameters:
      Name                           Flags
      elem                           final

  public java.lang.Object result();
    descriptor: ()Ljava/lang/Object;
    flags: (0x1041) ACC_PUBLIC, ACC_BRIDGE, ACC_SYNTHETIC
    Code:
      stack=1, locals=1, args_size=1
         0: aload_0
         1: invokevirtual #168                // Method result:()Lscala/collection/immutable/SeqMap;
         4: areturn
      LineNumberTable:
        line 228: 0
      LocalVariableTable:
        Start  Length  Slot  Name   Signature
            0       5     0  this   Lscala/collection/immutable/SeqMap$SeqMapBuilderImpl;

  public scala.collection.immutable.SeqMap$SeqMapBuilderImpl();
    descriptor: ()V
    flags: (0x0001) ACC_PUBLIC
    Code:
      stack=2, locals=1, args_size=1
         0: aload_0
         1: invokespecial #169                // Method java/lang/Object."<init>":()V
         4: aload_0
         5: getstatic     #107                // Field scala/collection/immutable/SeqMap$.MODULE$:Lscala/collection/immutable/SeqMap$;
         8: pop
         9: getstatic     #110                // Field scala/collection/immutable/SeqMap$EmptySeqMap$.MODULE$:Lscala/collection/immutable/SeqMap$EmptySeqMap$;
        12: putfield      #112                // Field elems:Lscala/collection/immutable/SeqMap;
        15: aload_0
        16: iconst_0
        17: putfield      #120                // Field switchedToVectorMapBuilder:Z
        20: return
      LineNumberTable:
        line 228: 0
        line 229: 4
        line 43: 9
        line 229: 12
        line 230: 15
        line 228: 20
      LocalVariableTable:
        Start  Length  Slot  Name   Signature
            0      21     0  this   Lscala/collection/immutable/SeqMap$SeqMapBuilderImpl;
}
InnerClasses:
  private static #13= #10 of #12;         // EmptySeqMap$=class scala/collection/immutable/SeqMap$EmptySeqMap$ of class scala/collection/immutable/SeqMap
  private static final #16= #15 of #12;   // SeqMap4=class scala/collection/immutable/SeqMap$SeqMap4 of class scala/collection/immutable/SeqMap
  private static final #17= #2 of #12;    // SeqMapBuilderImpl=class scala/collection/immutable/SeqMap$SeqMapBuilderImpl of class scala/collection/immutable/SeqMap
Signature: #3                           // <K:Ljava/lang/Object;V:Ljava/lang/Object;>Ljava/lang/Object;Lscala/collection/mutable/ReusableBuilder<Lscala/Tuple2<TK;TV;>;Lscala/collection/immutable/SeqMap<TK;TV;>;>;
SourceFile: "SeqMap.scala"
  ScalaInlineInfo: length = 0x59 (unknown attribute)
   01 01 00 11 00 46 00 47 05 00 46 00 50 05 00 57
   00 58 05 00 95 00 65 01 00 9D 00 9E 01 00 9D 00
   58 01 00 7F 00 47 01 00 7F 00 80 01 00 64 00 65
   01 00 5F 00 2F 01 00 3D 00 3E 01 00 79 00 8E 01
   00 79 00 7A 01 00 1A 00 1B 01 00 1A 00 26 01 00
   2E 00 2F 01 00 34 00 35 01
  Scala: length = 0x0 (unknown attribute)

