Classfile /Users/mw/Projects/slang-braindump/.jar/jar11/assemble/slang-braindump/assemble/content/scala/collection/immutable/StrictOptimizedSeqOps.class
  Last modified May 29, 2022; size 6430 bytes
  SHA-256 checksum 66f1e05defe255a9dab10c5e764aa4027e5206791eae73c686f02a8e4531c768
  Compiled from "StrictOptimizedSeqOps.scala"
public interface scala.collection.immutable.StrictOptimizedSeqOps<A extends java.lang.Object, CC extends java.lang.Object, C extends java.lang.Object> extends scala.collection.immutable.SeqOps<A, CC, C>, scala.collection.StrictOptimizedSeqOps<A, CC, C>
  minor version: 0
  major version: 52
  flags: (0x0601) ACC_PUBLIC, ACC_INTERFACE, ACC_ABSTRACT
  this_class: #2                          // scala/collection/immutable/StrictOptimizedSeqOps
  super_class: #5                         // java/lang/Object
  interfaces: 2, fields: 0, methods: 10, attributes: 5
Constant pool:
    #1 = Utf8               scala/collection/immutable/StrictOptimizedSeqOps
    #2 = Class              #1            // scala/collection/immutable/StrictOptimizedSeqOps
    #3 = Utf8               <A:Ljava/lang/Object;CC:Ljava/lang/Object;C:Ljava/lang/Object;>Ljava/lang/Object;Lscala/collection/immutable/SeqOps<TA;TCC;TC;>;Lscala/collection/StrictOptimizedSeqOps<TA;TCC;TC;>;
    #4 = Utf8               java/lang/Object
    #5 = Class              #4            // java/lang/Object
    #6 = Utf8               scala/collection/immutable/SeqOps
    #7 = Class              #6            // scala/collection/immutable/SeqOps
    #8 = Utf8               scala/collection/StrictOptimizedSeqOps
    #9 = Class              #8            // scala/collection/StrictOptimizedSeqOps
   #10 = Utf8               StrictOptimizedSeqOps.scala
   #11 = Utf8               Lscala/reflect/ScalaSignature;
   #12 = Utf8               bytes
   #13 = Utf8               \u0006\u0005i4qa\u0002\u0005\u0011\u0002\u0007\u0005q\u0002C\u00031\u0001\u0011\u0005\u0011\u0007C\u00036\u0001\u0011\u0005c\u0007C\u0003A\u0001\u0011\u0005\u0013\tC\u0003O\u0001\u0011\u0005s\nC\u0003^\u0001\u0011\u0005c\fC\u0006l\u0001A\u0005\u0019\u0011!A\u0005\n1D(!F*ue&\u001cGo\u00149uS6L\'0\u001a3TKF|\u0005o\u001d\u0006\u0003\u0013)\t\u0011\"[7nkR\f\'\r\\3\u000b\u0005-a\u0011AC2pY2,7\r^5p]*\tQ\"A\u0003tG\u0006d\u0017m\u0001\u0001\u0016\tAY\"\u0005K\n\u0006\u0001E)\"&\f\t\u0003%Mi\u0011\u0001D\u0005\u0003)1\u00111!\u00118z!\u00151r#G\u0011(\u001b\u0005A\u0011B\u0001\r\t\u0005\u0019\u0019V-](qgB\u0011!d\u0007\u0007\u0001\t\u0019a\u0002\u0001\"b\u0001;\t\t\u0011)\u0005\u0002\u001f#A\u0011!cH\u0005\u0003A1\u0011qAT8uQ&tw\r\u0005\u0002\u001bE\u001111\u0005\u0001CC\u0002\u0011\u0012!aQ\"\u0016\u0005u)C!\u0002\u0014#\u0005\u0004i\"\u0001B0%IE\u0002\"A\u0007\u0015\u0005\r%\u0002AQ1\u0001\u001e\u0005\u0005\u0019\u0005#B\u0016-3\u0005:S\"\u0001\u0006\n\u0005\u001dQ\u0001#B\u0016/3\u0005:\u0013BA\u0018\u000b\u0005i\u0019FO]5di>\u0003H/[7ju\u0016$\u0017\n^3sC\ndWm\u00149t\u0003\u0019!\u0013N\\5uIQ\t!\u0007\u0005\u0002\u0013g%\u0011A\u0007\u0004\u0002\u0005+:LG/\u0001\u0006eSN$\u0018N\\2u\u0005f,\"a\u000e \u0015\u0005\u001dB\u0004\"B\u001d\u0003\u0001\u0004Q\u0014!\u00014\u0011\tIY\u0014$P\u0005\u0003y1\u0011\u0011BR;oGRLwN\\\u0019\u0011\u0005iqD!B \u0003\u0005\u0004i\"!\u0001\"\u0002\u000fU\u0004H-\u0019;fIV\u0011!)\u0012\u000b\u0004\u0007\u001ec\u0005c\u0001\u000e#\tB\u0011!$\u0012\u0003\u0006\u007f\r\u0011\rAR\t\u00033EAQ\u0001S\u0002A\u0002%\u000bQ!\u001b8eKb\u0004\"A\u0005&\n\u0005-c!aA%oi\")Qj\u0001a\u0001\t\u0006!Q\r\\3n\u0003\u0015\u0001\u0018\r^2i+\t\u00016\u000b\u0006\u0003R)Z[\u0006c\u0001\u000e#%B\u0011!d\u0015\u0003\u0006\u007f\u0011\u0011\rA\u0012\u0005\u0006+\u0012\u0001\r!S\u0001\u0005MJ|W\u000eC\u0003X\t\u0001\u0007\u0001,A\u0003pi\",\'\u000fE\u0002,3JK!A\u0017\u0006\u0003\u0019%#XM]1cY\u0016|enY3\t\u000bq#\u0001\u0019A%\u0002\u0011I,\u0007\u000f\\1dK\u0012\faa]8si\u0016$WCA0k)\t9\u0003\rC\u0003b\u000b\u0001\u000f!-A\u0002pe\u0012\u00042a\u00194j\u001d\t\u0011B-\u0003\u0002f\u0019\u00059\u0001/Y2lC\u001e,\u0017BA4i\u0005!y%\u000fZ3sS:<\'BA3\r!\tQ\"\u000eB\u0003@\u000b\t\u0007a)\u0001\u0007tkB,\'\u000fJ:peR,G-\u0006\u0002noR\u0011qE\u001c\u0005\u0006C\u001a\u0001\u001da\u001c\t\u0004a\u001a4hBA9e\u001d\t\u0011X/D\u0001t\u0015\t!h\"\u0001\u0004=e>|GOP\u0005\u0002\u001bA\u0011!d\u001e\u0003\u0006\u007f\u0019\u0011\rAR\u0005\u0003;fL!\u0001\u0007\u0006
   #14 = Utf8               scala$collection$immutable$StrictOptimizedSeqOps$$super$sorted
   #15 = Utf8               (Lscala/math/Ordering;)Ljava/lang/Object;
   #16 = Utf8               ord
   #17 = Utf8               distinctBy$
   #18 = Utf8               (Lscala/collection/immutable/StrictOptimizedSeqOps;Lscala/Function1;)Ljava/lang/Object;
   #19 = Utf8               $this
   #20 = Utf8               f
   #21 = Utf8               distinctBy
   #22 = Utf8               (Lscala/Function1;)Ljava/lang/Object;
   #23 = NameAndType        #21:#22       // distinctBy:(Lscala/Function1;)Ljava/lang/Object;
   #24 = InterfaceMethodref #2.#23        // scala/collection/immutable/StrictOptimizedSeqOps.distinctBy:(Lscala/Function1;)Ljava/lang/Object;
   #25 = Utf8               Lscala/collection/immutable/StrictOptimizedSeqOps;
   #26 = Utf8               Lscala/Function1;
   #27 = Utf8               <B:Ljava/lang/Object;>(Lscala/Function1<TA;TB;>;)TC;
   #28 = Utf8               lengthCompare
   #29 = Utf8               (I)I
   #30 = NameAndType        #28:#29       // lengthCompare:(I)I
   #31 = InterfaceMethodref #2.#30        // scala/collection/immutable/StrictOptimizedSeqOps.lengthCompare:(I)I
   #32 = Utf8               coll
   #33 = Utf8               ()Ljava/lang/Object;
   #34 = NameAndType        #32:#33       // coll:()Ljava/lang/Object;
   #35 = InterfaceMethodref #2.#34        // scala/collection/immutable/StrictOptimizedSeqOps.coll:()Ljava/lang/Object;
   #36 = Utf8               newSpecificBuilder
   #37 = Utf8               ()Lscala/collection/mutable/Builder;
   #38 = NameAndType        #36:#37       // newSpecificBuilder:()Lscala/collection/mutable/Builder;
   #39 = InterfaceMethodref #2.#38        // scala/collection/immutable/StrictOptimizedSeqOps.newSpecificBuilder:()Lscala/collection/mutable/Builder;
   #40 = Utf8               scala/collection/mutable/HashSet$
   #41 = Class              #40           // scala/collection/mutable/HashSet$
   #42 = Utf8               MODULE$
   #43 = Utf8               Lscala/collection/mutable/HashSet$;
   #44 = NameAndType        #42:#43       // MODULE$:Lscala/collection/mutable/HashSet$;
   #45 = Fieldref           #41.#44       // scala/collection/mutable/HashSet$.MODULE$:Lscala/collection/mutable/HashSet$;
   #46 = Utf8               scala/collection/mutable/HashSet
   #47 = Class              #46           // scala/collection/mutable/HashSet
   #48 = Utf8               <init>
   #49 = Utf8               ()V
   #50 = NameAndType        #48:#49       // "<init>":()V
   #51 = Methodref          #47.#50       // scala/collection/mutable/HashSet."<init>":()V
   #52 = Utf8               iterator
   #53 = Utf8               ()Lscala/collection/Iterator;
   #54 = NameAndType        #52:#53       // iterator:()Lscala/collection/Iterator;
   #55 = InterfaceMethodref #2.#54        // scala/collection/immutable/StrictOptimizedSeqOps.iterator:()Lscala/collection/Iterator;
   #56 = Utf8               scala/collection/Iterator
   #57 = Class              #56           // scala/collection/Iterator
   #58 = Utf8               hasNext
   #59 = Utf8               ()Z
   #60 = NameAndType        #58:#59       // hasNext:()Z
   #61 = InterfaceMethodref #57.#60       // scala/collection/Iterator.hasNext:()Z
   #62 = Utf8               next
   #63 = NameAndType        #62:#33       // next:()Ljava/lang/Object;
   #64 = InterfaceMethodref #57.#63       // scala/collection/Iterator.next:()Ljava/lang/Object;
   #65 = Utf8               scala/Function1
   #66 = Class              #65           // scala/Function1
   #67 = Utf8               apply
   #68 = Utf8               (Ljava/lang/Object;)Ljava/lang/Object;
   #69 = NameAndType        #67:#68       // apply:(Ljava/lang/Object;)Ljava/lang/Object;
   #70 = InterfaceMethodref #66.#69       // scala/Function1.apply:(Ljava/lang/Object;)Ljava/lang/Object;
   #71 = Utf8               add
   #72 = Utf8               (Ljava/lang/Object;)Z
   #73 = NameAndType        #71:#72       // add:(Ljava/lang/Object;)Z
   #74 = Methodref          #47.#73       // scala/collection/mutable/HashSet.add:(Ljava/lang/Object;)Z
   #75 = Utf8               scala/collection/mutable/Growable
   #76 = Class              #75           // scala/collection/mutable/Growable
   #77 = Utf8               addOne
   #78 = Utf8               (Ljava/lang/Object;)Lscala/collection/mutable/Growable;
   #79 = NameAndType        #77:#78       // addOne:(Ljava/lang/Object;)Lscala/collection/mutable/Growable;
   #80 = InterfaceMethodref #76.#79       // scala/collection/mutable/Growable.addOne:(Ljava/lang/Object;)Lscala/collection/mutable/Growable;
   #81 = Utf8               scala/collection/mutable/Builder
   #82 = Class              #81           // scala/collection/mutable/Builder
   #83 = Utf8               result
   #84 = NameAndType        #83:#33       // result:()Ljava/lang/Object;
   #85 = InterfaceMethodref #82.#84       // scala/collection/mutable/Builder.result:()Ljava/lang/Object;
   #86 = Utf8               Ljava/lang/Object;
   #87 = Utf8               builder
   #88 = Utf8               Lscala/collection/mutable/Builder;
   #89 = Utf8               seen
   #90 = Utf8               Lscala/collection/mutable/HashSet;
   #91 = Utf8               it
   #92 = Utf8               Lscala/collection/Iterator;
   #93 = Utf8               different
   #94 = Utf8               Z
   #95 = Utf8               this
   #96 = Utf8               updated$
   #97 = Utf8               (Lscala/collection/immutable/StrictOptimizedSeqOps;ILjava/lang/Object;)Ljava/lang/Object;
   #98 = Utf8               index
   #99 = Utf8               elem
  #100 = Utf8               updated
  #101 = Utf8               (ILjava/lang/Object;)Ljava/lang/Object;
  #102 = NameAndType        #100:#101     // updated:(ILjava/lang/Object;)Ljava/lang/Object;
  #103 = InterfaceMethodref #2.#102       // scala/collection/immutable/StrictOptimizedSeqOps.updated:(ILjava/lang/Object;)Ljava/lang/Object;
  #104 = Utf8               I
  #105 = Utf8               <B:Ljava/lang/Object;>(ITB;)TCC;
  #106 = Utf8               java/lang/IndexOutOfBoundsException
  #107 = Class              #106          // java/lang/IndexOutOfBoundsException
  #108 = Utf8               java/lang/StringBuilder
  #109 = Class              #108          // java/lang/StringBuilder
  #110 = Integer            31
  #111 = Utf8               (I)V
  #112 = NameAndType        #48:#111      // "<init>":(I)V
  #113 = Methodref          #109.#112     // java/lang/StringBuilder."<init>":(I)V
  #114 = Utf8               append
  #115 = Utf8               (I)Ljava/lang/StringBuilder;
  #116 = NameAndType        #114:#115     // append:(I)Ljava/lang/StringBuilder;
  #117 = Methodref          #109.#116     // java/lang/StringBuilder.append:(I)Ljava/lang/StringBuilder;
  #118 = Utf8                is out of bounds (min 0, max
  #119 = String             #118          //  is out of bounds (min 0, max
  #120 = Utf8               (Ljava/lang/String;)Ljava/lang/StringBuilder;
  #121 = NameAndType        #114:#120     // append:(Ljava/lang/String;)Ljava/lang/StringBuilder;
  #122 = Methodref          #109.#121     // java/lang/StringBuilder.append:(Ljava/lang/String;)Ljava/lang/StringBuilder;
  #123 = Utf8               knownSize
  #124 = Utf8               ()I
  #125 = NameAndType        #123:#124     // knownSize:()I
  #126 = InterfaceMethodref #2.#125       // scala/collection/immutable/StrictOptimizedSeqOps.knownSize:()I
  #127 = Utf8               java/lang/Integer
  #128 = Class              #127          // java/lang/Integer
  #129 = Utf8               valueOf
  #130 = Utf8               (I)Ljava/lang/Integer;
  #131 = NameAndType        #129:#130     // valueOf:(I)Ljava/lang/Integer;
  #132 = Methodref          #128.#131     // java/lang/Integer.valueOf:(I)Ljava/lang/Integer;
  #133 = Utf8               unknown
  #134 = String             #133          // unknown
  #135 = Utf8               (Ljava/lang/Object;)Ljava/lang/StringBuilder;
  #136 = NameAndType        #114:#135     // append:(Ljava/lang/Object;)Ljava/lang/StringBuilder;
  #137 = Methodref          #109.#136     // java/lang/StringBuilder.append:(Ljava/lang/Object;)Ljava/lang/StringBuilder;
  #138 = Utf8               )
  #139 = String             #138          // )
  #140 = Utf8               toString
  #141 = Utf8               ()Ljava/lang/String;
  #142 = NameAndType        #140:#141     // toString:()Ljava/lang/String;
  #143 = Methodref          #109.#142     // java/lang/StringBuilder.toString:()Ljava/lang/String;
  #144 = Utf8               (Ljava/lang/String;)V
  #145 = NameAndType        #48:#144      // "<init>":(Ljava/lang/String;)V
  #146 = Methodref          #107.#145     // java/lang/IndexOutOfBoundsException."<init>":(Ljava/lang/String;)V
  #147 = Utf8               iterableFactory
  #148 = Utf8               ()Lscala/collection/IterableFactory;
  #149 = NameAndType        #147:#148     // iterableFactory:()Lscala/collection/IterableFactory;
  #150 = InterfaceMethodref #2.#149       // scala/collection/immutable/StrictOptimizedSeqOps.iterableFactory:()Lscala/collection/IterableFactory;
  #151 = Utf8               scala/collection/IterableFactory
  #152 = Class              #151          // scala/collection/IterableFactory
  #153 = Utf8               newBuilder
  #154 = NameAndType        #153:#37      // newBuilder:()Lscala/collection/mutable/Builder;
  #155 = InterfaceMethodref #152.#154     // scala/collection/IterableFactory.newBuilder:()Lscala/collection/mutable/Builder;
  #156 = Utf8               scala/collection/SeqOps
  #157 = Class              #156          // scala/collection/SeqOps
  #158 = Utf8               length
  #159 = NameAndType        #158:#124     // length:()I
  #160 = InterfaceMethodref #157.#159     // scala/collection/SeqOps.length:()I
  #161 = Utf8               sizeHint
  #162 = NameAndType        #161:#111     // sizeHint:(I)V
  #163 = InterfaceMethodref #82.#162      // scala/collection/mutable/Builder.sizeHint:(I)V
  #164 = Utf8               b
  #165 = Utf8               i
  #166 = Utf8               $plus$eq_elem
  #167 = Utf8               patch$
  #168 = Utf8               (Lscala/collection/immutable/StrictOptimizedSeqOps;ILscala/collection/IterableOnce;I)Ljava/lang/Object;
  #169 = Utf8               from
  #170 = Utf8               other
  #171 = Utf8               replaced
  #172 = Utf8               patch
  #173 = Utf8               (ILscala/collection/IterableOnce;I)Ljava/lang/Object;
  #174 = NameAndType        #172:#173     // patch:(ILscala/collection/IterableOnce;I)Ljava/lang/Object;
  #175 = InterfaceMethodref #2.#174       // scala/collection/immutable/StrictOptimizedSeqOps.patch:(ILscala/collection/IterableOnce;I)Ljava/lang/Object;
  #176 = Utf8               Lscala/collection/IterableOnce;
  #177 = Utf8               <B:Ljava/lang/Object;>(ILscala/collection/IterableOnce<TB;>;I)TCC;
  #178 = Utf8               addAll
  #179 = Utf8               (Lscala/collection/IterableOnce;)Lscala/collection/mutable/Growable;
  #180 = NameAndType        #178:#179     // addAll:(Lscala/collection/IterableOnce;)Lscala/collection/mutable/Growable;
  #181 = InterfaceMethodref #76.#180      // scala/collection/mutable/Growable.addAll:(Lscala/collection/IterableOnce;)Lscala/collection/mutable/Growable;
  #182 = Utf8               sorted$
  #183 = Utf8               (Lscala/collection/immutable/StrictOptimizedSeqOps;Lscala/math/Ordering;)Ljava/lang/Object;
  #184 = Utf8               sorted
  #185 = NameAndType        #184:#15      // sorted:(Lscala/math/Ordering;)Ljava/lang/Object;
  #186 = InterfaceMethodref #2.#185       // scala/collection/immutable/StrictOptimizedSeqOps.sorted:(Lscala/math/Ordering;)Ljava/lang/Object;
  #187 = Utf8               Lscala/math/Ordering;
  #188 = Utf8               <B:Ljava/lang/Object;>(Lscala/math/Ordering<TB;>;)TC;
  #189 = NameAndType        #14:#15       // scala$collection$immutable$StrictOptimizedSeqOps$$super$sorted:(Lscala/math/Ordering;)Ljava/lang/Object;
  #190 = InterfaceMethodref #2.#189       // scala/collection/immutable/StrictOptimizedSeqOps.scala$collection$immutable$StrictOptimizedSeqOps$$super$sorted:(Lscala/math/Ordering;)Ljava/lang/Object;
  #191 = Utf8               $init$
  #192 = Utf8               (Lscala/collection/immutable/StrictOptimizedSeqOps;)V
  #193 = Utf8               MethodParameters
  #194 = Utf8               Code
  #195 = Utf8               LineNumberTable
  #196 = Utf8               LocalVariableTable
  #197 = Utf8               StackMapTable
  #198 = Utf8               Signature
  #199 = Utf8               SourceFile
  #200 = Utf8               RuntimeVisibleAnnotations
  #201 = Utf8               ScalaInlineInfo
  #202 = Utf8               ScalaSig
{
  public abstract java.lang.Object scala$collection$immutable$StrictOptimizedSeqOps$$super$sorted(scala.math.Ordering);
    descriptor: (Lscala/math/Ordering;)Ljava/lang/Object;
    flags: (0x1401) ACC_PUBLIC, ACC_ABSTRACT, ACC_SYNTHETIC
    MethodParameters:
      Name                           Flags
      ord                            final

  public static java.lang.Object distinctBy$(scala.collection.immutable.StrictOptimizedSeqOps, scala.Function1);
    descriptor: (Lscala/collection/immutable/StrictOptimizedSeqOps;Lscala/Function1;)Ljava/lang/Object;
    flags: (0x1009) ACC_PUBLIC, ACC_STATIC, ACC_SYNTHETIC
    Code:
      stack=2, locals=2, args_size=2
         0: aload_0
         1: aload_1
         2: invokespecial #24                 // InterfaceMethod distinctBy:(Lscala/Function1;)Ljava/lang/Object;
         5: areturn
      LineNumberTable:
        line 26: 0
      LocalVariableTable:
        Start  Length  Slot  Name   Signature
            0       6     0 $this   Lscala/collection/immutable/StrictOptimizedSeqOps;
            0       6     1     f   Lscala/Function1;
    MethodParameters:
      Name                           Flags
      $this                          final synthetic
      f                              final

  public default <B extends java.lang.Object> C distinctBy(scala.Function1<A, B>);
    descriptor: (Lscala/Function1;)Ljava/lang/Object;
    flags: (0x0001) ACC_PUBLIC
    Code:
      stack=3, locals=8, args_size=2
         0: aload_0
         1: iconst_1
         2: invokeinterface #31,  2           // InterfaceMethod lengthCompare:(I)I
         7: iconst_0
         8: if_icmpgt     18
        11: aload_0
        12: invokeinterface #35,  1           // InterfaceMethod coll:()Ljava/lang/Object;
        17: areturn
        18: aload_0
        19: invokeinterface #39,  1           // InterfaceMethod newSpecificBuilder:()Lscala/collection/mutable/Builder;
        24: astore_2
        25: getstatic     #45                 // Field scala/collection/mutable/HashSet$.MODULE$:Lscala/collection/mutable/HashSet$;
        28: pop
        29: new           #47                 // class scala/collection/mutable/HashSet
        32: dup
        33: invokespecial #51                 // Method scala/collection/mutable/HashSet."<init>":()V
        36: astore        7
        38: aload         7
        40: aconst_null
        41: astore        7
        43: astore_3
        44: aload_0
        45: invokeinterface #55,  1           // InterfaceMethod iterator:()Lscala/collection/Iterator;
        50: astore        4
        52: iconst_0
        53: istore        5
        55: aload         4
        57: invokeinterface #61,  1           // InterfaceMethod scala/collection/Iterator.hasNext:()Z
        62: ifeq          113
        65: aload         4
        67: invokeinterface #64,  1           // InterfaceMethod scala/collection/Iterator.next:()Ljava/lang/Object;
        72: astore        6
        74: aload_3
        75: aload_1
        76: aload         6
        78: invokeinterface #70,  2           // InterfaceMethod scala/Function1.apply:(Ljava/lang/Object;)Ljava/lang/Object;
        83: invokevirtual #74                 // Method scala/collection/mutable/HashSet.add:(Ljava/lang/Object;)Z
        86: ifeq          107
        89: aload_2
        90: ifnonnull     95
        93: aconst_null
        94: athrow
        95: aload_2
        96: aload         6
        98: invokeinterface #80,  2           // InterfaceMethod scala/collection/mutable/Growable.addOne:(Ljava/lang/Object;)Lscala/collection/mutable/Growable;
       103: pop
       104: goto          55
       107: iconst_1
       108: istore        5
       110: goto          55
       113: iload         5
       115: ifeq          125
       118: aload_2
       119: invokeinterface #85,  1           // InterfaceMethod scala/collection/mutable/Builder.result:()Ljava/lang/Object;
       124: areturn
       125: aload_0
       126: invokeinterface #35,  1           // InterfaceMethod coll:()Ljava/lang/Object;
       131: areturn
      StackMapTable: number_of_entries = 6
        frame_type = 18 /* same */
        frame_type = 255 /* full_frame */
          offset_delta = 36
          locals = [ class scala/collection/immutable/StrictOptimizedSeqOps, class scala/Function1, class scala/collection/mutable/Builder, class scala/collection/mutable/HashSet, class scala/collection/Iterator, int, top, null ]
          stack = []
        frame_type = 255 /* full_frame */
          offset_delta = 39
          locals = [ class scala/collection/immutable/StrictOptimizedSeqOps, class scala/Function1, class scala/collection/mutable/Builder, class scala/collection/mutable/HashSet, class scala/collection/Iterator, int, class java/lang/Object, null ]
          stack = []
        frame_type = 11 /* same */
        frame_type = 255 /* full_frame */
          offset_delta = 5
          locals = [ class scala/collection/immutable/StrictOptimizedSeqOps, class scala/Function1, class scala/collection/mutable/Builder, class scala/collection/mutable/HashSet, class scala/collection/Iterator, int, top, null ]
          stack = []
        frame_type = 11 /* same */
      LineNumberTable:
        line 27: 0
        line 29: 18
        line 30: 25
        line 31: 44
        line 32: 52
        line 33: 55
        line 34: 65
        line 35: 74
        line 33: 110
        line 37: 113
      LocalVariableTable:
        Start  Length  Slot  Name   Signature
           74      36     6  next   Ljava/lang/Object;
           25     106     2 builder   Lscala/collection/mutable/Builder;
           44      87     3  seen   Lscala/collection/mutable/HashSet;
           52      79     4    it   Lscala/collection/Iterator;
           55      76     5 different   Z
            0     132     0  this   Lscala/collection/immutable/StrictOptimizedSeqOps;
            0     132     1     f   Lscala/Function1;
    Signature: #27                          // <B:Ljava/lang/Object;>(Lscala/Function1<TA;TB;>;)TC;
    MethodParameters:
      Name                           Flags
      f                              final

  public static java.lang.Object updated$(scala.collection.immutable.StrictOptimizedSeqOps, int, java.lang.Object);
    descriptor: (Lscala/collection/immutable/StrictOptimizedSeqOps;ILjava/lang/Object;)Ljava/lang/Object;
    flags: (0x1009) ACC_PUBLIC, ACC_STATIC, ACC_SYNTHETIC
    Code:
      stack=3, locals=3, args_size=3
         0: aload_0
         1: iload_1
         2: aload_2
         3: invokespecial #103                // InterfaceMethod updated:(ILjava/lang/Object;)Ljava/lang/Object;
         6: areturn
      LineNumberTable:
        line 41: 0
      LocalVariableTable:
        Start  Length  Slot  Name   Signature
            0       7     0 $this   Lscala/collection/immutable/StrictOptimizedSeqOps;
            0       7     1 index   I
            0       7     2  elem   Ljava/lang/Object;
    MethodParameters:
      Name                           Flags
      $this                          final synthetic
      index                          final
      elem                           final

  public default <B extends java.lang.Object> CC updated(int, B);
    descriptor: (ILjava/lang/Object;)Ljava/lang/Object;
    flags: (0x0001) ACC_PUBLIC
    Code:
      stack=5, locals=8, args_size=3
         0: iload_1
         1: iconst_0
         2: if_icmpge     66
         5: new           #107                // class java/lang/IndexOutOfBoundsException
         8: dup
         9: new           #109                // class java/lang/StringBuilder
        12: dup
        13: ldc           #110                // int 31
        15: invokespecial #113                // Method java/lang/StringBuilder."<init>":(I)V
        18: iload_1
        19: invokevirtual #117                // Method java/lang/StringBuilder.append:(I)Ljava/lang/StringBuilder;
        22: ldc           #119                // String  is out of bounds (min 0, max
        24: invokevirtual #122                // Method java/lang/StringBuilder.append:(Ljava/lang/String;)Ljava/lang/StringBuilder;
        27: aload_0
        28: invokeinterface #126,  1          // InterfaceMethod knownSize:()I
        33: iconst_0
        34: if_icmplt     49
        37: aload_0
        38: invokeinterface #126,  1          // InterfaceMethod knownSize:()I
        43: invokestatic  #132                // Method java/lang/Integer.valueOf:(I)Ljava/lang/Integer;
        46: goto          51
        49: ldc           #134                // String unknown
        51: invokevirtual #137                // Method java/lang/StringBuilder.append:(Ljava/lang/Object;)Ljava/lang/StringBuilder;
        54: ldc           #139                // String )
        56: invokevirtual #122                // Method java/lang/StringBuilder.append:(Ljava/lang/String;)Ljava/lang/StringBuilder;
        59: invokevirtual #143                // Method java/lang/StringBuilder.toString:()Ljava/lang/String;
        62: invokespecial #146                // Method java/lang/IndexOutOfBoundsException."<init>":(Ljava/lang/String;)V
        65: athrow
        66: aload_0
        67: invokeinterface #150,  1          // InterfaceMethod iterableFactory:()Lscala/collection/IterableFactory;
        72: invokeinterface #155,  1          // InterfaceMethod scala/collection/IterableFactory.newBuilder:()Lscala/collection/mutable/Builder;
        77: astore_3
        78: aload_0
        79: invokeinterface #126,  1          // InterfaceMethod knownSize:()I
        84: iconst_0
        85: if_icmplt     100
        88: aload_3
        89: aload_0
        90: invokeinterface #160,  1          // InterfaceMethod scala/collection/SeqOps.length:()I
        95: invokeinterface #163,  2          // InterfaceMethod scala/collection/mutable/Builder.sizeHint:(I)V
       100: iconst_0
       101: istore        4
       103: aload_0
       104: invokeinterface #55,  1           // InterfaceMethod iterator:()Lscala/collection/Iterator;
       109: astore        5
       111: iload         4
       113: iload_1
       114: if_icmpge     160
       117: aload         5
       119: invokeinterface #61,  1           // InterfaceMethod scala/collection/Iterator.hasNext:()Z
       124: ifeq          160
       127: aload_3
       128: aload         5
       130: invokeinterface #64,  1           // InterfaceMethod scala/collection/Iterator.next:()Ljava/lang/Object;
       135: astore        6
       137: ifnonnull     142
       140: aconst_null
       141: athrow
       142: aload_3
       143: aload         6
       145: invokeinterface #80,  2           // InterfaceMethod scala/collection/mutable/Growable.addOne:(Ljava/lang/Object;)Lscala/collection/mutable/Growable;
       150: pop
       151: aconst_null
       152: astore        6
       154: iinc          4, 1
       157: goto          111
       160: aload         5
       162: invokeinterface #61,  1           // InterfaceMethod scala/collection/Iterator.hasNext:()Z
       167: ifne          211
       170: new           #107                // class java/lang/IndexOutOfBoundsException
       173: dup
       174: new           #109                // class java/lang/StringBuilder
       177: dup
       178: ldc           #110                // int 31
       180: invokespecial #113                // Method java/lang/StringBuilder."<init>":(I)V
       183: iload_1
       184: invokevirtual #117                // Method java/lang/StringBuilder.append:(I)Ljava/lang/StringBuilder;
       187: ldc           #119                // String  is out of bounds (min 0, max
       189: invokevirtual #122                // Method java/lang/StringBuilder.append:(Ljava/lang/String;)Ljava/lang/StringBuilder;
       192: iload         4
       194: iconst_1
       195: isub
       196: invokevirtual #117                // Method java/lang/StringBuilder.append:(I)Ljava/lang/StringBuilder;
       199: ldc           #139                // String )
       201: invokevirtual #122                // Method java/lang/StringBuilder.append:(Ljava/lang/String;)Ljava/lang/StringBuilder;
       204: invokevirtual #143                // Method java/lang/StringBuilder.toString:()Ljava/lang/String;
       207: invokespecial #146                // Method java/lang/IndexOutOfBoundsException."<init>":(Ljava/lang/String;)V
       210: athrow
       211: aload_3
       212: ifnonnull     217
       215: aconst_null
       216: athrow
       217: aload_3
       218: aload_2
       219: invokeinterface #80,  2           // InterfaceMethod scala/collection/mutable/Growable.addOne:(Ljava/lang/Object;)Lscala/collection/mutable/Growable;
       224: pop
       225: aload         5
       227: invokeinterface #64,  1           // InterfaceMethod scala/collection/Iterator.next:()Ljava/lang/Object;
       232: pop
       233: aload         5
       235: invokeinterface #61,  1           // InterfaceMethod scala/collection/Iterator.hasNext:()Z
       240: ifeq          267
       243: aload         5
       245: invokeinterface #64,  1           // InterfaceMethod scala/collection/Iterator.next:()Ljava/lang/Object;
       250: astore        7
       252: aload_3
       253: aload         7
       255: invokeinterface #80,  2           // InterfaceMethod scala/collection/mutable/Growable.addOne:(Ljava/lang/Object;)Lscala/collection/mutable/Growable;
       260: pop
       261: aconst_null
       262: astore        7
       264: goto          233
       267: aload_3
       268: invokeinterface #85,  1           // InterfaceMethod scala/collection/mutable/Builder.result:()Ljava/lang/Object;
       273: areturn
      StackMapTable: number_of_entries = 11
        frame_type = 255 /* full_frame */
          offset_delta = 49
          locals = [ class scala/collection/immutable/StrictOptimizedSeqOps, int, class java/lang/Object ]
          stack = [ uninitialized 5, uninitialized 5, class java/lang/StringBuilder ]
        frame_type = 255 /* full_frame */
          offset_delta = 1
          locals = [ class scala/collection/immutable/StrictOptimizedSeqOps, int, class java/lang/Object ]
          stack = [ uninitialized 5, uninitialized 5, class java/lang/StringBuilder, class java/lang/Object ]
        frame_type = 14 /* same */
        frame_type = 252 /* append */
          offset_delta = 33
          locals = [ class scala/collection/mutable/Builder ]
        frame_type = 253 /* append */
          offset_delta = 10
          locals = [ int, class scala/collection/Iterator ]
        frame_type = 252 /* append */
          offset_delta = 30
          locals = [ class java/lang/Object ]
        frame_type = 250 /* chop */
          offset_delta = 17
        frame_type = 50 /* same */
        frame_type = 5 /* same */
        frame_type = 15 /* same */
        frame_type = 33 /* same */
      LineNumberTable:
        line 42: 0
        line 43: 66
        line 44: 78
        line 45: 88
        line 47: 100
        line 48: 103
        line 49: 111
        line 50: 127
        line 51: 154
        line 49: 157
        line 53: 160
        line 54: 211
        line 55: 225
        line 56: 233
        line 57: 267
      LocalVariableTable:
        Start  Length  Slot  Name   Signature
           78     195     3     b   Lscala/collection/mutable/Builder;
          103     170     4     i   I
          111     162     5    it   Lscala/collection/Iterator;
            0     274     0  this   Lscala/collection/immutable/StrictOptimizedSeqOps;
            0     274     1 index   I
            0     274     2  elem   Ljava/lang/Object;
          142       9     6 $plus$eq_elem   Ljava/lang/Object;
          252       9     7 $plus$eq_elem   Ljava/lang/Object;
    Signature: #105                         // <B:Ljava/lang/Object;>(ITB;)TCC;
    MethodParameters:
      Name                           Flags
      index                          final
      elem                           final

  public static java.lang.Object patch$(scala.collection.immutable.StrictOptimizedSeqOps, int, scala.collection.IterableOnce, int);
    descriptor: (Lscala/collection/immutable/StrictOptimizedSeqOps;ILscala/collection/IterableOnce;I)Ljava/lang/Object;
    flags: (0x1009) ACC_PUBLIC, ACC_STATIC, ACC_SYNTHETIC
    Code:
      stack=4, locals=4, args_size=4
         0: aload_0
         1: iload_1
         2: aload_2
         3: iload_3
         4: invokespecial #175                // InterfaceMethod patch:(ILscala/collection/IterableOnce;I)Ljava/lang/Object;
         7: areturn
      LineNumberTable:
        line 60: 0
      LocalVariableTable:
        Start  Length  Slot  Name   Signature
            0       8     0 $this   Lscala/collection/immutable/StrictOptimizedSeqOps;
            0       8     1  from   I
            0       8     2 other   Lscala/collection/IterableOnce;
            0       8     3 replaced   I
    MethodParameters:
      Name                           Flags
      $this                          final synthetic
      from                           final
      other                          final
      replaced                       final

  public default <B extends java.lang.Object> CC patch(int, scala.collection.IterableOnce<B>, int);
    descriptor: (ILscala/collection/IterableOnce;I)Ljava/lang/Object;
    flags: (0x0001) ACC_PUBLIC
    Code:
      stack=2, locals=9, args_size=4
         0: aload_0
         1: invokeinterface #150,  1          // InterfaceMethod iterableFactory:()Lscala/collection/IterableFactory;
         6: invokeinterface #155,  1          // InterfaceMethod scala/collection/IterableFactory.newBuilder:()Lscala/collection/mutable/Builder;
        11: astore        4
        13: iconst_0
        14: istore        5
        16: aload_0
        17: invokeinterface #55,  1           // InterfaceMethod iterator:()Lscala/collection/Iterator;
        22: astore        6
        24: iload         5
        26: iload_1
        27: if_icmpge     75
        30: aload         6
        32: invokeinterface #61,  1           // InterfaceMethod scala/collection/Iterator.hasNext:()Z
        37: ifeq          75
        40: aload         4
        42: aload         6
        44: invokeinterface #64,  1           // InterfaceMethod scala/collection/Iterator.next:()Ljava/lang/Object;
        49: astore        7
        51: ifnonnull     56
        54: aconst_null
        55: athrow
        56: aload         4
        58: aload         7
        60: invokeinterface #80,  2           // InterfaceMethod scala/collection/mutable/Growable.addOne:(Ljava/lang/Object;)Lscala/collection/mutable/Growable;
        65: pop
        66: aconst_null
        67: astore        7
        69: iinc          5, 1
        72: goto          24
        75: aload         4
        77: ifnonnull     82
        80: aconst_null
        81: athrow
        82: aload         4
        84: aload_2
        85: invokeinterface #181,  2          // InterfaceMethod scala/collection/mutable/Growable.addAll:(Lscala/collection/IterableOnce;)Lscala/collection/mutable/Growable;
        90: pop
        91: iload_3
        92: istore        5
        94: iload         5
        96: iconst_0
        97: if_icmple     124
       100: aload         6
       102: invokeinterface #61,  1           // InterfaceMethod scala/collection/Iterator.hasNext:()Z
       107: ifeq          124
       110: aload         6
       112: invokeinterface #64,  1           // InterfaceMethod scala/collection/Iterator.next:()Ljava/lang/Object;
       117: pop
       118: iinc          5, -1
       121: goto          94
       124: aload         6
       126: invokeinterface #61,  1           // InterfaceMethod scala/collection/Iterator.hasNext:()Z
       131: ifeq          159
       134: aload         6
       136: invokeinterface #64,  1           // InterfaceMethod scala/collection/Iterator.next:()Ljava/lang/Object;
       141: astore        8
       143: aload         4
       145: aload         8
       147: invokeinterface #80,  2           // InterfaceMethod scala/collection/mutable/Growable.addOne:(Ljava/lang/Object;)Lscala/collection/mutable/Growable;
       152: pop
       153: aconst_null
       154: astore        8
       156: goto          124
       159: aload         4
       161: invokeinterface #85,  1           // InterfaceMethod scala/collection/mutable/Builder.result:()Ljava/lang/Object;
       166: areturn
      StackMapTable: number_of_entries = 7
        frame_type = 254 /* append */
          offset_delta = 24
          locals = [ class scala/collection/mutable/Builder, int, class scala/collection/Iterator ]
        frame_type = 252 /* append */
          offset_delta = 31
          locals = [ class java/lang/Object ]
        frame_type = 250 /* chop */
          offset_delta = 18
        frame_type = 6 /* same */
        frame_type = 11 /* same */
        frame_type = 29 /* same */
        frame_type = 34 /* same */
      LineNumberTable:
        line 61: 0
        line 62: 13
        line 63: 16
        line 64: 24
        line 65: 40
        line 66: 69
        line 64: 72
        line 68: 75
        line 69: 91
        line 70: 94
        line 71: 110
        line 72: 118
        line 70: 121
        line 74: 124
        line 75: 159
      LocalVariableTable:
        Start  Length  Slot  Name   Signature
           13     153     4     b   Lscala/collection/mutable/Builder;
           16     150     5     i   I
           24     142     6    it   Lscala/collection/Iterator;
            0     167     0  this   Lscala/collection/immutable/StrictOptimizedSeqOps;
            0     167     1  from   I
            0     167     2 other   Lscala/collection/IterableOnce;
            0     167     3 replaced   I
           56      10     7 $plus$eq_elem   Ljava/lang/Object;
          143      10     8 $plus$eq_elem   Ljava/lang/Object;
    Signature: #177                         // <B:Ljava/lang/Object;>(ILscala/collection/IterableOnce<TB;>;I)TCC;
    MethodParameters:
      Name                           Flags
      from                           final
      other                          final
      replaced                       final

  public static java.lang.Object sorted$(scala.collection.immutable.StrictOptimizedSeqOps, scala.math.Ordering);
    descriptor: (Lscala/collection/immutable/StrictOptimizedSeqOps;Lscala/math/Ordering;)Ljava/lang/Object;
    flags: (0x1009) ACC_PUBLIC, ACC_STATIC, ACC_SYNTHETIC
    Code:
      stack=2, locals=2, args_size=2
         0: aload_0
         1: aload_1
         2: invokespecial #186                // InterfaceMethod sorted:(Lscala/math/Ordering;)Ljava/lang/Object;
         5: areturn
      LineNumberTable:
        line 78: 0
      LocalVariableTable:
        Start  Length  Slot  Name   Signature
            0       6     0 $this   Lscala/collection/immutable/StrictOptimizedSeqOps;
            0       6     1   ord   Lscala/math/Ordering;
    MethodParameters:
      Name                           Flags
      $this                          final synthetic
      ord                            final

  public default <B extends java.lang.Object> C sorted(scala.math.Ordering<B>);
    descriptor: (Lscala/math/Ordering;)Ljava/lang/Object;
    flags: (0x0001) ACC_PUBLIC
    Code:
      stack=2, locals=2, args_size=2
         0: aload_0
         1: aload_1
         2: invokeinterface #190,  2          // InterfaceMethod scala$collection$immutable$StrictOptimizedSeqOps$$super$sorted:(Lscala/math/Ordering;)Ljava/lang/Object;
         7: areturn
      LineNumberTable:
        line 78: 0
      LocalVariableTable:
        Start  Length  Slot  Name   Signature
            0       8     0  this   Lscala/collection/immutable/StrictOptimizedSeqOps;
            0       8     1   ord   Lscala/math/Ordering;
    Signature: #188                         // <B:Ljava/lang/Object;>(Lscala/math/Ordering<TB;>;)TC;
    MethodParameters:
      Name                           Flags
      ord                            final

  public static void $init$(scala.collection.immutable.StrictOptimizedSeqOps);
    descriptor: (Lscala/collection/immutable/StrictOptimizedSeqOps;)V
    flags: (0x0009) ACC_PUBLIC, ACC_STATIC
    Code:
      stack=0, locals=1, args_size=1
         0: return
      LineNumberTable:
        line 21: 0
      LocalVariableTable:
        Start  Length  Slot  Name   Signature
            0       1     0 $this   Lscala/collection/immutable/StrictOptimizedSeqOps;
    MethodParameters:
      Name                           Flags
      $this                          final synthetic
}
Signature: #3                           // <A:Ljava/lang/Object;CC:Ljava/lang/Object;C:Ljava/lang/Object;>Ljava/lang/Object;Lscala/collection/immutable/SeqOps<TA;TCC;TC;>;Lscala/collection/StrictOptimizedSeqOps<TA;TCC;TC;>;
SourceFile: "StrictOptimizedSeqOps.scala"
RuntimeVisibleAnnotations:
  0: #11(#12=s#13)
    scala.reflect.ScalaSignature(
      bytes="\u0006\u0005i4qa\u0002\u0005\u0011\u0002\u0007\u0005q\u0002C\u00031\u0001\u0011\u0005\u0011\u0007C\u00036\u0001\u0011\u0005c\u0007C\u0003A\u0001\u0011\u0005\u0013\tC\u0003O\u0001\u0011\u0005s\nC\u0003^\u0001\u0011\u0005c\fC\u0006l\u0001A\u0005\u0019\u0011!A\u0005\n1D(!F*ue&\u001cGo\u00149uS6L\'0\u001a3TKF|\u0005o\u001d\u0006\u0003\u0013)\t\u0011\"[7nkR\f\'\r\\3\u000b\u0005-a\u0011AC2pY2,7\r^5p]*\tQ\"A\u0003tG\u0006d\u0017m\u0001\u0001\u0016\tAY\"\u0005K\n\u0006\u0001E)\"&\f\t\u0003%Mi\u0011\u0001D\u0005\u0003)1\u00111!\u00118z!\u00151r#G\u0011(\u001b\u0005A\u0011B\u0001\r\t\u0005\u0019\u0019V-](qgB\u0011!d\u0007\u0007\u0001\t\u0019a\u0002\u0001\"b\u0001;\t\t\u0011)\u0005\u0002\u001f#A\u0011!cH\u0005\u0003A1\u0011qAT8uQ&tw\r\u0005\u0002\u001bE\u001111\u0005\u0001CC\u0002\u0011\u0012!aQ\"\u0016\u0005u)C!\u0002\u0014#\u0005\u0004i\"\u0001B0%IE\u0002\"A\u0007\u0015\u0005\r%\u0002AQ1\u0001\u001e\u0005\u0005\u0019\u0005#B\u0016-3\u0005:S\"\u0001\u0006\n\u0005\u001dQ\u0001#B\u0016/3\u0005:\u0013BA\u0018\u000b\u0005i\u0019FO]5di>\u0003H/[7ju\u0016$\u0017\n^3sC\ndWm\u00149t\u0003\u0019!\u0013N\\5uIQ\t!\u0007\u0005\u0002\u0013g%\u0011A\u0007\u0004\u0002\u0005+:LG/\u0001\u0006eSN$\u0018N\\2u\u0005f,\"a\u000e \u0015\u0005\u001dB\u0004\"B\u001d\u0003\u0001\u0004Q\u0014!\u00014\u0011\tIY\u0014$P\u0005\u0003y1\u0011\u0011BR;oGRLwN\\\u0019\u0011\u0005iqD!B \u0003\u0005\u0004i\"!\u0001\"\u0002\u000fU\u0004H-\u0019;fIV\u0011!)\u0012\u000b\u0004\u0007\u001ec\u0005c\u0001\u000e#\tB\u0011!$\u0012\u0003\u0006\u007f\r\u0011\rAR\t\u00033EAQ\u0001S\u0002A\u0002%\u000bQ!\u001b8eKb\u0004\"A\u0005&\n\u0005-c!aA%oi\")Qj\u0001a\u0001\t\u0006!Q\r\\3n\u0003\u0015\u0001\u0018\r^2i+\t\u00016\u000b\u0006\u0003R)Z[\u0006c\u0001\u000e#%B\u0011!d\u0015\u0003\u0006\u007f\u0011\u0011\rA\u0012\u0005\u0006+\u0012\u0001\r!S\u0001\u0005MJ|W\u000eC\u0003X\t\u0001\u0007\u0001,A\u0003pi\",\'\u000fE\u0002,3JK!A\u0017\u0006\u0003\u0019%#XM]1cY\u0016|enY3\t\u000bq#\u0001\u0019A%\u0002\u0011I,\u0007\u000f\\1dK\u0012\faa]8si\u0016$WCA0k)\t9\u0003\rC\u0003b\u000b\u0001\u000f!-A\u0002pe\u0012\u00042a\u00194j\u001d\t\u0011B-\u0003\u0002f\u0019\u00059\u0001/Y2lC\u001e,\u0017BA4i\u0005!y%\u000fZ3sS:<\'BA3\r!\tQ\"\u000eB\u0003@\u000b\t\u0007a)\u0001\u0007tkB,\'\u000fJ:peR,G-\u0006\u0002noR\u0011qE\u001c\u0005\u0006C\u001a\u0001\u001da\u001c\t\u0004a\u001a4hBA9e\u001d\t\u0011X/D\u0001t\u0015\t!h\"\u0001\u0004=e>|GOP\u0005\u0002\u001bA\u0011!d\u001e\u0003\u0006\u007f\u0019\u0011\rAR\u0005\u0003;fL!\u0001\u0007\u0006"
    )
  ScalaInlineInfo: length = 0x36 (unknown attribute)
   01 00 00 0A 00 BF 00 C0 01 00 15 00 16 00 00 11
   00 12 01 00 AC 00 AD 00 00 A7 00 A8 01 00 0E 00
   0F 01 00 B8 00 0F 00 00 B6 00 B7 01 00 64 00 65
   00 00 60 00 61 01
  ScalaSig: length = 0x3 (unknown attribute)
   05 02 00
