Classfile /Users/mw/Projects/slang-braindump/.jar/jar11/assemble/slang-braindump/assemble/content/scala/collection/immutable/TreeSeqMap$.class
  Last modified May 29, 2022; size 6232 bytes
  SHA-256 checksum bd52fa40f502363441f78d29cb880bde32abcffd08af7208afbda5eb2927fa4c
  Compiled from "TreeSeqMap.scala"
public final class scala.collection.immutable.TreeSeqMap$ extends java.lang.Object implements scala.collection.MapFactory<scala.collection.immutable.TreeSeqMap>
  minor version: 0
  major version: 52
  flags: (0x0031) ACC_PUBLIC, ACC_FINAL, ACC_SUPER
  this_class: #2                          // scala/collection/immutable/TreeSeqMap$
  super_class: #5                         // java/lang/Object
  interfaces: 1, fields: 5, methods: 17, attributes: 5
Constant pool:
    #1 = Utf8               scala/collection/immutable/TreeSeqMap$
    #2 = Class              #1            // scala/collection/immutable/TreeSeqMap$
    #3 = Utf8               Ljava/lang/Object;Lscala/collection/MapFactory<Lscala/collection/immutable/TreeSeqMap;>;
    #4 = Utf8               java/lang/Object
    #5 = Class              #4            // java/lang/Object
    #6 = Utf8               scala/collection/MapFactory
    #7 = Class              #6            // scala/collection/MapFactory
    #8 = Utf8               TreeSeqMap.scala
    #9 = Utf8               scala/collection/immutable/TreeSeqMap$Builder
   #10 = Class              #9            // scala/collection/immutable/TreeSeqMap$Builder
   #11 = Utf8               scala/collection/immutable/TreeSeqMap
   #12 = Class              #11           // scala/collection/immutable/TreeSeqMap
   #13 = Utf8               Builder
   #14 = Utf8               scala/collection/immutable/TreeSeqMap$OrderBy
   #15 = Class              #14           // scala/collection/immutable/TreeSeqMap$OrderBy
   #16 = Utf8               OrderBy
   #17 = Utf8               scala/collection/immutable/TreeSeqMap$OrderBy$
   #18 = Class              #17           // scala/collection/immutable/TreeSeqMap$OrderBy$
   #19 = Utf8               OrderBy$
   #20 = Utf8               scala/collection/immutable/TreeSeqMap$OrderBy$Insertion$
   #21 = Class              #20           // scala/collection/immutable/TreeSeqMap$OrderBy$Insertion$
   #22 = Utf8               Insertion$
   #23 = Utf8               scala/collection/immutable/TreeSeqMap$OrderBy$Modification$
   #24 = Class              #23           // scala/collection/immutable/TreeSeqMap$OrderBy$Modification$
   #25 = Utf8               Modification$
   #26 = Utf8               scala/collection/immutable/TreeSeqMap$Ordering
   #27 = Class              #26           // scala/collection/immutable/TreeSeqMap$Ordering
   #28 = Utf8               Ordering
   #29 = Utf8               scala/collection/immutable/TreeSeqMap$Ordering$
   #30 = Class              #29           // scala/collection/immutable/TreeSeqMap$Ordering$
   #31 = Utf8               Ordering$
   #32 = Utf8               scala/collection/immutable/TreeSeqMap$Ordering$Zero$
   #33 = Class              #32           // scala/collection/immutable/TreeSeqMap$Ordering$Zero$
   #34 = Utf8               Zero$
   #35 = Utf8               MODULE$
   #36 = Utf8               Lscala/collection/immutable/TreeSeqMap$;
   #37 = Utf8               EmptyByInsertion
   #38 = Utf8               Lscala/collection/immutable/TreeSeqMap;
   #39 = Utf8               Lscala/collection/immutable/TreeSeqMap<Lscala/runtime/Nothing$;Lscala/runtime/Nothing$;>;
   #40 = Utf8               EmptyByModification
   #41 = Utf8               Empty
   #42 = Utf8               Mapping
   #43 = Utf8               Lscala/collection/immutable/Map$;
   #44 = Utf8               <clinit>
   #45 = Utf8               ()V
   #46 = Utf8               <init>
   #47 = NameAndType        #46:#45       // "<init>":()V
   #48 = Methodref          #2.#47        // scala/collection/immutable/TreeSeqMap$."<init>":()V
   #49 = NameAndType        #35:#36       // MODULE$:Lscala/collection/immutable/TreeSeqMap$;
   #50 = Fieldref           #2.#49        // scala/collection/immutable/TreeSeqMap$.MODULE$:Lscala/collection/immutable/TreeSeqMap$;
   #51 = Utf8               Lscala/collection/immutable/TreeSeqMap$Ordering$;
   #52 = NameAndType        #35:#51       // MODULE$:Lscala/collection/immutable/TreeSeqMap$Ordering$;
   #53 = Fieldref           #30.#52       // scala/collection/immutable/TreeSeqMap$Ordering$.MODULE$:Lscala/collection/immutable/TreeSeqMap$Ordering$;
   #54 = Utf8               Lscala/collection/immutable/TreeSeqMap$Ordering$Zero$;
   #55 = NameAndType        #35:#54       // MODULE$:Lscala/collection/immutable/TreeSeqMap$Ordering$Zero$;
   #56 = Fieldref           #33.#55       // scala/collection/immutable/TreeSeqMap$Ordering$Zero$.MODULE$:Lscala/collection/immutable/TreeSeqMap$Ordering$Zero$;
   #57 = Utf8               scala/collection/immutable/HashMap$
   #58 = Class              #57           // scala/collection/immutable/HashMap$
   #59 = Utf8               Lscala/collection/immutable/HashMap$;
   #60 = NameAndType        #35:#59       // MODULE$:Lscala/collection/immutable/HashMap$;
   #61 = Fieldref           #58.#60       // scala/collection/immutable/HashMap$.MODULE$:Lscala/collection/immutable/HashMap$;
   #62 = Utf8               empty
   #63 = Utf8               ()Lscala/collection/immutable/HashMap;
   #64 = NameAndType        #62:#63       // empty:()Lscala/collection/immutable/HashMap;
   #65 = Methodref          #58.#64       // scala/collection/immutable/HashMap$.empty:()Lscala/collection/immutable/HashMap;
   #66 = Utf8               Lscala/collection/immutable/TreeSeqMap$OrderBy$Insertion$;
   #67 = NameAndType        #35:#66       // MODULE$:Lscala/collection/immutable/TreeSeqMap$OrderBy$Insertion$;
   #68 = Fieldref           #21.#67       // scala/collection/immutable/TreeSeqMap$OrderBy$Insertion$.MODULE$:Lscala/collection/immutable/TreeSeqMap$OrderBy$Insertion$;
   #69 = Utf8               (Lscala/collection/immutable/TreeSeqMap$Ordering;Lscala/collection/immutable/Map;ILscala/collection/immutable/TreeSeqMap$OrderBy;)V
   #70 = NameAndType        #46:#69       // "<init>":(Lscala/collection/immutable/TreeSeqMap$Ordering;Lscala/collection/immutable/Map;ILscala/collection/immutable/TreeSeqMap$OrderBy;)V
   #71 = Methodref          #12.#70       // scala/collection/immutable/TreeSeqMap."<init>":(Lscala/collection/immutable/TreeSeqMap$Ordering;Lscala/collection/immutable/Map;ILscala/collection/immutable/TreeSeqMap$OrderBy;)V
   #72 = NameAndType        #37:#38       // EmptyByInsertion:Lscala/collection/immutable/TreeSeqMap;
   #73 = Fieldref           #2.#72        // scala/collection/immutable/TreeSeqMap$.EmptyByInsertion:Lscala/collection/immutable/TreeSeqMap;
   #74 = Utf8               Lscala/collection/immutable/TreeSeqMap$OrderBy$Modification$;
   #75 = NameAndType        #35:#74       // MODULE$:Lscala/collection/immutable/TreeSeqMap$OrderBy$Modification$;
   #76 = Fieldref           #24.#75       // scala/collection/immutable/TreeSeqMap$OrderBy$Modification$.MODULE$:Lscala/collection/immutable/TreeSeqMap$OrderBy$Modification$;
   #77 = NameAndType        #40:#38       // EmptyByModification:Lscala/collection/immutable/TreeSeqMap;
   #78 = Fieldref           #2.#77        // scala/collection/immutable/TreeSeqMap$.EmptyByModification:Lscala/collection/immutable/TreeSeqMap;
   #79 = Utf8               ()Lscala/collection/immutable/TreeSeqMap;
   #80 = NameAndType        #37:#79       // EmptyByInsertion:()Lscala/collection/immutable/TreeSeqMap;
   #81 = Methodref          #2.#80        // scala/collection/immutable/TreeSeqMap$.EmptyByInsertion:()Lscala/collection/immutable/TreeSeqMap;
   #82 = NameAndType        #41:#38       // Empty:Lscala/collection/immutable/TreeSeqMap;
   #83 = Fieldref           #2.#82        // scala/collection/immutable/TreeSeqMap$.Empty:Lscala/collection/immutable/TreeSeqMap;
   #84 = Utf8               scala/collection/immutable/Map$
   #85 = Class              #84           // scala/collection/immutable/Map$
   #86 = NameAndType        #35:#43       // MODULE$:Lscala/collection/immutable/Map$;
   #87 = Fieldref           #85.#86       // scala/collection/immutable/Map$.MODULE$:Lscala/collection/immutable/Map$;
   #88 = NameAndType        #42:#43       // Mapping:Lscala/collection/immutable/Map$;
   #89 = Fieldref           #2.#88        // scala/collection/immutable/TreeSeqMap$.Mapping:Lscala/collection/immutable/Map$;
   #90 = Utf8               apply
   #91 = Utf8               (Lscala/collection/immutable/Seq;)Ljava/lang/Object;
   #92 = Utf8               elems
   #93 = Utf8               apply$
   #94 = Utf8               (Lscala/collection/MapFactory;Lscala/collection/immutable/Seq;)Ljava/lang/Object;
   #95 = NameAndType        #93:#94       // apply$:(Lscala/collection/MapFactory;Lscala/collection/immutable/Seq;)Ljava/lang/Object;
   #96 = InterfaceMethodref #7.#95        // scala/collection/MapFactory.apply$:(Lscala/collection/MapFactory;Lscala/collection/immutable/Seq;)Ljava/lang/Object;
   #97 = Utf8               this
   #98 = Utf8               Lscala/collection/immutable/Seq;
   #99 = Utf8               mapFactory
  #100 = Utf8               ()Lscala/collection/Factory;
  #101 = Utf8               <K:Ljava/lang/Object;V:Ljava/lang/Object;>()Lscala/collection/Factory<Lscala/Tuple2<TK;TV;>;Lscala/collection/immutable/TreeSeqMap<TK;TV;>;>;
  #102 = Utf8               mapFactory$
  #103 = Utf8               (Lscala/collection/MapFactory;)Lscala/collection/Factory;
  #104 = NameAndType        #102:#103     // mapFactory$:(Lscala/collection/MapFactory;)Lscala/collection/Factory;
  #105 = InterfaceMethodref #7.#104       // scala/collection/MapFactory.mapFactory$:(Lscala/collection/MapFactory;)Lscala/collection/Factory;
  #106 = Utf8               ()Lscala/collection/immutable/TreeSeqMap<Lscala/runtime/Nothing$;Lscala/runtime/Nothing$;>;
  #107 = Utf8               <K:Ljava/lang/Object;V:Ljava/lang/Object;>()Lscala/collection/immutable/TreeSeqMap<TK;TV;>;
  #108 = Utf8               (Lscala/collection/immutable/TreeSeqMap$OrderBy;)Lscala/collection/immutable/TreeSeqMap;
  #109 = NameAndType        #62:#108      // empty:(Lscala/collection/immutable/TreeSeqMap$OrderBy;)Lscala/collection/immutable/TreeSeqMap;
  #110 = Methodref          #2.#109       // scala/collection/immutable/TreeSeqMap$.empty:(Lscala/collection/immutable/TreeSeqMap$OrderBy;)Lscala/collection/immutable/TreeSeqMap;
  #111 = Utf8               <K:Ljava/lang/Object;V:Ljava/lang/Object;>(Lscala/collection/immutable/TreeSeqMap$OrderBy;)Lscala/collection/immutable/TreeSeqMap<TK;TV;>;
  #112 = Utf8               orderBy
  #113 = Utf8               equals
  #114 = Utf8               (Ljava/lang/Object;)Z
  #115 = NameAndType        #113:#114     // equals:(Ljava/lang/Object;)Z
  #116 = Methodref          #5.#115       // java/lang/Object.equals:(Ljava/lang/Object;)Z
  #117 = NameAndType        #40:#79       // EmptyByModification:()Lscala/collection/immutable/TreeSeqMap;
  #118 = Methodref          #2.#117       // scala/collection/immutable/TreeSeqMap$.EmptyByModification:()Lscala/collection/immutable/TreeSeqMap;
  #119 = Utf8               Lscala/collection/immutable/TreeSeqMap$OrderBy;
  #120 = Utf8               from
  #121 = Utf8               (Lscala/collection/IterableOnce;)Lscala/collection/immutable/TreeSeqMap;
  #122 = Utf8               <K:Ljava/lang/Object;V:Ljava/lang/Object;>(Lscala/collection/IterableOnce<Lscala/Tuple2<TK;TV;>;>;)Lscala/collection/immutable/TreeSeqMap<TK;TV;>;
  #123 = Utf8               it
  #124 = Utf8               (Lscala/collection/immutable/TreeSeqMap$OrderBy;)V
  #125 = NameAndType        #46:#124      // "<init>":(Lscala/collection/immutable/TreeSeqMap$OrderBy;)V
  #126 = Methodref          #10.#125      // scala/collection/immutable/TreeSeqMap$Builder."<init>":(Lscala/collection/immutable/TreeSeqMap$OrderBy;)V
  #127 = Utf8               scala/collection/mutable/Growable
  #128 = Class              #127          // scala/collection/mutable/Growable
  #129 = Utf8               addAll$
  #130 = Utf8               (Lscala/collection/mutable/Growable;Lscala/collection/IterableOnce;)Lscala/collection/mutable/Growable;
  #131 = NameAndType        #129:#130     // addAll$:(Lscala/collection/mutable/Growable;Lscala/collection/IterableOnce;)Lscala/collection/mutable/Growable;
  #132 = InterfaceMethodref #128.#131     // scala/collection/mutable/Growable.addAll$:(Lscala/collection/mutable/Growable;Lscala/collection/IterableOnce;)Lscala/collection/mutable/Growable;
  #133 = Utf8               scala/collection/mutable/Builder
  #134 = Class              #133          // scala/collection/mutable/Builder
  #135 = Utf8               result
  #136 = Utf8               ()Ljava/lang/Object;
  #137 = NameAndType        #135:#136     // result:()Ljava/lang/Object;
  #138 = InterfaceMethodref #134.#137     // scala/collection/mutable/Builder.result:()Ljava/lang/Object;
  #139 = Utf8               Lscala/collection/IterableOnce;
  #140 = Utf8               newBuilder_newBuilder_orderedBy
  #141 = Utf8               scala$collection$immutable$TreeSeqMap$$increment
  #142 = Utf8               (I)I
  #143 = Utf8               ord
  #144 = Integer            2147483647
  #145 = Integer            -2147483648
  #146 = Utf8               I
  #147 = Utf8               newBuilder
  #148 = Utf8               ()Lscala/collection/mutable/Builder;
  #149 = Utf8               <K:Ljava/lang/Object;V:Ljava/lang/Object;>()Lscala/collection/mutable/Builder<Lscala/Tuple2<TK;TV;>;Lscala/collection/immutable/TreeSeqMap<TK;TV;>;>;
  #150 = Utf8               newBuilder_orderedBy
  #151 = Utf8               (Lscala/collection/immutable/TreeSeqMap$OrderBy;)Lscala/collection/mutable/Builder;
  #152 = Utf8               <K:Ljava/lang/Object;V:Ljava/lang/Object;>(Lscala/collection/immutable/TreeSeqMap$OrderBy;)Lscala/collection/mutable/Builder<Lscala/Tuple2<TK;TV;>;Lscala/collection/immutable/TreeSeqMap<TK;TV;>;>;
  #153 = Utf8               orderedBy
  #154 = Utf8               ()Lscala/collection/immutable/Map$;
  #155 = Utf8               writeReplace
  #156 = Utf8               scala/runtime/ModuleSerializationProxy
  #157 = Class              #156          // scala/runtime/ModuleSerializationProxy
  #158 = Utf8               (Ljava/lang/Class;)V
  #159 = NameAndType        #46:#158      // "<init>":(Ljava/lang/Class;)V
  #160 = Methodref          #157.#159     // scala/runtime/ModuleSerializationProxy."<init>":(Ljava/lang/Class;)V
  #161 = Utf8               (Lscala/collection/IterableOnce;)Ljava/lang/Object;
  #162 = NameAndType        #120:#121     // from:(Lscala/collection/IterableOnce;)Lscala/collection/immutable/TreeSeqMap;
  #163 = Methodref          #2.#162       // scala/collection/immutable/TreeSeqMap$.from:(Lscala/collection/IterableOnce;)Lscala/collection/immutable/TreeSeqMap;
  #164 = NameAndType        #62:#79       // empty:()Lscala/collection/immutable/TreeSeqMap;
  #165 = Methodref          #2.#164       // scala/collection/immutable/TreeSeqMap$.empty:()Lscala/collection/immutable/TreeSeqMap;
  #166 = Methodref          #5.#47        // java/lang/Object."<init>":()V
  #167 = Utf8               Signature
  #168 = Utf8               Code
  #169 = Utf8               LineNumberTable
  #170 = Utf8               LocalVariableTable
  #171 = Utf8               MethodParameters
  #172 = Utf8               StackMapTable
  #173 = Utf8               InnerClasses
  #174 = Utf8               SourceFile
  #175 = Utf8               ScalaInlineInfo
  #176 = Utf8               Scala
{
  public static final scala.collection.immutable.TreeSeqMap$ MODULE$;
    descriptor: Lscala/collection/immutable/TreeSeqMap$;
    flags: (0x0019) ACC_PUBLIC, ACC_STATIC, ACC_FINAL

  private static final scala.collection.immutable.TreeSeqMap<scala.runtime.Nothing$, scala.runtime.Nothing$> EmptyByInsertion;
    descriptor: Lscala/collection/immutable/TreeSeqMap;
    flags: (0x001a) ACC_PRIVATE, ACC_STATIC, ACC_FINAL
    Signature: #39                          // Lscala/collection/immutable/TreeSeqMap<Lscala/runtime/Nothing$;Lscala/runtime/Nothing$;>;

  private static final scala.collection.immutable.TreeSeqMap<scala.runtime.Nothing$, scala.runtime.Nothing$> EmptyByModification;
    descriptor: Lscala/collection/immutable/TreeSeqMap;
    flags: (0x001a) ACC_PRIVATE, ACC_STATIC, ACC_FINAL
    Signature: #39                          // Lscala/collection/immutable/TreeSeqMap<Lscala/runtime/Nothing$;Lscala/runtime/Nothing$;>;

  private static final scala.collection.immutable.TreeSeqMap<scala.runtime.Nothing$, scala.runtime.Nothing$> Empty;
    descriptor: Lscala/collection/immutable/TreeSeqMap;
    flags: (0x001a) ACC_PRIVATE, ACC_STATIC, ACC_FINAL
    Signature: #39                          // Lscala/collection/immutable/TreeSeqMap<Lscala/runtime/Nothing$;Lscala/runtime/Nothing$;>;

  private static final scala.collection.immutable.Map$ Mapping;
    descriptor: Lscala/collection/immutable/Map$;
    flags: (0x001a) ACC_PRIVATE, ACC_STATIC, ACC_FINAL

  public static {};
    descriptor: ()V
    flags: (0x0009) ACC_PUBLIC, ACC_STATIC
    Code:
      stack=6, locals=0, args_size=0
         0: new           #2                  // class scala/collection/immutable/TreeSeqMap$
         3: dup
         4: invokespecial #48                 // Method "<init>":()V
         7: putstatic     #50                 // Field MODULE$:Lscala/collection/immutable/TreeSeqMap$;
        10: getstatic     #50                 // Field MODULE$:Lscala/collection/immutable/TreeSeqMap$;
        13: pop
        14: new           #12                 // class scala/collection/immutable/TreeSeqMap
        17: dup
        18: getstatic     #53                 // Field scala/collection/immutable/TreeSeqMap$Ordering$.MODULE$:Lscala/collection/immutable/TreeSeqMap$Ordering$;
        21: pop
        22: getstatic     #56                 // Field scala/collection/immutable/TreeSeqMap$Ordering$Zero$.MODULE$:Lscala/collection/immutable/TreeSeqMap$Ordering$Zero$;
        25: getstatic     #61                 // Field scala/collection/immutable/HashMap$.MODULE$:Lscala/collection/immutable/HashMap$;
        28: invokevirtual #65                 // Method scala/collection/immutable/HashMap$.empty:()Lscala/collection/immutable/HashMap;
        31: iconst_0
        32: getstatic     #68                 // Field scala/collection/immutable/TreeSeqMap$OrderBy$Insertion$.MODULE$:Lscala/collection/immutable/TreeSeqMap$OrderBy$Insertion$;
        35: invokespecial #71                 // Method scala/collection/immutable/TreeSeqMap."<init>":(Lscala/collection/immutable/TreeSeqMap$Ordering;Lscala/collection/immutable/Map;ILscala/collection/immutable/TreeSeqMap$OrderBy;)V
        38: putstatic     #73                 // Field EmptyByInsertion:Lscala/collection/immutable/TreeSeqMap;
        41: new           #12                 // class scala/collection/immutable/TreeSeqMap
        44: dup
        45: getstatic     #53                 // Field scala/collection/immutable/TreeSeqMap$Ordering$.MODULE$:Lscala/collection/immutable/TreeSeqMap$Ordering$;
        48: pop
        49: getstatic     #56                 // Field scala/collection/immutable/TreeSeqMap$Ordering$Zero$.MODULE$:Lscala/collection/immutable/TreeSeqMap$Ordering$Zero$;
        52: getstatic     #61                 // Field scala/collection/immutable/HashMap$.MODULE$:Lscala/collection/immutable/HashMap$;
        55: invokevirtual #65                 // Method scala/collection/immutable/HashMap$.empty:()Lscala/collection/immutable/HashMap;
        58: iconst_0
        59: getstatic     #76                 // Field scala/collection/immutable/TreeSeqMap$OrderBy$Modification$.MODULE$:Lscala/collection/immutable/TreeSeqMap$OrderBy$Modification$;
        62: invokespecial #71                 // Method scala/collection/immutable/TreeSeqMap."<init>":(Lscala/collection/immutable/TreeSeqMap$Ordering;Lscala/collection/immutable/Map;ILscala/collection/immutable/TreeSeqMap$OrderBy;)V
        65: putstatic     #78                 // Field EmptyByModification:Lscala/collection/immutable/TreeSeqMap;
        68: getstatic     #50                 // Field MODULE$:Lscala/collection/immutable/TreeSeqMap$;
        71: invokespecial #81                 // Method EmptyByInsertion:()Lscala/collection/immutable/TreeSeqMap;
        74: putstatic     #83                 // Field Empty:Lscala/collection/immutable/TreeSeqMap;
        77: getstatic     #87                 // Field scala/collection/immutable/Map$.MODULE$:Lscala/collection/immutable/Map$;
        80: putstatic     #89                 // Field Mapping:Lscala/collection/immutable/Map$;
        83: return
      LineNumberTable:
        line 289: 0
        line 296: 14
        line 369: 22
        line 296: 25
        line 297: 41
        line 369: 49
        line 297: 52
        line 298: 68
        line 361: 77
        line 289: 83

  public java.lang.Object apply(scala.collection.immutable.Seq);
    descriptor: (Lscala/collection/immutable/Seq;)Ljava/lang/Object;
    flags: (0x0001) ACC_PUBLIC
    Code:
      stack=2, locals=2, args_size=2
         0: aload_0
         1: aload_1
         2: invokestatic  #96                 // InterfaceMethod scala/collection/MapFactory.apply$:(Lscala/collection/MapFactory;Lscala/collection/immutable/Seq;)Ljava/lang/Object;
         5: areturn
      LineNumberTable:
        line 289: 0
      LocalVariableTable:
        Start  Length  Slot  Name   Signature
            0       6     0  this   Lscala/collection/immutable/TreeSeqMap$;
            0       6     1 elems   Lscala/collection/immutable/Seq;
    MethodParameters:
      Name                           Flags
      elems                          final

  public <K extends java.lang.Object, V extends java.lang.Object> scala.collection.Factory<scala.Tuple2<K, V>, scala.collection.immutable.TreeSeqMap<K, V>> mapFactory();
    descriptor: ()Lscala/collection/Factory;
    flags: (0x0001) ACC_PUBLIC
    Code:
      stack=1, locals=1, args_size=1
         0: aload_0
         1: invokestatic  #105                // InterfaceMethod scala/collection/MapFactory.mapFactory$:(Lscala/collection/MapFactory;)Lscala/collection/Factory;
         4: areturn
      LineNumberTable:
        line 289: 0
      LocalVariableTable:
        Start  Length  Slot  Name   Signature
            0       5     0  this   Lscala/collection/immutable/TreeSeqMap$;
    Signature: #101                         // <K:Ljava/lang/Object;V:Ljava/lang/Object;>()Lscala/collection/Factory<Lscala/Tuple2<TK;TV;>;Lscala/collection/immutable/TreeSeqMap<TK;TV;>;>;

  private scala.collection.immutable.TreeSeqMap<scala.runtime.Nothing$, scala.runtime.Nothing$> EmptyByInsertion();
    descriptor: ()Lscala/collection/immutable/TreeSeqMap;
    flags: (0x0002) ACC_PRIVATE
    Code:
      stack=1, locals=1, args_size=1
         0: getstatic     #73                 // Field EmptyByInsertion:Lscala/collection/immutable/TreeSeqMap;
         3: areturn
      LineNumberTable:
        line 296: 0
      LocalVariableTable:
        Start  Length  Slot  Name   Signature
            0       4     0  this   Lscala/collection/immutable/TreeSeqMap$;
    Signature: #106                         // ()Lscala/collection/immutable/TreeSeqMap<Lscala/runtime/Nothing$;Lscala/runtime/Nothing$;>;

  private scala.collection.immutable.TreeSeqMap<scala.runtime.Nothing$, scala.runtime.Nothing$> EmptyByModification();
    descriptor: ()Lscala/collection/immutable/TreeSeqMap;
    flags: (0x0002) ACC_PRIVATE
    Code:
      stack=1, locals=1, args_size=1
         0: getstatic     #78                 // Field EmptyByModification:Lscala/collection/immutable/TreeSeqMap;
         3: areturn
      LineNumberTable:
        line 297: 0
      LocalVariableTable:
        Start  Length  Slot  Name   Signature
            0       4     0  this   Lscala/collection/immutable/TreeSeqMap$;
    Signature: #106                         // ()Lscala/collection/immutable/TreeSeqMap<Lscala/runtime/Nothing$;Lscala/runtime/Nothing$;>;

  public scala.collection.immutable.TreeSeqMap<scala.runtime.Nothing$, scala.runtime.Nothing$> Empty();
    descriptor: ()Lscala/collection/immutable/TreeSeqMap;
    flags: (0x0001) ACC_PUBLIC
    Code:
      stack=1, locals=1, args_size=1
         0: getstatic     #83                 // Field Empty:Lscala/collection/immutable/TreeSeqMap;
         3: areturn
      LineNumberTable:
        line 298: 0
      LocalVariableTable:
        Start  Length  Slot  Name   Signature
            0       4     0  this   Lscala/collection/immutable/TreeSeqMap$;
    Signature: #106                         // ()Lscala/collection/immutable/TreeSeqMap<Lscala/runtime/Nothing$;Lscala/runtime/Nothing$;>;

  public <K extends java.lang.Object, V extends java.lang.Object> scala.collection.immutable.TreeSeqMap<K, V> empty();
    descriptor: ()Lscala/collection/immutable/TreeSeqMap;
    flags: (0x0001) ACC_PUBLIC
    Code:
      stack=2, locals=1, args_size=1
         0: aload_0
         1: getstatic     #68                 // Field scala/collection/immutable/TreeSeqMap$OrderBy$Insertion$.MODULE$:Lscala/collection/immutable/TreeSeqMap$OrderBy$Insertion$;
         4: invokevirtual #110                // Method empty:(Lscala/collection/immutable/TreeSeqMap$OrderBy;)Lscala/collection/immutable/TreeSeqMap;
         7: areturn
      LineNumberTable:
        line 299: 0
      LocalVariableTable:
        Start  Length  Slot  Name   Signature
            0       8     0  this   Lscala/collection/immutable/TreeSeqMap$;
    Signature: #107                         // <K:Ljava/lang/Object;V:Ljava/lang/Object;>()Lscala/collection/immutable/TreeSeqMap<TK;TV;>;

  public <K extends java.lang.Object, V extends java.lang.Object> scala.collection.immutable.TreeSeqMap<K, V> empty(scala.collection.immutable.TreeSeqMap$OrderBy);
    descriptor: (Lscala/collection/immutable/TreeSeqMap$OrderBy;)Lscala/collection/immutable/TreeSeqMap;
    flags: (0x0001) ACC_PUBLIC
    Code:
      stack=2, locals=3, args_size=2
         0: aload_1
         1: getstatic     #76                 // Field scala/collection/immutable/TreeSeqMap$OrderBy$Modification$.MODULE$:Lscala/collection/immutable/TreeSeqMap$OrderBy$Modification$;
         4: astore_2
         5: dup
         6: ifnonnull     13
         9: pop
        10: goto          25
        13: aload_2
        14: invokevirtual #116                // Method java/lang/Object.equals:(Ljava/lang/Object;)Z
        17: ifeq          25
        20: aload_0
        21: invokespecial #118                // Method EmptyByModification:()Lscala/collection/immutable/TreeSeqMap;
        24: areturn
        25: aload_0
        26: invokespecial #81                 // Method EmptyByInsertion:()Lscala/collection/immutable/TreeSeqMap;
        29: areturn
      StackMapTable: number_of_entries = 2
        frame_type = 255 /* full_frame */
          offset_delta = 13
          locals = [ class scala/collection/immutable/TreeSeqMap$, class scala/collection/immutable/TreeSeqMap$OrderBy, class scala/collection/immutable/TreeSeqMap$OrderBy$Modification$ ]
          stack = [ class scala/collection/immutable/TreeSeqMap$OrderBy ]
        frame_type = 11 /* same */
      LineNumberTable:
        line 301: 0
        line 302: 25
      LocalVariableTable:
        Start  Length  Slot  Name   Signature
            0      30     0  this   Lscala/collection/immutable/TreeSeqMap$;
            0      30     1 orderBy   Lscala/collection/immutable/TreeSeqMap$OrderBy;
    Signature: #111                         // <K:Ljava/lang/Object;V:Ljava/lang/Object;>(Lscala/collection/immutable/TreeSeqMap$OrderBy;)Lscala/collection/immutable/TreeSeqMap<TK;TV;>;
    MethodParameters:
      Name                           Flags
      orderBy                        final

  public <K extends java.lang.Object, V extends java.lang.Object> scala.collection.immutable.TreeSeqMap<K, V> from(scala.collection.IterableOnce<scala.Tuple2<K, V>>);
    descriptor: (Lscala/collection/IterableOnce;)Lscala/collection/immutable/TreeSeqMap;
    flags: (0x0001) ACC_PUBLIC
    Code:
      stack=3, locals=4, args_size=2
         0: aload_1
         1: instanceof    #12                 // class scala/collection/immutable/TreeSeqMap
         4: ifeq          15
         7: aload_1
         8: checkcast     #12                 // class scala/collection/immutable/TreeSeqMap
        11: astore_2
        12: goto          45
        15: getstatic     #68                 // Field scala/collection/immutable/TreeSeqMap$OrderBy$Insertion$.MODULE$:Lscala/collection/immutable/TreeSeqMap$OrderBy$Insertion$;
        18: astore_3
        19: new           #10                 // class scala/collection/immutable/TreeSeqMap$Builder
        22: dup
        23: aload_3
        24: invokespecial #126                // Method scala/collection/immutable/TreeSeqMap$Builder."<init>":(Lscala/collection/immutable/TreeSeqMap$OrderBy;)V
        27: aconst_null
        28: astore_3
        29: aload_1
        30: invokestatic  #132                // InterfaceMethod scala/collection/mutable/Growable.addAll$:(Lscala/collection/mutable/Growable;Lscala/collection/IterableOnce;)Lscala/collection/mutable/Growable;
        33: checkcast     #134                // class scala/collection/mutable/Builder
        36: invokeinterface #138,  1          // InterfaceMethod scala/collection/mutable/Builder.result:()Ljava/lang/Object;
        41: checkcast     #12                 // class scala/collection/immutable/TreeSeqMap
        44: astore_2
        45: aload_2
        46: areturn
      StackMapTable: number_of_entries = 2
        frame_type = 15 /* same */
        frame_type = 252 /* append */
          offset_delta = 29
          locals = [ class scala/collection/immutable/TreeSeqMap ]
      LineNumberTable:
        line 307: 0
        line 313: 15
        line 314: 19
        line 313: 27
        line 316: 29
        line 308: 33
        line 306: 45
      LocalVariableTable:
        Start  Length  Slot  Name   Signature
            0      47     0  this   Lscala/collection/immutable/TreeSeqMap$;
            0      47     1    it   Lscala/collection/IterableOnce;
           19       8     3 newBuilder_newBuilder_orderedBy   Lscala/collection/immutable/TreeSeqMap$OrderBy;
    Signature: #122                         // <K:Ljava/lang/Object;V:Ljava/lang/Object;>(Lscala/collection/IterableOnce<Lscala/Tuple2<TK;TV;>;>;)Lscala/collection/immutable/TreeSeqMap<TK;TV;>;
    MethodParameters:
      Name                           Flags
      it                             final

  public int scala$collection$immutable$TreeSeqMap$$increment(int);
    descriptor: (I)I
    flags: (0x0001) ACC_PUBLIC
    Code:
      stack=2, locals=2, args_size=2
         0: iload_1
         1: ldc           #144                // int 2147483647
         3: if_icmpne     9
         6: ldc           #145                // int -2147483648
         8: ireturn
         9: iload_1
        10: iconst_1
        11: iadd
        12: ireturn
      StackMapTable: number_of_entries = 1
        frame_type = 9 /* same */
      LineNumberTable:
        line 311: 0
      LocalVariableTable:
        Start  Length  Slot  Name   Signature
            0      13     0  this   Lscala/collection/immutable/TreeSeqMap$;
            0      13     1   ord   I
    MethodParameters:
      Name                           Flags
      ord                            final

  public <K extends java.lang.Object, V extends java.lang.Object> scala.collection.mutable.Builder<scala.Tuple2<K, V>, scala.collection.immutable.TreeSeqMap<K, V>> newBuilder();
    descriptor: ()Lscala/collection/mutable/Builder;
    flags: (0x0001) ACC_PUBLIC
    Code:
      stack=3, locals=2, args_size=1
         0: getstatic     #68                 // Field scala/collection/immutable/TreeSeqMap$OrderBy$Insertion$.MODULE$:Lscala/collection/immutable/TreeSeqMap$OrderBy$Insertion$;
         3: astore_1
         4: new           #10                 // class scala/collection/immutable/TreeSeqMap$Builder
         7: dup
         8: aload_1
         9: invokespecial #126                // Method scala/collection/immutable/TreeSeqMap$Builder."<init>":(Lscala/collection/immutable/TreeSeqMap$OrderBy;)V
        12: areturn
      LineNumberTable:
        line 313: 0
        line 314: 4
        line 313: 12
      LocalVariableTable:
        Start  Length  Slot  Name   Signature
            0      13     0  this   Lscala/collection/immutable/TreeSeqMap$;
            4       8     1 newBuilder_orderedBy   Lscala/collection/immutable/TreeSeqMap$OrderBy;
    Signature: #149                         // <K:Ljava/lang/Object;V:Ljava/lang/Object;>()Lscala/collection/mutable/Builder<Lscala/Tuple2<TK;TV;>;Lscala/collection/immutable/TreeSeqMap<TK;TV;>;>;

  public <K extends java.lang.Object, V extends java.lang.Object> scala.collection.mutable.Builder<scala.Tuple2<K, V>, scala.collection.immutable.TreeSeqMap<K, V>> newBuilder(scala.collection.immutable.TreeSeqMap$OrderBy);
    descriptor: (Lscala/collection/immutable/TreeSeqMap$OrderBy;)Lscala/collection/mutable/Builder;
    flags: (0x0001) ACC_PUBLIC
    Code:
      stack=3, locals=2, args_size=2
         0: new           #10                 // class scala/collection/immutable/TreeSeqMap$Builder
         3: dup
         4: aload_1
         5: invokespecial #126                // Method scala/collection/immutable/TreeSeqMap$Builder."<init>":(Lscala/collection/immutable/TreeSeqMap$OrderBy;)V
         8: areturn
      LineNumberTable:
        line 314: 0
      LocalVariableTable:
        Start  Length  Slot  Name   Signature
            0       9     0  this   Lscala/collection/immutable/TreeSeqMap$;
            0       9     1 orderedBy   Lscala/collection/immutable/TreeSeqMap$OrderBy;
    Signature: #152                         // <K:Ljava/lang/Object;V:Ljava/lang/Object;>(Lscala/collection/immutable/TreeSeqMap$OrderBy;)Lscala/collection/mutable/Builder<Lscala/Tuple2<TK;TV;>;Lscala/collection/immutable/TreeSeqMap<TK;TV;>;>;
    MethodParameters:
      Name                           Flags
      orderedBy                      final

  private scala.collection.immutable.Map$ Mapping();
    descriptor: ()Lscala/collection/immutable/Map$;
    flags: (0x0002) ACC_PRIVATE
    Code:
      stack=1, locals=1, args_size=1
         0: getstatic     #89                 // Field Mapping:Lscala/collection/immutable/Map$;
         3: areturn
      LineNumberTable:
        line 361: 0
      LocalVariableTable:
        Start  Length  Slot  Name   Signature
            0       4     0  this   Lscala/collection/immutable/TreeSeqMap$;

  private java.lang.Object writeReplace();
    descriptor: ()Ljava/lang/Object;
    flags: (0x0002) ACC_PRIVATE
    Code:
      stack=3, locals=1, args_size=1
         0: new           #157                // class scala/runtime/ModuleSerializationProxy
         3: dup
         4: ldc           #2                  // class scala/collection/immutable/TreeSeqMap$
         6: invokespecial #160                // Method scala/runtime/ModuleSerializationProxy."<init>":(Ljava/lang/Class;)V
         9: areturn
      LineNumberTable:
        line 289: 0
      LocalVariableTable:
        Start  Length  Slot  Name   Signature
            0      10     0  this   Lscala/collection/immutable/TreeSeqMap$;

  public java.lang.Object from(scala.collection.IterableOnce);
    descriptor: (Lscala/collection/IterableOnce;)Ljava/lang/Object;
    flags: (0x1041) ACC_PUBLIC, ACC_BRIDGE, ACC_SYNTHETIC
    Code:
      stack=2, locals=2, args_size=2
         0: aload_0
         1: aload_1
         2: invokevirtual #163                // Method from:(Lscala/collection/IterableOnce;)Lscala/collection/immutable/TreeSeqMap;
         5: areturn
      LineNumberTable:
        line 289: 0
      LocalVariableTable:
        Start  Length  Slot  Name   Signature
            0       6     0  this   Lscala/collection/immutable/TreeSeqMap$;
            0       6     1    it   Lscala/collection/IterableOnce;
    MethodParameters:
      Name                           Flags
      it                             final

  public java.lang.Object empty();
    descriptor: ()Ljava/lang/Object;
    flags: (0x1041) ACC_PUBLIC, ACC_BRIDGE, ACC_SYNTHETIC
    Code:
      stack=1, locals=1, args_size=1
         0: aload_0
         1: invokevirtual #165                // Method empty:()Lscala/collection/immutable/TreeSeqMap;
         4: areturn
      LineNumberTable:
        line 289: 0
      LocalVariableTable:
        Start  Length  Slot  Name   Signature
            0       5     0  this   Lscala/collection/immutable/TreeSeqMap$;

  private scala.collection.immutable.TreeSeqMap$();
    descriptor: ()V
    flags: (0x0002) ACC_PRIVATE
    Code:
      stack=1, locals=1, args_size=1
         0: aload_0
         1: invokespecial #166                // Method java/lang/Object."<init>":()V
         4: return
      LineNumberTable:
        line 289: 0
      LocalVariableTable:
        Start  Length  Slot  Name   Signature
            0       5     0  this   Lscala/collection/immutable/TreeSeqMap$;
}
InnerClasses:
  public static final #13= #10 of #12;    // Builder=class scala/collection/immutable/TreeSeqMap$Builder of class scala/collection/immutable/TreeSeqMap
  public static #16= #15 of #12;          // OrderBy=class scala/collection/immutable/TreeSeqMap$OrderBy of class scala/collection/immutable/TreeSeqMap
  public static #19= #18 of #12;          // OrderBy$=class scala/collection/immutable/TreeSeqMap$OrderBy$ of class scala/collection/immutable/TreeSeqMap
  public static #22= #21 of #18;          // Insertion$=class scala/collection/immutable/TreeSeqMap$OrderBy$Insertion$ of class scala/collection/immutable/TreeSeqMap$OrderBy$
  public static #25= #24 of #18;          // Modification$=class scala/collection/immutable/TreeSeqMap$OrderBy$Modification$ of class scala/collection/immutable/TreeSeqMap$OrderBy$
  public static abstract #28= #27 of #12; // Ordering=class scala/collection/immutable/TreeSeqMap$Ordering of class scala/collection/immutable/TreeSeqMap
  public static #31= #30 of #12;          // Ordering$=class scala/collection/immutable/TreeSeqMap$Ordering$ of class scala/collection/immutable/TreeSeqMap
  public static #34= #33 of #30;          // Zero$=class scala/collection/immutable/TreeSeqMap$Ordering$Zero$ of class scala/collection/immutable/TreeSeqMap$Ordering$
Signature: #3                           // Ljava/lang/Object;Lscala/collection/MapFactory<Lscala/collection/immutable/TreeSeqMap;>;
SourceFile: "TreeSeqMap.scala"
  ScalaInlineInfo: length = 0x54 (unknown attribute)
   01 01 00 10 00 2E 00 2D 01 00 29 00 4F 01 00 25
   00 4F 01 00 28 00 4F 01 00 2A 00 9A 01 00 5A 00
   5B 01 00 3E 00 88 01 00 3E 00 4F 01 00 3E 00 6C
   01 00 78 00 A1 01 00 78 00 79 01 00 63 00 64 01
   00 93 00 94 01 00 93 00 97 01 00 8D 00 8E 05 00
   9B 00 88 01
  Scala: length = 0x0 (unknown attribute)

