Classfile /Users/mw/Projects/slang-braindump/.jar/jar11/assemble/slang-braindump/assemble/content/scala/collection/immutable/TreeSeqMap$OrderBy$.class
  Last modified May 29, 2022; size 725 bytes
  SHA-256 checksum b6b7c4e96cd799329a8241c7e414c3260795ac15858fd6bec60f4446bd5f96b4
  Compiled from "TreeSeqMap.scala"
public class scala.collection.immutable.TreeSeqMap$OrderBy$
  minor version: 0
  major version: 52
  flags: (0x0021) ACC_PUBLIC, ACC_SUPER
  this_class: #2                          // scala/collection/immutable/TreeSeqMap$OrderBy$
  super_class: #4                         // java/lang/Object
  interfaces: 0, fields: 1, methods: 2, attributes: 4
Constant pool:
   #1 = Utf8               scala/collection/immutable/TreeSeqMap$OrderBy$
   #2 = Class              #1             // scala/collection/immutable/TreeSeqMap$OrderBy$
   #3 = Utf8               java/lang/Object
   #4 = Class              #3             // java/lang/Object
   #5 = Utf8               TreeSeqMap.scala
   #6 = Utf8               scala/collection/immutable/TreeSeqMap
   #7 = Class              #6             // scala/collection/immutable/TreeSeqMap
   #8 = Utf8               OrderBy$
   #9 = Utf8               scala/collection/immutable/TreeSeqMap$OrderBy$Insertion$
  #10 = Class              #9             // scala/collection/immutable/TreeSeqMap$OrderBy$Insertion$
  #11 = Utf8               Insertion$
  #12 = Utf8               scala/collection/immutable/TreeSeqMap$OrderBy$Modification$
  #13 = Class              #12            // scala/collection/immutable/TreeSeqMap$OrderBy$Modification$
  #14 = Utf8               Modification$
  #15 = Utf8               MODULE$
  #16 = Utf8               Lscala/collection/immutable/TreeSeqMap$OrderBy$;
  #17 = Utf8               <clinit>
  #18 = Utf8               ()V
  #19 = Utf8               <init>
  #20 = NameAndType        #19:#18        // "<init>":()V
  #21 = Methodref          #2.#20         // scala/collection/immutable/TreeSeqMap$OrderBy$."<init>":()V
  #22 = NameAndType        #15:#16        // MODULE$:Lscala/collection/immutable/TreeSeqMap$OrderBy$;
  #23 = Fieldref           #2.#22         // scala/collection/immutable/TreeSeqMap$OrderBy$.MODULE$:Lscala/collection/immutable/TreeSeqMap$OrderBy$;
  #24 = Methodref          #4.#20         // java/lang/Object."<init>":()V
  #25 = Utf8               this
  #26 = Utf8               Code
  #27 = Utf8               LineNumberTable
  #28 = Utf8               LocalVariableTable
  #29 = Utf8               InnerClasses
  #30 = Utf8               SourceFile
  #31 = Utf8               ScalaInlineInfo
  #32 = Utf8               Scala
{
  public static final scala.collection.immutable.TreeSeqMap$OrderBy$ MODULE$;
    descriptor: Lscala/collection/immutable/TreeSeqMap$OrderBy$;
    flags: (0x0019) ACC_PUBLIC, ACC_STATIC, ACC_FINAL

  public static {};
    descriptor: ()V
    flags: (0x0009) ACC_PUBLIC, ACC_STATIC
    Code:
      stack=2, locals=0, args_size=0
         0: new           #2                  // class scala/collection/immutable/TreeSeqMap$OrderBy$
         3: dup
         4: invokespecial #21                 // Method "<init>":()V
         7: putstatic     #23                 // Field MODULE$:Lscala/collection/immutable/TreeSeqMap$OrderBy$;
        10: return
      LineNumberTable:
        line 291: 0

  public scala.collection.immutable.TreeSeqMap$OrderBy$();
    descriptor: ()V
    flags: (0x0001) ACC_PUBLIC
    Code:
      stack=1, locals=1, args_size=1
         0: aload_0
         1: invokespecial #24                 // Method java/lang/Object."<init>":()V
         4: return
      LineNumberTable:
        line 291: 0
      LocalVariableTable:
        Start  Length  Slot  Name   Signature
            0       5     0  this   Lscala/collection/immutable/TreeSeqMap$OrderBy$;
}
InnerClasses:
  public static #8= #2 of #7;             // OrderBy$=class scala/collection/immutable/TreeSeqMap$OrderBy$ of class scala/collection/immutable/TreeSeqMap
  public static #11= #10 of #2;           // Insertion$=class scala/collection/immutable/TreeSeqMap$OrderBy$Insertion$ of class scala/collection/immutable/TreeSeqMap$OrderBy$
  public static #14= #13 of #2;           // Modification$=class scala/collection/immutable/TreeSeqMap$OrderBy$Modification$ of class scala/collection/immutable/TreeSeqMap$OrderBy$
SourceFile: "TreeSeqMap.scala"
  ScalaInlineInfo: length = 0x9 (unknown attribute)
   01 01 00 01 00 13 00 12 01
  Scala: length = 0x0 (unknown attribute)

