Classfile /Users/mw/Projects/slang-braindump/.jar/jar11/assemble/slang-braindump/assemble/content/scala/collection/immutable/Vector$.class
  Last modified May 29, 2022; size 10939 bytes
  SHA-256 checksum 81734dd9807c3f38604d98e6e03a170f26ad71b1fd4993cf5326b96234628c7d
  Compiled from "Vector.scala"
public final class scala.collection.immutable.Vector$ extends java.lang.Object implements scala.collection.StrictOptimizedSeqFactory<scala.collection.immutable.Vector>
  minor version: 0
  major version: 52
  flags: (0x0031) ACC_PUBLIC, ACC_FINAL, ACC_SUPER
  this_class: #2                          // scala/collection/immutable/Vector$
  super_class: #5                         // java/lang/Object
  interfaces: 1, fields: 4, methods: 34, attributes: 5
Constant pool:
    #1 = Utf8               scala/collection/immutable/Vector$
    #2 = Class              #1            // scala/collection/immutable/Vector$
    #3 = Utf8               Ljava/lang/Object;Lscala/collection/StrictOptimizedSeqFactory<Lscala/collection/immutable/Vector;>;
    #4 = Utf8               java/lang/Object
    #5 = Class              #4            // java/lang/Object
    #6 = Utf8               scala/collection/StrictOptimizedSeqFactory
    #7 = Class              #6            // scala/collection/StrictOptimizedSeqFactory
    #8 = Utf8               Vector.scala
    #9 = Utf8               scala/collection/immutable/ArraySeq$ofRef
   #10 = Class              #9            // scala/collection/immutable/ArraySeq$ofRef
   #11 = Utf8               scala/collection/immutable/ArraySeq
   #12 = Class              #11           // scala/collection/immutable/ArraySeq
   #13 = Utf8               ofRef
   #14 = Utf8               MODULE$
   #15 = Utf8               Lscala/collection/immutable/Vector$;
   #16 = Utf8               serialVersionUID
   #17 = Utf8               J
   #18 = Long               3l
   #20 = Utf8               scala$collection$immutable$Vector$$defaultApplyPreferredMaxLength
   #21 = Utf8               I
   #22 = Utf8               scala$collection$immutable$Vector$$emptyIterator
   #23 = Utf8               Lscala/collection/immutable/NewVectorIterator;
   #24 = Utf8               Lscala/collection/immutable/NewVectorIterator<Lscala/runtime/Nothing$;>;
   #25 = Utf8               <clinit>
   #26 = Utf8               ()V
   #27 = Utf8               <init>
   #28 = NameAndType        #27:#26       // "<init>":()V
   #29 = Methodref          #2.#28        // scala/collection/immutable/Vector$."<init>":()V
   #30 = NameAndType        #14:#15       // MODULE$:Lscala/collection/immutable/Vector$;
   #31 = Fieldref           #2.#30        // scala/collection/immutable/Vector$.MODULE$:Lscala/collection/immutable/Vector$;
   #32 = Utf8               liftedTree1$1
   #33 = Utf8               ()I
   #34 = NameAndType        #32:#33       // liftedTree1$1:()I
   #35 = Methodref          #2.#34        // scala/collection/immutable/Vector$.liftedTree1$1:()I
   #36 = NameAndType        #20:#21       // scala$collection$immutable$Vector$$defaultApplyPreferredMaxLength:I
   #37 = Fieldref           #2.#36        // scala/collection/immutable/Vector$.scala$collection$immutable$Vector$$defaultApplyPreferredMaxLength:I
   #38 = Utf8               scala/collection/immutable/NewVectorIterator
   #39 = Class              #38           // scala/collection/immutable/NewVectorIterator
   #40 = Utf8               scala/collection/immutable/Vector0$
   #41 = Class              #40           // scala/collection/immutable/Vector0$
   #42 = Utf8               Lscala/collection/immutable/Vector0$;
   #43 = NameAndType        #14:#42       // MODULE$:Lscala/collection/immutable/Vector0$;
   #44 = Fieldref           #41.#43       // scala/collection/immutable/Vector0$.MODULE$:Lscala/collection/immutable/Vector0$;
   #45 = Utf8               (Lscala/collection/immutable/Vector;II)V
   #46 = NameAndType        #27:#45       // "<init>":(Lscala/collection/immutable/Vector;II)V
   #47 = Methodref          #39.#46       // scala/collection/immutable/NewVectorIterator."<init>":(Lscala/collection/immutable/Vector;II)V
   #48 = NameAndType        #22:#23       // scala$collection$immutable$Vector$$emptyIterator:Lscala/collection/immutable/NewVectorIterator;
   #49 = Fieldref           #2.#48        // scala/collection/immutable/Vector$.scala$collection$immutable$Vector$$emptyIterator:Lscala/collection/immutable/NewVectorIterator;
   #50 = Utf8               fill
   #51 = Utf8               (ILscala/Function0;)Lscala/collection/SeqOps;
   #52 = Utf8               n
   #53 = Utf8               elem
   #54 = Utf8               fill$
   #55 = Utf8               (Lscala/collection/StrictOptimizedSeqFactory;ILscala/Function0;)Lscala/collection/SeqOps;
   #56 = NameAndType        #54:#55       // fill$:(Lscala/collection/StrictOptimizedSeqFactory;ILscala/Function0;)Lscala/collection/SeqOps;
   #57 = InterfaceMethodref #7.#56        // scala/collection/StrictOptimizedSeqFactory.fill$:(Lscala/collection/StrictOptimizedSeqFactory;ILscala/Function0;)Lscala/collection/SeqOps;
   #58 = Utf8               this
   #59 = Utf8               Lscala/Function0;
   #60 = Utf8               tabulate
   #61 = Utf8               (ILscala/Function1;)Lscala/collection/SeqOps;
   #62 = Utf8               f
   #63 = Utf8               tabulate$
   #64 = Utf8               (Lscala/collection/StrictOptimizedSeqFactory;ILscala/Function1;)Lscala/collection/SeqOps;
   #65 = NameAndType        #63:#64       // tabulate$:(Lscala/collection/StrictOptimizedSeqFactory;ILscala/Function1;)Lscala/collection/SeqOps;
   #66 = InterfaceMethodref #7.#65        // scala/collection/StrictOptimizedSeqFactory.tabulate$:(Lscala/collection/StrictOptimizedSeqFactory;ILscala/Function1;)Lscala/collection/SeqOps;
   #67 = Utf8               Lscala/Function1;
   #68 = Utf8               concat
   #69 = Utf8               (Lscala/collection/immutable/Seq;)Lscala/collection/SeqOps;
   #70 = Utf8               xss
   #71 = Utf8               concat$
   #72 = Utf8               (Lscala/collection/StrictOptimizedSeqFactory;Lscala/collection/immutable/Seq;)Lscala/collection/SeqOps;
   #73 = NameAndType        #71:#72       // concat$:(Lscala/collection/StrictOptimizedSeqFactory;Lscala/collection/immutable/Seq;)Lscala/collection/SeqOps;
   #74 = InterfaceMethodref #7.#73        // scala/collection/StrictOptimizedSeqFactory.concat$:(Lscala/collection/StrictOptimizedSeqFactory;Lscala/collection/immutable/Seq;)Lscala/collection/SeqOps;
   #75 = Utf8               Lscala/collection/immutable/Seq;
   #76 = Utf8               unapplySeq
   #77 = Utf8               (Lscala/collection/SeqOps;)Lscala/collection/SeqOps;
   #78 = Utf8               x
   #79 = Utf8               scala/collection/SeqFactory
   #80 = Class              #79           // scala/collection/SeqFactory
   #81 = Utf8               unapplySeq$
   #82 = Utf8               (Lscala/collection/SeqFactory;Lscala/collection/SeqOps;)Lscala/collection/SeqOps;
   #83 = NameAndType        #81:#82       // unapplySeq$:(Lscala/collection/SeqFactory;Lscala/collection/SeqOps;)Lscala/collection/SeqOps;
   #84 = InterfaceMethodref #80.#83       // scala/collection/SeqFactory.unapplySeq$:(Lscala/collection/SeqFactory;Lscala/collection/SeqOps;)Lscala/collection/SeqOps;
   #85 = Utf8               Lscala/collection/SeqOps;
   #86 = Utf8               apply
   #87 = Utf8               (Lscala/collection/immutable/Seq;)Ljava/lang/Object;
   #88 = Utf8               elems
   #89 = Utf8               scala/collection/IterableFactory
   #90 = Class              #89           // scala/collection/IterableFactory
   #91 = Utf8               apply$
   #92 = Utf8               (Lscala/collection/IterableFactory;Lscala/collection/immutable/Seq;)Ljava/lang/Object;
   #93 = NameAndType        #91:#92       // apply$:(Lscala/collection/IterableFactory;Lscala/collection/immutable/Seq;)Ljava/lang/Object;
   #94 = InterfaceMethodref #90.#93       // scala/collection/IterableFactory.apply$:(Lscala/collection/IterableFactory;Lscala/collection/immutable/Seq;)Ljava/lang/Object;
   #95 = Utf8               iterate
   #96 = Utf8               (Ljava/lang/Object;ILscala/Function1;)Ljava/lang/Object;
   #97 = Utf8               start
   #98 = Utf8               len
   #99 = Utf8               iterate$
  #100 = Utf8               (Lscala/collection/IterableFactory;Ljava/lang/Object;ILscala/Function1;)Ljava/lang/Object;
  #101 = NameAndType        #99:#100      // iterate$:(Lscala/collection/IterableFactory;Ljava/lang/Object;ILscala/Function1;)Ljava/lang/Object;
  #102 = InterfaceMethodref #90.#101      // scala/collection/IterableFactory.iterate$:(Lscala/collection/IterableFactory;Ljava/lang/Object;ILscala/Function1;)Ljava/lang/Object;
  #103 = Utf8               Ljava/lang/Object;
  #104 = Utf8               unfold
  #105 = Utf8               (Ljava/lang/Object;Lscala/Function1;)Ljava/lang/Object;
  #106 = Utf8               init
  #107 = Utf8               unfold$
  #108 = Utf8               (Lscala/collection/IterableFactory;Ljava/lang/Object;Lscala/Function1;)Ljava/lang/Object;
  #109 = NameAndType        #107:#108     // unfold$:(Lscala/collection/IterableFactory;Ljava/lang/Object;Lscala/Function1;)Ljava/lang/Object;
  #110 = InterfaceMethodref #90.#109      // scala/collection/IterableFactory.unfold$:(Lscala/collection/IterableFactory;Ljava/lang/Object;Lscala/Function1;)Ljava/lang/Object;
  #111 = Utf8               range
  #112 = Utf8               (Ljava/lang/Object;Ljava/lang/Object;Lscala/math/Integral;)Ljava/lang/Object;
  #113 = Utf8               end
  #114 = Utf8               evidence$3
  #115 = Utf8               range$
  #116 = Utf8               (Lscala/collection/IterableFactory;Ljava/lang/Object;Ljava/lang/Object;Lscala/math/Integral;)Ljava/lang/Object;
  #117 = NameAndType        #115:#116     // range$:(Lscala/collection/IterableFactory;Ljava/lang/Object;Ljava/lang/Object;Lscala/math/Integral;)Ljava/lang/Object;
  #118 = InterfaceMethodref #90.#117      // scala/collection/IterableFactory.range$:(Lscala/collection/IterableFactory;Ljava/lang/Object;Ljava/lang/Object;Lscala/math/Integral;)Ljava/lang/Object;
  #119 = Utf8               Lscala/math/Integral;
  #120 = Utf8               (Ljava/lang/Object;Ljava/lang/Object;Ljava/lang/Object;Lscala/math/Integral;)Ljava/lang/Object;
  #121 = Utf8               step
  #122 = Utf8               evidence$4
  #123 = Utf8               (Lscala/collection/IterableFactory;Ljava/lang/Object;Ljava/lang/Object;Ljava/lang/Object;Lscala/math/Integral;)Ljava/lang/Object;
  #124 = NameAndType        #115:#123     // range$:(Lscala/collection/IterableFactory;Ljava/lang/Object;Ljava/lang/Object;Ljava/lang/Object;Lscala/math/Integral;)Ljava/lang/Object;
  #125 = InterfaceMethodref #90.#124      // scala/collection/IterableFactory.range$:(Lscala/collection/IterableFactory;Ljava/lang/Object;Ljava/lang/Object;Ljava/lang/Object;Lscala/math/Integral;)Ljava/lang/Object;
  #126 = Utf8               (IILscala/Function0;)Ljava/lang/Object;
  #127 = Utf8               n1
  #128 = Utf8               n2
  #129 = Utf8               (Lscala/collection/IterableFactory;IILscala/Function0;)Ljava/lang/Object;
  #130 = NameAndType        #54:#129      // fill$:(Lscala/collection/IterableFactory;IILscala/Function0;)Ljava/lang/Object;
  #131 = InterfaceMethodref #90.#130      // scala/collection/IterableFactory.fill$:(Lscala/collection/IterableFactory;IILscala/Function0;)Ljava/lang/Object;
  #132 = Utf8               (IIILscala/Function0;)Ljava/lang/Object;
  #133 = Utf8               n3
  #134 = Utf8               (Lscala/collection/IterableFactory;IIILscala/Function0;)Ljava/lang/Object;
  #135 = NameAndType        #54:#134      // fill$:(Lscala/collection/IterableFactory;IIILscala/Function0;)Ljava/lang/Object;
  #136 = InterfaceMethodref #90.#135      // scala/collection/IterableFactory.fill$:(Lscala/collection/IterableFactory;IIILscala/Function0;)Ljava/lang/Object;
  #137 = Utf8               (IIIILscala/Function0;)Ljava/lang/Object;
  #138 = Utf8               n4
  #139 = Utf8               (Lscala/collection/IterableFactory;IIIILscala/Function0;)Ljava/lang/Object;
  #140 = NameAndType        #54:#139      // fill$:(Lscala/collection/IterableFactory;IIIILscala/Function0;)Ljava/lang/Object;
  #141 = InterfaceMethodref #90.#140      // scala/collection/IterableFactory.fill$:(Lscala/collection/IterableFactory;IIIILscala/Function0;)Ljava/lang/Object;
  #142 = Utf8               (IIIIILscala/Function0;)Ljava/lang/Object;
  #143 = Utf8               n5
  #144 = Utf8               (Lscala/collection/IterableFactory;IIIIILscala/Function0;)Ljava/lang/Object;
  #145 = NameAndType        #54:#144      // fill$:(Lscala/collection/IterableFactory;IIIIILscala/Function0;)Ljava/lang/Object;
  #146 = InterfaceMethodref #90.#145      // scala/collection/IterableFactory.fill$:(Lscala/collection/IterableFactory;IIIIILscala/Function0;)Ljava/lang/Object;
  #147 = Utf8               (IILscala/Function2;)Ljava/lang/Object;
  #148 = Utf8               (Lscala/collection/IterableFactory;IILscala/Function2;)Ljava/lang/Object;
  #149 = NameAndType        #63:#148      // tabulate$:(Lscala/collection/IterableFactory;IILscala/Function2;)Ljava/lang/Object;
  #150 = InterfaceMethodref #90.#149      // scala/collection/IterableFactory.tabulate$:(Lscala/collection/IterableFactory;IILscala/Function2;)Ljava/lang/Object;
  #151 = Utf8               Lscala/Function2;
  #152 = Utf8               (IIILscala/Function3;)Ljava/lang/Object;
  #153 = Utf8               (Lscala/collection/IterableFactory;IIILscala/Function3;)Ljava/lang/Object;
  #154 = NameAndType        #63:#153      // tabulate$:(Lscala/collection/IterableFactory;IIILscala/Function3;)Ljava/lang/Object;
  #155 = InterfaceMethodref #90.#154      // scala/collection/IterableFactory.tabulate$:(Lscala/collection/IterableFactory;IIILscala/Function3;)Ljava/lang/Object;
  #156 = Utf8               Lscala/Function3;
  #157 = Utf8               (IIIILscala/Function4;)Ljava/lang/Object;
  #158 = Utf8               (Lscala/collection/IterableFactory;IIIILscala/Function4;)Ljava/lang/Object;
  #159 = NameAndType        #63:#158      // tabulate$:(Lscala/collection/IterableFactory;IIIILscala/Function4;)Ljava/lang/Object;
  #160 = InterfaceMethodref #90.#159      // scala/collection/IterableFactory.tabulate$:(Lscala/collection/IterableFactory;IIIILscala/Function4;)Ljava/lang/Object;
  #161 = Utf8               Lscala/Function4;
  #162 = Utf8               (IIIIILscala/Function5;)Ljava/lang/Object;
  #163 = Utf8               (Lscala/collection/IterableFactory;IIIIILscala/Function5;)Ljava/lang/Object;
  #164 = NameAndType        #63:#163      // tabulate$:(Lscala/collection/IterableFactory;IIIIILscala/Function5;)Ljava/lang/Object;
  #165 = InterfaceMethodref #90.#164      // scala/collection/IterableFactory.tabulate$:(Lscala/collection/IterableFactory;IIIIILscala/Function5;)Ljava/lang/Object;
  #166 = Utf8               Lscala/Function5;
  #167 = Utf8               iterableFactory
  #168 = Utf8               ()Lscala/collection/Factory;
  #169 = Utf8               <A:Ljava/lang/Object;>()Lscala/collection/Factory<TA;Lscala/collection/immutable/Vector<TA;>;>;
  #170 = Utf8               iterableFactory$
  #171 = Utf8               (Lscala/collection/IterableFactory;)Lscala/collection/Factory;
  #172 = NameAndType        #170:#171     // iterableFactory$:(Lscala/collection/IterableFactory;)Lscala/collection/Factory;
  #173 = InterfaceMethodref #90.#172      // scala/collection/IterableFactory.iterableFactory$:(Lscala/collection/IterableFactory;)Lscala/collection/Factory;
  #174 = Utf8               empty
  #175 = Utf8               ()Lscala/collection/immutable/Vector;
  #176 = Utf8               <A:Ljava/lang/Object;>()Lscala/collection/immutable/Vector<TA;>;
  #177 = Utf8               from
  #178 = Utf8               (Lscala/collection/IterableOnce;)Lscala/collection/immutable/Vector;
  #179 = Utf8               <E:Ljava/lang/Object;>(Lscala/collection/IterableOnce<TE;>;)Lscala/collection/immutable/Vector<TE;>;
  #180 = Utf8               it
  #181 = Utf8               scala/collection/immutable/Vector
  #182 = Class              #181          // scala/collection/immutable/Vector
  #183 = Utf8               scala/collection/IterableOnce
  #184 = Class              #183          // scala/collection/IterableOnce
  #185 = Utf8               knownSize
  #186 = NameAndType        #185:#33      // knownSize:()I
  #187 = InterfaceMethodref #184.#186     // scala/collection/IterableOnce.knownSize:()I
  #188 = Utf8               elemTag
  #189 = Utf8               ()Lscala/reflect/ClassTag;
  #190 = NameAndType        #188:#189     // elemTag:()Lscala/reflect/ClassTag;
  #191 = Methodref          #10.#190      // scala/collection/immutable/ArraySeq$ofRef.elemTag:()Lscala/reflect/ClassTag;
  #192 = Utf8               scala/reflect/ClassTag
  #193 = Class              #192          // scala/reflect/ClassTag
  #194 = Utf8               runtimeClass
  #195 = Utf8               ()Ljava/lang/Class;
  #196 = NameAndType        #194:#195     // runtimeClass:()Ljava/lang/Class;
  #197 = InterfaceMethodref #193.#196     // scala/reflect/ClassTag.runtimeClass:()Ljava/lang/Class;
  #198 = Utf8               equals
  #199 = Utf8               (Ljava/lang/Object;)Z
  #200 = NameAndType        #198:#199     // equals:(Ljava/lang/Object;)Z
  #201 = Methodref          #5.#200       // java/lang/Object.equals:(Ljava/lang/Object;)Z
  #202 = Utf8               unsafeArray
  #203 = Utf8               ()[Ljava/lang/Object;
  #204 = NameAndType        #202:#203     // unsafeArray:()[Ljava/lang/Object;
  #205 = Methodref          #10.#204      // scala/collection/immutable/ArraySeq$ofRef.unsafeArray:()[Ljava/lang/Object;
  #206 = Utf8               scala/collection/immutable/Iterable
  #207 = Class              #206          // scala/collection/immutable/Iterable
  #208 = Utf8               copyToArray
  #209 = Utf8               (Ljava/lang/Object;)I
  #210 = NameAndType        #208:#209     // copyToArray:(Ljava/lang/Object;)I
  #211 = InterfaceMethodref #207.#210     // scala/collection/immutable/Iterable.copyToArray:(Ljava/lang/Object;)I
  #212 = Utf8               iterator
  #213 = Utf8               ()Lscala/collection/Iterator;
  #214 = NameAndType        #212:#213     // iterator:()Lscala/collection/Iterator;
  #215 = InterfaceMethodref #184.#214     // scala/collection/IterableOnce.iterator:()Lscala/collection/Iterator;
  #216 = Utf8               scala/collection/Iterator
  #217 = Class              #216          // scala/collection/Iterator
  #218 = InterfaceMethodref #217.#210     // scala/collection/Iterator.copyToArray:(Ljava/lang/Object;)I
  #219 = Utf8               scala/collection/immutable/Vector1
  #220 = Class              #219          // scala/collection/immutable/Vector1
  #221 = Utf8               ([Ljava/lang/Object;)V
  #222 = NameAndType        #27:#221      // "<init>":([Ljava/lang/Object;)V
  #223 = Methodref          #220.#222     // scala/collection/immutable/Vector1."<init>":([Ljava/lang/Object;)V
  #224 = Utf8               scala/collection/immutable/VectorBuilder
  #225 = Class              #224          // scala/collection/immutable/VectorBuilder
  #226 = Methodref          #225.#28      // scala/collection/immutable/VectorBuilder."<init>":()V
  #227 = Utf8               addAll
  #228 = Utf8               (Lscala/collection/IterableOnce;)Lscala/collection/immutable/VectorBuilder;
  #229 = NameAndType        #227:#228     // addAll:(Lscala/collection/IterableOnce;)Lscala/collection/immutable/VectorBuilder;
  #230 = Methodref          #225.#229     // scala/collection/immutable/VectorBuilder.addAll:(Lscala/collection/IterableOnce;)Lscala/collection/immutable/VectorBuilder;
  #231 = Utf8               scala/collection/mutable/ReusableBuilder
  #232 = Class              #231          // scala/collection/mutable/ReusableBuilder
  #233 = Utf8               result
  #234 = Utf8               ()Ljava/lang/Object;
  #235 = NameAndType        #233:#234     // result:()Ljava/lang/Object;
  #236 = InterfaceMethodref #232.#235     // scala/collection/mutable/ReusableBuilder.result:()Ljava/lang/Object;
  #237 = Utf8               a1
  #238 = Utf8               [Ljava/lang/Object;
  #239 = Utf8               Lscala/collection/IterableOnce;
  #240 = Utf8               java/lang/Class
  #241 = Class              #240          // java/lang/Class
  #242 = Class              #238          // "[Ljava/lang/Object;"
  #243 = Utf8               newBuilder
  #244 = Utf8               ()Lscala/collection/mutable/ReusableBuilder;
  #245 = Utf8               <A:Ljava/lang/Object;>()Lscala/collection/mutable/ReusableBuilder<TA;Lscala/collection/immutable/Vector<TA;>;>;
  #246 = Utf8               fillSparse
  #247 = Utf8               (ILjava/lang/Object;)Lscala/collection/immutable/Vector;
  #248 = Utf8               <A:Ljava/lang/Object;>(ITA;)Lscala/collection/immutable/Vector<TA;>;
  #249 = Utf8               initSparse
  #250 = Utf8               (ILjava/lang/Object;)V
  #251 = NameAndType        #249:#250     // initSparse:(ILjava/lang/Object;)V
  #252 = Methodref          #225.#251     // scala/collection/immutable/VectorBuilder.initSparse:(ILjava/lang/Object;)V
  #253 = NameAndType        #233:#175     // result:()Lscala/collection/immutable/Vector;
  #254 = Methodref          #225.#253     // scala/collection/immutable/VectorBuilder.result:()Lscala/collection/immutable/Vector;
  #255 = Utf8               b
  #256 = Utf8               Lscala/collection/immutable/VectorBuilder;
  #257 = Utf8               ()Lscala/collection/immutable/NewVectorIterator;
  #258 = Utf8               ()Lscala/collection/immutable/NewVectorIterator<Lscala/runtime/Nothing$;>;
  #259 = Utf8               writeReplace
  #260 = Utf8               scala/runtime/ModuleSerializationProxy
  #261 = Class              #260          // scala/runtime/ModuleSerializationProxy
  #262 = Utf8               (Ljava/lang/Class;)V
  #263 = NameAndType        #27:#262      // "<init>":(Ljava/lang/Class;)V
  #264 = Methodref          #261.#263     // scala/runtime/ModuleSerializationProxy."<init>":(Ljava/lang/Class;)V
  #265 = NameAndType        #68:#69       // concat:(Lscala/collection/immutable/Seq;)Lscala/collection/SeqOps;
  #266 = Methodref          #2.#265       // scala/collection/immutable/Vector$.concat:(Lscala/collection/immutable/Seq;)Lscala/collection/SeqOps;
  #267 = Utf8               (ILscala/Function1;)Ljava/lang/Object;
  #268 = NameAndType        #60:#61       // tabulate:(ILscala/Function1;)Lscala/collection/SeqOps;
  #269 = Methodref          #2.#268       // scala/collection/immutable/Vector$.tabulate:(ILscala/Function1;)Lscala/collection/SeqOps;
  #270 = Utf8               (ILscala/Function0;)Ljava/lang/Object;
  #271 = NameAndType        #50:#51       // fill:(ILscala/Function0;)Lscala/collection/SeqOps;
  #272 = Methodref          #2.#271       // scala/collection/immutable/Vector$.fill:(ILscala/Function0;)Lscala/collection/SeqOps;
  #273 = Utf8               ()Lscala/collection/mutable/Builder;
  #274 = NameAndType        #243:#244     // newBuilder:()Lscala/collection/mutable/ReusableBuilder;
  #275 = Methodref          #2.#274       // scala/collection/immutable/Vector$.newBuilder:()Lscala/collection/mutable/ReusableBuilder;
  #276 = Utf8               (Lscala/collection/IterableOnce;)Ljava/lang/Object;
  #277 = Utf8               source
  #278 = NameAndType        #177:#178     // from:(Lscala/collection/IterableOnce;)Lscala/collection/immutable/Vector;
  #279 = Methodref          #2.#278       // scala/collection/immutable/Vector$.from:(Lscala/collection/IterableOnce;)Lscala/collection/immutable/Vector;
  #280 = NameAndType        #174:#175     // empty:()Lscala/collection/immutable/Vector;
  #281 = Methodref          #2.#280       // scala/collection/immutable/Vector$.empty:()Lscala/collection/immutable/Vector;
  #282 = Utf8               java/lang/SecurityException
  #283 = Class              #282          // java/lang/SecurityException
  #284 = Utf8               scala.collection.immutable.Vector.defaultApplyPreferredMaxLength
  #285 = String             #284          // scala.collection.immutable.Vector.defaultApplyPreferredMaxLength
  #286 = Utf8               250
  #287 = String             #286          // 250
  #288 = Utf8               java/lang/System
  #289 = Class              #288          // java/lang/System
  #290 = Utf8               getProperty
  #291 = Utf8               (Ljava/lang/String;Ljava/lang/String;)Ljava/lang/String;
  #292 = NameAndType        #290:#291     // getProperty:(Ljava/lang/String;Ljava/lang/String;)Ljava/lang/String;
  #293 = Methodref          #289.#292     // java/lang/System.getProperty:(Ljava/lang/String;Ljava/lang/String;)Ljava/lang/String;
  #294 = Utf8               java/lang/Integer
  #295 = Class              #294          // java/lang/Integer
  #296 = Utf8               parseInt
  #297 = Utf8               (Ljava/lang/String;)I
  #298 = NameAndType        #296:#297     // parseInt:(Ljava/lang/String;)I
  #299 = Methodref          #295.#298     // java/lang/Integer.parseInt:(Ljava/lang/String;)I
  #300 = Methodref          #5.#28        // java/lang/Object."<init>":()V
  #301 = Utf8               ConstantValue
  #302 = Utf8               Signature
  #303 = Utf8               Code
  #304 = Utf8               LineNumberTable
  #305 = Utf8               LocalVariableTable
  #306 = Utf8               MethodParameters
  #307 = Utf8               StackMapTable
  #308 = Utf8               InnerClasses
  #309 = Utf8               SourceFile
  #310 = Utf8               ScalaInlineInfo
  #311 = Utf8               Scala
{
  public static final scala.collection.immutable.Vector$ MODULE$;
    descriptor: Lscala/collection/immutable/Vector$;
    flags: (0x0019) ACC_PUBLIC, ACC_STATIC, ACC_FINAL

  private static final long serialVersionUID;
    descriptor: J
    flags: (0x001a) ACC_PRIVATE, ACC_STATIC, ACC_FINAL
    ConstantValue: long 3l

  private static final int scala$collection$immutable$Vector$$defaultApplyPreferredMaxLength;
    descriptor: I
    flags: (0x001a) ACC_PRIVATE, ACC_STATIC, ACC_FINAL

  private static final scala.collection.immutable.NewVectorIterator<scala.runtime.Nothing$> scala$collection$immutable$Vector$$emptyIterator;
    descriptor: Lscala/collection/immutable/NewVectorIterator;
    flags: (0x001a) ACC_PRIVATE, ACC_STATIC, ACC_FINAL
    Signature: #24                          // Lscala/collection/immutable/NewVectorIterator<Lscala/runtime/Nothing$;>;

  public static {};
    descriptor: ()V
    flags: (0x0009) ACC_PUBLIC, ACC_STATIC
    Code:
      stack=5, locals=0, args_size=0
         0: new           #2                  // class scala/collection/immutable/Vector$
         3: dup
         4: invokespecial #29                 // Method "<init>":()V
         7: putstatic     #31                 // Field MODULE$:Lscala/collection/immutable/Vector$;
        10: getstatic     #31                 // Field MODULE$:Lscala/collection/immutable/Vector$;
        13: pop
        14: getstatic     #31                 // Field MODULE$:Lscala/collection/immutable/Vector$;
        17: pop
        18: getstatic     #31                 // Field MODULE$:Lscala/collection/immutable/Vector$;
        21: pop
        22: invokestatic  #35                 // Method liftedTree1$1:()I
        25: putstatic     #37                 // Field scala$collection$immutable$Vector$$defaultApplyPreferredMaxLength:I
        28: new           #39                 // class scala/collection/immutable/NewVectorIterator
        31: dup
        32: getstatic     #44                 // Field scala/collection/immutable/Vector0$.MODULE$:Lscala/collection/immutable/Vector0$;
        35: iconst_0
        36: iconst_0
        37: invokespecial #47                 // Method scala/collection/immutable/NewVectorIterator."<init>":(Lscala/collection/immutable/Vector;II)V
        40: putstatic     #49                 // Field scala$collection$immutable$Vector$$emptyIterator:Lscala/collection/immutable/NewVectorIterator;
        43: return
      LineNumberTable:
        line 34: 0
        line 82: 22
        line 81: 25
        line 88: 28
        line 34: 43

  public scala.collection.SeqOps fill(int, scala.Function0);
    descriptor: (ILscala/Function0;)Lscala/collection/SeqOps;
    flags: (0x0001) ACC_PUBLIC
    Code:
      stack=3, locals=3, args_size=3
         0: aload_0
         1: iload_1
         2: aload_2
         3: invokestatic  #57                 // InterfaceMethod scala/collection/StrictOptimizedSeqFactory.fill$:(Lscala/collection/StrictOptimizedSeqFactory;ILscala/Function0;)Lscala/collection/SeqOps;
         6: areturn
      LineNumberTable:
        line 34: 0
      LocalVariableTable:
        Start  Length  Slot  Name   Signature
            0       7     0  this   Lscala/collection/immutable/Vector$;
            0       7     1     n   I
            0       7     2  elem   Lscala/Function0;
    MethodParameters:
      Name                           Flags
      n                              final
      elem                           final

  public scala.collection.SeqOps tabulate(int, scala.Function1);
    descriptor: (ILscala/Function1;)Lscala/collection/SeqOps;
    flags: (0x0001) ACC_PUBLIC
    Code:
      stack=3, locals=3, args_size=3
         0: aload_0
         1: iload_1
         2: aload_2
         3: invokestatic  #66                 // InterfaceMethod scala/collection/StrictOptimizedSeqFactory.tabulate$:(Lscala/collection/StrictOptimizedSeqFactory;ILscala/Function1;)Lscala/collection/SeqOps;
         6: areturn
      LineNumberTable:
        line 34: 0
      LocalVariableTable:
        Start  Length  Slot  Name   Signature
            0       7     0  this   Lscala/collection/immutable/Vector$;
            0       7     1     n   I
            0       7     2     f   Lscala/Function1;
    MethodParameters:
      Name                           Flags
      n                              final
      f                              final

  public scala.collection.SeqOps concat(scala.collection.immutable.Seq);
    descriptor: (Lscala/collection/immutable/Seq;)Lscala/collection/SeqOps;
    flags: (0x0001) ACC_PUBLIC
    Code:
      stack=2, locals=2, args_size=2
         0: aload_0
         1: aload_1
         2: invokestatic  #74                 // InterfaceMethod scala/collection/StrictOptimizedSeqFactory.concat$:(Lscala/collection/StrictOptimizedSeqFactory;Lscala/collection/immutable/Seq;)Lscala/collection/SeqOps;
         5: areturn
      LineNumberTable:
        line 34: 0
      LocalVariableTable:
        Start  Length  Slot  Name   Signature
            0       6     0  this   Lscala/collection/immutable/Vector$;
            0       6     1   xss   Lscala/collection/immutable/Seq;
    MethodParameters:
      Name                           Flags
      xss                            final

  public final scala.collection.SeqOps unapplySeq(scala.collection.SeqOps);
    descriptor: (Lscala/collection/SeqOps;)Lscala/collection/SeqOps;
    flags: (0x0011) ACC_PUBLIC, ACC_FINAL
    Code:
      stack=2, locals=2, args_size=2
         0: aload_0
         1: aload_1
         2: invokestatic  #84                 // InterfaceMethod scala/collection/SeqFactory.unapplySeq$:(Lscala/collection/SeqFactory;Lscala/collection/SeqOps;)Lscala/collection/SeqOps;
         5: areturn
      LineNumberTable:
        line 34: 0
      LocalVariableTable:
        Start  Length  Slot  Name   Signature
            0       6     0  this   Lscala/collection/immutable/Vector$;
            0       6     1     x   Lscala/collection/SeqOps;
    MethodParameters:
      Name                           Flags
      x                              final

  public java.lang.Object apply(scala.collection.immutable.Seq);
    descriptor: (Lscala/collection/immutable/Seq;)Ljava/lang/Object;
    flags: (0x0001) ACC_PUBLIC
    Code:
      stack=2, locals=2, args_size=2
         0: aload_0
         1: aload_1
         2: invokestatic  #94                 // InterfaceMethod scala/collection/IterableFactory.apply$:(Lscala/collection/IterableFactory;Lscala/collection/immutable/Seq;)Ljava/lang/Object;
         5: areturn
      LineNumberTable:
        line 34: 0
      LocalVariableTable:
        Start  Length  Slot  Name   Signature
            0       6     0  this   Lscala/collection/immutable/Vector$;
            0       6     1 elems   Lscala/collection/immutable/Seq;
    MethodParameters:
      Name                           Flags
      elems                          final

  public java.lang.Object iterate(java.lang.Object, int, scala.Function1);
    descriptor: (Ljava/lang/Object;ILscala/Function1;)Ljava/lang/Object;
    flags: (0x0001) ACC_PUBLIC
    Code:
      stack=4, locals=4, args_size=4
         0: aload_0
         1: aload_1
         2: iload_2
         3: aload_3
         4: invokestatic  #102                // InterfaceMethod scala/collection/IterableFactory.iterate$:(Lscala/collection/IterableFactory;Ljava/lang/Object;ILscala/Function1;)Ljava/lang/Object;
         7: areturn
      LineNumberTable:
        line 34: 0
      LocalVariableTable:
        Start  Length  Slot  Name   Signature
            0       8     0  this   Lscala/collection/immutable/Vector$;
            0       8     1 start   Ljava/lang/Object;
            0       8     2   len   I
            0       8     3     f   Lscala/Function1;
    MethodParameters:
      Name                           Flags
      start                          final
      len                            final
      f                              final

  public java.lang.Object unfold(java.lang.Object, scala.Function1);
    descriptor: (Ljava/lang/Object;Lscala/Function1;)Ljava/lang/Object;
    flags: (0x0001) ACC_PUBLIC
    Code:
      stack=3, locals=3, args_size=3
         0: aload_0
         1: aload_1
         2: aload_2
         3: invokestatic  #110                // InterfaceMethod scala/collection/IterableFactory.unfold$:(Lscala/collection/IterableFactory;Ljava/lang/Object;Lscala/Function1;)Ljava/lang/Object;
         6: areturn
      LineNumberTable:
        line 34: 0
      LocalVariableTable:
        Start  Length  Slot  Name   Signature
            0       7     0  this   Lscala/collection/immutable/Vector$;
            0       7     1  init   Ljava/lang/Object;
            0       7     2     f   Lscala/Function1;
    MethodParameters:
      Name                           Flags
      init                           final
      f                              final

  public java.lang.Object range(java.lang.Object, java.lang.Object, scala.math.Integral);
    descriptor: (Ljava/lang/Object;Ljava/lang/Object;Lscala/math/Integral;)Ljava/lang/Object;
    flags: (0x0001) ACC_PUBLIC
    Code:
      stack=4, locals=4, args_size=4
         0: aload_0
         1: aload_1
         2: aload_2
         3: aload_3
         4: invokestatic  #118                // InterfaceMethod scala/collection/IterableFactory.range$:(Lscala/collection/IterableFactory;Ljava/lang/Object;Ljava/lang/Object;Lscala/math/Integral;)Ljava/lang/Object;
         7: areturn
      LineNumberTable:
        line 34: 0
      LocalVariableTable:
        Start  Length  Slot  Name   Signature
            0       8     0  this   Lscala/collection/immutable/Vector$;
            0       8     1 start   Ljava/lang/Object;
            0       8     2   end   Ljava/lang/Object;
            0       8     3 evidence$3   Lscala/math/Integral;
    MethodParameters:
      Name                           Flags
      start                          final
      end                            final
      evidence$3                     final

  public java.lang.Object range(java.lang.Object, java.lang.Object, java.lang.Object, scala.math.Integral);
    descriptor: (Ljava/lang/Object;Ljava/lang/Object;Ljava/lang/Object;Lscala/math/Integral;)Ljava/lang/Object;
    flags: (0x0001) ACC_PUBLIC
    Code:
      stack=5, locals=5, args_size=5
         0: aload_0
         1: aload_1
         2: aload_2
         3: aload_3
         4: aload         4
         6: invokestatic  #125                // InterfaceMethod scala/collection/IterableFactory.range$:(Lscala/collection/IterableFactory;Ljava/lang/Object;Ljava/lang/Object;Ljava/lang/Object;Lscala/math/Integral;)Ljava/lang/Object;
         9: areturn
      LineNumberTable:
        line 34: 0
      LocalVariableTable:
        Start  Length  Slot  Name   Signature
            0      10     0  this   Lscala/collection/immutable/Vector$;
            0      10     1 start   Ljava/lang/Object;
            0      10     2   end   Ljava/lang/Object;
            0      10     3  step   Ljava/lang/Object;
            0      10     4 evidence$4   Lscala/math/Integral;
    MethodParameters:
      Name                           Flags
      start                          final
      end                            final
      step                           final
      evidence$4                     final

  public java.lang.Object fill(int, int, scala.Function0);
    descriptor: (IILscala/Function0;)Ljava/lang/Object;
    flags: (0x0001) ACC_PUBLIC
    Code:
      stack=4, locals=4, args_size=4
         0: aload_0
         1: iload_1
         2: iload_2
         3: aload_3
         4: invokestatic  #131                // InterfaceMethod scala/collection/IterableFactory.fill$:(Lscala/collection/IterableFactory;IILscala/Function0;)Ljava/lang/Object;
         7: areturn
      LineNumberTable:
        line 34: 0
      LocalVariableTable:
        Start  Length  Slot  Name   Signature
            0       8     0  this   Lscala/collection/immutable/Vector$;
            0       8     1    n1   I
            0       8     2    n2   I
            0       8     3  elem   Lscala/Function0;
    MethodParameters:
      Name                           Flags
      n1                             final
      n2                             final
      elem                           final

  public java.lang.Object fill(int, int, int, scala.Function0);
    descriptor: (IIILscala/Function0;)Ljava/lang/Object;
    flags: (0x0001) ACC_PUBLIC
    Code:
      stack=5, locals=5, args_size=5
         0: aload_0
         1: iload_1
         2: iload_2
         3: iload_3
         4: aload         4
         6: invokestatic  #136                // InterfaceMethod scala/collection/IterableFactory.fill$:(Lscala/collection/IterableFactory;IIILscala/Function0;)Ljava/lang/Object;
         9: areturn
      LineNumberTable:
        line 34: 0
      LocalVariableTable:
        Start  Length  Slot  Name   Signature
            0      10     0  this   Lscala/collection/immutable/Vector$;
            0      10     1    n1   I
            0      10     2    n2   I
            0      10     3    n3   I
            0      10     4  elem   Lscala/Function0;
    MethodParameters:
      Name                           Flags
      n1                             final
      n2                             final
      n3                             final
      elem                           final

  public java.lang.Object fill(int, int, int, int, scala.Function0);
    descriptor: (IIIILscala/Function0;)Ljava/lang/Object;
    flags: (0x0001) ACC_PUBLIC
    Code:
      stack=6, locals=6, args_size=6
         0: aload_0
         1: iload_1
         2: iload_2
         3: iload_3
         4: iload         4
         6: aload         5
         8: invokestatic  #141                // InterfaceMethod scala/collection/IterableFactory.fill$:(Lscala/collection/IterableFactory;IIIILscala/Function0;)Ljava/lang/Object;
        11: areturn
      LineNumberTable:
        line 34: 0
      LocalVariableTable:
        Start  Length  Slot  Name   Signature
            0      12     0  this   Lscala/collection/immutable/Vector$;
            0      12     1    n1   I
            0      12     2    n2   I
            0      12     3    n3   I
            0      12     4    n4   I
            0      12     5  elem   Lscala/Function0;
    MethodParameters:
      Name                           Flags
      n1                             final
      n2                             final
      n3                             final
      n4                             final
      elem                           final

  public java.lang.Object fill(int, int, int, int, int, scala.Function0);
    descriptor: (IIIIILscala/Function0;)Ljava/lang/Object;
    flags: (0x0001) ACC_PUBLIC
    Code:
      stack=7, locals=7, args_size=7
         0: aload_0
         1: iload_1
         2: iload_2
         3: iload_3
         4: iload         4
         6: iload         5
         8: aload         6
        10: invokestatic  #146                // InterfaceMethod scala/collection/IterableFactory.fill$:(Lscala/collection/IterableFactory;IIIIILscala/Function0;)Ljava/lang/Object;
        13: areturn
      LineNumberTable:
        line 34: 0
      LocalVariableTable:
        Start  Length  Slot  Name   Signature
            0      14     0  this   Lscala/collection/immutable/Vector$;
            0      14     1    n1   I
            0      14     2    n2   I
            0      14     3    n3   I
            0      14     4    n4   I
            0      14     5    n5   I
            0      14     6  elem   Lscala/Function0;
    MethodParameters:
      Name                           Flags
      n1                             final
      n2                             final
      n3                             final
      n4                             final
      n5                             final
      elem                           final

  public java.lang.Object tabulate(int, int, scala.Function2);
    descriptor: (IILscala/Function2;)Ljava/lang/Object;
    flags: (0x0001) ACC_PUBLIC
    Code:
      stack=4, locals=4, args_size=4
         0: aload_0
         1: iload_1
         2: iload_2
         3: aload_3
         4: invokestatic  #150                // InterfaceMethod scala/collection/IterableFactory.tabulate$:(Lscala/collection/IterableFactory;IILscala/Function2;)Ljava/lang/Object;
         7: areturn
      LineNumberTable:
        line 34: 0
      LocalVariableTable:
        Start  Length  Slot  Name   Signature
            0       8     0  this   Lscala/collection/immutable/Vector$;
            0       8     1    n1   I
            0       8     2    n2   I
            0       8     3     f   Lscala/Function2;
    MethodParameters:
      Name                           Flags
      n1                             final
      n2                             final
      f                              final

  public java.lang.Object tabulate(int, int, int, scala.Function3);
    descriptor: (IIILscala/Function3;)Ljava/lang/Object;
    flags: (0x0001) ACC_PUBLIC
    Code:
      stack=5, locals=5, args_size=5
         0: aload_0
         1: iload_1
         2: iload_2
         3: iload_3
         4: aload         4
         6: invokestatic  #155                // InterfaceMethod scala/collection/IterableFactory.tabulate$:(Lscala/collection/IterableFactory;IIILscala/Function3;)Ljava/lang/Object;
         9: areturn
      LineNumberTable:
        line 34: 0
      LocalVariableTable:
        Start  Length  Slot  Name   Signature
            0      10     0  this   Lscala/collection/immutable/Vector$;
            0      10     1    n1   I
            0      10     2    n2   I
            0      10     3    n3   I
            0      10     4     f   Lscala/Function3;
    MethodParameters:
      Name                           Flags
      n1                             final
      n2                             final
      n3                             final
      f                              final

  public java.lang.Object tabulate(int, int, int, int, scala.Function4);
    descriptor: (IIIILscala/Function4;)Ljava/lang/Object;
    flags: (0x0001) ACC_PUBLIC
    Code:
      stack=6, locals=6, args_size=6
         0: aload_0
         1: iload_1
         2: iload_2
         3: iload_3
         4: iload         4
         6: aload         5
         8: invokestatic  #160                // InterfaceMethod scala/collection/IterableFactory.tabulate$:(Lscala/collection/IterableFactory;IIIILscala/Function4;)Ljava/lang/Object;
        11: areturn
      LineNumberTable:
        line 34: 0
      LocalVariableTable:
        Start  Length  Slot  Name   Signature
            0      12     0  this   Lscala/collection/immutable/Vector$;
            0      12     1    n1   I
            0      12     2    n2   I
            0      12     3    n3   I
            0      12     4    n4   I
            0      12     5     f   Lscala/Function4;
    MethodParameters:
      Name                           Flags
      n1                             final
      n2                             final
      n3                             final
      n4                             final
      f                              final

  public java.lang.Object tabulate(int, int, int, int, int, scala.Function5);
    descriptor: (IIIIILscala/Function5;)Ljava/lang/Object;
    flags: (0x0001) ACC_PUBLIC
    Code:
      stack=7, locals=7, args_size=7
         0: aload_0
         1: iload_1
         2: iload_2
         3: iload_3
         4: iload         4
         6: iload         5
         8: aload         6
        10: invokestatic  #165                // InterfaceMethod scala/collection/IterableFactory.tabulate$:(Lscala/collection/IterableFactory;IIIIILscala/Function5;)Ljava/lang/Object;
        13: areturn
      LineNumberTable:
        line 34: 0
      LocalVariableTable:
        Start  Length  Slot  Name   Signature
            0      14     0  this   Lscala/collection/immutable/Vector$;
            0      14     1    n1   I
            0      14     2    n2   I
            0      14     3    n3   I
            0      14     4    n4   I
            0      14     5    n5   I
            0      14     6     f   Lscala/Function5;
    MethodParameters:
      Name                           Flags
      n1                             final
      n2                             final
      n3                             final
      n4                             final
      n5                             final
      f                              final

  public <A extends java.lang.Object> scala.collection.Factory<A, scala.collection.immutable.Vector<A>> iterableFactory();
    descriptor: ()Lscala/collection/Factory;
    flags: (0x0001) ACC_PUBLIC
    Code:
      stack=1, locals=1, args_size=1
         0: aload_0
         1: invokestatic  #173                // InterfaceMethod scala/collection/IterableFactory.iterableFactory$:(Lscala/collection/IterableFactory;)Lscala/collection/Factory;
         4: areturn
      LineNumberTable:
        line 34: 0
      LocalVariableTable:
        Start  Length  Slot  Name   Signature
            0       5     0  this   Lscala/collection/immutable/Vector$;
    Signature: #169                         // <A:Ljava/lang/Object;>()Lscala/collection/Factory<TA;Lscala/collection/immutable/Vector<TA;>;>;

  public <A extends java.lang.Object> scala.collection.immutable.Vector<A> empty();
    descriptor: ()Lscala/collection/immutable/Vector;
    flags: (0x0001) ACC_PUBLIC
    Code:
      stack=1, locals=1, args_size=1
         0: getstatic     #44                 // Field scala/collection/immutable/Vector0$.MODULE$:Lscala/collection/immutable/Vector0$;
         3: areturn
      LineNumberTable:
        line 36: 0
      LocalVariableTable:
        Start  Length  Slot  Name   Signature
            0       4     0  this   Lscala/collection/immutable/Vector$;
    Signature: #176                         // <A:Ljava/lang/Object;>()Lscala/collection/immutable/Vector<TA;>;

  public <E extends java.lang.Object> scala.collection.immutable.Vector<E> from(scala.collection.IterableOnce<E>);
    descriptor: (Lscala/collection/IterableOnce;)Lscala/collection/immutable/Vector;
    flags: (0x0001) ACC_PUBLIC
    Code:
      stack=3, locals=10, args_size=2
         0: aload_1
         1: instanceof    #182                // class scala/collection/immutable/Vector
         4: ifeq          15
         7: aload_1
         8: checkcast     #182                // class scala/collection/immutable/Vector
        11: astore_2
        12: goto          191
        15: aload_1
        16: invokeinterface #187,  1          // InterfaceMethod scala/collection/IterableOnce.knownSize:()I
        21: istore        4
        23: iload         4
        25: iconst_0
        26: if_icmpne     35
        29: getstatic     #44                 // Field scala/collection/immutable/Vector0$.MODULE$:Lscala/collection/immutable/Vector0$;
        32: goto          190
        35: iload         4
        37: iconst_0
        38: if_icmple     171
        41: iload         4
        43: bipush        32
        45: if_icmpgt     171
        48: aload_1
        49: instanceof    #10                 // class scala/collection/immutable/ArraySeq$ofRef
        52: ifeq          100
        55: aload_1
        56: checkcast     #10                 // class scala/collection/immutable/ArraySeq$ofRef
        59: astore        5
        61: aload         5
        63: invokevirtual #191                // Method scala/collection/immutable/ArraySeq$ofRef.elemTag:()Lscala/reflect/ClassTag;
        66: invokeinterface #197,  1          // InterfaceMethod scala/reflect/ClassTag.runtimeClass:()Ljava/lang/Class;
        71: ldc           #5                  // class java/lang/Object
        73: astore        6
        75: dup
        76: ifnonnull     83
        79: pop
        80: goto          100
        83: aload         6
        85: invokevirtual #201                // Method java/lang/Object.equals:(Ljava/lang/Object;)Z
        88: ifeq          100
        91: aload         5
        93: invokevirtual #205                // Method scala/collection/immutable/ArraySeq$ofRef.unsafeArray:()[Ljava/lang/Object;
        96: astore_3
        97: goto          160
       100: aload_1
       101: instanceof    #207                // class scala/collection/immutable/Iterable
       104: ifeq          136
       107: aload_1
       108: checkcast     #207                // class scala/collection/immutable/Iterable
       111: astore        7
       113: iload         4
       115: anewarray     #5                  // class java/lang/Object
       118: astore        8
       120: aload         7
       122: aload         8
       124: invokeinterface #211,  2          // InterfaceMethod scala/collection/immutable/Iterable.copyToArray:(Ljava/lang/Object;)I
       129: pop
       130: aload         8
       132: astore_3
       133: goto          160
       136: iload         4
       138: anewarray     #5                  // class java/lang/Object
       141: astore        9
       143: aload_1
       144: invokeinterface #215,  1          // InterfaceMethod scala/collection/IterableOnce.iterator:()Lscala/collection/Iterator;
       149: aload         9
       151: invokeinterface #218,  2          // InterfaceMethod scala/collection/Iterator.copyToArray:(Ljava/lang/Object;)I
       156: pop
       157: aload         9
       159: astore_3
       160: new           #220                // class scala/collection/immutable/Vector1
       163: dup
       164: aload_3
       165: invokespecial #223                // Method scala/collection/immutable/Vector1."<init>":([Ljava/lang/Object;)V
       168: goto          190
       171: new           #225                // class scala/collection/immutable/VectorBuilder
       174: dup
       175: invokespecial #226                // Method scala/collection/immutable/VectorBuilder."<init>":()V
       178: aload_1
       179: invokevirtual #230                // Method scala/collection/immutable/VectorBuilder.addAll:(Lscala/collection/IterableOnce;)Lscala/collection/immutable/VectorBuilder;
       182: invokeinterface #236,  1          // InterfaceMethod scala/collection/mutable/ReusableBuilder.result:()Ljava/lang/Object;
       187: checkcast     #182                // class scala/collection/immutable/Vector
       190: astore_2
       191: aload_2
       192: areturn
      StackMapTable: number_of_entries = 9
        frame_type = 15 /* same */
        frame_type = 254 /* append */
          offset_delta = 19
          locals = [ top, top, int ]
        frame_type = 255 /* full_frame */
          offset_delta = 47
          locals = [ class scala/collection/immutable/Vector$, class scala/collection/IterableOnce, top, top, int, class scala/collection/immutable/ArraySeq$ofRef, class java/lang/Class ]
          stack = [ class java/lang/Class ]
        frame_type = 249 /* chop */
          offset_delta = 16
        frame_type = 35 /* same */
        frame_type = 255 /* full_frame */
          offset_delta = 23
          locals = [ class scala/collection/immutable/Vector$, class scala/collection/IterableOnce, top, class "[Ljava/lang/Object;", int ]
          stack = []
        frame_type = 255 /* full_frame */
          offset_delta = 10
          locals = [ class scala/collection/immutable/Vector$, class scala/collection/IterableOnce, top, top, int ]
          stack = []
        frame_type = 82 /* same_locals_1_stack_item */
          stack = [ class scala/collection/immutable/Vector ]
        frame_type = 255 /* full_frame */
          offset_delta = 0
          locals = [ class scala/collection/immutable/Vector$, class scala/collection/IterableOnce, class scala/collection/immutable/Vector ]
          stack = []
      LineNumberTable:
        line 40: 0
        line 42: 15
        line 43: 23
        line 36: 29
        line 43: 32
        line 44: 35
        line 46: 48
        line 47: 91
        line 48: 100
        line 49: 113
        line 50: 120
        line 51: 130
        line 53: 136
        line 54: 143
        line 55: 157
        line 57: 160
        line 63: 171
        line 1349: 178
        line 59: 182
        line 39: 191
      LocalVariableTable:
        Start  Length  Slot  Name   Signature
          120      12     8    a1   [Ljava/lang/Object;
          143      16     9    a1   [Ljava/lang/Object;
           23     167     4 knownSize   I
            0     193     0  this   Lscala/collection/immutable/Vector$;
            0     193     1    it   Lscala/collection/IterableOnce;
    Signature: #179                         // <E:Ljava/lang/Object;>(Lscala/collection/IterableOnce<TE;>;)Lscala/collection/immutable/Vector<TE;>;
    MethodParameters:
      Name                           Flags
      it                             final

  public <A extends java.lang.Object> scala.collection.mutable.ReusableBuilder<A, scala.collection.immutable.Vector<A>> newBuilder();
    descriptor: ()Lscala/collection/mutable/ReusableBuilder;
    flags: (0x0001) ACC_PUBLIC
    Code:
      stack=2, locals=1, args_size=1
         0: new           #225                // class scala/collection/immutable/VectorBuilder
         3: dup
         4: invokespecial #226                // Method scala/collection/immutable/VectorBuilder."<init>":()V
         7: areturn
      LineNumberTable:
        line 63: 0
      LocalVariableTable:
        Start  Length  Slot  Name   Signature
            0       8     0  this   Lscala/collection/immutable/Vector$;
    Signature: #245                         // <A:Ljava/lang/Object;>()Lscala/collection/mutable/ReusableBuilder<TA;Lscala/collection/immutable/Vector<TA;>;>;

  public <A extends java.lang.Object> scala.collection.immutable.Vector<A> fillSparse(int, A);
    descriptor: (ILjava/lang/Object;)Lscala/collection/immutable/Vector;
    flags: (0x0001) ACC_PUBLIC
    Code:
      stack=3, locals=4, args_size=3
         0: iload_1
         1: iconst_0
         2: if_icmpgt     9
         5: getstatic     #44                 // Field scala/collection/immutable/Vector0$.MODULE$:Lscala/collection/immutable/Vector0$;
         8: areturn
         9: new           #225                // class scala/collection/immutable/VectorBuilder
        12: dup
        13: invokespecial #226                // Method scala/collection/immutable/VectorBuilder."<init>":()V
        16: astore_3
        17: aload_3
        18: iload_1
        19: aload_2
        20: invokevirtual #252                // Method scala/collection/immutable/VectorBuilder.initSparse:(ILjava/lang/Object;)V
        23: aload_3
        24: invokevirtual #254                // Method scala/collection/immutable/VectorBuilder.result:()Lscala/collection/immutable/Vector;
        27: areturn
      StackMapTable: number_of_entries = 1
        frame_type = 9 /* same */
      LineNumberTable:
        line 73: 0
        line 75: 9
        line 76: 17
        line 77: 23
      LocalVariableTable:
        Start  Length  Slot  Name   Signature
           17      10     3     b   Lscala/collection/immutable/VectorBuilder;
            0      28     0  this   Lscala/collection/immutable/Vector$;
            0      28     1     n   I
            0      28     2  elem   Ljava/lang/Object;
    Signature: #248                         // <A:Ljava/lang/Object;>(ITA;)Lscala/collection/immutable/Vector<TA;>;
    MethodParameters:
      Name                           Flags
      n                              final
      elem                           final

  public int scala$collection$immutable$Vector$$defaultApplyPreferredMaxLength();
    descriptor: ()I
    flags: (0x0001) ACC_PUBLIC
    Code:
      stack=1, locals=1, args_size=1
         0: getstatic     #37                 // Field scala$collection$immutable$Vector$$defaultApplyPreferredMaxLength:I
         3: ireturn
      LineNumberTable:
        line 81: 0
      LocalVariableTable:
        Start  Length  Slot  Name   Signature
            0       4     0  this   Lscala/collection/immutable/Vector$;

  public scala.collection.immutable.NewVectorIterator<scala.runtime.Nothing$> scala$collection$immutable$Vector$$emptyIterator();
    descriptor: ()Lscala/collection/immutable/NewVectorIterator;
    flags: (0x0001) ACC_PUBLIC
    Code:
      stack=1, locals=1, args_size=1
         0: getstatic     #49                 // Field scala$collection$immutable$Vector$$emptyIterator:Lscala/collection/immutable/NewVectorIterator;
         3: areturn
      LineNumberTable:
        line 88: 0
      LocalVariableTable:
        Start  Length  Slot  Name   Signature
            0       4     0  this   Lscala/collection/immutable/Vector$;
    Signature: #258                         // ()Lscala/collection/immutable/NewVectorIterator<Lscala/runtime/Nothing$;>;

  private java.lang.Object writeReplace();
    descriptor: ()Ljava/lang/Object;
    flags: (0x0002) ACC_PRIVATE
    Code:
      stack=3, locals=1, args_size=1
         0: new           #261                // class scala/runtime/ModuleSerializationProxy
         3: dup
         4: ldc           #2                  // class scala/collection/immutable/Vector$
         6: invokespecial #264                // Method scala/runtime/ModuleSerializationProxy."<init>":(Ljava/lang/Class;)V
         9: areturn
      LineNumberTable:
        line 34: 0
      LocalVariableTable:
        Start  Length  Slot  Name   Signature
            0      10     0  this   Lscala/collection/immutable/Vector$;

  public java.lang.Object concat(scala.collection.immutable.Seq);
    descriptor: (Lscala/collection/immutable/Seq;)Ljava/lang/Object;
    flags: (0x1041) ACC_PUBLIC, ACC_BRIDGE, ACC_SYNTHETIC
    Code:
      stack=2, locals=2, args_size=2
         0: aload_0
         1: aload_1
         2: invokevirtual #266                // Method concat:(Lscala/collection/immutable/Seq;)Lscala/collection/SeqOps;
         5: areturn
      LineNumberTable:
        line 34: 0
      LocalVariableTable:
        Start  Length  Slot  Name   Signature
            0       6     0  this   Lscala/collection/immutable/Vector$;
            0       6     1   xss   Lscala/collection/immutable/Seq;
    MethodParameters:
      Name                           Flags
      xss                            final

  public java.lang.Object tabulate(int, scala.Function1);
    descriptor: (ILscala/Function1;)Ljava/lang/Object;
    flags: (0x1041) ACC_PUBLIC, ACC_BRIDGE, ACC_SYNTHETIC
    Code:
      stack=3, locals=3, args_size=3
         0: aload_0
         1: iload_1
         2: aload_2
         3: invokevirtual #269                // Method tabulate:(ILscala/Function1;)Lscala/collection/SeqOps;
         6: areturn
      LineNumberTable:
        line 34: 0
      LocalVariableTable:
        Start  Length  Slot  Name   Signature
            0       7     0  this   Lscala/collection/immutable/Vector$;
            0       7     1     n   I
            0       7     2     f   Lscala/Function1;
    MethodParameters:
      Name                           Flags
      n                              final
      f                              final

  public java.lang.Object fill(int, scala.Function0);
    descriptor: (ILscala/Function0;)Ljava/lang/Object;
    flags: (0x1041) ACC_PUBLIC, ACC_BRIDGE, ACC_SYNTHETIC
    Code:
      stack=3, locals=3, args_size=3
         0: aload_0
         1: iload_1
         2: aload_2
         3: invokevirtual #272                // Method fill:(ILscala/Function0;)Lscala/collection/SeqOps;
         6: areturn
      LineNumberTable:
        line 34: 0
      LocalVariableTable:
        Start  Length  Slot  Name   Signature
            0       7     0  this   Lscala/collection/immutable/Vector$;
            0       7     1     n   I
            0       7     2  elem   Lscala/Function0;
    MethodParameters:
      Name                           Flags
      n                              final
      elem                           final

  public scala.collection.mutable.Builder newBuilder();
    descriptor: ()Lscala/collection/mutable/Builder;
    flags: (0x1041) ACC_PUBLIC, ACC_BRIDGE, ACC_SYNTHETIC
    Code:
      stack=1, locals=1, args_size=1
         0: aload_0
         1: invokevirtual #275                // Method newBuilder:()Lscala/collection/mutable/ReusableBuilder;
         4: areturn
      LineNumberTable:
        line 34: 0
      LocalVariableTable:
        Start  Length  Slot  Name   Signature
            0       5     0  this   Lscala/collection/immutable/Vector$;

  public java.lang.Object from(scala.collection.IterableOnce);
    descriptor: (Lscala/collection/IterableOnce;)Ljava/lang/Object;
    flags: (0x1041) ACC_PUBLIC, ACC_BRIDGE, ACC_SYNTHETIC
    Code:
      stack=2, locals=2, args_size=2
         0: aload_0
         1: aload_1
         2: invokevirtual #279                // Method from:(Lscala/collection/IterableOnce;)Lscala/collection/immutable/Vector;
         5: areturn
      LineNumberTable:
        line 34: 0
      LocalVariableTable:
        Start  Length  Slot  Name   Signature
            0       6     0  this   Lscala/collection/immutable/Vector$;
            0       6     1 source   Lscala/collection/IterableOnce;
    MethodParameters:
      Name                           Flags
      source                         final

  public java.lang.Object empty();
    descriptor: ()Ljava/lang/Object;
    flags: (0x1041) ACC_PUBLIC, ACC_BRIDGE, ACC_SYNTHETIC
    Code:
      stack=1, locals=1, args_size=1
         0: aload_0
         1: invokevirtual #281                // Method empty:()Lscala/collection/immutable/Vector;
         4: areturn
      LineNumberTable:
        line 34: 0
      LocalVariableTable:
        Start  Length  Slot  Name   Signature
            0       5     0  this   Lscala/collection/immutable/Vector$;

  private static final int liftedTree1$1();
    descriptor: ()I
    flags: (0x101a) ACC_PRIVATE, ACC_STATIC, ACC_FINAL, ACC_SYNTHETIC
    Code:
      stack=2, locals=0, args_size=0
         0: ldc_w         #285                // String scala.collection.immutable.Vector.defaultApplyPreferredMaxLength
         3: ldc_w         #287                // String 250
         6: invokestatic  #293                // Method java/lang/System.getProperty:(Ljava/lang/String;Ljava/lang/String;)Ljava/lang/String;
         9: invokestatic  #299                // Method java/lang/Integer.parseInt:(Ljava/lang/String;)I
        12: ireturn
        13: pop
        14: sipush        250
        17: ireturn
      Exception table:
         from    to  target type
             0    12    13   Class java/lang/SecurityException
      StackMapTable: number_of_entries = 1
        frame_type = 77 /* same_locals_1_stack_item */
          stack = [ class java/lang/SecurityException ]
      LineNumberTable:
        line 82: 0
        line 83: 3
        line 85: 14

  private scala.collection.immutable.Vector$();
    descriptor: ()V
    flags: (0x0002) ACC_PRIVATE
    Code:
      stack=1, locals=1, args_size=1
         0: aload_0
         1: invokespecial #300                // Method java/lang/Object."<init>":()V
         4: return
      LineNumberTable:
        line 34: 0
      LocalVariableTable:
        Start  Length  Slot  Name   Signature
            0       5     0  this   Lscala/collection/immutable/Vector$;
}
InnerClasses:
  public static final #13= #10 of #12;    // ofRef=class scala/collection/immutable/ArraySeq$ofRef of class scala/collection/immutable/ArraySeq
Signature: #3                           // Ljava/lang/Object;Lscala/collection/StrictOptimizedSeqFactory<Lscala/collection/immutable/Vector;>;
SourceFile: "Vector.scala"
  ScalaInlineInfo: length = 0xA9 (unknown attribute)
   01 01 00 21 00 1B 00 1A 01 00 56 00 57 01 00 44
   00 57 01 00 44 00 45 01 00 AE 00 EA 01 00 AE 00
   AF 01 00 32 00 8E 01 00 32 00 89 01 00 32 00 84
   01 00 32 00 7E 01 00 32 01 0E 01 00 32 00 33 01
   00 F6 00 F7 01 00 B1 01 14 01 00 B1 00 B2 01 00
   A7 00 A8 01 00 5F 00 60 01 00 20 00 21 01 00 F3
   01 11 01 00 F3 00 F4 01 00 6F 00 78 01 00 6F 00
   70 01 00 14 00 21 01 00 16 01 01 01 00 3C 00 A2
   01 00 3C 00 9D 01 00 3C 00 98 01 00 3C 00 93 01
   00 3C 01 0B 01 00 3C 00 3D 01 00 4C 00 4D 01 00
   68 00 69 01 01 03 00 EA 01
  Scala: length = 0x0 (unknown attribute)

