Classfile /Users/mw/Projects/slang-braindump/.jar/jar11/assemble/slang-braindump/assemble/content/scala/collection/immutable/VectorMap$Tombstone$.class
  Last modified May 29, 2022; size 2090 bytes
  SHA-256 checksum d49bd336d90476713adea3454096f7ccbb497157f3c4a185740abe207d8781c9
  Compiled from "VectorMap.scala"
public class scala.collection.immutable.VectorMap$Tombstone$ extends scala.runtime.AbstractFunction1<java.lang.Object, scala.collection.immutable.VectorMap$Tombstone> implements java.io.Serializable
  minor version: 0
  major version: 52
  flags: (0x0021) ACC_PUBLIC, ACC_SUPER
  this_class: #2                          // scala/collection/immutable/VectorMap$Tombstone$
  super_class: #5                         // scala/runtime/AbstractFunction1
  interfaces: 1, fields: 1, methods: 7, attributes: 5
Constant pool:
   #1 = Utf8               scala/collection/immutable/VectorMap$Tombstone$
   #2 = Class              #1             // scala/collection/immutable/VectorMap$Tombstone$
   #3 = Utf8               Lscala/runtime/AbstractFunction1<Ljava/lang/Object;Lscala/collection/immutable/VectorMap$Tombstone;>;Ljava/io/Serializable;
   #4 = Utf8               scala/runtime/AbstractFunction1
   #5 = Class              #4             // scala/runtime/AbstractFunction1
   #6 = Utf8               java/io/Serializable
   #7 = Class              #6             // java/io/Serializable
   #8 = Utf8               VectorMap.scala
   #9 = Utf8               scala/collection/immutable/VectorMap$Tombstone
  #10 = Class              #9             // scala/collection/immutable/VectorMap$Tombstone
  #11 = Utf8               scala/collection/immutable/VectorMap
  #12 = Class              #11            // scala/collection/immutable/VectorMap
  #13 = Utf8               Tombstone
  #14 = Utf8               Tombstone$
  #15 = Utf8               MODULE$
  #16 = Utf8               Lscala/collection/immutable/VectorMap$Tombstone$;
  #17 = Utf8               <clinit>
  #18 = Utf8               ()V
  #19 = Utf8               <init>
  #20 = NameAndType        #19:#18        // "<init>":()V
  #21 = Methodref          #2.#20         // scala/collection/immutable/VectorMap$Tombstone$."<init>":()V
  #22 = NameAndType        #15:#16        // MODULE$:Lscala/collection/immutable/VectorMap$Tombstone$;
  #23 = Fieldref           #2.#22         // scala/collection/immutable/VectorMap$Tombstone$.MODULE$:Lscala/collection/immutable/VectorMap$Tombstone$;
  #24 = Utf8               toString
  #25 = Utf8               ()Ljava/lang/String;
  #26 = String             #13            // Tombstone
  #27 = Utf8               this
  #28 = Utf8               apply
  #29 = Utf8               (I)Lscala/collection/immutable/VectorMap$Tombstone;
  #30 = Utf8               distance
  #31 = Utf8               (I)V
  #32 = NameAndType        #19:#31        // "<init>":(I)V
  #33 = Methodref          #10.#32        // scala/collection/immutable/VectorMap$Tombstone."<init>":(I)V
  #34 = Utf8               I
  #35 = Utf8               unapply
  #36 = Utf8               (Lscala/collection/immutable/VectorMap$Tombstone;)Lscala/Option;
  #37 = Utf8               (Lscala/collection/immutable/VectorMap$Tombstone;)Lscala/Option<Ljava/lang/Object;>;
  #38 = Utf8               x$0
  #39 = Utf8               scala/None$
  #40 = Class              #39            // scala/None$
  #41 = Utf8               Lscala/None$;
  #42 = NameAndType        #15:#41        // MODULE$:Lscala/None$;
  #43 = Fieldref           #40.#42        // scala/None$.MODULE$:Lscala/None$;
  #44 = Utf8               scala/Some
  #45 = Class              #44            // scala/Some
  #46 = Utf8               ()I
  #47 = NameAndType        #30:#46        // distance:()I
  #48 = Methodref          #10.#47        // scala/collection/immutable/VectorMap$Tombstone.distance:()I
  #49 = Utf8               java/lang/Integer
  #50 = Class              #49            // java/lang/Integer
  #51 = Utf8               valueOf
  #52 = Utf8               (I)Ljava/lang/Integer;
  #53 = NameAndType        #51:#52        // valueOf:(I)Ljava/lang/Integer;
  #54 = Methodref          #50.#53        // java/lang/Integer.valueOf:(I)Ljava/lang/Integer;
  #55 = Utf8               (Ljava/lang/Object;)V
  #56 = NameAndType        #19:#55        // "<init>":(Ljava/lang/Object;)V
  #57 = Methodref          #45.#56        // scala/Some."<init>":(Ljava/lang/Object;)V
  #58 = Utf8               Lscala/collection/immutable/VectorMap$Tombstone;
  #59 = Utf8               writeReplace
  #60 = Utf8               ()Ljava/lang/Object;
  #61 = Utf8               scala/runtime/ModuleSerializationProxy
  #62 = Class              #61            // scala/runtime/ModuleSerializationProxy
  #63 = Utf8               (Ljava/lang/Class;)V
  #64 = NameAndType        #19:#63        // "<init>":(Ljava/lang/Class;)V
  #65 = Methodref          #62.#64        // scala/runtime/ModuleSerializationProxy."<init>":(Ljava/lang/Class;)V
  #66 = Utf8               (Ljava/lang/Object;)Ljava/lang/Object;
  #67 = Utf8               v1
  #68 = Utf8               scala/runtime/BoxesRunTime
  #69 = Class              #68            // scala/runtime/BoxesRunTime
  #70 = Utf8               unboxToInt
  #71 = Utf8               (Ljava/lang/Object;)I
  #72 = NameAndType        #70:#71        // unboxToInt:(Ljava/lang/Object;)I
  #73 = Methodref          #69.#72        // scala/runtime/BoxesRunTime.unboxToInt:(Ljava/lang/Object;)I
  #74 = NameAndType        #28:#29        // apply:(I)Lscala/collection/immutable/VectorMap$Tombstone;
  #75 = Methodref          #2.#74         // scala/collection/immutable/VectorMap$Tombstone$.apply:(I)Lscala/collection/immutable/VectorMap$Tombstone;
  #76 = Utf8               Ljava/lang/Object;
  #77 = Methodref          #5.#20         // scala/runtime/AbstractFunction1."<init>":()V
  #78 = Utf8               Code
  #79 = Utf8               LineNumberTable
  #80 = Utf8               LocalVariableTable
  #81 = Utf8               MethodParameters
  #82 = Utf8               StackMapTable
  #83 = Utf8               Signature
  #84 = Utf8               InnerClasses
  #85 = Utf8               SourceFile
  #86 = Utf8               ScalaInlineInfo
  #87 = Utf8               Scala
{
  public static final scala.collection.immutable.VectorMap$Tombstone$ MODULE$;
    descriptor: Lscala/collection/immutable/VectorMap$Tombstone$;
    flags: (0x0019) ACC_PUBLIC, ACC_STATIC, ACC_FINAL

  public static {};
    descriptor: ()V
    flags: (0x0009) ACC_PUBLIC, ACC_STATIC
    Code:
      stack=2, locals=0, args_size=0
         0: new           #2                  // class scala/collection/immutable/VectorMap$Tombstone$
         3: dup
         4: invokespecial #21                 // Method "<init>":()V
         7: putstatic     #23                 // Field MODULE$:Lscala/collection/immutable/VectorMap$Tombstone$;
        10: return
      LineNumberTable:
        line 225: 0

  public final java.lang.String toString();
    descriptor: ()Ljava/lang/String;
    flags: (0x0011) ACC_PUBLIC, ACC_FINAL
    Code:
      stack=1, locals=1, args_size=1
         0: ldc           #26                 // String Tombstone
         2: areturn
      LineNumberTable:
        line 225: 0
      LocalVariableTable:
        Start  Length  Slot  Name   Signature
            0       3     0  this   Lscala/collection/immutable/VectorMap$Tombstone$;

  public scala.collection.immutable.VectorMap$Tombstone apply(int);
    descriptor: (I)Lscala/collection/immutable/VectorMap$Tombstone;
    flags: (0x0001) ACC_PUBLIC
    Code:
      stack=3, locals=2, args_size=2
         0: new           #10                 // class scala/collection/immutable/VectorMap$Tombstone
         3: dup
         4: iload_1
         5: invokespecial #33                 // Method scala/collection/immutable/VectorMap$Tombstone."<init>":(I)V
         8: areturn
      LineNumberTable:
        line 225: 0
      LocalVariableTable:
        Start  Length  Slot  Name   Signature
            0       9     0  this   Lscala/collection/immutable/VectorMap$Tombstone$;
            0       9     1 distance   I
    MethodParameters:
      Name                           Flags
      distance                       final

  public scala.Option<java.lang.Object> unapply(scala.collection.immutable.VectorMap$Tombstone);
    descriptor: (Lscala/collection/immutable/VectorMap$Tombstone;)Lscala/Option;
    flags: (0x0001) ACC_PUBLIC
    Code:
      stack=3, locals=2, args_size=2
         0: aload_1
         1: ifnonnull     8
         4: getstatic     #43                 // Field scala/None$.MODULE$:Lscala/None$;
         7: areturn
         8: new           #45                 // class scala/Some
        11: dup
        12: aload_1
        13: invokevirtual #48                 // Method scala/collection/immutable/VectorMap$Tombstone.distance:()I
        16: invokestatic  #54                 // Method java/lang/Integer.valueOf:(I)Ljava/lang/Integer;
        19: invokespecial #57                 // Method scala/Some."<init>":(Ljava/lang/Object;)V
        22: areturn
      StackMapTable: number_of_entries = 1
        frame_type = 8 /* same */
      LineNumberTable:
        line 225: 0
      LocalVariableTable:
        Start  Length  Slot  Name   Signature
            0      23     0  this   Lscala/collection/immutable/VectorMap$Tombstone$;
            0      23     1   x$0   Lscala/collection/immutable/VectorMap$Tombstone;
    Signature: #37                          // (Lscala/collection/immutable/VectorMap$Tombstone;)Lscala/Option<Ljava/lang/Object;>;
    MethodParameters:
      Name                           Flags
      x$0                            final

  private java.lang.Object writeReplace();
    descriptor: ()Ljava/lang/Object;
    flags: (0x0002) ACC_PRIVATE
    Code:
      stack=3, locals=1, args_size=1
         0: new           #62                 // class scala/runtime/ModuleSerializationProxy
         3: dup
         4: ldc           #2                  // class scala/collection/immutable/VectorMap$Tombstone$
         6: invokespecial #65                 // Method scala/runtime/ModuleSerializationProxy."<init>":(Ljava/lang/Class;)V
         9: areturn
      LineNumberTable:
        line 225: 0
      LocalVariableTable:
        Start  Length  Slot  Name   Signature
            0      10     0  this   Lscala/collection/immutable/VectorMap$Tombstone$;

  public java.lang.Object apply(java.lang.Object);
    descriptor: (Ljava/lang/Object;)Ljava/lang/Object;
    flags: (0x1041) ACC_PUBLIC, ACC_BRIDGE, ACC_SYNTHETIC
    Code:
      stack=2, locals=2, args_size=2
         0: aload_0
         1: aload_1
         2: invokestatic  #73                 // Method scala/runtime/BoxesRunTime.unboxToInt:(Ljava/lang/Object;)I
         5: invokevirtual #75                 // Method apply:(I)Lscala/collection/immutable/VectorMap$Tombstone;
         8: areturn
      LineNumberTable:
        line 225: 0
      LocalVariableTable:
        Start  Length  Slot  Name   Signature
            0       9     0  this   Lscala/collection/immutable/VectorMap$Tombstone$;
            0       9     1    v1   Ljava/lang/Object;
    MethodParameters:
      Name                           Flags
      v1                             final

  public scala.collection.immutable.VectorMap$Tombstone$();
    descriptor: ()V
    flags: (0x0001) ACC_PUBLIC
    Code:
      stack=1, locals=1, args_size=1
         0: aload_0
         1: invokespecial #77                 // Method scala/runtime/AbstractFunction1."<init>":()V
         4: return
      LineNumberTable:
        line 225: 0
      LocalVariableTable:
        Start  Length  Slot  Name   Signature
            0       5     0  this   Lscala/collection/immutable/VectorMap$Tombstone$;
}
InnerClasses:
  public static final #13= #10 of #12;    // Tombstone=class scala/collection/immutable/VectorMap$Tombstone of class scala/collection/immutable/VectorMap
  public static #14= #2 of #12;           // Tombstone$=class scala/collection/immutable/VectorMap$Tombstone$ of class scala/collection/immutable/VectorMap
Signature: #3                           // Lscala/runtime/AbstractFunction1<Ljava/lang/Object;Lscala/collection/immutable/VectorMap$Tombstone;>;Ljava/io/Serializable;
SourceFile: "VectorMap.scala"
  ScalaInlineInfo: length = 0x22 (unknown attribute)
   01 01 00 06 00 13 00 12 01 00 1C 00 1D 01 00 1C
   00 42 01 00 18 00 19 01 00 23 00 24 01 00 3B 00
   3C 01
  Scala: length = 0x0 (unknown attribute)

