Classfile /Users/mw/Projects/slang-braindump/.jar/jar11/assemble/slang-braindump/assemble/content/scala/collection/immutable/VectorMap$.class
  Last modified May 29, 2022; size 3542 bytes
  SHA-256 checksum ae12b87da1f7694d9ad5557a1b230ff3131536b7f2bc4db99578843f224ca8e6
  Compiled from "VectorMap.scala"
public final class scala.collection.immutable.VectorMap$ extends java.lang.Object implements scala.collection.MapFactory<scala.collection.immutable.VectorMap>
  minor version: 0
  major version: 52
  flags: (0x0031) ACC_PUBLIC, ACC_FINAL, ACC_SUPER
  this_class: #2                          // scala/collection/immutable/VectorMap$
  super_class: #5                         // java/lang/Object
  interfaces: 1, fields: 2, methods: 10, attributes: 4
Constant pool:
    #1 = Utf8               scala/collection/immutable/VectorMap$
    #2 = Class              #1            // scala/collection/immutable/VectorMap$
    #3 = Utf8               Ljava/lang/Object;Lscala/collection/MapFactory<Lscala/collection/immutable/VectorMap;>;
    #4 = Utf8               java/lang/Object
    #5 = Class              #4            // java/lang/Object
    #6 = Utf8               scala/collection/MapFactory
    #7 = Class              #6            // scala/collection/MapFactory
    #8 = Utf8               VectorMap.scala
    #9 = Utf8               MODULE$
   #10 = Utf8               Lscala/collection/immutable/VectorMap$;
   #11 = Utf8               EmptyMap
   #12 = Utf8               Lscala/collection/immutable/VectorMap;
   #13 = Utf8               Lscala/collection/immutable/VectorMap<Lscala/runtime/Nothing$;Lscala/runtime/Nothing$;>;
   #14 = Utf8               <clinit>
   #15 = Utf8               ()V
   #16 = Utf8               <init>
   #17 = NameAndType        #16:#15       // "<init>":()V
   #18 = Methodref          #2.#17        // scala/collection/immutable/VectorMap$."<init>":()V
   #19 = NameAndType        #9:#10        // MODULE$:Lscala/collection/immutable/VectorMap$;
   #20 = Fieldref           #2.#19        // scala/collection/immutable/VectorMap$.MODULE$:Lscala/collection/immutable/VectorMap$;
   #21 = Utf8               scala/collection/immutable/VectorMap
   #22 = Class              #21           // scala/collection/immutable/VectorMap
   #23 = Utf8               scala/collection/immutable/Vector$
   #24 = Class              #23           // scala/collection/immutable/Vector$
   #25 = Utf8               Lscala/collection/immutable/Vector$;
   #26 = NameAndType        #9:#25        // MODULE$:Lscala/collection/immutable/Vector$;
   #27 = Fieldref           #24.#26       // scala/collection/immutable/Vector$.MODULE$:Lscala/collection/immutable/Vector$;
   #28 = Utf8               scala/collection/immutable/Vector0$
   #29 = Class              #28           // scala/collection/immutable/Vector0$
   #30 = Utf8               Lscala/collection/immutable/Vector0$;
   #31 = NameAndType        #9:#30        // MODULE$:Lscala/collection/immutable/Vector0$;
   #32 = Fieldref           #29.#31       // scala/collection/immutable/Vector0$.MODULE$:Lscala/collection/immutable/Vector0$;
   #33 = Utf8               scala/collection/immutable/HashMap$
   #34 = Class              #33           // scala/collection/immutable/HashMap$
   #35 = Utf8               Lscala/collection/immutable/HashMap$;
   #36 = NameAndType        #9:#35        // MODULE$:Lscala/collection/immutable/HashMap$;
   #37 = Fieldref           #34.#36       // scala/collection/immutable/HashMap$.MODULE$:Lscala/collection/immutable/HashMap$;
   #38 = Utf8               empty
   #39 = Utf8               ()Lscala/collection/immutable/HashMap;
   #40 = NameAndType        #38:#39       // empty:()Lscala/collection/immutable/HashMap;
   #41 = Methodref          #34.#40       // scala/collection/immutable/HashMap$.empty:()Lscala/collection/immutable/HashMap;
   #42 = Utf8               (Lscala/collection/immutable/Vector;Lscala/collection/immutable/Map;)V
   #43 = NameAndType        #16:#42       // "<init>":(Lscala/collection/immutable/Vector;Lscala/collection/immutable/Map;)V
   #44 = Methodref          #22.#43       // scala/collection/immutable/VectorMap."<init>":(Lscala/collection/immutable/Vector;Lscala/collection/immutable/Map;)V
   #45 = NameAndType        #11:#12       // EmptyMap:Lscala/collection/immutable/VectorMap;
   #46 = Fieldref           #2.#45        // scala/collection/immutable/VectorMap$.EmptyMap:Lscala/collection/immutable/VectorMap;
   #47 = Utf8               apply
   #48 = Utf8               (Lscala/collection/immutable/Seq;)Ljava/lang/Object;
   #49 = Utf8               elems
   #50 = Utf8               apply$
   #51 = Utf8               (Lscala/collection/MapFactory;Lscala/collection/immutable/Seq;)Ljava/lang/Object;
   #52 = NameAndType        #50:#51       // apply$:(Lscala/collection/MapFactory;Lscala/collection/immutable/Seq;)Ljava/lang/Object;
   #53 = InterfaceMethodref #7.#52        // scala/collection/MapFactory.apply$:(Lscala/collection/MapFactory;Lscala/collection/immutable/Seq;)Ljava/lang/Object;
   #54 = Utf8               this
   #55 = Utf8               Lscala/collection/immutable/Seq;
   #56 = Utf8               mapFactory
   #57 = Utf8               ()Lscala/collection/Factory;
   #58 = Utf8               <K:Ljava/lang/Object;V:Ljava/lang/Object;>()Lscala/collection/Factory<Lscala/Tuple2<TK;TV;>;Lscala/collection/immutable/VectorMap<TK;TV;>;>;
   #59 = Utf8               mapFactory$
   #60 = Utf8               (Lscala/collection/MapFactory;)Lscala/collection/Factory;
   #61 = NameAndType        #59:#60       // mapFactory$:(Lscala/collection/MapFactory;)Lscala/collection/Factory;
   #62 = InterfaceMethodref #7.#61        // scala/collection/MapFactory.mapFactory$:(Lscala/collection/MapFactory;)Lscala/collection/Factory;
   #63 = Utf8               ()Lscala/collection/immutable/VectorMap;
   #64 = Utf8               <K:Ljava/lang/Object;V:Ljava/lang/Object;>()Lscala/collection/immutable/VectorMap<TK;TV;>;
   #65 = Utf8               from
   #66 = Utf8               (Lscala/collection/IterableOnce;)Lscala/collection/immutable/VectorMap;
   #67 = Utf8               <K:Ljava/lang/Object;V:Ljava/lang/Object;>(Lscala/collection/IterableOnce<Lscala/Tuple2<TK;TV;>;>;)Lscala/collection/immutable/VectorMap<TK;TV;>;
   #68 = Utf8               it
   #69 = Utf8               scala/collection/immutable/VectorMapBuilder
   #70 = Class              #69           // scala/collection/immutable/VectorMapBuilder
   #71 = Methodref          #70.#17       // scala/collection/immutable/VectorMapBuilder."<init>":()V
   #72 = Utf8               scala/collection/mutable/Growable
   #73 = Class              #72           // scala/collection/mutable/Growable
   #74 = Utf8               addAll$
   #75 = Utf8               (Lscala/collection/mutable/Growable;Lscala/collection/IterableOnce;)Lscala/collection/mutable/Growable;
   #76 = NameAndType        #74:#75       // addAll$:(Lscala/collection/mutable/Growable;Lscala/collection/IterableOnce;)Lscala/collection/mutable/Growable;
   #77 = InterfaceMethodref #73.#76       // scala/collection/mutable/Growable.addAll$:(Lscala/collection/mutable/Growable;Lscala/collection/IterableOnce;)Lscala/collection/mutable/Growable;
   #78 = Utf8               scala/collection/mutable/Builder
   #79 = Class              #78           // scala/collection/mutable/Builder
   #80 = Utf8               result
   #81 = Utf8               ()Ljava/lang/Object;
   #82 = NameAndType        #80:#81       // result:()Ljava/lang/Object;
   #83 = InterfaceMethodref #79.#82       // scala/collection/mutable/Builder.result:()Ljava/lang/Object;
   #84 = Utf8               Lscala/collection/IterableOnce;
   #85 = Utf8               newBuilder
   #86 = Utf8               ()Lscala/collection/mutable/Builder;
   #87 = Utf8               <K:Ljava/lang/Object;V:Ljava/lang/Object;>()Lscala/collection/mutable/Builder<Lscala/Tuple2<TK;TV;>;Lscala/collection/immutable/VectorMap<TK;TV;>;>;
   #88 = Utf8               writeReplace
   #89 = Utf8               scala/runtime/ModuleSerializationProxy
   #90 = Class              #89           // scala/runtime/ModuleSerializationProxy
   #91 = Utf8               (Ljava/lang/Class;)V
   #92 = NameAndType        #16:#91       // "<init>":(Ljava/lang/Class;)V
   #93 = Methodref          #90.#92       // scala/runtime/ModuleSerializationProxy."<init>":(Ljava/lang/Class;)V
   #94 = Utf8               (Lscala/collection/IterableOnce;)Ljava/lang/Object;
   #95 = NameAndType        #65:#66       // from:(Lscala/collection/IterableOnce;)Lscala/collection/immutable/VectorMap;
   #96 = Methodref          #2.#95        // scala/collection/immutable/VectorMap$.from:(Lscala/collection/IterableOnce;)Lscala/collection/immutable/VectorMap;
   #97 = NameAndType        #38:#63       // empty:()Lscala/collection/immutable/VectorMap;
   #98 = Methodref          #2.#97        // scala/collection/immutable/VectorMap$.empty:()Lscala/collection/immutable/VectorMap;
   #99 = Methodref          #5.#17        // java/lang/Object."<init>":()V
  #100 = Utf8               Signature
  #101 = Utf8               Code
  #102 = Utf8               LineNumberTable
  #103 = Utf8               LocalVariableTable
  #104 = Utf8               MethodParameters
  #105 = Utf8               StackMapTable
  #106 = Utf8               SourceFile
  #107 = Utf8               ScalaInlineInfo
  #108 = Utf8               Scala
{
  public static final scala.collection.immutable.VectorMap$ MODULE$;
    descriptor: Lscala/collection/immutable/VectorMap$;
    flags: (0x0019) ACC_PUBLIC, ACC_STATIC, ACC_FINAL

  private static final scala.collection.immutable.VectorMap<scala.runtime.Nothing$, scala.runtime.Nothing$> EmptyMap;
    descriptor: Lscala/collection/immutable/VectorMap;
    flags: (0x001a) ACC_PRIVATE, ACC_STATIC, ACC_FINAL
    Signature: #13                          // Lscala/collection/immutable/VectorMap<Lscala/runtime/Nothing$;Lscala/runtime/Nothing$;>;

  public static {};
    descriptor: ()V
    flags: (0x0009) ACC_PUBLIC, ACC_STATIC
    Code:
      stack=4, locals=0, args_size=0
         0: new           #2                  // class scala/collection/immutable/VectorMap$
         3: dup
         4: invokespecial #18                 // Method "<init>":()V
         7: putstatic     #20                 // Field MODULE$:Lscala/collection/immutable/VectorMap$;
        10: getstatic     #20                 // Field MODULE$:Lscala/collection/immutable/VectorMap$;
        13: pop
        14: new           #22                 // class scala/collection/immutable/VectorMap
        17: dup
        18: getstatic     #27                 // Field scala/collection/immutable/Vector$.MODULE$:Lscala/collection/immutable/Vector$;
        21: pop
        22: getstatic     #32                 // Field scala/collection/immutable/Vector0$.MODULE$:Lscala/collection/immutable/Vector0$;
        25: getstatic     #37                 // Field scala/collection/immutable/HashMap$.MODULE$:Lscala/collection/immutable/HashMap$;
        28: invokevirtual #41                 // Method scala/collection/immutable/HashMap$.empty:()Lscala/collection/immutable/HashMap;
        31: invokespecial #44                 // Method scala/collection/immutable/VectorMap."<init>":(Lscala/collection/immutable/Vector;Lscala/collection/immutable/Map;)V
        34: putstatic     #46                 // Field EmptyMap:Lscala/collection/immutable/VectorMap;
        37: return
      LineNumberTable:
        line 218: 0
        line 228: 14
        line 227: 34
        line 218: 37

  public java.lang.Object apply(scala.collection.immutable.Seq);
    descriptor: (Lscala/collection/immutable/Seq;)Ljava/lang/Object;
    flags: (0x0001) ACC_PUBLIC
    Code:
      stack=2, locals=2, args_size=2
         0: aload_0
         1: aload_1
         2: invokestatic  #53                 // InterfaceMethod scala/collection/MapFactory.apply$:(Lscala/collection/MapFactory;Lscala/collection/immutable/Seq;)Ljava/lang/Object;
         5: areturn
      LineNumberTable:
        line 218: 0
      LocalVariableTable:
        Start  Length  Slot  Name   Signature
            0       6     0  this   Lscala/collection/immutable/VectorMap$;
            0       6     1 elems   Lscala/collection/immutable/Seq;
    MethodParameters:
      Name                           Flags
      elems                          final

  public <K extends java.lang.Object, V extends java.lang.Object> scala.collection.Factory<scala.Tuple2<K, V>, scala.collection.immutable.VectorMap<K, V>> mapFactory();
    descriptor: ()Lscala/collection/Factory;
    flags: (0x0001) ACC_PUBLIC
    Code:
      stack=1, locals=1, args_size=1
         0: aload_0
         1: invokestatic  #62                 // InterfaceMethod scala/collection/MapFactory.mapFactory$:(Lscala/collection/MapFactory;)Lscala/collection/Factory;
         4: areturn
      LineNumberTable:
        line 218: 0
      LocalVariableTable:
        Start  Length  Slot  Name   Signature
            0       5     0  this   Lscala/collection/immutable/VectorMap$;
    Signature: #58                          // <K:Ljava/lang/Object;V:Ljava/lang/Object;>()Lscala/collection/Factory<Lscala/Tuple2<TK;TV;>;Lscala/collection/immutable/VectorMap<TK;TV;>;>;

  public <K extends java.lang.Object, V extends java.lang.Object> scala.collection.immutable.VectorMap<K, V> empty();
    descriptor: ()Lscala/collection/immutable/VectorMap;
    flags: (0x0001) ACC_PUBLIC
    Code:
      stack=1, locals=1, args_size=1
         0: getstatic     #46                 // Field EmptyMap:Lscala/collection/immutable/VectorMap;
         3: areturn
      LineNumberTable:
        line 230: 0
      LocalVariableTable:
        Start  Length  Slot  Name   Signature
            0       4     0  this   Lscala/collection/immutable/VectorMap$;
    Signature: #64                          // <K:Ljava/lang/Object;V:Ljava/lang/Object;>()Lscala/collection/immutable/VectorMap<TK;TV;>;

  public <K extends java.lang.Object, V extends java.lang.Object> scala.collection.immutable.VectorMap<K, V> from(scala.collection.IterableOnce<scala.Tuple2<K, V>>);
    descriptor: (Lscala/collection/IterableOnce;)Lscala/collection/immutable/VectorMap;
    flags: (0x0001) ACC_PUBLIC
    Code:
      stack=2, locals=3, args_size=2
         0: aload_1
         1: instanceof    #22                 // class scala/collection/immutable/VectorMap
         4: ifeq          15
         7: aload_1
         8: checkcast     #22                 // class scala/collection/immutable/VectorMap
        11: astore_2
        12: goto          38
        15: new           #70                 // class scala/collection/immutable/VectorMapBuilder
        18: dup
        19: invokespecial #71                 // Method scala/collection/immutable/VectorMapBuilder."<init>":()V
        22: aload_1
        23: invokestatic  #77                 // InterfaceMethod scala/collection/mutable/Growable.addAll$:(Lscala/collection/mutable/Growable;Lscala/collection/IterableOnce;)Lscala/collection/mutable/Growable;
        26: checkcast     #79                 // class scala/collection/mutable/Builder
        29: invokeinterface #83,  1           // InterfaceMethod scala/collection/mutable/Builder.result:()Ljava/lang/Object;
        34: checkcast     #22                 // class scala/collection/immutable/VectorMap
        37: astore_2
        38: aload_2
        39: areturn
      StackMapTable: number_of_entries = 2
        frame_type = 15 /* same */
        frame_type = 252 /* append */
          offset_delta = 22
          locals = [ class scala/collection/immutable/VectorMap ]
      LineNumberTable:
        line 234: 0
        line 238: 15
        line 241: 22
        line 235: 26
        line 233: 38
      LocalVariableTable:
        Start  Length  Slot  Name   Signature
            0      40     0  this   Lscala/collection/immutable/VectorMap$;
            0      40     1    it   Lscala/collection/IterableOnce;
    Signature: #67                          // <K:Ljava/lang/Object;V:Ljava/lang/Object;>(Lscala/collection/IterableOnce<Lscala/Tuple2<TK;TV;>;>;)Lscala/collection/immutable/VectorMap<TK;TV;>;
    MethodParameters:
      Name                           Flags
      it                             final

  public <K extends java.lang.Object, V extends java.lang.Object> scala.collection.mutable.Builder<scala.Tuple2<K, V>, scala.collection.immutable.VectorMap<K, V>> newBuilder();
    descriptor: ()Lscala/collection/mutable/Builder;
    flags: (0x0001) ACC_PUBLIC
    Code:
      stack=2, locals=1, args_size=1
         0: new           #70                 // class scala/collection/immutable/VectorMapBuilder
         3: dup
         4: invokespecial #71                 // Method scala/collection/immutable/VectorMapBuilder."<init>":()V
         7: areturn
      LineNumberTable:
        line 238: 0
      LocalVariableTable:
        Start  Length  Slot  Name   Signature
            0       8     0  this   Lscala/collection/immutable/VectorMap$;
    Signature: #87                          // <K:Ljava/lang/Object;V:Ljava/lang/Object;>()Lscala/collection/mutable/Builder<Lscala/Tuple2<TK;TV;>;Lscala/collection/immutable/VectorMap<TK;TV;>;>;

  private java.lang.Object writeReplace();
    descriptor: ()Ljava/lang/Object;
    flags: (0x0002) ACC_PRIVATE
    Code:
      stack=3, locals=1, args_size=1
         0: new           #90                 // class scala/runtime/ModuleSerializationProxy
         3: dup
         4: ldc           #2                  // class scala/collection/immutable/VectorMap$
         6: invokespecial #93                 // Method scala/runtime/ModuleSerializationProxy."<init>":(Ljava/lang/Class;)V
         9: areturn
      LineNumberTable:
        line 218: 0
      LocalVariableTable:
        Start  Length  Slot  Name   Signature
            0      10     0  this   Lscala/collection/immutable/VectorMap$;

  public java.lang.Object from(scala.collection.IterableOnce);
    descriptor: (Lscala/collection/IterableOnce;)Ljava/lang/Object;
    flags: (0x1041) ACC_PUBLIC, ACC_BRIDGE, ACC_SYNTHETIC
    Code:
      stack=2, locals=2, args_size=2
         0: aload_0
         1: aload_1
         2: invokevirtual #96                 // Method from:(Lscala/collection/IterableOnce;)Lscala/collection/immutable/VectorMap;
         5: areturn
      LineNumberTable:
        line 218: 0
      LocalVariableTable:
        Start  Length  Slot  Name   Signature
            0       6     0  this   Lscala/collection/immutable/VectorMap$;
            0       6     1    it   Lscala/collection/IterableOnce;
    MethodParameters:
      Name                           Flags
      it                             final

  public java.lang.Object empty();
    descriptor: ()Ljava/lang/Object;
    flags: (0x1041) ACC_PUBLIC, ACC_BRIDGE, ACC_SYNTHETIC
    Code:
      stack=1, locals=1, args_size=1
         0: aload_0
         1: invokevirtual #98                 // Method empty:()Lscala/collection/immutable/VectorMap;
         4: areturn
      LineNumberTable:
        line 218: 0
      LocalVariableTable:
        Start  Length  Slot  Name   Signature
            0       5     0  this   Lscala/collection/immutable/VectorMap$;

  private scala.collection.immutable.VectorMap$();
    descriptor: ()V
    flags: (0x0002) ACC_PRIVATE
    Code:
      stack=1, locals=1, args_size=1
         0: aload_0
         1: invokespecial #99                 // Method java/lang/Object."<init>":()V
         4: return
      LineNumberTable:
        line 218: 0
      LocalVariableTable:
        Start  Length  Slot  Name   Signature
            0       5     0  this   Lscala/collection/immutable/VectorMap$;
}
Signature: #3                           // Ljava/lang/Object;Lscala/collection/MapFactory<Lscala/collection/immutable/VectorMap;>;
SourceFile: "VectorMap.scala"
  ScalaInlineInfo: length = 0x31 (unknown attribute)
   01 01 00 09 00 10 00 0F 01 00 2F 00 30 01 00 26
   00 51 01 00 26 00 3F 01 00 41 00 5E 01 00 41 00
   42 01 00 38 00 39 01 00 55 00 56 01 00 58 00 51
   01
  Scala: length = 0x0 (unknown attribute)

