Classfile /Users/mw/Projects/slang-braindump/.jar/jar11/assemble/slang-braindump/assemble/content/scala/collection/immutable/WrappedString$UnwrapOp$.class
  Last modified May 29, 2022; size 1772 bytes
  SHA-256 checksum 7bdf94cb157e95580e2c9c1735c19d7081610c2a086f392f20a03ca474d32668
  Compiled from "WrappedString.scala"
public class scala.collection.immutable.WrappedString$UnwrapOp$
  minor version: 0
  major version: 52
  flags: (0x0021) ACC_PUBLIC, ACC_SUPER
  this_class: #2                          // scala/collection/immutable/WrappedString$UnwrapOp$
  super_class: #4                         // java/lang/Object
  interfaces: 0, fields: 1, methods: 5, attributes: 4
Constant pool:
   #1 = Utf8               scala/collection/immutable/WrappedString$UnwrapOp$
   #2 = Class              #1             // scala/collection/immutable/WrappedString$UnwrapOp$
   #3 = Utf8               java/lang/Object
   #4 = Class              #3             // java/lang/Object
   #5 = Utf8               WrappedString.scala
   #6 = Utf8               scala/collection/immutable/WrappedString$UnwrapOp
   #7 = Class              #6             // scala/collection/immutable/WrappedString$UnwrapOp
   #8 = Utf8               scala/collection/immutable/WrappedString
   #9 = Class              #8             // scala/collection/immutable/WrappedString
  #10 = Utf8               UnwrapOp
  #11 = Utf8               UnwrapOp$
  #12 = Utf8               MODULE$
  #13 = Utf8               Lscala/collection/immutable/WrappedString$UnwrapOp$;
  #14 = Utf8               <clinit>
  #15 = Utf8               ()V
  #16 = Utf8               <init>
  #17 = NameAndType        #16:#15        // "<init>":()V
  #18 = Methodref          #2.#17         // scala/collection/immutable/WrappedString$UnwrapOp$."<init>":()V
  #19 = NameAndType        #12:#13        // MODULE$:Lscala/collection/immutable/WrappedString$UnwrapOp$;
  #20 = Fieldref           #2.#19         // scala/collection/immutable/WrappedString$UnwrapOp$.MODULE$:Lscala/collection/immutable/WrappedString$UnwrapOp$;
  #21 = Utf8               unwrap$extension
  #22 = Utf8               (Lscala/collection/immutable/WrappedString;)Ljava/lang/String;
  #23 = Utf8               $this
  #24 = Utf8               scala$collection$immutable$WrappedString$$self
  #25 = Utf8               ()Ljava/lang/String;
  #26 = NameAndType        #24:#25        // scala$collection$immutable$WrappedString$$self:()Ljava/lang/String;
  #27 = Methodref          #9.#26         // scala/collection/immutable/WrappedString.scala$collection$immutable$WrappedString$$self:()Ljava/lang/String;
  #28 = Utf8               this
  #29 = Utf8               Lscala/collection/immutable/WrappedString;
  #30 = Utf8               hashCode$extension
  #31 = Utf8               (Lscala/collection/immutable/WrappedString;)I
  #32 = Utf8               scala/util/hashing/MurmurHash3$
  #33 = Class              #32            // scala/util/hashing/MurmurHash3$
  #34 = Utf8               Lscala/util/hashing/MurmurHash3$;
  #35 = NameAndType        #12:#34        // MODULE$:Lscala/util/hashing/MurmurHash3$;
  #36 = Fieldref           #33.#35        // scala/util/hashing/MurmurHash3$.MODULE$:Lscala/util/hashing/MurmurHash3$;
  #37 = Utf8               seqHash
  #38 = Utf8               (Lscala/collection/Seq;)I
  #39 = NameAndType        #37:#38        // seqHash:(Lscala/collection/Seq;)I
  #40 = Methodref          #33.#39        // scala/util/hashing/MurmurHash3$.seqHash:(Lscala/collection/Seq;)I
  #41 = Utf8               equals$extension
  #42 = Utf8               (Lscala/collection/immutable/WrappedString;Ljava/lang/Object;)Z
  #43 = Utf8               x$1
  #44 = Utf8               scala$collection$immutable$WrappedString$UnwrapOp$$value
  #45 = Utf8               ()Lscala/collection/immutable/WrappedString;
  #46 = NameAndType        #44:#45        // scala$collection$immutable$WrappedString$UnwrapOp$$value:()Lscala/collection/immutable/WrappedString;
  #47 = Methodref          #7.#46         // scala/collection/immutable/WrappedString$UnwrapOp.scala$collection$immutable$WrappedString$UnwrapOp$$value:()Lscala/collection/immutable/WrappedString;
  #48 = Utf8               equals
  #49 = Utf8               (Ljava/lang/Object;)Z
  #50 = NameAndType        #48:#49        // equals:(Ljava/lang/Object;)Z
  #51 = Methodref          #4.#50         // java/lang/Object.equals:(Ljava/lang/Object;)Z
  #52 = Utf8               Ljava/lang/Object;
  #53 = Methodref          #4.#17         // java/lang/Object."<init>":()V
  #54 = Utf8               Code
  #55 = Utf8               LineNumberTable
  #56 = Utf8               LocalVariableTable
  #57 = Utf8               MethodParameters
  #58 = Utf8               StackMapTable
  #59 = Utf8               InnerClasses
  #60 = Utf8               SourceFile
  #61 = Utf8               ScalaInlineInfo
  #62 = Utf8               Scala
{
  public static final scala.collection.immutable.WrappedString$UnwrapOp$ MODULE$;
    descriptor: Lscala/collection/immutable/WrappedString$UnwrapOp$;
    flags: (0x0019) ACC_PUBLIC, ACC_STATIC, ACC_FINAL

  public static {};
    descriptor: ()V
    flags: (0x0009) ACC_PUBLIC, ACC_STATIC
    Code:
      stack=2, locals=0, args_size=0
         0: new           #2                  // class scala/collection/immutable/WrappedString$UnwrapOp$
         3: dup
         4: invokespecial #18                 // Method "<init>":()V
         7: putstatic     #20                 // Field MODULE$:Lscala/collection/immutable/WrappedString$UnwrapOp$;
        10: return
      LineNumberTable:
        line 137: 0

  public final java.lang.String unwrap$extension(scala.collection.immutable.WrappedString);
    descriptor: (Lscala/collection/immutable/WrappedString;)Ljava/lang/String;
    flags: (0x0011) ACC_PUBLIC, ACC_FINAL
    Code:
      stack=1, locals=2, args_size=2
         0: aload_1
         1: invokevirtual #27                 // Method scala/collection/immutable/WrappedString.scala$collection$immutable$WrappedString$$self:()Ljava/lang/String;
         4: areturn
      LineNumberTable:
        line 138: 0
      LocalVariableTable:
        Start  Length  Slot  Name   Signature
            0       5     0  this   Lscala/collection/immutable/WrappedString$UnwrapOp$;
            0       5     1 $this   Lscala/collection/immutable/WrappedString;
    MethodParameters:
      Name                           Flags
      $this                          final

  public final int hashCode$extension(scala.collection.immutable.WrappedString);
    descriptor: (Lscala/collection/immutable/WrappedString;)I
    flags: (0x0011) ACC_PUBLIC, ACC_FINAL
    Code:
      stack=2, locals=2, args_size=2
         0: aload_1
         1: ifnonnull     6
         4: aconst_null
         5: athrow
         6: getstatic     #36                 // Field scala/util/hashing/MurmurHash3$.MODULE$:Lscala/util/hashing/MurmurHash3$;
         9: aload_1
        10: invokevirtual #40                 // Method scala/util/hashing/MurmurHash3$.seqHash:(Lscala/collection/Seq;)I
        13: ireturn
      StackMapTable: number_of_entries = 1
        frame_type = 6 /* same */
      LineNumberTable:
        line 137: 0
      LocalVariableTable:
        Start  Length  Slot  Name   Signature
            0      14     0  this   Lscala/collection/immutable/WrappedString$UnwrapOp$;
            0      14     1 $this   Lscala/collection/immutable/WrappedString;
    MethodParameters:
      Name                           Flags
      $this                          final

  public final boolean equals$extension(scala.collection.immutable.WrappedString, java.lang.Object);
    descriptor: (Lscala/collection/immutable/WrappedString;Ljava/lang/Object;)Z
    flags: (0x0011) ACC_PUBLIC, ACC_FINAL
    Code:
      stack=2, locals=5, args_size=3
         0: aload_2
         1: instanceof    #7                  // class scala/collection/immutable/WrappedString$UnwrapOp
         4: ifeq          12
         7: iconst_1
         8: istore_3
         9: goto          14
        12: iconst_0
        13: istore_3
        14: iload_3
        15: ifeq          67
        18: aload_2
        19: ifnonnull     26
        22: aconst_null
        23: goto          33
        26: aload_2
        27: checkcast     #7                  // class scala/collection/immutable/WrappedString$UnwrapOp
        30: invokevirtual #47                 // Method scala/collection/immutable/WrappedString$UnwrapOp.scala$collection$immutable$WrappedString$UnwrapOp$$value:()Lscala/collection/immutable/WrappedString;
        33: astore        4
        35: aload_1
        36: dup
        37: ifnonnull     49
        40: pop
        41: aload         4
        43: ifnull        57
        46: goto          61
        49: aload         4
        51: invokevirtual #51                 // Method java/lang/Object.equals:(Ljava/lang/Object;)Z
        54: ifeq          61
        57: iconst_1
        58: goto          62
        61: iconst_0
        62: ifeq          67
        65: iconst_1
        66: ireturn
        67: iconst_0
        68: ireturn
      StackMapTable: number_of_entries = 9
        frame_type = 12 /* same */
        frame_type = 252 /* append */
          offset_delta = 1
          locals = [ int ]
        frame_type = 11 /* same */
        frame_type = 70 /* same_locals_1_stack_item */
          stack = [ class scala/collection/immutable/WrappedString ]
        frame_type = 255 /* full_frame */
          offset_delta = 15
          locals = [ class scala/collection/immutable/WrappedString$UnwrapOp$, class scala/collection/immutable/WrappedString, class java/lang/Object, int, class scala/collection/immutable/WrappedString ]
          stack = [ class scala/collection/immutable/WrappedString ]
        frame_type = 7 /* same */
        frame_type = 3 /* same */
        frame_type = 64 /* same_locals_1_stack_item */
          stack = [ int ]
        frame_type = 250 /* chop */
          offset_delta = 4
      LineNumberTable:
        line 137: 0
      LocalVariableTable:
        Start  Length  Slot  Name   Signature
            0      69     0  this   Lscala/collection/immutable/WrappedString$UnwrapOp$;
            0      69     1 $this   Lscala/collection/immutable/WrappedString;
            0      69     2   x$1   Ljava/lang/Object;
    MethodParameters:
      Name                           Flags
      $this                          final
      x$1                            final

  public scala.collection.immutable.WrappedString$UnwrapOp$();
    descriptor: ()V
    flags: (0x0001) ACC_PUBLIC
    Code:
      stack=1, locals=1, args_size=1
         0: aload_0
         1: invokespecial #53                 // Method java/lang/Object."<init>":()V
         4: return
      LineNumberTable:
        line 137: 0
      LocalVariableTable:
        Start  Length  Slot  Name   Signature
            0       5     0  this   Lscala/collection/immutable/WrappedString$UnwrapOp$;
}
InnerClasses:
  public static final #10= #7 of #9;      // UnwrapOp=class scala/collection/immutable/WrappedString$UnwrapOp of class scala/collection/immutable/WrappedString
  public static #11= #2 of #9;            // UnwrapOp$=class scala/collection/immutable/WrappedString$UnwrapOp$ of class scala/collection/immutable/WrappedString
SourceFile: "WrappedString.scala"
  ScalaInlineInfo: length = 0x18 (unknown attribute)
   01 01 00 04 00 10 00 0F 01 00 29 00 2A 01 00 1E
   00 1F 01 00 15 00 16 01
  Scala: length = 0x0 (unknown attribute)

