Classfile /Users/mw/Projects/slang-braindump/.jar/jar11/assemble/slang-braindump/assemble/content/argonaut/CursorOpDeleteGoField.class
  Last modified May 29, 2022; size 4648 bytes
  SHA-256 checksum e719c26eb116e91a3eaeca90d642456fe5b6c47606fed1bb6a66f135f932938e
  Compiled from "CursorOpElement.scala"
public class argonaut.CursorOpDeleteGoField extends argonaut.CursorOpElement
  minor version: 0
  major version: 52
  flags: (0x0021) ACC_PUBLIC, ACC_SUPER
  this_class: #2                          // argonaut/CursorOpDeleteGoField
  super_class: #4                         // argonaut/CursorOpElement
  interfaces: 0, fields: 1, methods: 17, attributes: 4
Constant pool:
    #1 = Utf8               argonaut/CursorOpDeleteGoField
    #2 = Class              #1            // argonaut/CursorOpDeleteGoField
    #3 = Utf8               argonaut/CursorOpElement
    #4 = Class              #3            // argonaut/CursorOpElement
    #5 = Utf8               CursorOpElement.scala
    #6 = Utf8               Lscala/reflect/ScalaSignature;
    #7 = Utf8               bytes
    #8 = Utf8               \u0006\u0005\u0005]b\u0001\u0002\f\u0018\u0001jA\u0001\"\r\u0001\u0003\u0016\u0004%\tA\r\u0005\tw\u0001\u0011\t\u0012)A\u0005g!)A\b\u0001C\u0001{!9\u0001\tAA\u0001\n\u0003\t\u0005bB\"\u0001#\u0003%\t\u0001\u0012\u0005\b\u001f\u0002\t\t\u0011\"\u0011Q\u0011\u001dI\u0006!!A\u0005\u0002iCqA\u0018\u0001\u0002\u0002\u0013\u0005q\fC\u0004f\u0001\u0005\u0005I\u0011\t4\t\u000f5\u0004\u0011\u0011!C\u0001]\"91\u000fAA\u0001\n\u0003\"\bb\u0002<\u0001\u0003\u0003%\te\u001e\u0005\bq\u0002\t\t\u0011\"\u0011z\u0011\u001dQ\b!!A\u0005Bm<q!`\f\u0002\u0002#\u0005aPB\u0004\u0017/\u0005\u0005\t\u0012A@\t\rq\u0002B\u0011AA\f\u0011\u001dA\b#!A\u0005FeD\u0011\"!\u0007\u0011\u0003\u0003%\t)a\u0007\t\u0013\u0005}\u0001#!A\u0005\u0002\u0006\u0005\u0002\"CA\u0017!\u0005\u0005I\u0011BA\u0018\u0005U\u0019UO]:pe>\u0003H)\u001a7fi\u0016<uNR5fY\u0012T\u0011\u0001G\u0001\tCJ<wN\\1vi\u000e\u00011\u0003\u0002\u0001\u001c?\u0015\u0002\"\u0001H\u000f\u000e\u0003]I!AH\f\u0003\u001f\r+(o]8s\u001fB,E.Z7f]R\u0004\"\u0001I\u0012\u000e\u0003\u0005R\u0011AI\u0001\u0006g\u000e\fG.Y\u0005\u0003I\u0005\u0012q\u0001\u0015:pIV\u001cG\u000f\u0005\u0002\']9\u0011q\u0005\f\b\u0003Q-j\u0011!\u000b\u0006\u0003Ue\ta\u0001\u0010:p_Rt\u0014\"\u0001\u0012\n\u00055\n\u0013a\u00029bG.\fw-Z\u0005\u0003_A\u0012AbU3sS\u0006d\u0017N_1cY\u0016T!!L\u0011\u0002\u0003\u0019,\u0012a\r\t\u0003i]r!\u0001H\u001b\n\u0005Y:\u0012\u0001\u0002&t_:L!\u0001O\u001d\u0003\u0013)\u001bxN\u001c$jK2$\u0017B\u0001\u001e\u0018\u0005\u0015Q5o\u001c8t\u0003\t1\u0007%\u0001\u0004=S:LGO\u0010\u000b\u0003}}\u0002\"\u0001\b\u0001\t\u000bE\u001a\u0001\u0019A\u001a\u0002\t\r|\u0007/\u001f\u000b\u0003}\tCq!\r\u0003\u0011\u0002\u0003\u00071\'\u0001\bd_BLH\u0005Z3gCVdG\u000fJ\u0019\u0016\u0003\u0015S#a\r$,\u0003\u001d\u0003\"\u0001S\'\u000e\u0003%S!AS&\u0002\u0013Ut7\r[3dW\u0016$\'B\u0001\'\"\u0003)\tgN\\8uCRLwN\\\u0005\u0003\u001d&\u0013\u0011#\u001e8dQ\u0016\u001c7.\u001a3WCJL\u0017M\\2f\u00035\u0001(o\u001c3vGR\u0004&/\u001a4jqV\t\u0011\u000b\u0005\u0002S/6\t1K\u0003\u0002U+\u0006!A.\u00198h\u0015\u00051\u0016\u0001\u00026bm\u0006L!\u0001W*\u0003\rM#(/\u001b8h\u00031\u0001(o\u001c3vGR\f%/\u001b;z+\u0005Y\u0006C\u0001\u0011]\u0013\ti\u0016EA\u0002J]R\fa\u0002\u001d:pIV\u001cG/\u00127f[\u0016tG\u000f\u0006\u0002aGB\u0011\u0001%Y\u0005\u0003E\u0006\u00121!\u00118z\u0011\u001d!\u0007\"!AA\u0002m\u000b1\u0001\u001f\u00132\u0003=\u0001(o\u001c3vGRLE/\u001a:bi>\u0014X#A4\u0011\u0007!\\\u0007-D\u0001j\u0015\tQ\u0017%\u0001\u0006d_2dWm\u0019;j_:L!\u0001\\5\u0003\u0011%#XM]1u_J\f\u0001bY1o\u000bF,\u0018\r\u001c\u000b\u0003_J\u0004\"\u0001\t9\n\u0005E\f#a\u0002\"p_2,\u0017M\u001c\u0005\bI*\t\t\u00111\u0001a\u0003I\u0001(o\u001c3vGR,E.Z7f]Rt\u0015-\\3\u0015\u0005E+\bb\u00023\f\u0003\u0003\u0005\raW\u0001\tQ\u0006\u001c\bnQ8eKR\t1,\u0001\u0005u_N#(/\u001b8h)\u0005\t\u0016AB3rk\u0006d7\u000f\u0006\u0002py\"9AMDA\u0001\u0002\u0004\u0001\u0017!F\"veN|\'o\u00149EK2,G/Z$p\r&,G\u000e\u001a\t\u00039A\u0019R\u0001EA\u0001\u0003\u001b\u0001b!a\u0001\u0002\nMrTBAA\u0003\u0015\r\t9!I\u0001\beVtG/[7f\u0013\u0011\tY!!\u0002\u0003#\u0005\u00137\u000f\u001e:bGR4UO\\2uS>t\u0017\u0007\u0005\u0003\u0002\u0010\u0005UQBAA\t\u0015\r\t\u0019\"V\u0001\u0003S>L1aLA\t)\u0005q\u0018!B1qa2LHc\u0001 \u0002\u001e!)\u0011g\u0005a\u0001g\u00059QO\\1qa2LH\u0003BA\u0012\u0003S\u0001B\u0001IA\u0013g%\u0019\u0011qE\u0011\u0003\r=\u0003H/[8o\u0011!\tY\u0003FA\u0001\u0002\u0004q\u0014a\u0001=%a\u0005aqO]5uKJ+\u0007\u000f\\1dKR\u0011\u0011\u0011\u0007\t\u0004%\u0006M\u0012bAA\u001b\'\n1qJ\u00196fGR\u0004
    #9 = Utf8               f
   #10 = Utf8               Ljava/lang/String;
   #11 = Utf8               unapply
   #12 = Utf8               (Largonaut/CursorOpDeleteGoField;)Lscala/Option;
   #13 = Utf8               (Largonaut/CursorOpDeleteGoField;)Lscala/Option<Ljava/lang/String;>;
   #14 = Utf8               x$0
   #15 = Utf8               argonaut/CursorOpDeleteGoField$
   #16 = Class              #15           // argonaut/CursorOpDeleteGoField$
   #17 = Utf8               MODULE$
   #18 = Utf8               Largonaut/CursorOpDeleteGoField$;
   #19 = NameAndType        #17:#18       // MODULE$:Largonaut/CursorOpDeleteGoField$;
   #20 = Fieldref           #16.#19       // argonaut/CursorOpDeleteGoField$.MODULE$:Largonaut/CursorOpDeleteGoField$;
   #21 = NameAndType        #11:#12       // unapply:(Largonaut/CursorOpDeleteGoField;)Lscala/Option;
   #22 = Methodref          #16.#21       // argonaut/CursorOpDeleteGoField$.unapply:(Largonaut/CursorOpDeleteGoField;)Lscala/Option;
   #23 = Utf8               apply
   #24 = Utf8               (Ljava/lang/String;)Largonaut/CursorOpDeleteGoField;
   #25 = NameAndType        #23:#24       // apply:(Ljava/lang/String;)Largonaut/CursorOpDeleteGoField;
   #26 = Methodref          #16.#25       // argonaut/CursorOpDeleteGoField$.apply:(Ljava/lang/String;)Largonaut/CursorOpDeleteGoField;
   #27 = Utf8               andThen
   #28 = Utf8               (Lscala/Function1;)Lscala/Function1;
   #29 = Utf8               <A:Ljava/lang/Object;>(Lscala/Function1<Largonaut/CursorOpDeleteGoField;TA;>;)Lscala/Function1<Ljava/lang/String;TA;>;
   #30 = Utf8               g
   #31 = NameAndType        #27:#28       // andThen:(Lscala/Function1;)Lscala/Function1;
   #32 = Methodref          #16.#31       // argonaut/CursorOpDeleteGoField$.andThen:(Lscala/Function1;)Lscala/Function1;
   #33 = Utf8               compose
   #34 = Utf8               <A:Ljava/lang/Object;>(Lscala/Function1<TA;Ljava/lang/String;>;)Lscala/Function1<TA;Largonaut/CursorOpDeleteGoField;>;
   #35 = NameAndType        #33:#28       // compose:(Lscala/Function1;)Lscala/Function1;
   #36 = Methodref          #16.#35       // argonaut/CursorOpDeleteGoField$.compose:(Lscala/Function1;)Lscala/Function1;
   #37 = Utf8               ()Ljava/lang/String;
   #38 = NameAndType        #9:#10        // f:Ljava/lang/String;
   #39 = Fieldref           #2.#38        // argonaut/CursorOpDeleteGoField.f:Ljava/lang/String;
   #40 = Utf8               this
   #41 = Utf8               Largonaut/CursorOpDeleteGoField;
   #42 = Utf8               copy
   #43 = Utf8               <init>
   #44 = Utf8               (Ljava/lang/String;)V
   #45 = NameAndType        #43:#44       // "<init>":(Ljava/lang/String;)V
   #46 = Methodref          #2.#45        // argonaut/CursorOpDeleteGoField."<init>":(Ljava/lang/String;)V
   #47 = Utf8               copy$default$1
   #48 = NameAndType        #9:#37        // f:()Ljava/lang/String;
   #49 = Methodref          #2.#48        // argonaut/CursorOpDeleteGoField.f:()Ljava/lang/String;
   #50 = Utf8               productPrefix
   #51 = Utf8               CursorOpDeleteGoField
   #52 = String             #51           // CursorOpDeleteGoField
   #53 = Utf8               productArity
   #54 = Utf8               ()I
   #55 = Utf8               productElement
   #56 = Utf8               (I)Ljava/lang/Object;
   #57 = Utf8               x$1
   #58 = Utf8               scala/runtime/Statics
   #59 = Class              #58           // scala/runtime/Statics
   #60 = Utf8               ioobe
   #61 = NameAndType        #60:#56       // ioobe:(I)Ljava/lang/Object;
   #62 = Methodref          #59.#61       // scala/runtime/Statics.ioobe:(I)Ljava/lang/Object;
   #63 = Utf8               I
   #64 = Utf8               java/lang/Object
   #65 = Class              #64           // java/lang/Object
   #66 = Utf8               productIterator
   #67 = Utf8               ()Lscala/collection/Iterator;
   #68 = Utf8               ()Lscala/collection/Iterator<Ljava/lang/Object;>;
   #69 = Utf8               scala/runtime/ScalaRunTime$
   #70 = Class              #69           // scala/runtime/ScalaRunTime$
   #71 = Utf8               Lscala/runtime/ScalaRunTime$;
   #72 = NameAndType        #17:#71       // MODULE$:Lscala/runtime/ScalaRunTime$;
   #73 = Fieldref           #70.#72       // scala/runtime/ScalaRunTime$.MODULE$:Lscala/runtime/ScalaRunTime$;
   #74 = Utf8               typedProductIterator
   #75 = Utf8               (Lscala/Product;)Lscala/collection/Iterator;
   #76 = NameAndType        #74:#75       // typedProductIterator:(Lscala/Product;)Lscala/collection/Iterator;
   #77 = Methodref          #70.#76       // scala/runtime/ScalaRunTime$.typedProductIterator:(Lscala/Product;)Lscala/collection/Iterator;
   #78 = Utf8               canEqual
   #79 = Utf8               (Ljava/lang/Object;)Z
   #80 = Utf8               Ljava/lang/Object;
   #81 = Utf8               productElementName
   #82 = Utf8               (I)Ljava/lang/String;
   #83 = String             #9            // f
   #84 = Utf8               java/lang/String
   #85 = Class              #84           // java/lang/String
   #86 = Utf8               hashCode
   #87 = Utf8               _hashCode
   #88 = Utf8               (Lscala/Product;)I
   #89 = NameAndType        #87:#88       // _hashCode:(Lscala/Product;)I
   #90 = Methodref          #70.#89       // scala/runtime/ScalaRunTime$._hashCode:(Lscala/Product;)I
   #91 = Utf8               toString
   #92 = Utf8               _toString
   #93 = Utf8               (Lscala/Product;)Ljava/lang/String;
   #94 = NameAndType        #92:#93       // _toString:(Lscala/Product;)Ljava/lang/String;
   #95 = Methodref          #70.#94       // scala/runtime/ScalaRunTime$._toString:(Lscala/Product;)Ljava/lang/String;
   #96 = Utf8               equals
   #97 = NameAndType        #96:#79       // equals:(Ljava/lang/Object;)Z
   #98 = Methodref          #65.#97       // java/lang/Object.equals:(Ljava/lang/Object;)Z
   #99 = NameAndType        #78:#79       // canEqual:(Ljava/lang/Object;)Z
  #100 = Methodref          #2.#99        // argonaut/CursorOpDeleteGoField.canEqual:(Ljava/lang/Object;)Z
  #101 = Utf8               ()V
  #102 = NameAndType        #43:#101      // "<init>":()V
  #103 = Methodref          #4.#102       // argonaut/CursorOpElement."<init>":()V
  #104 = Utf8               Code
  #105 = Utf8               Signature
  #106 = Utf8               MethodParameters
  #107 = Utf8               LineNumberTable
  #108 = Utf8               LocalVariableTable
  #109 = Utf8               StackMapTable
  #110 = Utf8               SourceFile
  #111 = Utf8               RuntimeVisibleAnnotations
  #112 = Utf8               ScalaInlineInfo
  #113 = Utf8               ScalaSig
{
  private final java.lang.String f;
    descriptor: Ljava/lang/String;
    flags: (0x0012) ACC_PRIVATE, ACC_FINAL

  public static scala.Option<java.lang.String> unapply(argonaut.CursorOpDeleteGoField);
    descriptor: (Largonaut/CursorOpDeleteGoField;)Lscala/Option;
    flags: (0x0009) ACC_PUBLIC, ACC_STATIC
    Code:
      stack=2, locals=1, args_size=1
         0: getstatic     #20                 // Field argonaut/CursorOpDeleteGoField$.MODULE$:Largonaut/CursorOpDeleteGoField$;
         3: aload_0
         4: invokevirtual #22                 // Method argonaut/CursorOpDeleteGoField$.unapply:(Largonaut/CursorOpDeleteGoField;)Lscala/Option;
         7: areturn
    Signature: #13                          // (Largonaut/CursorOpDeleteGoField;)Lscala/Option<Ljava/lang/String;>;
    MethodParameters:
      Name                           Flags
      x$0                            final

  public static argonaut.CursorOpDeleteGoField apply(java.lang.String);
    descriptor: (Ljava/lang/String;)Largonaut/CursorOpDeleteGoField;
    flags: (0x0009) ACC_PUBLIC, ACC_STATIC
    Code:
      stack=2, locals=1, args_size=1
         0: getstatic     #20                 // Field argonaut/CursorOpDeleteGoField$.MODULE$:Largonaut/CursorOpDeleteGoField$;
         3: aload_0
         4: invokevirtual #26                 // Method argonaut/CursorOpDeleteGoField$.apply:(Ljava/lang/String;)Largonaut/CursorOpDeleteGoField;
         7: areturn
    MethodParameters:
      Name                           Flags
      f                              final

  public static <A extends java.lang.Object> scala.Function1<java.lang.String, A> andThen(scala.Function1<argonaut.CursorOpDeleteGoField, A>);
    descriptor: (Lscala/Function1;)Lscala/Function1;
    flags: (0x0009) ACC_PUBLIC, ACC_STATIC
    Code:
      stack=2, locals=1, args_size=1
         0: getstatic     #20                 // Field argonaut/CursorOpDeleteGoField$.MODULE$:Largonaut/CursorOpDeleteGoField$;
         3: aload_0
         4: invokevirtual #32                 // Method argonaut/CursorOpDeleteGoField$.andThen:(Lscala/Function1;)Lscala/Function1;
         7: areturn
    Signature: #29                          // <A:Ljava/lang/Object;>(Lscala/Function1<Largonaut/CursorOpDeleteGoField;TA;>;)Lscala/Function1<Ljava/lang/String;TA;>;
    MethodParameters:
      Name                           Flags
      g                              final

  public static <A extends java.lang.Object> scala.Function1<A, argonaut.CursorOpDeleteGoField> compose(scala.Function1<A, java.lang.String>);
    descriptor: (Lscala/Function1;)Lscala/Function1;
    flags: (0x0009) ACC_PUBLIC, ACC_STATIC
    Code:
      stack=2, locals=1, args_size=1
         0: getstatic     #20                 // Field argonaut/CursorOpDeleteGoField$.MODULE$:Largonaut/CursorOpDeleteGoField$;
         3: aload_0
         4: invokevirtual #36                 // Method argonaut/CursorOpDeleteGoField$.compose:(Lscala/Function1;)Lscala/Function1;
         7: areturn
    Signature: #34                          // <A:Ljava/lang/Object;>(Lscala/Function1<TA;Ljava/lang/String;>;)Lscala/Function1<TA;Largonaut/CursorOpDeleteGoField;>;
    MethodParameters:
      Name                           Flags
      g                              final

  public java.lang.String f();
    descriptor: ()Ljava/lang/String;
    flags: (0x0001) ACC_PUBLIC
    Code:
      stack=1, locals=1, args_size=1
         0: aload_0
         1: getfield      #39                 // Field f:Ljava/lang/String;
         4: areturn
      LineNumberTable:
        line 63: 0
      LocalVariableTable:
        Start  Length  Slot  Name   Signature
            0       5     0  this   Largonaut/CursorOpDeleteGoField;

  public argonaut.CursorOpDeleteGoField copy(java.lang.String);
    descriptor: (Ljava/lang/String;)Largonaut/CursorOpDeleteGoField;
    flags: (0x0001) ACC_PUBLIC
    Code:
      stack=3, locals=2, args_size=2
         0: new           #2                  // class argonaut/CursorOpDeleteGoField
         3: dup
         4: aload_1
         5: invokespecial #46                 // Method "<init>":(Ljava/lang/String;)V
         8: areturn
      LineNumberTable:
        line 63: 0
      LocalVariableTable:
        Start  Length  Slot  Name   Signature
            0       9     0  this   Largonaut/CursorOpDeleteGoField;
            0       9     1     f   Ljava/lang/String;
    MethodParameters:
      Name                           Flags
      f                              final

  public java.lang.String copy$default$1();
    descriptor: ()Ljava/lang/String;
    flags: (0x0001) ACC_PUBLIC
    Code:
      stack=1, locals=1, args_size=1
         0: aload_0
         1: invokevirtual #49                 // Method f:()Ljava/lang/String;
         4: areturn
      LineNumberTable:
        line 63: 0
      LocalVariableTable:
        Start  Length  Slot  Name   Signature
            0       5     0  this   Largonaut/CursorOpDeleteGoField;

  public java.lang.String productPrefix();
    descriptor: ()Ljava/lang/String;
    flags: (0x0001) ACC_PUBLIC
    Code:
      stack=1, locals=1, args_size=1
         0: ldc           #52                 // String CursorOpDeleteGoField
         2: areturn
      LineNumberTable:
        line 63: 0
      LocalVariableTable:
        Start  Length  Slot  Name   Signature
            0       3     0  this   Largonaut/CursorOpDeleteGoField;

  public int productArity();
    descriptor: ()I
    flags: (0x0001) ACC_PUBLIC
    Code:
      stack=1, locals=1, args_size=1
         0: iconst_1
         1: ireturn
      LineNumberTable:
        line 63: 0
      LocalVariableTable:
        Start  Length  Slot  Name   Signature
            0       2     0  this   Largonaut/CursorOpDeleteGoField;

  public java.lang.Object productElement(int);
    descriptor: (I)Ljava/lang/Object;
    flags: (0x0001) ACC_PUBLIC
    Code:
      stack=1, locals=3, args_size=2
         0: iload_1
         1: istore_2
         2: iload_2
         3: tableswitch   { // 0 to 0
                       0: 20
                 default: 27
            }
        20: aload_0
        21: invokevirtual #49                 // Method f:()Ljava/lang/String;
        24: goto          34
        27: iload_1
        28: invokestatic  #62                 // Method scala/runtime/Statics.ioobe:(I)Ljava/lang/Object;
        31: goto          34
        34: areturn
      StackMapTable: number_of_entries = 3
        frame_type = 252 /* append */
          offset_delta = 20
          locals = [ int ]
        frame_type = 6 /* same */
        frame_type = 70 /* same_locals_1_stack_item */
          stack = [ class java/lang/Object ]
      LineNumberTable:
        line 63: 0
      LocalVariableTable:
        Start  Length  Slot  Name   Signature
            0      35     0  this   Largonaut/CursorOpDeleteGoField;
            0      35     1   x$1   I
    MethodParameters:
      Name                           Flags
      x$1                            final

  public scala.collection.Iterator<java.lang.Object> productIterator();
    descriptor: ()Lscala/collection/Iterator;
    flags: (0x0001) ACC_PUBLIC
    Code:
      stack=2, locals=1, args_size=1
         0: getstatic     #73                 // Field scala/runtime/ScalaRunTime$.MODULE$:Lscala/runtime/ScalaRunTime$;
         3: aload_0
         4: invokevirtual #77                 // Method scala/runtime/ScalaRunTime$.typedProductIterator:(Lscala/Product;)Lscala/collection/Iterator;
         7: areturn
      LineNumberTable:
        line 63: 0
      LocalVariableTable:
        Start  Length  Slot  Name   Signature
            0       8     0  this   Largonaut/CursorOpDeleteGoField;
    Signature: #68                          // ()Lscala/collection/Iterator<Ljava/lang/Object;>;

  public boolean canEqual(java.lang.Object);
    descriptor: (Ljava/lang/Object;)Z
    flags: (0x0001) ACC_PUBLIC
    Code:
      stack=1, locals=2, args_size=2
         0: aload_1
         1: instanceof    #2                  // class argonaut/CursorOpDeleteGoField
         4: ireturn
      LineNumberTable:
        line 63: 0
      LocalVariableTable:
        Start  Length  Slot  Name   Signature
            0       5     0  this   Largonaut/CursorOpDeleteGoField;
            0       5     1   x$1   Ljava/lang/Object;
    MethodParameters:
      Name                           Flags
      x$1                            final

  public java.lang.String productElementName(int);
    descriptor: (I)Ljava/lang/String;
    flags: (0x0001) ACC_PUBLIC
    Code:
      stack=1, locals=3, args_size=2
         0: iload_1
         1: istore_2
         2: iload_2
         3: tableswitch   { // 0 to 0
                       0: 20
                 default: 25
            }
        20: ldc           #83                 // String f
        22: goto          35
        25: iload_1
        26: invokestatic  #62                 // Method scala/runtime/Statics.ioobe:(I)Ljava/lang/Object;
        29: checkcast     #85                 // class java/lang/String
        32: goto          35
        35: areturn
      StackMapTable: number_of_entries = 3
        frame_type = 252 /* append */
          offset_delta = 20
          locals = [ int ]
        frame_type = 4 /* same */
        frame_type = 73 /* same_locals_1_stack_item */
          stack = [ class java/lang/String ]
      LineNumberTable:
        line 63: 0
      LocalVariableTable:
        Start  Length  Slot  Name   Signature
            0      36     0  this   Largonaut/CursorOpDeleteGoField;
            0      36     1   x$1   I
    MethodParameters:
      Name                           Flags
      x$1                            final

  public int hashCode();
    descriptor: ()I
    flags: (0x0001) ACC_PUBLIC
    Code:
      stack=2, locals=1, args_size=1
         0: getstatic     #73                 // Field scala/runtime/ScalaRunTime$.MODULE$:Lscala/runtime/ScalaRunTime$;
         3: aload_0
         4: invokevirtual #90                 // Method scala/runtime/ScalaRunTime$._hashCode:(Lscala/Product;)I
         7: ireturn
      LineNumberTable:
        line 63: 0
      LocalVariableTable:
        Start  Length  Slot  Name   Signature
            0       8     0  this   Largonaut/CursorOpDeleteGoField;

  public java.lang.String toString();
    descriptor: ()Ljava/lang/String;
    flags: (0x0001) ACC_PUBLIC
    Code:
      stack=2, locals=1, args_size=1
         0: getstatic     #73                 // Field scala/runtime/ScalaRunTime$.MODULE$:Lscala/runtime/ScalaRunTime$;
         3: aload_0
         4: invokevirtual #95                 // Method scala/runtime/ScalaRunTime$._toString:(Lscala/Product;)Ljava/lang/String;
         7: areturn
      LineNumberTable:
        line 63: 0
      LocalVariableTable:
        Start  Length  Slot  Name   Signature
            0       8     0  this   Largonaut/CursorOpDeleteGoField;

  public boolean equals(java.lang.Object);
    descriptor: (Ljava/lang/Object;)Z
    flags: (0x0001) ACC_PUBLIC
    Code:
      stack=2, locals=6, args_size=2
         0: aload_0
         1: aload_1
         2: if_acmpeq     86
         5: aload_1
         6: astore_3
         7: aload_3
         8: instanceof    #2                  // class argonaut/CursorOpDeleteGoField
        11: ifeq          19
        14: iconst_1
        15: istore_2
        16: goto          27
        19: goto          22
        22: iconst_0
        23: istore_2
        24: goto          27
        27: iload_2
        28: ifeq          90
        31: aload_1
        32: checkcast     #2                  // class argonaut/CursorOpDeleteGoField
        35: astore        4
        37: aload_0
        38: invokevirtual #49                 // Method f:()Ljava/lang/String;
        41: aload         4
        43: invokevirtual #49                 // Method f:()Ljava/lang/String;
        46: astore        5
        48: dup
        49: ifnonnull     61
        52: pop
        53: aload         5
        55: ifnull        69
        58: goto          82
        61: aload         5
        63: invokevirtual #98                 // Method java/lang/Object.equals:(Ljava/lang/Object;)Z
        66: ifeq          82
        69: aload         4
        71: aload_0
        72: invokevirtual #100                // Method canEqual:(Ljava/lang/Object;)Z
        75: ifeq          82
        78: iconst_1
        79: goto          83
        82: iconst_0
        83: ifeq          90
        86: iconst_1
        87: goto          91
        90: iconst_0
        91: ireturn
      StackMapTable: number_of_entries = 10
        frame_type = 253 /* append */
          offset_delta = 19
          locals = [ top, class java/lang/Object ]
        frame_type = 2 /* same */
        frame_type = 255 /* full_frame */
          offset_delta = 4
          locals = [ class argonaut/CursorOpDeleteGoField, class java/lang/Object, int, class java/lang/Object ]
          stack = []
        frame_type = 255 /* full_frame */
          offset_delta = 33
          locals = [ class argonaut/CursorOpDeleteGoField, class java/lang/Object, int, class java/lang/Object, class argonaut/CursorOpDeleteGoField, class java/lang/String ]
          stack = [ class java/lang/String ]
        frame_type = 7 /* same */
        frame_type = 12 /* same */
        frame_type = 64 /* same_locals_1_stack_item */
          stack = [ int ]
        frame_type = 255 /* full_frame */
          offset_delta = 2
          locals = [ class argonaut/CursorOpDeleteGoField, class java/lang/Object ]
          stack = []
        frame_type = 253 /* append */
          offset_delta = 3
          locals = [ int, class java/lang/Object ]
        frame_type = 255 /* full_frame */
          offset_delta = 0
          locals = [ class argonaut/CursorOpDeleteGoField, class java/lang/Object ]
          stack = [ int ]
      LineNumberTable:
        line 63: 0
      LocalVariableTable:
        Start  Length  Slot  Name   Signature
            0      92     0  this   Largonaut/CursorOpDeleteGoField;
            0      92     1   x$1   Ljava/lang/Object;
    MethodParameters:
      Name                           Flags
      x$1                            final

  public argonaut.CursorOpDeleteGoField(java.lang.String);
    descriptor: (Ljava/lang/String;)V
    flags: (0x0001) ACC_PUBLIC
    Code:
      stack=2, locals=2, args_size=2
         0: aload_0
         1: aload_1
         2: putfield      #39                 // Field f:Ljava/lang/String;
         5: aload_0
         6: invokespecial #103                // Method argonaut/CursorOpElement."<init>":()V
         9: return
      LineNumberTable:
        line 63: 0
      LocalVariableTable:
        Start  Length  Slot  Name   Signature
            0      10     0  this   Largonaut/CursorOpDeleteGoField;
            0      10     1     f   Ljava/lang/String;
    MethodParameters:
      Name                           Flags
      f                              final
}
SourceFile: "CursorOpElement.scala"
RuntimeVisibleAnnotations:
  0: #6(#7=s#8)
    scala.reflect.ScalaSignature(
      bytes="\u0006\u0005\u0005]b\u0001\u0002\f\u0018\u0001jA\u0001\"\r\u0001\u0003\u0016\u0004%\tA\r\u0005\tw\u0001\u0011\t\u0012)A\u0005g!)A\b\u0001C\u0001{!9\u0001\tAA\u0001\n\u0003\t\u0005bB\"\u0001#\u0003%\t\u0001\u0012\u0005\b\u001f\u0002\t\t\u0011\"\u0011Q\u0011\u001dI\u0006!!A\u0005\u0002iCqA\u0018\u0001\u0002\u0002\u0013\u0005q\fC\u0004f\u0001\u0005\u0005I\u0011\t4\t\u000f5\u0004\u0011\u0011!C\u0001]\"91\u000fAA\u0001\n\u0003\"\bb\u0002<\u0001\u0003\u0003%\te\u001e\u0005\bq\u0002\t\t\u0011\"\u0011z\u0011\u001dQ\b!!A\u0005Bm<q!`\f\u0002\u0002#\u0005aPB\u0004\u0017/\u0005\u0005\t\u0012A@\t\rq\u0002B\u0011AA\f\u0011\u001dA\b#!A\u0005FeD\u0011\"!\u0007\u0011\u0003\u0003%\t)a\u0007\t\u0013\u0005}\u0001#!A\u0005\u0002\u0006\u0005\u0002\"CA\u0017!\u0005\u0005I\u0011BA\u0018\u0005U\u0019UO]:pe>\u0003H)\u001a7fi\u0016<uNR5fY\u0012T\u0011\u0001G\u0001\tCJ<wN\\1vi\u000e\u00011\u0003\u0002\u0001\u001c?\u0015\u0002\"\u0001H\u000f\u000e\u0003]I!AH\f\u0003\u001f\r+(o]8s\u001fB,E.Z7f]R\u0004\"\u0001I\u0012\u000e\u0003\u0005R\u0011AI\u0001\u0006g\u000e\fG.Y\u0005\u0003I\u0005\u0012q\u0001\u0015:pIV\u001cG\u000f\u0005\u0002\']9\u0011q\u0005\f\b\u0003Q-j\u0011!\u000b\u0006\u0003Ue\ta\u0001\u0010:p_Rt\u0014\"\u0001\u0012\n\u00055\n\u0013a\u00029bG.\fw-Z\u0005\u0003_A\u0012AbU3sS\u0006d\u0017N_1cY\u0016T!!L\u0011\u0002\u0003\u0019,\u0012a\r\t\u0003i]r!\u0001H\u001b\n\u0005Y:\u0012\u0001\u0002&t_:L!\u0001O\u001d\u0003\u0013)\u001bxN\u001c$jK2$\u0017B\u0001\u001e\u0018\u0005\u0015Q5o\u001c8t\u0003\t1\u0007%\u0001\u0004=S:LGO\u0010\u000b\u0003}}\u0002\"\u0001\b\u0001\t\u000bE\u001a\u0001\u0019A\u001a\u0002\t\r|\u0007/\u001f\u000b\u0003}\tCq!\r\u0003\u0011\u0002\u0003\u00071\'\u0001\bd_BLH\u0005Z3gCVdG\u000fJ\u0019\u0016\u0003\u0015S#a\r$,\u0003\u001d\u0003\"\u0001S\'\u000e\u0003%S!AS&\u0002\u0013Ut7\r[3dW\u0016$\'B\u0001\'\"\u0003)\tgN\\8uCRLwN\\\u0005\u0003\u001d&\u0013\u0011#\u001e8dQ\u0016\u001c7.\u001a3WCJL\u0017M\\2f\u00035\u0001(o\u001c3vGR\u0004&/\u001a4jqV\t\u0011\u000b\u0005\u0002S/6\t1K\u0003\u0002U+\u0006!A.\u00198h\u0015\u00051\u0016\u0001\u00026bm\u0006L!\u0001W*\u0003\rM#(/\u001b8h\u00031\u0001(o\u001c3vGR\f%/\u001b;z+\u0005Y\u0006C\u0001\u0011]\u0013\ti\u0016EA\u0002J]R\fa\u0002\u001d:pIV\u001cG/\u00127f[\u0016tG\u000f\u0006\u0002aGB\u0011\u0001%Y\u0005\u0003E\u0006\u00121!\u00118z\u0011\u001d!\u0007\"!AA\u0002m\u000b1\u0001\u001f\u00132\u0003=\u0001(o\u001c3vGRLE/\u001a:bi>\u0014X#A4\u0011\u0007!\\\u0007-D\u0001j\u0015\tQ\u0017%\u0001\u0006d_2dWm\u0019;j_:L!\u0001\\5\u0003\u0011%#XM]1u_J\f\u0001bY1o\u000bF,\u0018\r\u001c\u000b\u0003_J\u0004\"\u0001\t9\n\u0005E\f#a\u0002\"p_2,\u0017M\u001c\u0005\bI*\t\t\u00111\u0001a\u0003I\u0001(o\u001c3vGR,E.Z7f]Rt\u0015-\\3\u0015\u0005E+\bb\u00023\f\u0003\u0003\u0005\raW\u0001\tQ\u0006\u001c\bnQ8eKR\t1,\u0001\u0005u_N#(/\u001b8h)\u0005\t\u0016AB3rk\u0006d7\u000f\u0006\u0002py\"9AMDA\u0001\u0002\u0004\u0001\u0017!F\"veN|\'o\u00149EK2,G/Z$p\r&,G\u000e\u001a\t\u00039A\u0019R\u0001EA\u0001\u0003\u001b\u0001b!a\u0001\u0002\nMrTBAA\u0003\u0015\r\t9!I\u0001\beVtG/[7f\u0013\u0011\tY!!\u0002\u0003#\u0005\u00137\u000f\u001e:bGR4UO\\2uS>t\u0017\u0007\u0005\u0003\u0002\u0010\u0005UQBAA\t\u0015\r\t\u0019\"V\u0001\u0003S>L1aLA\t)\u0005q\u0018!B1qa2LHc\u0001 \u0002\u001e!)\u0011g\u0005a\u0001g\u00059QO\\1qa2LH\u0003BA\u0012\u0003S\u0001B\u0001IA\u0013g%\u0019\u0011qE\u0011\u0003\r=\u0003H/[8o\u0011!\tY\u0003FA\u0001\u0002\u0004q\u0014a\u0001=%a\u0005aqO]5uKJ+\u0007\u000f\\1dKR\u0011\u0011\u0011\u0007\t\u0004%\u0006M\u0012bAA\u001b\'\n1qJ\u00196fGR\u0004"
    )
  ScalaInlineInfo: length = 0x45 (unknown attribute)
   01 00 00 0D 00 2B 00 2C 00 00 4E 00 4F 00 00 2A
   00 18 00 00 2F 00 25 00 00 60 00 4F 00 00 09 00
   25 00 00 56 00 36 00 00 35 00 36 00 00 37 00 38
   00 00 51 00 52 00 00 42 00 43 00 00 32 00 25 00
   00 5B 00 25 00
  ScalaSig: length = 0x3 (unknown attribute)
   05 02 00
