Classfile /Users/mw/Projects/slang-braindump/.jar/jar11/assemble/slang-braindump/assemble/content/argonaut/CursorHistory.class
  Last modified May 29, 2022; size 7672 bytes
  SHA-256 checksum 4b0dc2006cde69d7fda08ca99f5b5b8782e66ad5d86e126fc21e3a0a4bd3a2bc
  Compiled from "CursorHistory.scala"
public class argonaut.CursorHistory implements scala.Product,java.io.Serializable
  minor version: 0
  major version: 52
  flags: (0x0021) ACC_PUBLIC, ACC_SUPER
  this_class: #2                          // argonaut/CursorHistory
  super_class: #4                         // java/lang/Object
  interfaces: 2, fields: 1, methods: 24, attributes: 4
Constant pool:
    #1 = Utf8               argonaut/CursorHistory
    #2 = Class              #1            // argonaut/CursorHistory
    #3 = Utf8               java/lang/Object
    #4 = Class              #3            // java/lang/Object
    #5 = Utf8               scala/Product
    #6 = Class              #5            // scala/Product
    #7 = Utf8               java/io/Serializable
    #8 = Class              #7            // java/io/Serializable
    #9 = Utf8               CursorHistory.scala
   #10 = Utf8               Lscala/reflect/ScalaSignature;
   #11 = Utf8               bytes
   #12 = Utf8               \u0006\u0005\u0005Ee\u0001B\u000e\u001d\u0001~A\u0001\"\u000e\u0001\u0003\u0016\u0004%\tA\u000e\u0005\t}\u0001\u0011\t\u0012)A\u0005o!)q\b\u0001C\u0001\u0001\")1\t\u0001C\u0001\t\")\u0001\n\u0001C\u0001\u0013\")A\n\u0001C\u0001\u001b\")\u0011\r\u0001C\u0001E\")Q\r\u0001C\u0001M\")\u0001\u000e\u0001C\u0001S\")1\u000e\u0001C!Y\"9Q\u000fAA\u0001\n\u00031\bb\u0002=\u0001#\u0003%\t!\u001f\u0005\n\u0003\u0013\u0001\u0011\u0011!C!\u0003\u0017A\u0011\"a\u0007\u0001\u0003\u0003%\t!!\b\t\u0013\u0005\u0015\u0002!!A\u0005\u0002\u0005\u001d\u0002\"CA\u001a\u0001\u0005\u0005I\u0011IA\u001b\u0011%\t\u0019\u0005AA\u0001\n\u0003\t)\u0005C\u0005\u0002P\u0001\t\t\u0011\"\u0011\u0002R!I\u0011Q\u000b\u0001\u0002\u0002\u0013\u0005\u0013q\u000b\u0005\n\u00033\u0002\u0011\u0011!C!\u00037:q!a\u0018\u001d\u0011\u0003\t\tG\u0002\u0004\u001c9!\u0005\u00111\r\u0005\u0007\u007fY!\t!!\u001e\t\u0013\u0005]d#!A\u0005\u0002\u0006e\u0004\"CA?-\u0005\u0005I\u0011QA@\u0011%\t9IFA\u0001\n\u0013\tIIA\u0007DkJ\u001cxN\u001d%jgR|\'/\u001f\u0006\u0002;\u0005A\u0011M]4p]\u0006,Ho\u0001\u0001\u0014\t\u0001\u0001c%\u000b\t\u0003C\u0011j\u0011A\t\u0006\u0002G\u0005)1oY1mC&\u0011QE\t\u0002\u0007\u0003:L(+\u001a4\u0011\u0005\u0005:\u0013B\u0001\u0015#\u0005\u001d\u0001&o\u001c3vGR\u0004\"A\u000b\u001a\u000f\u0005-\u0002dB\u0001\u00170\u001b\u0005i#B\u0001\u0018\u001f\u0003\u0019a$o\\8u}%\t1%\u0003\u00022E\u00059\u0001/Y2lC\u001e,\u0017BA\u001a5\u00051\u0019VM]5bY&T\u0018M\u00197f\u0015\t\t$%\u0001\u0004u_2K7\u000f^\u000b\u0002oA\u0019!\u0006\u000f\u001e\n\u0005e\"$\u0001\u0002\'jgR\u0004\"a\u000f\u001f\u000e\u0003qI!!\u0010\u000f\u0003\u0011\r+(o]8s\u001fB\fq\u0001^8MSN$\b%\u0001\u0004=S:LGO\u0010\u000b\u0003\u0003\n\u0003\"a\u000f\u0001\t\u000bU\u001a\u0001\u0019A\u001c\u0002\t!,\u0017\rZ\u000b\u0002\u000bB\u0019\u0011E\u0012\u001e\n\u0005\u001d\u0013#AB(qi&|g.\u0001\u0006%a2,8\u000f\n9mkN$\"!\u0011&\t\u000b-+\u0001\u0019A!\u0002\u0003!\fa\"Y2veN|\'/\u00127f[\u0016tG\u000f\u0006\u0003O#jc\u0006CA\u001eP\u0013\t\u0001FDA\u0004B\u0007V\u00148o\u001c:\t\u000bI3\u0001\u0019A*\u0002\u0003\u0019\u0004B!\t+W3&\u0011QK\t\u0002\n\rVt7\r^5p]F\u0002\"aO,\n\u0005ac\"AB\"veN|\'\u000fE\u0002\"\rZCQa\u0017\u0004A\u0002Y\u000b\u0011a\u0019\u0005\u0006;\u001a\u0001\rAX\u0001\u0002KB\u00111hX\u0005\u0003Ar\u0011qbQ;sg>\u0014x\n]#mK6,g\u000e^\u0001\fIAdWo\u001d\u0013d_2|g\u000e\u0006\u0002BG\")Am\u0002a\u0001u\u0005\tq.A\u0007gC&dW\rZ!DkJ\u001cxN\u001d\u000b\u0003\u001d\u001eDQa\u0017\u0005A\u0002Y\u000bq!Y2veN|\'\u000f\u0006\u0002OU\")1,\u0003a\u0001-\u0006AAo\\*ue&tw\rF\u0001n!\tq\'O\u0004\u0002paB\u0011AFI\u0005\u0003c\n\na\u0001\u0015:fI\u00164\u0017BA:u\u0005\u0019\u0019FO]5oO*\u0011\u0011OI\u0001\u0005G>\u0004\u0018\u0010\u0006\u0002Bo\"9Qg\u0003I\u0001\u0002\u00049\u0014AD2paf$C-\u001a4bk2$H%M\u000b\u0002u*\u0012qg_\u0016\u0002yB\u0019Q0!\u0002\u000e\u0003yT1a`A\u0001\u0003%)hn\u00195fG.,GMC\u0002\u0002\u0004\t\n!\"\u00198o_R\fG/[8o\u0013\r\t9A \u0002\u0012k:\u001c\u0007.Z2lK\u00124\u0016M]5b]\u000e,\u0017!\u00049s_\u0012,8\r\u001e)sK\u001aL\u00070\u0006\u0002\u0002\u000eA!\u0011qBA\r\u001b\t\t\tB\u0003\u0003\u0002\u0014\u0005U\u0011\u0001\u00027b]\u001eT!!a\u0006\u0002\t)\fg/Y\u0005\u0004g\u0006E\u0011\u0001\u00049s_\u0012,8\r^!sSRLXCAA\u0010!\r\t\u0013\u0011E\u0005\u0004\u0003G\u0011#aA%oi\u0006q\u0001O]8ek\u000e$X\t\\3nK:$H\u0003BA\u0015\u0003_\u00012!IA\u0016\u0013\r\tiC\t\u0002\u0004\u0003:L\b\"CA\u0019\u001f\u0005\u0005\t\u0019AA\u0010\u0003\rAH%M\u0001\u0010aJ|G-^2u\u0013R,\'/\u0019;peV\u0011\u0011q\u0007\t\u0007\u0003s\ty$!\u000b\u000e\u0005\u0005m\"bAA\u001fE\u0005Q1m\u001c7mK\u000e$\u0018n\u001c8\n\t\u0005\u0005\u00131\b\u0002\t\u0013R,\'/\u0019;pe\u0006A1-\u00198FcV\fG\u000e\u0006\u0003\u0002H\u00055\u0003cA\u0011\u0002J%\u0019\u00111\n\u0012\u0003\u000f\t{w\u000e\\3b]\"I\u0011\u0011G\t\u0002\u0002\u0003\u0007\u0011\u0011F\u0001\u0013aJ|G-^2u\u000b2,W.\u001a8u\u001d\u0006lW\r\u0006\u0003\u0002\u000e\u0005M\u0003\"CA\u0019%\u0005\u0005\t\u0019AA\u0010\u0003!A\u0017m\u001d5D_\u0012,GCAA\u0010\u0003\u0019)\u0017/^1mgR!\u0011qIA/\u0011%\t\t\u0004FA\u0001\u0002\u0004\tI#A\u0007DkJ\u001cxN\u001d%jgR|\'/\u001f\t\u0003wY\u0019bA\u0006\u0011\u0002f\u0005-\u0004cA\u001e\u0002h%\u0019\u0011\u0011\u000e\u000f\u0003\u001d\r+(o]8s\u0011&\u001cHo\u001c:zgB!\u0011QNA:\u001b\t\tyG\u0003\u0003\u0002r\u0005U\u0011AA5p\u0013\r\u0019\u0014q\u000e\u000b\u0003\u0003C\nQ!\u00199qYf$2!QA>\u0011\u0015)\u0004\u00041\u00018\u0003\u001d)h.\u00199qYf$B!!!\u0002\u0004B\u0019\u0011ER\u001c\t\u0011\u0005\u0015\u0015$!AA\u0002\u0005\u000b1\u0001\u001f\u00131\u000319(/\u001b;f%\u0016\u0004H.Y2f)\t\tY\t\u0005\u0003\u0002\u0010\u00055\u0015\u0002BAH\u0003#\u0011aa\u00142kK\u000e$\b
   #13 = Utf8               toList
   #14 = Utf8               Lscala/collection/immutable/List;
   #15 = Utf8               Lscala/collection/immutable/List<Largonaut/CursorOp;>;
   #16 = Utf8               unapply
   #17 = Utf8               (Largonaut/CursorHistory;)Lscala/Option;
   #18 = Utf8               (Largonaut/CursorHistory;)Lscala/Option<Lscala/collection/immutable/List<Largonaut/CursorOp;>;>;
   #19 = Utf8               x$0
   #20 = Utf8               argonaut/CursorHistory$
   #21 = Class              #20           // argonaut/CursorHistory$
   #22 = Utf8               MODULE$
   #23 = Utf8               Largonaut/CursorHistory$;
   #24 = NameAndType        #22:#23       // MODULE$:Largonaut/CursorHistory$;
   #25 = Fieldref           #21.#24       // argonaut/CursorHistory$.MODULE$:Largonaut/CursorHistory$;
   #26 = NameAndType        #16:#17       // unapply:(Largonaut/CursorHistory;)Lscala/Option;
   #27 = Methodref          #21.#26       // argonaut/CursorHistory$.unapply:(Largonaut/CursorHistory;)Lscala/Option;
   #28 = Utf8               apply
   #29 = Utf8               (Lscala/collection/immutable/List;)Largonaut/CursorHistory;
   #30 = Utf8               (Lscala/collection/immutable/List<Largonaut/CursorOp;>;)Largonaut/CursorHistory;
   #31 = NameAndType        #28:#29       // apply:(Lscala/collection/immutable/List;)Largonaut/CursorHistory;
   #32 = Methodref          #21.#31       // argonaut/CursorHistory$.apply:(Lscala/collection/immutable/List;)Largonaut/CursorHistory;
   #33 = Utf8               start
   #34 = Utf8               (Largonaut/CursorOp;)Largonaut/CursorHistory;
   #35 = Utf8               e
   #36 = NameAndType        #33:#34       // start:(Largonaut/CursorOp;)Largonaut/CursorHistory;
   #37 = Methodref          #21.#36       // argonaut/CursorHistory$.start:(Largonaut/CursorOp;)Largonaut/CursorHistory;
   #38 = Utf8               empty
   #39 = Utf8               ()Largonaut/CursorHistory;
   #40 = NameAndType        #38:#39       // empty:()Largonaut/CursorHistory;
   #41 = Methodref          #21.#40       // argonaut/CursorHistory$.empty:()Largonaut/CursorHistory;
   #42 = Utf8               productElementNames
   #43 = Utf8               ()Lscala/collection/Iterator;
   #44 = Utf8               ()Lscala/collection/Iterator<Ljava/lang/String;>;
   #45 = Utf8               productElementNames$
   #46 = Utf8               (Lscala/Product;)Lscala/collection/Iterator;
   #47 = NameAndType        #45:#46       // productElementNames$:(Lscala/Product;)Lscala/collection/Iterator;
   #48 = InterfaceMethodref #6.#47        // scala/Product.productElementNames$:(Lscala/Product;)Lscala/collection/Iterator;
   #49 = Utf8               this
   #50 = Utf8               Largonaut/CursorHistory;
   #51 = Utf8               ()Lscala/collection/immutable/List;
   #52 = Utf8               ()Lscala/collection/immutable/List<Largonaut/CursorOp;>;
   #53 = NameAndType        #13:#14       // toList:Lscala/collection/immutable/List;
   #54 = Fieldref           #2.#53        // argonaut/CursorHistory.toList:Lscala/collection/immutable/List;
   #55 = Utf8               head
   #56 = Utf8               ()Lscala/Option;
   #57 = Utf8               ()Lscala/Option<Largonaut/CursorOp;>;
   #58 = NameAndType        #13:#51       // toList:()Lscala/collection/immutable/List;
   #59 = Methodref          #2.#58        // argonaut/CursorHistory.toList:()Lscala/collection/immutable/List;
   #60 = Utf8               scala/collection/immutable/List
   #61 = Class              #60           // scala/collection/immutable/List
   #62 = Utf8               headOption
   #63 = NameAndType        #62:#56       // headOption:()Lscala/Option;
   #64 = Methodref          #61.#63       // scala/collection/immutable/List.headOption:()Lscala/Option;
   #65 = Utf8               $plus$plus
   #66 = Utf8               (Largonaut/CursorHistory;)Largonaut/CursorHistory;
   #67 = Utf8               h
   #68 = Utf8               (Lscala/collection/IterableOnce;)Ljava/lang/Object;
   #69 = NameAndType        #65:#68       // $plus$plus:(Lscala/collection/IterableOnce;)Ljava/lang/Object;
   #70 = Methodref          #61.#69       // scala/collection/immutable/List.$plus$plus:(Lscala/collection/IterableOnce;)Ljava/lang/Object;
   #71 = Utf8               <init>
   #72 = Utf8               (Lscala/collection/immutable/List;)V
   #73 = NameAndType        #71:#72       // "<init>":(Lscala/collection/immutable/List;)V
   #74 = Methodref          #2.#73        // argonaut/CursorHistory."<init>":(Lscala/collection/immutable/List;)V
   #75 = Utf8               acursorElement
   #76 = Utf8               (Lscala/Function1;Largonaut/Cursor;Largonaut/CursorOpElement;)Largonaut/ACursor;
   #77 = Utf8               (Lscala/Function1<Largonaut/Cursor;Lscala/Option<Largonaut/Cursor;>;>;Largonaut/Cursor;Largonaut/CursorOpElement;)Largonaut/ACursor;
   #78 = Utf8               f
   #79 = Utf8               c
   #80 = Utf8               scala/Function1
   #81 = Class              #80           // scala/Function1
   #82 = Utf8               (Ljava/lang/Object;)Ljava/lang/Object;
   #83 = NameAndType        #28:#82       // apply:(Ljava/lang/Object;)Ljava/lang/Object;
   #84 = InterfaceMethodref #81.#83       // scala/Function1.apply:(Ljava/lang/Object;)Ljava/lang/Object;
   #85 = Utf8               scala/Option
   #86 = Class              #85           // scala/Option
   #87 = Utf8               scala/None$
   #88 = Class              #87           // scala/None$
   #89 = Utf8               Lscala/None$;
   #90 = NameAndType        #22:#89       // MODULE$:Lscala/None$;
   #91 = Fieldref           #88.#90       // scala/None$.MODULE$:Lscala/None$;
   #92 = Utf8               equals
   #93 = Utf8               (Ljava/lang/Object;)Z
   #94 = NameAndType        #92:#93       // equals:(Ljava/lang/Object;)Z
   #95 = Methodref          #4.#94        // java/lang/Object.equals:(Ljava/lang/Object;)Z
   #96 = Utf8               argonaut/CursorOp$
   #97 = Class              #96           // argonaut/CursorOp$
   #98 = Utf8               Largonaut/CursorOp$;
   #99 = NameAndType        #22:#98       // MODULE$:Largonaut/CursorOp$;
  #100 = Fieldref           #97.#99       // argonaut/CursorOp$.MODULE$:Largonaut/CursorOp$;
  #101 = Utf8               failedOp
  #102 = Utf8               (Largonaut/CursorOpElement;)Largonaut/CursorOp;
  #103 = NameAndType        #101:#102     // failedOp:(Largonaut/CursorOpElement;)Largonaut/CursorOp;
  #104 = Methodref          #97.#103      // argonaut/CursorOp$.failedOp:(Largonaut/CursorOpElement;)Largonaut/CursorOp;
  #105 = Utf8               $plus$colon
  #106 = NameAndType        #105:#34      // $plus$colon:(Largonaut/CursorOp;)Largonaut/CursorHistory;
  #107 = Methodref          #2.#106       // argonaut/CursorHistory.$plus$colon:(Largonaut/CursorOp;)Largonaut/CursorHistory;
  #108 = Utf8               failedACursor
  #109 = Utf8               (Largonaut/Cursor;)Largonaut/ACursor;
  #110 = NameAndType        #108:#109     // failedACursor:(Largonaut/Cursor;)Largonaut/ACursor;
  #111 = Methodref          #2.#110       // argonaut/CursorHistory.failedACursor:(Largonaut/Cursor;)Largonaut/ACursor;
  #112 = Utf8               scala/Some
  #113 = Class              #112          // scala/Some
  #114 = Utf8               value
  #115 = Utf8               ()Ljava/lang/Object;
  #116 = NameAndType        #114:#115     // value:()Ljava/lang/Object;
  #117 = Methodref          #113.#116     // scala/Some.value:()Ljava/lang/Object;
  #118 = Utf8               argonaut/Cursor
  #119 = Class              #118          // argonaut/Cursor
  #120 = NameAndType        #28:#102      // apply:(Largonaut/CursorOpElement;)Largonaut/CursorOp;
  #121 = Methodref          #97.#120      // argonaut/CursorOp$.apply:(Largonaut/CursorOpElement;)Largonaut/CursorOp;
  #122 = Utf8               acursor
  #123 = NameAndType        #122:#109     // acursor:(Largonaut/Cursor;)Largonaut/ACursor;
  #124 = Methodref          #2.#123       // argonaut/CursorHistory.acursor:(Largonaut/Cursor;)Largonaut/ACursor;
  #125 = Utf8               scala/MatchError
  #126 = Class              #125          // scala/MatchError
  #127 = Utf8               (Ljava/lang/Object;)V
  #128 = NameAndType        #71:#127      // "<init>":(Ljava/lang/Object;)V
  #129 = Methodref          #126.#128     // scala/MatchError."<init>":(Ljava/lang/Object;)V
  #130 = Utf8               q
  #131 = Utf8               Largonaut/Cursor;
  #132 = Utf8               Lscala/Function1;
  #133 = Utf8               Largonaut/CursorOpElement;
  #134 = Utf8               argonaut/CursorOpElement
  #135 = Class              #134          // argonaut/CursorOpElement
  #136 = Utf8               argonaut/ACursor
  #137 = Class              #136          // argonaut/ACursor
  #138 = Utf8               o
  #139 = NameAndType        #105:#82      // $plus$colon:(Ljava/lang/Object;)Ljava/lang/Object;
  #140 = Methodref          #61.#139      // scala/collection/immutable/List.$plus$colon:(Ljava/lang/Object;)Ljava/lang/Object;
  #141 = Utf8               Largonaut/CursorOp;
  #142 = Utf8               argonaut/ACursor$
  #143 = Class              #142          // argonaut/ACursor$
  #144 = Utf8               Largonaut/ACursor$;
  #145 = NameAndType        #22:#144      // MODULE$:Largonaut/ACursor$;
  #146 = Fieldref           #143.#145     // argonaut/ACursor$.MODULE$:Largonaut/ACursor$;
  #147 = Utf8               argonaut/HCursor
  #148 = Class              #147          // argonaut/HCursor
  #149 = Utf8               (Largonaut/Cursor;Largonaut/CursorHistory;)V
  #150 = NameAndType        #71:#149      // "<init>":(Largonaut/Cursor;Largonaut/CursorHistory;)V
  #151 = Methodref          #148.#150     // argonaut/HCursor."<init>":(Largonaut/Cursor;Largonaut/CursorHistory;)V
  #152 = Utf8               fail
  #153 = Utf8               (Largonaut/HCursor;)Largonaut/ACursor;
  #154 = NameAndType        #152:#153     // fail:(Largonaut/HCursor;)Largonaut/ACursor;
  #155 = Methodref          #143.#154     // argonaut/ACursor$.fail:(Largonaut/HCursor;)Largonaut/ACursor;
  #156 = Utf8               ok
  #157 = NameAndType        #156:#153     // ok:(Largonaut/HCursor;)Largonaut/ACursor;
  #158 = Methodref          #143.#157     // argonaut/ACursor$.ok:(Largonaut/HCursor;)Largonaut/ACursor;
  #159 = Utf8               toString
  #160 = Utf8               ()Ljava/lang/String;
  #161 = Utf8               java/lang/StringBuilder
  #162 = Class              #161          // java/lang/StringBuilder
  #163 = Integer            15
  #164 = Utf8               (I)V
  #165 = NameAndType        #71:#164      // "<init>":(I)V
  #166 = Methodref          #162.#165     // java/lang/StringBuilder."<init>":(I)V
  #167 = Utf8               CursorHistory(
  #168 = String             #167          // CursorHistory(
  #169 = Utf8               append
  #170 = Utf8               (Ljava/lang/String;)Ljava/lang/StringBuilder;
  #171 = NameAndType        #169:#170     // append:(Ljava/lang/String;)Ljava/lang/StringBuilder;
  #172 = Methodref          #162.#171     // java/lang/StringBuilder.append:(Ljava/lang/String;)Ljava/lang/StringBuilder;
  #173 = NameAndType        #159:#160     // toString:()Ljava/lang/String;
  #174 = Methodref          #61.#173      // scala/collection/immutable/List.toString:()Ljava/lang/String;
  #175 = Utf8               )
  #176 = String             #175          // )
  #177 = Methodref          #162.#173     // java/lang/StringBuilder.toString:()Ljava/lang/String;
  #178 = Utf8               copy
  #179 = Utf8               copy$default$1
  #180 = Utf8               productPrefix
  #181 = Utf8               CursorHistory
  #182 = String             #181          // CursorHistory
  #183 = Utf8               productArity
  #184 = Utf8               ()I
  #185 = Utf8               productElement
  #186 = Utf8               (I)Ljava/lang/Object;
  #187 = Utf8               x$1
  #188 = Utf8               scala/runtime/Statics
  #189 = Class              #188          // scala/runtime/Statics
  #190 = Utf8               ioobe
  #191 = NameAndType        #190:#186     // ioobe:(I)Ljava/lang/Object;
  #192 = Methodref          #189.#191     // scala/runtime/Statics.ioobe:(I)Ljava/lang/Object;
  #193 = Utf8               I
  #194 = Utf8               productIterator
  #195 = Utf8               ()Lscala/collection/Iterator<Ljava/lang/Object;>;
  #196 = Utf8               scala/runtime/ScalaRunTime$
  #197 = Class              #196          // scala/runtime/ScalaRunTime$
  #198 = Utf8               Lscala/runtime/ScalaRunTime$;
  #199 = NameAndType        #22:#198      // MODULE$:Lscala/runtime/ScalaRunTime$;
  #200 = Fieldref           #197.#199     // scala/runtime/ScalaRunTime$.MODULE$:Lscala/runtime/ScalaRunTime$;
  #201 = Utf8               typedProductIterator
  #202 = NameAndType        #201:#46      // typedProductIterator:(Lscala/Product;)Lscala/collection/Iterator;
  #203 = Methodref          #197.#202     // scala/runtime/ScalaRunTime$.typedProductIterator:(Lscala/Product;)Lscala/collection/Iterator;
  #204 = Utf8               canEqual
  #205 = Utf8               Ljava/lang/Object;
  #206 = Utf8               productElementName
  #207 = Utf8               (I)Ljava/lang/String;
  #208 = String             #13           // toList
  #209 = Utf8               java/lang/String
  #210 = Class              #209          // java/lang/String
  #211 = Utf8               hashCode
  #212 = Utf8               _hashCode
  #213 = Utf8               (Lscala/Product;)I
  #214 = NameAndType        #212:#213     // _hashCode:(Lscala/Product;)I
  #215 = Methodref          #197.#214     // scala/runtime/ScalaRunTime$._hashCode:(Lscala/Product;)I
  #216 = NameAndType        #204:#93      // canEqual:(Ljava/lang/Object;)Z
  #217 = Methodref          #2.#216       // argonaut/CursorHistory.canEqual:(Ljava/lang/Object;)Z
  #218 = Utf8               (Lscala/collection/immutable/List<Largonaut/CursorOp;>;)V
  #219 = Utf8               ()V
  #220 = NameAndType        #71:#219      // "<init>":()V
  #221 = Methodref          #4.#220       // java/lang/Object."<init>":()V
  #222 = Utf8               $init$
  #223 = Utf8               (Lscala/Product;)V
  #224 = NameAndType        #222:#223     // $init$:(Lscala/Product;)V
  #225 = InterfaceMethodref #6.#224       // scala/Product.$init$:(Lscala/Product;)V
  #226 = Utf8               Signature
  #227 = Utf8               Code
  #228 = Utf8               MethodParameters
  #229 = Utf8               LineNumberTable
  #230 = Utf8               LocalVariableTable
  #231 = Utf8               StackMapTable
  #232 = Utf8               SourceFile
  #233 = Utf8               RuntimeVisibleAnnotations
  #234 = Utf8               ScalaInlineInfo
  #235 = Utf8               ScalaSig
{
  private final scala.collection.immutable.List<argonaut.CursorOp> toList;
    descriptor: Lscala/collection/immutable/List;
    flags: (0x0012) ACC_PRIVATE, ACC_FINAL
    Signature: #15                          // Lscala/collection/immutable/List<Largonaut/CursorOp;>;

  public static scala.Option<scala.collection.immutable.List<argonaut.CursorOp>> unapply(argonaut.CursorHistory);
    descriptor: (Largonaut/CursorHistory;)Lscala/Option;
    flags: (0x0009) ACC_PUBLIC, ACC_STATIC
    Code:
      stack=2, locals=1, args_size=1
         0: getstatic     #25                 // Field argonaut/CursorHistory$.MODULE$:Largonaut/CursorHistory$;
         3: aload_0
         4: invokevirtual #27                 // Method argonaut/CursorHistory$.unapply:(Largonaut/CursorHistory;)Lscala/Option;
         7: areturn
    Signature: #18                          // (Largonaut/CursorHistory;)Lscala/Option<Lscala/collection/immutable/List<Largonaut/CursorOp;>;>;
    MethodParameters:
      Name                           Flags
      x$0                            final

  public static argonaut.CursorHistory apply(scala.collection.immutable.List<argonaut.CursorOp>);
    descriptor: (Lscala/collection/immutable/List;)Largonaut/CursorHistory;
    flags: (0x0009) ACC_PUBLIC, ACC_STATIC
    Code:
      stack=2, locals=1, args_size=1
         0: getstatic     #25                 // Field argonaut/CursorHistory$.MODULE$:Largonaut/CursorHistory$;
         3: aload_0
         4: invokevirtual #32                 // Method argonaut/CursorHistory$.apply:(Lscala/collection/immutable/List;)Largonaut/CursorHistory;
         7: areturn
    Signature: #30                          // (Lscala/collection/immutable/List<Largonaut/CursorOp;>;)Largonaut/CursorHistory;
    MethodParameters:
      Name                           Flags
      toList                         final

  public static argonaut.CursorHistory start(argonaut.CursorOp);
    descriptor: (Largonaut/CursorOp;)Largonaut/CursorHistory;
    flags: (0x0009) ACC_PUBLIC, ACC_STATIC
    Code:
      stack=2, locals=1, args_size=1
         0: getstatic     #25                 // Field argonaut/CursorHistory$.MODULE$:Largonaut/CursorHistory$;
         3: aload_0
         4: invokevirtual #37                 // Method argonaut/CursorHistory$.start:(Largonaut/CursorOp;)Largonaut/CursorHistory;
         7: areturn
    MethodParameters:
      Name                           Flags
      e                              final

  public static argonaut.CursorHistory empty();
    descriptor: ()Largonaut/CursorHistory;
    flags: (0x0009) ACC_PUBLIC, ACC_STATIC
    Code:
      stack=1, locals=0, args_size=0
         0: getstatic     #25                 // Field argonaut/CursorHistory$.MODULE$:Largonaut/CursorHistory$;
         3: invokevirtual #41                 // Method argonaut/CursorHistory$.empty:()Largonaut/CursorHistory;
         6: areturn

  public scala.collection.Iterator<java.lang.String> productElementNames();
    descriptor: ()Lscala/collection/Iterator;
    flags: (0x0001) ACC_PUBLIC
    Code:
      stack=1, locals=1, args_size=1
         0: aload_0
         1: invokestatic  #48                 // InterfaceMethod scala/Product.productElementNames$:(Lscala/Product;)Lscala/collection/Iterator;
         4: areturn
      LineNumberTable:
        line 10: 0
      LocalVariableTable:
        Start  Length  Slot  Name   Signature
            0       5     0  this   Largonaut/CursorHistory;
    Signature: #44                          // ()Lscala/collection/Iterator<Ljava/lang/String;>;

  public scala.collection.immutable.List<argonaut.CursorOp> toList();
    descriptor: ()Lscala/collection/immutable/List;
    flags: (0x0001) ACC_PUBLIC
    Code:
      stack=1, locals=1, args_size=1
         0: aload_0
         1: getfield      #54                 // Field toList:Lscala/collection/immutable/List;
         4: areturn
      LineNumberTable:
        line 10: 0
      LocalVariableTable:
        Start  Length  Slot  Name   Signature
            0       5     0  this   Largonaut/CursorHistory;
    Signature: #52                          // ()Lscala/collection/immutable/List<Largonaut/CursorOp;>;

  public scala.Option<argonaut.CursorOp> head();
    descriptor: ()Lscala/Option;
    flags: (0x0001) ACC_PUBLIC
    Code:
      stack=1, locals=1, args_size=1
         0: aload_0
         1: invokevirtual #59                 // Method toList:()Lscala/collection/immutable/List;
         4: invokevirtual #64                 // Method scala/collection/immutable/List.headOption:()Lscala/Option;
         7: areturn
      LineNumberTable:
        line 12: 0
      LocalVariableTable:
        Start  Length  Slot  Name   Signature
            0       8     0  this   Largonaut/CursorHistory;
    Signature: #57                          // ()Lscala/Option<Largonaut/CursorOp;>;

  public argonaut.CursorHistory $plus$plus(argonaut.CursorHistory);
    descriptor: (Largonaut/CursorHistory;)Largonaut/CursorHistory;
    flags: (0x0001) ACC_PUBLIC
    Code:
      stack=4, locals=2, args_size=2
         0: new           #2                  // class argonaut/CursorHistory
         3: dup
         4: aload_0
         5: invokevirtual #59                 // Method toList:()Lscala/collection/immutable/List;
         8: aload_1
         9: invokevirtual #59                 // Method toList:()Lscala/collection/immutable/List;
        12: invokevirtual #70                 // Method scala/collection/immutable/List.$plus$plus:(Lscala/collection/IterableOnce;)Ljava/lang/Object;
        15: checkcast     #61                 // class scala/collection/immutable/List
        18: invokespecial #74                 // Method "<init>":(Lscala/collection/immutable/List;)V
        21: areturn
      LineNumberTable:
        line 18: 0
      LocalVariableTable:
        Start  Length  Slot  Name   Signature
            0      22     0  this   Largonaut/CursorHistory;
            0      22     1     h   Largonaut/CursorHistory;
    MethodParameters:
      Name                           Flags
      h                              final

  public argonaut.ACursor acursorElement(scala.Function1<argonaut.Cursor, scala.Option<argonaut.Cursor>>, argonaut.Cursor, argonaut.CursorOpElement);
    descriptor: (Lscala/Function1;Largonaut/Cursor;Largonaut/CursorOpElement;)Largonaut/ACursor;
    flags: (0x0001) ACC_PUBLIC
    Code:
      stack=3, locals=8, args_size=4
         0: aload_1
         1: aload_2
         2: invokeinterface #84,  2           // InterfaceMethod scala/Function1.apply:(Ljava/lang/Object;)Ljava/lang/Object;
         7: checkcast     #86                 // class scala/Option
        10: astore        5
        12: getstatic     #91                 // Field scala/None$.MODULE$:Lscala/None$;
        15: aload         5
        17: invokevirtual #95                 // Method java/lang/Object.equals:(Ljava/lang/Object;)Z
        20: ifeq          43
        23: aload_0
        24: getstatic     #100                // Field argonaut/CursorOp$.MODULE$:Largonaut/CursorOp$;
        27: aload_3
        28: invokevirtual #104                // Method argonaut/CursorOp$.failedOp:(Largonaut/CursorOpElement;)Largonaut/CursorOp;
        31: invokevirtual #107                // Method $plus$colon:(Largonaut/CursorOp;)Largonaut/CursorHistory;
        34: aload_2
        35: invokevirtual #111                // Method failedACursor:(Largonaut/Cursor;)Largonaut/ACursor;
        38: astore        4
        40: goto          105
        43: goto          46
        46: aload         5
        48: instanceof    #113                // class scala/Some
        51: ifeq          92
        54: aload         5
        56: checkcast     #113                // class scala/Some
        59: astore        6
        61: aload         6
        63: invokevirtual #117                // Method scala/Some.value:()Ljava/lang/Object;
        66: checkcast     #119                // class argonaut/Cursor
        69: astore        7
        71: aload_0
        72: getstatic     #100                // Field argonaut/CursorOp$.MODULE$:Largonaut/CursorOp$;
        75: aload_3
        76: invokevirtual #121                // Method argonaut/CursorOp$.apply:(Largonaut/CursorOpElement;)Largonaut/CursorOp;
        79: invokevirtual #107                // Method $plus$colon:(Largonaut/CursorOp;)Largonaut/CursorHistory;
        82: aload         7
        84: invokevirtual #124                // Method acursor:(Largonaut/Cursor;)Largonaut/ACursor;
        87: astore        4
        89: goto          105
        92: goto          95
        95: new           #126                // class scala/MatchError
        98: dup
        99: aload         5
       101: invokespecial #129                // Method scala/MatchError."<init>":(Ljava/lang/Object;)V
       104: athrow
       105: aload         4
       107: areturn
      StackMapTable: number_of_entries = 5
        frame_type = 253 /* append */
          offset_delta = 43
          locals = [ top, class scala/Option ]
        frame_type = 2 /* same */
        frame_type = 45 /* same */
        frame_type = 2 /* same */
        frame_type = 255 /* full_frame */
          offset_delta = 9
          locals = [ class argonaut/CursorHistory, class scala/Function1, class argonaut/Cursor, class argonaut/CursorOpElement, class argonaut/ACursor, class scala/Option ]
          stack = []
      LineNumberTable:
        line 21: 0
        line 22: 12
        line 23: 46
        line 21: 95
      LocalVariableTable:
        Start  Length  Slot  Name   Signature
           69      23     7     q   Largonaut/Cursor;
            0     108     0  this   Largonaut/CursorHistory;
            0     108     1     f   Lscala/Function1;
            0     108     2     c   Largonaut/Cursor;
            0     108     3     e   Largonaut/CursorOpElement;
    Signature: #77                          // (Lscala/Function1<Largonaut/Cursor;Lscala/Option<Largonaut/Cursor;>;>;Largonaut/Cursor;Largonaut/CursorOpElement;)Largonaut/ACursor;
    MethodParameters:
      Name                           Flags
      f                              final
      c                              final
      e                              final

  public argonaut.CursorHistory $plus$colon(argonaut.CursorOp);
    descriptor: (Largonaut/CursorOp;)Largonaut/CursorHistory;
    flags: (0x0001) ACC_PUBLIC
    Code:
      stack=4, locals=3, args_size=2
         0: new           #2                  // class argonaut/CursorHistory
         3: dup
         4: aload_1
         5: astore_2
         6: aload_0
         7: invokevirtual #59                 // Method toList:()Lscala/collection/immutable/List;
        10: aload_2
        11: invokevirtual #140                // Method scala/collection/immutable/List.$plus$colon:(Ljava/lang/Object;)Ljava/lang/Object;
        14: checkcast     #61                 // class scala/collection/immutable/List
        17: invokespecial #74                 // Method "<init>":(Lscala/collection/immutable/List;)V
        20: areturn
      LineNumberTable:
        line 31: 0
      LocalVariableTable:
        Start  Length  Slot  Name   Signature
            0      21     0  this   Largonaut/CursorHistory;
            0      21     1     o   Largonaut/CursorOp;
    MethodParameters:
      Name                           Flags
      o                              final

  public argonaut.ACursor failedACursor(argonaut.Cursor);
    descriptor: (Largonaut/Cursor;)Largonaut/ACursor;
    flags: (0x0001) ACC_PUBLIC
    Code:
      stack=5, locals=2, args_size=2
         0: getstatic     #146                // Field argonaut/ACursor$.MODULE$:Largonaut/ACursor$;
         3: new           #148                // class argonaut/HCursor
         6: dup
         7: aload_1
         8: aload_0
         9: invokespecial #151                // Method argonaut/HCursor."<init>":(Largonaut/Cursor;Largonaut/CursorHistory;)V
        12: invokevirtual #155                // Method argonaut/ACursor$.fail:(Largonaut/HCursor;)Largonaut/ACursor;
        15: areturn
      LineNumberTable:
        line 34: 0
      LocalVariableTable:
        Start  Length  Slot  Name   Signature
            0      16     0  this   Largonaut/CursorHistory;
            0      16     1     c   Largonaut/Cursor;
    MethodParameters:
      Name                           Flags
      c                              final

  public argonaut.ACursor acursor(argonaut.Cursor);
    descriptor: (Largonaut/Cursor;)Largonaut/ACursor;
    flags: (0x0001) ACC_PUBLIC
    Code:
      stack=5, locals=2, args_size=2
         0: getstatic     #146                // Field argonaut/ACursor$.MODULE$:Largonaut/ACursor$;
         3: new           #148                // class argonaut/HCursor
         6: dup
         7: aload_1
         8: aload_0
         9: invokespecial #151                // Method argonaut/HCursor."<init>":(Largonaut/Cursor;Largonaut/CursorHistory;)V
        12: invokevirtual #158                // Method argonaut/ACursor$.ok:(Largonaut/HCursor;)Largonaut/ACursor;
        15: areturn
      LineNumberTable:
        line 37: 0
      LocalVariableTable:
        Start  Length  Slot  Name   Signature
            0      16     0  this   Largonaut/CursorHistory;
            0      16     1     c   Largonaut/Cursor;
    MethodParameters:
      Name                           Flags
      c                              final

  public java.lang.String toString();
    descriptor: ()Ljava/lang/String;
    flags: (0x0001) ACC_PUBLIC
    Code:
      stack=3, locals=1, args_size=1
         0: new           #162                // class java/lang/StringBuilder
         3: dup
         4: ldc           #163                // int 15
         6: invokespecial #166                // Method java/lang/StringBuilder."<init>":(I)V
         9: ldc           #168                // String CursorHistory(
        11: invokevirtual #172                // Method java/lang/StringBuilder.append:(Ljava/lang/String;)Ljava/lang/StringBuilder;
        14: aload_0
        15: invokevirtual #59                 // Method toList:()Lscala/collection/immutable/List;
        18: invokevirtual #174                // Method scala/collection/immutable/List.toString:()Ljava/lang/String;
        21: invokevirtual #172                // Method java/lang/StringBuilder.append:(Ljava/lang/String;)Ljava/lang/StringBuilder;
        24: ldc           #176                // String )
        26: invokevirtual #172                // Method java/lang/StringBuilder.append:(Ljava/lang/String;)Ljava/lang/StringBuilder;
        29: invokevirtual #177                // Method java/lang/StringBuilder.toString:()Ljava/lang/String;
        32: areturn
      LineNumberTable:
        line 39: 0
      LocalVariableTable:
        Start  Length  Slot  Name   Signature
            0      33     0  this   Largonaut/CursorHistory;

  public argonaut.CursorHistory copy(scala.collection.immutable.List<argonaut.CursorOp>);
    descriptor: (Lscala/collection/immutable/List;)Largonaut/CursorHistory;
    flags: (0x0001) ACC_PUBLIC
    Code:
      stack=3, locals=2, args_size=2
         0: new           #2                  // class argonaut/CursorHistory
         3: dup
         4: aload_1
         5: invokespecial #74                 // Method "<init>":(Lscala/collection/immutable/List;)V
         8: areturn
      LineNumberTable:
        line 10: 0
      LocalVariableTable:
        Start  Length  Slot  Name   Signature
            0       9     0  this   Largonaut/CursorHistory;
            0       9     1 toList   Lscala/collection/immutable/List;
    Signature: #30                          // (Lscala/collection/immutable/List<Largonaut/CursorOp;>;)Largonaut/CursorHistory;
    MethodParameters:
      Name                           Flags
      toList                         final

  public scala.collection.immutable.List<argonaut.CursorOp> copy$default$1();
    descriptor: ()Lscala/collection/immutable/List;
    flags: (0x0001) ACC_PUBLIC
    Code:
      stack=1, locals=1, args_size=1
         0: aload_0
         1: invokevirtual #59                 // Method toList:()Lscala/collection/immutable/List;
         4: areturn
      LineNumberTable:
        line 10: 0
      LocalVariableTable:
        Start  Length  Slot  Name   Signature
            0       5     0  this   Largonaut/CursorHistory;
    Signature: #52                          // ()Lscala/collection/immutable/List<Largonaut/CursorOp;>;

  public java.lang.String productPrefix();
    descriptor: ()Ljava/lang/String;
    flags: (0x0001) ACC_PUBLIC
    Code:
      stack=1, locals=1, args_size=1
         0: ldc           #182                // String CursorHistory
         2: areturn
      LineNumberTable:
        line 10: 0
      LocalVariableTable:
        Start  Length  Slot  Name   Signature
            0       3     0  this   Largonaut/CursorHistory;

  public int productArity();
    descriptor: ()I
    flags: (0x0001) ACC_PUBLIC
    Code:
      stack=1, locals=1, args_size=1
         0: iconst_1
         1: ireturn
      LineNumberTable:
        line 10: 0
      LocalVariableTable:
        Start  Length  Slot  Name   Signature
            0       2     0  this   Largonaut/CursorHistory;

  public java.lang.Object productElement(int);
    descriptor: (I)Ljava/lang/Object;
    flags: (0x0001) ACC_PUBLIC
    Code:
      stack=1, locals=3, args_size=2
         0: iload_1
         1: istore_2
         2: iload_2
         3: tableswitch   { // 0 to 0
                       0: 20
                 default: 27
            }
        20: aload_0
        21: invokevirtual #59                 // Method toList:()Lscala/collection/immutable/List;
        24: goto          34
        27: iload_1
        28: invokestatic  #192                // Method scala/runtime/Statics.ioobe:(I)Ljava/lang/Object;
        31: goto          34
        34: areturn
      StackMapTable: number_of_entries = 3
        frame_type = 252 /* append */
          offset_delta = 20
          locals = [ int ]
        frame_type = 6 /* same */
        frame_type = 70 /* same_locals_1_stack_item */
          stack = [ class java/lang/Object ]
      LineNumberTable:
        line 10: 0
      LocalVariableTable:
        Start  Length  Slot  Name   Signature
            0      35     0  this   Largonaut/CursorHistory;
            0      35     1   x$1   I
    MethodParameters:
      Name                           Flags
      x$1                            final

  public scala.collection.Iterator<java.lang.Object> productIterator();
    descriptor: ()Lscala/collection/Iterator;
    flags: (0x0001) ACC_PUBLIC
    Code:
      stack=2, locals=1, args_size=1
         0: getstatic     #200                // Field scala/runtime/ScalaRunTime$.MODULE$:Lscala/runtime/ScalaRunTime$;
         3: aload_0
         4: invokevirtual #203                // Method scala/runtime/ScalaRunTime$.typedProductIterator:(Lscala/Product;)Lscala/collection/Iterator;
         7: areturn
      LineNumberTable:
        line 10: 0
      LocalVariableTable:
        Start  Length  Slot  Name   Signature
            0       8     0  this   Largonaut/CursorHistory;
    Signature: #195                         // ()Lscala/collection/Iterator<Ljava/lang/Object;>;

  public boolean canEqual(java.lang.Object);
    descriptor: (Ljava/lang/Object;)Z
    flags: (0x0001) ACC_PUBLIC
    Code:
      stack=1, locals=2, args_size=2
         0: aload_1
         1: instanceof    #2                  // class argonaut/CursorHistory
         4: ireturn
      LineNumberTable:
        line 10: 0
      LocalVariableTable:
        Start  Length  Slot  Name   Signature
            0       5     0  this   Largonaut/CursorHistory;
            0       5     1   x$1   Ljava/lang/Object;
    MethodParameters:
      Name                           Flags
      x$1                            final

  public java.lang.String productElementName(int);
    descriptor: (I)Ljava/lang/String;
    flags: (0x0001) ACC_PUBLIC
    Code:
      stack=1, locals=3, args_size=2
         0: iload_1
         1: istore_2
         2: iload_2
         3: tableswitch   { // 0 to 0
                       0: 20
                 default: 25
            }
        20: ldc           #208                // String toList
        22: goto          35
        25: iload_1
        26: invokestatic  #192                // Method scala/runtime/Statics.ioobe:(I)Ljava/lang/Object;
        29: checkcast     #210                // class java/lang/String
        32: goto          35
        35: areturn
      StackMapTable: number_of_entries = 3
        frame_type = 252 /* append */
          offset_delta = 20
          locals = [ int ]
        frame_type = 4 /* same */
        frame_type = 73 /* same_locals_1_stack_item */
          stack = [ class java/lang/String ]
      LineNumberTable:
        line 10: 0
      LocalVariableTable:
        Start  Length  Slot  Name   Signature
            0      36     0  this   Largonaut/CursorHistory;
            0      36     1   x$1   I
    MethodParameters:
      Name                           Flags
      x$1                            final

  public int hashCode();
    descriptor: ()I
    flags: (0x0001) ACC_PUBLIC
    Code:
      stack=2, locals=1, args_size=1
         0: getstatic     #200                // Field scala/runtime/ScalaRunTime$.MODULE$:Lscala/runtime/ScalaRunTime$;
         3: aload_0
         4: invokevirtual #215                // Method scala/runtime/ScalaRunTime$._hashCode:(Lscala/Product;)I
         7: ireturn
      LineNumberTable:
        line 10: 0
      LocalVariableTable:
        Start  Length  Slot  Name   Signature
            0       8     0  this   Largonaut/CursorHistory;

  public boolean equals(java.lang.Object);
    descriptor: (Ljava/lang/Object;)Z
    flags: (0x0001) ACC_PUBLIC
    Code:
      stack=2, locals=6, args_size=2
         0: aload_0
         1: aload_1
         2: if_acmpeq     86
         5: aload_1
         6: astore_3
         7: aload_3
         8: instanceof    #2                  // class argonaut/CursorHistory
        11: ifeq          19
        14: iconst_1
        15: istore_2
        16: goto          27
        19: goto          22
        22: iconst_0
        23: istore_2
        24: goto          27
        27: iload_2
        28: ifeq          90
        31: aload_1
        32: checkcast     #2                  // class argonaut/CursorHistory
        35: astore        4
        37: aload_0
        38: invokevirtual #59                 // Method toList:()Lscala/collection/immutable/List;
        41: aload         4
        43: invokevirtual #59                 // Method toList:()Lscala/collection/immutable/List;
        46: astore        5
        48: dup
        49: ifnonnull     61
        52: pop
        53: aload         5
        55: ifnull        69
        58: goto          82
        61: aload         5
        63: invokevirtual #95                 // Method java/lang/Object.equals:(Ljava/lang/Object;)Z
        66: ifeq          82
        69: aload         4
        71: aload_0
        72: invokevirtual #217                // Method canEqual:(Ljava/lang/Object;)Z
        75: ifeq          82
        78: iconst_1
        79: goto          83
        82: iconst_0
        83: ifeq          90
        86: iconst_1
        87: goto          91
        90: iconst_0
        91: ireturn
      StackMapTable: number_of_entries = 10
        frame_type = 253 /* append */
          offset_delta = 19
          locals = [ top, class java/lang/Object ]
        frame_type = 2 /* same */
        frame_type = 255 /* full_frame */
          offset_delta = 4
          locals = [ class argonaut/CursorHistory, class java/lang/Object, int, class java/lang/Object ]
          stack = []
        frame_type = 255 /* full_frame */
          offset_delta = 33
          locals = [ class argonaut/CursorHistory, class java/lang/Object, int, class java/lang/Object, class argonaut/CursorHistory, class scala/collection/immutable/List ]
          stack = [ class scala/collection/immutable/List ]
        frame_type = 7 /* same */
        frame_type = 12 /* same */
        frame_type = 64 /* same_locals_1_stack_item */
          stack = [ int ]
        frame_type = 255 /* full_frame */
          offset_delta = 2
          locals = [ class argonaut/CursorHistory, class java/lang/Object ]
          stack = []
        frame_type = 253 /* append */
          offset_delta = 3
          locals = [ int, class java/lang/Object ]
        frame_type = 255 /* full_frame */
          offset_delta = 0
          locals = [ class argonaut/CursorHistory, class java/lang/Object ]
          stack = [ int ]
      LineNumberTable:
        line 10: 0
      LocalVariableTable:
        Start  Length  Slot  Name   Signature
            0      92     0  this   Largonaut/CursorHistory;
            0      92     1   x$1   Ljava/lang/Object;
    MethodParameters:
      Name                           Flags
      x$1                            final

  public argonaut.CursorHistory(scala.collection.immutable.List<argonaut.CursorOp>);
    descriptor: (Lscala/collection/immutable/List;)V
    flags: (0x0001) ACC_PUBLIC
    Code:
      stack=2, locals=2, args_size=2
         0: aload_0
         1: aload_1
         2: putfield      #54                 // Field toList:Lscala/collection/immutable/List;
         5: aload_0
         6: invokespecial #221                // Method java/lang/Object."<init>":()V
         9: aload_0
        10: invokestatic  #225                // InterfaceMethod scala/Product.$init$:(Lscala/Product;)V
        13: return
      LineNumberTable:
        line 10: 0
      LocalVariableTable:
        Start  Length  Slot  Name   Signature
            0      14     0  this   Largonaut/CursorHistory;
            0      14     1 toList   Lscala/collection/immutable/List;
    Signature: #218                         // (Lscala/collection/immutable/List<Largonaut/CursorOp;>;)V
    MethodParameters:
      Name                           Flags
      toList                         final
}
SourceFile: "CursorHistory.scala"
RuntimeVisibleAnnotations:
  0: #10(#11=s#12)
    scala.reflect.ScalaSignature(
      bytes="\u0006\u0005\u0005Ee\u0001B\u000e\u001d\u0001~A\u0001\"\u000e\u0001\u0003\u0016\u0004%\tA\u000e\u0005\t}\u0001\u0011\t\u0012)A\u0005o!)q\b\u0001C\u0001\u0001\")1\t\u0001C\u0001\t\")\u0001\n\u0001C\u0001\u0013\")A\n\u0001C\u0001\u001b\")\u0011\r\u0001C\u0001E\")Q\r\u0001C\u0001M\")\u0001\u000e\u0001C\u0001S\")1\u000e\u0001C!Y\"9Q\u000fAA\u0001\n\u00031\bb\u0002=\u0001#\u0003%\t!\u001f\u0005\n\u0003\u0013\u0001\u0011\u0011!C!\u0003\u0017A\u0011\"a\u0007\u0001\u0003\u0003%\t!!\b\t\u0013\u0005\u0015\u0002!!A\u0005\u0002\u0005\u001d\u0002\"CA\u001a\u0001\u0005\u0005I\u0011IA\u001b\u0011%\t\u0019\u0005AA\u0001\n\u0003\t)\u0005C\u0005\u0002P\u0001\t\t\u0011\"\u0011\u0002R!I\u0011Q\u000b\u0001\u0002\u0002\u0013\u0005\u0013q\u000b\u0005\n\u00033\u0002\u0011\u0011!C!\u00037:q!a\u0018\u001d\u0011\u0003\t\tG\u0002\u0004\u001c9!\u0005\u00111\r\u0005\u0007\u007fY!\t!!\u001e\t\u0013\u0005]d#!A\u0005\u0002\u0006e\u0004\"CA?-\u0005\u0005I\u0011QA@\u0011%\t9IFA\u0001\n\u0013\tIIA\u0007DkJ\u001cxN\u001d%jgR|\'/\u001f\u0006\u0002;\u0005A\u0011M]4p]\u0006,Ho\u0001\u0001\u0014\t\u0001\u0001c%\u000b\t\u0003C\u0011j\u0011A\t\u0006\u0002G\u0005)1oY1mC&\u0011QE\t\u0002\u0007\u0003:L(+\u001a4\u0011\u0005\u0005:\u0013B\u0001\u0015#\u0005\u001d\u0001&o\u001c3vGR\u0004\"A\u000b\u001a\u000f\u0005-\u0002dB\u0001\u00170\u001b\u0005i#B\u0001\u0018\u001f\u0003\u0019a$o\\8u}%\t1%\u0003\u00022E\u00059\u0001/Y2lC\u001e,\u0017BA\u001a5\u00051\u0019VM]5bY&T\u0018M\u00197f\u0015\t\t$%\u0001\u0004u_2K7\u000f^\u000b\u0002oA\u0019!\u0006\u000f\u001e\n\u0005e\"$\u0001\u0002\'jgR\u0004\"a\u000f\u001f\u000e\u0003qI!!\u0010\u000f\u0003\u0011\r+(o]8s\u001fB\fq\u0001^8MSN$\b%\u0001\u0004=S:LGO\u0010\u000b\u0003\u0003\n\u0003\"a\u000f\u0001\t\u000bU\u001a\u0001\u0019A\u001c\u0002\t!,\u0017\rZ\u000b\u0002\u000bB\u0019\u0011E\u0012\u001e\n\u0005\u001d\u0013#AB(qi&|g.\u0001\u0006%a2,8\u000f\n9mkN$\"!\u0011&\t\u000b-+\u0001\u0019A!\u0002\u0003!\fa\"Y2veN|\'/\u00127f[\u0016tG\u000f\u0006\u0003O#jc\u0006CA\u001eP\u0013\t\u0001FDA\u0004B\u0007V\u00148o\u001c:\t\u000bI3\u0001\u0019A*\u0002\u0003\u0019\u0004B!\t+W3&\u0011QK\t\u0002\n\rVt7\r^5p]F\u0002\"aO,\n\u0005ac\"AB\"veN|\'\u000fE\u0002\"\rZCQa\u0017\u0004A\u0002Y\u000b\u0011a\u0019\u0005\u0006;\u001a\u0001\rAX\u0001\u0002KB\u00111hX\u0005\u0003Ar\u0011qbQ;sg>\u0014x\n]#mK6,g\u000e^\u0001\fIAdWo\u001d\u0013d_2|g\u000e\u0006\u0002BG\")Am\u0002a\u0001u\u0005\tq.A\u0007gC&dW\rZ!DkJ\u001cxN\u001d\u000b\u0003\u001d\u001eDQa\u0017\u0005A\u0002Y\u000bq!Y2veN|\'\u000f\u0006\u0002OU\")1,\u0003a\u0001-\u0006AAo\\*ue&tw\rF\u0001n!\tq\'O\u0004\u0002paB\u0011AFI\u0005\u0003c\n\na\u0001\u0015:fI\u00164\u0017BA:u\u0005\u0019\u0019FO]5oO*\u0011\u0011OI\u0001\u0005G>\u0004\u0018\u0010\u0006\u0002Bo\"9Qg\u0003I\u0001\u0002\u00049\u0014AD2paf$C-\u001a4bk2$H%M\u000b\u0002u*\u0012qg_\u0016\u0002yB\u0019Q0!\u0002\u000e\u0003yT1a`A\u0001\u0003%)hn\u00195fG.,GMC\u0002\u0002\u0004\t\n!\"\u00198o_R\fG/[8o\u0013\r\t9A \u0002\u0012k:\u001c\u0007.Z2lK\u00124\u0016M]5b]\u000e,\u0017!\u00049s_\u0012,8\r\u001e)sK\u001aL\u00070\u0006\u0002\u0002\u000eA!\u0011qBA\r\u001b\t\t\tB\u0003\u0003\u0002\u0014\u0005U\u0011\u0001\u00027b]\u001eT!!a\u0006\u0002\t)\fg/Y\u0005\u0004g\u0006E\u0011\u0001\u00049s_\u0012,8\r^!sSRLXCAA\u0010!\r\t\u0013\u0011E\u0005\u0004\u0003G\u0011#aA%oi\u0006q\u0001O]8ek\u000e$X\t\\3nK:$H\u0003BA\u0015\u0003_\u00012!IA\u0016\u0013\r\tiC\t\u0002\u0004\u0003:L\b\"CA\u0019\u001f\u0005\u0005\t\u0019AA\u0010\u0003\rAH%M\u0001\u0010aJ|G-^2u\u0013R,\'/\u0019;peV\u0011\u0011q\u0007\t\u0007\u0003s\ty$!\u000b\u000e\u0005\u0005m\"bAA\u001fE\u0005Q1m\u001c7mK\u000e$\u0018n\u001c8\n\t\u0005\u0005\u00131\b\u0002\t\u0013R,\'/\u0019;pe\u0006A1-\u00198FcV\fG\u000e\u0006\u0003\u0002H\u00055\u0003cA\u0011\u0002J%\u0019\u00111\n\u0012\u0003\u000f\t{w\u000e\\3b]\"I\u0011\u0011G\t\u0002\u0002\u0003\u0007\u0011\u0011F\u0001\u0013aJ|G-^2u\u000b2,W.\u001a8u\u001d\u0006lW\r\u0006\u0003\u0002\u000e\u0005M\u0003\"CA\u0019%\u0005\u0005\t\u0019AA\u0010\u0003!A\u0017m\u001d5D_\u0012,GCAA\u0010\u0003\u0019)\u0017/^1mgR!\u0011qIA/\u0011%\t\t\u0004FA\u0001\u0002\u0004\tI#A\u0007DkJ\u001cxN\u001d%jgR|\'/\u001f\t\u0003wY\u0019bA\u0006\u0011\u0002f\u0005-\u0004cA\u001e\u0002h%\u0019\u0011\u0011\u000e\u000f\u0003\u001d\r+(o]8s\u0011&\u001cHo\u001c:zgB!\u0011QNA:\u001b\t\tyG\u0003\u0003\u0002r\u0005U\u0011AA5p\u0013\r\u0019\u0014q\u000e\u000b\u0003\u0003C\nQ!\u00199qYf$2!QA>\u0011\u0015)\u0004\u00041\u00018\u0003\u001d)h.\u00199qYf$B!!!\u0002\u0004B\u0019\u0011ER\u001c\t\u0011\u0005\u0015\u0015$!AA\u0002\u0005\u000b1\u0001\u001f\u00131\u000319(/\u001b;f%\u0016\u0004H.Y2f)\t\tY\t\u0005\u0003\u0002\u0010\u00055\u0015\u0002BAH\u0003#\u0011aa\u00142kK\u000e$\b"
    )
  ScalaInlineInfo: length = 0x68 (unknown attribute)
   01 00 00 14 00 69 00 22 00 00 41 00 42 00 00 47
   00 48 00 00 7A 00 6D 00 00 4B 00 4C 00 00 CC 00
   5D 00 00 B2 00 1D 00 00 B3 00 33 00 00 5C 00 5D
   00 00 6C 00 6D 00 00 D3 00 B8 00 00 37 00 38 00
   00 B7 00 B8 00 00 B9 00 BA 00 00 CE 00 CF 00 00
   2A 00 2B 00 00 C2 00 2B 00 00 B4 00 A0 00 00 0D
   00 33 00 00 9F 00 A0 00
  ScalaSig: length = 0x3 (unknown attribute)
   05 02 00
