Classfile /Users/mw/Projects/slang-braindump/.jar/jar11/assemble/slang-braindump/assemble/content/argonaut/CursorOpDownN.class
  Last modified May 29, 2022; size 4504 bytes
  SHA-256 checksum fa3cd5667b364a3b41248ee7d7eebcf88f312af6080a63899c8eb5c8b5df2ba6
  Compiled from "CursorOpElement.scala"
public class argonaut.CursorOpDownN extends argonaut.CursorOpElement
  minor version: 0
  major version: 52
  flags: (0x0021) ACC_PUBLIC, ACC_SUPER
  this_class: #2                          // argonaut/CursorOpDownN
  super_class: #4                         // argonaut/CursorOpElement
  interfaces: 0, fields: 1, methods: 17, attributes: 4
Constant pool:
    #1 = Utf8               argonaut/CursorOpDownN
    #2 = Class              #1            // argonaut/CursorOpDownN
    #3 = Utf8               argonaut/CursorOpElement
    #4 = Class              #3            // argonaut/CursorOpElement
    #5 = Utf8               CursorOpElement.scala
    #6 = Utf8               Lscala/reflect/ScalaSignature;
    #7 = Utf8               bytes
    #8 = Utf8               \u0006\u0005\u0005\u0015b\u0001\u0002\f\u0018\u0001jA\u0001\"\r\u0001\u0003\u0016\u0004%\tA\r\u0005\tm\u0001\u0011\t\u0012)A\u0005g!)q\u0007\u0001C\u0001q!91\bAA\u0001\n\u0003a\u0004b\u0002 \u0001#\u0003%\ta\u0010\u0005\b\u0015\u0002\t\t\u0011\"\u0011L\u0011\u001d!\u0006!!A\u0005\u0002IBq!\u0016\u0001\u0002\u0002\u0013\u0005a\u000bC\u0004]\u0001\u0005\u0005I\u0011I/\t\u000f\u0011\u0004\u0011\u0011!C\u0001K\"9!\u000eAA\u0001\n\u0003Z\u0007bB7\u0001\u0003\u0003%\tE\u001c\u0005\b_\u0002\t\t\u0011\"\u0011q\u0011\u001d\t\b!!A\u0005BI<q\u0001^\f\u0002\u0002#\u0005QOB\u0004\u0017/\u0005\u0005\t\u0012\u0001<\t\r]\u0002B\u0011AA\u0003\u0011\u001dy\u0007#!A\u0005FAD\u0011\"a\u0002\u0011\u0003\u0003%\t)!\u0003\t\u0013\u00055\u0001#!A\u0005\u0002\u0006=\u0001\"CA\u000e!\u0005\u0005I\u0011BA\u000f\u00055\u0019UO]:pe>\u0003Hi\\<o\u001d*\t\u0001$\u0001\u0005be\u001e|g.Y;u\u0007\u0001\u0019B\u0001A\u000e KA\u0011A$H\u0007\u0002/%\u0011ad\u0006\u0002\u0010\u0007V\u00148o\u001c:Pa\u0016cW-\\3oiB\u0011\u0001eI\u0007\u0002C)\t!%A\u0003tG\u0006d\u0017-\u0003\u0002%C\t9\u0001K]8ek\u000e$\bC\u0001\u0014/\u001d\t9CF\u0004\u0002)W5\t\u0011F\u0003\u0002+3\u00051AH]8pizJ\u0011AI\u0005\u0003[\u0005\nq\u0001]1dW\u0006<W-\u0003\u00020a\ta1+\u001a:jC2L\'0\u00192mK*\u0011Q&I\u0001\u0002]V\t1\u0007\u0005\u0002!i%\u0011Q\'\t\u0002\u0004\u0013:$\u0018A\u00018!\u0003\u0019a\u0014N\\5u}Q\u0011\u0011H\u000f\t\u00039\u0001AQ!M\u0002A\u0002M\nAaY8qsR\u0011\u0011(\u0010\u0005\bc\u0011\u0001\n\u00111\u00014\u00039\u0019w\u000e]=%I\u00164\u0017-\u001e7uIE*\u0012\u0001\u0011\u0016\u0003g\u0005[\u0013A\u0011\t\u0003\u0007\"k\u0011\u0001\u0012\u0006\u0003\u000b\u001a\u000b\u0011\"\u001e8dQ\u0016\u001c7.\u001a3\u000b\u0005\u001d\u000b\u0013AC1o]>$\u0018\r^5p]&\u0011\u0011\n\u0012\u0002\u0012k:\u001c\u0007.Z2lK\u00124\u0016M]5b]\u000e,\u0017!\u00049s_\u0012,8\r\u001e)sK\u001aL\u00070F\u0001M!\ti%+D\u0001O\u0015\ty\u0005+\u0001\u0003mC:<\'\"A)\u0002\t)\fg/Y\u0005\u0003\':\u0013aa\u0015;sS:<\u0017\u0001\u00049s_\u0012,8\r^!sSRL\u0018A\u00049s_\u0012,8\r^#mK6,g\u000e\u001e\u000b\u0003/j\u0003\"\u0001\t-\n\u0005e\u000b#aA!os\"91\fCA\u0001\u0002\u0004\u0019\u0014a\u0001=%c\u0005y\u0001O]8ek\u000e$\u0018\n^3sCR|\'/F\u0001_!\ry&mV\u0007\u0002A*\u0011\u0011-I\u0001\u000bG>dG.Z2uS>t\u0017BA2a\u0005!IE/\u001a:bi>\u0014\u0018\u0001C2b]\u0016\u000bX/\u00197\u0015\u0005\u0019L\u0007C\u0001\u0011h\u0013\tA\u0017EA\u0004C_>dW-\u00198\t\u000fmS\u0011\u0011!a\u0001/\u0006\u0011\u0002O]8ek\u000e$X\t\\3nK:$h*Y7f)\taE\u000eC\u0004\\\u0017\u0005\u0005\t\u0019A\u001a\u0002\u0011!\f7\u000f[\"pI\u0016$\u0012aM\u0001\ti>\u001cFO]5oOR\tA*\u0001\u0004fcV\fGn\u001d\u000b\u0003MNDqa\u0017\b\u0002\u0002\u0003\u0007q+A\u0007DkJ\u001cxN](q\t><hN\u0014\t\u00039A\u00192\u0001E<~!\u0011A8pM\u001d\u000e\u0003eT!A_\u0011\u0002\u000fI,h\u000e^5nK&\u0011A0\u001f\u0002\u0012\u0003\n\u001cHO]1di\u001a+hn\u0019;j_:\f\u0004c\u0001@\u0002\u00045\tqPC\u0002\u0002\u0002A\u000b!![8\n\u0005=zH#A;\u0002\u000b\u0005\u0004\b\u000f\\=\u0015\u0007e\nY\u0001C\u00032\'\u0001\u00071\'A\u0004v]\u0006\u0004\b\u000f\\=\u0015\t\u0005E\u0011q\u0003\t\u0005A\u0005M1\'C\u0002\u0002\u0016\u0005\u0012aa\u00149uS>t\u0007\u0002CA\r)\u0005\u0005\t\u0019A\u001d\u0002\u0007a$\u0003\'\u0001\u0007xe&$XMU3qY\u0006\u001cW\r\u0006\u0002\u0002 A\u0019Q*!\t\n\u0007\u0005\rbJ\u0001\u0004PE*,7\r\u001e
    #9 = Utf8               n
   #10 = Utf8               I
   #11 = Utf8               unapply
   #12 = Utf8               (Largonaut/CursorOpDownN;)Lscala/Option;
   #13 = Utf8               (Largonaut/CursorOpDownN;)Lscala/Option<Ljava/lang/Object;>;
   #14 = Utf8               x$0
   #15 = Utf8               argonaut/CursorOpDownN$
   #16 = Class              #15           // argonaut/CursorOpDownN$
   #17 = Utf8               MODULE$
   #18 = Utf8               Largonaut/CursorOpDownN$;
   #19 = NameAndType        #17:#18       // MODULE$:Largonaut/CursorOpDownN$;
   #20 = Fieldref           #16.#19       // argonaut/CursorOpDownN$.MODULE$:Largonaut/CursorOpDownN$;
   #21 = NameAndType        #11:#12       // unapply:(Largonaut/CursorOpDownN;)Lscala/Option;
   #22 = Methodref          #16.#21       // argonaut/CursorOpDownN$.unapply:(Largonaut/CursorOpDownN;)Lscala/Option;
   #23 = Utf8               apply
   #24 = Utf8               (I)Largonaut/CursorOpDownN;
   #25 = NameAndType        #23:#24       // apply:(I)Largonaut/CursorOpDownN;
   #26 = Methodref          #16.#25       // argonaut/CursorOpDownN$.apply:(I)Largonaut/CursorOpDownN;
   #27 = Utf8               andThen
   #28 = Utf8               (Lscala/Function1;)Lscala/Function1;
   #29 = Utf8               <A:Ljava/lang/Object;>(Lscala/Function1<Largonaut/CursorOpDownN;TA;>;)Lscala/Function1<Ljava/lang/Object;TA;>;
   #30 = Utf8               g
   #31 = NameAndType        #27:#28       // andThen:(Lscala/Function1;)Lscala/Function1;
   #32 = Methodref          #16.#31       // argonaut/CursorOpDownN$.andThen:(Lscala/Function1;)Lscala/Function1;
   #33 = Utf8               compose
   #34 = Utf8               <A:Ljava/lang/Object;>(Lscala/Function1<TA;Ljava/lang/Object;>;)Lscala/Function1<TA;Largonaut/CursorOpDownN;>;
   #35 = NameAndType        #33:#28       // compose:(Lscala/Function1;)Lscala/Function1;
   #36 = Methodref          #16.#35       // argonaut/CursorOpDownN$.compose:(Lscala/Function1;)Lscala/Function1;
   #37 = Utf8               ()I
   #38 = NameAndType        #9:#10        // n:I
   #39 = Fieldref           #2.#38        // argonaut/CursorOpDownN.n:I
   #40 = Utf8               this
   #41 = Utf8               Largonaut/CursorOpDownN;
   #42 = Utf8               copy
   #43 = Utf8               <init>
   #44 = Utf8               (I)V
   #45 = NameAndType        #43:#44       // "<init>":(I)V
   #46 = Methodref          #2.#45        // argonaut/CursorOpDownN."<init>":(I)V
   #47 = Utf8               copy$default$1
   #48 = NameAndType        #9:#37        // n:()I
   #49 = Methodref          #2.#48        // argonaut/CursorOpDownN.n:()I
   #50 = Utf8               productPrefix
   #51 = Utf8               ()Ljava/lang/String;
   #52 = Utf8               CursorOpDownN
   #53 = String             #52           // CursorOpDownN
   #54 = Utf8               productArity
   #55 = Utf8               productElement
   #56 = Utf8               (I)Ljava/lang/Object;
   #57 = Utf8               x$1
   #58 = Utf8               scala/runtime/BoxesRunTime
   #59 = Class              #58           // scala/runtime/BoxesRunTime
   #60 = Utf8               boxToInteger
   #61 = Utf8               (I)Ljava/lang/Integer;
   #62 = NameAndType        #60:#61       // boxToInteger:(I)Ljava/lang/Integer;
   #63 = Methodref          #59.#62       // scala/runtime/BoxesRunTime.boxToInteger:(I)Ljava/lang/Integer;
   #64 = Utf8               scala/runtime/Statics
   #65 = Class              #64           // scala/runtime/Statics
   #66 = Utf8               ioobe
   #67 = NameAndType        #66:#56       // ioobe:(I)Ljava/lang/Object;
   #68 = Methodref          #65.#67       // scala/runtime/Statics.ioobe:(I)Ljava/lang/Object;
   #69 = Utf8               java/lang/Object
   #70 = Class              #69           // java/lang/Object
   #71 = Utf8               productIterator
   #72 = Utf8               ()Lscala/collection/Iterator;
   #73 = Utf8               ()Lscala/collection/Iterator<Ljava/lang/Object;>;
   #74 = Utf8               scala/runtime/ScalaRunTime$
   #75 = Class              #74           // scala/runtime/ScalaRunTime$
   #76 = Utf8               Lscala/runtime/ScalaRunTime$;
   #77 = NameAndType        #17:#76       // MODULE$:Lscala/runtime/ScalaRunTime$;
   #78 = Fieldref           #75.#77       // scala/runtime/ScalaRunTime$.MODULE$:Lscala/runtime/ScalaRunTime$;
   #79 = Utf8               typedProductIterator
   #80 = Utf8               (Lscala/Product;)Lscala/collection/Iterator;
   #81 = NameAndType        #79:#80       // typedProductIterator:(Lscala/Product;)Lscala/collection/Iterator;
   #82 = Methodref          #75.#81       // scala/runtime/ScalaRunTime$.typedProductIterator:(Lscala/Product;)Lscala/collection/Iterator;
   #83 = Utf8               canEqual
   #84 = Utf8               (Ljava/lang/Object;)Z
   #85 = Utf8               Ljava/lang/Object;
   #86 = Utf8               productElementName
   #87 = Utf8               (I)Ljava/lang/String;
   #88 = String             #9            // n
   #89 = Utf8               java/lang/String
   #90 = Class              #89           // java/lang/String
   #91 = Utf8               hashCode
   #92 = Integer            -889275714
   #93 = NameAndType        #50:#51       // productPrefix:()Ljava/lang/String;
   #94 = Methodref          #2.#93        // argonaut/CursorOpDownN.productPrefix:()Ljava/lang/String;
   #95 = NameAndType        #91:#37       // hashCode:()I
   #96 = Methodref          #90.#95       // java/lang/String.hashCode:()I
   #97 = Utf8               mix
   #98 = Utf8               (II)I
   #99 = NameAndType        #97:#98       // mix:(II)I
  #100 = Methodref          #65.#99       // scala/runtime/Statics.mix:(II)I
  #101 = Utf8               finalizeHash
  #102 = NameAndType        #101:#98      // finalizeHash:(II)I
  #103 = Methodref          #65.#102      // scala/runtime/Statics.finalizeHash:(II)I
  #104 = Utf8               toString
  #105 = Utf8               _toString
  #106 = Utf8               (Lscala/Product;)Ljava/lang/String;
  #107 = NameAndType        #105:#106     // _toString:(Lscala/Product;)Ljava/lang/String;
  #108 = Methodref          #75.#107      // scala/runtime/ScalaRunTime$._toString:(Lscala/Product;)Ljava/lang/String;
  #109 = Utf8               equals
  #110 = NameAndType        #83:#84       // canEqual:(Ljava/lang/Object;)Z
  #111 = Methodref          #2.#110       // argonaut/CursorOpDownN.canEqual:(Ljava/lang/Object;)Z
  #112 = Utf8               ()V
  #113 = NameAndType        #43:#112      // "<init>":()V
  #114 = Methodref          #4.#113       // argonaut/CursorOpElement."<init>":()V
  #115 = Utf8               Code
  #116 = Utf8               Signature
  #117 = Utf8               MethodParameters
  #118 = Utf8               LineNumberTable
  #119 = Utf8               LocalVariableTable
  #120 = Utf8               StackMapTable
  #121 = Utf8               SourceFile
  #122 = Utf8               RuntimeVisibleAnnotations
  #123 = Utf8               ScalaInlineInfo
  #124 = Utf8               ScalaSig
{
  private final int n;
    descriptor: I
    flags: (0x0012) ACC_PRIVATE, ACC_FINAL

  public static scala.Option<java.lang.Object> unapply(argonaut.CursorOpDownN);
    descriptor: (Largonaut/CursorOpDownN;)Lscala/Option;
    flags: (0x0009) ACC_PUBLIC, ACC_STATIC
    Code:
      stack=2, locals=1, args_size=1
         0: getstatic     #20                 // Field argonaut/CursorOpDownN$.MODULE$:Largonaut/CursorOpDownN$;
         3: aload_0
         4: invokevirtual #22                 // Method argonaut/CursorOpDownN$.unapply:(Largonaut/CursorOpDownN;)Lscala/Option;
         7: areturn
    Signature: #13                          // (Largonaut/CursorOpDownN;)Lscala/Option<Ljava/lang/Object;>;
    MethodParameters:
      Name                           Flags
      x$0                            final

  public static argonaut.CursorOpDownN apply(int);
    descriptor: (I)Largonaut/CursorOpDownN;
    flags: (0x0009) ACC_PUBLIC, ACC_STATIC
    Code:
      stack=2, locals=1, args_size=1
         0: getstatic     #20                 // Field argonaut/CursorOpDownN$.MODULE$:Largonaut/CursorOpDownN$;
         3: iload_0
         4: invokevirtual #26                 // Method argonaut/CursorOpDownN$.apply:(I)Largonaut/CursorOpDownN;
         7: areturn
    MethodParameters:
      Name                           Flags
      n                              final

  public static <A extends java.lang.Object> scala.Function1<java.lang.Object, A> andThen(scala.Function1<argonaut.CursorOpDownN, A>);
    descriptor: (Lscala/Function1;)Lscala/Function1;
    flags: (0x0009) ACC_PUBLIC, ACC_STATIC
    Code:
      stack=2, locals=1, args_size=1
         0: getstatic     #20                 // Field argonaut/CursorOpDownN$.MODULE$:Largonaut/CursorOpDownN$;
         3: aload_0
         4: invokevirtual #32                 // Method argonaut/CursorOpDownN$.andThen:(Lscala/Function1;)Lscala/Function1;
         7: areturn
    Signature: #29                          // <A:Ljava/lang/Object;>(Lscala/Function1<Largonaut/CursorOpDownN;TA;>;)Lscala/Function1<Ljava/lang/Object;TA;>;
    MethodParameters:
      Name                           Flags
      g                              final

  public static <A extends java.lang.Object> scala.Function1<A, argonaut.CursorOpDownN> compose(scala.Function1<A, java.lang.Object>);
    descriptor: (Lscala/Function1;)Lscala/Function1;
    flags: (0x0009) ACC_PUBLIC, ACC_STATIC
    Code:
      stack=2, locals=1, args_size=1
         0: getstatic     #20                 // Field argonaut/CursorOpDownN$.MODULE$:Largonaut/CursorOpDownN$;
         3: aload_0
         4: invokevirtual #36                 // Method argonaut/CursorOpDownN$.compose:(Lscala/Function1;)Lscala/Function1;
         7: areturn
    Signature: #34                          // <A:Ljava/lang/Object;>(Lscala/Function1<TA;Ljava/lang/Object;>;)Lscala/Function1<TA;Largonaut/CursorOpDownN;>;
    MethodParameters:
      Name                           Flags
      g                              final

  public int n();
    descriptor: ()I
    flags: (0x0001) ACC_PUBLIC
    Code:
      stack=1, locals=1, args_size=1
         0: aload_0
         1: getfield      #39                 // Field n:I
         4: ireturn
      LineNumberTable:
        line 57: 0
      LocalVariableTable:
        Start  Length  Slot  Name   Signature
            0       5     0  this   Largonaut/CursorOpDownN;

  public argonaut.CursorOpDownN copy(int);
    descriptor: (I)Largonaut/CursorOpDownN;
    flags: (0x0001) ACC_PUBLIC
    Code:
      stack=3, locals=2, args_size=2
         0: new           #2                  // class argonaut/CursorOpDownN
         3: dup
         4: iload_1
         5: invokespecial #46                 // Method "<init>":(I)V
         8: areturn
      LineNumberTable:
        line 57: 0
      LocalVariableTable:
        Start  Length  Slot  Name   Signature
            0       9     0  this   Largonaut/CursorOpDownN;
            0       9     1     n   I
    MethodParameters:
      Name                           Flags
      n                              final

  public int copy$default$1();
    descriptor: ()I
    flags: (0x0001) ACC_PUBLIC
    Code:
      stack=1, locals=1, args_size=1
         0: aload_0
         1: invokevirtual #49                 // Method n:()I
         4: ireturn
      LineNumberTable:
        line 57: 0
      LocalVariableTable:
        Start  Length  Slot  Name   Signature
            0       5     0  this   Largonaut/CursorOpDownN;

  public java.lang.String productPrefix();
    descriptor: ()Ljava/lang/String;
    flags: (0x0001) ACC_PUBLIC
    Code:
      stack=1, locals=1, args_size=1
         0: ldc           #53                 // String CursorOpDownN
         2: areturn
      LineNumberTable:
        line 57: 0
      LocalVariableTable:
        Start  Length  Slot  Name   Signature
            0       3     0  this   Largonaut/CursorOpDownN;

  public int productArity();
    descriptor: ()I
    flags: (0x0001) ACC_PUBLIC
    Code:
      stack=1, locals=1, args_size=1
         0: iconst_1
         1: ireturn
      LineNumberTable:
        line 57: 0
      LocalVariableTable:
        Start  Length  Slot  Name   Signature
            0       2     0  this   Largonaut/CursorOpDownN;

  public java.lang.Object productElement(int);
    descriptor: (I)Ljava/lang/Object;
    flags: (0x0001) ACC_PUBLIC
    Code:
      stack=1, locals=3, args_size=2
         0: iload_1
         1: istore_2
         2: iload_2
         3: tableswitch   { // 0 to 0
                       0: 20
                 default: 30
            }
        20: aload_0
        21: invokevirtual #49                 // Method n:()I
        24: invokestatic  #63                 // Method scala/runtime/BoxesRunTime.boxToInteger:(I)Ljava/lang/Integer;
        27: goto          37
        30: iload_1
        31: invokestatic  #68                 // Method scala/runtime/Statics.ioobe:(I)Ljava/lang/Object;
        34: goto          37
        37: areturn
      StackMapTable: number_of_entries = 3
        frame_type = 252 /* append */
          offset_delta = 20
          locals = [ int ]
        frame_type = 9 /* same */
        frame_type = 70 /* same_locals_1_stack_item */
          stack = [ class java/lang/Object ]
      LineNumberTable:
        line 57: 0
      LocalVariableTable:
        Start  Length  Slot  Name   Signature
            0      38     0  this   Largonaut/CursorOpDownN;
            0      38     1   x$1   I
    MethodParameters:
      Name                           Flags
      x$1                            final

  public scala.collection.Iterator<java.lang.Object> productIterator();
    descriptor: ()Lscala/collection/Iterator;
    flags: (0x0001) ACC_PUBLIC
    Code:
      stack=2, locals=1, args_size=1
         0: getstatic     #78                 // Field scala/runtime/ScalaRunTime$.MODULE$:Lscala/runtime/ScalaRunTime$;
         3: aload_0
         4: invokevirtual #82                 // Method scala/runtime/ScalaRunTime$.typedProductIterator:(Lscala/Product;)Lscala/collection/Iterator;
         7: areturn
      LineNumberTable:
        line 57: 0
      LocalVariableTable:
        Start  Length  Slot  Name   Signature
            0       8     0  this   Largonaut/CursorOpDownN;
    Signature: #73                          // ()Lscala/collection/Iterator<Ljava/lang/Object;>;

  public boolean canEqual(java.lang.Object);
    descriptor: (Ljava/lang/Object;)Z
    flags: (0x0001) ACC_PUBLIC
    Code:
      stack=1, locals=2, args_size=2
         0: aload_1
         1: instanceof    #2                  // class argonaut/CursorOpDownN
         4: ireturn
      LineNumberTable:
        line 57: 0
      LocalVariableTable:
        Start  Length  Slot  Name   Signature
            0       5     0  this   Largonaut/CursorOpDownN;
            0       5     1   x$1   Ljava/lang/Object;
    MethodParameters:
      Name                           Flags
      x$1                            final

  public java.lang.String productElementName(int);
    descriptor: (I)Ljava/lang/String;
    flags: (0x0001) ACC_PUBLIC
    Code:
      stack=1, locals=3, args_size=2
         0: iload_1
         1: istore_2
         2: iload_2
         3: tableswitch   { // 0 to 0
                       0: 20
                 default: 25
            }
        20: ldc           #88                 // String n
        22: goto          35
        25: iload_1
        26: invokestatic  #68                 // Method scala/runtime/Statics.ioobe:(I)Ljava/lang/Object;
        29: checkcast     #90                 // class java/lang/String
        32: goto          35
        35: areturn
      StackMapTable: number_of_entries = 3
        frame_type = 252 /* append */
          offset_delta = 20
          locals = [ int ]
        frame_type = 4 /* same */
        frame_type = 73 /* same_locals_1_stack_item */
          stack = [ class java/lang/String ]
      LineNumberTable:
        line 57: 0
      LocalVariableTable:
        Start  Length  Slot  Name   Signature
            0      36     0  this   Largonaut/CursorOpDownN;
            0      36     1   x$1   I
    MethodParameters:
      Name                           Flags
      x$1                            final

  public int hashCode();
    descriptor: ()I
    flags: (0x0001) ACC_PUBLIC
    Code:
      stack=2, locals=2, args_size=1
         0: ldc           #92                 // int -889275714
         2: istore_1
         3: iload_1
         4: aload_0
         5: invokevirtual #94                 // Method productPrefix:()Ljava/lang/String;
         8: invokevirtual #96                 // Method java/lang/String.hashCode:()I
        11: invokestatic  #100                // Method scala/runtime/Statics.mix:(II)I
        14: istore_1
        15: iload_1
        16: aload_0
        17: invokevirtual #49                 // Method n:()I
        20: invokestatic  #100                // Method scala/runtime/Statics.mix:(II)I
        23: istore_1
        24: iload_1
        25: iconst_1
        26: invokestatic  #103                // Method scala/runtime/Statics.finalizeHash:(II)I
        29: ireturn
      LineNumberTable:
        line 57: 0
      LocalVariableTable:
        Start  Length  Slot  Name   Signature
            0      30     0  this   Largonaut/CursorOpDownN;

  public java.lang.String toString();
    descriptor: ()Ljava/lang/String;
    flags: (0x0001) ACC_PUBLIC
    Code:
      stack=2, locals=1, args_size=1
         0: getstatic     #78                 // Field scala/runtime/ScalaRunTime$.MODULE$:Lscala/runtime/ScalaRunTime$;
         3: aload_0
         4: invokevirtual #108                // Method scala/runtime/ScalaRunTime$._toString:(Lscala/Product;)Ljava/lang/String;
         7: areturn
      LineNumberTable:
        line 57: 0
      LocalVariableTable:
        Start  Length  Slot  Name   Signature
            0       8     0  this   Largonaut/CursorOpDownN;

  public boolean equals(java.lang.Object);
    descriptor: (Ljava/lang/Object;)Z
    flags: (0x0001) ACC_PUBLIC
    Code:
      stack=2, locals=5, args_size=2
         0: aload_0
         1: aload_1
         2: if_acmpeq     66
         5: aload_1
         6: astore_3
         7: aload_3
         8: instanceof    #2                  // class argonaut/CursorOpDownN
        11: ifeq          19
        14: iconst_1
        15: istore_2
        16: goto          27
        19: goto          22
        22: iconst_0
        23: istore_2
        24: goto          27
        27: iload_2
        28: ifeq          70
        31: aload_1
        32: checkcast     #2                  // class argonaut/CursorOpDownN
        35: astore        4
        37: aload_0
        38: invokevirtual #49                 // Method n:()I
        41: aload         4
        43: invokevirtual #49                 // Method n:()I
        46: if_icmpne     62
        49: aload         4
        51: aload_0
        52: invokevirtual #111                // Method canEqual:(Ljava/lang/Object;)Z
        55: ifeq          62
        58: iconst_1
        59: goto          63
        62: iconst_0
        63: ifeq          70
        66: iconst_1
        67: goto          71
        70: iconst_0
        71: ireturn
      StackMapTable: number_of_entries = 8
        frame_type = 253 /* append */
          offset_delta = 19
          locals = [ top, class java/lang/Object ]
        frame_type = 2 /* same */
        frame_type = 255 /* full_frame */
          offset_delta = 4
          locals = [ class argonaut/CursorOpDownN, class java/lang/Object, int, class java/lang/Object ]
          stack = []
        frame_type = 252 /* append */
          offset_delta = 34
          locals = [ class argonaut/CursorOpDownN ]
        frame_type = 64 /* same_locals_1_stack_item */
          stack = [ int ]
        frame_type = 248 /* chop */
          offset_delta = 2
        frame_type = 253 /* append */
          offset_delta = 3
          locals = [ int, class java/lang/Object ]
        frame_type = 255 /* full_frame */
          offset_delta = 0
          locals = [ class argonaut/CursorOpDownN, class java/lang/Object ]
          stack = [ int ]
      LineNumberTable:
        line 57: 0
      LocalVariableTable:
        Start  Length  Slot  Name   Signature
            0      72     0  this   Largonaut/CursorOpDownN;
            0      72     1   x$1   Ljava/lang/Object;
    MethodParameters:
      Name                           Flags
      x$1                            final

  public argonaut.CursorOpDownN(int);
    descriptor: (I)V
    flags: (0x0001) ACC_PUBLIC
    Code:
      stack=2, locals=2, args_size=2
         0: aload_0
         1: iload_1
         2: putfield      #39                 // Field n:I
         5: aload_0
         6: invokespecial #114                // Method argonaut/CursorOpElement."<init>":()V
         9: return
      LineNumberTable:
        line 57: 0
      LocalVariableTable:
        Start  Length  Slot  Name   Signature
            0      10     0  this   Largonaut/CursorOpDownN;
            0      10     1     n   I
    MethodParameters:
      Name                           Flags
      n                              final
}
SourceFile: "CursorOpElement.scala"
RuntimeVisibleAnnotations:
  0: #6(#7=s#8)
    scala.reflect.ScalaSignature(
      bytes="\u0006\u0005\u0005\u0015b\u0001\u0002\f\u0018\u0001jA\u0001\"\r\u0001\u0003\u0016\u0004%\tA\r\u0005\tm\u0001\u0011\t\u0012)A\u0005g!)q\u0007\u0001C\u0001q!91\bAA\u0001\n\u0003a\u0004b\u0002 \u0001#\u0003%\ta\u0010\u0005\b\u0015\u0002\t\t\u0011\"\u0011L\u0011\u001d!\u0006!!A\u0005\u0002IBq!\u0016\u0001\u0002\u0002\u0013\u0005a\u000bC\u0004]\u0001\u0005\u0005I\u0011I/\t\u000f\u0011\u0004\u0011\u0011!C\u0001K\"9!\u000eAA\u0001\n\u0003Z\u0007bB7\u0001\u0003\u0003%\tE\u001c\u0005\b_\u0002\t\t\u0011\"\u0011q\u0011\u001d\t\b!!A\u0005BI<q\u0001^\f\u0002\u0002#\u0005QOB\u0004\u0017/\u0005\u0005\t\u0012\u0001<\t\r]\u0002B\u0011AA\u0003\u0011\u001dy\u0007#!A\u0005FAD\u0011\"a\u0002\u0011\u0003\u0003%\t)!\u0003\t\u0013\u00055\u0001#!A\u0005\u0002\u0006=\u0001\"CA\u000e!\u0005\u0005I\u0011BA\u000f\u00055\u0019UO]:pe>\u0003Hi\\<o\u001d*\t\u0001$\u0001\u0005be\u001e|g.Y;u\u0007\u0001\u0019B\u0001A\u000e KA\u0011A$H\u0007\u0002/%\u0011ad\u0006\u0002\u0010\u0007V\u00148o\u001c:Pa\u0016cW-\\3oiB\u0011\u0001eI\u0007\u0002C)\t!%A\u0003tG\u0006d\u0017-\u0003\u0002%C\t9\u0001K]8ek\u000e$\bC\u0001\u0014/\u001d\t9CF\u0004\u0002)W5\t\u0011F\u0003\u0002+3\u00051AH]8pizJ\u0011AI\u0005\u0003[\u0005\nq\u0001]1dW\u0006<W-\u0003\u00020a\ta1+\u001a:jC2L\'0\u00192mK*\u0011Q&I\u0001\u0002]V\t1\u0007\u0005\u0002!i%\u0011Q\'\t\u0002\u0004\u0013:$\u0018A\u00018!\u0003\u0019a\u0014N\\5u}Q\u0011\u0011H\u000f\t\u00039\u0001AQ!M\u0002A\u0002M\nAaY8qsR\u0011\u0011(\u0010\u0005\bc\u0011\u0001\n\u00111\u00014\u00039\u0019w\u000e]=%I\u00164\u0017-\u001e7uIE*\u0012\u0001\u0011\u0016\u0003g\u0005[\u0013A\u0011\t\u0003\u0007\"k\u0011\u0001\u0012\u0006\u0003\u000b\u001a\u000b\u0011\"\u001e8dQ\u0016\u001c7.\u001a3\u000b\u0005\u001d\u000b\u0013AC1o]>$\u0018\r^5p]&\u0011\u0011\n\u0012\u0002\u0012k:\u001c\u0007.Z2lK\u00124\u0016M]5b]\u000e,\u0017!\u00049s_\u0012,8\r\u001e)sK\u001aL\u00070F\u0001M!\ti%+D\u0001O\u0015\ty\u0005+\u0001\u0003mC:<\'\"A)\u0002\t)\fg/Y\u0005\u0003\':\u0013aa\u0015;sS:<\u0017\u0001\u00049s_\u0012,8\r^!sSRL\u0018A\u00049s_\u0012,8\r^#mK6,g\u000e\u001e\u000b\u0003/j\u0003\"\u0001\t-\n\u0005e\u000b#aA!os\"91\fCA\u0001\u0002\u0004\u0019\u0014a\u0001=%c\u0005y\u0001O]8ek\u000e$\u0018\n^3sCR|\'/F\u0001_!\ry&mV\u0007\u0002A*\u0011\u0011-I\u0001\u000bG>dG.Z2uS>t\u0017BA2a\u0005!IE/\u001a:bi>\u0014\u0018\u0001C2b]\u0016\u000bX/\u00197\u0015\u0005\u0019L\u0007C\u0001\u0011h\u0013\tA\u0017EA\u0004C_>dW-\u00198\t\u000fmS\u0011\u0011!a\u0001/\u0006\u0011\u0002O]8ek\u000e$X\t\\3nK:$h*Y7f)\taE\u000eC\u0004\\\u0017\u0005\u0005\t\u0019A\u001a\u0002\u0011!\f7\u000f[\"pI\u0016$\u0012aM\u0001\ti>\u001cFO]5oOR\tA*\u0001\u0004fcV\fGn\u001d\u000b\u0003MNDqa\u0017\b\u0002\u0002\u0003\u0007q+A\u0007DkJ\u001cxN](q\t><hN\u0014\t\u00039A\u00192\u0001E<~!\u0011A8pM\u001d\u000e\u0003eT!A_\u0011\u0002\u000fI,h\u000e^5nK&\u0011A0\u001f\u0002\u0012\u0003\n\u001cHO]1di\u001a+hn\u0019;j_:\f\u0004c\u0001@\u0002\u00045\tqPC\u0002\u0002\u0002A\u000b!![8\n\u0005=zH#A;\u0002\u000b\u0005\u0004\b\u000f\\=\u0015\u0007e\nY\u0001C\u00032\'\u0001\u00071\'A\u0004v]\u0006\u0004\b\u000f\\=\u0015\t\u0005E\u0011q\u0003\t\u0005A\u0005M1\'C\u0002\u0002\u0016\u0005\u0012aa\u00149uS>t\u0007\u0002CA\r)\u0005\u0005\t\u0019A\u001d\u0002\u0007a$\u0003\'\u0001\u0007xe&$XMU3qY\u0006\u001cW\r\u0006\u0002\u0002 A\u0019Q*!\t\n\u0007\u0005\rbJ\u0001\u0004PE*,7\r\u001e"
    )
  ScalaInlineInfo: length = 0x45 (unknown attribute)
   01 00 00 0D 00 2B 00 2C 00 00 53 00 54 00 00 2A
   00 18 00 00 2F 00 25 00 00 6D 00 54 00 00 5B 00
   25 00 00 09 00 25 00 00 36 00 25 00 00 37 00 38
   00 00 56 00 57 00 00 47 00 48 00 00 32 00 33 00
   00 68 00 33 00
  ScalaSig: length = 0x3 (unknown attribute)
   05 02 00
