Classfile /Users/mw/Projects/slang-braindump/.jar/jar11/assemble/slang-braindump/assemble/content/argonaut/CursorOpDeleteGoRight.class
  Last modified May 29, 2022; size 2560 bytes
  SHA-256 checksum e51a54c6ba01b293acce6b8115cb2b14896f9f6dc727a780350c5153fde1134d
  Compiled from "CursorOpElement.scala"
public final class argonaut.CursorOpDeleteGoRight
  minor version: 0
  major version: 52
  flags: (0x0031) ACC_PUBLIC, ACC_FINAL, ACC_SUPER
  this_class: #2                          // argonaut/CursorOpDeleteGoRight
  super_class: #4                         // java/lang/Object
  interfaces: 0, fields: 0, methods: 21, attributes: 3
Constant pool:
   #1 = Utf8               argonaut/CursorOpDeleteGoRight
   #2 = Class              #1             // argonaut/CursorOpDeleteGoRight
   #3 = Utf8               java/lang/Object
   #4 = Class              #3             // java/lang/Object
   #5 = Utf8               CursorOpElement.scala
   #6 = Utf8               Lscala/reflect/ScalaSignature;
   #7 = Utf8               bytes
   #8 = Utf8               \u0006\u0005];Qa\u0003\u0007\t\u0002>1Q!\u0005\u0007\t\u0002JAQ\u0001K\u0001\u0005\u0002%BqAK\u0001\u0002\u0002\u0013\u00053\u0006C\u00045\u0003\u0005\u0005I\u0011A\u001b\t\u000fe\n\u0011\u0011!C\u0001u!9\u0001)AA\u0001\n\u0003\n\u0005b\u0002%\u0002\u0003\u0003%\t!\u0013\u0005\b\u001d\u0006\t\t\u0011\"\u0011P\u0011\u001d\u0001\u0016!!A\u0005BECqAU\u0001\u0002\u0002\u0013%1+A\u000bDkJ\u001cxN](q\t\u0016dW\r^3H_JKw\r\u001b;\u000b\u00035\t\u0001\"\u0019:h_:\fW\u000f^\u0002\u0001!\t\u0001\u0012!D\u0001\r\u0005U\u0019UO]:pe>\u0003H)\u001a7fi\u0016<uNU5hQR\u001cB!A\n\u00179A\u0011\u0001\u0003F\u0005\u0003+1\u0011qbQ;sg>\u0014x\n]#mK6,g\u000e\u001e\t\u0003/ii\u0011\u0001\u0007\u0006\u00023\u0005)1oY1mC&\u00111\u0004\u0007\u0002\b!J|G-^2u!\tiRE\u0004\u0002\u001fG9\u0011qDI\u0007\u0002A)\u0011\u0011ED\u0001\u0007yI|w\u000e\u001e \n\u0003eI!\u0001\n\r\u0002\u000fA\f7m[1hK&\u0011ae\n\u0002\r\'\u0016\u0014\u0018.\u00197ju\u0006\u0014G.\u001a\u0006\u0003Ia\ta\u0001P5oSRtD#A\b\u0002\u001bA\u0014x\u000eZ;diB\u0013XMZ5y+\u0005a\u0003CA\u00173\u001b\u0005q#BA\u00181\u0003\u0011a\u0017M\\4\u000b\u0003E\nAA[1wC&\u00111G\f\u0002\u0007\'R\u0014\u0018N\\4\u0002\u0019A\u0014x\u000eZ;di\u0006\u0013\u0018\u000e^=\u0016\u0003Y\u0002\"aF\u001c\n\u0005aB\"aA%oi\u0006q\u0001O]8ek\u000e$X\t\\3nK:$HCA\u001e?!\t9B(\u0003\u0002>1\t\u0019\u0011I\\=\t\u000f}*\u0011\u0011!a\u0001m\u0005\u0019\u0001\u0010J\u0019\u0002\u001fA\u0014x\u000eZ;di&#XM]1u_J,\u0012A\u0011\t\u0004\u0007\u001a[T\"\u0001#\u000b\u0005\u0015C\u0012AC2pY2,7\r^5p]&\u0011q\t\u0012\u0002\t\u0013R,\'/\u0019;pe\u0006A1-\u00198FcV\fG\u000e\u0006\u0002K\u001bB\u0011qcS\u0005\u0003\u0019b\u0011qAQ8pY\u0016\fg\u000eC\u0004@\u000f\u0005\u0005\t\u0019A\u001e\u0002\u0011!\f7\u000f[\"pI\u0016$\u0012AN\u0001\ti>\u001cFO]5oOR\tA&\u0001\u0007xe&$XMU3qY\u0006\u001cW\rF\u0001U!\tiS+\u0003\u0002W]\t1qJ\u00196fGR\u0004
   #9 = Utf8               toString
  #10 = Utf8               ()Ljava/lang/String;
  #11 = Utf8               argonaut/CursorOpDeleteGoRight$
  #12 = Class              #11            // argonaut/CursorOpDeleteGoRight$
  #13 = Utf8               MODULE$
  #14 = Utf8               Largonaut/CursorOpDeleteGoRight$;
  #15 = NameAndType        #13:#14        // MODULE$:Largonaut/CursorOpDeleteGoRight$;
  #16 = Fieldref           #12.#15        // argonaut/CursorOpDeleteGoRight$.MODULE$:Largonaut/CursorOpDeleteGoRight$;
  #17 = NameAndType        #9:#10         // toString:()Ljava/lang/String;
  #18 = Methodref          #12.#17        // argonaut/CursorOpDeleteGoRight$.toString:()Ljava/lang/String;
  #19 = Utf8               hashCode
  #20 = Utf8               ()I
  #21 = NameAndType        #19:#20        // hashCode:()I
  #22 = Methodref          #12.#21        // argonaut/CursorOpDeleteGoRight$.hashCode:()I
  #23 = Utf8               canEqual
  #24 = Utf8               (Ljava/lang/Object;)Z
  #25 = Utf8               x$1
  #26 = NameAndType        #23:#24        // canEqual:(Ljava/lang/Object;)Z
  #27 = Methodref          #12.#26        // argonaut/CursorOpDeleteGoRight$.canEqual:(Ljava/lang/Object;)Z
  #28 = Utf8               productIterator
  #29 = Utf8               ()Lscala/collection/Iterator;
  #30 = Utf8               ()Lscala/collection/Iterator<Ljava/lang/Object;>;
  #31 = NameAndType        #28:#29        // productIterator:()Lscala/collection/Iterator;
  #32 = Methodref          #12.#31        // argonaut/CursorOpDeleteGoRight$.productIterator:()Lscala/collection/Iterator;
  #33 = Utf8               productElement
  #34 = Utf8               (I)Ljava/lang/Object;
  #35 = NameAndType        #33:#34        // productElement:(I)Ljava/lang/Object;
  #36 = Methodref          #12.#35        // argonaut/CursorOpDeleteGoRight$.productElement:(I)Ljava/lang/Object;
  #37 = Utf8               productArity
  #38 = NameAndType        #37:#20        // productArity:()I
  #39 = Methodref          #12.#38        // argonaut/CursorOpDeleteGoRight$.productArity:()I
  #40 = Utf8               productPrefix
  #41 = NameAndType        #40:#10        // productPrefix:()Ljava/lang/String;
  #42 = Methodref          #12.#41        // argonaut/CursorOpDeleteGoRight$.productPrefix:()Ljava/lang/String;
  #43 = Utf8               isDeleteRights
  #44 = Utf8               ()Z
  #45 = NameAndType        #43:#44        // isDeleteRights:()Z
  #46 = Methodref          #12.#45        // argonaut/CursorOpDeleteGoRight$.isDeleteRights:()Z
  #47 = Utf8               isDeleteLefts
  #48 = NameAndType        #47:#44        // isDeleteLefts:()Z
  #49 = Methodref          #12.#48        // argonaut/CursorOpDeleteGoRight$.isDeleteLefts:()Z
  #50 = Utf8               isDeleteGoLast
  #51 = NameAndType        #50:#44        // isDeleteGoLast:()Z
  #52 = Methodref          #12.#51        // argonaut/CursorOpDeleteGoRight$.isDeleteGoLast:()Z
  #53 = Utf8               isDeleteGoFirst
  #54 = NameAndType        #53:#44        // isDeleteGoFirst:()Z
  #55 = Methodref          #12.#54        // argonaut/CursorOpDeleteGoRight$.isDeleteGoFirst:()Z
  #56 = Utf8               isDeleteGoRight
  #57 = NameAndType        #56:#44        // isDeleteGoRight:()Z
  #58 = Methodref          #12.#57        // argonaut/CursorOpDeleteGoRight$.isDeleteGoRight:()Z
  #59 = Utf8               isDeleteGoLeft
  #60 = NameAndType        #59:#44        // isDeleteGoLeft:()Z
  #61 = Methodref          #12.#60        // argonaut/CursorOpDeleteGoRight$.isDeleteGoLeft:()Z
  #62 = Utf8               isDeleteGoParent
  #63 = NameAndType        #62:#44        // isDeleteGoParent:()Z
  #64 = Methodref          #12.#63        // argonaut/CursorOpDeleteGoRight$.isDeleteGoParent:()Z
  #65 = Utf8               isUp
  #66 = NameAndType        #65:#44        // isUp:()Z
  #67 = Methodref          #12.#66        // argonaut/CursorOpDeleteGoRight$.isUp:()Z
  #68 = Utf8               isLast
  #69 = NameAndType        #68:#44        // isLast:()Z
  #70 = Methodref          #12.#69        // argonaut/CursorOpDeleteGoRight$.isLast:()Z
  #71 = Utf8               isFirst
  #72 = NameAndType        #71:#44        // isFirst:()Z
  #73 = Methodref          #12.#72        // argonaut/CursorOpDeleteGoRight$.isFirst:()Z
  #74 = Utf8               isRight
  #75 = NameAndType        #74:#44        // isRight:()Z
  #76 = Methodref          #12.#75        // argonaut/CursorOpDeleteGoRight$.isRight:()Z
  #77 = Utf8               isLeft
  #78 = NameAndType        #77:#44        // isLeft:()Z
  #79 = Methodref          #12.#78        // argonaut/CursorOpDeleteGoRight$.isLeft:()Z
  #80 = Utf8               productElementNames
  #81 = Utf8               ()Lscala/collection/Iterator<Ljava/lang/String;>;
  #82 = NameAndType        #80:#29        // productElementNames:()Lscala/collection/Iterator;
  #83 = Methodref          #12.#82        // argonaut/CursorOpDeleteGoRight$.productElementNames:()Lscala/collection/Iterator;
  #84 = Utf8               productElementName
  #85 = Utf8               (I)Ljava/lang/String;
  #86 = Utf8               n
  #87 = NameAndType        #84:#85        // productElementName:(I)Ljava/lang/String;
  #88 = Methodref          #12.#87        // argonaut/CursorOpDeleteGoRight$.productElementName:(I)Ljava/lang/String;
  #89 = Utf8               Code
  #90 = Utf8               MethodParameters
  #91 = Utf8               Signature
  #92 = Utf8               SourceFile
  #93 = Utf8               RuntimeVisibleAnnotations
  #94 = Utf8               ScalaSig
{
  public static java.lang.String toString();
    descriptor: ()Ljava/lang/String;
    flags: (0x0009) ACC_PUBLIC, ACC_STATIC
    Code:
      stack=1, locals=0, args_size=0
         0: getstatic     #16                 // Field argonaut/CursorOpDeleteGoRight$.MODULE$:Largonaut/CursorOpDeleteGoRight$;
         3: invokevirtual #18                 // Method argonaut/CursorOpDeleteGoRight$.toString:()Ljava/lang/String;
         6: areturn

  public static int hashCode();
    descriptor: ()I
    flags: (0x0009) ACC_PUBLIC, ACC_STATIC
    Code:
      stack=1, locals=0, args_size=0
         0: getstatic     #16                 // Field argonaut/CursorOpDeleteGoRight$.MODULE$:Largonaut/CursorOpDeleteGoRight$;
         3: invokevirtual #22                 // Method argonaut/CursorOpDeleteGoRight$.hashCode:()I
         6: ireturn

  public static boolean canEqual(java.lang.Object);
    descriptor: (Ljava/lang/Object;)Z
    flags: (0x0009) ACC_PUBLIC, ACC_STATIC
    Code:
      stack=2, locals=1, args_size=1
         0: getstatic     #16                 // Field argonaut/CursorOpDeleteGoRight$.MODULE$:Largonaut/CursorOpDeleteGoRight$;
         3: aload_0
         4: invokevirtual #27                 // Method argonaut/CursorOpDeleteGoRight$.canEqual:(Ljava/lang/Object;)Z
         7: ireturn
    MethodParameters:
      Name                           Flags
      x$1                            final

  public static scala.collection.Iterator<java.lang.Object> productIterator();
    descriptor: ()Lscala/collection/Iterator;
    flags: (0x0009) ACC_PUBLIC, ACC_STATIC
    Code:
      stack=1, locals=0, args_size=0
         0: getstatic     #16                 // Field argonaut/CursorOpDeleteGoRight$.MODULE$:Largonaut/CursorOpDeleteGoRight$;
         3: invokevirtual #32                 // Method argonaut/CursorOpDeleteGoRight$.productIterator:()Lscala/collection/Iterator;
         6: areturn
    Signature: #30                          // ()Lscala/collection/Iterator<Ljava/lang/Object;>;

  public static java.lang.Object productElement(int);
    descriptor: (I)Ljava/lang/Object;
    flags: (0x0009) ACC_PUBLIC, ACC_STATIC
    Code:
      stack=2, locals=1, args_size=1
         0: getstatic     #16                 // Field argonaut/CursorOpDeleteGoRight$.MODULE$:Largonaut/CursorOpDeleteGoRight$;
         3: iload_0
         4: invokevirtual #36                 // Method argonaut/CursorOpDeleteGoRight$.productElement:(I)Ljava/lang/Object;
         7: areturn
    MethodParameters:
      Name                           Flags
      x$1                            final

  public static int productArity();
    descriptor: ()I
    flags: (0x0009) ACC_PUBLIC, ACC_STATIC
    Code:
      stack=1, locals=0, args_size=0
         0: getstatic     #16                 // Field argonaut/CursorOpDeleteGoRight$.MODULE$:Largonaut/CursorOpDeleteGoRight$;
         3: invokevirtual #39                 // Method argonaut/CursorOpDeleteGoRight$.productArity:()I
         6: ireturn

  public static java.lang.String productPrefix();
    descriptor: ()Ljava/lang/String;
    flags: (0x0009) ACC_PUBLIC, ACC_STATIC
    Code:
      stack=1, locals=0, args_size=0
         0: getstatic     #16                 // Field argonaut/CursorOpDeleteGoRight$.MODULE$:Largonaut/CursorOpDeleteGoRight$;
         3: invokevirtual #42                 // Method argonaut/CursorOpDeleteGoRight$.productPrefix:()Ljava/lang/String;
         6: areturn

  public static boolean isDeleteRights();
    descriptor: ()Z
    flags: (0x0009) ACC_PUBLIC, ACC_STATIC
    Code:
      stack=1, locals=0, args_size=0
         0: getstatic     #16                 // Field argonaut/CursorOpDeleteGoRight$.MODULE$:Largonaut/CursorOpDeleteGoRight$;
         3: invokevirtual #46                 // Method argonaut/CursorOpDeleteGoRight$.isDeleteRights:()Z
         6: ireturn

  public static boolean isDeleteLefts();
    descriptor: ()Z
    flags: (0x0009) ACC_PUBLIC, ACC_STATIC
    Code:
      stack=1, locals=0, args_size=0
         0: getstatic     #16                 // Field argonaut/CursorOpDeleteGoRight$.MODULE$:Largonaut/CursorOpDeleteGoRight$;
         3: invokevirtual #49                 // Method argonaut/CursorOpDeleteGoRight$.isDeleteLefts:()Z
         6: ireturn

  public static boolean isDeleteGoLast();
    descriptor: ()Z
    flags: (0x0009) ACC_PUBLIC, ACC_STATIC
    Code:
      stack=1, locals=0, args_size=0
         0: getstatic     #16                 // Field argonaut/CursorOpDeleteGoRight$.MODULE$:Largonaut/CursorOpDeleteGoRight$;
         3: invokevirtual #52                 // Method argonaut/CursorOpDeleteGoRight$.isDeleteGoLast:()Z
         6: ireturn

  public static boolean isDeleteGoFirst();
    descriptor: ()Z
    flags: (0x0009) ACC_PUBLIC, ACC_STATIC
    Code:
      stack=1, locals=0, args_size=0
         0: getstatic     #16                 // Field argonaut/CursorOpDeleteGoRight$.MODULE$:Largonaut/CursorOpDeleteGoRight$;
         3: invokevirtual #55                 // Method argonaut/CursorOpDeleteGoRight$.isDeleteGoFirst:()Z
         6: ireturn

  public static boolean isDeleteGoRight();
    descriptor: ()Z
    flags: (0x0009) ACC_PUBLIC, ACC_STATIC
    Code:
      stack=1, locals=0, args_size=0
         0: getstatic     #16                 // Field argonaut/CursorOpDeleteGoRight$.MODULE$:Largonaut/CursorOpDeleteGoRight$;
         3: invokevirtual #58                 // Method argonaut/CursorOpDeleteGoRight$.isDeleteGoRight:()Z
         6: ireturn

  public static boolean isDeleteGoLeft();
    descriptor: ()Z
    flags: (0x0009) ACC_PUBLIC, ACC_STATIC
    Code:
      stack=1, locals=0, args_size=0
         0: getstatic     #16                 // Field argonaut/CursorOpDeleteGoRight$.MODULE$:Largonaut/CursorOpDeleteGoRight$;
         3: invokevirtual #61                 // Method argonaut/CursorOpDeleteGoRight$.isDeleteGoLeft:()Z
         6: ireturn

  public static boolean isDeleteGoParent();
    descriptor: ()Z
    flags: (0x0009) ACC_PUBLIC, ACC_STATIC
    Code:
      stack=1, locals=0, args_size=0
         0: getstatic     #16                 // Field argonaut/CursorOpDeleteGoRight$.MODULE$:Largonaut/CursorOpDeleteGoRight$;
         3: invokevirtual #64                 // Method argonaut/CursorOpDeleteGoRight$.isDeleteGoParent:()Z
         6: ireturn

  public static boolean isUp();
    descriptor: ()Z
    flags: (0x0009) ACC_PUBLIC, ACC_STATIC
    Code:
      stack=1, locals=0, args_size=0
         0: getstatic     #16                 // Field argonaut/CursorOpDeleteGoRight$.MODULE$:Largonaut/CursorOpDeleteGoRight$;
         3: invokevirtual #67                 // Method argonaut/CursorOpDeleteGoRight$.isUp:()Z
         6: ireturn

  public static boolean isLast();
    descriptor: ()Z
    flags: (0x0009) ACC_PUBLIC, ACC_STATIC
    Code:
      stack=1, locals=0, args_size=0
         0: getstatic     #16                 // Field argonaut/CursorOpDeleteGoRight$.MODULE$:Largonaut/CursorOpDeleteGoRight$;
         3: invokevirtual #70                 // Method argonaut/CursorOpDeleteGoRight$.isLast:()Z
         6: ireturn

  public static boolean isFirst();
    descriptor: ()Z
    flags: (0x0009) ACC_PUBLIC, ACC_STATIC
    Code:
      stack=1, locals=0, args_size=0
         0: getstatic     #16                 // Field argonaut/CursorOpDeleteGoRight$.MODULE$:Largonaut/CursorOpDeleteGoRight$;
         3: invokevirtual #73                 // Method argonaut/CursorOpDeleteGoRight$.isFirst:()Z
         6: ireturn

  public static boolean isRight();
    descriptor: ()Z
    flags: (0x0009) ACC_PUBLIC, ACC_STATIC
    Code:
      stack=1, locals=0, args_size=0
         0: getstatic     #16                 // Field argonaut/CursorOpDeleteGoRight$.MODULE$:Largonaut/CursorOpDeleteGoRight$;
         3: invokevirtual #76                 // Method argonaut/CursorOpDeleteGoRight$.isRight:()Z
         6: ireturn

  public static boolean isLeft();
    descriptor: ()Z
    flags: (0x0009) ACC_PUBLIC, ACC_STATIC
    Code:
      stack=1, locals=0, args_size=0
         0: getstatic     #16                 // Field argonaut/CursorOpDeleteGoRight$.MODULE$:Largonaut/CursorOpDeleteGoRight$;
         3: invokevirtual #79                 // Method argonaut/CursorOpDeleteGoRight$.isLeft:()Z
         6: ireturn

  public static scala.collection.Iterator<java.lang.String> productElementNames();
    descriptor: ()Lscala/collection/Iterator;
    flags: (0x0009) ACC_PUBLIC, ACC_STATIC
    Code:
      stack=1, locals=0, args_size=0
         0: getstatic     #16                 // Field argonaut/CursorOpDeleteGoRight$.MODULE$:Largonaut/CursorOpDeleteGoRight$;
         3: invokevirtual #83                 // Method argonaut/CursorOpDeleteGoRight$.productElementNames:()Lscala/collection/Iterator;
         6: areturn
    Signature: #81                          // ()Lscala/collection/Iterator<Ljava/lang/String;>;

  public static java.lang.String productElementName(int);
    descriptor: (I)Ljava/lang/String;
    flags: (0x0009) ACC_PUBLIC, ACC_STATIC
    Code:
      stack=2, locals=1, args_size=1
         0: getstatic     #16                 // Field argonaut/CursorOpDeleteGoRight$.MODULE$:Largonaut/CursorOpDeleteGoRight$;
         3: iload_0
         4: invokevirtual #88                 // Method argonaut/CursorOpDeleteGoRight$.productElementName:(I)Ljava/lang/String;
         7: areturn
    MethodParameters:
      Name                           Flags
      n                              final
}
SourceFile: "CursorOpElement.scala"
RuntimeVisibleAnnotations:
  0: #6(#7=s#8)
    scala.reflect.ScalaSignature(
      bytes="\u0006\u0005];Qa\u0003\u0007\t\u0002>1Q!\u0005\u0007\t\u0002JAQ\u0001K\u0001\u0005\u0002%BqAK\u0001\u0002\u0002\u0013\u00053\u0006C\u00045\u0003\u0005\u0005I\u0011A\u001b\t\u000fe\n\u0011\u0011!C\u0001u!9\u0001)AA\u0001\n\u0003\n\u0005b\u0002%\u0002\u0003\u0003%\t!\u0013\u0005\b\u001d\u0006\t\t\u0011\"\u0011P\u0011\u001d\u0001\u0016!!A\u0005BECqAU\u0001\u0002\u0002\u0013%1+A\u000bDkJ\u001cxN](q\t\u0016dW\r^3H_JKw\r\u001b;\u000b\u00035\t\u0001\"\u0019:h_:\fW\u000f^\u0002\u0001!\t\u0001\u0012!D\u0001\r\u0005U\u0019UO]:pe>\u0003H)\u001a7fi\u0016<uNU5hQR\u001cB!A\n\u00179A\u0011\u0001\u0003F\u0005\u0003+1\u0011qbQ;sg>\u0014x\n]#mK6,g\u000e\u001e\t\u0003/ii\u0011\u0001\u0007\u0006\u00023\u0005)1oY1mC&\u00111\u0004\u0007\u0002\b!J|G-^2u!\tiRE\u0004\u0002\u001fG9\u0011qDI\u0007\u0002A)\u0011\u0011ED\u0001\u0007yI|w\u000e\u001e \n\u0003eI!\u0001\n\r\u0002\u000fA\f7m[1hK&\u0011ae\n\u0002\r\'\u0016\u0014\u0018.\u00197ju\u0006\u0014G.\u001a\u0006\u0003Ia\ta\u0001P5oSRtD#A\b\u0002\u001bA\u0014x\u000eZ;diB\u0013XMZ5y+\u0005a\u0003CA\u00173\u001b\u0005q#BA\u00181\u0003\u0011a\u0017M\\4\u000b\u0003E\nAA[1wC&\u00111G\f\u0002\u0007\'R\u0014\u0018N\\4\u0002\u0019A\u0014x\u000eZ;di\u0006\u0013\u0018\u000e^=\u0016\u0003Y\u0002\"aF\u001c\n\u0005aB\"aA%oi\u0006q\u0001O]8ek\u000e$X\t\\3nK:$HCA\u001e?!\t9B(\u0003\u0002>1\t\u0019\u0011I\\=\t\u000f}*\u0011\u0011!a\u0001m\u0005\u0019\u0001\u0010J\u0019\u0002\u001fA\u0014x\u000eZ;di&#XM]1u_J,\u0012A\u0011\t\u0004\u0007\u001a[T\"\u0001#\u000b\u0005\u0015C\u0012AC2pY2,7\r^5p]&\u0011q\t\u0012\u0002\t\u0013R,\'/\u0019;pe\u0006A1-\u00198FcV\fG\u000e\u0006\u0002K\u001bB\u0011qcS\u0005\u0003\u0019b\u0011qAQ8pY\u0016\fg\u000eC\u0004@\u000f\u0005\u0005\t\u0019A\u001e\u0002\u0011!\f7\u000f[\"pI\u0016$\u0012AN\u0001\ti>\u001cFO]5oOR\tA&\u0001\u0007xe&$XMU3qY\u0006\u001cW\rF\u0001U!\tiS+\u0003\u0002W]\t1qJ\u00196fGR\u0004"
    )
  ScalaSig: length = 0x3 (unknown attribute)
   05 02 00
