Classfile /Users/mw/Projects/slang-braindump/.jar/jar11/assemble/slang-braindump/assemble/content/argonaut/CursorOpLeft.class
  Last modified May 29, 2022; size 2512 bytes
  SHA-256 checksum 8c8c65009c4432c5678a6382ce8648c876da58c02ceaf47adaa35d5dd1eed198
  Compiled from "CursorOpElement.scala"
public final class argonaut.CursorOpLeft
  minor version: 0
  major version: 52
  flags: (0x0031) ACC_PUBLIC, ACC_FINAL, ACC_SUPER
  this_class: #2                          // argonaut/CursorOpLeft
  super_class: #4                         // java/lang/Object
  interfaces: 0, fields: 0, methods: 21, attributes: 3
Constant pool:
   #1 = Utf8               argonaut/CursorOpLeft
   #2 = Class              #1             // argonaut/CursorOpLeft
   #3 = Utf8               java/lang/Object
   #4 = Class              #3             // java/lang/Object
   #5 = Utf8               CursorOpElement.scala
   #6 = Utf8               Lscala/reflect/ScalaSignature;
   #7 = Utf8               bytes
   #8 = Utf8               \u0006\u0005];Qa\u0003\u0007\t\u0002>1Q!\u0005\u0007\t\u0002JAQ\u0001K\u0001\u0005\u0002%BqAK\u0001\u0002\u0002\u0013\u00053\u0006C\u00045\u0003\u0005\u0005I\u0011A\u001b\t\u000fe\n\u0011\u0011!C\u0001u!9\u0001)AA\u0001\n\u0003\n\u0005b\u0002%\u0002\u0003\u0003%\t!\u0013\u0005\b\u001d\u0006\t\t\u0011\"\u0011P\u0011\u001d\u0001\u0016!!A\u0005BECqAU\u0001\u0002\u0002\u0013%1+\u0001\u0007DkJ\u001cxN](q\u0019\u00164GOC\u0001\u000e\u0003!\t\'oZ8oCV$8\u0001\u0001\t\u0003!\u0005i\u0011\u0001\u0004\u0002\r\u0007V\u00148o\u001c:Pa2+g\r^\n\u0005\u0003M1B\u0004\u0005\u0002\u0011)%\u0011Q\u0003\u0004\u0002\u0010\u0007V\u00148o\u001c:Pa\u0016cW-\\3oiB\u0011qCG\u0007\u00021)\t\u0011$A\u0003tG\u0006d\u0017-\u0003\u0002\u001c1\t9\u0001K]8ek\u000e$\bCA\u000f&\u001d\tq2E\u0004\u0002 E5\t\u0001E\u0003\u0002\"\u001d\u00051AH]8pizJ\u0011!G\u0005\u0003Ia\tq\u0001]1dW\u0006<W-\u0003\u0002\'O\ta1+\u001a:jC2L\'0\u00192mK*\u0011A\u0005G\u0001\u0007y%t\u0017\u000e\u001e \u0015\u0003=\tQ\u0002\u001d:pIV\u001cG\u000f\u0015:fM&DX#\u0001\u0017\u0011\u00055\u0012T\"\u0001\u0018\u000b\u0005=\u0002\u0014\u0001\u00027b]\u001eT\u0011!M\u0001\u0005U\u00064\u0018-\u0003\u00024]\t11\u000b\u001e:j]\u001e\fA\u0002\u001d:pIV\u001cG/\u0011:jif,\u0012A\u000e\t\u0003/]J!\u0001\u000f\r\u0003\u0007%sG/\u0001\bqe>$Wo\u0019;FY\u0016lWM\u001c;\u0015\u0005mr\u0004CA\f=\u0013\ti\u0004DA\u0002B]fDqaP\u0003\u0002\u0002\u0003\u0007a\'A\u0002yIE\nq\u0002\u001d:pIV\u001cG/\u0013;fe\u0006$xN]\u000b\u0002\u0005B\u00191IR\u001e\u000e\u0003\u0011S!!\u0012\r\u0002\u0015\r|G\u000e\\3di&|g.\u0003\u0002H\t\nA\u0011\n^3sCR|\'/\u0001\u0005dC:,\u0015/^1m)\tQU\n\u0005\u0002\u0018\u0017&\u0011A\n\u0007\u0002\b\u0005>|G.Z1o\u0011\u001dyt!!AA\u0002m\n\u0001\u0002[1tQ\u000e{G-\u001a\u000b\u0002m\u0005AAo\\*ue&tw\rF\u0001-\u000319(/\u001b;f%\u0016\u0004H.Y2f)\u0005!\u0006CA\u0017V\u0013\t1fF\u0001\u0004PE*,7\r\u001e
   #9 = Utf8               toString
  #10 = Utf8               ()Ljava/lang/String;
  #11 = Utf8               argonaut/CursorOpLeft$
  #12 = Class              #11            // argonaut/CursorOpLeft$
  #13 = Utf8               MODULE$
  #14 = Utf8               Largonaut/CursorOpLeft$;
  #15 = NameAndType        #13:#14        // MODULE$:Largonaut/CursorOpLeft$;
  #16 = Fieldref           #12.#15        // argonaut/CursorOpLeft$.MODULE$:Largonaut/CursorOpLeft$;
  #17 = NameAndType        #9:#10         // toString:()Ljava/lang/String;
  #18 = Methodref          #12.#17        // argonaut/CursorOpLeft$.toString:()Ljava/lang/String;
  #19 = Utf8               hashCode
  #20 = Utf8               ()I
  #21 = NameAndType        #19:#20        // hashCode:()I
  #22 = Methodref          #12.#21        // argonaut/CursorOpLeft$.hashCode:()I
  #23 = Utf8               canEqual
  #24 = Utf8               (Ljava/lang/Object;)Z
  #25 = Utf8               x$1
  #26 = NameAndType        #23:#24        // canEqual:(Ljava/lang/Object;)Z
  #27 = Methodref          #12.#26        // argonaut/CursorOpLeft$.canEqual:(Ljava/lang/Object;)Z
  #28 = Utf8               productIterator
  #29 = Utf8               ()Lscala/collection/Iterator;
  #30 = Utf8               ()Lscala/collection/Iterator<Ljava/lang/Object;>;
  #31 = NameAndType        #28:#29        // productIterator:()Lscala/collection/Iterator;
  #32 = Methodref          #12.#31        // argonaut/CursorOpLeft$.productIterator:()Lscala/collection/Iterator;
  #33 = Utf8               productElement
  #34 = Utf8               (I)Ljava/lang/Object;
  #35 = NameAndType        #33:#34        // productElement:(I)Ljava/lang/Object;
  #36 = Methodref          #12.#35        // argonaut/CursorOpLeft$.productElement:(I)Ljava/lang/Object;
  #37 = Utf8               productArity
  #38 = NameAndType        #37:#20        // productArity:()I
  #39 = Methodref          #12.#38        // argonaut/CursorOpLeft$.productArity:()I
  #40 = Utf8               productPrefix
  #41 = NameAndType        #40:#10        // productPrefix:()Ljava/lang/String;
  #42 = Methodref          #12.#41        // argonaut/CursorOpLeft$.productPrefix:()Ljava/lang/String;
  #43 = Utf8               isDeleteRights
  #44 = Utf8               ()Z
  #45 = NameAndType        #43:#44        // isDeleteRights:()Z
  #46 = Methodref          #12.#45        // argonaut/CursorOpLeft$.isDeleteRights:()Z
  #47 = Utf8               isDeleteLefts
  #48 = NameAndType        #47:#44        // isDeleteLefts:()Z
  #49 = Methodref          #12.#48        // argonaut/CursorOpLeft$.isDeleteLefts:()Z
  #50 = Utf8               isDeleteGoLast
  #51 = NameAndType        #50:#44        // isDeleteGoLast:()Z
  #52 = Methodref          #12.#51        // argonaut/CursorOpLeft$.isDeleteGoLast:()Z
  #53 = Utf8               isDeleteGoFirst
  #54 = NameAndType        #53:#44        // isDeleteGoFirst:()Z
  #55 = Methodref          #12.#54        // argonaut/CursorOpLeft$.isDeleteGoFirst:()Z
  #56 = Utf8               isDeleteGoRight
  #57 = NameAndType        #56:#44        // isDeleteGoRight:()Z
  #58 = Methodref          #12.#57        // argonaut/CursorOpLeft$.isDeleteGoRight:()Z
  #59 = Utf8               isDeleteGoLeft
  #60 = NameAndType        #59:#44        // isDeleteGoLeft:()Z
  #61 = Methodref          #12.#60        // argonaut/CursorOpLeft$.isDeleteGoLeft:()Z
  #62 = Utf8               isDeleteGoParent
  #63 = NameAndType        #62:#44        // isDeleteGoParent:()Z
  #64 = Methodref          #12.#63        // argonaut/CursorOpLeft$.isDeleteGoParent:()Z
  #65 = Utf8               isUp
  #66 = NameAndType        #65:#44        // isUp:()Z
  #67 = Methodref          #12.#66        // argonaut/CursorOpLeft$.isUp:()Z
  #68 = Utf8               isLast
  #69 = NameAndType        #68:#44        // isLast:()Z
  #70 = Methodref          #12.#69        // argonaut/CursorOpLeft$.isLast:()Z
  #71 = Utf8               isFirst
  #72 = NameAndType        #71:#44        // isFirst:()Z
  #73 = Methodref          #12.#72        // argonaut/CursorOpLeft$.isFirst:()Z
  #74 = Utf8               isRight
  #75 = NameAndType        #74:#44        // isRight:()Z
  #76 = Methodref          #12.#75        // argonaut/CursorOpLeft$.isRight:()Z
  #77 = Utf8               isLeft
  #78 = NameAndType        #77:#44        // isLeft:()Z
  #79 = Methodref          #12.#78        // argonaut/CursorOpLeft$.isLeft:()Z
  #80 = Utf8               productElementNames
  #81 = Utf8               ()Lscala/collection/Iterator<Ljava/lang/String;>;
  #82 = NameAndType        #80:#29        // productElementNames:()Lscala/collection/Iterator;
  #83 = Methodref          #12.#82        // argonaut/CursorOpLeft$.productElementNames:()Lscala/collection/Iterator;
  #84 = Utf8               productElementName
  #85 = Utf8               (I)Ljava/lang/String;
  #86 = Utf8               n
  #87 = NameAndType        #84:#85        // productElementName:(I)Ljava/lang/String;
  #88 = Methodref          #12.#87        // argonaut/CursorOpLeft$.productElementName:(I)Ljava/lang/String;
  #89 = Utf8               Code
  #90 = Utf8               MethodParameters
  #91 = Utf8               Signature
  #92 = Utf8               SourceFile
  #93 = Utf8               RuntimeVisibleAnnotations
  #94 = Utf8               ScalaSig
{
  public static java.lang.String toString();
    descriptor: ()Ljava/lang/String;
    flags: (0x0009) ACC_PUBLIC, ACC_STATIC
    Code:
      stack=1, locals=0, args_size=0
         0: getstatic     #16                 // Field argonaut/CursorOpLeft$.MODULE$:Largonaut/CursorOpLeft$;
         3: invokevirtual #18                 // Method argonaut/CursorOpLeft$.toString:()Ljava/lang/String;
         6: areturn

  public static int hashCode();
    descriptor: ()I
    flags: (0x0009) ACC_PUBLIC, ACC_STATIC
    Code:
      stack=1, locals=0, args_size=0
         0: getstatic     #16                 // Field argonaut/CursorOpLeft$.MODULE$:Largonaut/CursorOpLeft$;
         3: invokevirtual #22                 // Method argonaut/CursorOpLeft$.hashCode:()I
         6: ireturn

  public static boolean canEqual(java.lang.Object);
    descriptor: (Ljava/lang/Object;)Z
    flags: (0x0009) ACC_PUBLIC, ACC_STATIC
    Code:
      stack=2, locals=1, args_size=1
         0: getstatic     #16                 // Field argonaut/CursorOpLeft$.MODULE$:Largonaut/CursorOpLeft$;
         3: aload_0
         4: invokevirtual #27                 // Method argonaut/CursorOpLeft$.canEqual:(Ljava/lang/Object;)Z
         7: ireturn
    MethodParameters:
      Name                           Flags
      x$1                            final

  public static scala.collection.Iterator<java.lang.Object> productIterator();
    descriptor: ()Lscala/collection/Iterator;
    flags: (0x0009) ACC_PUBLIC, ACC_STATIC
    Code:
      stack=1, locals=0, args_size=0
         0: getstatic     #16                 // Field argonaut/CursorOpLeft$.MODULE$:Largonaut/CursorOpLeft$;
         3: invokevirtual #32                 // Method argonaut/CursorOpLeft$.productIterator:()Lscala/collection/Iterator;
         6: areturn
    Signature: #30                          // ()Lscala/collection/Iterator<Ljava/lang/Object;>;

  public static java.lang.Object productElement(int);
    descriptor: (I)Ljava/lang/Object;
    flags: (0x0009) ACC_PUBLIC, ACC_STATIC
    Code:
      stack=2, locals=1, args_size=1
         0: getstatic     #16                 // Field argonaut/CursorOpLeft$.MODULE$:Largonaut/CursorOpLeft$;
         3: iload_0
         4: invokevirtual #36                 // Method argonaut/CursorOpLeft$.productElement:(I)Ljava/lang/Object;
         7: areturn
    MethodParameters:
      Name                           Flags
      x$1                            final

  public static int productArity();
    descriptor: ()I
    flags: (0x0009) ACC_PUBLIC, ACC_STATIC
    Code:
      stack=1, locals=0, args_size=0
         0: getstatic     #16                 // Field argonaut/CursorOpLeft$.MODULE$:Largonaut/CursorOpLeft$;
         3: invokevirtual #39                 // Method argonaut/CursorOpLeft$.productArity:()I
         6: ireturn

  public static java.lang.String productPrefix();
    descriptor: ()Ljava/lang/String;
    flags: (0x0009) ACC_PUBLIC, ACC_STATIC
    Code:
      stack=1, locals=0, args_size=0
         0: getstatic     #16                 // Field argonaut/CursorOpLeft$.MODULE$:Largonaut/CursorOpLeft$;
         3: invokevirtual #42                 // Method argonaut/CursorOpLeft$.productPrefix:()Ljava/lang/String;
         6: areturn

  public static boolean isDeleteRights();
    descriptor: ()Z
    flags: (0x0009) ACC_PUBLIC, ACC_STATIC
    Code:
      stack=1, locals=0, args_size=0
         0: getstatic     #16                 // Field argonaut/CursorOpLeft$.MODULE$:Largonaut/CursorOpLeft$;
         3: invokevirtual #46                 // Method argonaut/CursorOpLeft$.isDeleteRights:()Z
         6: ireturn

  public static boolean isDeleteLefts();
    descriptor: ()Z
    flags: (0x0009) ACC_PUBLIC, ACC_STATIC
    Code:
      stack=1, locals=0, args_size=0
         0: getstatic     #16                 // Field argonaut/CursorOpLeft$.MODULE$:Largonaut/CursorOpLeft$;
         3: invokevirtual #49                 // Method argonaut/CursorOpLeft$.isDeleteLefts:()Z
         6: ireturn

  public static boolean isDeleteGoLast();
    descriptor: ()Z
    flags: (0x0009) ACC_PUBLIC, ACC_STATIC
    Code:
      stack=1, locals=0, args_size=0
         0: getstatic     #16                 // Field argonaut/CursorOpLeft$.MODULE$:Largonaut/CursorOpLeft$;
         3: invokevirtual #52                 // Method argonaut/CursorOpLeft$.isDeleteGoLast:()Z
         6: ireturn

  public static boolean isDeleteGoFirst();
    descriptor: ()Z
    flags: (0x0009) ACC_PUBLIC, ACC_STATIC
    Code:
      stack=1, locals=0, args_size=0
         0: getstatic     #16                 // Field argonaut/CursorOpLeft$.MODULE$:Largonaut/CursorOpLeft$;
         3: invokevirtual #55                 // Method argonaut/CursorOpLeft$.isDeleteGoFirst:()Z
         6: ireturn

  public static boolean isDeleteGoRight();
    descriptor: ()Z
    flags: (0x0009) ACC_PUBLIC, ACC_STATIC
    Code:
      stack=1, locals=0, args_size=0
         0: getstatic     #16                 // Field argonaut/CursorOpLeft$.MODULE$:Largonaut/CursorOpLeft$;
         3: invokevirtual #58                 // Method argonaut/CursorOpLeft$.isDeleteGoRight:()Z
         6: ireturn

  public static boolean isDeleteGoLeft();
    descriptor: ()Z
    flags: (0x0009) ACC_PUBLIC, ACC_STATIC
    Code:
      stack=1, locals=0, args_size=0
         0: getstatic     #16                 // Field argonaut/CursorOpLeft$.MODULE$:Largonaut/CursorOpLeft$;
         3: invokevirtual #61                 // Method argonaut/CursorOpLeft$.isDeleteGoLeft:()Z
         6: ireturn

  public static boolean isDeleteGoParent();
    descriptor: ()Z
    flags: (0x0009) ACC_PUBLIC, ACC_STATIC
    Code:
      stack=1, locals=0, args_size=0
         0: getstatic     #16                 // Field argonaut/CursorOpLeft$.MODULE$:Largonaut/CursorOpLeft$;
         3: invokevirtual #64                 // Method argonaut/CursorOpLeft$.isDeleteGoParent:()Z
         6: ireturn

  public static boolean isUp();
    descriptor: ()Z
    flags: (0x0009) ACC_PUBLIC, ACC_STATIC
    Code:
      stack=1, locals=0, args_size=0
         0: getstatic     #16                 // Field argonaut/CursorOpLeft$.MODULE$:Largonaut/CursorOpLeft$;
         3: invokevirtual #67                 // Method argonaut/CursorOpLeft$.isUp:()Z
         6: ireturn

  public static boolean isLast();
    descriptor: ()Z
    flags: (0x0009) ACC_PUBLIC, ACC_STATIC
    Code:
      stack=1, locals=0, args_size=0
         0: getstatic     #16                 // Field argonaut/CursorOpLeft$.MODULE$:Largonaut/CursorOpLeft$;
         3: invokevirtual #70                 // Method argonaut/CursorOpLeft$.isLast:()Z
         6: ireturn

  public static boolean isFirst();
    descriptor: ()Z
    flags: (0x0009) ACC_PUBLIC, ACC_STATIC
    Code:
      stack=1, locals=0, args_size=0
         0: getstatic     #16                 // Field argonaut/CursorOpLeft$.MODULE$:Largonaut/CursorOpLeft$;
         3: invokevirtual #73                 // Method argonaut/CursorOpLeft$.isFirst:()Z
         6: ireturn

  public static boolean isRight();
    descriptor: ()Z
    flags: (0x0009) ACC_PUBLIC, ACC_STATIC
    Code:
      stack=1, locals=0, args_size=0
         0: getstatic     #16                 // Field argonaut/CursorOpLeft$.MODULE$:Largonaut/CursorOpLeft$;
         3: invokevirtual #76                 // Method argonaut/CursorOpLeft$.isRight:()Z
         6: ireturn

  public static boolean isLeft();
    descriptor: ()Z
    flags: (0x0009) ACC_PUBLIC, ACC_STATIC
    Code:
      stack=1, locals=0, args_size=0
         0: getstatic     #16                 // Field argonaut/CursorOpLeft$.MODULE$:Largonaut/CursorOpLeft$;
         3: invokevirtual #79                 // Method argonaut/CursorOpLeft$.isLeft:()Z
         6: ireturn

  public static scala.collection.Iterator<java.lang.String> productElementNames();
    descriptor: ()Lscala/collection/Iterator;
    flags: (0x0009) ACC_PUBLIC, ACC_STATIC
    Code:
      stack=1, locals=0, args_size=0
         0: getstatic     #16                 // Field argonaut/CursorOpLeft$.MODULE$:Largonaut/CursorOpLeft$;
         3: invokevirtual #83                 // Method argonaut/CursorOpLeft$.productElementNames:()Lscala/collection/Iterator;
         6: areturn
    Signature: #81                          // ()Lscala/collection/Iterator<Ljava/lang/String;>;

  public static java.lang.String productElementName(int);
    descriptor: (I)Ljava/lang/String;
    flags: (0x0009) ACC_PUBLIC, ACC_STATIC
    Code:
      stack=2, locals=1, args_size=1
         0: getstatic     #16                 // Field argonaut/CursorOpLeft$.MODULE$:Largonaut/CursorOpLeft$;
         3: iload_0
         4: invokevirtual #88                 // Method argonaut/CursorOpLeft$.productElementName:(I)Ljava/lang/String;
         7: areturn
    MethodParameters:
      Name                           Flags
      n                              final
}
SourceFile: "CursorOpElement.scala"
RuntimeVisibleAnnotations:
  0: #6(#7=s#8)
    scala.reflect.ScalaSignature(
      bytes="\u0006\u0005];Qa\u0003\u0007\t\u0002>1Q!\u0005\u0007\t\u0002JAQ\u0001K\u0001\u0005\u0002%BqAK\u0001\u0002\u0002\u0013\u00053\u0006C\u00045\u0003\u0005\u0005I\u0011A\u001b\t\u000fe\n\u0011\u0011!C\u0001u!9\u0001)AA\u0001\n\u0003\n\u0005b\u0002%\u0002\u0003\u0003%\t!\u0013\u0005\b\u001d\u0006\t\t\u0011\"\u0011P\u0011\u001d\u0001\u0016!!A\u0005BECqAU\u0001\u0002\u0002\u0013%1+\u0001\u0007DkJ\u001cxN](q\u0019\u00164GOC\u0001\u000e\u0003!\t\'oZ8oCV$8\u0001\u0001\t\u0003!\u0005i\u0011\u0001\u0004\u0002\r\u0007V\u00148o\u001c:Pa2+g\r^\n\u0005\u0003M1B\u0004\u0005\u0002\u0011)%\u0011Q\u0003\u0004\u0002\u0010\u0007V\u00148o\u001c:Pa\u0016cW-\\3oiB\u0011qCG\u0007\u00021)\t\u0011$A\u0003tG\u0006d\u0017-\u0003\u0002\u001c1\t9\u0001K]8ek\u000e$\bCA\u000f&\u001d\tq2E\u0004\u0002 E5\t\u0001E\u0003\u0002\"\u001d\u00051AH]8pizJ\u0011!G\u0005\u0003Ia\tq\u0001]1dW\u0006<W-\u0003\u0002\'O\ta1+\u001a:jC2L\'0\u00192mK*\u0011A\u0005G\u0001\u0007y%t\u0017\u000e\u001e \u0015\u0003=\tQ\u0002\u001d:pIV\u001cG\u000f\u0015:fM&DX#\u0001\u0017\u0011\u00055\u0012T\"\u0001\u0018\u000b\u0005=\u0002\u0014\u0001\u00027b]\u001eT\u0011!M\u0001\u0005U\u00064\u0018-\u0003\u00024]\t11\u000b\u001e:j]\u001e\fA\u0002\u001d:pIV\u001cG/\u0011:jif,\u0012A\u000e\t\u0003/]J!\u0001\u000f\r\u0003\u0007%sG/\u0001\bqe>$Wo\u0019;FY\u0016lWM\u001c;\u0015\u0005mr\u0004CA\f=\u0013\ti\u0004DA\u0002B]fDqaP\u0003\u0002\u0002\u0003\u0007a\'A\u0002yIE\nq\u0002\u001d:pIV\u001cG/\u0013;fe\u0006$xN]\u000b\u0002\u0005B\u00191IR\u001e\u000e\u0003\u0011S!!\u0012\r\u0002\u0015\r|G\u000e\\3di&|g.\u0003\u0002H\t\nA\u0011\n^3sCR|\'/\u0001\u0005dC:,\u0015/^1m)\tQU\n\u0005\u0002\u0018\u0017&\u0011A\n\u0007\u0002\b\u0005>|G.Z1o\u0011\u001dyt!!AA\u0002m\n\u0001\u0002[1tQ\u000e{G-\u001a\u000b\u0002m\u0005AAo\\*ue&tw\rF\u0001-\u000319(/\u001b;f%\u0016\u0004H.Y2f)\u0005!\u0006CA\u0017V\u0013\t1fF\u0001\u0004PE*,7\r\u001e"
    )
  ScalaSig: length = 0x3 (unknown attribute)
   05 02 00
