Classfile /Users/mw/Projects/slang-braindump/.jar/jar11/assemble/slang-braindump/assemble/content/argonaut/CursorOpDeleteGoParent.class
  Last modified May 29, 2022; size 2565 bytes
  SHA-256 checksum cd62e36d7491c34e663041e5526d65e0018e2c13ee0e272892e4f2424bb4d185
  Compiled from "CursorOpElement.scala"
public final class argonaut.CursorOpDeleteGoParent
  minor version: 0
  major version: 52
  flags: (0x0031) ACC_PUBLIC, ACC_FINAL, ACC_SUPER
  this_class: #2                          // argonaut/CursorOpDeleteGoParent
  super_class: #4                         // java/lang/Object
  interfaces: 0, fields: 0, methods: 21, attributes: 3
Constant pool:
   #1 = Utf8               argonaut/CursorOpDeleteGoParent
   #2 = Class              #1             // argonaut/CursorOpDeleteGoParent
   #3 = Utf8               java/lang/Object
   #4 = Class              #3             // java/lang/Object
   #5 = Utf8               CursorOpElement.scala
   #6 = Utf8               Lscala/reflect/ScalaSignature;
   #7 = Utf8               bytes
   #8 = Utf8               \u0006\u0005];Qa\u0003\u0007\t\u0002>1Q!\u0005\u0007\t\u0002JAQ\u0001K\u0001\u0005\u0002%BqAK\u0001\u0002\u0002\u0013\u00053\u0006C\u00045\u0003\u0005\u0005I\u0011A\u001b\t\u000fe\n\u0011\u0011!C\u0001u!9\u0001)AA\u0001\n\u0003\n\u0005b\u0002%\u0002\u0003\u0003%\t!\u0013\u0005\b\u001d\u0006\t\t\u0011\"\u0011P\u0011\u001d\u0001\u0016!!A\u0005BECqAU\u0001\u0002\u0002\u0013%1+\u0001\fDkJ\u001cxN](q\t\u0016dW\r^3H_B\u000b\'/\u001a8u\u0015\u0005i\u0011\u0001C1sO>t\u0017-\u001e;\u0004\u0001A\u0011\u0001#A\u0007\u0002\u0019\t12)\u001e:t_J|\u0005\u000fR3mKR,wi\u001c)be\u0016tGo\u0005\u0003\u0002\'Ya\u0002C\u0001\t\u0015\u0013\t)BBA\bDkJ\u001cxN](q\u000b2,W.\u001a8u!\t9\"$D\u0001\u0019\u0015\u0005I\u0012!B:dC2\f\u0017BA\u000e\u0019\u0005\u001d\u0001&o\u001c3vGR\u0004\"!H\u0013\u000f\u0005y\u0019cBA\u0010#\u001b\u0005\u0001#BA\u0011\u000f\u0003\u0019a$o\\8u}%\t\u0011$\u0003\u0002%1\u00059\u0001/Y2lC\u001e,\u0017B\u0001\u0014(\u00051\u0019VM]5bY&T\u0018M\u00197f\u0015\t!\u0003$\u0001\u0004=S:LGO\u0010\u000b\u0002\u001f\u0005i\u0001O]8ek\u000e$\bK]3gSb,\u0012\u0001\f\t\u0003[Ij\u0011A\f\u0006\u0003_A\nA\u0001\\1oO*\t\u0011\'\u0001\u0003kCZ\f\u0017BA\u001a/\u0005\u0019\u0019FO]5oO\u0006a\u0001O]8ek\u000e$\u0018I]5usV\ta\u0007\u0005\u0002\u0018o%\u0011\u0001\b\u0007\u0002\u0004\u0013:$\u0018A\u00049s_\u0012,8\r^#mK6,g\u000e\u001e\u000b\u0003wy\u0002\"a\u0006\u001f\n\u0005uB\"aA!os\"9q(BA\u0001\u0002\u00041\u0014a\u0001=%c\u0005y\u0001O]8ek\u000e$\u0018\n^3sCR|\'/F\u0001C!\r\u0019eiO\u0007\u0002\t*\u0011Q\tG\u0001\u000bG>dG.Z2uS>t\u0017BA$E\u0005!IE/\u001a:bi>\u0014\u0018\u0001C2b]\u0016\u000bX/\u00197\u0015\u0005)k\u0005CA\fL\u0013\ta\u0005DA\u0004C_>dW-\u00198\t\u000f}:\u0011\u0011!a\u0001w\u0005A\u0001.Y:i\u0007>$W\rF\u00017\u0003!!xn\u0015;sS:<G#\u0001\u0017\u0002\u0019]\u0014\u0018\u000e^3SKBd\u0017mY3\u0015\u0003Q\u0003\"!L+\n\u0005Ys#AB(cU\u0016\u001cG\u000f
   #9 = Utf8               toString
  #10 = Utf8               ()Ljava/lang/String;
  #11 = Utf8               argonaut/CursorOpDeleteGoParent$
  #12 = Class              #11            // argonaut/CursorOpDeleteGoParent$
  #13 = Utf8               MODULE$
  #14 = Utf8               Largonaut/CursorOpDeleteGoParent$;
  #15 = NameAndType        #13:#14        // MODULE$:Largonaut/CursorOpDeleteGoParent$;
  #16 = Fieldref           #12.#15        // argonaut/CursorOpDeleteGoParent$.MODULE$:Largonaut/CursorOpDeleteGoParent$;
  #17 = NameAndType        #9:#10         // toString:()Ljava/lang/String;
  #18 = Methodref          #12.#17        // argonaut/CursorOpDeleteGoParent$.toString:()Ljava/lang/String;
  #19 = Utf8               hashCode
  #20 = Utf8               ()I
  #21 = NameAndType        #19:#20        // hashCode:()I
  #22 = Methodref          #12.#21        // argonaut/CursorOpDeleteGoParent$.hashCode:()I
  #23 = Utf8               canEqual
  #24 = Utf8               (Ljava/lang/Object;)Z
  #25 = Utf8               x$1
  #26 = NameAndType        #23:#24        // canEqual:(Ljava/lang/Object;)Z
  #27 = Methodref          #12.#26        // argonaut/CursorOpDeleteGoParent$.canEqual:(Ljava/lang/Object;)Z
  #28 = Utf8               productIterator
  #29 = Utf8               ()Lscala/collection/Iterator;
  #30 = Utf8               ()Lscala/collection/Iterator<Ljava/lang/Object;>;
  #31 = NameAndType        #28:#29        // productIterator:()Lscala/collection/Iterator;
  #32 = Methodref          #12.#31        // argonaut/CursorOpDeleteGoParent$.productIterator:()Lscala/collection/Iterator;
  #33 = Utf8               productElement
  #34 = Utf8               (I)Ljava/lang/Object;
  #35 = NameAndType        #33:#34        // productElement:(I)Ljava/lang/Object;
  #36 = Methodref          #12.#35        // argonaut/CursorOpDeleteGoParent$.productElement:(I)Ljava/lang/Object;
  #37 = Utf8               productArity
  #38 = NameAndType        #37:#20        // productArity:()I
  #39 = Methodref          #12.#38        // argonaut/CursorOpDeleteGoParent$.productArity:()I
  #40 = Utf8               productPrefix
  #41 = NameAndType        #40:#10        // productPrefix:()Ljava/lang/String;
  #42 = Methodref          #12.#41        // argonaut/CursorOpDeleteGoParent$.productPrefix:()Ljava/lang/String;
  #43 = Utf8               isDeleteRights
  #44 = Utf8               ()Z
  #45 = NameAndType        #43:#44        // isDeleteRights:()Z
  #46 = Methodref          #12.#45        // argonaut/CursorOpDeleteGoParent$.isDeleteRights:()Z
  #47 = Utf8               isDeleteLefts
  #48 = NameAndType        #47:#44        // isDeleteLefts:()Z
  #49 = Methodref          #12.#48        // argonaut/CursorOpDeleteGoParent$.isDeleteLefts:()Z
  #50 = Utf8               isDeleteGoLast
  #51 = NameAndType        #50:#44        // isDeleteGoLast:()Z
  #52 = Methodref          #12.#51        // argonaut/CursorOpDeleteGoParent$.isDeleteGoLast:()Z
  #53 = Utf8               isDeleteGoFirst
  #54 = NameAndType        #53:#44        // isDeleteGoFirst:()Z
  #55 = Methodref          #12.#54        // argonaut/CursorOpDeleteGoParent$.isDeleteGoFirst:()Z
  #56 = Utf8               isDeleteGoRight
  #57 = NameAndType        #56:#44        // isDeleteGoRight:()Z
  #58 = Methodref          #12.#57        // argonaut/CursorOpDeleteGoParent$.isDeleteGoRight:()Z
  #59 = Utf8               isDeleteGoLeft
  #60 = NameAndType        #59:#44        // isDeleteGoLeft:()Z
  #61 = Methodref          #12.#60        // argonaut/CursorOpDeleteGoParent$.isDeleteGoLeft:()Z
  #62 = Utf8               isDeleteGoParent
  #63 = NameAndType        #62:#44        // isDeleteGoParent:()Z
  #64 = Methodref          #12.#63        // argonaut/CursorOpDeleteGoParent$.isDeleteGoParent:()Z
  #65 = Utf8               isUp
  #66 = NameAndType        #65:#44        // isUp:()Z
  #67 = Methodref          #12.#66        // argonaut/CursorOpDeleteGoParent$.isUp:()Z
  #68 = Utf8               isLast
  #69 = NameAndType        #68:#44        // isLast:()Z
  #70 = Methodref          #12.#69        // argonaut/CursorOpDeleteGoParent$.isLast:()Z
  #71 = Utf8               isFirst
  #72 = NameAndType        #71:#44        // isFirst:()Z
  #73 = Methodref          #12.#72        // argonaut/CursorOpDeleteGoParent$.isFirst:()Z
  #74 = Utf8               isRight
  #75 = NameAndType        #74:#44        // isRight:()Z
  #76 = Methodref          #12.#75        // argonaut/CursorOpDeleteGoParent$.isRight:()Z
  #77 = Utf8               isLeft
  #78 = NameAndType        #77:#44        // isLeft:()Z
  #79 = Methodref          #12.#78        // argonaut/CursorOpDeleteGoParent$.isLeft:()Z
  #80 = Utf8               productElementNames
  #81 = Utf8               ()Lscala/collection/Iterator<Ljava/lang/String;>;
  #82 = NameAndType        #80:#29        // productElementNames:()Lscala/collection/Iterator;
  #83 = Methodref          #12.#82        // argonaut/CursorOpDeleteGoParent$.productElementNames:()Lscala/collection/Iterator;
  #84 = Utf8               productElementName
  #85 = Utf8               (I)Ljava/lang/String;
  #86 = Utf8               n
  #87 = NameAndType        #84:#85        // productElementName:(I)Ljava/lang/String;
  #88 = Methodref          #12.#87        // argonaut/CursorOpDeleteGoParent$.productElementName:(I)Ljava/lang/String;
  #89 = Utf8               Code
  #90 = Utf8               MethodParameters
  #91 = Utf8               Signature
  #92 = Utf8               SourceFile
  #93 = Utf8               RuntimeVisibleAnnotations
  #94 = Utf8               ScalaSig
{
  public static java.lang.String toString();
    descriptor: ()Ljava/lang/String;
    flags: (0x0009) ACC_PUBLIC, ACC_STATIC
    Code:
      stack=1, locals=0, args_size=0
         0: getstatic     #16                 // Field argonaut/CursorOpDeleteGoParent$.MODULE$:Largonaut/CursorOpDeleteGoParent$;
         3: invokevirtual #18                 // Method argonaut/CursorOpDeleteGoParent$.toString:()Ljava/lang/String;
         6: areturn

  public static int hashCode();
    descriptor: ()I
    flags: (0x0009) ACC_PUBLIC, ACC_STATIC
    Code:
      stack=1, locals=0, args_size=0
         0: getstatic     #16                 // Field argonaut/CursorOpDeleteGoParent$.MODULE$:Largonaut/CursorOpDeleteGoParent$;
         3: invokevirtual #22                 // Method argonaut/CursorOpDeleteGoParent$.hashCode:()I
         6: ireturn

  public static boolean canEqual(java.lang.Object);
    descriptor: (Ljava/lang/Object;)Z
    flags: (0x0009) ACC_PUBLIC, ACC_STATIC
    Code:
      stack=2, locals=1, args_size=1
         0: getstatic     #16                 // Field argonaut/CursorOpDeleteGoParent$.MODULE$:Largonaut/CursorOpDeleteGoParent$;
         3: aload_0
         4: invokevirtual #27                 // Method argonaut/CursorOpDeleteGoParent$.canEqual:(Ljava/lang/Object;)Z
         7: ireturn
    MethodParameters:
      Name                           Flags
      x$1                            final

  public static scala.collection.Iterator<java.lang.Object> productIterator();
    descriptor: ()Lscala/collection/Iterator;
    flags: (0x0009) ACC_PUBLIC, ACC_STATIC
    Code:
      stack=1, locals=0, args_size=0
         0: getstatic     #16                 // Field argonaut/CursorOpDeleteGoParent$.MODULE$:Largonaut/CursorOpDeleteGoParent$;
         3: invokevirtual #32                 // Method argonaut/CursorOpDeleteGoParent$.productIterator:()Lscala/collection/Iterator;
         6: areturn
    Signature: #30                          // ()Lscala/collection/Iterator<Ljava/lang/Object;>;

  public static java.lang.Object productElement(int);
    descriptor: (I)Ljava/lang/Object;
    flags: (0x0009) ACC_PUBLIC, ACC_STATIC
    Code:
      stack=2, locals=1, args_size=1
         0: getstatic     #16                 // Field argonaut/CursorOpDeleteGoParent$.MODULE$:Largonaut/CursorOpDeleteGoParent$;
         3: iload_0
         4: invokevirtual #36                 // Method argonaut/CursorOpDeleteGoParent$.productElement:(I)Ljava/lang/Object;
         7: areturn
    MethodParameters:
      Name                           Flags
      x$1                            final

  public static int productArity();
    descriptor: ()I
    flags: (0x0009) ACC_PUBLIC, ACC_STATIC
    Code:
      stack=1, locals=0, args_size=0
         0: getstatic     #16                 // Field argonaut/CursorOpDeleteGoParent$.MODULE$:Largonaut/CursorOpDeleteGoParent$;
         3: invokevirtual #39                 // Method argonaut/CursorOpDeleteGoParent$.productArity:()I
         6: ireturn

  public static java.lang.String productPrefix();
    descriptor: ()Ljava/lang/String;
    flags: (0x0009) ACC_PUBLIC, ACC_STATIC
    Code:
      stack=1, locals=0, args_size=0
         0: getstatic     #16                 // Field argonaut/CursorOpDeleteGoParent$.MODULE$:Largonaut/CursorOpDeleteGoParent$;
         3: invokevirtual #42                 // Method argonaut/CursorOpDeleteGoParent$.productPrefix:()Ljava/lang/String;
         6: areturn

  public static boolean isDeleteRights();
    descriptor: ()Z
    flags: (0x0009) ACC_PUBLIC, ACC_STATIC
    Code:
      stack=1, locals=0, args_size=0
         0: getstatic     #16                 // Field argonaut/CursorOpDeleteGoParent$.MODULE$:Largonaut/CursorOpDeleteGoParent$;
         3: invokevirtual #46                 // Method argonaut/CursorOpDeleteGoParent$.isDeleteRights:()Z
         6: ireturn

  public static boolean isDeleteLefts();
    descriptor: ()Z
    flags: (0x0009) ACC_PUBLIC, ACC_STATIC
    Code:
      stack=1, locals=0, args_size=0
         0: getstatic     #16                 // Field argonaut/CursorOpDeleteGoParent$.MODULE$:Largonaut/CursorOpDeleteGoParent$;
         3: invokevirtual #49                 // Method argonaut/CursorOpDeleteGoParent$.isDeleteLefts:()Z
         6: ireturn

  public static boolean isDeleteGoLast();
    descriptor: ()Z
    flags: (0x0009) ACC_PUBLIC, ACC_STATIC
    Code:
      stack=1, locals=0, args_size=0
         0: getstatic     #16                 // Field argonaut/CursorOpDeleteGoParent$.MODULE$:Largonaut/CursorOpDeleteGoParent$;
         3: invokevirtual #52                 // Method argonaut/CursorOpDeleteGoParent$.isDeleteGoLast:()Z
         6: ireturn

  public static boolean isDeleteGoFirst();
    descriptor: ()Z
    flags: (0x0009) ACC_PUBLIC, ACC_STATIC
    Code:
      stack=1, locals=0, args_size=0
         0: getstatic     #16                 // Field argonaut/CursorOpDeleteGoParent$.MODULE$:Largonaut/CursorOpDeleteGoParent$;
         3: invokevirtual #55                 // Method argonaut/CursorOpDeleteGoParent$.isDeleteGoFirst:()Z
         6: ireturn

  public static boolean isDeleteGoRight();
    descriptor: ()Z
    flags: (0x0009) ACC_PUBLIC, ACC_STATIC
    Code:
      stack=1, locals=0, args_size=0
         0: getstatic     #16                 // Field argonaut/CursorOpDeleteGoParent$.MODULE$:Largonaut/CursorOpDeleteGoParent$;
         3: invokevirtual #58                 // Method argonaut/CursorOpDeleteGoParent$.isDeleteGoRight:()Z
         6: ireturn

  public static boolean isDeleteGoLeft();
    descriptor: ()Z
    flags: (0x0009) ACC_PUBLIC, ACC_STATIC
    Code:
      stack=1, locals=0, args_size=0
         0: getstatic     #16                 // Field argonaut/CursorOpDeleteGoParent$.MODULE$:Largonaut/CursorOpDeleteGoParent$;
         3: invokevirtual #61                 // Method argonaut/CursorOpDeleteGoParent$.isDeleteGoLeft:()Z
         6: ireturn

  public static boolean isDeleteGoParent();
    descriptor: ()Z
    flags: (0x0009) ACC_PUBLIC, ACC_STATIC
    Code:
      stack=1, locals=0, args_size=0
         0: getstatic     #16                 // Field argonaut/CursorOpDeleteGoParent$.MODULE$:Largonaut/CursorOpDeleteGoParent$;
         3: invokevirtual #64                 // Method argonaut/CursorOpDeleteGoParent$.isDeleteGoParent:()Z
         6: ireturn

  public static boolean isUp();
    descriptor: ()Z
    flags: (0x0009) ACC_PUBLIC, ACC_STATIC
    Code:
      stack=1, locals=0, args_size=0
         0: getstatic     #16                 // Field argonaut/CursorOpDeleteGoParent$.MODULE$:Largonaut/CursorOpDeleteGoParent$;
         3: invokevirtual #67                 // Method argonaut/CursorOpDeleteGoParent$.isUp:()Z
         6: ireturn

  public static boolean isLast();
    descriptor: ()Z
    flags: (0x0009) ACC_PUBLIC, ACC_STATIC
    Code:
      stack=1, locals=0, args_size=0
         0: getstatic     #16                 // Field argonaut/CursorOpDeleteGoParent$.MODULE$:Largonaut/CursorOpDeleteGoParent$;
         3: invokevirtual #70                 // Method argonaut/CursorOpDeleteGoParent$.isLast:()Z
         6: ireturn

  public static boolean isFirst();
    descriptor: ()Z
    flags: (0x0009) ACC_PUBLIC, ACC_STATIC
    Code:
      stack=1, locals=0, args_size=0
         0: getstatic     #16                 // Field argonaut/CursorOpDeleteGoParent$.MODULE$:Largonaut/CursorOpDeleteGoParent$;
         3: invokevirtual #73                 // Method argonaut/CursorOpDeleteGoParent$.isFirst:()Z
         6: ireturn

  public static boolean isRight();
    descriptor: ()Z
    flags: (0x0009) ACC_PUBLIC, ACC_STATIC
    Code:
      stack=1, locals=0, args_size=0
         0: getstatic     #16                 // Field argonaut/CursorOpDeleteGoParent$.MODULE$:Largonaut/CursorOpDeleteGoParent$;
         3: invokevirtual #76                 // Method argonaut/CursorOpDeleteGoParent$.isRight:()Z
         6: ireturn

  public static boolean isLeft();
    descriptor: ()Z
    flags: (0x0009) ACC_PUBLIC, ACC_STATIC
    Code:
      stack=1, locals=0, args_size=0
         0: getstatic     #16                 // Field argonaut/CursorOpDeleteGoParent$.MODULE$:Largonaut/CursorOpDeleteGoParent$;
         3: invokevirtual #79                 // Method argonaut/CursorOpDeleteGoParent$.isLeft:()Z
         6: ireturn

  public static scala.collection.Iterator<java.lang.String> productElementNames();
    descriptor: ()Lscala/collection/Iterator;
    flags: (0x0009) ACC_PUBLIC, ACC_STATIC
    Code:
      stack=1, locals=0, args_size=0
         0: getstatic     #16                 // Field argonaut/CursorOpDeleteGoParent$.MODULE$:Largonaut/CursorOpDeleteGoParent$;
         3: invokevirtual #83                 // Method argonaut/CursorOpDeleteGoParent$.productElementNames:()Lscala/collection/Iterator;
         6: areturn
    Signature: #81                          // ()Lscala/collection/Iterator<Ljava/lang/String;>;

  public static java.lang.String productElementName(int);
    descriptor: (I)Ljava/lang/String;
    flags: (0x0009) ACC_PUBLIC, ACC_STATIC
    Code:
      stack=2, locals=1, args_size=1
         0: getstatic     #16                 // Field argonaut/CursorOpDeleteGoParent$.MODULE$:Largonaut/CursorOpDeleteGoParent$;
         3: iload_0
         4: invokevirtual #88                 // Method argonaut/CursorOpDeleteGoParent$.productElementName:(I)Ljava/lang/String;
         7: areturn
    MethodParameters:
      Name                           Flags
      n                              final
}
SourceFile: "CursorOpElement.scala"
RuntimeVisibleAnnotations:
  0: #6(#7=s#8)
    scala.reflect.ScalaSignature(
      bytes="\u0006\u0005];Qa\u0003\u0007\t\u0002>1Q!\u0005\u0007\t\u0002JAQ\u0001K\u0001\u0005\u0002%BqAK\u0001\u0002\u0002\u0013\u00053\u0006C\u00045\u0003\u0005\u0005I\u0011A\u001b\t\u000fe\n\u0011\u0011!C\u0001u!9\u0001)AA\u0001\n\u0003\n\u0005b\u0002%\u0002\u0003\u0003%\t!\u0013\u0005\b\u001d\u0006\t\t\u0011\"\u0011P\u0011\u001d\u0001\u0016!!A\u0005BECqAU\u0001\u0002\u0002\u0013%1+\u0001\fDkJ\u001cxN](q\t\u0016dW\r^3H_B\u000b\'/\u001a8u\u0015\u0005i\u0011\u0001C1sO>t\u0017-\u001e;\u0004\u0001A\u0011\u0001#A\u0007\u0002\u0019\t12)\u001e:t_J|\u0005\u000fR3mKR,wi\u001c)be\u0016tGo\u0005\u0003\u0002\'Ya\u0002C\u0001\t\u0015\u0013\t)BBA\bDkJ\u001cxN](q\u000b2,W.\u001a8u!\t9\"$D\u0001\u0019\u0015\u0005I\u0012!B:dC2\f\u0017BA\u000e\u0019\u0005\u001d\u0001&o\u001c3vGR\u0004\"!H\u0013\u000f\u0005y\u0019cBA\u0010#\u001b\u0005\u0001#BA\u0011\u000f\u0003\u0019a$o\\8u}%\t\u0011$\u0003\u0002%1\u00059\u0001/Y2lC\u001e,\u0017B\u0001\u0014(\u00051\u0019VM]5bY&T\u0018M\u00197f\u0015\t!\u0003$\u0001\u0004=S:LGO\u0010\u000b\u0002\u001f\u0005i\u0001O]8ek\u000e$\bK]3gSb,\u0012\u0001\f\t\u0003[Ij\u0011A\f\u0006\u0003_A\nA\u0001\\1oO*\t\u0011\'\u0001\u0003kCZ\f\u0017BA\u001a/\u0005\u0019\u0019FO]5oO\u0006a\u0001O]8ek\u000e$\u0018I]5usV\ta\u0007\u0005\u0002\u0018o%\u0011\u0001\b\u0007\u0002\u0004\u0013:$\u0018A\u00049s_\u0012,8\r^#mK6,g\u000e\u001e\u000b\u0003wy\u0002\"a\u0006\u001f\n\u0005uB\"aA!os\"9q(BA\u0001\u0002\u00041\u0014a\u0001=%c\u0005y\u0001O]8ek\u000e$\u0018\n^3sCR|\'/F\u0001C!\r\u0019eiO\u0007\u0002\t*\u0011Q\tG\u0001\u000bG>dG.Z2uS>t\u0017BA$E\u0005!IE/\u001a:bi>\u0014\u0018\u0001C2b]\u0016\u000bX/\u00197\u0015\u0005)k\u0005CA\fL\u0013\ta\u0005DA\u0004C_>dW-\u00198\t\u000f}:\u0011\u0011!a\u0001w\u0005A\u0001.Y:i\u0007>$W\rF\u00017\u0003!!xn\u0015;sS:<G#\u0001\u0017\u0002\u0019]\u0014\u0018\u000e^3SKBd\u0017mY3\u0015\u0003Q\u0003\"!L+\n\u0005Ys#AB(cU\u0016\u001cG\u000f"
    )
  ScalaSig: length = 0x3 (unknown attribute)
   05 02 00
