Classfile /Users/mw/Projects/slang-braindump/.jar/jar11/assemble/slang-braindump/assemble/content/argonaut/EncodeJsonNumber$$anon$5.class
  Last modified May 29, 2022; size 1276 bytes
  SHA-256 checksum dadc25cf6a2e197b145b98f613f35b0d77b46ac64fb5f1059300ef0ed5ab4bf6
  Compiled from "JsonNumber.scala"
public final class argonaut.EncodeJsonNumber$$anon$5 extends java.lang.Object implements argonaut.EncodePossibleJsonNumber<java.lang.Float>
  minor version: 0
  major version: 52
  flags: (0x0031) ACC_PUBLIC, ACC_FINAL, ACC_SUPER
  this_class: #2                          // argonaut/EncodeJsonNumber$$anon$5
  super_class: #5                         // java/lang/Object
  interfaces: 1, fields: 0, methods: 3, attributes: 6
Constant pool:
   #1 = Utf8               argonaut/EncodeJsonNumber$$anon$5
   #2 = Class              #1             // argonaut/EncodeJsonNumber$$anon$5
   #3 = Utf8               Ljava/lang/Object;Largonaut/EncodePossibleJsonNumber<Ljava/lang/Float;>;
   #4 = Utf8               java/lang/Object
   #5 = Class              #4             // java/lang/Object
   #6 = Utf8               argonaut/EncodePossibleJsonNumber
   #7 = Class              #6             // argonaut/EncodePossibleJsonNumber
   #8 = Utf8               JsonNumber.scala
   #9 = Utf8               argonaut/EncodeJsonNumber$
  #10 = Class              #9             // argonaut/EncodeJsonNumber$
  #11 = Utf8               possiblyEncodeJsonNumber
  #12 = Utf8               (Ljava/lang/Float;)Lscala/Option;
  #13 = Utf8               (Ljava/lang/Float;)Lscala/Option<Largonaut/JsonNumber;>;
  #14 = Utf8               value
  #15 = Utf8               MODULE$
  #16 = Utf8               Largonaut/EncodeJsonNumber$;
  #17 = NameAndType        #15:#16        // MODULE$:Largonaut/EncodeJsonNumber$;
  #18 = Fieldref           #10.#17        // argonaut/EncodeJsonNumber$.MODULE$:Largonaut/EncodeJsonNumber$;
  #19 = Utf8               encodeJsonNumberFloat
  #20 = Utf8               ()Largonaut/EncodePossibleJsonNumber;
  #21 = NameAndType        #19:#20        // encodeJsonNumberFloat:()Largonaut/EncodePossibleJsonNumber;
  #22 = Methodref          #10.#21        // argonaut/EncodeJsonNumber$.encodeJsonNumberFloat:()Largonaut/EncodePossibleJsonNumber;
  #23 = Utf8               java/lang/Float
  #24 = Class              #23            // java/lang/Float
  #25 = Utf8               floatValue
  #26 = Utf8               ()F
  #27 = NameAndType        #25:#26        // floatValue:()F
  #28 = Methodref          #24.#27        // java/lang/Float.floatValue:()F
  #29 = Utf8               scala/runtime/BoxesRunTime
  #30 = Class              #29            // scala/runtime/BoxesRunTime
  #31 = Utf8               boxToFloat
  #32 = Utf8               (F)Ljava/lang/Float;
  #33 = NameAndType        #31:#32        // boxToFloat:(F)Ljava/lang/Float;
  #34 = Methodref          #30.#33        // scala/runtime/BoxesRunTime.boxToFloat:(F)Ljava/lang/Float;
  #35 = Utf8               (Ljava/lang/Object;)Lscala/Option;
  #36 = NameAndType        #11:#35        // possiblyEncodeJsonNumber:(Ljava/lang/Object;)Lscala/Option;
  #37 = InterfaceMethodref #7.#36         // argonaut/EncodePossibleJsonNumber.possiblyEncodeJsonNumber:(Ljava/lang/Object;)Lscala/Option;
  #38 = Utf8               this
  #39 = Utf8               Largonaut/EncodeJsonNumber$$anon$5;
  #40 = Utf8               Ljava/lang/Float;
  #41 = NameAndType        #11:#12        // possiblyEncodeJsonNumber:(Ljava/lang/Float;)Lscala/Option;
  #42 = Methodref          #2.#41         // argonaut/EncodeJsonNumber$$anon$5.possiblyEncodeJsonNumber:(Ljava/lang/Float;)Lscala/Option;
  #43 = Utf8               Ljava/lang/Object;
  #44 = Utf8               <init>
  #45 = Utf8               ()V
  #46 = NameAndType        #44:#45        // "<init>":()V
  #47 = Methodref          #5.#46         // java/lang/Object."<init>":()V
  #48 = Utf8               Code
  #49 = Utf8               LineNumberTable
  #50 = Utf8               LocalVariableTable
  #51 = Utf8               Signature
  #52 = Utf8               MethodParameters
  #53 = Utf8               InnerClasses
  #54 = Utf8               EnclosingMethod
  #55 = Utf8               SourceFile
  #56 = Utf8               ScalaInlineInfo
  #57 = Utf8               Scala
{
  public scala.Option<argonaut.JsonNumber> possiblyEncodeJsonNumber(java.lang.Float);
    descriptor: (Ljava/lang/Float;)Lscala/Option;
    flags: (0x0001) ACC_PUBLIC
    Code:
      stack=2, locals=2, args_size=2
         0: getstatic     #18                 // Field argonaut/EncodeJsonNumber$.MODULE$:Largonaut/EncodeJsonNumber$;
         3: invokevirtual #22                 // Method argonaut/EncodeJsonNumber$.encodeJsonNumberFloat:()Largonaut/EncodePossibleJsonNumber;
         6: aload_1
         7: invokevirtual #28                 // Method java/lang/Float.floatValue:()F
        10: invokestatic  #34                 // Method scala/runtime/BoxesRunTime.boxToFloat:(F)Ljava/lang/Float;
        13: invokeinterface #37,  2           // InterfaceMethod argonaut/EncodePossibleJsonNumber.possiblyEncodeJsonNumber:(Ljava/lang/Object;)Lscala/Option;
        18: areturn
      LineNumberTable:
        line 402: 0
      LocalVariableTable:
        Start  Length  Slot  Name   Signature
            0      19     0  this   Largonaut/EncodeJsonNumber$$anon$5;
            0      19     1 value   Ljava/lang/Float;
    Signature: #13                          // (Ljava/lang/Float;)Lscala/Option<Largonaut/JsonNumber;>;
    MethodParameters:
      Name                           Flags
      value                          final

  public scala.Option possiblyEncodeJsonNumber(java.lang.Object);
    descriptor: (Ljava/lang/Object;)Lscala/Option;
    flags: (0x1041) ACC_PUBLIC, ACC_BRIDGE, ACC_SYNTHETIC
    Code:
      stack=2, locals=2, args_size=2
         0: aload_0
         1: aload_1
         2: checkcast     #24                 // class java/lang/Float
         5: invokevirtual #42                 // Method possiblyEncodeJsonNumber:(Ljava/lang/Float;)Lscala/Option;
         8: areturn
      LineNumberTable:
        line 401: 0
      LocalVariableTable:
        Start  Length  Slot  Name   Signature
            0       9     0  this   Largonaut/EncodeJsonNumber$$anon$5;
            0       9     1 value   Ljava/lang/Object;
    MethodParameters:
      Name                           Flags
      value                          final

  public argonaut.EncodeJsonNumber$$anon$5();
    descriptor: ()V
    flags: (0x0001) ACC_PUBLIC
    Code:
      stack=1, locals=1, args_size=1
         0: aload_0
         1: invokespecial #47                 // Method java/lang/Object."<init>":()V
         4: return
      LineNumberTable:
        line 401: 0
      LocalVariableTable:
        Start  Length  Slot  Name   Signature
            0       5     0  this   Largonaut/EncodeJsonNumber$$anon$5;
}
InnerClasses:
  public final #2;                        // class argonaut/EncodeJsonNumber$$anon$5
EnclosingMethod: #10.#0                 // argonaut.EncodeJsonNumber$
Signature: #3                           // Ljava/lang/Object;Largonaut/EncodePossibleJsonNumber<Ljava/lang/Float;>;
SourceFile: "JsonNumber.scala"
  ScalaInlineInfo: length = 0x13 (unknown attribute)
   01 01 00 03 00 2C 00 2D 01 00 0B 00 0C 01 00 0B
   00 23 01
  Scala: length = 0x0 (unknown attribute)

