Classfile /Users/mw/Projects/slang-braindump/.jar/jar11/assemble/slang-braindump/assemble/content/argonaut/JsonParser$JsonObjectBuilder$.class
  Last modified May 29, 2022; size 4173 bytes
  SHA-256 checksum 291ece323fd950ffc30e341d2f6d7733fa64806e525511f684150d37fedef79d
  Compiled from "JsonParser.scala"
public class argonaut.JsonParser$JsonObjectBuilder$ extends scala.runtime.AbstractFunction2<scala.collection.mutable.Builder<scala.Tuple2<java.lang.String, argonaut.Json>, scala.collection.immutable.Map<java.lang.String, argonaut.Json>>, scala.collection.mutable.Builder<java.lang.String, scala.collection.immutable.Vector<java.lang.String>>, argonaut.JsonParser$JsonObjectBuilder> implements java.io.Serializable
  minor version: 0
  major version: 52
  flags: (0x0021) ACC_PUBLIC, ACC_SUPER
  this_class: #2                          // argonaut/JsonParser$JsonObjectBuilder$
  super_class: #5                         // scala/runtime/AbstractFunction2
  interfaces: 1, fields: 1, methods: 11, attributes: 5
Constant pool:
    #1 = Utf8               argonaut/JsonParser$JsonObjectBuilder$
    #2 = Class              #1            // argonaut/JsonParser$JsonObjectBuilder$
    #3 = Utf8               Lscala/runtime/AbstractFunction2<Lscala/collection/mutable/Builder<Lscala/Tuple2<Ljava/lang/String;Largonaut/Json;>;Lscala/collection/immutable/Map<Ljava/lang/String;Largonaut/Json;>;>;Lscala/collection/mutable/Builder<Ljava/lang/String;Lscala/collection/immutable/Vector<Ljava/lang/String;>;>;Largonaut/JsonParser$JsonObjectBuilder;>;Ljava/io/Serializable;
    #4 = Utf8               scala/runtime/AbstractFunction2
    #5 = Class              #4            // scala/runtime/AbstractFunction2
    #6 = Utf8               java/io/Serializable
    #7 = Class              #6            // java/io/Serializable
    #8 = Utf8               JsonParser.scala
    #9 = Utf8               argonaut/JsonParser$JsonObjectBuilder
   #10 = Class              #9            // argonaut/JsonParser$JsonObjectBuilder
   #11 = Utf8               argonaut/JsonParser
   #12 = Class              #11           // argonaut/JsonParser
   #13 = Utf8               JsonObjectBuilder
   #14 = Utf8               JsonObjectBuilder$
   #15 = Utf8               MODULE$
   #16 = Utf8               Largonaut/JsonParser$JsonObjectBuilder$;
   #17 = Utf8               <clinit>
   #18 = Utf8               ()V
   #19 = Utf8               <init>
   #20 = NameAndType        #19:#18       // "<init>":()V
   #21 = Methodref          #2.#20        // argonaut/JsonParser$JsonObjectBuilder$."<init>":()V
   #22 = NameAndType        #15:#16       // MODULE$:Largonaut/JsonParser$JsonObjectBuilder$;
   #23 = Fieldref           #2.#22        // argonaut/JsonParser$JsonObjectBuilder$.MODULE$:Largonaut/JsonParser$JsonObjectBuilder$;
   #24 = Utf8               $lessinit$greater$default$1
   #25 = Utf8               ()Lscala/collection/mutable/Builder;
   #26 = Utf8               ()Lscala/collection/mutable/Builder<Lscala/Tuple2<Ljava/lang/String;Largonaut/Json;>;Lscala/collection/immutable/Map<Ljava/lang/String;Largonaut/Json;>;>;
   #27 = Utf8               scala/Predef$
   #28 = Class              #27           // scala/Predef$
   #29 = Utf8               Lscala/Predef$;
   #30 = NameAndType        #15:#29       // MODULE$:Lscala/Predef$;
   #31 = Fieldref           #28.#30       // scala/Predef$.MODULE$:Lscala/Predef$;
   #32 = Utf8               Map
   #33 = Utf8               ()Lscala/collection/immutable/Map$;
   #34 = NameAndType        #32:#33       // Map:()Lscala/collection/immutable/Map$;
   #35 = Methodref          #28.#34       // scala/Predef$.Map:()Lscala/collection/immutable/Map$;
   #36 = Utf8               scala/collection/immutable/Map$
   #37 = Class              #36           // scala/collection/immutable/Map$
   #38 = Utf8               newBuilder
   #39 = NameAndType        #38:#25       // newBuilder:()Lscala/collection/mutable/Builder;
   #40 = Methodref          #37.#39       // scala/collection/immutable/Map$.newBuilder:()Lscala/collection/mutable/Builder;
   #41 = Utf8               this
   #42 = Utf8               $lessinit$greater$default$2
   #43 = Utf8               ()Lscala/collection/mutable/Builder<Ljava/lang/String;Lscala/collection/immutable/Vector<Ljava/lang/String;>;>;
   #44 = Utf8               scala/package$
   #45 = Class              #44           // scala/package$
   #46 = Utf8               Lscala/package$;
   #47 = NameAndType        #15:#46       // MODULE$:Lscala/package$;
   #48 = Fieldref           #45.#47       // scala/package$.MODULE$:Lscala/package$;
   #49 = Utf8               Vector
   #50 = Utf8               ()Lscala/collection/immutable/Vector$;
   #51 = NameAndType        #49:#50       // Vector:()Lscala/collection/immutable/Vector$;
   #52 = Methodref          #45.#51       // scala/package$.Vector:()Lscala/collection/immutable/Vector$;
   #53 = Utf8               scala/collection/immutable/Vector$
   #54 = Class              #53           // scala/collection/immutable/Vector$
   #55 = Utf8               ()Lscala/collection/mutable/ReusableBuilder;
   #56 = NameAndType        #38:#55       // newBuilder:()Lscala/collection/mutable/ReusableBuilder;
   #57 = Methodref          #54.#56       // scala/collection/immutable/Vector$.newBuilder:()Lscala/collection/mutable/ReusableBuilder;
   #58 = Utf8               toString
   #59 = Utf8               ()Ljava/lang/String;
   #60 = String             #13           // JsonObjectBuilder
   #61 = Utf8               apply
   #62 = Utf8               (Lscala/collection/mutable/Builder;Lscala/collection/mutable/Builder;)Largonaut/JsonParser$JsonObjectBuilder;
   #63 = Utf8               (Lscala/collection/mutable/Builder<Lscala/Tuple2<Ljava/lang/String;Largonaut/Json;>;Lscala/collection/immutable/Map<Ljava/lang/String;Largonaut/Json;>;>;Lscala/collection/mutable/Builder<Ljava/lang/String;Lscala/collection/immutable/Vector<Ljava/lang/String;>;>;)Largonaut/JsonParser$JsonObjectBuilder;
   #64 = Utf8               fieldsMapBuilder
   #65 = Utf8               orderedFieldsBuilder
   #66 = Utf8               (Lscala/collection/mutable/Builder;Lscala/collection/mutable/Builder;)V
   #67 = NameAndType        #19:#66       // "<init>":(Lscala/collection/mutable/Builder;Lscala/collection/mutable/Builder;)V
   #68 = Methodref          #10.#67       // argonaut/JsonParser$JsonObjectBuilder."<init>":(Lscala/collection/mutable/Builder;Lscala/collection/mutable/Builder;)V
   #69 = Utf8               Lscala/collection/mutable/Builder;
   #70 = Utf8               apply$default$1
   #71 = Utf8               apply$default$2
   #72 = Utf8               unapply
   #73 = Utf8               (Largonaut/JsonParser$JsonObjectBuilder;)Lscala/Option;
   #74 = Utf8               (Largonaut/JsonParser$JsonObjectBuilder;)Lscala/Option<Lscala/Tuple2<Lscala/collection/mutable/Builder<Lscala/Tuple2<Ljava/lang/String;Largonaut/Json;>;Lscala/collection/immutable/Map<Ljava/lang/String;Largonaut/Json;>;>;Lscala/collection/mutable/Builder<Ljava/lang/String;Lscala/collection/immutable/Vector<Ljava/lang/String;>;>;>;>;
   #75 = Utf8               x$0
   #76 = Utf8               scala/None$
   #77 = Class              #76           // scala/None$
   #78 = Utf8               Lscala/None$;
   #79 = NameAndType        #15:#78       // MODULE$:Lscala/None$;
   #80 = Fieldref           #77.#79       // scala/None$.MODULE$:Lscala/None$;
   #81 = Utf8               scala/Some
   #82 = Class              #81           // scala/Some
   #83 = Utf8               scala/Tuple2
   #84 = Class              #83           // scala/Tuple2
   #85 = NameAndType        #64:#25       // fieldsMapBuilder:()Lscala/collection/mutable/Builder;
   #86 = Methodref          #10.#85       // argonaut/JsonParser$JsonObjectBuilder.fieldsMapBuilder:()Lscala/collection/mutable/Builder;
   #87 = NameAndType        #65:#25       // orderedFieldsBuilder:()Lscala/collection/mutable/Builder;
   #88 = Methodref          #10.#87       // argonaut/JsonParser$JsonObjectBuilder.orderedFieldsBuilder:()Lscala/collection/mutable/Builder;
   #89 = Utf8               (Ljava/lang/Object;Ljava/lang/Object;)V
   #90 = NameAndType        #19:#89       // "<init>":(Ljava/lang/Object;Ljava/lang/Object;)V
   #91 = Methodref          #84.#90       // scala/Tuple2."<init>":(Ljava/lang/Object;Ljava/lang/Object;)V
   #92 = Utf8               (Ljava/lang/Object;)V
   #93 = NameAndType        #19:#92       // "<init>":(Ljava/lang/Object;)V
   #94 = Methodref          #82.#93       // scala/Some."<init>":(Ljava/lang/Object;)V
   #95 = Utf8               Largonaut/JsonParser$JsonObjectBuilder;
   #96 = Utf8               scala/Option
   #97 = Class              #96           // scala/Option
   #98 = Utf8               writeReplace
   #99 = Utf8               ()Ljava/lang/Object;
  #100 = Utf8               scala/runtime/ModuleSerializationProxy
  #101 = Class              #100          // scala/runtime/ModuleSerializationProxy
  #102 = Utf8               (Ljava/lang/Class;)V
  #103 = NameAndType        #19:#102      // "<init>":(Ljava/lang/Class;)V
  #104 = Methodref          #101.#103     // scala/runtime/ModuleSerializationProxy."<init>":(Ljava/lang/Class;)V
  #105 = Utf8               (Ljava/lang/Object;Ljava/lang/Object;)Ljava/lang/Object;
  #106 = Utf8               v1
  #107 = Utf8               v2
  #108 = Utf8               scala/collection/mutable/Builder
  #109 = Class              #108          // scala/collection/mutable/Builder
  #110 = NameAndType        #61:#62       // apply:(Lscala/collection/mutable/Builder;Lscala/collection/mutable/Builder;)Largonaut/JsonParser$JsonObjectBuilder;
  #111 = Methodref          #2.#110       // argonaut/JsonParser$JsonObjectBuilder$.apply:(Lscala/collection/mutable/Builder;Lscala/collection/mutable/Builder;)Largonaut/JsonParser$JsonObjectBuilder;
  #112 = Utf8               Ljava/lang/Object;
  #113 = Methodref          #5.#20        // scala/runtime/AbstractFunction2."<init>":()V
  #114 = Utf8               Code
  #115 = Utf8               LineNumberTable
  #116 = Utf8               LocalVariableTable
  #117 = Utf8               Signature
  #118 = Utf8               MethodParameters
  #119 = Utf8               StackMapTable
  #120 = Utf8               InnerClasses
  #121 = Utf8               SourceFile
  #122 = Utf8               ScalaInlineInfo
  #123 = Utf8               Scala
{
  public static final argonaut.JsonParser$JsonObjectBuilder$ MODULE$;
    descriptor: Largonaut/JsonParser$JsonObjectBuilder$;
    flags: (0x0019) ACC_PUBLIC, ACC_STATIC, ACC_FINAL

  public static {};
    descriptor: ()V
    flags: (0x0009) ACC_PUBLIC, ACC_STATIC
    Code:
      stack=2, locals=0, args_size=0
         0: new           #2                  // class argonaut/JsonParser$JsonObjectBuilder$
         3: dup
         4: invokespecial #21                 // Method "<init>":()V
         7: putstatic     #23                 // Field MODULE$:Largonaut/JsonParser$JsonObjectBuilder$;
        10: return
      LineNumberTable:
        line 13: 0

  public scala.collection.mutable.Builder<scala.Tuple2<java.lang.String, argonaut.Json>, scala.collection.immutable.Map<java.lang.String, argonaut.Json>> $lessinit$greater$default$1();
    descriptor: ()Lscala/collection/mutable/Builder;
    flags: (0x0001) ACC_PUBLIC
    Code:
      stack=1, locals=1, args_size=1
         0: getstatic     #31                 // Field scala/Predef$.MODULE$:Lscala/Predef$;
         3: invokevirtual #35                 // Method scala/Predef$.Map:()Lscala/collection/immutable/Map$;
         6: invokevirtual #40                 // Method scala/collection/immutable/Map$.newBuilder:()Lscala/collection/mutable/Builder;
         9: areturn
      LineNumberTable:
        line 14: 0
      LocalVariableTable:
        Start  Length  Slot  Name   Signature
            0      10     0  this   Largonaut/JsonParser$JsonObjectBuilder$;
    Signature: #26                          // ()Lscala/collection/mutable/Builder<Lscala/Tuple2<Ljava/lang/String;Largonaut/Json;>;Lscala/collection/immutable/Map<Ljava/lang/String;Largonaut/Json;>;>;

  public scala.collection.mutable.Builder<java.lang.String, scala.collection.immutable.Vector<java.lang.String>> $lessinit$greater$default$2();
    descriptor: ()Lscala/collection/mutable/Builder;
    flags: (0x0001) ACC_PUBLIC
    Code:
      stack=1, locals=1, args_size=1
         0: getstatic     #48                 // Field scala/package$.MODULE$:Lscala/package$;
         3: invokevirtual #52                 // Method scala/package$.Vector:()Lscala/collection/immutable/Vector$;
         6: invokevirtual #57                 // Method scala/collection/immutable/Vector$.newBuilder:()Lscala/collection/mutable/ReusableBuilder;
         9: areturn
      LineNumberTable:
        line 15: 0
      LocalVariableTable:
        Start  Length  Slot  Name   Signature
            0      10     0  this   Largonaut/JsonParser$JsonObjectBuilder$;
    Signature: #43                          // ()Lscala/collection/mutable/Builder<Ljava/lang/String;Lscala/collection/immutable/Vector<Ljava/lang/String;>;>;

  public final java.lang.String toString();
    descriptor: ()Ljava/lang/String;
    flags: (0x0011) ACC_PUBLIC, ACC_FINAL
    Code:
      stack=1, locals=1, args_size=1
         0: ldc           #60                 // String JsonObjectBuilder
         2: areturn
      LineNumberTable:
        line 13: 0
      LocalVariableTable:
        Start  Length  Slot  Name   Signature
            0       3     0  this   Largonaut/JsonParser$JsonObjectBuilder$;

  public argonaut.JsonParser$JsonObjectBuilder apply(scala.collection.mutable.Builder<scala.Tuple2<java.lang.String, argonaut.Json>, scala.collection.immutable.Map<java.lang.String, argonaut.Json>>, scala.collection.mutable.Builder<java.lang.String, scala.collection.immutable.Vector<java.lang.String>>);
    descriptor: (Lscala/collection/mutable/Builder;Lscala/collection/mutable/Builder;)Largonaut/JsonParser$JsonObjectBuilder;
    flags: (0x0001) ACC_PUBLIC
    Code:
      stack=4, locals=3, args_size=3
         0: new           #10                 // class argonaut/JsonParser$JsonObjectBuilder
         3: dup
         4: aload_1
         5: aload_2
         6: invokespecial #68                 // Method argonaut/JsonParser$JsonObjectBuilder."<init>":(Lscala/collection/mutable/Builder;Lscala/collection/mutable/Builder;)V
         9: areturn
      LineNumberTable:
        line 13: 0
      LocalVariableTable:
        Start  Length  Slot  Name   Signature
            0      10     0  this   Largonaut/JsonParser$JsonObjectBuilder$;
            0      10     1 fieldsMapBuilder   Lscala/collection/mutable/Builder;
            0      10     2 orderedFieldsBuilder   Lscala/collection/mutable/Builder;
    Signature: #63                          // (Lscala/collection/mutable/Builder<Lscala/Tuple2<Ljava/lang/String;Largonaut/Json;>;Lscala/collection/immutable/Map<Ljava/lang/String;Largonaut/Json;>;>;Lscala/collection/mutable/Builder<Ljava/lang/String;Lscala/collection/immutable/Vector<Ljava/lang/String;>;>;)Largonaut/JsonParser$JsonObjectBuilder;
    MethodParameters:
      Name                           Flags
      fieldsMapBuilder               final
      orderedFieldsBuilder           final

  public scala.collection.mutable.Builder<scala.Tuple2<java.lang.String, argonaut.Json>, scala.collection.immutable.Map<java.lang.String, argonaut.Json>> apply$default$1();
    descriptor: ()Lscala/collection/mutable/Builder;
    flags: (0x0001) ACC_PUBLIC
    Code:
      stack=1, locals=1, args_size=1
         0: getstatic     #31                 // Field scala/Predef$.MODULE$:Lscala/Predef$;
         3: invokevirtual #35                 // Method scala/Predef$.Map:()Lscala/collection/immutable/Map$;
         6: invokevirtual #40                 // Method scala/collection/immutable/Map$.newBuilder:()Lscala/collection/mutable/Builder;
         9: areturn
      LineNumberTable:
        line 14: 0
      LocalVariableTable:
        Start  Length  Slot  Name   Signature
            0      10     0  this   Largonaut/JsonParser$JsonObjectBuilder$;
    Signature: #26                          // ()Lscala/collection/mutable/Builder<Lscala/Tuple2<Ljava/lang/String;Largonaut/Json;>;Lscala/collection/immutable/Map<Ljava/lang/String;Largonaut/Json;>;>;

  public scala.collection.mutable.Builder<java.lang.String, scala.collection.immutable.Vector<java.lang.String>> apply$default$2();
    descriptor: ()Lscala/collection/mutable/Builder;
    flags: (0x0001) ACC_PUBLIC
    Code:
      stack=1, locals=1, args_size=1
         0: getstatic     #48                 // Field scala/package$.MODULE$:Lscala/package$;
         3: invokevirtual #52                 // Method scala/package$.Vector:()Lscala/collection/immutable/Vector$;
         6: invokevirtual #57                 // Method scala/collection/immutable/Vector$.newBuilder:()Lscala/collection/mutable/ReusableBuilder;
         9: areturn
      LineNumberTable:
        line 15: 0
      LocalVariableTable:
        Start  Length  Slot  Name   Signature
            0      10     0  this   Largonaut/JsonParser$JsonObjectBuilder$;
    Signature: #43                          // ()Lscala/collection/mutable/Builder<Ljava/lang/String;Lscala/collection/immutable/Vector<Ljava/lang/String;>;>;

  public scala.Option<scala.Tuple2<scala.collection.mutable.Builder<scala.Tuple2<java.lang.String, argonaut.Json>, scala.collection.immutable.Map<java.lang.String, argonaut.Json>>, scala.collection.mutable.Builder<java.lang.String, scala.collection.immutable.Vector<java.lang.String>>>> unapply(argonaut.JsonParser$JsonObjectBuilder);
    descriptor: (Largonaut/JsonParser$JsonObjectBuilder;)Lscala/Option;
    flags: (0x0001) ACC_PUBLIC
    Code:
      stack=6, locals=2, args_size=2
         0: aload_1
         1: ifnonnull     10
         4: getstatic     #80                 // Field scala/None$.MODULE$:Lscala/None$;
         7: goto          32
        10: new           #82                 // class scala/Some
        13: dup
        14: new           #84                 // class scala/Tuple2
        17: dup
        18: aload_1
        19: invokevirtual #86                 // Method argonaut/JsonParser$JsonObjectBuilder.fieldsMapBuilder:()Lscala/collection/mutable/Builder;
        22: aload_1
        23: invokevirtual #88                 // Method argonaut/JsonParser$JsonObjectBuilder.orderedFieldsBuilder:()Lscala/collection/mutable/Builder;
        26: invokespecial #91                 // Method scala/Tuple2."<init>":(Ljava/lang/Object;Ljava/lang/Object;)V
        29: invokespecial #94                 // Method scala/Some."<init>":(Ljava/lang/Object;)V
        32: areturn
      StackMapTable: number_of_entries = 2
        frame_type = 10 /* same */
        frame_type = 85 /* same_locals_1_stack_item */
          stack = [ class scala/Option ]
      LineNumberTable:
        line 13: 0
      LocalVariableTable:
        Start  Length  Slot  Name   Signature
            0      33     0  this   Largonaut/JsonParser$JsonObjectBuilder$;
            0      33     1   x$0   Largonaut/JsonParser$JsonObjectBuilder;
    Signature: #74                          // (Largonaut/JsonParser$JsonObjectBuilder;)Lscala/Option<Lscala/Tuple2<Lscala/collection/mutable/Builder<Lscala/Tuple2<Ljava/lang/String;Largonaut/Json;>;Lscala/collection/immutable/Map<Ljava/lang/String;Largonaut/Json;>;>;Lscala/collection/mutable/Builder<Ljava/lang/String;Lscala/collection/immutable/Vector<Ljava/lang/String;>;>;>;>;
    MethodParameters:
      Name                           Flags
      x$0                            final

  private java.lang.Object writeReplace();
    descriptor: ()Ljava/lang/Object;
    flags: (0x0002) ACC_PRIVATE
    Code:
      stack=3, locals=1, args_size=1
         0: new           #101                // class scala/runtime/ModuleSerializationProxy
         3: dup
         4: ldc           #2                  // class argonaut/JsonParser$JsonObjectBuilder$
         6: invokespecial #104                // Method scala/runtime/ModuleSerializationProxy."<init>":(Ljava/lang/Class;)V
         9: areturn
      LineNumberTable:
        line 13: 0
      LocalVariableTable:
        Start  Length  Slot  Name   Signature
            0      10     0  this   Largonaut/JsonParser$JsonObjectBuilder$;

  public java.lang.Object apply(java.lang.Object, java.lang.Object);
    descriptor: (Ljava/lang/Object;Ljava/lang/Object;)Ljava/lang/Object;
    flags: (0x1041) ACC_PUBLIC, ACC_BRIDGE, ACC_SYNTHETIC
    Code:
      stack=3, locals=3, args_size=3
         0: aload_0
         1: aload_1
         2: checkcast     #109                // class scala/collection/mutable/Builder
         5: aload_2
         6: checkcast     #109                // class scala/collection/mutable/Builder
         9: invokevirtual #111                // Method apply:(Lscala/collection/mutable/Builder;Lscala/collection/mutable/Builder;)Largonaut/JsonParser$JsonObjectBuilder;
        12: areturn
      LineNumberTable:
        line 13: 0
      LocalVariableTable:
        Start  Length  Slot  Name   Signature
            0      13     0  this   Largonaut/JsonParser$JsonObjectBuilder$;
            0      13     1    v1   Ljava/lang/Object;
            0      13     2    v2   Ljava/lang/Object;
    MethodParameters:
      Name                           Flags
      v1                             final
      v2                             final

  public argonaut.JsonParser$JsonObjectBuilder$();
    descriptor: ()V
    flags: (0x0001) ACC_PUBLIC
    Code:
      stack=1, locals=1, args_size=1
         0: aload_0
         1: invokespecial #113                // Method scala/runtime/AbstractFunction2."<init>":()V
         4: return
      LineNumberTable:
        line 13: 0
      LocalVariableTable:
        Start  Length  Slot  Name   Signature
            0       5     0  this   Largonaut/JsonParser$JsonObjectBuilder$;
}
InnerClasses:
  public static #13= #10 of #12;          // JsonObjectBuilder=class argonaut/JsonParser$JsonObjectBuilder of class argonaut/JsonParser
  public static #14= #2 of #12;           // JsonObjectBuilder$=class argonaut/JsonParser$JsonObjectBuilder$ of class argonaut/JsonParser
Signature: #3                           // Lscala/runtime/AbstractFunction2<Lscala/collection/mutable/Builder<Lscala/Tuple2<Ljava/lang/String;Largonaut/Json;>;Lscala/collection/immutable/Map<Ljava/lang/String;Largonaut/Json;>;>;Lscala/collection/mutable/Builder<Ljava/lang/String;Lscala/collection/immutable/Vector<Ljava/lang/String;>;>;Largonaut/JsonParser$JsonObjectBuilder;>;Ljava/io/Serializable;
SourceFile: "JsonParser.scala"
  ScalaInlineInfo: length = 0x36 (unknown attribute)
   01 01 00 0A 00 18 00 19 01 00 2A 00 19 01 00 13
   00 12 01 00 3D 00 69 01 00 3D 00 3E 01 00 46 00
   19 01 00 47 00 19 01 00 3A 00 3B 01 00 48 00 49
   01 00 62 00 63 01
  Scala: length = 0x0 (unknown attribute)

