Classfile /Users/mw/Projects/slang-braindump/.jar/jar11/assemble/slang-braindump/assemble/content/argonaut/JsonParser.class
  Last modified May 29, 2022; size 4849 bytes
  SHA-256 checksum 87c04002ae4bd200f69af10b715689b94248d638f0bbe7059777cb1620f42b80
  Compiled from "JsonParser.scala"
public final class argonaut.JsonParser
  minor version: 0
  major version: 52
  flags: (0x0031) ACC_PUBLIC, ACC_FINAL, ACC_SUPER
  this_class: #2                          // argonaut/JsonParser
  super_class: #4                         // java/lang/Object
  interfaces: 0, fields: 0, methods: 1, attributes: 4
Constant pool:
   #1 = Utf8               argonaut/JsonParser
   #2 = Class              #1             // argonaut/JsonParser
   #3 = Utf8               java/lang/Object
   #4 = Class              #3             // java/lang/Object
   #5 = Utf8               JsonParser.scala
   #6 = Utf8               Lscala/reflect/ScalaSignature;
   #7 = Utf8               bytes
   #8 = Utf8               \u0006\u0005\r}q!\u0002\u001e<\u0011\u0003qd!\u0002!<\u0011\u0003\t\u0005\"\u0002%\u0002\t\u0003IUA\u0002&\u0002A\u000351\n\u0003\u0007W\u0003\u0011\u0005\tQ!A\u0001B\u0003%qK\u0002\u0004h\u0003\u0001\u0006I\t\u001b\u0005\tk\u0016\u0011\t\u001a!C\u0001m\"Q\u0011\u0011E\u0003\u0003\u0002\u0004%\t!a\t\t\u0013\u0005=RA!E!B\u00139\bBCA\u0019\u000b\tE\r\u0011\"\u0001\u00024!Q\u0011QH\u0003\u0003\u0002\u0004%\t!a\u0010\t\u0015\u0005\rSA!E!B\u0013\t)\u0004\u0003\u0004I\u000b\u0011\u0005\u0011Q\t\u0005\t\u0003\u001f*\u0001\u0015)\u0003\u0002R!9\u0011qK\u0003\u0005\u0002\u0005e\u0003bBA2\u000b\u0011\u0005\u0011Q\r\u0005\n\u0003O*\u0011\u0011!C\u0001\u0003SB\u0011\"a\u001c\u0006#\u0003%\t!!\u001d\t\u0013\u0005\u001dU!%A\u0005\u0002\u0005%\u0005\"CAG\u000b\u0005\u0005I\u0011IAH\u0011%\t\t*BA\u0001\n\u0003\t\u0019\nC\u0005\u0002\u001c\u0016\t\t\u0011\"\u0001\u0002\u001e\"I\u0011qU\u0003\u0002\u0002\u0013\u0005\u0013\u0011\u0016\u0005\n\u0003g+\u0011\u0011!C\u0001\u0003kC\u0011\"!/\u0006\u0003\u0003%\t%a/\t\u0013\u0005}V!!A\u0005B\u0005\u0005\u0007\"CAb\u000b\u0005\u0005I\u0011IAc\u0011%\t9-BA\u0001\n\u0003\nImB\u0005\u0002N\u0006\t\t\u0015#\u0003\u0002P\u001aAq-AA!\u0012\u0013\t\t\u000e\u0003\u0004I;\u0011\u0005\u0011\u0011\u001e\u0005\n\u0003\u0007l\u0012\u0011!C#\u0003\u000bD\u0011\"a;\u001e\u0003\u0003%\t)!<\t\u0013\u0005MX$%A\u0005\u0002\u0005E\u0004\"CA{;E\u0005I\u0011AAE\u0011%\t90HA\u0001\n\u0003\u000bI\u0010C\u0005\u0003\bu\t\n\u0011\"\u0001\u0002r!I!\u0011B\u000f\u0012\u0002\u0013\u0005\u0011\u0011\u0012\u0005\n\u0005\u0017i\u0012\u0011!C\u0005\u0005\u001bAaB!\u0006\u0002\t\u0003\u0005)\u0011!A!\n\u001b\u00119\u0002\u0003\b\u0003.\u0005!\t\u0011!B\u0001$\u0003%iAa\f\t\u000f\tM\u0012\u0001\"\u0002\u00036!q!\u0011I\u0001\u0005\u0002\u0003\u0015\t\u0011!Q\u0005\u000e\t\r\u0003B\u0004B5\u0003\u0011\u0005\tQ!A\u0001B\u00135!1\u000e\u0005\t\u0005g\n\u0001\u0015\"\u0004\u0003v!A!QP\u0001!\n\u001b\u0011y\b\u0003\u0005\u0003\b\u0006\u0001KQ\u0002BE\u0011%\u0011i*AI\u0001\n\u001b\u0011y\nC\u0005\u0003$\u0006\t\n\u0011\"\u0004\u0003&\"A!\u0011V\u0001!\n\u001b\u0011Y\u000bC\u0005\u0003@\u0006\t\n\u0011\"\u0004\u0003 \"I!\u0011Y\u0001\u0012\u0002\u00135!1\u0019\u0005\t\u0005\u000f\f\u0001\u0015\"\u0004\u0003J\"A!\u0011[\u0001!\n\u001b\u0011\u0019\u000e\u0003\u0005\u0003`\u0006\u0001KQ\u0002Bq\u00119\u001190\u0001C\u0001\u0002\u000b\u0005\t\u0011)C\u0007\u0005sDaba\u0004\u0002\t\u0003\u0005)\u0011aI\u0001\n\u001b\u0019\t\u0002\u0003\b\u0004\u0016\u0005!\t\u0011!B\u0001\u0002\u0003&iaa\u0006\u0002\u0015)\u001bxN\u001c)beN,\'OC\u0001=\u0003!\t\'oZ8oCV$8\u0001\u0001\t\u0003\u007f\u0005i\u0011a\u000f\u0002\u000b\u0015N|g\u000eU1sg\u0016\u00148CA\u0001C!\t\u0019e)D\u0001E\u0015\u0005)\u0015!B:dC2\f\u0017BA$E\u0005\u0019\te.\u001f*fM\u00061A(\u001b8jiz\"\u0012A\u0010\u0002\f)>\\WM\\*pkJ\u001cW\r\u0005\u0002M\':\u0011Q*\u0015\t\u0003\u001d\u0012k\u0011a\u0014\u0006\u0003!v\na\u0001\u0010:p_Rt\u0014B\u0001*E\u0003\u0019\u0001&/\u001a3fM&\u0011A+\u0016\u0002\u0007\'R\u0014\u0018N\\4\u000b\u0005I#\u0015AK1sO>t\u0017-\u001e;%\u0015N|g\u000eU1sg\u0016\u0014H\u0005J;oKb\u0004Xm\u0019;fIR+\'/\\5oCRLwN\u001c\t\u00051nkF-D\u0001Z\u0015\tQF)\u0001\u0003vi&d\u0017B\u0001/Z\u0005\u0011aUM\u001a;\u0011\u0005y\u001bW\"A0\u000b\u0005\u0001\f\u0017\u0001\u00027b]\u001eT\u0011AY\u0001\u0005U\u00064\u0018-\u0003\u0002U?B\u00111)Z\u0005\u0003M\u0012\u0013qAT8uQ&twMA\tKg>twJ\u00196fGR\u0014U/\u001b7eKJ\u001cB!\u0002\"jYB\u00111I[\u0005\u0003W\u0012\u0013q\u0001\u0015:pIV\u001cG\u000f\u0005\u0002ne:\u0011a\u000e\u001d\b\u0003\u001d>L\u0011!R\u0005\u0003c\u0012\u000bq\u0001]1dW\u0006<W-\u0003\u0002ti\na1+\u001a:jC2L\'0\u00192mK*\u0011\u0011\u000fR\u0001\u0011M&,G\u000eZ:NCB\u0014U/\u001b7eKJ,\u0012a\u001e\t\u0006qv|\u00181D\u0007\u0002s*\u0011!p_\u0001\b[V$\u0018M\u00197f\u0015\taH)\u0001\u0006d_2dWm\u0019;j_:L!A`=\u0003\u000f\t+\u0018\u000e\u001c3feB91)!\u0001\u0002\u0006\u0005U\u0011bAA\u0002\t\n1A+\u001e9mKJ\u0002B!a\u0002\u0002\u000e9\u0019q(!\u0003\n\u0007\u0005-1(\u0001\u0003Kg>t\u0017\u0002BA\b\u0003#\u0011\u0011BS:p]\u001aKW\r\u001c3\n\u0007\u0005M1HA\u0003Kg>t7\u000fE\u0002@\u0003/I1!!\u0007<\u0005\u0011Q5o\u001c8\u0011\u000f1\u000bi\"!\u0002\u0002\u0016%\u0019\u0011qD+\u0003\u00075\u000b\u0007/\u0001\u000bgS\u0016dGm]\'ba\n+\u0018\u000e\u001c3fe~#S-\u001d\u000b\u0005\u0003K\tY\u0003E\u0002D\u0003OI1!!\u000bE\u0005\u0011)f.\u001b;\t\u0011\u00055r!!AA\u0002]\f1\u0001\u001f\u00132\u0003E1\u0017.\u001a7eg6\u000b\u0007OQ;jY\u0012,\'\u000fI\u0001\u0015_J$WM]3e\r&,G\u000eZ:Ck&dG-\u001a:\u0016\u0005\u0005U\u0002C\u0002=~\u0003\u000b\t9\u0004E\u0003n\u0003s\t)!C\u0002\u0002<Q\u0014aAV3di>\u0014\u0018\u0001G8sI\u0016\u0014X\r\u001a$jK2$7OQ;jY\u0012,\'o\u0018\u0013fcR!\u0011QEA!\u0011%\tiCCA\u0001\u0002\u0004\t)$A\u000bpe\u0012,\'/\u001a3GS\u0016dGm\u001d\"vS2$WM\u001d\u0011\u0015\r\u0005\u001d\u00131JA\'!\r\tI%B\u0007\u0002\u0003!9Q\u000f\u0004I\u0001\u0002\u00049\b\"CA\u0019\u0019A\u0005\t\u0019AA\u001b\u0003\u001dI7/R7qif\u00042aQA*\u0013\r\t)\u0006\u0012\u0002\b\u0005>|G.Z1o\u0003\r\tG\r\u001a\u000b\u0007\u0003\u000f\nY&a\u0018\t\u000f\u0005uc\u00021\u0001\u0002\u0006\u0005\u00191.Z=\t\u000f\u0005\u0005d\u00021\u0001\u0002\u0016\u0005)a/\u00197vK\u0006)!-^5mIR\u0011\u0011QC\u0001\u0005G>\u0004\u0018\u0010\u0006\u0004\u0002H\u0005-\u0014Q\u000e\u0005\bkB\u0001\n\u00111\u0001x\u0011%\t\t\u0004\u0005I\u0001\u0002\u0004\t)$\u0001\bd_BLH\u0005Z3gCVdG\u000fJ\u0019\u0016\u0005\u0005M$fA<\u0002v-\u0012\u0011q\u000f\t\u0005\u0003s\n\u0019)\u0004\u0002\u0002|)!\u0011QPA@\u0003%)hn\u00195fG.,GMC\u0002\u0002\u0002\u0012\u000b!\"\u00198o_R\fG/[8o\u0013\u0011\t))a\u001f\u0003#Ut7\r[3dW\u0016$g+\u0019:jC:\u001cW-\u0001\bd_BLH\u0005Z3gCVdG\u000f\n\u001a\u0016\u0005\u0005-%\u0006BA\u001b\u0003k\nQ\u0002\u001d:pIV\u001cG\u000f\u0015:fM&DX#A/\u0002\u0019A\u0014x\u000eZ;di\u0006\u0013\u0018\u000e^=\u0016\u0005\u0005U\u0005cA\"\u0002\u0018&\u0019\u0011\u0011\u0014#\u0003\u0007%sG/\u0001\bqe>$Wo\u0019;FY\u0016lWM\u001c;\u0015\t\u0005}\u0015Q\u0015\t\u0004\u0007\u0006\u0005\u0016bAAR\t\n\u0019\u0011I\\=\t\u0013\u00055R#!AA\u0002\u0005U\u0015a\u00049s_\u0012,8\r^%uKJ\fGo\u001c:\u0016\u0005\u0005-\u0006CBAW\u0003_\u000by*D\u0001|\u0013\r\t\tl\u001f\u0002\t\u0013R,\'/\u0019;pe\u0006A1-\u00198FcV\fG\u000e\u0006\u0003\u0002R\u0005]\u0006\"CA\u0017/\u0005\u0005\t\u0019AAP\u0003I\u0001(o\u001c3vGR,E.Z7f]Rt\u0015-\\3\u0015\u0007u\u000bi\fC\u0005\u0002.a\t\t\u00111\u0001\u0002\u0016\u0006A\u0001.Y:i\u0007>$W\r\u0006\u0002\u0002\u0016\u0006AAo\\*ue&tw\rF\u0001^\u0003\u0019)\u0017/^1mgR!\u0011\u0011KAf\u0011%\ticGA\u0001\u0002\u0004\ty*A\tKg>twJ\u00196fGR\u0014U/\u001b7eKJ\u00042!!\u0013\u001e\'\u0015i\u00121[Ap!%\t).a7x\u0003k\t9%\u0004\u0002\u0002X*\u0019\u0011\u0011\u001c#\u0002\u000fI,h\u000e^5nK&!\u0011Q\\Al\u0005E\t%m\u001d;sC\u000e$h)\u001e8di&|gN\r\t\u0005\u0003C\f9/\u0004\u0002\u0002d*\u0019\u0011Q]1\u0002\u0005%|\u0017bA:\u0002dR\u0011\u0011qZ\u0001\u0006CB\u0004H.\u001f\u000b\u0007\u0003\u000f\ny/!=\t\u000fU\u0004\u0003\u0013!a\u0001o\"I\u0011\u0011\u0007\u0011\u0011\u0002\u0003\u0007\u0011QG\u0001\u0010CB\u0004H.\u001f\u0013eK\u001a\fW\u000f\u001c;%c\u0005y\u0011\r\u001d9ms\u0012\"WMZ1vYR$#\'A\u0004v]\u0006\u0004\b\u000f\\=\u0015\t\u0005m(1\u0001\t\u0006\u0007\u0006u(\u0011A\u0005\u0004\u0003\u007f$%AB(qi&|g\u000e\u0005\u0004D\u0003\u00039\u0018Q\u0007\u0005\n\u0005\u000b\u0019\u0013\u0011!a\u0001\u0003\u000f\n1\u0001\u001f\u00131\u0003m!C.Z:tS:LG\u000fJ4sK\u0006$XM\u001d\u0013eK\u001a\fW\u000f\u001c;%c\u0005YB\u0005\\3tg&t\u0017\u000e\u001e\u0013he\u0016\fG/\u001a:%I\u00164\u0017-\u001e7uII\nAb\u001e:ji\u0016\u0014V\r\u001d7bG\u0016$\"Aa\u0004\u0011\u0007y\u0013\t\"C\u0002\u0003\u0014}\u0013aa\u00142kK\u000e$\u0018\u0001H1sO>t\u0017-\u001e;%\u0015N|g\u000eU1sg\u0016\u0014H\u0005J3yG\u0016\u0014\b\u000f\u001e\u000b\b\u0017\ne!Q\u0004B\u0011\u0011\u0019\u0011Yb\na\u0001\u0017\u000611\u000f\u001e:j]\u001eDqAa\b(\u0001\u0004\t)*\u0001\u0005q_NLG/[8o\u0011%\u0011\u0019c\nI\u0001\u0002\u0004\t)*A\u0003mS6LG\u000fK\u0002(\u0005O\u00012a\u0011B\u0015\u0013\r\u0011Y\u0003\u0012\u0002\u0007S:d\u0017N\\3\u0002M\u0005\u0014xm\u001c8bkR$#j]8o!\u0006\u00148/\u001a:%I\u0015D8-\u001a:qi\u0012\"WMZ1vYR$3\'\u0006\u0002\u00032)\"\u0011QSA;\u0003\u0015\u0001\u0018M]:f)\u0011\u00119D!\u0010\u0011\r5\u0014IdSA\u000b\u0013\r\u0011Y\u0004\u001e\u0002\u0007\u000b&$\b.\u001a:\t\r\t}\u0012\u00061\u0001L\u0003\u0011Q7o\u001c8\u0002Q\u0005\u0014xm\u001c8bkR$#j]8o!\u0006\u00148/\u001a:%I\u0015D\b/Z2uK\u0012\u001c\u0006/Y2feR{7.\u001a8\u0015\u0015\t\u0015#q\tB\'\u0005\u001f\u0012I\u0006\u0005\u0004n\u0005sY\u0015Q\u0013\u0005\b\u0005\u0013R\u0003\u0019\u0001B&\u0003\u0019\u0019HO]3b[B\u0019\u0011\u0011J\u0002\t\u000f\t}!\u00061\u0001\u0002\u0016\"9!\u0011\u000b\u0016A\u0002\tM\u0013!\u0002;pW\u0016t\u0007cA\"\u0003V%\u0019!q\u000b#\u0003\t\rC\u0017M\u001d\u0005\u0007\u00057R\u0003\u0019A&\u0002\u0017\u0019\f\u0017\u000e\\\'fgN\fw-\u001a\u0015\u0004U\t\u001d\u0002f\u0001\u0016\u0003bA!!1\rB3\u001b\t\ty(\u0003\u0003\u0003h\u0005}$a\u0002;bS2\u0014XmY\u0001(CJ<wN\\1vi\u0012R5o\u001c8QCJ\u001cXM\u001d\u0013%Kb\u0004Xm\u0019;TiJLgn\u001a\"pk:$7\u000f\u0006\u0004\u0003F\t5$q\u000e\u0005\b\u0005\u0013Z\u0003\u0019\u0001B&\u0011\u001d\u0011yb\u000ba\u0001\u0003+C3a\u000bB\u0014\u0003Q)\u0007\u0010]3di\u0016sGO]=TKB\f\'/\u0019;peR1!Q\tB<\u0005sBqA!\u0013-\u0001\u0004\u0011Y\u0005C\u0004\u0003 1\u0002\r!!&)\u00071\u00129#\u0001\u000bfqB,7\r\u001e$jK2$7+\u001a9be\u0006$xN\u001d\u000b\u0007\u0005\u000b\u0012\tIa!\t\u000f\t%S\u00061\u0001\u0003L!9!qD\u0017A\u0002\u0005U\u0005fA\u0017\u0003(\u0005aQ\r\u001f9fGR|%M[3diRQ!1\u0012BH\u0005#\u0013\u0019Ja&\u0011\r5\u0014Id\u0013BG!\u001d\u0019\u0015\u0011AAK\u0003+AqA!\u0013/\u0001\u0004\u0011Y\u0005C\u0004\u0003 9\u0002\r!!&\t\u0013\tUe\u0006%AA\u0002\u0005E\u0013!\u00024jeN$\b\"\u0003BM]A\u0005\t\u0019AA$\u0003\u00191\u0017.\u001a7eg\"\u001aaF!\u0019\u0002-\u0015D\b/Z2u\u001f\nTWm\u0019;%I\u00164\u0017-\u001e7uIM*\"A!)+\t\u0005E\u0013QO\u0001\u0017Kb\u0004Xm\u0019;PE*,7\r\u001e\u0013eK\u001a\fW\u000f\u001c;%iU\u0011!q\u0015\u0016\u0005\u0003\u000f\n)(A\u0006fqB,7\r^!se\u0006LHC\u0003BF\u0005[\u0013yK!-\u00034\"9!\u0011J\u0019A\u0002\t-\u0003b\u0002B\u0010c\u0001\u0007\u0011Q\u0013\u0005\n\u0005+\u000b\u0004\u0013!a\u0001\u0003#B\u0011B!\'2!\u0003\u0005\rA!.\u0011\ral\u0018Q\u0003B\\!\u0015i\'\u0011XA\u000b\u0013\r\u0011Y\f\u001e\u0002\u0005\u0019&\u001cH\u000fK\u00022\u0005C\nQ#\u001a=qK\u000e$\u0018I\u001d:bs\u0012\"WMZ1vYR$3\'A\u000bfqB,7\r^!se\u0006LH\u0005Z3gCVdG\u000f\n\u001b\u0016\u0005\t\u0015\'\u0006\u0002B[\u0003k\n1\"\u001a=qK\u000e$h+\u00197vKR1!1\u0012Bf\u0005\u001bDqA!\u00135\u0001\u0004\u0011Y\u0005C\u0004\u0003 Q\u0002\r!!&)\u0007Q\u0012\t\'\u0001\u0007fqB,7\r^*ue&tw\r\u0006\u0004\u0003V\ne\'1\u001c\t\u0007[\ne2Ja6\u0011\r\r\u000b\t!!&L\u0011\u001d\u0011I%\u000ea\u0001\u0005\u0017BqAa\b6\u0001\u0004\t)\nK\u00026\u0005O\t\u0011#\u001e8fqB,7\r^3e\u0007>tG/\u001a8u+\u0011\u0011\u0019Oa;\u0015\r\t\u0015(\u0011\u001fBz!\u0019i\'\u0011H&\u0003hB!!\u0011\u001eBv\u0019\u0001!qA!<7\u0005\u0004\u0011yOA\u0001U#\r!\u0017q\u0014\u0005\b\u0005\u00132\u0004\u0019\u0001B&\u0011\u001d\u0011yB\u000ea\u0001\u0003+C3A\u000eB\u0014\u0003\u001d\n\'oZ8oCV$HES:p]B\u000b\'o]3sI\u0011\u001aw\u000e\u001c7fGR\u001cFO]5oOB\u000b\'\u000f^:\u0015\u0011\tm8QAB\u0004\u0007\u0013\u0001b!\u001cB\u001d\u0017\nu\bcB\"\u0002\u0002\u0005U%q \t\u0004=\u000e\u0005\u0011bAB\u0002?\ni1\u000b\u001e:j]\u001e\u0014U/\u001b7eKJDqA!\u00138\u0001\u0004\u0011Y\u0005C\u0004\u0003 ]\u0002\r!!&\t\u0013\r-q\u0007%AA\u0002\t}\u0018!D<pe.LgnZ*ue&tw\rK\u00028\u0005C\n\u0011\'\u0019:h_:\fW\u000f\u001e\u0013Kg>t\u0007+\u0019:tKJ$CeY8mY\u0016\u001cGo\u0015;sS:<\u0007+\u0019:ug\u0012\"WMZ1vYR$3\'\u0006\u0002\u0004\u0014)\"!q`A;\u00039\n\'oZ8oCV$HES:p]B\u000b\'o]3sI\u0011*\u0007\u0010]3diN#(/\u001b8h\u001d>\u001cF/\u0019:u\u0005>,h\u000eZ:\u0015\r\tU7\u0011DB\u000e\u0011\u001d\u0011I%\u000fa\u0001\u0005\u0017BqAa\b:\u0001\u0004\t)\nK\u0002:\u0005O\u0001
   #9 = Utf8               argonaut/JsonParser$JsonObjectBuilder
  #10 = Class              #9             // argonaut/JsonParser$JsonObjectBuilder
  #11 = Utf8               JsonObjectBuilder
  #12 = Utf8               argonaut/JsonParser$JsonObjectBuilder$
  #13 = Class              #12            // argonaut/JsonParser$JsonObjectBuilder$
  #14 = Utf8               JsonObjectBuilder$
  #15 = Utf8               parse
  #16 = Utf8               (Ljava/lang/String;)Lscala/util/Either;
  #17 = Utf8               (Ljava/lang/String;)Lscala/util/Either<Ljava/lang/String;Largonaut/Json;>;
  #18 = Utf8               json
  #19 = Utf8               argonaut/JsonParser$
  #20 = Class              #19            // argonaut/JsonParser$
  #21 = Utf8               MODULE$
  #22 = Utf8               Largonaut/JsonParser$;
  #23 = NameAndType        #21:#22        // MODULE$:Largonaut/JsonParser$;
  #24 = Fieldref           #20.#23        // argonaut/JsonParser$.MODULE$:Largonaut/JsonParser$;
  #25 = NameAndType        #15:#16        // parse:(Ljava/lang/String;)Lscala/util/Either;
  #26 = Methodref          #20.#25        // argonaut/JsonParser$.parse:(Ljava/lang/String;)Lscala/util/Either;
  #27 = Utf8               Code
  #28 = Utf8               Signature
  #29 = Utf8               MethodParameters
  #30 = Utf8               InnerClasses
  #31 = Utf8               SourceFile
  #32 = Utf8               RuntimeVisibleAnnotations
  #33 = Utf8               ScalaSig
{
  public static scala.util.Either<java.lang.String, argonaut.Json> parse(java.lang.String);
    descriptor: (Ljava/lang/String;)Lscala/util/Either;
    flags: (0x0009) ACC_PUBLIC, ACC_STATIC
    Code:
      stack=2, locals=1, args_size=1
         0: getstatic     #24                 // Field argonaut/JsonParser$.MODULE$:Largonaut/JsonParser$;
         3: aload_0
         4: invokevirtual #26                 // Method argonaut/JsonParser$.parse:(Ljava/lang/String;)Lscala/util/Either;
         7: areturn
    Signature: #17                          // (Ljava/lang/String;)Lscala/util/Either<Ljava/lang/String;Largonaut/Json;>;
    MethodParameters:
      Name                           Flags
      json                           final
}
InnerClasses:
  public static #11= #10 of #2;           // JsonObjectBuilder=class argonaut/JsonParser$JsonObjectBuilder of class argonaut/JsonParser
  public static #14= #13 of #2;           // JsonObjectBuilder$=class argonaut/JsonParser$JsonObjectBuilder$ of class argonaut/JsonParser
SourceFile: "JsonParser.scala"
RuntimeVisibleAnnotations:
  0: #6(#7=s#8)
    scala.reflect.ScalaSignature(
      bytes="\u0006\u0005\r}q!\u0002\u001e<\u0011\u0003qd!\u0002!<\u0011\u0003\t\u0005\"\u0002%\u0002\t\u0003IUA\u0002&\u0002A\u000351\n\u0003\u0007W\u0003\u0011\u0005\tQ!A\u0001B\u0003%qK\u0002\u0004h\u0003\u0001\u0006I\t\u001b\u0005\tk\u0016\u0011\t\u001a!C\u0001m\"Q\u0011\u0011E\u0003\u0003\u0002\u0004%\t!a\t\t\u0013\u0005=RA!E!B\u00139\bBCA\u0019\u000b\tE\r\u0011\"\u0001\u00024!Q\u0011QH\u0003\u0003\u0002\u0004%\t!a\u0010\t\u0015\u0005\rSA!E!B\u0013\t)\u0004\u0003\u0004I\u000b\u0011\u0005\u0011Q\t\u0005\t\u0003\u001f*\u0001\u0015)\u0003\u0002R!9\u0011qK\u0003\u0005\u0002\u0005e\u0003bBA2\u000b\u0011\u0005\u0011Q\r\u0005\n\u0003O*\u0011\u0011!C\u0001\u0003SB\u0011\"a\u001c\u0006#\u0003%\t!!\u001d\t\u0013\u0005\u001dU!%A\u0005\u0002\u0005%\u0005\"CAG\u000b\u0005\u0005I\u0011IAH\u0011%\t\t*BA\u0001\n\u0003\t\u0019\nC\u0005\u0002\u001c\u0016\t\t\u0011\"\u0001\u0002\u001e\"I\u0011qU\u0003\u0002\u0002\u0013\u0005\u0013\u0011\u0016\u0005\n\u0003g+\u0011\u0011!C\u0001\u0003kC\u0011\"!/\u0006\u0003\u0003%\t%a/\t\u0013\u0005}V!!A\u0005B\u0005\u0005\u0007\"CAb\u000b\u0005\u0005I\u0011IAc\u0011%\t9-BA\u0001\n\u0003\nImB\u0005\u0002N\u0006\t\t\u0015#\u0003\u0002P\u001aAq-AA!\u0012\u0013\t\t\u000e\u0003\u0004I;\u0011\u0005\u0011\u0011\u001e\u0005\n\u0003\u0007l\u0012\u0011!C#\u0003\u000bD\u0011\"a;\u001e\u0003\u0003%\t)!<\t\u0013\u0005MX$%A\u0005\u0002\u0005E\u0004\"CA{;E\u0005I\u0011AAE\u0011%\t90HA\u0001\n\u0003\u000bI\u0010C\u0005\u0003\bu\t\n\u0011\"\u0001\u0002r!I!\u0011B\u000f\u0012\u0002\u0013\u0005\u0011\u0011\u0012\u0005\n\u0005\u0017i\u0012\u0011!C\u0005\u0005\u001bAaB!\u0006\u0002\t\u0003\u0005)\u0011!A!\n\u001b\u00119\u0002\u0003\b\u0003.\u0005!\t\u0011!B\u0001$\u0003%iAa\f\t\u000f\tM\u0012\u0001\"\u0002\u00036!q!\u0011I\u0001\u0005\u0002\u0003\u0015\t\u0011!Q\u0005\u000e\t\r\u0003B\u0004B5\u0003\u0011\u0005\tQ!A\u0001B\u00135!1\u000e\u0005\t\u0005g\n\u0001\u0015\"\u0004\u0003v!A!QP\u0001!\n\u001b\u0011y\b\u0003\u0005\u0003\b\u0006\u0001KQ\u0002BE\u0011%\u0011i*AI\u0001\n\u001b\u0011y\nC\u0005\u0003$\u0006\t\n\u0011\"\u0004\u0003&\"A!\u0011V\u0001!\n\u001b\u0011Y\u000bC\u0005\u0003@\u0006\t\n\u0011\"\u0004\u0003 \"I!\u0011Y\u0001\u0012\u0002\u00135!1\u0019\u0005\t\u0005\u000f\f\u0001\u0015\"\u0004\u0003J\"A!\u0011[\u0001!\n\u001b\u0011\u0019\u000e\u0003\u0005\u0003`\u0006\u0001KQ\u0002Bq\u00119\u001190\u0001C\u0001\u0002\u000b\u0005\t\u0011)C\u0007\u0005sDaba\u0004\u0002\t\u0003\u0005)\u0011aI\u0001\n\u001b\u0019\t\u0002\u0003\b\u0004\u0016\u0005!\t\u0011!B\u0001\u0002\u0003&iaa\u0006\u0002\u0015)\u001bxN\u001c)beN,\'OC\u0001=\u0003!\t\'oZ8oCV$8\u0001\u0001\t\u0003\u007f\u0005i\u0011a\u000f\u0002\u000b\u0015N|g\u000eU1sg\u0016\u00148CA\u0001C!\t\u0019e)D\u0001E\u0015\u0005)\u0015!B:dC2\f\u0017BA$E\u0005\u0019\te.\u001f*fM\u00061A(\u001b8jiz\"\u0012A\u0010\u0002\f)>\\WM\\*pkJ\u001cW\r\u0005\u0002M\':\u0011Q*\u0015\t\u0003\u001d\u0012k\u0011a\u0014\u0006\u0003!v\na\u0001\u0010:p_Rt\u0014B\u0001*E\u0003\u0019\u0001&/\u001a3fM&\u0011A+\u0016\u0002\u0007\'R\u0014\u0018N\\4\u000b\u0005I#\u0015AK1sO>t\u0017-\u001e;%\u0015N|g\u000eU1sg\u0016\u0014H\u0005J;oKb\u0004Xm\u0019;fIR+\'/\\5oCRLwN\u001c\t\u00051nkF-D\u0001Z\u0015\tQF)\u0001\u0003vi&d\u0017B\u0001/Z\u0005\u0011aUM\u001a;\u0011\u0005y\u001bW\"A0\u000b\u0005\u0001\f\u0017\u0001\u00027b]\u001eT\u0011AY\u0001\u0005U\u00064\u0018-\u0003\u0002U?B\u00111)Z\u0005\u0003M\u0012\u0013qAT8uQ&twMA\tKg>twJ\u00196fGR\u0014U/\u001b7eKJ\u001cB!\u0002\"jYB\u00111I[\u0005\u0003W\u0012\u0013q\u0001\u0015:pIV\u001cG\u000f\u0005\u0002ne:\u0011a\u000e\u001d\b\u0003\u001d>L\u0011!R\u0005\u0003c\u0012\u000bq\u0001]1dW\u0006<W-\u0003\u0002ti\na1+\u001a:jC2L\'0\u00192mK*\u0011\u0011\u000fR\u0001\u0011M&,G\u000eZ:NCB\u0014U/\u001b7eKJ,\u0012a\u001e\t\u0006qv|\u00181D\u0007\u0002s*\u0011!p_\u0001\b[V$\u0018M\u00197f\u0015\taH)\u0001\u0006d_2dWm\u0019;j_:L!A`=\u0003\u000f\t+\u0018\u000e\u001c3feB91)!\u0001\u0002\u0006\u0005U\u0011bAA\u0002\t\n1A+\u001e9mKJ\u0002B!a\u0002\u0002\u000e9\u0019q(!\u0003\n\u0007\u0005-1(\u0001\u0003Kg>t\u0017\u0002BA\b\u0003#\u0011\u0011BS:p]\u001aKW\r\u001c3\n\u0007\u0005M1HA\u0003Kg>t7\u000fE\u0002@\u0003/I1!!\u0007<\u0005\u0011Q5o\u001c8\u0011\u000f1\u000bi\"!\u0002\u0002\u0016%\u0019\u0011qD+\u0003\u00075\u000b\u0007/\u0001\u000bgS\u0016dGm]\'ba\n+\u0018\u000e\u001c3fe~#S-\u001d\u000b\u0005\u0003K\tY\u0003E\u0002D\u0003OI1!!\u000bE\u0005\u0011)f.\u001b;\t\u0011\u00055r!!AA\u0002]\f1\u0001\u001f\u00132\u0003E1\u0017.\u001a7eg6\u000b\u0007OQ;jY\u0012,\'\u000fI\u0001\u0015_J$WM]3e\r&,G\u000eZ:Ck&dG-\u001a:\u0016\u0005\u0005U\u0002C\u0002=~\u0003\u000b\t9\u0004E\u0003n\u0003s\t)!C\u0002\u0002<Q\u0014aAV3di>\u0014\u0018\u0001G8sI\u0016\u0014X\r\u001a$jK2$7OQ;jY\u0012,\'o\u0018\u0013fcR!\u0011QEA!\u0011%\tiCCA\u0001\u0002\u0004\t)$A\u000bpe\u0012,\'/\u001a3GS\u0016dGm\u001d\"vS2$WM\u001d\u0011\u0015\r\u0005\u001d\u00131JA\'!\r\tI%B\u0007\u0002\u0003!9Q\u000f\u0004I\u0001\u0002\u00049\b\"CA\u0019\u0019A\u0005\t\u0019AA\u001b\u0003\u001dI7/R7qif\u00042aQA*\u0013\r\t)\u0006\u0012\u0002\b\u0005>|G.Z1o\u0003\r\tG\r\u001a\u000b\u0007\u0003\u000f\nY&a\u0018\t\u000f\u0005uc\u00021\u0001\u0002\u0006\u0005\u00191.Z=\t\u000f\u0005\u0005d\u00021\u0001\u0002\u0016\u0005)a/\u00197vK\u0006)!-^5mIR\u0011\u0011QC\u0001\u0005G>\u0004\u0018\u0010\u0006\u0004\u0002H\u0005-\u0014Q\u000e\u0005\bkB\u0001\n\u00111\u0001x\u0011%\t\t\u0004\u0005I\u0001\u0002\u0004\t)$\u0001\bd_BLH\u0005Z3gCVdG\u000fJ\u0019\u0016\u0005\u0005M$fA<\u0002v-\u0012\u0011q\u000f\t\u0005\u0003s\n\u0019)\u0004\u0002\u0002|)!\u0011QPA@\u0003%)hn\u00195fG.,GMC\u0002\u0002\u0002\u0012\u000b!\"\u00198o_R\fG/[8o\u0013\u0011\t))a\u001f\u0003#Ut7\r[3dW\u0016$g+\u0019:jC:\u001cW-\u0001\bd_BLH\u0005Z3gCVdG\u000f\n\u001a\u0016\u0005\u0005-%\u0006BA\u001b\u0003k\nQ\u0002\u001d:pIV\u001cG\u000f\u0015:fM&DX#A/\u0002\u0019A\u0014x\u000eZ;di\u0006\u0013\u0018\u000e^=\u0016\u0005\u0005U\u0005cA\"\u0002\u0018&\u0019\u0011\u0011\u0014#\u0003\u0007%sG/\u0001\bqe>$Wo\u0019;FY\u0016lWM\u001c;\u0015\t\u0005}\u0015Q\u0015\t\u0004\u0007\u0006\u0005\u0016bAAR\t\n\u0019\u0011I\\=\t\u0013\u00055R#!AA\u0002\u0005U\u0015a\u00049s_\u0012,8\r^%uKJ\fGo\u001c:\u0016\u0005\u0005-\u0006CBAW\u0003_\u000by*D\u0001|\u0013\r\t\tl\u001f\u0002\t\u0013R,\'/\u0019;pe\u0006A1-\u00198FcV\fG\u000e\u0006\u0003\u0002R\u0005]\u0006\"CA\u0017/\u0005\u0005\t\u0019AAP\u0003I\u0001(o\u001c3vGR,E.Z7f]Rt\u0015-\\3\u0015\u0007u\u000bi\fC\u0005\u0002.a\t\t\u00111\u0001\u0002\u0016\u0006A\u0001.Y:i\u0007>$W\r\u0006\u0002\u0002\u0016\u0006AAo\\*ue&tw\rF\u0001^\u0003\u0019)\u0017/^1mgR!\u0011\u0011KAf\u0011%\ticGA\u0001\u0002\u0004\ty*A\tKg>twJ\u00196fGR\u0014U/\u001b7eKJ\u00042!!\u0013\u001e\'\u0015i\u00121[Ap!%\t).a7x\u0003k\t9%\u0004\u0002\u0002X*\u0019\u0011\u0011\u001c#\u0002\u000fI,h\u000e^5nK&!\u0011Q\\Al\u0005E\t%m\u001d;sC\u000e$h)\u001e8di&|gN\r\t\u0005\u0003C\f9/\u0004\u0002\u0002d*\u0019\u0011Q]1\u0002\u0005%|\u0017bA:\u0002dR\u0011\u0011qZ\u0001\u0006CB\u0004H.\u001f\u000b\u0007\u0003\u000f\ny/!=\t\u000fU\u0004\u0003\u0013!a\u0001o\"I\u0011\u0011\u0007\u0011\u0011\u0002\u0003\u0007\u0011QG\u0001\u0010CB\u0004H.\u001f\u0013eK\u001a\fW\u000f\u001c;%c\u0005y\u0011\r\u001d9ms\u0012\"WMZ1vYR$#\'A\u0004v]\u0006\u0004\b\u000f\\=\u0015\t\u0005m(1\u0001\t\u0006\u0007\u0006u(\u0011A\u0005\u0004\u0003\u007f$%AB(qi&|g\u000e\u0005\u0004D\u0003\u00039\u0018Q\u0007\u0005\n\u0005\u000b\u0019\u0013\u0011!a\u0001\u0003\u000f\n1\u0001\u001f\u00131\u0003m!C.Z:tS:LG\u000fJ4sK\u0006$XM\u001d\u0013eK\u001a\fW\u000f\u001c;%c\u0005YB\u0005\\3tg&t\u0017\u000e\u001e\u0013he\u0016\fG/\u001a:%I\u00164\u0017-\u001e7uII\nAb\u001e:ji\u0016\u0014V\r\u001d7bG\u0016$\"Aa\u0004\u0011\u0007y\u0013\t\"C\u0002\u0003\u0014}\u0013aa\u00142kK\u000e$\u0018\u0001H1sO>t\u0017-\u001e;%\u0015N|g\u000eU1sg\u0016\u0014H\u0005J3yG\u0016\u0014\b\u000f\u001e\u000b\b\u0017\ne!Q\u0004B\u0011\u0011\u0019\u0011Yb\na\u0001\u0017\u000611\u000f\u001e:j]\u001eDqAa\b(\u0001\u0004\t)*\u0001\u0005q_NLG/[8o\u0011%\u0011\u0019c\nI\u0001\u0002\u0004\t)*A\u0003mS6LG\u000fK\u0002(\u0005O\u00012a\u0011B\u0015\u0013\r\u0011Y\u0003\u0012\u0002\u0007S:d\u0017N\\3\u0002M\u0005\u0014xm\u001c8bkR$#j]8o!\u0006\u00148/\u001a:%I\u0015D8-\u001a:qi\u0012\"WMZ1vYR$3\'\u0006\u0002\u00032)\"\u0011QSA;\u0003\u0015\u0001\u0018M]:f)\u0011\u00119D!\u0010\u0011\r5\u0014IdSA\u000b\u0013\r\u0011Y\u0004\u001e\u0002\u0007\u000b&$\b.\u001a:\t\r\t}\u0012\u00061\u0001L\u0003\u0011Q7o\u001c8\u0002Q\u0005\u0014xm\u001c8bkR$#j]8o!\u0006\u00148/\u001a:%I\u0015D\b/Z2uK\u0012\u001c\u0006/Y2feR{7.\u001a8\u0015\u0015\t\u0015#q\tB\'\u0005\u001f\u0012I\u0006\u0005\u0004n\u0005sY\u0015Q\u0013\u0005\b\u0005\u0013R\u0003\u0019\u0001B&\u0003\u0019\u0019HO]3b[B\u0019\u0011\u0011J\u0002\t\u000f\t}!\u00061\u0001\u0002\u0016\"9!\u0011\u000b\u0016A\u0002\tM\u0013!\u0002;pW\u0016t\u0007cA\"\u0003V%\u0019!q\u000b#\u0003\t\rC\u0017M\u001d\u0005\u0007\u00057R\u0003\u0019A&\u0002\u0017\u0019\f\u0017\u000e\\\'fgN\fw-\u001a\u0015\u0004U\t\u001d\u0002f\u0001\u0016\u0003bA!!1\rB3\u001b\t\ty(\u0003\u0003\u0003h\u0005}$a\u0002;bS2\u0014XmY\u0001(CJ<wN\\1vi\u0012R5o\u001c8QCJ\u001cXM\u001d\u0013%Kb\u0004Xm\u0019;TiJLgn\u001a\"pk:$7\u000f\u0006\u0004\u0003F\t5$q\u000e\u0005\b\u0005\u0013Z\u0003\u0019\u0001B&\u0011\u001d\u0011yb\u000ba\u0001\u0003+C3a\u000bB\u0014\u0003Q)\u0007\u0010]3di\u0016sGO]=TKB\f\'/\u0019;peR1!Q\tB<\u0005sBqA!\u0013-\u0001\u0004\u0011Y\u0005C\u0004\u0003 1\u0002\r!!&)\u00071\u00129#\u0001\u000bfqB,7\r\u001e$jK2$7+\u001a9be\u0006$xN\u001d\u000b\u0007\u0005\u000b\u0012\tIa!\t\u000f\t%S\u00061\u0001\u0003L!9!qD\u0017A\u0002\u0005U\u0005fA\u0017\u0003(\u0005aQ\r\u001f9fGR|%M[3diRQ!1\u0012BH\u0005#\u0013\u0019Ja&\u0011\r5\u0014Id\u0013BG!\u001d\u0019\u0015\u0011AAK\u0003+AqA!\u0013/\u0001\u0004\u0011Y\u0005C\u0004\u0003 9\u0002\r!!&\t\u0013\tUe\u0006%AA\u0002\u0005E\u0013!\u00024jeN$\b\"\u0003BM]A\u0005\t\u0019AA$\u0003\u00191\u0017.\u001a7eg\"\u001aaF!\u0019\u0002-\u0015D\b/Z2u\u001f\nTWm\u0019;%I\u00164\u0017-\u001e7uIM*\"A!)+\t\u0005E\u0013QO\u0001\u0017Kb\u0004Xm\u0019;PE*,7\r\u001e\u0013eK\u001a\fW\u000f\u001c;%iU\u0011!q\u0015\u0016\u0005\u0003\u000f\n)(A\u0006fqB,7\r^!se\u0006LHC\u0003BF\u0005[\u0013yK!-\u00034\"9!\u0011J\u0019A\u0002\t-\u0003b\u0002B\u0010c\u0001\u0007\u0011Q\u0013\u0005\n\u0005+\u000b\u0004\u0013!a\u0001\u0003#B\u0011B!\'2!\u0003\u0005\rA!.\u0011\ral\u0018Q\u0003B\\!\u0015i\'\u0011XA\u000b\u0013\r\u0011Y\f\u001e\u0002\u0005\u0019&\u001cH\u000fK\u00022\u0005C\nQ#\u001a=qK\u000e$\u0018I\u001d:bs\u0012\"WMZ1vYR$3\'A\u000bfqB,7\r^!se\u0006LH\u0005Z3gCVdG\u000f\n\u001b\u0016\u0005\t\u0015\'\u0006\u0002B[\u0003k\n1\"\u001a=qK\u000e$h+\u00197vKR1!1\u0012Bf\u0005\u001bDqA!\u00135\u0001\u0004\u0011Y\u0005C\u0004\u0003 Q\u0002\r!!&)\u0007Q\u0012\t\'\u0001\u0007fqB,7\r^*ue&tw\r\u0006\u0004\u0003V\ne\'1\u001c\t\u0007[\ne2Ja6\u0011\r\r\u000b\t!!&L\u0011\u001d\u0011I%\u000ea\u0001\u0005\u0017BqAa\b6\u0001\u0004\t)\nK\u00026\u0005O\t\u0011#\u001e8fqB,7\r^3e\u0007>tG/\u001a8u+\u0011\u0011\u0019Oa;\u0015\r\t\u0015(\u0011\u001fBz!\u0019i\'\u0011H&\u0003hB!!\u0011\u001eBv\u0019\u0001!qA!<7\u0005\u0004\u0011yOA\u0001U#\r!\u0017q\u0014\u0005\b\u0005\u00132\u0004\u0019\u0001B&\u0011\u001d\u0011yB\u000ea\u0001\u0003+C3A\u000eB\u0014\u0003\u001d\n\'oZ8oCV$HES:p]B\u000b\'o]3sI\u0011\u001aw\u000e\u001c7fGR\u001cFO]5oOB\u000b\'\u000f^:\u0015\u0011\tm8QAB\u0004\u0007\u0013\u0001b!\u001cB\u001d\u0017\nu\bcB\"\u0002\u0002\u0005U%q \t\u0004=\u000e\u0005\u0011bAB\u0002?\ni1\u000b\u001e:j]\u001e\u0014U/\u001b7eKJDqA!\u00138\u0001\u0004\u0011Y\u0005C\u0004\u0003 ]\u0002\r!!&\t\u0013\r-q\u0007%AA\u0002\t}\u0018!D<pe.LgnZ*ue&tw\rK\u00028\u0005C\n\u0011\'\u0019:h_:\fW\u000f\u001e\u0013Kg>t\u0007+\u0019:tKJ$CeY8mY\u0016\u001cGo\u0015;sS:<\u0007+\u0019:ug\u0012\"WMZ1vYR$3\'\u0006\u0002\u0004\u0014)\"!q`A;\u00039\n\'oZ8oCV$HES:p]B\u000b\'o]3sI\u0011*\u0007\u0010]3diN#(/\u001b8h\u001d>\u001cF/\u0019:u\u0005>,h\u000eZ:\u0015\r\tU7\u0011DB\u000e\u0011\u001d\u0011I%\u000fa\u0001\u0005\u0017BqAa\b:\u0001\u0004\t)\nK\u0002:\u0005O\u0001"
    )
  ScalaSig: length = 0x3 (unknown attribute)
   05 02 00
