Classfile /Users/mw/Projects/slang-braindump/.jar/jar11/assemble/slang-braindump/assemble/content/argonaut/Reattempt.class
  Last modified May 29, 2022; size 2022 bytes
  SHA-256 checksum d3489ad1f1c7240ab8fb8644fd5ffa9ac8d5f56277fd54f6472e5a679c7f11f8
  Compiled from "CursorOp.scala"
public final class argonaut.Reattempt
  minor version: 0
  major version: 52
  flags: (0x0031) ACC_PUBLIC, ACC_FINAL, ACC_SUPER
  this_class: #2                          // argonaut/Reattempt
  super_class: #4                         // java/lang/Object
  interfaces: 0, fields: 0, methods: 13, attributes: 3
Constant pool:
   #1 = Utf8               argonaut/Reattempt
   #2 = Class              #1             // argonaut/Reattempt
   #3 = Utf8               java/lang/Object
   #4 = Class              #3             // java/lang/Object
   #5 = Utf8               CursorOp.scala
   #6 = Utf8               Lscala/reflect/ScalaSignature;
   #7 = Utf8               bytes
   #8 = Utf8               \u0006\u0005];Qa\u0003\u0007\t\u0002>1Q!\u0005\u0007\t\u0002JAQ\u0001K\u0001\u0005\u0002%BqAK\u0001\u0002\u0002\u0013\u00053\u0006C\u00045\u0003\u0005\u0005I\u0011A\u001b\t\u000fe\n\u0011\u0011!C\u0001u!9\u0001)AA\u0001\n\u0003\n\u0005b\u0002%\u0002\u0003\u0003%\t!\u0013\u0005\b\u001d\u0006\t\t\u0011\"\u0011P\u0011\u001d\u0001\u0016!!A\u0005BECqAU\u0001\u0002\u0002\u0013%1+A\u0005SK\u0006$H/Z7qi*\tQ\"\u0001\u0005be\u001e|g.Y;u\u0007\u0001\u0001\"\u0001E\u0001\u000e\u00031\u0011\u0011BU3biR,W\u000e\u001d;\u0014\t\u0005\u0019b\u0003\b\t\u0003!QI!!\u0006\u0007\u0003\u0011\r+(o]8s\u001fB\u0004\"a\u0006\u000e\u000e\u0003aQ\u0011!G\u0001\u0006g\u000e\fG.Y\u0005\u00037a\u0011q\u0001\u0015:pIV\u001cG\u000f\u0005\u0002\u001eK9\u0011ad\t\b\u0003?\tj\u0011\u0001\t\u0006\u0003C9\ta\u0001\u0010:p_Rt\u0014\"A\r\n\u0005\u0011B\u0012a\u00029bG.\fw-Z\u0005\u0003M\u001d\u0012AbU3sS\u0006d\u0017N_1cY\u0016T!\u0001\n\r\u0002\rqJg.\u001b;?)\u0005y\u0011!\u00049s_\u0012,8\r\u001e)sK\u001aL\u00070F\u0001-!\ti#\'D\u0001/\u0015\ty\u0003\'\u0001\u0003mC:<\'\"A\u0019\u0002\t)\fg/Y\u0005\u0003g9\u0012aa\u0015;sS:<\u0017\u0001\u00049s_\u0012,8\r^!sSRLX#\u0001\u001c\u0011\u0005]9\u0014B\u0001\u001d\u0019\u0005\rIe\u000e^\u0001\u000faJ|G-^2u\u000b2,W.\u001a8u)\tYd\b\u0005\u0002\u0018y%\u0011Q\b\u0007\u0002\u0004\u0003:L\bbB \u0006\u0003\u0003\u0005\rAN\u0001\u0004q\u0012\n\u0014a\u00049s_\u0012,8\r^%uKJ\fGo\u001c:\u0016\u0003\t\u00032a\u0011$<\u001b\u0005!%BA#\u0019\u0003)\u0019w\u000e\u001c7fGRLwN\\\u0005\u0003\u000f\u0012\u0013\u0001\"\u0013;fe\u0006$xN]\u0001\tG\u0006tW)];bYR\u0011!*\u0014\t\u0003/-K!\u0001\u0014\r\u0003\u000f\t{w\u000e\\3b]\"9qhBA\u0001\u0002\u0004Y\u0014\u0001\u00035bg\"\u001cu\u000eZ3\u0015\u0003Y\n\u0001\u0002^8TiJLgn\u001a\u000b\u0002Y\u0005aqO]5uKJ+\u0007\u000f\\1dKR\tA\u000b\u0005\u0002.+&\u0011aK\f\u0002\u0007\u001f\nTWm\u0019;
   #9 = Utf8               toString
  #10 = Utf8               ()Ljava/lang/String;
  #11 = Utf8               argonaut/Reattempt$
  #12 = Class              #11            // argonaut/Reattempt$
  #13 = Utf8               MODULE$
  #14 = Utf8               Largonaut/Reattempt$;
  #15 = NameAndType        #13:#14        // MODULE$:Largonaut/Reattempt$;
  #16 = Fieldref           #12.#15        // argonaut/Reattempt$.MODULE$:Largonaut/Reattempt$;
  #17 = NameAndType        #9:#10         // toString:()Ljava/lang/String;
  #18 = Methodref          #12.#17        // argonaut/Reattempt$.toString:()Ljava/lang/String;
  #19 = Utf8               hashCode
  #20 = Utf8               ()I
  #21 = NameAndType        #19:#20        // hashCode:()I
  #22 = Methodref          #12.#21        // argonaut/Reattempt$.hashCode:()I
  #23 = Utf8               canEqual
  #24 = Utf8               (Ljava/lang/Object;)Z
  #25 = Utf8               x$1
  #26 = NameAndType        #23:#24        // canEqual:(Ljava/lang/Object;)Z
  #27 = Methodref          #12.#26        // argonaut/Reattempt$.canEqual:(Ljava/lang/Object;)Z
  #28 = Utf8               productIterator
  #29 = Utf8               ()Lscala/collection/Iterator;
  #30 = Utf8               ()Lscala/collection/Iterator<Ljava/lang/Object;>;
  #31 = NameAndType        #28:#29        // productIterator:()Lscala/collection/Iterator;
  #32 = Methodref          #12.#31        // argonaut/Reattempt$.productIterator:()Lscala/collection/Iterator;
  #33 = Utf8               productElement
  #34 = Utf8               (I)Ljava/lang/Object;
  #35 = NameAndType        #33:#34        // productElement:(I)Ljava/lang/Object;
  #36 = Methodref          #12.#35        // argonaut/Reattempt$.productElement:(I)Ljava/lang/Object;
  #37 = Utf8               productArity
  #38 = NameAndType        #37:#20        // productArity:()I
  #39 = Methodref          #12.#38        // argonaut/Reattempt$.productArity:()I
  #40 = Utf8               productPrefix
  #41 = NameAndType        #40:#10        // productPrefix:()Ljava/lang/String;
  #42 = Methodref          #12.#41        // argonaut/Reattempt$.productPrefix:()Ljava/lang/String;
  #43 = Utf8               failed
  #44 = Utf8               ()Z
  #45 = NameAndType        #43:#44        // failed:()Z
  #46 = Methodref          #12.#45        // argonaut/Reattempt$.failed:()Z
  #47 = Utf8               succeeded
  #48 = NameAndType        #47:#44        // succeeded:()Z
  #49 = Methodref          #12.#48        // argonaut/Reattempt$.succeeded:()Z
  #50 = Utf8               isNotReattempt
  #51 = NameAndType        #50:#44        // isNotReattempt:()Z
  #52 = Methodref          #12.#51        // argonaut/Reattempt$.isNotReattempt:()Z
  #53 = Utf8               isReattempt
  #54 = NameAndType        #53:#44        // isReattempt:()Z
  #55 = Methodref          #12.#54        // argonaut/Reattempt$.isReattempt:()Z
  #56 = Utf8               productElementNames
  #57 = Utf8               ()Lscala/collection/Iterator<Ljava/lang/String;>;
  #58 = NameAndType        #56:#29        // productElementNames:()Lscala/collection/Iterator;
  #59 = Methodref          #12.#58        // argonaut/Reattempt$.productElementNames:()Lscala/collection/Iterator;
  #60 = Utf8               productElementName
  #61 = Utf8               (I)Ljava/lang/String;
  #62 = Utf8               n
  #63 = NameAndType        #60:#61        // productElementName:(I)Ljava/lang/String;
  #64 = Methodref          #12.#63        // argonaut/Reattempt$.productElementName:(I)Ljava/lang/String;
  #65 = Utf8               Code
  #66 = Utf8               MethodParameters
  #67 = Utf8               Signature
  #68 = Utf8               SourceFile
  #69 = Utf8               RuntimeVisibleAnnotations
  #70 = Utf8               ScalaSig
{
  public static java.lang.String toString();
    descriptor: ()Ljava/lang/String;
    flags: (0x0009) ACC_PUBLIC, ACC_STATIC
    Code:
      stack=1, locals=0, args_size=0
         0: getstatic     #16                 // Field argonaut/Reattempt$.MODULE$:Largonaut/Reattempt$;
         3: invokevirtual #18                 // Method argonaut/Reattempt$.toString:()Ljava/lang/String;
         6: areturn

  public static int hashCode();
    descriptor: ()I
    flags: (0x0009) ACC_PUBLIC, ACC_STATIC
    Code:
      stack=1, locals=0, args_size=0
         0: getstatic     #16                 // Field argonaut/Reattempt$.MODULE$:Largonaut/Reattempt$;
         3: invokevirtual #22                 // Method argonaut/Reattempt$.hashCode:()I
         6: ireturn

  public static boolean canEqual(java.lang.Object);
    descriptor: (Ljava/lang/Object;)Z
    flags: (0x0009) ACC_PUBLIC, ACC_STATIC
    Code:
      stack=2, locals=1, args_size=1
         0: getstatic     #16                 // Field argonaut/Reattempt$.MODULE$:Largonaut/Reattempt$;
         3: aload_0
         4: invokevirtual #27                 // Method argonaut/Reattempt$.canEqual:(Ljava/lang/Object;)Z
         7: ireturn
    MethodParameters:
      Name                           Flags
      x$1                            final

  public static scala.collection.Iterator<java.lang.Object> productIterator();
    descriptor: ()Lscala/collection/Iterator;
    flags: (0x0009) ACC_PUBLIC, ACC_STATIC
    Code:
      stack=1, locals=0, args_size=0
         0: getstatic     #16                 // Field argonaut/Reattempt$.MODULE$:Largonaut/Reattempt$;
         3: invokevirtual #32                 // Method argonaut/Reattempt$.productIterator:()Lscala/collection/Iterator;
         6: areturn
    Signature: #30                          // ()Lscala/collection/Iterator<Ljava/lang/Object;>;

  public static java.lang.Object productElement(int);
    descriptor: (I)Ljava/lang/Object;
    flags: (0x0009) ACC_PUBLIC, ACC_STATIC
    Code:
      stack=2, locals=1, args_size=1
         0: getstatic     #16                 // Field argonaut/Reattempt$.MODULE$:Largonaut/Reattempt$;
         3: iload_0
         4: invokevirtual #36                 // Method argonaut/Reattempt$.productElement:(I)Ljava/lang/Object;
         7: areturn
    MethodParameters:
      Name                           Flags
      x$1                            final

  public static int productArity();
    descriptor: ()I
    flags: (0x0009) ACC_PUBLIC, ACC_STATIC
    Code:
      stack=1, locals=0, args_size=0
         0: getstatic     #16                 // Field argonaut/Reattempt$.MODULE$:Largonaut/Reattempt$;
         3: invokevirtual #39                 // Method argonaut/Reattempt$.productArity:()I
         6: ireturn

  public static java.lang.String productPrefix();
    descriptor: ()Ljava/lang/String;
    flags: (0x0009) ACC_PUBLIC, ACC_STATIC
    Code:
      stack=1, locals=0, args_size=0
         0: getstatic     #16                 // Field argonaut/Reattempt$.MODULE$:Largonaut/Reattempt$;
         3: invokevirtual #42                 // Method argonaut/Reattempt$.productPrefix:()Ljava/lang/String;
         6: areturn

  public static boolean failed();
    descriptor: ()Z
    flags: (0x0009) ACC_PUBLIC, ACC_STATIC
    Code:
      stack=1, locals=0, args_size=0
         0: getstatic     #16                 // Field argonaut/Reattempt$.MODULE$:Largonaut/Reattempt$;
         3: invokevirtual #46                 // Method argonaut/Reattempt$.failed:()Z
         6: ireturn

  public static boolean succeeded();
    descriptor: ()Z
    flags: (0x0009) ACC_PUBLIC, ACC_STATIC
    Code:
      stack=1, locals=0, args_size=0
         0: getstatic     #16                 // Field argonaut/Reattempt$.MODULE$:Largonaut/Reattempt$;
         3: invokevirtual #49                 // Method argonaut/Reattempt$.succeeded:()Z
         6: ireturn

  public static boolean isNotReattempt();
    descriptor: ()Z
    flags: (0x0009) ACC_PUBLIC, ACC_STATIC
    Code:
      stack=1, locals=0, args_size=0
         0: getstatic     #16                 // Field argonaut/Reattempt$.MODULE$:Largonaut/Reattempt$;
         3: invokevirtual #52                 // Method argonaut/Reattempt$.isNotReattempt:()Z
         6: ireturn

  public static boolean isReattempt();
    descriptor: ()Z
    flags: (0x0009) ACC_PUBLIC, ACC_STATIC
    Code:
      stack=1, locals=0, args_size=0
         0: getstatic     #16                 // Field argonaut/Reattempt$.MODULE$:Largonaut/Reattempt$;
         3: invokevirtual #55                 // Method argonaut/Reattempt$.isReattempt:()Z
         6: ireturn

  public static scala.collection.Iterator<java.lang.String> productElementNames();
    descriptor: ()Lscala/collection/Iterator;
    flags: (0x0009) ACC_PUBLIC, ACC_STATIC
    Code:
      stack=1, locals=0, args_size=0
         0: getstatic     #16                 // Field argonaut/Reattempt$.MODULE$:Largonaut/Reattempt$;
         3: invokevirtual #59                 // Method argonaut/Reattempt$.productElementNames:()Lscala/collection/Iterator;
         6: areturn
    Signature: #57                          // ()Lscala/collection/Iterator<Ljava/lang/String;>;

  public static java.lang.String productElementName(int);
    descriptor: (I)Ljava/lang/String;
    flags: (0x0009) ACC_PUBLIC, ACC_STATIC
    Code:
      stack=2, locals=1, args_size=1
         0: getstatic     #16                 // Field argonaut/Reattempt$.MODULE$:Largonaut/Reattempt$;
         3: iload_0
         4: invokevirtual #64                 // Method argonaut/Reattempt$.productElementName:(I)Ljava/lang/String;
         7: areturn
    MethodParameters:
      Name                           Flags
      n                              final
}
SourceFile: "CursorOp.scala"
RuntimeVisibleAnnotations:
  0: #6(#7=s#8)
    scala.reflect.ScalaSignature(
      bytes="\u0006\u0005];Qa\u0003\u0007\t\u0002>1Q!\u0005\u0007\t\u0002JAQ\u0001K\u0001\u0005\u0002%BqAK\u0001\u0002\u0002\u0013\u00053\u0006C\u00045\u0003\u0005\u0005I\u0011A\u001b\t\u000fe\n\u0011\u0011!C\u0001u!9\u0001)AA\u0001\n\u0003\n\u0005b\u0002%\u0002\u0003\u0003%\t!\u0013\u0005\b\u001d\u0006\t\t\u0011\"\u0011P\u0011\u001d\u0001\u0016!!A\u0005BECqAU\u0001\u0002\u0002\u0013%1+A\u0005SK\u0006$H/Z7qi*\tQ\"\u0001\u0005be\u001e|g.Y;u\u0007\u0001\u0001\"\u0001E\u0001\u000e\u00031\u0011\u0011BU3biR,W\u000e\u001d;\u0014\t\u0005\u0019b\u0003\b\t\u0003!QI!!\u0006\u0007\u0003\u0011\r+(o]8s\u001fB\u0004\"a\u0006\u000e\u000e\u0003aQ\u0011!G\u0001\u0006g\u000e\fG.Y\u0005\u00037a\u0011q\u0001\u0015:pIV\u001cG\u000f\u0005\u0002\u001eK9\u0011ad\t\b\u0003?\tj\u0011\u0001\t\u0006\u0003C9\ta\u0001\u0010:p_Rt\u0014\"A\r\n\u0005\u0011B\u0012a\u00029bG.\fw-Z\u0005\u0003M\u001d\u0012AbU3sS\u0006d\u0017N_1cY\u0016T!\u0001\n\r\u0002\rqJg.\u001b;?)\u0005y\u0011!\u00049s_\u0012,8\r\u001e)sK\u001aL\u00070F\u0001-!\ti#\'D\u0001/\u0015\ty\u0003\'\u0001\u0003mC:<\'\"A\u0019\u0002\t)\fg/Y\u0005\u0003g9\u0012aa\u0015;sS:<\u0017\u0001\u00049s_\u0012,8\r^!sSRLX#\u0001\u001c\u0011\u0005]9\u0014B\u0001\u001d\u0019\u0005\rIe\u000e^\u0001\u000faJ|G-^2u\u000b2,W.\u001a8u)\tYd\b\u0005\u0002\u0018y%\u0011Q\b\u0007\u0002\u0004\u0003:L\bbB \u0006\u0003\u0003\u0005\rAN\u0001\u0004q\u0012\n\u0014a\u00049s_\u0012,8\r^%uKJ\fGo\u001c:\u0016\u0003\t\u00032a\u0011$<\u001b\u0005!%BA#\u0019\u0003)\u0019w\u000e\u001c7fGRLwN\\\u0005\u0003\u000f\u0012\u0013\u0001\"\u0013;fe\u0006$xN]\u0001\tG\u0006tW)];bYR\u0011!*\u0014\t\u0003/-K!\u0001\u0014\r\u0003\u000f\t{w\u000e\\3b]\"9qhBA\u0001\u0002\u0004Y\u0014\u0001\u00035bg\"\u001cu\u000eZ3\u0015\u0003Y\n\u0001\u0002^8TiJLgn\u001a\u000b\u0002Y\u0005aqO]5uKJ+\u0007\u000f\\1dKR\tA\u000b\u0005\u0002.+&\u0011aK\f\u0002\u0007\u001f\nTWm\u0019;"
    )
  ScalaSig: length = 0x3 (unknown attribute)
   05 02 00
