Classfile /Users/mw/Projects/slang-braindump/.jar/jar11/assemble/slang-braindump/assemble/content/argonaut/StringWraps$$anon$1.class
  Last modified May 29, 2022; size 786 bytes
  SHA-256 checksum f7126ccb5ef991ac05919521cb57bedcd4f6988ebb7c1c7fd3bd8344d9191e11
  Compiled from "StringWrap.scala"
public final class argonaut.StringWraps$$anon$1 extends argonaut.StringWrap
  minor version: 0
  major version: 52
  flags: (0x0031) ACC_PUBLIC, ACC_FINAL, ACC_SUPER
  this_class: #2                          // argonaut/StringWraps$$anon$1
  super_class: #4                         // argonaut/StringWrap
  interfaces: 0, fields: 1, methods: 2, attributes: 5
Constant pool:
   #1 = Utf8               argonaut/StringWraps$$anon$1
   #2 = Class              #1             // argonaut/StringWraps$$anon$1
   #3 = Utf8               argonaut/StringWrap
   #4 = Class              #3             // argonaut/StringWrap
   #5 = Utf8               StringWrap.scala
   #6 = Utf8               argonaut/StringWraps
   #7 = Class              #6             // argonaut/StringWraps
   #8 = Utf8               StringToStringWrap
   #9 = Utf8               (Ljava/lang/String;)Largonaut/StringWrap;
  #10 = NameAndType        #8:#9          // StringToStringWrap:(Ljava/lang/String;)Largonaut/StringWrap;
  #11 = Utf8               value
  #12 = Utf8               Ljava/lang/String;
  #13 = Utf8               ()Ljava/lang/String;
  #14 = NameAndType        #11:#12        // value:Ljava/lang/String;
  #15 = Fieldref           #2.#14         // argonaut/StringWraps$$anon$1.value:Ljava/lang/String;
  #16 = Utf8               this
  #17 = Utf8               Largonaut/StringWraps$$anon$1;
  #18 = Utf8               <init>
  #19 = Utf8               (Largonaut/StringWraps;Ljava/lang/String;)V
  #20 = Utf8               $outer
  #21 = Utf8               s$1
  #22 = Utf8               ()V
  #23 = NameAndType        #18:#22        // "<init>":()V
  #24 = Methodref          #4.#23         // argonaut/StringWrap."<init>":()V
  #25 = Utf8               Largonaut/StringWraps;
  #26 = Utf8               Code
  #27 = Utf8               LineNumberTable
  #28 = Utf8               LocalVariableTable
  #29 = Utf8               MethodParameters
  #30 = Utf8               InnerClasses
  #31 = Utf8               EnclosingMethod
  #32 = Utf8               SourceFile
  #33 = Utf8               ScalaInlineInfo
  #34 = Utf8               Scala
{
  private final java.lang.String value;
    descriptor: Ljava/lang/String;
    flags: (0x0012) ACC_PRIVATE, ACC_FINAL

  public java.lang.String value();
    descriptor: ()Ljava/lang/String;
    flags: (0x0001) ACC_PUBLIC
    Code:
      stack=1, locals=1, args_size=1
         0: aload_0
         1: getfield      #15                 // Field value:Ljava/lang/String;
         4: areturn
      LineNumberTable:
        line 66: 0
      LocalVariableTable:
        Start  Length  Slot  Name   Signature
            0       5     0  this   Largonaut/StringWraps$$anon$1;

  public argonaut.StringWraps$$anon$1(argonaut.StringWraps, java.lang.String);
    descriptor: (Largonaut/StringWraps;Ljava/lang/String;)V
    flags: (0x0001) ACC_PUBLIC
    Code:
      stack=2, locals=3, args_size=3
         0: aload_0
         1: invokespecial #24                 // Method argonaut/StringWrap."<init>":()V
         4: aload_0
         5: aload_2
         6: putfield      #15                 // Field value:Ljava/lang/String;
         9: return
      LineNumberTable:
        line 65: 0
        line 66: 4
        line 65: 9
      LocalVariableTable:
        Start  Length  Slot  Name   Signature
            0      10     0  this   Largonaut/StringWraps$$anon$1;
            0      10     1 $outer   Largonaut/StringWraps;
            0      10     2   s$1   Ljava/lang/String;
    MethodParameters:
      Name                           Flags
      $outer                         final synthetic
      s$1                            final
}
InnerClasses:
  public final #2;                        // class argonaut/StringWraps$$anon$1
EnclosingMethod: #7.#10                 // argonaut.StringWraps.StringToStringWrap
SourceFile: "StringWrap.scala"
  ScalaInlineInfo: length = 0xE (unknown attribute)
   01 01 00 02 00 12 00 13 01 00 0B 00 0D 01
  Scala: length = 0x0 (unknown attribute)

