Classfile /Users/mw/Projects/slang-braindump/.jar/jar8/assemble/slang-braindump/assemble/content/coursier/internal/InMemoryCache.class
  Last modified May 29, 2022; size 7349 bytes
  SHA-256 checksum 02d15b35a9ac4e8c0fcc8aefed5b73c4d0a09ec0ea2eff5b1361555468211984
  Compiled from "InMemoryCache.scala"
public final class coursier.internal.InMemoryCache<F extends java.lang.Object> extends coursier.cache.Cache<F> implements scala.Product, java.io.Serializable
  minor version: 0
  major version: 52
  flags: (0x0031) ACC_PUBLIC, ACC_FINAL, ACC_SUPER
  this_class: #2                          // coursier/internal/InMemoryCache
  super_class: #5                         // coursier/cache/Cache
  interfaces: 2, fields: 2, methods: 22, attributes: 5
Constant pool:
    #1 = Utf8               coursier/internal/InMemoryCache
    #2 = Class              #1            // coursier/internal/InMemoryCache
    #3 = Utf8               <F:Ljava/lang/Object;>Lcoursier/cache/Cache<TF;>;Lscala/Product;Ljava/io/Serializable;
    #4 = Utf8               coursier/cache/Cache
    #5 = Class              #4            // coursier/cache/Cache
    #6 = Utf8               scala/Product
    #7 = Class              #6            // scala/Product
    #8 = Utf8               java/io/Serializable
    #9 = Class              #8            // java/io/Serializable
   #10 = Utf8               InMemoryCache.scala
   #11 = Utf8               Lscala/reflect/ScalaSignature;
   #12 = Utf8               bytes
   #13 = Utf8               \u0006\u0005\u0005\rf\u0001B\u000e\u001d\u0005\u0005B\u0001\"\u0013\u0001\u0003\u0006\u0004%\tA\u0013\u0005\t\u0017\u0002\u0011\t\u0011)A\u0005G!AA\n\u0001BC\u0002\u0013\u0005Q\n\u0003\u0005U\u0001\t\u0005\t\u0015!\u0003O\u0011\u0015)\u0006\u0001\"\u0001W\u0011\u0015Y\u0006\u0001b\u0003N\u0011\u0015a\u0006\u0001\"\u0001^\u0011\u0015)\u0007\u0001\"\u0001g\u0011\u0015Q\b\u0001\"\u0001|\u0011\u001d\t)\u0001\u0001C!\u0003\u000fAq!!\u0006\u0001\t\u0003\t9\u0002C\u0004\u0002\u001c\u0001!\t!!\b\t\u000f\u0005\u0005\u0002\u0001\"\u0011\u0002$!9\u0011\u0011\u0007\u0001\u0005B\u0005M\u0002bBA \u0001\u0011\u0005\u0013\u0011\t\u0005\b\u0003\u000b\u0002A\u0011IA$\u0011\u001d\ty\u0005\u0001C\u0005\u0003#Bq!!\u0017\u0001\t\u0003\nY\u0006C\u0004\u0002^\u0001!\t%a\u0018\t\u000f\u0005\u0005\u0004\u0001\"\u0011\u0002d!9\u0011\u0011\u000e\u0001\u0005B\u0005-taBA89!\u0005\u0011\u0011\u000f\u0004\u00077qA\t!a\u001d\t\rU;B\u0011AA@\u0011\u001d\t\ti\u0006C\u0001\u0003\u0007C\u0011\"!\'\u0018\u0003\u0003%I!a\'\u0003\u001b%sW*Z7pef\u001c\u0015m\u00195f\u0015\tib$\u0001\u0005j]R,\'O\\1m\u0015\u0005y\u0012\u0001C2pkJ\u001c\u0018.\u001a:\u0004\u0001U\u0011!eK\n\u0005\u0001\rRT\bE\u0002%O%j\u0011!\n\u0006\u0003My\tQaY1dQ\u0016L!\u0001K\u0013\u0003\u000b\r\u000b7\r[3\u0011\u0005)ZC\u0002\u0001\u0003\u0006Y\u0001\u0011\r!\f\u0002\u0002\rV\u0011a\u0006O\t\u0003_U\u0002\"\u0001M\u001a\u000e\u0003ER\u0011AM\u0001\u0006g\u000e\fG.Y\u0005\u0003iE\u0012qAT8uQ&tw\r\u0005\u00021m%\u0011q\'\r\u0002\u0004\u0003:LH!B\u001d,\u0005\u0004q#!A0\u0011\u0005AZ\u0014B\u0001\u001f2\u0005\u001d\u0001&o\u001c3vGR\u0004\"A\u0010$\u000f\u0005}\"eB\u0001!D\u001b\u0005\t%B\u0001\"!\u0003\u0019a$o\\8u}%\t!\'\u0003\u0002Fc\u00059\u0001/Y2lC\u001e,\u0017BA$I\u00051\u0019VM]5bY&T\u0018M\u00197f\u0015\t)\u0015\'\u0001\u0006v]\u0012,\'\u000f\\=j]\u001e,\u0012aI\u0001\fk:$WM\u001d7zS:<\u0007%A\u0001T+\u0005q\u0005cA(SS5\t\u0001K\u0003\u0002R=\u0005!Q\u000f^5m\u0013\t\u0019\u0006K\u0001\u0003Ts:\u001c\u0017AA*!\u0003\u0019a\u0014N\\5u}Q\u0019q+\u0017.\u0011\u0007a\u0003\u0011&D\u0001\u001d\u0011\u0015IU\u00011\u0001$\u0011\u0015aU\u00011\u0001O\u0003\t\u0019\u0006\'A\u0003gKR\u001c\u0007.F\u0001_!\ry&-\u000b\b\u0003I\u0001L!!Y\u0013\u0002\u000b\r\u000b7\r[3\n\u0005\r$\'!\u0002$fi\u000eD\'BA1&\u0003\u00111\u0017\u000e\\3\u0015\u0005\u001d,\b#B(iS)l\u0017BA5Q\u0005\u001d)\u0015\u000e\u001e5feR\u0003\"\u0001J6\n\u00051,#!D!si&4\u0017m\u0019;FeJ|\'\u000f\u0005\u0002og6\tqN\u0003\u0002qc\u0006\u0011\u0011n\u001c\u0006\u0002e\u0006!!.\u0019<b\u0013\t!xN\u0001\u0003GS2,\u0007\"\u0002<\t\u0001\u00049\u0018\u0001C1si&4\u0017m\u0019;\u0011\u0005=C\u0018BA=Q\u0005!\t%\u000f^5gC\u000e$\u0018AA3d+\u0005a\bcA?\u0002\u00025\taP\u0003\u0002\u0000c\u0005Q1m\u001c8dkJ\u0014XM\u001c;\n\u0007\u0005\raP\u0001\tFq\u0016\u001cW\u000f^5p]\u000e{g\u000e^3yi\u0006IAn\\4hKJ|\u0005\u000f^\u000b\u0003\u0003\u0013\u0001R\u0001MA\u0006\u0003\u001fI1!!\u00042\u0005\u0019y\u0005\u000f^5p]B\u0019A%!\u0005\n\u0007\u0005MQEA\u0006DC\u000eDW\rT8hO\u0016\u0014\u0018AD<ji\",f\u000eZ3sYfLgn\u001a\u000b\u0004/\u0006e\u0001\"B%\f\u0001\u0004\u0019\u0013!B<ji\"\u001cFcA,\u0002 !)A\n\u0004a\u0001\u001d\u0006AAo\\*ue&tw\r\u0006\u0002\u0002&A!\u0011qEA\u0017\u001b\t\tICC\u0002\u0002,E\fA\u0001\\1oO&!\u0011qFA\u0015\u0005\u0019\u0019FO]5oO\u0006A1-\u00198FcV\fG\u000e\u0006\u0003\u00026\u0005m\u0002c\u0001\u0019\u00028%\u0019\u0011\u0011H\u0019\u0003\u000f\t{w\u000e\\3b]\"1\u0011Q\b\bA\u0002U\n1a\u001c2k\u0003\u0019)\u0017/^1mgR!\u0011QGA\"\u0011\u0019\tid\u0004a\u0001k\u0005A\u0001.Y:i\u0007>$W\r\u0006\u0002\u0002JA\u0019\u0001\'a\u0013\n\u0007\u00055\u0013GA\u0002J]R\fQ\u0001^;qY\u0016,\"!a\u0015\u0011\u000bA\n)f\t(\n\u0007\u0005]\u0013G\u0001\u0004UkBdWMM\u0001\u000eaJ|G-^2u!J,g-\u001b=\u0016\u0005\u0005\u0015\u0012\u0001\u00049s_\u0012,8\r^!sSRLXCAA%\u00039\u0001(o\u001c3vGR,E.Z7f]R$2!NA3\u0011\u001d\t9\u0007\u0006a\u0001\u0003\u0013\n\u0011A\\\u0001\u0013aJ|G-^2u\u000b2,W.\u001a8u\u001d\u0006lW\r\u0006\u0003\u0002&\u00055\u0004bBA4+\u0001\u0007\u0011\u0011J\u0001\u000e\u0013:lU-\\8ss\u000e\u000b7\r[3\u0011\u0005a;2#B\f\u0002v\u0005m\u0004c\u0001\u0019\u0002x%\u0019\u0011\u0011P\u0019\u0003\r\u0005s\u0017PU3g!\rq\u0017QP\u0005\u0003\u000f>$\"!!\u001d\u0002\u000b\u0005\u0004\b\u000f\\=\u0016\t\u0005\u0015\u00151\u0012\u000b\u0007\u0003\u000f\u000b\t*!&\u0011\ta\u0003\u0011\u0011\u0012\t\u0004U\u0005-EA\u0002\u0017\u001a\u0005\u0004\ti)F\u0002/\u0003\u001f#a!OAF\u0005\u0004q\u0003BB%\u001a\u0001\u0004\t\u0019\n\u0005\u0003%O\u0005%\u0005B\u0002\'\u001a\u0001\u0004\t9\n\u0005\u0003P%\u0006%\u0015\u0001D<sSR,\'+\u001a9mC\u000e,GCAAO!\u0011\t9#a(\n\t\u0005\u0005\u0016\u0011\u0006\u0002\u0007\u001f\nTWm\u0019;
   #14 = Utf8               underlying
   #15 = Utf8               Lcoursier/cache/Cache;
   #16 = Utf8               Lcoursier/cache/Cache<TF;>;
   #17 = Utf8               S
   #18 = Utf8               Lcoursier/util/Sync;
   #19 = Utf8               Lcoursier/util/Sync<TF;>;
   #20 = Utf8               apply
   #21 = Utf8               (Lcoursier/cache/Cache;Lcoursier/util/Sync;)Lcoursier/internal/InMemoryCache;
   #22 = Utf8               <F:Ljava/lang/Object;>(Lcoursier/cache/Cache<TF;>;Lcoursier/util/Sync<TF;>;)Lcoursier/internal/InMemoryCache<TF;>;
   #23 = Utf8               coursier/internal/InMemoryCache$
   #24 = Class              #23           // coursier/internal/InMemoryCache$
   #25 = Utf8               MODULE$
   #26 = Utf8               Lcoursier/internal/InMemoryCache$;
   #27 = NameAndType        #25:#26       // MODULE$:Lcoursier/internal/InMemoryCache$;
   #28 = Fieldref           #24.#27       // coursier/internal/InMemoryCache$.MODULE$:Lcoursier/internal/InMemoryCache$;
   #29 = NameAndType        #20:#21       // apply:(Lcoursier/cache/Cache;Lcoursier/util/Sync;)Lcoursier/internal/InMemoryCache;
   #30 = Methodref          #24.#29       // coursier/internal/InMemoryCache$.apply:(Lcoursier/cache/Cache;Lcoursier/util/Sync;)Lcoursier/internal/InMemoryCache;
   #31 = Utf8               productIterator
   #32 = Utf8               ()Lscala/collection/Iterator;
   #33 = Utf8               ()Lscala/collection/Iterator<Ljava/lang/Object;>;
   #34 = Utf8               productIterator$
   #35 = Utf8               (Lscala/Product;)Lscala/collection/Iterator;
   #36 = NameAndType        #34:#35       // productIterator$:(Lscala/Product;)Lscala/collection/Iterator;
   #37 = InterfaceMethodref #7.#36        // scala/Product.productIterator$:(Lscala/Product;)Lscala/collection/Iterator;
   #38 = Utf8               this
   #39 = Utf8               Lcoursier/internal/InMemoryCache;
   #40 = Utf8               productElementNames
   #41 = Utf8               ()Lscala/collection/Iterator<Ljava/lang/String;>;
   #42 = Utf8               productElementNames$
   #43 = NameAndType        #42:#35       // productElementNames$:(Lscala/Product;)Lscala/collection/Iterator;
   #44 = InterfaceMethodref #7.#43        // scala/Product.productElementNames$:(Lscala/Product;)Lscala/collection/Iterator;
   #45 = Utf8               ()Lcoursier/cache/Cache;
   #46 = Utf8               ()Lcoursier/cache/Cache<TF;>;
   #47 = NameAndType        #14:#15       // underlying:Lcoursier/cache/Cache;
   #48 = Fieldref           #2.#47        // coursier/internal/InMemoryCache.underlying:Lcoursier/cache/Cache;
   #49 = Utf8               ()Lcoursier/util/Sync;
   #50 = Utf8               ()Lcoursier/util/Sync<TF;>;
   #51 = NameAndType        #17:#18       // S:Lcoursier/util/Sync;
   #52 = Fieldref           #2.#51        // coursier/internal/InMemoryCache.S:Lcoursier/util/Sync;
   #53 = Utf8               S0
   #54 = NameAndType        #17:#49       // S:()Lcoursier/util/Sync;
   #55 = Methodref          #2.#54        // coursier/internal/InMemoryCache.S:()Lcoursier/util/Sync;
   #56 = Utf8               fetch
   #57 = Utf8               ()Lscala/Function1;
   #58 = Utf8               ()Lscala/Function1<Lcoursier/util/Artifact;Lcoursier/util/EitherT<TF;Ljava/lang/String;Ljava/lang/String;>;>;
   #59 = Utf8               coursier/internal/InMemoryCachingFetcher
   #60 = Class              #59           // coursier/internal/InMemoryCachingFetcher
   #61 = NameAndType        #14:#45       // underlying:()Lcoursier/cache/Cache;
   #62 = Methodref          #2.#61        // coursier/internal/InMemoryCache.underlying:()Lcoursier/cache/Cache;
   #63 = NameAndType        #56:#57       // fetch:()Lscala/Function1;
   #64 = Methodref          #5.#63        // coursier/cache/Cache.fetch:()Lscala/Function1;
   #65 = NameAndType        #53:#49       // S0:()Lcoursier/util/Sync;
   #66 = Methodref          #2.#65        // coursier/internal/InMemoryCache.S0:()Lcoursier/util/Sync;
   #67 = Utf8               <init>
   #68 = Utf8               (Lscala/Function1;Lcoursier/util/Sync;)V
   #69 = NameAndType        #67:#68       // "<init>":(Lscala/Function1;Lcoursier/util/Sync;)V
   #70 = Methodref          #60.#69       // coursier/internal/InMemoryCachingFetcher."<init>":(Lscala/Function1;Lcoursier/util/Sync;)V
   #71 = Utf8               fetcher
   #72 = NameAndType        #71:#57       // fetcher:()Lscala/Function1;
   #73 = Methodref          #60.#72       // coursier/internal/InMemoryCachingFetcher.fetcher:()Lscala/Function1;
   #74 = Utf8               file
   #75 = Utf8               (Lcoursier/util/Artifact;)Lcoursier/util/EitherT;
   #76 = Utf8               (Lcoursier/util/Artifact;)Lcoursier/util/EitherT<TF;Lcoursier/cache/ArtifactError;Ljava/io/File;>;
   #77 = Utf8               artifact
   #78 = NameAndType        #74:#75       // file:(Lcoursier/util/Artifact;)Lcoursier/util/EitherT;
   #79 = Methodref          #5.#78        // coursier/cache/Cache.file:(Lcoursier/util/Artifact;)Lcoursier/util/EitherT;
   #80 = Utf8               Lcoursier/util/Artifact;
   #81 = Utf8               ec
   #82 = Utf8               ()Lscala/concurrent/ExecutionContext;
   #83 = NameAndType        #81:#82       // ec:()Lscala/concurrent/ExecutionContext;
   #84 = Methodref          #5.#83        // coursier/cache/Cache.ec:()Lscala/concurrent/ExecutionContext;
   #85 = Utf8               loggerOpt
   #86 = Utf8               ()Lscala/Option;
   #87 = Utf8               ()Lscala/Option<Lcoursier/cache/CacheLogger;>;
   #88 = NameAndType        #85:#86       // loggerOpt:()Lscala/Option;
   #89 = Methodref          #5.#88        // coursier/cache/Cache.loggerOpt:()Lscala/Option;
   #90 = Utf8               withUnderlying
   #91 = Utf8               (Lcoursier/cache/Cache;)Lcoursier/internal/InMemoryCache;
   #92 = Utf8               (Lcoursier/cache/Cache<TF;>;)Lcoursier/internal/InMemoryCache<TF;>;
   #93 = Utf8               (Lcoursier/cache/Cache;Lcoursier/util/Sync;)V
   #94 = NameAndType        #67:#93       // "<init>":(Lcoursier/cache/Cache;Lcoursier/util/Sync;)V
   #95 = Methodref          #2.#94        // coursier/internal/InMemoryCache."<init>":(Lcoursier/cache/Cache;Lcoursier/util/Sync;)V
   #96 = Utf8               withS
   #97 = Utf8               (Lcoursier/util/Sync;)Lcoursier/internal/InMemoryCache;
   #98 = Utf8               (Lcoursier/util/Sync<TF;>;)Lcoursier/internal/InMemoryCache<TF;>;
   #99 = Utf8               toString
  #100 = Utf8               ()Ljava/lang/String;
  #101 = Utf8               java/lang/StringBuilder
  #102 = Class              #101          // java/lang/StringBuilder
  #103 = Utf8               InMemoryCache(
  #104 = String             #103          // InMemoryCache(
  #105 = Utf8               (Ljava/lang/String;)V
  #106 = NameAndType        #67:#105      // "<init>":(Ljava/lang/String;)V
  #107 = Methodref          #102.#106     // java/lang/StringBuilder."<init>":(Ljava/lang/String;)V
  #108 = Utf8               java/lang/String
  #109 = Class              #108          // java/lang/String
  #110 = Utf8               valueOf
  #111 = Utf8               (Ljava/lang/Object;)Ljava/lang/String;
  #112 = NameAndType        #110:#111     // valueOf:(Ljava/lang/Object;)Ljava/lang/String;
  #113 = Methodref          #109.#112     // java/lang/String.valueOf:(Ljava/lang/Object;)Ljava/lang/String;
  #114 = Utf8               append
  #115 = Utf8               (Ljava/lang/String;)Ljava/lang/StringBuilder;
  #116 = NameAndType        #114:#115     // append:(Ljava/lang/String;)Ljava/lang/StringBuilder;
  #117 = Methodref          #102.#116     // java/lang/StringBuilder.append:(Ljava/lang/String;)Ljava/lang/StringBuilder;
  #118 = Utf8               ,
  #119 = String             #118          // ,
  #120 = Utf8               )
  #121 = String             #120          // )
  #122 = NameAndType        #99:#100      // toString:()Ljava/lang/String;
  #123 = Methodref          #102.#122     // java/lang/StringBuilder.toString:()Ljava/lang/String;
  #124 = Utf8               b
  #125 = Utf8               Ljava/lang/StringBuilder;
  #126 = Utf8               canEqual
  #127 = Utf8               (Ljava/lang/Object;)Z
  #128 = Utf8               obj
  #129 = Utf8               Ljava/lang/Object;
  #130 = Utf8               equals
  #131 = NameAndType        #126:#127     // canEqual:(Ljava/lang/Object;)Z
  #132 = Methodref          #2.#131       // coursier/internal/InMemoryCache.canEqual:(Ljava/lang/Object;)Z
  #133 = Utf8               java/lang/Object
  #134 = Class              #133          // java/lang/Object
  #135 = NameAndType        #130:#127     // equals:(Ljava/lang/Object;)Z
  #136 = Methodref          #134.#135     // java/lang/Object.equals:(Ljava/lang/Object;)Z
  #137 = Utf8               coursier/util/Sync
  #138 = Class              #137          // coursier/util/Sync
  #139 = Utf8               other
  #140 = Utf8               hashCode
  #141 = Utf8               ()I
  #142 = Utf8               InMemoryCache
  #143 = String             #142          // InMemoryCache
  #144 = Utf8               scala/runtime/Statics
  #145 = Class              #144          // scala/runtime/Statics
  #146 = Utf8               anyHash
  #147 = Utf8               (Ljava/lang/Object;)I
  #148 = NameAndType        #146:#147     // anyHash:(Ljava/lang/Object;)I
  #149 = Methodref          #145.#148     // scala/runtime/Statics.anyHash:(Ljava/lang/Object;)I
  #150 = Utf8               code
  #151 = Utf8               I
  #152 = Utf8               tuple
  #153 = Utf8               ()Lscala/Tuple2;
  #154 = Utf8               ()Lscala/Tuple2<Lcoursier/cache/Cache<TF;>;Lcoursier/util/Sync<TF;>;>;
  #155 = Utf8               scala/Tuple2
  #156 = Class              #155          // scala/Tuple2
  #157 = Utf8               (Ljava/lang/Object;Ljava/lang/Object;)V
  #158 = NameAndType        #67:#157      // "<init>":(Ljava/lang/Object;Ljava/lang/Object;)V
  #159 = Methodref          #156.#158     // scala/Tuple2."<init>":(Ljava/lang/Object;Ljava/lang/Object;)V
  #160 = Utf8               productPrefix
  #161 = Utf8               productArity
  #162 = Utf8               productElement
  #163 = Utf8               (I)Ljava/lang/Object;
  #164 = Utf8               n
  #165 = Utf8               java/lang/IndexOutOfBoundsException
  #166 = Class              #165          // java/lang/IndexOutOfBoundsException
  #167 = Utf8               scala/runtime/BoxesRunTime
  #168 = Class              #167          // scala/runtime/BoxesRunTime
  #169 = Utf8               boxToInteger
  #170 = Utf8               (I)Ljava/lang/Integer;
  #171 = NameAndType        #169:#170     // boxToInteger:(I)Ljava/lang/Integer;
  #172 = Methodref          #168.#171     // scala/runtime/BoxesRunTime.boxToInteger:(I)Ljava/lang/Integer;
  #173 = Methodref          #134.#122     // java/lang/Object.toString:()Ljava/lang/String;
  #174 = Methodref          #166.#106     // java/lang/IndexOutOfBoundsException."<init>":(Ljava/lang/String;)V
  #175 = Utf8               productElementName
  #176 = Utf8               (I)Ljava/lang/String;
  #177 = String             #14           // underlying
  #178 = String             #17           // S
  #179 = Utf8               (Lcoursier/cache/Cache<TF;>;Lcoursier/util/Sync<TF;>;)V
  #180 = Utf8               ()V
  #181 = NameAndType        #67:#180      // "<init>":()V
  #182 = Methodref          #5.#181       // coursier/cache/Cache."<init>":()V
  #183 = Utf8               $init$
  #184 = Utf8               (Lscala/Product;)V
  #185 = NameAndType        #183:#184     // $init$:(Lscala/Product;)V
  #186 = InterfaceMethodref #7.#185       // scala/Product.$init$:(Lscala/Product;)V
  #187 = Utf8               Signature
  #188 = Utf8               Code
  #189 = Utf8               MethodParameters
  #190 = Utf8               LineNumberTable
  #191 = Utf8               LocalVariableTable
  #192 = Utf8               StackMapTable
  #193 = Utf8               SourceFile
  #194 = Utf8               RuntimeVisibleAnnotations
  #195 = Utf8               ScalaInlineInfo
  #196 = Utf8               ScalaSig
{
  private final coursier.cache.Cache<F> underlying;
    descriptor: Lcoursier/cache/Cache;
    flags: (0x0012) ACC_PRIVATE, ACC_FINAL
    Signature: #16                          // Lcoursier/cache/Cache<TF;>;

  private final coursier.util.Sync<F> S;
    descriptor: Lcoursier/util/Sync;
    flags: (0x0012) ACC_PRIVATE, ACC_FINAL
    Signature: #19                          // Lcoursier/util/Sync<TF;>;

  public static <F extends java.lang.Object> coursier.internal.InMemoryCache<F> apply(coursier.cache.Cache<F>, coursier.util.Sync<F>);
    descriptor: (Lcoursier/cache/Cache;Lcoursier/util/Sync;)Lcoursier/internal/InMemoryCache;
    flags: (0x0009) ACC_PUBLIC, ACC_STATIC
    Code:
      stack=3, locals=2, args_size=2
         0: getstatic     #28                 // Field coursier/internal/InMemoryCache$.MODULE$:Lcoursier/internal/InMemoryCache$;
         3: aload_0
         4: aload_1
         5: invokevirtual #30                 // Method coursier/internal/InMemoryCache$.apply:(Lcoursier/cache/Cache;Lcoursier/util/Sync;)Lcoursier/internal/InMemoryCache;
         8: areturn
    Signature: #22                          // <F:Ljava/lang/Object;>(Lcoursier/cache/Cache<TF;>;Lcoursier/util/Sync<TF;>;)Lcoursier/internal/InMemoryCache<TF;>;
    MethodParameters:
      Name                           Flags
      underlying                     final
      S                              final

  public scala.collection.Iterator<java.lang.Object> productIterator();
    descriptor: ()Lscala/collection/Iterator;
    flags: (0x0001) ACC_PUBLIC
    Code:
      stack=1, locals=1, args_size=1
         0: aload_0
         1: invokestatic  #37                 // InterfaceMethod scala/Product.productIterator$:(Lscala/Product;)Lscala/collection/Iterator;
         4: areturn
      LineNumberTable:
        line 11: 0
      LocalVariableTable:
        Start  Length  Slot  Name   Signature
            0       5     0  this   Lcoursier/internal/InMemoryCache;
    Signature: #33                          // ()Lscala/collection/Iterator<Ljava/lang/Object;>;

  public scala.collection.Iterator<java.lang.String> productElementNames();
    descriptor: ()Lscala/collection/Iterator;
    flags: (0x0001) ACC_PUBLIC
    Code:
      stack=1, locals=1, args_size=1
         0: aload_0
         1: invokestatic  #44                 // InterfaceMethod scala/Product.productElementNames$:(Lscala/Product;)Lscala/collection/Iterator;
         4: areturn
      LineNumberTable:
        line 11: 0
      LocalVariableTable:
        Start  Length  Slot  Name   Signature
            0       5     0  this   Lcoursier/internal/InMemoryCache;
    Signature: #41                          // ()Lscala/collection/Iterator<Ljava/lang/String;>;

  public coursier.cache.Cache<F> underlying();
    descriptor: ()Lcoursier/cache/Cache;
    flags: (0x0001) ACC_PUBLIC
    Code:
      stack=1, locals=1, args_size=1
         0: aload_0
         1: getfield      #48                 // Field underlying:Lcoursier/cache/Cache;
         4: areturn
      LineNumberTable:
        line 11: 0
      LocalVariableTable:
        Start  Length  Slot  Name   Signature
            0       5     0  this   Lcoursier/internal/InMemoryCache;
    Signature: #46                          // ()Lcoursier/cache/Cache<TF;>;

  public coursier.util.Sync<F> S();
    descriptor: ()Lcoursier/util/Sync;
    flags: (0x0001) ACC_PUBLIC
    Code:
      stack=1, locals=1, args_size=1
         0: aload_0
         1: getfield      #52                 // Field S:Lcoursier/util/Sync;
         4: areturn
      LineNumberTable:
        line 11: 0
      LocalVariableTable:
        Start  Length  Slot  Name   Signature
            0       5     0  this   Lcoursier/internal/InMemoryCache;
    Signature: #50                          // ()Lcoursier/util/Sync<TF;>;

  private coursier.util.Sync<F> S0();
    descriptor: ()Lcoursier/util/Sync;
    flags: (0x0002) ACC_PRIVATE
    Code:
      stack=1, locals=1, args_size=1
         0: aload_0
         1: invokevirtual #55                 // Method S:()Lcoursier/util/Sync;
         4: areturn
      LineNumberTable:
        line 13: 0
      LocalVariableTable:
        Start  Length  Slot  Name   Signature
            0       5     0  this   Lcoursier/internal/InMemoryCache;
    Signature: #50                          // ()Lcoursier/util/Sync<TF;>;

  public scala.Function1<coursier.util.Artifact, coursier.util.EitherT<F, java.lang.String, java.lang.String>> fetch();
    descriptor: ()Lscala/Function1;
    flags: (0x0001) ACC_PUBLIC
    Code:
      stack=4, locals=1, args_size=1
         0: new           #60                 // class coursier/internal/InMemoryCachingFetcher
         3: dup
         4: aload_0
         5: invokevirtual #62                 // Method underlying:()Lcoursier/cache/Cache;
         8: invokevirtual #64                 // Method coursier/cache/Cache.fetch:()Lscala/Function1;
        11: aload_0
        12: invokespecial #66                 // Method S0:()Lcoursier/util/Sync;
        15: invokespecial #70                 // Method coursier/internal/InMemoryCachingFetcher."<init>":(Lscala/Function1;Lcoursier/util/Sync;)V
        18: invokevirtual #73                 // Method coursier/internal/InMemoryCachingFetcher.fetcher:()Lscala/Function1;
        21: areturn
      LineNumberTable:
        line 16: 0
      LocalVariableTable:
        Start  Length  Slot  Name   Signature
            0      22     0  this   Lcoursier/internal/InMemoryCache;
    Signature: #58                          // ()Lscala/Function1<Lcoursier/util/Artifact;Lcoursier/util/EitherT<TF;Ljava/lang/String;Ljava/lang/String;>;>;

  public coursier.util.EitherT<F, coursier.cache.ArtifactError, java.io.File> file(coursier.util.Artifact);
    descriptor: (Lcoursier/util/Artifact;)Lcoursier/util/EitherT;
    flags: (0x0001) ACC_PUBLIC
    Code:
      stack=2, locals=2, args_size=2
         0: aload_0
         1: invokevirtual #62                 // Method underlying:()Lcoursier/cache/Cache;
         4: aload_1
         5: invokevirtual #79                 // Method coursier/cache/Cache.file:(Lcoursier/util/Artifact;)Lcoursier/util/EitherT;
         8: areturn
      LineNumberTable:
        line 19: 0
      LocalVariableTable:
        Start  Length  Slot  Name   Signature
            0       9     0  this   Lcoursier/internal/InMemoryCache;
            0       9     1 artifact   Lcoursier/util/Artifact;
    Signature: #76                          // (Lcoursier/util/Artifact;)Lcoursier/util/EitherT<TF;Lcoursier/cache/ArtifactError;Ljava/io/File;>;
    MethodParameters:
      Name                           Flags
      artifact                       final

  public scala.concurrent.ExecutionContext ec();
    descriptor: ()Lscala/concurrent/ExecutionContext;
    flags: (0x0001) ACC_PUBLIC
    Code:
      stack=1, locals=1, args_size=1
         0: aload_0
         1: invokevirtual #62                 // Method underlying:()Lcoursier/cache/Cache;
         4: invokevirtual #84                 // Method coursier/cache/Cache.ec:()Lscala/concurrent/ExecutionContext;
         7: areturn
      LineNumberTable:
        line 22: 0
      LocalVariableTable:
        Start  Length  Slot  Name   Signature
            0       8     0  this   Lcoursier/internal/InMemoryCache;

  public scala.Option<coursier.cache.CacheLogger> loggerOpt();
    descriptor: ()Lscala/Option;
    flags: (0x0001) ACC_PUBLIC
    Code:
      stack=1, locals=1, args_size=1
         0: aload_0
         1: invokevirtual #62                 // Method underlying:()Lcoursier/cache/Cache;
         4: invokevirtual #89                 // Method coursier/cache/Cache.loggerOpt:()Lscala/Option;
         7: areturn
      LineNumberTable:
        line 25: 0
      LocalVariableTable:
        Start  Length  Slot  Name   Signature
            0       8     0  this   Lcoursier/internal/InMemoryCache;
    Signature: #87                          // ()Lscala/Option<Lcoursier/cache/CacheLogger;>;

  public coursier.internal.InMemoryCache<F> withUnderlying(coursier.cache.Cache<F>);
    descriptor: (Lcoursier/cache/Cache;)Lcoursier/internal/InMemoryCache;
    flags: (0x0001) ACC_PUBLIC
    Code:
      stack=4, locals=2, args_size=2
         0: new           #2                  // class coursier/internal/InMemoryCache
         3: dup
         4: aload_1
         5: aload_0
         6: invokevirtual #55                 // Method S:()Lcoursier/util/Sync;
         9: invokespecial #95                 // Method "<init>":(Lcoursier/cache/Cache;Lcoursier/util/Sync;)V
        12: areturn
      LineNumberTable:
        line 11: 0
      LocalVariableTable:
        Start  Length  Slot  Name   Signature
            0      13     0  this   Lcoursier/internal/InMemoryCache;
            0      13     1 underlying   Lcoursier/cache/Cache;
    Signature: #92                          // (Lcoursier/cache/Cache<TF;>;)Lcoursier/internal/InMemoryCache<TF;>;
    MethodParameters:
      Name                           Flags
      underlying                     final

  public coursier.internal.InMemoryCache<F> withS(coursier.util.Sync<F>);
    descriptor: (Lcoursier/util/Sync;)Lcoursier/internal/InMemoryCache;
    flags: (0x0001) ACC_PUBLIC
    Code:
      stack=4, locals=2, args_size=2
         0: new           #2                  // class coursier/internal/InMemoryCache
         3: dup
         4: aload_0
         5: invokevirtual #62                 // Method underlying:()Lcoursier/cache/Cache;
         8: aload_1
         9: invokespecial #95                 // Method "<init>":(Lcoursier/cache/Cache;Lcoursier/util/Sync;)V
        12: areturn
      LineNumberTable:
        line 11: 0
      LocalVariableTable:
        Start  Length  Slot  Name   Signature
            0      13     0  this   Lcoursier/internal/InMemoryCache;
            0      13     1     S   Lcoursier/util/Sync;
    Signature: #98                          // (Lcoursier/util/Sync<TF;>;)Lcoursier/internal/InMemoryCache<TF;>;
    MethodParameters:
      Name                           Flags
      S                              final

  public java.lang.String toString();
    descriptor: ()Ljava/lang/String;
    flags: (0x0001) ACC_PUBLIC
    Code:
      stack=3, locals=2, args_size=1
         0: new           #102                // class java/lang/StringBuilder
         3: dup
         4: ldc           #104                // String InMemoryCache(
         6: invokespecial #107                // Method java/lang/StringBuilder."<init>":(Ljava/lang/String;)V
         9: astore_1
        10: aload_1
        11: aload_0
        12: invokevirtual #62                 // Method underlying:()Lcoursier/cache/Cache;
        15: invokestatic  #113                // Method java/lang/String.valueOf:(Ljava/lang/Object;)Ljava/lang/String;
        18: invokevirtual #117                // Method java/lang/StringBuilder.append:(Ljava/lang/String;)Ljava/lang/StringBuilder;
        21: pop
        22: aload_1
        23: ldc           #119                // String ,
        25: invokevirtual #117                // Method java/lang/StringBuilder.append:(Ljava/lang/String;)Ljava/lang/StringBuilder;
        28: pop
        29: aload_1
        30: aload_0
        31: invokevirtual #55                 // Method S:()Lcoursier/util/Sync;
        34: invokestatic  #113                // Method java/lang/String.valueOf:(Ljava/lang/Object;)Ljava/lang/String;
        37: invokevirtual #117                // Method java/lang/StringBuilder.append:(Ljava/lang/String;)Ljava/lang/StringBuilder;
        40: pop
        41: aload_1
        42: ldc           #121                // String )
        44: invokevirtual #117                // Method java/lang/StringBuilder.append:(Ljava/lang/String;)Ljava/lang/StringBuilder;
        47: pop
        48: aload_1
        49: invokevirtual #123                // Method java/lang/StringBuilder.toString:()Ljava/lang/String;
        52: areturn
      LineNumberTable:
        line 11: 0
      LocalVariableTable:
        Start  Length  Slot  Name   Signature
           10      42     1     b   Ljava/lang/StringBuilder;
            0      53     0  this   Lcoursier/internal/InMemoryCache;

  public boolean canEqual(java.lang.Object);
    descriptor: (Ljava/lang/Object;)Z
    flags: (0x0001) ACC_PUBLIC
    Code:
      stack=1, locals=2, args_size=2
         0: aload_1
         1: ifnull        15
         4: aload_1
         5: instanceof    #2                  // class coursier/internal/InMemoryCache
         8: ifeq          15
        11: iconst_1
        12: goto          16
        15: iconst_0
        16: ireturn
      StackMapTable: number_of_entries = 2
        frame_type = 15 /* same */
        frame_type = 64 /* same_locals_1_stack_item */
          stack = [ int ]
      LineNumberTable:
        line 11: 0
      LocalVariableTable:
        Start  Length  Slot  Name   Signature
            0      17     0  this   Lcoursier/internal/InMemoryCache;
            0      17     1   obj   Ljava/lang/Object;
    MethodParameters:
      Name                           Flags
      obj                            final

  public boolean equals(java.lang.Object);
    descriptor: (Ljava/lang/Object;)Z
    flags: (0x0001) ACC_PUBLIC
    Code:
      stack=2, locals=5, args_size=2
         0: aload_0
         1: aload_1
         2: if_acmpeq     89
         5: aload_0
         6: aload_1
         7: invokevirtual #132                // Method canEqual:(Ljava/lang/Object;)Z
        10: ifeq          93
        13: aload_1
        14: checkcast     #2                  // class coursier/internal/InMemoryCache
        17: astore_2
        18: iconst_1
        19: ifeq          85
        22: aload_0
        23: invokevirtual #62                 // Method underlying:()Lcoursier/cache/Cache;
        26: aload_2
        27: invokevirtual #62                 // Method underlying:()Lcoursier/cache/Cache;
        30: astore_3
        31: dup
        32: ifnonnull     43
        35: pop
        36: aload_3
        37: ifnull        50
        40: goto          85
        43: aload_3
        44: invokevirtual #136                // Method java/lang/Object.equals:(Ljava/lang/Object;)Z
        47: ifeq          85
        50: aload_0
        51: invokevirtual #55                 // Method S:()Lcoursier/util/Sync;
        54: aload_2
        55: invokevirtual #55                 // Method S:()Lcoursier/util/Sync;
        58: astore        4
        60: dup
        61: ifnonnull     73
        64: pop
        65: aload         4
        67: ifnull        81
        70: goto          85
        73: aload         4
        75: invokevirtual #136                // Method java/lang/Object.equals:(Ljava/lang/Object;)Z
        78: ifeq          85
        81: iconst_1
        82: goto          86
        85: iconst_0
        86: ifeq          93
        89: iconst_1
        90: goto          94
        93: iconst_0
        94: ireturn
      StackMapTable: number_of_entries = 9
        frame_type = 255 /* full_frame */
          offset_delta = 43
          locals = [ class coursier/internal/InMemoryCache, class java/lang/Object, class coursier/internal/InMemoryCache, class coursier/cache/Cache ]
          stack = [ class coursier/cache/Cache ]
        frame_type = 6 /* same */
        frame_type = 255 /* full_frame */
          offset_delta = 22
          locals = [ class coursier/internal/InMemoryCache, class java/lang/Object, class coursier/internal/InMemoryCache, class coursier/cache/Cache, class coursier/util/Sync ]
          stack = [ class coursier/util/Sync ]
        frame_type = 7 /* same */
        frame_type = 249 /* chop */
          offset_delta = 3
        frame_type = 64 /* same_locals_1_stack_item */
          stack = [ int ]
        frame_type = 250 /* chop */
          offset_delta = 2
        frame_type = 3 /* same */
        frame_type = 64 /* same_locals_1_stack_item */
          stack = [ int ]
      LineNumberTable:
        line 11: 0
      LocalVariableTable:
        Start  Length  Slot  Name   Signature
           18      68     2 other   Lcoursier/internal/InMemoryCache;
            0      95     0  this   Lcoursier/internal/InMemoryCache;
            0      95     1   obj   Ljava/lang/Object;
    MethodParameters:
      Name                           Flags
      obj                            final

  public int hashCode();
    descriptor: ()I
    flags: (0x0001) ACC_PUBLIC
    Code:
      stack=2, locals=2, args_size=1
         0: bipush        17
         2: ldc           #143                // String InMemoryCache
         4: invokestatic  #149                // Method scala/runtime/Statics.anyHash:(Ljava/lang/Object;)I
         7: iadd
         8: istore_1
         9: bipush        37
        11: iload_1
        12: imul
        13: aload_0
        14: invokevirtual #62                 // Method underlying:()Lcoursier/cache/Cache;
        17: invokestatic  #149                // Method scala/runtime/Statics.anyHash:(Ljava/lang/Object;)I
        20: iadd
        21: istore_1
        22: bipush        37
        24: iload_1
        25: imul
        26: aload_0
        27: invokevirtual #55                 // Method S:()Lcoursier/util/Sync;
        30: invokestatic  #149                // Method scala/runtime/Statics.anyHash:(Ljava/lang/Object;)I
        33: iadd
        34: istore_1
        35: bipush        37
        37: iload_1
        38: imul
        39: ireturn
      LineNumberTable:
        line 11: 0
      LocalVariableTable:
        Start  Length  Slot  Name   Signature
            9      30     1  code   I
            0      40     0  this   Lcoursier/internal/InMemoryCache;

  private scala.Tuple2<coursier.cache.Cache<F>, coursier.util.Sync<F>> tuple();
    descriptor: ()Lscala/Tuple2;
    flags: (0x0002) ACC_PRIVATE
    Code:
      stack=4, locals=1, args_size=1
         0: new           #156                // class scala/Tuple2
         3: dup
         4: aload_0
         5: invokevirtual #62                 // Method underlying:()Lcoursier/cache/Cache;
         8: aload_0
         9: invokevirtual #55                 // Method S:()Lcoursier/util/Sync;
        12: invokespecial #159                // Method scala/Tuple2."<init>":(Ljava/lang/Object;Ljava/lang/Object;)V
        15: areturn
      LineNumberTable:
        line 11: 0
      LocalVariableTable:
        Start  Length  Slot  Name   Signature
            0      16     0  this   Lcoursier/internal/InMemoryCache;
    Signature: #154                         // ()Lscala/Tuple2<Lcoursier/cache/Cache<TF;>;Lcoursier/util/Sync<TF;>;>;

  public java.lang.String productPrefix();
    descriptor: ()Ljava/lang/String;
    flags: (0x0001) ACC_PUBLIC
    Code:
      stack=1, locals=1, args_size=1
         0: ldc           #143                // String InMemoryCache
         2: areturn
      LineNumberTable:
        line 11: 0
      LocalVariableTable:
        Start  Length  Slot  Name   Signature
            0       3     0  this   Lcoursier/internal/InMemoryCache;

  public int productArity();
    descriptor: ()I
    flags: (0x0001) ACC_PUBLIC
    Code:
      stack=1, locals=1, args_size=1
         0: iconst_2
         1: ireturn
      LineNumberTable:
        line 11: 0
      LocalVariableTable:
        Start  Length  Slot  Name   Signature
            0       2     0  this   Lcoursier/internal/InMemoryCache;

  public java.lang.Object productElement(int);
    descriptor: (I)Ljava/lang/Object;
    flags: (0x0001) ACC_PUBLIC
    Code:
      stack=3, locals=3, args_size=2
         0: iload_1
         1: istore_2
         2: iload_2
         3: tableswitch   { // 0 to 1
                       0: 24
                       1: 31
                 default: 38
            }
        24: aload_0
        25: invokevirtual #62                 // Method underlying:()Lcoursier/cache/Cache;
        28: goto          53
        31: aload_0
        32: invokevirtual #55                 // Method S:()Lcoursier/util/Sync;
        35: goto          53
        38: new           #166                // class java/lang/IndexOutOfBoundsException
        41: dup
        42: iload_2
        43: invokestatic  #172                // Method scala/runtime/BoxesRunTime.boxToInteger:(I)Ljava/lang/Integer;
        46: invokevirtual #173                // Method java/lang/Object.toString:()Ljava/lang/String;
        49: invokespecial #174                // Method java/lang/IndexOutOfBoundsException."<init>":(Ljava/lang/String;)V
        52: athrow
        53: areturn
      StackMapTable: number_of_entries = 4
        frame_type = 252 /* append */
          offset_delta = 24
          locals = [ int ]
        frame_type = 6 /* same */
        frame_type = 6 /* same */
        frame_type = 78 /* same_locals_1_stack_item */
          stack = [ class java/lang/Object ]
      LineNumberTable:
        line 11: 0
      LocalVariableTable:
        Start  Length  Slot  Name   Signature
            0      54     0  this   Lcoursier/internal/InMemoryCache;
            0      54     1     n   I
    MethodParameters:
      Name                           Flags
      n                              final

  public java.lang.String productElementName(int);
    descriptor: (I)Ljava/lang/String;
    flags: (0x0001) ACC_PUBLIC
    Code:
      stack=3, locals=3, args_size=2
         0: iload_1
         1: istore_2
         2: iload_2
         3: tableswitch   { // 0 to 1
                       0: 24
                       1: 29
                 default: 34
            }
        24: ldc           #177                // String underlying
        26: goto          49
        29: ldc           #178                // String S
        31: goto          49
        34: new           #166                // class java/lang/IndexOutOfBoundsException
        37: dup
        38: iload_2
        39: invokestatic  #172                // Method scala/runtime/BoxesRunTime.boxToInteger:(I)Ljava/lang/Integer;
        42: invokevirtual #173                // Method java/lang/Object.toString:()Ljava/lang/String;
        45: invokespecial #174                // Method java/lang/IndexOutOfBoundsException."<init>":(Ljava/lang/String;)V
        48: athrow
        49: areturn
      StackMapTable: number_of_entries = 4
        frame_type = 252 /* append */
          offset_delta = 24
          locals = [ int ]
        frame_type = 4 /* same */
        frame_type = 4 /* same */
        frame_type = 78 /* same_locals_1_stack_item */
          stack = [ class java/lang/String ]
      LineNumberTable:
        line 11: 0
      LocalVariableTable:
        Start  Length  Slot  Name   Signature
            0      50     0  this   Lcoursier/internal/InMemoryCache;
            0      50     1     n   I
    MethodParameters:
      Name                           Flags
      n                              final

  public coursier.internal.InMemoryCache(coursier.cache.Cache<F>, coursier.util.Sync<F>);
    descriptor: (Lcoursier/cache/Cache;Lcoursier/util/Sync;)V
    flags: (0x0001) ACC_PUBLIC
    Code:
      stack=2, locals=3, args_size=3
         0: aload_0
         1: aload_1
         2: putfield      #48                 // Field underlying:Lcoursier/cache/Cache;
         5: aload_0
         6: aload_2
         7: putfield      #52                 // Field S:Lcoursier/util/Sync;
        10: aload_0
        11: invokespecial #182                // Method coursier/cache/Cache."<init>":()V
        14: aload_0
        15: invokestatic  #186                // InterfaceMethod scala/Product.$init$:(Lscala/Product;)V
        18: return
      LineNumberTable:
        line 11: 0
      LocalVariableTable:
        Start  Length  Slot  Name   Signature
            0      19     0  this   Lcoursier/internal/InMemoryCache;
            0      19     1 underlying   Lcoursier/cache/Cache;
            0      19     2     S   Lcoursier/util/Sync;
    Signature: #179                         // (Lcoursier/cache/Cache<TF;>;Lcoursier/util/Sync<TF;>;)V
    MethodParameters:
      Name                           Flags
      underlying                     final
      S                              final
}
Signature: #3                           // <F:Ljava/lang/Object;>Lcoursier/cache/Cache<TF;>;Lscala/Product;Ljava/io/Serializable;
SourceFile: "InMemoryCache.scala"
RuntimeVisibleAnnotations:
  0: #11(#12=s#13)
    scala.reflect.ScalaSignature(
      bytes="\u0006\u0005\u0005\rf\u0001B\u000e\u001d\u0005\u0005B\u0001\"\u0013\u0001\u0003\u0006\u0004%\tA\u0013\u0005\t\u0017\u0002\u0011\t\u0011)A\u0005G!AA\n\u0001BC\u0002\u0013\u0005Q\n\u0003\u0005U\u0001\t\u0005\t\u0015!\u0003O\u0011\u0015)\u0006\u0001\"\u0001W\u0011\u0015Y\u0006\u0001b\u0003N\u0011\u0015a\u0006\u0001\"\u0001^\u0011\u0015)\u0007\u0001\"\u0001g\u0011\u0015Q\b\u0001\"\u0001|\u0011\u001d\t)\u0001\u0001C!\u0003\u000fAq!!\u0006\u0001\t\u0003\t9\u0002C\u0004\u0002\u001c\u0001!\t!!\b\t\u000f\u0005\u0005\u0002\u0001\"\u0011\u0002$!9\u0011\u0011\u0007\u0001\u0005B\u0005M\u0002bBA \u0001\u0011\u0005\u0013\u0011\t\u0005\b\u0003\u000b\u0002A\u0011IA$\u0011\u001d\ty\u0005\u0001C\u0005\u0003#Bq!!\u0017\u0001\t\u0003\nY\u0006C\u0004\u0002^\u0001!\t%a\u0018\t\u000f\u0005\u0005\u0004\u0001\"\u0011\u0002d!9\u0011\u0011\u000e\u0001\u0005B\u0005-taBA89!\u0005\u0011\u0011\u000f\u0004\u00077qA\t!a\u001d\t\rU;B\u0011AA@\u0011\u001d\t\ti\u0006C\u0001\u0003\u0007C\u0011\"!\'\u0018\u0003\u0003%I!a\'\u0003\u001b%sW*Z7pef\u001c\u0015m\u00195f\u0015\tib$\u0001\u0005j]R,\'O\\1m\u0015\u0005y\u0012\u0001C2pkJ\u001c\u0018.\u001a:\u0004\u0001U\u0011!eK\n\u0005\u0001\rRT\bE\u0002%O%j\u0011!\n\u0006\u0003My\tQaY1dQ\u0016L!\u0001K\u0013\u0003\u000b\r\u000b7\r[3\u0011\u0005)ZC\u0002\u0001\u0003\u0006Y\u0001\u0011\r!\f\u0002\u0002\rV\u0011a\u0006O\t\u0003_U\u0002\"\u0001M\u001a\u000e\u0003ER\u0011AM\u0001\u0006g\u000e\fG.Y\u0005\u0003iE\u0012qAT8uQ&tw\r\u0005\u00021m%\u0011q\'\r\u0002\u0004\u0003:LH!B\u001d,\u0005\u0004q#!A0\u0011\u0005AZ\u0014B\u0001\u001f2\u0005\u001d\u0001&o\u001c3vGR\u0004\"A\u0010$\u000f\u0005}\"eB\u0001!D\u001b\u0005\t%B\u0001\"!\u0003\u0019a$o\\8u}%\t!\'\u0003\u0002Fc\u00059\u0001/Y2lC\u001e,\u0017BA$I\u00051\u0019VM]5bY&T\u0018M\u00197f\u0015\t)\u0015\'\u0001\u0006v]\u0012,\'\u000f\\=j]\u001e,\u0012aI\u0001\fk:$WM\u001d7zS:<\u0007%A\u0001T+\u0005q\u0005cA(SS5\t\u0001K\u0003\u0002R=\u0005!Q\u000f^5m\u0013\t\u0019\u0006K\u0001\u0003Ts:\u001c\u0017AA*!\u0003\u0019a\u0014N\\5u}Q\u0019q+\u0017.\u0011\u0007a\u0003\u0011&D\u0001\u001d\u0011\u0015IU\u00011\u0001$\u0011\u0015aU\u00011\u0001O\u0003\t\u0019\u0006\'A\u0003gKR\u001c\u0007.F\u0001_!\ry&-\u000b\b\u0003I\u0001L!!Y\u0013\u0002\u000b\r\u000b7\r[3\n\u0005\r$\'!\u0002$fi\u000eD\'BA1&\u0003\u00111\u0017\u000e\\3\u0015\u0005\u001d,\b#B(iS)l\u0017BA5Q\u0005\u001d)\u0015\u000e\u001e5feR\u0003\"\u0001J6\n\u00051,#!D!si&4\u0017m\u0019;FeJ|\'\u000f\u0005\u0002og6\tqN\u0003\u0002qc\u0006\u0011\u0011n\u001c\u0006\u0002e\u0006!!.\u0019<b\u0013\t!xN\u0001\u0003GS2,\u0007\"\u0002<\t\u0001\u00049\u0018\u0001C1si&4\u0017m\u0019;\u0011\u0005=C\u0018BA=Q\u0005!\t%\u000f^5gC\u000e$\u0018AA3d+\u0005a\bcA?\u0002\u00025\taP\u0003\u0002\u0000c\u0005Q1m\u001c8dkJ\u0014XM\u001c;\n\u0007\u0005\raP\u0001\tFq\u0016\u001cW\u000f^5p]\u000e{g\u000e^3yi\u0006IAn\\4hKJ|\u0005\u000f^\u000b\u0003\u0003\u0013\u0001R\u0001MA\u0006\u0003\u001fI1!!\u00042\u0005\u0019y\u0005\u000f^5p]B\u0019A%!\u0005\n\u0007\u0005MQEA\u0006DC\u000eDW\rT8hO\u0016\u0014\u0018AD<ji\",f\u000eZ3sYfLgn\u001a\u000b\u0004/\u0006e\u0001\"B%\f\u0001\u0004\u0019\u0013!B<ji\"\u001cFcA,\u0002 !)A\n\u0004a\u0001\u001d\u0006AAo\\*ue&tw\r\u0006\u0002\u0002&A!\u0011qEA\u0017\u001b\t\tICC\u0002\u0002,E\fA\u0001\\1oO&!\u0011qFA\u0015\u0005\u0019\u0019FO]5oO\u0006A1-\u00198FcV\fG\u000e\u0006\u0003\u00026\u0005m\u0002c\u0001\u0019\u00028%\u0019\u0011\u0011H\u0019\u0003\u000f\t{w\u000e\\3b]\"1\u0011Q\b\bA\u0002U\n1a\u001c2k\u0003\u0019)\u0017/^1mgR!\u0011QGA\"\u0011\u0019\tid\u0004a\u0001k\u0005A\u0001.Y:i\u0007>$W\r\u0006\u0002\u0002JA\u0019\u0001\'a\u0013\n\u0007\u00055\u0013GA\u0002J]R\fQ\u0001^;qY\u0016,\"!a\u0015\u0011\u000bA\n)f\t(\n\u0007\u0005]\u0013G\u0001\u0004UkBdWMM\u0001\u000eaJ|G-^2u!J,g-\u001b=\u0016\u0005\u0005\u0015\u0012\u0001\u00049s_\u0012,8\r^!sSRLXCAA%\u00039\u0001(o\u001c3vGR,E.Z7f]R$2!NA3\u0011\u001d\t9\u0007\u0006a\u0001\u0003\u0013\n\u0011A\\\u0001\u0013aJ|G-^2u\u000b2,W.\u001a8u\u001d\u0006lW\r\u0006\u0003\u0002&\u00055\u0004bBA4+\u0001\u0007\u0011\u0011J\u0001\u000e\u0013:lU-\\8ss\u000e\u000b7\r[3\u0011\u0005a;2#B\f\u0002v\u0005m\u0004c\u0001\u0019\u0002x%\u0019\u0011\u0011P\u0019\u0003\r\u0005s\u0017PU3g!\rq\u0017QP\u0005\u0003\u000f>$\"!!\u001d\u0002\u000b\u0005\u0004\b\u000f\\=\u0016\t\u0005\u0015\u00151\u0012\u000b\u0007\u0003\u000f\u000b\t*!&\u0011\ta\u0003\u0011\u0011\u0012\t\u0004U\u0005-EA\u0002\u0017\u001a\u0005\u0004\ti)F\u0002/\u0003\u001f#a!OAF\u0005\u0004q\u0003BB%\u001a\u0001\u0004\t\u0019\n\u0005\u0003%O\u0005%\u0005B\u0002\'\u001a\u0001\u0004\t9\n\u0005\u0003P%\u0006%\u0015\u0001D<sSR,\'+\u001a9mC\u000e,GCAAO!\u0011\t9#a(\n\t\u0005\u0005\u0016\u0011\u0006\u0002\u0007\u001f\nTWm\u0019;"
    )
  ScalaInlineInfo: length = 0x6D (unknown attribute)
   01 01 00 15 00 43 00 5D 01 00 11 00 31 01 00 35
   00 31 01 00 7E 00 7F 01 00 51 00 52 01 00 82 00
   7F 01 00 38 00 39 01 00 4A 00 4B 01 00 8C 00 8D
   01 00 55 00 56 01 00 A1 00 8D 01 00 A2 00 A3 01
   00 AF 00 B0 01 00 28 00 20 01 00 1F 00 20 01 00
   A0 00 64 01 00 63 00 64 01 00 98 00 99 01 00 0E
   00 2D 01 00 60 00 61 01 00 5A 00 5B 01
  ScalaSig: length = 0x3 (unknown attribute)
   05 02 00
