Classfile /Users/mw/Projects/slang-braindump/.jar/jar8/assemble/slang-braindump/assemble/content/coursier/util/shaded/org/jsoup/nodes/Attributes$Dataset.class
  Last modified May 29, 2022; size 2450 bytes
  SHA-256 checksum 6b94f3d15a066a15ad16783f5fcfffa5131a5787fb1c92b802f1fca201d854fb
  Compiled from "Attributes.java"
class coursier.util.shaded.org.jsoup.nodes.Attributes$Dataset extends java.util.AbstractMap<java.lang.String, java.lang.String>
  minor version: 0
  major version: 51
  flags: (0x0020) ACC_SUPER
  this_class: #2                          // coursier/util/shaded/org/jsoup/nodes/Attributes$Dataset
  super_class: #5                         // java/util/AbstractMap
  interfaces: 0, fields: 1, methods: 6, attributes: 3
Constant pool:
   #1 = Utf8               coursier/util/shaded/org/jsoup/nodes/Attributes$Dataset
   #2 = Class              #1             // coursier/util/shaded/org/jsoup/nodes/Attributes$Dataset
   #3 = Utf8               Ljava/util/AbstractMap<Ljava/lang/String;Ljava/lang/String;>;
   #4 = Utf8               java/util/AbstractMap
   #5 = Class              #4             // java/util/AbstractMap
   #6 = Utf8               Attributes.java
   #7 = Utf8               coursier/util/shaded/org/jsoup/nodes/Attributes
   #8 = Class              #7             // coursier/util/shaded/org/jsoup/nodes/Attributes
   #9 = Utf8               Dataset
  #10 = Utf8               coursier/util/shaded/org/jsoup/nodes/Attributes$Dataset$EntrySet
  #11 = Class              #10            // coursier/util/shaded/org/jsoup/nodes/Attributes$Dataset$EntrySet
  #12 = Utf8               EntrySet
  #13 = Utf8               coursier/util/shaded/org/jsoup/nodes/Attributes$1
  #14 = Class              #13            // coursier/util/shaded/org/jsoup/nodes/Attributes$1
  #15 = Utf8               coursier/util/shaded/org/jsoup/nodes/Attributes$Dataset$DatasetIterator
  #16 = Class              #15            // coursier/util/shaded/org/jsoup/nodes/Attributes$Dataset$DatasetIterator
  #17 = Utf8               DatasetIterator
  #18 = Utf8               java/util/Map$Entry
  #19 = Class              #18            // java/util/Map$Entry
  #20 = Utf8               java/util/Map
  #21 = Class              #20            // java/util/Map
  #22 = Utf8               Entry
  #23 = Utf8               attributes
  #24 = Utf8               Lcoursier/util/shaded/org/jsoup/nodes/Attributes;
  #25 = Utf8               <init>
  #26 = Utf8               (Lcoursier/util/shaded/org/jsoup/nodes/Attributes;)V
  #27 = Utf8               ()V
  #28 = NameAndType        #25:#27        // "<init>":()V
  #29 = Methodref          #5.#28         // java/util/AbstractMap."<init>":()V
  #30 = NameAndType        #23:#24        // attributes:Lcoursier/util/shaded/org/jsoup/nodes/Attributes;
  #31 = Fieldref           #2.#30         // coursier/util/shaded/org/jsoup/nodes/Attributes$Dataset.attributes:Lcoursier/util/shaded/org/jsoup/nodes/Attributes;
  #32 = Utf8               this
  #33 = Utf8               Lcoursier/util/shaded/org/jsoup/nodes/Attributes$Dataset;
  #34 = Utf8               entrySet
  #35 = Utf8               ()Ljava/util/Set;
  #36 = Utf8               ()Ljava/util/Set<Ljava/util/Map$Entry<Ljava/lang/String;Ljava/lang/String;>;>;
  #37 = Utf8               (Lcoursier/util/shaded/org/jsoup/nodes/Attributes$Dataset;Lcoursier/util/shaded/org/jsoup/nodes/Attributes$1;)V
  #38 = NameAndType        #25:#37        // "<init>":(Lcoursier/util/shaded/org/jsoup/nodes/Attributes$Dataset;Lcoursier/util/shaded/org/jsoup/nodes/Attributes$1;)V
  #39 = Methodref          #11.#38        // coursier/util/shaded/org/jsoup/nodes/Attributes$Dataset$EntrySet."<init>":(Lcoursier/util/shaded/org/jsoup/nodes/Attributes$Dataset;Lcoursier/util/shaded/org/jsoup/nodes/Attributes$1;)V
  #40 = Utf8               put
  #41 = Utf8               (Ljava/lang/String;Ljava/lang/String;)Ljava/lang/String;
  #42 = Utf8               access$500
  #43 = Utf8               (Ljava/lang/String;)Ljava/lang/String;
  #44 = NameAndType        #42:#43        // access$500:(Ljava/lang/String;)Ljava/lang/String;
  #45 = Methodref          #8.#44         // coursier/util/shaded/org/jsoup/nodes/Attributes.access$500:(Ljava/lang/String;)Ljava/lang/String;
  #46 = Utf8               hasKey
  #47 = Utf8               (Ljava/lang/String;)Z
  #48 = NameAndType        #46:#47        // hasKey:(Ljava/lang/String;)Z
  #49 = Methodref          #8.#48         // coursier/util/shaded/org/jsoup/nodes/Attributes.hasKey:(Ljava/lang/String;)Z
  #50 = Utf8               get
  #51 = NameAndType        #50:#43        // get:(Ljava/lang/String;)Ljava/lang/String;
  #52 = Methodref          #8.#51         // coursier/util/shaded/org/jsoup/nodes/Attributes.get:(Ljava/lang/String;)Ljava/lang/String;
  #53 = Utf8               java/lang/String
  #54 = Class              #53            // java/lang/String
  #55 = Utf8               (Ljava/lang/String;Ljava/lang/String;)Lcoursier/util/shaded/org/jsoup/nodes/Attributes;
  #56 = NameAndType        #40:#55        // put:(Ljava/lang/String;Ljava/lang/String;)Lcoursier/util/shaded/org/jsoup/nodes/Attributes;
  #57 = Methodref          #8.#56         // coursier/util/shaded/org/jsoup/nodes/Attributes.put:(Ljava/lang/String;Ljava/lang/String;)Lcoursier/util/shaded/org/jsoup/nodes/Attributes;
  #58 = Utf8               key
  #59 = Utf8               Ljava/lang/String;
  #60 = Utf8               value
  #61 = Utf8               dataKey
  #62 = Utf8               oldValue
  #63 = Utf8               (Ljava/lang/Object;Ljava/lang/Object;)Ljava/lang/Object;
  #64 = NameAndType        #40:#41        // put:(Ljava/lang/String;Ljava/lang/String;)Ljava/lang/String;
  #65 = Methodref          #2.#64         // coursier/util/shaded/org/jsoup/nodes/Attributes$Dataset.put:(Ljava/lang/String;Ljava/lang/String;)Ljava/lang/String;
  #66 = Utf8               (Lcoursier/util/shaded/org/jsoup/nodes/Attributes;Lcoursier/util/shaded/org/jsoup/nodes/Attributes$1;)V
  #67 = NameAndType        #25:#26        // "<init>":(Lcoursier/util/shaded/org/jsoup/nodes/Attributes;)V
  #68 = Methodref          #2.#67         // coursier/util/shaded/org/jsoup/nodes/Attributes$Dataset."<init>":(Lcoursier/util/shaded/org/jsoup/nodes/Attributes;)V
  #69 = Utf8               x0
  #70 = Utf8               x1
  #71 = Utf8               Lcoursier/util/shaded/org/jsoup/nodes/Attributes$1;
  #72 = Utf8               access$700
  #73 = Utf8               (Lcoursier/util/shaded/org/jsoup/nodes/Attributes$Dataset;)Lcoursier/util/shaded/org/jsoup/nodes/Attributes;
  #74 = Utf8               Code
  #75 = Utf8               LineNumberTable
  #76 = Utf8               LocalVariableTable
  #77 = Utf8               Signature
  #78 = Utf8               StackMapTable
  #79 = Utf8               InnerClasses
  #80 = Utf8               SourceFile
{
  private final coursier.util.shaded.org.jsoup.nodes.Attributes attributes;
    descriptor: Lcoursier/util/shaded/org/jsoup/nodes/Attributes;
    flags: (0x0012) ACC_PRIVATE, ACC_FINAL

  private coursier.util.shaded.org.jsoup.nodes.Attributes$Dataset(coursier.util.shaded.org.jsoup.nodes.Attributes);
    descriptor: (Lcoursier/util/shaded/org/jsoup/nodes/Attributes;)V
    flags: (0x0002) ACC_PRIVATE
    Code:
      stack=2, locals=2, args_size=2
         0: aload_0
         1: invokespecial #29                 // Method java/util/AbstractMap."<init>":()V
         4: aload_0
         5: aload_1
         6: putfield      #31                 // Field attributes:Lcoursier/util/shaded/org/jsoup/nodes/Attributes;
         9: return
      LineNumberTable:
        line 462: 0
        line 463: 4
        line 464: 9
      LocalVariableTable:
        Start  Length  Slot  Name   Signature
            0      10     0  this   Lcoursier/util/shaded/org/jsoup/nodes/Attributes$Dataset;
            0      10     1 attributes   Lcoursier/util/shaded/org/jsoup/nodes/Attributes;

  public java.util.Set<java.util.Map$Entry<java.lang.String, java.lang.String>> entrySet();
    descriptor: ()Ljava/util/Set;
    flags: (0x0001) ACC_PUBLIC
    Code:
      stack=4, locals=1, args_size=1
         0: new           #11                 // class coursier/util/shaded/org/jsoup/nodes/Attributes$Dataset$EntrySet
         3: dup
         4: aload_0
         5: aconst_null
         6: invokespecial #39                 // Method coursier/util/shaded/org/jsoup/nodes/Attributes$Dataset$EntrySet."<init>":(Lcoursier/util/shaded/org/jsoup/nodes/Attributes$Dataset;Lcoursier/util/shaded/org/jsoup/nodes/Attributes$1;)V
         9: areturn
      LineNumberTable:
        line 468: 0
      LocalVariableTable:
        Start  Length  Slot  Name   Signature
            0      10     0  this   Lcoursier/util/shaded/org/jsoup/nodes/Attributes$Dataset;
    Signature: #36                          // ()Ljava/util/Set<Ljava/util/Map$Entry<Ljava/lang/String;Ljava/lang/String;>;>;

  public java.lang.String put(java.lang.String, java.lang.String);
    descriptor: (Ljava/lang/String;Ljava/lang/String;)Ljava/lang/String;
    flags: (0x0001) ACC_PUBLIC
    Code:
      stack=3, locals=5, args_size=3
         0: aload_1
         1: invokestatic  #45                 // Method coursier/util/shaded/org/jsoup/nodes/Attributes.access$500:(Ljava/lang/String;)Ljava/lang/String;
         4: astore_3
         5: aload_0
         6: getfield      #31                 // Field attributes:Lcoursier/util/shaded/org/jsoup/nodes/Attributes;
         9: aload_3
        10: invokevirtual #49                 // Method coursier/util/shaded/org/jsoup/nodes/Attributes.hasKey:(Ljava/lang/String;)Z
        13: ifeq          27
        16: aload_0
        17: getfield      #31                 // Field attributes:Lcoursier/util/shaded/org/jsoup/nodes/Attributes;
        20: aload_3
        21: invokevirtual #52                 // Method coursier/util/shaded/org/jsoup/nodes/Attributes.get:(Ljava/lang/String;)Ljava/lang/String;
        24: goto          28
        27: aconst_null
        28: astore        4
        30: aload_0
        31: getfield      #31                 // Field attributes:Lcoursier/util/shaded/org/jsoup/nodes/Attributes;
        34: aload_3
        35: aload_2
        36: invokevirtual #57                 // Method coursier/util/shaded/org/jsoup/nodes/Attributes.put:(Ljava/lang/String;Ljava/lang/String;)Lcoursier/util/shaded/org/jsoup/nodes/Attributes;
        39: pop
        40: aload         4
        42: areturn
      StackMapTable: number_of_entries = 2
        frame_type = 252 /* append */
          offset_delta = 27
          locals = [ class java/lang/String ]
        frame_type = 64 /* same_locals_1_stack_item */
          stack = [ class java/lang/String ]
      LineNumberTable:
        line 473: 0
        line 474: 5
        line 475: 30
        line 476: 40
      LocalVariableTable:
        Start  Length  Slot  Name   Signature
            0      43     0  this   Lcoursier/util/shaded/org/jsoup/nodes/Attributes$Dataset;
            0      43     1   key   Ljava/lang/String;
            0      43     2 value   Ljava/lang/String;
            5      38     3 dataKey   Ljava/lang/String;
           30      13     4 oldValue   Ljava/lang/String;

  public java.lang.Object put(java.lang.Object, java.lang.Object);
    descriptor: (Ljava/lang/Object;Ljava/lang/Object;)Ljava/lang/Object;
    flags: (0x1041) ACC_PUBLIC, ACC_BRIDGE, ACC_SYNTHETIC
    Code:
      stack=3, locals=3, args_size=3
         0: aload_0
         1: aload_1
         2: checkcast     #54                 // class java/lang/String
         5: aload_2
         6: checkcast     #54                 // class java/lang/String
         9: invokevirtual #65                 // Method put:(Ljava/lang/String;Ljava/lang/String;)Ljava/lang/String;
        12: areturn
      LineNumberTable:
        line 459: 0
      LocalVariableTable:
        Start  Length  Slot  Name   Signature
            0      13     0  this   Lcoursier/util/shaded/org/jsoup/nodes/Attributes$Dataset;

  coursier.util.shaded.org.jsoup.nodes.Attributes$Dataset(coursier.util.shaded.org.jsoup.nodes.Attributes, coursier.util.shaded.org.jsoup.nodes.Attributes$1);
    descriptor: (Lcoursier/util/shaded/org/jsoup/nodes/Attributes;Lcoursier/util/shaded/org/jsoup/nodes/Attributes$1;)V
    flags: (0x1000) ACC_SYNTHETIC
    Code:
      stack=2, locals=3, args_size=3
         0: aload_0
         1: aload_1
         2: invokespecial #68                 // Method "<init>":(Lcoursier/util/shaded/org/jsoup/nodes/Attributes;)V
         5: return
      LineNumberTable:
        line 459: 0
      LocalVariableTable:
        Start  Length  Slot  Name   Signature
            0       6     0  this   Lcoursier/util/shaded/org/jsoup/nodes/Attributes$Dataset;
            0       6     1    x0   Lcoursier/util/shaded/org/jsoup/nodes/Attributes;
            0       6     2    x1   Lcoursier/util/shaded/org/jsoup/nodes/Attributes$1;

  static coursier.util.shaded.org.jsoup.nodes.Attributes access$700(coursier.util.shaded.org.jsoup.nodes.Attributes$Dataset);
    descriptor: (Lcoursier/util/shaded/org/jsoup/nodes/Attributes$Dataset;)Lcoursier/util/shaded/org/jsoup/nodes/Attributes;
    flags: (0x1008) ACC_STATIC, ACC_SYNTHETIC
    Code:
      stack=1, locals=1, args_size=1
         0: aload_0
         1: getfield      #31                 // Field attributes:Lcoursier/util/shaded/org/jsoup/nodes/Attributes;
         4: areturn
      LineNumberTable:
        line 459: 0
      LocalVariableTable:
        Start  Length  Slot  Name   Signature
            0       5     0    x0   Lcoursier/util/shaded/org/jsoup/nodes/Attributes$Dataset;
}
InnerClasses:
  private static #9= #2 of #8;            // Dataset=class coursier/util/shaded/org/jsoup/nodes/Attributes$Dataset of class coursier/util/shaded/org/jsoup/nodes/Attributes
  private #12= #11 of #2;                 // EntrySet=class coursier/util/shaded/org/jsoup/nodes/Attributes$Dataset$EntrySet of class coursier/util/shaded/org/jsoup/nodes/Attributes$Dataset
  #14;                                    // class coursier/util/shaded/org/jsoup/nodes/Attributes$1
  private #17= #16 of #2;                 // DatasetIterator=class coursier/util/shaded/org/jsoup/nodes/Attributes$Dataset$DatasetIterator of class coursier/util/shaded/org/jsoup/nodes/Attributes$Dataset
  public static #22= #19 of #21;          // Entry=class java/util/Map$Entry of class java/util/Map
Signature: #3                           // Ljava/util/AbstractMap<Ljava/lang/String;Ljava/lang/String;>;
SourceFile: "Attributes.java"
