Classfile /Users/mw/Projects/slang-braindump/.jar/jar8/assemble/slang-braindump/assemble/content/coursier/util/shaded/org/jsoup/nodes/Attributes$Dataset$DatasetIterator.class
  Last modified May 29, 2022; size 2538 bytes
  SHA-256 checksum b4e81cda5105d6bbb71dcebbd6df5c5a1e95946933b22f9ec2679109f1fd0362
  Compiled from "Attributes.java"
class coursier.util.shaded.org.jsoup.nodes.Attributes$Dataset$DatasetIterator extends java.lang.Object implements java.util.Iterator<java.util.Map$Entry<java.lang.String, java.lang.String>>
  minor version: 0
  major version: 51
  flags: (0x0020) ACC_SUPER
  this_class: #2                          // coursier/util/shaded/org/jsoup/nodes/Attributes$Dataset$DatasetIterator
  super_class: #5                         // java/lang/Object
  interfaces: 1, fields: 3, methods: 6, attributes: 3
Constant pool:
    #1 = Utf8               coursier/util/shaded/org/jsoup/nodes/Attributes$Dataset$DatasetIterator
    #2 = Class              #1            // coursier/util/shaded/org/jsoup/nodes/Attributes$Dataset$DatasetIterator
    #3 = Utf8               Ljava/lang/Object;Ljava/util/Iterator<Ljava/util/Map$Entry<Ljava/lang/String;Ljava/lang/String;>;>;
    #4 = Utf8               java/lang/Object
    #5 = Class              #4            // java/lang/Object
    #6 = Utf8               java/util/Iterator
    #7 = Class              #6            // java/util/Iterator
    #8 = Utf8               Attributes.java
    #9 = Utf8               coursier/util/shaded/org/jsoup/nodes/Attributes$Dataset
   #10 = Class              #9            // coursier/util/shaded/org/jsoup/nodes/Attributes$Dataset
   #11 = Utf8               coursier/util/shaded/org/jsoup/nodes/Attributes
   #12 = Class              #11           // coursier/util/shaded/org/jsoup/nodes/Attributes
   #13 = Utf8               Dataset
   #14 = Utf8               DatasetIterator
   #15 = Utf8               java/util/Map$Entry
   #16 = Class              #15           // java/util/Map$Entry
   #17 = Utf8               java/util/Map
   #18 = Class              #17           // java/util/Map
   #19 = Utf8               Entry
   #20 = Utf8               coursier/util/shaded/org/jsoup/nodes/Attributes$1
   #21 = Class              #20           // coursier/util/shaded/org/jsoup/nodes/Attributes$1
   #22 = Utf8               attrIter
   #23 = Utf8               Ljava/util/Iterator;
   #24 = Utf8               Ljava/util/Iterator<Lcoursier/util/shaded/org/jsoup/nodes/Attribute;>;
   #25 = Utf8               attr
   #26 = Utf8               Lcoursier/util/shaded/org/jsoup/nodes/Attribute;
   #27 = Utf8               this$0
   #28 = Utf8               Lcoursier/util/shaded/org/jsoup/nodes/Attributes$Dataset;
   #29 = Utf8               <init>
   #30 = Utf8               (Lcoursier/util/shaded/org/jsoup/nodes/Attributes$Dataset;)V
   #31 = NameAndType        #27:#28       // this$0:Lcoursier/util/shaded/org/jsoup/nodes/Attributes$Dataset;
   #32 = Fieldref           #2.#31        // coursier/util/shaded/org/jsoup/nodes/Attributes$Dataset$DatasetIterator.this$0:Lcoursier/util/shaded/org/jsoup/nodes/Attributes$Dataset;
   #33 = Utf8               ()V
   #34 = NameAndType        #29:#33       // "<init>":()V
   #35 = Methodref          #5.#34        // java/lang/Object."<init>":()V
   #36 = Utf8               access$700
   #37 = Utf8               (Lcoursier/util/shaded/org/jsoup/nodes/Attributes$Dataset;)Lcoursier/util/shaded/org/jsoup/nodes/Attributes;
   #38 = NameAndType        #36:#37       // access$700:(Lcoursier/util/shaded/org/jsoup/nodes/Attributes$Dataset;)Lcoursier/util/shaded/org/jsoup/nodes/Attributes;
   #39 = Methodref          #10.#38       // coursier/util/shaded/org/jsoup/nodes/Attributes$Dataset.access$700:(Lcoursier/util/shaded/org/jsoup/nodes/Attributes$Dataset;)Lcoursier/util/shaded/org/jsoup/nodes/Attributes;
   #40 = Utf8               iterator
   #41 = Utf8               ()Ljava/util/Iterator;
   #42 = NameAndType        #40:#41       // iterator:()Ljava/util/Iterator;
   #43 = Methodref          #12.#42       // coursier/util/shaded/org/jsoup/nodes/Attributes.iterator:()Ljava/util/Iterator;
   #44 = NameAndType        #22:#23       // attrIter:Ljava/util/Iterator;
   #45 = Fieldref           #2.#44        // coursier/util/shaded/org/jsoup/nodes/Attributes$Dataset$DatasetIterator.attrIter:Ljava/util/Iterator;
   #46 = Utf8               this
   #47 = Utf8               Lcoursier/util/shaded/org/jsoup/nodes/Attributes$Dataset$DatasetIterator;
   #48 = Utf8               hasNext
   #49 = Utf8               ()Z
   #50 = NameAndType        #48:#49       // hasNext:()Z
   #51 = InterfaceMethodref #7.#50        // java/util/Iterator.hasNext:()Z
   #52 = Utf8               next
   #53 = Utf8               ()Ljava/lang/Object;
   #54 = NameAndType        #52:#53       // next:()Ljava/lang/Object;
   #55 = InterfaceMethodref #7.#54        // java/util/Iterator.next:()Ljava/lang/Object;
   #56 = Utf8               coursier/util/shaded/org/jsoup/nodes/Attribute
   #57 = Class              #56           // coursier/util/shaded/org/jsoup/nodes/Attribute
   #58 = NameAndType        #25:#26       // attr:Lcoursier/util/shaded/org/jsoup/nodes/Attribute;
   #59 = Fieldref           #2.#58        // coursier/util/shaded/org/jsoup/nodes/Attributes$Dataset$DatasetIterator.attr:Lcoursier/util/shaded/org/jsoup/nodes/Attribute;
   #60 = Utf8               isDataAttribute
   #61 = NameAndType        #60:#49       // isDataAttribute:()Z
   #62 = Methodref          #57.#61       // coursier/util/shaded/org/jsoup/nodes/Attribute.isDataAttribute:()Z
   #63 = Utf8               ()Ljava/util/Map$Entry;
   #64 = Utf8               ()Ljava/util/Map$Entry<Ljava/lang/String;Ljava/lang/String;>;
   #65 = Utf8               getKey
   #66 = Utf8               ()Ljava/lang/String;
   #67 = NameAndType        #65:#66       // getKey:()Ljava/lang/String;
   #68 = Methodref          #57.#67       // coursier/util/shaded/org/jsoup/nodes/Attribute.getKey:()Ljava/lang/String;
   #69 = Utf8               data-
   #70 = String             #69           // data-
   #71 = Utf8               java/lang/String
   #72 = Class              #71           // java/lang/String
   #73 = Utf8               length
   #74 = Utf8               ()I
   #75 = NameAndType        #73:#74       // length:()I
   #76 = Methodref          #72.#75       // java/lang/String.length:()I
   #77 = Utf8               substring
   #78 = Utf8               (I)Ljava/lang/String;
   #79 = NameAndType        #77:#78       // substring:(I)Ljava/lang/String;
   #80 = Methodref          #72.#79       // java/lang/String.substring:(I)Ljava/lang/String;
   #81 = Utf8               getValue
   #82 = NameAndType        #81:#66       // getValue:()Ljava/lang/String;
   #83 = Methodref          #57.#82       // coursier/util/shaded/org/jsoup/nodes/Attribute.getValue:()Ljava/lang/String;
   #84 = Utf8               (Ljava/lang/String;Ljava/lang/String;)V
   #85 = NameAndType        #29:#84       // "<init>":(Ljava/lang/String;Ljava/lang/String;)V
   #86 = Methodref          #57.#85       // coursier/util/shaded/org/jsoup/nodes/Attribute."<init>":(Ljava/lang/String;Ljava/lang/String;)V
   #87 = Utf8               remove
   #88 = Utf8               (Ljava/lang/String;)V
   #89 = NameAndType        #87:#88       // remove:(Ljava/lang/String;)V
   #90 = Methodref          #12.#89       // coursier/util/shaded/org/jsoup/nodes/Attributes.remove:(Ljava/lang/String;)V
   #91 = NameAndType        #52:#63       // next:()Ljava/util/Map$Entry;
   #92 = Methodref          #2.#91        // coursier/util/shaded/org/jsoup/nodes/Attributes$Dataset$DatasetIterator.next:()Ljava/util/Map$Entry;
   #93 = Utf8               (Lcoursier/util/shaded/org/jsoup/nodes/Attributes$Dataset;Lcoursier/util/shaded/org/jsoup/nodes/Attributes$1;)V
   #94 = NameAndType        #29:#30       // "<init>":(Lcoursier/util/shaded/org/jsoup/nodes/Attributes$Dataset;)V
   #95 = Methodref          #2.#94        // coursier/util/shaded/org/jsoup/nodes/Attributes$Dataset$DatasetIterator."<init>":(Lcoursier/util/shaded/org/jsoup/nodes/Attributes$Dataset;)V
   #96 = Utf8               x0
   #97 = Utf8               x1
   #98 = Utf8               Lcoursier/util/shaded/org/jsoup/nodes/Attributes$1;
   #99 = Utf8               Signature
  #100 = Utf8               Code
  #101 = Utf8               LineNumberTable
  #102 = Utf8               LocalVariableTable
  #103 = Utf8               StackMapTable
  #104 = Utf8               InnerClasses
  #105 = Utf8               SourceFile
{
  private java.util.Iterator<coursier.util.shaded.org.jsoup.nodes.Attribute> attrIter;
    descriptor: Ljava/util/Iterator;
    flags: (0x0002) ACC_PRIVATE
    Signature: #24                          // Ljava/util/Iterator<Lcoursier/util/shaded/org/jsoup/nodes/Attribute;>;

  private coursier.util.shaded.org.jsoup.nodes.Attribute attr;
    descriptor: Lcoursier/util/shaded/org/jsoup/nodes/Attribute;
    flags: (0x0002) ACC_PRIVATE

  final coursier.util.shaded.org.jsoup.nodes.Attributes$Dataset this$0;
    descriptor: Lcoursier/util/shaded/org/jsoup/nodes/Attributes$Dataset;
    flags: (0x1010) ACC_FINAL, ACC_SYNTHETIC

  private coursier.util.shaded.org.jsoup.nodes.Attributes$Dataset$DatasetIterator(coursier.util.shaded.org.jsoup.nodes.Attributes$Dataset);
    descriptor: (Lcoursier/util/shaded/org/jsoup/nodes/Attributes$Dataset;)V
    flags: (0x0002) ACC_PRIVATE
    Code:
      stack=2, locals=2, args_size=2
         0: aload_0
         1: aload_1
         2: putfield      #32                 // Field this$0:Lcoursier/util/shaded/org/jsoup/nodes/Attributes$Dataset;
         5: aload_0
         6: invokespecial #35                 // Method java/lang/Object."<init>":()V
         9: aload_0
        10: aload_0
        11: getfield      #32                 // Field this$0:Lcoursier/util/shaded/org/jsoup/nodes/Attributes$Dataset;
        14: invokestatic  #39                 // Method coursier/util/shaded/org/jsoup/nodes/Attributes$Dataset.access$700:(Lcoursier/util/shaded/org/jsoup/nodes/Attributes$Dataset;)Lcoursier/util/shaded/org/jsoup/nodes/Attributes;
        17: invokevirtual #43                 // Method coursier/util/shaded/org/jsoup/nodes/Attributes.iterator:()Ljava/util/Iterator;
        20: putfield      #45                 // Field attrIter:Ljava/util/Iterator;
        23: return
      LineNumberTable:
        line 496: 0
        line 497: 9
      LocalVariableTable:
        Start  Length  Slot  Name   Signature
            0      24     0  this   Lcoursier/util/shaded/org/jsoup/nodes/Attributes$Dataset$DatasetIterator;

  public boolean hasNext();
    descriptor: ()Z
    flags: (0x0001) ACC_PUBLIC
    Code:
      stack=2, locals=1, args_size=1
         0: aload_0
         1: getfield      #45                 // Field attrIter:Ljava/util/Iterator;
         4: invokeinterface #51,  1           // InterfaceMethod java/util/Iterator.hasNext:()Z
         9: ifeq          40
        12: aload_0
        13: aload_0
        14: getfield      #45                 // Field attrIter:Ljava/util/Iterator;
        17: invokeinterface #55,  1           // InterfaceMethod java/util/Iterator.next:()Ljava/lang/Object;
        22: checkcast     #57                 // class coursier/util/shaded/org/jsoup/nodes/Attribute
        25: putfield      #59                 // Field attr:Lcoursier/util/shaded/org/jsoup/nodes/Attribute;
        28: aload_0
        29: getfield      #59                 // Field attr:Lcoursier/util/shaded/org/jsoup/nodes/Attribute;
        32: invokevirtual #62                 // Method coursier/util/shaded/org/jsoup/nodes/Attribute.isDataAttribute:()Z
        35: ifeq          0
        38: iconst_1
        39: ireturn
        40: iconst_0
        41: ireturn
      StackMapTable: number_of_entries = 2
        frame_type = 0 /* same */
        frame_type = 39 /* same */
      LineNumberTable:
        line 500: 0
        line 501: 12
        line 502: 28
        line 504: 40
      LocalVariableTable:
        Start  Length  Slot  Name   Signature
            0      42     0  this   Lcoursier/util/shaded/org/jsoup/nodes/Attributes$Dataset$DatasetIterator;

  public java.util.Map$Entry<java.lang.String, java.lang.String> next();
    descriptor: ()Ljava/util/Map$Entry;
    flags: (0x0001) ACC_PUBLIC
    Code:
      stack=4, locals=1, args_size=1
         0: new           #57                 // class coursier/util/shaded/org/jsoup/nodes/Attribute
         3: dup
         4: aload_0
         5: getfield      #59                 // Field attr:Lcoursier/util/shaded/org/jsoup/nodes/Attribute;
         8: invokevirtual #68                 // Method coursier/util/shaded/org/jsoup/nodes/Attribute.getKey:()Ljava/lang/String;
        11: ldc           #70                 // String data-
        13: invokevirtual #76                 // Method java/lang/String.length:()I
        16: invokevirtual #80                 // Method java/lang/String.substring:(I)Ljava/lang/String;
        19: aload_0
        20: getfield      #59                 // Field attr:Lcoursier/util/shaded/org/jsoup/nodes/Attribute;
        23: invokevirtual #83                 // Method coursier/util/shaded/org/jsoup/nodes/Attribute.getValue:()Ljava/lang/String;
        26: invokespecial #86                 // Method coursier/util/shaded/org/jsoup/nodes/Attribute."<init>":(Ljava/lang/String;Ljava/lang/String;)V
        29: areturn
      LineNumberTable:
        line 508: 0
      LocalVariableTable:
        Start  Length  Slot  Name   Signature
            0      30     0  this   Lcoursier/util/shaded/org/jsoup/nodes/Attributes$Dataset$DatasetIterator;
    Signature: #64                          // ()Ljava/util/Map$Entry<Ljava/lang/String;Ljava/lang/String;>;

  public void remove();
    descriptor: ()V
    flags: (0x0001) ACC_PUBLIC
    Code:
      stack=2, locals=1, args_size=1
         0: aload_0
         1: getfield      #32                 // Field this$0:Lcoursier/util/shaded/org/jsoup/nodes/Attributes$Dataset;
         4: invokestatic  #39                 // Method coursier/util/shaded/org/jsoup/nodes/Attributes$Dataset.access$700:(Lcoursier/util/shaded/org/jsoup/nodes/Attributes$Dataset;)Lcoursier/util/shaded/org/jsoup/nodes/Attributes;
         7: aload_0
         8: getfield      #59                 // Field attr:Lcoursier/util/shaded/org/jsoup/nodes/Attribute;
        11: invokevirtual #68                 // Method coursier/util/shaded/org/jsoup/nodes/Attribute.getKey:()Ljava/lang/String;
        14: invokevirtual #90                 // Method coursier/util/shaded/org/jsoup/nodes/Attributes.remove:(Ljava/lang/String;)V
        17: return
      LineNumberTable:
        line 512: 0
        line 513: 17
      LocalVariableTable:
        Start  Length  Slot  Name   Signature
            0      18     0  this   Lcoursier/util/shaded/org/jsoup/nodes/Attributes$Dataset$DatasetIterator;

  public java.lang.Object next();
    descriptor: ()Ljava/lang/Object;
    flags: (0x1041) ACC_PUBLIC, ACC_BRIDGE, ACC_SYNTHETIC
    Code:
      stack=1, locals=1, args_size=1
         0: aload_0
         1: invokevirtual #92                 // Method next:()Ljava/util/Map$Entry;
         4: areturn
      LineNumberTable:
        line 496: 0
      LocalVariableTable:
        Start  Length  Slot  Name   Signature
            0       5     0  this   Lcoursier/util/shaded/org/jsoup/nodes/Attributes$Dataset$DatasetIterator;

  coursier.util.shaded.org.jsoup.nodes.Attributes$Dataset$DatasetIterator(coursier.util.shaded.org.jsoup.nodes.Attributes$Dataset, coursier.util.shaded.org.jsoup.nodes.Attributes$1);
    descriptor: (Lcoursier/util/shaded/org/jsoup/nodes/Attributes$Dataset;Lcoursier/util/shaded/org/jsoup/nodes/Attributes$1;)V
    flags: (0x1000) ACC_SYNTHETIC
    Code:
      stack=2, locals=3, args_size=3
         0: aload_0
         1: aload_1
         2: invokespecial #95                 // Method "<init>":(Lcoursier/util/shaded/org/jsoup/nodes/Attributes$Dataset;)V
         5: return
      LineNumberTable:
        line 496: 0
      LocalVariableTable:
        Start  Length  Slot  Name   Signature
            0       6     0  this   Lcoursier/util/shaded/org/jsoup/nodes/Attributes$Dataset$DatasetIterator;
            0       6     1    x0   Lcoursier/util/shaded/org/jsoup/nodes/Attributes$Dataset;
            0       6     2    x1   Lcoursier/util/shaded/org/jsoup/nodes/Attributes$1;
}
InnerClasses:
  private static #13= #10 of #12;         // Dataset=class coursier/util/shaded/org/jsoup/nodes/Attributes$Dataset of class coursier/util/shaded/org/jsoup/nodes/Attributes
  private #14= #2 of #10;                 // DatasetIterator=class coursier/util/shaded/org/jsoup/nodes/Attributes$Dataset$DatasetIterator of class coursier/util/shaded/org/jsoup/nodes/Attributes$Dataset
  public static #19= #16 of #18;          // Entry=class java/util/Map$Entry of class java/util/Map
  #21;                                    // class coursier/util/shaded/org/jsoup/nodes/Attributes$1
Signature: #3                           // Ljava/lang/Object;Ljava/util/Iterator<Ljava/util/Map$Entry<Ljava/lang/String;Ljava/lang/String;>;>;
SourceFile: "Attributes.java"
