Classfile /Users/mw/Projects/slang-braindump/.jar/jar8/assemble/slang-braindump/assemble/content/coursier/util/shaded/org/jsoup/nodes/Document.class
  Last modified May 29, 2022; size 10015 bytes
  SHA-256 checksum 6e3e2053abb368bef9123bd7d333c296bd11a7d054e5f0565c7a2c812411b0cb
  Compiled from "Document.java"
public class coursier.util.shaded.org.jsoup.nodes.Document extends coursier.util.shaded.org.jsoup.nodes.Element
  minor version: 0
  major version: 51
  flags: (0x0021) ACC_PUBLIC, ACC_SUPER
  this_class: #2                          // coursier/util/shaded/org/jsoup/nodes/Document
  super_class: #4                         // coursier/util/shaded/org/jsoup/nodes/Element
  interfaces: 0, fields: 5, methods: 31, attributes: 2
Constant pool:
    #1 = Utf8               coursier/util/shaded/org/jsoup/nodes/Document
    #2 = Class              #1            // coursier/util/shaded/org/jsoup/nodes/Document
    #3 = Utf8               coursier/util/shaded/org/jsoup/nodes/Element
    #4 = Class              #3            // coursier/util/shaded/org/jsoup/nodes/Element
    #5 = Utf8               Document.java
    #6 = Utf8               coursier/util/shaded/org/jsoup/nodes/Document$OutputSettings
    #7 = Class              #6            // coursier/util/shaded/org/jsoup/nodes/Document$OutputSettings
    #8 = Utf8               OutputSettings
    #9 = Utf8               coursier/util/shaded/org/jsoup/nodes/Document$QuirksMode
   #10 = Class              #9            // coursier/util/shaded/org/jsoup/nodes/Document$QuirksMode
   #11 = Utf8               QuirksMode
   #12 = Utf8               coursier/util/shaded/org/jsoup/nodes/Document$OutputSettings$Syntax
   #13 = Class              #12           // coursier/util/shaded/org/jsoup/nodes/Document$OutputSettings$Syntax
   #14 = Utf8               Syntax
   #15 = Utf8               outputSettings
   #16 = Utf8               Lcoursier/util/shaded/org/jsoup/nodes/Document$OutputSettings;
   #17 = Utf8               parser
   #18 = Utf8               Lcoursier/util/shaded/org/jsoup/parser/Parser;
   #19 = Utf8               quirksMode
   #20 = Utf8               Lcoursier/util/shaded/org/jsoup/nodes/Document$QuirksMode;
   #21 = Utf8               location
   #22 = Utf8               Ljava/lang/String;
   #23 = Utf8               updateMetaCharset
   #24 = Utf8               Z
   #25 = Utf8               <init>
   #26 = Utf8               (Ljava/lang/String;)V
   #27 = Utf8               #root
   #28 = String             #27           // #root
   #29 = Utf8               coursier/util/shaded/org/jsoup/parser/ParseSettings
   #30 = Class              #29           // coursier/util/shaded/org/jsoup/parser/ParseSettings
   #31 = Utf8               htmlDefault
   #32 = Utf8               Lcoursier/util/shaded/org/jsoup/parser/ParseSettings;
   #33 = NameAndType        #31:#32       // htmlDefault:Lcoursier/util/shaded/org/jsoup/parser/ParseSettings;
   #34 = Fieldref           #30.#33       // coursier/util/shaded/org/jsoup/parser/ParseSettings.htmlDefault:Lcoursier/util/shaded/org/jsoup/parser/ParseSettings;
   #35 = Utf8               coursier/util/shaded/org/jsoup/parser/Tag
   #36 = Class              #35           // coursier/util/shaded/org/jsoup/parser/Tag
   #37 = Utf8               valueOf
   #38 = Utf8               (Ljava/lang/String;Lcoursier/util/shaded/org/jsoup/parser/ParseSettings;)Lcoursier/util/shaded/org/jsoup/parser/Tag;
   #39 = NameAndType        #37:#38       // valueOf:(Ljava/lang/String;Lcoursier/util/shaded/org/jsoup/parser/ParseSettings;)Lcoursier/util/shaded/org/jsoup/parser/Tag;
   #40 = Methodref          #36.#39       // coursier/util/shaded/org/jsoup/parser/Tag.valueOf:(Ljava/lang/String;Lcoursier/util/shaded/org/jsoup/parser/ParseSettings;)Lcoursier/util/shaded/org/jsoup/parser/Tag;
   #41 = Utf8               (Lcoursier/util/shaded/org/jsoup/parser/Tag;Ljava/lang/String;)V
   #42 = NameAndType        #25:#41       // "<init>":(Lcoursier/util/shaded/org/jsoup/parser/Tag;Ljava/lang/String;)V
   #43 = Methodref          #4.#42        // coursier/util/shaded/org/jsoup/nodes/Element."<init>":(Lcoursier/util/shaded/org/jsoup/parser/Tag;Ljava/lang/String;)V
   #44 = Utf8               ()V
   #45 = NameAndType        #25:#44       // "<init>":()V
   #46 = Methodref          #7.#45        // coursier/util/shaded/org/jsoup/nodes/Document$OutputSettings."<init>":()V
   #47 = NameAndType        #15:#16       // outputSettings:Lcoursier/util/shaded/org/jsoup/nodes/Document$OutputSettings;
   #48 = Fieldref           #2.#47        // coursier/util/shaded/org/jsoup/nodes/Document.outputSettings:Lcoursier/util/shaded/org/jsoup/nodes/Document$OutputSettings;
   #49 = Utf8               noQuirks
   #50 = NameAndType        #49:#20       // noQuirks:Lcoursier/util/shaded/org/jsoup/nodes/Document$QuirksMode;
   #51 = Fieldref           #10.#50       // coursier/util/shaded/org/jsoup/nodes/Document$QuirksMode.noQuirks:Lcoursier/util/shaded/org/jsoup/nodes/Document$QuirksMode;
   #52 = NameAndType        #19:#20       // quirksMode:Lcoursier/util/shaded/org/jsoup/nodes/Document$QuirksMode;
   #53 = Fieldref           #2.#52        // coursier/util/shaded/org/jsoup/nodes/Document.quirksMode:Lcoursier/util/shaded/org/jsoup/nodes/Document$QuirksMode;
   #54 = NameAndType        #23:#24       // updateMetaCharset:Z
   #55 = Fieldref           #2.#54        // coursier/util/shaded/org/jsoup/nodes/Document.updateMetaCharset:Z
   #56 = NameAndType        #21:#22       // location:Ljava/lang/String;
   #57 = Fieldref           #2.#56        // coursier/util/shaded/org/jsoup/nodes/Document.location:Ljava/lang/String;
   #58 = Utf8               this
   #59 = Utf8               Lcoursier/util/shaded/org/jsoup/nodes/Document;
   #60 = Utf8               baseUri
   #61 = Utf8               createShell
   #62 = Utf8               (Ljava/lang/String;)Lcoursier/util/shaded/org/jsoup/nodes/Document;
   #63 = Utf8               coursier/util/shaded/org/jsoup/helper/Validate
   #64 = Class              #63           // coursier/util/shaded/org/jsoup/helper/Validate
   #65 = Utf8               notNull
   #66 = Utf8               (Ljava/lang/Object;)V
   #67 = NameAndType        #65:#66       // notNull:(Ljava/lang/Object;)V
   #68 = Methodref          #64.#67       // coursier/util/shaded/org/jsoup/helper/Validate.notNull:(Ljava/lang/Object;)V
   #69 = NameAndType        #25:#26       // "<init>":(Ljava/lang/String;)V
   #70 = Methodref          #2.#69        // coursier/util/shaded/org/jsoup/nodes/Document."<init>":(Ljava/lang/String;)V
   #71 = Utf8               ()Lcoursier/util/shaded/org/jsoup/parser/Parser;
   #72 = NameAndType        #17:#71       // parser:()Lcoursier/util/shaded/org/jsoup/parser/Parser;
   #73 = Methodref          #2.#72        // coursier/util/shaded/org/jsoup/nodes/Document.parser:()Lcoursier/util/shaded/org/jsoup/parser/Parser;
   #74 = NameAndType        #17:#18       // parser:Lcoursier/util/shaded/org/jsoup/parser/Parser;
   #75 = Fieldref           #2.#74        // coursier/util/shaded/org/jsoup/nodes/Document.parser:Lcoursier/util/shaded/org/jsoup/parser/Parser;
   #76 = Utf8               html
   #77 = String             #76           // html
   #78 = Utf8               appendElement
   #79 = Utf8               (Ljava/lang/String;)Lcoursier/util/shaded/org/jsoup/nodes/Element;
   #80 = NameAndType        #78:#79       // appendElement:(Ljava/lang/String;)Lcoursier/util/shaded/org/jsoup/nodes/Element;
   #81 = Methodref          #2.#80        // coursier/util/shaded/org/jsoup/nodes/Document.appendElement:(Ljava/lang/String;)Lcoursier/util/shaded/org/jsoup/nodes/Element;
   #82 = Utf8               head
   #83 = String             #82           // head
   #84 = Methodref          #4.#80        // coursier/util/shaded/org/jsoup/nodes/Element.appendElement:(Ljava/lang/String;)Lcoursier/util/shaded/org/jsoup/nodes/Element;
   #85 = Utf8               body
   #86 = String             #85           // body
   #87 = Utf8               doc
   #88 = Utf8               Lcoursier/util/shaded/org/jsoup/nodes/Element;
   #89 = Utf8               ()Ljava/lang/String;
   #90 = Utf8               documentType
   #91 = Utf8               ()Lcoursier/util/shaded/org/jsoup/nodes/DocumentType;
   #92 = Utf8               childNodes
   #93 = Utf8               Ljava/util/List;
   #94 = NameAndType        #92:#93       // childNodes:Ljava/util/List;
   #95 = Fieldref           #2.#94        // coursier/util/shaded/org/jsoup/nodes/Document.childNodes:Ljava/util/List;
   #96 = Utf8               java/util/List
   #97 = Class              #96           // java/util/List
   #98 = Utf8               iterator
   #99 = Utf8               ()Ljava/util/Iterator;
  #100 = NameAndType        #98:#99       // iterator:()Ljava/util/Iterator;
  #101 = InterfaceMethodref #97.#100      // java/util/List.iterator:()Ljava/util/Iterator;
  #102 = Utf8               java/util/Iterator
  #103 = Class              #102          // java/util/Iterator
  #104 = Utf8               hasNext
  #105 = Utf8               ()Z
  #106 = NameAndType        #104:#105     // hasNext:()Z
  #107 = InterfaceMethodref #103.#106     // java/util/Iterator.hasNext:()Z
  #108 = Utf8               next
  #109 = Utf8               ()Ljava/lang/Object;
  #110 = NameAndType        #108:#109     // next:()Ljava/lang/Object;
  #111 = InterfaceMethodref #103.#110     // java/util/Iterator.next:()Ljava/lang/Object;
  #112 = Utf8               coursier/util/shaded/org/jsoup/nodes/Node
  #113 = Class              #112          // coursier/util/shaded/org/jsoup/nodes/Node
  #114 = Utf8               coursier/util/shaded/org/jsoup/nodes/DocumentType
  #115 = Class              #114          // coursier/util/shaded/org/jsoup/nodes/DocumentType
  #116 = Utf8               coursier/util/shaded/org/jsoup/nodes/LeafNode
  #117 = Class              #116          // coursier/util/shaded/org/jsoup/nodes/LeafNode
  #118 = Utf8               node
  #119 = Utf8               Lcoursier/util/shaded/org/jsoup/nodes/Node;
  #120 = Utf8               ()Lcoursier/util/shaded/org/jsoup/nodes/Element;
  #121 = Utf8               findFirstElementByTagName
  #122 = Utf8               (Ljava/lang/String;Lcoursier/util/shaded/org/jsoup/nodes/Node;)Lcoursier/util/shaded/org/jsoup/nodes/Element;
  #123 = NameAndType        #121:#122     // findFirstElementByTagName:(Ljava/lang/String;Lcoursier/util/shaded/org/jsoup/nodes/Node;)Lcoursier/util/shaded/org/jsoup/nodes/Element;
  #124 = Methodref          #2.#123       // coursier/util/shaded/org/jsoup/nodes/Document.findFirstElementByTagName:(Ljava/lang/String;Lcoursier/util/shaded/org/jsoup/nodes/Node;)Lcoursier/util/shaded/org/jsoup/nodes/Element;
  #125 = Utf8               title
  #126 = String             #125          // title
  #127 = Utf8               getElementsByTag
  #128 = Utf8               (Ljava/lang/String;)Lcoursier/util/shaded/org/jsoup/select/Elements;
  #129 = NameAndType        #127:#128     // getElementsByTag:(Ljava/lang/String;)Lcoursier/util/shaded/org/jsoup/select/Elements;
  #130 = Methodref          #2.#129       // coursier/util/shaded/org/jsoup/nodes/Document.getElementsByTag:(Ljava/lang/String;)Lcoursier/util/shaded/org/jsoup/select/Elements;
  #131 = Utf8               coursier/util/shaded/org/jsoup/select/Elements
  #132 = Class              #131          // coursier/util/shaded/org/jsoup/select/Elements
  #133 = Utf8               first
  #134 = NameAndType        #133:#120     // first:()Lcoursier/util/shaded/org/jsoup/nodes/Element;
  #135 = Methodref          #132.#134     // coursier/util/shaded/org/jsoup/select/Elements.first:()Lcoursier/util/shaded/org/jsoup/nodes/Element;
  #136 = Utf8               text
  #137 = NameAndType        #136:#89      // text:()Ljava/lang/String;
  #138 = Methodref          #4.#137       // coursier/util/shaded/org/jsoup/nodes/Element.text:()Ljava/lang/String;
  #139 = Utf8               coursier/util/shaded/org/jsoup/internal/StringUtil
  #140 = Class              #139          // coursier/util/shaded/org/jsoup/internal/StringUtil
  #141 = Utf8               normaliseWhitespace
  #142 = Utf8               (Ljava/lang/String;)Ljava/lang/String;
  #143 = NameAndType        #141:#142     // normaliseWhitespace:(Ljava/lang/String;)Ljava/lang/String;
  #144 = Methodref          #140.#143     // coursier/util/shaded/org/jsoup/internal/StringUtil.normaliseWhitespace:(Ljava/lang/String;)Ljava/lang/String;
  #145 = Utf8               java/lang/String
  #146 = Class              #145          // java/lang/String
  #147 = Utf8               trim
  #148 = NameAndType        #147:#89      // trim:()Ljava/lang/String;
  #149 = Methodref          #146.#148     // java/lang/String.trim:()Ljava/lang/String;
  #150 = Utf8
  #151 = String             #150          //
  #152 = Utf8               titleEl
  #153 = NameAndType        #82:#120      // head:()Lcoursier/util/shaded/org/jsoup/nodes/Element;
  #154 = Methodref          #2.#153       // coursier/util/shaded/org/jsoup/nodes/Document.head:()Lcoursier/util/shaded/org/jsoup/nodes/Element;
  #155 = NameAndType        #136:#79      // text:(Ljava/lang/String;)Lcoursier/util/shaded/org/jsoup/nodes/Element;
  #156 = Methodref          #4.#155       // coursier/util/shaded/org/jsoup/nodes/Element.text:(Ljava/lang/String;)Lcoursier/util/shaded/org/jsoup/nodes/Element;
  #157 = Utf8               createElement
  #158 = Utf8               preserveCase
  #159 = NameAndType        #158:#32      // preserveCase:Lcoursier/util/shaded/org/jsoup/parser/ParseSettings;
  #160 = Fieldref           #30.#159      // coursier/util/shaded/org/jsoup/parser/ParseSettings.preserveCase:Lcoursier/util/shaded/org/jsoup/parser/ParseSettings;
  #161 = NameAndType        #60:#89       // baseUri:()Ljava/lang/String;
  #162 = Methodref          #2.#161       // coursier/util/shaded/org/jsoup/nodes/Document.baseUri:()Ljava/lang/String;
  #163 = Utf8               tagName
  #164 = Utf8               normalise
  #165 = Utf8               ()Lcoursier/util/shaded/org/jsoup/nodes/Document;
  #166 = Utf8               prependElement
  #167 = NameAndType        #166:#79      // prependElement:(Ljava/lang/String;)Lcoursier/util/shaded/org/jsoup/nodes/Element;
  #168 = Methodref          #4.#167       // coursier/util/shaded/org/jsoup/nodes/Element.prependElement:(Ljava/lang/String;)Lcoursier/util/shaded/org/jsoup/nodes/Element;
  #169 = NameAndType        #85:#120      // body:()Lcoursier/util/shaded/org/jsoup/nodes/Element;
  #170 = Methodref          #2.#169       // coursier/util/shaded/org/jsoup/nodes/Document.body:()Lcoursier/util/shaded/org/jsoup/nodes/Element;
  #171 = Utf8               normaliseTextNodes
  #172 = Utf8               (Lcoursier/util/shaded/org/jsoup/nodes/Element;)V
  #173 = NameAndType        #171:#172     // normaliseTextNodes:(Lcoursier/util/shaded/org/jsoup/nodes/Element;)V
  #174 = Methodref          #2.#173       // coursier/util/shaded/org/jsoup/nodes/Document.normaliseTextNodes:(Lcoursier/util/shaded/org/jsoup/nodes/Element;)V
  #175 = Utf8               normaliseStructure
  #176 = Utf8               (Ljava/lang/String;Lcoursier/util/shaded/org/jsoup/nodes/Element;)V
  #177 = NameAndType        #175:#176     // normaliseStructure:(Ljava/lang/String;Lcoursier/util/shaded/org/jsoup/nodes/Element;)V
  #178 = Methodref          #2.#177       // coursier/util/shaded/org/jsoup/nodes/Document.normaliseStructure:(Ljava/lang/String;Lcoursier/util/shaded/org/jsoup/nodes/Element;)V
  #179 = Utf8               ensureMetaCharsetElement
  #180 = NameAndType        #179:#44      // ensureMetaCharsetElement:()V
  #181 = Methodref          #2.#180       // coursier/util/shaded/org/jsoup/nodes/Document.ensureMetaCharsetElement:()V
  #182 = Utf8               htmlEl
  #183 = Utf8               java/util/ArrayList
  #184 = Class              #183          // java/util/ArrayList
  #185 = Methodref          #184.#45      // java/util/ArrayList."<init>":()V
  #186 = Fieldref           #4.#94        // coursier/util/shaded/org/jsoup/nodes/Element.childNodes:Ljava/util/List;
  #187 = Utf8               coursier/util/shaded/org/jsoup/nodes/TextNode
  #188 = Class              #187          // coursier/util/shaded/org/jsoup/nodes/TextNode
  #189 = Utf8               isBlank
  #190 = NameAndType        #189:#105     // isBlank:()Z
  #191 = Methodref          #188.#190     // coursier/util/shaded/org/jsoup/nodes/TextNode.isBlank:()Z
  #192 = Utf8               add
  #193 = Utf8               (Ljava/lang/Object;)Z
  #194 = NameAndType        #192:#193     // add:(Ljava/lang/Object;)Z
  #195 = InterfaceMethodref #97.#194      // java/util/List.add:(Ljava/lang/Object;)Z
  #196 = Utf8               size
  #197 = Utf8               ()I
  #198 = NameAndType        #196:#197     // size:()I
  #199 = InterfaceMethodref #97.#198      // java/util/List.size:()I
  #200 = Utf8               get
  #201 = Utf8               (I)Ljava/lang/Object;
  #202 = NameAndType        #200:#201     // get:(I)Ljava/lang/Object;
  #203 = InterfaceMethodref #97.#202      // java/util/List.get:(I)Ljava/lang/Object;
  #204 = Utf8               removeChild
  #205 = Utf8               (Lcoursier/util/shaded/org/jsoup/nodes/Node;)V
  #206 = NameAndType        #204:#205     // removeChild:(Lcoursier/util/shaded/org/jsoup/nodes/Node;)V
  #207 = Methodref          #4.#206       // coursier/util/shaded/org/jsoup/nodes/Element.removeChild:(Lcoursier/util/shaded/org/jsoup/nodes/Node;)V
  #208 = Utf8
  #209 = String             #208          //
  #210 = Methodref          #188.#69      // coursier/util/shaded/org/jsoup/nodes/TextNode."<init>":(Ljava/lang/String;)V
  #211 = Utf8               prependChild
  #212 = Utf8               (Lcoursier/util/shaded/org/jsoup/nodes/Node;)Lcoursier/util/shaded/org/jsoup/nodes/Element;
  #213 = NameAndType        #211:#212     // prependChild:(Lcoursier/util/shaded/org/jsoup/nodes/Node;)Lcoursier/util/shaded/org/jsoup/nodes/Element;
  #214 = Methodref          #4.#213       // coursier/util/shaded/org/jsoup/nodes/Element.prependChild:(Lcoursier/util/shaded/org/jsoup/nodes/Node;)Lcoursier/util/shaded/org/jsoup/nodes/Element;
  #215 = Utf8               tn
  #216 = Utf8               Lcoursier/util/shaded/org/jsoup/nodes/TextNode;
  #217 = Utf8               i
  #218 = Utf8               I
  #219 = Utf8               element
  #220 = Utf8               toMove
  #221 = Utf8               Ljava/util/List<Lcoursier/util/shaded/org/jsoup/nodes/Node;>;
  #222 = Methodref          #132.#198     // coursier/util/shaded/org/jsoup/select/Elements.size:()I
  #223 = Methodref          #132.#202     // coursier/util/shaded/org/jsoup/select/Elements.get:(I)Ljava/lang/Object;
  #224 = Utf8               ensureChildNodes
  #225 = Utf8               ()Ljava/util/List;
  #226 = NameAndType        #224:#225     // ensureChildNodes:()Ljava/util/List;
  #227 = Methodref          #113.#226     // coursier/util/shaded/org/jsoup/nodes/Node.ensureChildNodes:()Ljava/util/List;
  #228 = Utf8               addAll
  #229 = Utf8               (Ljava/util/Collection;)Z
  #230 = NameAndType        #228:#229     // addAll:(Ljava/util/Collection;)Z
  #231 = InterfaceMethodref #97.#230      // java/util/List.addAll:(Ljava/util/Collection;)Z
  #232 = Utf8               remove
  #233 = NameAndType        #232:#44      // remove:()V
  #234 = Methodref          #113.#233     // coursier/util/shaded/org/jsoup/nodes/Node.remove:()V
  #235 = Utf8               appendChild
  #236 = NameAndType        #235:#212     // appendChild:(Lcoursier/util/shaded/org/jsoup/nodes/Node;)Lcoursier/util/shaded/org/jsoup/nodes/Element;
  #237 = Methodref          #4.#236       // coursier/util/shaded/org/jsoup/nodes/Element.appendChild:(Lcoursier/util/shaded/org/jsoup/nodes/Node;)Lcoursier/util/shaded/org/jsoup/nodes/Element;
  #238 = Utf8               parent
  #239 = NameAndType        #238:#120     // parent:()Lcoursier/util/shaded/org/jsoup/nodes/Element;
  #240 = Methodref          #4.#239       // coursier/util/shaded/org/jsoup/nodes/Element.parent:()Lcoursier/util/shaded/org/jsoup/nodes/Element;
  #241 = Utf8               equals
  #242 = NameAndType        #241:#193     // equals:(Ljava/lang/Object;)Z
  #243 = Methodref          #4.#242       // coursier/util/shaded/org/jsoup/nodes/Element.equals:(Ljava/lang/Object;)Z
  #244 = Utf8               dupe
  #245 = Utf8               tag
  #246 = Utf8               elements
  #247 = Utf8               Lcoursier/util/shaded/org/jsoup/select/Elements;
  #248 = Utf8               master
  #249 = Utf8               nodeName
  #250 = NameAndType        #249:#89      // nodeName:()Ljava/lang/String;
  #251 = Methodref          #113.#250     // coursier/util/shaded/org/jsoup/nodes/Node.nodeName:()Ljava/lang/String;
  #252 = Methodref          #146.#242     // java/lang/String.equals:(Ljava/lang/Object;)Z
  #253 = Utf8               childNodeSize
  #254 = NameAndType        #253:#197     // childNodeSize:()I
  #255 = Methodref          #113.#254     // coursier/util/shaded/org/jsoup/nodes/Node.childNodeSize:()I
  #256 = Utf8               childNode
  #257 = Utf8               (I)Lcoursier/util/shaded/org/jsoup/nodes/Node;
  #258 = NameAndType        #256:#257     // childNode:(I)Lcoursier/util/shaded/org/jsoup/nodes/Node;
  #259 = Methodref          #113.#258     // coursier/util/shaded/org/jsoup/nodes/Node.childNode:(I)Lcoursier/util/shaded/org/jsoup/nodes/Node;
  #260 = Utf8               found
  #261 = Utf8               outerHtml
  #262 = NameAndType        #76:#89       // html:()Ljava/lang/String;
  #263 = Methodref          #4.#262       // coursier/util/shaded/org/jsoup/nodes/Element.html:()Ljava/lang/String;
  #264 = Utf8               #document
  #265 = String             #264          // #document
  #266 = Utf8               charset
  #267 = Utf8               (Ljava/nio/charset/Charset;)V
  #268 = Utf8               updateMetaCharsetElement
  #269 = Utf8               (Z)V
  #270 = NameAndType        #268:#269     // updateMetaCharsetElement:(Z)V
  #271 = Methodref          #2.#270       // coursier/util/shaded/org/jsoup/nodes/Document.updateMetaCharsetElement:(Z)V
  #272 = Utf8               (Ljava/nio/charset/Charset;)Lcoursier/util/shaded/org/jsoup/nodes/Document$OutputSettings;
  #273 = NameAndType        #266:#272     // charset:(Ljava/nio/charset/Charset;)Lcoursier/util/shaded/org/jsoup/nodes/Document$OutputSettings;
  #274 = Methodref          #7.#273       // coursier/util/shaded/org/jsoup/nodes/Document$OutputSettings.charset:(Ljava/nio/charset/Charset;)Lcoursier/util/shaded/org/jsoup/nodes/Document$OutputSettings;
  #275 = Utf8               Ljava/nio/charset/Charset;
  #276 = Utf8               ()Ljava/nio/charset/Charset;
  #277 = NameAndType        #266:#276     // charset:()Ljava/nio/charset/Charset;
  #278 = Methodref          #7.#277       // coursier/util/shaded/org/jsoup/nodes/Document$OutputSettings.charset:()Ljava/nio/charset/Charset;
  #279 = Utf8               update
  #280 = Utf8               clone
  #281 = NameAndType        #280:#120     // clone:()Lcoursier/util/shaded/org/jsoup/nodes/Element;
  #282 = Methodref          #4.#281       // coursier/util/shaded/org/jsoup/nodes/Element.clone:()Lcoursier/util/shaded/org/jsoup/nodes/Element;
  #283 = Utf8               ()Lcoursier/util/shaded/org/jsoup/nodes/Document$OutputSettings;
  #284 = NameAndType        #280:#283     // clone:()Lcoursier/util/shaded/org/jsoup/nodes/Document$OutputSettings;
  #285 = Methodref          #7.#284       // coursier/util/shaded/org/jsoup/nodes/Document$OutputSettings.clone:()Lcoursier/util/shaded/org/jsoup/nodes/Document$OutputSettings;
  #286 = NameAndType        #15:#283      // outputSettings:()Lcoursier/util/shaded/org/jsoup/nodes/Document$OutputSettings;
  #287 = Methodref          #2.#286       // coursier/util/shaded/org/jsoup/nodes/Document.outputSettings:()Lcoursier/util/shaded/org/jsoup/nodes/Document$OutputSettings;
  #288 = Utf8               syntax
  #289 = Utf8               ()Lcoursier/util/shaded/org/jsoup/nodes/Document$OutputSettings$Syntax;
  #290 = NameAndType        #288:#289     // syntax:()Lcoursier/util/shaded/org/jsoup/nodes/Document$OutputSettings$Syntax;
  #291 = Methodref          #7.#290       // coursier/util/shaded/org/jsoup/nodes/Document$OutputSettings.syntax:()Lcoursier/util/shaded/org/jsoup/nodes/Document$OutputSettings$Syntax;
  #292 = Utf8               Lcoursier/util/shaded/org/jsoup/nodes/Document$OutputSettings$Syntax;
  #293 = NameAndType        #76:#292      // html:Lcoursier/util/shaded/org/jsoup/nodes/Document$OutputSettings$Syntax;
  #294 = Fieldref           #13.#293      // coursier/util/shaded/org/jsoup/nodes/Document$OutputSettings$Syntax.html:Lcoursier/util/shaded/org/jsoup/nodes/Document$OutputSettings$Syntax;
  #295 = Utf8               meta[charset]
  #296 = String             #295          // meta[charset]
  #297 = Utf8               select
  #298 = NameAndType        #297:#128     // select:(Ljava/lang/String;)Lcoursier/util/shaded/org/jsoup/select/Elements;
  #299 = Methodref          #2.#298       // coursier/util/shaded/org/jsoup/nodes/Document.select:(Ljava/lang/String;)Lcoursier/util/shaded/org/jsoup/select/Elements;
  #300 = String             #266          // charset
  #301 = Methodref          #2.#277       // coursier/util/shaded/org/jsoup/nodes/Document.charset:()Ljava/nio/charset/Charset;
  #302 = Utf8               java/nio/charset/Charset
  #303 = Class              #302          // java/nio/charset/Charset
  #304 = Utf8               displayName
  #305 = NameAndType        #304:#89      // displayName:()Ljava/lang/String;
  #306 = Methodref          #303.#305     // java/nio/charset/Charset.displayName:()Ljava/lang/String;
  #307 = Utf8               attr
  #308 = Utf8               (Ljava/lang/String;Ljava/lang/String;)Lcoursier/util/shaded/org/jsoup/nodes/Element;
  #309 = NameAndType        #307:#308     // attr:(Ljava/lang/String;Ljava/lang/String;)Lcoursier/util/shaded/org/jsoup/nodes/Element;
  #310 = Methodref          #4.#309       // coursier/util/shaded/org/jsoup/nodes/Element.attr:(Ljava/lang/String;Ljava/lang/String;)Lcoursier/util/shaded/org/jsoup/nodes/Element;
  #311 = Utf8               meta
  #312 = String             #311          // meta
  #313 = Utf8               meta[name=charset]
  #314 = String             #313          // meta[name=charset]
  #315 = Utf8               ()Lcoursier/util/shaded/org/jsoup/select/Elements;
  #316 = NameAndType        #232:#315     // remove:()Lcoursier/util/shaded/org/jsoup/select/Elements;
  #317 = Methodref          #132.#316     // coursier/util/shaded/org/jsoup/select/Elements.remove:()Lcoursier/util/shaded/org/jsoup/select/Elements;
  #318 = Utf8               xml
  #319 = NameAndType        #318:#292     // xml:Lcoursier/util/shaded/org/jsoup/nodes/Document$OutputSettings$Syntax;
  #320 = Fieldref           #13.#319      // coursier/util/shaded/org/jsoup/nodes/Document$OutputSettings$Syntax.xml:Lcoursier/util/shaded/org/jsoup/nodes/Document$OutputSettings$Syntax;
  #321 = NameAndType        #92:#225      // childNodes:()Ljava/util/List;
  #322 = Methodref          #2.#321       // coursier/util/shaded/org/jsoup/nodes/Document.childNodes:()Ljava/util/List;
  #323 = Utf8               coursier/util/shaded/org/jsoup/nodes/XmlDeclaration
  #324 = Class              #323          // coursier/util/shaded/org/jsoup/nodes/XmlDeclaration
  #325 = Utf8               name
  #326 = NameAndType        #325:#89      // name:()Ljava/lang/String;
  #327 = Methodref          #324.#326     // coursier/util/shaded/org/jsoup/nodes/XmlDeclaration.name:()Ljava/lang/String;
  #328 = String             #318          // xml
  #329 = Utf8               encoding
  #330 = String             #329          // encoding
  #331 = Utf8               (Ljava/lang/String;Ljava/lang/String;)Lcoursier/util/shaded/org/jsoup/nodes/Node;
  #332 = NameAndType        #307:#331     // attr:(Ljava/lang/String;Ljava/lang/String;)Lcoursier/util/shaded/org/jsoup/nodes/Node;
  #333 = Methodref          #324.#332     // coursier/util/shaded/org/jsoup/nodes/XmlDeclaration.attr:(Ljava/lang/String;Ljava/lang/String;)Lcoursier/util/shaded/org/jsoup/nodes/Node;
  #334 = Utf8               version
  #335 = String             #334          // version
  #336 = NameAndType        #307:#142     // attr:(Ljava/lang/String;)Ljava/lang/String;
  #337 = Methodref          #324.#336     // coursier/util/shaded/org/jsoup/nodes/XmlDeclaration.attr:(Ljava/lang/String;)Ljava/lang/String;
  #338 = Utf8               1.0
  #339 = String             #338          // 1.0
  #340 = Utf8               (Ljava/lang/String;Z)V
  #341 = NameAndType        #25:#340      // "<init>":(Ljava/lang/String;Z)V
  #342 = Methodref          #324.#341     // coursier/util/shaded/org/jsoup/nodes/XmlDeclaration."<init>":(Ljava/lang/String;Z)V
  #343 = Methodref          #2.#213       // coursier/util/shaded/org/jsoup/nodes/Document.prependChild:(Lcoursier/util/shaded/org/jsoup/nodes/Node;)Lcoursier/util/shaded/org/jsoup/nodes/Element;
  #344 = Utf8               metaCharset
  #345 = Utf8               decl
  #346 = Utf8               Lcoursier/util/shaded/org/jsoup/nodes/XmlDeclaration;
  #347 = Utf8               (Lcoursier/util/shaded/org/jsoup/nodes/Document$OutputSettings;)Lcoursier/util/shaded/org/jsoup/nodes/Document;
  #348 = Utf8               ()Lcoursier/util/shaded/org/jsoup/nodes/Document$QuirksMode;
  #349 = Utf8               (Lcoursier/util/shaded/org/jsoup/nodes/Document$QuirksMode;)Lcoursier/util/shaded/org/jsoup/nodes/Document;
  #350 = Utf8               (Lcoursier/util/shaded/org/jsoup/parser/Parser;)Lcoursier/util/shaded/org/jsoup/nodes/Document;
  #351 = NameAndType        #280:#165     // clone:()Lcoursier/util/shaded/org/jsoup/nodes/Document;
  #352 = Methodref          #2.#351       // coursier/util/shaded/org/jsoup/nodes/Document.clone:()Lcoursier/util/shaded/org/jsoup/nodes/Document;
  #353 = Utf8               ()Lcoursier/util/shaded/org/jsoup/nodes/Node;
  #354 = Utf8               java/lang/CloneNotSupportedException
  #355 = Class              #354          // java/lang/CloneNotSupportedException
  #356 = Utf8               Code
  #357 = Utf8               LineNumberTable
  #358 = Utf8               LocalVariableTable
  #359 = Utf8               StackMapTable
  #360 = Utf8               LocalVariableTypeTable
  #361 = Utf8               Exceptions
  #362 = Utf8               InnerClasses
  #363 = Utf8               SourceFile
{
  private coursier.util.shaded.org.jsoup.nodes.Document$OutputSettings outputSettings;
    descriptor: Lcoursier/util/shaded/org/jsoup/nodes/Document$OutputSettings;
    flags: (0x0002) ACC_PRIVATE

  private coursier.util.shaded.org.jsoup.parser.Parser parser;
    descriptor: Lcoursier/util/shaded/org/jsoup/parser/Parser;
    flags: (0x0002) ACC_PRIVATE

  private coursier.util.shaded.org.jsoup.nodes.Document$QuirksMode quirksMode;
    descriptor: Lcoursier/util/shaded/org/jsoup/nodes/Document$QuirksMode;
    flags: (0x0002) ACC_PRIVATE

  private java.lang.String location;
    descriptor: Ljava/lang/String;
    flags: (0x0002) ACC_PRIVATE

  private boolean updateMetaCharset;
    descriptor: Z
    flags: (0x0002) ACC_PRIVATE

  public coursier.util.shaded.org.jsoup.nodes.Document(java.lang.String);
    descriptor: (Ljava/lang/String;)V
    flags: (0x0001) ACC_PUBLIC
    Code:
      stack=3, locals=2, args_size=2
         0: aload_0
         1: ldc           #28                 // String #root
         3: getstatic     #34                 // Field coursier/util/shaded/org/jsoup/parser/ParseSettings.htmlDefault:Lcoursier/util/shaded/org/jsoup/parser/ParseSettings;
         6: invokestatic  #40                 // Method coursier/util/shaded/org/jsoup/parser/Tag.valueOf:(Ljava/lang/String;Lcoursier/util/shaded/org/jsoup/parser/ParseSettings;)Lcoursier/util/shaded/org/jsoup/parser/Tag;
         9: aload_1
        10: invokespecial #43                 // Method coursier/util/shaded/org/jsoup/nodes/Element."<init>":(Lcoursier/util/shaded/org/jsoup/parser/Tag;Ljava/lang/String;)V
        13: aload_0
        14: new           #7                  // class coursier/util/shaded/org/jsoup/nodes/Document$OutputSettings
        17: dup
        18: invokespecial #46                 // Method coursier/util/shaded/org/jsoup/nodes/Document$OutputSettings."<init>":()V
        21: putfield      #48                 // Field outputSettings:Lcoursier/util/shaded/org/jsoup/nodes/Document$OutputSettings;
        24: aload_0
        25: getstatic     #51                 // Field coursier/util/shaded/org/jsoup/nodes/Document$QuirksMode.noQuirks:Lcoursier/util/shaded/org/jsoup/nodes/Document$QuirksMode;
        28: putfield      #53                 // Field quirksMode:Lcoursier/util/shaded/org/jsoup/nodes/Document$QuirksMode;
        31: aload_0
        32: iconst_0
        33: putfield      #55                 // Field updateMetaCharset:Z
        36: aload_0
        37: aload_1
        38: putfield      #57                 // Field location:Ljava/lang/String;
        41: return
      LineNumberTable:
        line 33: 0
        line 20: 13
        line 22: 24
        line 24: 31
        line 34: 36
        line 35: 41
      LocalVariableTable:
        Start  Length  Slot  Name   Signature
            0      42     0  this   Lcoursier/util/shaded/org/jsoup/nodes/Document;
            0      42     1 baseUri   Ljava/lang/String;

  public static coursier.util.shaded.org.jsoup.nodes.Document createShell(java.lang.String);
    descriptor: (Ljava/lang/String;)Lcoursier/util/shaded/org/jsoup/nodes/Document;
    flags: (0x0009) ACC_PUBLIC, ACC_STATIC
    Code:
      stack=3, locals=3, args_size=1
         0: aload_0
         1: invokestatic  #68                 // Method coursier/util/shaded/org/jsoup/helper/Validate.notNull:(Ljava/lang/Object;)V
         4: new           #2                  // class coursier/util/shaded/org/jsoup/nodes/Document
         7: dup
         8: aload_0
         9: invokespecial #70                 // Method "<init>":(Ljava/lang/String;)V
        12: astore_1
        13: aload_1
        14: aload_1
        15: invokevirtual #73                 // Method parser:()Lcoursier/util/shaded/org/jsoup/parser/Parser;
        18: putfield      #75                 // Field parser:Lcoursier/util/shaded/org/jsoup/parser/Parser;
        21: aload_1
        22: ldc           #77                 // String html
        24: invokevirtual #81                 // Method appendElement:(Ljava/lang/String;)Lcoursier/util/shaded/org/jsoup/nodes/Element;
        27: astore_2
        28: aload_2
        29: ldc           #83                 // String head
        31: invokevirtual #84                 // Method coursier/util/shaded/org/jsoup/nodes/Element.appendElement:(Ljava/lang/String;)Lcoursier/util/shaded/org/jsoup/nodes/Element;
        34: pop
        35: aload_2
        36: ldc           #86                 // String body
        38: invokevirtual #84                 // Method coursier/util/shaded/org/jsoup/nodes/Element.appendElement:(Ljava/lang/String;)Lcoursier/util/shaded/org/jsoup/nodes/Element;
        41: pop
        42: aload_1
        43: areturn
      LineNumberTable:
        line 43: 0
        line 45: 4
        line 46: 13
        line 47: 21
        line 48: 28
        line 49: 35
        line 51: 42
      LocalVariableTable:
        Start  Length  Slot  Name   Signature
            0      44     0 baseUri   Ljava/lang/String;
           13      31     1   doc   Lcoursier/util/shaded/org/jsoup/nodes/Document;
           28      16     2  html   Lcoursier/util/shaded/org/jsoup/nodes/Element;

  public java.lang.String location();
    descriptor: ()Ljava/lang/String;
    flags: (0x0001) ACC_PUBLIC
    Code:
      stack=1, locals=1, args_size=1
         0: aload_0
         1: getfield      #57                 // Field location:Ljava/lang/String;
         4: areturn
      LineNumberTable:
        line 60: 0
      LocalVariableTable:
        Start  Length  Slot  Name   Signature
            0       5     0  this   Lcoursier/util/shaded/org/jsoup/nodes/Document;

  public coursier.util.shaded.org.jsoup.nodes.DocumentType documentType();
    descriptor: ()Lcoursier/util/shaded/org/jsoup/nodes/DocumentType;
    flags: (0x0001) ACC_PUBLIC
    Code:
      stack=1, locals=3, args_size=1
         0: aload_0
         1: getfield      #95                 // Field childNodes:Ljava/util/List;
         4: invokeinterface #101,  1          // InterfaceMethod java/util/List.iterator:()Ljava/util/Iterator;
         9: astore_1
        10: aload_1
        11: invokeinterface #107,  1          // InterfaceMethod java/util/Iterator.hasNext:()Z
        16: ifeq          54
        19: aload_1
        20: invokeinterface #111,  1          // InterfaceMethod java/util/Iterator.next:()Ljava/lang/Object;
        25: checkcast     #113                // class coursier/util/shaded/org/jsoup/nodes/Node
        28: astore_2
        29: aload_2
        30: instanceof    #115                // class coursier/util/shaded/org/jsoup/nodes/DocumentType
        33: ifeq          41
        36: aload_2
        37: checkcast     #115                // class coursier/util/shaded/org/jsoup/nodes/DocumentType
        40: areturn
        41: aload_2
        42: instanceof    #117                // class coursier/util/shaded/org/jsoup/nodes/LeafNode
        45: ifne          51
        48: goto          54
        51: goto          10
        54: aconst_null
        55: areturn
      StackMapTable: number_of_entries = 4
        frame_type = 252 /* append */
          offset_delta = 10
          locals = [ class java/util/Iterator ]
        frame_type = 252 /* append */
          offset_delta = 30
          locals = [ class coursier/util/shaded/org/jsoup/nodes/Node ]
        frame_type = 250 /* chop */
          offset_delta = 9
        frame_type = 250 /* chop */
          offset_delta = 2
      LineNumberTable:
        line 68: 0
        line 69: 29
        line 70: 36
        line 71: 41
        line 72: 48
        line 73: 51
        line 74: 54
      LocalVariableTable:
        Start  Length  Slot  Name   Signature
           29      22     2  node   Lcoursier/util/shaded/org/jsoup/nodes/Node;
            0      56     0  this   Lcoursier/util/shaded/org/jsoup/nodes/Document;

  public coursier.util.shaded.org.jsoup.nodes.Element head();
    descriptor: ()Lcoursier/util/shaded/org/jsoup/nodes/Element;
    flags: (0x0001) ACC_PUBLIC
    Code:
      stack=3, locals=1, args_size=1
         0: aload_0
         1: ldc           #83                 // String head
         3: aload_0
         4: invokespecial #124                // Method findFirstElementByTagName:(Ljava/lang/String;Lcoursier/util/shaded/org/jsoup/nodes/Node;)Lcoursier/util/shaded/org/jsoup/nodes/Element;
         7: areturn
      LineNumberTable:
        line 83: 0
      LocalVariableTable:
        Start  Length  Slot  Name   Signature
            0       8     0  this   Lcoursier/util/shaded/org/jsoup/nodes/Document;

  public coursier.util.shaded.org.jsoup.nodes.Element body();
    descriptor: ()Lcoursier/util/shaded/org/jsoup/nodes/Element;
    flags: (0x0001) ACC_PUBLIC
    Code:
      stack=3, locals=1, args_size=1
         0: aload_0
         1: ldc           #86                 // String body
         3: aload_0
         4: invokespecial #124                // Method findFirstElementByTagName:(Ljava/lang/String;Lcoursier/util/shaded/org/jsoup/nodes/Node;)Lcoursier/util/shaded/org/jsoup/nodes/Element;
         7: areturn
      LineNumberTable:
        line 91: 0
      LocalVariableTable:
        Start  Length  Slot  Name   Signature
            0       8     0  this   Lcoursier/util/shaded/org/jsoup/nodes/Document;

  public java.lang.String title();
    descriptor: ()Ljava/lang/String;
    flags: (0x0001) ACC_PUBLIC
    Code:
      stack=2, locals=2, args_size=1
         0: aload_0
         1: ldc           #126                // String title
         3: invokevirtual #130                // Method getElementsByTag:(Ljava/lang/String;)Lcoursier/util/shaded/org/jsoup/select/Elements;
         6: invokevirtual #135                // Method coursier/util/shaded/org/jsoup/select/Elements.first:()Lcoursier/util/shaded/org/jsoup/nodes/Element;
         9: astore_1
        10: aload_1
        11: ifnull        27
        14: aload_1
        15: invokevirtual #138                // Method coursier/util/shaded/org/jsoup/nodes/Element.text:()Ljava/lang/String;
        18: invokestatic  #144                // Method coursier/util/shaded/org/jsoup/internal/StringUtil.normaliseWhitespace:(Ljava/lang/String;)Ljava/lang/String;
        21: invokevirtual #149                // Method java/lang/String.trim:()Ljava/lang/String;
        24: goto          29
        27: ldc           #151                // String
        29: areturn
      StackMapTable: number_of_entries = 2
        frame_type = 252 /* append */
          offset_delta = 27
          locals = [ class coursier/util/shaded/org/jsoup/nodes/Element ]
        frame_type = 65 /* same_locals_1_stack_item */
          stack = [ class java/lang/String ]
      LineNumberTable:
        line 100: 0
        line 101: 10
      LocalVariableTable:
        Start  Length  Slot  Name   Signature
            0      30     0  this   Lcoursier/util/shaded/org/jsoup/nodes/Document;
           10      20     1 titleEl   Lcoursier/util/shaded/org/jsoup/nodes/Element;

  public void title(java.lang.String);
    descriptor: (Ljava/lang/String;)V
    flags: (0x0001) ACC_PUBLIC
    Code:
      stack=2, locals=3, args_size=2
         0: aload_1
         1: invokestatic  #68                 // Method coursier/util/shaded/org/jsoup/helper/Validate.notNull:(Ljava/lang/Object;)V
         4: aload_0
         5: ldc           #126                // String title
         7: invokevirtual #130                // Method getElementsByTag:(Ljava/lang/String;)Lcoursier/util/shaded/org/jsoup/select/Elements;
        10: invokevirtual #135                // Method coursier/util/shaded/org/jsoup/select/Elements.first:()Lcoursier/util/shaded/org/jsoup/nodes/Element;
        13: astore_2
        14: aload_2
        15: ifnonnull     35
        18: aload_0
        19: invokevirtual #154                // Method head:()Lcoursier/util/shaded/org/jsoup/nodes/Element;
        22: ldc           #126                // String title
        24: invokevirtual #84                 // Method coursier/util/shaded/org/jsoup/nodes/Element.appendElement:(Ljava/lang/String;)Lcoursier/util/shaded/org/jsoup/nodes/Element;
        27: aload_1
        28: invokevirtual #156                // Method coursier/util/shaded/org/jsoup/nodes/Element.text:(Ljava/lang/String;)Lcoursier/util/shaded/org/jsoup/nodes/Element;
        31: pop
        32: goto          41
        35: aload_2
        36: aload_1
        37: invokevirtual #156                // Method coursier/util/shaded/org/jsoup/nodes/Element.text:(Ljava/lang/String;)Lcoursier/util/shaded/org/jsoup/nodes/Element;
        40: pop
        41: return
      StackMapTable: number_of_entries = 2
        frame_type = 252 /* append */
          offset_delta = 35
          locals = [ class coursier/util/shaded/org/jsoup/nodes/Element ]
        frame_type = 5 /* same */
      LineNumberTable:
        line 110: 0
        line 111: 4
        line 112: 14
        line 113: 18
        line 115: 35
        line 117: 41
      LocalVariableTable:
        Start  Length  Slot  Name   Signature
            0      42     0  this   Lcoursier/util/shaded/org/jsoup/nodes/Document;
            0      42     1 title   Ljava/lang/String;
           14      28     2 titleEl   Lcoursier/util/shaded/org/jsoup/nodes/Element;

  public coursier.util.shaded.org.jsoup.nodes.Element createElement(java.lang.String);
    descriptor: (Ljava/lang/String;)Lcoursier/util/shaded/org/jsoup/nodes/Element;
    flags: (0x0001) ACC_PUBLIC
    Code:
      stack=4, locals=2, args_size=2
         0: new           #4                  // class coursier/util/shaded/org/jsoup/nodes/Element
         3: dup
         4: aload_1
         5: getstatic     #160                // Field coursier/util/shaded/org/jsoup/parser/ParseSettings.preserveCase:Lcoursier/util/shaded/org/jsoup/parser/ParseSettings;
         8: invokestatic  #40                 // Method coursier/util/shaded/org/jsoup/parser/Tag.valueOf:(Ljava/lang/String;Lcoursier/util/shaded/org/jsoup/parser/ParseSettings;)Lcoursier/util/shaded/org/jsoup/parser/Tag;
        11: aload_0
        12: invokevirtual #162                // Method baseUri:()Ljava/lang/String;
        15: invokespecial #43                 // Method coursier/util/shaded/org/jsoup/nodes/Element."<init>":(Lcoursier/util/shaded/org/jsoup/parser/Tag;Ljava/lang/String;)V
        18: areturn
      LineNumberTable:
        line 125: 0
      LocalVariableTable:
        Start  Length  Slot  Name   Signature
            0      19     0  this   Lcoursier/util/shaded/org/jsoup/nodes/Document;
            0      19     1 tagName   Ljava/lang/String;

  public coursier.util.shaded.org.jsoup.nodes.Document normalise();
    descriptor: ()Lcoursier/util/shaded/org/jsoup/nodes/Document;
    flags: (0x0001) ACC_PUBLIC
    Code:
      stack=3, locals=2, args_size=1
         0: aload_0
         1: ldc           #77                 // String html
         3: aload_0
         4: invokespecial #124                // Method findFirstElementByTagName:(Ljava/lang/String;Lcoursier/util/shaded/org/jsoup/nodes/Node;)Lcoursier/util/shaded/org/jsoup/nodes/Element;
         7: astore_1
         8: aload_1
         9: ifnonnull     19
        12: aload_0
        13: ldc           #77                 // String html
        15: invokevirtual #81                 // Method appendElement:(Ljava/lang/String;)Lcoursier/util/shaded/org/jsoup/nodes/Element;
        18: astore_1
        19: aload_0
        20: invokevirtual #154                // Method head:()Lcoursier/util/shaded/org/jsoup/nodes/Element;
        23: ifnonnull     33
        26: aload_1
        27: ldc           #83                 // String head
        29: invokevirtual #168                // Method coursier/util/shaded/org/jsoup/nodes/Element.prependElement:(Ljava/lang/String;)Lcoursier/util/shaded/org/jsoup/nodes/Element;
        32: pop
        33: aload_0
        34: invokevirtual #170                // Method body:()Lcoursier/util/shaded/org/jsoup/nodes/Element;
        37: ifnonnull     47
        40: aload_1
        41: ldc           #86                 // String body
        43: invokevirtual #84                 // Method coursier/util/shaded/org/jsoup/nodes/Element.appendElement:(Ljava/lang/String;)Lcoursier/util/shaded/org/jsoup/nodes/Element;
        46: pop
        47: aload_0
        48: aload_0
        49: invokevirtual #154                // Method head:()Lcoursier/util/shaded/org/jsoup/nodes/Element;
        52: invokespecial #174                // Method normaliseTextNodes:(Lcoursier/util/shaded/org/jsoup/nodes/Element;)V
        55: aload_0
        56: aload_1
        57: invokespecial #174                // Method normaliseTextNodes:(Lcoursier/util/shaded/org/jsoup/nodes/Element;)V
        60: aload_0
        61: aload_0
        62: invokespecial #174                // Method normaliseTextNodes:(Lcoursier/util/shaded/org/jsoup/nodes/Element;)V
        65: aload_0
        66: ldc           #83                 // String head
        68: aload_1
        69: invokespecial #178                // Method normaliseStructure:(Ljava/lang/String;Lcoursier/util/shaded/org/jsoup/nodes/Element;)V
        72: aload_0
        73: ldc           #86                 // String body
        75: aload_1
        76: invokespecial #178                // Method normaliseStructure:(Ljava/lang/String;Lcoursier/util/shaded/org/jsoup/nodes/Element;)V
        79: aload_0
        80: invokespecial #181                // Method ensureMetaCharsetElement:()V
        83: aload_0
        84: areturn
      StackMapTable: number_of_entries = 3
        frame_type = 252 /* append */
          offset_delta = 19
          locals = [ class coursier/util/shaded/org/jsoup/nodes/Element ]
        frame_type = 13 /* same */
        frame_type = 13 /* same */
      LineNumberTable:
        line 134: 0
        line 135: 8
        line 136: 12
        line 137: 19
        line 138: 26
        line 139: 33
        line 140: 40
        line 144: 47
        line 145: 55
        line 146: 60
        line 148: 65
        line 149: 72
        line 151: 79
        line 153: 83
      LocalVariableTable:
        Start  Length  Slot  Name   Signature
            0      85     0  this   Lcoursier/util/shaded/org/jsoup/nodes/Document;
            8      77     1 htmlEl   Lcoursier/util/shaded/org/jsoup/nodes/Element;

  private void normaliseTextNodes(coursier.util.shaded.org.jsoup.nodes.Element);
    descriptor: (Lcoursier/util/shaded/org/jsoup/nodes/Element;)V
    flags: (0x0002) ACC_PRIVATE
    Code:
      stack=4, locals=6, args_size=2
         0: new           #184                // class java/util/ArrayList
         3: dup
         4: invokespecial #185                // Method java/util/ArrayList."<init>":()V
         7: astore_2
         8: aload_1
         9: getfield      #186                // Field coursier/util/shaded/org/jsoup/nodes/Element.childNodes:Ljava/util/List;
        12: invokeinterface #101,  1          // InterfaceMethod java/util/List.iterator:()Ljava/util/Iterator;
        17: astore_3
        18: aload_3
        19: invokeinterface #107,  1          // InterfaceMethod java/util/Iterator.hasNext:()Z
        24: ifeq          73
        27: aload_3
        28: invokeinterface #111,  1          // InterfaceMethod java/util/Iterator.next:()Ljava/lang/Object;
        33: checkcast     #113                // class coursier/util/shaded/org/jsoup/nodes/Node
        36: astore        4
        38: aload         4
        40: instanceof    #188                // class coursier/util/shaded/org/jsoup/nodes/TextNode
        43: ifeq          70
        46: aload         4
        48: checkcast     #188                // class coursier/util/shaded/org/jsoup/nodes/TextNode
        51: astore        5
        53: aload         5
        55: invokevirtual #191                // Method coursier/util/shaded/org/jsoup/nodes/TextNode.isBlank:()Z
        58: ifne          70
        61: aload_2
        62: aload         5
        64: invokeinterface #195,  2          // InterfaceMethod java/util/List.add:(Ljava/lang/Object;)Z
        69: pop
        70: goto          18
        73: aload_2
        74: invokeinterface #199,  1          // InterfaceMethod java/util/List.size:()I
        79: iconst_1
        80: isub
        81: istore_3
        82: iload_3
        83: iflt          137
        86: aload_2
        87: iload_3
        88: invokeinterface #203,  2          // InterfaceMethod java/util/List.get:(I)Ljava/lang/Object;
        93: checkcast     #113                // class coursier/util/shaded/org/jsoup/nodes/Node
        96: astore        4
        98: aload_1
        99: aload         4
       101: invokevirtual #207                // Method coursier/util/shaded/org/jsoup/nodes/Element.removeChild:(Lcoursier/util/shaded/org/jsoup/nodes/Node;)V
       104: aload_0
       105: invokevirtual #170                // Method body:()Lcoursier/util/shaded/org/jsoup/nodes/Element;
       108: new           #188                // class coursier/util/shaded/org/jsoup/nodes/TextNode
       111: dup
       112: ldc           #209                // String
       114: invokespecial #210                // Method coursier/util/shaded/org/jsoup/nodes/TextNode."<init>":(Ljava/lang/String;)V
       117: invokevirtual #214                // Method coursier/util/shaded/org/jsoup/nodes/Element.prependChild:(Lcoursier/util/shaded/org/jsoup/nodes/Node;)Lcoursier/util/shaded/org/jsoup/nodes/Element;
       120: pop
       121: aload_0
       122: invokevirtual #170                // Method body:()Lcoursier/util/shaded/org/jsoup/nodes/Element;
       125: aload         4
       127: invokevirtual #214                // Method coursier/util/shaded/org/jsoup/nodes/Element.prependChild:(Lcoursier/util/shaded/org/jsoup/nodes/Node;)Lcoursier/util/shaded/org/jsoup/nodes/Element;
       130: pop
       131: iinc          3, -1
       134: goto          82
       137: return
      StackMapTable: number_of_entries = 5
        frame_type = 253 /* append */
          offset_delta = 18
          locals = [ class java/util/List, class java/util/Iterator ]
        frame_type = 51 /* same */
        frame_type = 250 /* chop */
          offset_delta = 2
        frame_type = 252 /* append */
          offset_delta = 8
          locals = [ int ]
        frame_type = 250 /* chop */
          offset_delta = 54
      LineNumberTable:
        line 158: 0
        line 159: 8
        line 160: 38
        line 161: 46
        line 162: 53
        line 163: 61
        line 165: 70
        line 167: 73
        line 168: 86
        line 169: 98
        line 170: 104
        line 171: 121
        line 167: 131
        line 173: 137
      LocalVariableTable:
        Start  Length  Slot  Name   Signature
           53      17     5    tn   Lcoursier/util/shaded/org/jsoup/nodes/TextNode;
           38      32     4  node   Lcoursier/util/shaded/org/jsoup/nodes/Node;
           98      33     4  node   Lcoursier/util/shaded/org/jsoup/nodes/Node;
           82      55     3     i   I
            0     138     0  this   Lcoursier/util/shaded/org/jsoup/nodes/Document;
            0     138     1 element   Lcoursier/util/shaded/org/jsoup/nodes/Element;
            8     130     2 toMove   Ljava/util/List;
      LocalVariableTypeTable:
        Start  Length  Slot  Name   Signature
            8     130     2 toMove   Ljava/util/List<Lcoursier/util/shaded/org/jsoup/nodes/Node;>;

  private void normaliseStructure(java.lang.String, coursier.util.shaded.org.jsoup.nodes.Element);
    descriptor: (Ljava/lang/String;Lcoursier/util/shaded/org/jsoup/nodes/Element;)V
    flags: (0x0002) ACC_PRIVATE
    Code:
      stack=2, locals=8, args_size=3
         0: aload_0
         1: aload_1
         2: invokevirtual #130                // Method getElementsByTag:(Ljava/lang/String;)Lcoursier/util/shaded/org/jsoup/select/Elements;
         5: astore_3
         6: aload_3
         7: invokevirtual #135                // Method coursier/util/shaded/org/jsoup/select/Elements.first:()Lcoursier/util/shaded/org/jsoup/nodes/Element;
        10: astore        4
        12: aload_3
        13: invokevirtual #222                // Method coursier/util/shaded/org/jsoup/select/Elements.size:()I
        16: iconst_1
        17: if_icmple     118
        20: new           #184                // class java/util/ArrayList
        23: dup
        24: invokespecial #185                // Method java/util/ArrayList."<init>":()V
        27: astore        5
        29: iconst_1
        30: istore        6
        32: iload         6
        34: aload_3
        35: invokevirtual #222                // Method coursier/util/shaded/org/jsoup/select/Elements.size:()I
        38: if_icmpge     76
        41: aload_3
        42: iload         6
        44: invokevirtual #223                // Method coursier/util/shaded/org/jsoup/select/Elements.get:(I)Ljava/lang/Object;
        47: checkcast     #113                // class coursier/util/shaded/org/jsoup/nodes/Node
        50: astore        7
        52: aload         5
        54: aload         7
        56: invokevirtual #227                // Method coursier/util/shaded/org/jsoup/nodes/Node.ensureChildNodes:()Ljava/util/List;
        59: invokeinterface #231,  2          // InterfaceMethod java/util/List.addAll:(Ljava/util/Collection;)Z
        64: pop
        65: aload         7
        67: invokevirtual #234                // Method coursier/util/shaded/org/jsoup/nodes/Node.remove:()V
        70: iinc          6, 1
        73: goto          32
        76: aload         5
        78: invokeinterface #101,  1          // InterfaceMethod java/util/List.iterator:()Ljava/util/Iterator;
        83: astore        6
        85: aload         6
        87: invokeinterface #107,  1          // InterfaceMethod java/util/Iterator.hasNext:()Z
        92: ifeq          118
        95: aload         6
        97: invokeinterface #111,  1          // InterfaceMethod java/util/Iterator.next:()Ljava/lang/Object;
       102: checkcast     #113                // class coursier/util/shaded/org/jsoup/nodes/Node
       105: astore        7
       107: aload         4
       109: aload         7
       111: invokevirtual #237                // Method coursier/util/shaded/org/jsoup/nodes/Element.appendChild:(Lcoursier/util/shaded/org/jsoup/nodes/Node;)Lcoursier/util/shaded/org/jsoup/nodes/Element;
       114: pop
       115: goto          85
       118: aload         4
       120: invokevirtual #240                // Method coursier/util/shaded/org/jsoup/nodes/Element.parent:()Lcoursier/util/shaded/org/jsoup/nodes/Element;
       123: aload_2
       124: invokevirtual #243                // Method coursier/util/shaded/org/jsoup/nodes/Element.equals:(Ljava/lang/Object;)Z
       127: ifne          137
       130: aload_2
       131: aload         4
       133: invokevirtual #237                // Method coursier/util/shaded/org/jsoup/nodes/Element.appendChild:(Lcoursier/util/shaded/org/jsoup/nodes/Node;)Lcoursier/util/shaded/org/jsoup/nodes/Element;
       136: pop
       137: return
      StackMapTable: number_of_entries = 5
        frame_type = 255 /* full_frame */
          offset_delta = 32
          locals = [ class coursier/util/shaded/org/jsoup/nodes/Document, class java/lang/String, class coursier/util/shaded/org/jsoup/nodes/Element, class coursier/util/shaded/org/jsoup/select/Elements, class coursier/util/shaded/org/jsoup/nodes/Element, class java/util/List, int ]
          stack = []
        frame_type = 250 /* chop */
          offset_delta = 43
        frame_type = 252 /* append */
          offset_delta = 8
          locals = [ class java/util/Iterator ]
        frame_type = 249 /* chop */
          offset_delta = 32
        frame_type = 18 /* same */
      LineNumberTable:
        line 177: 0
        line 178: 6
        line 179: 12
        line 180: 20
        line 181: 29
        line 182: 41
        line 183: 52
        line 184: 65
        line 181: 70
        line 187: 76
        line 188: 107
        line 191: 118
        line 192: 130
        line 194: 137
      LocalVariableTable:
        Start  Length  Slot  Name   Signature
           52      18     7  dupe   Lcoursier/util/shaded/org/jsoup/nodes/Node;
           32      44     6     i   I
          107       8     7  dupe   Lcoursier/util/shaded/org/jsoup/nodes/Node;
           29      89     5 toMove   Ljava/util/List;
            0     138     0  this   Lcoursier/util/shaded/org/jsoup/nodes/Document;
            0     138     1   tag   Ljava/lang/String;
            0     138     2 htmlEl   Lcoursier/util/shaded/org/jsoup/nodes/Element;
            6     132     3 elements   Lcoursier/util/shaded/org/jsoup/select/Elements;
           12     126     4 master   Lcoursier/util/shaded/org/jsoup/nodes/Element;
      LocalVariableTypeTable:
        Start  Length  Slot  Name   Signature
           29      89     5 toMove   Ljava/util/List<Lcoursier/util/shaded/org/jsoup/nodes/Node;>;

  private coursier.util.shaded.org.jsoup.nodes.Element findFirstElementByTagName(java.lang.String, coursier.util.shaded.org.jsoup.nodes.Node);
    descriptor: (Ljava/lang/String;Lcoursier/util/shaded/org/jsoup/nodes/Node;)Lcoursier/util/shaded/org/jsoup/nodes/Element;
    flags: (0x0002) ACC_PRIVATE
    Code:
      stack=4, locals=6, args_size=3
         0: aload_2
         1: invokevirtual #251                // Method coursier/util/shaded/org/jsoup/nodes/Node.nodeName:()Ljava/lang/String;
         4: aload_1
         5: invokevirtual #252                // Method java/lang/String.equals:(Ljava/lang/Object;)Z
         8: ifeq          16
        11: aload_2
        12: checkcast     #4                  // class coursier/util/shaded/org/jsoup/nodes/Element
        15: areturn
        16: aload_2
        17: invokevirtual #255                // Method coursier/util/shaded/org/jsoup/nodes/Node.childNodeSize:()I
        20: istore_3
        21: iconst_0
        22: istore        4
        24: iload         4
        26: iload_3
        27: if_icmpge     57
        30: aload_0
        31: aload_1
        32: aload_2
        33: iload         4
        35: invokevirtual #259                // Method coursier/util/shaded/org/jsoup/nodes/Node.childNode:(I)Lcoursier/util/shaded/org/jsoup/nodes/Node;
        38: invokespecial #124                // Method findFirstElementByTagName:(Ljava/lang/String;Lcoursier/util/shaded/org/jsoup/nodes/Node;)Lcoursier/util/shaded/org/jsoup/nodes/Element;
        41: astore        5
        43: aload         5
        45: ifnull        51
        48: aload         5
        50: areturn
        51: iinc          4, 1
        54: goto          24
        57: aconst_null
        58: areturn
      StackMapTable: number_of_entries = 4
        frame_type = 16 /* same */
        frame_type = 253 /* append */
          offset_delta = 7
          locals = [ int, int ]
        frame_type = 26 /* same */
        frame_type = 249 /* chop */
          offset_delta = 5
      LineNumberTable:
        line 198: 0
        line 199: 11
        line 201: 16
        line 202: 21
        line 203: 30
        line 204: 43
        line 205: 48
        line 202: 51
        line 208: 57
      LocalVariableTable:
        Start  Length  Slot  Name   Signature
           43       8     5 found   Lcoursier/util/shaded/org/jsoup/nodes/Element;
           24      33     4     i   I
           21      36     3  size   I
            0      59     0  this   Lcoursier/util/shaded/org/jsoup/nodes/Document;
            0      59     1   tag   Ljava/lang/String;
            0      59     2  node   Lcoursier/util/shaded/org/jsoup/nodes/Node;

  public java.lang.String outerHtml();
    descriptor: ()Ljava/lang/String;
    flags: (0x0001) ACC_PUBLIC
    Code:
      stack=1, locals=1, args_size=1
         0: aload_0
         1: invokespecial #263                // Method coursier/util/shaded/org/jsoup/nodes/Element.html:()Ljava/lang/String;
         4: areturn
      LineNumberTable:
        line 213: 0
      LocalVariableTable:
        Start  Length  Slot  Name   Signature
            0       5     0  this   Lcoursier/util/shaded/org/jsoup/nodes/Document;

  public coursier.util.shaded.org.jsoup.nodes.Element text(java.lang.String);
    descriptor: (Ljava/lang/String;)Lcoursier/util/shaded/org/jsoup/nodes/Element;
    flags: (0x0001) ACC_PUBLIC
    Code:
      stack=2, locals=2, args_size=2
         0: aload_0
         1: invokevirtual #170                // Method body:()Lcoursier/util/shaded/org/jsoup/nodes/Element;
         4: aload_1
         5: invokevirtual #156                // Method coursier/util/shaded/org/jsoup/nodes/Element.text:(Ljava/lang/String;)Lcoursier/util/shaded/org/jsoup/nodes/Element;
         8: pop
         9: aload_0
        10: areturn
      LineNumberTable:
        line 223: 0
        line 224: 9
      LocalVariableTable:
        Start  Length  Slot  Name   Signature
            0      11     0  this   Lcoursier/util/shaded/org/jsoup/nodes/Document;
            0      11     1  text   Ljava/lang/String;

  public java.lang.String nodeName();
    descriptor: ()Ljava/lang/String;
    flags: (0x0001) ACC_PUBLIC
    Code:
      stack=1, locals=1, args_size=1
         0: ldc_w         #265                // String #document
         3: areturn
      LineNumberTable:
        line 229: 0
      LocalVariableTable:
        Start  Length  Slot  Name   Signature
            0       4     0  this   Lcoursier/util/shaded/org/jsoup/nodes/Document;

  public void charset(java.nio.charset.Charset);
    descriptor: (Ljava/nio/charset/Charset;)V
    flags: (0x0001) ACC_PUBLIC
    Code:
      stack=2, locals=2, args_size=2
         0: aload_0
         1: iconst_1
         2: invokevirtual #271                // Method updateMetaCharsetElement:(Z)V
         5: aload_0
         6: getfield      #48                 // Field outputSettings:Lcoursier/util/shaded/org/jsoup/nodes/Document$OutputSettings;
         9: aload_1
        10: invokevirtual #274                // Method coursier/util/shaded/org/jsoup/nodes/Document$OutputSettings.charset:(Ljava/nio/charset/Charset;)Lcoursier/util/shaded/org/jsoup/nodes/Document$OutputSettings;
        13: pop
        14: aload_0
        15: invokespecial #181                // Method ensureMetaCharsetElement:()V
        18: return
      LineNumberTable:
        line 257: 0
        line 258: 5
        line 259: 14
        line 260: 18
      LocalVariableTable:
        Start  Length  Slot  Name   Signature
            0      19     0  this   Lcoursier/util/shaded/org/jsoup/nodes/Document;
            0      19     1 charset   Ljava/nio/charset/Charset;

  public java.nio.charset.Charset charset();
    descriptor: ()Ljava/nio/charset/Charset;
    flags: (0x0001) ACC_PUBLIC
    Code:
      stack=1, locals=1, args_size=1
         0: aload_0
         1: getfield      #48                 // Field outputSettings:Lcoursier/util/shaded/org/jsoup/nodes/Document$OutputSettings;
         4: invokevirtual #278                // Method coursier/util/shaded/org/jsoup/nodes/Document$OutputSettings.charset:()Ljava/nio/charset/Charset;
         7: areturn
      LineNumberTable:
        line 271: 0
      LocalVariableTable:
        Start  Length  Slot  Name   Signature
            0       8     0  this   Lcoursier/util/shaded/org/jsoup/nodes/Document;

  public void updateMetaCharsetElement(boolean);
    descriptor: (Z)V
    flags: (0x0001) ACC_PUBLIC
    Code:
      stack=2, locals=2, args_size=2
         0: aload_0
         1: iload_1
         2: putfield      #55                 // Field updateMetaCharset:Z
         5: return
      LineNumberTable:
        line 288: 0
        line 289: 5
      LocalVariableTable:
        Start  Length  Slot  Name   Signature
            0       6     0  this   Lcoursier/util/shaded/org/jsoup/nodes/Document;
            0       6     1 update   Z

  public boolean updateMetaCharsetElement();
    descriptor: ()Z
    flags: (0x0001) ACC_PUBLIC
    Code:
      stack=1, locals=1, args_size=1
         0: aload_0
         1: getfield      #55                 // Field updateMetaCharset:Z
         4: ireturn
      LineNumberTable:
        line 300: 0
      LocalVariableTable:
        Start  Length  Slot  Name   Signature
            0       5     0  this   Lcoursier/util/shaded/org/jsoup/nodes/Document;

  public coursier.util.shaded.org.jsoup.nodes.Document clone();
    descriptor: ()Lcoursier/util/shaded/org/jsoup/nodes/Document;
    flags: (0x0001) ACC_PUBLIC
    Code:
      stack=2, locals=2, args_size=1
         0: aload_0
         1: invokespecial #282                // Method coursier/util/shaded/org/jsoup/nodes/Element.clone:()Lcoursier/util/shaded/org/jsoup/nodes/Element;
         4: checkcast     #2                  // class coursier/util/shaded/org/jsoup/nodes/Document
         7: astore_1
         8: aload_1
         9: aload_0
        10: getfield      #48                 // Field outputSettings:Lcoursier/util/shaded/org/jsoup/nodes/Document$OutputSettings;
        13: invokevirtual #285                // Method coursier/util/shaded/org/jsoup/nodes/Document$OutputSettings.clone:()Lcoursier/util/shaded/org/jsoup/nodes/Document$OutputSettings;
        16: putfield      #48                 // Field outputSettings:Lcoursier/util/shaded/org/jsoup/nodes/Document$OutputSettings;
        19: aload_1
        20: areturn
      LineNumberTable:
        line 305: 0
        line 306: 8
        line 307: 19
      LocalVariableTable:
        Start  Length  Slot  Name   Signature
            0      21     0  this   Lcoursier/util/shaded/org/jsoup/nodes/Document;
            8      13     1 clone   Lcoursier/util/shaded/org/jsoup/nodes/Document;

  private void ensureMetaCharsetElement();
    descriptor: ()V
    flags: (0x0002) ACC_PRIVATE
    Code:
      stack=4, locals=5, args_size=1
         0: aload_0
         1: getfield      #55                 // Field updateMetaCharset:Z
         4: ifeq          279
         7: aload_0
         8: invokevirtual #287                // Method outputSettings:()Lcoursier/util/shaded/org/jsoup/nodes/Document$OutputSettings;
        11: invokevirtual #291                // Method coursier/util/shaded/org/jsoup/nodes/Document$OutputSettings.syntax:()Lcoursier/util/shaded/org/jsoup/nodes/Document$OutputSettings$Syntax;
        14: astore_1
        15: aload_1
        16: getstatic     #294                // Field coursier/util/shaded/org/jsoup/nodes/Document$OutputSettings$Syntax.html:Lcoursier/util/shaded/org/jsoup/nodes/Document$OutputSettings$Syntax;
        19: if_acmpne     99
        22: aload_0
        23: ldc_w         #296                // String meta[charset]
        26: invokevirtual #299                // Method select:(Ljava/lang/String;)Lcoursier/util/shaded/org/jsoup/select/Elements;
        29: invokevirtual #135                // Method coursier/util/shaded/org/jsoup/select/Elements.first:()Lcoursier/util/shaded/org/jsoup/nodes/Element;
        32: astore_2
        33: aload_2
        34: ifnull        55
        37: aload_2
        38: ldc_w         #300                // String charset
        41: aload_0
        42: invokevirtual #301                // Method charset:()Ljava/nio/charset/Charset;
        45: invokevirtual #306                // Method java/nio/charset/Charset.displayName:()Ljava/lang/String;
        48: invokevirtual #310                // Method coursier/util/shaded/org/jsoup/nodes/Element.attr:(Ljava/lang/String;Ljava/lang/String;)Lcoursier/util/shaded/org/jsoup/nodes/Element;
        51: pop
        52: goto          85
        55: aload_0
        56: invokevirtual #154                // Method head:()Lcoursier/util/shaded/org/jsoup/nodes/Element;
        59: astore_3
        60: aload_3
        61: ifnull        85
        64: aload_3
        65: ldc_w         #312                // String meta
        68: invokevirtual #84                 // Method coursier/util/shaded/org/jsoup/nodes/Element.appendElement:(Ljava/lang/String;)Lcoursier/util/shaded/org/jsoup/nodes/Element;
        71: ldc_w         #300                // String charset
        74: aload_0
        75: invokevirtual #301                // Method charset:()Ljava/nio/charset/Charset;
        78: invokevirtual #306                // Method java/nio/charset/Charset.displayName:()Ljava/lang/String;
        81: invokevirtual #310                // Method coursier/util/shaded/org/jsoup/nodes/Element.attr:(Ljava/lang/String;Ljava/lang/String;)Lcoursier/util/shaded/org/jsoup/nodes/Element;
        84: pop
        85: aload_0
        86: ldc_w         #314                // String meta[name=charset]
        89: invokevirtual #299                // Method select:(Ljava/lang/String;)Lcoursier/util/shaded/org/jsoup/select/Elements;
        92: invokevirtual #317                // Method coursier/util/shaded/org/jsoup/select/Elements.remove:()Lcoursier/util/shaded/org/jsoup/select/Elements;
        95: pop
        96: goto          279
        99: aload_1
       100: getstatic     #320                // Field coursier/util/shaded/org/jsoup/nodes/Document$OutputSettings$Syntax.xml:Lcoursier/util/shaded/org/jsoup/nodes/Document$OutputSettings$Syntax;
       103: if_acmpne     279
       106: aload_0
       107: invokevirtual #322                // Method childNodes:()Ljava/util/List;
       110: iconst_0
       111: invokeinterface #203,  2          // InterfaceMethod java/util/List.get:(I)Ljava/lang/Object;
       116: checkcast     #113                // class coursier/util/shaded/org/jsoup/nodes/Node
       119: astore_2
       120: aload_2
       121: instanceof    #324                // class coursier/util/shaded/org/jsoup/nodes/XmlDeclaration
       124: ifeq          235
       127: aload_2
       128: checkcast     #324                // class coursier/util/shaded/org/jsoup/nodes/XmlDeclaration
       131: astore_3
       132: aload_3
       133: invokevirtual #327                // Method coursier/util/shaded/org/jsoup/nodes/XmlDeclaration.name:()Ljava/lang/String;
       136: ldc_w         #328                // String xml
       139: invokevirtual #252                // Method java/lang/String.equals:(Ljava/lang/Object;)Z
       142: ifeq          188
       145: aload_3
       146: ldc_w         #330                // String encoding
       149: aload_0
       150: invokevirtual #301                // Method charset:()Ljava/nio/charset/Charset;
       153: invokevirtual #306                // Method java/nio/charset/Charset.displayName:()Ljava/lang/String;
       156: invokevirtual #333                // Method coursier/util/shaded/org/jsoup/nodes/XmlDeclaration.attr:(Ljava/lang/String;Ljava/lang/String;)Lcoursier/util/shaded/org/jsoup/nodes/Node;
       159: pop
       160: aload_3
       161: ldc_w         #335                // String version
       164: invokevirtual #337                // Method coursier/util/shaded/org/jsoup/nodes/XmlDeclaration.attr:(Ljava/lang/String;)Ljava/lang/String;
       167: astore        4
       169: aload         4
       171: ifnull        185
       174: aload_3
       175: ldc_w         #335                // String version
       178: ldc_w         #339                // String 1.0
       181: invokevirtual #333                // Method coursier/util/shaded/org/jsoup/nodes/XmlDeclaration.attr:(Ljava/lang/String;Ljava/lang/String;)Lcoursier/util/shaded/org/jsoup/nodes/Node;
       184: pop
       185: goto          232
       188: new           #324                // class coursier/util/shaded/org/jsoup/nodes/XmlDeclaration
       191: dup
       192: ldc_w         #328                // String xml
       195: iconst_0
       196: invokespecial #342                // Method coursier/util/shaded/org/jsoup/nodes/XmlDeclaration."<init>":(Ljava/lang/String;Z)V
       199: astore_3
       200: aload_3
       201: ldc_w         #335                // String version
       204: ldc_w         #339                // String 1.0
       207: invokevirtual #333                // Method coursier/util/shaded/org/jsoup/nodes/XmlDeclaration.attr:(Ljava/lang/String;Ljava/lang/String;)Lcoursier/util/shaded/org/jsoup/nodes/Node;
       210: pop
       211: aload_3
       212: ldc_w         #330                // String encoding
       215: aload_0
       216: invokevirtual #301                // Method charset:()Ljava/nio/charset/Charset;
       219: invokevirtual #306                // Method java/nio/charset/Charset.displayName:()Ljava/lang/String;
       222: invokevirtual #333                // Method coursier/util/shaded/org/jsoup/nodes/XmlDeclaration.attr:(Ljava/lang/String;Ljava/lang/String;)Lcoursier/util/shaded/org/jsoup/nodes/Node;
       225: pop
       226: aload_0
       227: aload_3
       228: invokevirtual #343                // Method prependChild:(Lcoursier/util/shaded/org/jsoup/nodes/Node;)Lcoursier/util/shaded/org/jsoup/nodes/Element;
       231: pop
       232: goto          279
       235: new           #324                // class coursier/util/shaded/org/jsoup/nodes/XmlDeclaration
       238: dup
       239: ldc_w         #328                // String xml
       242: iconst_0
       243: invokespecial #342                // Method coursier/util/shaded/org/jsoup/nodes/XmlDeclaration."<init>":(Ljava/lang/String;Z)V
       246: astore_3
       247: aload_3
       248: ldc_w         #335                // String version
       251: ldc_w         #339                // String 1.0
       254: invokevirtual #333                // Method coursier/util/shaded/org/jsoup/nodes/XmlDeclaration.attr:(Ljava/lang/String;Ljava/lang/String;)Lcoursier/util/shaded/org/jsoup/nodes/Node;
       257: pop
       258: aload_3
       259: ldc_w         #330                // String encoding
       262: aload_0
       263: invokevirtual #301                // Method charset:()Ljava/nio/charset/Charset;
       266: invokevirtual #306                // Method java/nio/charset/Charset.displayName:()Ljava/lang/String;
       269: invokevirtual #333                // Method coursier/util/shaded/org/jsoup/nodes/XmlDeclaration.attr:(Ljava/lang/String;Ljava/lang/String;)Lcoursier/util/shaded/org/jsoup/nodes/Node;
       272: pop
       273: aload_0
       274: aload_3
       275: invokevirtual #343                // Method prependChild:(Lcoursier/util/shaded/org/jsoup/nodes/Node;)Lcoursier/util/shaded/org/jsoup/nodes/Element;
       278: pop
       279: return
      StackMapTable: number_of_entries = 8
        frame_type = 253 /* append */
          offset_delta = 55
          locals = [ class coursier/util/shaded/org/jsoup/nodes/Document$OutputSettings$Syntax, class coursier/util/shaded/org/jsoup/nodes/Element ]
        frame_type = 29 /* same */
        frame_type = 250 /* chop */
          offset_delta = 13
        frame_type = 253 /* append */
          offset_delta = 85
          locals = [ class coursier/util/shaded/org/jsoup/nodes/Node, class coursier/util/shaded/org/jsoup/nodes/XmlDeclaration ]
        frame_type = 2 /* same */
        frame_type = 250 /* chop */
          offset_delta = 43
        frame_type = 2 /* same */
        frame_type = 249 /* chop */
          offset_delta = 43
      LineNumberTable:
        line 330: 0
        line 331: 7
        line 333: 15
        line 334: 22
        line 336: 33
        line 337: 37
        line 339: 55
        line 341: 60
        line 342: 64
        line 347: 85
        line 348: 96
        line 349: 106
        line 351: 120
        line 352: 127
        line 354: 132
        line 355: 145
        line 357: 160
        line 359: 169
        line 360: 174
        line 362: 185
        line 363: 188
        line 364: 200
        line 365: 211
        line 367: 226
        line 369: 232
        line 370: 235
        line 371: 247
        line 372: 258
        line 374: 273
        line 378: 279
      LocalVariableTable:
        Start  Length  Slot  Name   Signature
           60      25     3  head   Lcoursier/util/shaded/org/jsoup/nodes/Element;
           33      63     2 metaCharset   Lcoursier/util/shaded/org/jsoup/nodes/Element;
          169      16     4 version   Ljava/lang/String;
          132     100     3  decl   Lcoursier/util/shaded/org/jsoup/nodes/XmlDeclaration;
          247      32     3  decl   Lcoursier/util/shaded/org/jsoup/nodes/XmlDeclaration;
          120     159     2  node   Lcoursier/util/shaded/org/jsoup/nodes/Node;
           15     264     1 syntax   Lcoursier/util/shaded/org/jsoup/nodes/Document$OutputSettings$Syntax;
            0     280     0  this   Lcoursier/util/shaded/org/jsoup/nodes/Document;

  public coursier.util.shaded.org.jsoup.nodes.Document$OutputSettings outputSettings();
    descriptor: ()Lcoursier/util/shaded/org/jsoup/nodes/Document$OutputSettings;
    flags: (0x0001) ACC_PUBLIC
    Code:
      stack=1, locals=1, args_size=1
         0: aload_0
         1: getfield      #48                 // Field outputSettings:Lcoursier/util/shaded/org/jsoup/nodes/Document$OutputSettings;
         4: areturn
      LineNumberTable:
        line 568: 0
      LocalVariableTable:
        Start  Length  Slot  Name   Signature
            0       5     0  this   Lcoursier/util/shaded/org/jsoup/nodes/Document;

  public coursier.util.shaded.org.jsoup.nodes.Document outputSettings(coursier.util.shaded.org.jsoup.nodes.Document$OutputSettings);
    descriptor: (Lcoursier/util/shaded/org/jsoup/nodes/Document$OutputSettings;)Lcoursier/util/shaded/org/jsoup/nodes/Document;
    flags: (0x0001) ACC_PUBLIC
    Code:
      stack=2, locals=2, args_size=2
         0: aload_1
         1: invokestatic  #68                 // Method coursier/util/shaded/org/jsoup/helper/Validate.notNull:(Ljava/lang/Object;)V
         4: aload_0
         5: aload_1
         6: putfield      #48                 // Field outputSettings:Lcoursier/util/shaded/org/jsoup/nodes/Document$OutputSettings;
         9: aload_0
        10: areturn
      LineNumberTable:
        line 577: 0
        line 578: 4
        line 579: 9
      LocalVariableTable:
        Start  Length  Slot  Name   Signature
            0      11     0  this   Lcoursier/util/shaded/org/jsoup/nodes/Document;
            0      11     1 outputSettings   Lcoursier/util/shaded/org/jsoup/nodes/Document$OutputSettings;

  public coursier.util.shaded.org.jsoup.nodes.Document$QuirksMode quirksMode();
    descriptor: ()Lcoursier/util/shaded/org/jsoup/nodes/Document$QuirksMode;
    flags: (0x0001) ACC_PUBLIC
    Code:
      stack=1, locals=1, args_size=1
         0: aload_0
         1: getfield      #53                 // Field quirksMode:Lcoursier/util/shaded/org/jsoup/nodes/Document$QuirksMode;
         4: areturn
      LineNumberTable:
        line 587: 0
      LocalVariableTable:
        Start  Length  Slot  Name   Signature
            0       5     0  this   Lcoursier/util/shaded/org/jsoup/nodes/Document;

  public coursier.util.shaded.org.jsoup.nodes.Document quirksMode(coursier.util.shaded.org.jsoup.nodes.Document$QuirksMode);
    descriptor: (Lcoursier/util/shaded/org/jsoup/nodes/Document$QuirksMode;)Lcoursier/util/shaded/org/jsoup/nodes/Document;
    flags: (0x0001) ACC_PUBLIC
    Code:
      stack=2, locals=2, args_size=2
         0: aload_0
         1: aload_1
         2: putfield      #53                 // Field quirksMode:Lcoursier/util/shaded/org/jsoup/nodes/Document$QuirksMode;
         5: aload_0
         6: areturn
      LineNumberTable:
        line 591: 0
        line 592: 5
      LocalVariableTable:
        Start  Length  Slot  Name   Signature
            0       7     0  this   Lcoursier/util/shaded/org/jsoup/nodes/Document;
            0       7     1 quirksMode   Lcoursier/util/shaded/org/jsoup/nodes/Document$QuirksMode;

  public coursier.util.shaded.org.jsoup.parser.Parser parser();
    descriptor: ()Lcoursier/util/shaded/org/jsoup/parser/Parser;
    flags: (0x0001) ACC_PUBLIC
    Code:
      stack=1, locals=1, args_size=1
         0: aload_0
         1: getfield      #75                 // Field parser:Lcoursier/util/shaded/org/jsoup/parser/Parser;
         4: areturn
      LineNumberTable:
        line 600: 0
      LocalVariableTable:
        Start  Length  Slot  Name   Signature
            0       5     0  this   Lcoursier/util/shaded/org/jsoup/nodes/Document;

  public coursier.util.shaded.org.jsoup.nodes.Document parser(coursier.util.shaded.org.jsoup.parser.Parser);
    descriptor: (Lcoursier/util/shaded/org/jsoup/parser/Parser;)Lcoursier/util/shaded/org/jsoup/nodes/Document;
    flags: (0x0001) ACC_PUBLIC
    Code:
      stack=2, locals=2, args_size=2
         0: aload_0
         1: aload_1
         2: putfield      #75                 // Field parser:Lcoursier/util/shaded/org/jsoup/parser/Parser;
         5: aload_0
         6: areturn
      LineNumberTable:
        line 610: 0
        line 611: 5
      LocalVariableTable:
        Start  Length  Slot  Name   Signature
            0       7     0  this   Lcoursier/util/shaded/org/jsoup/nodes/Document;
            0       7     1 parser   Lcoursier/util/shaded/org/jsoup/parser/Parser;

  public coursier.util.shaded.org.jsoup.nodes.Element clone();
    descriptor: ()Lcoursier/util/shaded/org/jsoup/nodes/Element;
    flags: (0x1041) ACC_PUBLIC, ACC_BRIDGE, ACC_SYNTHETIC
    Code:
      stack=1, locals=1, args_size=1
         0: aload_0
         1: invokevirtual #352                // Method clone:()Lcoursier/util/shaded/org/jsoup/nodes/Document;
         4: areturn
      LineNumberTable:
        line 19: 0
      LocalVariableTable:
        Start  Length  Slot  Name   Signature
            0       5     0  this   Lcoursier/util/shaded/org/jsoup/nodes/Document;

  public coursier.util.shaded.org.jsoup.nodes.Node clone();
    descriptor: ()Lcoursier/util/shaded/org/jsoup/nodes/Node;
    flags: (0x1041) ACC_PUBLIC, ACC_BRIDGE, ACC_SYNTHETIC
    Code:
      stack=1, locals=1, args_size=1
         0: aload_0
         1: invokevirtual #352                // Method clone:()Lcoursier/util/shaded/org/jsoup/nodes/Document;
         4: areturn
      LineNumberTable:
        line 19: 0
      LocalVariableTable:
        Start  Length  Slot  Name   Signature
            0       5     0  this   Lcoursier/util/shaded/org/jsoup/nodes/Document;

  public java.lang.Object clone() throws java.lang.CloneNotSupportedException;
    descriptor: ()Ljava/lang/Object;
    flags: (0x1041) ACC_PUBLIC, ACC_BRIDGE, ACC_SYNTHETIC
    Code:
      stack=1, locals=1, args_size=1
         0: aload_0
         1: invokevirtual #352                // Method clone:()Lcoursier/util/shaded/org/jsoup/nodes/Document;
         4: areturn
      LineNumberTable:
        line 19: 0
      LocalVariableTable:
        Start  Length  Slot  Name   Signature
            0       5     0  this   Lcoursier/util/shaded/org/jsoup/nodes/Document;
    Exceptions:
      throws java.lang.CloneNotSupportedException
}
InnerClasses:
  public static #8= #7 of #2;             // OutputSettings=class coursier/util/shaded/org/jsoup/nodes/Document$OutputSettings of class coursier/util/shaded/org/jsoup/nodes/Document
  public static final #11= #10 of #2;     // QuirksMode=class coursier/util/shaded/org/jsoup/nodes/Document$QuirksMode of class coursier/util/shaded/org/jsoup/nodes/Document
  public static final #14= #13 of #7;     // Syntax=class coursier/util/shaded/org/jsoup/nodes/Document$OutputSettings$Syntax of class coursier/util/shaded/org/jsoup/nodes/Document$OutputSettings
SourceFile: "Document.java"
