Classfile /Users/mw/Projects/slang-braindump/.jar/jar8/assemble/slang-braindump/assemble/content/coursier/util/shaded/org/jsoup/nodes/DocumentType.class
  Last modified May 29, 2022; size 3959 bytes
  SHA-256 checksum 44b106b1a4202b21bcff02a4866d20f64a9457f774ad01c7d3506aa77d06c48a
  Compiled from "DocumentType.java"
public class coursier.util.shaded.org.jsoup.nodes.DocumentType extends coursier.util.shaded.org.jsoup.nodes.LeafNode
  minor version: 0
  major version: 51
  flags: (0x0021) ACC_PUBLIC, ACC_SUPER
  this_class: #2                          // coursier/util/shaded/org/jsoup/nodes/DocumentType
  super_class: #4                         // coursier/util/shaded/org/jsoup/nodes/LeafNode
  interfaces: 0, fields: 6, methods: 18, attributes: 2
Constant pool:
    #1 = Utf8               coursier/util/shaded/org/jsoup/nodes/DocumentType
    #2 = Class              #1            // coursier/util/shaded/org/jsoup/nodes/DocumentType
    #3 = Utf8               coursier/util/shaded/org/jsoup/nodes/LeafNode
    #4 = Class              #3            // coursier/util/shaded/org/jsoup/nodes/LeafNode
    #5 = Utf8               DocumentType.java
    #6 = Utf8               coursier/util/shaded/org/jsoup/nodes/Document$OutputSettings
    #7 = Class              #6            // coursier/util/shaded/org/jsoup/nodes/Document$OutputSettings
    #8 = Utf8               coursier/util/shaded/org/jsoup/nodes/Document
    #9 = Class              #8            // coursier/util/shaded/org/jsoup/nodes/Document
   #10 = Utf8               OutputSettings
   #11 = Utf8               coursier/util/shaded/org/jsoup/nodes/Document$OutputSettings$Syntax
   #12 = Class              #11           // coursier/util/shaded/org/jsoup/nodes/Document$OutputSettings$Syntax
   #13 = Utf8               Syntax
   #14 = Utf8               PUBLIC_KEY
   #15 = Utf8               Ljava/lang/String;
   #16 = Utf8               PUBLIC
   #17 = String             #16           // PUBLIC
   #18 = Utf8               SYSTEM_KEY
   #19 = Utf8               SYSTEM
   #20 = String             #19           // SYSTEM
   #21 = Utf8               NAME
   #22 = Utf8               name
   #23 = String             #22           // name
   #24 = Utf8               PUB_SYS_KEY
   #25 = Utf8               pubSysKey
   #26 = String             #25           // pubSysKey
   #27 = Utf8               PUBLIC_ID
   #28 = Utf8               publicId
   #29 = String             #28           // publicId
   #30 = Utf8               SYSTEM_ID
   #31 = Utf8               systemId
   #32 = String             #31           // systemId
   #33 = Utf8               <init>
   #34 = Utf8               (Ljava/lang/String;Ljava/lang/String;Ljava/lang/String;)V
   #35 = Utf8               ()V
   #36 = NameAndType        #33:#35       // "<init>":()V
   #37 = Methodref          #4.#36        // coursier/util/shaded/org/jsoup/nodes/LeafNode."<init>":()V
   #38 = Utf8               coursier/util/shaded/org/jsoup/helper/Validate
   #39 = Class              #38           // coursier/util/shaded/org/jsoup/helper/Validate
   #40 = Utf8               notNull
   #41 = Utf8               (Ljava/lang/Object;)V
   #42 = NameAndType        #40:#41       // notNull:(Ljava/lang/Object;)V
   #43 = Methodref          #39.#42       // coursier/util/shaded/org/jsoup/helper/Validate.notNull:(Ljava/lang/Object;)V
   #44 = Utf8               attr
   #45 = Utf8               (Ljava/lang/String;Ljava/lang/String;)Lcoursier/util/shaded/org/jsoup/nodes/Node;
   #46 = NameAndType        #44:#45       // attr:(Ljava/lang/String;Ljava/lang/String;)Lcoursier/util/shaded/org/jsoup/nodes/Node;
   #47 = Methodref          #2.#46        // coursier/util/shaded/org/jsoup/nodes/DocumentType.attr:(Ljava/lang/String;Ljava/lang/String;)Lcoursier/util/shaded/org/jsoup/nodes/Node;
   #48 = Utf8               updatePubSyskey
   #49 = NameAndType        #48:#35       // updatePubSyskey:()V
   #50 = Methodref          #2.#49        // coursier/util/shaded/org/jsoup/nodes/DocumentType.updatePubSyskey:()V
   #51 = Utf8               this
   #52 = Utf8               Lcoursier/util/shaded/org/jsoup/nodes/DocumentType;
   #53 = Utf8               setPubSysKey
   #54 = Utf8               (Ljava/lang/String;)V
   #55 = Utf8               value
   #56 = Utf8               has
   #57 = Utf8               (Ljava/lang/String;)Z
   #58 = NameAndType        #56:#57       // has:(Ljava/lang/String;)Z
   #59 = Methodref          #2.#58        // coursier/util/shaded/org/jsoup/nodes/DocumentType.has:(Ljava/lang/String;)Z
   #60 = Utf8               ()Ljava/lang/String;
   #61 = Utf8               (Ljava/lang/String;)Ljava/lang/String;
   #62 = NameAndType        #44:#61       // attr:(Ljava/lang/String;)Ljava/lang/String;
   #63 = Methodref          #2.#62        // coursier/util/shaded/org/jsoup/nodes/DocumentType.attr:(Ljava/lang/String;)Ljava/lang/String;
   #64 = Utf8               nodeName
   #65 = Utf8               #doctype
   #66 = String             #65           // #doctype
   #67 = Utf8               outerHtmlHead
   #68 = Utf8               (Ljava/lang/Appendable;ILcoursier/util/shaded/org/jsoup/nodes/Document$OutputSettings;)V
   #69 = Utf8               java/io/IOException
   #70 = Class              #69           // java/io/IOException
   #71 = Utf8               syntax
   #72 = Utf8               ()Lcoursier/util/shaded/org/jsoup/nodes/Document$OutputSettings$Syntax;
   #73 = NameAndType        #71:#72       // syntax:()Lcoursier/util/shaded/org/jsoup/nodes/Document$OutputSettings$Syntax;
   #74 = Methodref          #7.#73        // coursier/util/shaded/org/jsoup/nodes/Document$OutputSettings.syntax:()Lcoursier/util/shaded/org/jsoup/nodes/Document$OutputSettings$Syntax;
   #75 = Utf8               html
   #76 = Utf8               Lcoursier/util/shaded/org/jsoup/nodes/Document$OutputSettings$Syntax;
   #77 = NameAndType        #75:#76       // html:Lcoursier/util/shaded/org/jsoup/nodes/Document$OutputSettings$Syntax;
   #78 = Fieldref           #12.#77       // coursier/util/shaded/org/jsoup/nodes/Document$OutputSettings$Syntax.html:Lcoursier/util/shaded/org/jsoup/nodes/Document$OutputSettings$Syntax;
   #79 = Utf8               <!doctype
   #80 = String             #79           // <!doctype
   #81 = Utf8               java/lang/Appendable
   #82 = Class              #81           // java/lang/Appendable
   #83 = Utf8               append
   #84 = Utf8               (Ljava/lang/CharSequence;)Ljava/lang/Appendable;
   #85 = NameAndType        #83:#84       // append:(Ljava/lang/CharSequence;)Ljava/lang/Appendable;
   #86 = InterfaceMethodref #82.#85       // java/lang/Appendable.append:(Ljava/lang/CharSequence;)Ljava/lang/Appendable;
   #87 = Utf8               <!DOCTYPE
   #88 = String             #87           // <!DOCTYPE
   #89 = Utf8
   #90 = String             #89           //
   #91 = Utf8                \"
   #92 = String             #91           //  \"
   #93 = Utf8               (C)Ljava/lang/Appendable;
   #94 = NameAndType        #83:#93       // append:(C)Ljava/lang/Appendable;
   #95 = InterfaceMethodref #82.#94       // java/lang/Appendable.append:(C)Ljava/lang/Appendable;
   #96 = Utf8               accum
   #97 = Utf8               Ljava/lang/Appendable;
   #98 = Utf8               depth
   #99 = Utf8               I
  #100 = Utf8               out
  #101 = Utf8               Lcoursier/util/shaded/org/jsoup/nodes/Document$OutputSettings;
  #102 = Utf8               outerHtmlTail
  #103 = Utf8               coursier/util/shaded/org/jsoup/internal/StringUtil
  #104 = Class              #103          // coursier/util/shaded/org/jsoup/internal/StringUtil
  #105 = Utf8               isBlank
  #106 = NameAndType        #105:#57      // isBlank:(Ljava/lang/String;)Z
  #107 = Methodref          #104.#106     // coursier/util/shaded/org/jsoup/internal/StringUtil.isBlank:(Ljava/lang/String;)Z
  #108 = Utf8               attribute
  #109 = Utf8               empty
  #110 = Utf8               ()Lcoursier/util/shaded/org/jsoup/nodes/Node;
  #111 = NameAndType        #109:#110     // empty:()Lcoursier/util/shaded/org/jsoup/nodes/Node;
  #112 = Methodref          #4.#111       // coursier/util/shaded/org/jsoup/nodes/LeafNode.empty:()Lcoursier/util/shaded/org/jsoup/nodes/Node;
  #113 = Utf8               childNodeSize
  #114 = Utf8               ()I
  #115 = NameAndType        #113:#114     // childNodeSize:()I
  #116 = Methodref          #4.#115       // coursier/util/shaded/org/jsoup/nodes/LeafNode.childNodeSize:()I
  #117 = Utf8               baseUri
  #118 = NameAndType        #117:#60      // baseUri:()Ljava/lang/String;
  #119 = Methodref          #4.#118       // coursier/util/shaded/org/jsoup/nodes/LeafNode.baseUri:()Ljava/lang/String;
  #120 = Utf8               absUrl
  #121 = NameAndType        #120:#61      // absUrl:(Ljava/lang/String;)Ljava/lang/String;
  #122 = Methodref          #4.#121       // coursier/util/shaded/org/jsoup/nodes/LeafNode.absUrl:(Ljava/lang/String;)Ljava/lang/String;
  #123 = Utf8               removeAttr
  #124 = Utf8               (Ljava/lang/String;)Lcoursier/util/shaded/org/jsoup/nodes/Node;
  #125 = NameAndType        #123:#124     // removeAttr:(Ljava/lang/String;)Lcoursier/util/shaded/org/jsoup/nodes/Node;
  #126 = Methodref          #4.#125       // coursier/util/shaded/org/jsoup/nodes/LeafNode.removeAttr:(Ljava/lang/String;)Lcoursier/util/shaded/org/jsoup/nodes/Node;
  #127 = Utf8               hasAttr
  #128 = NameAndType        #127:#57      // hasAttr:(Ljava/lang/String;)Z
  #129 = Methodref          #4.#128       // coursier/util/shaded/org/jsoup/nodes/LeafNode.hasAttr:(Ljava/lang/String;)Z
  #130 = Methodref          #4.#46        // coursier/util/shaded/org/jsoup/nodes/LeafNode.attr:(Ljava/lang/String;Ljava/lang/String;)Lcoursier/util/shaded/org/jsoup/nodes/Node;
  #131 = Methodref          #4.#62        // coursier/util/shaded/org/jsoup/nodes/LeafNode.attr:(Ljava/lang/String;)Ljava/lang/String;
  #132 = Utf8               ConstantValue
  #133 = Utf8               Code
  #134 = Utf8               LineNumberTable
  #135 = Utf8               LocalVariableTable
  #136 = Utf8               StackMapTable
  #137 = Utf8               Exceptions
  #138 = Utf8               InnerClasses
  #139 = Utf8               SourceFile
{
  public static final java.lang.String PUBLIC_KEY;
    descriptor: Ljava/lang/String;
    flags: (0x0019) ACC_PUBLIC, ACC_STATIC, ACC_FINAL
    ConstantValue: String PUBLIC

  public static final java.lang.String SYSTEM_KEY;
    descriptor: Ljava/lang/String;
    flags: (0x0019) ACC_PUBLIC, ACC_STATIC, ACC_FINAL
    ConstantValue: String SYSTEM

  private static final java.lang.String NAME;
    descriptor: Ljava/lang/String;
    flags: (0x001a) ACC_PRIVATE, ACC_STATIC, ACC_FINAL
    ConstantValue: String name

  private static final java.lang.String PUB_SYS_KEY;
    descriptor: Ljava/lang/String;
    flags: (0x001a) ACC_PRIVATE, ACC_STATIC, ACC_FINAL
    ConstantValue: String pubSysKey

  private static final java.lang.String PUBLIC_ID;
    descriptor: Ljava/lang/String;
    flags: (0x001a) ACC_PRIVATE, ACC_STATIC, ACC_FINAL
    ConstantValue: String publicId

  private static final java.lang.String SYSTEM_ID;
    descriptor: Ljava/lang/String;
    flags: (0x001a) ACC_PRIVATE, ACC_STATIC, ACC_FINAL
    ConstantValue: String systemId

  public coursier.util.shaded.org.jsoup.nodes.DocumentType(java.lang.String, java.lang.String, java.lang.String);
    descriptor: (Ljava/lang/String;Ljava/lang/String;Ljava/lang/String;)V
    flags: (0x0001) ACC_PUBLIC
    Code:
      stack=3, locals=4, args_size=4
         0: aload_0
         1: invokespecial #37                 // Method coursier/util/shaded/org/jsoup/nodes/LeafNode."<init>":()V
         4: aload_1
         5: invokestatic  #43                 // Method coursier/util/shaded/org/jsoup/helper/Validate.notNull:(Ljava/lang/Object;)V
         8: aload_2
         9: invokestatic  #43                 // Method coursier/util/shaded/org/jsoup/helper/Validate.notNull:(Ljava/lang/Object;)V
        12: aload_3
        13: invokestatic  #43                 // Method coursier/util/shaded/org/jsoup/helper/Validate.notNull:(Ljava/lang/Object;)V
        16: aload_0
        17: ldc           #23                 // String name
        19: aload_1
        20: invokevirtual #47                 // Method attr:(Ljava/lang/String;Ljava/lang/String;)Lcoursier/util/shaded/org/jsoup/nodes/Node;
        23: pop
        24: aload_0
        25: ldc           #29                 // String publicId
        27: aload_2
        28: invokevirtual #47                 // Method attr:(Ljava/lang/String;Ljava/lang/String;)Lcoursier/util/shaded/org/jsoup/nodes/Node;
        31: pop
        32: aload_0
        33: ldc           #32                 // String systemId
        35: aload_3
        36: invokevirtual #47                 // Method attr:(Ljava/lang/String;Ljava/lang/String;)Lcoursier/util/shaded/org/jsoup/nodes/Node;
        39: pop
        40: aload_0
        41: invokespecial #50                 // Method updatePubSyskey:()V
        44: return
      LineNumberTable:
        line 28: 0
        line 29: 4
        line 30: 8
        line 31: 12
        line 32: 16
        line 33: 24
        line 34: 32
        line 35: 40
        line 36: 44
      LocalVariableTable:
        Start  Length  Slot  Name   Signature
            0      45     0  this   Lcoursier/util/shaded/org/jsoup/nodes/DocumentType;
            0      45     1  name   Ljava/lang/String;
            0      45     2 publicId   Ljava/lang/String;
            0      45     3 systemId   Ljava/lang/String;

  public void setPubSysKey(java.lang.String);
    descriptor: (Ljava/lang/String;)V
    flags: (0x0001) ACC_PUBLIC
    Code:
      stack=3, locals=2, args_size=2
         0: aload_1
         1: ifnull        12
         4: aload_0
         5: ldc           #26                 // String pubSysKey
         7: aload_1
         8: invokevirtual #47                 // Method attr:(Ljava/lang/String;Ljava/lang/String;)Lcoursier/util/shaded/org/jsoup/nodes/Node;
        11: pop
        12: return
      StackMapTable: number_of_entries = 1
        frame_type = 12 /* same */
      LineNumberTable:
        line 39: 0
        line 40: 4
        line 41: 12
      LocalVariableTable:
        Start  Length  Slot  Name   Signature
            0      13     0  this   Lcoursier/util/shaded/org/jsoup/nodes/DocumentType;
            0      13     1 value   Ljava/lang/String;

  private void updatePubSyskey();
    descriptor: ()V
    flags: (0x0002) ACC_PRIVATE
    Code:
      stack=3, locals=1, args_size=1
         0: aload_0
         1: ldc           #29                 // String publicId
         3: invokespecial #59                 // Method has:(Ljava/lang/String;)Z
         6: ifeq          21
         9: aload_0
        10: ldc           #26                 // String pubSysKey
        12: ldc           #17                 // String PUBLIC
        14: invokevirtual #47                 // Method attr:(Ljava/lang/String;Ljava/lang/String;)Lcoursier/util/shaded/org/jsoup/nodes/Node;
        17: pop
        18: goto          39
        21: aload_0
        22: ldc           #32                 // String systemId
        24: invokespecial #59                 // Method has:(Ljava/lang/String;)Z
        27: ifeq          39
        30: aload_0
        31: ldc           #26                 // String pubSysKey
        33: ldc           #20                 // String SYSTEM
        35: invokevirtual #47                 // Method attr:(Ljava/lang/String;Ljava/lang/String;)Lcoursier/util/shaded/org/jsoup/nodes/Node;
        38: pop
        39: return
      StackMapTable: number_of_entries = 2
        frame_type = 21 /* same */
        frame_type = 17 /* same */
      LineNumberTable:
        line 44: 0
        line 45: 9
        line 46: 21
        line 47: 30
        line 48: 39
      LocalVariableTable:
        Start  Length  Slot  Name   Signature
            0      40     0  this   Lcoursier/util/shaded/org/jsoup/nodes/DocumentType;

  public java.lang.String name();
    descriptor: ()Ljava/lang/String;
    flags: (0x0001) ACC_PUBLIC
    Code:
      stack=2, locals=1, args_size=1
         0: aload_0
         1: ldc           #23                 // String name
         3: invokevirtual #63                 // Method attr:(Ljava/lang/String;)Ljava/lang/String;
         6: areturn
      LineNumberTable:
        line 55: 0
      LocalVariableTable:
        Start  Length  Slot  Name   Signature
            0       7     0  this   Lcoursier/util/shaded/org/jsoup/nodes/DocumentType;

  public java.lang.String publicId();
    descriptor: ()Ljava/lang/String;
    flags: (0x0001) ACC_PUBLIC
    Code:
      stack=2, locals=1, args_size=1
         0: aload_0
         1: ldc           #29                 // String publicId
         3: invokevirtual #63                 // Method attr:(Ljava/lang/String;)Ljava/lang/String;
         6: areturn
      LineNumberTable:
        line 63: 0
      LocalVariableTable:
        Start  Length  Slot  Name   Signature
            0       7     0  this   Lcoursier/util/shaded/org/jsoup/nodes/DocumentType;

  public java.lang.String systemId();
    descriptor: ()Ljava/lang/String;
    flags: (0x0001) ACC_PUBLIC
    Code:
      stack=2, locals=1, args_size=1
         0: aload_0
         1: ldc           #32                 // String systemId
         3: invokevirtual #63                 // Method attr:(Ljava/lang/String;)Ljava/lang/String;
         6: areturn
      LineNumberTable:
        line 71: 0
      LocalVariableTable:
        Start  Length  Slot  Name   Signature
            0       7     0  this   Lcoursier/util/shaded/org/jsoup/nodes/DocumentType;

  public java.lang.String nodeName();
    descriptor: ()Ljava/lang/String;
    flags: (0x0001) ACC_PUBLIC
    Code:
      stack=1, locals=1, args_size=1
         0: ldc           #66                 // String #doctype
         2: areturn
      LineNumberTable:
        line 76: 0
      LocalVariableTable:
        Start  Length  Slot  Name   Signature
            0       3     0  this   Lcoursier/util/shaded/org/jsoup/nodes/DocumentType;

  void outerHtmlHead(java.lang.Appendable, int, coursier.util.shaded.org.jsoup.nodes.Document$OutputSettings) throws java.io.IOException;
    descriptor: (Ljava/lang/Appendable;ILcoursier/util/shaded/org/jsoup/nodes/Document$OutputSettings;)V
    flags: (0x0000)
    Code:
      stack=3, locals=4, args_size=4
         0: aload_3
         1: invokevirtual #74                 // Method coursier/util/shaded/org/jsoup/nodes/Document$OutputSettings.syntax:()Lcoursier/util/shaded/org/jsoup/nodes/Document$OutputSettings$Syntax;
         4: getstatic     #78                 // Field coursier/util/shaded/org/jsoup/nodes/Document$OutputSettings$Syntax.html:Lcoursier/util/shaded/org/jsoup/nodes/Document$OutputSettings$Syntax;
         7: if_acmpne     40
        10: aload_0
        11: ldc           #29                 // String publicId
        13: invokespecial #59                 // Method has:(Ljava/lang/String;)Z
        16: ifne          40
        19: aload_0
        20: ldc           #32                 // String systemId
        22: invokespecial #59                 // Method has:(Ljava/lang/String;)Z
        25: ifne          40
        28: aload_1
        29: ldc           #80                 // String <!doctype
        31: invokeinterface #86,  2           // InterfaceMethod java/lang/Appendable.append:(Ljava/lang/CharSequence;)Ljava/lang/Appendable;
        36: pop
        37: goto          49
        40: aload_1
        41: ldc           #88                 // String <!DOCTYPE
        43: invokeinterface #86,  2           // InterfaceMethod java/lang/Appendable.append:(Ljava/lang/CharSequence;)Ljava/lang/Appendable;
        48: pop
        49: aload_0
        50: ldc           #23                 // String name
        52: invokespecial #59                 // Method has:(Ljava/lang/String;)Z
        55: ifeq          78
        58: aload_1
        59: ldc           #90                 // String
        61: invokeinterface #86,  2           // InterfaceMethod java/lang/Appendable.append:(Ljava/lang/CharSequence;)Ljava/lang/Appendable;
        66: aload_0
        67: ldc           #23                 // String name
        69: invokevirtual #63                 // Method attr:(Ljava/lang/String;)Ljava/lang/String;
        72: invokeinterface #86,  2           // InterfaceMethod java/lang/Appendable.append:(Ljava/lang/CharSequence;)Ljava/lang/Appendable;
        77: pop
        78: aload_0
        79: ldc           #26                 // String pubSysKey
        81: invokespecial #59                 // Method has:(Ljava/lang/String;)Z
        84: ifeq          107
        87: aload_1
        88: ldc           #90                 // String
        90: invokeinterface #86,  2           // InterfaceMethod java/lang/Appendable.append:(Ljava/lang/CharSequence;)Ljava/lang/Appendable;
        95: aload_0
        96: ldc           #26                 // String pubSysKey
        98: invokevirtual #63                 // Method attr:(Ljava/lang/String;)Ljava/lang/String;
       101: invokeinterface #86,  2           // InterfaceMethod java/lang/Appendable.append:(Ljava/lang/CharSequence;)Ljava/lang/Appendable;
       106: pop
       107: aload_0
       108: ldc           #29                 // String publicId
       110: invokespecial #59                 // Method has:(Ljava/lang/String;)Z
       113: ifeq          143
       116: aload_1
       117: ldc           #92                 // String  \"
       119: invokeinterface #86,  2           // InterfaceMethod java/lang/Appendable.append:(Ljava/lang/CharSequence;)Ljava/lang/Appendable;
       124: aload_0
       125: ldc           #29                 // String publicId
       127: invokevirtual #63                 // Method attr:(Ljava/lang/String;)Ljava/lang/String;
       130: invokeinterface #86,  2           // InterfaceMethod java/lang/Appendable.append:(Ljava/lang/CharSequence;)Ljava/lang/Appendable;
       135: bipush        34
       137: invokeinterface #95,  2           // InterfaceMethod java/lang/Appendable.append:(C)Ljava/lang/Appendable;
       142: pop
       143: aload_0
       144: ldc           #32                 // String systemId
       146: invokespecial #59                 // Method has:(Ljava/lang/String;)Z
       149: ifeq          179
       152: aload_1
       153: ldc           #92                 // String  \"
       155: invokeinterface #86,  2           // InterfaceMethod java/lang/Appendable.append:(Ljava/lang/CharSequence;)Ljava/lang/Appendable;
       160: aload_0
       161: ldc           #32                 // String systemId
       163: invokevirtual #63                 // Method attr:(Ljava/lang/String;)Ljava/lang/String;
       166: invokeinterface #86,  2           // InterfaceMethod java/lang/Appendable.append:(Ljava/lang/CharSequence;)Ljava/lang/Appendable;
       171: bipush        34
       173: invokeinterface #95,  2           // InterfaceMethod java/lang/Appendable.append:(C)Ljava/lang/Appendable;
       178: pop
       179: aload_1
       180: bipush        62
       182: invokeinterface #95,  2           // InterfaceMethod java/lang/Appendable.append:(C)Ljava/lang/Appendable;
       187: pop
       188: return
      StackMapTable: number_of_entries = 6
        frame_type = 40 /* same */
        frame_type = 8 /* same */
        frame_type = 28 /* same */
        frame_type = 28 /* same */
        frame_type = 35 /* same */
        frame_type = 35 /* same */
      LineNumberTable:
        line 81: 0
        line 83: 28
        line 85: 40
        line 87: 49
        line 88: 58
        line 89: 78
        line 90: 87
        line 91: 107
        line 92: 116
        line 93: 143
        line 94: 152
        line 95: 179
        line 96: 188
      LocalVariableTable:
        Start  Length  Slot  Name   Signature
            0     189     0  this   Lcoursier/util/shaded/org/jsoup/nodes/DocumentType;
            0     189     1 accum   Ljava/lang/Appendable;
            0     189     2 depth   I
            0     189     3   out   Lcoursier/util/shaded/org/jsoup/nodes/Document$OutputSettings;
    Exceptions:
      throws java.io.IOException

  void outerHtmlTail(java.lang.Appendable, int, coursier.util.shaded.org.jsoup.nodes.Document$OutputSettings);
    descriptor: (Ljava/lang/Appendable;ILcoursier/util/shaded/org/jsoup/nodes/Document$OutputSettings;)V
    flags: (0x0000)
    Code:
      stack=0, locals=4, args_size=4
         0: return
      LineNumberTable:
        line 100: 0
      LocalVariableTable:
        Start  Length  Slot  Name   Signature
            0       1     0  this   Lcoursier/util/shaded/org/jsoup/nodes/DocumentType;
            0       1     1 accum   Ljava/lang/Appendable;
            0       1     2 depth   I
            0       1     3   out   Lcoursier/util/shaded/org/jsoup/nodes/Document$OutputSettings;

  private boolean has(java.lang.String);
    descriptor: (Ljava/lang/String;)Z
    flags: (0x0002) ACC_PRIVATE
    Code:
      stack=2, locals=2, args_size=2
         0: aload_0
         1: aload_1
         2: invokevirtual #63                 // Method attr:(Ljava/lang/String;)Ljava/lang/String;
         5: invokestatic  #107                // Method coursier/util/shaded/org/jsoup/internal/StringUtil.isBlank:(Ljava/lang/String;)Z
         8: ifne          15
        11: iconst_1
        12: goto          16
        15: iconst_0
        16: ireturn
      StackMapTable: number_of_entries = 2
        frame_type = 15 /* same */
        frame_type = 64 /* same_locals_1_stack_item */
          stack = [ int ]
      LineNumberTable:
        line 103: 0
      LocalVariableTable:
        Start  Length  Slot  Name   Signature
            0      17     0  this   Lcoursier/util/shaded/org/jsoup/nodes/DocumentType;
            0      17     1 attribute   Ljava/lang/String;

  public coursier.util.shaded.org.jsoup.nodes.Node empty();
    descriptor: ()Lcoursier/util/shaded/org/jsoup/nodes/Node;
    flags: (0x1041) ACC_PUBLIC, ACC_BRIDGE, ACC_SYNTHETIC
    Code:
      stack=1, locals=1, args_size=1
         0: aload_0
         1: invokespecial #112                // Method coursier/util/shaded/org/jsoup/nodes/LeafNode.empty:()Lcoursier/util/shaded/org/jsoup/nodes/Node;
         4: areturn
      LineNumberTable:
        line 12: 0
      LocalVariableTable:
        Start  Length  Slot  Name   Signature
            0       5     0  this   Lcoursier/util/shaded/org/jsoup/nodes/DocumentType;

  public int childNodeSize();
    descriptor: ()I
    flags: (0x1041) ACC_PUBLIC, ACC_BRIDGE, ACC_SYNTHETIC
    Code:
      stack=1, locals=1, args_size=1
         0: aload_0
         1: invokespecial #116                // Method coursier/util/shaded/org/jsoup/nodes/LeafNode.childNodeSize:()I
         4: ireturn
      LineNumberTable:
        line 12: 0
      LocalVariableTable:
        Start  Length  Slot  Name   Signature
            0       5     0  this   Lcoursier/util/shaded/org/jsoup/nodes/DocumentType;

  public java.lang.String baseUri();
    descriptor: ()Ljava/lang/String;
    flags: (0x1041) ACC_PUBLIC, ACC_BRIDGE, ACC_SYNTHETIC
    Code:
      stack=1, locals=1, args_size=1
         0: aload_0
         1: invokespecial #119                // Method coursier/util/shaded/org/jsoup/nodes/LeafNode.baseUri:()Ljava/lang/String;
         4: areturn
      LineNumberTable:
        line 12: 0
      LocalVariableTable:
        Start  Length  Slot  Name   Signature
            0       5     0  this   Lcoursier/util/shaded/org/jsoup/nodes/DocumentType;

  public java.lang.String absUrl(java.lang.String);
    descriptor: (Ljava/lang/String;)Ljava/lang/String;
    flags: (0x1041) ACC_PUBLIC, ACC_BRIDGE, ACC_SYNTHETIC
    Code:
      stack=2, locals=2, args_size=2
         0: aload_0
         1: aload_1
         2: invokespecial #122                // Method coursier/util/shaded/org/jsoup/nodes/LeafNode.absUrl:(Ljava/lang/String;)Ljava/lang/String;
         5: areturn
      LineNumberTable:
        line 12: 0
      LocalVariableTable:
        Start  Length  Slot  Name   Signature
            0       6     0  this   Lcoursier/util/shaded/org/jsoup/nodes/DocumentType;

  public coursier.util.shaded.org.jsoup.nodes.Node removeAttr(java.lang.String);
    descriptor: (Ljava/lang/String;)Lcoursier/util/shaded/org/jsoup/nodes/Node;
    flags: (0x1041) ACC_PUBLIC, ACC_BRIDGE, ACC_SYNTHETIC
    Code:
      stack=2, locals=2, args_size=2
         0: aload_0
         1: aload_1
         2: invokespecial #126                // Method coursier/util/shaded/org/jsoup/nodes/LeafNode.removeAttr:(Ljava/lang/String;)Lcoursier/util/shaded/org/jsoup/nodes/Node;
         5: areturn
      LineNumberTable:
        line 12: 0
      LocalVariableTable:
        Start  Length  Slot  Name   Signature
            0       6     0  this   Lcoursier/util/shaded/org/jsoup/nodes/DocumentType;

  public boolean hasAttr(java.lang.String);
    descriptor: (Ljava/lang/String;)Z
    flags: (0x1041) ACC_PUBLIC, ACC_BRIDGE, ACC_SYNTHETIC
    Code:
      stack=2, locals=2, args_size=2
         0: aload_0
         1: aload_1
         2: invokespecial #129                // Method coursier/util/shaded/org/jsoup/nodes/LeafNode.hasAttr:(Ljava/lang/String;)Z
         5: ireturn
      LineNumberTable:
        line 12: 0
      LocalVariableTable:
        Start  Length  Slot  Name   Signature
            0       6     0  this   Lcoursier/util/shaded/org/jsoup/nodes/DocumentType;

  public coursier.util.shaded.org.jsoup.nodes.Node attr(java.lang.String, java.lang.String);
    descriptor: (Ljava/lang/String;Ljava/lang/String;)Lcoursier/util/shaded/org/jsoup/nodes/Node;
    flags: (0x1041) ACC_PUBLIC, ACC_BRIDGE, ACC_SYNTHETIC
    Code:
      stack=3, locals=3, args_size=3
         0: aload_0
         1: aload_1
         2: aload_2
         3: invokespecial #130                // Method coursier/util/shaded/org/jsoup/nodes/LeafNode.attr:(Ljava/lang/String;Ljava/lang/String;)Lcoursier/util/shaded/org/jsoup/nodes/Node;
         6: areturn
      LineNumberTable:
        line 12: 0
      LocalVariableTable:
        Start  Length  Slot  Name   Signature
            0       7     0  this   Lcoursier/util/shaded/org/jsoup/nodes/DocumentType;

  public java.lang.String attr(java.lang.String);
    descriptor: (Ljava/lang/String;)Ljava/lang/String;
    flags: (0x1041) ACC_PUBLIC, ACC_BRIDGE, ACC_SYNTHETIC
    Code:
      stack=2, locals=2, args_size=2
         0: aload_0
         1: aload_1
         2: invokespecial #131                // Method coursier/util/shaded/org/jsoup/nodes/LeafNode.attr:(Ljava/lang/String;)Ljava/lang/String;
         5: areturn
      LineNumberTable:
        line 12: 0
      LocalVariableTable:
        Start  Length  Slot  Name   Signature
            0       6     0  this   Lcoursier/util/shaded/org/jsoup/nodes/DocumentType;
}
InnerClasses:
  public static #10= #7 of #9;            // OutputSettings=class coursier/util/shaded/org/jsoup/nodes/Document$OutputSettings of class coursier/util/shaded/org/jsoup/nodes/Document
  public static final #13= #12 of #7;     // Syntax=class coursier/util/shaded/org/jsoup/nodes/Document$OutputSettings$Syntax of class coursier/util/shaded/org/jsoup/nodes/Document$OutputSettings
SourceFile: "DocumentType.java"
