Classfile /Users/mw/Projects/slang-braindump/.jar/jar8/assemble/slang-braindump/assemble/content/coursier/util/shaded/org/jsoup/nodes/Entities$EscapeMode.class
  Last modified May 29, 2022; size 3367 bytes
  SHA-256 checksum cfe836a099b75c423458f1eca86add77bc53fbb9d6f2fa74bd66df194a38f477
  Compiled from "Entities.java"
public final class coursier.util.shaded.org.jsoup.nodes.Entities$EscapeMode extends java.lang.Enum<coursier.util.shaded.org.jsoup.nodes.Entities$EscapeMode>
  minor version: 0
  major version: 51
  flags: (0x4031) ACC_PUBLIC, ACC_FINAL, ACC_SUPER, ACC_ENUM
  this_class: #2                          // coursier/util/shaded/org/jsoup/nodes/Entities$EscapeMode
  super_class: #5                         // java/lang/Enum
  interfaces: 0, fields: 8, methods: 15, attributes: 3
Constant pool:
    #1 = Utf8               coursier/util/shaded/org/jsoup/nodes/Entities$EscapeMode
    #2 = Class              #1            // coursier/util/shaded/org/jsoup/nodes/Entities$EscapeMode
    #3 = Utf8               Ljava/lang/Enum<Lcoursier/util/shaded/org/jsoup/nodes/Entities$EscapeMode;>;
    #4 = Utf8               java/lang/Enum
    #5 = Class              #4            // java/lang/Enum
    #6 = Utf8               Entities.java
    #7 = Utf8               coursier/util/shaded/org/jsoup/nodes/Entities
    #8 = Class              #7            // coursier/util/shaded/org/jsoup/nodes/Entities
    #9 = Utf8               EscapeMode
   #10 = Utf8               xhtml
   #11 = Utf8               Lcoursier/util/shaded/org/jsoup/nodes/Entities$EscapeMode;
   #12 = Utf8               base
   #13 = Utf8               extended
   #14 = Utf8               nameKeys
   #15 = Utf8               [Ljava/lang/String;
   #16 = Utf8               codeVals
   #17 = Utf8               [I
   #18 = Utf8               codeKeys
   #19 = Utf8               nameVals
   #20 = Utf8               $VALUES
   #21 = Utf8               [Lcoursier/util/shaded/org/jsoup/nodes/Entities$EscapeMode;
   #22 = Utf8               values
   #23 = Utf8               ()[Lcoursier/util/shaded/org/jsoup/nodes/Entities$EscapeMode;
   #24 = NameAndType        #20:#21       // $VALUES:[Lcoursier/util/shaded/org/jsoup/nodes/Entities$EscapeMode;
   #25 = Fieldref           #2.#24        // coursier/util/shaded/org/jsoup/nodes/Entities$EscapeMode.$VALUES:[Lcoursier/util/shaded/org/jsoup/nodes/Entities$EscapeMode;
   #26 = Class              #21           // "[Lcoursier/util/shaded/org/jsoup/nodes/Entities$EscapeMode;"
   #27 = Utf8               clone
   #28 = Utf8               ()Ljava/lang/Object;
   #29 = NameAndType        #27:#28       // clone:()Ljava/lang/Object;
   #30 = Methodref          #26.#29       // "[Lcoursier/util/shaded/org/jsoup/nodes/Entities$EscapeMode;".clone:()Ljava/lang/Object;
   #31 = Utf8               valueOf
   #32 = Utf8               (Ljava/lang/String;)Lcoursier/util/shaded/org/jsoup/nodes/Entities$EscapeMode;
   #33 = Utf8               (Ljava/lang/Class;Ljava/lang/String;)Ljava/lang/Enum;
   #34 = NameAndType        #31:#33       // valueOf:(Ljava/lang/Class;Ljava/lang/String;)Ljava/lang/Enum;
   #35 = Methodref          #5.#34        // java/lang/Enum.valueOf:(Ljava/lang/Class;Ljava/lang/String;)Ljava/lang/Enum;
   #36 = Utf8               name
   #37 = Utf8               Ljava/lang/String;
   #38 = Utf8               <init>
   #39 = Utf8               (Ljava/lang/String;ILjava/lang/String;I)V
   #40 = Utf8               (Ljava/lang/String;I)V
   #41 = NameAndType        #38:#40       // "<init>":(Ljava/lang/String;I)V
   #42 = Methodref          #5.#41        // java/lang/Enum."<init>":(Ljava/lang/String;I)V
   #43 = Utf8               access$000
   #44 = Utf8               (Lcoursier/util/shaded/org/jsoup/nodes/Entities$EscapeMode;Ljava/lang/String;I)V
   #45 = NameAndType        #43:#44       // access$000:(Lcoursier/util/shaded/org/jsoup/nodes/Entities$EscapeMode;Ljava/lang/String;I)V
   #46 = Methodref          #8.#45        // coursier/util/shaded/org/jsoup/nodes/Entities.access$000:(Lcoursier/util/shaded/org/jsoup/nodes/Entities$EscapeMode;Ljava/lang/String;I)V
   #47 = Utf8               this
   #48 = Utf8               file
   #49 = Utf8               size
   #50 = Utf8               I
   #51 = Utf8               codepointForName
   #52 = Utf8               (Ljava/lang/String;)I
   #53 = NameAndType        #14:#15       // nameKeys:[Ljava/lang/String;
   #54 = Fieldref           #2.#53        // coursier/util/shaded/org/jsoup/nodes/Entities$EscapeMode.nameKeys:[Ljava/lang/String;
   #55 = Utf8               java/util/Arrays
   #56 = Class              #55           // java/util/Arrays
   #57 = Utf8               binarySearch
   #58 = Utf8               ([Ljava/lang/Object;Ljava/lang/Object;)I
   #59 = NameAndType        #57:#58       // binarySearch:([Ljava/lang/Object;Ljava/lang/Object;)I
   #60 = Methodref          #56.#59       // java/util/Arrays.binarySearch:([Ljava/lang/Object;Ljava/lang/Object;)I
   #61 = NameAndType        #16:#17       // codeVals:[I
   #62 = Fieldref           #2.#61        // coursier/util/shaded/org/jsoup/nodes/Entities$EscapeMode.codeVals:[I
   #63 = Utf8               index
   #64 = Utf8               nameForCodepoint
   #65 = Utf8               (I)Ljava/lang/String;
   #66 = NameAndType        #18:#17       // codeKeys:[I
   #67 = Fieldref           #2.#66        // coursier/util/shaded/org/jsoup/nodes/Entities$EscapeMode.codeKeys:[I
   #68 = Utf8               ([II)I
   #69 = NameAndType        #57:#68       // binarySearch:([II)I
   #70 = Methodref          #56.#69       // java/util/Arrays.binarySearch:([II)I
   #71 = NameAndType        #19:#15       // nameVals:[Ljava/lang/String;
   #72 = Fieldref           #2.#71        // coursier/util/shaded/org/jsoup/nodes/Entities$EscapeMode.nameVals:[Ljava/lang/String;
   #73 = Utf8               java/lang/String
   #74 = Class              #73           // java/lang/String
   #75 = Utf8
   #76 = String             #75           //
   #77 = Utf8               codepoint
   #78 = Utf8               ()I
   #79 = Utf8               access$102
   #80 = Utf8               (Lcoursier/util/shaded/org/jsoup/nodes/Entities$EscapeMode;[Ljava/lang/String;)[Ljava/lang/String;
   #81 = Utf8               x0
   #82 = Utf8               x1
   #83 = Utf8               access$202
   #84 = Utf8               (Lcoursier/util/shaded/org/jsoup/nodes/Entities$EscapeMode;[I)[I
   #85 = Utf8               access$302
   #86 = Utf8               access$402
   #87 = Utf8               access$100
   #88 = Utf8               (Lcoursier/util/shaded/org/jsoup/nodes/Entities$EscapeMode;)[Ljava/lang/String;
   #89 = Utf8               access$200
   #90 = Utf8               (Lcoursier/util/shaded/org/jsoup/nodes/Entities$EscapeMode;)[I
   #91 = Utf8               access$300
   #92 = Utf8               access$400
   #93 = Utf8               <clinit>
   #94 = Utf8               ()V
   #95 = String             #10           // xhtml
   #96 = Utf8               coursier/util/shaded/org/jsoup/nodes/EntitiesData
   #97 = Class              #96           // coursier/util/shaded/org/jsoup/nodes/EntitiesData
   #98 = Utf8               xmlPoints
   #99 = NameAndType        #98:#37       // xmlPoints:Ljava/lang/String;
  #100 = Fieldref           #97.#99       // coursier/util/shaded/org/jsoup/nodes/EntitiesData.xmlPoints:Ljava/lang/String;
  #101 = NameAndType        #38:#39       // "<init>":(Ljava/lang/String;ILjava/lang/String;I)V
  #102 = Methodref          #2.#101       // coursier/util/shaded/org/jsoup/nodes/Entities$EscapeMode."<init>":(Ljava/lang/String;ILjava/lang/String;I)V
  #103 = NameAndType        #10:#11       // xhtml:Lcoursier/util/shaded/org/jsoup/nodes/Entities$EscapeMode;
  #104 = Fieldref           #2.#103       // coursier/util/shaded/org/jsoup/nodes/Entities$EscapeMode.xhtml:Lcoursier/util/shaded/org/jsoup/nodes/Entities$EscapeMode;
  #105 = String             #12           // base
  #106 = Utf8               basePoints
  #107 = NameAndType        #106:#37      // basePoints:Ljava/lang/String;
  #108 = Fieldref           #97.#107      // coursier/util/shaded/org/jsoup/nodes/EntitiesData.basePoints:Ljava/lang/String;
  #109 = NameAndType        #12:#11       // base:Lcoursier/util/shaded/org/jsoup/nodes/Entities$EscapeMode;
  #110 = Fieldref           #2.#109       // coursier/util/shaded/org/jsoup/nodes/Entities$EscapeMode.base:Lcoursier/util/shaded/org/jsoup/nodes/Entities$EscapeMode;
  #111 = String             #13           // extended
  #112 = Utf8               fullPoints
  #113 = NameAndType        #112:#37      // fullPoints:Ljava/lang/String;
  #114 = Fieldref           #97.#113      // coursier/util/shaded/org/jsoup/nodes/EntitiesData.fullPoints:Ljava/lang/String;
  #115 = NameAndType        #13:#11       // extended:Lcoursier/util/shaded/org/jsoup/nodes/Entities$EscapeMode;
  #116 = Fieldref           #2.#115       // coursier/util/shaded/org/jsoup/nodes/Entities$EscapeMode.extended:Lcoursier/util/shaded/org/jsoup/nodes/Entities$EscapeMode;
  #117 = Utf8               Code
  #118 = Utf8               LineNumberTable
  #119 = Utf8               LocalVariableTable
  #120 = Utf8               Signature
  #121 = Utf8               StackMapTable
  #122 = Utf8               InnerClasses
  #123 = Utf8               SourceFile
{
  public static final coursier.util.shaded.org.jsoup.nodes.Entities$EscapeMode xhtml;
    descriptor: Lcoursier/util/shaded/org/jsoup/nodes/Entities$EscapeMode;
    flags: (0x4019) ACC_PUBLIC, ACC_STATIC, ACC_FINAL, ACC_ENUM

  public static final coursier.util.shaded.org.jsoup.nodes.Entities$EscapeMode base;
    descriptor: Lcoursier/util/shaded/org/jsoup/nodes/Entities$EscapeMode;
    flags: (0x4019) ACC_PUBLIC, ACC_STATIC, ACC_FINAL, ACC_ENUM

  public static final coursier.util.shaded.org.jsoup.nodes.Entities$EscapeMode extended;
    descriptor: Lcoursier/util/shaded/org/jsoup/nodes/Entities$EscapeMode;
    flags: (0x4019) ACC_PUBLIC, ACC_STATIC, ACC_FINAL, ACC_ENUM

  private java.lang.String[] nameKeys;
    descriptor: [Ljava/lang/String;
    flags: (0x0002) ACC_PRIVATE

  private int[] codeVals;
    descriptor: [I
    flags: (0x0002) ACC_PRIVATE

  private int[] codeKeys;
    descriptor: [I
    flags: (0x0002) ACC_PRIVATE

  private java.lang.String[] nameVals;
    descriptor: [Ljava/lang/String;
    flags: (0x0002) ACC_PRIVATE

  private static final coursier.util.shaded.org.jsoup.nodes.Entities$EscapeMode[] $VALUES;
    descriptor: [Lcoursier/util/shaded/org/jsoup/nodes/Entities$EscapeMode;
    flags: (0x101a) ACC_PRIVATE, ACC_STATIC, ACC_FINAL, ACC_SYNTHETIC

  public static coursier.util.shaded.org.jsoup.nodes.Entities$EscapeMode[] values();
    descriptor: ()[Lcoursier/util/shaded/org/jsoup/nodes/Entities$EscapeMode;
    flags: (0x0009) ACC_PUBLIC, ACC_STATIC
    Code:
      stack=1, locals=0, args_size=0
         0: getstatic     #25                 // Field $VALUES:[Lcoursier/util/shaded/org/jsoup/nodes/Entities$EscapeMode;
         3: invokevirtual #30                 // Method "[Lcoursier/util/shaded/org/jsoup/nodes/Entities$EscapeMode;".clone:()Ljava/lang/Object;
         6: checkcast     #26                 // class "[Lcoursier/util/shaded/org/jsoup/nodes/Entities$EscapeMode;"
         9: areturn
      LineNumberTable:
        line 29: 0

  public static coursier.util.shaded.org.jsoup.nodes.Entities$EscapeMode valueOf(java.lang.String);
    descriptor: (Ljava/lang/String;)Lcoursier/util/shaded/org/jsoup/nodes/Entities$EscapeMode;
    flags: (0x0009) ACC_PUBLIC, ACC_STATIC
    Code:
      stack=2, locals=1, args_size=1
         0: ldc           #2                  // class coursier/util/shaded/org/jsoup/nodes/Entities$EscapeMode
         2: aload_0
         3: invokestatic  #35                 // Method java/lang/Enum.valueOf:(Ljava/lang/Class;Ljava/lang/String;)Ljava/lang/Enum;
         6: checkcast     #2                  // class coursier/util/shaded/org/jsoup/nodes/Entities$EscapeMode
         9: areturn
      LineNumberTable:
        line 29: 0
      LocalVariableTable:
        Start  Length  Slot  Name   Signature
            0      10     0  name   Ljava/lang/String;

  private coursier.util.shaded.org.jsoup.nodes.Entities$EscapeMode(java.lang.String, int);
    descriptor: (Ljava/lang/String;ILjava/lang/String;I)V
    flags: (0x0002) ACC_PRIVATE
    Code:
      stack=3, locals=5, args_size=5
         0: aload_0
         1: aload_1
         2: iload_2
         3: invokespecial #42                 // Method java/lang/Enum."<init>":(Ljava/lang/String;I)V
         6: aload_0
         7: aload_3
         8: iload         4
        10: invokestatic  #46                 // Method coursier/util/shaded/org/jsoup/nodes/Entities.access$000:(Lcoursier/util/shaded/org/jsoup/nodes/Entities$EscapeMode;Ljava/lang/String;I)V
        13: return
      LineNumberTable:
        line 51: 0
        line 52: 6
        line 53: 13
      LocalVariableTable:
        Start  Length  Slot  Name   Signature
            0      14     0  this   Lcoursier/util/shaded/org/jsoup/nodes/Entities$EscapeMode;
            0      14     3  file   Ljava/lang/String;
            0      14     4  size   I
    Signature: #40                          // (Ljava/lang/String;I)V

  int codepointForName(java.lang.String);
    descriptor: (Ljava/lang/String;)I
    flags: (0x0000)
    Code:
      stack=2, locals=3, args_size=2
         0: aload_0
         1: getfield      #54                 // Field nameKeys:[Ljava/lang/String;
         4: aload_1
         5: invokestatic  #60                 // Method java/util/Arrays.binarySearch:([Ljava/lang/Object;Ljava/lang/Object;)I
         8: istore_2
         9: iload_2
        10: iflt          22
        13: aload_0
        14: getfield      #62                 // Field codeVals:[I
        17: iload_2
        18: iaload
        19: goto          23
        22: iconst_m1
        23: ireturn
      StackMapTable: number_of_entries = 2
        frame_type = 252 /* append */
          offset_delta = 22
          locals = [ int ]
        frame_type = 64 /* same_locals_1_stack_item */
          stack = [ int ]
      LineNumberTable:
        line 56: 0
        line 57: 9
      LocalVariableTable:
        Start  Length  Slot  Name   Signature
            0      24     0  this   Lcoursier/util/shaded/org/jsoup/nodes/Entities$EscapeMode;
            0      24     1  name   Ljava/lang/String;
            9      15     2 index   I

  java.lang.String nameForCodepoint(int);
    descriptor: (I)Ljava/lang/String;
    flags: (0x0000)
    Code:
      stack=3, locals=3, args_size=2
         0: aload_0
         1: getfield      #67                 // Field codeKeys:[I
         4: iload_1
         5: invokestatic  #70                 // Method java/util/Arrays.binarySearch:([II)I
         8: istore_2
         9: iload_2
        10: iflt          54
        13: iload_2
        14: aload_0
        15: getfield      #72                 // Field nameVals:[Ljava/lang/String;
        18: arraylength
        19: iconst_1
        20: isub
        21: if_icmpge     47
        24: aload_0
        25: getfield      #67                 // Field codeKeys:[I
        28: iload_2
        29: iconst_1
        30: iadd
        31: iaload
        32: iload_1
        33: if_icmpne     47
        36: aload_0
        37: getfield      #72                 // Field nameVals:[Ljava/lang/String;
        40: iload_2
        41: iconst_1
        42: iadd
        43: aaload
        44: goto          53
        47: aload_0
        48: getfield      #72                 // Field nameVals:[Ljava/lang/String;
        51: iload_2
        52: aaload
        53: areturn
        54: ldc           #76                 // String
        56: areturn
      StackMapTable: number_of_entries = 3
        frame_type = 252 /* append */
          offset_delta = 47
          locals = [ int ]
        frame_type = 69 /* same_locals_1_stack_item */
          stack = [ class java/lang/String ]
        frame_type = 0 /* same */
      LineNumberTable:
        line 61: 0
        line 62: 9
        line 65: 13
        line 66: 36
        line 65: 53
        line 68: 54
      LocalVariableTable:
        Start  Length  Slot  Name   Signature
            0      57     0  this   Lcoursier/util/shaded/org/jsoup/nodes/Entities$EscapeMode;
            0      57     1 codepoint   I
            9      48     2 index   I

  private int size();
    descriptor: ()I
    flags: (0x0002) ACC_PRIVATE
    Code:
      stack=1, locals=1, args_size=1
         0: aload_0
         1: getfield      #54                 // Field nameKeys:[Ljava/lang/String;
         4: arraylength
         5: ireturn
      LineNumberTable:
        line 72: 0
      LocalVariableTable:
        Start  Length  Slot  Name   Signature
            0       6     0  this   Lcoursier/util/shaded/org/jsoup/nodes/Entities$EscapeMode;

  static java.lang.String[] access$102(coursier.util.shaded.org.jsoup.nodes.Entities$EscapeMode, java.lang.String[]);
    descriptor: (Lcoursier/util/shaded/org/jsoup/nodes/Entities$EscapeMode;[Ljava/lang/String;)[Ljava/lang/String;
    flags: (0x1008) ACC_STATIC, ACC_SYNTHETIC
    Code:
      stack=3, locals=2, args_size=2
         0: aload_0
         1: aload_1
         2: dup_x1
         3: putfield      #54                 // Field nameKeys:[Ljava/lang/String;
         6: areturn
      LineNumberTable:
        line 29: 0
      LocalVariableTable:
        Start  Length  Slot  Name   Signature
            0       7     0    x0   Lcoursier/util/shaded/org/jsoup/nodes/Entities$EscapeMode;
            0       7     1    x1   [Ljava/lang/String;

  static int[] access$202(coursier.util.shaded.org.jsoup.nodes.Entities$EscapeMode, int[]);
    descriptor: (Lcoursier/util/shaded/org/jsoup/nodes/Entities$EscapeMode;[I)[I
    flags: (0x1008) ACC_STATIC, ACC_SYNTHETIC
    Code:
      stack=3, locals=2, args_size=2
         0: aload_0
         1: aload_1
         2: dup_x1
         3: putfield      #62                 // Field codeVals:[I
         6: areturn
      LineNumberTable:
        line 29: 0
      LocalVariableTable:
        Start  Length  Slot  Name   Signature
            0       7     0    x0   Lcoursier/util/shaded/org/jsoup/nodes/Entities$EscapeMode;
            0       7     1    x1   [I

  static int[] access$302(coursier.util.shaded.org.jsoup.nodes.Entities$EscapeMode, int[]);
    descriptor: (Lcoursier/util/shaded/org/jsoup/nodes/Entities$EscapeMode;[I)[I
    flags: (0x1008) ACC_STATIC, ACC_SYNTHETIC
    Code:
      stack=3, locals=2, args_size=2
         0: aload_0
         1: aload_1
         2: dup_x1
         3: putfield      #67                 // Field codeKeys:[I
         6: areturn
      LineNumberTable:
        line 29: 0
      LocalVariableTable:
        Start  Length  Slot  Name   Signature
            0       7     0    x0   Lcoursier/util/shaded/org/jsoup/nodes/Entities$EscapeMode;
            0       7     1    x1   [I

  static java.lang.String[] access$402(coursier.util.shaded.org.jsoup.nodes.Entities$EscapeMode, java.lang.String[]);
    descriptor: (Lcoursier/util/shaded/org/jsoup/nodes/Entities$EscapeMode;[Ljava/lang/String;)[Ljava/lang/String;
    flags: (0x1008) ACC_STATIC, ACC_SYNTHETIC
    Code:
      stack=3, locals=2, args_size=2
         0: aload_0
         1: aload_1
         2: dup_x1
         3: putfield      #72                 // Field nameVals:[Ljava/lang/String;
         6: areturn
      LineNumberTable:
        line 29: 0
      LocalVariableTable:
        Start  Length  Slot  Name   Signature
            0       7     0    x0   Lcoursier/util/shaded/org/jsoup/nodes/Entities$EscapeMode;
            0       7     1    x1   [Ljava/lang/String;

  static java.lang.String[] access$100(coursier.util.shaded.org.jsoup.nodes.Entities$EscapeMode);
    descriptor: (Lcoursier/util/shaded/org/jsoup/nodes/Entities$EscapeMode;)[Ljava/lang/String;
    flags: (0x1008) ACC_STATIC, ACC_SYNTHETIC
    Code:
      stack=1, locals=1, args_size=1
         0: aload_0
         1: getfield      #54                 // Field nameKeys:[Ljava/lang/String;
         4: areturn
      LineNumberTable:
        line 29: 0
      LocalVariableTable:
        Start  Length  Slot  Name   Signature
            0       5     0    x0   Lcoursier/util/shaded/org/jsoup/nodes/Entities$EscapeMode;

  static int[] access$200(coursier.util.shaded.org.jsoup.nodes.Entities$EscapeMode);
    descriptor: (Lcoursier/util/shaded/org/jsoup/nodes/Entities$EscapeMode;)[I
    flags: (0x1008) ACC_STATIC, ACC_SYNTHETIC
    Code:
      stack=1, locals=1, args_size=1
         0: aload_0
         1: getfield      #62                 // Field codeVals:[I
         4: areturn
      LineNumberTable:
        line 29: 0
      LocalVariableTable:
        Start  Length  Slot  Name   Signature
            0       5     0    x0   Lcoursier/util/shaded/org/jsoup/nodes/Entities$EscapeMode;

  static int[] access$300(coursier.util.shaded.org.jsoup.nodes.Entities$EscapeMode);
    descriptor: (Lcoursier/util/shaded/org/jsoup/nodes/Entities$EscapeMode;)[I
    flags: (0x1008) ACC_STATIC, ACC_SYNTHETIC
    Code:
      stack=1, locals=1, args_size=1
         0: aload_0
         1: getfield      #67                 // Field codeKeys:[I
         4: areturn
      LineNumberTable:
        line 29: 0
      LocalVariableTable:
        Start  Length  Slot  Name   Signature
            0       5     0    x0   Lcoursier/util/shaded/org/jsoup/nodes/Entities$EscapeMode;

  static java.lang.String[] access$400(coursier.util.shaded.org.jsoup.nodes.Entities$EscapeMode);
    descriptor: (Lcoursier/util/shaded/org/jsoup/nodes/Entities$EscapeMode;)[Ljava/lang/String;
    flags: (0x1008) ACC_STATIC, ACC_SYNTHETIC
    Code:
      stack=1, locals=1, args_size=1
         0: aload_0
         1: getfield      #72                 // Field nameVals:[Ljava/lang/String;
         4: areturn
      LineNumberTable:
        line 29: 0
      LocalVariableTable:
        Start  Length  Slot  Name   Signature
            0       5     0    x0   Lcoursier/util/shaded/org/jsoup/nodes/Entities$EscapeMode;

  static {};
    descriptor: ()V
    flags: (0x0008) ACC_STATIC
    Code:
      stack=6, locals=0, args_size=0
         0: new           #2                  // class coursier/util/shaded/org/jsoup/nodes/Entities$EscapeMode
         3: dup
         4: ldc           #95                 // String xhtml
         6: iconst_0
         7: getstatic     #100                // Field coursier/util/shaded/org/jsoup/nodes/EntitiesData.xmlPoints:Ljava/lang/String;
        10: iconst_4
        11: invokespecial #102                // Method "<init>":(Ljava/lang/String;ILjava/lang/String;I)V
        14: putstatic     #104                // Field xhtml:Lcoursier/util/shaded/org/jsoup/nodes/Entities$EscapeMode;
        17: new           #2                  // class coursier/util/shaded/org/jsoup/nodes/Entities$EscapeMode
        20: dup
        21: ldc           #105                // String base
        23: iconst_1
        24: getstatic     #108                // Field coursier/util/shaded/org/jsoup/nodes/EntitiesData.basePoints:Ljava/lang/String;
        27: bipush        106
        29: invokespecial #102                // Method "<init>":(Ljava/lang/String;ILjava/lang/String;I)V
        32: putstatic     #110                // Field base:Lcoursier/util/shaded/org/jsoup/nodes/Entities$EscapeMode;
        35: new           #2                  // class coursier/util/shaded/org/jsoup/nodes/Entities$EscapeMode
        38: dup
        39: ldc           #111                // String extended
        41: iconst_2
        42: getstatic     #114                // Field coursier/util/shaded/org/jsoup/nodes/EntitiesData.fullPoints:Ljava/lang/String;
        45: sipush        2125
        48: invokespecial #102                // Method "<init>":(Ljava/lang/String;ILjava/lang/String;I)V
        51: putstatic     #116                // Field extended:Lcoursier/util/shaded/org/jsoup/nodes/Entities$EscapeMode;
        54: iconst_3
        55: anewarray     #2                  // class coursier/util/shaded/org/jsoup/nodes/Entities$EscapeMode
        58: dup
        59: iconst_0
        60: getstatic     #104                // Field xhtml:Lcoursier/util/shaded/org/jsoup/nodes/Entities$EscapeMode;
        63: aastore
        64: dup
        65: iconst_1
        66: getstatic     #110                // Field base:Lcoursier/util/shaded/org/jsoup/nodes/Entities$EscapeMode;
        69: aastore
        70: dup
        71: iconst_2
        72: getstatic     #116                // Field extended:Lcoursier/util/shaded/org/jsoup/nodes/Entities$EscapeMode;
        75: aastore
        76: putstatic     #25                 // Field $VALUES:[Lcoursier/util/shaded/org/jsoup/nodes/Entities$EscapeMode;
        79: return
      LineNumberTable:
        line 33: 0
        line 37: 17
        line 41: 35
        line 29: 54
}
InnerClasses:
  public static final #9= #2 of #8;       // EscapeMode=class coursier/util/shaded/org/jsoup/nodes/Entities$EscapeMode of class coursier/util/shaded/org/jsoup/nodes/Entities
Signature: #3                           // Ljava/lang/Enum<Lcoursier/util/shaded/org/jsoup/nodes/Entities$EscapeMode;>;
SourceFile: "Entities.java"
