Classfile /Users/mw/Projects/slang-braindump/.jar/jar8/assemble/slang-braindump/assemble/content/coursier/util/shaded/org/jsoup/nodes/PseudoTextElement.class
  Last modified May 29, 2022; size 1251 bytes
  SHA-256 checksum 065bfbf13a272893c7e73fcdf92c645a725c2e00d04103497ed878f202d317f9
  Compiled from "PseudoTextElement.java"
public class coursier.util.shaded.org.jsoup.nodes.PseudoTextElement extends coursier.util.shaded.org.jsoup.nodes.Element
  minor version: 0
  major version: 51
  flags: (0x0021) ACC_PUBLIC, ACC_SUPER
  this_class: #2                          // coursier/util/shaded/org/jsoup/nodes/PseudoTextElement
  super_class: #4                         // coursier/util/shaded/org/jsoup/nodes/Element
  interfaces: 0, fields: 0, methods: 3, attributes: 2
Constant pool:
   #1 = Utf8               coursier/util/shaded/org/jsoup/nodes/PseudoTextElement
   #2 = Class              #1             // coursier/util/shaded/org/jsoup/nodes/PseudoTextElement
   #3 = Utf8               coursier/util/shaded/org/jsoup/nodes/Element
   #4 = Class              #3             // coursier/util/shaded/org/jsoup/nodes/Element
   #5 = Utf8               PseudoTextElement.java
   #6 = Utf8               coursier/util/shaded/org/jsoup/nodes/Document$OutputSettings
   #7 = Class              #6             // coursier/util/shaded/org/jsoup/nodes/Document$OutputSettings
   #8 = Utf8               coursier/util/shaded/org/jsoup/nodes/Document
   #9 = Class              #8             // coursier/util/shaded/org/jsoup/nodes/Document
  #10 = Utf8               OutputSettings
  #11 = Utf8               <init>
  #12 = Utf8               (Lcoursier/util/shaded/org/jsoup/parser/Tag;Ljava/lang/String;Lcoursier/util/shaded/org/jsoup/nodes/Attributes;)V
  #13 = NameAndType        #11:#12        // "<init>":(Lcoursier/util/shaded/org/jsoup/parser/Tag;Ljava/lang/String;Lcoursier/util/shaded/org/jsoup/nodes/Attributes;)V
  #14 = Methodref          #4.#13         // coursier/util/shaded/org/jsoup/nodes/Element."<init>":(Lcoursier/util/shaded/org/jsoup/parser/Tag;Ljava/lang/String;Lcoursier/util/shaded/org/jsoup/nodes/Attributes;)V
  #15 = Utf8               this
  #16 = Utf8               Lcoursier/util/shaded/org/jsoup/nodes/PseudoTextElement;
  #17 = Utf8               tag
  #18 = Utf8               Lcoursier/util/shaded/org/jsoup/parser/Tag;
  #19 = Utf8               baseUri
  #20 = Utf8               Ljava/lang/String;
  #21 = Utf8               attributes
  #22 = Utf8               Lcoursier/util/shaded/org/jsoup/nodes/Attributes;
  #23 = Utf8               outerHtmlHead
  #24 = Utf8               (Ljava/lang/Appendable;ILcoursier/util/shaded/org/jsoup/nodes/Document$OutputSettings;)V
  #25 = Utf8               accum
  #26 = Utf8               Ljava/lang/Appendable;
  #27 = Utf8               depth
  #28 = Utf8               I
  #29 = Utf8               out
  #30 = Utf8               Lcoursier/util/shaded/org/jsoup/nodes/Document$OutputSettings;
  #31 = Utf8               outerHtmlTail
  #32 = Utf8               Code
  #33 = Utf8               LineNumberTable
  #34 = Utf8               LocalVariableTable
  #35 = Utf8               InnerClasses
  #36 = Utf8               SourceFile
{
  public coursier.util.shaded.org.jsoup.nodes.PseudoTextElement(coursier.util.shaded.org.jsoup.parser.Tag, java.lang.String, coursier.util.shaded.org.jsoup.nodes.Attributes);
    descriptor: (Lcoursier/util/shaded/org/jsoup/parser/Tag;Ljava/lang/String;Lcoursier/util/shaded/org/jsoup/nodes/Attributes;)V
    flags: (0x0001) ACC_PUBLIC
    Code:
      stack=4, locals=4, args_size=4
         0: aload_0
         1: aload_1
         2: aload_2
         3: aload_3
         4: invokespecial #14                 // Method coursier/util/shaded/org/jsoup/nodes/Element."<init>":(Lcoursier/util/shaded/org/jsoup/parser/Tag;Ljava/lang/String;Lcoursier/util/shaded/org/jsoup/nodes/Attributes;)V
         7: return
      LineNumberTable:
        line 12: 0
        line 13: 7
      LocalVariableTable:
        Start  Length  Slot  Name   Signature
            0       8     0  this   Lcoursier/util/shaded/org/jsoup/nodes/PseudoTextElement;
            0       8     1   tag   Lcoursier/util/shaded/org/jsoup/parser/Tag;
            0       8     2 baseUri   Ljava/lang/String;
            0       8     3 attributes   Lcoursier/util/shaded/org/jsoup/nodes/Attributes;

  void outerHtmlHead(java.lang.Appendable, int, coursier.util.shaded.org.jsoup.nodes.Document$OutputSettings);
    descriptor: (Ljava/lang/Appendable;ILcoursier/util/shaded/org/jsoup/nodes/Document$OutputSettings;)V
    flags: (0x0000)
    Code:
      stack=0, locals=4, args_size=4
         0: return
      LineNumberTable:
        line 17: 0
      LocalVariableTable:
        Start  Length  Slot  Name   Signature
            0       1     0  this   Lcoursier/util/shaded/org/jsoup/nodes/PseudoTextElement;
            0       1     1 accum   Ljava/lang/Appendable;
            0       1     2 depth   I
            0       1     3   out   Lcoursier/util/shaded/org/jsoup/nodes/Document$OutputSettings;

  void outerHtmlTail(java.lang.Appendable, int, coursier.util.shaded.org.jsoup.nodes.Document$OutputSettings);
    descriptor: (Ljava/lang/Appendable;ILcoursier/util/shaded/org/jsoup/nodes/Document$OutputSettings;)V
    flags: (0x0000)
    Code:
      stack=0, locals=4, args_size=4
         0: return
      LineNumberTable:
        line 21: 0
      LocalVariableTable:
        Start  Length  Slot  Name   Signature
            0       1     0  this   Lcoursier/util/shaded/org/jsoup/nodes/PseudoTextElement;
            0       1     1 accum   Ljava/lang/Appendable;
            0       1     2 depth   I
            0       1     3   out   Lcoursier/util/shaded/org/jsoup/nodes/Document$OutputSettings;
}
InnerClasses:
  public static #10= #7 of #9;            // OutputSettings=class coursier/util/shaded/org/jsoup/nodes/Document$OutputSettings of class coursier/util/shaded/org/jsoup/nodes/Document
SourceFile: "PseudoTextElement.java"
