Classfile /Users/mw/Projects/slang-braindump/.jar/jar8/assemble/slang-braindump/assemble/content/scala/AnyVal.class
  Last modified May 29, 2022; size 658 bytes
  SHA-256 checksum f0009f63ea8da17c6c2f6a986658847ba92a6f4e446bc51d371e1ccea3e5ee4e
  Compiled from "AnyVal.scala"
public abstract class scala.AnyVal
  minor version: 0
  major version: 52
  flags: (0x0421) ACC_PUBLIC, ACC_SUPER, ACC_ABSTRACT
  this_class: #2                          // scala/AnyVal
  super_class: #4                         // java/lang/Object
  interfaces: 0, fields: 0, methods: 1, attributes: 4
Constant pool:
   #1 = Utf8               scala/AnyVal
   #2 = Class              #1             // scala/AnyVal
   #3 = Utf8               java/lang/Object
   #4 = Class              #3             // java/lang/Object
   #5 = Utf8               AnyVal.scala
   #6 = Utf8               Lscala/reflect/ScalaSignature;
   #7 = Utf8               bytes
   #8 = Utf8               \u0006\u0005\u00152Qa\u0001\u0003\u0002\u0002\u001dAQ\u0001\u0004\u0001\u0005\u00025AQa\u0004\u0001\u0005\u0002A\u0011a!\u00118z-\u0006d\'\"A\u0003\u0002\u000bM\u001c\u0017\r\\1\u0004\u0001M\u0011\u0001\u0001\u0003\t\u0003\u0013)i\u0011\u0001B\u0005\u0003\u0017\u0011\u00111!\u00118z\u0003\u0019a\u0014N\\5u}Q\ta\u0002\u0005\u0002\n\u0001\u0005Aq-\u001a;DY\u0006\u001c8\u000fF\u0001\u0012a\t\u0011r\u0004E\u0002\u00145uq!\u0001\u0006\r\u0011\u0005U!Q\"\u0001\f\u000b\u0005]1\u0011A\u0002\u001fs_>$h(\u0003\u0002\u001a\t\u00051\u0001K]3eK\u001aL!a\u0007\u000f\u0003\u000b\rc\u0017m]:\u000b\u0005e!\u0001C\u0001\u0010 \u0019\u0001!\u0011\u0002\t\u0002\u0002\u0002\u0003\u0005)\u0011A\u0011\u0003\u0007}#\u0013\'\u0005\u0002#\u001dA\u0011\u0011bI\u0005\u0003I\u0011\u0011qAT8uQ&tw\r
   #9 = Utf8               <init>
  #10 = Utf8               ()V
  #11 = NameAndType        #9:#10         // "<init>":()V
  #12 = Methodref          #4.#11         // java/lang/Object."<init>":()V
  #13 = Utf8               this
  #14 = Utf8               Lscala/AnyVal;
  #15 = Utf8               Code
  #16 = Utf8               LineNumberTable
  #17 = Utf8               LocalVariableTable
  #18 = Utf8               SourceFile
  #19 = Utf8               RuntimeVisibleAnnotations
  #20 = Utf8               ScalaInlineInfo
  #21 = Utf8               getClass
  #22 = Utf8               ()Ljava/lang/Class;
  #23 = Utf8               ScalaSig
{
  public scala.AnyVal();
    descriptor: ()V
    flags: (0x0001) ACC_PUBLIC
    Code:
      stack=1, locals=1, args_size=1
         0: aload_0
         1: invokespecial #12                 // Method java/lang/Object."<init>":()V
         4: return
      LineNumberTable:
        line 57: 4
      LocalVariableTable:
        Start  Length  Slot  Name   Signature
            0       5     0  this   Lscala/AnyVal;
}
SourceFile: "AnyVal.scala"
RuntimeVisibleAnnotations:
  0: #6(#7=s#8)
    scala.reflect.ScalaSignature(
      bytes="\u0006\u0005\u00152Qa\u0001\u0003\u0002\u0002\u001dAQ\u0001\u0004\u0001\u0005\u00025AQa\u0004\u0001\u0005\u0002A\u0011a!\u00118z-\u0006d\'\"A\u0003\u0002\u000bM\u001c\u0017\r\\1\u0004\u0001M\u0011\u0001\u0001\u0003\t\u0003\u0013)i\u0011\u0001B\u0005\u0003\u0017\u0011\u00111!\u00118z\u0003\u0019a\u0014N\\5u}Q\ta\u0002\u0005\u0002\n\u0001\u0005Aq-\u001a;DY\u0006\u001c8\u000fF\u0001\u0012a\t\u0011r\u0004E\u0002\u00145uq!\u0001\u0006\r\u0011\u0005U!Q\"\u0001\f\u000b\u0005]1\u0011A\u0002\u001fs_>$h(\u0003\u0002\u001a\t\u00051\u0001K]3eK\u001aL!a\u0007\u000f\u0003\u000b\rc\u0017m]:\u000b\u0005e!\u0001C\u0001\u0010 \u0019\u0001!\u0011\u0002\t\u0002\u0002\u0002\u0003\u0005)\u0011A\u0011\u0003\u0007}#\u0013\'\u0005\u0002#\u001dA\u0011\u0011bI\u0005\u0003I\u0011\u0011qAT8uQ&tw\r"
    )
  ScalaInlineInfo: length = 0xE (unknown attribute)
   01 00 00 02 00 09 00 0A 00 00 15 00 16 00
  ScalaSig: length = 0x3 (unknown attribute)
   05 02 00
