Classfile /Users/mw/Projects/slang-braindump/.jar/jar8/assemble/slang-braindump/assemble/content/scala/deprecated.class
  Last modified May 29, 2022; size 1586 bytes
  SHA-256 checksum 1e019a96f00ac407accc5d57a92fdce7d5a144df265aa742396d62677df0abd9
  Compiled from "deprecated.scala"
public class scala.deprecated extends scala.annotation.Annotation implements scala.annotation.ConstantAnnotation
  minor version: 0
  major version: 52
  flags: (0x0021) ACC_PUBLIC, ACC_SUPER
  this_class: #2                          // scala/deprecated
  super_class: #4                         // scala/annotation/Annotation
  interfaces: 1, fields: 0, methods: 3, attributes: 4
Constant pool:
   #1 = Utf8               scala/deprecated
   #2 = Class              #1             // scala/deprecated
   #3 = Utf8               scala/annotation/Annotation
   #4 = Class              #3             // scala/annotation/Annotation
   #5 = Utf8               scala/annotation/ConstantAnnotation
   #6 = Class              #5             // scala/annotation/ConstantAnnotation
   #7 = Utf8               deprecated.scala
   #8 = Utf8               Lscala/reflect/ScalaSignature;
   #9 = Utf8               bytes
  #10 = Utf8               \u0006\u0005m3A!\u0003\u0006\u0001\u001b!Aq\u0003\u0001B\u0001B\u0003%\u0001\u0004\u0003\u0005$\u0001\t\u0005\t\u0015!\u0003\u0019\u0011\u0015!\u0003\u0001\"\u0001&\u000f\u001dI%\"!A\t\u0002)3q!\u0003\u0006\u0002\u0002#\u00051\nC\u0003%\u000b\u0011\u0005q\nC\u0004Q\u000bE\u0005I\u0011A)\t\u000fi+\u0011\u0013!C\u0001#\nQA-\u001a9sK\u000e\fG/\u001a3\u000b\u0003-\tQa]2bY\u0006\u001c\u0001aE\u0002\u0001\u001dQ\u0001\"a\u0004\n\u000e\u0003AQ!!\u0005\u0006\u0002\u0015\u0005tgn\u001c;bi&|g.\u0003\u0002\u0014!\tQ\u0011I\u001c8pi\u0006$\u0018n\u001c8\u0011\u0005=)\u0012B\u0001\f\u0011\u0005I\u0019uN\\:uC:$\u0018I\u001c8pi\u0006$\u0018n\u001c8\u0002\u000f5,7o]1hKB\u0011\u0011\u0004\t\b\u00035y\u0001\"a\u0007\u0006\u000e\u0003qQ!!\b\u0007\u0002\rq\u0012xn\u001c;?\u0013\ty\"\"\u0001\u0004Qe\u0016$WMZ\u0005\u0003C\t\u0012aa\u0015;sS:<\'BA\u0010\u000b\u0003\u0015\u0019\u0018N\\2f\u0003\u0019a\u0014N\\5u}Q\u0019a\u0005K\u0015\u0011\u0005\u001d\u0002Q\"\u0001\u0006\t\u000f]\u0019\u0001\u0013!a\u00011!91e\u0001I\u0001\u0002\u0004A\u0002F\u0002\u0001,/9\u001a\u0003\u0007\u0005\u0002(Y%\u0011QF\u0003\u0002\u0016I\u0016\u0004(/Z2bi\u0016$\u0017J\u001c5fe&$\u0018M\\2fC\u0005y\u0013aJ*dQ\u0016$W\u000f\\3eA\u0019|\'\u000f\t2fS:<\u0007EZ5oC2\u0004\u0013N\u001c\u0011uQ\u0016\u0004c-\u001e;ve\u0016\f\u0013!M\u0001\u0007e9\n4G\f\u0019)\u0005\u0001\u0019\u0004C\u0001\u001b8\u001b\u0005)$B\u0001\u001c\u0011\u0003\u0011iW\r^1\n\u0005a*$!\u00024jK2$\u0007F\u0001\u0001;!\t!4(\u0003\u0002=k\tQ!-Z1o\'\u0016$H/\u001a:)\u0005\u0001q\u0004C\u0001\u001b@\u0013\t\u0001UG\u0001\u0006cK\u0006tw)\u001a;uKJD#\u0001\u0001\"\u0011\u0005Q\u001a\u0015B\u0001#6\u0005\u0019\u0019X\r\u001e;fe\"\u0012\u0001A\u0012\t\u0003i\u001dK!\u0001S\u001b\u0003\r\u001d,G\u000f^3s\u0003)!W\r\u001d:fG\u0006$X\r\u001a\t\u0003O\u0015\u0019\"!\u0002\'\u0011\u0005\u001dj\u0015B\u0001(\u000b\u0005\u0019\te.\u001f*fMR\t!*A\u000e%Y\u0016\u001c8/\u001b8ji\u0012:\'/Z1uKJ$C-\u001a4bk2$H%M\u000b\u0002%*\u0012\u0001dU\u0016\u0002)B\u0011Q\u000bW\u0007\u0002-*\u0011q\u000bE\u0001\nk:\u001c\u0007.Z2lK\u0012L!!\u0017,\u0003#Ut7\r[3dW\u0016$g+\u0019:jC:\u001cW-A\u000e%Y\u0016\u001c8/\u001b8ji\u0012:\'/Z1uKJ$C-\u001a4bk2$HE\r
  #11 = Utf8               $lessinit$greater$default$2
  #12 = Utf8               ()Ljava/lang/String;
  #13 = Utf8               scala/deprecated$
  #14 = Class              #13            // scala/deprecated$
  #15 = Utf8               MODULE$
  #16 = Utf8               Lscala/deprecated$;
  #17 = NameAndType        #15:#16        // MODULE$:Lscala/deprecated$;
  #18 = Fieldref           #14.#17        // scala/deprecated$.MODULE$:Lscala/deprecated$;
  #19 = Utf8
  #20 = String             #19            //
  #21 = Utf8               $lessinit$greater$default$1
  #22 = Utf8               <init>
  #23 = Utf8               (Ljava/lang/String;Ljava/lang/String;)V
  #24 = Utf8               message
  #25 = Utf8               since
  #26 = Utf8               ()V
  #27 = NameAndType        #22:#26        // "<init>":()V
  #28 = Methodref          #4.#27         // scala/annotation/Annotation."<init>":()V
  #29 = Utf8               this
  #30 = Utf8               Lscala/deprecated;
  #31 = Utf8               Ljava/lang/String;
  #32 = Utf8               Code
  #33 = Utf8               LineNumberTable
  #34 = Utf8               LocalVariableTable
  #35 = Utf8               MethodParameters
  #36 = Utf8               SourceFile
  #37 = Utf8               RuntimeVisibleAnnotations
  #38 = Utf8               ScalaInlineInfo
  #39 = Utf8               ScalaSig
{
  public static java.lang.String $lessinit$greater$default$2();
    descriptor: ()Ljava/lang/String;
    flags: (0x0009) ACC_PUBLIC, ACC_STATIC
    Code:
      stack=1, locals=0, args_size=0
         0: getstatic     #18                 // Field scala/deprecated$.MODULE$:Lscala/deprecated$;
         3: pop
         4: ldc           #20                 // String
         6: areturn
      LineNumberTable:
        line 61: 4

  public static java.lang.String $lessinit$greater$default$1();
    descriptor: ()Ljava/lang/String;
    flags: (0x0009) ACC_PUBLIC, ACC_STATIC
    Code:
      stack=1, locals=0, args_size=0
         0: getstatic     #18                 // Field scala/deprecated$.MODULE$:Lscala/deprecated$;
         3: pop
         4: ldc           #20                 // String
         6: areturn
      LineNumberTable:
        line 61: 4

  public scala.deprecated(java.lang.String, java.lang.String);
    descriptor: (Ljava/lang/String;Ljava/lang/String;)V
    flags: (0x0001) ACC_PUBLIC
    Code:
      stack=1, locals=3, args_size=3
         0: aload_0
         1: invokespecial #28                 // Method scala/annotation/Annotation."<init>":()V
         4: return
      LineNumberTable:
        line 61: 0
      LocalVariableTable:
        Start  Length  Slot  Name   Signature
            0       5     0  this   Lscala/deprecated;
            0       5     1 message   Ljava/lang/String;
            0       5     2 since   Ljava/lang/String;
    MethodParameters:
      Name                           Flags
      message                        final
      since                          final
}
SourceFile: "deprecated.scala"
RuntimeVisibleAnnotations:
  0: #8(#9=s#10)
    scala.reflect.ScalaSignature(
      bytes="\u0006\u0005m3A!\u0003\u0006\u0001\u001b!Aq\u0003\u0001B\u0001B\u0003%\u0001\u0004\u0003\u0005$\u0001\t\u0005\t\u0015!\u0003\u0019\u0011\u0015!\u0003\u0001\"\u0001&\u000f\u001dI%\"!A\t\u0002)3q!\u0003\u0006\u0002\u0002#\u00051\nC\u0003%\u000b\u0011\u0005q\nC\u0004Q\u000bE\u0005I\u0011A)\t\u000fi+\u0011\u0013!C\u0001#\nQA-\u001a9sK\u000e\fG/\u001a3\u000b\u0003-\tQa]2bY\u0006\u001c\u0001aE\u0002\u0001\u001dQ\u0001\"a\u0004\n\u000e\u0003AQ!!\u0005\u0006\u0002\u0015\u0005tgn\u001c;bi&|g.\u0003\u0002\u0014!\tQ\u0011I\u001c8pi\u0006$\u0018n\u001c8\u0011\u0005=)\u0012B\u0001\f\u0011\u0005I\u0019uN\\:uC:$\u0018I\u001c8pi\u0006$\u0018n\u001c8\u0002\u000f5,7o]1hKB\u0011\u0011\u0004\t\b\u00035y\u0001\"a\u0007\u0006\u000e\u0003qQ!!\b\u0007\u0002\rq\u0012xn\u001c;?\u0013\ty\"\"\u0001\u0004Qe\u0016$WMZ\u0005\u0003C\t\u0012aa\u0015;sS:<\'BA\u0010\u000b\u0003\u0015\u0019\u0018N\\2f\u0003\u0019a\u0014N\\5u}Q\u0019a\u0005K\u0015\u0011\u0005\u001d\u0002Q\"\u0001\u0006\t\u000f]\u0019\u0001\u0013!a\u00011!91e\u0001I\u0001\u0002\u0004A\u0002F\u0002\u0001,/9\u001a\u0003\u0007\u0005\u0002(Y%\u0011QF\u0003\u0002\u0016I\u0016\u0004(/Z2bi\u0016$\u0017J\u001c5fe&$\u0018M\\2fC\u0005y\u0013aJ*dQ\u0016$W\u000f\\3eA\u0019|\'\u000f\t2fS:<\u0007EZ5oC2\u0004\u0013N\u001c\u0011uQ\u0016\u0004c-\u001e;ve\u0016\f\u0013!M\u0001\u0007e9\n4G\f\u0019)\u0005\u0001\u0019\u0004C\u0001\u001b8\u001b\u0005)$B\u0001\u001c\u0011\u0003\u0011iW\r^1\n\u0005a*$!\u00024jK2$\u0007F\u0001\u0001;!\t!4(\u0003\u0002=k\tQ!-Z1o\'\u0016$H/\u001a:)\u0005\u0001q\u0004C\u0001\u001b@\u0013\t\u0001UG\u0001\u0006cK\u0006tw)\u001a;uKJD#\u0001\u0001\"\u0011\u0005Q\u001a\u0015B\u0001#6\u0005\u0019\u0019X\r\u001e;fe\"\u0012\u0001A\u0012\t\u0003i\u001dK!\u0001S\u001b\u0003\r\u001d,G\u000f^3s\u0003)!W\r\u001d:fG\u0006$X\r\u001a\t\u0003O\u0015\u0019\"!\u0002\'\u0011\u0005\u001dj\u0015B\u0001(\u000b\u0005\u0019\te.\u001f*fMR\t!*A\u000e%Y\u0016\u001c8/\u001b8ji\u0012:\'/Z1uKJ$C-\u001a4bk2$H%M\u000b\u0002%*\u0012\u0001dU\u0016\u0002)B\u0011Q\u000bW\u0007\u0002-*\u0011q\u000bE\u0001\nk:\u001c\u0007.Z2lK\u0012L!!\u0017,\u0003#Ut7\r[3dW\u0016$g+\u0019:jC:\u001cW-A\u000e%Y\u0016\u001c8/\u001b8ji\u0012:\'/Z1uKJ$C-\u001a4bk2$HE\r"
    )
  ScalaInlineInfo: length = 0x9 (unknown attribute)
   01 00 00 01 00 16 00 17 00
  ScalaSig: length = 0x3 (unknown attribute)
   05 02 00
