Classfile /Users/mw/Projects/slang-braindump/.jar/jar8/assemble/slang-braindump/assemble/content/scala/Function2.class
  Last modified May 29, 2022; size 20683 bytes
  SHA-256 checksum 68c159a5d4569ffa308004054ce539b64c83f6dafe0d2a1b65268a7502a1bf9b
  Compiled from "Function2.scala"
public interface scala.Function2<T1 extends java.lang.Object, T2 extends java.lang.Object, R extends java.lang.Object>
  minor version: 0
  major version: 52
  flags: (0x0601) ACC_PUBLIC, ACC_INTERFACE, ACC_ABSTRACT
  this_class: #2                          // scala/Function2
  super_class: #5                         // java/lang/Object
  interfaces: 0, fields: 0, methods: 120, attributes: 7
Constant pool:
    #1 = Utf8               scala/Function2
    #2 = Class              #1            // scala/Function2
    #3 = Utf8               <T1:Ljava/lang/Object;T2:Ljava/lang/Object;R:Ljava/lang/Object;>Ljava/lang/Object;
    #4 = Utf8               java/lang/Object
    #5 = Class              #4            // java/lang/Object
    #6 = Utf8               Function2.scala
    #7 = Utf8               Lscala/reflect/ScalaSignature;
    #8 = Utf8               bytes
    #9 = Utf8               \u0006\u0005i4qAB\u0004\u0011\u0002\u0007\u0005!\u0002C\u0003\u0011\u0001\u0011\u0005\u0011\u0003C\u0003\u0016\u0001\u0019\u0005a\u0003C\u0003Z\u0001\u0011\u0005!\fC\u0003g\u0001\u0011\u0005q\rC\u0003n\u0001\u0011\u0005cNA\u0005Gk:\u001cG/[8oe)\t\u0001\"A\u0003tG\u0006d\u0017m\u0001\u0001\u0016\t-1E+G\n\u0003\u00011\u0001\"!\u0004\b\u000e\u0003\u001dI!aD\u0004\u0003\r\u0005s\u0017PU3g\u0003\u0019!\u0013N\\5uIQ\t!\u0003\u0005\u0002\u000e\'%\u0011Ac\u0002\u0002\u0005+:LG/A\u0003baBd\u0017\u0010F\u0002\u0018\u0007F\u0003\"\u0001G\r\r\u0001\u0011I!\u0004\u0001Q\u0001\u0002\u0013\u0015\ra\u0007\u0002\u0002%F\u0011Ad\b\t\u0003\u001buI!AH\u0004\u0003\u000f9{G\u000f[5oOB\u0011Q\u0002I\u0005\u0003C\u001d\u00111!\u00118zQ\rI2E\n\t\u0003\u001b\u0011J!!J\u0004\u0003\u0017M\u0004XmY5bY&TX\rZ\u0019\u0006G\u001d\u0002%)\u0011\t\u0004Q-rcBA\u0007*\u0013\tQs!A\u0007Ta\u0016\u001c\u0017.\u00197ju\u0006\u0014G.Z\u0005\u0003Y5\u0012Qa\u0012:pkBT!AK\u0004\u0011\u00115y\u0013\u0007N\u001c;{II!\u0001M\u0004\u0003\rQ+\b\u000f\\37!\ti!\'\u0003\u00024\u000f\t\u0019\u0011J\u001c;\u0011\u00055)\u0014B\u0001\u001c\b\u0005\u0011auN\\4\u0011\u00055A\u0014BA\u001d\b\u0005\u00151En\\1u!\ti1(\u0003\u0002=\u000f\t1Ai\\;cY\u0016\u0004\"!\u0004 \n\u0005}:!a\u0002\"p_2,\u0017M\\\u0005\u0003\u00036\naAU3ukJt\u0017\u0007\u0002\u0013)S)BQ\u0001\u0012\u0002A\u0002\u0015\u000b!A^\u0019\u0011\u0005a1E!C$\u0001A\u0003\u0005\tR1\u0001\u001c\u0005\t!\u0016\u0007K\u0002GG%\u000bTa\t&O!>\u00032\u0001K\u0016L!\u0015iA*\r\u001b;\u0013\tiuA\u0001\u0004UkBdWmM\u0005\u0003\u001f6\nA!\u0011:hgF\"A\u0005K\u0015+\u0011\u0015\u0011&\u00011\u0001T\u0003\t1(\u0007\u0005\u0002\u0019)\u0012IQ\u000b\u0001Q\u0001\u0002#\u0015\ra\u0007\u0002\u0003)JB3\u0001V\u0012Xc\u0015\u0019#J\u0014-Pc\u0011!\u0003&\u000b\u0016\u0002\u000f\r,(O]5fIV\t1\f\u0005\u0003\u000e9\u0016s\u0016BA/\b\u0005%1UO\\2uS>t\u0017\u0007\u0005\u0003\u000e9N;\u0002FA\u0002a!\t\tG-D\u0001c\u0015\t\u0019w!\u0001\u0006b]:|G/\u0019;j_:L!!\u001a2\u0003\u001bUt7\u000f]3dS\u0006d\u0017N_3e\u0003\u0019!X\u000f\u001d7fIV\t\u0001\u000e\u0005\u0003\u000e9&<\u0002\u0003B\u0007k\u000bNK!a[\u0004\u0003\rQ+\b\u000f\\33Q\t!\u0001-\u0001\u0005u_N#(/\u001b8h)\u0005y\u0007C\u00019x\u001d\t\tX\u000f\u0005\u0002s\u000f5\t1O\u0003\u0002u\u0013\u00051AH]8pizJ!A^\u0004\u0002\rA\u0013X\rZ3g\u0013\tA\u0018P\u0001\u0004TiJLgn\u001a\u0006\u0003m\u001e\u0001
   #10 = Utf8               java/lang/invoke/MethodHandles$Lookup
   #11 = Class              #10           // java/lang/invoke/MethodHandles$Lookup
   #12 = Utf8               java/lang/invoke/MethodHandles
   #13 = Class              #12           // java/lang/invoke/MethodHandles
   #14 = Utf8               Lookup
   #15 = Utf8               apply
   #16 = Utf8               (Ljava/lang/Object;Ljava/lang/Object;)Ljava/lang/Object;
   #17 = Utf8               (TT1;TT2;)TR;
   #18 = Utf8               v1
   #19 = Utf8               v2
   #20 = Utf8               curried$
   #21 = Utf8               (Lscala/Function2;)Lscala/Function1;
   #22 = Utf8               $this
   #23 = Utf8               curried
   #24 = Utf8               ()Lscala/Function1;
   #25 = NameAndType        #23:#24       // curried:()Lscala/Function1;
   #26 = InterfaceMethodref #2.#25        // scala/Function2.curried:()Lscala/Function1;
   #27 = Utf8               Lscala/Function2;
   #28 = Utf8               ()Lscala/Function1<TT1;Lscala/Function1<TT2;TR;>;>;
   #29 = Utf8               (Ljava/lang/Object;)Ljava/lang/Object;
   #30 = MethodType         #29           //  (Ljava/lang/Object;)Ljava/lang/Object;
   #31 = Utf8               $anonfun$curried$1
   #32 = Utf8               (Lscala/Function2;Ljava/lang/Object;)Lscala/Function1;
   #33 = NameAndType        #31:#32       // $anonfun$curried$1:(Lscala/Function2;Ljava/lang/Object;)Lscala/Function1;
   #34 = InterfaceMethodref #2.#33        // scala/Function2.$anonfun$curried$1:(Lscala/Function2;Ljava/lang/Object;)Lscala/Function1;
   #35 = MethodHandle       6:#34         // REF_invokeStatic scala/Function2.$anonfun$curried$1:(Lscala/Function2;Ljava/lang/Object;)Lscala/Function1;
   #36 = Utf8               (Ljava/lang/Object;)Lscala/Function1;
   #37 = MethodType         #36           //  (Ljava/lang/Object;)Lscala/Function1;
   #38 = Integer            5
   #39 = Integer            1
   #40 = Utf8               java/lang/invoke/LambdaMetafactory
   #41 = Class              #40           // java/lang/invoke/LambdaMetafactory
   #42 = Utf8               altMetafactory
   #43 = Utf8               (Ljava/lang/invoke/MethodHandles$Lookup;Ljava/lang/String;Ljava/lang/invoke/MethodType;[Ljava/lang/Object;)Ljava/lang/invoke/CallSite;
   #44 = NameAndType        #42:#43       // altMetafactory:(Ljava/lang/invoke/MethodHandles$Lookup;Ljava/lang/String;Ljava/lang/invoke/MethodType;[Ljava/lang/Object;)Ljava/lang/invoke/CallSite;
   #45 = Methodref          #41.#44       // java/lang/invoke/LambdaMetafactory.altMetafactory:(Ljava/lang/invoke/MethodHandles$Lookup;Ljava/lang/String;Ljava/lang/invoke/MethodType;[Ljava/lang/Object;)Ljava/lang/invoke/CallSite;
   #46 = MethodHandle       6:#45         // REF_invokeStatic java/lang/invoke/LambdaMetafactory.altMetafactory:(Ljava/lang/invoke/MethodHandles$Lookup;Ljava/lang/String;Ljava/lang/invoke/MethodType;[Ljava/lang/Object;)Ljava/lang/invoke/CallSite;
   #47 = NameAndType        #15:#21       // apply:(Lscala/Function2;)Lscala/Function1;
   #48 = InvokeDynamic      #0:#47        // #0:apply:(Lscala/Function2;)Lscala/Function1;
   #49 = Utf8               this
   #50 = Utf8               tupled$
   #51 = Utf8               tupled
   #52 = NameAndType        #51:#24       // tupled:()Lscala/Function1;
   #53 = InterfaceMethodref #2.#52        // scala/Function2.tupled:()Lscala/Function1;
   #54 = Utf8               ()Lscala/Function1<Lscala/Tuple2<TT1;TT2;>;TR;>;
   #55 = Utf8               $anonfun$tupled$1
   #56 = Utf8               (Lscala/Function2;Lscala/Tuple2;)Ljava/lang/Object;
   #57 = NameAndType        #55:#56       // $anonfun$tupled$1:(Lscala/Function2;Lscala/Tuple2;)Ljava/lang/Object;
   #58 = InterfaceMethodref #2.#57        // scala/Function2.$anonfun$tupled$1:(Lscala/Function2;Lscala/Tuple2;)Ljava/lang/Object;
   #59 = MethodHandle       6:#58         // REF_invokeStatic scala/Function2.$anonfun$tupled$1:(Lscala/Function2;Lscala/Tuple2;)Ljava/lang/Object;
   #60 = Utf8               (Lscala/Tuple2;)Ljava/lang/Object;
   #61 = MethodType         #60           //  (Lscala/Tuple2;)Ljava/lang/Object;
   #62 = InvokeDynamic      #1:#47        // #1:apply:(Lscala/Function2;)Lscala/Function1;
   #63 = Utf8               toString$
   #64 = Utf8               (Lscala/Function2;)Ljava/lang/String;
   #65 = Utf8               toString
   #66 = Utf8               ()Ljava/lang/String;
   #67 = NameAndType        #65:#66       // toString:()Ljava/lang/String;
   #68 = InterfaceMethodref #2.#67        // scala/Function2.toString:()Ljava/lang/String;
   #69 = Utf8               <function2>
   #70 = String             #69           // <function2>
   #71 = Utf8               apply$mcZDD$sp$
   #72 = Utf8               (Lscala/Function2;DD)Z
   #73 = Utf8               apply$mcZDD$sp
   #74 = Utf8               (DD)Z
   #75 = NameAndType        #73:#74       // apply$mcZDD$sp:(DD)Z
   #76 = InterfaceMethodref #2.#75        // scala/Function2.apply$mcZDD$sp:(DD)Z
   #77 = Utf8               D
   #78 = Utf8               java/lang/Double
   #79 = Class              #78           // java/lang/Double
   #80 = Utf8               valueOf
   #81 = Utf8               (D)Ljava/lang/Double;
   #82 = NameAndType        #80:#81       // valueOf:(D)Ljava/lang/Double;
   #83 = Methodref          #79.#82       // java/lang/Double.valueOf:(D)Ljava/lang/Double;
   #84 = NameAndType        #15:#16       // apply:(Ljava/lang/Object;Ljava/lang/Object;)Ljava/lang/Object;
   #85 = InterfaceMethodref #2.#84        // scala/Function2.apply:(Ljava/lang/Object;Ljava/lang/Object;)Ljava/lang/Object;
   #86 = Utf8               scala/runtime/BoxesRunTime
   #87 = Class              #86           // scala/runtime/BoxesRunTime
   #88 = Utf8               unboxToBoolean
   #89 = Utf8               (Ljava/lang/Object;)Z
   #90 = NameAndType        #88:#89       // unboxToBoolean:(Ljava/lang/Object;)Z
   #91 = Methodref          #87.#90       // scala/runtime/BoxesRunTime.unboxToBoolean:(Ljava/lang/Object;)Z
   #92 = Utf8               apply$mcDDD$sp$
   #93 = Utf8               (Lscala/Function2;DD)D
   #94 = Utf8               apply$mcDDD$sp
   #95 = Utf8               (DD)D
   #96 = NameAndType        #94:#95       // apply$mcDDD$sp:(DD)D
   #97 = InterfaceMethodref #2.#96        // scala/Function2.apply$mcDDD$sp:(DD)D
   #98 = Utf8               unboxToDouble
   #99 = Utf8               (Ljava/lang/Object;)D
  #100 = NameAndType        #98:#99       // unboxToDouble:(Ljava/lang/Object;)D
  #101 = Methodref          #87.#100      // scala/runtime/BoxesRunTime.unboxToDouble:(Ljava/lang/Object;)D
  #102 = Utf8               apply$mcFDD$sp$
  #103 = Utf8               (Lscala/Function2;DD)F
  #104 = Utf8               apply$mcFDD$sp
  #105 = Utf8               (DD)F
  #106 = NameAndType        #104:#105     // apply$mcFDD$sp:(DD)F
  #107 = InterfaceMethodref #2.#106       // scala/Function2.apply$mcFDD$sp:(DD)F
  #108 = Utf8               unboxToFloat
  #109 = Utf8               (Ljava/lang/Object;)F
  #110 = NameAndType        #108:#109     // unboxToFloat:(Ljava/lang/Object;)F
  #111 = Methodref          #87.#110      // scala/runtime/BoxesRunTime.unboxToFloat:(Ljava/lang/Object;)F
  #112 = Utf8               apply$mcIDD$sp$
  #113 = Utf8               (Lscala/Function2;DD)I
  #114 = Utf8               apply$mcIDD$sp
  #115 = Utf8               (DD)I
  #116 = NameAndType        #114:#115     // apply$mcIDD$sp:(DD)I
  #117 = InterfaceMethodref #2.#116       // scala/Function2.apply$mcIDD$sp:(DD)I
  #118 = Utf8               unboxToInt
  #119 = Utf8               (Ljava/lang/Object;)I
  #120 = NameAndType        #118:#119     // unboxToInt:(Ljava/lang/Object;)I
  #121 = Methodref          #87.#120      // scala/runtime/BoxesRunTime.unboxToInt:(Ljava/lang/Object;)I
  #122 = Utf8               apply$mcJDD$sp$
  #123 = Utf8               (Lscala/Function2;DD)J
  #124 = Utf8               apply$mcJDD$sp
  #125 = Utf8               (DD)J
  #126 = NameAndType        #124:#125     // apply$mcJDD$sp:(DD)J
  #127 = InterfaceMethodref #2.#126       // scala/Function2.apply$mcJDD$sp:(DD)J
  #128 = Utf8               unboxToLong
  #129 = Utf8               (Ljava/lang/Object;)J
  #130 = NameAndType        #128:#129     // unboxToLong:(Ljava/lang/Object;)J
  #131 = Methodref          #87.#130      // scala/runtime/BoxesRunTime.unboxToLong:(Ljava/lang/Object;)J
  #132 = Utf8               apply$mcVDD$sp$
  #133 = Utf8               (Lscala/Function2;DD)V
  #134 = Utf8               apply$mcVDD$sp
  #135 = Utf8               (DD)V
  #136 = NameAndType        #134:#135     // apply$mcVDD$sp:(DD)V
  #137 = InterfaceMethodref #2.#136       // scala/Function2.apply$mcVDD$sp:(DD)V
  #138 = Utf8               apply$mcZDI$sp$
  #139 = Utf8               (Lscala/Function2;DI)Z
  #140 = Utf8               apply$mcZDI$sp
  #141 = Utf8               (DI)Z
  #142 = NameAndType        #140:#141     // apply$mcZDI$sp:(DI)Z
  #143 = InterfaceMethodref #2.#142       // scala/Function2.apply$mcZDI$sp:(DI)Z
  #144 = Utf8               I
  #145 = Utf8               java/lang/Integer
  #146 = Class              #145          // java/lang/Integer
  #147 = Utf8               (I)Ljava/lang/Integer;
  #148 = NameAndType        #80:#147      // valueOf:(I)Ljava/lang/Integer;
  #149 = Methodref          #146.#148     // java/lang/Integer.valueOf:(I)Ljava/lang/Integer;
  #150 = Utf8               apply$mcDDI$sp$
  #151 = Utf8               (Lscala/Function2;DI)D
  #152 = Utf8               apply$mcDDI$sp
  #153 = Utf8               (DI)D
  #154 = NameAndType        #152:#153     // apply$mcDDI$sp:(DI)D
  #155 = InterfaceMethodref #2.#154       // scala/Function2.apply$mcDDI$sp:(DI)D
  #156 = Utf8               apply$mcFDI$sp$
  #157 = Utf8               (Lscala/Function2;DI)F
  #158 = Utf8               apply$mcFDI$sp
  #159 = Utf8               (DI)F
  #160 = NameAndType        #158:#159     // apply$mcFDI$sp:(DI)F
  #161 = InterfaceMethodref #2.#160       // scala/Function2.apply$mcFDI$sp:(DI)F
  #162 = Utf8               apply$mcIDI$sp$
  #163 = Utf8               (Lscala/Function2;DI)I
  #164 = Utf8               apply$mcIDI$sp
  #165 = Utf8               (DI)I
  #166 = NameAndType        #164:#165     // apply$mcIDI$sp:(DI)I
  #167 = InterfaceMethodref #2.#166       // scala/Function2.apply$mcIDI$sp:(DI)I
  #168 = Utf8               apply$mcJDI$sp$
  #169 = Utf8               (Lscala/Function2;DI)J
  #170 = Utf8               apply$mcJDI$sp
  #171 = Utf8               (DI)J
  #172 = NameAndType        #170:#171     // apply$mcJDI$sp:(DI)J
  #173 = InterfaceMethodref #2.#172       // scala/Function2.apply$mcJDI$sp:(DI)J
  #174 = Utf8               apply$mcVDI$sp$
  #175 = Utf8               (Lscala/Function2;DI)V
  #176 = Utf8               apply$mcVDI$sp
  #177 = Utf8               (DI)V
  #178 = NameAndType        #176:#177     // apply$mcVDI$sp:(DI)V
  #179 = InterfaceMethodref #2.#178       // scala/Function2.apply$mcVDI$sp:(DI)V
  #180 = Utf8               apply$mcZDJ$sp$
  #181 = Utf8               (Lscala/Function2;DJ)Z
  #182 = Utf8               apply$mcZDJ$sp
  #183 = Utf8               (DJ)Z
  #184 = NameAndType        #182:#183     // apply$mcZDJ$sp:(DJ)Z
  #185 = InterfaceMethodref #2.#184       // scala/Function2.apply$mcZDJ$sp:(DJ)Z
  #186 = Utf8               J
  #187 = Utf8               java/lang/Long
  #188 = Class              #187          // java/lang/Long
  #189 = Utf8               (J)Ljava/lang/Long;
  #190 = NameAndType        #80:#189      // valueOf:(J)Ljava/lang/Long;
  #191 = Methodref          #188.#190     // java/lang/Long.valueOf:(J)Ljava/lang/Long;
  #192 = Utf8               apply$mcDDJ$sp$
  #193 = Utf8               (Lscala/Function2;DJ)D
  #194 = Utf8               apply$mcDDJ$sp
  #195 = Utf8               (DJ)D
  #196 = NameAndType        #194:#195     // apply$mcDDJ$sp:(DJ)D
  #197 = InterfaceMethodref #2.#196       // scala/Function2.apply$mcDDJ$sp:(DJ)D
  #198 = Utf8               apply$mcFDJ$sp$
  #199 = Utf8               (Lscala/Function2;DJ)F
  #200 = Utf8               apply$mcFDJ$sp
  #201 = Utf8               (DJ)F
  #202 = NameAndType        #200:#201     // apply$mcFDJ$sp:(DJ)F
  #203 = InterfaceMethodref #2.#202       // scala/Function2.apply$mcFDJ$sp:(DJ)F
  #204 = Utf8               apply$mcIDJ$sp$
  #205 = Utf8               (Lscala/Function2;DJ)I
  #206 = Utf8               apply$mcIDJ$sp
  #207 = Utf8               (DJ)I
  #208 = NameAndType        #206:#207     // apply$mcIDJ$sp:(DJ)I
  #209 = InterfaceMethodref #2.#208       // scala/Function2.apply$mcIDJ$sp:(DJ)I
  #210 = Utf8               apply$mcJDJ$sp$
  #211 = Utf8               (Lscala/Function2;DJ)J
  #212 = Utf8               apply$mcJDJ$sp
  #213 = Utf8               (DJ)J
  #214 = NameAndType        #212:#213     // apply$mcJDJ$sp:(DJ)J
  #215 = InterfaceMethodref #2.#214       // scala/Function2.apply$mcJDJ$sp:(DJ)J
  #216 = Utf8               apply$mcVDJ$sp$
  #217 = Utf8               (Lscala/Function2;DJ)V
  #218 = Utf8               apply$mcVDJ$sp
  #219 = Utf8               (DJ)V
  #220 = NameAndType        #218:#219     // apply$mcVDJ$sp:(DJ)V
  #221 = InterfaceMethodref #2.#220       // scala/Function2.apply$mcVDJ$sp:(DJ)V
  #222 = Utf8               apply$mcZID$sp$
  #223 = Utf8               (Lscala/Function2;ID)Z
  #224 = Utf8               apply$mcZID$sp
  #225 = Utf8               (ID)Z
  #226 = NameAndType        #224:#225     // apply$mcZID$sp:(ID)Z
  #227 = InterfaceMethodref #2.#226       // scala/Function2.apply$mcZID$sp:(ID)Z
  #228 = Utf8               apply$mcDID$sp$
  #229 = Utf8               (Lscala/Function2;ID)D
  #230 = Utf8               apply$mcDID$sp
  #231 = Utf8               (ID)D
  #232 = NameAndType        #230:#231     // apply$mcDID$sp:(ID)D
  #233 = InterfaceMethodref #2.#232       // scala/Function2.apply$mcDID$sp:(ID)D
  #234 = Utf8               apply$mcFID$sp$
  #235 = Utf8               (Lscala/Function2;ID)F
  #236 = Utf8               apply$mcFID$sp
  #237 = Utf8               (ID)F
  #238 = NameAndType        #236:#237     // apply$mcFID$sp:(ID)F
  #239 = InterfaceMethodref #2.#238       // scala/Function2.apply$mcFID$sp:(ID)F
  #240 = Utf8               apply$mcIID$sp$
  #241 = Utf8               (Lscala/Function2;ID)I
  #242 = Utf8               apply$mcIID$sp
  #243 = Utf8               (ID)I
  #244 = NameAndType        #242:#243     // apply$mcIID$sp:(ID)I
  #245 = InterfaceMethodref #2.#244       // scala/Function2.apply$mcIID$sp:(ID)I
  #246 = Utf8               apply$mcJID$sp$
  #247 = Utf8               (Lscala/Function2;ID)J
  #248 = Utf8               apply$mcJID$sp
  #249 = Utf8               (ID)J
  #250 = NameAndType        #248:#249     // apply$mcJID$sp:(ID)J
  #251 = InterfaceMethodref #2.#250       // scala/Function2.apply$mcJID$sp:(ID)J
  #252 = Utf8               apply$mcVID$sp$
  #253 = Utf8               (Lscala/Function2;ID)V
  #254 = Utf8               apply$mcVID$sp
  #255 = Utf8               (ID)V
  #256 = NameAndType        #254:#255     // apply$mcVID$sp:(ID)V
  #257 = InterfaceMethodref #2.#256       // scala/Function2.apply$mcVID$sp:(ID)V
  #258 = Utf8               apply$mcZII$sp$
  #259 = Utf8               (Lscala/Function2;II)Z
  #260 = Utf8               apply$mcZII$sp
  #261 = Utf8               (II)Z
  #262 = NameAndType        #260:#261     // apply$mcZII$sp:(II)Z
  #263 = InterfaceMethodref #2.#262       // scala/Function2.apply$mcZII$sp:(II)Z
  #264 = Utf8               apply$mcDII$sp$
  #265 = Utf8               (Lscala/Function2;II)D
  #266 = Utf8               apply$mcDII$sp
  #267 = Utf8               (II)D
  #268 = NameAndType        #266:#267     // apply$mcDII$sp:(II)D
  #269 = InterfaceMethodref #2.#268       // scala/Function2.apply$mcDII$sp:(II)D
  #270 = Utf8               apply$mcFII$sp$
  #271 = Utf8               (Lscala/Function2;II)F
  #272 = Utf8               apply$mcFII$sp
  #273 = Utf8               (II)F
  #274 = NameAndType        #272:#273     // apply$mcFII$sp:(II)F
  #275 = InterfaceMethodref #2.#274       // scala/Function2.apply$mcFII$sp:(II)F
  #276 = Utf8               apply$mcIII$sp$
  #277 = Utf8               (Lscala/Function2;II)I
  #278 = Utf8               apply$mcIII$sp
  #279 = Utf8               (II)I
  #280 = NameAndType        #278:#279     // apply$mcIII$sp:(II)I
  #281 = InterfaceMethodref #2.#280       // scala/Function2.apply$mcIII$sp:(II)I
  #282 = Utf8               apply$mcJII$sp$
  #283 = Utf8               (Lscala/Function2;II)J
  #284 = Utf8               apply$mcJII$sp
  #285 = Utf8               (II)J
  #286 = NameAndType        #284:#285     // apply$mcJII$sp:(II)J
  #287 = InterfaceMethodref #2.#286       // scala/Function2.apply$mcJII$sp:(II)J
  #288 = Utf8               apply$mcVII$sp$
  #289 = Utf8               (Lscala/Function2;II)V
  #290 = Utf8               apply$mcVII$sp
  #291 = Utf8               (II)V
  #292 = NameAndType        #290:#291     // apply$mcVII$sp:(II)V
  #293 = InterfaceMethodref #2.#292       // scala/Function2.apply$mcVII$sp:(II)V
  #294 = Utf8               apply$mcZIJ$sp$
  #295 = Utf8               (Lscala/Function2;IJ)Z
  #296 = Utf8               apply$mcZIJ$sp
  #297 = Utf8               (IJ)Z
  #298 = NameAndType        #296:#297     // apply$mcZIJ$sp:(IJ)Z
  #299 = InterfaceMethodref #2.#298       // scala/Function2.apply$mcZIJ$sp:(IJ)Z
  #300 = Utf8               apply$mcDIJ$sp$
  #301 = Utf8               (Lscala/Function2;IJ)D
  #302 = Utf8               apply$mcDIJ$sp
  #303 = Utf8               (IJ)D
  #304 = NameAndType        #302:#303     // apply$mcDIJ$sp:(IJ)D
  #305 = InterfaceMethodref #2.#304       // scala/Function2.apply$mcDIJ$sp:(IJ)D
  #306 = Utf8               apply$mcFIJ$sp$
  #307 = Utf8               (Lscala/Function2;IJ)F
  #308 = Utf8               apply$mcFIJ$sp
  #309 = Utf8               (IJ)F
  #310 = NameAndType        #308:#309     // apply$mcFIJ$sp:(IJ)F
  #311 = InterfaceMethodref #2.#310       // scala/Function2.apply$mcFIJ$sp:(IJ)F
  #312 = Utf8               apply$mcIIJ$sp$
  #313 = Utf8               (Lscala/Function2;IJ)I
  #314 = Utf8               apply$mcIIJ$sp
  #315 = Utf8               (IJ)I
  #316 = NameAndType        #314:#315     // apply$mcIIJ$sp:(IJ)I
  #317 = InterfaceMethodref #2.#316       // scala/Function2.apply$mcIIJ$sp:(IJ)I
  #318 = Utf8               apply$mcJIJ$sp$
  #319 = Utf8               (Lscala/Function2;IJ)J
  #320 = Utf8               apply$mcJIJ$sp
  #321 = Utf8               (IJ)J
  #322 = NameAndType        #320:#321     // apply$mcJIJ$sp:(IJ)J
  #323 = InterfaceMethodref #2.#322       // scala/Function2.apply$mcJIJ$sp:(IJ)J
  #324 = Utf8               apply$mcVIJ$sp$
  #325 = Utf8               (Lscala/Function2;IJ)V
  #326 = Utf8               apply$mcVIJ$sp
  #327 = Utf8               (IJ)V
  #328 = NameAndType        #326:#327     // apply$mcVIJ$sp:(IJ)V
  #329 = InterfaceMethodref #2.#328       // scala/Function2.apply$mcVIJ$sp:(IJ)V
  #330 = Utf8               apply$mcZJD$sp$
  #331 = Utf8               (Lscala/Function2;JD)Z
  #332 = Utf8               apply$mcZJD$sp
  #333 = Utf8               (JD)Z
  #334 = NameAndType        #332:#333     // apply$mcZJD$sp:(JD)Z
  #335 = InterfaceMethodref #2.#334       // scala/Function2.apply$mcZJD$sp:(JD)Z
  #336 = Utf8               apply$mcDJD$sp$
  #337 = Utf8               (Lscala/Function2;JD)D
  #338 = Utf8               apply$mcDJD$sp
  #339 = Utf8               (JD)D
  #340 = NameAndType        #338:#339     // apply$mcDJD$sp:(JD)D
  #341 = InterfaceMethodref #2.#340       // scala/Function2.apply$mcDJD$sp:(JD)D
  #342 = Utf8               apply$mcFJD$sp$
  #343 = Utf8               (Lscala/Function2;JD)F
  #344 = Utf8               apply$mcFJD$sp
  #345 = Utf8               (JD)F
  #346 = NameAndType        #344:#345     // apply$mcFJD$sp:(JD)F
  #347 = InterfaceMethodref #2.#346       // scala/Function2.apply$mcFJD$sp:(JD)F
  #348 = Utf8               apply$mcIJD$sp$
  #349 = Utf8               (Lscala/Function2;JD)I
  #350 = Utf8               apply$mcIJD$sp
  #351 = Utf8               (JD)I
  #352 = NameAndType        #350:#351     // apply$mcIJD$sp:(JD)I
  #353 = InterfaceMethodref #2.#352       // scala/Function2.apply$mcIJD$sp:(JD)I
  #354 = Utf8               apply$mcJJD$sp$
  #355 = Utf8               (Lscala/Function2;JD)J
  #356 = Utf8               apply$mcJJD$sp
  #357 = Utf8               (JD)J
  #358 = NameAndType        #356:#357     // apply$mcJJD$sp:(JD)J
  #359 = InterfaceMethodref #2.#358       // scala/Function2.apply$mcJJD$sp:(JD)J
  #360 = Utf8               apply$mcVJD$sp$
  #361 = Utf8               (Lscala/Function2;JD)V
  #362 = Utf8               apply$mcVJD$sp
  #363 = Utf8               (JD)V
  #364 = NameAndType        #362:#363     // apply$mcVJD$sp:(JD)V
  #365 = InterfaceMethodref #2.#364       // scala/Function2.apply$mcVJD$sp:(JD)V
  #366 = Utf8               apply$mcZJI$sp$
  #367 = Utf8               (Lscala/Function2;JI)Z
  #368 = Utf8               apply$mcZJI$sp
  #369 = Utf8               (JI)Z
  #370 = NameAndType        #368:#369     // apply$mcZJI$sp:(JI)Z
  #371 = InterfaceMethodref #2.#370       // scala/Function2.apply$mcZJI$sp:(JI)Z
  #372 = Utf8               apply$mcDJI$sp$
  #373 = Utf8               (Lscala/Function2;JI)D
  #374 = Utf8               apply$mcDJI$sp
  #375 = Utf8               (JI)D
  #376 = NameAndType        #374:#375     // apply$mcDJI$sp:(JI)D
  #377 = InterfaceMethodref #2.#376       // scala/Function2.apply$mcDJI$sp:(JI)D
  #378 = Utf8               apply$mcFJI$sp$
  #379 = Utf8               (Lscala/Function2;JI)F
  #380 = Utf8               apply$mcFJI$sp
  #381 = Utf8               (JI)F
  #382 = NameAndType        #380:#381     // apply$mcFJI$sp:(JI)F
  #383 = InterfaceMethodref #2.#382       // scala/Function2.apply$mcFJI$sp:(JI)F
  #384 = Utf8               apply$mcIJI$sp$
  #385 = Utf8               (Lscala/Function2;JI)I
  #386 = Utf8               apply$mcIJI$sp
  #387 = Utf8               (JI)I
  #388 = NameAndType        #386:#387     // apply$mcIJI$sp:(JI)I
  #389 = InterfaceMethodref #2.#388       // scala/Function2.apply$mcIJI$sp:(JI)I
  #390 = Utf8               apply$mcJJI$sp$
  #391 = Utf8               (Lscala/Function2;JI)J
  #392 = Utf8               apply$mcJJI$sp
  #393 = Utf8               (JI)J
  #394 = NameAndType        #392:#393     // apply$mcJJI$sp:(JI)J
  #395 = InterfaceMethodref #2.#394       // scala/Function2.apply$mcJJI$sp:(JI)J
  #396 = Utf8               apply$mcVJI$sp$
  #397 = Utf8               (Lscala/Function2;JI)V
  #398 = Utf8               apply$mcVJI$sp
  #399 = Utf8               (JI)V
  #400 = NameAndType        #398:#399     // apply$mcVJI$sp:(JI)V
  #401 = InterfaceMethodref #2.#400       // scala/Function2.apply$mcVJI$sp:(JI)V
  #402 = Utf8               apply$mcZJJ$sp$
  #403 = Utf8               (Lscala/Function2;JJ)Z
  #404 = Utf8               apply$mcZJJ$sp
  #405 = Utf8               (JJ)Z
  #406 = NameAndType        #404:#405     // apply$mcZJJ$sp:(JJ)Z
  #407 = InterfaceMethodref #2.#406       // scala/Function2.apply$mcZJJ$sp:(JJ)Z
  #408 = Utf8               apply$mcDJJ$sp$
  #409 = Utf8               (Lscala/Function2;JJ)D
  #410 = Utf8               apply$mcDJJ$sp
  #411 = Utf8               (JJ)D
  #412 = NameAndType        #410:#411     // apply$mcDJJ$sp:(JJ)D
  #413 = InterfaceMethodref #2.#412       // scala/Function2.apply$mcDJJ$sp:(JJ)D
  #414 = Utf8               apply$mcFJJ$sp$
  #415 = Utf8               (Lscala/Function2;JJ)F
  #416 = Utf8               apply$mcFJJ$sp
  #417 = Utf8               (JJ)F
  #418 = NameAndType        #416:#417     // apply$mcFJJ$sp:(JJ)F
  #419 = InterfaceMethodref #2.#418       // scala/Function2.apply$mcFJJ$sp:(JJ)F
  #420 = Utf8               apply$mcIJJ$sp$
  #421 = Utf8               (Lscala/Function2;JJ)I
  #422 = Utf8               apply$mcIJJ$sp
  #423 = Utf8               (JJ)I
  #424 = NameAndType        #422:#423     // apply$mcIJJ$sp:(JJ)I
  #425 = InterfaceMethodref #2.#424       // scala/Function2.apply$mcIJJ$sp:(JJ)I
  #426 = Utf8               apply$mcJJJ$sp$
  #427 = Utf8               (Lscala/Function2;JJ)J
  #428 = Utf8               apply$mcJJJ$sp
  #429 = Utf8               (JJ)J
  #430 = NameAndType        #428:#429     // apply$mcJJJ$sp:(JJ)J
  #431 = InterfaceMethodref #2.#430       // scala/Function2.apply$mcJJJ$sp:(JJ)J
  #432 = Utf8               apply$mcVJJ$sp$
  #433 = Utf8               (Lscala/Function2;JJ)V
  #434 = Utf8               apply$mcVJJ$sp
  #435 = Utf8               (JJ)V
  #436 = NameAndType        #434:#435     // apply$mcVJJ$sp:(JJ)V
  #437 = InterfaceMethodref #2.#436       // scala/Function2.apply$mcVJJ$sp:(JJ)V
  #438 = Utf8               $anonfun$curried$2
  #439 = Utf8               (Lscala/Function2;Ljava/lang/Object;Ljava/lang/Object;)Ljava/lang/Object;
  #440 = Utf8               x1$1
  #441 = Utf8               x2
  #442 = Utf8               Ljava/lang/Object;
  #443 = Utf8               x1
  #444 = NameAndType        #438:#439     // $anonfun$curried$2:(Lscala/Function2;Ljava/lang/Object;Ljava/lang/Object;)Ljava/lang/Object;
  #445 = InterfaceMethodref #2.#444       // scala/Function2.$anonfun$curried$2:(Lscala/Function2;Ljava/lang/Object;Ljava/lang/Object;)Ljava/lang/Object;
  #446 = MethodHandle       6:#445        // REF_invokeStatic scala/Function2.$anonfun$curried$2:(Lscala/Function2;Ljava/lang/Object;Ljava/lang/Object;)Ljava/lang/Object;
  #447 = NameAndType        #15:#32       // apply:(Lscala/Function2;Ljava/lang/Object;)Lscala/Function1;
  #448 = InvokeDynamic      #2:#447       // #2:apply:(Lscala/Function2;Ljava/lang/Object;)Lscala/Function1;
  #449 = Utf8               x0$1
  #450 = Utf8               scala/Tuple2
  #451 = Class              #450          // scala/Tuple2
  #452 = Utf8               _1
  #453 = Utf8               ()Ljava/lang/Object;
  #454 = NameAndType        #452:#453     // _1:()Ljava/lang/Object;
  #455 = Methodref          #451.#454     // scala/Tuple2._1:()Ljava/lang/Object;
  #456 = Utf8               _2
  #457 = NameAndType        #456:#453     // _2:()Ljava/lang/Object;
  #458 = Methodref          #451.#457     // scala/Tuple2._2:()Ljava/lang/Object;
  #459 = Utf8               scala/MatchError
  #460 = Class              #459          // scala/MatchError
  #461 = Utf8               <init>
  #462 = Utf8               (Ljava/lang/Object;)V
  #463 = NameAndType        #461:#462     // "<init>":(Ljava/lang/Object;)V
  #464 = Methodref          #460.#463     // scala/MatchError."<init>":(Ljava/lang/Object;)V
  #465 = Utf8               Lscala/Tuple2;
  #466 = Utf8               $init$
  #467 = Utf8               (Lscala/Function2;)V
  #468 = Utf8               $deserializeLambda$
  #469 = Utf8               (Ljava/lang/invoke/SerializedLambda;)Ljava/lang/Object;
  #470 = Utf8               scala/runtime/LambdaDeserialize
  #471 = Class              #470          // scala/runtime/LambdaDeserialize
  #472 = Utf8               bootstrap
  #473 = Utf8               (Ljava/lang/invoke/MethodHandles$Lookup;Ljava/lang/String;Ljava/lang/invoke/MethodType;[Ljava/lang/invoke/MethodHandle;)Ljava/lang/invoke/CallSite;
  #474 = NameAndType        #472:#473     // bootstrap:(Ljava/lang/invoke/MethodHandles$Lookup;Ljava/lang/String;Ljava/lang/invoke/MethodType;[Ljava/lang/invoke/MethodHandle;)Ljava/lang/invoke/CallSite;
  #475 = Methodref          #471.#474     // scala/runtime/LambdaDeserialize.bootstrap:(Ljava/lang/invoke/MethodHandles$Lookup;Ljava/lang/String;Ljava/lang/invoke/MethodType;[Ljava/lang/invoke/MethodHandle;)Ljava/lang/invoke/CallSite;
  #476 = MethodHandle       6:#475        // REF_invokeStatic scala/runtime/LambdaDeserialize.bootstrap:(Ljava/lang/invoke/MethodHandles$Lookup;Ljava/lang/String;Ljava/lang/invoke/MethodType;[Ljava/lang/invoke/MethodHandle;)Ljava/lang/invoke/CallSite;
  #477 = Utf8               lambdaDeserialize
  #478 = NameAndType        #477:#469     // lambdaDeserialize:(Ljava/lang/invoke/SerializedLambda;)Ljava/lang/Object;
  #479 = InvokeDynamic      #3:#478       // #3:lambdaDeserialize:(Ljava/lang/invoke/SerializedLambda;)Ljava/lang/Object;
  #480 = Utf8               Signature
  #481 = Utf8               MethodParameters
  #482 = Utf8               Code
  #483 = Utf8               LineNumberTable
  #484 = Utf8               LocalVariableTable
  #485 = Utf8               StackMapTable
  #486 = Utf8               InnerClasses
  #487 = Utf8               SourceFile
  #488 = Utf8               RuntimeVisibleAnnotations
  #489 = Utf8               BootstrapMethods
  #490 = Utf8               ScalaInlineInfo
  #491 = Utf8               ScalaSig
{
  public abstract R apply(T1, T2);
    descriptor: (Ljava/lang/Object;Ljava/lang/Object;)Ljava/lang/Object;
    flags: (0x0401) ACC_PUBLIC, ACC_ABSTRACT
    Signature: #17                          // (TT1;TT2;)TR;
    MethodParameters:
      Name                           Flags
      v1                             final
      v2                             final

  public static scala.Function1 curried$(scala.Function2);
    descriptor: (Lscala/Function2;)Lscala/Function1;
    flags: (0x1009) ACC_PUBLIC, ACC_STATIC, ACC_SYNTHETIC
    Code:
      stack=1, locals=1, args_size=1
         0: aload_0
         1: invokespecial #26                 // InterfaceMethod curried:()Lscala/Function1;
         4: areturn
      LineNumberTable:
        line 43: 0
      LocalVariableTable:
        Start  Length  Slot  Name   Signature
            0       5     0 $this   Lscala/Function2;
    MethodParameters:
      Name                           Flags
      $this                          final synthetic

  public default scala.Function1<T1, scala.Function1<T2, R>> curried();
    descriptor: ()Lscala/Function1;
    flags: (0x0001) ACC_PUBLIC
    Code:
      stack=1, locals=1, args_size=1
         0: aload_0
         1: invokedynamic #48,  0             // InvokeDynamic #0:apply:(Lscala/Function2;)Lscala/Function1;
         6: areturn
      LineNumberTable:
        line 44: 0
      LocalVariableTable:
        Start  Length  Slot  Name   Signature
            0       7     0  this   Lscala/Function2;
    Signature: #28                          // ()Lscala/Function1<TT1;Lscala/Function1<TT2;TR;>;>;

  public static scala.Function1 tupled$(scala.Function2);
    descriptor: (Lscala/Function2;)Lscala/Function1;
    flags: (0x1009) ACC_PUBLIC, ACC_STATIC, ACC_SYNTHETIC
    Code:
      stack=1, locals=1, args_size=1
         0: aload_0
         1: invokespecial #53                 // InterfaceMethod tupled:()Lscala/Function1;
         4: areturn
      LineNumberTable:
        line 52: 0
      LocalVariableTable:
        Start  Length  Slot  Name   Signature
            0       5     0 $this   Lscala/Function2;
    MethodParameters:
      Name                           Flags
      $this                          final synthetic

  public default scala.Function1<scala.Tuple2<T1, T2>, R> tupled();
    descriptor: ()Lscala/Function1;
    flags: (0x0001) ACC_PUBLIC
    Code:
      stack=1, locals=1, args_size=1
         0: aload_0
         1: invokedynamic #62,  0             // InvokeDynamic #1:apply:(Lscala/Function2;)Lscala/Function1;
         6: areturn
      LineNumberTable:
        line 52: 0
      LocalVariableTable:
        Start  Length  Slot  Name   Signature
            0       7     0  this   Lscala/Function2;
    Signature: #54                          // ()Lscala/Function1<Lscala/Tuple2<TT1;TT2;>;TR;>;

  public static java.lang.String toString$(scala.Function2);
    descriptor: (Lscala/Function2;)Ljava/lang/String;
    flags: (0x1009) ACC_PUBLIC, ACC_STATIC, ACC_SYNTHETIC
    Code:
      stack=1, locals=1, args_size=1
         0: aload_0
         1: invokespecial #68                 // InterfaceMethod toString:()Ljava/lang/String;
         4: areturn
      LineNumberTable:
        line 55: 0
      LocalVariableTable:
        Start  Length  Slot  Name   Signature
            0       5     0 $this   Lscala/Function2;
    MethodParameters:
      Name                           Flags
      $this                          final synthetic

  public default java.lang.String toString();
    descriptor: ()Ljava/lang/String;
    flags: (0x0001) ACC_PUBLIC
    Code:
      stack=1, locals=1, args_size=1
         0: ldc           #70                 // String <function2>
         2: areturn
      LineNumberTable:
        line 55: 0
      LocalVariableTable:
        Start  Length  Slot  Name   Signature
            0       3     0  this   Lscala/Function2;

  public static boolean apply$mcZDD$sp$(scala.Function2, double, double);
    descriptor: (Lscala/Function2;DD)Z
    flags: (0x1009) ACC_PUBLIC, ACC_STATIC, ACC_SYNTHETIC
    Code:
      stack=5, locals=5, args_size=3
         0: aload_0
         1: dload_1
         2: dload_3
         3: invokespecial #76                 // InterfaceMethod apply$mcZDD$sp:(DD)Z
         6: ireturn
      LineNumberTable:
        line 38: 0
      LocalVariableTable:
        Start  Length  Slot  Name   Signature
            0       7     0 $this   Lscala/Function2;
            0       7     1    v1   D
            0       7     3    v2   D
    MethodParameters:
      Name                           Flags
      $this                          final synthetic
      v1                             final
      v2                             final

  public default boolean apply$mcZDD$sp(double, double);
    descriptor: (DD)Z
    flags: (0x0001) ACC_PUBLIC
    Code:
      stack=4, locals=5, args_size=3
         0: aload_0
         1: dload_1
         2: invokestatic  #83                 // Method java/lang/Double.valueOf:(D)Ljava/lang/Double;
         5: dload_3
         6: invokestatic  #83                 // Method java/lang/Double.valueOf:(D)Ljava/lang/Double;
         9: invokeinterface #85,  3           // InterfaceMethod apply:(Ljava/lang/Object;Ljava/lang/Object;)Ljava/lang/Object;
        14: invokestatic  #91                 // Method scala/runtime/BoxesRunTime.unboxToBoolean:(Ljava/lang/Object;)Z
        17: ireturn
      LineNumberTable:
        line 38: 0
      LocalVariableTable:
        Start  Length  Slot  Name   Signature
            0      18     0  this   Lscala/Function2;
            0      18     1    v1   D
            0      18     3    v2   D
    MethodParameters:
      Name                           Flags
      v1                             final
      v2                             final

  public static double apply$mcDDD$sp$(scala.Function2, double, double);
    descriptor: (Lscala/Function2;DD)D
    flags: (0x1009) ACC_PUBLIC, ACC_STATIC, ACC_SYNTHETIC
    Code:
      stack=5, locals=5, args_size=3
         0: aload_0
         1: dload_1
         2: dload_3
         3: invokespecial #97                 // InterfaceMethod apply$mcDDD$sp:(DD)D
         6: dreturn
      LineNumberTable:
        line 38: 0
      LocalVariableTable:
        Start  Length  Slot  Name   Signature
            0       7     0 $this   Lscala/Function2;
            0       7     1    v1   D
            0       7     3    v2   D
    MethodParameters:
      Name                           Flags
      $this                          final synthetic
      v1                             final
      v2                             final

  public default double apply$mcDDD$sp(double, double);
    descriptor: (DD)D
    flags: (0x0001) ACC_PUBLIC
    Code:
      stack=4, locals=5, args_size=3
         0: aload_0
         1: dload_1
         2: invokestatic  #83                 // Method java/lang/Double.valueOf:(D)Ljava/lang/Double;
         5: dload_3
         6: invokestatic  #83                 // Method java/lang/Double.valueOf:(D)Ljava/lang/Double;
         9: invokeinterface #85,  3           // InterfaceMethod apply:(Ljava/lang/Object;Ljava/lang/Object;)Ljava/lang/Object;
        14: invokestatic  #101                // Method scala/runtime/BoxesRunTime.unboxToDouble:(Ljava/lang/Object;)D
        17: dreturn
      LineNumberTable:
        line 38: 0
      LocalVariableTable:
        Start  Length  Slot  Name   Signature
            0      18     0  this   Lscala/Function2;
            0      18     1    v1   D
            0      18     3    v2   D
    MethodParameters:
      Name                           Flags
      v1                             final
      v2                             final

  public static float apply$mcFDD$sp$(scala.Function2, double, double);
    descriptor: (Lscala/Function2;DD)F
    flags: (0x1009) ACC_PUBLIC, ACC_STATIC, ACC_SYNTHETIC
    Code:
      stack=5, locals=5, args_size=3
         0: aload_0
         1: dload_1
         2: dload_3
         3: invokespecial #107                // InterfaceMethod apply$mcFDD$sp:(DD)F
         6: freturn
      LineNumberTable:
        line 38: 0
      LocalVariableTable:
        Start  Length  Slot  Name   Signature
            0       7     0 $this   Lscala/Function2;
            0       7     1    v1   D
            0       7     3    v2   D
    MethodParameters:
      Name                           Flags
      $this                          final synthetic
      v1                             final
      v2                             final

  public default float apply$mcFDD$sp(double, double);
    descriptor: (DD)F
    flags: (0x0001) ACC_PUBLIC
    Code:
      stack=4, locals=5, args_size=3
         0: aload_0
         1: dload_1
         2: invokestatic  #83                 // Method java/lang/Double.valueOf:(D)Ljava/lang/Double;
         5: dload_3
         6: invokestatic  #83                 // Method java/lang/Double.valueOf:(D)Ljava/lang/Double;
         9: invokeinterface #85,  3           // InterfaceMethod apply:(Ljava/lang/Object;Ljava/lang/Object;)Ljava/lang/Object;
        14: invokestatic  #111                // Method scala/runtime/BoxesRunTime.unboxToFloat:(Ljava/lang/Object;)F
        17: freturn
      LineNumberTable:
        line 38: 0
      LocalVariableTable:
        Start  Length  Slot  Name   Signature
            0      18     0  this   Lscala/Function2;
            0      18     1    v1   D
            0      18     3    v2   D
    MethodParameters:
      Name                           Flags
      v1                             final
      v2                             final

  public static int apply$mcIDD$sp$(scala.Function2, double, double);
    descriptor: (Lscala/Function2;DD)I
    flags: (0x1009) ACC_PUBLIC, ACC_STATIC, ACC_SYNTHETIC
    Code:
      stack=5, locals=5, args_size=3
         0: aload_0
         1: dload_1
         2: dload_3
         3: invokespecial #117                // InterfaceMethod apply$mcIDD$sp:(DD)I
         6: ireturn
      LineNumberTable:
        line 38: 0
      LocalVariableTable:
        Start  Length  Slot  Name   Signature
            0       7     0 $this   Lscala/Function2;
            0       7     1    v1   D
            0       7     3    v2   D
    MethodParameters:
      Name                           Flags
      $this                          final synthetic
      v1                             final
      v2                             final

  public default int apply$mcIDD$sp(double, double);
    descriptor: (DD)I
    flags: (0x0001) ACC_PUBLIC
    Code:
      stack=4, locals=5, args_size=3
         0: aload_0
         1: dload_1
         2: invokestatic  #83                 // Method java/lang/Double.valueOf:(D)Ljava/lang/Double;
         5: dload_3
         6: invokestatic  #83                 // Method java/lang/Double.valueOf:(D)Ljava/lang/Double;
         9: invokeinterface #85,  3           // InterfaceMethod apply:(Ljava/lang/Object;Ljava/lang/Object;)Ljava/lang/Object;
        14: invokestatic  #121                // Method scala/runtime/BoxesRunTime.unboxToInt:(Ljava/lang/Object;)I
        17: ireturn
      LineNumberTable:
        line 38: 0
      LocalVariableTable:
        Start  Length  Slot  Name   Signature
            0      18     0  this   Lscala/Function2;
            0      18     1    v1   D
            0      18     3    v2   D
    MethodParameters:
      Name                           Flags
      v1                             final
      v2                             final

  public static long apply$mcJDD$sp$(scala.Function2, double, double);
    descriptor: (Lscala/Function2;DD)J
    flags: (0x1009) ACC_PUBLIC, ACC_STATIC, ACC_SYNTHETIC
    Code:
      stack=5, locals=5, args_size=3
         0: aload_0
         1: dload_1
         2: dload_3
         3: invokespecial #127                // InterfaceMethod apply$mcJDD$sp:(DD)J
         6: lreturn
      LineNumberTable:
        line 38: 0
      LocalVariableTable:
        Start  Length  Slot  Name   Signature
            0       7     0 $this   Lscala/Function2;
            0       7     1    v1   D
            0       7     3    v2   D
    MethodParameters:
      Name                           Flags
      $this                          final synthetic
      v1                             final
      v2                             final

  public default long apply$mcJDD$sp(double, double);
    descriptor: (DD)J
    flags: (0x0001) ACC_PUBLIC
    Code:
      stack=4, locals=5, args_size=3
         0: aload_0
         1: dload_1
         2: invokestatic  #83                 // Method java/lang/Double.valueOf:(D)Ljava/lang/Double;
         5: dload_3
         6: invokestatic  #83                 // Method java/lang/Double.valueOf:(D)Ljava/lang/Double;
         9: invokeinterface #85,  3           // InterfaceMethod apply:(Ljava/lang/Object;Ljava/lang/Object;)Ljava/lang/Object;
        14: invokestatic  #131                // Method scala/runtime/BoxesRunTime.unboxToLong:(Ljava/lang/Object;)J
        17: lreturn
      LineNumberTable:
        line 38: 0
      LocalVariableTable:
        Start  Length  Slot  Name   Signature
            0      18     0  this   Lscala/Function2;
            0      18     1    v1   D
            0      18     3    v2   D
    MethodParameters:
      Name                           Flags
      v1                             final
      v2                             final

  public static void apply$mcVDD$sp$(scala.Function2, double, double);
    descriptor: (Lscala/Function2;DD)V
    flags: (0x1009) ACC_PUBLIC, ACC_STATIC, ACC_SYNTHETIC
    Code:
      stack=5, locals=5, args_size=3
         0: aload_0
         1: dload_1
         2: dload_3
         3: invokespecial #137                // InterfaceMethod apply$mcVDD$sp:(DD)V
         6: return
      LineNumberTable:
        line 38: 0
      LocalVariableTable:
        Start  Length  Slot  Name   Signature
            0       7     0 $this   Lscala/Function2;
            0       7     1    v1   D
            0       7     3    v2   D
    MethodParameters:
      Name                           Flags
      $this                          final synthetic
      v1                             final
      v2                             final

  public default void apply$mcVDD$sp(double, double);
    descriptor: (DD)V
    flags: (0x0001) ACC_PUBLIC
    Code:
      stack=4, locals=5, args_size=3
         0: aload_0
         1: dload_1
         2: invokestatic  #83                 // Method java/lang/Double.valueOf:(D)Ljava/lang/Double;
         5: dload_3
         6: invokestatic  #83                 // Method java/lang/Double.valueOf:(D)Ljava/lang/Double;
         9: invokeinterface #85,  3           // InterfaceMethod apply:(Ljava/lang/Object;Ljava/lang/Object;)Ljava/lang/Object;
        14: pop
        15: return
      LineNumberTable:
        line 38: 0
      LocalVariableTable:
        Start  Length  Slot  Name   Signature
            0      16     0  this   Lscala/Function2;
            0      16     1    v1   D
            0      16     3    v2   D
    MethodParameters:
      Name                           Flags
      v1                             final
      v2                             final

  public static boolean apply$mcZDI$sp$(scala.Function2, double, int);
    descriptor: (Lscala/Function2;DI)Z
    flags: (0x1009) ACC_PUBLIC, ACC_STATIC, ACC_SYNTHETIC
    Code:
      stack=4, locals=4, args_size=3
         0: aload_0
         1: dload_1
         2: iload_3
         3: invokespecial #143                // InterfaceMethod apply$mcZDI$sp:(DI)Z
         6: ireturn
      LineNumberTable:
        line 38: 0
      LocalVariableTable:
        Start  Length  Slot  Name   Signature
            0       7     0 $this   Lscala/Function2;
            0       7     1    v1   D
            0       7     3    v2   I
    MethodParameters:
      Name                           Flags
      $this                          final synthetic
      v1                             final
      v2                             final

  public default boolean apply$mcZDI$sp(double, int);
    descriptor: (DI)Z
    flags: (0x0001) ACC_PUBLIC
    Code:
      stack=3, locals=4, args_size=3
         0: aload_0
         1: dload_1
         2: invokestatic  #83                 // Method java/lang/Double.valueOf:(D)Ljava/lang/Double;
         5: iload_3
         6: invokestatic  #149                // Method java/lang/Integer.valueOf:(I)Ljava/lang/Integer;
         9: invokeinterface #85,  3           // InterfaceMethod apply:(Ljava/lang/Object;Ljava/lang/Object;)Ljava/lang/Object;
        14: invokestatic  #91                 // Method scala/runtime/BoxesRunTime.unboxToBoolean:(Ljava/lang/Object;)Z
        17: ireturn
      LineNumberTable:
        line 38: 0
      LocalVariableTable:
        Start  Length  Slot  Name   Signature
            0      18     0  this   Lscala/Function2;
            0      18     1    v1   D
            0      18     3    v2   I
    MethodParameters:
      Name                           Flags
      v1                             final
      v2                             final

  public static double apply$mcDDI$sp$(scala.Function2, double, int);
    descriptor: (Lscala/Function2;DI)D
    flags: (0x1009) ACC_PUBLIC, ACC_STATIC, ACC_SYNTHETIC
    Code:
      stack=4, locals=4, args_size=3
         0: aload_0
         1: dload_1
         2: iload_3
         3: invokespecial #155                // InterfaceMethod apply$mcDDI$sp:(DI)D
         6: dreturn
      LineNumberTable:
        line 38: 0
      LocalVariableTable:
        Start  Length  Slot  Name   Signature
            0       7     0 $this   Lscala/Function2;
            0       7     1    v1   D
            0       7     3    v2   I
    MethodParameters:
      Name                           Flags
      $this                          final synthetic
      v1                             final
      v2                             final

  public default double apply$mcDDI$sp(double, int);
    descriptor: (DI)D
    flags: (0x0001) ACC_PUBLIC
    Code:
      stack=3, locals=4, args_size=3
         0: aload_0
         1: dload_1
         2: invokestatic  #83                 // Method java/lang/Double.valueOf:(D)Ljava/lang/Double;
         5: iload_3
         6: invokestatic  #149                // Method java/lang/Integer.valueOf:(I)Ljava/lang/Integer;
         9: invokeinterface #85,  3           // InterfaceMethod apply:(Ljava/lang/Object;Ljava/lang/Object;)Ljava/lang/Object;
        14: invokestatic  #101                // Method scala/runtime/BoxesRunTime.unboxToDouble:(Ljava/lang/Object;)D
        17: dreturn
      LineNumberTable:
        line 38: 0
      LocalVariableTable:
        Start  Length  Slot  Name   Signature
            0      18     0  this   Lscala/Function2;
            0      18     1    v1   D
            0      18     3    v2   I
    MethodParameters:
      Name                           Flags
      v1                             final
      v2                             final

  public static float apply$mcFDI$sp$(scala.Function2, double, int);
    descriptor: (Lscala/Function2;DI)F
    flags: (0x1009) ACC_PUBLIC, ACC_STATIC, ACC_SYNTHETIC
    Code:
      stack=4, locals=4, args_size=3
         0: aload_0
         1: dload_1
         2: iload_3
         3: invokespecial #161                // InterfaceMethod apply$mcFDI$sp:(DI)F
         6: freturn
      LineNumberTable:
        line 38: 0
      LocalVariableTable:
        Start  Length  Slot  Name   Signature
            0       7     0 $this   Lscala/Function2;
            0       7     1    v1   D
            0       7     3    v2   I
    MethodParameters:
      Name                           Flags
      $this                          final synthetic
      v1                             final
      v2                             final

  public default float apply$mcFDI$sp(double, int);
    descriptor: (DI)F
    flags: (0x0001) ACC_PUBLIC
    Code:
      stack=3, locals=4, args_size=3
         0: aload_0
         1: dload_1
         2: invokestatic  #83                 // Method java/lang/Double.valueOf:(D)Ljava/lang/Double;
         5: iload_3
         6: invokestatic  #149                // Method java/lang/Integer.valueOf:(I)Ljava/lang/Integer;
         9: invokeinterface #85,  3           // InterfaceMethod apply:(Ljava/lang/Object;Ljava/lang/Object;)Ljava/lang/Object;
        14: invokestatic  #111                // Method scala/runtime/BoxesRunTime.unboxToFloat:(Ljava/lang/Object;)F
        17: freturn
      LineNumberTable:
        line 38: 0
      LocalVariableTable:
        Start  Length  Slot  Name   Signature
            0      18     0  this   Lscala/Function2;
            0      18     1    v1   D
            0      18     3    v2   I
    MethodParameters:
      Name                           Flags
      v1                             final
      v2                             final

  public static int apply$mcIDI$sp$(scala.Function2, double, int);
    descriptor: (Lscala/Function2;DI)I
    flags: (0x1009) ACC_PUBLIC, ACC_STATIC, ACC_SYNTHETIC
    Code:
      stack=4, locals=4, args_size=3
         0: aload_0
         1: dload_1
         2: iload_3
         3: invokespecial #167                // InterfaceMethod apply$mcIDI$sp:(DI)I
         6: ireturn
      LineNumberTable:
        line 38: 0
      LocalVariableTable:
        Start  Length  Slot  Name   Signature
            0       7     0 $this   Lscala/Function2;
            0       7     1    v1   D
            0       7     3    v2   I
    MethodParameters:
      Name                           Flags
      $this                          final synthetic
      v1                             final
      v2                             final

  public default int apply$mcIDI$sp(double, int);
    descriptor: (DI)I
    flags: (0x0001) ACC_PUBLIC
    Code:
      stack=3, locals=4, args_size=3
         0: aload_0
         1: dload_1
         2: invokestatic  #83                 // Method java/lang/Double.valueOf:(D)Ljava/lang/Double;
         5: iload_3
         6: invokestatic  #149                // Method java/lang/Integer.valueOf:(I)Ljava/lang/Integer;
         9: invokeinterface #85,  3           // InterfaceMethod apply:(Ljava/lang/Object;Ljava/lang/Object;)Ljava/lang/Object;
        14: invokestatic  #121                // Method scala/runtime/BoxesRunTime.unboxToInt:(Ljava/lang/Object;)I
        17: ireturn
      LineNumberTable:
        line 38: 0
      LocalVariableTable:
        Start  Length  Slot  Name   Signature
            0      18     0  this   Lscala/Function2;
            0      18     1    v1   D
            0      18     3    v2   I
    MethodParameters:
      Name                           Flags
      v1                             final
      v2                             final

  public static long apply$mcJDI$sp$(scala.Function2, double, int);
    descriptor: (Lscala/Function2;DI)J
    flags: (0x1009) ACC_PUBLIC, ACC_STATIC, ACC_SYNTHETIC
    Code:
      stack=4, locals=4, args_size=3
         0: aload_0
         1: dload_1
         2: iload_3
         3: invokespecial #173                // InterfaceMethod apply$mcJDI$sp:(DI)J
         6: lreturn
      LineNumberTable:
        line 38: 0
      LocalVariableTable:
        Start  Length  Slot  Name   Signature
            0       7     0 $this   Lscala/Function2;
            0       7     1    v1   D
            0       7     3    v2   I
    MethodParameters:
      Name                           Flags
      $this                          final synthetic
      v1                             final
      v2                             final

  public default long apply$mcJDI$sp(double, int);
    descriptor: (DI)J
    flags: (0x0001) ACC_PUBLIC
    Code:
      stack=3, locals=4, args_size=3
         0: aload_0
         1: dload_1
         2: invokestatic  #83                 // Method java/lang/Double.valueOf:(D)Ljava/lang/Double;
         5: iload_3
         6: invokestatic  #149                // Method java/lang/Integer.valueOf:(I)Ljava/lang/Integer;
         9: invokeinterface #85,  3           // InterfaceMethod apply:(Ljava/lang/Object;Ljava/lang/Object;)Ljava/lang/Object;
        14: invokestatic  #131                // Method scala/runtime/BoxesRunTime.unboxToLong:(Ljava/lang/Object;)J
        17: lreturn
      LineNumberTable:
        line 38: 0
      LocalVariableTable:
        Start  Length  Slot  Name   Signature
            0      18     0  this   Lscala/Function2;
            0      18     1    v1   D
            0      18     3    v2   I
    MethodParameters:
      Name                           Flags
      v1                             final
      v2                             final

  public static void apply$mcVDI$sp$(scala.Function2, double, int);
    descriptor: (Lscala/Function2;DI)V
    flags: (0x1009) ACC_PUBLIC, ACC_STATIC, ACC_SYNTHETIC
    Code:
      stack=4, locals=4, args_size=3
         0: aload_0
         1: dload_1
         2: iload_3
         3: invokespecial #179                // InterfaceMethod apply$mcVDI$sp:(DI)V
         6: return
      LineNumberTable:
        line 38: 0
      LocalVariableTable:
        Start  Length  Slot  Name   Signature
            0       7     0 $this   Lscala/Function2;
            0       7     1    v1   D
            0       7     3    v2   I
    MethodParameters:
      Name                           Flags
      $this                          final synthetic
      v1                             final
      v2                             final

  public default void apply$mcVDI$sp(double, int);
    descriptor: (DI)V
    flags: (0x0001) ACC_PUBLIC
    Code:
      stack=3, locals=4, args_size=3
         0: aload_0
         1: dload_1
         2: invokestatic  #83                 // Method java/lang/Double.valueOf:(D)Ljava/lang/Double;
         5: iload_3
         6: invokestatic  #149                // Method java/lang/Integer.valueOf:(I)Ljava/lang/Integer;
         9: invokeinterface #85,  3           // InterfaceMethod apply:(Ljava/lang/Object;Ljava/lang/Object;)Ljava/lang/Object;
        14: pop
        15: return
      LineNumberTable:
        line 38: 0
      LocalVariableTable:
        Start  Length  Slot  Name   Signature
            0      16     0  this   Lscala/Function2;
            0      16     1    v1   D
            0      16     3    v2   I
    MethodParameters:
      Name                           Flags
      v1                             final
      v2                             final

  public static boolean apply$mcZDJ$sp$(scala.Function2, double, long);
    descriptor: (Lscala/Function2;DJ)Z
    flags: (0x1009) ACC_PUBLIC, ACC_STATIC, ACC_SYNTHETIC
    Code:
      stack=5, locals=5, args_size=3
         0: aload_0
         1: dload_1
         2: lload_3
         3: invokespecial #185                // InterfaceMethod apply$mcZDJ$sp:(DJ)Z
         6: ireturn
      LineNumberTable:
        line 38: 0
      LocalVariableTable:
        Start  Length  Slot  Name   Signature
            0       7     0 $this   Lscala/Function2;
            0       7     1    v1   D
            0       7     3    v2   J
    MethodParameters:
      Name                           Flags
      $this                          final synthetic
      v1                             final
      v2                             final

  public default boolean apply$mcZDJ$sp(double, long);
    descriptor: (DJ)Z
    flags: (0x0001) ACC_PUBLIC
    Code:
      stack=4, locals=5, args_size=3
         0: aload_0
         1: dload_1
         2: invokestatic  #83                 // Method java/lang/Double.valueOf:(D)Ljava/lang/Double;
         5: lload_3
         6: invokestatic  #191                // Method java/lang/Long.valueOf:(J)Ljava/lang/Long;
         9: invokeinterface #85,  3           // InterfaceMethod apply:(Ljava/lang/Object;Ljava/lang/Object;)Ljava/lang/Object;
        14: invokestatic  #91                 // Method scala/runtime/BoxesRunTime.unboxToBoolean:(Ljava/lang/Object;)Z
        17: ireturn
      LineNumberTable:
        line 38: 0
      LocalVariableTable:
        Start  Length  Slot  Name   Signature
            0      18     0  this   Lscala/Function2;
            0      18     1    v1   D
            0      18     3    v2   J
    MethodParameters:
      Name                           Flags
      v1                             final
      v2                             final

  public static double apply$mcDDJ$sp$(scala.Function2, double, long);
    descriptor: (Lscala/Function2;DJ)D
    flags: (0x1009) ACC_PUBLIC, ACC_STATIC, ACC_SYNTHETIC
    Code:
      stack=5, locals=5, args_size=3
         0: aload_0
         1: dload_1
         2: lload_3
         3: invokespecial #197                // InterfaceMethod apply$mcDDJ$sp:(DJ)D
         6: dreturn
      LineNumberTable:
        line 38: 0
      LocalVariableTable:
        Start  Length  Slot  Name   Signature
            0       7     0 $this   Lscala/Function2;
            0       7     1    v1   D
            0       7     3    v2   J
    MethodParameters:
      Name                           Flags
      $this                          final synthetic
      v1                             final
      v2                             final

  public default double apply$mcDDJ$sp(double, long);
    descriptor: (DJ)D
    flags: (0x0001) ACC_PUBLIC
    Code:
      stack=4, locals=5, args_size=3
         0: aload_0
         1: dload_1
         2: invokestatic  #83                 // Method java/lang/Double.valueOf:(D)Ljava/lang/Double;
         5: lload_3
         6: invokestatic  #191                // Method java/lang/Long.valueOf:(J)Ljava/lang/Long;
         9: invokeinterface #85,  3           // InterfaceMethod apply:(Ljava/lang/Object;Ljava/lang/Object;)Ljava/lang/Object;
        14: invokestatic  #101                // Method scala/runtime/BoxesRunTime.unboxToDouble:(Ljava/lang/Object;)D
        17: dreturn
      LineNumberTable:
        line 38: 0
      LocalVariableTable:
        Start  Length  Slot  Name   Signature
            0      18     0  this   Lscala/Function2;
            0      18     1    v1   D
            0      18     3    v2   J
    MethodParameters:
      Name                           Flags
      v1                             final
      v2                             final

  public static float apply$mcFDJ$sp$(scala.Function2, double, long);
    descriptor: (Lscala/Function2;DJ)F
    flags: (0x1009) ACC_PUBLIC, ACC_STATIC, ACC_SYNTHETIC
    Code:
      stack=5, locals=5, args_size=3
         0: aload_0
         1: dload_1
         2: lload_3
         3: invokespecial #203                // InterfaceMethod apply$mcFDJ$sp:(DJ)F
         6: freturn
      LineNumberTable:
        line 38: 0
      LocalVariableTable:
        Start  Length  Slot  Name   Signature
            0       7     0 $this   Lscala/Function2;
            0       7     1    v1   D
            0       7     3    v2   J
    MethodParameters:
      Name                           Flags
      $this                          final synthetic
      v1                             final
      v2                             final

  public default float apply$mcFDJ$sp(double, long);
    descriptor: (DJ)F
    flags: (0x0001) ACC_PUBLIC
    Code:
      stack=4, locals=5, args_size=3
         0: aload_0
         1: dload_1
         2: invokestatic  #83                 // Method java/lang/Double.valueOf:(D)Ljava/lang/Double;
         5: lload_3
         6: invokestatic  #191                // Method java/lang/Long.valueOf:(J)Ljava/lang/Long;
         9: invokeinterface #85,  3           // InterfaceMethod apply:(Ljava/lang/Object;Ljava/lang/Object;)Ljava/lang/Object;
        14: invokestatic  #111                // Method scala/runtime/BoxesRunTime.unboxToFloat:(Ljava/lang/Object;)F
        17: freturn
      LineNumberTable:
        line 38: 0
      LocalVariableTable:
        Start  Length  Slot  Name   Signature
            0      18     0  this   Lscala/Function2;
            0      18     1    v1   D
            0      18     3    v2   J
    MethodParameters:
      Name                           Flags
      v1                             final
      v2                             final

  public static int apply$mcIDJ$sp$(scala.Function2, double, long);
    descriptor: (Lscala/Function2;DJ)I
    flags: (0x1009) ACC_PUBLIC, ACC_STATIC, ACC_SYNTHETIC
    Code:
      stack=5, locals=5, args_size=3
         0: aload_0
         1: dload_1
         2: lload_3
         3: invokespecial #209                // InterfaceMethod apply$mcIDJ$sp:(DJ)I
         6: ireturn
      LineNumberTable:
        line 38: 0
      LocalVariableTable:
        Start  Length  Slot  Name   Signature
            0       7     0 $this   Lscala/Function2;
            0       7     1    v1   D
            0       7     3    v2   J
    MethodParameters:
      Name                           Flags
      $this                          final synthetic
      v1                             final
      v2                             final

  public default int apply$mcIDJ$sp(double, long);
    descriptor: (DJ)I
    flags: (0x0001) ACC_PUBLIC
    Code:
      stack=4, locals=5, args_size=3
         0: aload_0
         1: dload_1
         2: invokestatic  #83                 // Method java/lang/Double.valueOf:(D)Ljava/lang/Double;
         5: lload_3
         6: invokestatic  #191                // Method java/lang/Long.valueOf:(J)Ljava/lang/Long;
         9: invokeinterface #85,  3           // InterfaceMethod apply:(Ljava/lang/Object;Ljava/lang/Object;)Ljava/lang/Object;
        14: invokestatic  #121                // Method scala/runtime/BoxesRunTime.unboxToInt:(Ljava/lang/Object;)I
        17: ireturn
      LineNumberTable:
        line 38: 0
      LocalVariableTable:
        Start  Length  Slot  Name   Signature
            0      18     0  this   Lscala/Function2;
            0      18     1    v1   D
            0      18     3    v2   J
    MethodParameters:
      Name                           Flags
      v1                             final
      v2                             final

  public static long apply$mcJDJ$sp$(scala.Function2, double, long);
    descriptor: (Lscala/Function2;DJ)J
    flags: (0x1009) ACC_PUBLIC, ACC_STATIC, ACC_SYNTHETIC
    Code:
      stack=5, locals=5, args_size=3
         0: aload_0
         1: dload_1
         2: lload_3
         3: invokespecial #215                // InterfaceMethod apply$mcJDJ$sp:(DJ)J
         6: lreturn
      LineNumberTable:
        line 38: 0
      LocalVariableTable:
        Start  Length  Slot  Name   Signature
            0       7     0 $this   Lscala/Function2;
            0       7     1    v1   D
            0       7     3    v2   J
    MethodParameters:
      Name                           Flags
      $this                          final synthetic
      v1                             final
      v2                             final

  public default long apply$mcJDJ$sp(double, long);
    descriptor: (DJ)J
    flags: (0x0001) ACC_PUBLIC
    Code:
      stack=4, locals=5, args_size=3
         0: aload_0
         1: dload_1
         2: invokestatic  #83                 // Method java/lang/Double.valueOf:(D)Ljava/lang/Double;
         5: lload_3
         6: invokestatic  #191                // Method java/lang/Long.valueOf:(J)Ljava/lang/Long;
         9: invokeinterface #85,  3           // InterfaceMethod apply:(Ljava/lang/Object;Ljava/lang/Object;)Ljava/lang/Object;
        14: invokestatic  #131                // Method scala/runtime/BoxesRunTime.unboxToLong:(Ljava/lang/Object;)J
        17: lreturn
      LineNumberTable:
        line 38: 0
      LocalVariableTable:
        Start  Length  Slot  Name   Signature
            0      18     0  this   Lscala/Function2;
            0      18     1    v1   D
            0      18     3    v2   J
    MethodParameters:
      Name                           Flags
      v1                             final
      v2                             final

  public static void apply$mcVDJ$sp$(scala.Function2, double, long);
    descriptor: (Lscala/Function2;DJ)V
    flags: (0x1009) ACC_PUBLIC, ACC_STATIC, ACC_SYNTHETIC
    Code:
      stack=5, locals=5, args_size=3
         0: aload_0
         1: dload_1
         2: lload_3
         3: invokespecial #221                // InterfaceMethod apply$mcVDJ$sp:(DJ)V
         6: return
      LineNumberTable:
        line 38: 0
      LocalVariableTable:
        Start  Length  Slot  Name   Signature
            0       7     0 $this   Lscala/Function2;
            0       7     1    v1   D
            0       7     3    v2   J
    MethodParameters:
      Name                           Flags
      $this                          final synthetic
      v1                             final
      v2                             final

  public default void apply$mcVDJ$sp(double, long);
    descriptor: (DJ)V
    flags: (0x0001) ACC_PUBLIC
    Code:
      stack=4, locals=5, args_size=3
         0: aload_0
         1: dload_1
         2: invokestatic  #83                 // Method java/lang/Double.valueOf:(D)Ljava/lang/Double;
         5: lload_3
         6: invokestatic  #191                // Method java/lang/Long.valueOf:(J)Ljava/lang/Long;
         9: invokeinterface #85,  3           // InterfaceMethod apply:(Ljava/lang/Object;Ljava/lang/Object;)Ljava/lang/Object;
        14: pop
        15: return
      LineNumberTable:
        line 38: 0
      LocalVariableTable:
        Start  Length  Slot  Name   Signature
            0      16     0  this   Lscala/Function2;
            0      16     1    v1   D
            0      16     3    v2   J
    MethodParameters:
      Name                           Flags
      v1                             final
      v2                             final

  public static boolean apply$mcZID$sp$(scala.Function2, int, double);
    descriptor: (Lscala/Function2;ID)Z
    flags: (0x1009) ACC_PUBLIC, ACC_STATIC, ACC_SYNTHETIC
    Code:
      stack=4, locals=4, args_size=3
         0: aload_0
         1: iload_1
         2: dload_2
         3: invokespecial #227                // InterfaceMethod apply$mcZID$sp:(ID)Z
         6: ireturn
      LineNumberTable:
        line 38: 0
      LocalVariableTable:
        Start  Length  Slot  Name   Signature
            0       7     0 $this   Lscala/Function2;
            0       7     1    v1   I
            0       7     2    v2   D
    MethodParameters:
      Name                           Flags
      $this                          final synthetic
      v1                             final
      v2                             final

  public default boolean apply$mcZID$sp(int, double);
    descriptor: (ID)Z
    flags: (0x0001) ACC_PUBLIC
    Code:
      stack=4, locals=4, args_size=3
         0: aload_0
         1: iload_1
         2: invokestatic  #149                // Method java/lang/Integer.valueOf:(I)Ljava/lang/Integer;
         5: dload_2
         6: invokestatic  #83                 // Method java/lang/Double.valueOf:(D)Ljava/lang/Double;
         9: invokeinterface #85,  3           // InterfaceMethod apply:(Ljava/lang/Object;Ljava/lang/Object;)Ljava/lang/Object;
        14: invokestatic  #91                 // Method scala/runtime/BoxesRunTime.unboxToBoolean:(Ljava/lang/Object;)Z
        17: ireturn
      LineNumberTable:
        line 38: 0
      LocalVariableTable:
        Start  Length  Slot  Name   Signature
            0      18     0  this   Lscala/Function2;
            0      18     1    v1   I
            0      18     2    v2   D
    MethodParameters:
      Name                           Flags
      v1                             final
      v2                             final

  public static double apply$mcDID$sp$(scala.Function2, int, double);
    descriptor: (Lscala/Function2;ID)D
    flags: (0x1009) ACC_PUBLIC, ACC_STATIC, ACC_SYNTHETIC
    Code:
      stack=4, locals=4, args_size=3
         0: aload_0
         1: iload_1
         2: dload_2
         3: invokespecial #233                // InterfaceMethod apply$mcDID$sp:(ID)D
         6: dreturn
      LineNumberTable:
        line 38: 0
      LocalVariableTable:
        Start  Length  Slot  Name   Signature
            0       7     0 $this   Lscala/Function2;
            0       7     1    v1   I
            0       7     2    v2   D
    MethodParameters:
      Name                           Flags
      $this                          final synthetic
      v1                             final
      v2                             final

  public default double apply$mcDID$sp(int, double);
    descriptor: (ID)D
    flags: (0x0001) ACC_PUBLIC
    Code:
      stack=4, locals=4, args_size=3
         0: aload_0
         1: iload_1
         2: invokestatic  #149                // Method java/lang/Integer.valueOf:(I)Ljava/lang/Integer;
         5: dload_2
         6: invokestatic  #83                 // Method java/lang/Double.valueOf:(D)Ljava/lang/Double;
         9: invokeinterface #85,  3           // InterfaceMethod apply:(Ljava/lang/Object;Ljava/lang/Object;)Ljava/lang/Object;
        14: invokestatic  #101                // Method scala/runtime/BoxesRunTime.unboxToDouble:(Ljava/lang/Object;)D
        17: dreturn
      LineNumberTable:
        line 38: 0
      LocalVariableTable:
        Start  Length  Slot  Name   Signature
            0      18     0  this   Lscala/Function2;
            0      18     1    v1   I
            0      18     2    v2   D
    MethodParameters:
      Name                           Flags
      v1                             final
      v2                             final

  public static float apply$mcFID$sp$(scala.Function2, int, double);
    descriptor: (Lscala/Function2;ID)F
    flags: (0x1009) ACC_PUBLIC, ACC_STATIC, ACC_SYNTHETIC
    Code:
      stack=4, locals=4, args_size=3
         0: aload_0
         1: iload_1
         2: dload_2
         3: invokespecial #239                // InterfaceMethod apply$mcFID$sp:(ID)F
         6: freturn
      LineNumberTable:
        line 38: 0
      LocalVariableTable:
        Start  Length  Slot  Name   Signature
            0       7     0 $this   Lscala/Function2;
            0       7     1    v1   I
            0       7     2    v2   D
    MethodParameters:
      Name                           Flags
      $this                          final synthetic
      v1                             final
      v2                             final

  public default float apply$mcFID$sp(int, double);
    descriptor: (ID)F
    flags: (0x0001) ACC_PUBLIC
    Code:
      stack=4, locals=4, args_size=3
         0: aload_0
         1: iload_1
         2: invokestatic  #149                // Method java/lang/Integer.valueOf:(I)Ljava/lang/Integer;
         5: dload_2
         6: invokestatic  #83                 // Method java/lang/Double.valueOf:(D)Ljava/lang/Double;
         9: invokeinterface #85,  3           // InterfaceMethod apply:(Ljava/lang/Object;Ljava/lang/Object;)Ljava/lang/Object;
        14: invokestatic  #111                // Method scala/runtime/BoxesRunTime.unboxToFloat:(Ljava/lang/Object;)F
        17: freturn
      LineNumberTable:
        line 38: 0
      LocalVariableTable:
        Start  Length  Slot  Name   Signature
            0      18     0  this   Lscala/Function2;
            0      18     1    v1   I
            0      18     2    v2   D
    MethodParameters:
      Name                           Flags
      v1                             final
      v2                             final

  public static int apply$mcIID$sp$(scala.Function2, int, double);
    descriptor: (Lscala/Function2;ID)I
    flags: (0x1009) ACC_PUBLIC, ACC_STATIC, ACC_SYNTHETIC
    Code:
      stack=4, locals=4, args_size=3
         0: aload_0
         1: iload_1
         2: dload_2
         3: invokespecial #245                // InterfaceMethod apply$mcIID$sp:(ID)I
         6: ireturn
      LineNumberTable:
        line 38: 0
      LocalVariableTable:
        Start  Length  Slot  Name   Signature
            0       7     0 $this   Lscala/Function2;
            0       7     1    v1   I
            0       7     2    v2   D
    MethodParameters:
      Name                           Flags
      $this                          final synthetic
      v1                             final
      v2                             final

  public default int apply$mcIID$sp(int, double);
    descriptor: (ID)I
    flags: (0x0001) ACC_PUBLIC
    Code:
      stack=4, locals=4, args_size=3
         0: aload_0
         1: iload_1
         2: invokestatic  #149                // Method java/lang/Integer.valueOf:(I)Ljava/lang/Integer;
         5: dload_2
         6: invokestatic  #83                 // Method java/lang/Double.valueOf:(D)Ljava/lang/Double;
         9: invokeinterface #85,  3           // InterfaceMethod apply:(Ljava/lang/Object;Ljava/lang/Object;)Ljava/lang/Object;
        14: invokestatic  #121                // Method scala/runtime/BoxesRunTime.unboxToInt:(Ljava/lang/Object;)I
        17: ireturn
      LineNumberTable:
        line 38: 0
      LocalVariableTable:
        Start  Length  Slot  Name   Signature
            0      18     0  this   Lscala/Function2;
            0      18     1    v1   I
            0      18     2    v2   D
    MethodParameters:
      Name                           Flags
      v1                             final
      v2                             final

  public static long apply$mcJID$sp$(scala.Function2, int, double);
    descriptor: (Lscala/Function2;ID)J
    flags: (0x1009) ACC_PUBLIC, ACC_STATIC, ACC_SYNTHETIC
    Code:
      stack=4, locals=4, args_size=3
         0: aload_0
         1: iload_1
         2: dload_2
         3: invokespecial #251                // InterfaceMethod apply$mcJID$sp:(ID)J
         6: lreturn
      LineNumberTable:
        line 38: 0
      LocalVariableTable:
        Start  Length  Slot  Name   Signature
            0       7     0 $this   Lscala/Function2;
            0       7     1    v1   I
            0       7     2    v2   D
    MethodParameters:
      Name                           Flags
      $this                          final synthetic
      v1                             final
      v2                             final

  public default long apply$mcJID$sp(int, double);
    descriptor: (ID)J
    flags: (0x0001) ACC_PUBLIC
    Code:
      stack=4, locals=4, args_size=3
         0: aload_0
         1: iload_1
         2: invokestatic  #149                // Method java/lang/Integer.valueOf:(I)Ljava/lang/Integer;
         5: dload_2
         6: invokestatic  #83                 // Method java/lang/Double.valueOf:(D)Ljava/lang/Double;
         9: invokeinterface #85,  3           // InterfaceMethod apply:(Ljava/lang/Object;Ljava/lang/Object;)Ljava/lang/Object;
        14: invokestatic  #131                // Method scala/runtime/BoxesRunTime.unboxToLong:(Ljava/lang/Object;)J
        17: lreturn
      LineNumberTable:
        line 38: 0
      LocalVariableTable:
        Start  Length  Slot  Name   Signature
            0      18     0  this   Lscala/Function2;
            0      18     1    v1   I
            0      18     2    v2   D
    MethodParameters:
      Name                           Flags
      v1                             final
      v2                             final

  public static void apply$mcVID$sp$(scala.Function2, int, double);
    descriptor: (Lscala/Function2;ID)V
    flags: (0x1009) ACC_PUBLIC, ACC_STATIC, ACC_SYNTHETIC
    Code:
      stack=4, locals=4, args_size=3
         0: aload_0
         1: iload_1
         2: dload_2
         3: invokespecial #257                // InterfaceMethod apply$mcVID$sp:(ID)V
         6: return
      LineNumberTable:
        line 38: 0
      LocalVariableTable:
        Start  Length  Slot  Name   Signature
            0       7     0 $this   Lscala/Function2;
            0       7     1    v1   I
            0       7     2    v2   D
    MethodParameters:
      Name                           Flags
      $this                          final synthetic
      v1                             final
      v2                             final

  public default void apply$mcVID$sp(int, double);
    descriptor: (ID)V
    flags: (0x0001) ACC_PUBLIC
    Code:
      stack=4, locals=4, args_size=3
         0: aload_0
         1: iload_1
         2: invokestatic  #149                // Method java/lang/Integer.valueOf:(I)Ljava/lang/Integer;
         5: dload_2
         6: invokestatic  #83                 // Method java/lang/Double.valueOf:(D)Ljava/lang/Double;
         9: invokeinterface #85,  3           // InterfaceMethod apply:(Ljava/lang/Object;Ljava/lang/Object;)Ljava/lang/Object;
        14: pop
        15: return
      LineNumberTable:
        line 38: 0
      LocalVariableTable:
        Start  Length  Slot  Name   Signature
            0      16     0  this   Lscala/Function2;
            0      16     1    v1   I
            0      16     2    v2   D
    MethodParameters:
      Name                           Flags
      v1                             final
      v2                             final

  public static boolean apply$mcZII$sp$(scala.Function2, int, int);
    descriptor: (Lscala/Function2;II)Z
    flags: (0x1009) ACC_PUBLIC, ACC_STATIC, ACC_SYNTHETIC
    Code:
      stack=3, locals=3, args_size=3
         0: aload_0
         1: iload_1
         2: iload_2
         3: invokespecial #263                // InterfaceMethod apply$mcZII$sp:(II)Z
         6: ireturn
      LineNumberTable:
        line 38: 0
      LocalVariableTable:
        Start  Length  Slot  Name   Signature
            0       7     0 $this   Lscala/Function2;
            0       7     1    v1   I
            0       7     2    v2   I
    MethodParameters:
      Name                           Flags
      $this                          final synthetic
      v1                             final
      v2                             final

  public default boolean apply$mcZII$sp(int, int);
    descriptor: (II)Z
    flags: (0x0001) ACC_PUBLIC
    Code:
      stack=3, locals=3, args_size=3
         0: aload_0
         1: iload_1
         2: invokestatic  #149                // Method java/lang/Integer.valueOf:(I)Ljava/lang/Integer;
         5: iload_2
         6: invokestatic  #149                // Method java/lang/Integer.valueOf:(I)Ljava/lang/Integer;
         9: invokeinterface #85,  3           // InterfaceMethod apply:(Ljava/lang/Object;Ljava/lang/Object;)Ljava/lang/Object;
        14: invokestatic  #91                 // Method scala/runtime/BoxesRunTime.unboxToBoolean:(Ljava/lang/Object;)Z
        17: ireturn
      LineNumberTable:
        line 38: 0
      LocalVariableTable:
        Start  Length  Slot  Name   Signature
            0      18     0  this   Lscala/Function2;
            0      18     1    v1   I
            0      18     2    v2   I
    MethodParameters:
      Name                           Flags
      v1                             final
      v2                             final

  public static double apply$mcDII$sp$(scala.Function2, int, int);
    descriptor: (Lscala/Function2;II)D
    flags: (0x1009) ACC_PUBLIC, ACC_STATIC, ACC_SYNTHETIC
    Code:
      stack=3, locals=3, args_size=3
         0: aload_0
         1: iload_1
         2: iload_2
         3: invokespecial #269                // InterfaceMethod apply$mcDII$sp:(II)D
         6: dreturn
      LineNumberTable:
        line 38: 0
      LocalVariableTable:
        Start  Length  Slot  Name   Signature
            0       7     0 $this   Lscala/Function2;
            0       7     1    v1   I
            0       7     2    v2   I
    MethodParameters:
      Name                           Flags
      $this                          final synthetic
      v1                             final
      v2                             final

  public default double apply$mcDII$sp(int, int);
    descriptor: (II)D
    flags: (0x0001) ACC_PUBLIC
    Code:
      stack=3, locals=3, args_size=3
         0: aload_0
         1: iload_1
         2: invokestatic  #149                // Method java/lang/Integer.valueOf:(I)Ljava/lang/Integer;
         5: iload_2
         6: invokestatic  #149                // Method java/lang/Integer.valueOf:(I)Ljava/lang/Integer;
         9: invokeinterface #85,  3           // InterfaceMethod apply:(Ljava/lang/Object;Ljava/lang/Object;)Ljava/lang/Object;
        14: invokestatic  #101                // Method scala/runtime/BoxesRunTime.unboxToDouble:(Ljava/lang/Object;)D
        17: dreturn
      LineNumberTable:
        line 38: 0
      LocalVariableTable:
        Start  Length  Slot  Name   Signature
            0      18     0  this   Lscala/Function2;
            0      18     1    v1   I
            0      18     2    v2   I
    MethodParameters:
      Name                           Flags
      v1                             final
      v2                             final

  public static float apply$mcFII$sp$(scala.Function2, int, int);
    descriptor: (Lscala/Function2;II)F
    flags: (0x1009) ACC_PUBLIC, ACC_STATIC, ACC_SYNTHETIC
    Code:
      stack=3, locals=3, args_size=3
         0: aload_0
         1: iload_1
         2: iload_2
         3: invokespecial #275                // InterfaceMethod apply$mcFII$sp:(II)F
         6: freturn
      LineNumberTable:
        line 38: 0
      LocalVariableTable:
        Start  Length  Slot  Name   Signature
            0       7     0 $this   Lscala/Function2;
            0       7     1    v1   I
            0       7     2    v2   I
    MethodParameters:
      Name                           Flags
      $this                          final synthetic
      v1                             final
      v2                             final

  public default float apply$mcFII$sp(int, int);
    descriptor: (II)F
    flags: (0x0001) ACC_PUBLIC
    Code:
      stack=3, locals=3, args_size=3
         0: aload_0
         1: iload_1
         2: invokestatic  #149                // Method java/lang/Integer.valueOf:(I)Ljava/lang/Integer;
         5: iload_2
         6: invokestatic  #149                // Method java/lang/Integer.valueOf:(I)Ljava/lang/Integer;
         9: invokeinterface #85,  3           // InterfaceMethod apply:(Ljava/lang/Object;Ljava/lang/Object;)Ljava/lang/Object;
        14: invokestatic  #111                // Method scala/runtime/BoxesRunTime.unboxToFloat:(Ljava/lang/Object;)F
        17: freturn
      LineNumberTable:
        line 38: 0
      LocalVariableTable:
        Start  Length  Slot  Name   Signature
            0      18     0  this   Lscala/Function2;
            0      18     1    v1   I
            0      18     2    v2   I
    MethodParameters:
      Name                           Flags
      v1                             final
      v2                             final

  public static int apply$mcIII$sp$(scala.Function2, int, int);
    descriptor: (Lscala/Function2;II)I
    flags: (0x1009) ACC_PUBLIC, ACC_STATIC, ACC_SYNTHETIC
    Code:
      stack=3, locals=3, args_size=3
         0: aload_0
         1: iload_1
         2: iload_2
         3: invokespecial #281                // InterfaceMethod apply$mcIII$sp:(II)I
         6: ireturn
      LineNumberTable:
        line 38: 0
      LocalVariableTable:
        Start  Length  Slot  Name   Signature
            0       7     0 $this   Lscala/Function2;
            0       7     1    v1   I
            0       7     2    v2   I
    MethodParameters:
      Name                           Flags
      $this                          final synthetic
      v1                             final
      v2                             final

  public default int apply$mcIII$sp(int, int);
    descriptor: (II)I
    flags: (0x0001) ACC_PUBLIC
    Code:
      stack=3, locals=3, args_size=3
         0: aload_0
         1: iload_1
         2: invokestatic  #149                // Method java/lang/Integer.valueOf:(I)Ljava/lang/Integer;
         5: iload_2
         6: invokestatic  #149                // Method java/lang/Integer.valueOf:(I)Ljava/lang/Integer;
         9: invokeinterface #85,  3           // InterfaceMethod apply:(Ljava/lang/Object;Ljava/lang/Object;)Ljava/lang/Object;
        14: invokestatic  #121                // Method scala/runtime/BoxesRunTime.unboxToInt:(Ljava/lang/Object;)I
        17: ireturn
      LineNumberTable:
        line 38: 0
      LocalVariableTable:
        Start  Length  Slot  Name   Signature
            0      18     0  this   Lscala/Function2;
            0      18     1    v1   I
            0      18     2    v2   I
    MethodParameters:
      Name                           Flags
      v1                             final
      v2                             final

  public static long apply$mcJII$sp$(scala.Function2, int, int);
    descriptor: (Lscala/Function2;II)J
    flags: (0x1009) ACC_PUBLIC, ACC_STATIC, ACC_SYNTHETIC
    Code:
      stack=3, locals=3, args_size=3
         0: aload_0
         1: iload_1
         2: iload_2
         3: invokespecial #287                // InterfaceMethod apply$mcJII$sp:(II)J
         6: lreturn
      LineNumberTable:
        line 38: 0
      LocalVariableTable:
        Start  Length  Slot  Name   Signature
            0       7     0 $this   Lscala/Function2;
            0       7     1    v1   I
            0       7     2    v2   I
    MethodParameters:
      Name                           Flags
      $this                          final synthetic
      v1                             final
      v2                             final

  public default long apply$mcJII$sp(int, int);
    descriptor: (II)J
    flags: (0x0001) ACC_PUBLIC
    Code:
      stack=3, locals=3, args_size=3
         0: aload_0
         1: iload_1
         2: invokestatic  #149                // Method java/lang/Integer.valueOf:(I)Ljava/lang/Integer;
         5: iload_2
         6: invokestatic  #149                // Method java/lang/Integer.valueOf:(I)Ljava/lang/Integer;
         9: invokeinterface #85,  3           // InterfaceMethod apply:(Ljava/lang/Object;Ljava/lang/Object;)Ljava/lang/Object;
        14: invokestatic  #131                // Method scala/runtime/BoxesRunTime.unboxToLong:(Ljava/lang/Object;)J
        17: lreturn
      LineNumberTable:
        line 38: 0
      LocalVariableTable:
        Start  Length  Slot  Name   Signature
            0      18     0  this   Lscala/Function2;
            0      18     1    v1   I
            0      18     2    v2   I
    MethodParameters:
      Name                           Flags
      v1                             final
      v2                             final

  public static void apply$mcVII$sp$(scala.Function2, int, int);
    descriptor: (Lscala/Function2;II)V
    flags: (0x1009) ACC_PUBLIC, ACC_STATIC, ACC_SYNTHETIC
    Code:
      stack=3, locals=3, args_size=3
         0: aload_0
         1: iload_1
         2: iload_2
         3: invokespecial #293                // InterfaceMethod apply$mcVII$sp:(II)V
         6: return
      LineNumberTable:
        line 38: 0
      LocalVariableTable:
        Start  Length  Slot  Name   Signature
            0       7     0 $this   Lscala/Function2;
            0       7     1    v1   I
            0       7     2    v2   I
    MethodParameters:
      Name                           Flags
      $this                          final synthetic
      v1                             final
      v2                             final

  public default void apply$mcVII$sp(int, int);
    descriptor: (II)V
    flags: (0x0001) ACC_PUBLIC
    Code:
      stack=3, locals=3, args_size=3
         0: aload_0
         1: iload_1
         2: invokestatic  #149                // Method java/lang/Integer.valueOf:(I)Ljava/lang/Integer;
         5: iload_2
         6: invokestatic  #149                // Method java/lang/Integer.valueOf:(I)Ljava/lang/Integer;
         9: invokeinterface #85,  3           // InterfaceMethod apply:(Ljava/lang/Object;Ljava/lang/Object;)Ljava/lang/Object;
        14: pop
        15: return
      LineNumberTable:
        line 38: 0
      LocalVariableTable:
        Start  Length  Slot  Name   Signature
            0      16     0  this   Lscala/Function2;
            0      16     1    v1   I
            0      16     2    v2   I
    MethodParameters:
      Name                           Flags
      v1                             final
      v2                             final

  public static boolean apply$mcZIJ$sp$(scala.Function2, int, long);
    descriptor: (Lscala/Function2;IJ)Z
    flags: (0x1009) ACC_PUBLIC, ACC_STATIC, ACC_SYNTHETIC
    Code:
      stack=4, locals=4, args_size=3
         0: aload_0
         1: iload_1
         2: lload_2
         3: invokespecial #299                // InterfaceMethod apply$mcZIJ$sp:(IJ)Z
         6: ireturn
      LineNumberTable:
        line 38: 0
      LocalVariableTable:
        Start  Length  Slot  Name   Signature
            0       7     0 $this   Lscala/Function2;
            0       7     1    v1   I
            0       7     2    v2   J
    MethodParameters:
      Name                           Flags
      $this                          final synthetic
      v1                             final
      v2                             final

  public default boolean apply$mcZIJ$sp(int, long);
    descriptor: (IJ)Z
    flags: (0x0001) ACC_PUBLIC
    Code:
      stack=4, locals=4, args_size=3
         0: aload_0
         1: iload_1
         2: invokestatic  #149                // Method java/lang/Integer.valueOf:(I)Ljava/lang/Integer;
         5: lload_2
         6: invokestatic  #191                // Method java/lang/Long.valueOf:(J)Ljava/lang/Long;
         9: invokeinterface #85,  3           // InterfaceMethod apply:(Ljava/lang/Object;Ljava/lang/Object;)Ljava/lang/Object;
        14: invokestatic  #91                 // Method scala/runtime/BoxesRunTime.unboxToBoolean:(Ljava/lang/Object;)Z
        17: ireturn
      LineNumberTable:
        line 38: 0
      LocalVariableTable:
        Start  Length  Slot  Name   Signature
            0      18     0  this   Lscala/Function2;
            0      18     1    v1   I
            0      18     2    v2   J
    MethodParameters:
      Name                           Flags
      v1                             final
      v2                             final

  public static double apply$mcDIJ$sp$(scala.Function2, int, long);
    descriptor: (Lscala/Function2;IJ)D
    flags: (0x1009) ACC_PUBLIC, ACC_STATIC, ACC_SYNTHETIC
    Code:
      stack=4, locals=4, args_size=3
         0: aload_0
         1: iload_1
         2: lload_2
         3: invokespecial #305                // InterfaceMethod apply$mcDIJ$sp:(IJ)D
         6: dreturn
      LineNumberTable:
        line 38: 0
      LocalVariableTable:
        Start  Length  Slot  Name   Signature
            0       7     0 $this   Lscala/Function2;
            0       7     1    v1   I
            0       7     2    v2   J
    MethodParameters:
      Name                           Flags
      $this                          final synthetic
      v1                             final
      v2                             final

  public default double apply$mcDIJ$sp(int, long);
    descriptor: (IJ)D
    flags: (0x0001) ACC_PUBLIC
    Code:
      stack=4, locals=4, args_size=3
         0: aload_0
         1: iload_1
         2: invokestatic  #149                // Method java/lang/Integer.valueOf:(I)Ljava/lang/Integer;
         5: lload_2
         6: invokestatic  #191                // Method java/lang/Long.valueOf:(J)Ljava/lang/Long;
         9: invokeinterface #85,  3           // InterfaceMethod apply:(Ljava/lang/Object;Ljava/lang/Object;)Ljava/lang/Object;
        14: invokestatic  #101                // Method scala/runtime/BoxesRunTime.unboxToDouble:(Ljava/lang/Object;)D
        17: dreturn
      LineNumberTable:
        line 38: 0
      LocalVariableTable:
        Start  Length  Slot  Name   Signature
            0      18     0  this   Lscala/Function2;
            0      18     1    v1   I
            0      18     2    v2   J
    MethodParameters:
      Name                           Flags
      v1                             final
      v2                             final

  public static float apply$mcFIJ$sp$(scala.Function2, int, long);
    descriptor: (Lscala/Function2;IJ)F
    flags: (0x1009) ACC_PUBLIC, ACC_STATIC, ACC_SYNTHETIC
    Code:
      stack=4, locals=4, args_size=3
         0: aload_0
         1: iload_1
         2: lload_2
         3: invokespecial #311                // InterfaceMethod apply$mcFIJ$sp:(IJ)F
         6: freturn
      LineNumberTable:
        line 38: 0
      LocalVariableTable:
        Start  Length  Slot  Name   Signature
            0       7     0 $this   Lscala/Function2;
            0       7     1    v1   I
            0       7     2    v2   J
    MethodParameters:
      Name                           Flags
      $this                          final synthetic
      v1                             final
      v2                             final

  public default float apply$mcFIJ$sp(int, long);
    descriptor: (IJ)F
    flags: (0x0001) ACC_PUBLIC
    Code:
      stack=4, locals=4, args_size=3
         0: aload_0
         1: iload_1
         2: invokestatic  #149                // Method java/lang/Integer.valueOf:(I)Ljava/lang/Integer;
         5: lload_2
         6: invokestatic  #191                // Method java/lang/Long.valueOf:(J)Ljava/lang/Long;
         9: invokeinterface #85,  3           // InterfaceMethod apply:(Ljava/lang/Object;Ljava/lang/Object;)Ljava/lang/Object;
        14: invokestatic  #111                // Method scala/runtime/BoxesRunTime.unboxToFloat:(Ljava/lang/Object;)F
        17: freturn
      LineNumberTable:
        line 38: 0
      LocalVariableTable:
        Start  Length  Slot  Name   Signature
            0      18     0  this   Lscala/Function2;
            0      18     1    v1   I
            0      18     2    v2   J
    MethodParameters:
      Name                           Flags
      v1                             final
      v2                             final

  public static int apply$mcIIJ$sp$(scala.Function2, int, long);
    descriptor: (Lscala/Function2;IJ)I
    flags: (0x1009) ACC_PUBLIC, ACC_STATIC, ACC_SYNTHETIC
    Code:
      stack=4, locals=4, args_size=3
         0: aload_0
         1: iload_1
         2: lload_2
         3: invokespecial #317                // InterfaceMethod apply$mcIIJ$sp:(IJ)I
         6: ireturn
      LineNumberTable:
        line 38: 0
      LocalVariableTable:
        Start  Length  Slot  Name   Signature
            0       7     0 $this   Lscala/Function2;
            0       7     1    v1   I
            0       7     2    v2   J
    MethodParameters:
      Name                           Flags
      $this                          final synthetic
      v1                             final
      v2                             final

  public default int apply$mcIIJ$sp(int, long);
    descriptor: (IJ)I
    flags: (0x0001) ACC_PUBLIC
    Code:
      stack=4, locals=4, args_size=3
         0: aload_0
         1: iload_1
         2: invokestatic  #149                // Method java/lang/Integer.valueOf:(I)Ljava/lang/Integer;
         5: lload_2
         6: invokestatic  #191                // Method java/lang/Long.valueOf:(J)Ljava/lang/Long;
         9: invokeinterface #85,  3           // InterfaceMethod apply:(Ljava/lang/Object;Ljava/lang/Object;)Ljava/lang/Object;
        14: invokestatic  #121                // Method scala/runtime/BoxesRunTime.unboxToInt:(Ljava/lang/Object;)I
        17: ireturn
      LineNumberTable:
        line 38: 0
      LocalVariableTable:
        Start  Length  Slot  Name   Signature
            0      18     0  this   Lscala/Function2;
            0      18     1    v1   I
            0      18     2    v2   J
    MethodParameters:
      Name                           Flags
      v1                             final
      v2                             final

  public static long apply$mcJIJ$sp$(scala.Function2, int, long);
    descriptor: (Lscala/Function2;IJ)J
    flags: (0x1009) ACC_PUBLIC, ACC_STATIC, ACC_SYNTHETIC
    Code:
      stack=4, locals=4, args_size=3
         0: aload_0
         1: iload_1
         2: lload_2
         3: invokespecial #323                // InterfaceMethod apply$mcJIJ$sp:(IJ)J
         6: lreturn
      LineNumberTable:
        line 38: 0
      LocalVariableTable:
        Start  Length  Slot  Name   Signature
            0       7     0 $this   Lscala/Function2;
            0       7     1    v1   I
            0       7     2    v2   J
    MethodParameters:
      Name                           Flags
      $this                          final synthetic
      v1                             final
      v2                             final

  public default long apply$mcJIJ$sp(int, long);
    descriptor: (IJ)J
    flags: (0x0001) ACC_PUBLIC
    Code:
      stack=4, locals=4, args_size=3
         0: aload_0
         1: iload_1
         2: invokestatic  #149                // Method java/lang/Integer.valueOf:(I)Ljava/lang/Integer;
         5: lload_2
         6: invokestatic  #191                // Method java/lang/Long.valueOf:(J)Ljava/lang/Long;
         9: invokeinterface #85,  3           // InterfaceMethod apply:(Ljava/lang/Object;Ljava/lang/Object;)Ljava/lang/Object;
        14: invokestatic  #131                // Method scala/runtime/BoxesRunTime.unboxToLong:(Ljava/lang/Object;)J
        17: lreturn
      LineNumberTable:
        line 38: 0
      LocalVariableTable:
        Start  Length  Slot  Name   Signature
            0      18     0  this   Lscala/Function2;
            0      18     1    v1   I
            0      18     2    v2   J
    MethodParameters:
      Name                           Flags
      v1                             final
      v2                             final

  public static void apply$mcVIJ$sp$(scala.Function2, int, long);
    descriptor: (Lscala/Function2;IJ)V
    flags: (0x1009) ACC_PUBLIC, ACC_STATIC, ACC_SYNTHETIC
    Code:
      stack=4, locals=4, args_size=3
         0: aload_0
         1: iload_1
         2: lload_2
         3: invokespecial #329                // InterfaceMethod apply$mcVIJ$sp:(IJ)V
         6: return
      LineNumberTable:
        line 38: 0
      LocalVariableTable:
        Start  Length  Slot  Name   Signature
            0       7     0 $this   Lscala/Function2;
            0       7     1    v1   I
            0       7     2    v2   J
    MethodParameters:
      Name                           Flags
      $this                          final synthetic
      v1                             final
      v2                             final

  public default void apply$mcVIJ$sp(int, long);
    descriptor: (IJ)V
    flags: (0x0001) ACC_PUBLIC
    Code:
      stack=4, locals=4, args_size=3
         0: aload_0
         1: iload_1
         2: invokestatic  #149                // Method java/lang/Integer.valueOf:(I)Ljava/lang/Integer;
         5: lload_2
         6: invokestatic  #191                // Method java/lang/Long.valueOf:(J)Ljava/lang/Long;
         9: invokeinterface #85,  3           // InterfaceMethod apply:(Ljava/lang/Object;Ljava/lang/Object;)Ljava/lang/Object;
        14: pop
        15: return
      LineNumberTable:
        line 38: 0
      LocalVariableTable:
        Start  Length  Slot  Name   Signature
            0      16     0  this   Lscala/Function2;
            0      16     1    v1   I
            0      16     2    v2   J
    MethodParameters:
      Name                           Flags
      v1                             final
      v2                             final

  public static boolean apply$mcZJD$sp$(scala.Function2, long, double);
    descriptor: (Lscala/Function2;JD)Z
    flags: (0x1009) ACC_PUBLIC, ACC_STATIC, ACC_SYNTHETIC
    Code:
      stack=5, locals=5, args_size=3
         0: aload_0
         1: lload_1
         2: dload_3
         3: invokespecial #335                // InterfaceMethod apply$mcZJD$sp:(JD)Z
         6: ireturn
      LineNumberTable:
        line 38: 0
      LocalVariableTable:
        Start  Length  Slot  Name   Signature
            0       7     0 $this   Lscala/Function2;
            0       7     1    v1   J
            0       7     3    v2   D
    MethodParameters:
      Name                           Flags
      $this                          final synthetic
      v1                             final
      v2                             final

  public default boolean apply$mcZJD$sp(long, double);
    descriptor: (JD)Z
    flags: (0x0001) ACC_PUBLIC
    Code:
      stack=4, locals=5, args_size=3
         0: aload_0
         1: lload_1
         2: invokestatic  #191                // Method java/lang/Long.valueOf:(J)Ljava/lang/Long;
         5: dload_3
         6: invokestatic  #83                 // Method java/lang/Double.valueOf:(D)Ljava/lang/Double;
         9: invokeinterface #85,  3           // InterfaceMethod apply:(Ljava/lang/Object;Ljava/lang/Object;)Ljava/lang/Object;
        14: invokestatic  #91                 // Method scala/runtime/BoxesRunTime.unboxToBoolean:(Ljava/lang/Object;)Z
        17: ireturn
      LineNumberTable:
        line 38: 0
      LocalVariableTable:
        Start  Length  Slot  Name   Signature
            0      18     0  this   Lscala/Function2;
            0      18     1    v1   J
            0      18     3    v2   D
    MethodParameters:
      Name                           Flags
      v1                             final
      v2                             final

  public static double apply$mcDJD$sp$(scala.Function2, long, double);
    descriptor: (Lscala/Function2;JD)D
    flags: (0x1009) ACC_PUBLIC, ACC_STATIC, ACC_SYNTHETIC
    Code:
      stack=5, locals=5, args_size=3
         0: aload_0
         1: lload_1
         2: dload_3
         3: invokespecial #341                // InterfaceMethod apply$mcDJD$sp:(JD)D
         6: dreturn
      LineNumberTable:
        line 38: 0
      LocalVariableTable:
        Start  Length  Slot  Name   Signature
            0       7     0 $this   Lscala/Function2;
            0       7     1    v1   J
            0       7     3    v2   D
    MethodParameters:
      Name                           Flags
      $this                          final synthetic
      v1                             final
      v2                             final

  public default double apply$mcDJD$sp(long, double);
    descriptor: (JD)D
    flags: (0x0001) ACC_PUBLIC
    Code:
      stack=4, locals=5, args_size=3
         0: aload_0
         1: lload_1
         2: invokestatic  #191                // Method java/lang/Long.valueOf:(J)Ljava/lang/Long;
         5: dload_3
         6: invokestatic  #83                 // Method java/lang/Double.valueOf:(D)Ljava/lang/Double;
         9: invokeinterface #85,  3           // InterfaceMethod apply:(Ljava/lang/Object;Ljava/lang/Object;)Ljava/lang/Object;
        14: invokestatic  #101                // Method scala/runtime/BoxesRunTime.unboxToDouble:(Ljava/lang/Object;)D
        17: dreturn
      LineNumberTable:
        line 38: 0
      LocalVariableTable:
        Start  Length  Slot  Name   Signature
            0      18     0  this   Lscala/Function2;
            0      18     1    v1   J
            0      18     3    v2   D
    MethodParameters:
      Name                           Flags
      v1                             final
      v2                             final

  public static float apply$mcFJD$sp$(scala.Function2, long, double);
    descriptor: (Lscala/Function2;JD)F
    flags: (0x1009) ACC_PUBLIC, ACC_STATIC, ACC_SYNTHETIC
    Code:
      stack=5, locals=5, args_size=3
         0: aload_0
         1: lload_1
         2: dload_3
         3: invokespecial #347                // InterfaceMethod apply$mcFJD$sp:(JD)F
         6: freturn
      LineNumberTable:
        line 38: 0
      LocalVariableTable:
        Start  Length  Slot  Name   Signature
            0       7     0 $this   Lscala/Function2;
            0       7     1    v1   J
            0       7     3    v2   D
    MethodParameters:
      Name                           Flags
      $this                          final synthetic
      v1                             final
      v2                             final

  public default float apply$mcFJD$sp(long, double);
    descriptor: (JD)F
    flags: (0x0001) ACC_PUBLIC
    Code:
      stack=4, locals=5, args_size=3
         0: aload_0
         1: lload_1
         2: invokestatic  #191                // Method java/lang/Long.valueOf:(J)Ljava/lang/Long;
         5: dload_3
         6: invokestatic  #83                 // Method java/lang/Double.valueOf:(D)Ljava/lang/Double;
         9: invokeinterface #85,  3           // InterfaceMethod apply:(Ljava/lang/Object;Ljava/lang/Object;)Ljava/lang/Object;
        14: invokestatic  #111                // Method scala/runtime/BoxesRunTime.unboxToFloat:(Ljava/lang/Object;)F
        17: freturn
      LineNumberTable:
        line 38: 0
      LocalVariableTable:
        Start  Length  Slot  Name   Signature
            0      18     0  this   Lscala/Function2;
            0      18     1    v1   J
            0      18     3    v2   D
    MethodParameters:
      Name                           Flags
      v1                             final
      v2                             final

  public static int apply$mcIJD$sp$(scala.Function2, long, double);
    descriptor: (Lscala/Function2;JD)I
    flags: (0x1009) ACC_PUBLIC, ACC_STATIC, ACC_SYNTHETIC
    Code:
      stack=5, locals=5, args_size=3
         0: aload_0
         1: lload_1
         2: dload_3
         3: invokespecial #353                // InterfaceMethod apply$mcIJD$sp:(JD)I
         6: ireturn
      LineNumberTable:
        line 38: 0
      LocalVariableTable:
        Start  Length  Slot  Name   Signature
            0       7     0 $this   Lscala/Function2;
            0       7     1    v1   J
            0       7     3    v2   D
    MethodParameters:
      Name                           Flags
      $this                          final synthetic
      v1                             final
      v2                             final

  public default int apply$mcIJD$sp(long, double);
    descriptor: (JD)I
    flags: (0x0001) ACC_PUBLIC
    Code:
      stack=4, locals=5, args_size=3
         0: aload_0
         1: lload_1
         2: invokestatic  #191                // Method java/lang/Long.valueOf:(J)Ljava/lang/Long;
         5: dload_3
         6: invokestatic  #83                 // Method java/lang/Double.valueOf:(D)Ljava/lang/Double;
         9: invokeinterface #85,  3           // InterfaceMethod apply:(Ljava/lang/Object;Ljava/lang/Object;)Ljava/lang/Object;
        14: invokestatic  #121                // Method scala/runtime/BoxesRunTime.unboxToInt:(Ljava/lang/Object;)I
        17: ireturn
      LineNumberTable:
        line 38: 0
      LocalVariableTable:
        Start  Length  Slot  Name   Signature
            0      18     0  this   Lscala/Function2;
            0      18     1    v1   J
            0      18     3    v2   D
    MethodParameters:
      Name                           Flags
      v1                             final
      v2                             final

  public static long apply$mcJJD$sp$(scala.Function2, long, double);
    descriptor: (Lscala/Function2;JD)J
    flags: (0x1009) ACC_PUBLIC, ACC_STATIC, ACC_SYNTHETIC
    Code:
      stack=5, locals=5, args_size=3
         0: aload_0
         1: lload_1
         2: dload_3
         3: invokespecial #359                // InterfaceMethod apply$mcJJD$sp:(JD)J
         6: lreturn
      LineNumberTable:
        line 38: 0
      LocalVariableTable:
        Start  Length  Slot  Name   Signature
            0       7     0 $this   Lscala/Function2;
            0       7     1    v1   J
            0       7     3    v2   D
    MethodParameters:
      Name                           Flags
      $this                          final synthetic
      v1                             final
      v2                             final

  public default long apply$mcJJD$sp(long, double);
    descriptor: (JD)J
    flags: (0x0001) ACC_PUBLIC
    Code:
      stack=4, locals=5, args_size=3
         0: aload_0
         1: lload_1
         2: invokestatic  #191                // Method java/lang/Long.valueOf:(J)Ljava/lang/Long;
         5: dload_3
         6: invokestatic  #83                 // Method java/lang/Double.valueOf:(D)Ljava/lang/Double;
         9: invokeinterface #85,  3           // InterfaceMethod apply:(Ljava/lang/Object;Ljava/lang/Object;)Ljava/lang/Object;
        14: invokestatic  #131                // Method scala/runtime/BoxesRunTime.unboxToLong:(Ljava/lang/Object;)J
        17: lreturn
      LineNumberTable:
        line 38: 0
      LocalVariableTable:
        Start  Length  Slot  Name   Signature
            0      18     0  this   Lscala/Function2;
            0      18     1    v1   J
            0      18     3    v2   D
    MethodParameters:
      Name                           Flags
      v1                             final
      v2                             final

  public static void apply$mcVJD$sp$(scala.Function2, long, double);
    descriptor: (Lscala/Function2;JD)V
    flags: (0x1009) ACC_PUBLIC, ACC_STATIC, ACC_SYNTHETIC
    Code:
      stack=5, locals=5, args_size=3
         0: aload_0
         1: lload_1
         2: dload_3
         3: invokespecial #365                // InterfaceMethod apply$mcVJD$sp:(JD)V
         6: return
      LineNumberTable:
        line 38: 0
      LocalVariableTable:
        Start  Length  Slot  Name   Signature
            0       7     0 $this   Lscala/Function2;
            0       7     1    v1   J
            0       7     3    v2   D
    MethodParameters:
      Name                           Flags
      $this                          final synthetic
      v1                             final
      v2                             final

  public default void apply$mcVJD$sp(long, double);
    descriptor: (JD)V
    flags: (0x0001) ACC_PUBLIC
    Code:
      stack=4, locals=5, args_size=3
         0: aload_0
         1: lload_1
         2: invokestatic  #191                // Method java/lang/Long.valueOf:(J)Ljava/lang/Long;
         5: dload_3
         6: invokestatic  #83                 // Method java/lang/Double.valueOf:(D)Ljava/lang/Double;
         9: invokeinterface #85,  3           // InterfaceMethod apply:(Ljava/lang/Object;Ljava/lang/Object;)Ljava/lang/Object;
        14: pop
        15: return
      LineNumberTable:
        line 38: 0
      LocalVariableTable:
        Start  Length  Slot  Name   Signature
            0      16     0  this   Lscala/Function2;
            0      16     1    v1   J
            0      16     3    v2   D
    MethodParameters:
      Name                           Flags
      v1                             final
      v2                             final

  public static boolean apply$mcZJI$sp$(scala.Function2, long, int);
    descriptor: (Lscala/Function2;JI)Z
    flags: (0x1009) ACC_PUBLIC, ACC_STATIC, ACC_SYNTHETIC
    Code:
      stack=4, locals=4, args_size=3
         0: aload_0
         1: lload_1
         2: iload_3
         3: invokespecial #371                // InterfaceMethod apply$mcZJI$sp:(JI)Z
         6: ireturn
      LineNumberTable:
        line 38: 0
      LocalVariableTable:
        Start  Length  Slot  Name   Signature
            0       7     0 $this   Lscala/Function2;
            0       7     1    v1   J
            0       7     3    v2   I
    MethodParameters:
      Name                           Flags
      $this                          final synthetic
      v1                             final
      v2                             final

  public default boolean apply$mcZJI$sp(long, int);
    descriptor: (JI)Z
    flags: (0x0001) ACC_PUBLIC
    Code:
      stack=3, locals=4, args_size=3
         0: aload_0
         1: lload_1
         2: invokestatic  #191                // Method java/lang/Long.valueOf:(J)Ljava/lang/Long;
         5: iload_3
         6: invokestatic  #149                // Method java/lang/Integer.valueOf:(I)Ljava/lang/Integer;
         9: invokeinterface #85,  3           // InterfaceMethod apply:(Ljava/lang/Object;Ljava/lang/Object;)Ljava/lang/Object;
        14: invokestatic  #91                 // Method scala/runtime/BoxesRunTime.unboxToBoolean:(Ljava/lang/Object;)Z
        17: ireturn
      LineNumberTable:
        line 38: 0
      LocalVariableTable:
        Start  Length  Slot  Name   Signature
            0      18     0  this   Lscala/Function2;
            0      18     1    v1   J
            0      18     3    v2   I
    MethodParameters:
      Name                           Flags
      v1                             final
      v2                             final

  public static double apply$mcDJI$sp$(scala.Function2, long, int);
    descriptor: (Lscala/Function2;JI)D
    flags: (0x1009) ACC_PUBLIC, ACC_STATIC, ACC_SYNTHETIC
    Code:
      stack=4, locals=4, args_size=3
         0: aload_0
         1: lload_1
         2: iload_3
         3: invokespecial #377                // InterfaceMethod apply$mcDJI$sp:(JI)D
         6: dreturn
      LineNumberTable:
        line 38: 0
      LocalVariableTable:
        Start  Length  Slot  Name   Signature
            0       7     0 $this   Lscala/Function2;
            0       7     1    v1   J
            0       7     3    v2   I
    MethodParameters:
      Name                           Flags
      $this                          final synthetic
      v1                             final
      v2                             final

  public default double apply$mcDJI$sp(long, int);
    descriptor: (JI)D
    flags: (0x0001) ACC_PUBLIC
    Code:
      stack=3, locals=4, args_size=3
         0: aload_0
         1: lload_1
         2: invokestatic  #191                // Method java/lang/Long.valueOf:(J)Ljava/lang/Long;
         5: iload_3
         6: invokestatic  #149                // Method java/lang/Integer.valueOf:(I)Ljava/lang/Integer;
         9: invokeinterface #85,  3           // InterfaceMethod apply:(Ljava/lang/Object;Ljava/lang/Object;)Ljava/lang/Object;
        14: invokestatic  #101                // Method scala/runtime/BoxesRunTime.unboxToDouble:(Ljava/lang/Object;)D
        17: dreturn
      LineNumberTable:
        line 38: 0
      LocalVariableTable:
        Start  Length  Slot  Name   Signature
            0      18     0  this   Lscala/Function2;
            0      18     1    v1   J
            0      18     3    v2   I
    MethodParameters:
      Name                           Flags
      v1                             final
      v2                             final

  public static float apply$mcFJI$sp$(scala.Function2, long, int);
    descriptor: (Lscala/Function2;JI)F
    flags: (0x1009) ACC_PUBLIC, ACC_STATIC, ACC_SYNTHETIC
    Code:
      stack=4, locals=4, args_size=3
         0: aload_0
         1: lload_1
         2: iload_3
         3: invokespecial #383                // InterfaceMethod apply$mcFJI$sp:(JI)F
         6: freturn
      LineNumberTable:
        line 38: 0
      LocalVariableTable:
        Start  Length  Slot  Name   Signature
            0       7     0 $this   Lscala/Function2;
            0       7     1    v1   J
            0       7     3    v2   I
    MethodParameters:
      Name                           Flags
      $this                          final synthetic
      v1                             final
      v2                             final

  public default float apply$mcFJI$sp(long, int);
    descriptor: (JI)F
    flags: (0x0001) ACC_PUBLIC
    Code:
      stack=3, locals=4, args_size=3
         0: aload_0
         1: lload_1
         2: invokestatic  #191                // Method java/lang/Long.valueOf:(J)Ljava/lang/Long;
         5: iload_3
         6: invokestatic  #149                // Method java/lang/Integer.valueOf:(I)Ljava/lang/Integer;
         9: invokeinterface #85,  3           // InterfaceMethod apply:(Ljava/lang/Object;Ljava/lang/Object;)Ljava/lang/Object;
        14: invokestatic  #111                // Method scala/runtime/BoxesRunTime.unboxToFloat:(Ljava/lang/Object;)F
        17: freturn
      LineNumberTable:
        line 38: 0
      LocalVariableTable:
        Start  Length  Slot  Name   Signature
            0      18     0  this   Lscala/Function2;
            0      18     1    v1   J
            0      18     3    v2   I
    MethodParameters:
      Name                           Flags
      v1                             final
      v2                             final

  public static int apply$mcIJI$sp$(scala.Function2, long, int);
    descriptor: (Lscala/Function2;JI)I
    flags: (0x1009) ACC_PUBLIC, ACC_STATIC, ACC_SYNTHETIC
    Code:
      stack=4, locals=4, args_size=3
         0: aload_0
         1: lload_1
         2: iload_3
         3: invokespecial #389                // InterfaceMethod apply$mcIJI$sp:(JI)I
         6: ireturn
      LineNumberTable:
        line 38: 0
      LocalVariableTable:
        Start  Length  Slot  Name   Signature
            0       7     0 $this   Lscala/Function2;
            0       7     1    v1   J
            0       7     3    v2   I
    MethodParameters:
      Name                           Flags
      $this                          final synthetic
      v1                             final
      v2                             final

  public default int apply$mcIJI$sp(long, int);
    descriptor: (JI)I
    flags: (0x0001) ACC_PUBLIC
    Code:
      stack=3, locals=4, args_size=3
         0: aload_0
         1: lload_1
         2: invokestatic  #191                // Method java/lang/Long.valueOf:(J)Ljava/lang/Long;
         5: iload_3
         6: invokestatic  #149                // Method java/lang/Integer.valueOf:(I)Ljava/lang/Integer;
         9: invokeinterface #85,  3           // InterfaceMethod apply:(Ljava/lang/Object;Ljava/lang/Object;)Ljava/lang/Object;
        14: invokestatic  #121                // Method scala/runtime/BoxesRunTime.unboxToInt:(Ljava/lang/Object;)I
        17: ireturn
      LineNumberTable:
        line 38: 0
      LocalVariableTable:
        Start  Length  Slot  Name   Signature
            0      18     0  this   Lscala/Function2;
            0      18     1    v1   J
            0      18     3    v2   I
    MethodParameters:
      Name                           Flags
      v1                             final
      v2                             final

  public static long apply$mcJJI$sp$(scala.Function2, long, int);
    descriptor: (Lscala/Function2;JI)J
    flags: (0x1009) ACC_PUBLIC, ACC_STATIC, ACC_SYNTHETIC
    Code:
      stack=4, locals=4, args_size=3
         0: aload_0
         1: lload_1
         2: iload_3
         3: invokespecial #395                // InterfaceMethod apply$mcJJI$sp:(JI)J
         6: lreturn
      LineNumberTable:
        line 38: 0
      LocalVariableTable:
        Start  Length  Slot  Name   Signature
            0       7     0 $this   Lscala/Function2;
            0       7     1    v1   J
            0       7     3    v2   I
    MethodParameters:
      Name                           Flags
      $this                          final synthetic
      v1                             final
      v2                             final

  public default long apply$mcJJI$sp(long, int);
    descriptor: (JI)J
    flags: (0x0001) ACC_PUBLIC
    Code:
      stack=3, locals=4, args_size=3
         0: aload_0
         1: lload_1
         2: invokestatic  #191                // Method java/lang/Long.valueOf:(J)Ljava/lang/Long;
         5: iload_3
         6: invokestatic  #149                // Method java/lang/Integer.valueOf:(I)Ljava/lang/Integer;
         9: invokeinterface #85,  3           // InterfaceMethod apply:(Ljava/lang/Object;Ljava/lang/Object;)Ljava/lang/Object;
        14: invokestatic  #131                // Method scala/runtime/BoxesRunTime.unboxToLong:(Ljava/lang/Object;)J
        17: lreturn
      LineNumberTable:
        line 38: 0
      LocalVariableTable:
        Start  Length  Slot  Name   Signature
            0      18     0  this   Lscala/Function2;
            0      18     1    v1   J
            0      18     3    v2   I
    MethodParameters:
      Name                           Flags
      v1                             final
      v2                             final

  public static void apply$mcVJI$sp$(scala.Function2, long, int);
    descriptor: (Lscala/Function2;JI)V
    flags: (0x1009) ACC_PUBLIC, ACC_STATIC, ACC_SYNTHETIC
    Code:
      stack=4, locals=4, args_size=3
         0: aload_0
         1: lload_1
         2: iload_3
         3: invokespecial #401                // InterfaceMethod apply$mcVJI$sp:(JI)V
         6: return
      LineNumberTable:
        line 38: 0
      LocalVariableTable:
        Start  Length  Slot  Name   Signature
            0       7     0 $this   Lscala/Function2;
            0       7     1    v1   J
            0       7     3    v2   I
    MethodParameters:
      Name                           Flags
      $this                          final synthetic
      v1                             final
      v2                             final

  public default void apply$mcVJI$sp(long, int);
    descriptor: (JI)V
    flags: (0x0001) ACC_PUBLIC
    Code:
      stack=3, locals=4, args_size=3
         0: aload_0
         1: lload_1
         2: invokestatic  #191                // Method java/lang/Long.valueOf:(J)Ljava/lang/Long;
         5: iload_3
         6: invokestatic  #149                // Method java/lang/Integer.valueOf:(I)Ljava/lang/Integer;
         9: invokeinterface #85,  3           // InterfaceMethod apply:(Ljava/lang/Object;Ljava/lang/Object;)Ljava/lang/Object;
        14: pop
        15: return
      LineNumberTable:
        line 38: 0
      LocalVariableTable:
        Start  Length  Slot  Name   Signature
            0      16     0  this   Lscala/Function2;
            0      16     1    v1   J
            0      16     3    v2   I
    MethodParameters:
      Name                           Flags
      v1                             final
      v2                             final

  public static boolean apply$mcZJJ$sp$(scala.Function2, long, long);
    descriptor: (Lscala/Function2;JJ)Z
    flags: (0x1009) ACC_PUBLIC, ACC_STATIC, ACC_SYNTHETIC
    Code:
      stack=5, locals=5, args_size=3
         0: aload_0
         1: lload_1
         2: lload_3
         3: invokespecial #407                // InterfaceMethod apply$mcZJJ$sp:(JJ)Z
         6: ireturn
      LineNumberTable:
        line 38: 0
      LocalVariableTable:
        Start  Length  Slot  Name   Signature
            0       7     0 $this   Lscala/Function2;
            0       7     1    v1   J
            0       7     3    v2   J
    MethodParameters:
      Name                           Flags
      $this                          final synthetic
      v1                             final
      v2                             final

  public default boolean apply$mcZJJ$sp(long, long);
    descriptor: (JJ)Z
    flags: (0x0001) ACC_PUBLIC
    Code:
      stack=4, locals=5, args_size=3
         0: aload_0
         1: lload_1
         2: invokestatic  #191                // Method java/lang/Long.valueOf:(J)Ljava/lang/Long;
         5: lload_3
         6: invokestatic  #191                // Method java/lang/Long.valueOf:(J)Ljava/lang/Long;
         9: invokeinterface #85,  3           // InterfaceMethod apply:(Ljava/lang/Object;Ljava/lang/Object;)Ljava/lang/Object;
        14: invokestatic  #91                 // Method scala/runtime/BoxesRunTime.unboxToBoolean:(Ljava/lang/Object;)Z
        17: ireturn
      LineNumberTable:
        line 38: 0
      LocalVariableTable:
        Start  Length  Slot  Name   Signature
            0      18     0  this   Lscala/Function2;
            0      18     1    v1   J
            0      18     3    v2   J
    MethodParameters:
      Name                           Flags
      v1                             final
      v2                             final

  public static double apply$mcDJJ$sp$(scala.Function2, long, long);
    descriptor: (Lscala/Function2;JJ)D
    flags: (0x1009) ACC_PUBLIC, ACC_STATIC, ACC_SYNTHETIC
    Code:
      stack=5, locals=5, args_size=3
         0: aload_0
         1: lload_1
         2: lload_3
         3: invokespecial #413                // InterfaceMethod apply$mcDJJ$sp:(JJ)D
         6: dreturn
      LineNumberTable:
        line 38: 0
      LocalVariableTable:
        Start  Length  Slot  Name   Signature
            0       7     0 $this   Lscala/Function2;
            0       7     1    v1   J
            0       7     3    v2   J
    MethodParameters:
      Name                           Flags
      $this                          final synthetic
      v1                             final
      v2                             final

  public default double apply$mcDJJ$sp(long, long);
    descriptor: (JJ)D
    flags: (0x0001) ACC_PUBLIC
    Code:
      stack=4, locals=5, args_size=3
         0: aload_0
         1: lload_1
         2: invokestatic  #191                // Method java/lang/Long.valueOf:(J)Ljava/lang/Long;
         5: lload_3
         6: invokestatic  #191                // Method java/lang/Long.valueOf:(J)Ljava/lang/Long;
         9: invokeinterface #85,  3           // InterfaceMethod apply:(Ljava/lang/Object;Ljava/lang/Object;)Ljava/lang/Object;
        14: invokestatic  #101                // Method scala/runtime/BoxesRunTime.unboxToDouble:(Ljava/lang/Object;)D
        17: dreturn
      LineNumberTable:
        line 38: 0
      LocalVariableTable:
        Start  Length  Slot  Name   Signature
            0      18     0  this   Lscala/Function2;
            0      18     1    v1   J
            0      18     3    v2   J
    MethodParameters:
      Name                           Flags
      v1                             final
      v2                             final

  public static float apply$mcFJJ$sp$(scala.Function2, long, long);
    descriptor: (Lscala/Function2;JJ)F
    flags: (0x1009) ACC_PUBLIC, ACC_STATIC, ACC_SYNTHETIC
    Code:
      stack=5, locals=5, args_size=3
         0: aload_0
         1: lload_1
         2: lload_3
         3: invokespecial #419                // InterfaceMethod apply$mcFJJ$sp:(JJ)F
         6: freturn
      LineNumberTable:
        line 38: 0
      LocalVariableTable:
        Start  Length  Slot  Name   Signature
            0       7     0 $this   Lscala/Function2;
            0       7     1    v1   J
            0       7     3    v2   J
    MethodParameters:
      Name                           Flags
      $this                          final synthetic
      v1                             final
      v2                             final

  public default float apply$mcFJJ$sp(long, long);
    descriptor: (JJ)F
    flags: (0x0001) ACC_PUBLIC
    Code:
      stack=4, locals=5, args_size=3
         0: aload_0
         1: lload_1
         2: invokestatic  #191                // Method java/lang/Long.valueOf:(J)Ljava/lang/Long;
         5: lload_3
         6: invokestatic  #191                // Method java/lang/Long.valueOf:(J)Ljava/lang/Long;
         9: invokeinterface #85,  3           // InterfaceMethod apply:(Ljava/lang/Object;Ljava/lang/Object;)Ljava/lang/Object;
        14: invokestatic  #111                // Method scala/runtime/BoxesRunTime.unboxToFloat:(Ljava/lang/Object;)F
        17: freturn
      LineNumberTable:
        line 38: 0
      LocalVariableTable:
        Start  Length  Slot  Name   Signature
            0      18     0  this   Lscala/Function2;
            0      18     1    v1   J
            0      18     3    v2   J
    MethodParameters:
      Name                           Flags
      v1                             final
      v2                             final

  public static int apply$mcIJJ$sp$(scala.Function2, long, long);
    descriptor: (Lscala/Function2;JJ)I
    flags: (0x1009) ACC_PUBLIC, ACC_STATIC, ACC_SYNTHETIC
    Code:
      stack=5, locals=5, args_size=3
         0: aload_0
         1: lload_1
         2: lload_3
         3: invokespecial #425                // InterfaceMethod apply$mcIJJ$sp:(JJ)I
         6: ireturn
      LineNumberTable:
        line 38: 0
      LocalVariableTable:
        Start  Length  Slot  Name   Signature
            0       7     0 $this   Lscala/Function2;
            0       7     1    v1   J
            0       7     3    v2   J
    MethodParameters:
      Name                           Flags
      $this                          final synthetic
      v1                             final
      v2                             final

  public default int apply$mcIJJ$sp(long, long);
    descriptor: (JJ)I
    flags: (0x0001) ACC_PUBLIC
    Code:
      stack=4, locals=5, args_size=3
         0: aload_0
         1: lload_1
         2: invokestatic  #191                // Method java/lang/Long.valueOf:(J)Ljava/lang/Long;
         5: lload_3
         6: invokestatic  #191                // Method java/lang/Long.valueOf:(J)Ljava/lang/Long;
         9: invokeinterface #85,  3           // InterfaceMethod apply:(Ljava/lang/Object;Ljava/lang/Object;)Ljava/lang/Object;
        14: invokestatic  #121                // Method scala/runtime/BoxesRunTime.unboxToInt:(Ljava/lang/Object;)I
        17: ireturn
      LineNumberTable:
        line 38: 0
      LocalVariableTable:
        Start  Length  Slot  Name   Signature
            0      18     0  this   Lscala/Function2;
            0      18     1    v1   J
            0      18     3    v2   J
    MethodParameters:
      Name                           Flags
      v1                             final
      v2                             final

  public static long apply$mcJJJ$sp$(scala.Function2, long, long);
    descriptor: (Lscala/Function2;JJ)J
    flags: (0x1009) ACC_PUBLIC, ACC_STATIC, ACC_SYNTHETIC
    Code:
      stack=5, locals=5, args_size=3
         0: aload_0
         1: lload_1
         2: lload_3
         3: invokespecial #431                // InterfaceMethod apply$mcJJJ$sp:(JJ)J
         6: lreturn
      LineNumberTable:
        line 38: 0
      LocalVariableTable:
        Start  Length  Slot  Name   Signature
            0       7     0 $this   Lscala/Function2;
            0       7     1    v1   J
            0       7     3    v2   J
    MethodParameters:
      Name                           Flags
      $this                          final synthetic
      v1                             final
      v2                             final

  public default long apply$mcJJJ$sp(long, long);
    descriptor: (JJ)J
    flags: (0x0001) ACC_PUBLIC
    Code:
      stack=4, locals=5, args_size=3
         0: aload_0
         1: lload_1
         2: invokestatic  #191                // Method java/lang/Long.valueOf:(J)Ljava/lang/Long;
         5: lload_3
         6: invokestatic  #191                // Method java/lang/Long.valueOf:(J)Ljava/lang/Long;
         9: invokeinterface #85,  3           // InterfaceMethod apply:(Ljava/lang/Object;Ljava/lang/Object;)Ljava/lang/Object;
        14: invokestatic  #131                // Method scala/runtime/BoxesRunTime.unboxToLong:(Ljava/lang/Object;)J
        17: lreturn
      LineNumberTable:
        line 38: 0
      LocalVariableTable:
        Start  Length  Slot  Name   Signature
            0      18     0  this   Lscala/Function2;
            0      18     1    v1   J
            0      18     3    v2   J
    MethodParameters:
      Name                           Flags
      v1                             final
      v2                             final

  public static void apply$mcVJJ$sp$(scala.Function2, long, long);
    descriptor: (Lscala/Function2;JJ)V
    flags: (0x1009) ACC_PUBLIC, ACC_STATIC, ACC_SYNTHETIC
    Code:
      stack=5, locals=5, args_size=3
         0: aload_0
         1: lload_1
         2: lload_3
         3: invokespecial #437                // InterfaceMethod apply$mcVJJ$sp:(JJ)V
         6: return
      LineNumberTable:
        line 38: 0
      LocalVariableTable:
        Start  Length  Slot  Name   Signature
            0       7     0 $this   Lscala/Function2;
            0       7     1    v1   J
            0       7     3    v2   J
    MethodParameters:
      Name                           Flags
      $this                          final synthetic
      v1                             final
      v2                             final

  public default void apply$mcVJJ$sp(long, long);
    descriptor: (JJ)V
    flags: (0x0001) ACC_PUBLIC
    Code:
      stack=4, locals=5, args_size=3
         0: aload_0
         1: lload_1
         2: invokestatic  #191                // Method java/lang/Long.valueOf:(J)Ljava/lang/Long;
         5: lload_3
         6: invokestatic  #191                // Method java/lang/Long.valueOf:(J)Ljava/lang/Long;
         9: invokeinterface #85,  3           // InterfaceMethod apply:(Ljava/lang/Object;Ljava/lang/Object;)Ljava/lang/Object;
        14: pop
        15: return
      LineNumberTable:
        line 38: 0
      LocalVariableTable:
        Start  Length  Slot  Name   Signature
            0      16     0  this   Lscala/Function2;
            0      16     1    v1   J
            0      16     3    v2   J
    MethodParameters:
      Name                           Flags
      v1                             final
      v2                             final

  public static java.lang.Object $anonfun$curried$2(scala.Function2, java.lang.Object, java.lang.Object);
    descriptor: (Lscala/Function2;Ljava/lang/Object;Ljava/lang/Object;)Ljava/lang/Object;
    flags: (0x1009) ACC_PUBLIC, ACC_STATIC, ACC_SYNTHETIC
    Code:
      stack=3, locals=3, args_size=3
         0: aload_0
         1: aload_1
         2: aload_2
         3: invokeinterface #85,  3           // InterfaceMethod apply:(Ljava/lang/Object;Ljava/lang/Object;)Ljava/lang/Object;
         8: areturn
      LineNumberTable:
        line 44: 0
      LocalVariableTable:
        Start  Length  Slot  Name   Signature
            0       9     0 $this   Lscala/Function2;
            0       9     1  x1$1   Ljava/lang/Object;
            0       9     2    x2   Ljava/lang/Object;
    MethodParameters:
      Name                           Flags
      $this                          final synthetic
      x1$1                           final
      x2                             final

  public static scala.Function1 $anonfun$curried$1(scala.Function2, java.lang.Object);
    descriptor: (Lscala/Function2;Ljava/lang/Object;)Lscala/Function1;
    flags: (0x1009) ACC_PUBLIC, ACC_STATIC, ACC_SYNTHETIC
    Code:
      stack=2, locals=2, args_size=2
         0: aload_0
         1: aload_1
         2: invokedynamic #448,  0            // InvokeDynamic #2:apply:(Lscala/Function2;Ljava/lang/Object;)Lscala/Function1;
         7: areturn
      LineNumberTable:
        line 44: 0
      LocalVariableTable:
        Start  Length  Slot  Name   Signature
            0       8     0 $this   Lscala/Function2;
            0       8     1    x1   Ljava/lang/Object;
    MethodParameters:
      Name                           Flags
      $this                          final synthetic
      x1                             final

  public static java.lang.Object $anonfun$tupled$1(scala.Function2, scala.Tuple2);
    descriptor: (Lscala/Function2;Lscala/Tuple2;)Ljava/lang/Object;
    flags: (0x1009) ACC_PUBLIC, ACC_STATIC, ACC_SYNTHETIC
    Code:
      stack=3, locals=5, args_size=2
         0: aload_1
         1: ifnull        28
         4: aload_1
         5: invokevirtual #455                // Method scala/Tuple2._1:()Ljava/lang/Object;
         8: astore_3
         9: aload_1
        10: invokevirtual #458                // Method scala/Tuple2._2:()Ljava/lang/Object;
        13: astore        4
        15: aload_0
        16: aload_3
        17: aload         4
        19: invokeinterface #85,  3           // InterfaceMethod apply:(Ljava/lang/Object;Ljava/lang/Object;)Ljava/lang/Object;
        24: astore_2
        25: goto          37
        28: new           #460                // class scala/MatchError
        31: dup
        32: aconst_null
        33: invokespecial #464                // Method scala/MatchError."<init>":(Ljava/lang/Object;)V
        36: athrow
        37: aload_2
        38: areturn
      StackMapTable: number_of_entries = 2
        frame_type = 28 /* same */
        frame_type = 254 /* append */
          offset_delta = 8
          locals = [ class java/lang/Object, class java/lang/Object, class java/lang/Object ]
      LineNumberTable:
        line 53: 0
        line 52: 28
      LocalVariableTable:
        Start  Length  Slot  Name   Signature
            9      19     3    x1   Ljava/lang/Object;
           15      13     4    x2   Ljava/lang/Object;
            0      39     0 $this   Lscala/Function2;
            0      39     1  x0$1   Lscala/Tuple2;
    MethodParameters:
      Name                           Flags
      $this                          final synthetic
      x0$1                           final

  public static void $init$(scala.Function2);
    descriptor: (Lscala/Function2;)V
    flags: (0x0009) ACC_PUBLIC, ACC_STATIC
    Code:
      stack=0, locals=1, args_size=1
         0: return
      LineNumberTable:
        line 34: 0
      LocalVariableTable:
        Start  Length  Slot  Name   Signature
            0       1     0 $this   Lscala/Function2;
    MethodParameters:
      Name                           Flags
      $this                          final synthetic

  private static java.lang.Object $deserializeLambda$(java.lang.invoke.SerializedLambda);
    descriptor: (Ljava/lang/invoke/SerializedLambda;)Ljava/lang/Object;
    flags: (0x100a) ACC_PRIVATE, ACC_STATIC, ACC_SYNTHETIC
    Code:
      stack=1, locals=1, args_size=1
         0: aload_0
         1: invokedynamic #479,  0            // InvokeDynamic #3:lambdaDeserialize:(Ljava/lang/invoke/SerializedLambda;)Ljava/lang/Object;
         6: areturn
}
InnerClasses:
  public static final #14= #11 of #13;    // Lookup=class java/lang/invoke/MethodHandles$Lookup of class java/lang/invoke/MethodHandles
Signature: #3                           // <T1:Ljava/lang/Object;T2:Ljava/lang/Object;R:Ljava/lang/Object;>Ljava/lang/Object;
SourceFile: "Function2.scala"
RuntimeVisibleAnnotations:
  0: #7(#8=s#9)
    scala.reflect.ScalaSignature(
      bytes="\u0006\u0005i4qAB\u0004\u0011\u0002\u0007\u0005!\u0002C\u0003\u0011\u0001\u0011\u0005\u0011\u0003C\u0003\u0016\u0001\u0019\u0005a\u0003C\u0003Z\u0001\u0011\u0005!\fC\u0003g\u0001\u0011\u0005q\rC\u0003n\u0001\u0011\u0005cNA\u0005Gk:\u001cG/[8oe)\t\u0001\"A\u0003tG\u0006d\u0017m\u0001\u0001\u0016\t-1E+G\n\u0003\u00011\u0001\"!\u0004\b\u000e\u0003\u001dI!aD\u0004\u0003\r\u0005s\u0017PU3g\u0003\u0019!\u0013N\\5uIQ\t!\u0003\u0005\u0002\u000e\'%\u0011Ac\u0002\u0002\u0005+:LG/A\u0003baBd\u0017\u0010F\u0002\u0018\u0007F\u0003\"\u0001G\r\r\u0001\u0011I!\u0004\u0001Q\u0001\u0002\u0013\u0015\ra\u0007\u0002\u0002%F\u0011Ad\b\t\u0003\u001buI!AH\u0004\u0003\u000f9{G\u000f[5oOB\u0011Q\u0002I\u0005\u0003C\u001d\u00111!\u00118zQ\rI2E\n\t\u0003\u001b\u0011J!!J\u0004\u0003\u0017M\u0004XmY5bY&TX\rZ\u0019\u0006G\u001d\u0002%)\u0011\t\u0004Q-rcBA\u0007*\u0013\tQs!A\u0007Ta\u0016\u001c\u0017.\u00197ju\u0006\u0014G.Z\u0005\u0003Y5\u0012Qa\u0012:pkBT!AK\u0004\u0011\u00115y\u0013\u0007N\u001c;{II!\u0001M\u0004\u0003\rQ+\b\u000f\\37!\ti!\'\u0003\u00024\u000f\t\u0019\u0011J\u001c;\u0011\u00055)\u0014B\u0001\u001c\b\u0005\u0011auN\\4\u0011\u00055A\u0014BA\u001d\b\u0005\u00151En\\1u!\ti1(\u0003\u0002=\u000f\t1Ai\\;cY\u0016\u0004\"!\u0004 \n\u0005}:!a\u0002\"p_2,\u0017M\\\u0005\u0003\u00036\naAU3ukJt\u0017\u0007\u0002\u0013)S)BQ\u0001\u0012\u0002A\u0002\u0015\u000b!A^\u0019\u0011\u0005a1E!C$\u0001A\u0003\u0005\tR1\u0001\u001c\u0005\t!\u0016\u0007K\u0002GG%\u000bTa\t&O!>\u00032\u0001K\u0016L!\u0015iA*\r\u001b;\u0013\tiuA\u0001\u0004UkBdWmM\u0005\u0003\u001f6\nA!\u0011:hgF\"A\u0005K\u0015+\u0011\u0015\u0011&\u00011\u0001T\u0003\t1(\u0007\u0005\u0002\u0019)\u0012IQ\u000b\u0001Q\u0001\u0002#\u0015\ra\u0007\u0002\u0003)JB3\u0001V\u0012Xc\u0015\u0019#J\u0014-Pc\u0011!\u0003&\u000b\u0016\u0002\u000f\r,(O]5fIV\t1\f\u0005\u0003\u000e9\u0016s\u0016BA/\b\u0005%1UO\\2uS>t\u0017\u0007\u0005\u0003\u000e9N;\u0002FA\u0002a!\t\tG-D\u0001c\u0015\t\u0019w!\u0001\u0006b]:|G/\u0019;j_:L!!\u001a2\u0003\u001bUt7\u000f]3dS\u0006d\u0017N_3e\u0003\u0019!X\u000f\u001d7fIV\t\u0001\u000e\u0005\u0003\u000e9&<\u0002\u0003B\u0007k\u000bNK!a[\u0004\u0003\rQ+\b\u000f\\33Q\t!\u0001-\u0001\u0005u_N#(/\u001b8h)\u0005y\u0007C\u00019x\u001d\t\tX\u000f\u0005\u0002s\u000f5\t1O\u0003\u0002u\u0013\u00051AH]8pizJ!A^\u0004\u0002\rA\u0013X\rZ3g\u0013\tA\u0018P\u0001\u0004TiJLgn\u001a\u0006\u0003m\u001e\u0001"
    )
BootstrapMethods:
  0: #46 REF_invokeStatic java/lang/invoke/LambdaMetafactory.altMetafactory:(Ljava/lang/invoke/MethodHandles$Lookup;Ljava/lang/String;Ljava/lang/invoke/MethodType;[Ljava/lang/Object;)Ljava/lang/invoke/CallSite;
    Method arguments:
      #30 (Ljava/lang/Object;)Ljava/lang/Object;
      #35 REF_invokeStatic scala/Function2.$anonfun$curried$1:(Lscala/Function2;Ljava/lang/Object;)Lscala/Function1;
      #37 (Ljava/lang/Object;)Lscala/Function1;
      #38 5
      #39 1
      #37 (Ljava/lang/Object;)Lscala/Function1;
  1: #46 REF_invokeStatic java/lang/invoke/LambdaMetafactory.altMetafactory:(Ljava/lang/invoke/MethodHandles$Lookup;Ljava/lang/String;Ljava/lang/invoke/MethodType;[Ljava/lang/Object;)Ljava/lang/invoke/CallSite;
    Method arguments:
      #30 (Ljava/lang/Object;)Ljava/lang/Object;
      #59 REF_invokeStatic scala/Function2.$anonfun$tupled$1:(Lscala/Function2;Lscala/Tuple2;)Ljava/lang/Object;
      #61 (Lscala/Tuple2;)Ljava/lang/Object;
      #38 5
      #39 1
      #61 (Lscala/Tuple2;)Ljava/lang/Object;
  2: #46 REF_invokeStatic java/lang/invoke/LambdaMetafactory.altMetafactory:(Ljava/lang/invoke/MethodHandles$Lookup;Ljava/lang/String;Ljava/lang/invoke/MethodType;[Ljava/lang/Object;)Ljava/lang/invoke/CallSite;
    Method arguments:
      #30 (Ljava/lang/Object;)Ljava/lang/Object;
      #446 REF_invokeStatic scala/Function2.$anonfun$curried$2:(Lscala/Function2;Ljava/lang/Object;Ljava/lang/Object;)Ljava/lang/Object;
      #30 (Ljava/lang/Object;)Ljava/lang/Object;
      #39 1
  3: #476 REF_invokeStatic scala/runtime/LambdaDeserialize.bootstrap:(Ljava/lang/invoke/MethodHandles$Lookup;Ljava/lang/String;Ljava/lang/invoke/MethodType;[Ljava/lang/invoke/MethodHandle;)Ljava/lang/invoke/CallSite;
    Method arguments:
      #35 REF_invokeStatic scala/Function2.$anonfun$curried$1:(Lscala/Function2;Ljava/lang/Object;)Lscala/Function1;
      #446 REF_invokeStatic scala/Function2.$anonfun$curried$2:(Lscala/Function2;Ljava/lang/Object;Ljava/lang/Object;)Ljava/lang/Object;
      #59 REF_invokeStatic scala/Function2.$anonfun$tupled$1:(Lscala/Function2;Lscala/Tuple2;)Ljava/lang/Object;
  ScalaInlineInfo: length = 0x25B (unknown attribute)
   01 04 00 0F 00 10 00 77 00 1F 00 20 01 01 B6 01
   B7 01 00 37 00 38 01 01 D2 01 D3 01 00 0F 00 10
   00 00 5E 00 5F 00 00 5C 00 5D 01 00 98 00 99 00
   00 96 00 97 01 00 C2 00 C3 00 00 C0 00 C1 01 00
   E6 00 E7 00 00 E4 00 E5 01 01 0A 01 0B 00 01 08
   01 09 01 01 2E 01 2F 00 01 2C 01 2D 01 01 52 01
   53 00 01 50 01 51 01 01 76 01 77 00 01 74 01 75
   01 01 9A 01 9B 00 01 98 01 99 01 00 68 00 69 00
   00 66 00 67 01 00 9E 00 9F 00 00 9C 00 9D 01 00
   C8 00 C9 00 00 C6 00 C7 01 00 EC 00 ED 00 00 EA
   00 EB 01 01 10 01 11 00 01 0E 01 0F 01 01 34 01
   35 00 01 32 01 33 01 01 58 01 59 00 01 56 01 57
   01 01 7C 01 7D 00 01 7A 01 7B 01 01 A0 01 A1 00
   01 9E 01 9F 01 00 72 00 73 00 00 70 00 71 01 00
   A4 00 A5 00 00 A2 00 A3 01 00 CE 00 CF 00 00 CC
   00 CD 01 00 F2 00 F3 00 00 F0 00 F1 01 01 16 01
   17 00 01 14 01 15 01 01 3A 01 3B 00 01 38 01 39
   01 01 5E 01 5F 00 01 5C 01 5D 01 01 82 01 83 00
   01 80 01 81 01 01 A6 01 A7 00 01 A4 01 A5 01 00
   7C 00 7D 00 00 7A 00 7B 01 00 AA 00 AB 00 00 A8
   00 A9 01 00 D4 00 D5 00 00 D2 00 D3 01 00 F8 00
   F9 00 00 F6 00 F7 01 01 1C 01 1D 00 01 1A 01 1B
   01 01 40 01 41 00 01 3E 01 3F 01 01 64 01 65 00
   01 62 01 63 01 01 88 01 89 00 01 86 01 87 01 01
   AC 01 AD 00 01 AA 01 AB 01 00 86 00 87 00 00 84
   00 85 01 00 B0 00 B1 00 00 AE 00 AF 01 00 DA 00
   DB 00 00 D8 00 D9 01 00 FE 00 FF 00 00 FC 00 FD
   01 01 22 01 23 00 01 20 01 21 01 01 46 01 47 00
   01 44 01 45 01 01 6A 01 6B 00 01 68 01 69 01 01
   8E 01 8F 00 01 8C 01 8D 01 01 B2 01 B3 00 01 B0
   01 B1 01 00 49 00 4A 00 00 47 00 48 01 00 8C 00
   8D 00 00 8A 00 8B 01 00 B6 00 B7 00 00 B4 00 B5
   01 00 E0 00 E1 00 00 DE 00 DF 01 01 04 01 05 00
   01 02 01 03 01 01 28 01 29 00 01 26 01 27 01 01
   4C 01 4D 00 01 4A 01 4B 01 01 70 01 71 00 01 6E
   01 6F 01 01 94 01 95 00 01 92 01 93 01 00 17 00
   18 00 00 14 00 15 01 00 41 00 42 00 00 3F 00 40
   01 00 33 00 18 00 00 32 00 15 01
  ScalaSig: length = 0x3 (unknown attribute)
   05 02 00
