Classfile /Users/mw/Projects/slang-braindump/.jar/jar8/assemble/slang-braindump/assemble/content/scala/Function22.class
  Last modified May 29, 2022; size 8445 bytes
  SHA-256 checksum ff67fddbe9bf695c33107b9ca2cb30f485948802214a639740d4926a5c9722f1
  Compiled from "Function22.scala"
public interface scala.Function22<T1 extends java.lang.Object, T2 extends java.lang.Object, T3 extends java.lang.Object, T4 extends java.lang.Object, T5 extends java.lang.Object, T6 extends java.lang.Object, T7 extends java.lang.Object, T8 extends java.lang.Object, T9 extends java.lang.Object, T10 extends java.lang.Object, T11 extends java.lang.Object, T12 extends java.lang.Object, T13 extends java.lang.Object, T14 extends java.lang.Object, T15 extends java.lang.Object, T16 extends java.lang.Object, T17 extends java.lang.Object, T18 extends java.lang.Object, T19 extends java.lang.Object, T20 extends java.lang.Object, T21 extends java.lang.Object, T22 extends java.lang.Object, R extends java.lang.Object>
  minor version: 0
  major version: 52
  flags: (0x0601) ACC_PUBLIC, ACC_INTERFACE, ACC_ABSTRACT
  this_class: #2                          // scala/Function22
  super_class: #5                         // java/lang/Object
  interfaces: 0, fields: 0, methods: 12, attributes: 7
Constant pool:
    #1 = Utf8               scala/Function22
    #2 = Class              #1            // scala/Function22
    #3 = Utf8               <T1:Ljava/lang/Object;T2:Ljava/lang/Object;T3:Ljava/lang/Object;T4:Ljava/lang/Object;T5:Ljava/lang/Object;T6:Ljava/lang/Object;T7:Ljava/lang/Object;T8:Ljava/lang/Object;T9:Ljava/lang/Object;T10:Ljava/lang/Object;T11:Ljava/lang/Object;T12:Ljava/lang/Object;T13:Ljava/lang/Object;T14:Ljava/lang/Object;T15:Ljava/lang/Object;T16:Ljava/lang/Object;T17:Ljava/lang/Object;T18:Ljava/lang/Object;T19:Ljava/lang/Object;T20:Ljava/lang/Object;T21:Ljava/lang/Object;T22:Ljava/lang/Object;R:Ljava/lang/Object;>Ljava/lang/Object;
    #4 = Utf8               java/lang/Object
    #5 = Class              #4            // java/lang/Object
    #6 = Utf8               Function22.scala
    #7 = Utf8               Lscala/reflect/ScalaSignature;
    #8 = Utf8               bytes
    #9 = Utf8               \u0006\u0005\u0005-ea\u0002\u0004\b!\u0003\r\tA\u0003\u0005\u0006!\u0001!\t!\u0005\u0005\u0006+\u00011\tA\u0006\u0005\b\u0003C\u0001A\u0011AA\u0012\u0011\u001d\t\u0019\u0007\u0001C\u0001\u0003KBq!!\u001d\u0001\t\u0003\n\u0019H\u0001\u0006Gk:\u001cG/[8oeIR\u0011\u0001C\u0001\u0006g\u000e\fG.Y\u0002\u0001+mYQEK\u00185sy\u001a\u0005*\u0014*X9\u000647\u000e];{\u007f\u0006%\u00111CA\u000f3M\u0011\u0001\u0001\u0004\t\u0003\u001b9i\u0011aB\u0005\u0003\u001f\u001d\u0011a!\u00118z%\u00164\u0017A\u0002\u0013j]&$H\u0005F\u0001\u0013!\ti1#\u0003\u0002\u0015\u000f\t!QK\\5u\u0003\u0015\t\u0007\u000f\u001d7z)i9\"e\n\u00172mm\u0002UIS(U3z\u001b\u0007.\u001c:xy\u0006\r\u0011QBA\f!\tA\u0012\u0004\u0004\u0001\u0005\ri\u0001AQ1\u0001\u001c\u0005\u0005\u0011\u0016C\u0001\u000f !\tiQ$\u0003\u0002\u001f\u000f\t9aj\u001c;iS:<\u0007CA\u0007!\u0013\t\tsAA\u0002B]fDQa\t\u0002A\u0002\u0011\n!A^\u0019\u0011\u0005a)CA\u0002\u0014\u0001\u0011\u000b\u00071D\u0001\u0002Uc!)\u0001F\u0001a\u0001S\u0005\u0011aO\r\t\u00031)\"aa\u000b\u0001\t\u0006\u0004Y\"A\u0001+3\u0011\u0015i#\u00011\u0001/\u0003\t18\u0007\u0005\u0002\u0019_\u00111\u0001\u0007\u0001EC\u0002m\u0011!\u0001V\u001a\t\u000bI\u0012\u0001\u0019A\u001a\u0002\u0005Y$\u0004C\u0001\r5\t\u0019)\u0004\u0001#b\u00017\t\u0011A\u000b\u000e\u0005\u0006o\t\u0001\r\u0001O\u0001\u0003mV\u0002\"\u0001G\u001d\u0005\ri\u0002\u0001R1\u0001\u001c\u0005\t!V\u0007C\u0003=\u0005\u0001\u0007Q(\u0001\u0002wmA\u0011\u0001D\u0010\u0003\u0007\u007f\u0001A)\u0019A\u000e\u0003\u0005Q3\u0004\"B!\u0003\u0001\u0004\u0011\u0015A\u0001<8!\tA2\t\u0002\u0004E\u0001!\u0015\ra\u0007\u0002\u0003)^BQA\u0012\u0002A\u0002\u001d\u000b!A\u001e\u001d\u0011\u0005aAEAB%\u0001\u0011\u000b\u00071D\u0001\u0002Uq!)1J\u0001a\u0001\u0019\u0006\u0011a/\u000f\t\u000315#aA\u0014\u0001\t\u0006\u0004Y\"A\u0001+:\u0011\u0015\u0001&\u00011\u0001R\u0003\r1\u0018\u0007\r\t\u00031I#aa\u0015\u0001\t\u0006\u0004Y\"a\u0001+2a!)QK\u0001a\u0001-\u0006\u0019a/M\u0019\u0011\u0005a9FA\u0002-\u0001\u0011\u000b\u00071DA\u0002UcEBQA\u0017\u0002A\u0002m\u000b1A^\u00193!\tAB\f\u0002\u0004^\u0001!\u0015\ra\u0007\u0002\u0004)F\u0012\u0004\"B0\u0003\u0001\u0004\u0001\u0017a\u0001<2gA\u0011\u0001$\u0019\u0003\u0007E\u0002A)\u0019A\u000e\u0003\u0007Q\u000b4\u0007C\u0003e\u0005\u0001\u0007Q-A\u0002wcQ\u0002\"\u0001\u00074\u0005\r\u001d\u0004\u0001R1\u0001\u001c\u0005\r!\u0016\u0007\u000e\u0005\u0006S\n\u0001\rA[\u0001\u0004mF*\u0004C\u0001\rl\t\u0019a\u0007\u0001#b\u00017\t\u0019A+M\u001b\t\u000b9\u0014\u0001\u0019A8\u0002\u0007Y\fd\u0007\u0005\u0002\u0019a\u00121\u0011\u000f\u0001EC\u0002m\u00111\u0001V\u00197\u0011\u0015\u0019(\u00011\u0001u\u0003\r1\u0018g\u000e\t\u00031U$aA\u001e\u0001\t\u0006\u0004Y\"a\u0001+2o!)\u0001P\u0001a\u0001s\u0006\u0019a/\r\u001d\u0011\u0005aQHAB>\u0001\u0011\u000b\u00071DA\u0002UcaBQ! \u0002A\u0002y\f1A^\u0019:!\tAr\u0010B\u0004\u0002\u0002\u0001A)\u0019A\u000e\u0003\u0007Q\u000b\u0014\bC\u0004\u0002\u0006\t\u0001\r!a\u0002\u0002\u0007Y\u0014\u0004\u0007E\u0002\u0019\u0003\u0013!q!a\u0003\u0001\u0011\u000b\u00071DA\u0002UeABq!a\u0004\u0003\u0001\u0004\t\t\"A\u0002weE\u00022\u0001GA\n\t\u001d\t)\u0002\u0001EC\u0002m\u00111\u0001\u0016\u001a2\u0011\u001d\tIB\u0001a\u0001\u00037\t1A\u001e\u001a3!\rA\u0012Q\u0004\u0003\b\u0003?\u0001\u0001R1\u0001\u001c\u0005\r!&GM\u0001\bGV\u0014(/[3e+\t\t)\u0003\u0005\u0004\u000e\u0003O!\u00131F\u0005\u0004\u0003S9!!\u0003$v]\u000e$\u0018n\u001c82!\u0019i\u0011qE\u0015\u0002.A1Q\"a\n/\u0003_\u0001b!DA\u0014g\u0005E\u0002CB\u0007\u0002(a\n\u0019\u0004\u0005\u0004\u000e\u0003Oi\u0014Q\u0007\t\u0007\u001b\u0005\u001d\")a\u000e\u0011\r5\t9cRA\u001d!\u0019i\u0011q\u0005\'\u0002<A1Q\"a\nR\u0003{\u0001b!DA\u0014-\u0006}\u0002CB\u0007\u0002(m\u000b\t\u0005\u0005\u0004\u000e\u0003O\u0001\u00171\t\t\u0007\u001b\u0005\u001dR-!\u0012\u0011\r5\t9C[A$!\u0019i\u0011qE8\u0002JA1Q\"a\nu\u0003\u0017\u0002b!DA\u0014s\u00065\u0003CB\u0007\u0002(y\fy\u0005E\u0004\u000e\u0003O\t9!!\u0015\u0011\u000f5\t9#!\u0005\u0002TA1Q\"a\n\u0002\u001c]A3aAA,!\u0011\tI&a\u0018\u000e\u0005\u0005m#bAA/\u000f\u0005Q\u0011M\u001c8pi\u0006$\u0018n\u001c8\n\t\u0005\u0005\u00141\f\u0002\u000ek:\u001c\b/Z2jC2L\'0\u001a3\u0002\rQ,\b\u000f\\3e+\t\t9\u0007\u0005\u0004\u000e\u0003O\tIg\u0006\t\u001d\u001b\u0005-D%\u000b\u00184qu\u0012u\tT)W7\u0002,\'n\u001c;z}\u0006\u001d\u0011\u0011CA\u000e\u0013\r\tig\u0002\u0002\b)V\u0004H.\u001a\u001a3Q\r!\u0011qK\u0001\ti>\u001cFO]5oOR\u0011\u0011Q\u000f\t\u0005\u0003o\n)I\u0004\u0003\u0002z\u0005\u0005\u0005cAA>\u000f5\u0011\u0011Q\u0010\u0006\u0004\u0003\u007fJ\u0011A\u0002\u001fs_>$h(C\u0002\u0002\u0004\u001e\ta\u0001\u0015:fI\u00164\u0017\u0002BAD\u0003\u0013\u0013aa\u0015;sS:<\'bAAB\u000f\u0001
   #10 = Utf8               java/lang/invoke/MethodHandles$Lookup
   #11 = Class              #10           // java/lang/invoke/MethodHandles$Lookup
   #12 = Utf8               java/lang/invoke/MethodHandles
   #13 = Class              #12           // java/lang/invoke/MethodHandles
   #14 = Utf8               Lookup
   #15 = Utf8               apply
   #16 = Utf8               (Ljava/lang/Object;Ljava/lang/Object;Ljava/lang/Object;Ljava/lang/Object;Ljava/lang/Object;Ljava/lang/Object;Ljava/lang/Object;Ljava/lang/Object;Ljava/lang/Object;Ljava/lang/Object;Ljava/lang/Object;Ljava/lang/Object;Ljava/lang/Object;Ljava/lang/Object;Ljava/lang/Object;Ljava/lang/Object;Ljava/lang/Object;Ljava/lang/Object;Ljava/lang/Object;Ljava/lang/Object;Ljava/lang/Object;Ljava/lang/Object;)Ljava/lang/Object;
   #17 = Utf8               (TT1;TT2;TT3;TT4;TT5;TT6;TT7;TT8;TT9;TT10;TT11;TT12;TT13;TT14;TT15;TT16;TT17;TT18;TT19;TT20;TT21;TT22;)TR;
   #18 = Utf8               v1
   #19 = Utf8               v2
   #20 = Utf8               v3
   #21 = Utf8               v4
   #22 = Utf8               v5
   #23 = Utf8               v6
   #24 = Utf8               v7
   #25 = Utf8               v8
   #26 = Utf8               v9
   #27 = Utf8               v10
   #28 = Utf8               v11
   #29 = Utf8               v12
   #30 = Utf8               v13
   #31 = Utf8               v14
   #32 = Utf8               v15
   #33 = Utf8               v16
   #34 = Utf8               v17
   #35 = Utf8               v18
   #36 = Utf8               v19
   #37 = Utf8               v20
   #38 = Utf8               v21
   #39 = Utf8               v22
   #40 = Utf8               curried$
   #41 = Utf8               (Lscala/Function22;)Lscala/Function1;
   #42 = Utf8               $this
   #43 = Utf8               curried
   #44 = Utf8               ()Lscala/Function1;
   #45 = NameAndType        #43:#44       // curried:()Lscala/Function1;
   #46 = InterfaceMethodref #2.#45        // scala/Function22.curried:()Lscala/Function1;
   #47 = Utf8               Lscala/Function22;
   #48 = Utf8               ()Lscala/Function1<TT1;Lscala/Function1<TT2;Lscala/Function1<TT3;Lscala/Function1<TT4;Lscala/Function1<TT5;Lscala/Function1<TT6;Lscala/Function1<TT7;Lscala/Function1<TT8;Lscala/Function1<TT9;Lscala/Function1<TT10;Lscala/Function1<TT11;Lscala/Function1<TT12;Lscala/Function1<TT13;Lscala/Function1<TT14;Lscala/Function1<TT15;Lscala/Function1<TT16;Lscala/Function1<TT17;Lscala/Function1<TT18;Lscala/Function1<TT19;Lscala/Function1<TT20;Lscala/Function1<TT21;Lscala/Function1<TT22;TR;>;>;>;>;>;>;>;>;>;>;>;>;>;>;>;>;>;>;>;>;>;>;
   #49 = Utf8               (Ljava/lang/Object;)Ljava/lang/Object;
   #50 = MethodType         #49           //  (Ljava/lang/Object;)Ljava/lang/Object;
   #51 = Utf8               $anonfun$curried$1
   #52 = Utf8               (Lscala/Function22;Ljava/lang/Object;)Lscala/Function1;
   #53 = NameAndType        #51:#52       // $anonfun$curried$1:(Lscala/Function22;Ljava/lang/Object;)Lscala/Function1;
   #54 = InterfaceMethodref #2.#53        // scala/Function22.$anonfun$curried$1:(Lscala/Function22;Ljava/lang/Object;)Lscala/Function1;
   #55 = MethodHandle       6:#54         // REF_invokeStatic scala/Function22.$anonfun$curried$1:(Lscala/Function22;Ljava/lang/Object;)Lscala/Function1;
   #56 = Utf8               (Ljava/lang/Object;)Lscala/Function1;
   #57 = MethodType         #56           //  (Ljava/lang/Object;)Lscala/Function1;
   #58 = Integer            5
   #59 = Integer            1
   #60 = Utf8               java/lang/invoke/LambdaMetafactory
   #61 = Class              #60           // java/lang/invoke/LambdaMetafactory
   #62 = Utf8               altMetafactory
   #63 = Utf8               (Ljava/lang/invoke/MethodHandles$Lookup;Ljava/lang/String;Ljava/lang/invoke/MethodType;[Ljava/lang/Object;)Ljava/lang/invoke/CallSite;
   #64 = NameAndType        #62:#63       // altMetafactory:(Ljava/lang/invoke/MethodHandles$Lookup;Ljava/lang/String;Ljava/lang/invoke/MethodType;[Ljava/lang/Object;)Ljava/lang/invoke/CallSite;
   #65 = Methodref          #61.#64       // java/lang/invoke/LambdaMetafactory.altMetafactory:(Ljava/lang/invoke/MethodHandles$Lookup;Ljava/lang/String;Ljava/lang/invoke/MethodType;[Ljava/lang/Object;)Ljava/lang/invoke/CallSite;
   #66 = MethodHandle       6:#65         // REF_invokeStatic java/lang/invoke/LambdaMetafactory.altMetafactory:(Ljava/lang/invoke/MethodHandles$Lookup;Ljava/lang/String;Ljava/lang/invoke/MethodType;[Ljava/lang/Object;)Ljava/lang/invoke/CallSite;
   #67 = NameAndType        #15:#41       // apply:(Lscala/Function22;)Lscala/Function1;
   #68 = InvokeDynamic      #0:#67        // #0:apply:(Lscala/Function22;)Lscala/Function1;
   #69 = Utf8               this
   #70 = Utf8               tupled$
   #71 = Utf8               tupled
   #72 = NameAndType        #71:#44       // tupled:()Lscala/Function1;
   #73 = InterfaceMethodref #2.#72        // scala/Function22.tupled:()Lscala/Function1;
   #74 = Utf8               ()Lscala/Function1<Lscala/Tuple22<TT1;TT2;TT3;TT4;TT5;TT6;TT7;TT8;TT9;TT10;TT11;TT12;TT13;TT14;TT15;TT16;TT17;TT18;TT19;TT20;TT21;TT22;>;TR;>;
   #75 = Utf8               $anonfun$tupled$1
   #76 = Utf8               (Lscala/Function22;Lscala/Tuple22;)Ljava/lang/Object;
   #77 = NameAndType        #75:#76       // $anonfun$tupled$1:(Lscala/Function22;Lscala/Tuple22;)Ljava/lang/Object;
   #78 = InterfaceMethodref #2.#77        // scala/Function22.$anonfun$tupled$1:(Lscala/Function22;Lscala/Tuple22;)Ljava/lang/Object;
   #79 = MethodHandle       6:#78         // REF_invokeStatic scala/Function22.$anonfun$tupled$1:(Lscala/Function22;Lscala/Tuple22;)Ljava/lang/Object;
   #80 = Utf8               (Lscala/Tuple22;)Ljava/lang/Object;
   #81 = MethodType         #80           //  (Lscala/Tuple22;)Ljava/lang/Object;
   #82 = InvokeDynamic      #1:#67        // #1:apply:(Lscala/Function22;)Lscala/Function1;
   #83 = Utf8               toString$
   #84 = Utf8               (Lscala/Function22;)Ljava/lang/String;
   #85 = Utf8               toString
   #86 = Utf8               ()Ljava/lang/String;
   #87 = NameAndType        #85:#86       // toString:()Ljava/lang/String;
   #88 = InterfaceMethodref #2.#87        // scala/Function22.toString:()Ljava/lang/String;
   #89 = Utf8               <function22>
   #90 = String             #89           // <function22>
   #91 = Utf8               $anonfun$curried$2
   #92 = Utf8               (Lscala/Function22;Ljava/lang/Object;Ljava/lang/Object;Ljava/lang/Object;Ljava/lang/Object;Ljava/lang/Object;Ljava/lang/Object;Ljava/lang/Object;Ljava/lang/Object;Ljava/lang/Object;Ljava/lang/Object;Ljava/lang/Object;Ljava/lang/Object;Ljava/lang/Object;Ljava/lang/Object;Ljava/lang/Object;Ljava/lang/Object;Ljava/lang/Object;Ljava/lang/Object;Ljava/lang/Object;Ljava/lang/Object;Ljava/lang/Object;Ljava/lang/Object;)Ljava/lang/Object;
   #93 = Utf8               x1$1
   #94 = Utf8               x2
   #95 = Utf8               x3
   #96 = Utf8               x4
   #97 = Utf8               x5
   #98 = Utf8               x6
   #99 = Utf8               x7
  #100 = Utf8               x8
  #101 = Utf8               x9
  #102 = Utf8               x10
  #103 = Utf8               x11
  #104 = Utf8               x12
  #105 = Utf8               x13
  #106 = Utf8               x14
  #107 = Utf8               x15
  #108 = Utf8               x16
  #109 = Utf8               x17
  #110 = Utf8               x18
  #111 = Utf8               x19
  #112 = Utf8               x20
  #113 = Utf8               x21
  #114 = Utf8               x22
  #115 = NameAndType        #15:#16       // apply:(Ljava/lang/Object;Ljava/lang/Object;Ljava/lang/Object;Ljava/lang/Object;Ljava/lang/Object;Ljava/lang/Object;Ljava/lang/Object;Ljava/lang/Object;Ljava/lang/Object;Ljava/lang/Object;Ljava/lang/Object;Ljava/lang/Object;Ljava/lang/Object;Ljava/lang/Object;Ljava/lang/Object;Ljava/lang/Object;Ljava/lang/Object;Ljava/lang/Object;Ljava/lang/Object;Ljava/lang/Object;Ljava/lang/Object;Ljava/lang/Object;)Ljava/lang/Object;
  #116 = InterfaceMethodref #2.#115       // scala/Function22.apply:(Ljava/lang/Object;Ljava/lang/Object;Ljava/lang/Object;Ljava/lang/Object;Ljava/lang/Object;Ljava/lang/Object;Ljava/lang/Object;Ljava/lang/Object;Ljava/lang/Object;Ljava/lang/Object;Ljava/lang/Object;Ljava/lang/Object;Ljava/lang/Object;Ljava/lang/Object;Ljava/lang/Object;Ljava/lang/Object;Ljava/lang/Object;Ljava/lang/Object;Ljava/lang/Object;Ljava/lang/Object;Ljava/lang/Object;Ljava/lang/Object;)Ljava/lang/Object;
  #117 = Utf8               Ljava/lang/Object;
  #118 = Utf8               x1
  #119 = Utf8               (Ljava/lang/Object;Ljava/lang/Object;Ljava/lang/Object;Ljava/lang/Object;Ljava/lang/Object;Ljava/lang/Object;Ljava/lang/Object;Ljava/lang/Object;Ljava/lang/Object;Ljava/lang/Object;Ljava/lang/Object;Ljava/lang/Object;Ljava/lang/Object;Ljava/lang/Object;Ljava/lang/Object;Ljava/lang/Object;Ljava/lang/Object;Ljava/lang/Object;Ljava/lang/Object;Ljava/lang/Object;Ljava/lang/Object;)Ljava/lang/Object;
  #120 = MethodType         #119          //  (Ljava/lang/Object;Ljava/lang/Object;Ljava/lang/Object;Ljava/lang/Object;Ljava/lang/Object;Ljava/lang/Object;Ljava/lang/Object;Ljava/lang/Object;Ljava/lang/Object;Ljava/lang/Object;Ljava/lang/Object;Ljava/lang/Object;Ljava/lang/Object;Ljava/lang/Object;Ljava/lang/Object;Ljava/lang/Object;Ljava/lang/Object;Ljava/lang/Object;Ljava/lang/Object;Ljava/lang/Object;Ljava/lang/Object;)Ljava/lang/Object;
  #121 = NameAndType        #91:#92       // $anonfun$curried$2:(Lscala/Function22;Ljava/lang/Object;Ljava/lang/Object;Ljava/lang/Object;Ljava/lang/Object;Ljava/lang/Object;Ljava/lang/Object;Ljava/lang/Object;Ljava/lang/Object;Ljava/lang/Object;Ljava/lang/Object;Ljava/lang/Object;Ljava/lang/Object;Ljava/lang/Object;Ljava/lang/Object;Ljava/lang/Object;Ljava/lang/Object;Ljava/lang/Object;Ljava/lang/Object;Ljava/lang/Object;Ljava/lang/Object;Ljava/lang/Object;Ljava/lang/Object;)Ljava/lang/Object;
  #122 = InterfaceMethodref #2.#121       // scala/Function22.$anonfun$curried$2:(Lscala/Function22;Ljava/lang/Object;Ljava/lang/Object;Ljava/lang/Object;Ljava/lang/Object;Ljava/lang/Object;Ljava/lang/Object;Ljava/lang/Object;Ljava/lang/Object;Ljava/lang/Object;Ljava/lang/Object;Ljava/lang/Object;Ljava/lang/Object;Ljava/lang/Object;Ljava/lang/Object;Ljava/lang/Object;Ljava/lang/Object;Ljava/lang/Object;Ljava/lang/Object;Ljava/lang/Object;Ljava/lang/Object;Ljava/lang/Object;Ljava/lang/Object;)Ljava/lang/Object;
  #123 = MethodHandle       6:#122        // REF_invokeStatic scala/Function22.$anonfun$curried$2:(Lscala/Function22;Ljava/lang/Object;Ljava/lang/Object;Ljava/lang/Object;Ljava/lang/Object;Ljava/lang/Object;Ljava/lang/Object;Ljava/lang/Object;Ljava/lang/Object;Ljava/lang/Object;Ljava/lang/Object;Ljava/lang/Object;Ljava/lang/Object;Ljava/lang/Object;Ljava/lang/Object;Ljava/lang/Object;Ljava/lang/Object;Ljava/lang/Object;Ljava/lang/Object;Ljava/lang/Object;Ljava/lang/Object;Ljava/lang/Object;Ljava/lang/Object;)Ljava/lang/Object;
  #124 = Utf8               (Lscala/Function22;Ljava/lang/Object;)Lscala/Function21;
  #125 = NameAndType        #15:#124      // apply:(Lscala/Function22;Ljava/lang/Object;)Lscala/Function21;
  #126 = InvokeDynamic      #2:#125       // #2:apply:(Lscala/Function22;Ljava/lang/Object;)Lscala/Function21;
  #127 = Utf8               scala/Function21
  #128 = Class              #127          // scala/Function21
  #129 = InterfaceMethodref #128.#45      // scala/Function21.curried:()Lscala/Function1;
  #130 = Utf8               x0$1
  #131 = Utf8               scala/Tuple22
  #132 = Class              #131          // scala/Tuple22
  #133 = Utf8               _1
  #134 = Utf8               ()Ljava/lang/Object;
  #135 = NameAndType        #133:#134     // _1:()Ljava/lang/Object;
  #136 = Methodref          #132.#135     // scala/Tuple22._1:()Ljava/lang/Object;
  #137 = Utf8               _2
  #138 = NameAndType        #137:#134     // _2:()Ljava/lang/Object;
  #139 = Methodref          #132.#138     // scala/Tuple22._2:()Ljava/lang/Object;
  #140 = Utf8               _3
  #141 = NameAndType        #140:#134     // _3:()Ljava/lang/Object;
  #142 = Methodref          #132.#141     // scala/Tuple22._3:()Ljava/lang/Object;
  #143 = Utf8               _4
  #144 = NameAndType        #143:#134     // _4:()Ljava/lang/Object;
  #145 = Methodref          #132.#144     // scala/Tuple22._4:()Ljava/lang/Object;
  #146 = Utf8               _5
  #147 = NameAndType        #146:#134     // _5:()Ljava/lang/Object;
  #148 = Methodref          #132.#147     // scala/Tuple22._5:()Ljava/lang/Object;
  #149 = Utf8               _6
  #150 = NameAndType        #149:#134     // _6:()Ljava/lang/Object;
  #151 = Methodref          #132.#150     // scala/Tuple22._6:()Ljava/lang/Object;
  #152 = Utf8               _7
  #153 = NameAndType        #152:#134     // _7:()Ljava/lang/Object;
  #154 = Methodref          #132.#153     // scala/Tuple22._7:()Ljava/lang/Object;
  #155 = Utf8               _8
  #156 = NameAndType        #155:#134     // _8:()Ljava/lang/Object;
  #157 = Methodref          #132.#156     // scala/Tuple22._8:()Ljava/lang/Object;
  #158 = Utf8               _9
  #159 = NameAndType        #158:#134     // _9:()Ljava/lang/Object;
  #160 = Methodref          #132.#159     // scala/Tuple22._9:()Ljava/lang/Object;
  #161 = Utf8               _10
  #162 = NameAndType        #161:#134     // _10:()Ljava/lang/Object;
  #163 = Methodref          #132.#162     // scala/Tuple22._10:()Ljava/lang/Object;
  #164 = Utf8               _11
  #165 = NameAndType        #164:#134     // _11:()Ljava/lang/Object;
  #166 = Methodref          #132.#165     // scala/Tuple22._11:()Ljava/lang/Object;
  #167 = Utf8               _12
  #168 = NameAndType        #167:#134     // _12:()Ljava/lang/Object;
  #169 = Methodref          #132.#168     // scala/Tuple22._12:()Ljava/lang/Object;
  #170 = Utf8               _13
  #171 = NameAndType        #170:#134     // _13:()Ljava/lang/Object;
  #172 = Methodref          #132.#171     // scala/Tuple22._13:()Ljava/lang/Object;
  #173 = Utf8               _14
  #174 = NameAndType        #173:#134     // _14:()Ljava/lang/Object;
  #175 = Methodref          #132.#174     // scala/Tuple22._14:()Ljava/lang/Object;
  #176 = Utf8               _15
  #177 = NameAndType        #176:#134     // _15:()Ljava/lang/Object;
  #178 = Methodref          #132.#177     // scala/Tuple22._15:()Ljava/lang/Object;
  #179 = Utf8               _16
  #180 = NameAndType        #179:#134     // _16:()Ljava/lang/Object;
  #181 = Methodref          #132.#180     // scala/Tuple22._16:()Ljava/lang/Object;
  #182 = Utf8               _17
  #183 = NameAndType        #182:#134     // _17:()Ljava/lang/Object;
  #184 = Methodref          #132.#183     // scala/Tuple22._17:()Ljava/lang/Object;
  #185 = Utf8               _18
  #186 = NameAndType        #185:#134     // _18:()Ljava/lang/Object;
  #187 = Methodref          #132.#186     // scala/Tuple22._18:()Ljava/lang/Object;
  #188 = Utf8               _19
  #189 = NameAndType        #188:#134     // _19:()Ljava/lang/Object;
  #190 = Methodref          #132.#189     // scala/Tuple22._19:()Ljava/lang/Object;
  #191 = Utf8               _20
  #192 = NameAndType        #191:#134     // _20:()Ljava/lang/Object;
  #193 = Methodref          #132.#192     // scala/Tuple22._20:()Ljava/lang/Object;
  #194 = Utf8               _21
  #195 = NameAndType        #194:#134     // _21:()Ljava/lang/Object;
  #196 = Methodref          #132.#195     // scala/Tuple22._21:()Ljava/lang/Object;
  #197 = Utf8               _22
  #198 = NameAndType        #197:#134     // _22:()Ljava/lang/Object;
  #199 = Methodref          #132.#198     // scala/Tuple22._22:()Ljava/lang/Object;
  #200 = Utf8               scala/MatchError
  #201 = Class              #200          // scala/MatchError
  #202 = Utf8               <init>
  #203 = Utf8               (Ljava/lang/Object;)V
  #204 = NameAndType        #202:#203     // "<init>":(Ljava/lang/Object;)V
  #205 = Methodref          #201.#204     // scala/MatchError."<init>":(Ljava/lang/Object;)V
  #206 = Utf8               Lscala/Tuple22;
  #207 = Utf8               $init$
  #208 = Utf8               (Lscala/Function22;)V
  #209 = Utf8               $deserializeLambda$
  #210 = Utf8               (Ljava/lang/invoke/SerializedLambda;)Ljava/lang/Object;
  #211 = Utf8               scala/runtime/LambdaDeserialize
  #212 = Class              #211          // scala/runtime/LambdaDeserialize
  #213 = Utf8               bootstrap
  #214 = Utf8               (Ljava/lang/invoke/MethodHandles$Lookup;Ljava/lang/String;Ljava/lang/invoke/MethodType;[Ljava/lang/invoke/MethodHandle;)Ljava/lang/invoke/CallSite;
  #215 = NameAndType        #213:#214     // bootstrap:(Ljava/lang/invoke/MethodHandles$Lookup;Ljava/lang/String;Ljava/lang/invoke/MethodType;[Ljava/lang/invoke/MethodHandle;)Ljava/lang/invoke/CallSite;
  #216 = Methodref          #212.#215     // scala/runtime/LambdaDeserialize.bootstrap:(Ljava/lang/invoke/MethodHandles$Lookup;Ljava/lang/String;Ljava/lang/invoke/MethodType;[Ljava/lang/invoke/MethodHandle;)Ljava/lang/invoke/CallSite;
  #217 = MethodHandle       6:#216        // REF_invokeStatic scala/runtime/LambdaDeserialize.bootstrap:(Ljava/lang/invoke/MethodHandles$Lookup;Ljava/lang/String;Ljava/lang/invoke/MethodType;[Ljava/lang/invoke/MethodHandle;)Ljava/lang/invoke/CallSite;
  #218 = Utf8               lambdaDeserialize
  #219 = NameAndType        #218:#210     // lambdaDeserialize:(Ljava/lang/invoke/SerializedLambda;)Ljava/lang/Object;
  #220 = InvokeDynamic      #3:#219       // #3:lambdaDeserialize:(Ljava/lang/invoke/SerializedLambda;)Ljava/lang/Object;
  #221 = Utf8               Signature
  #222 = Utf8               MethodParameters
  #223 = Utf8               Code
  #224 = Utf8               LineNumberTable
  #225 = Utf8               LocalVariableTable
  #226 = Utf8               StackMapTable
  #227 = Utf8               InnerClasses
  #228 = Utf8               SourceFile
  #229 = Utf8               RuntimeVisibleAnnotations
  #230 = Utf8               BootstrapMethods
  #231 = Utf8               ScalaInlineInfo
  #232 = Utf8               ScalaSig
{
  public abstract R apply(T1, T2, T3, T4, T5, T6, T7, T8, T9, T10, T11, T12, T13, T14, T15, T16, T17, T18, T19, T20, T21, T22);
    descriptor: (Ljava/lang/Object;Ljava/lang/Object;Ljava/lang/Object;Ljava/lang/Object;Ljava/lang/Object;Ljava/lang/Object;Ljava/lang/Object;Ljava/lang/Object;Ljava/lang/Object;Ljava/lang/Object;Ljava/lang/Object;Ljava/lang/Object;Ljava/lang/Object;Ljava/lang/Object;Ljava/lang/Object;Ljava/lang/Object;Ljava/lang/Object;Ljava/lang/Object;Ljava/lang/Object;Ljava/lang/Object;Ljava/lang/Object;Ljava/lang/Object;)Ljava/lang/Object;
    flags: (0x0401) ACC_PUBLIC, ACC_ABSTRACT
    Signature: #17                          // (TT1;TT2;TT3;TT4;TT5;TT6;TT7;TT8;TT9;TT10;TT11;TT12;TT13;TT14;TT15;TT16;TT17;TT18;TT19;TT20;TT21;TT22;)TR;
    MethodParameters:
      Name                           Flags
      v1                             final
      v2                             final
      v3                             final
      v4                             final
      v5                             final
      v6                             final
      v7                             final
      v8                             final
      v9                             final
      v10                            final
      v11                            final
      v12                            final
      v13                            final
      v14                            final
      v15                            final
      v16                            final
      v17                            final
      v18                            final
      v19                            final
      v20                            final
      v21                            final
      v22                            final

  public static scala.Function1 curried$(scala.Function22);
    descriptor: (Lscala/Function22;)Lscala/Function1;
    flags: (0x1009) ACC_PUBLIC, ACC_STATIC, ACC_SYNTHETIC
    Code:
      stack=1, locals=1, args_size=1
         0: aload_0
         1: invokespecial #46                 // InterfaceMethod curried:()Lscala/Function1;
         4: areturn
      LineNumberTable:
        line 30: 0
      LocalVariableTable:
        Start  Length  Slot  Name   Signature
            0       5     0 $this   Lscala/Function22;
    MethodParameters:
      Name                           Flags
      $this                          final synthetic

  public default scala.Function1<T1, scala.Function1<T2, scala.Function1<T3, scala.Function1<T4, scala.Function1<T5, scala.Function1<T6, scala.Function1<T7, scala.Function1<T8, scala.Function1<T9, scala.Function1<T10, scala.Function1<T11, scala.Function1<T12, scala.Function1<T13, scala.Function1<T14, scala.Function1<T15, scala.Function1<T16, scala.Function1<T17, scala.Function1<T18, scala.Function1<T19, scala.Function1<T20, scala.Function1<T21, scala.Function1<T22, R>>>>>>>>>>>>>>>>>>>>>> curried();
    descriptor: ()Lscala/Function1;
    flags: (0x0001) ACC_PUBLIC
    Code:
      stack=1, locals=1, args_size=1
         0: aload_0
         1: invokedynamic #68,  0             // InvokeDynamic #0:apply:(Lscala/Function22;)Lscala/Function1;
         6: areturn
      LineNumberTable:
        line 31: 0
      LocalVariableTable:
        Start  Length  Slot  Name   Signature
            0       7     0  this   Lscala/Function22;
    Signature: #48                          // ()Lscala/Function1<TT1;Lscala/Function1<TT2;Lscala/Function1<TT3;Lscala/Function1<TT4;Lscala/Function1<TT5;Lscala/Function1<TT6;Lscala/Function1<TT7;Lscala/Function1<TT8;Lscala/Function1<TT9;Lscala/Function1<TT10;Lscala/Function1<TT11;Lscala/Function1<TT12;Lscala/Function1<TT13;Lscala/Function1<TT14;Lscala/Function1<TT15;Lscala/Function1<TT16;Lscala/Function1<TT17;Lscala/Function1<TT18;Lscala/Function1<TT19;Lscala/Function1<TT20;Lscala/Function1<TT21;Lscala/Function1<TT22;TR;>;>;>;>;>;>;>;>;>;>;>;>;>;>;>;>;>;>;>;>;>;>;

  public static scala.Function1 tupled$(scala.Function22);
    descriptor: (Lscala/Function22;)Lscala/Function1;
    flags: (0x1009) ACC_PUBLIC, ACC_STATIC, ACC_SYNTHETIC
    Code:
      stack=1, locals=1, args_size=1
         0: aload_0
         1: invokespecial #73                 // InterfaceMethod tupled:()Lscala/Function1;
         4: areturn
      LineNumberTable:
        line 39: 0
      LocalVariableTable:
        Start  Length  Slot  Name   Signature
            0       5     0 $this   Lscala/Function22;
    MethodParameters:
      Name                           Flags
      $this                          final synthetic

  public default scala.Function1<scala.Tuple22<T1, T2, T3, T4, T5, T6, T7, T8, T9, T10, T11, T12, T13, T14, T15, T16, T17, T18, T19, T20, T21, T22>, R> tupled();
    descriptor: ()Lscala/Function1;
    flags: (0x0001) ACC_PUBLIC
    Code:
      stack=1, locals=1, args_size=1
         0: aload_0
         1: invokedynamic #82,  0             // InvokeDynamic #1:apply:(Lscala/Function22;)Lscala/Function1;
         6: areturn
      LineNumberTable:
        line 39: 0
      LocalVariableTable:
        Start  Length  Slot  Name   Signature
            0       7     0  this   Lscala/Function22;
    Signature: #74                          // ()Lscala/Function1<Lscala/Tuple22<TT1;TT2;TT3;TT4;TT5;TT6;TT7;TT8;TT9;TT10;TT11;TT12;TT13;TT14;TT15;TT16;TT17;TT18;TT19;TT20;TT21;TT22;>;TR;>;

  public static java.lang.String toString$(scala.Function22);
    descriptor: (Lscala/Function22;)Ljava/lang/String;
    flags: (0x1009) ACC_PUBLIC, ACC_STATIC, ACC_SYNTHETIC
    Code:
      stack=1, locals=1, args_size=1
         0: aload_0
         1: invokespecial #88                 // InterfaceMethod toString:()Ljava/lang/String;
         4: areturn
      LineNumberTable:
        line 42: 0
      LocalVariableTable:
        Start  Length  Slot  Name   Signature
            0       5     0 $this   Lscala/Function22;
    MethodParameters:
      Name                           Flags
      $this                          final synthetic

  public default java.lang.String toString();
    descriptor: ()Ljava/lang/String;
    flags: (0x0001) ACC_PUBLIC
    Code:
      stack=1, locals=1, args_size=1
         0: ldc           #90                 // String <function22>
         2: areturn
      LineNumberTable:
        line 42: 0
      LocalVariableTable:
        Start  Length  Slot  Name   Signature
            0       3     0  this   Lscala/Function22;

  public static java.lang.Object $anonfun$curried$2(scala.Function22, java.lang.Object, java.lang.Object, java.lang.Object, java.lang.Object, java.lang.Object, java.lang.Object, java.lang.Object, java.lang.Object, java.lang.Object, java.lang.Object, java.lang.Object, java.lang.Object, java.lang.Object, java.lang.Object, java.lang.Object, java.lang.Object, java.lang.Object, java.lang.Object, java.lang.Object, java.lang.Object, java.lang.Object, java.lang.Object);
    descriptor: (Lscala/Function22;Ljava/lang/Object;Ljava/lang/Object;Ljava/lang/Object;Ljava/lang/Object;Ljava/lang/Object;Ljava/lang/Object;Ljava/lang/Object;Ljava/lang/Object;Ljava/lang/Object;Ljava/lang/Object;Ljava/lang/Object;Ljava/lang/Object;Ljava/lang/Object;Ljava/lang/Object;Ljava/lang/Object;Ljava/lang/Object;Ljava/lang/Object;Ljava/lang/Object;Ljava/lang/Object;Ljava/lang/Object;Ljava/lang/Object;Ljava/lang/Object;)Ljava/lang/Object;
    flags: (0x1009) ACC_PUBLIC, ACC_STATIC, ACC_SYNTHETIC
    Code:
      stack=23, locals=23, args_size=23
         0: aload_0
         1: aload_1
         2: aload_2
         3: aload_3
         4: aload         4
         6: aload         5
         8: aload         6
        10: aload         7
        12: aload         8
        14: aload         9
        16: aload         10
        18: aload         11
        20: aload         12
        22: aload         13
        24: aload         14
        26: aload         15
        28: aload         16
        30: aload         17
        32: aload         18
        34: aload         19
        36: aload         20
        38: aload         21
        40: aload         22
        42: invokeinterface #116,  23         // InterfaceMethod apply:(Ljava/lang/Object;Ljava/lang/Object;Ljava/lang/Object;Ljava/lang/Object;Ljava/lang/Object;Ljava/lang/Object;Ljava/lang/Object;Ljava/lang/Object;Ljava/lang/Object;Ljava/lang/Object;Ljava/lang/Object;Ljava/lang/Object;Ljava/lang/Object;Ljava/lang/Object;Ljava/lang/Object;Ljava/lang/Object;Ljava/lang/Object;Ljava/lang/Object;Ljava/lang/Object;Ljava/lang/Object;Ljava/lang/Object;Ljava/lang/Object;)Ljava/lang/Object;
        47: areturn
      LineNumberTable:
        line 31: 0
      LocalVariableTable:
        Start  Length  Slot  Name   Signature
            0      48     0 $this   Lscala/Function22;
            0      48     1  x1$1   Ljava/lang/Object;
            0      48     2    x2   Ljava/lang/Object;
            0      48     3    x3   Ljava/lang/Object;
            0      48     4    x4   Ljava/lang/Object;
            0      48     5    x5   Ljava/lang/Object;
            0      48     6    x6   Ljava/lang/Object;
            0      48     7    x7   Ljava/lang/Object;
            0      48     8    x8   Ljava/lang/Object;
            0      48     9    x9   Ljava/lang/Object;
            0      48    10   x10   Ljava/lang/Object;
            0      48    11   x11   Ljava/lang/Object;
            0      48    12   x12   Ljava/lang/Object;
            0      48    13   x13   Ljava/lang/Object;
            0      48    14   x14   Ljava/lang/Object;
            0      48    15   x15   Ljava/lang/Object;
            0      48    16   x16   Ljava/lang/Object;
            0      48    17   x17   Ljava/lang/Object;
            0      48    18   x18   Ljava/lang/Object;
            0      48    19   x19   Ljava/lang/Object;
            0      48    20   x20   Ljava/lang/Object;
            0      48    21   x21   Ljava/lang/Object;
            0      48    22   x22   Ljava/lang/Object;
    MethodParameters:
      Name                           Flags
      $this                          final synthetic
      x1$1                           final
      x2                             final
      x3                             final
      x4                             final
      x5                             final
      x6                             final
      x7                             final
      x8                             final
      x9                             final
      x10                            final
      x11                            final
      x12                            final
      x13                            final
      x14                            final
      x15                            final
      x16                            final
      x17                            final
      x18                            final
      x19                            final
      x20                            final
      x21                            final
      x22                            final

  public static scala.Function1 $anonfun$curried$1(scala.Function22, java.lang.Object);
    descriptor: (Lscala/Function22;Ljava/lang/Object;)Lscala/Function1;
    flags: (0x1009) ACC_PUBLIC, ACC_STATIC, ACC_SYNTHETIC
    Code:
      stack=2, locals=2, args_size=2
         0: aload_0
         1: aload_1
         2: invokedynamic #126,  0            // InvokeDynamic #2:apply:(Lscala/Function22;Ljava/lang/Object;)Lscala/Function21;
         7: invokeinterface #129,  1          // InterfaceMethod scala/Function21.curried:()Lscala/Function1;
        12: areturn
      LineNumberTable:
        line 31: 0
      LocalVariableTable:
        Start  Length  Slot  Name   Signature
            0      13     0 $this   Lscala/Function22;
            0      13     1    x1   Ljava/lang/Object;
    MethodParameters:
      Name                           Flags
      $this                          final synthetic
      x1                             final

  public static java.lang.Object $anonfun$tupled$1(scala.Function22, scala.Tuple22);
    descriptor: (Lscala/Function22;Lscala/Tuple22;)Ljava/lang/Object;
    flags: (0x1009) ACC_PUBLIC, ACC_STATIC, ACC_SYNTHETIC
    Code:
      stack=23, locals=25, args_size=2
         0: aload_1
         1: ifnull        188
         4: aload_1
         5: invokevirtual #136                // Method scala/Tuple22._1:()Ljava/lang/Object;
         8: astore_3
         9: aload_1
        10: invokevirtual #139                // Method scala/Tuple22._2:()Ljava/lang/Object;
        13: astore        4
        15: aload_1
        16: invokevirtual #142                // Method scala/Tuple22._3:()Ljava/lang/Object;
        19: astore        5
        21: aload_1
        22: invokevirtual #145                // Method scala/Tuple22._4:()Ljava/lang/Object;
        25: astore        6
        27: aload_1
        28: invokevirtual #148                // Method scala/Tuple22._5:()Ljava/lang/Object;
        31: astore        7
        33: aload_1
        34: invokevirtual #151                // Method scala/Tuple22._6:()Ljava/lang/Object;
        37: astore        8
        39: aload_1
        40: invokevirtual #154                // Method scala/Tuple22._7:()Ljava/lang/Object;
        43: astore        9
        45: aload_1
        46: invokevirtual #157                // Method scala/Tuple22._8:()Ljava/lang/Object;
        49: astore        10
        51: aload_1
        52: invokevirtual #160                // Method scala/Tuple22._9:()Ljava/lang/Object;
        55: astore        11
        57: aload_1
        58: invokevirtual #163                // Method scala/Tuple22._10:()Ljava/lang/Object;
        61: astore        12
        63: aload_1
        64: invokevirtual #166                // Method scala/Tuple22._11:()Ljava/lang/Object;
        67: astore        13
        69: aload_1
        70: invokevirtual #169                // Method scala/Tuple22._12:()Ljava/lang/Object;
        73: astore        14
        75: aload_1
        76: invokevirtual #172                // Method scala/Tuple22._13:()Ljava/lang/Object;
        79: astore        15
        81: aload_1
        82: invokevirtual #175                // Method scala/Tuple22._14:()Ljava/lang/Object;
        85: astore        16
        87: aload_1
        88: invokevirtual #178                // Method scala/Tuple22._15:()Ljava/lang/Object;
        91: astore        17
        93: aload_1
        94: invokevirtual #181                // Method scala/Tuple22._16:()Ljava/lang/Object;
        97: astore        18
        99: aload_1
       100: invokevirtual #184                // Method scala/Tuple22._17:()Ljava/lang/Object;
       103: astore        19
       105: aload_1
       106: invokevirtual #187                // Method scala/Tuple22._18:()Ljava/lang/Object;
       109: astore        20
       111: aload_1
       112: invokevirtual #190                // Method scala/Tuple22._19:()Ljava/lang/Object;
       115: astore        21
       117: aload_1
       118: invokevirtual #193                // Method scala/Tuple22._20:()Ljava/lang/Object;
       121: astore        22
       123: aload_1
       124: invokevirtual #196                // Method scala/Tuple22._21:()Ljava/lang/Object;
       127: astore        23
       129: aload_1
       130: invokevirtual #199                // Method scala/Tuple22._22:()Ljava/lang/Object;
       133: astore        24
       135: aload_0
       136: aload_3
       137: aload         4
       139: aload         5
       141: aload         6
       143: aload         7
       145: aload         8
       147: aload         9
       149: aload         10
       151: aload         11
       153: aload         12
       155: aload         13
       157: aload         14
       159: aload         15
       161: aload         16
       163: aload         17
       165: aload         18
       167: aload         19
       169: aload         20
       171: aload         21
       173: aload         22
       175: aload         23
       177: aload         24
       179: invokeinterface #116,  23         // InterfaceMethod apply:(Ljava/lang/Object;Ljava/lang/Object;Ljava/lang/Object;Ljava/lang/Object;Ljava/lang/Object;Ljava/lang/Object;Ljava/lang/Object;Ljava/lang/Object;Ljava/lang/Object;Ljava/lang/Object;Ljava/lang/Object;Ljava/lang/Object;Ljava/lang/Object;Ljava/lang/Object;Ljava/lang/Object;Ljava/lang/Object;Ljava/lang/Object;Ljava/lang/Object;Ljava/lang/Object;Ljava/lang/Object;Ljava/lang/Object;Ljava/lang/Object;)Ljava/lang/Object;
       184: astore_2
       185: goto          197
       188: new           #201                // class scala/MatchError
       191: dup
       192: aconst_null
       193: invokespecial #205                // Method scala/MatchError."<init>":(Ljava/lang/Object;)V
       196: athrow
       197: aload_2
       198: areturn
      StackMapTable: number_of_entries = 2
        frame_type = 251 /* same_frame_extended */
          offset_delta = 188
        frame_type = 255 /* full_frame */
          offset_delta = 8
          locals = [ class scala/Function22, class scala/Tuple22, class java/lang/Object, class java/lang/Object, class java/lang/Object, class java/lang/Object, class java/lang/Object, class java/lang/Object, class java/lang/Object, class java/lang/Object, class java/lang/Object, class java/lang/Object, class java/lang/Object, class java/lang/Object, class java/lang/Object, class java/lang/Object, class java/lang/Object, class java/lang/Object, class java/lang/Object, class java/lang/Object, class java/lang/Object, class java/lang/Object, class java/lang/Object, class java/lang/Object, class java/lang/Object ]
          stack = []
      LineNumberTable:
        line 40: 0
        line 39: 188
      LocalVariableTable:
        Start  Length  Slot  Name   Signature
            9     179     3    x1   Ljava/lang/Object;
           15     173     4    x2   Ljava/lang/Object;
           21     167     5    x3   Ljava/lang/Object;
           27     161     6    x4   Ljava/lang/Object;
           33     155     7    x5   Ljava/lang/Object;
           39     149     8    x6   Ljava/lang/Object;
           45     143     9    x7   Ljava/lang/Object;
           51     137    10    x8   Ljava/lang/Object;
           57     131    11    x9   Ljava/lang/Object;
           63     125    12   x10   Ljava/lang/Object;
           69     119    13   x11   Ljava/lang/Object;
           75     113    14   x12   Ljava/lang/Object;
           81     107    15   x13   Ljava/lang/Object;
           87     101    16   x14   Ljava/lang/Object;
           93      95    17   x15   Ljava/lang/Object;
           99      89    18   x16   Ljava/lang/Object;
          105      83    19   x17   Ljava/lang/Object;
          111      77    20   x18   Ljava/lang/Object;
          117      71    21   x19   Ljava/lang/Object;
          123      65    22   x20   Ljava/lang/Object;
          129      59    23   x21   Ljava/lang/Object;
          135      53    24   x22   Ljava/lang/Object;
            0     199     0 $this   Lscala/Function22;
            0     199     1  x0$1   Lscala/Tuple22;
    MethodParameters:
      Name                           Flags
      $this                          final synthetic
      x0$1                           final

  public static void $init$(scala.Function22);
    descriptor: (Lscala/Function22;)V
    flags: (0x0009) ACC_PUBLIC, ACC_STATIC
    Code:
      stack=0, locals=1, args_size=1
         0: return
      LineNumberTable:
        line 21: 0
      LocalVariableTable:
        Start  Length  Slot  Name   Signature
            0       1     0 $this   Lscala/Function22;
    MethodParameters:
      Name                           Flags
      $this                          final synthetic

  private static java.lang.Object $deserializeLambda$(java.lang.invoke.SerializedLambda);
    descriptor: (Ljava/lang/invoke/SerializedLambda;)Ljava/lang/Object;
    flags: (0x100a) ACC_PRIVATE, ACC_STATIC, ACC_SYNTHETIC
    Code:
      stack=1, locals=1, args_size=1
         0: aload_0
         1: invokedynamic #220,  0            // InvokeDynamic #3:lambdaDeserialize:(Ljava/lang/invoke/SerializedLambda;)Ljava/lang/Object;
         6: areturn
}
InnerClasses:
  public static final #14= #11 of #13;    // Lookup=class java/lang/invoke/MethodHandles$Lookup of class java/lang/invoke/MethodHandles
Signature: #3                           // <T1:Ljava/lang/Object;T2:Ljava/lang/Object;T3:Ljava/lang/Object;T4:Ljava/lang/Object;T5:Ljava/lang/Object;T6:Ljava/lang/Object;T7:Ljava/lang/Object;T8:Ljava/lang/Object;T9:Ljava/lang/Object;T10:Ljava/lang/Object;T11:Ljava/lang/Object;T12:Ljava/lang/Object;T13:Ljava/lang/Object;T14:Ljava/lang/Object;T15:Ljava/lang/Object;T16:Ljava/lang/Object;T17:Ljava/lang/Object;T18:Ljava/lang/Object;T19:Ljava/lang/Object;T20:Ljava/lang/Object;T21:Ljava/lang/Object;T22:Ljava/lang/Object;R:Ljava/lang/Object;>Ljava/lang/Object;
SourceFile: "Function22.scala"
RuntimeVisibleAnnotations:
  0: #7(#8=s#9)
    scala.reflect.ScalaSignature(
      bytes="\u0006\u0005\u0005-ea\u0002\u0004\b!\u0003\r\tA\u0003\u0005\u0006!\u0001!\t!\u0005\u0005\u0006+\u00011\tA\u0006\u0005\b\u0003C\u0001A\u0011AA\u0012\u0011\u001d\t\u0019\u0007\u0001C\u0001\u0003KBq!!\u001d\u0001\t\u0003\n\u0019H\u0001\u0006Gk:\u001cG/[8oeIR\u0011\u0001C\u0001\u0006g\u000e\fG.Y\u0002\u0001+mYQEK\u00185sy\u001a\u0005*\u0014*X9\u000647\u000e];{\u007f\u0006%\u00111CA\u000f3M\u0011\u0001\u0001\u0004\t\u0003\u001b9i\u0011aB\u0005\u0003\u001f\u001d\u0011a!\u00118z%\u00164\u0017A\u0002\u0013j]&$H\u0005F\u0001\u0013!\ti1#\u0003\u0002\u0015\u000f\t!QK\\5u\u0003\u0015\t\u0007\u000f\u001d7z)i9\"e\n\u00172mm\u0002UIS(U3z\u001b\u0007.\u001c:xy\u0006\r\u0011QBA\f!\tA\u0012\u0004\u0004\u0001\u0005\ri\u0001AQ1\u0001\u001c\u0005\u0005\u0011\u0016C\u0001\u000f !\tiQ$\u0003\u0002\u001f\u000f\t9aj\u001c;iS:<\u0007CA\u0007!\u0013\t\tsAA\u0002B]fDQa\t\u0002A\u0002\u0011\n!A^\u0019\u0011\u0005a)CA\u0002\u0014\u0001\u0011\u000b\u00071D\u0001\u0002Uc!)\u0001F\u0001a\u0001S\u0005\u0011aO\r\t\u00031)\"aa\u000b\u0001\t\u0006\u0004Y\"A\u0001+3\u0011\u0015i#\u00011\u0001/\u0003\t18\u0007\u0005\u0002\u0019_\u00111\u0001\u0007\u0001EC\u0002m\u0011!\u0001V\u001a\t\u000bI\u0012\u0001\u0019A\u001a\u0002\u0005Y$\u0004C\u0001\r5\t\u0019)\u0004\u0001#b\u00017\t\u0011A\u000b\u000e\u0005\u0006o\t\u0001\r\u0001O\u0001\u0003mV\u0002\"\u0001G\u001d\u0005\ri\u0002\u0001R1\u0001\u001c\u0005\t!V\u0007C\u0003=\u0005\u0001\u0007Q(\u0001\u0002wmA\u0011\u0001D\u0010\u0003\u0007\u007f\u0001A)\u0019A\u000e\u0003\u0005Q3\u0004\"B!\u0003\u0001\u0004\u0011\u0015A\u0001<8!\tA2\t\u0002\u0004E\u0001!\u0015\ra\u0007\u0002\u0003)^BQA\u0012\u0002A\u0002\u001d\u000b!A\u001e\u001d\u0011\u0005aAEAB%\u0001\u0011\u000b\u00071D\u0001\u0002Uq!)1J\u0001a\u0001\u0019\u0006\u0011a/\u000f\t\u000315#aA\u0014\u0001\t\u0006\u0004Y\"A\u0001+:\u0011\u0015\u0001&\u00011\u0001R\u0003\r1\u0018\u0007\r\t\u00031I#aa\u0015\u0001\t\u0006\u0004Y\"a\u0001+2a!)QK\u0001a\u0001-\u0006\u0019a/M\u0019\u0011\u0005a9FA\u0002-\u0001\u0011\u000b\u00071DA\u0002UcEBQA\u0017\u0002A\u0002m\u000b1A^\u00193!\tAB\f\u0002\u0004^\u0001!\u0015\ra\u0007\u0002\u0004)F\u0012\u0004\"B0\u0003\u0001\u0004\u0001\u0017a\u0001<2gA\u0011\u0001$\u0019\u0003\u0007E\u0002A)\u0019A\u000e\u0003\u0007Q\u000b4\u0007C\u0003e\u0005\u0001\u0007Q-A\u0002wcQ\u0002\"\u0001\u00074\u0005\r\u001d\u0004\u0001R1\u0001\u001c\u0005\r!\u0016\u0007\u000e\u0005\u0006S\n\u0001\rA[\u0001\u0004mF*\u0004C\u0001\rl\t\u0019a\u0007\u0001#b\u00017\t\u0019A+M\u001b\t\u000b9\u0014\u0001\u0019A8\u0002\u0007Y\fd\u0007\u0005\u0002\u0019a\u00121\u0011\u000f\u0001EC\u0002m\u00111\u0001V\u00197\u0011\u0015\u0019(\u00011\u0001u\u0003\r1\u0018g\u000e\t\u00031U$aA\u001e\u0001\t\u0006\u0004Y\"a\u0001+2o!)\u0001P\u0001a\u0001s\u0006\u0019a/\r\u001d\u0011\u0005aQHAB>\u0001\u0011\u000b\u00071DA\u0002UcaBQ! \u0002A\u0002y\f1A^\u0019:!\tAr\u0010B\u0004\u0002\u0002\u0001A)\u0019A\u000e\u0003\u0007Q\u000b\u0014\bC\u0004\u0002\u0006\t\u0001\r!a\u0002\u0002\u0007Y\u0014\u0004\u0007E\u0002\u0019\u0003\u0013!q!a\u0003\u0001\u0011\u000b\u00071DA\u0002UeABq!a\u0004\u0003\u0001\u0004\t\t\"A\u0002weE\u00022\u0001GA\n\t\u001d\t)\u0002\u0001EC\u0002m\u00111\u0001\u0016\u001a2\u0011\u001d\tIB\u0001a\u0001\u00037\t1A\u001e\u001a3!\rA\u0012Q\u0004\u0003\b\u0003?\u0001\u0001R1\u0001\u001c\u0005\r!&GM\u0001\bGV\u0014(/[3e+\t\t)\u0003\u0005\u0004\u000e\u0003O!\u00131F\u0005\u0004\u0003S9!!\u0003$v]\u000e$\u0018n\u001c82!\u0019i\u0011qE\u0015\u0002.A1Q\"a\n/\u0003_\u0001b!DA\u0014g\u0005E\u0002CB\u0007\u0002(a\n\u0019\u0004\u0005\u0004\u000e\u0003Oi\u0014Q\u0007\t\u0007\u001b\u0005\u001d\")a\u000e\u0011\r5\t9cRA\u001d!\u0019i\u0011q\u0005\'\u0002<A1Q\"a\nR\u0003{\u0001b!DA\u0014-\u0006}\u0002CB\u0007\u0002(m\u000b\t\u0005\u0005\u0004\u000e\u0003O\u0001\u00171\t\t\u0007\u001b\u0005\u001dR-!\u0012\u0011\r5\t9C[A$!\u0019i\u0011qE8\u0002JA1Q\"a\nu\u0003\u0017\u0002b!DA\u0014s\u00065\u0003CB\u0007\u0002(y\fy\u0005E\u0004\u000e\u0003O\t9!!\u0015\u0011\u000f5\t9#!\u0005\u0002TA1Q\"a\n\u0002\u001c]A3aAA,!\u0011\tI&a\u0018\u000e\u0005\u0005m#bAA/\u000f\u0005Q\u0011M\u001c8pi\u0006$\u0018n\u001c8\n\t\u0005\u0005\u00141\f\u0002\u000ek:\u001c\b/Z2jC2L\'0\u001a3\u0002\rQ,\b\u000f\\3e+\t\t9\u0007\u0005\u0004\u000e\u0003O\tIg\u0006\t\u001d\u001b\u0005-D%\u000b\u00184qu\u0012u\tT)W7\u0002,\'n\u001c;z}\u0006\u001d\u0011\u0011CA\u000e\u0013\r\tig\u0002\u0002\b)V\u0004H.\u001a\u001a3Q\r!\u0011qK\u0001\ti>\u001cFO]5oOR\u0011\u0011Q\u000f\t\u0005\u0003o\n)I\u0004\u0003\u0002z\u0005\u0005\u0005cAA>\u000f5\u0011\u0011Q\u0010\u0006\u0004\u0003\u007fJ\u0011A\u0002\u001fs_>$h(C\u0002\u0002\u0004\u001e\ta\u0001\u0015:fI\u00164\u0017\u0002BAD\u0003\u0013\u0013aa\u0015;sS:<\'bAAB\u000f\u0001"
    )
BootstrapMethods:
  0: #66 REF_invokeStatic java/lang/invoke/LambdaMetafactory.altMetafactory:(Ljava/lang/invoke/MethodHandles$Lookup;Ljava/lang/String;Ljava/lang/invoke/MethodType;[Ljava/lang/Object;)Ljava/lang/invoke/CallSite;
    Method arguments:
      #50 (Ljava/lang/Object;)Ljava/lang/Object;
      #55 REF_invokeStatic scala/Function22.$anonfun$curried$1:(Lscala/Function22;Ljava/lang/Object;)Lscala/Function1;
      #57 (Ljava/lang/Object;)Lscala/Function1;
      #58 5
      #59 1
      #57 (Ljava/lang/Object;)Lscala/Function1;
  1: #66 REF_invokeStatic java/lang/invoke/LambdaMetafactory.altMetafactory:(Ljava/lang/invoke/MethodHandles$Lookup;Ljava/lang/String;Ljava/lang/invoke/MethodType;[Ljava/lang/Object;)Ljava/lang/invoke/CallSite;
    Method arguments:
      #50 (Ljava/lang/Object;)Ljava/lang/Object;
      #79 REF_invokeStatic scala/Function22.$anonfun$tupled$1:(Lscala/Function22;Lscala/Tuple22;)Ljava/lang/Object;
      #81 (Lscala/Tuple22;)Ljava/lang/Object;
      #58 5
      #59 1
      #81 (Lscala/Tuple22;)Ljava/lang/Object;
  2: #66 REF_invokeStatic java/lang/invoke/LambdaMetafactory.altMetafactory:(Ljava/lang/invoke/MethodHandles$Lookup;Ljava/lang/String;Ljava/lang/invoke/MethodType;[Ljava/lang/Object;)Ljava/lang/invoke/CallSite;
    Method arguments:
      #120 (Ljava/lang/Object;Ljava/lang/Object;Ljava/lang/Object;Ljava/lang/Object;Ljava/lang/Object;Ljava/lang/Object;Ljava/lang/Object;Ljava/lang/Object;Ljava/lang/Object;Ljava/lang/Object;Ljava/lang/Object;Ljava/lang/Object;Ljava/lang/Object;Ljava/lang/Object;Ljava/lang/Object;Ljava/lang/Object;Ljava/lang/Object;Ljava/lang/Object;Ljava/lang/Object;Ljava/lang/Object;Ljava/lang/Object;)Ljava/lang/Object;
      #123 REF_invokeStatic scala/Function22.$anonfun$curried$2:(Lscala/Function22;Ljava/lang/Object;Ljava/lang/Object;Ljava/lang/Object;Ljava/lang/Object;Ljava/lang/Object;Ljava/lang/Object;Ljava/lang/Object;Ljava/lang/Object;Ljava/lang/Object;Ljava/lang/Object;Ljava/lang/Object;Ljava/lang/Object;Ljava/lang/Object;Ljava/lang/Object;Ljava/lang/Object;Ljava/lang/Object;Ljava/lang/Object;Ljava/lang/Object;Ljava/lang/Object;Ljava/lang/Object;Ljava/lang/Object;Ljava/lang/Object;)Ljava/lang/Object;
      #120 (Ljava/lang/Object;Ljava/lang/Object;Ljava/lang/Object;Ljava/lang/Object;Ljava/lang/Object;Ljava/lang/Object;Ljava/lang/Object;Ljava/lang/Object;Ljava/lang/Object;Ljava/lang/Object;Ljava/lang/Object;Ljava/lang/Object;Ljava/lang/Object;Ljava/lang/Object;Ljava/lang/Object;Ljava/lang/Object;Ljava/lang/Object;Ljava/lang/Object;Ljava/lang/Object;Ljava/lang/Object;Ljava/lang/Object;)Ljava/lang/Object;
      #59 1
  3: #217 REF_invokeStatic scala/runtime/LambdaDeserialize.bootstrap:(Ljava/lang/invoke/MethodHandles$Lookup;Ljava/lang/String;Ljava/lang/invoke/MethodType;[Ljava/lang/invoke/MethodHandle;)Ljava/lang/invoke/CallSite;
    Method arguments:
      #55 REF_invokeStatic scala/Function22.$anonfun$curried$1:(Lscala/Function22;Ljava/lang/Object;)Lscala/Function1;
      #123 REF_invokeStatic scala/Function22.$anonfun$curried$2:(Lscala/Function22;Ljava/lang/Object;Ljava/lang/Object;Ljava/lang/Object;Ljava/lang/Object;Ljava/lang/Object;Ljava/lang/Object;Ljava/lang/Object;Ljava/lang/Object;Ljava/lang/Object;Ljava/lang/Object;Ljava/lang/Object;Ljava/lang/Object;Ljava/lang/Object;Ljava/lang/Object;Ljava/lang/Object;Ljava/lang/Object;Ljava/lang/Object;Ljava/lang/Object;Ljava/lang/Object;Ljava/lang/Object;Ljava/lang/Object;Ljava/lang/Object;)Ljava/lang/Object;
      #79 REF_invokeStatic scala/Function22.$anonfun$tupled$1:(Lscala/Function22;Lscala/Tuple22;)Ljava/lang/Object;
  ScalaInlineInfo: length = 0x3F (unknown attribute)
   01 04 00 0F 00 10 00 0B 00 33 00 34 01 00 5B 00
   5C 01 00 4B 00 4C 01 00 CF 00 D0 01 00 0F 00 10
   00 00 2B 00 2C 00 00 28 00 29 01 00 55 00 56 00
   00 53 00 54 01 00 47 00 2C 00 00 46 00 29 01
  ScalaSig: length = 0x3 (unknown attribute)
   05 02 00
