Classfile /Users/mw/Projects/slang-braindump/.jar/jar8/assemble/slang-braindump/assemble/content/scala/PartialFunction$Lifted.class
  Last modified May 29, 2022; size 1802 bytes
  SHA-256 checksum fd0ef22c6ff066b88cd4bf6960b62288fe92f11a992840e690278c2edaef8a1a
  Compiled from "PartialFunction.scala"
public class scala.PartialFunction$Lifted<A extends java.lang.Object, B extends java.lang.Object> extends scala.runtime.AbstractFunction1<A, scala.Option<B>> implements java.io.Serializable
  minor version: 0
  major version: 52
  flags: (0x0021) ACC_PUBLIC, ACC_SUPER
  this_class: #2                          // scala/PartialFunction$Lifted
  super_class: #5                         // scala/runtime/AbstractFunction1
  interfaces: 1, fields: 1, methods: 4, attributes: 5
Constant pool:
   #1 = Utf8               scala/PartialFunction$Lifted
   #2 = Class              #1             // scala/PartialFunction$Lifted
   #3 = Utf8               <A:Ljava/lang/Object;B:Ljava/lang/Object;>Lscala/runtime/AbstractFunction1<TA;Lscala/Option<TB;>;>;Ljava/io/Serializable;
   #4 = Utf8               scala/runtime/AbstractFunction1
   #5 = Class              #4             // scala/runtime/AbstractFunction1
   #6 = Utf8               java/io/Serializable
   #7 = Class              #6             // java/io/Serializable
   #8 = Utf8               PartialFunction.scala
   #9 = Utf8               scala/PartialFunction
  #10 = Class              #9             // scala/PartialFunction
  #11 = Utf8               Lifted
  #12 = Utf8               pf
  #13 = Utf8               Lscala/PartialFunction;
  #14 = Utf8               Lscala/PartialFunction<TA;TB;>;
  #15 = Utf8               ()Lscala/PartialFunction;
  #16 = Utf8               ()Lscala/PartialFunction<TA;TB;>;
  #17 = NameAndType        #12:#13        // pf:Lscala/PartialFunction;
  #18 = Fieldref           #2.#17         // scala/PartialFunction$Lifted.pf:Lscala/PartialFunction;
  #19 = Utf8               this
  #20 = Utf8               Lscala/PartialFunction$Lifted;
  #21 = Utf8               apply
  #22 = Utf8               (Ljava/lang/Object;)Lscala/Option;
  #23 = Utf8               (TA;)Lscala/Option<TB;>;
  #24 = Utf8               x
  #25 = NameAndType        #12:#15        // pf:()Lscala/PartialFunction;
  #26 = Methodref          #2.#25         // scala/PartialFunction$Lifted.pf:()Lscala/PartialFunction;
  #27 = Utf8               scala/PartialFunction$
  #28 = Class              #27            // scala/PartialFunction$
  #29 = Utf8               MODULE$
  #30 = Utf8               Lscala/PartialFunction$;
  #31 = NameAndType        #29:#30        // MODULE$:Lscala/PartialFunction$;
  #32 = Fieldref           #28.#31        // scala/PartialFunction$.MODULE$:Lscala/PartialFunction$;
  #33 = Utf8               scala$PartialFunction$$checkFallback
  #34 = Utf8               ()Lscala/Function1;
  #35 = NameAndType        #33:#34        // scala$PartialFunction$$checkFallback:()Lscala/Function1;
  #36 = Methodref          #28.#35        // scala/PartialFunction$.scala$PartialFunction$$checkFallback:()Lscala/Function1;
  #37 = Utf8               applyOrElse
  #38 = Utf8               (Ljava/lang/Object;Lscala/Function1;)Ljava/lang/Object;
  #39 = NameAndType        #37:#38        // applyOrElse:(Ljava/lang/Object;Lscala/Function1;)Ljava/lang/Object;
  #40 = InterfaceMethodref #10.#39        // scala/PartialFunction.applyOrElse:(Ljava/lang/Object;Lscala/Function1;)Ljava/lang/Object;
  #41 = Utf8               scala$PartialFunction$$fallbackOccurred
  #42 = Utf8               (Ljava/lang/Object;)Z
  #43 = NameAndType        #41:#42        // scala$PartialFunction$$fallbackOccurred:(Ljava/lang/Object;)Z
  #44 = Methodref          #28.#43        // scala/PartialFunction$.scala$PartialFunction$$fallbackOccurred:(Ljava/lang/Object;)Z
  #45 = Utf8               scala/Some
  #46 = Class              #45            // scala/Some
  #47 = Utf8               <init>
  #48 = Utf8               (Ljava/lang/Object;)V
  #49 = NameAndType        #47:#48        // "<init>":(Ljava/lang/Object;)V
  #50 = Methodref          #46.#49        // scala/Some."<init>":(Ljava/lang/Object;)V
  #51 = Utf8               scala/None$
  #52 = Class              #51            // scala/None$
  #53 = Utf8               Lscala/None$;
  #54 = NameAndType        #29:#53        // MODULE$:Lscala/None$;
  #55 = Fieldref           #52.#54        // scala/None$.MODULE$:Lscala/None$;
  #56 = Utf8               z
  #57 = Utf8               Ljava/lang/Object;
  #58 = Utf8               java/lang/Object
  #59 = Class              #58            // java/lang/Object
  #60 = Utf8               (Ljava/lang/Object;)Ljava/lang/Object;
  #61 = Utf8               v1
  #62 = NameAndType        #21:#22        // apply:(Ljava/lang/Object;)Lscala/Option;
  #63 = Methodref          #2.#62         // scala/PartialFunction$Lifted.apply:(Ljava/lang/Object;)Lscala/Option;
  #64 = Utf8               (Lscala/PartialFunction;)V
  #65 = Utf8               (Lscala/PartialFunction<TA;TB;>;)V
  #66 = Utf8               ()V
  #67 = NameAndType        #47:#66        // "<init>":()V
  #68 = Methodref          #5.#67         // scala/runtime/AbstractFunction1."<init>":()V
  #69 = Utf8               Signature
  #70 = Utf8               Code
  #71 = Utf8               LineNumberTable
  #72 = Utf8               LocalVariableTable
  #73 = Utf8               StackMapTable
  #74 = Utf8               MethodParameters
  #75 = Utf8               InnerClasses
  #76 = Utf8               SourceFile
  #77 = Utf8               ScalaInlineInfo
  #78 = Utf8               Scala
{
  private final scala.PartialFunction<A, B> pf;
    descriptor: Lscala/PartialFunction;
    flags: (0x0012) ACC_PRIVATE, ACC_FINAL
    Signature: #14                          // Lscala/PartialFunction<TA;TB;>;

  public scala.PartialFunction<A, B> pf();
    descriptor: ()Lscala/PartialFunction;
    flags: (0x0001) ACC_PUBLIC
    Code:
      stack=1, locals=1, args_size=1
         0: aload_0
         1: getfield      #18                 // Field pf:Lscala/PartialFunction;
         4: areturn
      LineNumberTable:
        line 334: 0
      LocalVariableTable:
        Start  Length  Slot  Name   Signature
            0       5     0  this   Lscala/PartialFunction$Lifted;
    Signature: #16                          // ()Lscala/PartialFunction<TA;TB;>;

  public scala.Option<B> apply(A);
    descriptor: (Ljava/lang/Object;)Lscala/Option;
    flags: (0x0001) ACC_PUBLIC
    Code:
      stack=3, locals=3, args_size=2
         0: aload_0
         1: invokevirtual #26                 // Method pf:()Lscala/PartialFunction;
         4: aload_1
         5: getstatic     #32                 // Field scala/PartialFunction$.MODULE$:Lscala/PartialFunction$;
         8: invokevirtual #36                 // Method scala/PartialFunction$.scala$PartialFunction$$checkFallback:()Lscala/Function1;
        11: invokeinterface #40,  3           // InterfaceMethod scala/PartialFunction.applyOrElse:(Ljava/lang/Object;Lscala/Function1;)Ljava/lang/Object;
        16: astore_2
        17: getstatic     #32                 // Field scala/PartialFunction$.MODULE$:Lscala/PartialFunction$;
        20: aload_2
        21: invokevirtual #44                 // Method scala/PartialFunction$.scala$PartialFunction$$fallbackOccurred:(Ljava/lang/Object;)Z
        24: ifne          36
        27: new           #46                 // class scala/Some
        30: dup
        31: aload_2
        32: invokespecial #50                 // Method scala/Some."<init>":(Ljava/lang/Object;)V
        35: areturn
        36: getstatic     #55                 // Field scala/None$.MODULE$:Lscala/None$;
        39: areturn
      StackMapTable: number_of_entries = 1
        frame_type = 252 /* append */
          offset_delta = 36
          locals = [ class java/lang/Object ]
      LineNumberTable:
        line 338: 0
        line 339: 17
      LocalVariableTable:
        Start  Length  Slot  Name   Signature
           17      22     2     z   Ljava/lang/Object;
            0      40     0  this   Lscala/PartialFunction$Lifted;
            0      40     1     x   Ljava/lang/Object;
    Signature: #23                          // (TA;)Lscala/Option<TB;>;
    MethodParameters:
      Name                           Flags
      x                              final

  public java.lang.Object apply(java.lang.Object);
    descriptor: (Ljava/lang/Object;)Ljava/lang/Object;
    flags: (0x1041) ACC_PUBLIC, ACC_BRIDGE, ACC_SYNTHETIC
    Code:
      stack=2, locals=2, args_size=2
         0: aload_0
         1: aload_1
         2: invokevirtual #63                 // Method apply:(Ljava/lang/Object;)Lscala/Option;
         5: areturn
      LineNumberTable:
        line 334: 0
      LocalVariableTable:
        Start  Length  Slot  Name   Signature
            0       6     0  this   Lscala/PartialFunction$Lifted;
            0       6     1    v1   Ljava/lang/Object;
    MethodParameters:
      Name                           Flags
      v1                             final

  public scala.PartialFunction$Lifted(scala.PartialFunction<A, B>);
    descriptor: (Lscala/PartialFunction;)V
    flags: (0x0001) ACC_PUBLIC
    Code:
      stack=2, locals=2, args_size=2
         0: aload_0
         1: aload_1
         2: putfield      #18                 // Field pf:Lscala/PartialFunction;
         5: aload_0
         6: invokespecial #68                 // Method scala/runtime/AbstractFunction1."<init>":()V
         9: return
      LineNumberTable:
        line 334: 0
        line 335: 5
        line 334: 9
      LocalVariableTable:
        Start  Length  Slot  Name   Signature
            0      10     0  this   Lscala/PartialFunction$Lifted;
            0      10     1    pf   Lscala/PartialFunction;
    Signature: #65                          // (Lscala/PartialFunction<TA;TB;>;)V
    MethodParameters:
      Name                           Flags
      pf                             final
}
InnerClasses:
  private static #11= #2 of #10;          // Lifted=class scala/PartialFunction$Lifted of class scala/PartialFunction
Signature: #3                           // <A:Ljava/lang/Object;B:Ljava/lang/Object;>Lscala/runtime/AbstractFunction1<TA;Lscala/Option<TB;>;>;Ljava/io/Serializable;
SourceFile: "PartialFunction.scala"
  ScalaInlineInfo: length = 0x18 (unknown attribute)
   01 00 00 04 00 2F 00 40 00 00 15 00 3C 00 00 15
   00 16 00 00 0C 00 0F 00
  Scala: length = 0x0 (unknown attribute)

