Classfile /Users/mw/Projects/slang-braindump/.jar/jar8/assemble/slang-braindump/assemble/content/scala/PartialFunction.class
  Last modified May 29, 2022; size 11636 bytes
  SHA-256 checksum d2c03c73cc25fac49e9d82789499a83b06d7d7761de7da71aabc6a7d8726aa8f
  Compiled from "PartialFunction.scala"
public interface scala.PartialFunction<A extends java.lang.Object, B extends java.lang.Object> extends scala.Function1<A, B>
  minor version: 0
  major version: 52
  flags: (0x0601) ACC_PUBLIC, ACC_INTERFACE, ACC_ABSTRACT
  this_class: #2                          // scala/PartialFunction
  super_class: #5                         // java/lang/Object
  interfaces: 1, fields: 0, methods: 27, attributes: 7
Constant pool:
    #1 = Utf8               scala/PartialFunction
    #2 = Class              #1            // scala/PartialFunction
    #3 = Utf8               <A:Ljava/lang/Object;B:Ljava/lang/Object;>Ljava/lang/Object;Lscala/Function1<TA;TB;>;
    #4 = Utf8               java/lang/Object
    #5 = Class              #4            // java/lang/Object
    #6 = Utf8               scala/Function1
    #7 = Class              #6            // scala/Function1
    #8 = Utf8               PartialFunction.scala
    #9 = Utf8               Lscala/reflect/ScalaSignature;
   #10 = Utf8               bytes
   #11 = Utf8               \u0006\u0005\rEha\u0002%J!\u0003\r\t\u0001\u0014\u0005\u0006G\u0002!\t\u0001\u001a\u0005\u0006Q\u0002!\t!\u001b\u0005\u0006_\u0002!\t\u0001\u001d\u0005\b\u0003\u000b\u0004a\u0011ABA\u0011\u001d\t\t\u0010\u0001C\u0001\u0007\u000bCqAa\u0002\u0001\t\u0003\u001aI\nC\u0004\u0003\b\u0001!\taa*\t\u000f\rU\u0006\u0001\"\u0001\u00048\"91\u0011\u0003\u0001\u0005\u0002\r\u001d\u0007bBAj\u0001\u0011\u000511\u001a\u0005\b\u0007;\u0004A\u0011ABp\u000f\u0015\u0019\u0018\n#\u0001u\r\u0015A\u0015\n#\u0001v\u0011\u00151X\u0002\"\u0001x\r\u0011AXBA=\t\u0019y|A\u0011!A\u0003\u0006\u000b\u0007I\u0011B@\t\u0017\u0005-qB!B\u0001B\u0003%\u0011\u0011\u0001\u0005\bm>!\t!DA\u0007\u0011\u001d\t9b\u0004C\u0001\u00033A\u0011\"!\r\u0010\u0003\u0003%\t%a\r\t\u0013\u0005mr\"!A\u0005B\u0005ur!CA%\u001b\u0005\u0005\t\u0012AA&\r!AX\"!A\t\u0002\u00055\u0003B\u0002<\u0018\t\u0003\ty\u0005C\u0004\u0002R]!)!a\u0015\t\u0013\u0005=t#!A\u0005\u0006\u0005E\u0004\"CAA/\u0005\u0005IQAAB\r\u0019\t9*\u0004\u0003\u0002\u001a\"Q\u0011q\u0017\u000f\u0003\u0002\u0003\u0006I!!/\t\u0015\u0005mFD!A!\u0002\u0013\tI\f\u0003\u0004w9\u0011\u0005\u0011Q\u0018\u0005\b\u0003\u000bdB\u0011AAd\u0011\u001d\ti\r\bC!\u0003\u001fDq!a5\u001d\t\u0003\n)\u000eC\u0004\u0002rr!\t%a=\t\u000f\t\u001dA\u0004\"\u0011\u0003\n\u00191!1D\u0007\u0005\u0005;A!\"!\u0006&\u0005\u0003\u0005\u000b\u0011\u0002B\u0016\u0011)\u00119\"\nB\u0001B\u0003%!\u0011\u0007\u0005\u0007m\u0016\"\tAa\r\t\u000f\u0005\u0015W\u0005\"\u0001\u0003<!9\u0011QZ\u0013\u0005\u0002\t}\u0002bBAjK\u0011\u0005#1\t\u0004\u0007\u00057jAA!\u0018\t\u0015\u0005UAF!A!\u0002\u0013\u0011Y\u0007\u0003\u0006\u0003\u00181\u0012\t\u0011)A\u0005\u0005cBaA\u001e\u0017\u0005\u0002\tM\u0004bBAcY\u0011\u0005!1\u0010\u0005\b\u0003\u001bdC\u0011\u0001B@\u0011\u001d\t\u0019\u000e\fC!\u0005\u0007C\u0001B!\'\u000eA\u0003%!1\u0014\u0005\b\u0005;kA\u0011\u0002BP\u0011\u001d\u0011I+\u0004C\u0005\u0005W3aA!.\u000e\t\t]\u0006BCA\u000bm\t\u0015\r\u0011\"\u0001\u0003L\"Q!q\u001a\u001c\u0003\u0002\u0003\u0006IA!4\t\rY4D\u0011\u0001Bi\u0011\u001d\tiM\u000eC\u0001\u0005/4aAa7\u000e\t\tu\u0007B\u0003Bvw\t\u0005\t\u0015!\u0003\u0003n\"1ao\u000fC\u0001\u0005cDq!!2<\t\u0003\u00119\u0010C\u0004\u0002Tn\"\tEa?\t\u000f\rE1\b\"\u0011\u0004\u0014!A1QC\u0007\u0005\u0002%\u001b9\u0002C\u0004\u0004,5!\ta!\f\t\u0011\r}R\u0002)A\u0005\u0007\u0003B\u0001ba\u0011\u000eA\u0003%1Q\t\u0005\b\u0007\u000fjA\u0011AB%\u0011\u001d\u00199&\u0004C\u0001\u00073Bqa!\u001b\u000e\t\u0003\u0019YGA\bQCJ$\u0018.\u00197Gk:\u001cG/[8o\u0015\u0005Q\u0015!B:dC2\f7\u0001A\u000b\u0004\u001b^\u000b7c\u0001\u0001O%B\u0011q\nU\u0007\u0002\u0013&\u0011\u0011+\u0013\u0002\u0007\u0003:L(+\u001a4\u0011\t=\u001bV\u000bY\u0005\u0003)&\u0013\u0011BR;oGRLwN\\\u0019\u0011\u0005Y;F\u0002\u0001\u0003\u00071\u0002A)\u0019A-\u0003\u0003\u0005\u000b\"AW/\u0011\u0005=[\u0016B\u0001/J\u0005\u001dqu\u000e\u001e5j]\u001e\u0004\"a\u00140\n\u0005}K%aA!osB\u0011a+\u0019\u0003\u0007E\u0002!)\u0019A-\u0003\u0003\t\u000ba\u0001J5oSR$C#A3\u0011\u0005=3\u0017BA4J\u0005\u0011)f.\u001b;\u0002\u000fUt\u0017\r\u001d9msR\u0011!.\u001c\t\u0004\u001f.\u0004\u0017B\u00017J\u0005\u0019y\u0005\u000f^5p]\")aN\u0001a\u0001+\u0006\t\u0011-A\u0006fY\u0016lWM\u001c;XSN,W#A9\u0011\tI|Q\u000b\u0019\b\u0003\u001f2\tq\u0002U1si&\fGNR;oGRLwN\u001c\t\u0003\u001f6\u0019\"!\u0004(\u0002\rqJg.\u001b;?)\u0005!(\u0001F#mK6,g\u000e^,jg\u0016,\u0005\u0010\u001e:bGR|\'/F\u0003{\u0003\u000b\tIa\u0005\u0002\u0010wB\u0011q\n`\u0005\u0003{&\u0013a!\u00118z-\u0006d\u0017AL:dC2\fG\u0005U1si&\fGNR;oGRLwN\u001c\u0013FY\u0016lWM\u001c;XSN,W\t\u001f;sC\u000e$xN\u001d\u0013%a\u001a,\"!!\u0001\u0011\r=\u0003\u00111AA\u0004!\r1\u0016Q\u0001\u0003\u00071>A)\u0019A-\u0011\u0007Y\u000bI\u0001\u0002\u0004c\u001f\u0011\u0015\r!W\u00010g\u000e\fG.\u0019\u0013QCJ$\u0018.\u00197Gk:\u001cG/[8oI\u0015cW-\\3oi^K7/Z#yiJ\f7\r^8sI\u0011\u0002h\r\t\u000b\u0005\u0003\u001f\t\u0019\u0002E\u0004\u0002\u0012=\t\u0019!a\u0002\u000e\u00035Aq!!\u0006\u0013\u0001\u0004\t\t!\u0001\u0002qM\u0006QQO\\1qa2L8+Z9\u0015\t\u0005m\u00111\u0006\t\u0005\u001f.\fi\u0002\u0005\u0004\u0002 \u0005\u0015\u0012q\u0001\b\u0004\u001f\u0006\u0005\u0012bAA\u0012\u0013\u00069\u0001/Y2lC\u001e,\u0017\u0002BA\u0014\u0003S\u00111aU3r\u0015\r\t\u0019#\u0013\u0005\b\u0003[\u0019\u0002\u0019AA\u0018\u0003\r\u0019X-\u001d\t\u0007\u0003?\t)#a\u0001\u0002\u0011!\f7\u000f[\"pI\u0016$\"!!\u000e\u0011\u0007=\u000b9$C\u0002\u0002:%\u00131!\u00138u\u0003\u0019)\u0017/^1mgR!\u0011qHA#!\ry\u0015\u0011I\u0005\u0004\u0003\u0007J%a\u0002\"p_2,\u0017M\u001c\u0005\t\u0003\u000f*\u0012\u0011!a\u0001;\u0006\u0019\u0001\u0010J\u0019\u0002)\u0015cW-\\3oi^K7/Z#yiJ\f7\r^8s!\r\t\tbF\n\u0003/9#\"!a\u0013\u0002)Ut\u0017\r\u001d9msN+\u0017\u000fJ3yi\u0016t7/[8o+\u0019\t)&a\u001a\u0002`Q!\u0011qKA5)\u0011\tI&!\u0019\u0011\t=[\u00171\f\t\u0007\u0003?\t)#!\u0018\u0011\u0007Y\u000by\u0006B\u0003c3\t\u0007\u0011\fC\u0004\u0002.e\u0001\r!a\u0019\u0011\r\u0005}\u0011QEA3!\r1\u0016q\r\u0003\u00061f\u0011\r!\u0017\u0005\b\u0003WJ\u0002\u0019AA7\u0003\u0015!C\u000f[5t!\u001d\t\tbDA3\u0003;\n!\u0003[1tQ\u000e{G-\u001a\u0013fqR,gn]5p]V1\u00111OA>\u0003\u007f\"B!a\r\u0002v!9\u00111\u000e\u000eA\u0002\u0005]\u0004cBA\t\u001f\u0005e\u0014Q\u0010\t\u0004-\u0006mD!\u0002-\u001b\u0005\u0004I\u0006c\u0001,\u0002\u0000\u0011)!M\u0007b\u00013\u0006\u0001R-];bYN$S\r\u001f;f]NLwN\\\u000b\u0007\u0003\u000b\u000b\t*!&\u0015\t\u0005\u001d\u00151\u0012\u000b\u0005\u0003\u007f\tI\t\u0003\u0005\u0002Hm\t\t\u00111\u0001^\u0011\u001d\tYg\u0007a\u0001\u0003\u001b\u0003r!!\u0005\u0010\u0003\u001f\u000b\u0019\nE\u0002W\u0003##Q\u0001W\u000eC\u0002e\u00032AVAK\t\u0015\u00117D1\u0001Z\u0005\u0019y%/\u00127tKV1\u00111TAV\u0003_\u001bR\u0001HAO\u0003c\u0003\u0002\"a(\u0002&\u0006%\u0016QV\u0007\u0003\u0003CS1!a)J\u0003\u001d\u0011XO\u001c;j[\u0016LA!a*\u0002\"\n9\u0012IY:ue\u0006\u001cG\u000fU1si&\fGNR;oGRLwN\u001c\t\u0004-\u0006-FA\u0002-\u001d\u0011\u000b\u0007\u0011\fE\u0002W\u0003_#aA\u0019\u000f\u0005\u0006\u0004I\u0006\u0003BA\u0010\u0003gKA!!.\u0002*\ta1+\u001a:jC2L\'0\u00192mK\u0006\u0011a-\r\t\u0007\u001f\u0002\tI+!,\u0002\u0005\u0019\u0014DCBA`\u0003\u0003\f\u0019\rE\u0004\u0002\u0012q\tI+!,\t\u000f\u0005]v\u00041\u0001\u0002:\"9\u00111X\u0010A\u0002\u0005e\u0016aC5t\t\u00164\u0017N\\3e\u0003R$B!a\u0010\u0002J\"9\u00111\u001a\u0011A\u0002\u0005%\u0016!\u0001=\u0002\u000b\u0005\u0004\b\u000f\\=\u0015\t\u00055\u0016\u0011\u001b\u0005\b\u0003\u0017\f\u0003\u0019AAU\u0003-\t\u0007\u000f\u001d7z\u001fJ,En]3\u0016\r\u0005]\u0017Q]An)\u0019\tI.!9\u0002lB\u0019a+a7\u0005\u000f\u0005u\'E1\u0001\u0002`\n\u0011!)M\t\u0004\u0003[k\u0006bBAfE\u0001\u0007\u00111\u001d\t\u0004-\u0006\u0015HaBAtE\t\u0007\u0011\u0011\u001e\u0002\u0003\u0003F\n2AWAU\u0011\u001d\tiO\ta\u0001\u0003_\fq\u0001Z3gCVdG\u000f\u0005\u0004P\'\u0006\r\u0018\u0011\\\u0001\u0007_J,En]3\u0016\r\u0005U\u00181`A\u0000)\u0011\t9P!\u0001\u0011\u000f\u0005EA$!?\u0002~B\u0019a+a?\u0005\u000f\u0005\u001d8E1\u0001\u0002jB\u0019a+a@\u0005\u000f\u0005u7E1\u0001\u0002`\"9!1A\u0012A\u0002\t\u0015\u0011\u0001\u0002;iCR\u0004ba\u0014\u0001\u0002z\u0006u\u0018aB1oIRCWM\\\u000b\u0005\u0005\u0017\u0011\t\u0002\u0006\u0003\u0003\u000e\tU\u0001cBA\t9\u0005%&q\u0002\t\u0004-\nEAA\u0002B\nI\t\u0007\u0011LA\u0001D\u0011\u001d\u00119\u0002\na\u0001\u00053\t\u0011a\u001b\t\u0007\u001fN\u000biKa\u0004\u0003\u000f\u0005sG\r\u00165f]VA!q\u0004B\u0013\u0005_\u0011Ic\u0005\u0004&\u001d\n\u0005\u0012\u0011\u0017\t\u0007\u001f\u0002\u0011\u0019Ca\n\u0011\u0007Y\u0013)\u0003\u0002\u0004YK!\u0015\r!\u0017\t\u0004-\n%Ba\u0002B\nK\u0011\u0015\r!\u0017\t\u0007\u001f\u0002\u0011\u0019C!\f\u0011\u0007Y\u0013y\u0003B\u0003cK\t\u0007\u0011\f\u0005\u0004P\'\n5\"q\u0005\u000b\u0007\u0005k\u00119D!\u000f\u0011\u0013\u0005EQEa\t\u0003.\t\u001d\u0002bBA\u000bQ\u0001\u0007!1\u0006\u0005\b\u0005/A\u0003\u0019\u0001B\u0019)\u0011\tyD!\u0010\t\u000f\u0005-\u0017\u00061\u0001\u0003$Q!!q\u0005B!\u0011\u001d\tYM\u000ba\u0001\u0005G)bA!\u0012\u0003T\t%CC\u0002B$\u0005\u001f\u00129\u0006E\u0002W\u0005\u0013\"qAa\u0013,\u0005\u0004\u0011iE\u0001\u0002DcE\u0019!qE/\t\u000f\u0005-7\u00061\u0001\u0003RA\u0019aKa\u0015\u0005\u000f\u0005\u001d8F1\u0001\u0003VE\u0019!La\t\t\u000f\u000558\u00061\u0001\u0003ZA1qj\u0015B)\u0005\u000f\u0012\u0001bQ8nE&tW\rZ\u000b\t\u0005?\u0012)Ga\u001c\u0003jM1AF\u0014B1\u0003c\u0003ba\u0014\u0001\u0003d\t\u001d\u0004c\u0001,\u0003f\u00111\u0001\f\fEC\u0002e\u00032A\u0016B5\t\u001d\u0011\u0019\u0002\fCC\u0002e\u0003ba\u0014\u0001\u0003d\t5\u0004c\u0001,\u0003p\u0011)!\r\fb\u00013B1q\n\u0001B7\u0005O\"bA!\u001e\u0003x\te\u0004#CA\tY\t\r$Q\u000eB4\u0011\u001d\t)b\fa\u0001\u0005WBqAa\u00060\u0001\u0004\u0011\t\b\u0006\u0003\u0002@\tu\u0004bBAfa\u0001\u0007!1\r\u000b\u0005\u0005O\u0012\t\tC\u0004\u0002LF\u0002\rAa\u0019\u0016\r\t\u0015%\u0011\u0013BE)\u0019\u00119I!$\u0003\u0016B\u0019aK!#\u0005\u000f\t-#G1\u0001\u0003\fF\u0019!qM/\t\u000f\u0005-\'\u00071\u0001\u0003\u0010B\u0019aK!%\u0005\u000f\u0005\u001d(G1\u0001\u0003\u0014F\u0019!La\u0019\t\u000f\u00055(\u00071\u0001\u0003\u0018B1qj\u0015BH\u0005\u000f\u000b1BZ1mY\n\f7m[0g]B!qjU/^\u00035\u0019\u0007.Z2l\r\u0006dGNY1dWV!!\u0011\u0015BT+\t\u0011\u0019\u000bE\u0003P\'v\u0013)\u000bE\u0002W\u0005O#QA\u0019\u001bC\u0002e\u000b\u0001CZ1mY\n\f7m[(dGV\u0014(/\u001a3\u0016\t\t5&1\u0017\u000b\u0005\u0003\u007f\u0011y\u000bC\u0004\u0002LV\u0002\rA!-\u0011\u0007Y\u0013\u0019\fB\u0003ck\t\u0007\u0011L\u0001\u0004MS\u001a$X\rZ\u000b\u0007\u0005s\u0013\u0019M!3\u0014\u000bY\u0012Y,!-\u0011\u0011\u0005}%Q\u0018Ba\u0005\u000bLAAa0\u0002\"\n\t\u0012IY:ue\u0006\u001cGOR;oGRLwN\\\u0019\u0011\u0007Y\u0013\u0019\r\u0002\u0004Ym!\u0015\r!\u0017\t\u0005\u001f.\u00149\rE\u0002W\u0005\u0013$aA\u0019\u001c\u0005\u0006\u0004IVC\u0001Bg!\u0019y\u0005A!1\u0003H\u0006\u0019\u0001O\u001a\u0011\u0015\t\tM\'Q\u001b\t\b\u0003#1$\u0011\u0019Bd\u0011\u001d\t)\"\u000fa\u0001\u0005\u001b$BA!2\u0003Z\"9\u00111\u001a\u001eA\u0002\t\u0005\'\u0001C+oY&4G/\u001a3\u0016\r\t}\'Q\u001dBu\'\u0015Y$\u0011]AY!!\ty*!*\u0003d\n\u001d\bc\u0001,\u0003f\u0012)\u0001l\u000fb\u00013B\u0019aK!;\u0005\u000b\t\\$\u0019A-\u0002\u0003\u0019\u0004baT*\u0003d\n=\b\u0003B(l\u0005O$BAa=\u0003vB9\u0011\u0011C\u001e\u0003d\n\u001d\bb\u0002Bv{\u0001\u0007!Q\u001e\u000b\u0005\u0003\u007f\u0011I\u0010C\u0004\u0002Lz\u0002\rAa9\u0016\r\tu8\u0011BB\u0001)\u0019\u0011yp!\u0002\u0004\u000eA\u0019ak!\u0001\u0005\u000f\u0005uwH1\u0001\u0004\u0004E\u0019!q]/\t\u000f\u0005-w\b1\u0001\u0004\bA\u0019ak!\u0003\u0005\u000f\u0005\u001dxH1\u0001\u0004\fE\u0019!La9\t\u000f\u00055x\b1\u0001\u0004\u0010A1qjUB\u0004\u0005\u007f\fA\u0001\\5giV\u0011!Q^\u0001\tk:d\u0017N\u001a;fIV11\u0011DB\u0010\u0007G!Baa\u0007\u0004&A1q\nAB\u000f\u0007C\u00012AVB\u0010\t\u0015A\u0016I1\u0001Z!\r161\u0005\u0003\u0006E\u0006\u0013\r!\u0017\u0005\b\u0005W\f\u0005\u0019AB\u0014!\u0019y5k!\b\u0004*A!qj[B\u0011\u000311\'o\\7Gk:\u001cG/[8o+\u0019\u0019yc!\u000e\u0004:Q!1\u0011GB\u001e!\u0019y\u0005aa\r\u00048A\u0019ak!\u000e\u0005\u000ba\u0013%\u0019A-\u0011\u0007Y\u001bI\u0004B\u0003c\u0005\n\u0007\u0011\fC\u0004\u0003l\n\u0003\ra!\u0010\u0011\r=\u001b61GB\u001c\u0003)\u0019wN\\:u\r\u0006d7/\u001a\t\u0006\u001fNk\u0016qH\u0001\tK6\u0004H/_0qMB!q\nA/[\u0003\u0015)W\u000e\u001d;z+\u0019\u0019Ye!\u0015\u0004VU\u00111Q\n\t\u0007\u001f\u0002\u0019yea\u0015\u0011\u0007Y\u001b\t\u0006B\u0003Y\u000b\n\u0007\u0011\fE\u0002W\u0007+\"QAY#C\u0002e\u000bAaY8oIV!11LB3)\u0011\u0019ifa\u001a\u0015\t\u0005}2q\f\u0005\b\u0003+1\u0005\u0019AB1!\u0019y\u0005aa\u0019\u0002@A\u0019ak!\u001a\u0005\u000ba3%\u0019A-\t\u000f\u0005-g\t1\u0001\u0004d\u000591m\u001c8e\u001fB$XCBB7\u0007{\u001a)\b\u0006\u0003\u0004p\r}D\u0003BB9\u0007o\u0002BaT6\u0004tA\u0019ak!\u001e\u0005\u000b\t<%\u0019A-\t\u000f\u0005Uq\t1\u0001\u0004zA1q\nAB>\u0007g\u00022AVB?\t\u0015AvI1\u0001Z\u0011\u001d\tYm\u0012a\u0001\u0007w\"B!a\u0010\u0004\u0004\"1\u00111\u001a\u0003A\u0002U+baa\"\u0004\u000e\u000eME\u0003BBE\u0007/\u0003ba\u0014\u0001\u0004\f\u000eE\u0005c\u0001,\u0004\u000e\u00129\u0011q]\u0003C\u0002\r=\u0015C\u0001.V!\r161\u0013\u0003\b\u0003;,!\u0019ABK#\t\u0001W\fC\u0004\u0003\u0004\u0015\u0001\ra!#\u0016\t\rm5\u0011\u0015\u000b\u0005\u0007;\u001b\u0019\u000bE\u0003P\u0001U\u001by\nE\u0002W\u0007C#aAa\u0005\u0007\u0005\u0004I\u0006b\u0002B\f\r\u0001\u00071Q\u0015\t\u0006\u001fN\u00037qT\u000b\u0005\u0007S\u001by\u000b\u0006\u0003\u0004,\u000eE\u0006#B(\u0001+\u000e5\u0006c\u0001,\u00040\u00121!1C\u0004C\u0002eCqAa\u0006\b\u0001\u0004\u0019\u0019\fE\u0003P\u0001\u0001\u001ci+A\u0004d_6\u0004xn]3\u0016\t\re6q\u0018\u000b\u0005\u0007w\u001b\u0019\rE\u0003P\u0001\ru\u0006\rE\u0002W\u0007\u007f#aa!1\t\u0005\u0004I&!\u0001*\t\u000f\t]\u0001\u00021\u0001\u0004FB)q\nAB_+V\u00111\u0011\u001a\t\u0005\u001fN+&.\u0006\u0004\u0004N\u000e]7\u0011\u001b\u000b\u0007\u0007\u001f\u001c\u0019n!7\u0011\u0007Y\u001b\t\u000eB\u0004\u0002^*\u0011\ra!&\t\u000f\u0005-\'\u00021\u0001\u0004VB\u0019aka6\u0005\u000f\u0005\u001d(B1\u0001\u0004\u0010\"9\u0011Q\u001e\u0006A\u0002\rm\u0007CB(T\u0007+\u001cy-A\u0004sk:<\u0016\u000e\u001e5\u0016\t\r\u00058Q\u001e\u000b\u0005\u0007G\u001c)\u000fE\u0003P\'V\u000by\u0004C\u0004\u0004h.\u0001\ra!;\u0002\r\u0005\u001cG/[8o!\u0015y5\u000bYBv!\r16Q\u001e\u0003\u0007\u0007_\\!\u0019A-\u0003\u0003U\u0003
   #12 = Utf8               java/lang/invoke/MethodHandles$Lookup
   #13 = Class              #12           // java/lang/invoke/MethodHandles$Lookup
   #14 = Utf8               java/lang/invoke/MethodHandles
   #15 = Class              #14           // java/lang/invoke/MethodHandles
   #16 = Utf8               Lookup
   #17 = Utf8               scala/PartialFunction$$anonfun$fromFunction$1
   #18 = Class              #17           // scala/PartialFunction$$anonfun$fromFunction$1
   #19 = Utf8               scala/PartialFunction$AndThen
   #20 = Class              #19           // scala/PartialFunction$AndThen
   #21 = Utf8               AndThen
   #22 = Utf8               scala/PartialFunction$Combined
   #23 = Class              #22           // scala/PartialFunction$Combined
   #24 = Utf8               Combined
   #25 = Utf8               scala/PartialFunction$ElementWiseExtractor
   #26 = Class              #25           // scala/PartialFunction$ElementWiseExtractor
   #27 = Utf8               ElementWiseExtractor
   #28 = Utf8               scala/PartialFunction$ElementWiseExtractor$
   #29 = Class              #28           // scala/PartialFunction$ElementWiseExtractor$
   #30 = Utf8               ElementWiseExtractor$
   #31 = Utf8               scala/PartialFunction$Lifted
   #32 = Class              #31           // scala/PartialFunction$Lifted
   #33 = Utf8               Lifted
   #34 = Utf8               scala/PartialFunction$OrElse
   #35 = Class              #34           // scala/PartialFunction$OrElse
   #36 = Utf8               OrElse
   #37 = Utf8               scala/PartialFunction$Unlifted
   #38 = Class              #37           // scala/PartialFunction$Unlifted
   #39 = Utf8               Unlifted
   #40 = Utf8               condOpt
   #41 = Utf8               (Ljava/lang/Object;Lscala/PartialFunction;)Lscala/Option;
   #42 = Utf8               <A:Ljava/lang/Object;B:Ljava/lang/Object;>(TA;Lscala/PartialFunction<TA;TB;>;)Lscala/Option<TB;>;
   #43 = Utf8               x
   #44 = Utf8               pf
   #45 = Utf8               scala/PartialFunction$
   #46 = Class              #45           // scala/PartialFunction$
   #47 = Utf8               MODULE$
   #48 = Utf8               Lscala/PartialFunction$;
   #49 = NameAndType        #47:#48       // MODULE$:Lscala/PartialFunction$;
   #50 = Fieldref           #46.#49       // scala/PartialFunction$.MODULE$:Lscala/PartialFunction$;
   #51 = NameAndType        #40:#41       // condOpt:(Ljava/lang/Object;Lscala/PartialFunction;)Lscala/Option;
   #52 = Methodref          #46.#51       // scala/PartialFunction$.condOpt:(Ljava/lang/Object;Lscala/PartialFunction;)Lscala/Option;
   #53 = Utf8               Ljava/lang/Object;
   #54 = Utf8               Lscala/PartialFunction;
   #55 = Utf8               cond
   #56 = Utf8               (Ljava/lang/Object;Lscala/PartialFunction;)Z
   #57 = Utf8               <A:Ljava/lang/Object;>(TA;Lscala/PartialFunction<TA;Ljava/lang/Object;>;)Z
   #58 = NameAndType        #55:#56       // cond:(Ljava/lang/Object;Lscala/PartialFunction;)Z
   #59 = Methodref          #46.#58       // scala/PartialFunction$.cond:(Ljava/lang/Object;Lscala/PartialFunction;)Z
   #60 = Utf8               empty
   #61 = Utf8               ()Lscala/PartialFunction;
   #62 = Utf8               <A:Ljava/lang/Object;B:Ljava/lang/Object;>()Lscala/PartialFunction<TA;TB;>;
   #63 = NameAndType        #60:#61       // empty:()Lscala/PartialFunction;
   #64 = Methodref          #46.#63       // scala/PartialFunction$.empty:()Lscala/PartialFunction;
   #65 = Utf8               fromFunction
   #66 = Utf8               (Lscala/Function1;)Lscala/PartialFunction;
   #67 = Utf8               <A:Ljava/lang/Object;B:Ljava/lang/Object;>(Lscala/Function1<TA;TB;>;)Lscala/PartialFunction<TA;TB;>;
   #68 = Utf8               f
   #69 = Utf8               <init>
   #70 = Utf8               (Lscala/Function1;)V
   #71 = NameAndType        #69:#70       // "<init>":(Lscala/Function1;)V
   #72 = Methodref          #18.#71       // scala/PartialFunction$$anonfun$fromFunction$1."<init>":(Lscala/Function1;)V
   #73 = Utf8               Lscala/Function1;
   #74 = Utf8               unapply$
   #75 = Utf8               (Lscala/PartialFunction;Ljava/lang/Object;)Lscala/Option;
   #76 = Utf8               $this
   #77 = Utf8               a
   #78 = Utf8               unapply
   #79 = Utf8               (Ljava/lang/Object;)Lscala/Option;
   #80 = NameAndType        #78:#79       // unapply:(Ljava/lang/Object;)Lscala/Option;
   #81 = InterfaceMethodref #2.#80        // scala/PartialFunction.unapply:(Ljava/lang/Object;)Lscala/Option;
   #82 = Utf8               (TA;)Lscala/Option<TB;>;
   #83 = Utf8               lift
   #84 = Utf8               ()Lscala/Function1;
   #85 = NameAndType        #83:#84       // lift:()Lscala/Function1;
   #86 = InterfaceMethodref #2.#85        // scala/PartialFunction.lift:()Lscala/Function1;
   #87 = Utf8               apply
   #88 = Utf8               (Ljava/lang/Object;)Ljava/lang/Object;
   #89 = NameAndType        #87:#88       // apply:(Ljava/lang/Object;)Ljava/lang/Object;
   #90 = InterfaceMethodref #7.#89        // scala/Function1.apply:(Ljava/lang/Object;)Ljava/lang/Object;
   #91 = Utf8               scala/Option
   #92 = Class              #91           // scala/Option
   #93 = Utf8               this
   #94 = Utf8               elementWise$
   #95 = Utf8               (Lscala/PartialFunction;)Lscala/PartialFunction;
   #96 = Utf8               elementWise
   #97 = NameAndType        #96:#61       // elementWise:()Lscala/PartialFunction;
   #98 = InterfaceMethodref #2.#97        // scala/PartialFunction.elementWise:()Lscala/PartialFunction;
   #99 = Utf8               ()Lscala/PartialFunction<TA;TB;>;
  #100 = Utf8               isDefinedAt
  #101 = Utf8               (Ljava/lang/Object;)Z
  #102 = Utf8               (TA;)Z
  #103 = Utf8               orElse$
  #104 = Utf8               (Lscala/PartialFunction;Lscala/PartialFunction;)Lscala/PartialFunction;
  #105 = Utf8               that
  #106 = Utf8               orElse
  #107 = NameAndType        #106:#95      // orElse:(Lscala/PartialFunction;)Lscala/PartialFunction;
  #108 = InterfaceMethodref #2.#107       // scala/PartialFunction.orElse:(Lscala/PartialFunction;)Lscala/PartialFunction;
  #109 = Utf8               <A1:TA;B1:Ljava/lang/Object;>(Lscala/PartialFunction<TA1;TB1;>;)Lscala/PartialFunction<TA1;TB1;>;
  #110 = Utf8               (Lscala/PartialFunction;Lscala/PartialFunction;)V
  #111 = NameAndType        #69:#110      // "<init>":(Lscala/PartialFunction;Lscala/PartialFunction;)V
  #112 = Methodref          #35.#111      // scala/PartialFunction$OrElse."<init>":(Lscala/PartialFunction;Lscala/PartialFunction;)V
  #113 = Utf8               andThen$
  #114 = Utf8               (Lscala/PartialFunction;Lscala/Function1;)Lscala/PartialFunction;
  #115 = Utf8               k
  #116 = Utf8               andThen
  #117 = NameAndType        #116:#66      // andThen:(Lscala/Function1;)Lscala/PartialFunction;
  #118 = InterfaceMethodref #2.#117       // scala/PartialFunction.andThen:(Lscala/Function1;)Lscala/PartialFunction;
  #119 = Utf8               <C$:Ljava/lang/Object;>(Lscala/Function1<TB;TC$;>;)Lscala/PartialFunction<TA;TC$;>;
  #120 = NameAndType        #116:#95      // andThen:(Lscala/PartialFunction;)Lscala/PartialFunction;
  #121 = InterfaceMethodref #2.#120       // scala/PartialFunction.andThen:(Lscala/PartialFunction;)Lscala/PartialFunction;
  #122 = Utf8               (Lscala/PartialFunction;Lscala/Function1;)V
  #123 = NameAndType        #69:#122      // "<init>":(Lscala/PartialFunction;Lscala/Function1;)V
  #124 = Methodref          #20.#123      // scala/PartialFunction$AndThen."<init>":(Lscala/PartialFunction;Lscala/Function1;)V
  #125 = Utf8               <C$:Ljava/lang/Object;>(Lscala/PartialFunction<TB;TC$;>;)Lscala/PartialFunction<TA;TC$;>;
  #126 = Methodref          #23.#111      // scala/PartialFunction$Combined."<init>":(Lscala/PartialFunction;Lscala/PartialFunction;)V
  #127 = Utf8               compose$
  #128 = Utf8               compose
  #129 = NameAndType        #128:#95      // compose:(Lscala/PartialFunction;)Lscala/PartialFunction;
  #130 = InterfaceMethodref #2.#129       // scala/PartialFunction.compose:(Lscala/PartialFunction;)Lscala/PartialFunction;
  #131 = Utf8               <R$:Ljava/lang/Object;>(Lscala/PartialFunction<TR$;TA;>;)Lscala/PartialFunction<TR$;TB;>;
  #132 = Utf8               lift$
  #133 = Utf8               (Lscala/PartialFunction;)Lscala/Function1;
  #134 = Utf8               ()Lscala/Function1<TA;Lscala/Option<TB;>;>;
  #135 = Utf8               (Lscala/PartialFunction;)V
  #136 = NameAndType        #69:#135      // "<init>":(Lscala/PartialFunction;)V
  #137 = Methodref          #32.#136      // scala/PartialFunction$Lifted."<init>":(Lscala/PartialFunction;)V
  #138 = Utf8               applyOrElse$
  #139 = Utf8               (Lscala/PartialFunction;Ljava/lang/Object;Lscala/Function1;)Ljava/lang/Object;
  #140 = Utf8               default
  #141 = Utf8               applyOrElse
  #142 = Utf8               (Ljava/lang/Object;Lscala/Function1;)Ljava/lang/Object;
  #143 = NameAndType        #141:#142     // applyOrElse:(Ljava/lang/Object;Lscala/Function1;)Ljava/lang/Object;
  #144 = InterfaceMethodref #2.#143       // scala/PartialFunction.applyOrElse:(Ljava/lang/Object;Lscala/Function1;)Ljava/lang/Object;
  #145 = Utf8               <A1:TA;B1:Ljava/lang/Object;>(TA1;Lscala/Function1<TA1;TB1;>;)TB1;
  #146 = NameAndType        #100:#101     // isDefinedAt:(Ljava/lang/Object;)Z
  #147 = InterfaceMethodref #2.#146       // scala/PartialFunction.isDefinedAt:(Ljava/lang/Object;)Z
  #148 = InterfaceMethodref #2.#89        // scala/PartialFunction.apply:(Ljava/lang/Object;)Ljava/lang/Object;
  #149 = Utf8               runWith$
  #150 = Utf8               (Lscala/PartialFunction;Lscala/Function1;)Lscala/Function1;
  #151 = Utf8               action
  #152 = Utf8               runWith
  #153 = Utf8               (Lscala/Function1;)Lscala/Function1;
  #154 = NameAndType        #152:#153     // runWith:(Lscala/Function1;)Lscala/Function1;
  #155 = InterfaceMethodref #2.#154       // scala/PartialFunction.runWith:(Lscala/Function1;)Lscala/Function1;
  #156 = Utf8               <U:Ljava/lang/Object;>(Lscala/Function1<TB;TU;>;)Lscala/Function1<TA;Ljava/lang/Object;>;
  #157 = MethodType         #88           //  (Ljava/lang/Object;)Ljava/lang/Object;
  #158 = Utf8               $anonfun$runWith$1$adapted
  #159 = Utf8               (Lscala/PartialFunction;Lscala/Function1;Ljava/lang/Object;)Ljava/lang/Object;
  #160 = NameAndType        #158:#159     // $anonfun$runWith$1$adapted:(Lscala/PartialFunction;Lscala/Function1;Ljava/lang/Object;)Ljava/lang/Object;
  #161 = InterfaceMethodref #2.#160       // scala/PartialFunction.$anonfun$runWith$1$adapted:(Lscala/PartialFunction;Lscala/Function1;Ljava/lang/Object;)Ljava/lang/Object;
  #162 = MethodHandle       6:#161        // REF_invokeStatic scala/PartialFunction.$anonfun$runWith$1$adapted:(Lscala/PartialFunction;Lscala/Function1;Ljava/lang/Object;)Ljava/lang/Object;
  #163 = Integer            1
  #164 = Utf8               java/lang/invoke/LambdaMetafactory
  #165 = Class              #164          // java/lang/invoke/LambdaMetafactory
  #166 = Utf8               altMetafactory
  #167 = Utf8               (Ljava/lang/invoke/MethodHandles$Lookup;Ljava/lang/String;Ljava/lang/invoke/MethodType;[Ljava/lang/Object;)Ljava/lang/invoke/CallSite;
  #168 = NameAndType        #166:#167     // altMetafactory:(Ljava/lang/invoke/MethodHandles$Lookup;Ljava/lang/String;Ljava/lang/invoke/MethodType;[Ljava/lang/Object;)Ljava/lang/invoke/CallSite;
  #169 = Methodref          #165.#168     // java/lang/invoke/LambdaMetafactory.altMetafactory:(Ljava/lang/invoke/MethodHandles$Lookup;Ljava/lang/String;Ljava/lang/invoke/MethodType;[Ljava/lang/Object;)Ljava/lang/invoke/CallSite;
  #170 = MethodHandle       6:#169        // REF_invokeStatic java/lang/invoke/LambdaMetafactory.altMetafactory:(Ljava/lang/invoke/MethodHandles$Lookup;Ljava/lang/String;Ljava/lang/invoke/MethodType;[Ljava/lang/Object;)Ljava/lang/invoke/CallSite;
  #171 = NameAndType        #87:#150      // apply:(Lscala/PartialFunction;Lscala/Function1;)Lscala/Function1;
  #172 = InvokeDynamic      #0:#171       // #0:apply:(Lscala/PartialFunction;Lscala/Function1;)Lscala/Function1;
  #173 = Utf8               $anonfun$runWith$1
  #174 = Utf8               (Lscala/PartialFunction;Lscala/Function1;Ljava/lang/Object;)Z
  #175 = Utf8               action$1
  #176 = Utf8               scala$PartialFunction$$checkFallback
  #177 = NameAndType        #176:#84      // scala$PartialFunction$$checkFallback:()Lscala/Function1;
  #178 = Methodref          #46.#177      // scala/PartialFunction$.scala$PartialFunction$$checkFallback:()Lscala/Function1;
  #179 = Utf8               scala$PartialFunction$$fallbackOccurred
  #180 = NameAndType        #179:#101     // scala$PartialFunction$$fallbackOccurred:(Ljava/lang/Object;)Z
  #181 = Methodref          #46.#180      // scala/PartialFunction$.scala$PartialFunction$$fallbackOccurred:(Ljava/lang/Object;)Z
  #182 = Utf8               z
  #183 = Utf8               $init$
  #184 = NameAndType        #173:#174     // $anonfun$runWith$1:(Lscala/PartialFunction;Lscala/Function1;Ljava/lang/Object;)Z
  #185 = InterfaceMethodref #2.#184       // scala/PartialFunction.$anonfun$runWith$1:(Lscala/PartialFunction;Lscala/Function1;Ljava/lang/Object;)Z
  #186 = Utf8               scala/runtime/BoxesRunTime
  #187 = Class              #186          // scala/runtime/BoxesRunTime
  #188 = Utf8               boxToBoolean
  #189 = Utf8               (Z)Ljava/lang/Boolean;
  #190 = NameAndType        #188:#189     // boxToBoolean:(Z)Ljava/lang/Boolean;
  #191 = Methodref          #187.#190     // scala/runtime/BoxesRunTime.boxToBoolean:(Z)Ljava/lang/Boolean;
  #192 = Utf8               $deserializeLambda$
  #193 = Utf8               (Ljava/lang/invoke/SerializedLambda;)Ljava/lang/Object;
  #194 = Utf8               scala/runtime/LambdaDeserialize
  #195 = Class              #194          // scala/runtime/LambdaDeserialize
  #196 = Utf8               bootstrap
  #197 = Utf8               (Ljava/lang/invoke/MethodHandles$Lookup;Ljava/lang/String;Ljava/lang/invoke/MethodType;[Ljava/lang/invoke/MethodHandle;)Ljava/lang/invoke/CallSite;
  #198 = NameAndType        #196:#197     // bootstrap:(Ljava/lang/invoke/MethodHandles$Lookup;Ljava/lang/String;Ljava/lang/invoke/MethodType;[Ljava/lang/invoke/MethodHandle;)Ljava/lang/invoke/CallSite;
  #199 = Methodref          #195.#198     // scala/runtime/LambdaDeserialize.bootstrap:(Ljava/lang/invoke/MethodHandles$Lookup;Ljava/lang/String;Ljava/lang/invoke/MethodType;[Ljava/lang/invoke/MethodHandle;)Ljava/lang/invoke/CallSite;
  #200 = MethodHandle       6:#199        // REF_invokeStatic scala/runtime/LambdaDeserialize.bootstrap:(Ljava/lang/invoke/MethodHandles$Lookup;Ljava/lang/String;Ljava/lang/invoke/MethodType;[Ljava/lang/invoke/MethodHandle;)Ljava/lang/invoke/CallSite;
  #201 = Utf8               lambdaDeserialize
  #202 = NameAndType        #201:#193     // lambdaDeserialize:(Ljava/lang/invoke/SerializedLambda;)Ljava/lang/Object;
  #203 = InvokeDynamic      #1:#202       // #1:lambdaDeserialize:(Ljava/lang/invoke/SerializedLambda;)Ljava/lang/Object;
  #204 = Utf8               Code
  #205 = Utf8               LocalVariableTable
  #206 = Utf8               Signature
  #207 = Utf8               MethodParameters
  #208 = Utf8               LineNumberTable
  #209 = Utf8               StackMapTable
  #210 = Utf8               InnerClasses
  #211 = Utf8               SourceFile
  #212 = Utf8               RuntimeVisibleAnnotations
  #213 = Utf8               BootstrapMethods
  #214 = Utf8               ScalaInlineInfo
  #215 = Utf8               ScalaSig
{
  public static <A extends java.lang.Object, B extends java.lang.Object> scala.Option<B> condOpt(A, scala.PartialFunction<A, B>);
    descriptor: (Ljava/lang/Object;Lscala/PartialFunction;)Lscala/Option;
    flags: (0x0009) ACC_PUBLIC, ACC_STATIC
    Code:
      stack=3, locals=2, args_size=2
         0: getstatic     #50                 // Field scala/PartialFunction$.MODULE$:Lscala/PartialFunction$;
         3: aload_0
         4: aload_1
         5: invokevirtual #52                 // Method scala/PartialFunction$.condOpt:(Ljava/lang/Object;Lscala/PartialFunction;)Lscala/Option;
         8: areturn
      LocalVariableTable:
        Start  Length  Slot  Name   Signature
            0       9     0     x   Ljava/lang/Object;
            0       9     1    pf   Lscala/PartialFunction;
    Signature: #42                          // <A:Ljava/lang/Object;B:Ljava/lang/Object;>(TA;Lscala/PartialFunction<TA;TB;>;)Lscala/Option<TB;>;
    MethodParameters:
      Name                           Flags
      x                              final
      pf                             final

  public static <A extends java.lang.Object> boolean cond(A, scala.PartialFunction<A, java.lang.Object>);
    descriptor: (Ljava/lang/Object;Lscala/PartialFunction;)Z
    flags: (0x0009) ACC_PUBLIC, ACC_STATIC
    Code:
      stack=3, locals=2, args_size=2
         0: getstatic     #50                 // Field scala/PartialFunction$.MODULE$:Lscala/PartialFunction$;
         3: aload_0
         4: aload_1
         5: invokevirtual #59                 // Method scala/PartialFunction$.cond:(Ljava/lang/Object;Lscala/PartialFunction;)Z
         8: ireturn
      LocalVariableTable:
        Start  Length  Slot  Name   Signature
            0       9     0     x   Ljava/lang/Object;
            0       9     1    pf   Lscala/PartialFunction;
    Signature: #57                          // <A:Ljava/lang/Object;>(TA;Lscala/PartialFunction<TA;Ljava/lang/Object;>;)Z
    MethodParameters:
      Name                           Flags
      x                              final
      pf                             final

  public static <A extends java.lang.Object, B extends java.lang.Object> scala.PartialFunction<A, B> empty();
    descriptor: ()Lscala/PartialFunction;
    flags: (0x0009) ACC_PUBLIC, ACC_STATIC
    Code:
      stack=1, locals=0, args_size=0
         0: getstatic     #50                 // Field scala/PartialFunction$.MODULE$:Lscala/PartialFunction$;
         3: invokevirtual #64                 // Method scala/PartialFunction$.empty:()Lscala/PartialFunction;
         6: areturn
    Signature: #62                          // <A:Ljava/lang/Object;B:Ljava/lang/Object;>()Lscala/PartialFunction<TA;TB;>;

  public static <A extends java.lang.Object, B extends java.lang.Object> scala.PartialFunction<A, B> fromFunction(scala.Function1<A, B>);
    descriptor: (Lscala/Function1;)Lscala/PartialFunction;
    flags: (0x0009) ACC_PUBLIC, ACC_STATIC
    Code:
      stack=3, locals=1, args_size=1
         0: getstatic     #50                 // Field scala/PartialFunction$.MODULE$:Lscala/PartialFunction$;
         3: pop
         4: new           #18                 // class scala/PartialFunction$$anonfun$fromFunction$1
         7: dup
         8: aload_0
         9: invokespecial #72                 // Method scala/PartialFunction$$anonfun$fromFunction$1."<init>":(Lscala/Function1;)V
        12: areturn
      LineNumberTable:
        line 363: 4
      LocalVariableTable:
        Start  Length  Slot  Name   Signature
            0      13     0     f   Lscala/Function1;
    Signature: #67                          // <A:Ljava/lang/Object;B:Ljava/lang/Object;>(Lscala/Function1<TA;TB;>;)Lscala/PartialFunction<TA;TB;>;
    MethodParameters:
      Name                           Flags
      f                              final

  public static scala.Option unapply$(scala.PartialFunction, java.lang.Object);
    descriptor: (Lscala/PartialFunction;Ljava/lang/Object;)Lscala/Option;
    flags: (0x1009) ACC_PUBLIC, ACC_STATIC, ACC_SYNTHETIC
    Code:
      stack=2, locals=2, args_size=2
         0: aload_0
         1: aload_1
         2: invokespecial #81                 // InterfaceMethod unapply:(Ljava/lang/Object;)Lscala/Option;
         5: areturn
      LineNumberTable:
        line 100: 0
      LocalVariableTable:
        Start  Length  Slot  Name   Signature
            0       6     0 $this   Lscala/PartialFunction;
            0       6     1     a   Ljava/lang/Object;
    MethodParameters:
      Name                           Flags
      $this                          final synthetic
      a                              final

  public default scala.Option<B> unapply(A);
    descriptor: (Ljava/lang/Object;)Lscala/Option;
    flags: (0x0001) ACC_PUBLIC
    Code:
      stack=2, locals=2, args_size=2
         0: aload_0
         1: invokeinterface #86,  1           // InterfaceMethod lift:()Lscala/Function1;
         6: aload_1
         7: invokeinterface #90,  2           // InterfaceMethod scala/Function1.apply:(Ljava/lang/Object;)Ljava/lang/Object;
        12: checkcast     #92                 // class scala/Option
        15: areturn
      LineNumberTable:
        line 100: 0
      LocalVariableTable:
        Start  Length  Slot  Name   Signature
            0      16     0  this   Lscala/PartialFunction;
            0      16     1     a   Ljava/lang/Object;
    Signature: #82                          // (TA;)Lscala/Option<TB;>;
    MethodParameters:
      Name                           Flags
      a                              final

  public static scala.PartialFunction elementWise$(scala.PartialFunction);
    descriptor: (Lscala/PartialFunction;)Lscala/PartialFunction;
    flags: (0x1009) ACC_PUBLIC, ACC_STATIC, ACC_SYNTHETIC
    Code:
      stack=1, locals=1, args_size=1
         0: aload_0
         1: invokespecial #98                 // InterfaceMethod elementWise:()Lscala/PartialFunction;
         4: areturn
      LineNumberTable:
        line 113: 0
      LocalVariableTable:
        Start  Length  Slot  Name   Signature
            0       5     0 $this   Lscala/PartialFunction;
    MethodParameters:
      Name                           Flags
      $this                          final synthetic

  public default scala.PartialFunction<A, B> elementWise();
    descriptor: ()Lscala/PartialFunction;
    flags: (0x0001) ACC_PUBLIC
    Code:
      stack=1, locals=1, args_size=1
         0: aload_0
         1: areturn
      LineNumberTable:
        line 113: 0
      LocalVariableTable:
        Start  Length  Slot  Name   Signature
            0       2     0  this   Lscala/PartialFunction;
    Signature: #99                          // ()Lscala/PartialFunction<TA;TB;>;

  public abstract boolean isDefinedAt(A);
    descriptor: (Ljava/lang/Object;)Z
    flags: (0x0401) ACC_PUBLIC, ACC_ABSTRACT
    Signature: #102                         // (TA;)Z
    MethodParameters:
      Name                           Flags
      x                              final

  public static scala.PartialFunction orElse$(scala.PartialFunction, scala.PartialFunction);
    descriptor: (Lscala/PartialFunction;Lscala/PartialFunction;)Lscala/PartialFunction;
    flags: (0x1009) ACC_PUBLIC, ACC_STATIC, ACC_SYNTHETIC
    Code:
      stack=2, locals=2, args_size=2
         0: aload_0
         1: aload_1
         2: invokespecial #108                // InterfaceMethod orElse:(Lscala/PartialFunction;)Lscala/PartialFunction;
         5: areturn
      LineNumberTable:
        line 132: 0
      LocalVariableTable:
        Start  Length  Slot  Name   Signature
            0       6     0 $this   Lscala/PartialFunction;
            0       6     1  that   Lscala/PartialFunction;
    MethodParameters:
      Name                           Flags
      $this                          final synthetic
      that                           final

  public default <A1 extends A, B1 extends java.lang.Object> scala.PartialFunction<A1, B1> orElse(scala.PartialFunction<A1, B1>);
    descriptor: (Lscala/PartialFunction;)Lscala/PartialFunction;
    flags: (0x0001) ACC_PUBLIC
    Code:
      stack=4, locals=2, args_size=2
         0: new           #35                 // class scala/PartialFunction$OrElse
         3: dup
         4: aload_0
         5: aload_1
         6: invokespecial #112                // Method scala/PartialFunction$OrElse."<init>":(Lscala/PartialFunction;Lscala/PartialFunction;)V
         9: areturn
      LineNumberTable:
        line 133: 0
      LocalVariableTable:
        Start  Length  Slot  Name   Signature
            0      10     0  this   Lscala/PartialFunction;
            0      10     1  that   Lscala/PartialFunction;
    Signature: #109                         // <A1:TA;B1:Ljava/lang/Object;>(Lscala/PartialFunction<TA1;TB1;>;)Lscala/PartialFunction<TA1;TB1;>;
    MethodParameters:
      Name                           Flags
      that                           final

  public static scala.PartialFunction andThen$(scala.PartialFunction, scala.Function1);
    descriptor: (Lscala/PartialFunction;Lscala/Function1;)Lscala/PartialFunction;
    flags: (0x1009) ACC_PUBLIC, ACC_STATIC, ACC_SYNTHETIC
    Code:
      stack=2, locals=2, args_size=2
         0: aload_0
         1: aload_1
         2: invokespecial #118                // InterfaceMethod andThen:(Lscala/Function1;)Lscala/PartialFunction;
         5: areturn
      LineNumberTable:
        line 148: 0
      LocalVariableTable:
        Start  Length  Slot  Name   Signature
            0       6     0 $this   Lscala/PartialFunction;
            0       6     1     k   Lscala/Function1;
    MethodParameters:
      Name                           Flags
      $this                          final synthetic
      k                              final

  public default <C$ extends java.lang.Object> scala.PartialFunction<A, C$> andThen(scala.Function1<B, C$>);
    descriptor: (Lscala/Function1;)Lscala/PartialFunction;
    flags: (0x0001) ACC_PUBLIC
    Code:
      stack=4, locals=4, args_size=2
         0: aload_1
         1: instanceof    #2                  // class scala/PartialFunction
         4: ifeq          23
         7: aload_1
         8: checkcast     #2                  // class scala/PartialFunction
        11: astore_3
        12: aload_0
        13: aload_3
        14: invokeinterface #121,  2          // InterfaceMethod andThen:(Lscala/PartialFunction;)Lscala/PartialFunction;
        19: astore_2
        20: goto          33
        23: new           #20                 // class scala/PartialFunction$AndThen
        26: dup
        27: aload_0
        28: aload_1
        29: invokespecial #124                // Method scala/PartialFunction$AndThen."<init>":(Lscala/PartialFunction;Lscala/Function1;)V
        32: astore_2
        33: aload_2
        34: areturn
      StackMapTable: number_of_entries = 2
        frame_type = 23 /* same */
        frame_type = 252 /* append */
          offset_delta = 9
          locals = [ class scala/PartialFunction ]
      LineNumberTable:
        line 149: 0
        line 150: 23
        line 148: 33
      LocalVariableTable:
        Start  Length  Slot  Name   Signature
            0      35     0  this   Lscala/PartialFunction;
            0      35     1     k   Lscala/Function1;
    Signature: #119                         // <C$:Ljava/lang/Object;>(Lscala/Function1<TB;TC$;>;)Lscala/PartialFunction<TA;TC$;>;
    MethodParameters:
      Name                           Flags
      k                              final

  public static scala.PartialFunction andThen$(scala.PartialFunction, scala.PartialFunction);
    descriptor: (Lscala/PartialFunction;Lscala/PartialFunction;)Lscala/PartialFunction;
    flags: (0x1009) ACC_PUBLIC, ACC_STATIC, ACC_SYNTHETIC
    Code:
      stack=2, locals=2, args_size=2
         0: aload_0
         1: aload_1
         2: invokespecial #121                // InterfaceMethod andThen:(Lscala/PartialFunction;)Lscala/PartialFunction;
         5: areturn
      LineNumberTable:
        line 164: 0
      LocalVariableTable:
        Start  Length  Slot  Name   Signature
            0       6     0 $this   Lscala/PartialFunction;
            0       6     1     k   Lscala/PartialFunction;
    MethodParameters:
      Name                           Flags
      $this                          final synthetic
      k                              final

  public default <C$ extends java.lang.Object> scala.PartialFunction<A, C$> andThen(scala.PartialFunction<B, C$>);
    descriptor: (Lscala/PartialFunction;)Lscala/PartialFunction;
    flags: (0x0001) ACC_PUBLIC
    Code:
      stack=4, locals=2, args_size=2
         0: new           #23                 // class scala/PartialFunction$Combined
         3: dup
         4: aload_0
         5: aload_1
         6: invokespecial #126                // Method scala/PartialFunction$Combined."<init>":(Lscala/PartialFunction;Lscala/PartialFunction;)V
         9: areturn
      LineNumberTable:
        line 165: 0
      LocalVariableTable:
        Start  Length  Slot  Name   Signature
            0      10     0  this   Lscala/PartialFunction;
            0      10     1     k   Lscala/PartialFunction;
    Signature: #125                         // <C$:Ljava/lang/Object;>(Lscala/PartialFunction<TB;TC$;>;)Lscala/PartialFunction<TA;TC$;>;
    MethodParameters:
      Name                           Flags
      k                              final

  public static scala.PartialFunction compose$(scala.PartialFunction, scala.PartialFunction);
    descriptor: (Lscala/PartialFunction;Lscala/PartialFunction;)Lscala/PartialFunction;
    flags: (0x1009) ACC_PUBLIC, ACC_STATIC, ACC_SYNTHETIC
    Code:
      stack=2, locals=2, args_size=2
         0: aload_0
         1: aload_1
         2: invokespecial #130                // InterfaceMethod compose:(Lscala/PartialFunction;)Lscala/PartialFunction;
         5: areturn
      LineNumberTable:
        line 178: 0
      LocalVariableTable:
        Start  Length  Slot  Name   Signature
            0       6     0 $this   Lscala/PartialFunction;
            0       6     1     k   Lscala/PartialFunction;
    MethodParameters:
      Name                           Flags
      $this                          final synthetic
      k                              final

  public default <R$ extends java.lang.Object> scala.PartialFunction<R$, B> compose(scala.PartialFunction<R$, A>);
    descriptor: (Lscala/PartialFunction;)Lscala/PartialFunction;
    flags: (0x0001) ACC_PUBLIC
    Code:
      stack=4, locals=2, args_size=2
         0: new           #23                 // class scala/PartialFunction$Combined
         3: dup
         4: aload_1
         5: aload_0
         6: invokespecial #126                // Method scala/PartialFunction$Combined."<init>":(Lscala/PartialFunction;Lscala/PartialFunction;)V
         9: areturn
      LineNumberTable:
        line 179: 0
      LocalVariableTable:
        Start  Length  Slot  Name   Signature
            0      10     0  this   Lscala/PartialFunction;
            0      10     1     k   Lscala/PartialFunction;
    Signature: #131                         // <R$:Ljava/lang/Object;>(Lscala/PartialFunction<TR$;TA;>;)Lscala/PartialFunction<TR$;TB;>;
    MethodParameters:
      Name                           Flags
      k                              final

  public static scala.Function1 lift$(scala.PartialFunction);
    descriptor: (Lscala/PartialFunction;)Lscala/Function1;
    flags: (0x1009) ACC_PUBLIC, ACC_STATIC, ACC_SYNTHETIC
    Code:
      stack=1, locals=1, args_size=1
         0: aload_0
         1: invokespecial #86                 // InterfaceMethod lift:()Lscala/Function1;
         4: areturn
      LineNumberTable:
        line 186: 0
      LocalVariableTable:
        Start  Length  Slot  Name   Signature
            0       5     0 $this   Lscala/PartialFunction;
    MethodParameters:
      Name                           Flags
      $this                          final synthetic

  public default scala.Function1<A, scala.Option<B>> lift();
    descriptor: ()Lscala/Function1;
    flags: (0x0001) ACC_PUBLIC
    Code:
      stack=3, locals=1, args_size=1
         0: new           #32                 // class scala/PartialFunction$Lifted
         3: dup
         4: aload_0
         5: invokespecial #137                // Method scala/PartialFunction$Lifted."<init>":(Lscala/PartialFunction;)V
         8: areturn
      LineNumberTable:
        line 186: 0
      LocalVariableTable:
        Start  Length  Slot  Name   Signature
            0       9     0  this   Lscala/PartialFunction;
    Signature: #134                         // ()Lscala/Function1<TA;Lscala/Option<TB;>;>;

  public static java.lang.Object applyOrElse$(scala.PartialFunction, java.lang.Object, scala.Function1);
    descriptor: (Lscala/PartialFunction;Ljava/lang/Object;Lscala/Function1;)Ljava/lang/Object;
    flags: (0x1009) ACC_PUBLIC, ACC_STATIC, ACC_SYNTHETIC
    Code:
      stack=3, locals=3, args_size=3
         0: aload_0
         1: aload_1
         2: aload_2
         3: invokespecial #144                // InterfaceMethod applyOrElse:(Ljava/lang/Object;Lscala/Function1;)Ljava/lang/Object;
         6: areturn
      LineNumberTable:
        line 213: 0
      LocalVariableTable:
        Start  Length  Slot  Name   Signature
            0       7     0 $this   Lscala/PartialFunction;
            0       7     1     x   Ljava/lang/Object;
            0       7     2 default   Lscala/Function1;
    MethodParameters:
      Name                           Flags
      $this                          final synthetic
      x                              final
      default                        final

  public default <A1 extends A, B1 extends java.lang.Object> B1 applyOrElse(A1, scala.Function1<A1, B1>);
    descriptor: (Ljava/lang/Object;Lscala/Function1;)Ljava/lang/Object;
    flags: (0x0001) ACC_PUBLIC
    Code:
      stack=2, locals=3, args_size=3
         0: aload_0
         1: aload_1
         2: invokeinterface #147,  2          // InterfaceMethod isDefinedAt:(Ljava/lang/Object;)Z
         7: ifeq          18
        10: aload_0
        11: aload_1
        12: invokeinterface #148,  2          // InterfaceMethod apply:(Ljava/lang/Object;)Ljava/lang/Object;
        17: areturn
        18: aload_2
        19: aload_1
        20: invokeinterface #90,  2           // InterfaceMethod scala/Function1.apply:(Ljava/lang/Object;)Ljava/lang/Object;
        25: areturn
      StackMapTable: number_of_entries = 1
        frame_type = 18 /* same */
      LineNumberTable:
        line 214: 0
      LocalVariableTable:
        Start  Length  Slot  Name   Signature
            0      26     0  this   Lscala/PartialFunction;
            0      26     1     x   Ljava/lang/Object;
            0      26     2 default   Lscala/Function1;
    Signature: #145                         // <A1:TA;B1:Ljava/lang/Object;>(TA1;Lscala/Function1<TA1;TB1;>;)TB1;
    MethodParameters:
      Name                           Flags
      x                              final
      default                        final

  public static scala.Function1 runWith$(scala.PartialFunction, scala.Function1);
    descriptor: (Lscala/PartialFunction;Lscala/Function1;)Lscala/Function1;
    flags: (0x1009) ACC_PUBLIC, ACC_STATIC, ACC_SYNTHETIC
    Code:
      stack=2, locals=2, args_size=2
         0: aload_0
         1: aload_1
         2: invokespecial #155                // InterfaceMethod runWith:(Lscala/Function1;)Lscala/Function1;
         5: areturn
      LineNumberTable:
        line 230: 0
      LocalVariableTable:
        Start  Length  Slot  Name   Signature
            0       6     0 $this   Lscala/PartialFunction;
            0       6     1 action   Lscala/Function1;
    MethodParameters:
      Name                           Flags
      $this                          final synthetic
      action                         final

  public default <U extends java.lang.Object> scala.Function1<A, java.lang.Object> runWith(scala.Function1<B, U>);
    descriptor: (Lscala/Function1;)Lscala/Function1;
    flags: (0x0001) ACC_PUBLIC
    Code:
      stack=2, locals=2, args_size=2
         0: aload_0
         1: aload_1
         2: invokedynamic #172,  0            // InvokeDynamic #0:apply:(Lscala/PartialFunction;Lscala/Function1;)Lscala/Function1;
         7: areturn
      LineNumberTable:
        line 230: 0
      LocalVariableTable:
        Start  Length  Slot  Name   Signature
            0       8     0  this   Lscala/PartialFunction;
            0       8     1 action   Lscala/Function1;
    Signature: #156                         // <U:Ljava/lang/Object;>(Lscala/Function1<TB;TU;>;)Lscala/Function1<TA;Ljava/lang/Object;>;
    MethodParameters:
      Name                           Flags
      action                         final

  public static boolean $anonfun$runWith$1(scala.PartialFunction, scala.Function1, java.lang.Object);
    descriptor: (Lscala/PartialFunction;Lscala/Function1;Ljava/lang/Object;)Z
    flags: (0x1009) ACC_PUBLIC, ACC_STATIC, ACC_SYNTHETIC
    Code:
      stack=3, locals=4, args_size=3
         0: aload_0
         1: aload_2
         2: getstatic     #50                 // Field scala/PartialFunction$.MODULE$:Lscala/PartialFunction$;
         5: invokevirtual #178                // Method scala/PartialFunction$.scala$PartialFunction$$checkFallback:()Lscala/Function1;
         8: invokeinterface #144,  3          // InterfaceMethod applyOrElse:(Ljava/lang/Object;Lscala/Function1;)Ljava/lang/Object;
        13: astore_3
        14: getstatic     #50                 // Field scala/PartialFunction$.MODULE$:Lscala/PartialFunction$;
        17: aload_3
        18: invokevirtual #181                // Method scala/PartialFunction$.scala$PartialFunction$$fallbackOccurred:(Ljava/lang/Object;)Z
        21: ifne          34
        24: aload_1
        25: aload_3
        26: invokeinterface #90,  2           // InterfaceMethod scala/Function1.apply:(Ljava/lang/Object;)Ljava/lang/Object;
        31: pop
        32: iconst_1
        33: ireturn
        34: iconst_0
        35: ireturn
      StackMapTable: number_of_entries = 1
        frame_type = 252 /* append */
          offset_delta = 34
          locals = [ class java/lang/Object ]
      LineNumberTable:
        line 231: 0
        line 232: 14
      LocalVariableTable:
        Start  Length  Slot  Name   Signature
           14      21     3     z   Ljava/lang/Object;
            0      36     0 $this   Lscala/PartialFunction;
            0      36     1 action$1   Lscala/Function1;
            0      36     2     x   Ljava/lang/Object;
    MethodParameters:
      Name                           Flags
      $this                          final synthetic
      action$1                       final
      x                              final

  public static void $init$(scala.PartialFunction);
    descriptor: (Lscala/PartialFunction;)V
    flags: (0x0009) ACC_PUBLIC, ACC_STATIC
    Code:
      stack=0, locals=1, args_size=1
         0: return
      LineNumberTable:
        line 96: 0
      LocalVariableTable:
        Start  Length  Slot  Name   Signature
            0       1     0 $this   Lscala/PartialFunction;
    MethodParameters:
      Name                           Flags
      $this                          final synthetic

  public static java.lang.Object $anonfun$runWith$1$adapted(scala.PartialFunction, scala.Function1, java.lang.Object);
    descriptor: (Lscala/PartialFunction;Lscala/Function1;Ljava/lang/Object;)Ljava/lang/Object;
    flags: (0x1009) ACC_PUBLIC, ACC_STATIC, ACC_SYNTHETIC
    Code:
      stack=3, locals=3, args_size=3
         0: aload_0
         1: aload_1
         2: aload_2
         3: invokestatic  #185                // InterfaceMethod $anonfun$runWith$1:(Lscala/PartialFunction;Lscala/Function1;Ljava/lang/Object;)Z
         6: invokestatic  #191                // Method scala/runtime/BoxesRunTime.boxToBoolean:(Z)Ljava/lang/Boolean;
         9: areturn
      LineNumberTable:
        line 230: 0
      LocalVariableTable:
        Start  Length  Slot  Name   Signature
            0      10     0 $this   Lscala/PartialFunction;
            0      10     1 action$1   Lscala/Function1;
            0      10     2     x   Ljava/lang/Object;
    MethodParameters:
      Name                           Flags
      $this                          final
      action$1                       final
      x                              final

  private static java.lang.Object $deserializeLambda$(java.lang.invoke.SerializedLambda);
    descriptor: (Ljava/lang/invoke/SerializedLambda;)Ljava/lang/Object;
    flags: (0x100a) ACC_PRIVATE, ACC_STATIC, ACC_SYNTHETIC
    Code:
      stack=1, locals=1, args_size=1
         0: aload_0
         1: invokedynamic #203,  0            // InvokeDynamic #1:lambdaDeserialize:(Ljava/lang/invoke/SerializedLambda;)Ljava/lang/Object;
         6: areturn
}
InnerClasses:
  public static final #16= #13 of #15;    // Lookup=class java/lang/invoke/MethodHandles$Lookup of class java/lang/invoke/MethodHandles
  public final #18;                       // class scala/PartialFunction$$anonfun$fromFunction$1
  private static #21= #20 of #2;          // AndThen=class scala/PartialFunction$AndThen of class scala/PartialFunction
  private static #24= #23 of #2;          // Combined=class scala/PartialFunction$Combined of class scala/PartialFunction
  public static final #27= #26 of #2;     // ElementWiseExtractor=class scala/PartialFunction$ElementWiseExtractor of class scala/PartialFunction
  public static #30= #29 of #2;           // ElementWiseExtractor$=class scala/PartialFunction$ElementWiseExtractor$ of class scala/PartialFunction
  private static #33= #32 of #2;          // Lifted=class scala/PartialFunction$Lifted of class scala/PartialFunction
  private static #36= #35 of #2;          // OrElse=class scala/PartialFunction$OrElse of class scala/PartialFunction
  private static #39= #38 of #2;          // Unlifted=class scala/PartialFunction$Unlifted of class scala/PartialFunction
Signature: #3                           // <A:Ljava/lang/Object;B:Ljava/lang/Object;>Ljava/lang/Object;Lscala/Function1<TA;TB;>;
SourceFile: "PartialFunction.scala"
RuntimeVisibleAnnotations:
  0: #9(#10=s#11)
    scala.reflect.ScalaSignature(
      bytes="\u0006\u0005\rEha\u0002%J!\u0003\r\t\u0001\u0014\u0005\u0006G\u0002!\t\u0001\u001a\u0005\u0006Q\u0002!\t!\u001b\u0005\u0006_\u0002!\t\u0001\u001d\u0005\b\u0003\u000b\u0004a\u0011ABA\u0011\u001d\t\t\u0010\u0001C\u0001\u0007\u000bCqAa\u0002\u0001\t\u0003\u001aI\nC\u0004\u0003\b\u0001!\taa*\t\u000f\rU\u0006\u0001\"\u0001\u00048\"91\u0011\u0003\u0001\u0005\u0002\r\u001d\u0007bBAj\u0001\u0011\u000511\u001a\u0005\b\u0007;\u0004A\u0011ABp\u000f\u0015\u0019\u0018\n#\u0001u\r\u0015A\u0015\n#\u0001v\u0011\u00151X\u0002\"\u0001x\r\u0011AXBA=\t\u0019y|A\u0011!A\u0003\u0006\u000b\u0007I\u0011B@\t\u0017\u0005-qB!B\u0001B\u0003%\u0011\u0011\u0001\u0005\bm>!\t!DA\u0007\u0011\u001d\t9b\u0004C\u0001\u00033A\u0011\"!\r\u0010\u0003\u0003%\t%a\r\t\u0013\u0005mr\"!A\u0005B\u0005ur!CA%\u001b\u0005\u0005\t\u0012AA&\r!AX\"!A\t\u0002\u00055\u0003B\u0002<\u0018\t\u0003\ty\u0005C\u0004\u0002R]!)!a\u0015\t\u0013\u0005=t#!A\u0005\u0006\u0005E\u0004\"CAA/\u0005\u0005IQAAB\r\u0019\t9*\u0004\u0003\u0002\u001a\"Q\u0011q\u0017\u000f\u0003\u0002\u0003\u0006I!!/\t\u0015\u0005mFD!A!\u0002\u0013\tI\f\u0003\u0004w9\u0011\u0005\u0011Q\u0018\u0005\b\u0003\u000bdB\u0011AAd\u0011\u001d\ti\r\bC!\u0003\u001fDq!a5\u001d\t\u0003\n)\u000eC\u0004\u0002rr!\t%a=\t\u000f\t\u001dA\u0004\"\u0011\u0003\n\u00191!1D\u0007\u0005\u0005;A!\"!\u0006&\u0005\u0003\u0005\u000b\u0011\u0002B\u0016\u0011)\u00119\"\nB\u0001B\u0003%!\u0011\u0007\u0005\u0007m\u0016\"\tAa\r\t\u000f\u0005\u0015W\u0005\"\u0001\u0003<!9\u0011QZ\u0013\u0005\u0002\t}\u0002bBAjK\u0011\u0005#1\t\u0004\u0007\u00057jAA!\u0018\t\u0015\u0005UAF!A!\u0002\u0013\u0011Y\u0007\u0003\u0006\u0003\u00181\u0012\t\u0011)A\u0005\u0005cBaA\u001e\u0017\u0005\u0002\tM\u0004bBAcY\u0011\u0005!1\u0010\u0005\b\u0003\u001bdC\u0011\u0001B@\u0011\u001d\t\u0019\u000e\fC!\u0005\u0007C\u0001B!\'\u000eA\u0003%!1\u0014\u0005\b\u0005;kA\u0011\u0002BP\u0011\u001d\u0011I+\u0004C\u0005\u0005W3aA!.\u000e\t\t]\u0006BCA\u000bm\t\u0015\r\u0011\"\u0001\u0003L\"Q!q\u001a\u001c\u0003\u0002\u0003\u0006IA!4\t\rY4D\u0011\u0001Bi\u0011\u001d\tiM\u000eC\u0001\u0005/4aAa7\u000e\t\tu\u0007B\u0003Bvw\t\u0005\t\u0015!\u0003\u0003n\"1ao\u000fC\u0001\u0005cDq!!2<\t\u0003\u00119\u0010C\u0004\u0002Tn\"\tEa?\t\u000f\rE1\b\"\u0011\u0004\u0014!A1QC\u0007\u0005\u0002%\u001b9\u0002C\u0004\u0004,5!\ta!\f\t\u0011\r}R\u0002)A\u0005\u0007\u0003B\u0001ba\u0011\u000eA\u0003%1Q\t\u0005\b\u0007\u000fjA\u0011AB%\u0011\u001d\u00199&\u0004C\u0001\u00073Bqa!\u001b\u000e\t\u0003\u0019YGA\bQCJ$\u0018.\u00197Gk:\u001cG/[8o\u0015\u0005Q\u0015!B:dC2\f7\u0001A\u000b\u0004\u001b^\u000b7c\u0001\u0001O%B\u0011q\nU\u0007\u0002\u0013&\u0011\u0011+\u0013\u0002\u0007\u0003:L(+\u001a4\u0011\t=\u001bV\u000bY\u0005\u0003)&\u0013\u0011BR;oGRLwN\\\u0019\u0011\u0005Y;F\u0002\u0001\u0003\u00071\u0002A)\u0019A-\u0003\u0003\u0005\u000b\"AW/\u0011\u0005=[\u0016B\u0001/J\u0005\u001dqu\u000e\u001e5j]\u001e\u0004\"a\u00140\n\u0005}K%aA!osB\u0011a+\u0019\u0003\u0007E\u0002!)\u0019A-\u0003\u0003\t\u000ba\u0001J5oSR$C#A3\u0011\u0005=3\u0017BA4J\u0005\u0011)f.\u001b;\u0002\u000fUt\u0017\r\u001d9msR\u0011!.\u001c\t\u0004\u001f.\u0004\u0017B\u00017J\u0005\u0019y\u0005\u000f^5p]\")aN\u0001a\u0001+\u0006\t\u0011-A\u0006fY\u0016lWM\u001c;XSN,W#A9\u0011\tI|Q\u000b\u0019\b\u0003\u001f2\tq\u0002U1si&\fGNR;oGRLwN\u001c\t\u0003\u001f6\u0019\"!\u0004(\u0002\rqJg.\u001b;?)\u0005!(\u0001F#mK6,g\u000e^,jg\u0016,\u0005\u0010\u001e:bGR|\'/F\u0003{\u0003\u000b\tIa\u0005\u0002\u0010wB\u0011q\n`\u0005\u0003{&\u0013a!\u00118z-\u0006d\u0017AL:dC2\fG\u0005U1si&\fGNR;oGRLwN\u001c\u0013FY\u0016lWM\u001c;XSN,W\t\u001f;sC\u000e$xN\u001d\u0013%a\u001a,\"!!\u0001\u0011\r=\u0003\u00111AA\u0004!\r1\u0016Q\u0001\u0003\u00071>A)\u0019A-\u0011\u0007Y\u000bI\u0001\u0002\u0004c\u001f\u0011\u0015\r!W\u00010g\u000e\fG.\u0019\u0013QCJ$\u0018.\u00197Gk:\u001cG/[8oI\u0015cW-\\3oi^K7/Z#yiJ\f7\r^8sI\u0011\u0002h\r\t\u000b\u0005\u0003\u001f\t\u0019\u0002E\u0004\u0002\u0012=\t\u0019!a\u0002\u000e\u00035Aq!!\u0006\u0013\u0001\u0004\t\t!\u0001\u0002qM\u0006QQO\\1qa2L8+Z9\u0015\t\u0005m\u00111\u0006\t\u0005\u001f.\fi\u0002\u0005\u0004\u0002 \u0005\u0015\u0012q\u0001\b\u0004\u001f\u0006\u0005\u0012bAA\u0012\u0013\u00069\u0001/Y2lC\u001e,\u0017\u0002BA\u0014\u0003S\u00111aU3r\u0015\r\t\u0019#\u0013\u0005\b\u0003[\u0019\u0002\u0019AA\u0018\u0003\r\u0019X-\u001d\t\u0007\u0003?\t)#a\u0001\u0002\u0011!\f7\u000f[\"pI\u0016$\"!!\u000e\u0011\u0007=\u000b9$C\u0002\u0002:%\u00131!\u00138u\u0003\u0019)\u0017/^1mgR!\u0011qHA#!\ry\u0015\u0011I\u0005\u0004\u0003\u0007J%a\u0002\"p_2,\u0017M\u001c\u0005\t\u0003\u000f*\u0012\u0011!a\u0001;\u0006\u0019\u0001\u0010J\u0019\u0002)\u0015cW-\\3oi^K7/Z#yiJ\f7\r^8s!\r\t\tbF\n\u0003/9#\"!a\u0013\u0002)Ut\u0017\r\u001d9msN+\u0017\u000fJ3yi\u0016t7/[8o+\u0019\t)&a\u001a\u0002`Q!\u0011qKA5)\u0011\tI&!\u0019\u0011\t=[\u00171\f\t\u0007\u0003?\t)#!\u0018\u0011\u0007Y\u000by\u0006B\u0003c3\t\u0007\u0011\fC\u0004\u0002.e\u0001\r!a\u0019\u0011\r\u0005}\u0011QEA3!\r1\u0016q\r\u0003\u00061f\u0011\r!\u0017\u0005\b\u0003WJ\u0002\u0019AA7\u0003\u0015!C\u000f[5t!\u001d\t\tbDA3\u0003;\n!\u0003[1tQ\u000e{G-\u001a\u0013fqR,gn]5p]V1\u00111OA>\u0003\u007f\"B!a\r\u0002v!9\u00111\u000e\u000eA\u0002\u0005]\u0004cBA\t\u001f\u0005e\u0014Q\u0010\t\u0004-\u0006mD!\u0002-\u001b\u0005\u0004I\u0006c\u0001,\u0002\u0000\u0011)!M\u0007b\u00013\u0006\u0001R-];bYN$S\r\u001f;f]NLwN\\\u000b\u0007\u0003\u000b\u000b\t*!&\u0015\t\u0005\u001d\u00151\u0012\u000b\u0005\u0003\u007f\tI\t\u0003\u0005\u0002Hm\t\t\u00111\u0001^\u0011\u001d\tYg\u0007a\u0001\u0003\u001b\u0003r!!\u0005\u0010\u0003\u001f\u000b\u0019\nE\u0002W\u0003##Q\u0001W\u000eC\u0002e\u00032AVAK\t\u0015\u00117D1\u0001Z\u0005\u0019y%/\u00127tKV1\u00111TAV\u0003_\u001bR\u0001HAO\u0003c\u0003\u0002\"a(\u0002&\u0006%\u0016QV\u0007\u0003\u0003CS1!a)J\u0003\u001d\u0011XO\u001c;j[\u0016LA!a*\u0002\"\n9\u0012IY:ue\u0006\u001cG\u000fU1si&\fGNR;oGRLwN\u001c\t\u0004-\u0006-FA\u0002-\u001d\u0011\u000b\u0007\u0011\fE\u0002W\u0003_#aA\u0019\u000f\u0005\u0006\u0004I\u0006\u0003BA\u0010\u0003gKA!!.\u0002*\ta1+\u001a:jC2L\'0\u00192mK\u0006\u0011a-\r\t\u0007\u001f\u0002\tI+!,\u0002\u0005\u0019\u0014DCBA`\u0003\u0003\f\u0019\rE\u0004\u0002\u0012q\tI+!,\t\u000f\u0005]v\u00041\u0001\u0002:\"9\u00111X\u0010A\u0002\u0005e\u0016aC5t\t\u00164\u0017N\\3e\u0003R$B!a\u0010\u0002J\"9\u00111\u001a\u0011A\u0002\u0005%\u0016!\u0001=\u0002\u000b\u0005\u0004\b\u000f\\=\u0015\t\u00055\u0016\u0011\u001b\u0005\b\u0003\u0017\f\u0003\u0019AAU\u0003-\t\u0007\u000f\u001d7z\u001fJ,En]3\u0016\r\u0005]\u0017Q]An)\u0019\tI.!9\u0002lB\u0019a+a7\u0005\u000f\u0005u\'E1\u0001\u0002`\n\u0011!)M\t\u0004\u0003[k\u0006bBAfE\u0001\u0007\u00111\u001d\t\u0004-\u0006\u0015HaBAtE\t\u0007\u0011\u0011\u001e\u0002\u0003\u0003F\n2AWAU\u0011\u001d\tiO\ta\u0001\u0003_\fq\u0001Z3gCVdG\u000f\u0005\u0004P\'\u0006\r\u0018\u0011\\\u0001\u0007_J,En]3\u0016\r\u0005U\u00181`A\u0000)\u0011\t9P!\u0001\u0011\u000f\u0005EA$!?\u0002~B\u0019a+a?\u0005\u000f\u0005\u001d8E1\u0001\u0002jB\u0019a+a@\u0005\u000f\u0005u7E1\u0001\u0002`\"9!1A\u0012A\u0002\t\u0015\u0011\u0001\u0002;iCR\u0004ba\u0014\u0001\u0002z\u0006u\u0018aB1oIRCWM\\\u000b\u0005\u0005\u0017\u0011\t\u0002\u0006\u0003\u0003\u000e\tU\u0001cBA\t9\u0005%&q\u0002\t\u0004-\nEAA\u0002B\nI\t\u0007\u0011LA\u0001D\u0011\u001d\u00119\u0002\na\u0001\u00053\t\u0011a\u001b\t\u0007\u001fN\u000biKa\u0004\u0003\u000f\u0005sG\r\u00165f]VA!q\u0004B\u0013\u0005_\u0011Ic\u0005\u0004&\u001d\n\u0005\u0012\u0011\u0017\t\u0007\u001f\u0002\u0011\u0019Ca\n\u0011\u0007Y\u0013)\u0003\u0002\u0004YK!\u0015\r!\u0017\t\u0004-\n%Ba\u0002B\nK\u0011\u0015\r!\u0017\t\u0007\u001f\u0002\u0011\u0019C!\f\u0011\u0007Y\u0013y\u0003B\u0003cK\t\u0007\u0011\f\u0005\u0004P\'\n5\"q\u0005\u000b\u0007\u0005k\u00119D!\u000f\u0011\u0013\u0005EQEa\t\u0003.\t\u001d\u0002bBA\u000bQ\u0001\u0007!1\u0006\u0005\b\u0005/A\u0003\u0019\u0001B\u0019)\u0011\tyD!\u0010\t\u000f\u0005-\u0017\u00061\u0001\u0003$Q!!q\u0005B!\u0011\u001d\tYM\u000ba\u0001\u0005G)bA!\u0012\u0003T\t%CC\u0002B$\u0005\u001f\u00129\u0006E\u0002W\u0005\u0013\"qAa\u0013,\u0005\u0004\u0011iE\u0001\u0002DcE\u0019!qE/\t\u000f\u0005-7\u00061\u0001\u0003RA\u0019aKa\u0015\u0005\u000f\u0005\u001d8F1\u0001\u0003VE\u0019!La\t\t\u000f\u000558\u00061\u0001\u0003ZA1qj\u0015B)\u0005\u000f\u0012\u0001bQ8nE&tW\rZ\u000b\t\u0005?\u0012)Ga\u001c\u0003jM1AF\u0014B1\u0003c\u0003ba\u0014\u0001\u0003d\t\u001d\u0004c\u0001,\u0003f\u00111\u0001\f\fEC\u0002e\u00032A\u0016B5\t\u001d\u0011\u0019\u0002\fCC\u0002e\u0003ba\u0014\u0001\u0003d\t5\u0004c\u0001,\u0003p\u0011)!\r\fb\u00013B1q\n\u0001B7\u0005O\"bA!\u001e\u0003x\te\u0004#CA\tY\t\r$Q\u000eB4\u0011\u001d\t)b\fa\u0001\u0005WBqAa\u00060\u0001\u0004\u0011\t\b\u0006\u0003\u0002@\tu\u0004bBAfa\u0001\u0007!1\r\u000b\u0005\u0005O\u0012\t\tC\u0004\u0002LF\u0002\rAa\u0019\u0016\r\t\u0015%\u0011\u0013BE)\u0019\u00119I!$\u0003\u0016B\u0019aK!#\u0005\u000f\t-#G1\u0001\u0003\fF\u0019!qM/\t\u000f\u0005-\'\u00071\u0001\u0003\u0010B\u0019aK!%\u0005\u000f\u0005\u001d(G1\u0001\u0003\u0014F\u0019!La\u0019\t\u000f\u00055(\u00071\u0001\u0003\u0018B1qj\u0015BH\u0005\u000f\u000b1BZ1mY\n\f7m[0g]B!qjU/^\u00035\u0019\u0007.Z2l\r\u0006dGNY1dWV!!\u0011\u0015BT+\t\u0011\u0019\u000bE\u0003P\'v\u0013)\u000bE\u0002W\u0005O#QA\u0019\u001bC\u0002e\u000b\u0001CZ1mY\n\f7m[(dGV\u0014(/\u001a3\u0016\t\t5&1\u0017\u000b\u0005\u0003\u007f\u0011y\u000bC\u0004\u0002LV\u0002\rA!-\u0011\u0007Y\u0013\u0019\fB\u0003ck\t\u0007\u0011L\u0001\u0004MS\u001a$X\rZ\u000b\u0007\u0005s\u0013\u0019M!3\u0014\u000bY\u0012Y,!-\u0011\u0011\u0005}%Q\u0018Ba\u0005\u000bLAAa0\u0002\"\n\t\u0012IY:ue\u0006\u001cGOR;oGRLwN\\\u0019\u0011\u0007Y\u0013\u0019\r\u0002\u0004Ym!\u0015\r!\u0017\t\u0005\u001f.\u00149\rE\u0002W\u0005\u0013$aA\u0019\u001c\u0005\u0006\u0004IVC\u0001Bg!\u0019y\u0005A!1\u0003H\u0006\u0019\u0001O\u001a\u0011\u0015\t\tM\'Q\u001b\t\b\u0003#1$\u0011\u0019Bd\u0011\u001d\t)\"\u000fa\u0001\u0005\u001b$BA!2\u0003Z\"9\u00111\u001a\u001eA\u0002\t\u0005\'\u0001C+oY&4G/\u001a3\u0016\r\t}\'Q\u001dBu\'\u0015Y$\u0011]AY!!\ty*!*\u0003d\n\u001d\bc\u0001,\u0003f\u0012)\u0001l\u000fb\u00013B\u0019aK!;\u0005\u000b\t\\$\u0019A-\u0002\u0003\u0019\u0004baT*\u0003d\n=\b\u0003B(l\u0005O$BAa=\u0003vB9\u0011\u0011C\u001e\u0003d\n\u001d\bb\u0002Bv{\u0001\u0007!Q\u001e\u000b\u0005\u0003\u007f\u0011I\u0010C\u0004\u0002Lz\u0002\rAa9\u0016\r\tu8\u0011BB\u0001)\u0019\u0011yp!\u0002\u0004\u000eA\u0019ak!\u0001\u0005\u000f\u0005uwH1\u0001\u0004\u0004E\u0019!q]/\t\u000f\u0005-w\b1\u0001\u0004\bA\u0019ak!\u0003\u0005\u000f\u0005\u001dxH1\u0001\u0004\fE\u0019!La9\t\u000f\u00055x\b1\u0001\u0004\u0010A1qjUB\u0004\u0005\u007f\fA\u0001\\5giV\u0011!Q^\u0001\tk:d\u0017N\u001a;fIV11\u0011DB\u0010\u0007G!Baa\u0007\u0004&A1q\nAB\u000f\u0007C\u00012AVB\u0010\t\u0015A\u0016I1\u0001Z!\r161\u0005\u0003\u0006E\u0006\u0013\r!\u0017\u0005\b\u0005W\f\u0005\u0019AB\u0014!\u0019y5k!\b\u0004*A!qj[B\u0011\u000311\'o\\7Gk:\u001cG/[8o+\u0019\u0019yc!\u000e\u0004:Q!1\u0011GB\u001e!\u0019y\u0005aa\r\u00048A\u0019ak!\u000e\u0005\u000ba\u0013%\u0019A-\u0011\u0007Y\u001bI\u0004B\u0003c\u0005\n\u0007\u0011\fC\u0004\u0003l\n\u0003\ra!\u0010\u0011\r=\u001b61GB\u001c\u0003)\u0019wN\\:u\r\u0006d7/\u001a\t\u0006\u001fNk\u0016qH\u0001\tK6\u0004H/_0qMB!q\nA/[\u0003\u0015)W\u000e\u001d;z+\u0019\u0019Ye!\u0015\u0004VU\u00111Q\n\t\u0007\u001f\u0002\u0019yea\u0015\u0011\u0007Y\u001b\t\u0006B\u0003Y\u000b\n\u0007\u0011\fE\u0002W\u0007+\"QAY#C\u0002e\u000bAaY8oIV!11LB3)\u0011\u0019ifa\u001a\u0015\t\u0005}2q\f\u0005\b\u0003+1\u0005\u0019AB1!\u0019y\u0005aa\u0019\u0002@A\u0019ak!\u001a\u0005\u000ba3%\u0019A-\t\u000f\u0005-g\t1\u0001\u0004d\u000591m\u001c8e\u001fB$XCBB7\u0007{\u001a)\b\u0006\u0003\u0004p\r}D\u0003BB9\u0007o\u0002BaT6\u0004tA\u0019ak!\u001e\u0005\u000b\t<%\u0019A-\t\u000f\u0005Uq\t1\u0001\u0004zA1q\nAB>\u0007g\u00022AVB?\t\u0015AvI1\u0001Z\u0011\u001d\tYm\u0012a\u0001\u0007w\"B!a\u0010\u0004\u0004\"1\u00111\u001a\u0003A\u0002U+baa\"\u0004\u000e\u000eME\u0003BBE\u0007/\u0003ba\u0014\u0001\u0004\f\u000eE\u0005c\u0001,\u0004\u000e\u00129\u0011q]\u0003C\u0002\r=\u0015C\u0001.V!\r161\u0013\u0003\b\u0003;,!\u0019ABK#\t\u0001W\fC\u0004\u0003\u0004\u0015\u0001\ra!#\u0016\t\rm5\u0011\u0015\u000b\u0005\u0007;\u001b\u0019\u000bE\u0003P\u0001U\u001by\nE\u0002W\u0007C#aAa\u0005\u0007\u0005\u0004I\u0006b\u0002B\f\r\u0001\u00071Q\u0015\t\u0006\u001fN\u00037qT\u000b\u0005\u0007S\u001by\u000b\u0006\u0003\u0004,\u000eE\u0006#B(\u0001+\u000e5\u0006c\u0001,\u00040\u00121!1C\u0004C\u0002eCqAa\u0006\b\u0001\u0004\u0019\u0019\fE\u0003P\u0001\u0001\u001ci+A\u0004d_6\u0004xn]3\u0016\t\re6q\u0018\u000b\u0005\u0007w\u001b\u0019\rE\u0003P\u0001\ru\u0006\rE\u0002W\u0007\u007f#aa!1\t\u0005\u0004I&!\u0001*\t\u000f\t]\u0001\u00021\u0001\u0004FB)q\nAB_+V\u00111\u0011\u001a\t\u0005\u001fN+&.\u0006\u0004\u0004N\u000e]7\u0011\u001b\u000b\u0007\u0007\u001f\u001c\u0019n!7\u0011\u0007Y\u001b\t\u000eB\u0004\u0002^*\u0011\ra!&\t\u000f\u0005-\'\u00021\u0001\u0004VB\u0019aka6\u0005\u000f\u0005\u001d(B1\u0001\u0004\u0010\"9\u0011Q\u001e\u0006A\u0002\rm\u0007CB(T\u0007+\u001cy-A\u0004sk:<\u0016\u000e\u001e5\u0016\t\r\u00058Q\u001e\u000b\u0005\u0007G\u001c)\u000fE\u0003P\'V\u000by\u0004C\u0004\u0004h.\u0001\ra!;\u0002\r\u0005\u001cG/[8o!\u0015y5\u000bYBv!\r16Q\u001e\u0003\u0007\u0007_\\!\u0019A-\u0003\u0003U\u0003"
    )
BootstrapMethods:
  0: #170 REF_invokeStatic java/lang/invoke/LambdaMetafactory.altMetafactory:(Ljava/lang/invoke/MethodHandles$Lookup;Ljava/lang/String;Ljava/lang/invoke/MethodType;[Ljava/lang/Object;)Ljava/lang/invoke/CallSite;
    Method arguments:
      #157 (Ljava/lang/Object;)Ljava/lang/Object;
      #162 REF_invokeStatic scala/PartialFunction.$anonfun$runWith$1$adapted:(Lscala/PartialFunction;Lscala/Function1;Ljava/lang/Object;)Ljava/lang/Object;
      #157 (Ljava/lang/Object;)Ljava/lang/Object;
      #163 1
  1: #200 REF_invokeStatic scala/runtime/LambdaDeserialize.bootstrap:(Ljava/lang/invoke/MethodHandles$Lookup;Ljava/lang/String;Ljava/lang/invoke/MethodType;[Ljava/lang/invoke/MethodHandle;)Ljava/lang/invoke/CallSite;
    Method arguments:
      #162 REF_invokeStatic scala/PartialFunction.$anonfun$runWith$1$adapted:(Lscala/PartialFunction;Lscala/Function1;Ljava/lang/Object;)Ljava/lang/Object;
  ScalaInlineInfo: length = 0x72 (unknown attribute)
   01 00 00 16 00 AD 00 AE 01 00 9E 00 9F 01 00 B7
   00 87 01 00 74 00 42 00 00 74 00 5F 00 00 71 00
   72 01 00 71 00 68 01 00 8D 00 8E 00 00 8A 00 8B
   01 00 80 00 5F 00 00 7F 00 68 01 00 60 00 3D 00
   00 5E 00 5F 01 00 64 00 65 00 00 53 00 54 00 00
   84 00 85 01 00 6A 00 5F 00 00 67 00 68 01 00 98
   00 99 00 00 95 00 96 01 00 4E 00 4F 00 00 4A 00
   4B 01
  ScalaSig: length = 0x3 (unknown attribute)
   05 02 00
