Classfile /Users/mw/Projects/slang-braindump/.jar/jar8/assemble/slang-braindump/assemble/content/scala/Product6.class
  Last modified May 29, 2022; size 3207 bytes
  SHA-256 checksum 64dfd71e3b5a94ca1fa63c82d89e103a1fe7546721eeab99986286d2ca6c79a2
  Compiled from "Product6.scala"
public interface scala.Product6<T1 extends java.lang.Object, T2 extends java.lang.Object, T3 extends java.lang.Object, T4 extends java.lang.Object, T5 extends java.lang.Object, T6 extends java.lang.Object> extends scala.Product
  minor version: 0
  major version: 52
  flags: (0x0601) ACC_PUBLIC, ACC_INTERFACE, ACC_ABSTRACT
  this_class: #2                          // scala/Product6
  super_class: #5                         // java/lang/Object
  interfaces: 1, fields: 0, methods: 12, attributes: 5
Constant pool:
    #1 = Utf8               scala/Product6
    #2 = Class              #1            // scala/Product6
    #3 = Utf8               <T1:Ljava/lang/Object;T2:Ljava/lang/Object;T3:Ljava/lang/Object;T4:Ljava/lang/Object;T5:Ljava/lang/Object;T6:Ljava/lang/Object;>Ljava/lang/Object;Lscala/Product;
    #4 = Utf8               java/lang/Object
    #5 = Class              #4            // java/lang/Object
    #6 = Utf8               scala/Product
    #7 = Class              #6            // scala/Product
    #8 = Utf8               Product6.scala
    #9 = Utf8               Lscala/reflect/ScalaSignature;
   #10 = Utf8               bytes
   #11 = Utf8               \u0006\u0005U<QAD\b\t\u0002I1Q\u0001F\b\t\u0002UAQ!G\u0001\u0005\u0002iAQaG\u0001\u0005\u0002q1q\u0001F\b\u0011\u0002\u0007\u0005!\u0005C\u0003+\t\u0011\u00051\u0006C\u00030\t\u0011\u0005\u0003\u0007C\u00035\t\u0011\u0005S\u0007C\u0003E\t\u0019\u0005Q\tC\u0003O\t\u0019\u0005q\nC\u0003T\t\u0019\u0005A\u000bC\u0003Y\t\u0019\u0005\u0011\fC\u0003^\t\u0019\u0005a\fC\u0003c\t\u0019\u00051-\u0001\u0005Qe>$Wo\u0019;7\u0015\u0005\u0001\u0012!B:dC2\f7\u0001\u0001\t\u0003\'\u0005i\u0011a\u0004\u0002\t!J|G-^2umM\u0011\u0011A\u0006\t\u0003\']I!\u0001G\b\u0003\r\u0005s\u0017PU3g\u0003\u0019a\u0014N\\5u}Q\t!#A\u0004v]\u0006\u0004\b\u000f\\=\u0016\u000fuA\'\u000e\u001c8qeR\u0011ad\u001d\t\u0004\'}\t\u0013B\u0001\u0011\u0010\u0005\u0019y\u0005\u000f^5p]BA1\u0003B4jW6|\u0017/F\u0004$\u0011F36\fY3\u0014\u0007\u0011!s\u0005\u0005\u0002\u0014K%\u0011ae\u0004\u0002\u0004\u0003:L\bCA\n)\u0013\tIsBA\u0004Qe>$Wo\u0019;\u0002\r\u0011Jg.\u001b;%)\u0005a\u0003CA\n.\u0013\tqsB\u0001\u0003V]&$\u0018\u0001\u00049s_\u0012,8\r^!sSRLX#A\u0019\u0011\u0005M\u0011\u0014BA\u001a\u0010\u0005\rIe\u000e^\u0001\u000faJ|G-^2u\u000b2,W.\u001a8u)\t!c\u0007C\u00038\u000f\u0001\u0007\u0011\'A\u0001oQ\r9\u0011h\u0011\t\u0004\'ib\u0014BA\u001e\u0010\u0005\u0019!\bN]8xgB\u0011Q\b\u0011\b\u0003\'yJ!aP\b\u0002\u000fA\f7m[1hK&\u0011\u0011I\u0011\u0002\u001a\u0013:$W\r_(vi>3\'i\\;oIN,\u0005pY3qi&|gN\u0003\u0002@\u001f\r\nA(\u0001\u0002`cU\ta\t\u0005\u0002H\u00112\u0001AAB%\u0005\t\u000b\u0007!J\u0001\u0002UcE\u00111\n\n\t\u0003\'1K!!T\b\u0003\u000f9{G\u000f[5oO\u0006\u0011qLM\u000b\u0002!B\u0011q)\u0015\u0003\u0007%\u0012!)\u0019\u0001&\u0003\u0005Q\u0013\u0014AA04+\u0005)\u0006CA$W\t\u00199F\u0001\"b\u0001\u0015\n\u0011AkM\u0001\u0003?R*\u0012A\u0017\t\u0003\u000fn#a\u0001\u0018\u0003\u0005\u0006\u0004Q%A\u0001+5\u0003\tyV\'F\u0001`!\t9\u0005\r\u0002\u0004b\t\u0011\u0015\rA\u0013\u0002\u0003)V\n!a\u0018\u001c\u0016\u0003\u0011\u0004\"aR3\u0005\r\u0019$AQ1\u0001K\u0005\t!f\u0007\u0005\u0002HQ\u0012)\u0011j\u0001b\u0001\u0015B\u0011qI\u001b\u0003\u0006%\u000e\u0011\rA\u0013\t\u0003\u000f2$QaV\u0002C\u0002)\u0003\"a\u00128\u0005\u000bq\u001b!\u0019\u0001&\u0011\u0005\u001d\u0003H!B1\u0004\u0005\u0004Q\u0005CA$s\t\u001517A1\u0001K\u0011\u0015!8\u00011\u0001\"\u0003\u0005A\b
   #12 = Utf8               unapply
   #13 = Utf8               (Lscala/Product6;)Lscala/Option;
   #14 = Utf8               <T1:Ljava/lang/Object;T2:Ljava/lang/Object;T3:Ljava/lang/Object;T4:Ljava/lang/Object;T5:Ljava/lang/Object;T6:Ljava/lang/Object;>(Lscala/Product6<TT1;TT2;TT3;TT4;TT5;TT6;>;)Lscala/Option<Lscala/Product6<TT1;TT2;TT3;TT4;TT5;TT6;>;>;
   #15 = Utf8               x
   #16 = Utf8               scala/Product6$
   #17 = Class              #16           // scala/Product6$
   #18 = Utf8               MODULE$
   #19 = Utf8               Lscala/Product6$;
   #20 = NameAndType        #18:#19       // MODULE$:Lscala/Product6$;
   #21 = Fieldref           #17.#20       // scala/Product6$.MODULE$:Lscala/Product6$;
   #22 = Utf8               scala/Some
   #23 = Class              #22           // scala/Some
   #24 = Utf8               <init>
   #25 = Utf8               (Ljava/lang/Object;)V
   #26 = NameAndType        #24:#25       // "<init>":(Ljava/lang/Object;)V
   #27 = Methodref          #23.#26       // scala/Some."<init>":(Ljava/lang/Object;)V
   #28 = Utf8               Lscala/Product6;
   #29 = Utf8               productArity$
   #30 = Utf8               (Lscala/Product6;)I
   #31 = Utf8               $this
   #32 = Utf8               productArity
   #33 = Utf8               ()I
   #34 = NameAndType        #32:#33       // productArity:()I
   #35 = InterfaceMethodref #2.#34        // scala/Product6.productArity:()I
   #36 = Utf8               this
   #37 = Utf8               productElement$
   #38 = Utf8               (Lscala/Product6;I)Ljava/lang/Object;
   #39 = Utf8               n
   #40 = Utf8               productElement
   #41 = Utf8               (I)Ljava/lang/Object;
   #42 = NameAndType        #40:#41       // productElement:(I)Ljava/lang/Object;
   #43 = InterfaceMethodref #2.#42        // scala/Product6.productElement:(I)Ljava/lang/Object;
   #44 = Utf8               I
   #45 = Utf8               java/lang/IndexOutOfBoundsException
   #46 = Class              #45           // java/lang/IndexOutOfBoundsException
   #47 = Utf8               _1
   #48 = Utf8               ()Ljava/lang/Object;
   #49 = NameAndType        #47:#48       // _1:()Ljava/lang/Object;
   #50 = InterfaceMethodref #2.#49        // scala/Product6._1:()Ljava/lang/Object;
   #51 = Utf8               _2
   #52 = NameAndType        #51:#48       // _2:()Ljava/lang/Object;
   #53 = InterfaceMethodref #2.#52        // scala/Product6._2:()Ljava/lang/Object;
   #54 = Utf8               _3
   #55 = NameAndType        #54:#48       // _3:()Ljava/lang/Object;
   #56 = InterfaceMethodref #2.#55        // scala/Product6._3:()Ljava/lang/Object;
   #57 = Utf8               _4
   #58 = NameAndType        #57:#48       // _4:()Ljava/lang/Object;
   #59 = InterfaceMethodref #2.#58        // scala/Product6._4:()Ljava/lang/Object;
   #60 = Utf8               _5
   #61 = NameAndType        #60:#48       // _5:()Ljava/lang/Object;
   #62 = InterfaceMethodref #2.#61        // scala/Product6._5:()Ljava/lang/Object;
   #63 = Utf8               _6
   #64 = NameAndType        #63:#48       // _6:()Ljava/lang/Object;
   #65 = InterfaceMethodref #2.#64        // scala/Product6._6:()Ljava/lang/Object;
   #66 = Utf8               java/lang/StringBuilder
   #67 = Class              #66           // java/lang/StringBuilder
   #68 = Integer            32
   #69 = Utf8               (I)V
   #70 = NameAndType        #24:#69       // "<init>":(I)V
   #71 = Methodref          #67.#70       // java/lang/StringBuilder."<init>":(I)V
   #72 = Utf8               append
   #73 = Utf8               (I)Ljava/lang/StringBuilder;
   #74 = NameAndType        #72:#73       // append:(I)Ljava/lang/StringBuilder;
   #75 = Methodref          #67.#74       // java/lang/StringBuilder.append:(I)Ljava/lang/StringBuilder;
   #76 = Utf8                is out of bounds (min 0, max 5)
   #77 = String             #76           //  is out of bounds (min 0, max 5)
   #78 = Utf8               (Ljava/lang/String;)Ljava/lang/StringBuilder;
   #79 = NameAndType        #72:#78       // append:(Ljava/lang/String;)Ljava/lang/StringBuilder;
   #80 = Methodref          #67.#79       // java/lang/StringBuilder.append:(Ljava/lang/String;)Ljava/lang/StringBuilder;
   #81 = Utf8               toString
   #82 = Utf8               ()Ljava/lang/String;
   #83 = NameAndType        #81:#82       // toString:()Ljava/lang/String;
   #84 = Methodref          #67.#83       // java/lang/StringBuilder.toString:()Ljava/lang/String;
   #85 = Utf8               (Ljava/lang/String;)V
   #86 = NameAndType        #24:#85       // "<init>":(Ljava/lang/String;)V
   #87 = Methodref          #46.#86       // java/lang/IndexOutOfBoundsException."<init>":(Ljava/lang/String;)V
   #88 = Utf8               ()TT1;
   #89 = Utf8               ()TT2;
   #90 = Utf8               ()TT3;
   #91 = Utf8               ()TT4;
   #92 = Utf8               ()TT5;
   #93 = Utf8               ()TT6;
   #94 = Utf8               $init$
   #95 = Utf8               (Lscala/Product6;)V
   #96 = Utf8               Code
   #97 = Utf8               LineNumberTable
   #98 = Utf8               LocalVariableTable
   #99 = Utf8               Signature
  #100 = Utf8               MethodParameters
  #101 = Utf8               StackMapTable
  #102 = Utf8               Exceptions
  #103 = Utf8               SourceFile
  #104 = Utf8               RuntimeVisibleAnnotations
  #105 = Utf8               ScalaInlineInfo
  #106 = Utf8               ScalaSig
{
  public static <T1 extends java.lang.Object, T2 extends java.lang.Object, T3 extends java.lang.Object, T4 extends java.lang.Object, T5 extends java.lang.Object, T6 extends java.lang.Object> scala.Option<scala.Product6<T1, T2, T3, T4, T5, T6>> unapply(scala.Product6<T1, T2, T3, T4, T5, T6>);
    descriptor: (Lscala/Product6;)Lscala/Option;
    flags: (0x0009) ACC_PUBLIC, ACC_STATIC
    Code:
      stack=3, locals=1, args_size=1
         0: getstatic     #21                 // Field scala/Product6$.MODULE$:Lscala/Product6$;
         3: pop
         4: new           #23                 // class scala/Some
         7: dup
         8: aload_0
         9: invokespecial #27                 // Method scala/Some."<init>":(Ljava/lang/Object;)V
        12: areturn
      LineNumberTable:
        line 19: 4
      LocalVariableTable:
        Start  Length  Slot  Name   Signature
            0      13     0     x   Lscala/Product6;
    Signature: #14                          // <T1:Ljava/lang/Object;T2:Ljava/lang/Object;T3:Ljava/lang/Object;T4:Ljava/lang/Object;T5:Ljava/lang/Object;T6:Ljava/lang/Object;>(Lscala/Product6<TT1;TT2;TT3;TT4;TT5;TT6;>;)Lscala/Option<Lscala/Product6<TT1;TT2;TT3;TT4;TT5;TT6;>;>;
    MethodParameters:
      Name                           Flags
      x                              final

  public static int productArity$(scala.Product6);
    descriptor: (Lscala/Product6;)I
    flags: (0x1009) ACC_PUBLIC, ACC_STATIC, ACC_SYNTHETIC
    Code:
      stack=1, locals=1, args_size=1
         0: aload_0
         1: invokespecial #35                 // InterfaceMethod productArity:()I
         4: ireturn
      LineNumberTable:
        line 28: 0
      LocalVariableTable:
        Start  Length  Slot  Name   Signature
            0       5     0 $this   Lscala/Product6;
    MethodParameters:
      Name                           Flags
      $this                          final synthetic

  public default int productArity();
    descriptor: ()I
    flags: (0x0001) ACC_PUBLIC
    Code:
      stack=1, locals=1, args_size=1
         0: bipush        6
         2: ireturn
      LineNumberTable:
        line 28: 0
      LocalVariableTable:
        Start  Length  Slot  Name   Signature
            0       3     0  this   Lscala/Product6;

  public static java.lang.Object productElement$(scala.Product6, int);
    descriptor: (Lscala/Product6;I)Ljava/lang/Object;
    flags: (0x1009) ACC_PUBLIC, ACC_STATIC, ACC_SYNTHETIC
    Code:
      stack=2, locals=2, args_size=2
         0: aload_0
         1: iload_1
         2: invokespecial #43                 // InterfaceMethod productElement:(I)Ljava/lang/Object;
         5: areturn
      LineNumberTable:
        line 40: 0
      LocalVariableTable:
        Start  Length  Slot  Name   Signature
            0       6     0 $this   Lscala/Product6;
            0       6     1     n   I
    MethodParameters:
      Name                           Flags
      $this                          final synthetic
      n                              final

  public default java.lang.Object productElement(int) throws java.lang.IndexOutOfBoundsException;
    descriptor: (I)Ljava/lang/Object;
    flags: (0x0001) ACC_PUBLIC
    Code:
      stack=5, locals=2, args_size=2
         0: iload_1
         1: tableswitch   { // 0 to 5
                       0: 40
                       1: 47
                       2: 54
                       3: 61
                       4: 68
                       5: 75
                 default: 82
            }
        40: aload_0
        41: invokeinterface #50,  1           // InterfaceMethod _1:()Ljava/lang/Object;
        46: areturn
        47: aload_0
        48: invokeinterface #53,  1           // InterfaceMethod _2:()Ljava/lang/Object;
        53: areturn
        54: aload_0
        55: invokeinterface #56,  1           // InterfaceMethod _3:()Ljava/lang/Object;
        60: areturn
        61: aload_0
        62: invokeinterface #59,  1           // InterfaceMethod _4:()Ljava/lang/Object;
        67: areturn
        68: aload_0
        69: invokeinterface #62,  1           // InterfaceMethod _5:()Ljava/lang/Object;
        74: areturn
        75: aload_0
        76: invokeinterface #65,  1           // InterfaceMethod _6:()Ljava/lang/Object;
        81: areturn
        82: new           #46                 // class java/lang/IndexOutOfBoundsException
        85: dup
        86: new           #67                 // class java/lang/StringBuilder
        89: dup
        90: ldc           #68                 // int 32
        92: invokespecial #71                 // Method java/lang/StringBuilder."<init>":(I)V
        95: iload_1
        96: invokevirtual #75                 // Method java/lang/StringBuilder.append:(I)Ljava/lang/StringBuilder;
        99: ldc           #77                 // String  is out of bounds (min 0, max 5)
       101: invokevirtual #80                 // Method java/lang/StringBuilder.append:(Ljava/lang/String;)Ljava/lang/StringBuilder;
       104: invokevirtual #84                 // Method java/lang/StringBuilder.toString:()Ljava/lang/String;
       107: invokespecial #87                 // Method java/lang/IndexOutOfBoundsException."<init>":(Ljava/lang/String;)V
       110: athrow
      StackMapTable: number_of_entries = 7
        frame_type = 40 /* same */
        frame_type = 6 /* same */
        frame_type = 6 /* same */
        frame_type = 6 /* same */
        frame_type = 6 /* same */
        frame_type = 6 /* same */
        frame_type = 6 /* same */
      LineNumberTable:
        line 40: 0
        line 41: 40
        line 42: 47
        line 43: 54
        line 44: 61
        line 45: 68
        line 46: 75
        line 47: 82
      LocalVariableTable:
        Start  Length  Slot  Name   Signature
            0     111     0  this   Lscala/Product6;
            0     111     1     n   I
    Exceptions:
      throws java.lang.IndexOutOfBoundsException
    MethodParameters:
      Name                           Flags
      n                              final

  public abstract T1 _1();
    descriptor: ()Ljava/lang/Object;
    flags: (0x0401) ACC_PUBLIC, ACC_ABSTRACT
    Signature: #88                          // ()TT1;

  public abstract T2 _2();
    descriptor: ()Ljava/lang/Object;
    flags: (0x0401) ACC_PUBLIC, ACC_ABSTRACT
    Signature: #89                          // ()TT2;

  public abstract T3 _3();
    descriptor: ()Ljava/lang/Object;
    flags: (0x0401) ACC_PUBLIC, ACC_ABSTRACT
    Signature: #90                          // ()TT3;

  public abstract T4 _4();
    descriptor: ()Ljava/lang/Object;
    flags: (0x0401) ACC_PUBLIC, ACC_ABSTRACT
    Signature: #91                          // ()TT4;

  public abstract T5 _5();
    descriptor: ()Ljava/lang/Object;
    flags: (0x0401) ACC_PUBLIC, ACC_ABSTRACT
    Signature: #92                          // ()TT5;

  public abstract T6 _6();
    descriptor: ()Ljava/lang/Object;
    flags: (0x0401) ACC_PUBLIC, ACC_ABSTRACT
    Signature: #93                          // ()TT6;

  public static void $init$(scala.Product6);
    descriptor: (Lscala/Product6;)V
    flags: (0x0009) ACC_PUBLIC, ACC_STATIC
    Code:
      stack=0, locals=1, args_size=1
         0: return
      LineNumberTable:
        line 24: 0
      LocalVariableTable:
        Start  Length  Slot  Name   Signature
            0       1     0 $this   Lscala/Product6;
    MethodParameters:
      Name                           Flags
      $this                          final synthetic
}
Signature: #3                           // <T1:Ljava/lang/Object;T2:Ljava/lang/Object;T3:Ljava/lang/Object;T4:Ljava/lang/Object;T5:Ljava/lang/Object;T6:Ljava/lang/Object;>Ljava/lang/Object;Lscala/Product;
SourceFile: "Product6.scala"
RuntimeVisibleAnnotations:
  0: #9(#10=s#11)
    scala.reflect.ScalaSignature(
      bytes="\u0006\u0005U<QAD\b\t\u0002I1Q\u0001F\b\t\u0002UAQ!G\u0001\u0005\u0002iAQaG\u0001\u0005\u0002q1q\u0001F\b\u0011\u0002\u0007\u0005!\u0005C\u0003+\t\u0011\u00051\u0006C\u00030\t\u0011\u0005\u0003\u0007C\u00035\t\u0011\u0005S\u0007C\u0003E\t\u0019\u0005Q\tC\u0003O\t\u0019\u0005q\nC\u0003T\t\u0019\u0005A\u000bC\u0003Y\t\u0019\u0005\u0011\fC\u0003^\t\u0019\u0005a\fC\u0003c\t\u0019\u00051-\u0001\u0005Qe>$Wo\u0019;7\u0015\u0005\u0001\u0012!B:dC2\f7\u0001\u0001\t\u0003\'\u0005i\u0011a\u0004\u0002\t!J|G-^2umM\u0011\u0011A\u0006\t\u0003\']I!\u0001G\b\u0003\r\u0005s\u0017PU3g\u0003\u0019a\u0014N\\5u}Q\t!#A\u0004v]\u0006\u0004\b\u000f\\=\u0016\u000fuA\'\u000e\u001c8qeR\u0011ad\u001d\t\u0004\'}\t\u0013B\u0001\u0011\u0010\u0005\u0019y\u0005\u000f^5p]BA1\u0003B4jW6|\u0017/F\u0004$\u0011F36\fY3\u0014\u0007\u0011!s\u0005\u0005\u0002\u0014K%\u0011ae\u0004\u0002\u0004\u0003:L\bCA\n)\u0013\tIsBA\u0004Qe>$Wo\u0019;\u0002\r\u0011Jg.\u001b;%)\u0005a\u0003CA\n.\u0013\tqsB\u0001\u0003V]&$\u0018\u0001\u00049s_\u0012,8\r^!sSRLX#A\u0019\u0011\u0005M\u0011\u0014BA\u001a\u0010\u0005\rIe\u000e^\u0001\u000faJ|G-^2u\u000b2,W.\u001a8u)\t!c\u0007C\u00038\u000f\u0001\u0007\u0011\'A\u0001oQ\r9\u0011h\u0011\t\u0004\'ib\u0014BA\u001e\u0010\u0005\u0019!\bN]8xgB\u0011Q\b\u0011\b\u0003\'yJ!aP\b\u0002\u000fA\f7m[1hK&\u0011\u0011I\u0011\u0002\u001a\u0013:$W\r_(vi>3\'i\\;oIN,\u0005pY3qi&|gN\u0003\u0002@\u001f\r\nA(\u0001\u0002`cU\ta\t\u0005\u0002H\u00112\u0001AAB%\u0005\t\u000b\u0007!J\u0001\u0002UcE\u00111\n\n\t\u0003\'1K!!T\b\u0003\u000f9{G\u000f[5oO\u0006\u0011qLM\u000b\u0002!B\u0011q)\u0015\u0003\u0007%\u0012!)\u0019\u0001&\u0003\u0005Q\u0013\u0014AA04+\u0005)\u0006CA$W\t\u00199F\u0001\"b\u0001\u0015\n\u0011AkM\u0001\u0003?R*\u0012A\u0017\t\u0003\u000fn#a\u0001\u0018\u0003\u0005\u0006\u0004Q%A\u0001+5\u0003\tyV\'F\u0001`!\t9\u0005\r\u0002\u0004b\t\u0011\u0015\rA\u0013\u0002\u0003)V\n!a\u0018\u001c\u0016\u0003\u0011\u0004\"aR3\u0005\r\u0019$AQ1\u0001K\u0005\t!f\u0007\u0005\u0002HQ\u0012)\u0011j\u0001b\u0001\u0015B\u0011qI\u001b\u0003\u0006%\u000e\u0011\rA\u0013\t\u0003\u000f2$QaV\u0002C\u0002)\u0003\"a\u00128\u0005\u000bq\u001b!\u0019\u0001&\u0011\u0005\u001d\u0003H!B1\u0004\u0005\u0004Q\u0005CA$s\t\u001517A1\u0001K\u0011\u0015!8\u00011\u0001\"\u0003\u0005A\b"
    )
  ScalaInlineInfo: length = 0x3B (unknown attribute)
   01 00 00 0B 00 5E 00 5F 01 00 2F 00 30 00 00 33
   00 30 00 00 36 00 30 00 00 39 00 30 00 00 3C 00
   30 00 00 3F 00 30 00 00 20 00 21 00 00 1D 00 1E
   01 00 28 00 29 00 00 25 00 26 01
  ScalaSig: length = 0x3 (unknown attribute)
   05 02 00
