Classfile /Users/mw/Projects/slang-braindump/.jar/jar8/assemble/slang-braindump/assemble/content/scala/Product11.class
  Last modified May 29, 2022; size 4093 bytes
  SHA-256 checksum edb3d7b3078a007604b4088ccbf0754092405137736475b19d51ff34ba3ff313
  Compiled from "Product11.scala"
public interface scala.Product11<T1 extends java.lang.Object, T2 extends java.lang.Object, T3 extends java.lang.Object, T4 extends java.lang.Object, T5 extends java.lang.Object, T6 extends java.lang.Object, T7 extends java.lang.Object, T8 extends java.lang.Object, T9 extends java.lang.Object, T10 extends java.lang.Object, T11 extends java.lang.Object> extends scala.Product
  minor version: 0
  major version: 52
  flags: (0x0601) ACC_PUBLIC, ACC_INTERFACE, ACC_ABSTRACT
  this_class: #2                          // scala/Product11
  super_class: #5                         // java/lang/Object
  interfaces: 1, fields: 0, methods: 17, attributes: 5
Constant pool:
    #1 = Utf8               scala/Product11
    #2 = Class              #1            // scala/Product11
    #3 = Utf8               <T1:Ljava/lang/Object;T2:Ljava/lang/Object;T3:Ljava/lang/Object;T4:Ljava/lang/Object;T5:Ljava/lang/Object;T6:Ljava/lang/Object;T7:Ljava/lang/Object;T8:Ljava/lang/Object;T9:Ljava/lang/Object;T10:Ljava/lang/Object;T11:Ljava/lang/Object;>Ljava/lang/Object;Lscala/Product;
    #4 = Utf8               java/lang/Object
    #5 = Class              #4            // java/lang/Object
    #6 = Utf8               scala/Product
    #7 = Class              #6            // scala/Product
    #8 = Utf8               Product11.scala
    #9 = Utf8               Lscala/reflect/ScalaSignature;
   #10 = Utf8               bytes
   #11 = Utf8               \u0006\u0005\u0005mr!B\n\u0015\u0011\u00039b!B\r\u0015\u0011\u0003Q\u0002\"\u0002\u0010\u0002\t\u0003y\u0002\"\u0002\u0011\u0002\t\u0003\tcaB\r\u0015!\u0003\r\ta\n\u0005\u0006_\u0011!\t\u0001\r\u0005\u0006i\u0011!\t%\u000e\u0005\u0006s\u0011!\tE\u000f\u0005\u0006\u0013\u00121\tA\u0013\u0005\u0006\'\u00121\t\u0001\u0016\u0005\u00061\u00121\t!\u0017\u0005\u0006;\u00121\tA\u0018\u0005\u0006E\u00121\ta\u0019\u0005\u0006O\u00121\t\u0001\u001b\u0005\u0006Y\u00121\t!\u001c\u0005\u0006c\u00121\tA\u001d\u0005\u0006m\u00121\ta\u001e\u0005\u0006w\u00121\t\u0001 \u0005\b\u0003\u0003!a\u0011AA\u0002\u0003%\u0001&o\u001c3vGR\f\u0014GC\u0001\u0016\u0003\u0015\u00198-\u00197b\u0007\u0001\u0001\"\u0001G\u0001\u000e\u0003Q\u0011\u0011\u0002\u0015:pIV\u001cG/M\u0019\u0014\u0005\u0005Y\u0002C\u0001\r\u001d\u0013\tiBC\u0001\u0004B]f\u0014VMZ\u0001\u0007y%t\u0017\u000e\u001e \u0015\u0003]\tq!\u001e8baBd\u00170F\f#\u0003\u001b\t\t\"!\u0006\u0002\u001a\u0005u\u0011\u0011EA\u0013\u0003S\ti#!\r\u00026Q\u00191%a\u000e\u0011\u0007a!c%\u0003\u0002&)\t1q\n\u001d;j_:\u0004\u0002\u0004\u0007\u0003\u0002\f\u0005=\u00111CA\f\u00037\ty\"a\t\u0002(\u0005-\u0012qFA\u001a+5ASJV.aK*|G/\u001f@\u0002\bM\u0019A!\u000b\u0017\u0011\u0005aQ\u0013BA\u0016\u0015\u0005\r\te.\u001f\t\u000315J!A\f\u000b\u0003\u000fA\u0013x\u000eZ;di\u00061A%\u001b8ji\u0012\"\u0012!\r\t\u00031IJ!a\r\u000b\u0003\tUs\u0017\u000e^\u0001\raJ|G-^2u\u0003JLG/_\u000b\u0002mA\u0011\u0001dN\u0005\u0003qQ\u00111!\u00138u\u00039\u0001(o\u001c3vGR,E.Z7f]R$\"!K\u001e\t\u000bq:\u0001\u0019\u0001\u001c\u0002\u00039D3a\u0002 I!\rAr(Q\u0005\u0003\u0001R\u0011a\u0001\u001e5s_^\u001c\bC\u0001\"F\u001d\tA2)\u0003\u0002E)\u00059\u0001/Y2lC\u001e,\u0017B\u0001$H\u0005eIe\u000eZ3y\u001fV$xJ\u001a\"pk:$7/\u0012=dKB$\u0018n\u001c8\u000b\u0005\u0011#2%A!\u0002\u0005}\u000bT#A&\u0011\u00051kE\u0002\u0001\u0003\u0007\u001d\u0012!)\u0019A(\u0003\u0005Q\u000b\u0014C\u0001)*!\tA\u0012+\u0003\u0002S)\t9aj\u001c;iS:<\u0017AA03+\u0005)\u0006C\u0001\'W\t\u00199F\u0001\"b\u0001\u001f\n\u0011AKM\u0001\u0003?N*\u0012A\u0017\t\u0003\u0019n#a\u0001\u0018\u0003\u0005\u0006\u0004y%A\u0001+4\u0003\tyF\'F\u0001`!\ta\u0005\r\u0002\u0004b\t\u0011\u0015\ra\u0014\u0002\u0003)R\n!aX\u001b\u0016\u0003\u0011\u0004\"\u0001T3\u0005\r\u0019$AQ1\u0001P\u0005\t!V\'\u0001\u0002`mU\t\u0011\u000e\u0005\u0002MU\u001211\u000e\u0002CC\u0002=\u0013!\u0001\u0016\u001c\u0002\u0005};T#\u00018\u0011\u00051{GA\u00029\u0005\t\u000b\u0007qJ\u0001\u0002Uo\u0005\u0011q\fO\u000b\u0002gB\u0011A\n\u001e\u0003\u0007k\u0012!)\u0019A(\u0003\u0005QC\u0014AA0:+\u0005A\bC\u0001\'z\t\u0019QH\u0001\"b\u0001\u001f\n\u0011A+O\u0001\u0004?F\u0002T#A?\u0011\u00051sHAB@\u0005\t\u000b\u0007qJA\u0002UcA\n1aX\u00192+\t\t)\u0001E\u0002M\u0003\u000f!q!!\u0003\u0005\t\u000b\u0007qJA\u0002UcE\u00022\u0001TA\u0007\t\u0015q5A1\u0001P!\ra\u0015\u0011\u0003\u0003\u0006/\u000e\u0011\ra\u0014\t\u0004\u0019\u0006UA!\u0002/\u0004\u0005\u0004y\u0005c\u0001\'\u0002\u001a\u0011)\u0011m\u0001b\u0001\u001fB\u0019A*!\b\u0005\u000b\u0019\u001c!\u0019A(\u0011\u00071\u000b\t\u0003B\u0003l\u0007\t\u0007q\nE\u0002M\u0003K!Q\u0001]\u0002C\u0002=\u00032\u0001TA\u0015\t\u0015)8A1\u0001P!\ra\u0015Q\u0006\u0003\u0006u\u000e\u0011\ra\u0014\t\u0004\u0019\u0006EB!B@\u0004\u0005\u0004y\u0005c\u0001\'\u00026\u00111\u0011\u0011B\u0002C\u0002=Ca!!\u000f\u0004\u0001\u00041\u0013!\u0001=
   #12 = Utf8               unapply
   #13 = Utf8               (Lscala/Product11;)Lscala/Option;
   #14 = Utf8               <T1:Ljava/lang/Object;T2:Ljava/lang/Object;T3:Ljava/lang/Object;T4:Ljava/lang/Object;T5:Ljava/lang/Object;T6:Ljava/lang/Object;T7:Ljava/lang/Object;T8:Ljava/lang/Object;T9:Ljava/lang/Object;T10:Ljava/lang/Object;T11:Ljava/lang/Object;>(Lscala/Product11<TT1;TT2;TT3;TT4;TT5;TT6;TT7;TT8;TT9;TT10;TT11;>;)Lscala/Option<Lscala/Product11<TT1;TT2;TT3;TT4;TT5;TT6;TT7;TT8;TT9;TT10;TT11;>;>;
   #15 = Utf8               x
   #16 = Utf8               scala/Product11$
   #17 = Class              #16           // scala/Product11$
   #18 = Utf8               MODULE$
   #19 = Utf8               Lscala/Product11$;
   #20 = NameAndType        #18:#19       // MODULE$:Lscala/Product11$;
   #21 = Fieldref           #17.#20       // scala/Product11$.MODULE$:Lscala/Product11$;
   #22 = Utf8               scala/Some
   #23 = Class              #22           // scala/Some
   #24 = Utf8               <init>
   #25 = Utf8               (Ljava/lang/Object;)V
   #26 = NameAndType        #24:#25       // "<init>":(Ljava/lang/Object;)V
   #27 = Methodref          #23.#26       // scala/Some."<init>":(Ljava/lang/Object;)V
   #28 = Utf8               Lscala/Product11;
   #29 = Utf8               productArity$
   #30 = Utf8               (Lscala/Product11;)I
   #31 = Utf8               $this
   #32 = Utf8               productArity
   #33 = Utf8               ()I
   #34 = NameAndType        #32:#33       // productArity:()I
   #35 = InterfaceMethodref #2.#34        // scala/Product11.productArity:()I
   #36 = Utf8               this
   #37 = Utf8               productElement$
   #38 = Utf8               (Lscala/Product11;I)Ljava/lang/Object;
   #39 = Utf8               n
   #40 = Utf8               productElement
   #41 = Utf8               (I)Ljava/lang/Object;
   #42 = NameAndType        #40:#41       // productElement:(I)Ljava/lang/Object;
   #43 = InterfaceMethodref #2.#42        // scala/Product11.productElement:(I)Ljava/lang/Object;
   #44 = Utf8               I
   #45 = Utf8               java/lang/IndexOutOfBoundsException
   #46 = Class              #45           // java/lang/IndexOutOfBoundsException
   #47 = Utf8               _1
   #48 = Utf8               ()Ljava/lang/Object;
   #49 = NameAndType        #47:#48       // _1:()Ljava/lang/Object;
   #50 = InterfaceMethodref #2.#49        // scala/Product11._1:()Ljava/lang/Object;
   #51 = Utf8               _2
   #52 = NameAndType        #51:#48       // _2:()Ljava/lang/Object;
   #53 = InterfaceMethodref #2.#52        // scala/Product11._2:()Ljava/lang/Object;
   #54 = Utf8               _3
   #55 = NameAndType        #54:#48       // _3:()Ljava/lang/Object;
   #56 = InterfaceMethodref #2.#55        // scala/Product11._3:()Ljava/lang/Object;
   #57 = Utf8               _4
   #58 = NameAndType        #57:#48       // _4:()Ljava/lang/Object;
   #59 = InterfaceMethodref #2.#58        // scala/Product11._4:()Ljava/lang/Object;
   #60 = Utf8               _5
   #61 = NameAndType        #60:#48       // _5:()Ljava/lang/Object;
   #62 = InterfaceMethodref #2.#61        // scala/Product11._5:()Ljava/lang/Object;
   #63 = Utf8               _6
   #64 = NameAndType        #63:#48       // _6:()Ljava/lang/Object;
   #65 = InterfaceMethodref #2.#64        // scala/Product11._6:()Ljava/lang/Object;
   #66 = Utf8               _7
   #67 = NameAndType        #66:#48       // _7:()Ljava/lang/Object;
   #68 = InterfaceMethodref #2.#67        // scala/Product11._7:()Ljava/lang/Object;
   #69 = Utf8               _8
   #70 = NameAndType        #69:#48       // _8:()Ljava/lang/Object;
   #71 = InterfaceMethodref #2.#70        // scala/Product11._8:()Ljava/lang/Object;
   #72 = Utf8               _9
   #73 = NameAndType        #72:#48       // _9:()Ljava/lang/Object;
   #74 = InterfaceMethodref #2.#73        // scala/Product11._9:()Ljava/lang/Object;
   #75 = Utf8               _10
   #76 = NameAndType        #75:#48       // _10:()Ljava/lang/Object;
   #77 = InterfaceMethodref #2.#76        // scala/Product11._10:()Ljava/lang/Object;
   #78 = Utf8               _11
   #79 = NameAndType        #78:#48       // _11:()Ljava/lang/Object;
   #80 = InterfaceMethodref #2.#79        // scala/Product11._11:()Ljava/lang/Object;
   #81 = Utf8               java/lang/StringBuilder
   #82 = Class              #81           // java/lang/StringBuilder
   #83 = Integer            33
   #84 = Utf8               (I)V
   #85 = NameAndType        #24:#84       // "<init>":(I)V
   #86 = Methodref          #82.#85       // java/lang/StringBuilder."<init>":(I)V
   #87 = Utf8               append
   #88 = Utf8               (I)Ljava/lang/StringBuilder;
   #89 = NameAndType        #87:#88       // append:(I)Ljava/lang/StringBuilder;
   #90 = Methodref          #82.#89       // java/lang/StringBuilder.append:(I)Ljava/lang/StringBuilder;
   #91 = Utf8                is out of bounds (min 0, max 10)
   #92 = String             #91           //  is out of bounds (min 0, max 10)
   #93 = Utf8               (Ljava/lang/String;)Ljava/lang/StringBuilder;
   #94 = NameAndType        #87:#93       // append:(Ljava/lang/String;)Ljava/lang/StringBuilder;
   #95 = Methodref          #82.#94       // java/lang/StringBuilder.append:(Ljava/lang/String;)Ljava/lang/StringBuilder;
   #96 = Utf8               toString
   #97 = Utf8               ()Ljava/lang/String;
   #98 = NameAndType        #96:#97       // toString:()Ljava/lang/String;
   #99 = Methodref          #82.#98       // java/lang/StringBuilder.toString:()Ljava/lang/String;
  #100 = Utf8               (Ljava/lang/String;)V
  #101 = NameAndType        #24:#100      // "<init>":(Ljava/lang/String;)V
  #102 = Methodref          #46.#101      // java/lang/IndexOutOfBoundsException."<init>":(Ljava/lang/String;)V
  #103 = Utf8               ()TT1;
  #104 = Utf8               ()TT2;
  #105 = Utf8               ()TT3;
  #106 = Utf8               ()TT4;
  #107 = Utf8               ()TT5;
  #108 = Utf8               ()TT6;
  #109 = Utf8               ()TT7;
  #110 = Utf8               ()TT8;
  #111 = Utf8               ()TT9;
  #112 = Utf8               ()TT10;
  #113 = Utf8               ()TT11;
  #114 = Utf8               $init$
  #115 = Utf8               (Lscala/Product11;)V
  #116 = Utf8               Code
  #117 = Utf8               LineNumberTable
  #118 = Utf8               LocalVariableTable
  #119 = Utf8               Signature
  #120 = Utf8               MethodParameters
  #121 = Utf8               StackMapTable
  #122 = Utf8               Exceptions
  #123 = Utf8               SourceFile
  #124 = Utf8               RuntimeVisibleAnnotations
  #125 = Utf8               ScalaInlineInfo
  #126 = Utf8               ScalaSig
{
  public static <T1 extends java.lang.Object, T2 extends java.lang.Object, T3 extends java.lang.Object, T4 extends java.lang.Object, T5 extends java.lang.Object, T6 extends java.lang.Object, T7 extends java.lang.Object, T8 extends java.lang.Object, T9 extends java.lang.Object, T10 extends java.lang.Object, T11 extends java.lang.Object> scala.Option<scala.Product11<T1, T2, T3, T4, T5, T6, T7, T8, T9, T10, T11>> unapply(scala.Product11<T1, T2, T3, T4, T5, T6, T7, T8, T9, T10, T11>);
    descriptor: (Lscala/Product11;)Lscala/Option;
    flags: (0x0009) ACC_PUBLIC, ACC_STATIC
    Code:
      stack=3, locals=1, args_size=1
         0: getstatic     #21                 // Field scala/Product11$.MODULE$:Lscala/Product11$;
         3: pop
         4: new           #23                 // class scala/Some
         7: dup
         8: aload_0
         9: invokespecial #27                 // Method scala/Some."<init>":(Ljava/lang/Object;)V
        12: areturn
      LineNumberTable:
        line 19: 4
      LocalVariableTable:
        Start  Length  Slot  Name   Signature
            0      13     0     x   Lscala/Product11;
    Signature: #14                          // <T1:Ljava/lang/Object;T2:Ljava/lang/Object;T3:Ljava/lang/Object;T4:Ljava/lang/Object;T5:Ljava/lang/Object;T6:Ljava/lang/Object;T7:Ljava/lang/Object;T8:Ljava/lang/Object;T9:Ljava/lang/Object;T10:Ljava/lang/Object;T11:Ljava/lang/Object;>(Lscala/Product11<TT1;TT2;TT3;TT4;TT5;TT6;TT7;TT8;TT9;TT10;TT11;>;)Lscala/Option<Lscala/Product11<TT1;TT2;TT3;TT4;TT5;TT6;TT7;TT8;TT9;TT10;TT11;>;>;
    MethodParameters:
      Name                           Flags
      x                              final

  public static int productArity$(scala.Product11);
    descriptor: (Lscala/Product11;)I
    flags: (0x1009) ACC_PUBLIC, ACC_STATIC, ACC_SYNTHETIC
    Code:
      stack=1, locals=1, args_size=1
         0: aload_0
         1: invokespecial #35                 // InterfaceMethod productArity:()I
         4: ireturn
      LineNumberTable:
        line 28: 0
      LocalVariableTable:
        Start  Length  Slot  Name   Signature
            0       5     0 $this   Lscala/Product11;
    MethodParameters:
      Name                           Flags
      $this                          final synthetic

  public default int productArity();
    descriptor: ()I
    flags: (0x0001) ACC_PUBLIC
    Code:
      stack=1, locals=1, args_size=1
         0: bipush        11
         2: ireturn
      LineNumberTable:
        line 28: 0
      LocalVariableTable:
        Start  Length  Slot  Name   Signature
            0       3     0  this   Lscala/Product11;

  public static java.lang.Object productElement$(scala.Product11, int);
    descriptor: (Lscala/Product11;I)Ljava/lang/Object;
    flags: (0x1009) ACC_PUBLIC, ACC_STATIC, ACC_SYNTHETIC
    Code:
      stack=2, locals=2, args_size=2
         0: aload_0
         1: iload_1
         2: invokespecial #43                 // InterfaceMethod productElement:(I)Ljava/lang/Object;
         5: areturn
      LineNumberTable:
        line 40: 0
      LocalVariableTable:
        Start  Length  Slot  Name   Signature
            0       6     0 $this   Lscala/Product11;
            0       6     1     n   I
    MethodParameters:
      Name                           Flags
      $this                          final synthetic
      n                              final

  public default java.lang.Object productElement(int) throws java.lang.IndexOutOfBoundsException;
    descriptor: (I)Ljava/lang/Object;
    flags: (0x0001) ACC_PUBLIC
    Code:
      stack=5, locals=2, args_size=2
         0: iload_1
         1: tableswitch   { // 0 to 10
                       0: 60
                       1: 67
                       2: 74
                       3: 81
                       4: 88
                       5: 95
                       6: 102
                       7: 109
                       8: 116
                       9: 123
                      10: 130
                 default: 137
            }
        60: aload_0
        61: invokeinterface #50,  1           // InterfaceMethod _1:()Ljava/lang/Object;
        66: areturn
        67: aload_0
        68: invokeinterface #53,  1           // InterfaceMethod _2:()Ljava/lang/Object;
        73: areturn
        74: aload_0
        75: invokeinterface #56,  1           // InterfaceMethod _3:()Ljava/lang/Object;
        80: areturn
        81: aload_0
        82: invokeinterface #59,  1           // InterfaceMethod _4:()Ljava/lang/Object;
        87: areturn
        88: aload_0
        89: invokeinterface #62,  1           // InterfaceMethod _5:()Ljava/lang/Object;
        94: areturn
        95: aload_0
        96: invokeinterface #65,  1           // InterfaceMethod _6:()Ljava/lang/Object;
       101: areturn
       102: aload_0
       103: invokeinterface #68,  1           // InterfaceMethod _7:()Ljava/lang/Object;
       108: areturn
       109: aload_0
       110: invokeinterface #71,  1           // InterfaceMethod _8:()Ljava/lang/Object;
       115: areturn
       116: aload_0
       117: invokeinterface #74,  1           // InterfaceMethod _9:()Ljava/lang/Object;
       122: areturn
       123: aload_0
       124: invokeinterface #77,  1           // InterfaceMethod _10:()Ljava/lang/Object;
       129: areturn
       130: aload_0
       131: invokeinterface #80,  1           // InterfaceMethod _11:()Ljava/lang/Object;
       136: areturn
       137: new           #46                 // class java/lang/IndexOutOfBoundsException
       140: dup
       141: new           #82                 // class java/lang/StringBuilder
       144: dup
       145: ldc           #83                 // int 33
       147: invokespecial #86                 // Method java/lang/StringBuilder."<init>":(I)V
       150: iload_1
       151: invokevirtual #90                 // Method java/lang/StringBuilder.append:(I)Ljava/lang/StringBuilder;
       154: ldc           #92                 // String  is out of bounds (min 0, max 10)
       156: invokevirtual #95                 // Method java/lang/StringBuilder.append:(Ljava/lang/String;)Ljava/lang/StringBuilder;
       159: invokevirtual #99                 // Method java/lang/StringBuilder.toString:()Ljava/lang/String;
       162: invokespecial #102                // Method java/lang/IndexOutOfBoundsException."<init>":(Ljava/lang/String;)V
       165: athrow
      StackMapTable: number_of_entries = 12
        frame_type = 60 /* same */
        frame_type = 6 /* same */
        frame_type = 6 /* same */
        frame_type = 6 /* same */
        frame_type = 6 /* same */
        frame_type = 6 /* same */
        frame_type = 6 /* same */
        frame_type = 6 /* same */
        frame_type = 6 /* same */
        frame_type = 6 /* same */
        frame_type = 6 /* same */
        frame_type = 6 /* same */
      LineNumberTable:
        line 40: 0
        line 41: 60
        line 42: 67
        line 43: 74
        line 44: 81
        line 45: 88
        line 46: 95
        line 47: 102
        line 48: 109
        line 49: 116
        line 50: 123
        line 51: 130
        line 52: 137
      LocalVariableTable:
        Start  Length  Slot  Name   Signature
            0     166     0  this   Lscala/Product11;
            0     166     1     n   I
    Exceptions:
      throws java.lang.IndexOutOfBoundsException
    MethodParameters:
      Name                           Flags
      n                              final

  public abstract T1 _1();
    descriptor: ()Ljava/lang/Object;
    flags: (0x0401) ACC_PUBLIC, ACC_ABSTRACT
    Signature: #103                         // ()TT1;

  public abstract T2 _2();
    descriptor: ()Ljava/lang/Object;
    flags: (0x0401) ACC_PUBLIC, ACC_ABSTRACT
    Signature: #104                         // ()TT2;

  public abstract T3 _3();
    descriptor: ()Ljava/lang/Object;
    flags: (0x0401) ACC_PUBLIC, ACC_ABSTRACT
    Signature: #105                         // ()TT3;

  public abstract T4 _4();
    descriptor: ()Ljava/lang/Object;
    flags: (0x0401) ACC_PUBLIC, ACC_ABSTRACT
    Signature: #106                         // ()TT4;

  public abstract T5 _5();
    descriptor: ()Ljava/lang/Object;
    flags: (0x0401) ACC_PUBLIC, ACC_ABSTRACT
    Signature: #107                         // ()TT5;

  public abstract T6 _6();
    descriptor: ()Ljava/lang/Object;
    flags: (0x0401) ACC_PUBLIC, ACC_ABSTRACT
    Signature: #108                         // ()TT6;

  public abstract T7 _7();
    descriptor: ()Ljava/lang/Object;
    flags: (0x0401) ACC_PUBLIC, ACC_ABSTRACT
    Signature: #109                         // ()TT7;

  public abstract T8 _8();
    descriptor: ()Ljava/lang/Object;
    flags: (0x0401) ACC_PUBLIC, ACC_ABSTRACT
    Signature: #110                         // ()TT8;

  public abstract T9 _9();
    descriptor: ()Ljava/lang/Object;
    flags: (0x0401) ACC_PUBLIC, ACC_ABSTRACT
    Signature: #111                         // ()TT9;

  public abstract T10 _10();
    descriptor: ()Ljava/lang/Object;
    flags: (0x0401) ACC_PUBLIC, ACC_ABSTRACT
    Signature: #112                         // ()TT10;

  public abstract T11 _11();
    descriptor: ()Ljava/lang/Object;
    flags: (0x0401) ACC_PUBLIC, ACC_ABSTRACT
    Signature: #113                         // ()TT11;

  public static void $init$(scala.Product11);
    descriptor: (Lscala/Product11;)V
    flags: (0x0009) ACC_PUBLIC, ACC_STATIC
    Code:
      stack=0, locals=1, args_size=1
         0: return
      LineNumberTable:
        line 24: 0
      LocalVariableTable:
        Start  Length  Slot  Name   Signature
            0       1     0 $this   Lscala/Product11;
    MethodParameters:
      Name                           Flags
      $this                          final synthetic
}
Signature: #3                           // <T1:Ljava/lang/Object;T2:Ljava/lang/Object;T3:Ljava/lang/Object;T4:Ljava/lang/Object;T5:Ljava/lang/Object;T6:Ljava/lang/Object;T7:Ljava/lang/Object;T8:Ljava/lang/Object;T9:Ljava/lang/Object;T10:Ljava/lang/Object;T11:Ljava/lang/Object;>Ljava/lang/Object;Lscala/Product;
SourceFile: "Product11.scala"
RuntimeVisibleAnnotations:
  0: #9(#10=s#11)
    scala.reflect.ScalaSignature(
      bytes="\u0006\u0005\u0005mr!B\n\u0015\u0011\u00039b!B\r\u0015\u0011\u0003Q\u0002\"\u0002\u0010\u0002\t\u0003y\u0002\"\u0002\u0011\u0002\t\u0003\tcaB\r\u0015!\u0003\r\ta\n\u0005\u0006_\u0011!\t\u0001\r\u0005\u0006i\u0011!\t%\u000e\u0005\u0006s\u0011!\tE\u000f\u0005\u0006\u0013\u00121\tA\u0013\u0005\u0006\'\u00121\t\u0001\u0016\u0005\u00061\u00121\t!\u0017\u0005\u0006;\u00121\tA\u0018\u0005\u0006E\u00121\ta\u0019\u0005\u0006O\u00121\t\u0001\u001b\u0005\u0006Y\u00121\t!\u001c\u0005\u0006c\u00121\tA\u001d\u0005\u0006m\u00121\ta\u001e\u0005\u0006w\u00121\t\u0001 \u0005\b\u0003\u0003!a\u0011AA\u0002\u0003%\u0001&o\u001c3vGR\f\u0014GC\u0001\u0016\u0003\u0015\u00198-\u00197b\u0007\u0001\u0001\"\u0001G\u0001\u000e\u0003Q\u0011\u0011\u0002\u0015:pIV\u001cG/M\u0019\u0014\u0005\u0005Y\u0002C\u0001\r\u001d\u0013\tiBC\u0001\u0004B]f\u0014VMZ\u0001\u0007y%t\u0017\u000e\u001e \u0015\u0003]\tq!\u001e8baBd\u00170F\f#\u0003\u001b\t\t\"!\u0006\u0002\u001a\u0005u\u0011\u0011EA\u0013\u0003S\ti#!\r\u00026Q\u00191%a\u000e\u0011\u0007a!c%\u0003\u0002&)\t1q\n\u001d;j_:\u0004\u0002\u0004\u0007\u0003\u0002\f\u0005=\u00111CA\f\u00037\ty\"a\t\u0002(\u0005-\u0012qFA\u001a+5ASJV.aK*|G/\u001f@\u0002\bM\u0019A!\u000b\u0017\u0011\u0005aQ\u0013BA\u0016\u0015\u0005\r\te.\u001f\t\u000315J!A\f\u000b\u0003\u000fA\u0013x\u000eZ;di\u00061A%\u001b8ji\u0012\"\u0012!\r\t\u00031IJ!a\r\u000b\u0003\tUs\u0017\u000e^\u0001\raJ|G-^2u\u0003JLG/_\u000b\u0002mA\u0011\u0001dN\u0005\u0003qQ\u00111!\u00138u\u00039\u0001(o\u001c3vGR,E.Z7f]R$\"!K\u001e\t\u000bq:\u0001\u0019\u0001\u001c\u0002\u00039D3a\u0002 I!\rAr(Q\u0005\u0003\u0001R\u0011a\u0001\u001e5s_^\u001c\bC\u0001\"F\u001d\tA2)\u0003\u0002E)\u00059\u0001/Y2lC\u001e,\u0017B\u0001$H\u0005eIe\u000eZ3y\u001fV$xJ\u001a\"pk:$7/\u0012=dKB$\u0018n\u001c8\u000b\u0005\u0011#2%A!\u0002\u0005}\u000bT#A&\u0011\u00051kE\u0002\u0001\u0003\u0007\u001d\u0012!)\u0019A(\u0003\u0005Q\u000b\u0014C\u0001)*!\tA\u0012+\u0003\u0002S)\t9aj\u001c;iS:<\u0017AA03+\u0005)\u0006C\u0001\'W\t\u00199F\u0001\"b\u0001\u001f\n\u0011AKM\u0001\u0003?N*\u0012A\u0017\t\u0003\u0019n#a\u0001\u0018\u0003\u0005\u0006\u0004y%A\u0001+4\u0003\tyF\'F\u0001`!\ta\u0005\r\u0002\u0004b\t\u0011\u0015\ra\u0014\u0002\u0003)R\n!aX\u001b\u0016\u0003\u0011\u0004\"\u0001T3\u0005\r\u0019$AQ1\u0001P\u0005\t!V\'\u0001\u0002`mU\t\u0011\u000e\u0005\u0002MU\u001211\u000e\u0002CC\u0002=\u0013!\u0001\u0016\u001c\u0002\u0005};T#\u00018\u0011\u00051{GA\u00029\u0005\t\u000b\u0007qJ\u0001\u0002Uo\u0005\u0011q\fO\u000b\u0002gB\u0011A\n\u001e\u0003\u0007k\u0012!)\u0019A(\u0003\u0005QC\u0014AA0:+\u0005A\bC\u0001\'z\t\u0019QH\u0001\"b\u0001\u001f\n\u0011A+O\u0001\u0004?F\u0002T#A?\u0011\u00051sHAB@\u0005\t\u000b\u0007qJA\u0002UcA\n1aX\u00192+\t\t)\u0001E\u0002M\u0003\u000f!q!!\u0003\u0005\t\u000b\u0007qJA\u0002UcE\u00022\u0001TA\u0007\t\u0015q5A1\u0001P!\ra\u0015\u0011\u0003\u0003\u0006/\u000e\u0011\ra\u0014\t\u0004\u0019\u0006UA!\u0002/\u0004\u0005\u0004y\u0005c\u0001\'\u0002\u001a\u0011)\u0011m\u0001b\u0001\u001fB\u0019A*!\b\u0005\u000b\u0019\u001c!\u0019A(\u0011\u00071\u000b\t\u0003B\u0003l\u0007\t\u0007q\nE\u0002M\u0003K!Q\u0001]\u0002C\u0002=\u00032\u0001TA\u0015\t\u0015)8A1\u0001P!\ra\u0015Q\u0006\u0003\u0006u\u000e\u0011\ra\u0014\t\u0004\u0019\u0006EB!B@\u0004\u0005\u0004y\u0005c\u0001\'\u00026\u00111\u0011\u0011B\u0002C\u0002=Ca!!\u000f\u0004\u0001\u00041\u0013!\u0001="
    )
  ScalaInlineInfo: length = 0x54 (unknown attribute)
   01 00 00 10 00 72 00 73 01 00 2F 00 30 00 00 4B
   00 30 00 00 4E 00 30 00 00 33 00 30 00 00 36 00
   30 00 00 39 00 30 00 00 3C 00 30 00 00 3F 00 30
   00 00 42 00 30 00 00 45 00 30 00 00 48 00 30 00
   00 20 00 21 00 00 1D 00 1E 01 00 28 00 29 00 00
   25 00 26 01
  ScalaSig: length = 0x3 (unknown attribute)
   05 02 00
