Classfile /Users/mw/Projects/slang-braindump/.jar/jar8/assemble/slang-braindump/assemble/content/scala/Product8.class
  Last modified May 29, 2022; size 3539 bytes
  SHA-256 checksum 7055d970fd8770d7e0655e63be2113b3930e114a631e1fa8a49b2c7d811f5886
  Compiled from "Product8.scala"
public interface scala.Product8<T1 extends java.lang.Object, T2 extends java.lang.Object, T3 extends java.lang.Object, T4 extends java.lang.Object, T5 extends java.lang.Object, T6 extends java.lang.Object, T7 extends java.lang.Object, T8 extends java.lang.Object> extends scala.Product
  minor version: 0
  major version: 52
  flags: (0x0601) ACC_PUBLIC, ACC_INTERFACE, ACC_ABSTRACT
  this_class: #2                          // scala/Product8
  super_class: #5                         // java/lang/Object
  interfaces: 1, fields: 0, methods: 14, attributes: 5
Constant pool:
    #1 = Utf8               scala/Product8
    #2 = Class              #1            // scala/Product8
    #3 = Utf8               <T1:Ljava/lang/Object;T2:Ljava/lang/Object;T3:Ljava/lang/Object;T4:Ljava/lang/Object;T5:Ljava/lang/Object;T6:Ljava/lang/Object;T7:Ljava/lang/Object;T8:Ljava/lang/Object;>Ljava/lang/Object;Lscala/Product;
    #4 = Utf8               java/lang/Object
    #5 = Class              #4            // java/lang/Object
    #6 = Utf8               scala/Product
    #7 = Class              #6            // scala/Product
    #8 = Utf8               Product8.scala
    #9 = Utf8               Lscala/reflect/ScalaSignature;
   #10 = Utf8               bytes
   #11 = Utf8               \u0006\u0005\u0005-q!\u0002\t\u0012\u0011\u0003!b!\u0002\f\u0012\u0011\u00039\u0002\"B\u000e\u0002\t\u0003a\u0002\"B\u000f\u0002\t\u0003qba\u0002\f\u0012!\u0003\r\t\u0001\n\u0005\u0006Y\u0011!\t!\f\u0005\u0006c\u0011!\tE\r\u0005\u0006m\u0011!\te\u000e\u0005\u0006\r\u00121\ta\u0012\u0005\u0006!\u00121\t!\u0015\u0005\u0006+\u00121\tA\u0016\u0005\u00065\u00121\ta\u0017\u0005\u0006?\u00121\t\u0001\u0019\u0005\u0006I\u00121\t!\u001a\u0005\u0006S\u00121\tA\u001b\u0005\u0006]\u00121\ta\\\u0001\t!J|G-^2uq)\t!#A\u0003tG\u0006d\u0017m\u0001\u0001\u0011\u0005U\tQ\"A\t\u0003\u0011A\u0013x\u000eZ;dib\u001a\"!\u0001\r\u0011\u0005UI\u0012B\u0001\u000e\u0012\u0005\u0019\te.\u001f*fM\u00061A(\u001b8jiz\"\u0012\u0001F\u0001\bk:\f\u0007\u000f\u001d7z+-yBO\u001e={yz\f\t!!\u0002\u0015\u0007\u0001\n9\u0001E\u0002\u0016C\rJ!AI\t\u0003\r=\u0003H/[8o!-)Ba];xsnlx0a\u0001\u0016\u0013\u0015R5\u000bW/cO2\f8c\u0001\u0003\'SA\u0011QcJ\u0005\u0003QE\u00111!\u00118z!\t)\"&\u0003\u0002,#\t9\u0001K]8ek\u000e$\u0018A\u0002\u0013j]&$H\u0005F\u0001/!\t)r&\u0003\u00021#\t!QK\\5u\u00031\u0001(o\u001c3vGR\f%/\u001b;z+\u0005\u0019\u0004CA\u000b5\u0013\t)\u0014CA\u0002J]R\fa\u0002\u001d:pIV\u001cG/\u00127f[\u0016tG\u000f\u0006\u0002\'q!)\u0011h\u0002a\u0001g\u0005\ta\u000eK\u0002\bw\u0015\u00032!\u0006\u001f?\u0013\ti\u0014C\u0001\u0004uQJ|wo\u001d\t\u0003\u007f\ts!!\u0006!\n\u0005\u0005\u000b\u0012a\u00029bG.\fw-Z\u0005\u0003\u0007\u0012\u0013\u0011$\u00138eKb|U\u000f^(g\u0005>,h\u000eZ:Fq\u000e,\u0007\u000f^5p]*\u0011\u0011)E\u0012\u0002}\u0005\u0011q,M\u000b\u0002\u0011B\u0011\u0011J\u0013\u0007\u0001\t\u0019YE\u0001\"b\u0001\u0019\n\u0011A+M\t\u0003\u001b\u001a\u0002\"!\u0006(\n\u0005=\u000b\"a\u0002(pi\"LgnZ\u0001\u0003?J*\u0012A\u0015\t\u0003\u0013N#a\u0001\u0016\u0003\u0005\u0006\u0004a%A\u0001+3\u0003\ty6\'F\u0001X!\tI\u0005\f\u0002\u0004Z\t\u0011\u0015\r\u0001\u0014\u0002\u0003)N\n!a\u0018\u001b\u0016\u0003q\u0003\"!S/\u0005\ry#AQ1\u0001M\u0005\t!F\'\u0001\u0002`kU\t\u0011\r\u0005\u0002JE\u001211\r\u0002CC\u00021\u0013!\u0001V\u001b\u0002\u0005}3T#\u00014\u0011\u0005%;GA\u00025\u0005\t\u000b\u0007AJ\u0001\u0002Um\u0005\u0011qlN\u000b\u0002WB\u0011\u0011\n\u001c\u0003\u0007[\u0012!)\u0019\u0001\'\u0003\u0005Q;\u0014AA09+\u0005\u0001\bCA%r\t\u0019\u0011H\u0001\"b\u0001\u0019\n\u0011A\u000b\u000f\t\u0003\u0013R$QaS\u0002C\u00021\u0003\"!\u0013<\u0005\u000bQ\u001b!\u0019\u0001\'\u0011\u0005%CH!B-\u0004\u0005\u0004a\u0005CA%{\t\u0015q6A1\u0001M!\tIE\u0010B\u0003d\u0007\t\u0007A\n\u0005\u0002J}\u0012)\u0001n\u0001b\u0001\u0019B\u0019\u0011*!\u0001\u0005\u000b5\u001c!\u0019\u0001\'\u0011\u0007%\u000b)\u0001B\u0003s\u0007\t\u0007A\n\u0003\u0004\u0002\n\r\u0001\raI\u0001\u0002q\u0002
   #12 = Utf8               unapply
   #13 = Utf8               (Lscala/Product8;)Lscala/Option;
   #14 = Utf8               <T1:Ljava/lang/Object;T2:Ljava/lang/Object;T3:Ljava/lang/Object;T4:Ljava/lang/Object;T5:Ljava/lang/Object;T6:Ljava/lang/Object;T7:Ljava/lang/Object;T8:Ljava/lang/Object;>(Lscala/Product8<TT1;TT2;TT3;TT4;TT5;TT6;TT7;TT8;>;)Lscala/Option<Lscala/Product8<TT1;TT2;TT3;TT4;TT5;TT6;TT7;TT8;>;>;
   #15 = Utf8               x
   #16 = Utf8               scala/Product8$
   #17 = Class              #16           // scala/Product8$
   #18 = Utf8               MODULE$
   #19 = Utf8               Lscala/Product8$;
   #20 = NameAndType        #18:#19       // MODULE$:Lscala/Product8$;
   #21 = Fieldref           #17.#20       // scala/Product8$.MODULE$:Lscala/Product8$;
   #22 = Utf8               scala/Some
   #23 = Class              #22           // scala/Some
   #24 = Utf8               <init>
   #25 = Utf8               (Ljava/lang/Object;)V
   #26 = NameAndType        #24:#25       // "<init>":(Ljava/lang/Object;)V
   #27 = Methodref          #23.#26       // scala/Some."<init>":(Ljava/lang/Object;)V
   #28 = Utf8               Lscala/Product8;
   #29 = Utf8               productArity$
   #30 = Utf8               (Lscala/Product8;)I
   #31 = Utf8               $this
   #32 = Utf8               productArity
   #33 = Utf8               ()I
   #34 = NameAndType        #32:#33       // productArity:()I
   #35 = InterfaceMethodref #2.#34        // scala/Product8.productArity:()I
   #36 = Utf8               this
   #37 = Utf8               productElement$
   #38 = Utf8               (Lscala/Product8;I)Ljava/lang/Object;
   #39 = Utf8               n
   #40 = Utf8               productElement
   #41 = Utf8               (I)Ljava/lang/Object;
   #42 = NameAndType        #40:#41       // productElement:(I)Ljava/lang/Object;
   #43 = InterfaceMethodref #2.#42        // scala/Product8.productElement:(I)Ljava/lang/Object;
   #44 = Utf8               I
   #45 = Utf8               java/lang/IndexOutOfBoundsException
   #46 = Class              #45           // java/lang/IndexOutOfBoundsException
   #47 = Utf8               _1
   #48 = Utf8               ()Ljava/lang/Object;
   #49 = NameAndType        #47:#48       // _1:()Ljava/lang/Object;
   #50 = InterfaceMethodref #2.#49        // scala/Product8._1:()Ljava/lang/Object;
   #51 = Utf8               _2
   #52 = NameAndType        #51:#48       // _2:()Ljava/lang/Object;
   #53 = InterfaceMethodref #2.#52        // scala/Product8._2:()Ljava/lang/Object;
   #54 = Utf8               _3
   #55 = NameAndType        #54:#48       // _3:()Ljava/lang/Object;
   #56 = InterfaceMethodref #2.#55        // scala/Product8._3:()Ljava/lang/Object;
   #57 = Utf8               _4
   #58 = NameAndType        #57:#48       // _4:()Ljava/lang/Object;
   #59 = InterfaceMethodref #2.#58        // scala/Product8._4:()Ljava/lang/Object;
   #60 = Utf8               _5
   #61 = NameAndType        #60:#48       // _5:()Ljava/lang/Object;
   #62 = InterfaceMethodref #2.#61        // scala/Product8._5:()Ljava/lang/Object;
   #63 = Utf8               _6
   #64 = NameAndType        #63:#48       // _6:()Ljava/lang/Object;
   #65 = InterfaceMethodref #2.#64        // scala/Product8._6:()Ljava/lang/Object;
   #66 = Utf8               _7
   #67 = NameAndType        #66:#48       // _7:()Ljava/lang/Object;
   #68 = InterfaceMethodref #2.#67        // scala/Product8._7:()Ljava/lang/Object;
   #69 = Utf8               _8
   #70 = NameAndType        #69:#48       // _8:()Ljava/lang/Object;
   #71 = InterfaceMethodref #2.#70        // scala/Product8._8:()Ljava/lang/Object;
   #72 = Utf8               java/lang/StringBuilder
   #73 = Class              #72           // java/lang/StringBuilder
   #74 = Integer            32
   #75 = Utf8               (I)V
   #76 = NameAndType        #24:#75       // "<init>":(I)V
   #77 = Methodref          #73.#76       // java/lang/StringBuilder."<init>":(I)V
   #78 = Utf8               append
   #79 = Utf8               (I)Ljava/lang/StringBuilder;
   #80 = NameAndType        #78:#79       // append:(I)Ljava/lang/StringBuilder;
   #81 = Methodref          #73.#80       // java/lang/StringBuilder.append:(I)Ljava/lang/StringBuilder;
   #82 = Utf8                is out of bounds (min 0, max 7)
   #83 = String             #82           //  is out of bounds (min 0, max 7)
   #84 = Utf8               (Ljava/lang/String;)Ljava/lang/StringBuilder;
   #85 = NameAndType        #78:#84       // append:(Ljava/lang/String;)Ljava/lang/StringBuilder;
   #86 = Methodref          #73.#85       // java/lang/StringBuilder.append:(Ljava/lang/String;)Ljava/lang/StringBuilder;
   #87 = Utf8               toString
   #88 = Utf8               ()Ljava/lang/String;
   #89 = NameAndType        #87:#88       // toString:()Ljava/lang/String;
   #90 = Methodref          #73.#89       // java/lang/StringBuilder.toString:()Ljava/lang/String;
   #91 = Utf8               (Ljava/lang/String;)V
   #92 = NameAndType        #24:#91       // "<init>":(Ljava/lang/String;)V
   #93 = Methodref          #46.#92       // java/lang/IndexOutOfBoundsException."<init>":(Ljava/lang/String;)V
   #94 = Utf8               ()TT1;
   #95 = Utf8               ()TT2;
   #96 = Utf8               ()TT3;
   #97 = Utf8               ()TT4;
   #98 = Utf8               ()TT5;
   #99 = Utf8               ()TT6;
  #100 = Utf8               ()TT7;
  #101 = Utf8               ()TT8;
  #102 = Utf8               $init$
  #103 = Utf8               (Lscala/Product8;)V
  #104 = Utf8               Code
  #105 = Utf8               LineNumberTable
  #106 = Utf8               LocalVariableTable
  #107 = Utf8               Signature
  #108 = Utf8               MethodParameters
  #109 = Utf8               StackMapTable
  #110 = Utf8               Exceptions
  #111 = Utf8               SourceFile
  #112 = Utf8               RuntimeVisibleAnnotations
  #113 = Utf8               ScalaInlineInfo
  #114 = Utf8               ScalaSig
{
  public static <T1 extends java.lang.Object, T2 extends java.lang.Object, T3 extends java.lang.Object, T4 extends java.lang.Object, T5 extends java.lang.Object, T6 extends java.lang.Object, T7 extends java.lang.Object, T8 extends java.lang.Object> scala.Option<scala.Product8<T1, T2, T3, T4, T5, T6, T7, T8>> unapply(scala.Product8<T1, T2, T3, T4, T5, T6, T7, T8>);
    descriptor: (Lscala/Product8;)Lscala/Option;
    flags: (0x0009) ACC_PUBLIC, ACC_STATIC
    Code:
      stack=3, locals=1, args_size=1
         0: getstatic     #21                 // Field scala/Product8$.MODULE$:Lscala/Product8$;
         3: pop
         4: new           #23                 // class scala/Some
         7: dup
         8: aload_0
         9: invokespecial #27                 // Method scala/Some."<init>":(Ljava/lang/Object;)V
        12: areturn
      LineNumberTable:
        line 19: 4
      LocalVariableTable:
        Start  Length  Slot  Name   Signature
            0      13     0     x   Lscala/Product8;
    Signature: #14                          // <T1:Ljava/lang/Object;T2:Ljava/lang/Object;T3:Ljava/lang/Object;T4:Ljava/lang/Object;T5:Ljava/lang/Object;T6:Ljava/lang/Object;T7:Ljava/lang/Object;T8:Ljava/lang/Object;>(Lscala/Product8<TT1;TT2;TT3;TT4;TT5;TT6;TT7;TT8;>;)Lscala/Option<Lscala/Product8<TT1;TT2;TT3;TT4;TT5;TT6;TT7;TT8;>;>;
    MethodParameters:
      Name                           Flags
      x                              final

  public static int productArity$(scala.Product8);
    descriptor: (Lscala/Product8;)I
    flags: (0x1009) ACC_PUBLIC, ACC_STATIC, ACC_SYNTHETIC
    Code:
      stack=1, locals=1, args_size=1
         0: aload_0
         1: invokespecial #35                 // InterfaceMethod productArity:()I
         4: ireturn
      LineNumberTable:
        line 28: 0
      LocalVariableTable:
        Start  Length  Slot  Name   Signature
            0       5     0 $this   Lscala/Product8;
    MethodParameters:
      Name                           Flags
      $this                          final synthetic

  public default int productArity();
    descriptor: ()I
    flags: (0x0001) ACC_PUBLIC
    Code:
      stack=1, locals=1, args_size=1
         0: bipush        8
         2: ireturn
      LineNumberTable:
        line 28: 0
      LocalVariableTable:
        Start  Length  Slot  Name   Signature
            0       3     0  this   Lscala/Product8;

  public static java.lang.Object productElement$(scala.Product8, int);
    descriptor: (Lscala/Product8;I)Ljava/lang/Object;
    flags: (0x1009) ACC_PUBLIC, ACC_STATIC, ACC_SYNTHETIC
    Code:
      stack=2, locals=2, args_size=2
         0: aload_0
         1: iload_1
         2: invokespecial #43                 // InterfaceMethod productElement:(I)Ljava/lang/Object;
         5: areturn
      LineNumberTable:
        line 40: 0
      LocalVariableTable:
        Start  Length  Slot  Name   Signature
            0       6     0 $this   Lscala/Product8;
            0       6     1     n   I
    MethodParameters:
      Name                           Flags
      $this                          final synthetic
      n                              final

  public default java.lang.Object productElement(int) throws java.lang.IndexOutOfBoundsException;
    descriptor: (I)Ljava/lang/Object;
    flags: (0x0001) ACC_PUBLIC
    Code:
      stack=5, locals=2, args_size=2
         0: iload_1
         1: tableswitch   { // 0 to 7
                       0: 48
                       1: 55
                       2: 62
                       3: 69
                       4: 76
                       5: 83
                       6: 90
                       7: 97
                 default: 104
            }
        48: aload_0
        49: invokeinterface #50,  1           // InterfaceMethod _1:()Ljava/lang/Object;
        54: areturn
        55: aload_0
        56: invokeinterface #53,  1           // InterfaceMethod _2:()Ljava/lang/Object;
        61: areturn
        62: aload_0
        63: invokeinterface #56,  1           // InterfaceMethod _3:()Ljava/lang/Object;
        68: areturn
        69: aload_0
        70: invokeinterface #59,  1           // InterfaceMethod _4:()Ljava/lang/Object;
        75: areturn
        76: aload_0
        77: invokeinterface #62,  1           // InterfaceMethod _5:()Ljava/lang/Object;
        82: areturn
        83: aload_0
        84: invokeinterface #65,  1           // InterfaceMethod _6:()Ljava/lang/Object;
        89: areturn
        90: aload_0
        91: invokeinterface #68,  1           // InterfaceMethod _7:()Ljava/lang/Object;
        96: areturn
        97: aload_0
        98: invokeinterface #71,  1           // InterfaceMethod _8:()Ljava/lang/Object;
       103: areturn
       104: new           #46                 // class java/lang/IndexOutOfBoundsException
       107: dup
       108: new           #73                 // class java/lang/StringBuilder
       111: dup
       112: ldc           #74                 // int 32
       114: invokespecial #77                 // Method java/lang/StringBuilder."<init>":(I)V
       117: iload_1
       118: invokevirtual #81                 // Method java/lang/StringBuilder.append:(I)Ljava/lang/StringBuilder;
       121: ldc           #83                 // String  is out of bounds (min 0, max 7)
       123: invokevirtual #86                 // Method java/lang/StringBuilder.append:(Ljava/lang/String;)Ljava/lang/StringBuilder;
       126: invokevirtual #90                 // Method java/lang/StringBuilder.toString:()Ljava/lang/String;
       129: invokespecial #93                 // Method java/lang/IndexOutOfBoundsException."<init>":(Ljava/lang/String;)V
       132: athrow
      StackMapTable: number_of_entries = 9
        frame_type = 48 /* same */
        frame_type = 6 /* same */
        frame_type = 6 /* same */
        frame_type = 6 /* same */
        frame_type = 6 /* same */
        frame_type = 6 /* same */
        frame_type = 6 /* same */
        frame_type = 6 /* same */
        frame_type = 6 /* same */
      LineNumberTable:
        line 40: 0
        line 41: 48
        line 42: 55
        line 43: 62
        line 44: 69
        line 45: 76
        line 46: 83
        line 47: 90
        line 48: 97
        line 49: 104
      LocalVariableTable:
        Start  Length  Slot  Name   Signature
            0     133     0  this   Lscala/Product8;
            0     133     1     n   I
    Exceptions:
      throws java.lang.IndexOutOfBoundsException
    MethodParameters:
      Name                           Flags
      n                              final

  public abstract T1 _1();
    descriptor: ()Ljava/lang/Object;
    flags: (0x0401) ACC_PUBLIC, ACC_ABSTRACT
    Signature: #94                          // ()TT1;

  public abstract T2 _2();
    descriptor: ()Ljava/lang/Object;
    flags: (0x0401) ACC_PUBLIC, ACC_ABSTRACT
    Signature: #95                          // ()TT2;

  public abstract T3 _3();
    descriptor: ()Ljava/lang/Object;
    flags: (0x0401) ACC_PUBLIC, ACC_ABSTRACT
    Signature: #96                          // ()TT3;

  public abstract T4 _4();
    descriptor: ()Ljava/lang/Object;
    flags: (0x0401) ACC_PUBLIC, ACC_ABSTRACT
    Signature: #97                          // ()TT4;

  public abstract T5 _5();
    descriptor: ()Ljava/lang/Object;
    flags: (0x0401) ACC_PUBLIC, ACC_ABSTRACT
    Signature: #98                          // ()TT5;

  public abstract T6 _6();
    descriptor: ()Ljava/lang/Object;
    flags: (0x0401) ACC_PUBLIC, ACC_ABSTRACT
    Signature: #99                          // ()TT6;

  public abstract T7 _7();
    descriptor: ()Ljava/lang/Object;
    flags: (0x0401) ACC_PUBLIC, ACC_ABSTRACT
    Signature: #100                         // ()TT7;

  public abstract T8 _8();
    descriptor: ()Ljava/lang/Object;
    flags: (0x0401) ACC_PUBLIC, ACC_ABSTRACT
    Signature: #101                         // ()TT8;

  public static void $init$(scala.Product8);
    descriptor: (Lscala/Product8;)V
    flags: (0x0009) ACC_PUBLIC, ACC_STATIC
    Code:
      stack=0, locals=1, args_size=1
         0: return
      LineNumberTable:
        line 24: 0
      LocalVariableTable:
        Start  Length  Slot  Name   Signature
            0       1     0 $this   Lscala/Product8;
    MethodParameters:
      Name                           Flags
      $this                          final synthetic
}
Signature: #3                           // <T1:Ljava/lang/Object;T2:Ljava/lang/Object;T3:Ljava/lang/Object;T4:Ljava/lang/Object;T5:Ljava/lang/Object;T6:Ljava/lang/Object;T7:Ljava/lang/Object;T8:Ljava/lang/Object;>Ljava/lang/Object;Lscala/Product;
SourceFile: "Product8.scala"
RuntimeVisibleAnnotations:
  0: #9(#10=s#11)
    scala.reflect.ScalaSignature(
      bytes="\u0006\u0005\u0005-q!\u0002\t\u0012\u0011\u0003!b!\u0002\f\u0012\u0011\u00039\u0002\"B\u000e\u0002\t\u0003a\u0002\"B\u000f\u0002\t\u0003qba\u0002\f\u0012!\u0003\r\t\u0001\n\u0005\u0006Y\u0011!\t!\f\u0005\u0006c\u0011!\tE\r\u0005\u0006m\u0011!\te\u000e\u0005\u0006\r\u00121\ta\u0012\u0005\u0006!\u00121\t!\u0015\u0005\u0006+\u00121\tA\u0016\u0005\u00065\u00121\ta\u0017\u0005\u0006?\u00121\t\u0001\u0019\u0005\u0006I\u00121\t!\u001a\u0005\u0006S\u00121\tA\u001b\u0005\u0006]\u00121\ta\\\u0001\t!J|G-^2uq)\t!#A\u0003tG\u0006d\u0017m\u0001\u0001\u0011\u0005U\tQ\"A\t\u0003\u0011A\u0013x\u000eZ;dib\u001a\"!\u0001\r\u0011\u0005UI\u0012B\u0001\u000e\u0012\u0005\u0019\te.\u001f*fM\u00061A(\u001b8jiz\"\u0012\u0001F\u0001\bk:\f\u0007\u000f\u001d7z+-yBO\u001e={yz\f\t!!\u0002\u0015\u0007\u0001\n9\u0001E\u0002\u0016C\rJ!AI\t\u0003\r=\u0003H/[8o!-)Ba];xsnlx0a\u0001\u0016\u0013\u0015R5\u000bW/cO2\f8c\u0001\u0003\'SA\u0011QcJ\u0005\u0003QE\u00111!\u00118z!\t)\"&\u0003\u0002,#\t9\u0001K]8ek\u000e$\u0018A\u0002\u0013j]&$H\u0005F\u0001/!\t)r&\u0003\u00021#\t!QK\\5u\u00031\u0001(o\u001c3vGR\f%/\u001b;z+\u0005\u0019\u0004CA\u000b5\u0013\t)\u0014CA\u0002J]R\fa\u0002\u001d:pIV\u001cG/\u00127f[\u0016tG\u000f\u0006\u0002\'q!)\u0011h\u0002a\u0001g\u0005\ta\u000eK\u0002\bw\u0015\u00032!\u0006\u001f?\u0013\ti\u0014C\u0001\u0004uQJ|wo\u001d\t\u0003\u007f\ts!!\u0006!\n\u0005\u0005\u000b\u0012a\u00029bG.\fw-Z\u0005\u0003\u0007\u0012\u0013\u0011$\u00138eKb|U\u000f^(g\u0005>,h\u000eZ:Fq\u000e,\u0007\u000f^5p]*\u0011\u0011)E\u0012\u0002}\u0005\u0011q,M\u000b\u0002\u0011B\u0011\u0011J\u0013\u0007\u0001\t\u0019YE\u0001\"b\u0001\u0019\n\u0011A+M\t\u0003\u001b\u001a\u0002\"!\u0006(\n\u0005=\u000b\"a\u0002(pi\"LgnZ\u0001\u0003?J*\u0012A\u0015\t\u0003\u0013N#a\u0001\u0016\u0003\u0005\u0006\u0004a%A\u0001+3\u0003\ty6\'F\u0001X!\tI\u0005\f\u0002\u0004Z\t\u0011\u0015\r\u0001\u0014\u0002\u0003)N\n!a\u0018\u001b\u0016\u0003q\u0003\"!S/\u0005\ry#AQ1\u0001M\u0005\t!F\'\u0001\u0002`kU\t\u0011\r\u0005\u0002JE\u001211\r\u0002CC\u00021\u0013!\u0001V\u001b\u0002\u0005}3T#\u00014\u0011\u0005%;GA\u00025\u0005\t\u000b\u0007AJ\u0001\u0002Um\u0005\u0011qlN\u000b\u0002WB\u0011\u0011\n\u001c\u0003\u0007[\u0012!)\u0019\u0001\'\u0003\u0005Q;\u0014AA09+\u0005\u0001\bCA%r\t\u0019\u0011H\u0001\"b\u0001\u0019\n\u0011A\u000b\u000f\t\u0003\u0013R$QaS\u0002C\u00021\u0003\"!\u0013<\u0005\u000bQ\u001b!\u0019\u0001\'\u0011\u0005%CH!B-\u0004\u0005\u0004a\u0005CA%{\t\u0015q6A1\u0001M!\tIE\u0010B\u0003d\u0007\t\u0007A\n\u0005\u0002J}\u0012)\u0001n\u0001b\u0001\u0019B\u0019\u0011*!\u0001\u0005\u000b5\u001c!\u0019\u0001\'\u0011\u0007%\u000b)\u0001B\u0003s\u0007\t\u0007A\n\u0003\u0004\u0002\n\r\u0001\raI\u0001\u0002q\u0002"
    )
  ScalaInlineInfo: length = 0x45 (unknown attribute)
   01 00 00 0D 00 66 00 67 01 00 2F 00 30 00 00 33
   00 30 00 00 36 00 30 00 00 39 00 30 00 00 3C 00
   30 00 00 3F 00 30 00 00 42 00 30 00 00 45 00 30
   00 00 20 00 21 00 00 1D 00 1E 01 00 28 00 29 00
   00 25 00 26 01
  ScalaSig: length = 0x3 (unknown attribute)
   05 02 00
