Classfile /Users/mw/Projects/slang-braindump/.jar/jar8/assemble/slang-braindump/assemble/content/scala/StringContext.class
  Last modified May 29, 2022; size 8892 bytes
  SHA-256 checksum e249d34d84637464120cdcf7fc1ccb9396efe973435203d82a86b3e640750e47
  Compiled from "StringContext.scala"
public class scala.StringContext implements scala.Product,java.io.Serializable
  minor version: 0
  major version: 52
  flags: (0x0021) ACC_PUBLIC, ACC_SUPER
  this_class: #2                          // scala/StringContext
  super_class: #4                         // java/lang/Object
  interfaces: 2, fields: 2, methods: 21, attributes: 5
Constant pool:
    #1 = Utf8               scala/StringContext
    #2 = Class              #1            // scala/StringContext
    #3 = Utf8               java/lang/Object
    #4 = Class              #3            // java/lang/Object
    #5 = Utf8               scala/Product
    #6 = Class              #5            // scala/Product
    #7 = Utf8               java/io/Serializable
    #8 = Class              #7            // java/io/Serializable
    #9 = Utf8               StringContext.scala
   #10 = Utf8               Lscala/reflect/ScalaSignature;
   #11 = Utf8               bytes
   #12 = Utf8               \u0006\u0005\t\u0015c\u0001B\u00193\u0001VB\u0001\"\u0013\u0001\u0003\u0016\u0004%\tA\u0013\u0005\t-\u0002\u0011\t\u0012)A\u0005\u0017\")q\u000b\u0001C\u00011\")1\f\u0001C\u00019\"1Q\u000f\u0001B\u0005\u0002Y<Q!\u001e\u0001\t\u0002e4Qa\u001f\u0001\t\u0002qDQaV\u0004\u0005\u0002uDQA`\u0004\u0005\u0002}D\u0001\"a\u0004\u0001\u0005\u0013\u0005\u0011\u0011\u0003\u0005\b\u0003+\u0001A\u0011AA\f\u0011!\ti\u0003\u0001B\u0005\u0002\u0005=\u0002\"CA!\u0001\u0005\u0005I\u0011IA\"\u0011%\t\u0019\u0006AA\u0001\n\u0003\t)\u0006C\u0005\u0002^\u0001\t\t\u0011\"\u0001\u0002`!I\u0011Q\r\u0001\u0002\u0002\u0013\u0005\u0013q\r\u0005\n\u0003_\u0002\u0011\u0011!C\u0001\u0003cB\u0011\"a\u001f\u0001\u0003\u0003%\t%! \t\u0013\u0005\u0005\u0005!!A\u0005B\u0005\r\u0005\"CAC\u0001\u0005\u0005I\u0011IAD\u0011%\tI\tAA\u0001\n\u0003\nYiB\u0004\u0002\u0010JB\t!!%\u0007\rE\u0012\u0004\u0012AAJ\u0011\u00199v\u0003\"\u0001\u0002 \"9\u0011\u0011U\f\u0005\u0002\u0005\rfABAW/\u0001\ty\u000bC\u0005\u00028j\u0011\t\u0011)A\u0005\u001d\"Q\u0011\u0011\u0018\u000e\u0003\u0006\u0004%\t!!\u0016\t\u0015\u0005m&D!A!\u0002\u0013\t9\u0006\u0003\u0004X5\u0011\u0005\u0011Q\u0018\u0004\b\u0003\u000f<\u0002BMAe\u0011%\t9l\bB\u0001B\u0003%a\n\u0003\u0006\u0002L~\u0011)\u0019!C\u0001\u0003+B!\"!4 \u0005\u0003\u0005\u000b\u0011BA,\u0011)\tIl\bBC\u0002\u0013\u0005\u0011Q\u000b\u0005\u000b\u0003w{\"\u0011!Q\u0001\n\u0005]\u0003BB, \t\u0003\ty\r\u0003\u0005\u0002Z^\u0001K\u0011BAn\u0011\u001d\t\tp\u0006C\u0001\u0003gDq!!@\u0018\t\u0003\ty\u0010\u0003\u0005\u0003\u0004]!\tB\rB\u0003\u0011!\u0011Ia\u0006Q\u0005\n\t-\u0001\u0002\u0003B\n/\u0001&IA!\u0006\t\u000f\u0005Uq\u0003\"\u0001\u0003\u001e!11l\u0006C\u0001\u0005KA\u0011Ba\u000b\u0018\u0003\u0003%\tI!\f\t\u0011y<\u0012\u0011!CA\u0005cA\u0011Ba\u000f\u0018\u0003\u0003%IA!\u0010\u0003\u001bM#(/\u001b8h\u0007>tG/\u001a=u\u0015\u0005\u0019\u0014!B:dC2\f7\u0001A\n\u0005\u0001YRT\b\u0005\u00028q5\t!\'\u0003\u0002:e\t1\u0011I\\=SK\u001a\u0004\"aN\u001e\n\u0005q\u0012$a\u0002)s_\u0012,8\r\u001e\t\u0003}\u0019s!a\u0010#\u000f\u0005\u0001\u001bU\"A!\u000b\u0005\t#\u0014A\u0002\u001fs_>$h(C\u00014\u0013\t)%\'A\u0004qC\u000e\\\u0017mZ3\n\u0005\u001dC%\u0001D*fe&\fG.\u001b>bE2,\'BA#3\u0003\u0015\u0001\u0018M\u001d;t+\u0005Y\u0005cA\u001cM\u001d&\u0011QJ\r\u0002\u000byI,\u0007/Z1uK\u0012t\u0004CA(T\u001d\t\u0001\u0016\u000b\u0005\u0002Ae%\u0011!KM\u0001\u0007!J,G-\u001a4\n\u0005Q+&AB*ue&twM\u0003\u0002Se\u00051\u0001/\u0019:ug\u0002\na\u0001P5oSRtDCA-[!\t9\u0004\u0001C\u0003J\u0007\u0001\u00071*\u0001\u0007dQ\u0016\u001c7\u000eT3oORD7\u000f\u0006\u0002^AB\u0011qGX\u0005\u0003?J\u0012A!\u00168ji\")\u0011\r\u0002a\u0001E\u0006!\u0011M]4t!\r\u0019g\r[\u0007\u0002I*\u0011QMM\u0001\u000bG>dG.Z2uS>t\u0017BA4e\u0005\r\u0019V-\u001d\t\u0003o%L!A\u001b\u001a\u0003\u0007\u0005s\u0017\u0010\u000b\u0004\u0005Y>\u0004(o\u001d\t\u0003o5L!A\u001c\u001a\u0003\u0015\u0011,\u0007O]3dCR,G-A\u0004nKN\u001c\u0018mZ3\"\u0003E\fq\'^:fAM\fW.Z\u0017oC6,G\rI7fi\"|G\rI8oAM#(/\u001b8h\u0007>tG/\u001a=uA\r|W\u000e]1oS>t\u0007e\u001c2kK\u000e$\u0018!B:j]\u000e,\u0017%\u0001;\u0002\rIr\u0013g\r\u00181\u0003\u0005\u0019HC\u0001(x\u0011\u0015\tW\u00011\u0001y!\r9D\n\u001b\t\u0003u\u001ei\u0011\u0001\u0001\u0002\u0002gN\u0011qA\u000e\u000b\u0002s\u0006QQO\\1qa2L8+Z9\u0015\t\u0005\u0005\u0011Q\u0002\t\u0006o\u0005\r\u0011qA\u0005\u0004\u0003\u000b\u0011$AB(qi&|g\u000eE\u0003\u0002\n\u0005-aJ\u0004\u00028\t&\u0011q\r\u0013\u0005\u0006k&\u0001\rAT\u0001\u0004e\u0006<Hc\u0001(\u0002\u0014!)\u0011M\u0003a\u0001q\u0006!2\u000f^1oI\u0006\u0014H-\u00138uKJ\u0004x\u000e\\1u_J$RATA\r\u0003GAq!a\u0007\f\u0001\u0004\ti\"A\u0004qe>\u001cWm]:\u0011\u000b]\nyB\u0014(\n\u0007\u0005\u0005\"GA\u0005Gk:\u001cG/[8oc!1\u0011m\u0003a\u0001\u0003K\u0001R!!\u0003\u0002\f!Dsa\u00037p\u0003S\u00118/\t\u0002\u0002,\u00059Vk]3!i\",\u0007e\u001d;bi&\u001c\u0007%\\3uQ>$\u0007e\u0015;sS:<7i\u001c8uKb$hf\u001d;b]\u0012\f\'\u000fZ%oi\u0016\u0014\bo\u001c7bi>\u0014\b%\u001b8ti\u0016\fG\rI8gAQDW\rI5ogR\fgnY3![\u0016$\bn\u001c3\u0002\u0003\u0019,B!!\r\u0002<Q\u0019a*a\r\t\r\u0005d\u0001\u0019AA\u001b!\u00119D*a\u000e\u0011\t\u0005e\u00121\b\u0007\u0001\t\u001d\ti\u0004\u0004b\u0001\u0003\u007f\u0011\u0011!Q\t\u0003Q\"\fQ\u0002\u001d:pIV\u001cG\u000f\u0015:fM&DXCAA#!\u0011\t9%!\u0015\u000e\u0005\u0005%#\u0002BA&\u0003\u001b\nA\u0001\\1oO*\u0011\u0011qJ\u0001\u0005U\u00064\u0018-C\u0002U\u0003\u0013\nA\u0002\u001d:pIV\u001cG/\u0011:jif,\"!a\u0016\u0011\u0007]\nI&C\u0002\u0002\\I\u00121!\u00138u\u00039\u0001(o\u001c3vGR,E.Z7f]R$2\u0001[A1\u0011%\t\u0019gDA\u0001\u0002\u0004\t9&A\u0002yIE\nq\u0002\u001d:pIV\u001cG/\u0013;fe\u0006$xN]\u000b\u0003\u0003S\u0002BaYA6Q&\u0019\u0011Q\u000e3\u0003\u0011%#XM]1u_J\f\u0001bY1o\u000bF,\u0018\r\u001c\u000b\u0005\u0003g\nI\bE\u00028\u0003kJ1!a\u001e3\u0005\u001d\u0011un\u001c7fC:D\u0001\"a\u0019\u0012\u0003\u0003\u0005\r\u0001[\u0001\u0013aJ|G-^2u\u000b2,W.\u001a8u\u001d\u0006lW\r\u0006\u0003\u0002F\u0005}\u0004\"CA2%\u0005\u0005\t\u0019AA,\u0003!A\u0017m\u001d5D_\u0012,GCAA,\u0003!!xn\u0015;sS:<GCAA#\u0003\u0019)\u0017/^1mgR!\u00111OAG\u0011!\t\u0019\'FA\u0001\u0002\u0004A\u0017!D*ue&twmQ8oi\u0016DH\u000f\u0005\u00028/M!qCNAK!\u0011\t9*!(\u000e\u0005\u0005e%\u0002BAN\u0003\u001b\n!![8\n\u0007\u001d\u000bI\n\u0006\u0002\u0002\u0012\u0006!q\r\\8c)\u0019\t\t!!*\u0002*\"9\u0011qU\rA\u0002\u0005\u001d\u0011!\u00049biR,\'O\\\"ik:\\7\u000f\u0003\u0004\u0002,f\u0001\rAT\u0001\u0006S:\u0004X\u000f\u001e\u0002\u0017\u0013:4\u0018\r\\5e\u000bN\u001c\u0017\r]3Fq\u000e,\u0007\u000f^5p]N\u0019!$!-\u0011\t\u0005%\u00111W\u0005\u0004\u0003kC%\u0001G%mY\u0016<\u0017\r\\!sOVlWM\u001c;Fq\u000e,\u0007\u000f^5p]\u0006\u00191\u000f\u001e:\u0002\u000b%tG-\u001a=\u0002\r%tG-\u001a=!)\u0019\ty,a1\u0002FB\u0019\u0011\u0011\u0019\u000e\u000e\u0003]Aa!a.\u001f\u0001\u0004q\u0005bBA]=\u0001\u0007\u0011q\u000b\u0002\u001e\u0013:4\u0018\r\\5e+:L7m\u001c3f\u000bN\u001c\u0017\r]3Fq\u000e,\u0007\u000f^5p]N\u0019q$!-\u0002\u0017\u0015\u001c8-\u00199f\'R\f\'\u000f^\u0001\rKN\u001c\u0017\r]3Ti\u0006\u0014H\u000f\t\u000b\t\u0003#\f\u0019.!6\u0002XB\u0019\u0011\u0011Y\u0010\t\r\u0005]V\u00051\u0001O\u0011\u001d\tY-\na\u0001\u0003/Bq!!/&\u0001\u0004\t9&A\u0006sK\u0006$W+R:dCB,GCBAo\u0003S\fi\u000fE\u00048\u0003?\f\u0019/a\u0016\n\u0007\u0005\u0005(G\u0001\u0004UkBdWM\r\t\u0004o\u0005\u0015\u0018bAAte\t!1\t[1s\u0011\u0019\tYO\na\u0001\u001d\u0006\u00191O]2\t\u000f\u0005=h\u00051\u0001\u0002X\u0005Q1\u000f^1si&tG-\u001a=\u0002\u0019Q\u0014X-\u0019;Fg\u000e\f\u0007/Z:\u0015\u00079\u000b)\u0010\u0003\u0004\u00028\u001e\u0002\rA\u0014\u0015\bO1|\u0017\u0011 :tC\t\tY0\u0001\nvg\u0016\u0004\u0003O]8dKN\u001cXi]2ba\u0016\u001c\u0018A\u00049s_\u000e,7o]#tG\u0006\u0004Xm\u001d\u000b\u0004\u001d\n\u0005\u0001BBA\\Q\u0001\u0007a*\u0001\bqe>\u001cWm]:V]&\u001cw\u000eZ3\u0015\u00079\u00139\u0001\u0003\u0004\u00028&\u0002\rAT\u0001\be\u0016\u0004H.Y2f)\u0015q%Q\u0002B\b\u0011\u0019\t9L\u000ba\u0001\u001d\"9!\u0011\u0003\u0016A\u0002\u0005]\u0013!\u00024jeN$\u0018\u0001\u0003:fa2\f7-Z+\u0015\u000b9\u00139B!\u0007\t\r\u0005]6\u00061\u0001O\u0011\u001d\u0011Yb\u000ba\u0001\u0003/\n\u0011BY1dWNd\u0017m\u001d5\u0015\u000f9\u0013yB!\t\u0003$!9\u00111\u0004\u0017A\u0002\u0005u\u0001\"B1-\u0001\u0004\u0011\u0007BB%-\u0001\u0004\t9\u0001F\u0003^\u0005O\u0011I\u0003C\u0003b[\u0001\u0007!\r\u0003\u0004J[\u0001\u0007\u0011qA\u0001\u0006CB\u0004H.\u001f\u000b\u00043\n=\u0002\"B%/\u0001\u0004YE\u0003\u0002B\u001a\u0005o\u0001RaNA\u0002\u0005k\u0001BAPA\u0006\u001d\"A!\u0011H\u0018\u0002\u0002\u0003\u0007\u0011,A\u0002yIA\nAb\u001e:ji\u0016\u0014V\r\u001d7bG\u0016$\"Aa\u0010\u0011\t\u0005\u001d#\u0011I\u0005\u0005\u0005\u0007\nIE\u0001\u0004PE*,7\r\u001e
   #13 = Utf8               scala/StringContext$InvalidEscapeException
   #14 = Class              #13           // scala/StringContext$InvalidEscapeException
   #15 = Utf8               InvalidEscapeException
   #16 = Utf8               scala/StringContext$InvalidUnicodeEscapeException
   #17 = Class              #16           // scala/StringContext$InvalidUnicodeEscapeException
   #18 = Utf8               InvalidUnicodeEscapeException
   #19 = Utf8               scala/StringContext$s$
   #20 = Class              #19           // scala/StringContext$s$
   #21 = Utf8               s$
   #22 = Utf8               scala/runtime/ScalaRunTime$$anon$1
   #23 = Class              #22           // scala/runtime/ScalaRunTime$$anon$1
   #24 = Utf8               s$module
   #25 = Utf8               Lscala/StringContext$s$;
   #26 = Utf8               parts
   #27 = Utf8               Lscala/collection/immutable/Seq;
   #28 = Utf8               Lscala/collection/immutable/Seq<Ljava/lang/String;>;
   #29 = Utf8               unapplySeq
   #30 = Utf8               (Lscala/StringContext;)Lscala/Option;
   #31 = Utf8               (Lscala/StringContext;)Lscala/Option<Lscala/collection/immutable/Seq<Ljava/lang/String;>;>;
   #32 = Utf8               x$0
   #33 = Utf8               scala/StringContext$
   #34 = Class              #33           // scala/StringContext$
   #35 = Utf8               MODULE$
   #36 = Utf8               Lscala/StringContext$;
   #37 = NameAndType        #35:#36       // MODULE$:Lscala/StringContext$;
   #38 = Fieldref           #34.#37       // scala/StringContext$.MODULE$:Lscala/StringContext$;
   #39 = NameAndType        #29:#30       // unapplySeq:(Lscala/StringContext;)Lscala/Option;
   #40 = Methodref          #34.#39       // scala/StringContext$.unapplySeq:(Lscala/StringContext;)Lscala/Option;
   #41 = Utf8               Lscala/StringContext;
   #42 = Utf8               apply
   #43 = Utf8               (Lscala/collection/immutable/Seq;)Lscala/StringContext;
   #44 = Utf8               (Lscala/collection/immutable/Seq<Ljava/lang/String;>;)Lscala/StringContext;
   #45 = Utf8               <init>
   #46 = Utf8               (Lscala/collection/immutable/Seq;)V
   #47 = NameAndType        #45:#46       // "<init>":(Lscala/collection/immutable/Seq;)V
   #48 = Methodref          #2.#47        // scala/StringContext."<init>":(Lscala/collection/immutable/Seq;)V
   #49 = Utf8               processEscapes
   #50 = Utf8               (Ljava/lang/String;)Ljava/lang/String;
   #51 = Utf8               str
   #52 = NameAndType        #49:#50       // processEscapes:(Ljava/lang/String;)Ljava/lang/String;
   #53 = Methodref          #34.#52       // scala/StringContext$.processEscapes:(Ljava/lang/String;)Ljava/lang/String;
   #54 = Utf8               Ljava/lang/String;
   #55 = Utf8               treatEscapes
   #56 = Utf8               glob
   #57 = Utf8               (Lscala/collection/immutable/Seq;Ljava/lang/String;)Lscala/Option;
   #58 = Utf8               (Lscala/collection/immutable/Seq<Ljava/lang/String;>;Ljava/lang/String;)Lscala/Option<Lscala/collection/immutable/Seq<Ljava/lang/String;>;>;
   #59 = Utf8               patternChunks
   #60 = Utf8               input
   #61 = NameAndType        #56:#57       // glob:(Lscala/collection/immutable/Seq;Ljava/lang/String;)Lscala/Option;
   #62 = Methodref          #34.#61       // scala/StringContext$.glob:(Lscala/collection/immutable/Seq;Ljava/lang/String;)Lscala/Option;
   #63 = Utf8               productElementNames
   #64 = Utf8               ()Lscala/collection/Iterator;
   #65 = Utf8               ()Lscala/collection/Iterator<Ljava/lang/String;>;
   #66 = Utf8               productElementNames$
   #67 = Utf8               (Lscala/Product;)Lscala/collection/Iterator;
   #68 = NameAndType        #66:#67       // productElementNames$:(Lscala/Product;)Lscala/collection/Iterator;
   #69 = InterfaceMethodref #6.#68        // scala/Product.productElementNames$:(Lscala/Product;)Lscala/collection/Iterator;
   #70 = Utf8               this
   #71 = Utf8               s
   #72 = Utf8               ()Lscala/StringContext$s$;
   #73 = NameAndType        #24:#25       // s$module:Lscala/StringContext$s$;
   #74 = Fieldref           #2.#73        // scala/StringContext.s$module:Lscala/StringContext$s$;
   #75 = Utf8               s$lzycompute$1
   #76 = Utf8               ()V
   #77 = NameAndType        #75:#76       // s$lzycompute$1:()V
   #78 = Methodref          #2.#77        // scala/StringContext.s$lzycompute$1:()V
   #79 = Utf8               ()Lscala/collection/immutable/Seq;
   #80 = Utf8               ()Lscala/collection/immutable/Seq<Ljava/lang/String;>;
   #81 = NameAndType        #26:#27       // parts:Lscala/collection/immutable/Seq;
   #82 = Fieldref           #2.#81        // scala/StringContext.parts:Lscala/collection/immutable/Seq;
   #83 = Utf8               checkLengths
   #84 = Utf8               (Lscala/collection/Seq;)V
   #85 = Utf8               (Lscala/collection/Seq<Ljava/lang/Object;>;)V
   #86 = Utf8               args
   #87 = NameAndType        #26:#79       // parts:()Lscala/collection/immutable/Seq;
   #88 = Methodref          #2.#87        // scala/StringContext.parts:()Lscala/collection/immutable/Seq;
   #89 = Utf8               (Lscala/collection/Seq;Lscala/collection/immutable/Seq;)V
   #90 = NameAndType        #83:#89       // checkLengths:(Lscala/collection/Seq;Lscala/collection/immutable/Seq;)V
   #91 = Methodref          #34.#90       // scala/StringContext$.checkLengths:(Lscala/collection/Seq;Lscala/collection/immutable/Seq;)V
   #92 = Utf8               Lscala/collection/Seq;
   #93 = Utf8               standardInterpolator
   #94 = Utf8               (Lscala/Function1;Lscala/collection/immutable/Seq;)Ljava/lang/String;
   #95 = Utf8               (Lscala/Function1<Ljava/lang/String;Ljava/lang/String;>;Lscala/collection/immutable/Seq<Ljava/lang/Object;>;)Ljava/lang/String;
   #96 = Utf8               process
   #97 = Utf8               scala/collection/immutable/Seq
   #98 = Class              #97           // scala/collection/immutable/Seq
   #99 = Utf8               iterator
  #100 = NameAndType        #99:#64       // iterator:()Lscala/collection/Iterator;
  #101 = InterfaceMethodref #98.#100      // scala/collection/immutable/Seq.iterator:()Lscala/collection/Iterator;
  #102 = Utf8               scala/collection/Seq
  #103 = Class              #102          // scala/collection/Seq
  #104 = InterfaceMethodref #103.#100     // scala/collection/Seq.iterator:()Lscala/collection/Iterator;
  #105 = Utf8               java/lang/StringBuilder
  #106 = Class              #105          // java/lang/StringBuilder
  #107 = Utf8               scala/collection/Iterator
  #108 = Class              #107          // scala/collection/Iterator
  #109 = Utf8               next
  #110 = Utf8               ()Ljava/lang/Object;
  #111 = NameAndType        #109:#110     // next:()Ljava/lang/Object;
  #112 = InterfaceMethodref #108.#111     // scala/collection/Iterator.next:()Ljava/lang/Object;
  #113 = Utf8               scala/Function1
  #114 = Class              #113          // scala/Function1
  #115 = Utf8               (Ljava/lang/Object;)Ljava/lang/Object;
  #116 = NameAndType        #42:#115      // apply:(Ljava/lang/Object;)Ljava/lang/Object;
  #117 = InterfaceMethodref #114.#116     // scala/Function1.apply:(Ljava/lang/Object;)Ljava/lang/Object;
  #118 = Utf8               java/lang/String
  #119 = Class              #118          // java/lang/String
  #120 = Utf8               (Ljava/lang/String;)V
  #121 = NameAndType        #45:#120      // "<init>":(Ljava/lang/String;)V
  #122 = Methodref          #106.#121     // java/lang/StringBuilder."<init>":(Ljava/lang/String;)V
  #123 = Utf8               hasNext
  #124 = Utf8               ()Z
  #125 = NameAndType        #123:#124     // hasNext:()Z
  #126 = InterfaceMethodref #108.#125     // scala/collection/Iterator.hasNext:()Z
  #127 = Utf8               append
  #128 = Utf8               (Ljava/lang/Object;)Ljava/lang/StringBuilder;
  #129 = NameAndType        #127:#128     // append:(Ljava/lang/Object;)Ljava/lang/StringBuilder;
  #130 = Methodref          #106.#129     // java/lang/StringBuilder.append:(Ljava/lang/Object;)Ljava/lang/StringBuilder;
  #131 = Utf8               (Ljava/lang/String;)Ljava/lang/StringBuilder;
  #132 = NameAndType        #127:#131     // append:(Ljava/lang/String;)Ljava/lang/StringBuilder;
  #133 = Methodref          #106.#132     // java/lang/StringBuilder.append:(Ljava/lang/String;)Ljava/lang/StringBuilder;
  #134 = Utf8               toString
  #135 = Utf8               ()Ljava/lang/String;
  #136 = NameAndType        #134:#135     // toString:()Ljava/lang/String;
  #137 = Methodref          #106.#136     // java/lang/StringBuilder.toString:()Ljava/lang/String;
  #138 = Utf8               Lscala/Function1;
  #139 = Utf8               standardInterpolator_pi
  #140 = Utf8               Lscala/collection/Iterator;
  #141 = Utf8               standardInterpolator_ai
  #142 = Utf8               standardInterpolator_bldr
  #143 = Utf8               Ljava/lang/StringBuilder;
  #144 = Utf8               standardInterpolator_parts
  #145 = Utf8               productPrefix
  #146 = Utf8               StringContext
  #147 = String             #146          // StringContext
  #148 = Utf8               productArity
  #149 = Utf8               ()I
  #150 = Utf8               productElement
  #151 = Utf8               (I)Ljava/lang/Object;
  #152 = Utf8               x$1
  #153 = Utf8               scala/runtime/Statics
  #154 = Class              #153          // scala/runtime/Statics
  #155 = Utf8               ioobe
  #156 = NameAndType        #155:#151     // ioobe:(I)Ljava/lang/Object;
  #157 = Methodref          #154.#156     // scala/runtime/Statics.ioobe:(I)Ljava/lang/Object;
  #158 = Utf8               I
  #159 = Utf8               productIterator
  #160 = Utf8               ()Lscala/collection/Iterator<Ljava/lang/Object;>;
  #161 = Utf8               (Lscala/Product;)V
  #162 = NameAndType        #45:#161      // "<init>":(Lscala/Product;)V
  #163 = Methodref          #23.#162      // scala/runtime/ScalaRunTime$$anon$1."<init>":(Lscala/Product;)V
  #164 = Utf8               canEqual
  #165 = Utf8               (Ljava/lang/Object;)Z
  #166 = Utf8               Ljava/lang/Object;
  #167 = Utf8               productElementName
  #168 = Utf8               (I)Ljava/lang/String;
  #169 = String             #26           // parts
  #170 = Utf8               hashCode
  #171 = Utf8               scala/util/hashing/MurmurHash3$
  #172 = Class              #171          // scala/util/hashing/MurmurHash3$
  #173 = Utf8               Lscala/util/hashing/MurmurHash3$;
  #174 = NameAndType        #35:#173      // MODULE$:Lscala/util/hashing/MurmurHash3$;
  #175 = Fieldref           #172.#174     // scala/util/hashing/MurmurHash3$.MODULE$:Lscala/util/hashing/MurmurHash3$;
  #176 = Utf8               productHash
  #177 = Utf8               (Lscala/Product;)I
  #178 = NameAndType        #176:#177     // productHash:(Lscala/Product;)I
  #179 = Methodref          #172.#178     // scala/util/hashing/MurmurHash3$.productHash:(Lscala/Product;)I
  #180 = Utf8               scala/runtime/ScalaRunTime$
  #181 = Class              #180          // scala/runtime/ScalaRunTime$
  #182 = Utf8               Lscala/runtime/ScalaRunTime$;
  #183 = NameAndType        #35:#182      // MODULE$:Lscala/runtime/ScalaRunTime$;
  #184 = Fieldref           #181.#183     // scala/runtime/ScalaRunTime$.MODULE$:Lscala/runtime/ScalaRunTime$;
  #185 = Utf8               _toString
  #186 = Utf8               (Lscala/Product;)Ljava/lang/String;
  #187 = NameAndType        #185:#186     // _toString:(Lscala/Product;)Ljava/lang/String;
  #188 = Methodref          #181.#187     // scala/runtime/ScalaRunTime$._toString:(Lscala/Product;)Ljava/lang/String;
  #189 = Utf8               equals
  #190 = NameAndType        #189:#165     // equals:(Ljava/lang/Object;)Z
  #191 = Methodref          #4.#190       // java/lang/Object.equals:(Ljava/lang/Object;)Z
  #192 = NameAndType        #164:#165     // canEqual:(Ljava/lang/Object;)Z
  #193 = Methodref          #2.#192       // scala/StringContext.canEqual:(Ljava/lang/Object;)Z
  #194 = Utf8               (Lscala/StringContext;)V
  #195 = NameAndType        #45:#194      // "<init>":(Lscala/StringContext;)V
  #196 = Methodref          #20.#195      // scala/StringContext$s$."<init>":(Lscala/StringContext;)V
  #197 = Utf8               java/lang/Throwable
  #198 = Class              #197          // java/lang/Throwable
  #199 = Utf8               (Lscala/collection/immutable/Seq<Ljava/lang/String;>;)V
  #200 = NameAndType        #45:#76       // "<init>":()V
  #201 = Methodref          #4.#200       // java/lang/Object."<init>":()V
  #202 = Utf8               Signature
  #203 = Utf8               Code
  #204 = Utf8               LocalVariableTable
  #205 = Utf8               MethodParameters
  #206 = Utf8               LineNumberTable
  #207 = Utf8               Deprecated
  #208 = Utf8               StackMapTable
  #209 = Utf8               InnerClasses
  #210 = Utf8               SourceFile
  #211 = Utf8               RuntimeVisibleAnnotations
  #212 = Utf8               ScalaInlineInfo
  #213 = Utf8               f
  #214 = Utf8               (Lscala/collection/immutable/Seq;)Ljava/lang/String;
  #215 = Utf8               raw
  #216 = Utf8               ScalaSig
{
  private volatile scala.StringContext$s$ s$module;
    descriptor: Lscala/StringContext$s$;
    flags: (0x0042) ACC_PRIVATE, ACC_VOLATILE

  private final scala.collection.immutable.Seq<java.lang.String> parts;
    descriptor: Lscala/collection/immutable/Seq;
    flags: (0x0012) ACC_PRIVATE, ACC_FINAL
    Signature: #28                          // Lscala/collection/immutable/Seq<Ljava/lang/String;>;

  public static scala.Option<scala.collection.immutable.Seq<java.lang.String>> unapplySeq(scala.StringContext);
    descriptor: (Lscala/StringContext;)Lscala/Option;
    flags: (0x0009) ACC_PUBLIC, ACC_STATIC
    Code:
      stack=2, locals=1, args_size=1
         0: getstatic     #38                 // Field scala/StringContext$.MODULE$:Lscala/StringContext$;
         3: aload_0
         4: invokevirtual #40                 // Method scala/StringContext$.unapplySeq:(Lscala/StringContext;)Lscala/Option;
         7: areturn
      LocalVariableTable:
        Start  Length  Slot  Name   Signature
            0       8     0   x$0   Lscala/StringContext;
    Signature: #31                          // (Lscala/StringContext;)Lscala/Option<Lscala/collection/immutable/Seq<Ljava/lang/String;>;>;
    MethodParameters:
      Name                           Flags
      x$0                            final

  public static scala.StringContext apply(scala.collection.immutable.Seq<java.lang.String>);
    descriptor: (Lscala/collection/immutable/Seq;)Lscala/StringContext;
    flags: (0x0009) ACC_PUBLIC, ACC_STATIC
    Code:
      stack=3, locals=1, args_size=1
         0: getstatic     #38                 // Field scala/StringContext$.MODULE$:Lscala/StringContext$;
         3: pop
         4: new           #2                  // class scala/StringContext
         7: dup
         8: aload_0
         9: invokespecial #48                 // Method "<init>":(Lscala/collection/immutable/Seq;)V
        12: areturn
      LineNumberTable:
        line 57: 4
      LocalVariableTable:
        Start  Length  Slot  Name   Signature
            0      13     0 parts   Lscala/collection/immutable/Seq;
    Signature: #44                          // (Lscala/collection/immutable/Seq<Ljava/lang/String;>;)Lscala/StringContext;
    MethodParameters:
      Name                           Flags
      parts                          final

  public static java.lang.String processEscapes(java.lang.String);
    descriptor: (Ljava/lang/String;)Ljava/lang/String;
    flags: (0x0009) ACC_PUBLIC, ACC_STATIC
    Code:
      stack=2, locals=1, args_size=1
         0: getstatic     #38                 // Field scala/StringContext$.MODULE$:Lscala/StringContext$;
         3: aload_0
         4: invokevirtual #53                 // Method scala/StringContext$.processEscapes:(Ljava/lang/String;)Ljava/lang/String;
         7: areturn
      LocalVariableTable:
        Start  Length  Slot  Name   Signature
            0       8     0   str   Ljava/lang/String;
    MethodParameters:
      Name                           Flags
      str                            final

  public static java.lang.String treatEscapes(java.lang.String);
    descriptor: (Ljava/lang/String;)Ljava/lang/String;
    flags: (0x0009) ACC_PUBLIC, ACC_STATIC
    Code:
      stack=2, locals=1, args_size=1
         0: getstatic     #38                 // Field scala/StringContext$.MODULE$:Lscala/StringContext$;
         3: aload_0
         4: invokevirtual #53                 // Method scala/StringContext$.processEscapes:(Ljava/lang/String;)Ljava/lang/String;
         7: areturn
      LineNumberTable:
        line 374: 3
      LocalVariableTable:
        Start  Length  Slot  Name   Signature
            0       8     0   str   Ljava/lang/String;
    Deprecated: true
    MethodParameters:
      Name                           Flags
      str                            final

  public static scala.Option<scala.collection.immutable.Seq<java.lang.String>> glob(scala.collection.immutable.Seq<java.lang.String>, java.lang.String);
    descriptor: (Lscala/collection/immutable/Seq;Ljava/lang/String;)Lscala/Option;
    flags: (0x0009) ACC_PUBLIC, ACC_STATIC
    Code:
      stack=3, locals=2, args_size=2
         0: getstatic     #38                 // Field scala/StringContext$.MODULE$:Lscala/StringContext$;
         3: aload_0
         4: aload_1
         5: invokevirtual #62                 // Method scala/StringContext$.glob:(Lscala/collection/immutable/Seq;Ljava/lang/String;)Lscala/Option;
         8: areturn
      LocalVariableTable:
        Start  Length  Slot  Name   Signature
            0       9     0 patternChunks   Lscala/collection/immutable/Seq;
            0       9     1 input   Ljava/lang/String;
    Signature: #58                          // (Lscala/collection/immutable/Seq<Ljava/lang/String;>;Ljava/lang/String;)Lscala/Option<Lscala/collection/immutable/Seq<Ljava/lang/String;>;>;
    MethodParameters:
      Name                           Flags
      patternChunks                  final
      input                          final

  public scala.collection.Iterator<java.lang.String> productElementNames();
    descriptor: ()Lscala/collection/Iterator;
    flags: (0x0001) ACC_PUBLIC
    Code:
      stack=1, locals=1, args_size=1
         0: aload_0
         1: invokestatic  #69                 // InterfaceMethod scala/Product.productElementNames$:(Lscala/Product;)Lscala/collection/Iterator;
         4: areturn
      LineNumberTable:
        line 57: 0
      LocalVariableTable:
        Start  Length  Slot  Name   Signature
            0       5     0  this   Lscala/StringContext;
    Signature: #65                          // ()Lscala/collection/Iterator<Ljava/lang/String;>;

  public scala.StringContext$s$ s();
    descriptor: ()Lscala/StringContext$s$;
    flags: (0x0001) ACC_PUBLIC
    Code:
      stack=1, locals=1, args_size=1
         0: aload_0
         1: getfield      #74                 // Field s$module:Lscala/StringContext$s$;
         4: ifnonnull     11
         7: aload_0
         8: invokespecial #78                 // Method s$lzycompute$1:()V
        11: aload_0
        12: getfield      #74                 // Field s$module:Lscala/StringContext$s$;
        15: areturn
      StackMapTable: number_of_entries = 1
        frame_type = 11 /* same */
      LineNumberTable:
        line 93: 0
      LocalVariableTable:
        Start  Length  Slot  Name   Signature
            0      16     0  this   Lscala/StringContext;

  public scala.collection.immutable.Seq<java.lang.String> parts();
    descriptor: ()Lscala/collection/immutable/Seq;
    flags: (0x0001) ACC_PUBLIC
    Code:
      stack=1, locals=1, args_size=1
         0: aload_0
         1: getfield      #82                 // Field parts:Lscala/collection/immutable/Seq;
         4: areturn
      LineNumberTable:
        line 57: 0
      LocalVariableTable:
        Start  Length  Slot  Name   Signature
            0       5     0  this   Lscala/StringContext;
    Signature: #80                          // ()Lscala/collection/immutable/Seq<Ljava/lang/String;>;

  public void checkLengths(scala.collection.Seq<java.lang.Object>);
    descriptor: (Lscala/collection/Seq;)V
    flags: (0x0001) ACC_PUBLIC
    Code:
      stack=3, locals=2, args_size=2
         0: getstatic     #38                 // Field scala/StringContext$.MODULE$:Lscala/StringContext$;
         3: aload_1
         4: aload_0
         5: invokevirtual #88                 // Method parts:()Lscala/collection/immutable/Seq;
         8: invokevirtual #91                 // Method scala/StringContext$.checkLengths:(Lscala/collection/Seq;Lscala/collection/immutable/Seq;)V
        11: return
      LineNumberTable:
        line 62: 0
      LocalVariableTable:
        Start  Length  Slot  Name   Signature
            0      12     0  this   Lscala/StringContext;
            0      12     1  args   Lscala/collection/Seq;
    Signature: #85                          // (Lscala/collection/Seq<Ljava/lang/Object;>;)V
    Deprecated: true
    MethodParameters:
      Name                           Flags
      args                           final

  public java.lang.String standardInterpolator(scala.Function1<java.lang.String, java.lang.String>, scala.collection.immutable.Seq<java.lang.Object>);
    descriptor: (Lscala/Function1;Lscala/collection/immutable/Seq;)Ljava/lang/String;
    flags: (0x0001) ACC_PUBLIC
    Code:
      stack=4, locals=7, args_size=3
         0: getstatic     #38                 // Field scala/StringContext$.MODULE$:Lscala/StringContext$;
         3: aload_0
         4: invokevirtual #88                 // Method parts:()Lscala/collection/immutable/Seq;
         7: astore_3
         8: aload_2
         9: aload_3
        10: invokevirtual #91                 // Method scala/StringContext$.checkLengths:(Lscala/collection/Seq;Lscala/collection/immutable/Seq;)V
        13: aload_3
        14: invokeinterface #101,  1          // InterfaceMethod scala/collection/immutable/Seq.iterator:()Lscala/collection/Iterator;
        19: astore        4
        21: aload_2
        22: invokeinterface #104,  1          // InterfaceMethod scala/collection/Seq.iterator:()Lscala/collection/Iterator;
        27: astore        5
        29: new           #106                // class java/lang/StringBuilder
        32: dup
        33: aload_1
        34: aload         4
        36: invokeinterface #112,  1          // InterfaceMethod scala/collection/Iterator.next:()Ljava/lang/Object;
        41: invokeinterface #117,  2          // InterfaceMethod scala/Function1.apply:(Ljava/lang/Object;)Ljava/lang/Object;
        46: checkcast     #119                // class java/lang/String
        49: invokespecial #122                // Method java/lang/StringBuilder."<init>":(Ljava/lang/String;)V
        52: astore        6
        54: aload         5
        56: invokeinterface #126,  1          // InterfaceMethod scala/collection/Iterator.hasNext:()Z
        61: ifeq          102
        64: aload         6
        66: aload         5
        68: invokeinterface #112,  1          // InterfaceMethod scala/collection/Iterator.next:()Ljava/lang/Object;
        73: invokevirtual #130                // Method java/lang/StringBuilder.append:(Ljava/lang/Object;)Ljava/lang/StringBuilder;
        76: pop
        77: aload         6
        79: aload_1
        80: aload         4
        82: invokeinterface #112,  1          // InterfaceMethod scala/collection/Iterator.next:()Ljava/lang/Object;
        87: invokeinterface #117,  2          // InterfaceMethod scala/Function1.apply:(Ljava/lang/Object;)Ljava/lang/Object;
        92: checkcast     #119                // class java/lang/String
        95: invokevirtual #133                // Method java/lang/StringBuilder.append:(Ljava/lang/String;)Ljava/lang/StringBuilder;
        98: pop
        99: goto          54
       102: aload         6
       104: invokevirtual #137                // Method java/lang/StringBuilder.toString:()Ljava/lang/String;
       107: areturn
      StackMapTable: number_of_entries = 2
        frame_type = 255 /* full_frame */
          offset_delta = 54
          locals = [ class scala/StringContext, class scala/Function1, class scala/collection/immutable/Seq, class scala/collection/immutable/Seq, class scala/collection/Iterator, class scala/collection/Iterator, class java/lang/StringBuilder ]
          stack = []
        frame_type = 47 /* same */
      LineNumberTable:
        line 158: 0
        line 476: 8
        line 477: 13
        line 478: 21
        line 479: 29
        line 480: 54
        line 481: 64
        line 482: 77
        line 480: 99
        line 484: 102
        line 158: 107
      LocalVariableTable:
        Start  Length  Slot  Name   Signature
            0     108     0  this   Lscala/StringContext;
            0     108     1 process   Lscala/Function1;
            0     108     2  args   Lscala/collection/immutable/Seq;
           21      86     4 standardInterpolator_pi   Lscala/collection/Iterator;
           29      78     5 standardInterpolator_ai   Lscala/collection/Iterator;
           54      53     6 standardInterpolator_bldr   Ljava/lang/StringBuilder;
            8      99     3 standardInterpolator_parts   Lscala/collection/immutable/Seq;
    Signature: #95                          // (Lscala/Function1<Ljava/lang/String;Ljava/lang/String;>;Lscala/collection/immutable/Seq<Ljava/lang/Object;>;)Ljava/lang/String;
    Deprecated: true
    MethodParameters:
      Name                           Flags
      process                        final
      args                           final

  public java.lang.String productPrefix();
    descriptor: ()Ljava/lang/String;
    flags: (0x0001) ACC_PUBLIC
    Code:
      stack=1, locals=1, args_size=1
         0: ldc           #147                // String StringContext
         2: areturn
      LineNumberTable:
        line 57: 0
      LocalVariableTable:
        Start  Length  Slot  Name   Signature
            0       3     0  this   Lscala/StringContext;

  public int productArity();
    descriptor: ()I
    flags: (0x0001) ACC_PUBLIC
    Code:
      stack=1, locals=1, args_size=1
         0: iconst_1
         1: ireturn
      LineNumberTable:
        line 57: 0
      LocalVariableTable:
        Start  Length  Slot  Name   Signature
            0       2     0  this   Lscala/StringContext;

  public java.lang.Object productElement(int);
    descriptor: (I)Ljava/lang/Object;
    flags: (0x0001) ACC_PUBLIC
    Code:
      stack=1, locals=2, args_size=2
         0: iload_1
         1: tableswitch   { // 0 to 0
                       0: 20
                 default: 25
            }
        20: aload_0
        21: invokevirtual #88                 // Method parts:()Lscala/collection/immutable/Seq;
        24: areturn
        25: iload_1
        26: invokestatic  #157                // Method scala/runtime/Statics.ioobe:(I)Ljava/lang/Object;
        29: areturn
      StackMapTable: number_of_entries = 2
        frame_type = 20 /* same */
        frame_type = 4 /* same */
      LineNumberTable:
        line 57: 0
      LocalVariableTable:
        Start  Length  Slot  Name   Signature
            0      30     0  this   Lscala/StringContext;
            0      30     1   x$1   I
    MethodParameters:
      Name                           Flags
      x$1                            final

  public scala.collection.Iterator<java.lang.Object> productIterator();
    descriptor: ()Lscala/collection/Iterator;
    flags: (0x0001) ACC_PUBLIC
    Code:
      stack=3, locals=1, args_size=1
         0: new           #23                 // class scala/runtime/ScalaRunTime$$anon$1
         3: dup
         4: aload_0
         5: invokespecial #163                // Method scala/runtime/ScalaRunTime$$anon$1."<init>":(Lscala/Product;)V
         8: areturn
      LineNumberTable:
        line 57: 0
      LocalVariableTable:
        Start  Length  Slot  Name   Signature
            0       9     0  this   Lscala/StringContext;
    Signature: #160                         // ()Lscala/collection/Iterator<Ljava/lang/Object;>;

  public boolean canEqual(java.lang.Object);
    descriptor: (Ljava/lang/Object;)Z
    flags: (0x0001) ACC_PUBLIC
    Code:
      stack=1, locals=2, args_size=2
         0: aload_1
         1: instanceof    #2                  // class scala/StringContext
         4: ireturn
      LineNumberTable:
        line 57: 0
      LocalVariableTable:
        Start  Length  Slot  Name   Signature
            0       5     0  this   Lscala/StringContext;
            0       5     1   x$1   Ljava/lang/Object;
    MethodParameters:
      Name                           Flags
      x$1                            final

  public java.lang.String productElementName(int);
    descriptor: (I)Ljava/lang/String;
    flags: (0x0001) ACC_PUBLIC
    Code:
      stack=1, locals=2, args_size=2
         0: iload_1
         1: tableswitch   { // 0 to 0
                       0: 20
                 default: 23
            }
        20: ldc           #169                // String parts
        22: areturn
        23: iload_1
        24: invokestatic  #157                // Method scala/runtime/Statics.ioobe:(I)Ljava/lang/Object;
        27: checkcast     #119                // class java/lang/String
        30: areturn
      StackMapTable: number_of_entries = 2
        frame_type = 20 /* same */
        frame_type = 2 /* same */
      LineNumberTable:
        line 57: 0
      LocalVariableTable:
        Start  Length  Slot  Name   Signature
            0      31     0  this   Lscala/StringContext;
            0      31     1   x$1   I
    MethodParameters:
      Name                           Flags
      x$1                            final

  public int hashCode();
    descriptor: ()I
    flags: (0x0001) ACC_PUBLIC
    Code:
      stack=2, locals=1, args_size=1
         0: getstatic     #175                // Field scala/util/hashing/MurmurHash3$.MODULE$:Lscala/util/hashing/MurmurHash3$;
         3: aload_0
         4: invokevirtual #179                // Method scala/util/hashing/MurmurHash3$.productHash:(Lscala/Product;)I
         7: ireturn
      LineNumberTable:
        line 57: 0
      LocalVariableTable:
        Start  Length  Slot  Name   Signature
            0       8     0  this   Lscala/StringContext;

  public java.lang.String toString();
    descriptor: ()Ljava/lang/String;
    flags: (0x0001) ACC_PUBLIC
    Code:
      stack=2, locals=1, args_size=1
         0: getstatic     #184                // Field scala/runtime/ScalaRunTime$.MODULE$:Lscala/runtime/ScalaRunTime$;
         3: aload_0
         4: invokevirtual #188                // Method scala/runtime/ScalaRunTime$._toString:(Lscala/Product;)Ljava/lang/String;
         7: areturn
      LineNumberTable:
        line 57: 0
      LocalVariableTable:
        Start  Length  Slot  Name   Signature
            0       8     0  this   Lscala/StringContext;

  public boolean equals(java.lang.Object);
    descriptor: (Ljava/lang/Object;)Z
    flags: (0x0001) ACC_PUBLIC
    Code:
      stack=2, locals=5, args_size=2
         0: aload_0
         1: aload_1
         2: if_acmpeq     75
         5: aload_1
         6: instanceof    #2                  // class scala/StringContext
         9: ifeq          17
        12: iconst_1
        13: istore_2
        14: goto          19
        17: iconst_0
        18: istore_2
        19: iload_2
        20: ifeq          77
        23: aload_1
        24: checkcast     #2                  // class scala/StringContext
        27: astore_3
        28: aload_0
        29: invokevirtual #88                 // Method parts:()Lscala/collection/immutable/Seq;
        32: aload_3
        33: invokevirtual #88                 // Method parts:()Lscala/collection/immutable/Seq;
        36: astore        4
        38: dup
        39: ifnonnull     51
        42: pop
        43: aload         4
        45: ifnull        59
        48: goto          71
        51: aload         4
        53: invokevirtual #191                // Method java/lang/Object.equals:(Ljava/lang/Object;)Z
        56: ifeq          71
        59: aload_3
        60: aload_0
        61: invokevirtual #193                // Method canEqual:(Ljava/lang/Object;)Z
        64: ifeq          71
        67: iconst_1
        68: goto          72
        71: iconst_0
        72: ifeq          77
        75: iconst_1
        76: ireturn
        77: iconst_0
        78: ireturn
      StackMapTable: number_of_entries = 8
        frame_type = 17 /* same */
        frame_type = 252 /* append */
          offset_delta = 1
          locals = [ int ]
        frame_type = 255 /* full_frame */
          offset_delta = 31
          locals = [ class scala/StringContext, class java/lang/Object, int, class scala/StringContext, class scala/collection/immutable/Seq ]
          stack = [ class scala/collection/immutable/Seq ]
        frame_type = 7 /* same */
        frame_type = 11 /* same */
        frame_type = 64 /* same_locals_1_stack_item */
          stack = [ int ]
        frame_type = 248 /* chop */
          offset_delta = 2
        frame_type = 252 /* append */
          offset_delta = 1
          locals = [ int ]
      LineNumberTable:
        line 57: 0
      LocalVariableTable:
        Start  Length  Slot  Name   Signature
            0      79     0  this   Lscala/StringContext;
            0      79     1   x$1   Ljava/lang/Object;
    MethodParameters:
      Name                           Flags
      x$1                            final

  private final void s$lzycompute$1();
    descriptor: ()V
    flags: (0x0012) ACC_PRIVATE, ACC_FINAL
    Code:
      stack=4, locals=1, args_size=1
         0: aload_0
         1: monitorenter
         2: aload_0
         3: getfield      #74                 // Field s$module:Lscala/StringContext$s$;
         6: ifnonnull     21
         9: aload_0
        10: new           #20                 // class scala/StringContext$s$
        13: dup
        14: aload_0
        15: invokespecial #196                // Method scala/StringContext$s$."<init>":(Lscala/StringContext;)V
        18: putfield      #74                 // Field s$module:Lscala/StringContext$s$;
        21: aload_0
        22: monitorexit
        23: return
        24: aload_0
        25: monitorexit
        26: athrow
      Exception table:
         from    to  target type
             2    21    24   any
      StackMapTable: number_of_entries = 2
        frame_type = 21 /* same */
        frame_type = 66 /* same_locals_1_stack_item */
          stack = [ class java/lang/Throwable ]
      LineNumberTable:
        line 93: 0
      LocalVariableTable:
        Start  Length  Slot  Name   Signature
            0      27     0  this   Lscala/StringContext;

  public scala.StringContext(scala.collection.immutable.Seq<java.lang.String>);
    descriptor: (Lscala/collection/immutable/Seq;)V
    flags: (0x0001) ACC_PUBLIC
    Code:
      stack=2, locals=2, args_size=2
         0: aload_0
         1: aload_1
         2: putfield      #82                 // Field parts:Lscala/collection/immutable/Seq;
         5: aload_0
         6: invokespecial #201                // Method java/lang/Object."<init>":()V
         9: return
      LineNumberTable:
        line 57: 0
      LocalVariableTable:
        Start  Length  Slot  Name   Signature
            0      10     0  this   Lscala/StringContext;
            0      10     1 parts   Lscala/collection/immutable/Seq;
    Signature: #199                         // (Lscala/collection/immutable/Seq<Ljava/lang/String;>;)V
    MethodParameters:
      Name                           Flags
      parts                          final
}
InnerClasses:
  public static #15= #14 of #2;           // InvalidEscapeException=class scala/StringContext$InvalidEscapeException of class scala/StringContext
  public static #18= #17 of #2;           // InvalidUnicodeEscapeException=class scala/StringContext$InvalidUnicodeEscapeException of class scala/StringContext
  public #21= #20 of #2;                  // s$=class scala/StringContext$s$ of class scala/StringContext
  public final #23;                       // class scala/runtime/ScalaRunTime$$anon$1
SourceFile: "StringContext.scala"
RuntimeVisibleAnnotations:
  0: #10(#11=s#12)
    scala.reflect.ScalaSignature(
      bytes="\u0006\u0005\t\u0015c\u0001B\u00193\u0001VB\u0001\"\u0013\u0001\u0003\u0016\u0004%\tA\u0013\u0005\t-\u0002\u0011\t\u0012)A\u0005\u0017\")q\u000b\u0001C\u00011\")1\f\u0001C\u00019\"1Q\u000f\u0001B\u0005\u0002Y<Q!\u001e\u0001\t\u0002e4Qa\u001f\u0001\t\u0002qDQaV\u0004\u0005\u0002uDQA`\u0004\u0005\u0002}D\u0001\"a\u0004\u0001\u0005\u0013\u0005\u0011\u0011\u0003\u0005\b\u0003+\u0001A\u0011AA\f\u0011!\ti\u0003\u0001B\u0005\u0002\u0005=\u0002\"CA!\u0001\u0005\u0005I\u0011IA\"\u0011%\t\u0019\u0006AA\u0001\n\u0003\t)\u0006C\u0005\u0002^\u0001\t\t\u0011\"\u0001\u0002`!I\u0011Q\r\u0001\u0002\u0002\u0013\u0005\u0013q\r\u0005\n\u0003_\u0002\u0011\u0011!C\u0001\u0003cB\u0011\"a\u001f\u0001\u0003\u0003%\t%! \t\u0013\u0005\u0005\u0005!!A\u0005B\u0005\r\u0005\"CAC\u0001\u0005\u0005I\u0011IAD\u0011%\tI\tAA\u0001\n\u0003\nYiB\u0004\u0002\u0010JB\t!!%\u0007\rE\u0012\u0004\u0012AAJ\u0011\u00199v\u0003\"\u0001\u0002 \"9\u0011\u0011U\f\u0005\u0002\u0005\rfABAW/\u0001\ty\u000bC\u0005\u00028j\u0011\t\u0011)A\u0005\u001d\"Q\u0011\u0011\u0018\u000e\u0003\u0006\u0004%\t!!\u0016\t\u0015\u0005m&D!A!\u0002\u0013\t9\u0006\u0003\u0004X5\u0011\u0005\u0011Q\u0018\u0004\b\u0003\u000f<\u0002BMAe\u0011%\t9l\bB\u0001B\u0003%a\n\u0003\u0006\u0002L~\u0011)\u0019!C\u0001\u0003+B!\"!4 \u0005\u0003\u0005\u000b\u0011BA,\u0011)\tIl\bBC\u0002\u0013\u0005\u0011Q\u000b\u0005\u000b\u0003w{\"\u0011!Q\u0001\n\u0005]\u0003BB, \t\u0003\ty\r\u0003\u0005\u0002Z^\u0001K\u0011BAn\u0011\u001d\t\tp\u0006C\u0001\u0003gDq!!@\u0018\t\u0003\ty\u0010\u0003\u0005\u0003\u0004]!\tB\rB\u0003\u0011!\u0011Ia\u0006Q\u0005\n\t-\u0001\u0002\u0003B\n/\u0001&IA!\u0006\t\u000f\u0005Uq\u0003\"\u0001\u0003\u001e!11l\u0006C\u0001\u0005KA\u0011Ba\u000b\u0018\u0003\u0003%\tI!\f\t\u0011y<\u0012\u0011!CA\u0005cA\u0011Ba\u000f\u0018\u0003\u0003%IA!\u0010\u0003\u001bM#(/\u001b8h\u0007>tG/\u001a=u\u0015\u0005\u0019\u0014!B:dC2\f7\u0001A\n\u0005\u0001YRT\b\u0005\u00028q5\t!\'\u0003\u0002:e\t1\u0011I\\=SK\u001a\u0004\"aN\u001e\n\u0005q\u0012$a\u0002)s_\u0012,8\r\u001e\t\u0003}\u0019s!a\u0010#\u000f\u0005\u0001\u001bU\"A!\u000b\u0005\t#\u0014A\u0002\u001fs_>$h(C\u00014\u0013\t)%\'A\u0004qC\u000e\\\u0017mZ3\n\u0005\u001dC%\u0001D*fe&\fG.\u001b>bE2,\'BA#3\u0003\u0015\u0001\u0018M\u001d;t+\u0005Y\u0005cA\u001cM\u001d&\u0011QJ\r\u0002\u000byI,\u0007/Z1uK\u0012t\u0004CA(T\u001d\t\u0001\u0016\u000b\u0005\u0002Ae%\u0011!KM\u0001\u0007!J,G-\u001a4\n\u0005Q+&AB*ue&twM\u0003\u0002Se\u00051\u0001/\u0019:ug\u0002\na\u0001P5oSRtDCA-[!\t9\u0004\u0001C\u0003J\u0007\u0001\u00071*\u0001\u0007dQ\u0016\u001c7\u000eT3oORD7\u000f\u0006\u0002^AB\u0011qGX\u0005\u0003?J\u0012A!\u00168ji\")\u0011\r\u0002a\u0001E\u0006!\u0011M]4t!\r\u0019g\r[\u0007\u0002I*\u0011QMM\u0001\u000bG>dG.Z2uS>t\u0017BA4e\u0005\r\u0019V-\u001d\t\u0003o%L!A\u001b\u001a\u0003\u0007\u0005s\u0017\u0010\u000b\u0004\u0005Y>\u0004(o\u001d\t\u0003o5L!A\u001c\u001a\u0003\u0015\u0011,\u0007O]3dCR,G-A\u0004nKN\u001c\u0018mZ3\"\u0003E\fq\'^:fAM\fW.Z\u0017oC6,G\rI7fi\"|G\rI8oAM#(/\u001b8h\u0007>tG/\u001a=uA\r|W\u000e]1oS>t\u0007e\u001c2kK\u000e$\u0018!B:j]\u000e,\u0017%\u0001;\u0002\rIr\u0013g\r\u00181\u0003\u0005\u0019HC\u0001(x\u0011\u0015\tW\u00011\u0001y!\r9D\n\u001b\t\u0003u\u001ei\u0011\u0001\u0001\u0002\u0002gN\u0011qA\u000e\u000b\u0002s\u0006QQO\\1qa2L8+Z9\u0015\t\u0005\u0005\u0011Q\u0002\t\u0006o\u0005\r\u0011qA\u0005\u0004\u0003\u000b\u0011$AB(qi&|g\u000eE\u0003\u0002\n\u0005-aJ\u0004\u00028\t&\u0011q\r\u0013\u0005\u0006k&\u0001\rAT\u0001\u0004e\u0006<Hc\u0001(\u0002\u0014!)\u0011M\u0003a\u0001q\u0006!2\u000f^1oI\u0006\u0014H-\u00138uKJ\u0004x\u000e\\1u_J$RATA\r\u0003GAq!a\u0007\f\u0001\u0004\ti\"A\u0004qe>\u001cWm]:\u0011\u000b]\nyB\u0014(\n\u0007\u0005\u0005\"GA\u0005Gk:\u001cG/[8oc!1\u0011m\u0003a\u0001\u0003K\u0001R!!\u0003\u0002\f!Dsa\u00037p\u0003S\u00118/\t\u0002\u0002,\u00059Vk]3!i\",\u0007e\u001d;bi&\u001c\u0007%\\3uQ>$\u0007e\u0015;sS:<7i\u001c8uKb$hf\u001d;b]\u0012\f\'\u000fZ%oi\u0016\u0014\bo\u001c7bi>\u0014\b%\u001b8ti\u0016\fG\rI8gAQDW\rI5ogR\fgnY3![\u0016$\bn\u001c3\u0002\u0003\u0019,B!!\r\u0002<Q\u0019a*a\r\t\r\u0005d\u0001\u0019AA\u001b!\u00119D*a\u000e\u0011\t\u0005e\u00121\b\u0007\u0001\t\u001d\ti\u0004\u0004b\u0001\u0003\u007f\u0011\u0011!Q\t\u0003Q\"\fQ\u0002\u001d:pIV\u001cG\u000f\u0015:fM&DXCAA#!\u0011\t9%!\u0015\u000e\u0005\u0005%#\u0002BA&\u0003\u001b\nA\u0001\\1oO*\u0011\u0011qJ\u0001\u0005U\u00064\u0018-C\u0002U\u0003\u0013\nA\u0002\u001d:pIV\u001cG/\u0011:jif,\"!a\u0016\u0011\u0007]\nI&C\u0002\u0002\\I\u00121!\u00138u\u00039\u0001(o\u001c3vGR,E.Z7f]R$2\u0001[A1\u0011%\t\u0019gDA\u0001\u0002\u0004\t9&A\u0002yIE\nq\u0002\u001d:pIV\u001cG/\u0013;fe\u0006$xN]\u000b\u0003\u0003S\u0002BaYA6Q&\u0019\u0011Q\u000e3\u0003\u0011%#XM]1u_J\f\u0001bY1o\u000bF,\u0018\r\u001c\u000b\u0005\u0003g\nI\bE\u00028\u0003kJ1!a\u001e3\u0005\u001d\u0011un\u001c7fC:D\u0001\"a\u0019\u0012\u0003\u0003\u0005\r\u0001[\u0001\u0013aJ|G-^2u\u000b2,W.\u001a8u\u001d\u0006lW\r\u0006\u0003\u0002F\u0005}\u0004\"CA2%\u0005\u0005\t\u0019AA,\u0003!A\u0017m\u001d5D_\u0012,GCAA,\u0003!!xn\u0015;sS:<GCAA#\u0003\u0019)\u0017/^1mgR!\u00111OAG\u0011!\t\u0019\'FA\u0001\u0002\u0004A\u0017!D*ue&twmQ8oi\u0016DH\u000f\u0005\u00028/M!qCNAK!\u0011\t9*!(\u000e\u0005\u0005e%\u0002BAN\u0003\u001b\n!![8\n\u0007\u001d\u000bI\n\u0006\u0002\u0002\u0012\u0006!q\r\\8c)\u0019\t\t!!*\u0002*\"9\u0011qU\rA\u0002\u0005\u001d\u0011!\u00049biR,\'O\\\"ik:\\7\u000f\u0003\u0004\u0002,f\u0001\rAT\u0001\u0006S:\u0004X\u000f\u001e\u0002\u0017\u0013:4\u0018\r\\5e\u000bN\u001c\u0017\r]3Fq\u000e,\u0007\u000f^5p]N\u0019!$!-\u0011\t\u0005%\u00111W\u0005\u0004\u0003kC%\u0001G%mY\u0016<\u0017\r\\!sOVlWM\u001c;Fq\u000e,\u0007\u000f^5p]\u0006\u00191\u000f\u001e:\u0002\u000b%tG-\u001a=\u0002\r%tG-\u001a=!)\u0019\ty,a1\u0002FB\u0019\u0011\u0011\u0019\u000e\u000e\u0003]Aa!a.\u001f\u0001\u0004q\u0005bBA]=\u0001\u0007\u0011q\u000b\u0002\u001e\u0013:4\u0018\r\\5e+:L7m\u001c3f\u000bN\u001c\u0017\r]3Fq\u000e,\u0007\u000f^5p]N\u0019q$!-\u0002\u0017\u0015\u001c8-\u00199f\'R\f\'\u000f^\u0001\rKN\u001c\u0017\r]3Ti\u0006\u0014H\u000f\t\u000b\t\u0003#\f\u0019.!6\u0002XB\u0019\u0011\u0011Y\u0010\t\r\u0005]V\u00051\u0001O\u0011\u001d\tY-\na\u0001\u0003/Bq!!/&\u0001\u0004\t9&A\u0006sK\u0006$W+R:dCB,GCBAo\u0003S\fi\u000fE\u00048\u0003?\f\u0019/a\u0016\n\u0007\u0005\u0005(G\u0001\u0004UkBdWM\r\t\u0004o\u0005\u0015\u0018bAAte\t!1\t[1s\u0011\u0019\tYO\na\u0001\u001d\u0006\u00191O]2\t\u000f\u0005=h\u00051\u0001\u0002X\u0005Q1\u000f^1si&tG-\u001a=\u0002\u0019Q\u0014X-\u0019;Fg\u000e\f\u0007/Z:\u0015\u00079\u000b)\u0010\u0003\u0004\u00028\u001e\u0002\rA\u0014\u0015\bO1|\u0017\u0011 :tC\t\tY0\u0001\nvg\u0016\u0004\u0003O]8dKN\u001cXi]2ba\u0016\u001c\u0018A\u00049s_\u000e,7o]#tG\u0006\u0004Xm\u001d\u000b\u0004\u001d\n\u0005\u0001BBA\\Q\u0001\u0007a*\u0001\bqe>\u001cWm]:V]&\u001cw\u000eZ3\u0015\u00079\u00139\u0001\u0003\u0004\u00028&\u0002\rAT\u0001\be\u0016\u0004H.Y2f)\u0015q%Q\u0002B\b\u0011\u0019\t9L\u000ba\u0001\u001d\"9!\u0011\u0003\u0016A\u0002\u0005]\u0013!\u00024jeN$\u0018\u0001\u0003:fa2\f7-Z+\u0015\u000b9\u00139B!\u0007\t\r\u0005]6\u00061\u0001O\u0011\u001d\u0011Yb\u000ba\u0001\u0003/\n\u0011BY1dWNd\u0017m\u001d5\u0015\u000f9\u0013yB!\t\u0003$!9\u00111\u0004\u0017A\u0002\u0005u\u0001\"B1-\u0001\u0004\u0011\u0007BB%-\u0001\u0004\t9\u0001F\u0003^\u0005O\u0011I\u0003C\u0003b[\u0001\u0007!\r\u0003\u0004J[\u0001\u0007\u0011qA\u0001\u0006CB\u0004H.\u001f\u000b\u00043\n=\u0002\"B%/\u0001\u0004YE\u0003\u0002B\u001a\u0005o\u0001RaNA\u0002\u0005k\u0001BAPA\u0006\u001d\"A!\u0011H\u0018\u0002\u0002\u0003\u0007\u0011,A\u0002yIA\nAb\u001e:ji\u0016\u0014V\r\u001d7bG\u0016$\"Aa\u0010\u0011\t\u0005\u001d#\u0011I\u0005\u0005\u0005\u0007\nIE\u0001\u0004PE*,7\r\u001e"
    )
  ScalaInlineInfo: length = 0x63 (unknown attribute)
   01 00 00 13 00 2D 00 2E 00 00 A4 00 A5 00 00 53
   00 54 00 00 BD 00 A5 00 00 D5 00 D6 00 00 AA 00
   95 00 00 1A 00 4F 00 00 94 00 95 00 00 96 00 97
   00 00 A7 00 A8 00 00 3F 00 40 00 00 9F 00 40 00
   00 91 00 87 00 00 D7 00 D6 00 00 47 00 48 01 00
   47 00 D6 00 00 4B 00 4C 01 00 5D 00 5E 00 00 86
   00 87 00
  ScalaSig: length = 0x3 (unknown attribute)
   05 02 00
