Classfile /Users/mw/Projects/slang-braindump/.jar/jar8/assemble/slang-braindump/assemble/content/scala/transient.class
  Last modified May 29, 2022; size 641 bytes
  SHA-256 checksum 2c02237e73e510d9879aeb692d62486090c2cbc0375e6d0482e4076890d6a073
  Compiled from "transient.scala"
public final class scala.transient extends scala.annotation.Annotation implements scala.annotation.StaticAnnotation
  minor version: 0
  major version: 52
  flags: (0x0031) ACC_PUBLIC, ACC_FINAL, ACC_SUPER
  this_class: #2                          // scala/transient
  super_class: #4                         // scala/annotation/Annotation
  interfaces: 1, fields: 0, methods: 1, attributes: 4
Constant pool:
   #1 = Utf8               scala/transient
   #2 = Class              #1             // scala/transient
   #3 = Utf8               scala/annotation/Annotation
   #4 = Class              #3             // scala/annotation/Annotation
   #5 = Utf8               scala/annotation/StaticAnnotation
   #6 = Class              #5             // scala/annotation/StaticAnnotation
   #7 = Utf8               transient.scala
   #8 = Utf8               Lscala/reflect/ScalaSignature;
   #9 = Utf8               bytes
  #10 = Utf8               \u0006\u0005m1AAA\u0002\u0003\r!)\u0001\u0003\u0001C\u0001#\tIAO]1og&,g\u000e\u001e\u0006\u0002\t\u0005)1oY1mC\u000e\u00011c\u0001\u0001\b\u001bA\u0011\u0001bC\u0007\u0002\u0013)\u0011!bA\u0001\u000bC:tw\u000e^1uS>t\u0017B\u0001\u0007\n\u0005)\teN\\8uCRLwN\u001c\t\u0003\u00119I!aD\u0005\u0003!M#\u0018\r^5d\u0003:tw\u000e^1uS>t\u0017A\u0002\u001fj]&$h\bF\u0001\u0013!\t\u0019\u0002!D\u0001\u0004Q\t\u0001Q\u0003\u0005\u0002\u001735\tqC\u0003\u0002\u0019\u0013\u0005!Q.\u001a;b\u0013\tQrCA\u0003gS\u0016dG\r
  #11 = Utf8               <init>
  #12 = Utf8               ()V
  #13 = NameAndType        #11:#12        // "<init>":()V
  #14 = Methodref          #4.#13         // scala/annotation/Annotation."<init>":()V
  #15 = Utf8               this
  #16 = Utf8               Lscala/transient;
  #17 = Utf8               Code
  #18 = Utf8               LineNumberTable
  #19 = Utf8               LocalVariableTable
  #20 = Utf8               SourceFile
  #21 = Utf8               RuntimeVisibleAnnotations
  #22 = Utf8               ScalaInlineInfo
  #23 = Utf8               ScalaSig
{
  public scala.transient();
    descriptor: ()V
    flags: (0x0001) ACC_PUBLIC
    Code:
      stack=1, locals=1, args_size=1
         0: aload_0
         1: invokespecial #14                 // Method scala/annotation/Annotation."<init>":()V
         4: return
      LineNumberTable:
        line 18: 0
      LocalVariableTable:
        Start  Length  Slot  Name   Signature
            0       5     0  this   Lscala/transient;
}
SourceFile: "transient.scala"
RuntimeVisibleAnnotations:
  0: #8(#9=s#10)
    scala.reflect.ScalaSignature(
      bytes="\u0006\u0005m1AAA\u0002\u0003\r!)\u0001\u0003\u0001C\u0001#\tIAO]1og&,g\u000e\u001e\u0006\u0002\t\u0005)1oY1mC\u000e\u00011c\u0001\u0001\b\u001bA\u0011\u0001bC\u0007\u0002\u0013)\u0011!bA\u0001\u000bC:tw\u000e^1uS>t\u0017B\u0001\u0007\n\u0005)\teN\\8uCRLwN\u001c\t\u0003\u00119I!aD\u0005\u0003!M#\u0018\r^5d\u0003:tw\u000e^1uS>t\u0017A\u0002\u001fj]&$h\bF\u0001\u0013!\t\u0019\u0002!D\u0001\u0004Q\t\u0001Q\u0003\u0005\u0002\u001735\tqC\u0003\u0002\u0019\u0013\u0005!Q.\u001a;b\u0013\tQrCA\u0003gS\u0016dG\r"
    )
  ScalaInlineInfo: length = 0x9 (unknown attribute)
   01 01 00 01 00 0B 00 0C 01
  ScalaSig: length = 0x3 (unknown attribute)
   05 02 00
