Classfile /Users/mw/Projects/slang-braindump/.jar/jar8/assemble/slang-braindump/assemble/content/scala/Tuple9.class
  Last modified May 29, 2022; size 12652 bytes
  SHA-256 checksum 3c7c113928106fb33ab21dc048387752b8c37b46c5a2f76a368b6e3175ee44e1
  Compiled from "Tuple9.scala"
public final class scala.Tuple9<T1 extends java.lang.Object, T2 extends java.lang.Object, T3 extends java.lang.Object, T4 extends java.lang.Object, T5 extends java.lang.Object, T6 extends java.lang.Object, T7 extends java.lang.Object, T8 extends java.lang.Object, T9 extends java.lang.Object> extends java.lang.Object implements scala.Product9<T1, T2, T3, T4, T5, T6, T7, T8, T9>, java.io.Serializable
  minor version: 0
  major version: 52
  flags: (0x0031) ACC_PUBLIC, ACC_FINAL, ACC_SUPER
  this_class: #2                          // scala/Tuple9
  super_class: #5                         // java/lang/Object
  interfaces: 2, fields: 9, methods: 32, attributes: 6
Constant pool:
    #1 = Utf8               scala/Tuple9
    #2 = Class              #1            // scala/Tuple9
    #3 = Utf8               <T1:Ljava/lang/Object;T2:Ljava/lang/Object;T3:Ljava/lang/Object;T4:Ljava/lang/Object;T5:Ljava/lang/Object;T6:Ljava/lang/Object;T7:Ljava/lang/Object;T8:Ljava/lang/Object;T9:Ljava/lang/Object;>Ljava/lang/Object;Lscala/Product9<TT1;TT2;TT3;TT4;TT5;TT6;TT7;TT8;TT9;>;Ljava/io/Serializable;
    #4 = Utf8               java/lang/Object
    #5 = Class              #4            // java/lang/Object
    #6 = Utf8               scala/Product9
    #7 = Class              #6            // scala/Product9
    #8 = Utf8               java/io/Serializable
    #9 = Class              #8            // java/io/Serializable
   #10 = Utf8               Tuple9.scala
   #11 = Utf8               Lscala/reflect/ScalaSignature;
   #12 = Utf8               bytes
   #13 = Utf8               \u0006\u0005\r-c\u0001\u0002\u0017.\u0005BB\u0001b\u001b\u0001\u0003\u0016\u0004%\t\u0001\u001c\u0005\t[\u0002\u0011\t\u0012)A\u0005s!Aa\u000e\u0001BK\u0002\u0013\u0005q\u000e\u0003\u0005q\u0001\tE\t\u0015!\u0003E\u0011!\t\bA!f\u0001\n\u0003\u0011\b\u0002C:\u0001\u0005#\u0005\u000b\u0011B$\t\u0011Q\u0004!Q3A\u0005\u0002UD\u0001B\u001e\u0001\u0003\u0012\u0003\u0006IA\u0013\u0005\to\u0002\u0011)\u001a!C\u0001q\"A\u0011\u0010\u0001B\tB\u0003%Q\n\u0003\u0005{\u0001\tU\r\u0011\"\u0001|\u0011!a\bA!E!\u0002\u0013\u0001\u0006\u0002C?\u0001\u0005+\u0007I\u0011\u0001@\t\u0011}\u0004!\u0011#Q\u0001\nMC!\"!\u0001\u0001\u0005+\u0007I\u0011AA\u0002\u0011%\t)\u0001\u0001B\tB\u0003%a\u000b\u0003\u0006\u0002\b\u0001\u0011)\u001a!C\u0001\u0003\u0013A\u0011\"a\u0003\u0001\u0005#\u0005\u000b\u0011B-\t\u000f\u00055\u0001\u0001\"\u0001\u0002\u0010!9\u0011Q\u0005\u0001\u0005B\u0005\u001d\u0002\"CA\u001d\u0001\u0005\u0005I\u0011AA\u001e\u0011%\t9\bAI\u0001\n\u0003\tI\bC\u0005\u0002$\u0002\t\n\u0011\"\u0001\u0002&\"I\u0011Q\u0018\u0001\u0012\u0002\u0013\u0005\u0011q\u0018\u0005\n\u0003/\u0004\u0011\u0013!C\u0001\u00033D\u0011\"!=\u0001#\u0003%\t!a=\t\u0013\t-\u0001!%A\u0005\u0002\t5\u0001\"\u0003B\u0013\u0001E\u0005I\u0011\u0001B\u0014\u0011%\u0011y\u0004AI\u0001\n\u0003\u0011\t\u0005C\u0005\u0003Z\u0001\t\n\u0011\"\u0001\u0003\\!I!1\u000f\u0001\u0002\u0002\u0013\u0005#Q\u000f\u0005\n\u0005\u000b\u0003\u0011\u0011!C!\u0005\u000fC\u0011B!&\u0001\u0003\u0003%\tAa&\t\u0013\t\r\u0006!!A\u0005B\t\u0015\u0006\"\u0003BX\u0001\u0005\u0005I\u0011\tBY\u0011%\u0011\u0019\fAA\u0001\n\u0003\u0012)lB\u0005\u0003:6\n\t\u0011#\u0001\u0003<\u001aAA&LA\u0001\u0012\u0003\u0011i\fC\u0004\u0002\u000e\u0019\"\tA!3\t\u0013\u0005\u0015b%!A\u0005F\t-\u0007\"\u0003BgM\u0005\u0005I\u0011\u0011Bh\u0011%\u0019YAJA\u0001\n\u0003\u001bi\u0001C\u0005\u0004B\u0019\n\t\u0011\"\u0003\u0004D\t1A+\u001e9mKfR\u0011AL\u0001\u0006g\u000e\fG.Y\u0002\u0001+)\t4(\u0012%L\u001dF#vKW\n\u0006\u0001I2Dl\u0018\t\u0003gQj\u0011!L\u0005\u0003k5\u0012a!\u00118z%\u00164\u0007cC\u001a8s\u0011;%*\u0014)T-fK!\u0001O\u0017\u0003\u0011A\u0013x\u000eZ;dif\u0002\"AO\u001e\r\u0001\u00111A\b\u0001CC\u0002u\u0012!\u0001V\u0019\u0012\u0005y\n\u0005CA\u001a@\u0013\t\u0001UFA\u0004O_RD\u0017N\\4\u0011\u0005M\u0012\u0015BA\".\u0005\r\te.\u001f\t\u0003u\u0015#aA\u0012\u0001\u0005\u0006\u0004i$A\u0001+3!\tQ\u0004\n\u0002\u0004J\u0001\u0011\u0015\r!\u0010\u0002\u0003)N\u0002\"AO&\u0005\r1\u0003AQ1\u0001>\u0005\t!F\u0007\u0005\u0002;\u001d\u00121q\n\u0001CC\u0002u\u0012!\u0001V\u001b\u0011\u0005i\nFA\u0002*\u0001\t\u000b\u0007QH\u0001\u0002UmA\u0011!\b\u0016\u0003\u0007+\u0002!)\u0019A\u001f\u0003\u0005Q;\u0004C\u0001\u001eX\t\u0019A\u0006\u0001\"b\u0001{\t\u0011A\u000b\u000f\t\u0003ui#aa\u0017\u0001\u0005\u0006\u0004i$A\u0001+:!\t\u0019T,\u0003\u0002_[\t9\u0001K]8ek\u000e$\bC\u00011i\u001d\t\tgM\u0004\u0002cK6\t1M\u0003\u0002e_\u00051AH]8pizJ\u0011AL\u0005\u0003O6\nq\u0001]1dW\u0006<W-\u0003\u0002jU\na1+\u001a:jC2L\'0\u00192mK*\u0011q-L\u0001\u0003?F*\u0012!O\u0001\u0004?F\u0002\u0013AA03+\u0005!\u0015aA03A\u0005\u0011qlM\u000b\u0002\u000f\u0006\u0019ql\r\u0011\u0002\u0005}#T#\u0001&\u0002\u0007}#\u0004%\u0001\u0002`kU\tQ*A\u0002`k\u0001\n!a\u0018\u001c\u0016\u0003A\u000b1a\u0018\u001c!\u0003\tyv\'F\u0001T\u0003\ryv\u0007I\u0001\u0003?b*\u0012AV\u0001\u0004?b\u0002\u0013AA0:+\u0005I\u0016aA0:A\u00051A(\u001b8jiz\"B#!\u0005\u0002\u0014\u0005U\u0011qCA\r\u00037\ti\"a\b\u0002\"\u0005\r\u0002cC\u001a\u0001s\u0011;%*\u0014)T-fCQa[\nA\u0002eBQA\\\nA\u0002\u0011CQ!]\nA\u0002\u001dCQ\u0001^\nA\u0002)CQa^\nA\u00025CQA_\nA\u0002ACQ!`\nA\u0002MCa!!\u0001\u0014\u0001\u00041\u0006BBA\u0004\'\u0001\u0007\u0011,\u0001\u0005u_N#(/\u001b8h)\t\tI\u0003\u0005\u0003\u0002,\u0005Mb\u0002BA\u0017\u0003_\u0001\"AY\u0017\n\u0007\u0005ER&\u0001\u0004Qe\u0016$WMZ\u0005\u0005\u0003k\t9D\u0001\u0004TiJLgn\u001a\u0006\u0004\u0003ci\u0013\u0001B2paf,B#!\u0010\u0002D\u0005\u001d\u00131JA(\u0003\'\n9&a\u0017\u0002`\u0005\rD\u0003FA \u0003K\n9\'!\u001b\u0002l\u00055\u0014qNA9\u0003g\n)\b\u0005\u000b4\u0001\u0005\u0005\u0013QIA%\u0003\u001b\n\t&!\u0016\u0002Z\u0005u\u0013\u0011\r\t\u0004u\u0005\rC!\u0002\u001f\u0016\u0005\u0004i\u0004c\u0001\u001e\u0002H\u0011)a)\u0006b\u0001{A\u0019!(a\u0013\u0005\u000b%+\"\u0019A\u001f\u0011\u0007i\ny\u0005B\u0003M+\t\u0007Q\bE\u0002;\u0003\'\"QaT\u000bC\u0002u\u00022AOA,\t\u0015\u0011VC1\u0001>!\rQ\u00141\f\u0003\u0006+V\u0011\r!\u0010\t\u0004u\u0005}C!\u0002-\u0016\u0005\u0004i\u0004c\u0001\u001e\u0002d\u0011)1,\u0006b\u0001{!A1.\u0006I\u0001\u0002\u0004\t\t\u0005\u0003\u0005o+A\u0005\t\u0019AA#\u0011!\tX\u0003%AA\u0002\u0005%\u0003\u0002\u0003;\u0016!\u0003\u0005\r!!\u0014\t\u0011],\u0002\u0013!a\u0001\u0003#B\u0001B_\u000b\u0011\u0002\u0003\u0007\u0011Q\u000b\u0005\t{V\u0001\n\u00111\u0001\u0002Z!I\u0011\u0011A\u000b\u0011\u0002\u0003\u0007\u0011Q\f\u0005\n\u0003\u000f)\u0002\u0013!a\u0001\u0003C\nabY8qs\u0012\"WMZ1vYR$\u0013\'\u0006\u000b\u0002|\u0005E\u00151SAK\u0003/\u000bI*a\'\u0002\u001e\u0006}\u0015\u0011U\u000b\u0003\u0003{R3!OA@W\t\t\t\t\u0005\u0003\u0002\u0004\u00065UBAAC\u0015\u0011\t9)!#\u0002\u0013Ut7\r[3dW\u0016$\'bAAF[\u0005Q\u0011M\u001c8pi\u0006$\u0018n\u001c8\n\t\u0005=\u0015Q\u0011\u0002\u0012k:\u001c\u0007.Z2lK\u00124\u0016M]5b]\u000e,G!\u0002\u001f\u0017\u0005\u0004iD!\u0002$\u0017\u0005\u0004iD!B%\u0017\u0005\u0004iD!\u0002\'\u0017\u0005\u0004iD!B(\u0017\u0005\u0004iD!\u0002*\u0017\u0005\u0004iD!B+\u0017\u0005\u0004iD!\u0002-\u0017\u0005\u0004iD!B.\u0017\u0005\u0004i\u0014AD2paf$C-\u001a4bk2$HEM\u000b\u0015\u0003O\u000bY+!,\u00020\u0006E\u00161WA[\u0003o\u000bI,a/\u0016\u0005\u0005%&f\u0001#\u0002\u0000\u0011)Ah\u0006b\u0001{\u0011)ai\u0006b\u0001{\u0011)\u0011j\u0006b\u0001{\u0011)Aj\u0006b\u0001{\u0011)qj\u0006b\u0001{\u0011)!k\u0006b\u0001{\u0011)Qk\u0006b\u0001{\u0011)\u0001l\u0006b\u0001{\u0011)1l\u0006b\u0001{\u0005q1m\u001c9zI\u0011,g-Y;mi\u0012\u001aT\u0003FAa\u0003\u000b\f9-!3\u0002L\u00065\u0017qZAi\u0003\'\f).\u0006\u0002\u0002D*\u001aq)a \u0005\u000bqB\"\u0019A\u001f\u0005\u000b\u0019C\"\u0019A\u001f\u0005\u000b%C\"\u0019A\u001f\u0005\u000b1C\"\u0019A\u001f\u0005\u000b=C\"\u0019A\u001f\u0005\u000bIC\"\u0019A\u001f\u0005\u000bUC\"\u0019A\u001f\u0005\u000baC\"\u0019A\u001f\u0005\u000bmC\"\u0019A\u001f\u0002\u001d\r|\u0007/\u001f\u0013eK\u001a\fW\u000f\u001c;%iU!\u00121\\Ap\u0003C\f\u0019/!:\u0002h\u0006%\u00181^Aw\u0003_,\"!!8+\u0007)\u000by\bB\u0003=3\t\u0007Q\bB\u0003G3\t\u0007Q\bB\u0003J3\t\u0007Q\bB\u0003M3\t\u0007Q\bB\u0003P3\t\u0007Q\bB\u0003S3\t\u0007Q\bB\u0003V3\t\u0007Q\bB\u0003Y3\t\u0007Q\bB\u0003\\3\t\u0007Q(\u0001\bd_BLH\u0005Z3gCVdG\u000fJ\u001b\u0016)\u0005U\u0018\u0011`A~\u0003{\fyP!\u0001\u0003\u0004\t\u0015!q\u0001B\u0005+\t\t9PK\u0002N\u0003\u007f\"Q\u0001\u0010\u000eC\u0002u\"QA\u0012\u000eC\u0002u\"Q!\u0013\u000eC\u0002u\"Q\u0001\u0014\u000eC\u0002u\"Qa\u0014\u000eC\u0002u\"QA\u0015\u000eC\u0002u\"Q!\u0016\u000eC\u0002u\"Q\u0001\u0017\u000eC\u0002u\"Qa\u0017\u000eC\u0002u\nabY8qs\u0012\"WMZ1vYR$c\'\u0006\u000b\u0003\u0010\tM!Q\u0003B\f\u00053\u0011YB!\b\u0003 \t\u0005\"1E\u000b\u0003\u0005#Q3\u0001UA@\t\u0015a4D1\u0001>\t\u001515D1\u0001>\t\u0015I5D1\u0001>\t\u0015a5D1\u0001>\t\u0015y5D1\u0001>\t\u0015\u00116D1\u0001>\t\u0015)6D1\u0001>\t\u0015A6D1\u0001>\t\u0015Y6D1\u0001>\u00039\u0019w\u000e]=%I\u00164\u0017-\u001e7uI]*BC!\u000b\u0003.\t=\"\u0011\u0007B\u001a\u0005k\u00119D!\u000f\u0003<\tuRC\u0001B\u0016U\r\u0019\u0016q\u0010\u0003\u0006yq\u0011\r!\u0010\u0003\u0006\rr\u0011\r!\u0010\u0003\u0006\u0013r\u0011\r!\u0010\u0003\u0006\u0019r\u0011\r!\u0010\u0003\u0006\u001fr\u0011\r!\u0010\u0003\u0006%r\u0011\r!\u0010\u0003\u0006+r\u0011\r!\u0010\u0003\u00061r\u0011\r!\u0010\u0003\u00067r\u0011\r!P\u0001\u000fG>\u0004\u0018\u0010\n3fM\u0006,H\u000e\u001e\u00139+Q\u0011\u0019Ea\u0012\u0003J\t-#Q\nB(\u0005#\u0012\u0019F!\u0016\u0003XU\u0011!Q\t\u0016\u0004-\u0006}D!\u0002\u001f\u001e\u0005\u0004iD!\u0002$\u001e\u0005\u0004iD!B%\u001e\u0005\u0004iD!\u0002\'\u001e\u0005\u0004iD!B(\u001e\u0005\u0004iD!\u0002*\u001e\u0005\u0004iD!B+\u001e\u0005\u0004iD!\u0002-\u001e\u0005\u0004iD!B.\u001e\u0005\u0004i\u0014AD2paf$C-\u001a4bk2$H%O\u000b\u0015\u0005;\u0012\tGa\u0019\u0003f\t\u001d$\u0011\u000eB6\u0005[\u0012yG!\u001d\u0016\u0005\t}#fA-\u0002\u0000\u0011)AH\bb\u0001{\u0011)aI\bb\u0001{\u0011)\u0011J\bb\u0001{\u0011)AJ\bb\u0001{\u0011)qJ\bb\u0001{\u0011)!K\bb\u0001{\u0011)QK\bb\u0001{\u0011)\u0001L\bb\u0001{\u0011)1L\bb\u0001{\u0005i\u0001O]8ek\u000e$\bK]3gSb,\"Aa\u001e\u0011\t\te$1Q\u0007\u0003\u0005wRAA! \u0003\u0000\u0005!A.\u00198h\u0015\t\u0011\t)\u0001\u0003kCZ\f\u0017\u0002BA\u001b\u0005w\nq\u0002\u001d:pIV\u001cG/\u0013;fe\u0006$xN]\u000b\u0003\u0005\u0013\u0003RAa#\u0003\u0012\u0006k!A!$\u000b\u0007\t=U&\u0001\u0006d_2dWm\u0019;j_:LAAa%\u0003\u000e\nA\u0011\n^3sCR|\'/\u0001\u0005dC:,\u0015/^1m)\u0011\u0011IJa(\u0011\u0007M\u0012Y*C\u0002\u0003\u001e6\u0012qAQ8pY\u0016\fg\u000e\u0003\u0005\u0003\"\u0006\n\t\u00111\u0001B\u0003\rAH%M\u0001\u0013aJ|G-^2u\u000b2,W.\u001a8u\u001d\u0006lW\r\u0006\u0003\u0003x\t\u001d\u0006\"\u0003BQE\u0005\u0005\t\u0019\u0001BU!\r\u0019$1V\u0005\u0004\u0005[k#aA%oi\u0006A\u0001.Y:i\u0007>$W\r\u0006\u0002\u0003*\u00061Q-];bYN$BA!\'\u00038\"A!\u0011\u0015\u0013\u0002\u0002\u0003\u0007\u0011)\u0001\u0004UkBdW-\u000f\t\u0003g\u0019\u001aBA\n\u001a\u0003@B!!\u0011\u0019Bd\u001b\t\u0011\u0019M\u0003\u0003\u0003F\n}\u0014AA5p\u0013\rI\'1\u0019\u000b\u0003\u0005w#\"Aa\u001e\u0002\u000b\u0005\u0004\b\u000f\\=\u0016)\tE\'q\u001bBn\u0005?\u0014\u0019Oa:\u0003l\n=(1\u001fB|)Q\u0011\u0019N!?\u0003|\nu(q`B\u0001\u0007\u0007\u0019)aa\u0002\u0004\nA!2\u0007\u0001Bk\u00053\u0014iN!9\u0003f\n%(Q\u001eBy\u0005k\u00042A\u000fBl\t\u0015a\u0014F1\u0001>!\rQ$1\u001c\u0003\u0006\r&\u0012\r!\u0010\t\u0004u\t}G!B%*\u0005\u0004i\u0004c\u0001\u001e\u0003d\u0012)A*\u000bb\u0001{A\u0019!Ha:\u0005\u000b=K#\u0019A\u001f\u0011\u0007i\u0012Y\u000fB\u0003SS\t\u0007Q\bE\u0002;\u0005_$Q!V\u0015C\u0002u\u00022A\u000fBz\t\u0015A\u0016F1\u0001>!\rQ$q\u001f\u0003\u00067&\u0012\r!\u0010\u0005\u0007W&\u0002\rA!6\t\r9L\u0003\u0019\u0001Bm\u0011\u0019\t\u0018\u00061\u0001\u0003^\"1A/\u000ba\u0001\u0005CDaa^\u0015A\u0002\t\u0015\bB\u0002>*\u0001\u0004\u0011I\u000f\u0003\u0004~S\u0001\u0007!Q\u001e\u0005\b\u0003\u0003I\u0003\u0019\u0001By\u0011\u001d\t9!\u000ba\u0001\u0005k\fq!\u001e8baBd\u00170\u0006\u000b\u0004\u0010\rm1qDB\u0012\u0007O\u0019Yca\f\u00044\r]21\b\u000b\u0005\u0007#\u0019i\u0004E\u00034\u0007\'\u00199\"C\u0002\u0004\u00165\u0012aa\u00149uS>t\u0007\u0003F\u001a\u0001\u00073\u0019ib!\t\u0004&\r%2QFB\u0019\u0007k\u0019I\u0004E\u0002;\u00077!Q\u0001\u0010\u0016C\u0002u\u00022AOB\u0010\t\u00151%F1\u0001>!\rQ41\u0005\u0003\u0006\u0013*\u0012\r!\u0010\t\u0004u\r\u001dB!\u0002\'+\u0005\u0004i\u0004c\u0001\u001e\u0004,\u0011)qJ\u000bb\u0001{A\u0019!ha\f\u0005\u000bIS#\u0019A\u001f\u0011\u0007i\u001a\u0019\u0004B\u0003VU\t\u0007Q\bE\u0002;\u0007o!Q\u0001\u0017\u0016C\u0002u\u00022AOB\u001e\t\u0015Y&F1\u0001>\u0011%\u0019yDKA\u0001\u0002\u0004\u00199\"A\u0002yIA\nAb\u001e:ji\u0016\u0014V\r\u001d7bG\u0016$\"a!\u0012\u0011\t\te4qI\u0005\u0005\u0007\u0013\u0012YH\u0001\u0004PE*,7\r\u001e
   #14 = Utf8               scala/runtime/ScalaRunTime$$anon$1
   #15 = Class              #14           // scala/runtime/ScalaRunTime$$anon$1
   #16 = Utf8               _1
   #17 = Utf8               Ljava/lang/Object;
   #18 = Utf8               TT1;
   #19 = Utf8               _2
   #20 = Utf8               TT2;
   #21 = Utf8               _3
   #22 = Utf8               TT3;
   #23 = Utf8               _4
   #24 = Utf8               TT4;
   #25 = Utf8               _5
   #26 = Utf8               TT5;
   #27 = Utf8               _6
   #28 = Utf8               TT6;
   #29 = Utf8               _7
   #30 = Utf8               TT7;
   #31 = Utf8               _8
   #32 = Utf8               TT8;
   #33 = Utf8               _9
   #34 = Utf8               TT9;
   #35 = Utf8               unapply
   #36 = Utf8               (Lscala/Tuple9;)Lscala/Option;
   #37 = Utf8               <T1:Ljava/lang/Object;T2:Ljava/lang/Object;T3:Ljava/lang/Object;T4:Ljava/lang/Object;T5:Ljava/lang/Object;T6:Ljava/lang/Object;T7:Ljava/lang/Object;T8:Ljava/lang/Object;T9:Ljava/lang/Object;>(Lscala/Tuple9<TT1;TT2;TT3;TT4;TT5;TT6;TT7;TT8;TT9;>;)Lscala/Option<Lscala/Tuple9<TT1;TT2;TT3;TT4;TT5;TT6;TT7;TT8;TT9;>;>;
   #38 = Utf8               x$0
   #39 = Utf8               scala/Tuple9$
   #40 = Class              #39           // scala/Tuple9$
   #41 = Utf8               MODULE$
   #42 = Utf8               Lscala/Tuple9$;
   #43 = NameAndType        #41:#42       // MODULE$:Lscala/Tuple9$;
   #44 = Fieldref           #40.#43       // scala/Tuple9$.MODULE$:Lscala/Tuple9$;
   #45 = NameAndType        #35:#36       // unapply:(Lscala/Tuple9;)Lscala/Option;
   #46 = Methodref          #40.#45       // scala/Tuple9$.unapply:(Lscala/Tuple9;)Lscala/Option;
   #47 = Utf8               Lscala/Tuple9;
   #48 = Utf8               apply
   #49 = Utf8               (Ljava/lang/Object;Ljava/lang/Object;Ljava/lang/Object;Ljava/lang/Object;Ljava/lang/Object;Ljava/lang/Object;Ljava/lang/Object;Ljava/lang/Object;Ljava/lang/Object;)Lscala/Tuple9;
   #50 = Utf8               <T1:Ljava/lang/Object;T2:Ljava/lang/Object;T3:Ljava/lang/Object;T4:Ljava/lang/Object;T5:Ljava/lang/Object;T6:Ljava/lang/Object;T7:Ljava/lang/Object;T8:Ljava/lang/Object;T9:Ljava/lang/Object;>(TT1;TT2;TT3;TT4;TT5;TT6;TT7;TT8;TT9;)Lscala/Tuple9<TT1;TT2;TT3;TT4;TT5;TT6;TT7;TT8;TT9;>;
   #51 = Utf8               <init>
   #52 = Utf8               (Ljava/lang/Object;Ljava/lang/Object;Ljava/lang/Object;Ljava/lang/Object;Ljava/lang/Object;Ljava/lang/Object;Ljava/lang/Object;Ljava/lang/Object;Ljava/lang/Object;)V
   #53 = NameAndType        #51:#52       // "<init>":(Ljava/lang/Object;Ljava/lang/Object;Ljava/lang/Object;Ljava/lang/Object;Ljava/lang/Object;Ljava/lang/Object;Ljava/lang/Object;Ljava/lang/Object;Ljava/lang/Object;)V
   #54 = Methodref          #2.#53        // scala/Tuple9."<init>":(Ljava/lang/Object;Ljava/lang/Object;Ljava/lang/Object;Ljava/lang/Object;Ljava/lang/Object;Ljava/lang/Object;Ljava/lang/Object;Ljava/lang/Object;Ljava/lang/Object;)V
   #55 = Utf8               productArity
   #56 = Utf8               ()I
   #57 = Utf8               productArity$
   #58 = Utf8               (Lscala/Product9;)I
   #59 = NameAndType        #57:#58       // productArity$:(Lscala/Product9;)I
   #60 = InterfaceMethodref #7.#59        // scala/Product9.productArity$:(Lscala/Product9;)I
   #61 = Utf8               this
   #62 = Utf8               productElement
   #63 = Utf8               (I)Ljava/lang/Object;
   #64 = Utf8               java/lang/IndexOutOfBoundsException
   #65 = Class              #64           // java/lang/IndexOutOfBoundsException
   #66 = Utf8               n
   #67 = Utf8               productElement$
   #68 = Utf8               (Lscala/Product9;I)Ljava/lang/Object;
   #69 = NameAndType        #67:#68       // productElement$:(Lscala/Product9;I)Ljava/lang/Object;
   #70 = InterfaceMethodref #7.#69        // scala/Product9.productElement$:(Lscala/Product9;I)Ljava/lang/Object;
   #71 = Utf8               I
   #72 = Utf8               productElementNames
   #73 = Utf8               ()Lscala/collection/Iterator;
   #74 = Utf8               ()Lscala/collection/Iterator<Ljava/lang/String;>;
   #75 = Utf8               scala/Product
   #76 = Class              #75           // scala/Product
   #77 = Utf8               productElementNames$
   #78 = Utf8               (Lscala/Product;)Lscala/collection/Iterator;
   #79 = NameAndType        #77:#78       // productElementNames$:(Lscala/Product;)Lscala/collection/Iterator;
   #80 = InterfaceMethodref #76.#79       // scala/Product.productElementNames$:(Lscala/Product;)Lscala/collection/Iterator;
   #81 = Utf8               ()Ljava/lang/Object;
   #82 = Utf8               ()TT1;
   #83 = NameAndType        #16:#17       // _1:Ljava/lang/Object;
   #84 = Fieldref           #2.#83        // scala/Tuple9._1:Ljava/lang/Object;
   #85 = Utf8               ()TT2;
   #86 = NameAndType        #19:#17       // _2:Ljava/lang/Object;
   #87 = Fieldref           #2.#86        // scala/Tuple9._2:Ljava/lang/Object;
   #88 = Utf8               ()TT3;
   #89 = NameAndType        #21:#17       // _3:Ljava/lang/Object;
   #90 = Fieldref           #2.#89        // scala/Tuple9._3:Ljava/lang/Object;
   #91 = Utf8               ()TT4;
   #92 = NameAndType        #23:#17       // _4:Ljava/lang/Object;
   #93 = Fieldref           #2.#92        // scala/Tuple9._4:Ljava/lang/Object;
   #94 = Utf8               ()TT5;
   #95 = NameAndType        #25:#17       // _5:Ljava/lang/Object;
   #96 = Fieldref           #2.#95        // scala/Tuple9._5:Ljava/lang/Object;
   #97 = Utf8               ()TT6;
   #98 = NameAndType        #27:#17       // _6:Ljava/lang/Object;
   #99 = Fieldref           #2.#98        // scala/Tuple9._6:Ljava/lang/Object;
  #100 = Utf8               ()TT7;
  #101 = NameAndType        #29:#17       // _7:Ljava/lang/Object;
  #102 = Fieldref           #2.#101       // scala/Tuple9._7:Ljava/lang/Object;
  #103 = Utf8               ()TT8;
  #104 = NameAndType        #31:#17       // _8:Ljava/lang/Object;
  #105 = Fieldref           #2.#104       // scala/Tuple9._8:Ljava/lang/Object;
  #106 = Utf8               ()TT9;
  #107 = NameAndType        #33:#17       // _9:Ljava/lang/Object;
  #108 = Fieldref           #2.#107       // scala/Tuple9._9:Ljava/lang/Object;
  #109 = Utf8               toString
  #110 = Utf8               ()Ljava/lang/String;
  #111 = Utf8               java/lang/StringBuilder
  #112 = Class              #111          // java/lang/StringBuilder
  #113 = Integer            10
  #114 = Utf8               (I)V
  #115 = NameAndType        #51:#114      // "<init>":(I)V
  #116 = Methodref          #112.#115     // java/lang/StringBuilder."<init>":(I)V
  #117 = Utf8               (
  #118 = String             #117          // (
  #119 = Utf8               append
  #120 = Utf8               (Ljava/lang/String;)Ljava/lang/StringBuilder;
  #121 = NameAndType        #119:#120     // append:(Ljava/lang/String;)Ljava/lang/StringBuilder;
  #122 = Methodref          #112.#121     // java/lang/StringBuilder.append:(Ljava/lang/String;)Ljava/lang/StringBuilder;
  #123 = NameAndType        #16:#81       // _1:()Ljava/lang/Object;
  #124 = Methodref          #2.#123       // scala/Tuple9._1:()Ljava/lang/Object;
  #125 = Utf8               (Ljava/lang/Object;)Ljava/lang/StringBuilder;
  #126 = NameAndType        #119:#125     // append:(Ljava/lang/Object;)Ljava/lang/StringBuilder;
  #127 = Methodref          #112.#126     // java/lang/StringBuilder.append:(Ljava/lang/Object;)Ljava/lang/StringBuilder;
  #128 = Utf8               ,
  #129 = String             #128          // ,
  #130 = NameAndType        #19:#81       // _2:()Ljava/lang/Object;
  #131 = Methodref          #2.#130       // scala/Tuple9._2:()Ljava/lang/Object;
  #132 = NameAndType        #21:#81       // _3:()Ljava/lang/Object;
  #133 = Methodref          #2.#132       // scala/Tuple9._3:()Ljava/lang/Object;
  #134 = NameAndType        #23:#81       // _4:()Ljava/lang/Object;
  #135 = Methodref          #2.#134       // scala/Tuple9._4:()Ljava/lang/Object;
  #136 = NameAndType        #25:#81       // _5:()Ljava/lang/Object;
  #137 = Methodref          #2.#136       // scala/Tuple9._5:()Ljava/lang/Object;
  #138 = NameAndType        #27:#81       // _6:()Ljava/lang/Object;
  #139 = Methodref          #2.#138       // scala/Tuple9._6:()Ljava/lang/Object;
  #140 = NameAndType        #29:#81       // _7:()Ljava/lang/Object;
  #141 = Methodref          #2.#140       // scala/Tuple9._7:()Ljava/lang/Object;
  #142 = NameAndType        #31:#81       // _8:()Ljava/lang/Object;
  #143 = Methodref          #2.#142       // scala/Tuple9._8:()Ljava/lang/Object;
  #144 = NameAndType        #33:#81       // _9:()Ljava/lang/Object;
  #145 = Methodref          #2.#144       // scala/Tuple9._9:()Ljava/lang/Object;
  #146 = Utf8               )
  #147 = String             #146          // )
  #148 = NameAndType        #109:#110     // toString:()Ljava/lang/String;
  #149 = Methodref          #112.#148     // java/lang/StringBuilder.toString:()Ljava/lang/String;
  #150 = Utf8               copy
  #151 = Utf8               copy$default$1
  #152 = Utf8               <T1:Ljava/lang/Object;T2:Ljava/lang/Object;T3:Ljava/lang/Object;T4:Ljava/lang/Object;T5:Ljava/lang/Object;T6:Ljava/lang/Object;T7:Ljava/lang/Object;T8:Ljava/lang/Object;T9:Ljava/lang/Object;>()TT1;
  #153 = Utf8               copy$default$2
  #154 = Utf8               <T1:Ljava/lang/Object;T2:Ljava/lang/Object;T3:Ljava/lang/Object;T4:Ljava/lang/Object;T5:Ljava/lang/Object;T6:Ljava/lang/Object;T7:Ljava/lang/Object;T8:Ljava/lang/Object;T9:Ljava/lang/Object;>()TT2;
  #155 = Utf8               copy$default$3
  #156 = Utf8               <T1:Ljava/lang/Object;T2:Ljava/lang/Object;T3:Ljava/lang/Object;T4:Ljava/lang/Object;T5:Ljava/lang/Object;T6:Ljava/lang/Object;T7:Ljava/lang/Object;T8:Ljava/lang/Object;T9:Ljava/lang/Object;>()TT3;
  #157 = Utf8               copy$default$4
  #158 = Utf8               <T1:Ljava/lang/Object;T2:Ljava/lang/Object;T3:Ljava/lang/Object;T4:Ljava/lang/Object;T5:Ljava/lang/Object;T6:Ljava/lang/Object;T7:Ljava/lang/Object;T8:Ljava/lang/Object;T9:Ljava/lang/Object;>()TT4;
  #159 = Utf8               copy$default$5
  #160 = Utf8               <T1:Ljava/lang/Object;T2:Ljava/lang/Object;T3:Ljava/lang/Object;T4:Ljava/lang/Object;T5:Ljava/lang/Object;T6:Ljava/lang/Object;T7:Ljava/lang/Object;T8:Ljava/lang/Object;T9:Ljava/lang/Object;>()TT5;
  #161 = Utf8               copy$default$6
  #162 = Utf8               <T1:Ljava/lang/Object;T2:Ljava/lang/Object;T3:Ljava/lang/Object;T4:Ljava/lang/Object;T5:Ljava/lang/Object;T6:Ljava/lang/Object;T7:Ljava/lang/Object;T8:Ljava/lang/Object;T9:Ljava/lang/Object;>()TT6;
  #163 = Utf8               copy$default$7
  #164 = Utf8               <T1:Ljava/lang/Object;T2:Ljava/lang/Object;T3:Ljava/lang/Object;T4:Ljava/lang/Object;T5:Ljava/lang/Object;T6:Ljava/lang/Object;T7:Ljava/lang/Object;T8:Ljava/lang/Object;T9:Ljava/lang/Object;>()TT7;
  #165 = Utf8               copy$default$8
  #166 = Utf8               <T1:Ljava/lang/Object;T2:Ljava/lang/Object;T3:Ljava/lang/Object;T4:Ljava/lang/Object;T5:Ljava/lang/Object;T6:Ljava/lang/Object;T7:Ljava/lang/Object;T8:Ljava/lang/Object;T9:Ljava/lang/Object;>()TT8;
  #167 = Utf8               copy$default$9
  #168 = Utf8               <T1:Ljava/lang/Object;T2:Ljava/lang/Object;T3:Ljava/lang/Object;T4:Ljava/lang/Object;T5:Ljava/lang/Object;T6:Ljava/lang/Object;T7:Ljava/lang/Object;T8:Ljava/lang/Object;T9:Ljava/lang/Object;>()TT9;
  #169 = Utf8               productPrefix
  #170 = Utf8               Tuple9
  #171 = String             #170          // Tuple9
  #172 = Utf8               productIterator
  #173 = Utf8               ()Lscala/collection/Iterator<Ljava/lang/Object;>;
  #174 = Utf8               (Lscala/Product;)V
  #175 = NameAndType        #51:#174      // "<init>":(Lscala/Product;)V
  #176 = Methodref          #15.#175      // scala/runtime/ScalaRunTime$$anon$1."<init>":(Lscala/Product;)V
  #177 = Utf8               canEqual
  #178 = Utf8               (Ljava/lang/Object;)Z
  #179 = Utf8               x$1
  #180 = Utf8               productElementName
  #181 = Utf8               (I)Ljava/lang/String;
  #182 = String             #16           // _1
  #183 = String             #19           // _2
  #184 = String             #21           // _3
  #185 = String             #23           // _4
  #186 = String             #25           // _5
  #187 = String             #27           // _6
  #188 = String             #29           // _7
  #189 = String             #31           // _8
  #190 = String             #33           // _9
  #191 = Utf8               scala/runtime/Statics
  #192 = Class              #191          // scala/runtime/Statics
  #193 = Utf8               ioobe
  #194 = NameAndType        #193:#63      // ioobe:(I)Ljava/lang/Object;
  #195 = Methodref          #192.#194     // scala/runtime/Statics.ioobe:(I)Ljava/lang/Object;
  #196 = Utf8               java/lang/String
  #197 = Class              #196          // java/lang/String
  #198 = Utf8               hashCode
  #199 = Utf8               scala/util/hashing/MurmurHash3$
  #200 = Class              #199          // scala/util/hashing/MurmurHash3$
  #201 = Utf8               Lscala/util/hashing/MurmurHash3$;
  #202 = NameAndType        #41:#201      // MODULE$:Lscala/util/hashing/MurmurHash3$;
  #203 = Fieldref           #200.#202     // scala/util/hashing/MurmurHash3$.MODULE$:Lscala/util/hashing/MurmurHash3$;
  #204 = Utf8               productHash
  #205 = Utf8               (Lscala/Product;)I
  #206 = NameAndType        #204:#205     // productHash:(Lscala/Product;)I
  #207 = Methodref          #200.#206     // scala/util/hashing/MurmurHash3$.productHash:(Lscala/Product;)I
  #208 = Utf8               equals
  #209 = Utf8               scala/runtime/BoxesRunTime
  #210 = Class              #209          // scala/runtime/BoxesRunTime
  #211 = Utf8               (Ljava/lang/Object;Ljava/lang/Object;)Z
  #212 = NameAndType        #208:#211     // equals:(Ljava/lang/Object;Ljava/lang/Object;)Z
  #213 = Methodref          #210.#212     // scala/runtime/BoxesRunTime.equals:(Ljava/lang/Object;Ljava/lang/Object;)Z
  #214 = Utf8               (TT1;TT2;TT3;TT4;TT5;TT6;TT7;TT8;TT9;)V
  #215 = Utf8               ()V
  #216 = NameAndType        #51:#215      // "<init>":()V
  #217 = Methodref          #5.#216       // java/lang/Object."<init>":()V
  #218 = Utf8               Signature
  #219 = Utf8               Code
  #220 = Utf8               LocalVariableTable
  #221 = Utf8               MethodParameters
  #222 = Utf8               LineNumberTable
  #223 = Utf8               Exceptions
  #224 = Utf8               StackMapTable
  #225 = Utf8               InnerClasses
  #226 = Utf8               SourceFile
  #227 = Utf8               RuntimeVisibleAnnotations
  #228 = Utf8               ScalaInlineInfo
  #229 = Utf8               ScalaSig
{
  private final T1 _1;
    descriptor: Ljava/lang/Object;
    flags: (0x0012) ACC_PRIVATE, ACC_FINAL
    Signature: #18                          // TT1;

  private final T2 _2;
    descriptor: Ljava/lang/Object;
    flags: (0x0012) ACC_PRIVATE, ACC_FINAL
    Signature: #20                          // TT2;

  private final T3 _3;
    descriptor: Ljava/lang/Object;
    flags: (0x0012) ACC_PRIVATE, ACC_FINAL
    Signature: #22                          // TT3;

  private final T4 _4;
    descriptor: Ljava/lang/Object;
    flags: (0x0012) ACC_PRIVATE, ACC_FINAL
    Signature: #24                          // TT4;

  private final T5 _5;
    descriptor: Ljava/lang/Object;
    flags: (0x0012) ACC_PRIVATE, ACC_FINAL
    Signature: #26                          // TT5;

  private final T6 _6;
    descriptor: Ljava/lang/Object;
    flags: (0x0012) ACC_PRIVATE, ACC_FINAL
    Signature: #28                          // TT6;

  private final T7 _7;
    descriptor: Ljava/lang/Object;
    flags: (0x0012) ACC_PRIVATE, ACC_FINAL
    Signature: #30                          // TT7;

  private final T8 _8;
    descriptor: Ljava/lang/Object;
    flags: (0x0012) ACC_PRIVATE, ACC_FINAL
    Signature: #32                          // TT8;

  private final T9 _9;
    descriptor: Ljava/lang/Object;
    flags: (0x0012) ACC_PRIVATE, ACC_FINAL
    Signature: #34                          // TT9;

  public static <T1 extends java.lang.Object, T2 extends java.lang.Object, T3 extends java.lang.Object, T4 extends java.lang.Object, T5 extends java.lang.Object, T6 extends java.lang.Object, T7 extends java.lang.Object, T8 extends java.lang.Object, T9 extends java.lang.Object> scala.Option<scala.Tuple9<T1, T2, T3, T4, T5, T6, T7, T8, T9>> unapply(scala.Tuple9<T1, T2, T3, T4, T5, T6, T7, T8, T9>);
    descriptor: (Lscala/Tuple9;)Lscala/Option;
    flags: (0x0009) ACC_PUBLIC, ACC_STATIC
    Code:
      stack=2, locals=1, args_size=1
         0: getstatic     #44                 // Field scala/Tuple9$.MODULE$:Lscala/Tuple9$;
         3: aload_0
         4: invokevirtual #46                 // Method scala/Tuple9$.unapply:(Lscala/Tuple9;)Lscala/Option;
         7: areturn
      LocalVariableTable:
        Start  Length  Slot  Name   Signature
            0       8     0   x$0   Lscala/Tuple9;
    Signature: #37                          // <T1:Ljava/lang/Object;T2:Ljava/lang/Object;T3:Ljava/lang/Object;T4:Ljava/lang/Object;T5:Ljava/lang/Object;T6:Ljava/lang/Object;T7:Ljava/lang/Object;T8:Ljava/lang/Object;T9:Ljava/lang/Object;>(Lscala/Tuple9<TT1;TT2;TT3;TT4;TT5;TT6;TT7;TT8;TT9;>;)Lscala/Option<Lscala/Tuple9<TT1;TT2;TT3;TT4;TT5;TT6;TT7;TT8;TT9;>;>;
    MethodParameters:
      Name                           Flags
      x$0                            final

  public static <T1 extends java.lang.Object, T2 extends java.lang.Object, T3 extends java.lang.Object, T4 extends java.lang.Object, T5 extends java.lang.Object, T6 extends java.lang.Object, T7 extends java.lang.Object, T8 extends java.lang.Object, T9 extends java.lang.Object> scala.Tuple9<T1, T2, T3, T4, T5, T6, T7, T8, T9> apply(T1, T2, T3, T4, T5, T6, T7, T8, T9);
    descriptor: (Ljava/lang/Object;Ljava/lang/Object;Ljava/lang/Object;Ljava/lang/Object;Ljava/lang/Object;Ljava/lang/Object;Ljava/lang/Object;Ljava/lang/Object;Ljava/lang/Object;)Lscala/Tuple9;
    flags: (0x0009) ACC_PUBLIC, ACC_STATIC
    Code:
      stack=11, locals=9, args_size=9
         0: getstatic     #44                 // Field scala/Tuple9$.MODULE$:Lscala/Tuple9$;
         3: pop
         4: new           #2                  // class scala/Tuple9
         7: dup
         8: aload_0
         9: aload_1
        10: aload_2
        11: aload_3
        12: aload         4
        14: aload         5
        16: aload         6
        18: aload         7
        20: aload         8
        22: invokespecial #54                 // Method "<init>":(Ljava/lang/Object;Ljava/lang/Object;Ljava/lang/Object;Ljava/lang/Object;Ljava/lang/Object;Ljava/lang/Object;Ljava/lang/Object;Ljava/lang/Object;Ljava/lang/Object;)V
        25: areturn
      LineNumberTable:
        line 31: 4
      LocalVariableTable:
        Start  Length  Slot  Name   Signature
            0      26     0    _1   Ljava/lang/Object;
            0      26     1    _2   Ljava/lang/Object;
            0      26     2    _3   Ljava/lang/Object;
            0      26     3    _4   Ljava/lang/Object;
            0      26     4    _5   Ljava/lang/Object;
            0      26     5    _6   Ljava/lang/Object;
            0      26     6    _7   Ljava/lang/Object;
            0      26     7    _8   Ljava/lang/Object;
            0      26     8    _9   Ljava/lang/Object;
    Signature: #50                          // <T1:Ljava/lang/Object;T2:Ljava/lang/Object;T3:Ljava/lang/Object;T4:Ljava/lang/Object;T5:Ljava/lang/Object;T6:Ljava/lang/Object;T7:Ljava/lang/Object;T8:Ljava/lang/Object;T9:Ljava/lang/Object;>(TT1;TT2;TT3;TT4;TT5;TT6;TT7;TT8;TT9;)Lscala/Tuple9<TT1;TT2;TT3;TT4;TT5;TT6;TT7;TT8;TT9;>;
    MethodParameters:
      Name                           Flags
      _1                             final
      _2                             final
      _3                             final
      _4                             final
      _5                             final
      _6                             final
      _7                             final
      _8                             final
      _9                             final

  public int productArity();
    descriptor: ()I
    flags: (0x0001) ACC_PUBLIC
    Code:
      stack=1, locals=1, args_size=1
         0: aload_0
         1: invokestatic  #60                 // InterfaceMethod scala/Product9.productArity$:(Lscala/Product9;)I
         4: ireturn
      LineNumberTable:
        line 31: 0
      LocalVariableTable:
        Start  Length  Slot  Name   Signature
            0       5     0  this   Lscala/Tuple9;

  public java.lang.Object productElement(int) throws java.lang.IndexOutOfBoundsException;
    descriptor: (I)Ljava/lang/Object;
    flags: (0x0001) ACC_PUBLIC
    Code:
      stack=2, locals=2, args_size=2
         0: aload_0
         1: iload_1
         2: invokestatic  #70                 // InterfaceMethod scala/Product9.productElement$:(Lscala/Product9;I)Ljava/lang/Object;
         5: areturn
      LineNumberTable:
        line 31: 0
      LocalVariableTable:
        Start  Length  Slot  Name   Signature
            0       6     0  this   Lscala/Tuple9;
            0       6     1     n   I
    Exceptions:
      throws java.lang.IndexOutOfBoundsException
    MethodParameters:
      Name                           Flags
      n                              final

  public scala.collection.Iterator<java.lang.String> productElementNames();
    descriptor: ()Lscala/collection/Iterator;
    flags: (0x0001) ACC_PUBLIC
    Code:
      stack=1, locals=1, args_size=1
         0: aload_0
         1: invokestatic  #80                 // InterfaceMethod scala/Product.productElementNames$:(Lscala/Product;)Lscala/collection/Iterator;
         4: areturn
      LineNumberTable:
        line 31: 0
      LocalVariableTable:
        Start  Length  Slot  Name   Signature
            0       5     0  this   Lscala/Tuple9;
    Signature: #74                          // ()Lscala/collection/Iterator<Ljava/lang/String;>;

  public T1 _1();
    descriptor: ()Ljava/lang/Object;
    flags: (0x0001) ACC_PUBLIC
    Code:
      stack=1, locals=1, args_size=1
         0: aload_0
         1: getfield      #84                 // Field _1:Ljava/lang/Object;
         4: areturn
      LineNumberTable:
        line 31: 0
      LocalVariableTable:
        Start  Length  Slot  Name   Signature
            0       5     0  this   Lscala/Tuple9;
    Signature: #82                          // ()TT1;

  public T2 _2();
    descriptor: ()Ljava/lang/Object;
    flags: (0x0001) ACC_PUBLIC
    Code:
      stack=1, locals=1, args_size=1
         0: aload_0
         1: getfield      #87                 // Field _2:Ljava/lang/Object;
         4: areturn
      LineNumberTable:
        line 31: 0
      LocalVariableTable:
        Start  Length  Slot  Name   Signature
            0       5     0  this   Lscala/Tuple9;
    Signature: #85                          // ()TT2;

  public T3 _3();
    descriptor: ()Ljava/lang/Object;
    flags: (0x0001) ACC_PUBLIC
    Code:
      stack=1, locals=1, args_size=1
         0: aload_0
         1: getfield      #90                 // Field _3:Ljava/lang/Object;
         4: areturn
      LineNumberTable:
        line 31: 0
      LocalVariableTable:
        Start  Length  Slot  Name   Signature
            0       5     0  this   Lscala/Tuple9;
    Signature: #88                          // ()TT3;

  public T4 _4();
    descriptor: ()Ljava/lang/Object;
    flags: (0x0001) ACC_PUBLIC
    Code:
      stack=1, locals=1, args_size=1
         0: aload_0
         1: getfield      #93                 // Field _4:Ljava/lang/Object;
         4: areturn
      LineNumberTable:
        line 31: 0
      LocalVariableTable:
        Start  Length  Slot  Name   Signature
            0       5     0  this   Lscala/Tuple9;
    Signature: #91                          // ()TT4;

  public T5 _5();
    descriptor: ()Ljava/lang/Object;
    flags: (0x0001) ACC_PUBLIC
    Code:
      stack=1, locals=1, args_size=1
         0: aload_0
         1: getfield      #96                 // Field _5:Ljava/lang/Object;
         4: areturn
      LineNumberTable:
        line 31: 0
      LocalVariableTable:
        Start  Length  Slot  Name   Signature
            0       5     0  this   Lscala/Tuple9;
    Signature: #94                          // ()TT5;

  public T6 _6();
    descriptor: ()Ljava/lang/Object;
    flags: (0x0001) ACC_PUBLIC
    Code:
      stack=1, locals=1, args_size=1
         0: aload_0
         1: getfield      #99                 // Field _6:Ljava/lang/Object;
         4: areturn
      LineNumberTable:
        line 31: 0
      LocalVariableTable:
        Start  Length  Slot  Name   Signature
            0       5     0  this   Lscala/Tuple9;
    Signature: #97                          // ()TT6;

  public T7 _7();
    descriptor: ()Ljava/lang/Object;
    flags: (0x0001) ACC_PUBLIC
    Code:
      stack=1, locals=1, args_size=1
         0: aload_0
         1: getfield      #102                // Field _7:Ljava/lang/Object;
         4: areturn
      LineNumberTable:
        line 31: 0
      LocalVariableTable:
        Start  Length  Slot  Name   Signature
            0       5     0  this   Lscala/Tuple9;
    Signature: #100                         // ()TT7;

  public T8 _8();
    descriptor: ()Ljava/lang/Object;
    flags: (0x0001) ACC_PUBLIC
    Code:
      stack=1, locals=1, args_size=1
         0: aload_0
         1: getfield      #105                // Field _8:Ljava/lang/Object;
         4: areturn
      LineNumberTable:
        line 31: 0
      LocalVariableTable:
        Start  Length  Slot  Name   Signature
            0       5     0  this   Lscala/Tuple9;
    Signature: #103                         // ()TT8;

  public T9 _9();
    descriptor: ()Ljava/lang/Object;
    flags: (0x0001) ACC_PUBLIC
    Code:
      stack=1, locals=1, args_size=1
         0: aload_0
         1: getfield      #108                // Field _9:Ljava/lang/Object;
         4: areturn
      LineNumberTable:
        line 31: 0
      LocalVariableTable:
        Start  Length  Slot  Name   Signature
            0       5     0  this   Lscala/Tuple9;
    Signature: #106                         // ()TT9;

  public java.lang.String toString();
    descriptor: ()Ljava/lang/String;
    flags: (0x0001) ACC_PUBLIC
    Code:
      stack=3, locals=1, args_size=1
         0: new           #112                // class java/lang/StringBuilder
         3: dup
         4: ldc           #113                // int 10
         6: invokespecial #116                // Method java/lang/StringBuilder."<init>":(I)V
         9: ldc           #118                // String (
        11: invokevirtual #122                // Method java/lang/StringBuilder.append:(Ljava/lang/String;)Ljava/lang/StringBuilder;
        14: aload_0
        15: invokevirtual #124                // Method _1:()Ljava/lang/Object;
        18: invokevirtual #127                // Method java/lang/StringBuilder.append:(Ljava/lang/Object;)Ljava/lang/StringBuilder;
        21: ldc           #129                // String ,
        23: invokevirtual #122                // Method java/lang/StringBuilder.append:(Ljava/lang/String;)Ljava/lang/StringBuilder;
        26: aload_0
        27: invokevirtual #131                // Method _2:()Ljava/lang/Object;
        30: invokevirtual #127                // Method java/lang/StringBuilder.append:(Ljava/lang/Object;)Ljava/lang/StringBuilder;
        33: ldc           #129                // String ,
        35: invokevirtual #122                // Method java/lang/StringBuilder.append:(Ljava/lang/String;)Ljava/lang/StringBuilder;
        38: aload_0
        39: invokevirtual #133                // Method _3:()Ljava/lang/Object;
        42: invokevirtual #127                // Method java/lang/StringBuilder.append:(Ljava/lang/Object;)Ljava/lang/StringBuilder;
        45: ldc           #129                // String ,
        47: invokevirtual #122                // Method java/lang/StringBuilder.append:(Ljava/lang/String;)Ljava/lang/StringBuilder;
        50: aload_0
        51: invokevirtual #135                // Method _4:()Ljava/lang/Object;
        54: invokevirtual #127                // Method java/lang/StringBuilder.append:(Ljava/lang/Object;)Ljava/lang/StringBuilder;
        57: ldc           #129                // String ,
        59: invokevirtual #122                // Method java/lang/StringBuilder.append:(Ljava/lang/String;)Ljava/lang/StringBuilder;
        62: aload_0
        63: invokevirtual #137                // Method _5:()Ljava/lang/Object;
        66: invokevirtual #127                // Method java/lang/StringBuilder.append:(Ljava/lang/Object;)Ljava/lang/StringBuilder;
        69: ldc           #129                // String ,
        71: invokevirtual #122                // Method java/lang/StringBuilder.append:(Ljava/lang/String;)Ljava/lang/StringBuilder;
        74: aload_0
        75: invokevirtual #139                // Method _6:()Ljava/lang/Object;
        78: invokevirtual #127                // Method java/lang/StringBuilder.append:(Ljava/lang/Object;)Ljava/lang/StringBuilder;
        81: ldc           #129                // String ,
        83: invokevirtual #122                // Method java/lang/StringBuilder.append:(Ljava/lang/String;)Ljava/lang/StringBuilder;
        86: aload_0
        87: invokevirtual #141                // Method _7:()Ljava/lang/Object;
        90: invokevirtual #127                // Method java/lang/StringBuilder.append:(Ljava/lang/Object;)Ljava/lang/StringBuilder;
        93: ldc           #129                // String ,
        95: invokevirtual #122                // Method java/lang/StringBuilder.append:(Ljava/lang/String;)Ljava/lang/StringBuilder;
        98: aload_0
        99: invokevirtual #143                // Method _8:()Ljava/lang/Object;
       102: invokevirtual #127                // Method java/lang/StringBuilder.append:(Ljava/lang/Object;)Ljava/lang/StringBuilder;
       105: ldc           #129                // String ,
       107: invokevirtual #122                // Method java/lang/StringBuilder.append:(Ljava/lang/String;)Ljava/lang/StringBuilder;
       110: aload_0
       111: invokevirtual #145                // Method _9:()Ljava/lang/Object;
       114: invokevirtual #127                // Method java/lang/StringBuilder.append:(Ljava/lang/Object;)Ljava/lang/StringBuilder;
       117: ldc           #147                // String )
       119: invokevirtual #122                // Method java/lang/StringBuilder.append:(Ljava/lang/String;)Ljava/lang/StringBuilder;
       122: invokevirtual #149                // Method java/lang/StringBuilder.toString:()Ljava/lang/String;
       125: areturn
      LineNumberTable:
        line 34: 0
      LocalVariableTable:
        Start  Length  Slot  Name   Signature
            0     126     0  this   Lscala/Tuple9;

  public <T1 extends java.lang.Object, T2 extends java.lang.Object, T3 extends java.lang.Object, T4 extends java.lang.Object, T5 extends java.lang.Object, T6 extends java.lang.Object, T7 extends java.lang.Object, T8 extends java.lang.Object, T9 extends java.lang.Object> scala.Tuple9<T1, T2, T3, T4, T5, T6, T7, T8, T9> copy(T1, T2, T3, T4, T5, T6, T7, T8, T9);
    descriptor: (Ljava/lang/Object;Ljava/lang/Object;Ljava/lang/Object;Ljava/lang/Object;Ljava/lang/Object;Ljava/lang/Object;Ljava/lang/Object;Ljava/lang/Object;Ljava/lang/Object;)Lscala/Tuple9;
    flags: (0x0001) ACC_PUBLIC
    Code:
      stack=11, locals=10, args_size=10
         0: new           #2                  // class scala/Tuple9
         3: dup
         4: aload_1
         5: aload_2
         6: aload_3
         7: aload         4
         9: aload         5
        11: aload         6
        13: aload         7
        15: aload         8
        17: aload         9
        19: invokespecial #54                 // Method "<init>":(Ljava/lang/Object;Ljava/lang/Object;Ljava/lang/Object;Ljava/lang/Object;Ljava/lang/Object;Ljava/lang/Object;Ljava/lang/Object;Ljava/lang/Object;Ljava/lang/Object;)V
        22: areturn
      LineNumberTable:
        line 31: 0
      LocalVariableTable:
        Start  Length  Slot  Name   Signature
            0      23     0  this   Lscala/Tuple9;
            0      23     1    _1   Ljava/lang/Object;
            0      23     2    _2   Ljava/lang/Object;
            0      23     3    _3   Ljava/lang/Object;
            0      23     4    _4   Ljava/lang/Object;
            0      23     5    _5   Ljava/lang/Object;
            0      23     6    _6   Ljava/lang/Object;
            0      23     7    _7   Ljava/lang/Object;
            0      23     8    _8   Ljava/lang/Object;
            0      23     9    _9   Ljava/lang/Object;
    Signature: #50                          // <T1:Ljava/lang/Object;T2:Ljava/lang/Object;T3:Ljava/lang/Object;T4:Ljava/lang/Object;T5:Ljava/lang/Object;T6:Ljava/lang/Object;T7:Ljava/lang/Object;T8:Ljava/lang/Object;T9:Ljava/lang/Object;>(TT1;TT2;TT3;TT4;TT5;TT6;TT7;TT8;TT9;)Lscala/Tuple9<TT1;TT2;TT3;TT4;TT5;TT6;TT7;TT8;TT9;>;
    MethodParameters:
      Name                           Flags
      _1                             final
      _2                             final
      _3                             final
      _4                             final
      _5                             final
      _6                             final
      _7                             final
      _8                             final
      _9                             final

  public <T1 extends java.lang.Object, T2 extends java.lang.Object, T3 extends java.lang.Object, T4 extends java.lang.Object, T5 extends java.lang.Object, T6 extends java.lang.Object, T7 extends java.lang.Object, T8 extends java.lang.Object, T9 extends java.lang.Object> T1 copy$default$1();
    descriptor: ()Ljava/lang/Object;
    flags: (0x0001) ACC_PUBLIC
    Code:
      stack=1, locals=1, args_size=1
         0: aload_0
         1: invokevirtual #124                // Method _1:()Ljava/lang/Object;
         4: areturn
      LineNumberTable:
        line 31: 0
      LocalVariableTable:
        Start  Length  Slot  Name   Signature
            0       5     0  this   Lscala/Tuple9;
    Signature: #152                         // <T1:Ljava/lang/Object;T2:Ljava/lang/Object;T3:Ljava/lang/Object;T4:Ljava/lang/Object;T5:Ljava/lang/Object;T6:Ljava/lang/Object;T7:Ljava/lang/Object;T8:Ljava/lang/Object;T9:Ljava/lang/Object;>()TT1;

  public <T1 extends java.lang.Object, T2 extends java.lang.Object, T3 extends java.lang.Object, T4 extends java.lang.Object, T5 extends java.lang.Object, T6 extends java.lang.Object, T7 extends java.lang.Object, T8 extends java.lang.Object, T9 extends java.lang.Object> T2 copy$default$2();
    descriptor: ()Ljava/lang/Object;
    flags: (0x0001) ACC_PUBLIC
    Code:
      stack=1, locals=1, args_size=1
         0: aload_0
         1: invokevirtual #131                // Method _2:()Ljava/lang/Object;
         4: areturn
      LineNumberTable:
        line 31: 0
      LocalVariableTable:
        Start  Length  Slot  Name   Signature
            0       5     0  this   Lscala/Tuple9;
    Signature: #154                         // <T1:Ljava/lang/Object;T2:Ljava/lang/Object;T3:Ljava/lang/Object;T4:Ljava/lang/Object;T5:Ljava/lang/Object;T6:Ljava/lang/Object;T7:Ljava/lang/Object;T8:Ljava/lang/Object;T9:Ljava/lang/Object;>()TT2;

  public <T1 extends java.lang.Object, T2 extends java.lang.Object, T3 extends java.lang.Object, T4 extends java.lang.Object, T5 extends java.lang.Object, T6 extends java.lang.Object, T7 extends java.lang.Object, T8 extends java.lang.Object, T9 extends java.lang.Object> T3 copy$default$3();
    descriptor: ()Ljava/lang/Object;
    flags: (0x0001) ACC_PUBLIC
    Code:
      stack=1, locals=1, args_size=1
         0: aload_0
         1: invokevirtual #133                // Method _3:()Ljava/lang/Object;
         4: areturn
      LineNumberTable:
        line 31: 0
      LocalVariableTable:
        Start  Length  Slot  Name   Signature
            0       5     0  this   Lscala/Tuple9;
    Signature: #156                         // <T1:Ljava/lang/Object;T2:Ljava/lang/Object;T3:Ljava/lang/Object;T4:Ljava/lang/Object;T5:Ljava/lang/Object;T6:Ljava/lang/Object;T7:Ljava/lang/Object;T8:Ljava/lang/Object;T9:Ljava/lang/Object;>()TT3;

  public <T1 extends java.lang.Object, T2 extends java.lang.Object, T3 extends java.lang.Object, T4 extends java.lang.Object, T5 extends java.lang.Object, T6 extends java.lang.Object, T7 extends java.lang.Object, T8 extends java.lang.Object, T9 extends java.lang.Object> T4 copy$default$4();
    descriptor: ()Ljava/lang/Object;
    flags: (0x0001) ACC_PUBLIC
    Code:
      stack=1, locals=1, args_size=1
         0: aload_0
         1: invokevirtual #135                // Method _4:()Ljava/lang/Object;
         4: areturn
      LineNumberTable:
        line 31: 0
      LocalVariableTable:
        Start  Length  Slot  Name   Signature
            0       5     0  this   Lscala/Tuple9;
    Signature: #158                         // <T1:Ljava/lang/Object;T2:Ljava/lang/Object;T3:Ljava/lang/Object;T4:Ljava/lang/Object;T5:Ljava/lang/Object;T6:Ljava/lang/Object;T7:Ljava/lang/Object;T8:Ljava/lang/Object;T9:Ljava/lang/Object;>()TT4;

  public <T1 extends java.lang.Object, T2 extends java.lang.Object, T3 extends java.lang.Object, T4 extends java.lang.Object, T5 extends java.lang.Object, T6 extends java.lang.Object, T7 extends java.lang.Object, T8 extends java.lang.Object, T9 extends java.lang.Object> T5 copy$default$5();
    descriptor: ()Ljava/lang/Object;
    flags: (0x0001) ACC_PUBLIC
    Code:
      stack=1, locals=1, args_size=1
         0: aload_0
         1: invokevirtual #137                // Method _5:()Ljava/lang/Object;
         4: areturn
      LineNumberTable:
        line 31: 0
      LocalVariableTable:
        Start  Length  Slot  Name   Signature
            0       5     0  this   Lscala/Tuple9;
    Signature: #160                         // <T1:Ljava/lang/Object;T2:Ljava/lang/Object;T3:Ljava/lang/Object;T4:Ljava/lang/Object;T5:Ljava/lang/Object;T6:Ljava/lang/Object;T7:Ljava/lang/Object;T8:Ljava/lang/Object;T9:Ljava/lang/Object;>()TT5;

  public <T1 extends java.lang.Object, T2 extends java.lang.Object, T3 extends java.lang.Object, T4 extends java.lang.Object, T5 extends java.lang.Object, T6 extends java.lang.Object, T7 extends java.lang.Object, T8 extends java.lang.Object, T9 extends java.lang.Object> T6 copy$default$6();
    descriptor: ()Ljava/lang/Object;
    flags: (0x0001) ACC_PUBLIC
    Code:
      stack=1, locals=1, args_size=1
         0: aload_0
         1: invokevirtual #139                // Method _6:()Ljava/lang/Object;
         4: areturn
      LineNumberTable:
        line 31: 0
      LocalVariableTable:
        Start  Length  Slot  Name   Signature
            0       5     0  this   Lscala/Tuple9;
    Signature: #162                         // <T1:Ljava/lang/Object;T2:Ljava/lang/Object;T3:Ljava/lang/Object;T4:Ljava/lang/Object;T5:Ljava/lang/Object;T6:Ljava/lang/Object;T7:Ljava/lang/Object;T8:Ljava/lang/Object;T9:Ljava/lang/Object;>()TT6;

  public <T1 extends java.lang.Object, T2 extends java.lang.Object, T3 extends java.lang.Object, T4 extends java.lang.Object, T5 extends java.lang.Object, T6 extends java.lang.Object, T7 extends java.lang.Object, T8 extends java.lang.Object, T9 extends java.lang.Object> T7 copy$default$7();
    descriptor: ()Ljava/lang/Object;
    flags: (0x0001) ACC_PUBLIC
    Code:
      stack=1, locals=1, args_size=1
         0: aload_0
         1: invokevirtual #141                // Method _7:()Ljava/lang/Object;
         4: areturn
      LineNumberTable:
        line 31: 0
      LocalVariableTable:
        Start  Length  Slot  Name   Signature
            0       5     0  this   Lscala/Tuple9;
    Signature: #164                         // <T1:Ljava/lang/Object;T2:Ljava/lang/Object;T3:Ljava/lang/Object;T4:Ljava/lang/Object;T5:Ljava/lang/Object;T6:Ljava/lang/Object;T7:Ljava/lang/Object;T8:Ljava/lang/Object;T9:Ljava/lang/Object;>()TT7;

  public <T1 extends java.lang.Object, T2 extends java.lang.Object, T3 extends java.lang.Object, T4 extends java.lang.Object, T5 extends java.lang.Object, T6 extends java.lang.Object, T7 extends java.lang.Object, T8 extends java.lang.Object, T9 extends java.lang.Object> T8 copy$default$8();
    descriptor: ()Ljava/lang/Object;
    flags: (0x0001) ACC_PUBLIC
    Code:
      stack=1, locals=1, args_size=1
         0: aload_0
         1: invokevirtual #143                // Method _8:()Ljava/lang/Object;
         4: areturn
      LineNumberTable:
        line 31: 0
      LocalVariableTable:
        Start  Length  Slot  Name   Signature
            0       5     0  this   Lscala/Tuple9;
    Signature: #166                         // <T1:Ljava/lang/Object;T2:Ljava/lang/Object;T3:Ljava/lang/Object;T4:Ljava/lang/Object;T5:Ljava/lang/Object;T6:Ljava/lang/Object;T7:Ljava/lang/Object;T8:Ljava/lang/Object;T9:Ljava/lang/Object;>()TT8;

  public <T1 extends java.lang.Object, T2 extends java.lang.Object, T3 extends java.lang.Object, T4 extends java.lang.Object, T5 extends java.lang.Object, T6 extends java.lang.Object, T7 extends java.lang.Object, T8 extends java.lang.Object, T9 extends java.lang.Object> T9 copy$default$9();
    descriptor: ()Ljava/lang/Object;
    flags: (0x0001) ACC_PUBLIC
    Code:
      stack=1, locals=1, args_size=1
         0: aload_0
         1: invokevirtual #145                // Method _9:()Ljava/lang/Object;
         4: areturn
      LineNumberTable:
        line 31: 0
      LocalVariableTable:
        Start  Length  Slot  Name   Signature
            0       5     0  this   Lscala/Tuple9;
    Signature: #168                         // <T1:Ljava/lang/Object;T2:Ljava/lang/Object;T3:Ljava/lang/Object;T4:Ljava/lang/Object;T5:Ljava/lang/Object;T6:Ljava/lang/Object;T7:Ljava/lang/Object;T8:Ljava/lang/Object;T9:Ljava/lang/Object;>()TT9;

  public java.lang.String productPrefix();
    descriptor: ()Ljava/lang/String;
    flags: (0x0001) ACC_PUBLIC
    Code:
      stack=1, locals=1, args_size=1
         0: ldc           #171                // String Tuple9
         2: areturn
      LineNumberTable:
        line 31: 0
      LocalVariableTable:
        Start  Length  Slot  Name   Signature
            0       3     0  this   Lscala/Tuple9;

  public scala.collection.Iterator<java.lang.Object> productIterator();
    descriptor: ()Lscala/collection/Iterator;
    flags: (0x0001) ACC_PUBLIC
    Code:
      stack=3, locals=1, args_size=1
         0: new           #15                 // class scala/runtime/ScalaRunTime$$anon$1
         3: dup
         4: aload_0
         5: invokespecial #176                // Method scala/runtime/ScalaRunTime$$anon$1."<init>":(Lscala/Product;)V
         8: areturn
      LineNumberTable:
        line 31: 0
      LocalVariableTable:
        Start  Length  Slot  Name   Signature
            0       9     0  this   Lscala/Tuple9;
    Signature: #173                         // ()Lscala/collection/Iterator<Ljava/lang/Object;>;

  public boolean canEqual(java.lang.Object);
    descriptor: (Ljava/lang/Object;)Z
    flags: (0x0001) ACC_PUBLIC
    Code:
      stack=1, locals=2, args_size=2
         0: aload_1
         1: instanceof    #2                  // class scala/Tuple9
         4: ireturn
      LineNumberTable:
        line 31: 0
      LocalVariableTable:
        Start  Length  Slot  Name   Signature
            0       5     0  this   Lscala/Tuple9;
            0       5     1   x$1   Ljava/lang/Object;
    MethodParameters:
      Name                           Flags
      x$1                            final

  public java.lang.String productElementName(int);
    descriptor: (I)Ljava/lang/String;
    flags: (0x0001) ACC_PUBLIC
    Code:
      stack=1, locals=2, args_size=2
         0: iload_1
         1: tableswitch   { // 0 to 8
                       0: 52
                       1: 55
                       2: 58
                       3: 61
                       4: 64
                       5: 67
                       6: 70
                       7: 73
                       8: 76
                 default: 79
            }
        52: ldc           #182                // String _1
        54: areturn
        55: ldc           #183                // String _2
        57: areturn
        58: ldc           #184                // String _3
        60: areturn
        61: ldc           #185                // String _4
        63: areturn
        64: ldc           #186                // String _5
        66: areturn
        67: ldc           #187                // String _6
        69: areturn
        70: ldc           #188                // String _7
        72: areturn
        73: ldc           #189                // String _8
        75: areturn
        76: ldc           #190                // String _9
        78: areturn
        79: iload_1
        80: invokestatic  #195                // Method scala/runtime/Statics.ioobe:(I)Ljava/lang/Object;
        83: checkcast     #197                // class java/lang/String
        86: areturn
      StackMapTable: number_of_entries = 10
        frame_type = 52 /* same */
        frame_type = 2 /* same */
        frame_type = 2 /* same */
        frame_type = 2 /* same */
        frame_type = 2 /* same */
        frame_type = 2 /* same */
        frame_type = 2 /* same */
        frame_type = 2 /* same */
        frame_type = 2 /* same */
        frame_type = 2 /* same */
      LineNumberTable:
        line 31: 0
      LocalVariableTable:
        Start  Length  Slot  Name   Signature
            0      87     0  this   Lscala/Tuple9;
            0      87     1   x$1   I
    MethodParameters:
      Name                           Flags
      x$1                            final

  public int hashCode();
    descriptor: ()I
    flags: (0x0001) ACC_PUBLIC
    Code:
      stack=2, locals=1, args_size=1
         0: getstatic     #203                // Field scala/util/hashing/MurmurHash3$.MODULE$:Lscala/util/hashing/MurmurHash3$;
         3: aload_0
         4: invokevirtual #207                // Method scala/util/hashing/MurmurHash3$.productHash:(Lscala/Product;)I
         7: ireturn
      LineNumberTable:
        line 31: 0
      LocalVariableTable:
        Start  Length  Slot  Name   Signature
            0       8     0  this   Lscala/Tuple9;

  public boolean equals(java.lang.Object);
    descriptor: (Ljava/lang/Object;)Z
    flags: (0x0001) ACC_PUBLIC
    Code:
      stack=2, locals=4, args_size=2
         0: aload_0
         1: aload_1
         2: if_acmpeq     162
         5: aload_1
         6: instanceof    #2                  // class scala/Tuple9
         9: ifeq          17
        12: iconst_1
        13: istore_2
        14: goto          19
        17: iconst_0
        18: istore_2
        19: iload_2
        20: ifeq          164
        23: aload_1
        24: checkcast     #2                  // class scala/Tuple9
        27: astore_3
        28: aload_0
        29: invokevirtual #124                // Method _1:()Ljava/lang/Object;
        32: aload_3
        33: invokevirtual #124                // Method _1:()Ljava/lang/Object;
        36: invokestatic  #213                // Method scala/runtime/BoxesRunTime.equals:(Ljava/lang/Object;Ljava/lang/Object;)Z
        39: ifeq          158
        42: aload_0
        43: invokevirtual #131                // Method _2:()Ljava/lang/Object;
        46: aload_3
        47: invokevirtual #131                // Method _2:()Ljava/lang/Object;
        50: invokestatic  #213                // Method scala/runtime/BoxesRunTime.equals:(Ljava/lang/Object;Ljava/lang/Object;)Z
        53: ifeq          158
        56: aload_0
        57: invokevirtual #133                // Method _3:()Ljava/lang/Object;
        60: aload_3
        61: invokevirtual #133                // Method _3:()Ljava/lang/Object;
        64: invokestatic  #213                // Method scala/runtime/BoxesRunTime.equals:(Ljava/lang/Object;Ljava/lang/Object;)Z
        67: ifeq          158
        70: aload_0
        71: invokevirtual #135                // Method _4:()Ljava/lang/Object;
        74: aload_3
        75: invokevirtual #135                // Method _4:()Ljava/lang/Object;
        78: invokestatic  #213                // Method scala/runtime/BoxesRunTime.equals:(Ljava/lang/Object;Ljava/lang/Object;)Z
        81: ifeq          158
        84: aload_0
        85: invokevirtual #137                // Method _5:()Ljava/lang/Object;
        88: aload_3
        89: invokevirtual #137                // Method _5:()Ljava/lang/Object;
        92: invokestatic  #213                // Method scala/runtime/BoxesRunTime.equals:(Ljava/lang/Object;Ljava/lang/Object;)Z
        95: ifeq          158
        98: aload_0
        99: invokevirtual #139                // Method _6:()Ljava/lang/Object;
       102: aload_3
       103: invokevirtual #139                // Method _6:()Ljava/lang/Object;
       106: invokestatic  #213                // Method scala/runtime/BoxesRunTime.equals:(Ljava/lang/Object;Ljava/lang/Object;)Z
       109: ifeq          158
       112: aload_0
       113: invokevirtual #141                // Method _7:()Ljava/lang/Object;
       116: aload_3
       117: invokevirtual #141                // Method _7:()Ljava/lang/Object;
       120: invokestatic  #213                // Method scala/runtime/BoxesRunTime.equals:(Ljava/lang/Object;Ljava/lang/Object;)Z
       123: ifeq          158
       126: aload_0
       127: invokevirtual #143                // Method _8:()Ljava/lang/Object;
       130: aload_3
       131: invokevirtual #143                // Method _8:()Ljava/lang/Object;
       134: invokestatic  #213                // Method scala/runtime/BoxesRunTime.equals:(Ljava/lang/Object;Ljava/lang/Object;)Z
       137: ifeq          158
       140: aload_0
       141: invokevirtual #145                // Method _9:()Ljava/lang/Object;
       144: aload_3
       145: invokevirtual #145                // Method _9:()Ljava/lang/Object;
       148: invokestatic  #213                // Method scala/runtime/BoxesRunTime.equals:(Ljava/lang/Object;Ljava/lang/Object;)Z
       151: ifeq          158
       154: iconst_1
       155: goto          159
       158: iconst_0
       159: ifeq          164
       162: iconst_1
       163: ireturn
       164: iconst_0
       165: ireturn
      StackMapTable: number_of_entries = 6
        frame_type = 17 /* same */
        frame_type = 252 /* append */
          offset_delta = 1
          locals = [ int ]
        frame_type = 252 /* append */
          offset_delta = 138
          locals = [ class scala/Tuple9 ]
        frame_type = 64 /* same_locals_1_stack_item */
          stack = [ int ]
        frame_type = 249 /* chop */
          offset_delta = 2
        frame_type = 252 /* append */
          offset_delta = 1
          locals = [ int ]
      LineNumberTable:
        line 31: 0
      LocalVariableTable:
        Start  Length  Slot  Name   Signature
            0     166     0  this   Lscala/Tuple9;
            0     166     1   x$1   Ljava/lang/Object;
    MethodParameters:
      Name                           Flags
      x$1                            final

  public scala.Tuple9(T1, T2, T3, T4, T5, T6, T7, T8, T9);
    descriptor: (Ljava/lang/Object;Ljava/lang/Object;Ljava/lang/Object;Ljava/lang/Object;Ljava/lang/Object;Ljava/lang/Object;Ljava/lang/Object;Ljava/lang/Object;Ljava/lang/Object;)V
    flags: (0x0001) ACC_PUBLIC
    Code:
      stack=2, locals=10, args_size=10
         0: aload_0
         1: aload_1
         2: putfield      #84                 // Field _1:Ljava/lang/Object;
         5: aload_0
         6: aload_2
         7: putfield      #87                 // Field _2:Ljava/lang/Object;
        10: aload_0
        11: aload_3
        12: putfield      #90                 // Field _3:Ljava/lang/Object;
        15: aload_0
        16: aload         4
        18: putfield      #93                 // Field _4:Ljava/lang/Object;
        21: aload_0
        22: aload         5
        24: putfield      #96                 // Field _5:Ljava/lang/Object;
        27: aload_0
        28: aload         6
        30: putfield      #99                 // Field _6:Ljava/lang/Object;
        33: aload_0
        34: aload         7
        36: putfield      #102                // Field _7:Ljava/lang/Object;
        39: aload_0
        40: aload         8
        42: putfield      #105                // Field _8:Ljava/lang/Object;
        45: aload_0
        46: aload         9
        48: putfield      #108                // Field _9:Ljava/lang/Object;
        51: aload_0
        52: invokespecial #217                // Method java/lang/Object."<init>":()V
        55: return
      LineNumberTable:
        line 31: 0
        line 32: 51
      LocalVariableTable:
        Start  Length  Slot  Name   Signature
            0      56     0  this   Lscala/Tuple9;
            0      56     1    _1   Ljava/lang/Object;
            0      56     2    _2   Ljava/lang/Object;
            0      56     3    _3   Ljava/lang/Object;
            0      56     4    _4   Ljava/lang/Object;
            0      56     5    _5   Ljava/lang/Object;
            0      56     6    _6   Ljava/lang/Object;
            0      56     7    _7   Ljava/lang/Object;
            0      56     8    _8   Ljava/lang/Object;
            0      56     9    _9   Ljava/lang/Object;
    Signature: #214                         // (TT1;TT2;TT3;TT4;TT5;TT6;TT7;TT8;TT9;)V
    MethodParameters:
      Name                           Flags
      _1                             final
      _2                             final
      _3                             final
      _4                             final
      _5                             final
      _6                             final
      _7                             final
      _8                             final
      _9                             final
}
InnerClasses:
  public final #15;                       // class scala/runtime/ScalaRunTime$$anon$1
Signature: #3                           // <T1:Ljava/lang/Object;T2:Ljava/lang/Object;T3:Ljava/lang/Object;T4:Ljava/lang/Object;T5:Ljava/lang/Object;T6:Ljava/lang/Object;T7:Ljava/lang/Object;T8:Ljava/lang/Object;T9:Ljava/lang/Object;>Ljava/lang/Object;Lscala/Product9<TT1;TT2;TT3;TT4;TT5;TT6;TT7;TT8;TT9;>;Ljava/io/Serializable;
SourceFile: "Tuple9.scala"
RuntimeVisibleAnnotations:
  0: #11(#12=s#13)
    scala.reflect.ScalaSignature(
      bytes="\u0006\u0005\r-c\u0001\u0002\u0017.\u0005BB\u0001b\u001b\u0001\u0003\u0016\u0004%\t\u0001\u001c\u0005\t[\u0002\u0011\t\u0012)A\u0005s!Aa\u000e\u0001BK\u0002\u0013\u0005q\u000e\u0003\u0005q\u0001\tE\t\u0015!\u0003E\u0011!\t\bA!f\u0001\n\u0003\u0011\b\u0002C:\u0001\u0005#\u0005\u000b\u0011B$\t\u0011Q\u0004!Q3A\u0005\u0002UD\u0001B\u001e\u0001\u0003\u0012\u0003\u0006IA\u0013\u0005\to\u0002\u0011)\u001a!C\u0001q\"A\u0011\u0010\u0001B\tB\u0003%Q\n\u0003\u0005{\u0001\tU\r\u0011\"\u0001|\u0011!a\bA!E!\u0002\u0013\u0001\u0006\u0002C?\u0001\u0005+\u0007I\u0011\u0001@\t\u0011}\u0004!\u0011#Q\u0001\nMC!\"!\u0001\u0001\u0005+\u0007I\u0011AA\u0002\u0011%\t)\u0001\u0001B\tB\u0003%a\u000b\u0003\u0006\u0002\b\u0001\u0011)\u001a!C\u0001\u0003\u0013A\u0011\"a\u0003\u0001\u0005#\u0005\u000b\u0011B-\t\u000f\u00055\u0001\u0001\"\u0001\u0002\u0010!9\u0011Q\u0005\u0001\u0005B\u0005\u001d\u0002\"CA\u001d\u0001\u0005\u0005I\u0011AA\u001e\u0011%\t9\bAI\u0001\n\u0003\tI\bC\u0005\u0002$\u0002\t\n\u0011\"\u0001\u0002&\"I\u0011Q\u0018\u0001\u0012\u0002\u0013\u0005\u0011q\u0018\u0005\n\u0003/\u0004\u0011\u0013!C\u0001\u00033D\u0011\"!=\u0001#\u0003%\t!a=\t\u0013\t-\u0001!%A\u0005\u0002\t5\u0001\"\u0003B\u0013\u0001E\u0005I\u0011\u0001B\u0014\u0011%\u0011y\u0004AI\u0001\n\u0003\u0011\t\u0005C\u0005\u0003Z\u0001\t\n\u0011\"\u0001\u0003\\!I!1\u000f\u0001\u0002\u0002\u0013\u0005#Q\u000f\u0005\n\u0005\u000b\u0003\u0011\u0011!C!\u0005\u000fC\u0011B!&\u0001\u0003\u0003%\tAa&\t\u0013\t\r\u0006!!A\u0005B\t\u0015\u0006\"\u0003BX\u0001\u0005\u0005I\u0011\tBY\u0011%\u0011\u0019\fAA\u0001\n\u0003\u0012)lB\u0005\u0003:6\n\t\u0011#\u0001\u0003<\u001aAA&LA\u0001\u0012\u0003\u0011i\fC\u0004\u0002\u000e\u0019\"\tA!3\t\u0013\u0005\u0015b%!A\u0005F\t-\u0007\"\u0003BgM\u0005\u0005I\u0011\u0011Bh\u0011%\u0019YAJA\u0001\n\u0003\u001bi\u0001C\u0005\u0004B\u0019\n\t\u0011\"\u0003\u0004D\t1A+\u001e9mKfR\u0011AL\u0001\u0006g\u000e\fG.Y\u0002\u0001+)\t4(\u0012%L\u001dF#vKW\n\u0006\u0001I2Dl\u0018\t\u0003gQj\u0011!L\u0005\u0003k5\u0012a!\u00118z%\u00164\u0007cC\u001a8s\u0011;%*\u0014)T-fK!\u0001O\u0017\u0003\u0011A\u0013x\u000eZ;dif\u0002\"AO\u001e\r\u0001\u00111A\b\u0001CC\u0002u\u0012!\u0001V\u0019\u0012\u0005y\n\u0005CA\u001a@\u0013\t\u0001UFA\u0004O_RD\u0017N\\4\u0011\u0005M\u0012\u0015BA\".\u0005\r\te.\u001f\t\u0003u\u0015#aA\u0012\u0001\u0005\u0006\u0004i$A\u0001+3!\tQ\u0004\n\u0002\u0004J\u0001\u0011\u0015\r!\u0010\u0002\u0003)N\u0002\"AO&\u0005\r1\u0003AQ1\u0001>\u0005\t!F\u0007\u0005\u0002;\u001d\u00121q\n\u0001CC\u0002u\u0012!\u0001V\u001b\u0011\u0005i\nFA\u0002*\u0001\t\u000b\u0007QH\u0001\u0002UmA\u0011!\b\u0016\u0003\u0007+\u0002!)\u0019A\u001f\u0003\u0005Q;\u0004C\u0001\u001eX\t\u0019A\u0006\u0001\"b\u0001{\t\u0011A\u000b\u000f\t\u0003ui#aa\u0017\u0001\u0005\u0006\u0004i$A\u0001+:!\t\u0019T,\u0003\u0002_[\t9\u0001K]8ek\u000e$\bC\u00011i\u001d\t\tgM\u0004\u0002cK6\t1M\u0003\u0002e_\u00051AH]8pizJ\u0011AL\u0005\u0003O6\nq\u0001]1dW\u0006<W-\u0003\u0002jU\na1+\u001a:jC2L\'0\u00192mK*\u0011q-L\u0001\u0003?F*\u0012!O\u0001\u0004?F\u0002\u0013AA03+\u0005!\u0015aA03A\u0005\u0011qlM\u000b\u0002\u000f\u0006\u0019ql\r\u0011\u0002\u0005}#T#\u0001&\u0002\u0007}#\u0004%\u0001\u0002`kU\tQ*A\u0002`k\u0001\n!a\u0018\u001c\u0016\u0003A\u000b1a\u0018\u001c!\u0003\tyv\'F\u0001T\u0003\ryv\u0007I\u0001\u0003?b*\u0012AV\u0001\u0004?b\u0002\u0013AA0:+\u0005I\u0016aA0:A\u00051A(\u001b8jiz\"B#!\u0005\u0002\u0014\u0005U\u0011qCA\r\u00037\ti\"a\b\u0002\"\u0005\r\u0002cC\u001a\u0001s\u0011;%*\u0014)T-fCQa[\nA\u0002eBQA\\\nA\u0002\u0011CQ!]\nA\u0002\u001dCQ\u0001^\nA\u0002)CQa^\nA\u00025CQA_\nA\u0002ACQ!`\nA\u0002MCa!!\u0001\u0014\u0001\u00041\u0006BBA\u0004\'\u0001\u0007\u0011,\u0001\u0005u_N#(/\u001b8h)\t\tI\u0003\u0005\u0003\u0002,\u0005Mb\u0002BA\u0017\u0003_\u0001\"AY\u0017\n\u0007\u0005ER&\u0001\u0004Qe\u0016$WMZ\u0005\u0005\u0003k\t9D\u0001\u0004TiJLgn\u001a\u0006\u0004\u0003ci\u0013\u0001B2paf,B#!\u0010\u0002D\u0005\u001d\u00131JA(\u0003\'\n9&a\u0017\u0002`\u0005\rD\u0003FA \u0003K\n9\'!\u001b\u0002l\u00055\u0014qNA9\u0003g\n)\b\u0005\u000b4\u0001\u0005\u0005\u0013QIA%\u0003\u001b\n\t&!\u0016\u0002Z\u0005u\u0013\u0011\r\t\u0004u\u0005\rC!\u0002\u001f\u0016\u0005\u0004i\u0004c\u0001\u001e\u0002H\u0011)a)\u0006b\u0001{A\u0019!(a\u0013\u0005\u000b%+\"\u0019A\u001f\u0011\u0007i\ny\u0005B\u0003M+\t\u0007Q\bE\u0002;\u0003\'\"QaT\u000bC\u0002u\u00022AOA,\t\u0015\u0011VC1\u0001>!\rQ\u00141\f\u0003\u0006+V\u0011\r!\u0010\t\u0004u\u0005}C!\u0002-\u0016\u0005\u0004i\u0004c\u0001\u001e\u0002d\u0011)1,\u0006b\u0001{!A1.\u0006I\u0001\u0002\u0004\t\t\u0005\u0003\u0005o+A\u0005\t\u0019AA#\u0011!\tX\u0003%AA\u0002\u0005%\u0003\u0002\u0003;\u0016!\u0003\u0005\r!!\u0014\t\u0011],\u0002\u0013!a\u0001\u0003#B\u0001B_\u000b\u0011\u0002\u0003\u0007\u0011Q\u000b\u0005\t{V\u0001\n\u00111\u0001\u0002Z!I\u0011\u0011A\u000b\u0011\u0002\u0003\u0007\u0011Q\f\u0005\n\u0003\u000f)\u0002\u0013!a\u0001\u0003C\nabY8qs\u0012\"WMZ1vYR$\u0013\'\u0006\u000b\u0002|\u0005E\u00151SAK\u0003/\u000bI*a\'\u0002\u001e\u0006}\u0015\u0011U\u000b\u0003\u0003{R3!OA@W\t\t\t\t\u0005\u0003\u0002\u0004\u00065UBAAC\u0015\u0011\t9)!#\u0002\u0013Ut7\r[3dW\u0016$\'bAAF[\u0005Q\u0011M\u001c8pi\u0006$\u0018n\u001c8\n\t\u0005=\u0015Q\u0011\u0002\u0012k:\u001c\u0007.Z2lK\u00124\u0016M]5b]\u000e,G!\u0002\u001f\u0017\u0005\u0004iD!\u0002$\u0017\u0005\u0004iD!B%\u0017\u0005\u0004iD!\u0002\'\u0017\u0005\u0004iD!B(\u0017\u0005\u0004iD!\u0002*\u0017\u0005\u0004iD!B+\u0017\u0005\u0004iD!\u0002-\u0017\u0005\u0004iD!B.\u0017\u0005\u0004i\u0014AD2paf$C-\u001a4bk2$HEM\u000b\u0015\u0003O\u000bY+!,\u00020\u0006E\u00161WA[\u0003o\u000bI,a/\u0016\u0005\u0005%&f\u0001#\u0002\u0000\u0011)Ah\u0006b\u0001{\u0011)ai\u0006b\u0001{\u0011)\u0011j\u0006b\u0001{\u0011)Aj\u0006b\u0001{\u0011)qj\u0006b\u0001{\u0011)!k\u0006b\u0001{\u0011)Qk\u0006b\u0001{\u0011)\u0001l\u0006b\u0001{\u0011)1l\u0006b\u0001{\u0005q1m\u001c9zI\u0011,g-Y;mi\u0012\u001aT\u0003FAa\u0003\u000b\f9-!3\u0002L\u00065\u0017qZAi\u0003\'\f).\u0006\u0002\u0002D*\u001aq)a \u0005\u000bqB\"\u0019A\u001f\u0005\u000b\u0019C\"\u0019A\u001f\u0005\u000b%C\"\u0019A\u001f\u0005\u000b1C\"\u0019A\u001f\u0005\u000b=C\"\u0019A\u001f\u0005\u000bIC\"\u0019A\u001f\u0005\u000bUC\"\u0019A\u001f\u0005\u000baC\"\u0019A\u001f\u0005\u000bmC\"\u0019A\u001f\u0002\u001d\r|\u0007/\u001f\u0013eK\u001a\fW\u000f\u001c;%iU!\u00121\\Ap\u0003C\f\u0019/!:\u0002h\u0006%\u00181^Aw\u0003_,\"!!8+\u0007)\u000by\bB\u0003=3\t\u0007Q\bB\u0003G3\t\u0007Q\bB\u0003J3\t\u0007Q\bB\u0003M3\t\u0007Q\bB\u0003P3\t\u0007Q\bB\u0003S3\t\u0007Q\bB\u0003V3\t\u0007Q\bB\u0003Y3\t\u0007Q\bB\u0003\\3\t\u0007Q(\u0001\bd_BLH\u0005Z3gCVdG\u000fJ\u001b\u0016)\u0005U\u0018\u0011`A~\u0003{\fyP!\u0001\u0003\u0004\t\u0015!q\u0001B\u0005+\t\t9PK\u0002N\u0003\u007f\"Q\u0001\u0010\u000eC\u0002u\"QA\u0012\u000eC\u0002u\"Q!\u0013\u000eC\u0002u\"Q\u0001\u0014\u000eC\u0002u\"Qa\u0014\u000eC\u0002u\"QA\u0015\u000eC\u0002u\"Q!\u0016\u000eC\u0002u\"Q\u0001\u0017\u000eC\u0002u\"Qa\u0017\u000eC\u0002u\nabY8qs\u0012\"WMZ1vYR$c\'\u0006\u000b\u0003\u0010\tM!Q\u0003B\f\u00053\u0011YB!\b\u0003 \t\u0005\"1E\u000b\u0003\u0005#Q3\u0001UA@\t\u0015a4D1\u0001>\t\u001515D1\u0001>\t\u0015I5D1\u0001>\t\u0015a5D1\u0001>\t\u0015y5D1\u0001>\t\u0015\u00116D1\u0001>\t\u0015)6D1\u0001>\t\u0015A6D1\u0001>\t\u0015Y6D1\u0001>\u00039\u0019w\u000e]=%I\u00164\u0017-\u001e7uI]*BC!\u000b\u0003.\t=\"\u0011\u0007B\u001a\u0005k\u00119D!\u000f\u0003<\tuRC\u0001B\u0016U\r\u0019\u0016q\u0010\u0003\u0006yq\u0011\r!\u0010\u0003\u0006\rr\u0011\r!\u0010\u0003\u0006\u0013r\u0011\r!\u0010\u0003\u0006\u0019r\u0011\r!\u0010\u0003\u0006\u001fr\u0011\r!\u0010\u0003\u0006%r\u0011\r!\u0010\u0003\u0006+r\u0011\r!\u0010\u0003\u00061r\u0011\r!\u0010\u0003\u00067r\u0011\r!P\u0001\u000fG>\u0004\u0018\u0010\n3fM\u0006,H\u000e\u001e\u00139+Q\u0011\u0019Ea\u0012\u0003J\t-#Q\nB(\u0005#\u0012\u0019F!\u0016\u0003XU\u0011!Q\t\u0016\u0004-\u0006}D!\u0002\u001f\u001e\u0005\u0004iD!\u0002$\u001e\u0005\u0004iD!B%\u001e\u0005\u0004iD!\u0002\'\u001e\u0005\u0004iD!B(\u001e\u0005\u0004iD!\u0002*\u001e\u0005\u0004iD!B+\u001e\u0005\u0004iD!\u0002-\u001e\u0005\u0004iD!B.\u001e\u0005\u0004i\u0014AD2paf$C-\u001a4bk2$H%O\u000b\u0015\u0005;\u0012\tGa\u0019\u0003f\t\u001d$\u0011\u000eB6\u0005[\u0012yG!\u001d\u0016\u0005\t}#fA-\u0002\u0000\u0011)AH\bb\u0001{\u0011)aI\bb\u0001{\u0011)\u0011J\bb\u0001{\u0011)AJ\bb\u0001{\u0011)qJ\bb\u0001{\u0011)!K\bb\u0001{\u0011)QK\bb\u0001{\u0011)\u0001L\bb\u0001{\u0011)1L\bb\u0001{\u0005i\u0001O]8ek\u000e$\bK]3gSb,\"Aa\u001e\u0011\t\te$1Q\u0007\u0003\u0005wRAA! \u0003\u0000\u0005!A.\u00198h\u0015\t\u0011\t)\u0001\u0003kCZ\f\u0017\u0002BA\u001b\u0005w\nq\u0002\u001d:pIV\u001cG/\u0013;fe\u0006$xN]\u000b\u0003\u0005\u0013\u0003RAa#\u0003\u0012\u0006k!A!$\u000b\u0007\t=U&\u0001\u0006d_2dWm\u0019;j_:LAAa%\u0003\u000e\nA\u0011\n^3sCR|\'/\u0001\u0005dC:,\u0015/^1m)\u0011\u0011IJa(\u0011\u0007M\u0012Y*C\u0002\u0003\u001e6\u0012qAQ8pY\u0016\fg\u000e\u0003\u0005\u0003\"\u0006\n\t\u00111\u0001B\u0003\rAH%M\u0001\u0013aJ|G-^2u\u000b2,W.\u001a8u\u001d\u0006lW\r\u0006\u0003\u0003x\t\u001d\u0006\"\u0003BQE\u0005\u0005\t\u0019\u0001BU!\r\u0019$1V\u0005\u0004\u0005[k#aA%oi\u0006A\u0001.Y:i\u0007>$W\r\u0006\u0002\u0003*\u00061Q-];bYN$BA!\'\u00038\"A!\u0011\u0015\u0013\u0002\u0002\u0003\u0007\u0011)\u0001\u0004UkBdW-\u000f\t\u0003g\u0019\u001aBA\n\u001a\u0003@B!!\u0011\u0019Bd\u001b\t\u0011\u0019M\u0003\u0003\u0003F\n}\u0014AA5p\u0013\rI\'1\u0019\u000b\u0003\u0005w#\"Aa\u001e\u0002\u000b\u0005\u0004\b\u000f\\=\u0016)\tE\'q\u001bBn\u0005?\u0014\u0019Oa:\u0003l\n=(1\u001fB|)Q\u0011\u0019N!?\u0003|\nu(q`B\u0001\u0007\u0007\u0019)aa\u0002\u0004\nA!2\u0007\u0001Bk\u00053\u0014iN!9\u0003f\n%(Q\u001eBy\u0005k\u00042A\u000fBl\t\u0015a\u0014F1\u0001>!\rQ$1\u001c\u0003\u0006\r&\u0012\r!\u0010\t\u0004u\t}G!B%*\u0005\u0004i\u0004c\u0001\u001e\u0003d\u0012)A*\u000bb\u0001{A\u0019!Ha:\u0005\u000b=K#\u0019A\u001f\u0011\u0007i\u0012Y\u000fB\u0003SS\t\u0007Q\bE\u0002;\u0005_$Q!V\u0015C\u0002u\u00022A\u000fBz\t\u0015A\u0016F1\u0001>!\rQ$q\u001f\u0003\u00067&\u0012\r!\u0010\u0005\u0007W&\u0002\rA!6\t\r9L\u0003\u0019\u0001Bm\u0011\u0019\t\u0018\u00061\u0001\u0003^\"1A/\u000ba\u0001\u0005CDaa^\u0015A\u0002\t\u0015\bB\u0002>*\u0001\u0004\u0011I\u000f\u0003\u0004~S\u0001\u0007!Q\u001e\u0005\b\u0003\u0003I\u0003\u0019\u0001By\u0011\u001d\t9!\u000ba\u0001\u0005k\fq!\u001e8baBd\u00170\u0006\u000b\u0004\u0010\rm1qDB\u0012\u0007O\u0019Yca\f\u00044\r]21\b\u000b\u0005\u0007#\u0019i\u0004E\u00034\u0007\'\u00199\"C\u0002\u0004\u00165\u0012aa\u00149uS>t\u0007\u0003F\u001a\u0001\u00073\u0019ib!\t\u0004&\r%2QFB\u0019\u0007k\u0019I\u0004E\u0002;\u00077!Q\u0001\u0010\u0016C\u0002u\u00022AOB\u0010\t\u00151%F1\u0001>!\rQ41\u0005\u0003\u0006\u0013*\u0012\r!\u0010\t\u0004u\r\u001dB!\u0002\'+\u0005\u0004i\u0004c\u0001\u001e\u0004,\u0011)qJ\u000bb\u0001{A\u0019!ha\f\u0005\u000bIS#\u0019A\u001f\u0011\u0007i\u001a\u0019\u0004B\u0003VU\t\u0007Q\bE\u0002;\u0007o!Q\u0001\u0017\u0016C\u0002u\u00022AOB\u001e\t\u0015Y&F1\u0001>\u0011%\u0019yDKA\u0001\u0002\u0004\u00199\"A\u0002yIA\nAb\u001e:ji\u0016\u0014V\r\u001d7bG\u0016$\"a!\u0012\u0011\t\te4qI\u0005\u0005\u0007\u0013\u0012YH\u0001\u0004PE*,7\r\u001e"
    )
  ScalaInlineInfo: length = 0x9A (unknown attribute)
   01 01 00 1E 00 33 00 34 01 00 10 00 51 01 00 13
   00 51 01 00 15 00 51 01 00 17 00 51 01 00 19 00
   51 01 00 1B 00 51 01 00 1D 00 51 01 00 1F 00 51
   01 00 21 00 51 01 00 B1 00 B2 01 00 96 00 31 01
   00 97 00 51 01 00 99 00 51 01 00 9B 00 51 01 00
   9D 00 51 01 00 9F 00 51 01 00 A1 00 51 01 00 A3
   00 51 01 00 A5 00 51 01 00 A7 00 51 01 00 D0 00
   B2 01 00 C6 00 38 01 00 37 00 38 01 00 3E 00 3F
   01 00 B4 00 B5 01 00 48 00 49 01 00 AC 00 49 01
   00 A9 00 6E 01 00 6D 00 6E 01
  ScalaSig: length = 0x3 (unknown attribute)
   05 02 00
