Classfile /Users/mw/Projects/slang-braindump/.jar/jar8/assemble/slang-braindump/assemble/content/scala/Tuple2$mcDI$sp.class
  Last modified May 29, 2022; size 2275 bytes
  SHA-256 checksum abce608651d8de870240518e5e37c72dde7970b210274475e1e1a353dab2f680
  Compiled from "Tuple2.scala"
public final class scala.Tuple2$mcDI$sp extends scala.Tuple2<java.lang.Object, java.lang.Object> implements scala.Product2$mcDI$sp
  minor version: 0
  major version: 52
  flags: (0x0031) ACC_PUBLIC, ACC_FINAL, ACC_SUPER
  this_class: #2                          // scala/Tuple2$mcDI$sp
  super_class: #5                         // scala/Tuple2
  interfaces: 1, fields: 2, methods: 16, attributes: 4
Constant pool:
   #1 = Utf8               scala/Tuple2$mcDI$sp
   #2 = Class              #1             // scala/Tuple2$mcDI$sp
   #3 = Utf8               Lscala/Tuple2<Ljava/lang/Object;Ljava/lang/Object;>;Lscala/Product2$mcDI$sp;
   #4 = Utf8               scala/Tuple2
   #5 = Class              #4             // scala/Tuple2
   #6 = Utf8               scala/Product2$mcDI$sp
   #7 = Class              #6             // scala/Product2$mcDI$sp
   #8 = Utf8               Tuple2.scala
   #9 = Utf8               _1$mcD$sp
  #10 = Utf8               D
  #11 = Utf8               _2$mcI$sp
  #12 = Utf8               I
  #13 = Utf8               ()D
  #14 = NameAndType        #9:#10         // _1$mcD$sp:D
  #15 = Fieldref           #2.#14         // scala/Tuple2$mcDI$sp._1$mcD$sp:D
  #16 = Utf8               this
  #17 = Utf8               Lscala/Tuple2$mcDI$sp;
  #18 = Utf8               _1
  #19 = NameAndType        #9:#13         // _1$mcD$sp:()D
  #20 = Methodref          #2.#19         // scala/Tuple2$mcDI$sp._1$mcD$sp:()D
  #21 = Utf8               ()I
  #22 = NameAndType        #11:#12        // _2$mcI$sp:I
  #23 = Fieldref           #2.#22         // scala/Tuple2$mcDI$sp._2$mcI$sp:I
  #24 = Utf8               _2
  #25 = NameAndType        #11:#21        // _2$mcI$sp:()I
  #26 = Methodref          #2.#25         // scala/Tuple2$mcDI$sp._2$mcI$sp:()I
  #27 = Utf8               swap
  #28 = Utf8               ()Lscala/Tuple2;
  #29 = Utf8               ()Lscala/Tuple2<Ljava/lang/Object;Ljava/lang/Object;>;
  #30 = Utf8               swap$mcDI$sp
  #31 = NameAndType        #30:#28        // swap$mcDI$sp:()Lscala/Tuple2;
  #32 = Methodref          #2.#31         // scala/Tuple2$mcDI$sp.swap$mcDI$sp:()Lscala/Tuple2;
  #33 = Utf8               scala/Tuple2$mcID$sp
  #34 = Class              #33            // scala/Tuple2$mcID$sp
  #35 = Utf8               <init>
  #36 = Utf8               (ID)V
  #37 = NameAndType        #35:#36        // "<init>":(ID)V
  #38 = Methodref          #34.#37        // scala/Tuple2$mcID$sp."<init>":(ID)V
  #39 = Utf8               copy$default$1
  #40 = Utf8               <T1:Ljava/lang/Object;T2:Ljava/lang/Object;>()D
  #41 = Utf8               copy$default$1$mcD$sp
  #42 = Utf8               copy$default$2
  #43 = Utf8               <T1:Ljava/lang/Object;T2:Ljava/lang/Object;>()I
  #44 = Utf8               copy$default$2$mcI$sp
  #45 = Utf8               specInstance$
  #46 = Utf8               ()Z
  #47 = Utf8               ()Ljava/lang/Object;
  #48 = NameAndType        #42:#21        // copy$default$2:()I
  #49 = Methodref          #2.#48         // scala/Tuple2$mcDI$sp.copy$default$2:()I
  #50 = Utf8               scala/runtime/BoxesRunTime
  #51 = Class              #50            // scala/runtime/BoxesRunTime
  #52 = Utf8               boxToInteger
  #53 = Utf8               (I)Ljava/lang/Integer;
  #54 = NameAndType        #52:#53        // boxToInteger:(I)Ljava/lang/Integer;
  #55 = Methodref          #51.#54        // scala/runtime/BoxesRunTime.boxToInteger:(I)Ljava/lang/Integer;
  #56 = NameAndType        #39:#13        // copy$default$1:()D
  #57 = Methodref          #2.#56         // scala/Tuple2$mcDI$sp.copy$default$1:()D
  #58 = Utf8               boxToDouble
  #59 = Utf8               (D)Ljava/lang/Double;
  #60 = NameAndType        #58:#59        // boxToDouble:(D)Ljava/lang/Double;
  #61 = Methodref          #51.#60        // scala/runtime/BoxesRunTime.boxToDouble:(D)Ljava/lang/Double;
  #62 = NameAndType        #24:#21        // _2:()I
  #63 = Methodref          #2.#62         // scala/Tuple2$mcDI$sp._2:()I
  #64 = NameAndType        #18:#13        // _1:()D
  #65 = Methodref          #2.#64         // scala/Tuple2$mcDI$sp._1:()D
  #66 = Utf8               (DI)V
  #67 = Utf8               (Ljava/lang/Object;Ljava/lang/Object;)V
  #68 = NameAndType        #35:#67        // "<init>":(Ljava/lang/Object;Ljava/lang/Object;)V
  #69 = Methodref          #5.#68         // scala/Tuple2."<init>":(Ljava/lang/Object;Ljava/lang/Object;)V
  #70 = Utf8               Code
  #71 = Utf8               LocalVariableTable
  #72 = Utf8               LineNumberTable
  #73 = Utf8               Signature
  #74 = Utf8               MethodParameters
  #75 = Utf8               SourceFile
  #76 = Utf8               ScalaInlineInfo
  #77 = Utf8               Scala
{
  public final double _1$mcD$sp;
    descriptor: D
    flags: (0x0011) ACC_PUBLIC, ACC_FINAL

  public final int _2$mcI$sp;
    descriptor: I
    flags: (0x0011) ACC_PUBLIC, ACC_FINAL

  public double _1$mcD$sp();
    descriptor: ()D
    flags: (0x0001) ACC_PUBLIC
    Code:
      stack=2, locals=1, args_size=1
         0: aload_0
         1: getfield      #15                 // Field _1$mcD$sp:D
         4: dreturn
      LocalVariableTable:
        Start  Length  Slot  Name   Signature
            0       5     0  this   Lscala/Tuple2$mcDI$sp;

  public double _1();
    descriptor: ()D
    flags: (0x0001) ACC_PUBLIC
    Code:
      stack=2, locals=1, args_size=1
         0: aload_0
         1: invokevirtual #20                 // Method _1$mcD$sp:()D
         4: dreturn
      LineNumberTable:
        line 24: 0
      LocalVariableTable:
        Start  Length  Slot  Name   Signature
            0       5     0  this   Lscala/Tuple2$mcDI$sp;

  public int _2$mcI$sp();
    descriptor: ()I
    flags: (0x0001) ACC_PUBLIC
    Code:
      stack=1, locals=1, args_size=1
         0: aload_0
         1: getfield      #23                 // Field _2$mcI$sp:I
         4: ireturn
      LocalVariableTable:
        Start  Length  Slot  Name   Signature
            0       5     0  this   Lscala/Tuple2$mcDI$sp;

  public int _2();
    descriptor: ()I
    flags: (0x0001) ACC_PUBLIC
    Code:
      stack=1, locals=1, args_size=1
         0: aload_0
         1: invokevirtual #26                 // Method _2$mcI$sp:()I
         4: ireturn
      LineNumberTable:
        line 24: 0
      LocalVariableTable:
        Start  Length  Slot  Name   Signature
            0       5     0  this   Lscala/Tuple2$mcDI$sp;

  public scala.Tuple2<java.lang.Object, java.lang.Object> swap();
    descriptor: ()Lscala/Tuple2;
    flags: (0x0001) ACC_PUBLIC
    Code:
      stack=1, locals=1, args_size=1
         0: aload_0
         1: invokevirtual #32                 // Method swap$mcDI$sp:()Lscala/Tuple2;
         4: areturn
      LineNumberTable:
        line 33: 0
      LocalVariableTable:
        Start  Length  Slot  Name   Signature
            0       5     0  this   Lscala/Tuple2$mcDI$sp;
    Signature: #29                          // ()Lscala/Tuple2<Ljava/lang/Object;Ljava/lang/Object;>;

  public scala.Tuple2<java.lang.Object, java.lang.Object> swap$mcDI$sp();
    descriptor: ()Lscala/Tuple2;
    flags: (0x0001) ACC_PUBLIC
    Code:
      stack=5, locals=1, args_size=1
         0: new           #34                 // class scala/Tuple2$mcID$sp
         3: dup
         4: aload_0
         5: invokevirtual #26                 // Method _2$mcI$sp:()I
         8: aload_0
         9: invokevirtual #20                 // Method _1$mcD$sp:()D
        12: invokespecial #38                 // Method scala/Tuple2$mcID$sp."<init>":(ID)V
        15: areturn
      LineNumberTable:
        line 33: 0
        line 24: 4
        line 24: 8
        line 33: 12
      LocalVariableTable:
        Start  Length  Slot  Name   Signature
            0      16     0  this   Lscala/Tuple2$mcDI$sp;
    Signature: #29                          // ()Lscala/Tuple2<Ljava/lang/Object;Ljava/lang/Object;>;

  public <T1 extends java.lang.Object, T2 extends java.lang.Object> double copy$default$1();
    descriptor: ()D
    flags: (0x0001) ACC_PUBLIC
    Code:
      stack=2, locals=1, args_size=1
         0: aload_0
         1: invokevirtual #20                 // Method _1$mcD$sp:()D
         4: dreturn
      LineNumberTable:
        line 24: 0
        line 24: 4
      LocalVariableTable:
        Start  Length  Slot  Name   Signature
            0       5     0  this   Lscala/Tuple2$mcDI$sp;
    Signature: #40                          // <T1:Ljava/lang/Object;T2:Ljava/lang/Object;>()D

  public <T1 extends java.lang.Object, T2 extends java.lang.Object> double copy$default$1$mcD$sp();
    descriptor: ()D
    flags: (0x0001) ACC_PUBLIC
    Code:
      stack=2, locals=1, args_size=1
         0: aload_0
         1: invokevirtual #20                 // Method _1$mcD$sp:()D
         4: dreturn
      LineNumberTable:
        line 24: 0
        line 24: 4
      LocalVariableTable:
        Start  Length  Slot  Name   Signature
            0       5     0  this   Lscala/Tuple2$mcDI$sp;
    Signature: #40                          // <T1:Ljava/lang/Object;T2:Ljava/lang/Object;>()D

  public <T1 extends java.lang.Object, T2 extends java.lang.Object> int copy$default$2();
    descriptor: ()I
    flags: (0x0001) ACC_PUBLIC
    Code:
      stack=1, locals=1, args_size=1
         0: aload_0
         1: invokevirtual #26                 // Method _2$mcI$sp:()I
         4: ireturn
      LineNumberTable:
        line 24: 0
        line 24: 4
      LocalVariableTable:
        Start  Length  Slot  Name   Signature
            0       5     0  this   Lscala/Tuple2$mcDI$sp;
    Signature: #43                          // <T1:Ljava/lang/Object;T2:Ljava/lang/Object;>()I

  public <T1 extends java.lang.Object, T2 extends java.lang.Object> int copy$default$2$mcI$sp();
    descriptor: ()I
    flags: (0x0001) ACC_PUBLIC
    Code:
      stack=1, locals=1, args_size=1
         0: aload_0
         1: invokevirtual #26                 // Method _2$mcI$sp:()I
         4: ireturn
      LineNumberTable:
        line 24: 0
        line 24: 4
      LocalVariableTable:
        Start  Length  Slot  Name   Signature
            0       5     0  this   Lscala/Tuple2$mcDI$sp;
    Signature: #43                          // <T1:Ljava/lang/Object;T2:Ljava/lang/Object;>()I

  public boolean specInstance$();
    descriptor: ()Z
    flags: (0x0001) ACC_PUBLIC
    Code:
      stack=1, locals=1, args_size=1
         0: iconst_1
         1: ireturn
      LineNumberTable:
        line 24: 0
      LocalVariableTable:
        Start  Length  Slot  Name   Signature
            0       2     0  this   Lscala/Tuple2$mcDI$sp;

  public java.lang.Object copy$default$2();
    descriptor: ()Ljava/lang/Object;
    flags: (0x1041) ACC_PUBLIC, ACC_BRIDGE, ACC_SYNTHETIC
    Code:
      stack=1, locals=1, args_size=1
         0: aload_0
         1: invokevirtual #49                 // Method copy$default$2:()I
         4: invokestatic  #55                 // Method scala/runtime/BoxesRunTime.boxToInteger:(I)Ljava/lang/Integer;
         7: areturn
      LineNumberTable:
        line 24: 0
      LocalVariableTable:
        Start  Length  Slot  Name   Signature
            0       8     0  this   Lscala/Tuple2$mcDI$sp;

  public java.lang.Object copy$default$1();
    descriptor: ()Ljava/lang/Object;
    flags: (0x1041) ACC_PUBLIC, ACC_BRIDGE, ACC_SYNTHETIC
    Code:
      stack=2, locals=1, args_size=1
         0: aload_0
         1: invokevirtual #57                 // Method copy$default$1:()D
         4: invokestatic  #61                 // Method scala/runtime/BoxesRunTime.boxToDouble:(D)Ljava/lang/Double;
         7: areturn
      LineNumberTable:
        line 24: 0
      LocalVariableTable:
        Start  Length  Slot  Name   Signature
            0       8     0  this   Lscala/Tuple2$mcDI$sp;

  public java.lang.Object _2();
    descriptor: ()Ljava/lang/Object;
    flags: (0x1041) ACC_PUBLIC, ACC_BRIDGE, ACC_SYNTHETIC
    Code:
      stack=1, locals=1, args_size=1
         0: aload_0
         1: invokevirtual #63                 // Method _2:()I
         4: invokestatic  #55                 // Method scala/runtime/BoxesRunTime.boxToInteger:(I)Ljava/lang/Integer;
         7: areturn
      LineNumberTable:
        line 24: 0
      LocalVariableTable:
        Start  Length  Slot  Name   Signature
            0       8     0  this   Lscala/Tuple2$mcDI$sp;

  public java.lang.Object _1();
    descriptor: ()Ljava/lang/Object;
    flags: (0x1041) ACC_PUBLIC, ACC_BRIDGE, ACC_SYNTHETIC
    Code:
      stack=2, locals=1, args_size=1
         0: aload_0
         1: invokevirtual #65                 // Method _1:()D
         4: invokestatic  #61                 // Method scala/runtime/BoxesRunTime.boxToDouble:(D)Ljava/lang/Double;
         7: areturn
      LineNumberTable:
        line 24: 0
      LocalVariableTable:
        Start  Length  Slot  Name   Signature
            0       8     0  this   Lscala/Tuple2$mcDI$sp;

  public scala.Tuple2$mcDI$sp(double, int);
    descriptor: (DI)V
    flags: (0x0001) ACC_PUBLIC
    Code:
      stack=3, locals=4, args_size=3
         0: aload_0
         1: dload_1
         2: putfield      #15                 // Field _1$mcD$sp:D
         5: aload_0
         6: iload_3
         7: putfield      #23                 // Field _2$mcI$sp:I
        10: aload_0
        11: aconst_null
        12: aconst_null
        13: invokespecial #69                 // Method scala/Tuple2."<init>":(Ljava/lang/Object;Ljava/lang/Object;)V
        16: return
      LineNumberTable:
        line 24: 0
      LocalVariableTable:
        Start  Length  Slot  Name   Signature
            0      17     0  this   Lscala/Tuple2$mcDI$sp;
            0      17     1 _1$mcD$sp   D
            0      17     3 _2$mcI$sp   I
    MethodParameters:
      Name                           Flags
      _1$mcD$sp                      final
      _2$mcI$sp                      final
}
Signature: #3                           // Lscala/Tuple2<Ljava/lang/Object;Ljava/lang/Object;>;Lscala/Product2$mcDI$sp;
SourceFile: "Tuple2.scala"
  ScalaInlineInfo: length = 0x54 (unknown attribute)
   01 01 00 10 00 23 00 42 01 00 12 00 0D 01 00 12
   00 2F 01 00 09 00 0D 01 00 18 00 15 01 00 18 00
   2F 01 00 0B 00 15 01 00 27 00 0D 01 00 27 00 2F
   01 00 29 00 0D 01 00 2A 00 15 01 00 2A 00 2F 01
   00 2C 00 15 01 00 2D 00 2E 01 00 1B 00 1C 01 00
   1E 00 1C 01
  Scala: length = 0x0 (unknown attribute)

