Classfile /Users/mw/Projects/slang-braindump/.jar/jar8/assemble/slang-braindump/assemble/content/scala/Tuple10.class
  Last modified May 29, 2022; size 13952 bytes
  SHA-256 checksum 8877425ba8425cff999ad163fb58c701a1504341724d0d820621670240d26e91
  Compiled from "Tuple10.scala"
public final class scala.Tuple10<T1 extends java.lang.Object, T2 extends java.lang.Object, T3 extends java.lang.Object, T4 extends java.lang.Object, T5 extends java.lang.Object, T6 extends java.lang.Object, T7 extends java.lang.Object, T8 extends java.lang.Object, T9 extends java.lang.Object, T10 extends java.lang.Object> extends java.lang.Object implements scala.Product10<T1, T2, T3, T4, T5, T6, T7, T8, T9, T10>, java.io.Serializable
  minor version: 0
  major version: 52
  flags: (0x0031) ACC_PUBLIC, ACC_FINAL, ACC_SUPER
  this_class: #2                          // scala/Tuple10
  super_class: #5                         // java/lang/Object
  interfaces: 2, fields: 10, methods: 34, attributes: 6
Constant pool:
    #1 = Utf8               scala/Tuple10
    #2 = Class              #1            // scala/Tuple10
    #3 = Utf8               <T1:Ljava/lang/Object;T2:Ljava/lang/Object;T3:Ljava/lang/Object;T4:Ljava/lang/Object;T5:Ljava/lang/Object;T6:Ljava/lang/Object;T7:Ljava/lang/Object;T8:Ljava/lang/Object;T9:Ljava/lang/Object;T10:Ljava/lang/Object;>Ljava/lang/Object;Lscala/Product10<TT1;TT2;TT3;TT4;TT5;TT6;TT7;TT8;TT9;TT10;>;Ljava/io/Serializable;
    #4 = Utf8               java/lang/Object
    #5 = Class              #4            // java/lang/Object
    #6 = Utf8               scala/Product10
    #7 = Class              #6            // scala/Product10
    #8 = Utf8               java/io/Serializable
    #9 = Class              #8            // java/io/Serializable
   #10 = Utf8               Tuple10.scala
   #11 = Utf8               Lscala/reflect/ScalaSignature;
   #12 = Utf8               bytes
   #13 = Utf8               \u0006\u0005\rue\u0001B\u00181\u0005NB\u0001\"\u001d\u0001\u0003\u0016\u0004%\tA\u001d\u0005\tg\u0002\u0011\t\u0012)A\u0005y!AA\u000f\u0001BK\u0002\u0013\u0005Q\u000f\u0003\u0005w\u0001\tE\t\u0015!\u0003H\u0011!9\bA!f\u0001\n\u0003A\b\u0002C=\u0001\u0005#\u0005\u000b\u0011\u0002&\t\u0011i\u0004!Q3A\u0005\u0002mD\u0001\u0002 \u0001\u0003\u0012\u0003\u0006I!\u0014\u0005\t{\u0002\u0011)\u001a!C\u0001}\"Aq\u0010\u0001B\tB\u0003%\u0001\u000b\u0003\u0006\u0002\u0002\u0001\u0011)\u001a!C\u0001\u0003\u0007A\u0011\"!\u0002\u0001\u0005#\u0005\u000b\u0011B*\t\u0015\u0005\u001d\u0001A!f\u0001\n\u0003\tI\u0001C\u0005\u0002\f\u0001\u0011\t\u0012)A\u0005-\"Q\u0011Q\u0002\u0001\u0003\u0016\u0004%\t!a\u0004\t\u0013\u0005E\u0001A!E!\u0002\u0013I\u0006BCA\n\u0001\tU\r\u0011\"\u0001\u0002\u0016!I\u0011q\u0003\u0001\u0003\u0012\u0003\u0006I\u0001\u0018\u0005\u000b\u00033\u0001!Q3A\u0005\u0002\u0005m\u0001\"CA\u000f\u0001\tE\t\u0015!\u0003`\u0011\u001d\ty\u0002\u0001C\u0001\u0003CAq!!\u000f\u0001\t\u0003\nY\u0004C\u0005\u0002N\u0001\t\t\u0011\"\u0001\u0002P!I\u0011\u0011\u0013\u0001\u0012\u0002\u0013\u0005\u00111\u0013\u0005\n\u0003\u007f\u0003\u0011\u0013!C\u0001\u0003\u0003D\u0011\"a7\u0001#\u0003%\t!!8\t\u0013\u0005]\b!%A\u0005\u0002\u0005e\b\"\u0003B\n\u0001E\u0005I\u0011\u0001B\u000b\u0011%\u0011y\u0003AI\u0001\n\u0003\u0011\t\u0004C\u0005\u0003L\u0001\t\n\u0011\"\u0001\u0003N!I!q\r\u0001\u0012\u0002\u0013\u0005!\u0011\u000e\u0005\n\u0005\u0007\u0003\u0011\u0013!C\u0001\u0005\u000bC\u0011Ba(\u0001#\u0003%\tA!)\t\u0013\tm\u0006!!A\u0005B\tu\u0006\"\u0003Bg\u0001\u0005\u0005I\u0011\tBh\u0011%\u0011i\u000eAA\u0001\n\u0003\u0011y\u000eC\u0005\u0003l\u0002\t\t\u0011\"\u0011\u0003n\"I!q\u001f\u0001\u0002\u0002\u0013\u0005#\u0011 \u0005\n\u0005w\u0004\u0011\u0011!C!\u0005{<\u0011b!\u00011\u0003\u0003E\taa\u0001\u0007\u0011=\u0002\u0014\u0011!E\u0001\u0007\u000bAq!a\b*\t\u0003\u0019\t\u0002C\u0005\u0002:%\n\t\u0011\"\u0012\u0004\u0014!I1QC\u0015\u0002\u0002\u0013\u00055q\u0003\u0005\n\u00073J\u0013\u0011!CA\u00077B\u0011ba%*\u0003\u0003%Ia!&\u0003\u000fQ+\b\u000f\\32a)\t\u0011\'A\u0003tG\u0006d\u0017m\u0001\u0001\u0016\u0017Qr\u0004j\u0013(R)^SV\fY\n\u0006\u0001UJ$-\u001a\t\u0003m]j\u0011\u0001M\u0005\u0003qA\u0012a!\u00118z%\u00164\u0007\u0003\u0004\u001c;y\u001dSU\nU*W3r{\u0016BA\u001e1\u0005%\u0001&o\u001c3vGR\f\u0004\u0007\u0005\u0002>}1\u0001AAB \u0001\t\u000b\u0007\u0001I\u0001\u0002UcE\u0011\u0011\t\u0012\t\u0003m\tK!a\u0011\u0019\u0003\u000f9{G\u000f[5oOB\u0011a\'R\u0005\u0003\rB\u00121!\u00118z!\ti\u0004\n\u0002\u0004J\u0001\u0011\u0015\r\u0001\u0011\u0002\u0003)J\u0002\"!P&\u0005\r1\u0003AQ1\u0001A\u0005\t!6\u0007\u0005\u0002>\u001d\u00121q\n\u0001CC\u0002\u0001\u0013!\u0001\u0016\u001b\u0011\u0005u\nFA\u0002*\u0001\t\u000b\u0007\u0001I\u0001\u0002UkA\u0011Q\b\u0016\u0003\u0007+\u0002!)\u0019\u0001!\u0003\u0005Q3\u0004CA\u001fX\t\u0019A\u0006\u0001\"b\u0001\u0001\n\u0011Ak\u000e\t\u0003{i#aa\u0017\u0001\u0005\u0006\u0004\u0001%A\u0001+9!\tiT\f\u0002\u0004_\u0001\u0011\u0015\r\u0001\u0011\u0002\u0003)f\u0002\"!\u00101\u0005\r\u0005\u0004AQ1\u0001A\u0005\r!\u0016\u0007\r\t\u0003m\rL!\u0001\u001a\u0019\u0003\u000fA\u0013x\u000eZ;diB\u0011aM\u001c\b\u0003O2t!\u0001[6\u000e\u0003%T!A\u001b\u001a\u0002\rq\u0012xn\u001c;?\u0013\u0005\t\u0014BA71\u0003\u001d\u0001\u0018mY6bO\u0016L!a\u001c9\u0003\u0019M+\'/[1mSj\f\'\r\\3\u000b\u00055\u0004\u0014AA02+\u0005a\u0014aA02A\u0005\u0011qLM\u000b\u0002\u000f\u0006\u0019qL\r\u0011\u0002\u0005}\u001bT#\u0001&\u0002\u0007}\u001b\u0004%\u0001\u0002`iU\tQ*A\u0002`i\u0001\n!aX\u001b\u0016\u0003A\u000b1aX\u001b!\u0003\tyf\'F\u0001T\u0003\ryf\u0007I\u0001\u0003?^*\u0012AV\u0001\u0004?^\u0002\u0013AA09+\u0005I\u0016aA09A\u0005\u0011q,O\u000b\u00029\u0006\u0019q,\u000f\u0011\u0002\u0007}\u000b\u0004\'F\u0001`\u0003\u0011y\u0016\u0007\r\u0011\u0002\rqJg.\u001b;?)Y\t\u0019#!\n\u0002(\u0005%\u00121FA\u0017\u0003_\t\t$a\r\u00026\u0005]\u0002\u0003\u0004\u001c\u0001y\u001dSU\nU*W3r{\u0006\"B9\u0016\u0001\u0004a\u0004\"\u0002;\u0016\u0001\u00049\u0005\"B<\u0016\u0001\u0004Q\u0005\"\u0002>\u0016\u0001\u0004i\u0005\"B?\u0016\u0001\u0004\u0001\u0006BBA\u0001+\u0001\u00071\u000b\u0003\u0004\u0002\bU\u0001\rA\u0016\u0005\u0007\u0003\u001b)\u0002\u0019A-\t\r\u0005MQ\u00031\u0001]\u0011\u0019\tI\"\u0006a\u0001?\u0006AAo\\*ue&tw\r\u0006\u0002\u0002>A!\u0011qHA$\u001d\u0011\t\t%a\u0011\u0011\u0005!\u0004\u0014bAA#a\u00051\u0001K]3eK\u001aLA!!\u0013\u0002L\t11\u000b\u001e:j]\u001eT1!!\u00121\u0003\u0011\u0019w\u000e]=\u0016-\u0005E\u0013qKA.\u0003?\n\u0019\'a\u001a\u0002l\u0005=\u00141OA<\u0003w\"b#a\u0015\u0002~\u0005}\u0014\u0011QAB\u0003\u000b\u000b9)!#\u0002\f\u00065\u0015q\u0012\t\u0017m\u0001\t)&!\u0017\u0002^\u0005\u0005\u0014QMA5\u0003[\n\t(!\u001e\u0002zA\u0019Q(a\u0016\u0005\u000b}:\"\u0019\u0001!\u0011\u0007u\nY\u0006B\u0003J/\t\u0007\u0001\tE\u0002>\u0003?\"Q\u0001T\fC\u0002\u0001\u00032!PA2\t\u0015yuC1\u0001A!\ri\u0014q\r\u0003\u0006%^\u0011\r\u0001\u0011\t\u0004{\u0005-D!B+\u0018\u0005\u0004\u0001\u0005cA\u001f\u0002p\u0011)\u0001l\u0006b\u0001\u0001B\u0019Q(a\u001d\u0005\u000bm;\"\u0019\u0001!\u0011\u0007u\n9\bB\u0003_/\t\u0007\u0001\tE\u0002>\u0003w\"Q!Y\fC\u0002\u0001C\u0001\"]\f\u0011\u0002\u0003\u0007\u0011Q\u000b\u0005\ti^\u0001\n\u00111\u0001\u0002Z!Aqo\u0006I\u0001\u0002\u0004\ti\u0006\u0003\u0005{/A\u0005\t\u0019AA1\u0011!ix\u0003%AA\u0002\u0005\u0015\u0004\"CA\u0001/A\u0005\t\u0019AA5\u0011%\t9a\u0006I\u0001\u0002\u0004\ti\u0007C\u0005\u0002\u000e]\u0001\n\u00111\u0001\u0002r!I\u00111C\f\u0011\u0002\u0003\u0007\u0011Q\u000f\u0005\n\u000339\u0002\u0013!a\u0001\u0003s\nabY8qs\u0012\"WMZ1vYR$\u0013\'\u0006\f\u0002\u0016\u0006-\u0016QVAX\u0003c\u000b\u0019,!.\u00028\u0006e\u00161XA_+\t\t9JK\u0002=\u00033[#!a\'\u0011\t\u0005u\u0015qU\u0007\u0003\u0003?SA!!)\u0002$\u0006IQO\\2iK\u000e\\W\r\u001a\u0006\u0004\u0003K\u0003\u0014AC1o]>$\u0018\r^5p]&!\u0011\u0011VAP\u0005E)hn\u00195fG.,GMV1sS\u0006t7-\u001a\u0003\u0006\u007fa\u0011\r\u0001\u0011\u0003\u0006\u0013b\u0011\r\u0001\u0011\u0003\u0006\u0019b\u0011\r\u0001\u0011\u0003\u0006\u001fb\u0011\r\u0001\u0011\u0003\u0006%b\u0011\r\u0001\u0011\u0003\u0006+b\u0011\r\u0001\u0011\u0003\u00061b\u0011\r\u0001\u0011\u0003\u00067b\u0011\r\u0001\u0011\u0003\u0006=b\u0011\r\u0001\u0011\u0003\u0006Cb\u0011\r\u0001Q\u0001\u000fG>\u0004\u0018\u0010\n3fM\u0006,H\u000e\u001e\u00133+Y\t\u0019-a2\u0002J\u0006-\u0017QZAh\u0003#\f\u0019.!6\u0002X\u0006eWCAAcU\r9\u0015\u0011\u0014\u0003\u0006\u007fe\u0011\r\u0001\u0011\u0003\u0006\u0013f\u0011\r\u0001\u0011\u0003\u0006\u0019f\u0011\r\u0001\u0011\u0003\u0006\u001ff\u0011\r\u0001\u0011\u0003\u0006%f\u0011\r\u0001\u0011\u0003\u0006+f\u0011\r\u0001\u0011\u0003\u00061f\u0011\r\u0001\u0011\u0003\u00067f\u0011\r\u0001\u0011\u0003\u0006=f\u0011\r\u0001\u0011\u0003\u0006Cf\u0011\r\u0001Q\u0001\u000fG>\u0004\u0018\u0010\n3fM\u0006,H\u000e\u001e\u00134+Y\ty.a9\u0002f\u0006\u001d\u0018\u0011^Av\u0003[\fy/!=\u0002t\u0006UXCAAqU\rQ\u0015\u0011\u0014\u0003\u0006\u007fi\u0011\r\u0001\u0011\u0003\u0006\u0013j\u0011\r\u0001\u0011\u0003\u0006\u0019j\u0011\r\u0001\u0011\u0003\u0006\u001fj\u0011\r\u0001\u0011\u0003\u0006%j\u0011\r\u0001\u0011\u0003\u0006+j\u0011\r\u0001\u0011\u0003\u00061j\u0011\r\u0001\u0011\u0003\u00067j\u0011\r\u0001\u0011\u0003\u0006=j\u0011\r\u0001\u0011\u0003\u0006Cj\u0011\r\u0001Q\u0001\u000fG>\u0004\u0018\u0010\n3fM\u0006,H\u000e\u001e\u00135+Y\tY0a@\u0003\u0002\t\r!Q\u0001B\u0004\u0005\u0013\u0011YA!\u0004\u0003\u0010\tEQCAA\u007fU\ri\u0015\u0011\u0014\u0003\u0006\u007fm\u0011\r\u0001\u0011\u0003\u0006\u0013n\u0011\r\u0001\u0011\u0003\u0006\u0019n\u0011\r\u0001\u0011\u0003\u0006\u001fn\u0011\r\u0001\u0011\u0003\u0006%n\u0011\r\u0001\u0011\u0003\u0006+n\u0011\r\u0001\u0011\u0003\u00061n\u0011\r\u0001\u0011\u0003\u00067n\u0011\r\u0001\u0011\u0003\u0006=n\u0011\r\u0001\u0011\u0003\u0006Cn\u0011\r\u0001Q\u0001\u000fG>\u0004\u0018\u0010\n3fM\u0006,H\u000e\u001e\u00136+Y\u00119Ba\u0007\u0003\u001e\t}!\u0011\u0005B\u0012\u0005K\u00119C!\u000b\u0003,\t5RC\u0001B\rU\r\u0001\u0016\u0011\u0014\u0003\u0006\u007fq\u0011\r\u0001\u0011\u0003\u0006\u0013r\u0011\r\u0001\u0011\u0003\u0006\u0019r\u0011\r\u0001\u0011\u0003\u0006\u001fr\u0011\r\u0001\u0011\u0003\u0006%r\u0011\r\u0001\u0011\u0003\u0006+r\u0011\r\u0001\u0011\u0003\u00061r\u0011\r\u0001\u0011\u0003\u00067r\u0011\r\u0001\u0011\u0003\u0006=r\u0011\r\u0001\u0011\u0003\u0006Cr\u0011\r\u0001Q\u0001\u000fG>\u0004\u0018\u0010\n3fM\u0006,H\u000e\u001e\u00137+Y\u0011\u0019Da\u000e\u0003:\tm\"Q\bB \u0005\u0003\u0012\u0019E!\u0012\u0003H\t%SC\u0001B\u001bU\r\u0019\u0016\u0011\u0014\u0003\u0006\u007fu\u0011\r\u0001\u0011\u0003\u0006\u0013v\u0011\r\u0001\u0011\u0003\u0006\u0019v\u0011\r\u0001\u0011\u0003\u0006\u001fv\u0011\r\u0001\u0011\u0003\u0006%v\u0011\r\u0001\u0011\u0003\u0006+v\u0011\r\u0001\u0011\u0003\u00061v\u0011\r\u0001\u0011\u0003\u00067v\u0011\r\u0001\u0011\u0003\u0006=v\u0011\r\u0001\u0011\u0003\u0006Cv\u0011\r\u0001Q\u0001\u000fG>\u0004\u0018\u0010\n3fM\u0006,H\u000e\u001e\u00138+Y\u0011yEa\u0015\u0003V\t]#\u0011\fB.\u0005;\u0012yF!\u0019\u0003d\t\u0015TC\u0001B)U\r1\u0016\u0011\u0014\u0003\u0006\u007fy\u0011\r\u0001\u0011\u0003\u0006\u0013z\u0011\r\u0001\u0011\u0003\u0006\u0019z\u0011\r\u0001\u0011\u0003\u0006\u001fz\u0011\r\u0001\u0011\u0003\u0006%z\u0011\r\u0001\u0011\u0003\u0006+z\u0011\r\u0001\u0011\u0003\u00061z\u0011\r\u0001\u0011\u0003\u00067z\u0011\r\u0001\u0011\u0003\u0006=z\u0011\r\u0001\u0011\u0003\u0006Cz\u0011\r\u0001Q\u0001\u000fG>\u0004\u0018\u0010\n3fM\u0006,H\u000e\u001e\u00139+Y\u0011YGa\u001c\u0003r\tM$Q\u000fB<\u0005s\u0012YH! \u0003\u0000\t\u0005UC\u0001B7U\rI\u0016\u0011\u0014\u0003\u0006\u007f}\u0011\r\u0001\u0011\u0003\u0006\u0013~\u0011\r\u0001\u0011\u0003\u0006\u0019~\u0011\r\u0001\u0011\u0003\u0006\u001f~\u0011\r\u0001\u0011\u0003\u0006%~\u0011\r\u0001\u0011\u0003\u0006+~\u0011\r\u0001\u0011\u0003\u00061~\u0011\r\u0001\u0011\u0003\u00067~\u0011\r\u0001\u0011\u0003\u0006=~\u0011\r\u0001\u0011\u0003\u0006C~\u0011\r\u0001Q\u0001\u000fG>\u0004\u0018\u0010\n3fM\u0006,H\u000e\u001e\u0013:+Y\u00119Ia#\u0003\u000e\n=%\u0011\u0013BJ\u0005+\u00139J!\'\u0003\u001c\nuUC\u0001BEU\ra\u0016\u0011\u0014\u0003\u0006\u007f\u0001\u0012\r\u0001\u0011\u0003\u0006\u0013\u0002\u0012\r\u0001\u0011\u0003\u0006\u0019\u0002\u0012\r\u0001\u0011\u0003\u0006\u001f\u0002\u0012\r\u0001\u0011\u0003\u0006%\u0002\u0012\r\u0001\u0011\u0003\u0006+\u0002\u0012\r\u0001\u0011\u0003\u00061\u0002\u0012\r\u0001\u0011\u0003\u00067\u0002\u0012\r\u0001\u0011\u0003\u0006=\u0002\u0012\r\u0001\u0011\u0003\u0006C\u0002\u0012\r\u0001Q\u0001\u0010G>\u0004\u0018\u0010\n3fM\u0006,H\u000e\u001e\u00132aU1\"1\u0015BT\u0005S\u0013YK!,\u00030\nE&1\u0017B[\u0005o\u0013I,\u0006\u0002\u0003&*\u001aq,!\'\u0005\u000b}\n#\u0019\u0001!\u0005\u000b%\u000b#\u0019\u0001!\u0005\u000b1\u000b#\u0019\u0001!\u0005\u000b=\u000b#\u0019\u0001!\u0005\u000bI\u000b#\u0019\u0001!\u0005\u000bU\u000b#\u0019\u0001!\u0005\u000ba\u000b#\u0019\u0001!\u0005\u000bm\u000b#\u0019\u0001!\u0005\u000by\u000b#\u0019\u0001!\u0005\u000b\u0005\f#\u0019\u0001!\u0002\u001bA\u0014x\u000eZ;diB\u0013XMZ5y+\t\u0011y\f\u0005\u0003\u0003B\n-WB\u0001Bb\u0015\u0011\u0011)Ma2\u0002\t1\fgn\u001a\u0006\u0003\u0005\u0013\fAA[1wC&!\u0011\u0011\nBb\u0003=\u0001(o\u001c3vGRLE/\u001a:bi>\u0014XC\u0001Bi!\u0015\u0011\u0019N!7E\u001b\t\u0011)NC\u0002\u0003XB\n!bY8mY\u0016\u001cG/[8o\u0013\u0011\u0011YN!6\u0003\u0011%#XM]1u_J\f\u0001bY1o\u000bF,\u0018\r\u001c\u000b\u0005\u0005C\u00149\u000fE\u00027\u0005GL1A!:1\u0005\u001d\u0011un\u001c7fC:D\u0001B!;%\u0003\u0003\u0005\r\u0001R\u0001\u0004q\u0012\n\u0014A\u00059s_\u0012,8\r^#mK6,g\u000e\u001e(b[\u0016$BAa0\u0003p\"I!\u0011^\u0013\u0002\u0002\u0003\u0007!\u0011\u001f\t\u0004m\tM\u0018b\u0001B{a\t\u0019\u0011J\u001c;\u0002\u0011!\f7\u000f[\"pI\u0016$\"A!=\u0002\r\u0015\fX/\u00197t)\u0011\u0011\tOa@\t\u0011\t%x%!AA\u0002\u0011\u000bq\u0001V;qY\u0016\f\u0004\u0007\u0005\u00027SM!\u0011&NB\u0004!\u0011\u0019Iaa\u0004\u000e\u0005\r-!\u0002BB\u0007\u0005\u000f\f!![8\n\u0007=\u001cY\u0001\u0006\u0002\u0004\u0004Q\u0011!qX\u0001\u0006CB\u0004H._\u000b\u0017\u00073\u0019yba\t\u0004(\r-2qFB\u001a\u0007o\u0019Yda\u0010\u0004DQ121DB#\u0007\u000f\u001aIea\u0013\u0004N\r=3\u0011KB*\u0007+\u001a9\u0006\u0005\f7\u0001\ru1\u0011EB\u0013\u0007S\u0019ic!\r\u00046\re2QHB!!\ri4q\u0004\u0003\u0006\u007f1\u0012\r\u0001\u0011\t\u0004{\r\rB!B%-\u0005\u0004\u0001\u0005cA\u001f\u0004(\u0011)A\n\fb\u0001\u0001B\u0019Qha\u000b\u0005\u000b=c#\u0019\u0001!\u0011\u0007u\u001ay\u0003B\u0003SY\t\u0007\u0001\tE\u0002>\u0007g!Q!\u0016\u0017C\u0002\u0001\u00032!PB\u001c\t\u0015AFF1\u0001A!\ri41\b\u0003\u000672\u0012\r\u0001\u0011\t\u0004{\r}B!\u00020-\u0005\u0004\u0001\u0005cA\u001f\u0004D\u0011)\u0011\r\fb\u0001\u0001\"1\u0011\u000f\fa\u0001\u0007;Aa\u0001\u001e\u0017A\u0002\r\u0005\u0002BB<-\u0001\u0004\u0019)\u0003\u0003\u0004{Y\u0001\u00071\u0011\u0006\u0005\u0007{2\u0002\ra!\f\t\u000f\u0005\u0005A\u00061\u0001\u00042!9\u0011q\u0001\u0017A\u0002\rU\u0002bBA\u0007Y\u0001\u00071\u0011\b\u0005\b\u0003\'a\u0003\u0019AB\u001f\u0011\u001d\tI\u0002\fa\u0001\u0007\u0003\nq!\u001e8baBd\u00170\u0006\f\u0004^\r%4QNB9\u0007k\u001aIh! \u0004\u0002\u000e\u00155\u0011RBG)\u0011\u0019yfa$\u0011\u000bY\u001a\tg!\u001a\n\u0007\r\r\u0004G\u0001\u0004PaRLwN\u001c\t\u0017m\u0001\u00199ga\u001b\u0004p\rM4qOB>\u0007\u007f\u001a\u0019ia\"\u0004\fB\u0019Qh!\u001b\u0005\u000b}j#\u0019\u0001!\u0011\u0007u\u001ai\u0007B\u0003J[\t\u0007\u0001\tE\u0002>\u0007c\"Q\u0001T\u0017C\u0002\u0001\u00032!PB;\t\u0015yUF1\u0001A!\ri4\u0011\u0010\u0003\u0006%6\u0012\r\u0001\u0011\t\u0004{\ruD!B+.\u0005\u0004\u0001\u0005cA\u001f\u0004\u0002\u0012)\u0001,\fb\u0001\u0001B\u0019Qh!\"\u0005\u000bmk#\u0019\u0001!\u0011\u0007u\u001aI\tB\u0003_[\t\u0007\u0001\tE\u0002>\u0007\u001b#Q!Y\u0017C\u0002\u0001C\u0011b!%.\u0003\u0003\u0005\ra!\u001a\u0002\u0007a$\u0003\'\u0001\u0007xe&$XMU3qY\u0006\u001cW\r\u0006\u0002\u0004\u0018B!!\u0011YBM\u0013\u0011\u0019YJa1\u0003\r=\u0013\'.Z2u\u0001
   #14 = Utf8               scala/runtime/ScalaRunTime$$anon$1
   #15 = Class              #14           // scala/runtime/ScalaRunTime$$anon$1
   #16 = Utf8               _1
   #17 = Utf8               Ljava/lang/Object;
   #18 = Utf8               TT1;
   #19 = Utf8               _2
   #20 = Utf8               TT2;
   #21 = Utf8               _3
   #22 = Utf8               TT3;
   #23 = Utf8               _4
   #24 = Utf8               TT4;
   #25 = Utf8               _5
   #26 = Utf8               TT5;
   #27 = Utf8               _6
   #28 = Utf8               TT6;
   #29 = Utf8               _7
   #30 = Utf8               TT7;
   #31 = Utf8               _8
   #32 = Utf8               TT8;
   #33 = Utf8               _9
   #34 = Utf8               TT9;
   #35 = Utf8               _10
   #36 = Utf8               TT10;
   #37 = Utf8               unapply
   #38 = Utf8               (Lscala/Tuple10;)Lscala/Option;
   #39 = Utf8               <T1:Ljava/lang/Object;T2:Ljava/lang/Object;T3:Ljava/lang/Object;T4:Ljava/lang/Object;T5:Ljava/lang/Object;T6:Ljava/lang/Object;T7:Ljava/lang/Object;T8:Ljava/lang/Object;T9:Ljava/lang/Object;T10:Ljava/lang/Object;>(Lscala/Tuple10<TT1;TT2;TT3;TT4;TT5;TT6;TT7;TT8;TT9;TT10;>;)Lscala/Option<Lscala/Tuple10<TT1;TT2;TT3;TT4;TT5;TT6;TT7;TT8;TT9;TT10;>;>;
   #40 = Utf8               x$0
   #41 = Utf8               scala/Tuple10$
   #42 = Class              #41           // scala/Tuple10$
   #43 = Utf8               MODULE$
   #44 = Utf8               Lscala/Tuple10$;
   #45 = NameAndType        #43:#44       // MODULE$:Lscala/Tuple10$;
   #46 = Fieldref           #42.#45       // scala/Tuple10$.MODULE$:Lscala/Tuple10$;
   #47 = NameAndType        #37:#38       // unapply:(Lscala/Tuple10;)Lscala/Option;
   #48 = Methodref          #42.#47       // scala/Tuple10$.unapply:(Lscala/Tuple10;)Lscala/Option;
   #49 = Utf8               Lscala/Tuple10;
   #50 = Utf8               apply
   #51 = Utf8               (Ljava/lang/Object;Ljava/lang/Object;Ljava/lang/Object;Ljava/lang/Object;Ljava/lang/Object;Ljava/lang/Object;Ljava/lang/Object;Ljava/lang/Object;Ljava/lang/Object;Ljava/lang/Object;)Lscala/Tuple10;
   #52 = Utf8               <T1:Ljava/lang/Object;T2:Ljava/lang/Object;T3:Ljava/lang/Object;T4:Ljava/lang/Object;T5:Ljava/lang/Object;T6:Ljava/lang/Object;T7:Ljava/lang/Object;T8:Ljava/lang/Object;T9:Ljava/lang/Object;T10:Ljava/lang/Object;>(TT1;TT2;TT3;TT4;TT5;TT6;TT7;TT8;TT9;TT10;)Lscala/Tuple10<TT1;TT2;TT3;TT4;TT5;TT6;TT7;TT8;TT9;TT10;>;
   #53 = Utf8               <init>
   #54 = Utf8               (Ljava/lang/Object;Ljava/lang/Object;Ljava/lang/Object;Ljava/lang/Object;Ljava/lang/Object;Ljava/lang/Object;Ljava/lang/Object;Ljava/lang/Object;Ljava/lang/Object;Ljava/lang/Object;)V
   #55 = NameAndType        #53:#54       // "<init>":(Ljava/lang/Object;Ljava/lang/Object;Ljava/lang/Object;Ljava/lang/Object;Ljava/lang/Object;Ljava/lang/Object;Ljava/lang/Object;Ljava/lang/Object;Ljava/lang/Object;Ljava/lang/Object;)V
   #56 = Methodref          #2.#55        // scala/Tuple10."<init>":(Ljava/lang/Object;Ljava/lang/Object;Ljava/lang/Object;Ljava/lang/Object;Ljava/lang/Object;Ljava/lang/Object;Ljava/lang/Object;Ljava/lang/Object;Ljava/lang/Object;Ljava/lang/Object;)V
   #57 = Utf8               productArity
   #58 = Utf8               ()I
   #59 = Utf8               productArity$
   #60 = Utf8               (Lscala/Product10;)I
   #61 = NameAndType        #59:#60       // productArity$:(Lscala/Product10;)I
   #62 = InterfaceMethodref #7.#61        // scala/Product10.productArity$:(Lscala/Product10;)I
   #63 = Utf8               this
   #64 = Utf8               productElement
   #65 = Utf8               (I)Ljava/lang/Object;
   #66 = Utf8               java/lang/IndexOutOfBoundsException
   #67 = Class              #66           // java/lang/IndexOutOfBoundsException
   #68 = Utf8               n
   #69 = Utf8               productElement$
   #70 = Utf8               (Lscala/Product10;I)Ljava/lang/Object;
   #71 = NameAndType        #69:#70       // productElement$:(Lscala/Product10;I)Ljava/lang/Object;
   #72 = InterfaceMethodref #7.#71        // scala/Product10.productElement$:(Lscala/Product10;I)Ljava/lang/Object;
   #73 = Utf8               I
   #74 = Utf8               productElementNames
   #75 = Utf8               ()Lscala/collection/Iterator;
   #76 = Utf8               ()Lscala/collection/Iterator<Ljava/lang/String;>;
   #77 = Utf8               scala/Product
   #78 = Class              #77           // scala/Product
   #79 = Utf8               productElementNames$
   #80 = Utf8               (Lscala/Product;)Lscala/collection/Iterator;
   #81 = NameAndType        #79:#80       // productElementNames$:(Lscala/Product;)Lscala/collection/Iterator;
   #82 = InterfaceMethodref #78.#81       // scala/Product.productElementNames$:(Lscala/Product;)Lscala/collection/Iterator;
   #83 = Utf8               ()Ljava/lang/Object;
   #84 = Utf8               ()TT1;
   #85 = NameAndType        #16:#17       // _1:Ljava/lang/Object;
   #86 = Fieldref           #2.#85        // scala/Tuple10._1:Ljava/lang/Object;
   #87 = Utf8               ()TT2;
   #88 = NameAndType        #19:#17       // _2:Ljava/lang/Object;
   #89 = Fieldref           #2.#88        // scala/Tuple10._2:Ljava/lang/Object;
   #90 = Utf8               ()TT3;
   #91 = NameAndType        #21:#17       // _3:Ljava/lang/Object;
   #92 = Fieldref           #2.#91        // scala/Tuple10._3:Ljava/lang/Object;
   #93 = Utf8               ()TT4;
   #94 = NameAndType        #23:#17       // _4:Ljava/lang/Object;
   #95 = Fieldref           #2.#94        // scala/Tuple10._4:Ljava/lang/Object;
   #96 = Utf8               ()TT5;
   #97 = NameAndType        #25:#17       // _5:Ljava/lang/Object;
   #98 = Fieldref           #2.#97        // scala/Tuple10._5:Ljava/lang/Object;
   #99 = Utf8               ()TT6;
  #100 = NameAndType        #27:#17       // _6:Ljava/lang/Object;
  #101 = Fieldref           #2.#100       // scala/Tuple10._6:Ljava/lang/Object;
  #102 = Utf8               ()TT7;
  #103 = NameAndType        #29:#17       // _7:Ljava/lang/Object;
  #104 = Fieldref           #2.#103       // scala/Tuple10._7:Ljava/lang/Object;
  #105 = Utf8               ()TT8;
  #106 = NameAndType        #31:#17       // _8:Ljava/lang/Object;
  #107 = Fieldref           #2.#106       // scala/Tuple10._8:Ljava/lang/Object;
  #108 = Utf8               ()TT9;
  #109 = NameAndType        #33:#17       // _9:Ljava/lang/Object;
  #110 = Fieldref           #2.#109       // scala/Tuple10._9:Ljava/lang/Object;
  #111 = Utf8               ()TT10;
  #112 = NameAndType        #35:#17       // _10:Ljava/lang/Object;
  #113 = Fieldref           #2.#112       // scala/Tuple10._10:Ljava/lang/Object;
  #114 = Utf8               toString
  #115 = Utf8               ()Ljava/lang/String;
  #116 = Utf8               java/lang/StringBuilder
  #117 = Class              #116          // java/lang/StringBuilder
  #118 = Integer            11
  #119 = Utf8               (I)V
  #120 = NameAndType        #53:#119      // "<init>":(I)V
  #121 = Methodref          #117.#120     // java/lang/StringBuilder."<init>":(I)V
  #122 = Utf8               (
  #123 = String             #122          // (
  #124 = Utf8               append
  #125 = Utf8               (Ljava/lang/String;)Ljava/lang/StringBuilder;
  #126 = NameAndType        #124:#125     // append:(Ljava/lang/String;)Ljava/lang/StringBuilder;
  #127 = Methodref          #117.#126     // java/lang/StringBuilder.append:(Ljava/lang/String;)Ljava/lang/StringBuilder;
  #128 = NameAndType        #16:#83       // _1:()Ljava/lang/Object;
  #129 = Methodref          #2.#128       // scala/Tuple10._1:()Ljava/lang/Object;
  #130 = Utf8               (Ljava/lang/Object;)Ljava/lang/StringBuilder;
  #131 = NameAndType        #124:#130     // append:(Ljava/lang/Object;)Ljava/lang/StringBuilder;
  #132 = Methodref          #117.#131     // java/lang/StringBuilder.append:(Ljava/lang/Object;)Ljava/lang/StringBuilder;
  #133 = Utf8               ,
  #134 = String             #133          // ,
  #135 = NameAndType        #19:#83       // _2:()Ljava/lang/Object;
  #136 = Methodref          #2.#135       // scala/Tuple10._2:()Ljava/lang/Object;
  #137 = NameAndType        #21:#83       // _3:()Ljava/lang/Object;
  #138 = Methodref          #2.#137       // scala/Tuple10._3:()Ljava/lang/Object;
  #139 = NameAndType        #23:#83       // _4:()Ljava/lang/Object;
  #140 = Methodref          #2.#139       // scala/Tuple10._4:()Ljava/lang/Object;
  #141 = NameAndType        #25:#83       // _5:()Ljava/lang/Object;
  #142 = Methodref          #2.#141       // scala/Tuple10._5:()Ljava/lang/Object;
  #143 = NameAndType        #27:#83       // _6:()Ljava/lang/Object;
  #144 = Methodref          #2.#143       // scala/Tuple10._6:()Ljava/lang/Object;
  #145 = NameAndType        #29:#83       // _7:()Ljava/lang/Object;
  #146 = Methodref          #2.#145       // scala/Tuple10._7:()Ljava/lang/Object;
  #147 = NameAndType        #31:#83       // _8:()Ljava/lang/Object;
  #148 = Methodref          #2.#147       // scala/Tuple10._8:()Ljava/lang/Object;
  #149 = NameAndType        #33:#83       // _9:()Ljava/lang/Object;
  #150 = Methodref          #2.#149       // scala/Tuple10._9:()Ljava/lang/Object;
  #151 = NameAndType        #35:#83       // _10:()Ljava/lang/Object;
  #152 = Methodref          #2.#151       // scala/Tuple10._10:()Ljava/lang/Object;
  #153 = Utf8               )
  #154 = String             #153          // )
  #155 = NameAndType        #114:#115     // toString:()Ljava/lang/String;
  #156 = Methodref          #117.#155     // java/lang/StringBuilder.toString:()Ljava/lang/String;
  #157 = Utf8               copy
  #158 = Utf8               copy$default$1
  #159 = Utf8               <T1:Ljava/lang/Object;T2:Ljava/lang/Object;T3:Ljava/lang/Object;T4:Ljava/lang/Object;T5:Ljava/lang/Object;T6:Ljava/lang/Object;T7:Ljava/lang/Object;T8:Ljava/lang/Object;T9:Ljava/lang/Object;T10:Ljava/lang/Object;>()TT1;
  #160 = Utf8               copy$default$10
  #161 = Utf8               <T1:Ljava/lang/Object;T2:Ljava/lang/Object;T3:Ljava/lang/Object;T4:Ljava/lang/Object;T5:Ljava/lang/Object;T6:Ljava/lang/Object;T7:Ljava/lang/Object;T8:Ljava/lang/Object;T9:Ljava/lang/Object;T10:Ljava/lang/Object;>()TT10;
  #162 = Utf8               copy$default$2
  #163 = Utf8               <T1:Ljava/lang/Object;T2:Ljava/lang/Object;T3:Ljava/lang/Object;T4:Ljava/lang/Object;T5:Ljava/lang/Object;T6:Ljava/lang/Object;T7:Ljava/lang/Object;T8:Ljava/lang/Object;T9:Ljava/lang/Object;T10:Ljava/lang/Object;>()TT2;
  #164 = Utf8               copy$default$3
  #165 = Utf8               <T1:Ljava/lang/Object;T2:Ljava/lang/Object;T3:Ljava/lang/Object;T4:Ljava/lang/Object;T5:Ljava/lang/Object;T6:Ljava/lang/Object;T7:Ljava/lang/Object;T8:Ljava/lang/Object;T9:Ljava/lang/Object;T10:Ljava/lang/Object;>()TT3;
  #166 = Utf8               copy$default$4
  #167 = Utf8               <T1:Ljava/lang/Object;T2:Ljava/lang/Object;T3:Ljava/lang/Object;T4:Ljava/lang/Object;T5:Ljava/lang/Object;T6:Ljava/lang/Object;T7:Ljava/lang/Object;T8:Ljava/lang/Object;T9:Ljava/lang/Object;T10:Ljava/lang/Object;>()TT4;
  #168 = Utf8               copy$default$5
  #169 = Utf8               <T1:Ljava/lang/Object;T2:Ljava/lang/Object;T3:Ljava/lang/Object;T4:Ljava/lang/Object;T5:Ljava/lang/Object;T6:Ljava/lang/Object;T7:Ljava/lang/Object;T8:Ljava/lang/Object;T9:Ljava/lang/Object;T10:Ljava/lang/Object;>()TT5;
  #170 = Utf8               copy$default$6
  #171 = Utf8               <T1:Ljava/lang/Object;T2:Ljava/lang/Object;T3:Ljava/lang/Object;T4:Ljava/lang/Object;T5:Ljava/lang/Object;T6:Ljava/lang/Object;T7:Ljava/lang/Object;T8:Ljava/lang/Object;T9:Ljava/lang/Object;T10:Ljava/lang/Object;>()TT6;
  #172 = Utf8               copy$default$7
  #173 = Utf8               <T1:Ljava/lang/Object;T2:Ljava/lang/Object;T3:Ljava/lang/Object;T4:Ljava/lang/Object;T5:Ljava/lang/Object;T6:Ljava/lang/Object;T7:Ljava/lang/Object;T8:Ljava/lang/Object;T9:Ljava/lang/Object;T10:Ljava/lang/Object;>()TT7;
  #174 = Utf8               copy$default$8
  #175 = Utf8               <T1:Ljava/lang/Object;T2:Ljava/lang/Object;T3:Ljava/lang/Object;T4:Ljava/lang/Object;T5:Ljava/lang/Object;T6:Ljava/lang/Object;T7:Ljava/lang/Object;T8:Ljava/lang/Object;T9:Ljava/lang/Object;T10:Ljava/lang/Object;>()TT8;
  #176 = Utf8               copy$default$9
  #177 = Utf8               <T1:Ljava/lang/Object;T2:Ljava/lang/Object;T3:Ljava/lang/Object;T4:Ljava/lang/Object;T5:Ljava/lang/Object;T6:Ljava/lang/Object;T7:Ljava/lang/Object;T8:Ljava/lang/Object;T9:Ljava/lang/Object;T10:Ljava/lang/Object;>()TT9;
  #178 = Utf8               productPrefix
  #179 = Utf8               Tuple10
  #180 = String             #179          // Tuple10
  #181 = Utf8               productIterator
  #182 = Utf8               ()Lscala/collection/Iterator<Ljava/lang/Object;>;
  #183 = Utf8               (Lscala/Product;)V
  #184 = NameAndType        #53:#183      // "<init>":(Lscala/Product;)V
  #185 = Methodref          #15.#184      // scala/runtime/ScalaRunTime$$anon$1."<init>":(Lscala/Product;)V
  #186 = Utf8               canEqual
  #187 = Utf8               (Ljava/lang/Object;)Z
  #188 = Utf8               x$1
  #189 = Utf8               productElementName
  #190 = Utf8               (I)Ljava/lang/String;
  #191 = String             #16           // _1
  #192 = String             #19           // _2
  #193 = String             #21           // _3
  #194 = String             #23           // _4
  #195 = String             #25           // _5
  #196 = String             #27           // _6
  #197 = String             #29           // _7
  #198 = String             #31           // _8
  #199 = String             #33           // _9
  #200 = String             #35           // _10
  #201 = Utf8               scala/runtime/Statics
  #202 = Class              #201          // scala/runtime/Statics
  #203 = Utf8               ioobe
  #204 = NameAndType        #203:#65      // ioobe:(I)Ljava/lang/Object;
  #205 = Methodref          #202.#204     // scala/runtime/Statics.ioobe:(I)Ljava/lang/Object;
  #206 = Utf8               java/lang/String
  #207 = Class              #206          // java/lang/String
  #208 = Utf8               hashCode
  #209 = Utf8               scala/util/hashing/MurmurHash3$
  #210 = Class              #209          // scala/util/hashing/MurmurHash3$
  #211 = Utf8               Lscala/util/hashing/MurmurHash3$;
  #212 = NameAndType        #43:#211      // MODULE$:Lscala/util/hashing/MurmurHash3$;
  #213 = Fieldref           #210.#212     // scala/util/hashing/MurmurHash3$.MODULE$:Lscala/util/hashing/MurmurHash3$;
  #214 = Utf8               productHash
  #215 = Utf8               (Lscala/Product;)I
  #216 = NameAndType        #214:#215     // productHash:(Lscala/Product;)I
  #217 = Methodref          #210.#216     // scala/util/hashing/MurmurHash3$.productHash:(Lscala/Product;)I
  #218 = Utf8               equals
  #219 = Utf8               scala/runtime/BoxesRunTime
  #220 = Class              #219          // scala/runtime/BoxesRunTime
  #221 = Utf8               (Ljava/lang/Object;Ljava/lang/Object;)Z
  #222 = NameAndType        #218:#221     // equals:(Ljava/lang/Object;Ljava/lang/Object;)Z
  #223 = Methodref          #220.#222     // scala/runtime/BoxesRunTime.equals:(Ljava/lang/Object;Ljava/lang/Object;)Z
  #224 = Utf8               (TT1;TT2;TT3;TT4;TT5;TT6;TT7;TT8;TT9;TT10;)V
  #225 = Utf8               ()V
  #226 = NameAndType        #53:#225      // "<init>":()V
  #227 = Methodref          #5.#226       // java/lang/Object."<init>":()V
  #228 = Utf8               Signature
  #229 = Utf8               Code
  #230 = Utf8               LocalVariableTable
  #231 = Utf8               MethodParameters
  #232 = Utf8               LineNumberTable
  #233 = Utf8               Exceptions
  #234 = Utf8               StackMapTable
  #235 = Utf8               InnerClasses
  #236 = Utf8               SourceFile
  #237 = Utf8               RuntimeVisibleAnnotations
  #238 = Utf8               ScalaInlineInfo
  #239 = Utf8               ScalaSig
{
  private final T1 _1;
    descriptor: Ljava/lang/Object;
    flags: (0x0012) ACC_PRIVATE, ACC_FINAL
    Signature: #18                          // TT1;

  private final T2 _2;
    descriptor: Ljava/lang/Object;
    flags: (0x0012) ACC_PRIVATE, ACC_FINAL
    Signature: #20                          // TT2;

  private final T3 _3;
    descriptor: Ljava/lang/Object;
    flags: (0x0012) ACC_PRIVATE, ACC_FINAL
    Signature: #22                          // TT3;

  private final T4 _4;
    descriptor: Ljava/lang/Object;
    flags: (0x0012) ACC_PRIVATE, ACC_FINAL
    Signature: #24                          // TT4;

  private final T5 _5;
    descriptor: Ljava/lang/Object;
    flags: (0x0012) ACC_PRIVATE, ACC_FINAL
    Signature: #26                          // TT5;

  private final T6 _6;
    descriptor: Ljava/lang/Object;
    flags: (0x0012) ACC_PRIVATE, ACC_FINAL
    Signature: #28                          // TT6;

  private final T7 _7;
    descriptor: Ljava/lang/Object;
    flags: (0x0012) ACC_PRIVATE, ACC_FINAL
    Signature: #30                          // TT7;

  private final T8 _8;
    descriptor: Ljava/lang/Object;
    flags: (0x0012) ACC_PRIVATE, ACC_FINAL
    Signature: #32                          // TT8;

  private final T9 _9;
    descriptor: Ljava/lang/Object;
    flags: (0x0012) ACC_PRIVATE, ACC_FINAL
    Signature: #34                          // TT9;

  private final T10 _10;
    descriptor: Ljava/lang/Object;
    flags: (0x0012) ACC_PRIVATE, ACC_FINAL
    Signature: #36                          // TT10;

  public static <T1 extends java.lang.Object, T2 extends java.lang.Object, T3 extends java.lang.Object, T4 extends java.lang.Object, T5 extends java.lang.Object, T6 extends java.lang.Object, T7 extends java.lang.Object, T8 extends java.lang.Object, T9 extends java.lang.Object, T10 extends java.lang.Object> scala.Option<scala.Tuple10<T1, T2, T3, T4, T5, T6, T7, T8, T9, T10>> unapply(scala.Tuple10<T1, T2, T3, T4, T5, T6, T7, T8, T9, T10>);
    descriptor: (Lscala/Tuple10;)Lscala/Option;
    flags: (0x0009) ACC_PUBLIC, ACC_STATIC
    Code:
      stack=2, locals=1, args_size=1
         0: getstatic     #46                 // Field scala/Tuple10$.MODULE$:Lscala/Tuple10$;
         3: aload_0
         4: invokevirtual #48                 // Method scala/Tuple10$.unapply:(Lscala/Tuple10;)Lscala/Option;
         7: areturn
      LocalVariableTable:
        Start  Length  Slot  Name   Signature
            0       8     0   x$0   Lscala/Tuple10;
    Signature: #39                          // <T1:Ljava/lang/Object;T2:Ljava/lang/Object;T3:Ljava/lang/Object;T4:Ljava/lang/Object;T5:Ljava/lang/Object;T6:Ljava/lang/Object;T7:Ljava/lang/Object;T8:Ljava/lang/Object;T9:Ljava/lang/Object;T10:Ljava/lang/Object;>(Lscala/Tuple10<TT1;TT2;TT3;TT4;TT5;TT6;TT7;TT8;TT9;TT10;>;)Lscala/Option<Lscala/Tuple10<TT1;TT2;TT3;TT4;TT5;TT6;TT7;TT8;TT9;TT10;>;>;
    MethodParameters:
      Name                           Flags
      x$0                            final

  public static <T1 extends java.lang.Object, T2 extends java.lang.Object, T3 extends java.lang.Object, T4 extends java.lang.Object, T5 extends java.lang.Object, T6 extends java.lang.Object, T7 extends java.lang.Object, T8 extends java.lang.Object, T9 extends java.lang.Object, T10 extends java.lang.Object> scala.Tuple10<T1, T2, T3, T4, T5, T6, T7, T8, T9, T10> apply(T1, T2, T3, T4, T5, T6, T7, T8, T9, T10);
    descriptor: (Ljava/lang/Object;Ljava/lang/Object;Ljava/lang/Object;Ljava/lang/Object;Ljava/lang/Object;Ljava/lang/Object;Ljava/lang/Object;Ljava/lang/Object;Ljava/lang/Object;Ljava/lang/Object;)Lscala/Tuple10;
    flags: (0x0009) ACC_PUBLIC, ACC_STATIC
    Code:
      stack=12, locals=10, args_size=10
         0: getstatic     #46                 // Field scala/Tuple10$.MODULE$:Lscala/Tuple10$;
         3: pop
         4: new           #2                  // class scala/Tuple10
         7: dup
         8: aload_0
         9: aload_1
        10: aload_2
        11: aload_3
        12: aload         4
        14: aload         5
        16: aload         6
        18: aload         7
        20: aload         8
        22: aload         9
        24: invokespecial #56                 // Method "<init>":(Ljava/lang/Object;Ljava/lang/Object;Ljava/lang/Object;Ljava/lang/Object;Ljava/lang/Object;Ljava/lang/Object;Ljava/lang/Object;Ljava/lang/Object;Ljava/lang/Object;Ljava/lang/Object;)V
        27: areturn
      LineNumberTable:
        line 32: 4
      LocalVariableTable:
        Start  Length  Slot  Name   Signature
            0      28     0    _1   Ljava/lang/Object;
            0      28     1    _2   Ljava/lang/Object;
            0      28     2    _3   Ljava/lang/Object;
            0      28     3    _4   Ljava/lang/Object;
            0      28     4    _5   Ljava/lang/Object;
            0      28     5    _6   Ljava/lang/Object;
            0      28     6    _7   Ljava/lang/Object;
            0      28     7    _8   Ljava/lang/Object;
            0      28     8    _9   Ljava/lang/Object;
            0      28     9   _10   Ljava/lang/Object;
    Signature: #52                          // <T1:Ljava/lang/Object;T2:Ljava/lang/Object;T3:Ljava/lang/Object;T4:Ljava/lang/Object;T5:Ljava/lang/Object;T6:Ljava/lang/Object;T7:Ljava/lang/Object;T8:Ljava/lang/Object;T9:Ljava/lang/Object;T10:Ljava/lang/Object;>(TT1;TT2;TT3;TT4;TT5;TT6;TT7;TT8;TT9;TT10;)Lscala/Tuple10<TT1;TT2;TT3;TT4;TT5;TT6;TT7;TT8;TT9;TT10;>;
    MethodParameters:
      Name                           Flags
      _1                             final
      _2                             final
      _3                             final
      _4                             final
      _5                             final
      _6                             final
      _7                             final
      _8                             final
      _9                             final
      _10                            final

  public int productArity();
    descriptor: ()I
    flags: (0x0001) ACC_PUBLIC
    Code:
      stack=1, locals=1, args_size=1
         0: aload_0
         1: invokestatic  #62                 // InterfaceMethod scala/Product10.productArity$:(Lscala/Product10;)I
         4: ireturn
      LineNumberTable:
        line 32: 0
      LocalVariableTable:
        Start  Length  Slot  Name   Signature
            0       5     0  this   Lscala/Tuple10;

  public java.lang.Object productElement(int) throws java.lang.IndexOutOfBoundsException;
    descriptor: (I)Ljava/lang/Object;
    flags: (0x0001) ACC_PUBLIC
    Code:
      stack=2, locals=2, args_size=2
         0: aload_0
         1: iload_1
         2: invokestatic  #72                 // InterfaceMethod scala/Product10.productElement$:(Lscala/Product10;I)Ljava/lang/Object;
         5: areturn
      LineNumberTable:
        line 32: 0
      LocalVariableTable:
        Start  Length  Slot  Name   Signature
            0       6     0  this   Lscala/Tuple10;
            0       6     1     n   I
    Exceptions:
      throws java.lang.IndexOutOfBoundsException
    MethodParameters:
      Name                           Flags
      n                              final

  public scala.collection.Iterator<java.lang.String> productElementNames();
    descriptor: ()Lscala/collection/Iterator;
    flags: (0x0001) ACC_PUBLIC
    Code:
      stack=1, locals=1, args_size=1
         0: aload_0
         1: invokestatic  #82                 // InterfaceMethod scala/Product.productElementNames$:(Lscala/Product;)Lscala/collection/Iterator;
         4: areturn
      LineNumberTable:
        line 32: 0
      LocalVariableTable:
        Start  Length  Slot  Name   Signature
            0       5     0  this   Lscala/Tuple10;
    Signature: #76                          // ()Lscala/collection/Iterator<Ljava/lang/String;>;

  public T1 _1();
    descriptor: ()Ljava/lang/Object;
    flags: (0x0001) ACC_PUBLIC
    Code:
      stack=1, locals=1, args_size=1
         0: aload_0
         1: getfield      #86                 // Field _1:Ljava/lang/Object;
         4: areturn
      LineNumberTable:
        line 32: 0
      LocalVariableTable:
        Start  Length  Slot  Name   Signature
            0       5     0  this   Lscala/Tuple10;
    Signature: #84                          // ()TT1;

  public T2 _2();
    descriptor: ()Ljava/lang/Object;
    flags: (0x0001) ACC_PUBLIC
    Code:
      stack=1, locals=1, args_size=1
         0: aload_0
         1: getfield      #89                 // Field _2:Ljava/lang/Object;
         4: areturn
      LineNumberTable:
        line 32: 0
      LocalVariableTable:
        Start  Length  Slot  Name   Signature
            0       5     0  this   Lscala/Tuple10;
    Signature: #87                          // ()TT2;

  public T3 _3();
    descriptor: ()Ljava/lang/Object;
    flags: (0x0001) ACC_PUBLIC
    Code:
      stack=1, locals=1, args_size=1
         0: aload_0
         1: getfield      #92                 // Field _3:Ljava/lang/Object;
         4: areturn
      LineNumberTable:
        line 32: 0
      LocalVariableTable:
        Start  Length  Slot  Name   Signature
            0       5     0  this   Lscala/Tuple10;
    Signature: #90                          // ()TT3;

  public T4 _4();
    descriptor: ()Ljava/lang/Object;
    flags: (0x0001) ACC_PUBLIC
    Code:
      stack=1, locals=1, args_size=1
         0: aload_0
         1: getfield      #95                 // Field _4:Ljava/lang/Object;
         4: areturn
      LineNumberTable:
        line 32: 0
      LocalVariableTable:
        Start  Length  Slot  Name   Signature
            0       5     0  this   Lscala/Tuple10;
    Signature: #93                          // ()TT4;

  public T5 _5();
    descriptor: ()Ljava/lang/Object;
    flags: (0x0001) ACC_PUBLIC
    Code:
      stack=1, locals=1, args_size=1
         0: aload_0
         1: getfield      #98                 // Field _5:Ljava/lang/Object;
         4: areturn
      LineNumberTable:
        line 32: 0
      LocalVariableTable:
        Start  Length  Slot  Name   Signature
            0       5     0  this   Lscala/Tuple10;
    Signature: #96                          // ()TT5;

  public T6 _6();
    descriptor: ()Ljava/lang/Object;
    flags: (0x0001) ACC_PUBLIC
    Code:
      stack=1, locals=1, args_size=1
         0: aload_0
         1: getfield      #101                // Field _6:Ljava/lang/Object;
         4: areturn
      LineNumberTable:
        line 32: 0
      LocalVariableTable:
        Start  Length  Slot  Name   Signature
            0       5     0  this   Lscala/Tuple10;
    Signature: #99                          // ()TT6;

  public T7 _7();
    descriptor: ()Ljava/lang/Object;
    flags: (0x0001) ACC_PUBLIC
    Code:
      stack=1, locals=1, args_size=1
         0: aload_0
         1: getfield      #104                // Field _7:Ljava/lang/Object;
         4: areturn
      LineNumberTable:
        line 32: 0
      LocalVariableTable:
        Start  Length  Slot  Name   Signature
            0       5     0  this   Lscala/Tuple10;
    Signature: #102                         // ()TT7;

  public T8 _8();
    descriptor: ()Ljava/lang/Object;
    flags: (0x0001) ACC_PUBLIC
    Code:
      stack=1, locals=1, args_size=1
         0: aload_0
         1: getfield      #107                // Field _8:Ljava/lang/Object;
         4: areturn
      LineNumberTable:
        line 32: 0
      LocalVariableTable:
        Start  Length  Slot  Name   Signature
            0       5     0  this   Lscala/Tuple10;
    Signature: #105                         // ()TT8;

  public T9 _9();
    descriptor: ()Ljava/lang/Object;
    flags: (0x0001) ACC_PUBLIC
    Code:
      stack=1, locals=1, args_size=1
         0: aload_0
         1: getfield      #110                // Field _9:Ljava/lang/Object;
         4: areturn
      LineNumberTable:
        line 32: 0
      LocalVariableTable:
        Start  Length  Slot  Name   Signature
            0       5     0  this   Lscala/Tuple10;
    Signature: #108                         // ()TT9;

  public T10 _10();
    descriptor: ()Ljava/lang/Object;
    flags: (0x0001) ACC_PUBLIC
    Code:
      stack=1, locals=1, args_size=1
         0: aload_0
         1: getfield      #113                // Field _10:Ljava/lang/Object;
         4: areturn
      LineNumberTable:
        line 32: 0
      LocalVariableTable:
        Start  Length  Slot  Name   Signature
            0       5     0  this   Lscala/Tuple10;
    Signature: #111                         // ()TT10;

  public java.lang.String toString();
    descriptor: ()Ljava/lang/String;
    flags: (0x0001) ACC_PUBLIC
    Code:
      stack=3, locals=1, args_size=1
         0: new           #117                // class java/lang/StringBuilder
         3: dup
         4: ldc           #118                // int 11
         6: invokespecial #121                // Method java/lang/StringBuilder."<init>":(I)V
         9: ldc           #123                // String (
        11: invokevirtual #127                // Method java/lang/StringBuilder.append:(Ljava/lang/String;)Ljava/lang/StringBuilder;
        14: aload_0
        15: invokevirtual #129                // Method _1:()Ljava/lang/Object;
        18: invokevirtual #132                // Method java/lang/StringBuilder.append:(Ljava/lang/Object;)Ljava/lang/StringBuilder;
        21: ldc           #134                // String ,
        23: invokevirtual #127                // Method java/lang/StringBuilder.append:(Ljava/lang/String;)Ljava/lang/StringBuilder;
        26: aload_0
        27: invokevirtual #136                // Method _2:()Ljava/lang/Object;
        30: invokevirtual #132                // Method java/lang/StringBuilder.append:(Ljava/lang/Object;)Ljava/lang/StringBuilder;
        33: ldc           #134                // String ,
        35: invokevirtual #127                // Method java/lang/StringBuilder.append:(Ljava/lang/String;)Ljava/lang/StringBuilder;
        38: aload_0
        39: invokevirtual #138                // Method _3:()Ljava/lang/Object;
        42: invokevirtual #132                // Method java/lang/StringBuilder.append:(Ljava/lang/Object;)Ljava/lang/StringBuilder;
        45: ldc           #134                // String ,
        47: invokevirtual #127                // Method java/lang/StringBuilder.append:(Ljava/lang/String;)Ljava/lang/StringBuilder;
        50: aload_0
        51: invokevirtual #140                // Method _4:()Ljava/lang/Object;
        54: invokevirtual #132                // Method java/lang/StringBuilder.append:(Ljava/lang/Object;)Ljava/lang/StringBuilder;
        57: ldc           #134                // String ,
        59: invokevirtual #127                // Method java/lang/StringBuilder.append:(Ljava/lang/String;)Ljava/lang/StringBuilder;
        62: aload_0
        63: invokevirtual #142                // Method _5:()Ljava/lang/Object;
        66: invokevirtual #132                // Method java/lang/StringBuilder.append:(Ljava/lang/Object;)Ljava/lang/StringBuilder;
        69: ldc           #134                // String ,
        71: invokevirtual #127                // Method java/lang/StringBuilder.append:(Ljava/lang/String;)Ljava/lang/StringBuilder;
        74: aload_0
        75: invokevirtual #144                // Method _6:()Ljava/lang/Object;
        78: invokevirtual #132                // Method java/lang/StringBuilder.append:(Ljava/lang/Object;)Ljava/lang/StringBuilder;
        81: ldc           #134                // String ,
        83: invokevirtual #127                // Method java/lang/StringBuilder.append:(Ljava/lang/String;)Ljava/lang/StringBuilder;
        86: aload_0
        87: invokevirtual #146                // Method _7:()Ljava/lang/Object;
        90: invokevirtual #132                // Method java/lang/StringBuilder.append:(Ljava/lang/Object;)Ljava/lang/StringBuilder;
        93: ldc           #134                // String ,
        95: invokevirtual #127                // Method java/lang/StringBuilder.append:(Ljava/lang/String;)Ljava/lang/StringBuilder;
        98: aload_0
        99: invokevirtual #148                // Method _8:()Ljava/lang/Object;
       102: invokevirtual #132                // Method java/lang/StringBuilder.append:(Ljava/lang/Object;)Ljava/lang/StringBuilder;
       105: ldc           #134                // String ,
       107: invokevirtual #127                // Method java/lang/StringBuilder.append:(Ljava/lang/String;)Ljava/lang/StringBuilder;
       110: aload_0
       111: invokevirtual #150                // Method _9:()Ljava/lang/Object;
       114: invokevirtual #132                // Method java/lang/StringBuilder.append:(Ljava/lang/Object;)Ljava/lang/StringBuilder;
       117: ldc           #134                // String ,
       119: invokevirtual #127                // Method java/lang/StringBuilder.append:(Ljava/lang/String;)Ljava/lang/StringBuilder;
       122: aload_0
       123: invokevirtual #152                // Method _10:()Ljava/lang/Object;
       126: invokevirtual #132                // Method java/lang/StringBuilder.append:(Ljava/lang/Object;)Ljava/lang/StringBuilder;
       129: ldc           #154                // String )
       131: invokevirtual #127                // Method java/lang/StringBuilder.append:(Ljava/lang/String;)Ljava/lang/StringBuilder;
       134: invokevirtual #156                // Method java/lang/StringBuilder.toString:()Ljava/lang/String;
       137: areturn
      LineNumberTable:
        line 35: 0
      LocalVariableTable:
        Start  Length  Slot  Name   Signature
            0     138     0  this   Lscala/Tuple10;

  public <T1 extends java.lang.Object, T2 extends java.lang.Object, T3 extends java.lang.Object, T4 extends java.lang.Object, T5 extends java.lang.Object, T6 extends java.lang.Object, T7 extends java.lang.Object, T8 extends java.lang.Object, T9 extends java.lang.Object, T10 extends java.lang.Object> scala.Tuple10<T1, T2, T3, T4, T5, T6, T7, T8, T9, T10> copy(T1, T2, T3, T4, T5, T6, T7, T8, T9, T10);
    descriptor: (Ljava/lang/Object;Ljava/lang/Object;Ljava/lang/Object;Ljava/lang/Object;Ljava/lang/Object;Ljava/lang/Object;Ljava/lang/Object;Ljava/lang/Object;Ljava/lang/Object;Ljava/lang/Object;)Lscala/Tuple10;
    flags: (0x0001) ACC_PUBLIC
    Code:
      stack=12, locals=11, args_size=11
         0: new           #2                  // class scala/Tuple10
         3: dup
         4: aload_1
         5: aload_2
         6: aload_3
         7: aload         4
         9: aload         5
        11: aload         6
        13: aload         7
        15: aload         8
        17: aload         9
        19: aload         10
        21: invokespecial #56                 // Method "<init>":(Ljava/lang/Object;Ljava/lang/Object;Ljava/lang/Object;Ljava/lang/Object;Ljava/lang/Object;Ljava/lang/Object;Ljava/lang/Object;Ljava/lang/Object;Ljava/lang/Object;Ljava/lang/Object;)V
        24: areturn
      LineNumberTable:
        line 32: 0
      LocalVariableTable:
        Start  Length  Slot  Name   Signature
            0      25     0  this   Lscala/Tuple10;
            0      25     1    _1   Ljava/lang/Object;
            0      25     2    _2   Ljava/lang/Object;
            0      25     3    _3   Ljava/lang/Object;
            0      25     4    _4   Ljava/lang/Object;
            0      25     5    _5   Ljava/lang/Object;
            0      25     6    _6   Ljava/lang/Object;
            0      25     7    _7   Ljava/lang/Object;
            0      25     8    _8   Ljava/lang/Object;
            0      25     9    _9   Ljava/lang/Object;
            0      25    10   _10   Ljava/lang/Object;
    Signature: #52                          // <T1:Ljava/lang/Object;T2:Ljava/lang/Object;T3:Ljava/lang/Object;T4:Ljava/lang/Object;T5:Ljava/lang/Object;T6:Ljava/lang/Object;T7:Ljava/lang/Object;T8:Ljava/lang/Object;T9:Ljava/lang/Object;T10:Ljava/lang/Object;>(TT1;TT2;TT3;TT4;TT5;TT6;TT7;TT8;TT9;TT10;)Lscala/Tuple10<TT1;TT2;TT3;TT4;TT5;TT6;TT7;TT8;TT9;TT10;>;
    MethodParameters:
      Name                           Flags
      _1                             final
      _2                             final
      _3                             final
      _4                             final
      _5                             final
      _6                             final
      _7                             final
      _8                             final
      _9                             final
      _10                            final

  public <T1 extends java.lang.Object, T2 extends java.lang.Object, T3 extends java.lang.Object, T4 extends java.lang.Object, T5 extends java.lang.Object, T6 extends java.lang.Object, T7 extends java.lang.Object, T8 extends java.lang.Object, T9 extends java.lang.Object, T10 extends java.lang.Object> T1 copy$default$1();
    descriptor: ()Ljava/lang/Object;
    flags: (0x0001) ACC_PUBLIC
    Code:
      stack=1, locals=1, args_size=1
         0: aload_0
         1: invokevirtual #129                // Method _1:()Ljava/lang/Object;
         4: areturn
      LineNumberTable:
        line 32: 0
      LocalVariableTable:
        Start  Length  Slot  Name   Signature
            0       5     0  this   Lscala/Tuple10;
    Signature: #159                         // <T1:Ljava/lang/Object;T2:Ljava/lang/Object;T3:Ljava/lang/Object;T4:Ljava/lang/Object;T5:Ljava/lang/Object;T6:Ljava/lang/Object;T7:Ljava/lang/Object;T8:Ljava/lang/Object;T9:Ljava/lang/Object;T10:Ljava/lang/Object;>()TT1;

  public <T1 extends java.lang.Object, T2 extends java.lang.Object, T3 extends java.lang.Object, T4 extends java.lang.Object, T5 extends java.lang.Object, T6 extends java.lang.Object, T7 extends java.lang.Object, T8 extends java.lang.Object, T9 extends java.lang.Object, T10 extends java.lang.Object> T10 copy$default$10();
    descriptor: ()Ljava/lang/Object;
    flags: (0x0001) ACC_PUBLIC
    Code:
      stack=1, locals=1, args_size=1
         0: aload_0
         1: invokevirtual #152                // Method _10:()Ljava/lang/Object;
         4: areturn
      LineNumberTable:
        line 32: 0
      LocalVariableTable:
        Start  Length  Slot  Name   Signature
            0       5     0  this   Lscala/Tuple10;
    Signature: #161                         // <T1:Ljava/lang/Object;T2:Ljava/lang/Object;T3:Ljava/lang/Object;T4:Ljava/lang/Object;T5:Ljava/lang/Object;T6:Ljava/lang/Object;T7:Ljava/lang/Object;T8:Ljava/lang/Object;T9:Ljava/lang/Object;T10:Ljava/lang/Object;>()TT10;

  public <T1 extends java.lang.Object, T2 extends java.lang.Object, T3 extends java.lang.Object, T4 extends java.lang.Object, T5 extends java.lang.Object, T6 extends java.lang.Object, T7 extends java.lang.Object, T8 extends java.lang.Object, T9 extends java.lang.Object, T10 extends java.lang.Object> T2 copy$default$2();
    descriptor: ()Ljava/lang/Object;
    flags: (0x0001) ACC_PUBLIC
    Code:
      stack=1, locals=1, args_size=1
         0: aload_0
         1: invokevirtual #136                // Method _2:()Ljava/lang/Object;
         4: areturn
      LineNumberTable:
        line 32: 0
      LocalVariableTable:
        Start  Length  Slot  Name   Signature
            0       5     0  this   Lscala/Tuple10;
    Signature: #163                         // <T1:Ljava/lang/Object;T2:Ljava/lang/Object;T3:Ljava/lang/Object;T4:Ljava/lang/Object;T5:Ljava/lang/Object;T6:Ljava/lang/Object;T7:Ljava/lang/Object;T8:Ljava/lang/Object;T9:Ljava/lang/Object;T10:Ljava/lang/Object;>()TT2;

  public <T1 extends java.lang.Object, T2 extends java.lang.Object, T3 extends java.lang.Object, T4 extends java.lang.Object, T5 extends java.lang.Object, T6 extends java.lang.Object, T7 extends java.lang.Object, T8 extends java.lang.Object, T9 extends java.lang.Object, T10 extends java.lang.Object> T3 copy$default$3();
    descriptor: ()Ljava/lang/Object;
    flags: (0x0001) ACC_PUBLIC
    Code:
      stack=1, locals=1, args_size=1
         0: aload_0
         1: invokevirtual #138                // Method _3:()Ljava/lang/Object;
         4: areturn
      LineNumberTable:
        line 32: 0
      LocalVariableTable:
        Start  Length  Slot  Name   Signature
            0       5     0  this   Lscala/Tuple10;
    Signature: #165                         // <T1:Ljava/lang/Object;T2:Ljava/lang/Object;T3:Ljava/lang/Object;T4:Ljava/lang/Object;T5:Ljava/lang/Object;T6:Ljava/lang/Object;T7:Ljava/lang/Object;T8:Ljava/lang/Object;T9:Ljava/lang/Object;T10:Ljava/lang/Object;>()TT3;

  public <T1 extends java.lang.Object, T2 extends java.lang.Object, T3 extends java.lang.Object, T4 extends java.lang.Object, T5 extends java.lang.Object, T6 extends java.lang.Object, T7 extends java.lang.Object, T8 extends java.lang.Object, T9 extends java.lang.Object, T10 extends java.lang.Object> T4 copy$default$4();
    descriptor: ()Ljava/lang/Object;
    flags: (0x0001) ACC_PUBLIC
    Code:
      stack=1, locals=1, args_size=1
         0: aload_0
         1: invokevirtual #140                // Method _4:()Ljava/lang/Object;
         4: areturn
      LineNumberTable:
        line 32: 0
      LocalVariableTable:
        Start  Length  Slot  Name   Signature
            0       5     0  this   Lscala/Tuple10;
    Signature: #167                         // <T1:Ljava/lang/Object;T2:Ljava/lang/Object;T3:Ljava/lang/Object;T4:Ljava/lang/Object;T5:Ljava/lang/Object;T6:Ljava/lang/Object;T7:Ljava/lang/Object;T8:Ljava/lang/Object;T9:Ljava/lang/Object;T10:Ljava/lang/Object;>()TT4;

  public <T1 extends java.lang.Object, T2 extends java.lang.Object, T3 extends java.lang.Object, T4 extends java.lang.Object, T5 extends java.lang.Object, T6 extends java.lang.Object, T7 extends java.lang.Object, T8 extends java.lang.Object, T9 extends java.lang.Object, T10 extends java.lang.Object> T5 copy$default$5();
    descriptor: ()Ljava/lang/Object;
    flags: (0x0001) ACC_PUBLIC
    Code:
      stack=1, locals=1, args_size=1
         0: aload_0
         1: invokevirtual #142                // Method _5:()Ljava/lang/Object;
         4: areturn
      LineNumberTable:
        line 32: 0
      LocalVariableTable:
        Start  Length  Slot  Name   Signature
            0       5     0  this   Lscala/Tuple10;
    Signature: #169                         // <T1:Ljava/lang/Object;T2:Ljava/lang/Object;T3:Ljava/lang/Object;T4:Ljava/lang/Object;T5:Ljava/lang/Object;T6:Ljava/lang/Object;T7:Ljava/lang/Object;T8:Ljava/lang/Object;T9:Ljava/lang/Object;T10:Ljava/lang/Object;>()TT5;

  public <T1 extends java.lang.Object, T2 extends java.lang.Object, T3 extends java.lang.Object, T4 extends java.lang.Object, T5 extends java.lang.Object, T6 extends java.lang.Object, T7 extends java.lang.Object, T8 extends java.lang.Object, T9 extends java.lang.Object, T10 extends java.lang.Object> T6 copy$default$6();
    descriptor: ()Ljava/lang/Object;
    flags: (0x0001) ACC_PUBLIC
    Code:
      stack=1, locals=1, args_size=1
         0: aload_0
         1: invokevirtual #144                // Method _6:()Ljava/lang/Object;
         4: areturn
      LineNumberTable:
        line 32: 0
      LocalVariableTable:
        Start  Length  Slot  Name   Signature
            0       5     0  this   Lscala/Tuple10;
    Signature: #171                         // <T1:Ljava/lang/Object;T2:Ljava/lang/Object;T3:Ljava/lang/Object;T4:Ljava/lang/Object;T5:Ljava/lang/Object;T6:Ljava/lang/Object;T7:Ljava/lang/Object;T8:Ljava/lang/Object;T9:Ljava/lang/Object;T10:Ljava/lang/Object;>()TT6;

  public <T1 extends java.lang.Object, T2 extends java.lang.Object, T3 extends java.lang.Object, T4 extends java.lang.Object, T5 extends java.lang.Object, T6 extends java.lang.Object, T7 extends java.lang.Object, T8 extends java.lang.Object, T9 extends java.lang.Object, T10 extends java.lang.Object> T7 copy$default$7();
    descriptor: ()Ljava/lang/Object;
    flags: (0x0001) ACC_PUBLIC
    Code:
      stack=1, locals=1, args_size=1
         0: aload_0
         1: invokevirtual #146                // Method _7:()Ljava/lang/Object;
         4: areturn
      LineNumberTable:
        line 32: 0
      LocalVariableTable:
        Start  Length  Slot  Name   Signature
            0       5     0  this   Lscala/Tuple10;
    Signature: #173                         // <T1:Ljava/lang/Object;T2:Ljava/lang/Object;T3:Ljava/lang/Object;T4:Ljava/lang/Object;T5:Ljava/lang/Object;T6:Ljava/lang/Object;T7:Ljava/lang/Object;T8:Ljava/lang/Object;T9:Ljava/lang/Object;T10:Ljava/lang/Object;>()TT7;

  public <T1 extends java.lang.Object, T2 extends java.lang.Object, T3 extends java.lang.Object, T4 extends java.lang.Object, T5 extends java.lang.Object, T6 extends java.lang.Object, T7 extends java.lang.Object, T8 extends java.lang.Object, T9 extends java.lang.Object, T10 extends java.lang.Object> T8 copy$default$8();
    descriptor: ()Ljava/lang/Object;
    flags: (0x0001) ACC_PUBLIC
    Code:
      stack=1, locals=1, args_size=1
         0: aload_0
         1: invokevirtual #148                // Method _8:()Ljava/lang/Object;
         4: areturn
      LineNumberTable:
        line 32: 0
      LocalVariableTable:
        Start  Length  Slot  Name   Signature
            0       5     0  this   Lscala/Tuple10;
    Signature: #175                         // <T1:Ljava/lang/Object;T2:Ljava/lang/Object;T3:Ljava/lang/Object;T4:Ljava/lang/Object;T5:Ljava/lang/Object;T6:Ljava/lang/Object;T7:Ljava/lang/Object;T8:Ljava/lang/Object;T9:Ljava/lang/Object;T10:Ljava/lang/Object;>()TT8;

  public <T1 extends java.lang.Object, T2 extends java.lang.Object, T3 extends java.lang.Object, T4 extends java.lang.Object, T5 extends java.lang.Object, T6 extends java.lang.Object, T7 extends java.lang.Object, T8 extends java.lang.Object, T9 extends java.lang.Object, T10 extends java.lang.Object> T9 copy$default$9();
    descriptor: ()Ljava/lang/Object;
    flags: (0x0001) ACC_PUBLIC
    Code:
      stack=1, locals=1, args_size=1
         0: aload_0
         1: invokevirtual #150                // Method _9:()Ljava/lang/Object;
         4: areturn
      LineNumberTable:
        line 32: 0
      LocalVariableTable:
        Start  Length  Slot  Name   Signature
            0       5     0  this   Lscala/Tuple10;
    Signature: #177                         // <T1:Ljava/lang/Object;T2:Ljava/lang/Object;T3:Ljava/lang/Object;T4:Ljava/lang/Object;T5:Ljava/lang/Object;T6:Ljava/lang/Object;T7:Ljava/lang/Object;T8:Ljava/lang/Object;T9:Ljava/lang/Object;T10:Ljava/lang/Object;>()TT9;

  public java.lang.String productPrefix();
    descriptor: ()Ljava/lang/String;
    flags: (0x0001) ACC_PUBLIC
    Code:
      stack=1, locals=1, args_size=1
         0: ldc           #180                // String Tuple10
         2: areturn
      LineNumberTable:
        line 32: 0
      LocalVariableTable:
        Start  Length  Slot  Name   Signature
            0       3     0  this   Lscala/Tuple10;

  public scala.collection.Iterator<java.lang.Object> productIterator();
    descriptor: ()Lscala/collection/Iterator;
    flags: (0x0001) ACC_PUBLIC
    Code:
      stack=3, locals=1, args_size=1
         0: new           #15                 // class scala/runtime/ScalaRunTime$$anon$1
         3: dup
         4: aload_0
         5: invokespecial #185                // Method scala/runtime/ScalaRunTime$$anon$1."<init>":(Lscala/Product;)V
         8: areturn
      LineNumberTable:
        line 32: 0
      LocalVariableTable:
        Start  Length  Slot  Name   Signature
            0       9     0  this   Lscala/Tuple10;
    Signature: #182                         // ()Lscala/collection/Iterator<Ljava/lang/Object;>;

  public boolean canEqual(java.lang.Object);
    descriptor: (Ljava/lang/Object;)Z
    flags: (0x0001) ACC_PUBLIC
    Code:
      stack=1, locals=2, args_size=2
         0: aload_1
         1: instanceof    #2                  // class scala/Tuple10
         4: ireturn
      LineNumberTable:
        line 32: 0
      LocalVariableTable:
        Start  Length  Slot  Name   Signature
            0       5     0  this   Lscala/Tuple10;
            0       5     1   x$1   Ljava/lang/Object;
    MethodParameters:
      Name                           Flags
      x$1                            final

  public java.lang.String productElementName(int);
    descriptor: (I)Ljava/lang/String;
    flags: (0x0001) ACC_PUBLIC
    Code:
      stack=1, locals=2, args_size=2
         0: iload_1
         1: tableswitch   { // 0 to 9
                       0: 56
                       1: 59
                       2: 62
                       3: 65
                       4: 68
                       5: 71
                       6: 74
                       7: 77
                       8: 80
                       9: 83
                 default: 86
            }
        56: ldc           #191                // String _1
        58: areturn
        59: ldc           #192                // String _2
        61: areturn
        62: ldc           #193                // String _3
        64: areturn
        65: ldc           #194                // String _4
        67: areturn
        68: ldc           #195                // String _5
        70: areturn
        71: ldc           #196                // String _6
        73: areturn
        74: ldc           #197                // String _7
        76: areturn
        77: ldc           #198                // String _8
        79: areturn
        80: ldc           #199                // String _9
        82: areturn
        83: ldc           #200                // String _10
        85: areturn
        86: iload_1
        87: invokestatic  #205                // Method scala/runtime/Statics.ioobe:(I)Ljava/lang/Object;
        90: checkcast     #207                // class java/lang/String
        93: areturn
      StackMapTable: number_of_entries = 11
        frame_type = 56 /* same */
        frame_type = 2 /* same */
        frame_type = 2 /* same */
        frame_type = 2 /* same */
        frame_type = 2 /* same */
        frame_type = 2 /* same */
        frame_type = 2 /* same */
        frame_type = 2 /* same */
        frame_type = 2 /* same */
        frame_type = 2 /* same */
        frame_type = 2 /* same */
      LineNumberTable:
        line 32: 0
      LocalVariableTable:
        Start  Length  Slot  Name   Signature
            0      94     0  this   Lscala/Tuple10;
            0      94     1   x$1   I
    MethodParameters:
      Name                           Flags
      x$1                            final

  public int hashCode();
    descriptor: ()I
    flags: (0x0001) ACC_PUBLIC
    Code:
      stack=2, locals=1, args_size=1
         0: getstatic     #213                // Field scala/util/hashing/MurmurHash3$.MODULE$:Lscala/util/hashing/MurmurHash3$;
         3: aload_0
         4: invokevirtual #217                // Method scala/util/hashing/MurmurHash3$.productHash:(Lscala/Product;)I
         7: ireturn
      LineNumberTable:
        line 32: 0
      LocalVariableTable:
        Start  Length  Slot  Name   Signature
            0       8     0  this   Lscala/Tuple10;

  public boolean equals(java.lang.Object);
    descriptor: (Ljava/lang/Object;)Z
    flags: (0x0001) ACC_PUBLIC
    Code:
      stack=2, locals=4, args_size=2
         0: aload_0
         1: aload_1
         2: if_acmpeq     176
         5: aload_1
         6: instanceof    #2                  // class scala/Tuple10
         9: ifeq          17
        12: iconst_1
        13: istore_2
        14: goto          19
        17: iconst_0
        18: istore_2
        19: iload_2
        20: ifeq          178
        23: aload_1
        24: checkcast     #2                  // class scala/Tuple10
        27: astore_3
        28: aload_0
        29: invokevirtual #129                // Method _1:()Ljava/lang/Object;
        32: aload_3
        33: invokevirtual #129                // Method _1:()Ljava/lang/Object;
        36: invokestatic  #223                // Method scala/runtime/BoxesRunTime.equals:(Ljava/lang/Object;Ljava/lang/Object;)Z
        39: ifeq          172
        42: aload_0
        43: invokevirtual #136                // Method _2:()Ljava/lang/Object;
        46: aload_3
        47: invokevirtual #136                // Method _2:()Ljava/lang/Object;
        50: invokestatic  #223                // Method scala/runtime/BoxesRunTime.equals:(Ljava/lang/Object;Ljava/lang/Object;)Z
        53: ifeq          172
        56: aload_0
        57: invokevirtual #138                // Method _3:()Ljava/lang/Object;
        60: aload_3
        61: invokevirtual #138                // Method _3:()Ljava/lang/Object;
        64: invokestatic  #223                // Method scala/runtime/BoxesRunTime.equals:(Ljava/lang/Object;Ljava/lang/Object;)Z
        67: ifeq          172
        70: aload_0
        71: invokevirtual #140                // Method _4:()Ljava/lang/Object;
        74: aload_3
        75: invokevirtual #140                // Method _4:()Ljava/lang/Object;
        78: invokestatic  #223                // Method scala/runtime/BoxesRunTime.equals:(Ljava/lang/Object;Ljava/lang/Object;)Z
        81: ifeq          172
        84: aload_0
        85: invokevirtual #142                // Method _5:()Ljava/lang/Object;
        88: aload_3
        89: invokevirtual #142                // Method _5:()Ljava/lang/Object;
        92: invokestatic  #223                // Method scala/runtime/BoxesRunTime.equals:(Ljava/lang/Object;Ljava/lang/Object;)Z
        95: ifeq          172
        98: aload_0
        99: invokevirtual #144                // Method _6:()Ljava/lang/Object;
       102: aload_3
       103: invokevirtual #144                // Method _6:()Ljava/lang/Object;
       106: invokestatic  #223                // Method scala/runtime/BoxesRunTime.equals:(Ljava/lang/Object;Ljava/lang/Object;)Z
       109: ifeq          172
       112: aload_0
       113: invokevirtual #146                // Method _7:()Ljava/lang/Object;
       116: aload_3
       117: invokevirtual #146                // Method _7:()Ljava/lang/Object;
       120: invokestatic  #223                // Method scala/runtime/BoxesRunTime.equals:(Ljava/lang/Object;Ljava/lang/Object;)Z
       123: ifeq          172
       126: aload_0
       127: invokevirtual #148                // Method _8:()Ljava/lang/Object;
       130: aload_3
       131: invokevirtual #148                // Method _8:()Ljava/lang/Object;
       134: invokestatic  #223                // Method scala/runtime/BoxesRunTime.equals:(Ljava/lang/Object;Ljava/lang/Object;)Z
       137: ifeq          172
       140: aload_0
       141: invokevirtual #150                // Method _9:()Ljava/lang/Object;
       144: aload_3
       145: invokevirtual #150                // Method _9:()Ljava/lang/Object;
       148: invokestatic  #223                // Method scala/runtime/BoxesRunTime.equals:(Ljava/lang/Object;Ljava/lang/Object;)Z
       151: ifeq          172
       154: aload_0
       155: invokevirtual #152                // Method _10:()Ljava/lang/Object;
       158: aload_3
       159: invokevirtual #152                // Method _10:()Ljava/lang/Object;
       162: invokestatic  #223                // Method scala/runtime/BoxesRunTime.equals:(Ljava/lang/Object;Ljava/lang/Object;)Z
       165: ifeq          172
       168: iconst_1
       169: goto          173
       172: iconst_0
       173: ifeq          178
       176: iconst_1
       177: ireturn
       178: iconst_0
       179: ireturn
      StackMapTable: number_of_entries = 6
        frame_type = 17 /* same */
        frame_type = 252 /* append */
          offset_delta = 1
          locals = [ int ]
        frame_type = 252 /* append */
          offset_delta = 152
          locals = [ class scala/Tuple10 ]
        frame_type = 64 /* same_locals_1_stack_item */
          stack = [ int ]
        frame_type = 249 /* chop */
          offset_delta = 2
        frame_type = 252 /* append */
          offset_delta = 1
          locals = [ int ]
      LineNumberTable:
        line 32: 0
      LocalVariableTable:
        Start  Length  Slot  Name   Signature
            0     180     0  this   Lscala/Tuple10;
            0     180     1   x$1   Ljava/lang/Object;
    MethodParameters:
      Name                           Flags
      x$1                            final

  public scala.Tuple10(T1, T2, T3, T4, T5, T6, T7, T8, T9, T10);
    descriptor: (Ljava/lang/Object;Ljava/lang/Object;Ljava/lang/Object;Ljava/lang/Object;Ljava/lang/Object;Ljava/lang/Object;Ljava/lang/Object;Ljava/lang/Object;Ljava/lang/Object;Ljava/lang/Object;)V
    flags: (0x0001) ACC_PUBLIC
    Code:
      stack=2, locals=11, args_size=11
         0: aload_0
         1: aload_1
         2: putfield      #86                 // Field _1:Ljava/lang/Object;
         5: aload_0
         6: aload_2
         7: putfield      #89                 // Field _2:Ljava/lang/Object;
        10: aload_0
        11: aload_3
        12: putfield      #92                 // Field _3:Ljava/lang/Object;
        15: aload_0
        16: aload         4
        18: putfield      #95                 // Field _4:Ljava/lang/Object;
        21: aload_0
        22: aload         5
        24: putfield      #98                 // Field _5:Ljava/lang/Object;
        27: aload_0
        28: aload         6
        30: putfield      #101                // Field _6:Ljava/lang/Object;
        33: aload_0
        34: aload         7
        36: putfield      #104                // Field _7:Ljava/lang/Object;
        39: aload_0
        40: aload         8
        42: putfield      #107                // Field _8:Ljava/lang/Object;
        45: aload_0
        46: aload         9
        48: putfield      #110                // Field _9:Ljava/lang/Object;
        51: aload_0
        52: aload         10
        54: putfield      #113                // Field _10:Ljava/lang/Object;
        57: aload_0
        58: invokespecial #227                // Method java/lang/Object."<init>":()V
        61: return
      LineNumberTable:
        line 32: 0
        line 33: 57
      LocalVariableTable:
        Start  Length  Slot  Name   Signature
            0      62     0  this   Lscala/Tuple10;
            0      62     1    _1   Ljava/lang/Object;
            0      62     2    _2   Ljava/lang/Object;
            0      62     3    _3   Ljava/lang/Object;
            0      62     4    _4   Ljava/lang/Object;
            0      62     5    _5   Ljava/lang/Object;
            0      62     6    _6   Ljava/lang/Object;
            0      62     7    _7   Ljava/lang/Object;
            0      62     8    _8   Ljava/lang/Object;
            0      62     9    _9   Ljava/lang/Object;
            0      62    10   _10   Ljava/lang/Object;
    Signature: #224                         // (TT1;TT2;TT3;TT4;TT5;TT6;TT7;TT8;TT9;TT10;)V
    MethodParameters:
      Name                           Flags
      _1                             final
      _2                             final
      _3                             final
      _4                             final
      _5                             final
      _6                             final
      _7                             final
      _8                             final
      _9                             final
      _10                            final
}
InnerClasses:
  public final #15;                       // class scala/runtime/ScalaRunTime$$anon$1
Signature: #3                           // <T1:Ljava/lang/Object;T2:Ljava/lang/Object;T3:Ljava/lang/Object;T4:Ljava/lang/Object;T5:Ljava/lang/Object;T6:Ljava/lang/Object;T7:Ljava/lang/Object;T8:Ljava/lang/Object;T9:Ljava/lang/Object;T10:Ljava/lang/Object;>Ljava/lang/Object;Lscala/Product10<TT1;TT2;TT3;TT4;TT5;TT6;TT7;TT8;TT9;TT10;>;Ljava/io/Serializable;
SourceFile: "Tuple10.scala"
RuntimeVisibleAnnotations:
  0: #11(#12=s#13)
    scala.reflect.ScalaSignature(
      bytes="\u0006\u0005\rue\u0001B\u00181\u0005NB\u0001\"\u001d\u0001\u0003\u0016\u0004%\tA\u001d\u0005\tg\u0002\u0011\t\u0012)A\u0005y!AA\u000f\u0001BK\u0002\u0013\u0005Q\u000f\u0003\u0005w\u0001\tE\t\u0015!\u0003H\u0011!9\bA!f\u0001\n\u0003A\b\u0002C=\u0001\u0005#\u0005\u000b\u0011\u0002&\t\u0011i\u0004!Q3A\u0005\u0002mD\u0001\u0002 \u0001\u0003\u0012\u0003\u0006I!\u0014\u0005\t{\u0002\u0011)\u001a!C\u0001}\"Aq\u0010\u0001B\tB\u0003%\u0001\u000b\u0003\u0006\u0002\u0002\u0001\u0011)\u001a!C\u0001\u0003\u0007A\u0011\"!\u0002\u0001\u0005#\u0005\u000b\u0011B*\t\u0015\u0005\u001d\u0001A!f\u0001\n\u0003\tI\u0001C\u0005\u0002\f\u0001\u0011\t\u0012)A\u0005-\"Q\u0011Q\u0002\u0001\u0003\u0016\u0004%\t!a\u0004\t\u0013\u0005E\u0001A!E!\u0002\u0013I\u0006BCA\n\u0001\tU\r\u0011\"\u0001\u0002\u0016!I\u0011q\u0003\u0001\u0003\u0012\u0003\u0006I\u0001\u0018\u0005\u000b\u00033\u0001!Q3A\u0005\u0002\u0005m\u0001\"CA\u000f\u0001\tE\t\u0015!\u0003`\u0011\u001d\ty\u0002\u0001C\u0001\u0003CAq!!\u000f\u0001\t\u0003\nY\u0004C\u0005\u0002N\u0001\t\t\u0011\"\u0001\u0002P!I\u0011\u0011\u0013\u0001\u0012\u0002\u0013\u0005\u00111\u0013\u0005\n\u0003\u007f\u0003\u0011\u0013!C\u0001\u0003\u0003D\u0011\"a7\u0001#\u0003%\t!!8\t\u0013\u0005]\b!%A\u0005\u0002\u0005e\b\"\u0003B\n\u0001E\u0005I\u0011\u0001B\u000b\u0011%\u0011y\u0003AI\u0001\n\u0003\u0011\t\u0004C\u0005\u0003L\u0001\t\n\u0011\"\u0001\u0003N!I!q\r\u0001\u0012\u0002\u0013\u0005!\u0011\u000e\u0005\n\u0005\u0007\u0003\u0011\u0013!C\u0001\u0005\u000bC\u0011Ba(\u0001#\u0003%\tA!)\t\u0013\tm\u0006!!A\u0005B\tu\u0006\"\u0003Bg\u0001\u0005\u0005I\u0011\tBh\u0011%\u0011i\u000eAA\u0001\n\u0003\u0011y\u000eC\u0005\u0003l\u0002\t\t\u0011\"\u0011\u0003n\"I!q\u001f\u0001\u0002\u0002\u0013\u0005#\u0011 \u0005\n\u0005w\u0004\u0011\u0011!C!\u0005{<\u0011b!\u00011\u0003\u0003E\taa\u0001\u0007\u0011=\u0002\u0014\u0011!E\u0001\u0007\u000bAq!a\b*\t\u0003\u0019\t\u0002C\u0005\u0002:%\n\t\u0011\"\u0012\u0004\u0014!I1QC\u0015\u0002\u0002\u0013\u00055q\u0003\u0005\n\u00073J\u0013\u0011!CA\u00077B\u0011ba%*\u0003\u0003%Ia!&\u0003\u000fQ+\b\u000f\\32a)\t\u0011\'A\u0003tG\u0006d\u0017m\u0001\u0001\u0016\u0017Qr\u0004j\u0013(R)^SV\fY\n\u0006\u0001UJ$-\u001a\t\u0003m]j\u0011\u0001M\u0005\u0003qA\u0012a!\u00118z%\u00164\u0007\u0003\u0004\u001c;y\u001dSU\nU*W3r{\u0016BA\u001e1\u0005%\u0001&o\u001c3vGR\f\u0004\u0007\u0005\u0002>}1\u0001AAB \u0001\t\u000b\u0007\u0001I\u0001\u0002UcE\u0011\u0011\t\u0012\t\u0003m\tK!a\u0011\u0019\u0003\u000f9{G\u000f[5oOB\u0011a\'R\u0005\u0003\rB\u00121!\u00118z!\ti\u0004\n\u0002\u0004J\u0001\u0011\u0015\r\u0001\u0011\u0002\u0003)J\u0002\"!P&\u0005\r1\u0003AQ1\u0001A\u0005\t!6\u0007\u0005\u0002>\u001d\u00121q\n\u0001CC\u0002\u0001\u0013!\u0001\u0016\u001b\u0011\u0005u\nFA\u0002*\u0001\t\u000b\u0007\u0001I\u0001\u0002UkA\u0011Q\b\u0016\u0003\u0007+\u0002!)\u0019\u0001!\u0003\u0005Q3\u0004CA\u001fX\t\u0019A\u0006\u0001\"b\u0001\u0001\n\u0011Ak\u000e\t\u0003{i#aa\u0017\u0001\u0005\u0006\u0004\u0001%A\u0001+9!\tiT\f\u0002\u0004_\u0001\u0011\u0015\r\u0001\u0011\u0002\u0003)f\u0002\"!\u00101\u0005\r\u0005\u0004AQ1\u0001A\u0005\r!\u0016\u0007\r\t\u0003m\rL!\u0001\u001a\u0019\u0003\u000fA\u0013x\u000eZ;diB\u0011aM\u001c\b\u0003O2t!\u0001[6\u000e\u0003%T!A\u001b\u001a\u0002\rq\u0012xn\u001c;?\u0013\u0005\t\u0014BA71\u0003\u001d\u0001\u0018mY6bO\u0016L!a\u001c9\u0003\u0019M+\'/[1mSj\f\'\r\\3\u000b\u00055\u0004\u0014AA02+\u0005a\u0014aA02A\u0005\u0011qLM\u000b\u0002\u000f\u0006\u0019qL\r\u0011\u0002\u0005}\u001bT#\u0001&\u0002\u0007}\u001b\u0004%\u0001\u0002`iU\tQ*A\u0002`i\u0001\n!aX\u001b\u0016\u0003A\u000b1aX\u001b!\u0003\tyf\'F\u0001T\u0003\ryf\u0007I\u0001\u0003?^*\u0012AV\u0001\u0004?^\u0002\u0013AA09+\u0005I\u0016aA09A\u0005\u0011q,O\u000b\u00029\u0006\u0019q,\u000f\u0011\u0002\u0007}\u000b\u0004\'F\u0001`\u0003\u0011y\u0016\u0007\r\u0011\u0002\rqJg.\u001b;?)Y\t\u0019#!\n\u0002(\u0005%\u00121FA\u0017\u0003_\t\t$a\r\u00026\u0005]\u0002\u0003\u0004\u001c\u0001y\u001dSU\nU*W3r{\u0006\"B9\u0016\u0001\u0004a\u0004\"\u0002;\u0016\u0001\u00049\u0005\"B<\u0016\u0001\u0004Q\u0005\"\u0002>\u0016\u0001\u0004i\u0005\"B?\u0016\u0001\u0004\u0001\u0006BBA\u0001+\u0001\u00071\u000b\u0003\u0004\u0002\bU\u0001\rA\u0016\u0005\u0007\u0003\u001b)\u0002\u0019A-\t\r\u0005MQ\u00031\u0001]\u0011\u0019\tI\"\u0006a\u0001?\u0006AAo\\*ue&tw\r\u0006\u0002\u0002>A!\u0011qHA$\u001d\u0011\t\t%a\u0011\u0011\u0005!\u0004\u0014bAA#a\u00051\u0001K]3eK\u001aLA!!\u0013\u0002L\t11\u000b\u001e:j]\u001eT1!!\u00121\u0003\u0011\u0019w\u000e]=\u0016-\u0005E\u0013qKA.\u0003?\n\u0019\'a\u001a\u0002l\u0005=\u00141OA<\u0003w\"b#a\u0015\u0002~\u0005}\u0014\u0011QAB\u0003\u000b\u000b9)!#\u0002\f\u00065\u0015q\u0012\t\u0017m\u0001\t)&!\u0017\u0002^\u0005\u0005\u0014QMA5\u0003[\n\t(!\u001e\u0002zA\u0019Q(a\u0016\u0005\u000b}:\"\u0019\u0001!\u0011\u0007u\nY\u0006B\u0003J/\t\u0007\u0001\tE\u0002>\u0003?\"Q\u0001T\fC\u0002\u0001\u00032!PA2\t\u0015yuC1\u0001A!\ri\u0014q\r\u0003\u0006%^\u0011\r\u0001\u0011\t\u0004{\u0005-D!B+\u0018\u0005\u0004\u0001\u0005cA\u001f\u0002p\u0011)\u0001l\u0006b\u0001\u0001B\u0019Q(a\u001d\u0005\u000bm;\"\u0019\u0001!\u0011\u0007u\n9\bB\u0003_/\t\u0007\u0001\tE\u0002>\u0003w\"Q!Y\fC\u0002\u0001C\u0001\"]\f\u0011\u0002\u0003\u0007\u0011Q\u000b\u0005\ti^\u0001\n\u00111\u0001\u0002Z!Aqo\u0006I\u0001\u0002\u0004\ti\u0006\u0003\u0005{/A\u0005\t\u0019AA1\u0011!ix\u0003%AA\u0002\u0005\u0015\u0004\"CA\u0001/A\u0005\t\u0019AA5\u0011%\t9a\u0006I\u0001\u0002\u0004\ti\u0007C\u0005\u0002\u000e]\u0001\n\u00111\u0001\u0002r!I\u00111C\f\u0011\u0002\u0003\u0007\u0011Q\u000f\u0005\n\u000339\u0002\u0013!a\u0001\u0003s\nabY8qs\u0012\"WMZ1vYR$\u0013\'\u0006\f\u0002\u0016\u0006-\u0016QVAX\u0003c\u000b\u0019,!.\u00028\u0006e\u00161XA_+\t\t9JK\u0002=\u00033[#!a\'\u0011\t\u0005u\u0015qU\u0007\u0003\u0003?SA!!)\u0002$\u0006IQO\\2iK\u000e\\W\r\u001a\u0006\u0004\u0003K\u0003\u0014AC1o]>$\u0018\r^5p]&!\u0011\u0011VAP\u0005E)hn\u00195fG.,GMV1sS\u0006t7-\u001a\u0003\u0006\u007fa\u0011\r\u0001\u0011\u0003\u0006\u0013b\u0011\r\u0001\u0011\u0003\u0006\u0019b\u0011\r\u0001\u0011\u0003\u0006\u001fb\u0011\r\u0001\u0011\u0003\u0006%b\u0011\r\u0001\u0011\u0003\u0006+b\u0011\r\u0001\u0011\u0003\u00061b\u0011\r\u0001\u0011\u0003\u00067b\u0011\r\u0001\u0011\u0003\u0006=b\u0011\r\u0001\u0011\u0003\u0006Cb\u0011\r\u0001Q\u0001\u000fG>\u0004\u0018\u0010\n3fM\u0006,H\u000e\u001e\u00133+Y\t\u0019-a2\u0002J\u0006-\u0017QZAh\u0003#\f\u0019.!6\u0002X\u0006eWCAAcU\r9\u0015\u0011\u0014\u0003\u0006\u007fe\u0011\r\u0001\u0011\u0003\u0006\u0013f\u0011\r\u0001\u0011\u0003\u0006\u0019f\u0011\r\u0001\u0011\u0003\u0006\u001ff\u0011\r\u0001\u0011\u0003\u0006%f\u0011\r\u0001\u0011\u0003\u0006+f\u0011\r\u0001\u0011\u0003\u00061f\u0011\r\u0001\u0011\u0003\u00067f\u0011\r\u0001\u0011\u0003\u0006=f\u0011\r\u0001\u0011\u0003\u0006Cf\u0011\r\u0001Q\u0001\u000fG>\u0004\u0018\u0010\n3fM\u0006,H\u000e\u001e\u00134+Y\ty.a9\u0002f\u0006\u001d\u0018\u0011^Av\u0003[\fy/!=\u0002t\u0006UXCAAqU\rQ\u0015\u0011\u0014\u0003\u0006\u007fi\u0011\r\u0001\u0011\u0003\u0006\u0013j\u0011\r\u0001\u0011\u0003\u0006\u0019j\u0011\r\u0001\u0011\u0003\u0006\u001fj\u0011\r\u0001\u0011\u0003\u0006%j\u0011\r\u0001\u0011\u0003\u0006+j\u0011\r\u0001\u0011\u0003\u00061j\u0011\r\u0001\u0011\u0003\u00067j\u0011\r\u0001\u0011\u0003\u0006=j\u0011\r\u0001\u0011\u0003\u0006Cj\u0011\r\u0001Q\u0001\u000fG>\u0004\u0018\u0010\n3fM\u0006,H\u000e\u001e\u00135+Y\tY0a@\u0003\u0002\t\r!Q\u0001B\u0004\u0005\u0013\u0011YA!\u0004\u0003\u0010\tEQCAA\u007fU\ri\u0015\u0011\u0014\u0003\u0006\u007fm\u0011\r\u0001\u0011\u0003\u0006\u0013n\u0011\r\u0001\u0011\u0003\u0006\u0019n\u0011\r\u0001\u0011\u0003\u0006\u001fn\u0011\r\u0001\u0011\u0003\u0006%n\u0011\r\u0001\u0011\u0003\u0006+n\u0011\r\u0001\u0011\u0003\u00061n\u0011\r\u0001\u0011\u0003\u00067n\u0011\r\u0001\u0011\u0003\u0006=n\u0011\r\u0001\u0011\u0003\u0006Cn\u0011\r\u0001Q\u0001\u000fG>\u0004\u0018\u0010\n3fM\u0006,H\u000e\u001e\u00136+Y\u00119Ba\u0007\u0003\u001e\t}!\u0011\u0005B\u0012\u0005K\u00119C!\u000b\u0003,\t5RC\u0001B\rU\r\u0001\u0016\u0011\u0014\u0003\u0006\u007fq\u0011\r\u0001\u0011\u0003\u0006\u0013r\u0011\r\u0001\u0011\u0003\u0006\u0019r\u0011\r\u0001\u0011\u0003\u0006\u001fr\u0011\r\u0001\u0011\u0003\u0006%r\u0011\r\u0001\u0011\u0003\u0006+r\u0011\r\u0001\u0011\u0003\u00061r\u0011\r\u0001\u0011\u0003\u00067r\u0011\r\u0001\u0011\u0003\u0006=r\u0011\r\u0001\u0011\u0003\u0006Cr\u0011\r\u0001Q\u0001\u000fG>\u0004\u0018\u0010\n3fM\u0006,H\u000e\u001e\u00137+Y\u0011\u0019Da\u000e\u0003:\tm\"Q\bB \u0005\u0003\u0012\u0019E!\u0012\u0003H\t%SC\u0001B\u001bU\r\u0019\u0016\u0011\u0014\u0003\u0006\u007fu\u0011\r\u0001\u0011\u0003\u0006\u0013v\u0011\r\u0001\u0011\u0003\u0006\u0019v\u0011\r\u0001\u0011\u0003\u0006\u001fv\u0011\r\u0001\u0011\u0003\u0006%v\u0011\r\u0001\u0011\u0003\u0006+v\u0011\r\u0001\u0011\u0003\u00061v\u0011\r\u0001\u0011\u0003\u00067v\u0011\r\u0001\u0011\u0003\u0006=v\u0011\r\u0001\u0011\u0003\u0006Cv\u0011\r\u0001Q\u0001\u000fG>\u0004\u0018\u0010\n3fM\u0006,H\u000e\u001e\u00138+Y\u0011yEa\u0015\u0003V\t]#\u0011\fB.\u0005;\u0012yF!\u0019\u0003d\t\u0015TC\u0001B)U\r1\u0016\u0011\u0014\u0003\u0006\u007fy\u0011\r\u0001\u0011\u0003\u0006\u0013z\u0011\r\u0001\u0011\u0003\u0006\u0019z\u0011\r\u0001\u0011\u0003\u0006\u001fz\u0011\r\u0001\u0011\u0003\u0006%z\u0011\r\u0001\u0011\u0003\u0006+z\u0011\r\u0001\u0011\u0003\u00061z\u0011\r\u0001\u0011\u0003\u00067z\u0011\r\u0001\u0011\u0003\u0006=z\u0011\r\u0001\u0011\u0003\u0006Cz\u0011\r\u0001Q\u0001\u000fG>\u0004\u0018\u0010\n3fM\u0006,H\u000e\u001e\u00139+Y\u0011YGa\u001c\u0003r\tM$Q\u000fB<\u0005s\u0012YH! \u0003\u0000\t\u0005UC\u0001B7U\rI\u0016\u0011\u0014\u0003\u0006\u007f}\u0011\r\u0001\u0011\u0003\u0006\u0013~\u0011\r\u0001\u0011\u0003\u0006\u0019~\u0011\r\u0001\u0011\u0003\u0006\u001f~\u0011\r\u0001\u0011\u0003\u0006%~\u0011\r\u0001\u0011\u0003\u0006+~\u0011\r\u0001\u0011\u0003\u00061~\u0011\r\u0001\u0011\u0003\u00067~\u0011\r\u0001\u0011\u0003\u0006=~\u0011\r\u0001\u0011\u0003\u0006C~\u0011\r\u0001Q\u0001\u000fG>\u0004\u0018\u0010\n3fM\u0006,H\u000e\u001e\u0013:+Y\u00119Ia#\u0003\u000e\n=%\u0011\u0013BJ\u0005+\u00139J!\'\u0003\u001c\nuUC\u0001BEU\ra\u0016\u0011\u0014\u0003\u0006\u007f\u0001\u0012\r\u0001\u0011\u0003\u0006\u0013\u0002\u0012\r\u0001\u0011\u0003\u0006\u0019\u0002\u0012\r\u0001\u0011\u0003\u0006\u001f\u0002\u0012\r\u0001\u0011\u0003\u0006%\u0002\u0012\r\u0001\u0011\u0003\u0006+\u0002\u0012\r\u0001\u0011\u0003\u00061\u0002\u0012\r\u0001\u0011\u0003\u00067\u0002\u0012\r\u0001\u0011\u0003\u0006=\u0002\u0012\r\u0001\u0011\u0003\u0006C\u0002\u0012\r\u0001Q\u0001\u0010G>\u0004\u0018\u0010\n3fM\u0006,H\u000e\u001e\u00132aU1\"1\u0015BT\u0005S\u0013YK!,\u00030\nE&1\u0017B[\u0005o\u0013I,\u0006\u0002\u0003&*\u001aq,!\'\u0005\u000b}\n#\u0019\u0001!\u0005\u000b%\u000b#\u0019\u0001!\u0005\u000b1\u000b#\u0019\u0001!\u0005\u000b=\u000b#\u0019\u0001!\u0005\u000bI\u000b#\u0019\u0001!\u0005\u000bU\u000b#\u0019\u0001!\u0005\u000ba\u000b#\u0019\u0001!\u0005\u000bm\u000b#\u0019\u0001!\u0005\u000by\u000b#\u0019\u0001!\u0005\u000b\u0005\f#\u0019\u0001!\u0002\u001bA\u0014x\u000eZ;diB\u0013XMZ5y+\t\u0011y\f\u0005\u0003\u0003B\n-WB\u0001Bb\u0015\u0011\u0011)Ma2\u0002\t1\fgn\u001a\u0006\u0003\u0005\u0013\fAA[1wC&!\u0011\u0011\nBb\u0003=\u0001(o\u001c3vGRLE/\u001a:bi>\u0014XC\u0001Bi!\u0015\u0011\u0019N!7E\u001b\t\u0011)NC\u0002\u0003XB\n!bY8mY\u0016\u001cG/[8o\u0013\u0011\u0011YN!6\u0003\u0011%#XM]1u_J\f\u0001bY1o\u000bF,\u0018\r\u001c\u000b\u0005\u0005C\u00149\u000fE\u00027\u0005GL1A!:1\u0005\u001d\u0011un\u001c7fC:D\u0001B!;%\u0003\u0003\u0005\r\u0001R\u0001\u0004q\u0012\n\u0014A\u00059s_\u0012,8\r^#mK6,g\u000e\u001e(b[\u0016$BAa0\u0003p\"I!\u0011^\u0013\u0002\u0002\u0003\u0007!\u0011\u001f\t\u0004m\tM\u0018b\u0001B{a\t\u0019\u0011J\u001c;\u0002\u0011!\f7\u000f[\"pI\u0016$\"A!=\u0002\r\u0015\fX/\u00197t)\u0011\u0011\tOa@\t\u0011\t%x%!AA\u0002\u0011\u000bq\u0001V;qY\u0016\f\u0004\u0007\u0005\u00027SM!\u0011&NB\u0004!\u0011\u0019Iaa\u0004\u000e\u0005\r-!\u0002BB\u0007\u0005\u000f\f!![8\n\u0007=\u001cY\u0001\u0006\u0002\u0004\u0004Q\u0011!qX\u0001\u0006CB\u0004H._\u000b\u0017\u00073\u0019yba\t\u0004(\r-2qFB\u001a\u0007o\u0019Yda\u0010\u0004DQ121DB#\u0007\u000f\u001aIea\u0013\u0004N\r=3\u0011KB*\u0007+\u001a9\u0006\u0005\f7\u0001\ru1\u0011EB\u0013\u0007S\u0019ic!\r\u00046\re2QHB!!\ri4q\u0004\u0003\u0006\u007f1\u0012\r\u0001\u0011\t\u0004{\r\rB!B%-\u0005\u0004\u0001\u0005cA\u001f\u0004(\u0011)A\n\fb\u0001\u0001B\u0019Qha\u000b\u0005\u000b=c#\u0019\u0001!\u0011\u0007u\u001ay\u0003B\u0003SY\t\u0007\u0001\tE\u0002>\u0007g!Q!\u0016\u0017C\u0002\u0001\u00032!PB\u001c\t\u0015AFF1\u0001A!\ri41\b\u0003\u000672\u0012\r\u0001\u0011\t\u0004{\r}B!\u00020-\u0005\u0004\u0001\u0005cA\u001f\u0004D\u0011)\u0011\r\fb\u0001\u0001\"1\u0011\u000f\fa\u0001\u0007;Aa\u0001\u001e\u0017A\u0002\r\u0005\u0002BB<-\u0001\u0004\u0019)\u0003\u0003\u0004{Y\u0001\u00071\u0011\u0006\u0005\u0007{2\u0002\ra!\f\t\u000f\u0005\u0005A\u00061\u0001\u00042!9\u0011q\u0001\u0017A\u0002\rU\u0002bBA\u0007Y\u0001\u00071\u0011\b\u0005\b\u0003\'a\u0003\u0019AB\u001f\u0011\u001d\tI\u0002\fa\u0001\u0007\u0003\nq!\u001e8baBd\u00170\u0006\f\u0004^\r%4QNB9\u0007k\u001aIh! \u0004\u0002\u000e\u00155\u0011RBG)\u0011\u0019yfa$\u0011\u000bY\u001a\tg!\u001a\n\u0007\r\r\u0004G\u0001\u0004PaRLwN\u001c\t\u0017m\u0001\u00199ga\u001b\u0004p\rM4qOB>\u0007\u007f\u001a\u0019ia\"\u0004\fB\u0019Qh!\u001b\u0005\u000b}j#\u0019\u0001!\u0011\u0007u\u001ai\u0007B\u0003J[\t\u0007\u0001\tE\u0002>\u0007c\"Q\u0001T\u0017C\u0002\u0001\u00032!PB;\t\u0015yUF1\u0001A!\ri4\u0011\u0010\u0003\u0006%6\u0012\r\u0001\u0011\t\u0004{\ruD!B+.\u0005\u0004\u0001\u0005cA\u001f\u0004\u0002\u0012)\u0001,\fb\u0001\u0001B\u0019Qh!\"\u0005\u000bmk#\u0019\u0001!\u0011\u0007u\u001aI\tB\u0003_[\t\u0007\u0001\tE\u0002>\u0007\u001b#Q!Y\u0017C\u0002\u0001C\u0011b!%.\u0003\u0003\u0005\ra!\u001a\u0002\u0007a$\u0003\'\u0001\u0007xe&$XMU3qY\u0006\u001cW\r\u0006\u0002\u0004\u0018B!!\u0011YBM\u0013\u0011\u0019YJa1\u0003\r=\u0013\'.Z2u\u0001"
    )
  ScalaInlineInfo: length = 0xA4 (unknown attribute)
   01 01 00 20 00 35 00 36 01 00 10 00 53 01 00 23
   00 53 01 00 13 00 53 01 00 15 00 53 01 00 17 00
   53 01 00 19 00 53 01 00 1B 00 53 01 00 1D 00 53
   01 00 1F 00 53 01 00 21 00 53 01 00 BA 00 BB 01
   00 9D 00 33 01 00 9E 00 53 01 00 A0 00 53 01 00
   A2 00 53 01 00 A4 00 53 01 00 A6 00 53 01 00 A8
   00 53 01 00 AA 00 53 01 00 AC 00 53 01 00 AE 00
   53 01 00 B0 00 53 01 00 DA 00 BB 01 00 D0 00 3A
   01 00 39 00 3A 01 00 40 00 41 01 00 BD 00 BE 01
   00 4A 00 4B 01 00 B5 00 4B 01 00 B2 00 73 01 00
   72 00 73 01
  ScalaSig: length = 0x3 (unknown attribute)
   05 02 00
