Classfile /Users/mw/Projects/slang-braindump/.jar/jar11/assemble/slang-braindump/assemble/content/coursier/paths/Mirror$MirrorPropertiesException.class
  Last modified May 29, 2022; size 443 bytes
  SHA-256 checksum a34319fb93bb66ee31b0acd2f8dfb4f50ca3df18c2265aea996fec54674b73e1
  Compiled from "Mirror.java"
public class coursier.paths.Mirror$MirrorPropertiesException extends java.lang.Exception
  minor version: 0
  major version: 52
  flags: (0x0021) ACC_PUBLIC, ACC_SUPER
  this_class: #2                          // coursier/paths/Mirror$MirrorPropertiesException
  super_class: #4                         // java/lang/Exception
  interfaces: 0, fields: 0, methods: 2, attributes: 2
Constant pool:
   #1 = Utf8               coursier/paths/Mirror$MirrorPropertiesException
   #2 = Class              #1             // coursier/paths/Mirror$MirrorPropertiesException
   #3 = Utf8               java/lang/Exception
   #4 = Class              #3             // java/lang/Exception
   #5 = Utf8               Mirror.java
   #6 = Utf8               coursier/paths/Mirror
   #7 = Class              #6             // coursier/paths/Mirror
   #8 = Utf8               MirrorPropertiesException
   #9 = Utf8               <init>
  #10 = Utf8               (Ljava/lang/String;)V
  #11 = NameAndType        #9:#10         // "<init>":(Ljava/lang/String;)V
  #12 = Methodref          #4.#11         // java/lang/Exception."<init>":(Ljava/lang/String;)V
  #13 = Utf8               (Ljava/lang/String;Ljava/lang/Throwable;)V
  #14 = NameAndType        #9:#13         // "<init>":(Ljava/lang/String;Ljava/lang/Throwable;)V
  #15 = Methodref          #4.#14         // java/lang/Exception."<init>":(Ljava/lang/String;Ljava/lang/Throwable;)V
  #16 = Utf8               Code
  #17 = Utf8               LineNumberTable
  #18 = Utf8               InnerClasses
  #19 = Utf8               SourceFile
{
  public coursier.paths.Mirror$MirrorPropertiesException(java.lang.String);
    descriptor: (Ljava/lang/String;)V
    flags: (0x0001) ACC_PUBLIC
    Code:
      stack=2, locals=2, args_size=2
         0: aload_0
         1: aload_1
         2: invokespecial #12                 // Method java/lang/Exception."<init>":(Ljava/lang/String;)V
         5: return
      LineNumberTable:
        line 97: 0
        line 98: 5

  public coursier.paths.Mirror$MirrorPropertiesException(java.lang.String, java.lang.Throwable);
    descriptor: (Ljava/lang/String;Ljava/lang/Throwable;)V
    flags: (0x0001) ACC_PUBLIC
    Code:
      stack=3, locals=3, args_size=3
         0: aload_0
         1: aload_1
         2: aload_2
         3: invokespecial #15                 // Method java/lang/Exception."<init>":(Ljava/lang/String;Ljava/lang/Throwable;)V
         6: return
      LineNumberTable:
        line 100: 0
        line 101: 6
}
InnerClasses:
  public static #8= #2 of #7;             // MirrorPropertiesException=class coursier/paths/Mirror$MirrorPropertiesException of class coursier/paths/Mirror
SourceFile: "Mirror.java"
